{
  "type": "Feature",
  "properties": {
    "gn:country":"US",
    "gn:fcode":"PPL",
    "gn:population":0,
    "iso:country":"US",
    "name:bar_x_preferred":[
        "Greystone"
    ],
    "name:deu_x_preferred":[
        "Greystone"
    ],
    "qs_pg:aaroncc":"US",
    "qs_pg:gn_country":"US",
    "qs_pg:gn_fcode":"PPL",
    "qs_pg:gn_pop":0,
    "qs_pg:name":"Greystone",
    "qs_pg:name_adm0":"United States",
    "qs_pg:name_adm1":"Connecticut",
    "qs_pg:photos":502,
    "qs_pg:photos_1k":102,
    "qs_pg:photos_9k":2,
    "qs_pg:photos_9r":5,
    "qs_pg:photos_all":502,
    "qs_pg:photos_sr":7,
    "qs_pg:pop_sr":0,
    "qs_pg:qs_pg_placetype":"neighbourhood",
    "qs_pg:qs_pg_placetype_gp":"Suburb",
    "qs_pg:woe_adm0":23424977,
    "woe:adm0_id":23424977,
    "woe:name_adm0":"United States",
    "woe:name_adm1":"Connecticut",
    "woe:placetype":"Suburb",
    "wof:name":"Greystone",
    "wof:placetype":"neighbourhood"
},
  "geometry": {"coordinates":[-73.04122,41.61899],"type":"Point"}
}