{
  "type": "Feature",
  "properties": {
    "gn:admin1_code":"AL",
    "gn:admin2_code":"93.0",
    "gn:asciiname":"South Haleyville",
    "gn:country_code":"US",
    "gn:dem":272,
    "gn:elevation":"269.0",
    "gn:feature_class":"P",
    "gn:feature_code":"PPL",
    "gn:name":"South Haleyville",
    "gn:population":0,
    "gn:timezone":"America/Chicago",
    "iso:country":"US",
    "name:fas_x_preferred":[
        "\u0633\u0627\u0648\u062a \u0647\u0627\u0644\u06cc\u200c\u0648\u06cc\u0644"
    ],
    "name:zho_x_preferred":[
        "\u5357\u9ed1\u5229\u7dad\u723e"
    ],
    "wof:name":"South Haleyville",
    "wof:placetype":"locality"
},
  "geometry": {"coordinates":[-87.63502,34.21120999999999],"type":"Point"}
}