{
  "type": "Feature",
  "properties": {
    "gn:admin1_code":"GA",
    "gn:admin2_code":"73",
    "gn:asciiname":"Westport",
    "gn:country_code":"US",
    "gn:dem":93,
    "gn:elevation":"82.0",
    "gn:feature_class":"P",
    "gn:feature_code":"PPL",
    "gn:name":"Westport",
    "gn:population":0,
    "gn:timezone":"America/New_York",
    "iso:country":"US",
    "name:bul_x_preferred":[
        "\u0423\u0435\u0441\u0442\u043f\u043e\u0440\u0442"
    ],
    "name:cat_x_preferred":[
        "Westport"
    ],
    "name:ceb_x_preferred":[
        "Westport"
    ],
    "name:ces_x_preferred":[
        "Westport"
    ],
    "name:deu_x_preferred":[
        "Westport"
    ],
    "name:fao_x_preferred":[
        "Westport"
    ],
    "name:fas_x_preferred":[
        "\u0648\u0633\u062a\u067e\u0648\u0631\u062a"
    ],
    "name:fin_x_preferred":[
        "Westport"
    ],
    "name:fra_x_preferred":[
        "Westport"
    ],
    "name:heb_x_preferred":[
        "\u05d5\u05e1\u05d8\u05e4\u05d5\u05e8\u05d8"
    ],
    "name:hun_x_preferred":[
        "Westport"
    ],
    "name:ita_x_preferred":[
        "Westport"
    ],
    "name:kor_x_preferred":[
        "\uc6e8\uc2a4\ud2b8\ud3ec\ud2b8"
    ],
    "name:ltz_x_preferred":[
        "Westport"
    ],
    "name:nld_x_preferred":[
        "Westport"
    ],
    "name:nor_x_preferred":[
        "Westport"
    ],
    "name:pol_x_preferred":[
        "Westport"
    ],
    "name:por_x_preferred":[
        "Westport"
    ],
    "name:rus_x_preferred":[
        "\u0412\u0435\u0441\u0442\u043f\u043e\u0440\u0442"
    ],
    "name:rus_x_variant":[
        "\u0423\u044d\u0441\u0442\u043f\u043e\u0440\u0442"
    ],
    "name:spa_x_preferred":[
        "Westport"
    ],
    "name:srp_x_preferred":[
        "\u0412\u0435\u0441\u0442\u043f\u043e\u0440\u0442"
    ],
    "name:swe_x_preferred":[
        "Westport"
    ],
    "name:tur_x_preferred":[
        "Westport"
    ],
    "name:ukr_x_preferred":[
        "\u0412\u0435\u0441\u0442\u043f\u043e\u0440\u0442"
    ],
    "name:urd_x_preferred":[
        "\u0648\u06cc\u0633\u0679 \u067e\u0648\u0631\u0679"
    ],
    "name:vie_x_preferred":[
        "Westport"
    ],
    "name:vol_x_preferred":[
        "Westport"
    ],
    "name:zho_cn_x_preferred":[
        "\u97e6\u65af\u7279\u6ce2\u7279"
    ],
    "name:zho_tw_x_preferred":[
        "\u97cb\u65af\u7279\u6ce2\u7279"
    ],
    "wof:name":"Westport",
    "wof:placetype":"locality"
},
  "geometry": {"coordinates":[-82.06928000000001,33.55708],"type":"Point"}
}