{
  "type": "Feature",
  "properties": {
    "gn:admin1_code":"TX",
    "gn:admin2_code":"61",
    "gn:asciiname":"Ismael Montalvo Colonia Number 2",
    "gn:country_code":"US",
    "gn:dem":16,
    "gn:elevation":"14.0",
    "gn:feature_class":"P",
    "gn:feature_code":"PPL",
    "gn:name":"Ismael Montalvo Colonia Number 2",
    "gn:population":0,
    "gn:timezone":"America/Chicago",
    "iso:country":"US",
    "name:eng_x_preferred":[
        "Ismael Montalvo Colonia Number 2"
    ],
    "name:und_x_variant":[
        "Ismael Montalvo Subdivision Number 2"
    ],
    "wof:name":"Ismael Montalvo Colonia Number 2",
    "wof:placetype":"locality"
},
  "geometry": {"coordinates":[-97.62582,26.0273],"type":"Point"}
}