{
  "type": "Feature",
  "properties": {
    "gn:admin1_code":"FL",
    "gn:admin2_code":"35.0",
    "gn:asciiname":"Plantation Oaks Mobile Home Park",
    "gn:country_code":"US",
    "gn:dem":15,
    "gn:elevation":"6.0",
    "gn:feature_class":"P",
    "gn:feature_code":"PPL",
    "gn:name":"Plantation Oaks Mobile Home Park",
    "gn:population":0,
    "gn:timezone":"America/New_York",
    "iso:country":"US",
    "wof:name":"Plantation Oaks Mobile Home Park",
    "wof:placetype":"campus"
},
  "geometry": {"coordinates":[-81.14869,29.42858],"type":"Point"}
}