{
  "type": "Feature",
  "properties": {
    "gn:country":"US",
    "gn:fcode":"PPLX",
    "gn:population":0,
    "iso:country":"US",
    "qs_pg:aaroncc":"US",
    "qs_pg:gn_country":"US",
    "qs_pg:gn_fcode":"PPLX",
    "qs_pg:gn_pop":0,
    "qs_pg:name":"Booker Washington Heights",
    "qs_pg:name_adm0":"United States",
    "qs_pg:name_adm1":"South Carolina",
    "qs_pg:photos":12,
    "qs_pg:photos_1k":2,
    "qs_pg:photos_9k":1,
    "qs_pg:photos_9r":1,
    "qs_pg:photos_all":12,
    "qs_pg:photos_sr":1,
    "qs_pg:pop_sr":0,
    "qs_pg:qs_pg_placetype":"neighbourhood",
    "qs_pg:qs_pg_placetype_gp":"Suburb",
    "qs_pg:woe_adm0":23424977,
    "woe:adm0_id":23424977,
    "woe:name_adm0":"United States",
    "woe:name_adm1":"South Carolina",
    "woe:placetype":"Suburb",
    "wof:name":"Booker Washington Heights",
    "wof:placetype":"neighbourhood"
},
  "geometry": {"coordinates":[-81.02258999999999,34.03043],"type":"Point"}
}