{
  "type": "Feature",
  "properties": {
    "iso:country":"US",
    "name:eng_x_preferred":[
        "Baker Heights"
    ],
    "wof:name":"Baker Heights",
    "wof:placetype":"neighbourhood",
    "wof:population":185,
    "zs:area_m":846363.690114,
    "zs:blockids":[
        490572015002010
    ],
    "zs:housing10":75,
    "zs:label":"Baker Heights",
    "zs:pop10":185
},
  "geometry": {"coordinates":[-111.934433,41.201517],"type":"Point"}
}