{
  "type": "Feature",
  "properties": {
    "gn:admin1_code":"WY",
    "gn:admin2_code":"41.0",
    "gn:asciiname":"Elkhurst",
    "gn:country_code":"US",
    "gn:dem":1966,
    "gn:elevation":"1964.0",
    "gn:feature_class":"P",
    "gn:feature_code":"PPL",
    "gn:name":"Elkhurst",
    "gn:population":0,
    "gn:timezone":"America/Denver",
    "iso:country":"US",
    "wof:name":"Elkhurst",
    "wof:placetype":"locality"
},
  "geometry": {"coordinates":[-110.35044000000001,41.4919],"type":"Point"}
}