{
  "type": "Feature",
  "properties": {
    "gn:admin1_code":"MO",
    "gn:admin2_code":"103.0",
    "gn:admin3_code":"65576.0",
    "gn:asciiname":"Locust Hill",
    "gn:country_code":"US",
    "gn:dem":266,
    "gn:elevation":"263.0",
    "gn:feature_class":"P",
    "gn:feature_code":"PPL",
    "gn:name":"Locust Hill",
    "gn:population":0,
    "gn:timezone":"America/Chicago",
    "iso:country":"US",
    "name:ceb_x_preferred":[
        "Locust Hill"
    ],
    "name:deu_x_preferred":[
        "Locust Hill"
    ],
    "name:fra_x_preferred":[
        "Locust Hill"
    ],
    "wof:name":"Locust Hill",
    "wof:placetype":"locality"
},
  "geometry": {"coordinates":[-92.27574,40.02587],"type":"Point"}
}