{
  "type": "Feature",
  "properties": {
    "gn:admin1_code":"VA",
    "gn:admin2_code":"57",
    "gn:asciiname":"Oakley",
    "gn:country_code":"US",
    "gn:dem":39,
    "gn:elevation":"37.0",
    "gn:feature_class":"P",
    "gn:feature_code":"PPL",
    "gn:name":"Oakley",
    "gn:population":0,
    "gn:timezone":"America/New_York",
    "iso:country":"US",
    "name:cat_x_preferred":[
        "Oakley"
    ],
    "name:ceb_x_preferred":[
        "Oakley"
    ],
    "name:ces_x_preferred":[
        "Oakley"
    ],
    "name:cym_x_preferred":[
        "Oakley"
    ],
    "name:deu_x_preferred":[
        "Oakley"
    ],
    "name:fas_x_preferred":[
        "\u0627\u0648\u06a9\u0644\u06cc"
    ],
    "name:fin_x_preferred":[
        "Oakley"
    ],
    "name:fra_x_preferred":[
        "Oakley"
    ],
    "name:heb_x_preferred":[
        "\u05d0\u05d5\u05e7\u05dc\u05d9"
    ],
    "name:ita_x_preferred":[
        "Oakley"
    ],
    "name:jpn_x_preferred":[
        "\u30aa\u30fc\u30af\u30ec\u30fc"
    ],
    "name:nld_x_preferred":[
        "Oakley"
    ],
    "name:pol_x_preferred":[
        "Oakley"
    ],
    "name:por_x_preferred":[
        "Oakley"
    ],
    "name:rus_x_preferred":[
        "\u041e\u043a\u043b\u0438"
    ],
    "name:spa_x_preferred":[
        "Oakley"
    ],
    "name:srp_x_preferred":[
        "\u041e\u0443\u043a\u043b\u0438"
    ],
    "name:swe_x_preferred":[
        "Oakley"
    ],
    "name:vol_x_preferred":[
        "Oakley"
    ],
    "wof:name":"Oakley",
    "wof:placetype":"locality"
},
  "geometry": {"coordinates":[-76.75496,37.77486],"type":"Point"}
}