{
  "type": "Feature",
  "properties": {
    "gn:admin1_code":"FL",
    "gn:admin2_code":"127.0",
    "gn:asciiname":"Emporia",
    "gn:country_code":"US",
    "gn:dem":16,
    "gn:elevation":"14.0",
    "gn:feature_class":"P",
    "gn:feature_code":"PPL",
    "gn:name":"Emporia",
    "gn:population":0,
    "gn:timezone":"America/New_York",
    "iso:country":"US",
    "name:ben_x_preferred":[
        "\u098f\u09ae\u09cd\u09aa\u09cb\u09b0\u09bf\u09df\u09be"
    ],
    "name:ceb_x_preferred":[
        "Emporia"
    ],
    "name:dan_x_preferred":[
        "Emporia"
    ],
    "name:deu_x_preferred":[
        "Emporia"
    ],
    "name:fin_x_preferred":[
        "Emporia"
    ],
    "name:fra_x_preferred":[
        "Emporia"
    ],
    "name:hin_x_preferred":[
        "\u090f\u092e\u094d\u092a\u094b\u0930\u093f\u092f\u093e"
    ],
    "name:ind_x_preferred":[
        "Emporia"
    ],
    "name:ita_x_preferred":[
        "Emporia"
    ],
    "name:jpn_x_preferred":[
        "\u30a8\u30f3\u30dd\u30ea\u30a2"
    ],
    "name:kor_x_preferred":[
        "\uc5e0\ud3ec\ub9ac\uc544"
    ],
    "name:lat_x_preferred":[
        "Emporia"
    ],
    "name:nld_x_preferred":[
        "Emporia"
    ],
    "name:nor_x_preferred":[
        "Emporia"
    ],
    "name:pol_x_preferred":[
        "Emporia"
    ],
    "name:rus_x_preferred":[
        "\u042d\u043c\u043f\u043e\u0440\u0438\u044f"
    ],
    "name:spa_x_preferred":[
        "Emporia"
    ],
    "name:srp_x_preferred":[
        "\u0415\u043c\u043f\u043e\u0440\u0438\u0458\u0430"
    ],
    "name:swe_x_preferred":[
        "Emporia"
    ],
    "name:ukr_x_preferred":[
        "\u0415\u043c\u043f\u043e\u0440\u0456\u044f"
    ],
    "name:vol_x_preferred":[
        "Emporia"
    ],
    "wof:name":"Emporia",
    "wof:placetype":"locality"
},
  "geometry": {"coordinates":[-81.46813,29.19915],"type":"Point"}
}