{
  "type": "Feature",
  "properties": {
    "iso:country":"US",
    "qs_pg:aaroncc":"US",
    "qs_pg:name":"Falls Park",
    "qs_pg:name_adm0":"United States",
    "qs_pg:name_adm1":"South Dakota",
    "qs_pg:photos":63,
    "qs_pg:photos_1k":13,
    "qs_pg:photos_9k":1,
    "qs_pg:photos_9r":2,
    "qs_pg:photos_all":63,
    "qs_pg:photos_sr":2,
    "qs_pg:pop_sr":0,
    "qs_pg:qs_pg_placetype":"neighbourhood",
    "qs_pg:qs_pg_placetype_gp":"Suburb",
    "qs_pg:woe_adm0":23424977,
    "woe:adm0_id":23424977,
    "woe:name_adm0":"United States",
    "woe:name_adm1":"South Dakota",
    "woe:placetype":"Suburb",
    "wof:name":"Falls Park",
    "wof:placetype":"neighbourhood"
},
  "geometry": {"coordinates":[-96.722302,43.555557],"type":"Point"}
}