{
  "type": "Feature",
  "properties": {
    "gn:admin1_code":"OH",
    "gn:admin2_code":"41.0",
    "gn:admin3_code":"21469.0",
    "gn:asciiname":"Kensington Place",
    "gn:country_code":"US",
    "gn:dem":285,
    "gn:elevation":"287.0",
    "gn:feature_class":"P",
    "gn:feature_code":"PPL",
    "gn:name":"Kensington Place",
    "gn:population":0,
    "gn:timezone":"America/New_York",
    "iso:country":"US",
    "wof:name":"Kensington Place",
    "wof:placetype":"locality"
},
  "geometry": {"coordinates":[-83.03516999999999,40.30226],"type":"Point"}
}