{
  "type": "Feature",
  "properties": {
    "gn:country":"US",
    "gn:fcode":"PPL",
    "gn:population":0,
    "iso:country":"US",
    "name:deu_x_preferred":[
        "Suissevale"
    ],
    "name:eng_x_preferred":[
        "State Landing"
    ],
    "name:eng_x_variant":[
        "Suissevale"
    ],
    "name:fas_x_preferred":[
        "\u0633\u0648\u0646\u06a9\u0648\u06a9\u060c \u0646\u06cc\u0648\u0647\u0645\u067e\u0634\u0627\u06cc\u0631"
    ],
    "name:fas_x_variant":[
        "\u0633\u0648\u0646\u06a9\u0648\u06a9"
    ],
    "name:fra_x_preferred":[
        "Suissevale"
    ],
    "name:gle_x_preferred":[
        "Suissevale"
    ],
    "name:ita_x_preferred":[
        "Suissevale"
    ],
    "name:lld_x_preferred":[
        "Suissevale"
    ],
    "name:pol_x_preferred":[
        "Suissevale"
    ],
    "name:spa_x_preferred":[
        "Suissevale"
    ],
    "name:srp_x_preferred":[
        "\u0421\u0432\u0438\u0441\u0432\u0435\u0458\u043b"
    ],
    "name:tat_x_preferred":[
        "\u0421\u0432\u0438\u0441\u0441\u0435\u0432\u0435\u0439\u043b"
    ],
    "name:tur_x_preferred":[
        "Suissevale"
    ],
    "name:ukr_x_preferred":[
        "\u0421\u0432\u0456\u0441\u0441\u0435\u0432\u0435\u0439\u043b"
    ],
    "qs_pg:aaroncc":"US",
    "qs_pg:gn_country":"US",
    "qs_pg:gn_fcode":"PPL",
    "qs_pg:gn_pop":0,
    "qs_pg:name":"State Landing",
    "qs_pg:name_adm0":"United States",
    "qs_pg:name_adm1":"New Hampshire",
    "qs_pg:photos":124,
    "qs_pg:photos_1k":25,
    "qs_pg:photos_9k":1,
    "qs_pg:photos_9r":3,
    "qs_pg:photos_all":124,
    "qs_pg:photos_sr":3,
    "qs_pg:pop_sr":0,
    "qs_pg:qs_pg_placetype":"locality",
    "qs_pg:qs_pg_placetype_gp":"Town",
    "qs_pg:woe_adm0":23424977,
    "woe:adm0_id":23424977,
    "woe:name_adm0":"United States",
    "woe:name_adm1":"New Hampshire",
    "woe:placetype":"Town",
    "wof:name":"State Landing",
    "wof:placetype":"locality"
},
  "geometry": {"coordinates":[-71.37396,43.72619],"type":"Point"}
}