{
  "type": "Feature",
  "properties": {
    "gn:admin1_code":"VA",
    "gn:admin2_code":"59",
    "gn:asciiname":"Maple Grove Estates",
    "gn:country_code":"US",
    "gn:dem":72,
    "gn:elevation":"72.0",
    "gn:feature_class":"P",
    "gn:feature_code":"PPL",
    "gn:name":"Maple Grove Estates",
    "gn:population":0,
    "gn:timezone":"America/New_York",
    "iso:country":"US",
    "wof:name":"Maple Grove Estates",
    "wof:placetype":"locality"
},
  "geometry": {"coordinates":[-77.14554,38.78428],"type":"Point"}
}