{
  "type": "Feature",
  "properties": {
    "gn:admin1_code":"WI",
    "gn:admin2_code":"35.0",
    "gn:admin3_code":"63400.0",
    "gn:asciiname":"Cleghorn",
    "gn:country_code":"US",
    "gn:dem":295,
    "gn:elevation":"293.0",
    "gn:feature_class":"P",
    "gn:feature_code":"PPL",
    "gn:name":"Cleghorn",
    "gn:population":0,
    "gn:timezone":"America/Chicago",
    "iso:country":"US",
    "wof:name":"Cleghorn",
    "wof:placetype":"locality"
},
  "geometry": {"coordinates":[-91.42683,44.68357],"type":"Point"}
}