{
  "type": "Feature",
  "properties": {
    "iso:country":"US",
    "name:eng_x_preferred":[
        "Chaparral Ranch I"
    ],
    "wof:name":"Chaparral Ranch I",
    "wof:placetype":"neighbourhood",
    "wof:population":986,
    "zs:area_m":719104.537378,
    "zs:blockids":[
        40130719037009,
        40130719037014,
        40130719153001,
        40130719037004,
        40130719153000,
        40130719037006,
        40130719037012,
        40130719037021,
        40130923051007,
        40131042223013,
        40130719037003,
        40130719037013,
        40130719037001
    ],
    "zs:housing10":603,
    "zs:label":"Chaparral Ranch I",
    "zs:pop10":986
},
  "geometry": {"coordinates":[-112.204385,33.581515],"type":"Point"}
}