{
  "type": "Feature",
  "properties": {
    "gn:admin1_code":"IL",
    "gn:admin2_code":"129.0",
    "gn:asciiname":"Culver",
    "gn:country_code":"US",
    "gn:dem":184,
    "gn:elevation":"185.0",
    "gn:feature_class":"P",
    "gn:feature_code":"PPL",
    "gn:name":"Culver",
    "gn:population":0,
    "gn:timezone":"America/Chicago",
    "iso:country":"US",
    "wof:name":"Culver",
    "wof:placetype":"locality"
},
  "geometry": {"coordinates":[-89.68733,40.00672],"type":"Point"}
}