{
  "type": "Feature",
  "properties": {
    "iso:country":"US",
    "name:eng_x_preferred":[
        "Groves Edge"
    ],
    "wof:name":"Groves Edge",
    "wof:placetype":"neighbourhood",
    "wof:population":286,
    "zs:area_m":103745.64755,
    "zs:blockids":[
        371830537191004,
        371830537191005,
        371830537191003
    ],
    "zs:housing10":115,
    "zs:label":"Groves Edge",
    "zs:pop10":286
},
  "geometry": {"coordinates":[-78.742423,35.922713],"type":"Point"}
}