{
  "type": "Feature",
  "properties": {
    "gn:gn_country":"US",
    "gn:gn_fcode":"PPLX",
    "gn:gn_pop":0,
    "iso:country":"US",
    "name:ceb_x_preferred":[
        "Hilldale"
    ],
    "name:deu_x_preferred":[
        "Hilldale"
    ],
    "name:swe_x_preferred":[
        "Hilldale"
    ],
    "qs_pg:aaroncc":"US",
    "qs_pg:gn_country":"US",
    "qs_pg:gn_fcode":"PPLX",
    "qs_pg:gn_pop":0,
    "qs_pg:name":"Hilldale",
    "qs_pg:name_adm0":"United States",
    "qs_pg:name_adm1":"South Carolina",
    "qs_pg:photos":3,
    "qs_pg:photos_1k":1,
    "qs_pg:photos_9k":1,
    "qs_pg:photos_9r":1,
    "qs_pg:photos_all":3,
    "qs_pg:photos_sr":1,
    "qs_pg:pop_sr":0,
    "qs_pg:qs_pg_placetype":"neighbourhood",
    "qs_pg:qs_pg_placetype_gp":"Suburb",
    "qs_pg:woe_adm0":23424977,
    "woe:adm0_id":23424977,
    "woe:name_adm0":"United States",
    "woe:name_adm1":"South Carolina",
    "woe:placetype":"Suburb",
    "wof:name":"Hilldale",
    "wof:placetype":"neighbourhood"
},
  "geometry": {"coordinates":[-80.85259000000001,33.53626],"type":"Point"}
}