{
  "type": "Feature",
  "properties": {
    "iso:country":"US",
    "name:eng_x_preferred":[
        "Griffin Gate"
    ],
    "qs:gn_adm0_cc":"US",
    "qs:gn_local":4297983,
    "qs:gn_nam_loc":"Lexington, Fayette, Kentucky, US",
    "qs:gn_namadm1":"KY",
    "qs:local_max":4034,
    "qs:local_sum":30708,
    "qs:localhoods":91,
    "qs:name":"Griffin Gate",
    "qs:name_adm0":"United States",
    "qs:name_adm1":"Kentucky",
    "qs:name_adm2":"Fayette",
    "qs:name_local":"Lexington",
    "qs:photo_max":367,
    "qs:photo_sum":822,
    "qs:placetype":"Suburb",
    "qs:quad_count":15,
    "qs:woe_adm0":23424977,
    "qs:woe_adm1":2347576,
    "qs:woe_adm2":12588509,
    "qs:woe_lau":0,
    "qs:woe_local":2438841,
    "qs:woe_ver":"7.10.0",
    "wof:lang":[
        "eng"
    ],
    "wof:name":"Griffin Gate",
    "wof:placetype":"neighbourhood",
    "wof:population":3498,
    "zs:blockids":[
        210670038023003,
        210670038031024,
        210670038031018,
        210670038031021,
        210670038043011,
        210670038043009,
        210670038023004,
        210670038033004,
        210670038031015,
        210670038031028,
        210670038033010,
        210670038041005,
        210670038031030,
        210670038031027,
        210670038023029,
        210670038031014,
        210670038031038,
        210670038031039,
        210670038041006,
        210670038031035,
        210670038033008,
        210670038032020,
        210670038043008,
        210670038023012,
        210670038031002,
        210670038041001,
        210670038031019,
        210670038041002,
        210670038041004,
        210670038042002,
        210670038033000,
        210670038023026,
        210670038031029,
        210670038033006,
        210670038031005,
        210670038031011,
        210670038041007,
        210670038031040,
        210670038031022,
        210670038033005,
        210670038043007,
        210670038031033,
        210670038023001,
        210670038041000,
        210670038023002,
        210670038043013,
        210670038043010,
        210670038043014,
        210670038031025,
        210670038023005,
        210670038023006,
        210670038033001,
        210670038033003,
        210670038033011,
        210670038043012,
        210670038033007,
        210670038033009,
        210670038033002,
        210670038031020,
        210670038041003,
        210670038031034,
        210670038031032,
        210670038031031,
        210670038043015
    ],
    "zs:housing10":1493,
    "zs:pop10":3498
},
  "geometry": {"coordinates":[-84.485894,38.096227],"type":"Point"}
}