{
  "type": "Feature",
  "properties": {
    "gn:admin1_code":"VA",
    "gn:admin2_code":"131.0",
    "gn:asciiname":"Bay Ridge",
    "gn:country_code":"US",
    "gn:dem":4,
    "gn:elevation":"4.0",
    "gn:feature_class":"P",
    "gn:feature_code":"PPL",
    "gn:name":"Bay Ridge",
    "gn:population":0,
    "gn:timezone":"America/New_York",
    "iso:country":"US",
    "wof:name":"Bay Ridge",
    "wof:placetype":"locality"
},
  "geometry": {"coordinates":[-76.01021,37.21125],"type":"Point"}
}