{
  "type": "Feature",
  "properties": {
    "gn:admin1_code":"TX",
    "gn:admin2_code":"225.0",
    "gn:asciiname":"Percilla",
    "gn:country_code":"US",
    "gn:dem":137,
    "gn:elevation":"130.0",
    "gn:feature_class":"P",
    "gn:feature_code":"PPL",
    "gn:name":"Percilla",
    "gn:population":0,
    "gn:timezone":"America/Chicago",
    "iso:country":"US",
    "wof:name":"Percilla",
    "wof:placetype":"locality"
},
  "geometry": {"coordinates":[-95.39910999999999,31.54712],"type":"Point"}
}