{
  "type": "Feature",
  "properties": {
    "gn:admin1_code":"OH",
    "gn:admin2_code":"139",
    "gn:admin3_code":"50092.0",
    "gn:asciiname":"Shady Lane Mobile Home Park",
    "gn:country_code":"US",
    "gn:dem":414,
    "gn:elevation":"409.0",
    "gn:feature_class":"P",
    "gn:feature_code":"PPL",
    "gn:name":"Shady Lane Mobile Home Park",
    "gn:population":0,
    "gn:timezone":"America/New_York",
    "iso:country":"US",
    "wof:name":"Shady Lane Mobile Home Park",
    "wof:placetype":"campus"
},
  "geometry": {"coordinates":[-82.4525,40.76056],"type":"Point"}
}