{
  "type": "Feature",
  "properties": {
    "gn:admin1_code":"GA",
    "gn:admin2_code":"121",
    "gn:asciiname":"Sunnybrook Farms",
    "gn:country_code":"US",
    "gn:dem":300,
    "gn:elevation":"298.0",
    "gn:feature_class":"P",
    "gn:feature_code":"PPL",
    "gn:name":"Sunnybrook Farms",
    "gn:population":0,
    "gn:timezone":"America/New_York",
    "iso:country":"US",
    "wof:name":"Sunnybrook Farms",
    "wof:placetype":"locality"
},
  "geometry": {"coordinates":[-84.2877,34.12871],"type":"Point"}
}