{
  "type": "Feature",
  "properties": {
    "gn:admin1_code":"ME",
    "gn:admin2_code":"13.0",
    "gn:admin3_code":"26805.0",
    "gn:asciiname":"East Friendship",
    "gn:country_code":"US",
    "gn:dem":29,
    "gn:elevation":"28.0",
    "gn:feature_class":"P",
    "gn:feature_code":"PPL",
    "gn:name":"East Friendship",
    "gn:population":0,
    "gn:timezone":"America/New_York",
    "iso:country":"US",
    "wof:name":"East Friendship",
    "wof:placetype":"locality"
},
  "geometry": {"coordinates":[-69.29644,44.00869],"type":"Point"}
}