{
  "type": "Feature",
  "properties": {
    "gn:admin1_code":"IL",
    "gn:admin2_code":"179.0",
    "gn:admin3_code":"44017.0",
    "gn:asciiname":"Walnut",
    "gn:country_code":"US",
    "gn:dem":191,
    "gn:elevation":"191.0",
    "gn:feature_class":"P",
    "gn:feature_code":"PPL",
    "gn:name":"Walnut",
    "gn:population":0,
    "gn:timezone":"America/Chicago",
    "iso:country":"US",
    "name:afr_x_preferred":[
        "Okkerneut"
    ],
    "name:ara_x_preferred":[
        "\u062c\u0648\u0632"
    ],
    "name:ast_x_preferred":[
        "Nuez"
    ],
    "name:ben_x_preferred":[
        "\u0986\u0996\u09b0\u09cb\u099f"
    ],
    "name:bul_x_preferred":[
        "\u041e\u0440\u0435\u0445"
    ],
    "name:ces_x_preferred":[
        "Vla\u0161sk\u00fd o\u0159ech"
    ],
    "name:cos_x_preferred":[
        "Noce"
    ],
    "name:dty_x_preferred":[
        "\u0913\u0916\u0923"
    ],
    "name:ell_x_preferred":[
        "\u039a\u03b1\u03c1\u03cd\u03b4\u03b9"
    ],
    "name:est_x_preferred":[
        "Kreeka p\u00e4hklid"
    ],
    "name:eus_x_preferred":[
        "Intxaur"
    ],
    "name:fas_x_preferred":[
        "\u0645\u063a\u0632 \u06af\u0631\u062f\u0648"
    ],
    "name:fra_x_preferred":[
        "Noix"
    ],
    "name:gle_x_preferred":[
        "Gallchn\u00f3"
    ],
    "name:glg_x_preferred":[
        "Noz"
    ],
    "name:gom_x_preferred":[
        "Akrutt"
    ],
    "name:hin_x_preferred":[
        "\u0905\u0916\u0930\u094b\u091f"
    ],
    "name:hye_x_preferred":[
        "\u0538\u0576\u056f\u0578\u0582\u0575\u0566"
    ],
    "name:ido_x_preferred":[
        "Nuco"
    ],
    "name:ind_x_preferred":[
        "Kacang kenari"
    ],
    "name:ita_x_preferred":[
        "Noce"
    ],
    "name:kab_x_preferred":[
        "Agusim"
    ],
    "name:kan_x_preferred":[
        "\u0c85\u0c96\u0ccd\u0cb0\u0ccb\u0c9f\u0ccd"
    ],
    "name:kir_x_preferred":[
        "\u0416\u0430\u04a3\u0433\u0430\u043a"
    ],
    "name:lav_x_preferred":[
        "Valrieksts"
    ],
    "name:ltz_x_preferred":[
        "Noss"
    ],
    "name:mar_x_preferred":[
        "\u0905\u0915\u094d\u0930\u094b\u0921"
    ],
    "name:nav_x_preferred":[
        "Ha\u02bca\u0142ts\u00e9dii"
    ],
    "name:nld_x_preferred":[
        "Walnoot"
    ],
    "name:oci_x_preferred":[
        "Notz"
    ],
    "name:pan_x_preferred":[
        "\u0a05\u0a16\u0a30\u0a4b\u0a1f"
    ],
    "name:pus_x_preferred":[
        "\u063a\u0648\u0632"
    ],
    "name:rus_x_preferred":[
        "\u0413\u0440\u0435\u0446\u043a\u0438\u0439 \u043e\u0440\u0435\u0445"
    ],
    "name:snd_x_preferred":[
        "\u0627\u06a9\u0631\u0648\u067d"
    ],
    "name:tam_x_preferred":[
        "\u0bb5\u0bbe\u0ba4\u0bc1\u0bae\u0bc8\u0b95\u0bcd \u0b95\u0bca\u0b9f\u0bcd\u0b9f\u0bc8"
    ],
    "name:tat_x_preferred":[
        "\u04d8\u0441\u0442\u0435\u0440\u0445\u0430\u043d \u0447\u0438\u043a\u043b\u04d9\u0432\u0435\u0433\u0435"
    ],
    "wof:name":"Walnut",
    "wof:placetype":"locality"
},
  "geometry": {"coordinates":[-89.37148000000001,40.48393],"type":"Point"}
}