{
  "type": "Feature",
  "properties": {
    "gn:admin1_code":"AZ",
    "gn:admin2_code":"5.0",
    "gn:asciiname":"Angell",
    "gn:country_code":"US",
    "gn:dem":1802,
    "gn:elevation":"1802.0",
    "gn:feature_class":"P",
    "gn:feature_code":"PPL",
    "gn:name":"Angell",
    "gn:population":0,
    "gn:timezone":"America/Phoenix",
    "iso:country":"US",
    "name:eng_x_preferred":[
        "Angell"
    ],
    "name:und_x_variant":[
        "Laguna"
    ],
    "name:zho_x_preferred":[
        "\u5b89\u683c\u723e"
    ],
    "wof:name":"Angell",
    "wof:placetype":"locality"
},
  "geometry": {"coordinates":[-111.30404,35.19557000000001],"type":"Point"}
}