{
  "type": "Feature",
  "properties": {
    "gn:elevation":91,
    "iso:country":"US",
    "name:eng_x_preferred":[
        "Wickwood"
    ],
    "qs:gn_fcode":"PPL",
    "qs:gn_local":0,
    "qs:gn_namadm1":"DE",
    "qs:gn_name":"Wickwood",
    "qs:local_max":2533,
    "qs:local_sum":18472,
    "qs:localhoods":42,
    "qs:name":"Wickwood",
    "qs:name_adm0":"United States",
    "qs:name_adm1":"Delaware",
    "qs:name_adm2":"New Castle",
    "qs:name_local":"Wilmington",
    "qs:photo_max":32,
    "qs:photo_sum":51,
    "qs:placetype":"Suburb",
    "qs:quad_count":10,
    "qs:woe_adm0":23424977,
    "qs:woe_adm1":2347566,
    "qs:woe_adm2":12587800,
    "qs:woe_lau":0,
    "qs:woe_local":2521358,
    "qs:woe_ver":"7.10.0",
    "wof:name":"Wickwood",
    "wof:placetype":"neighbourhood",
    "wof:population":4175,
    "zs:blockids":[
        100030112062024,
        100030112011012,
        100030115003017,
        100030114003017,
        100030114003021,
        100030115001005,
        100030114003004,
        100030114003001,
        100030115001000,
        100030114002007,
        100030114002008,
        100030114002005,
        100030114002014,
        100030112062027,
        100030115003009,
        100030114003014,
        100030114003003,
        100030115002009,
        100030115003008,
        100030116002005,
        100030114003009,
        100030114003006,
        100030114002012,
        100030114002019,
        100030114002017,
        100030115001003,
        100030112062018,
        100030116002002,
        100030115001001,
        100030116002000,
        100030114003023,
        100030114003020,
        100030112061010,
        100030114003016,
        100030112062017,
        100030112062029,
        100030112062025,
        100030112062020,
        100030114003002,
        100030114002000,
        100030114003010,
        100030114003012,
        100030115002011,
        100030114003022,
        100030114002016,
        100030115001004,
        100030112062021,
        100030114003000,
        100030114003018,
        100030112061016,
        100030116002001,
        100030114003005,
        100030114003019,
        100030114003008,
        100030112062028,
        100030112062026,
        100030115002016,
        100030115001002,
        100030114003015,
        100030114003013,
        100030114002006,
        100030112062016,
        100030115002010,
        100030115003007,
        100030114003011,
        100030116002003,
        100030115003000,
        100030115001006,
        100030116002006,
        100030114003007,
        100030114002011
    ],
    "zs:housing10":1740,
    "zs:pop10":4175
},
  "geometry": {"coordinates":[-75.524484,39.801538],"type":"Point"}
}