{
  "type": "Feature",
  "properties": {
    "gn:admin1_code":"SC",
    "gn:admin2_code":"69.0",
    "gn:asciiname":"Fulton",
    "gn:country_code":"US",
    "gn:dem":70,
    "gn:elevation":"68.0",
    "gn:feature_class":"P",
    "gn:feature_code":"PPL",
    "gn:name":"Fulton",
    "gn:population":0,
    "gn:timezone":"America/New_York",
    "iso:country":"US",
    "name:cat_x_preferred":[
        "Fulton"
    ],
    "name:ceb_x_preferred":[
        "Fulton"
    ],
    "name:ces_x_preferred":[
        "Fulton"
    ],
    "name:deu_x_preferred":[
        "Fulton"
    ],
    "name:fas_x_preferred":[
        "\u0641\u0648\u0644\u062a\u0646"
    ],
    "name:fin_x_preferred":[
        "Fulton"
    ],
    "name:fra_x_preferred":[
        "Fulton"
    ],
    "name:hrv_x_preferred":[
        "Fulton"
    ],
    "name:hun_x_preferred":[
        "Fulton"
    ],
    "name:ido_x_preferred":[
        "Fulton"
    ],
    "name:ita_x_preferred":[
        "Fulton"
    ],
    "name:jpn_x_preferred":[
        "\u30d5\u30eb\u30c8\u30f3"
    ],
    "name:nld_x_preferred":[
        "Fulton"
    ],
    "name:nor_x_preferred":[
        "Fulton"
    ],
    "name:pol_x_preferred":[
        "Fulton"
    ],
    "name:por_x_preferred":[
        "Fulton"
    ],
    "name:rus_x_preferred":[
        "\u0424\u0443\u043b\u0442\u043e\u043d"
    ],
    "name:spa_x_preferred":[
        "Fulton"
    ],
    "name:srp_x_preferred":[
        "\u0424\u0443\u043b\u0442\u043e\u043d"
    ],
    "name:swe_x_preferred":[
        "Fulton"
    ],
    "name:tur_x_preferred":[
        "Fulton"
    ],
    "name:ukr_x_preferred":[
        "\u0424\u0443\u043b\u0442\u043e\u043d"
    ],
    "name:urd_x_preferred":[
        "\u0641\u0644\u0679\u0646"
    ],
    "name:vol_x_preferred":[
        "Fulton"
    ],
    "name:zho_x_preferred":[
        "\u5bcc\u5c14\u987f"
    ],
    "wof:name":"Fulton",
    "wof:placetype":"locality"
},
  "geometry": {"coordinates":[-79.79173,34.77820999999999],"type":"Point"}
}