{
  "type": "Feature",
  "properties": {
    "gn:admin1_code":"MD",
    "gn:admin2_code":"21.0",
    "gn:asciiname":"Fox Pass",
    "gn:country_code":"US",
    "gn:dem":117,
    "gn:elevation":"118.0",
    "gn:feature_class":"P",
    "gn:feature_code":"PPL",
    "gn:name":"Fox Pass",
    "gn:population":0,
    "gn:timezone":"America/New_York",
    "iso:country":"US",
    "wof:name":"Fox Pass",
    "wof:placetype":"locality"
},
  "geometry": {"coordinates":[-77.25332,39.45732],"type":"Point"}
}