{
  "type": "Feature",
  "properties": {
    "gn:admin1_code":"LA",
    "gn:admin2_code":"19.0",
    "gn:asciiname":"Goss",
    "gn:country_code":"US",
    "gn:dem":5,
    "gn:elevation":"6.0",
    "gn:feature_class":"P",
    "gn:feature_code":"PPL",
    "gn:name":"Goss",
    "gn:population":0,
    "gn:timezone":"America/Chicago",
    "iso:country":"US",
    "name:deu_x_preferred":[
        "Goss"
    ],
    "name:fra_x_preferred":[
        "Goss"
    ],
    "name:ita_x_preferred":[
        "Goss"
    ],
    "name:pol_x_preferred":[
        "Goss"
    ],
    "name:rus_x_preferred":[
        "\u0413\u043e\u0441\u0441"
    ],
    "name:slv_x_preferred":[
        "Goss"
    ],
    "wof:name":"Goss",
    "wof:placetype":"locality"
},
  "geometry": {"coordinates":[-93.14988,30.30687],"type":"Point"}
}