{
  "type": "Feature",
  "properties": {
    "gn:admin1_code":"MN",
    "gn:admin2_code":"35.0",
    "gn:admin3_code":"7300.0",
    "gn:asciiname":"East Gate Mobile Home Park",
    "gn:country_code":"US",
    "gn:dem":360,
    "gn:elevation":"363.0",
    "gn:feature_class":"P",
    "gn:feature_code":"PPL",
    "gn:name":"East Gate Mobile Home Park",
    "gn:population":0,
    "gn:timezone":"America/Chicago",
    "iso:country":"US",
    "wof:name":"East Gate Mobile Home Park",
    "wof:placetype":"campus"
},
  "geometry": {"coordinates":[-94.16943999999999,46.36722],"type":"Point"}
}