{
  "type": "Feature",
  "properties": {
    "gn:admin1_code":"VA",
    "gn:admin2_code":"33.0",
    "gn:asciiname":"Bagby",
    "gn:country_code":"US",
    "gn:dem":58,
    "gn:elevation":"57.0",
    "gn:feature_class":"P",
    "gn:feature_code":"PPL",
    "gn:name":"Bagby",
    "gn:population":0,
    "gn:timezone":"America/New_York",
    "iso:country":"US",
    "name:fas_x_preferred":[
        "\u0628\u0627\u06af\u0628\u06cc"
    ],
    "wof:name":"Bagby",
    "wof:placetype":"locality"
},
  "geometry": {"coordinates":[-77.23137,37.92625],"type":"Point"}
}