{
  "type": "Feature",
  "properties": {
    "gn:admin1_code":"NC",
    "gn:admin2_code":"171",
    "gn:admin3_code":"93064.0",
    "gn:asciiname":"Indian Grove",
    "gn:country_code":"US",
    "gn:dem":429,
    "gn:elevation":"429.0",
    "gn:feature_class":"P",
    "gn:feature_code":"PPL",
    "gn:name":"Indian Grove",
    "gn:population":0,
    "gn:timezone":"America/New_York",
    "iso:country":"US",
    "name:eng_x_preferred":[
        "Indian Grove"
    ],
    "name:und_x_variant":[
        "Indian Graves"
    ],
    "name:vol_x_preferred":[
        "Indian Grove"
    ],
    "wof:name":"Indian Grove",
    "wof:placetype":"locality"
},
  "geometry": {"coordinates":[-80.52478000000001,36.49097],"type":"Point"}
}