{
  "type": "Feature",
  "properties": {
    "gn:admin1_code":"CO",
    "gn:admin2_code":"113.0",
    "gn:asciiname":"Noel",
    "gn:country_code":"US",
    "gn:dem":2691,
    "gn:elevation":"2681.0",
    "gn:feature_class":"P",
    "gn:feature_code":"PPL",
    "gn:name":"Noel",
    "gn:population":0,
    "gn:timezone":"America/Denver",
    "iso:country":"US",
    "name:ceb_x_preferred":[
        "Noel"
    ],
    "name:ces_x_preferred":[
        "Noel"
    ],
    "name:fin_x_preferred":[
        "Noel"
    ],
    "name:heb_x_preferred":[
        "\u05e0\u05d5\u05d0\u05dc"
    ],
    "name:hun_x_preferred":[
        "Noel"
    ],
    "name:ita_x_preferred":[
        "Noel"
    ],
    "name:jpn_x_preferred":[
        "\u30ce\u30a8\u30eb"
    ],
    "name:pol_x_preferred":[
        "Noel"
    ],
    "name:por_x_preferred":[
        "Noel"
    ],
    "name:rus_x_preferred":[
        "\u041d\u043e\u044d\u043b\u044c"
    ],
    "name:swe_x_preferred":[
        "Noel"
    ],
    "wof:name":"Noel",
    "wof:placetype":"locality"
},
  "geometry": {"coordinates":[-107.91284,38.09971],"type":"Point"}
}