{
  "type": "Feature",
  "properties": {
    "gn:admin1_code":"MO",
    "gn:admin2_code":"11.0",
    "gn:admin3_code":"53048.0",
    "gn:asciiname":"Esrom",
    "gn:country_code":"US",
    "gn:dem":297,
    "gn:elevation":"294.0",
    "gn:feature_class":"P",
    "gn:feature_code":"PPL",
    "gn:name":"Esrom",
    "gn:population":0,
    "gn:timezone":"America/Chicago",
    "iso:country":"US",
    "name:ces_x_preferred":[
        "Esrom"
    ],
    "name:deu_x_preferred":[
        "Esrom"
    ],
    "name:eng_x_preferred":[
        "Esrom"
    ],
    "name:fin_x_preferred":[
        "Esrom"
    ],
    "name:fra_x_preferred":[
        "Esrom"
    ],
    "name:hrv_x_preferred":[
        "Esrom"
    ],
    "name:ind_x_preferred":[
        "Esrom"
    ],
    "name:lat_x_preferred":[
        "Esrom"
    ],
    "name:spa_x_preferred":[
        "Esrom"
    ],
    "name:und_x_variant":[
        "Farmersville"
    ],
    "name:zho_x_preferred":[
        "\u827e\u65af\u8afe\u59c6\u829d\u58eb"
    ],
    "wof:name":"Esrom",
    "wof:placetype":"locality"
},
  "geometry": {"coordinates":[-94.32767,37.41339],"type":"Point"}
}