{
  "type": "Feature",
  "properties": {
    "gn:country":"US",
    "gn:fcode":"PPL",
    "gn:population":0,
    "iso:country":"US",
    "name:azb_x_preferred":[
        "\u0646\u067e\u0627"
    ],
    "name:eng_x_preferred":[
        "Knappa"
    ],
    "name:fas_x_preferred":[
        "\u0646\u067e\u0627"
    ],
    "name:fra_x_preferred":[
        "Knappa"
    ],
    "name:hat_x_preferred":[
        "Knappa"
    ],
    "name:hun_x_preferred":[
        "Knappa"
    ],
    "name:lld_x_preferred":[
        "Knappa"
    ],
    "name:vie_x_preferred":[
        "Knappa"
    ],
    "name:vol_x_preferred":[
        "Knappa"
    ],
    "qs_pg:aaroncc":"US",
    "qs_pg:gn_country":"US",
    "qs_pg:gn_fcode":"PPL",
    "qs_pg:gn_pop":0,
    "qs_pg:name":"Knappa",
    "qs_pg:name_adm0":"United States",
    "qs_pg:name_adm1":"Oregon",
    "qs_pg:photos":45,
    "qs_pg:photos_1k":9,
    "qs_pg:photos_9k":1,
    "qs_pg:photos_9r":2,
    "qs_pg:photos_all":45,
    "qs_pg:photos_sr":2,
    "qs_pg:pop_sr":5,
    "qs_pg:qs_pg_placetype":"locality",
    "qs_pg:qs_pg_placetype_gp":"Town",
    "qs_pg:woe_adm0":23424977,
    "woe:adm0_id":23424977,
    "woe:name_adm0":"United States",
    "woe:name_adm1":"Oregon",
    "woe:placetype":"Town",
    "wof:name":"Knappa",
    "wof:placetype":"locality"
},
  "geometry": {"coordinates":[-123.58597,46.18511],"type":"Point"}
}