{
  "type": "Feature",
  "properties": {
    "gn:country":"US",
    "gn:fcode":"PPL",
    "gn:population":73,
    "iso:country":"US",
    "name:ceb_x_preferred":[
        "Wyman"
    ],
    "name:deu_x_preferred":[
        "Wyman"
    ],
    "name:fra_x_preferred":[
        "Wyman"
    ],
    "name:heb_x_preferred":[
        "\u05d5\u05d9\u05d9\u05de\u05df"
    ],
    "name:jpn_x_preferred":[
        "\u30ef\u30a4\u30de\u30f3"
    ],
    "name:por_x_preferred":[
        "Wyman"
    ],
    "name:rus_x_preferred":[
        "\u0423\u0430\u0439\u043c\u0435\u043d"
    ],
    "name:swe_x_preferred":[
        "Wyman"
    ],
    "qs_pg:aaroncc":"US",
    "qs_pg:gn_country":"US",
    "qs_pg:gn_fcode":"PPL",
    "qs_pg:gn_pop":73,
    "qs_pg:name":"Wyman",
    "qs_pg:photos_9r":0,
    "qs_pg:photos_sr":0,
    "qs_pg:pop_sr":1,
    "qs_pg:qs_pg_placetype":"locality",
    "wof:name":"Wyman",
    "wof:placetype":"locality",
    "wof:population":73
},
  "geometry": {"coordinates":[-67.85917000000001,44.50786],"type":"Point"}
}