{
  "type": "Feature",
  "properties": {
    "gn:admin1_code":"WV",
    "gn:admin2_code":"87.0",
    "gn:asciiname":"Tristan",
    "gn:country_code":"US",
    "gn:dem":222,
    "gn:elevation":"220.0",
    "gn:feature_class":"P",
    "gn:feature_code":"PPL",
    "gn:name":"Tristan",
    "gn:population":0,
    "gn:timezone":"America/New_York",
    "iso:country":"US",
    "name:bre_x_preferred":[
        "Tristan"
    ],
    "name:bul_x_preferred":[
        "\u0422\u0440\u0438\u0441\u0442\u0430\u043d"
    ],
    "name:cat_x_preferred":[
        "Tristany"
    ],
    "name:ces_x_preferred":[
        "Tristan"
    ],
    "name:cym_x_preferred":[
        "Trystan"
    ],
    "name:dan_x_preferred":[
        "Tristan"
    ],
    "name:epo_x_preferred":[
        "Tristan"
    ],
    "name:eus_x_preferred":[
        "Tristan"
    ],
    "name:fin_x_preferred":[
        "Tristan"
    ],
    "name:fra_x_preferred":[
        "Tristan"
    ],
    "name:ind_x_preferred":[
        "Tristan"
    ],
    "name:jpn_x_preferred":[
        "\u30c8\u30ea\u30b9\u30bf\u30f3"
    ],
    "name:nld_x_preferred":[
        "Tristan"
    ],
    "name:nor_x_preferred":[
        "Tristan"
    ],
    "name:pol_x_preferred":[
        "Tristan"
    ],
    "name:por_x_preferred":[
        "Trist\u00e3o"
    ],
    "name:spa_x_preferred":[
        "Trist\u00e1n"
    ],
    "name:tur_x_preferred":[
        "Tristan"
    ],
    "name:zho_x_preferred":[
        "\u5d14\u65af\u5766"
    ],
    "wof:name":"Tristan",
    "wof:placetype":"locality"
},
  "geometry": {"coordinates":[-81.22705999999999,38.80259],"type":"Point"}
}