{
  "type": "Feature",
  "properties": {
    "gn:admin1_code":"GA",
    "gn:admin2_code":"217",
    "gn:asciiname":"Skyline",
    "gn:country_code":"US",
    "gn:dem":242,
    "gn:elevation":"237.0",
    "gn:feature_class":"P",
    "gn:feature_code":"PPL",
    "gn:name":"Skyline",
    "gn:population":0,
    "gn:timezone":"America/New_York",
    "iso:country":"US",
    "name:ara_x_preferred":[
        "\u062e\u0637 \u0623\u0641\u0642"
    ],
    "name:ast_x_preferred":[
        "Panorama urbanu"
    ],
    "name:bel_x_preferred":[
        "\u0421\u043a\u0430\u0439\u043b\u0430\u0439\u043d"
    ],
    "name:ben_x_preferred":[
        "\u09a6\u09bf\u0997\u09a8\u09cd\u09a4 \u09b0\u09c2\u09aa\u09b0\u09c7\u0996\u09be"
    ],
    "name:bul_x_preferred":[
        "\u0413\u0440\u0430\u0434\u0441\u043a\u0430 \u043f\u0430\u043d\u043e\u0440\u0430\u043c\u0430"
    ],
    "name:cat_x_preferred":[
        "Silueta urbana"
    ],
    "name:dan_x_preferred":[
        "Skyline"
    ],
    "name:deu_x_preferred":[
        "Skyline"
    ],
    "name:fas_x_preferred":[
        "\u062f\u0648\u0631\u0646\u0645\u0627\u06cc \u0634\u0647\u0631\u06cc"
    ],
    "name:fin_x_preferred":[
        "Skyline"
    ],
    "name:fra_x_preferred":[
        "Panorama urbain"
    ],
    "name:fry_x_preferred":[
        "Stedssilh\u00fbet"
    ],
    "name:heb_x_preferred":[
        "\u05e7\u05d5 \u05e8\u05e7\u05d9\u05e2"
    ],
    "name:ita_x_preferred":[
        "Skyline"
    ],
    "name:jpn_x_preferred":[
        "\u30b9\u30ab\u30a4\u30e9\u30a4\u30f3"
    ],
    "name:kor_x_preferred":[
        "\uc2a4\uce74\uc774\ub77c\uc778"
    ],
    "name:lat_x_preferred":[
        "Linea caelestis"
    ],
    "name:msa_x_preferred":[
        "Latar langit"
    ],
    "name:nld_x_preferred":[
        "Skyline"
    ],
    "name:nor_x_preferred":[
        "Skyline"
    ],
    "name:pol_x_preferred":[
        "Skyline"
    ],
    "name:por_x_preferred":[
        "Panorama urbano"
    ],
    "name:rus_x_preferred":[
        "\u0421\u043a\u0430\u0439\u043b\u0430\u0439\u043d"
    ],
    "name:slk_x_preferred":[
        "Skyline"
    ],
    "name:spa_x_preferred":[
        "Panorama urbano"
    ],
    "name:swe_x_preferred":[
        "Stadssiluett"
    ],
    "name:tgl_x_preferred":[
        "Panoramang urbano"
    ],
    "name:tur_x_preferred":[
        "\u015eehir sil\u00fceti"
    ],
    "name:ukr_x_preferred":[
        "\u0421\u043a\u0430\u0439\u043b\u0430\u0439\u043d"
    ],
    "name:urd_x_preferred":[
        "\u062e\u0637 \u0641\u0644\u06a9\u06cc"
    ],
    "name:yid_x_preferred":[
        "\u05d4\u05d9\u05de\u05dc \u05dc\u05d9\u05e0\u05d9\u05e2"
    ],
    "name:zho_x_preferred":[
        "\u5929\u969b\u7dda"
    ],
    "wof:name":"Skyline",
    "wof:placetype":"locality"
},
  "geometry": {"coordinates":[-83.75546,33.58817],"type":"Point"}
}