{
  "type": "Feature",
  "properties": {
    "iso:country":"US",
    "name:eng_x_preferred":[
        "Morgan Road"
    ],
    "wof:name":"Morgan Road",
    "wof:placetype":"neighbourhood",
    "wof:population":1790,
    "zs:area_m":6477841.92097,
    "zs:blockids":[
        370210025031006,
        370210025041015,
        370210025043010,
        370210025032003,
        370210025031003,
        370210025032008,
        370210025043011,
        370210025041016,
        370210025032004,
        370210025032005,
        370210025031004,
        370210025032001,
        370210025031005,
        370210025041022,
        370210025043000,
        370210025043006,
        370210025032002,
        370210025032011,
        370210025032007,
        370210025031000,
        370210025032009,
        370210025032013,
        370210025032006,
        370210025032010
    ],
    "zs:housing10":783,
    "zs:label":"Morgan Road",
    "zs:pop10":1790
},
  "geometry": {"coordinates":[-82.717366,35.553328],"type":"Point"}
}