{
  "type": "Feature",
  "properties": {
    "gn:admin1_code":"TX",
    "gn:admin2_code":"487.0",
    "gn:asciiname":"Parsley Hill",
    "gn:country_code":"US",
    "gn:dem":404,
    "gn:elevation":"402.0",
    "gn:feature_class":"P",
    "gn:feature_code":"PPL",
    "gn:name":"Parsley Hill",
    "gn:population":0,
    "gn:timezone":"America/Chicago",
    "iso:country":"US",
    "wof:name":"Parsley Hill",
    "wof:placetype":"locality"
},
  "geometry": {"coordinates":[-99.41674999999999,34.04009],"type":"Point"}
}