{
  "type": "Feature",
  "properties": {
    "iso:country":"US",
    "name:eng_x_preferred":[
        "Downtown Tarrytown"
    ],
    "qs:gn_adm0_cc":"US",
    "qs:gn_local":5140538,
    "qs:gn_nam_loc":"Tarrytown, Westchester, New York, US",
    "qs:gn_namadm1":"NY",
    "qs:local_max":1923,
    "qs:local_sum":5389,
    "qs:localhoods":6,
    "qs:name":"Downtown Tarrytown",
    "qs:name_adm0":"United States",
    "qs:name_adm1":"New York",
    "qs:name_adm2":"Westchester",
    "qs:name_local":"Tarrytown",
    "qs:photo_max":348,
    "qs:photo_sum":881,
    "qs:placetype":"Suburb",
    "qs:quad_count":19,
    "qs:woe_adm0":23424977,
    "qs:woe_adm1":2347591,
    "qs:woe_adm2":12589371,
    "qs:woe_lau":0,
    "qs:woe_local":2504171,
    "qs:woe_ver":"7.10.0",
    "wof:lang":[
        "eng"
    ],
    "wof:name":"Downtown Tarrytown",
    "wof:placetype":"neighbourhood",
    "wof:population":6115,
    "zs:blockids":[
        361190116002000,
        361190116002006,
        361190116001004,
        361190116001007,
        361190115001024,
        361190115001025,
        361190115001020,
        361190114004013,
        361190114004014,
        361190115001014,
        361190117001020,
        361190115002001,
        361190115001013,
        361190115001015,
        361190114005014,
        361190115001004,
        361190115002007,
        361190116001000,
        361190116003008,
        361190116002005,
        361190115001002,
        361190116001001,
        361190115001007,
        361190115001021,
        361190117001045,
        361190117001044,
        361190115001010,
        361190115001019,
        361190115001001,
        361190114005008,
        361190115001012,
        361190115001017,
        361190117001047,
        361190117001043,
        361190115001023,
        361190117001048,
        361190115001018,
        361190115001026,
        361190115001005,
        361190117001046,
        361190117001049,
        361190116001006,
        361190116002001,
        361190115002002,
        361190115002009,
        361190116002003,
        361190115001000,
        361190115001011,
        361190115001022,
        361190117001035,
        361190114004017,
        361190117001026,
        361190115001003,
        361190115002006,
        361190114004016,
        361190117001021,
        361190116001005,
        361190114005007,
        361190116002002,
        361190115002000,
        361190115001009,
        361190116001002,
        361190115001008,
        361190116001008,
        361190116001009,
        361190115001006
    ],
    "zs:housing10":2479,
    "zs:pop10":6115
},
  "geometry": {"coordinates":[-73.85954700000001,41.079196],"type":"Point"}
}