{
  "type": "Feature",
  "properties": {
    "gn:admin1_code":"FL",
    "gn:admin2_code":"57",
    "gn:asciiname":"Rustic Village",
    "gn:country_code":"US",
    "gn:dem":25,
    "gn:elevation":"12.0",
    "gn:feature_class":"P",
    "gn:feature_code":"PPL",
    "gn:name":"Rustic Village",
    "gn:population":0,
    "gn:timezone":"America/New_York",
    "iso:country":"US",
    "wof:name":"Rustic Village",
    "wof:placetype":"locality"
},
  "geometry": {"coordinates":[-82.37350000000001,28.0517],"type":"Point"}
}