{
  "type": "Feature",
  "properties": {
    "gn:country":"US",
    "gn:fcode":"PPL",
    "gn:population":0,
    "iso:country":"US",
    "name:azb_x_preferred":[
        "\u0648\u0646\u0648\u0633"
    ],
    "name:cat_x_preferred":[
        "Venus"
    ],
    "name:deu_x_preferred":[
        "Venus"
    ],
    "name:eng_x_preferred":[
        "Venus"
    ],
    "name:fas_x_preferred":[
        "\u0648\u0646\u0648\u0633\u060c \u0641\u0644\u0648\u0631\u06cc\u062f\u0627"
    ],
    "name:fas_x_variant":[
        "\u0648\u0646\u0648\u0633"
    ],
    "name:fra_x_preferred":[
        "Venus"
    ],
    "name:ita_x_preferred":[
        "Venus"
    ],
    "name:nan_x_preferred":[
        "Venus"
    ],
    "name:nld_x_preferred":[
        "Venus"
    ],
    "name:nno_x_preferred":[
        "Venus"
    ],
    "name:nob_x_preferred":[
        "Venus"
    ],
    "name:oci_x_preferred":[
        "Venus"
    ],
    "name:por_x_preferred":[
        "Venus"
    ],
    "name:rus_x_preferred":[
        "\u0412\u0435\u043d\u0443\u0441"
    ],
    "name:spa_x_preferred":[
        "Venus"
    ],
    "name:zho_x_preferred":[
        "\u7dad\u7d0d\u65af"
    ],
    "qs_pg:aaroncc":"US",
    "qs_pg:gn_country":"US",
    "qs_pg:gn_fcode":"PPL",
    "qs_pg:gn_pop":0,
    "qs_pg:name":"Venus",
    "qs_pg:name_adm0":"United States",
    "qs_pg:name_adm1":"Florida",
    "qs_pg:photos_9k":1,
    "qs_pg:photos_9r":1,
    "qs_pg:photos_all":11,
    "qs_pg:photos_sr":0,
    "qs_pg:pop_sr":5,
    "qs_pg:qs_pg_placetype":"locality",
    "qs_pg:qs_pg_placetype_gp":"Town",
    "qs_pg:woe_adm0":23424977,
    "woe:adm0_id":23424977,
    "woe:name_adm0":"United States",
    "woe:name_adm1":"Florida",
    "woe:placetype":"Town",
    "wof:name":"Venus",
    "wof:placetype":"locality"
},
  "geometry": {"coordinates":[-81.35674,27.06728],"type":"Point"}
}