{
  "type": "Feature",
  "properties": {
    "gn:admin1_code":"IN",
    "gn:admin2_code":"109.0",
    "gn:admin3_code":"80846.0",
    "gn:asciiname":"Woodcrest",
    "gn:country_code":"US",
    "gn:dem":250,
    "gn:elevation":"243.0",
    "gn:feature_class":"P",
    "gn:feature_code":"PPL",
    "gn:name":"Woodcrest",
    "gn:population":0,
    "gn:timezone":"America/Indiana/Indianapolis",
    "iso:country":"US",
    "name:deu_x_preferred":[
        "Woodcrest"
    ],
    "name:ita_x_preferred":[
        "Woodcrest"
    ],
    "wof:name":"Woodcrest",
    "wof:placetype":"locality"
},
  "geometry": {"coordinates":[-86.39471999999998,39.43755],"type":"Point"}
}