{
  "type": "Feature",
  "properties": {
    "iso:country":"US",
    "name:eng_x_preferred":[
        "Brushy Creek North"
    ],
    "wof:name":"Brushy Creek North",
    "wof:placetype":"neighbourhood",
    "wof:population":1997,
    "zs:area_m":2684228.003283,
    "zs:blockids":[
        484910206032039,
        484910206032028,
        484910206032037,
        484910206032016,
        484910206032036,
        484910206032013,
        484910203101029,
        484910206032012,
        484910206032042,
        484910206032015,
        484910206032019,
        484910206032026,
        484910206032022,
        484910206032010,
        484910206032009,
        484910206032030,
        484910206032023,
        484910203102024,
        484910206032020,
        484910206032047,
        484910203102025,
        484910206032038,
        484910206032011,
        484910206032027,
        484910206032032,
        484910206032014,
        484910203102023,
        484910206032043,
        484910206032018,
        484910206032052,
        484910206032021,
        484910206032017,
        484910206032025,
        484910206032029
    ],
    "zs:housing10":658,
    "zs:label":"Brushy Creek North",
    "zs:pop10":1997
},
  "geometry": {"coordinates":[-97.737257,30.539737],"type":"Point"}
}