{
  "type": "Feature",
  "properties": {
    "gn:country":"US",
    "gn:fcode":"PPL",
    "gn:population":718,
    "iso:country":"US",
    "name:ara_x_preferred":[
        "\u0648\u0627\u064a\u0646 \u0644\u064a\u0643\u0633"
    ],
    "name:cat_x_preferred":[
        "Wayne Lakes"
    ],
    "name:deu_x_preferred":[
        "Wayne Lakes"
    ],
    "name:eng_x_preferred":[
        "Wayne Lakes Park"
    ],
    "name:eng_x_variant":[
        "Wayne Lakes"
    ],
    "name:eus_x_preferred":[
        "Wayne Lakes"
    ],
    "name:fra_x_preferred":[
        "Wayne Lakes"
    ],
    "name:hat_x_preferred":[
        "Wayne Lakes"
    ],
    "name:ita_x_preferred":[
        "Wayne Lakes"
    ],
    "name:mlg_x_preferred":[
        "Wayne Lakes"
    ],
    "name:nan_x_preferred":[
        "Wayne Lakes"
    ],
    "name:nld_x_preferred":[
        "Wayne Lakes"
    ],
    "name:pol_x_preferred":[
        "Wayne Lakes"
    ],
    "name:por_x_preferred":[
        "Wayne Lakes"
    ],
    "name:spa_x_preferred":[
        "Wayne Lakes"
    ],
    "name:srp_x_preferred":[
        "\u0412\u0435\u0458\u043d \u041b\u0435\u0458\u043a\u0441"
    ],
    "name:vie_x_preferred":[
        "Wayne Lakes"
    ],
    "name:vol_x_preferred":[
        "Wayne Lakes"
    ],
    "qs_pg:aaroncc":"US",
    "qs_pg:gn_country":"US",
    "qs_pg:gn_fcode":"PPL",
    "qs_pg:gn_pop":718,
    "qs_pg:name":"Wayne Lakes Park",
    "qs_pg:name_adm0":"United States",
    "qs_pg:name_adm1":"Ohio",
    "qs_pg:photos_9r":0,
    "qs_pg:photos_sr":0,
    "qs_pg:pop_sr":2,
    "qs_pg:qs_pg_placetype":"locality",
    "qs_pg:qs_pg_placetype_gp":"Town",
    "qs_pg:woe_adm0":23424977,
    "woe:adm0_id":23424977,
    "woe:name_adm0":"United States",
    "woe:name_adm1":"Ohio",
    "woe:placetype":"Town",
    "wof:name":"Wayne Lakes Park",
    "wof:placetype":"locality",
    "wof:population":718
},
  "geometry": {"coordinates":[-84.6619,40.0231],"type":"Point"}
}