{
  "type": "Feature",
  "properties": {
    "gn:admin1_code":"TN",
    "gn:admin2_code":"51",
    "gn:asciiname":"Oak Grove",
    "gn:country_code":"US",
    "gn:dem":325,
    "gn:elevation":"325.0",
    "gn:feature_class":"P",
    "gn:feature_code":"PPL",
    "gn:name":"Oak Grove",
    "gn:population":0,
    "gn:timezone":"America/Chicago",
    "iso:country":"US",
    "name:cat_x_preferred":[
        "Oak Grove"
    ],
    "name:ceb_x_preferred":[
        "Oak Grove"
    ],
    "name:deu_x_preferred":[
        "Oak Grove"
    ],
    "name:fra_x_preferred":[
        "Oak Grove"
    ],
    "name:hun_x_preferred":[
        "Oak Grove"
    ],
    "name:ita_x_preferred":[
        "Oak Grove"
    ],
    "name:nld_x_preferred":[
        "Oak Grove"
    ],
    "name:pol_x_preferred":[
        "Oak Grove"
    ],
    "name:por_x_preferred":[
        "Oak Grove"
    ],
    "name:rus_x_preferred":[
        "\u041e\u0443\u043a-\u0413\u0440\u043e\u0443\u0432"
    ],
    "name:spa_x_preferred":[
        "Oak Grove"
    ],
    "name:srp_x_preferred":[
        "\u041e\u0443\u043a \u0413\u0440\u043e\u0443\u0432"
    ],
    "name:swe_x_preferred":[
        "Oak Grove"
    ],
    "name:vol_x_preferred":[
        "Oak Grove"
    ],
    "wof:name":"Oak Grove",
    "wof:placetype":"locality"
},
  "geometry": {"coordinates":[-85.99998000000002,35.2573],"type":"Point"}
}