{
  "type": "Feature",
  "properties": {
    "gn:admin1_code":"MD",
    "gn:admin2_code":"13.0",
    "gn:asciiname":"Buckhorn Run",
    "gn:country_code":"US",
    "gn:dem":194,
    "gn:elevation":"193.0",
    "gn:feature_class":"P",
    "gn:feature_code":"PPL",
    "gn:name":"Buckhorn Run",
    "gn:population":0,
    "gn:timezone":"America/New_York",
    "iso:country":"US",
    "wof:name":"Buckhorn Run",
    "wof:placetype":"locality"
},
  "geometry": {"coordinates":[-77.01442,39.41816],"type":"Point"}
}