{
  "type": "Feature",
  "properties": {
    "gn:country":"US",
    "gn:fcode":"PPL",
    "gn:population":0,
    "iso:country":"US",
    "name:ben_x_preferred":[
        "\u09aa\u09bf\u099f\u09b8\u09ab\u09bf\u09b2\u09cd\u09a1"
    ],
    "name:ell_x_preferred":[
        "\u03a0\u03af\u03c4\u03c3\u03c6\u03b9\u03bb\u03bd\u03c4"
    ],
    "name:eng_x_preferred":[
        "Pittsfield"
    ],
    "name:hin_x_preferred":[
        "\u092a\u093f\u091f\u094d\u0938\u092b\u093c\u0940\u0932\u094d\u0921"
    ],
    "name:ind_x_preferred":[
        "Pittsfield"
    ],
    "qs_pg:aaroncc":"US",
    "qs_pg:gn_country":"US",
    "qs_pg:gn_fcode":"PPL",
    "qs_pg:gn_pop":0,
    "qs_pg:name":"Pittsfield",
    "qs_pg:name_adm0":"United States",
    "qs_pg:name_adm1":"Michigan",
    "qs_pg:photos":2006,
    "qs_pg:photos_1k":406,
    "qs_pg:photos_9k":9,
    "qs_pg:photos_9r":9,
    "qs_pg:photos_all":2006,
    "qs_pg:photos_sr":15,
    "qs_pg:pop_sr":0,
    "qs_pg:qs_pg_placetype":"locality",
    "qs_pg:qs_pg_placetype_gp":"Town",
    "qs_pg:woe_adm0":23424977,
    "woe:adm0_id":23424977,
    "woe:name_adm0":"United States",
    "woe:name_adm1":"Michigan",
    "woe:placetype":"Town",
    "wof:coterminous":[
        404508479
    ],
    "wof:name":"Pittsfield",
    "wof:placetype":"locality",
    "wof:statistical_gore":1
},
  "geometry": {"coordinates":[-83.72411,42.21032],"type":"Point"}
}