{
  "type": "Feature",
  "properties": {
    "iso:country":"US",
    "name:eng_x_preferred":[
        "Pickway Korner"
    ],
    "qs:gn_adm0_cc":"US",
    "qs:gn_local":4297983,
    "qs:gn_nam_loc":"Lexington, Fayette, Kentucky, US",
    "qs:gn_namadm1":"KY",
    "qs:local_max":4034,
    "qs:local_sum":30708,
    "qs:localhoods":91,
    "qs:name":"Pickway Korner",
    "qs:name_adm0":"United States",
    "qs:name_adm1":"Kentucky",
    "qs:name_adm2":"Fayette",
    "qs:name_local":"Lexington",
    "qs:photo_max":97,
    "qs:photo_sum":108,
    "qs:placetype":"Suburb",
    "qs:quad_count":4,
    "qs:woe_adm0":23424977,
    "qs:woe_adm1":2347576,
    "qs:woe_adm2":12588509,
    "qs:woe_lau":0,
    "qs:woe_local":2438841,
    "qs:woe_ver":"7.10.0",
    "wof:lang":[
        "eng"
    ],
    "wof:name":"Pickway Korner",
    "wof:placetype":"neighbourhood",
    "wof:population":2610,
    "zs:blockids":[
        210670041062002,
        210670041062011,
        210670041053012,
        210670041062012,
        210670041031004,
        210670041053005,
        210670041053001,
        210670042041052,
        210670042101000,
        210670041053002,
        210670042101020,
        210670041053006,
        210670041053003,
        210670041062001,
        210670041062013,
        210670041062008,
        210670042041047,
        210670042101024,
        210670041052001,
        210670041053008,
        210670041062003,
        210670041052005,
        210670042101023,
        210670041062000,
        210670042101022,
        210670041062010,
        210670041053007,
        210670041062004,
        210670041053009,
        210670042101021,
        210670041062022,
        210670041062009,
        210670041053004,
        210670041053011,
        210670041053010,
        210670041062005,
        210670041053015
    ],
    "zs:housing10":1244,
    "zs:pop10":2610
},
  "geometry": {"coordinates":[-84.53544599999999,37.971188],"type":"Point"}
}