{
  "type": "Feature",
  "properties": {
    "gn:admin1_code":"AL",
    "gn:admin2_code":"99.0",
    "gn:asciiname":"Renson",
    "gn:country_code":"US",
    "gn:dem":55,
    "gn:elevation":"45.0",
    "gn:feature_class":"P",
    "gn:feature_code":"PPL",
    "gn:name":"Renson",
    "gn:population":0,
    "gn:timezone":"America/Chicago",
    "iso:country":"US",
    "wof:name":"Renson",
    "wof:placetype":"locality"
},
  "geometry": {"coordinates":[-87.28386999999999,31.55405],"type":"Point"}
}