{
  "type": "Feature",
  "properties": {
    "gn:admin1_code":"NC",
    "gn:admin2_code":"159",
    "gn:admin3_code":"90660.0",
    "gn:asciiname":"Corriher Heights",
    "gn:country_code":"US",
    "gn:dem":267,
    "gn:elevation":"267.0",
    "gn:feature_class":"P",
    "gn:feature_code":"PPL",
    "gn:name":"Corriher Heights",
    "gn:population":0,
    "gn:timezone":"America/New_York",
    "iso:country":"US",
    "wof:name":"Corriher Heights",
    "wof:placetype":"locality"
},
  "geometry": {"coordinates":[-80.63479,35.56069],"type":"Point"}
}