{
  "type": "Feature",
  "properties": {
    "gn:admin1_code":"MS",
    "gn:admin2_code":"133.0",
    "gn:asciiname":"Johnsonville",
    "gn:country_code":"US",
    "gn:dem":38,
    "gn:elevation":"36.0",
    "gn:feature_class":"P",
    "gn:feature_code":"PPL",
    "gn:name":"Johnsonville",
    "gn:population":0,
    "gn:timezone":"America/Chicago",
    "iso:country":"US",
    "name:ceb_x_preferred":[
        "Johnsonville"
    ],
    "name:deu_x_preferred":[
        "Johnsonville"
    ],
    "name:fra_x_preferred":[
        "Johnsonville"
    ],
    "name:ita_x_preferred":[
        "Johnsonville"
    ],
    "name:nld_x_preferred":[
        "Johnsonville"
    ],
    "name:pol_x_preferred":[
        "Johnsonville"
    ],
    "name:spa_x_preferred":[
        "Johnsonville"
    ],
    "name:srp_x_preferred":[
        "\u040f\u043e\u043d\u0441\u043e\u043d\u0432\u0438\u043b"
    ],
    "name:ukr_x_preferred":[
        "\u0414\u0436\u043e\u043d\u0441\u043e\u043d\u0432\u0456\u043b\u043b"
    ],
    "name:vol_x_preferred":[
        "Johnsonville"
    ],
    "wof:name":"Johnsonville",
    "wof:placetype":"locality"
},
  "geometry": {"coordinates":[-90.59537,33.41956],"type":"Point"}
}