{
  "type": "Feature",
  "properties": {
    "gn:admin1_code":"TX",
    "gn:admin2_code":"427.0",
    "gn:asciiname":"Robinson Colonia",
    "gn:country_code":"US",
    "gn:dem":59,
    "gn:elevation":"57.0",
    "gn:feature_class":"P",
    "gn:feature_code":"PPL",
    "gn:name":"Robinson Colonia",
    "gn:population":0,
    "gn:timezone":"America/Chicago",
    "iso:country":"US",
    "wof:name":"Robinson Colonia",
    "wof:placetype":"locality"
},
  "geometry": {"coordinates":[-98.98531,26.40923],"type":"Point"}
}