{
  "type": "Feature",
  "properties": {
    "gn:admin1_code":"TX",
    "gn:admin2_code":"107.0",
    "gn:asciiname":"Owens",
    "gn:country_code":"US",
    "gn:dem":929,
    "gn:elevation":"925.0",
    "gn:feature_class":"P",
    "gn:feature_code":"PPL",
    "gn:name":"Owens",
    "gn:population":0,
    "gn:timezone":"America/Chicago",
    "iso:country":"US",
    "name:ces_x_preferred":[
        "Owens"
    ],
    "name:deu_x_preferred":[
        "Owens"
    ],
    "name:fin_x_preferred":[
        "Owens"
    ],
    "name:fra_x_preferred":[
        "Owens"
    ],
    "name:ita_x_preferred":[
        "Owens"
    ],
    "name:nds_x_preferred":[
        "Owens"
    ],
    "name:nld_x_preferred":[
        "Owens"
    ],
    "name:por_x_preferred":[
        "Owens"
    ],
    "name:rus_x_preferred":[
        "\u041e\u0443\u044d\u043d\u0441"
    ],
    "name:ukr_x_preferred":[
        "\u041e\u0443\u0435\u043d\u0441"
    ],
    "wof:name":"Owens",
    "wof:placetype":"locality"
},
  "geometry": {"coordinates":[-101.35293,33.55842],"type":"Point"}
}