{
  "type": "Feature",
  "properties": {
    "gn:admin1_code":"MD",
    "gn:admin2_code":"9.0",
    "gn:asciiname":"Wards Meadow",
    "gn:country_code":"US",
    "gn:dem":28,
    "gn:elevation":"31.0",
    "gn:feature_class":"P",
    "gn:feature_code":"PPL",
    "gn:name":"Wards Meadow",
    "gn:population":0,
    "gn:timezone":"America/New_York",
    "iso:country":"US",
    "wof:name":"Wards Meadow",
    "wof:placetype":"locality"
},
  "geometry": {"coordinates":[-76.65385000000001,38.70345],"type":"Point"}
}