{
  "type": "Feature",
  "properties": {
    "gn:admin1_code":"NH",
    "gn:admin2_code":"9.0",
    "gn:admin3_code":"34820.0",
    "gn:asciiname":"Pike",
    "gn:country_code":"US",
    "gn:dem":229,
    "gn:elevation":"226.0",
    "gn:feature_class":"P",
    "gn:feature_code":"PPL",
    "gn:name":"Pike",
    "gn:population":0,
    "gn:timezone":"America/New_York",
    "iso:country":"US",
    "wof:name":"Pike",
    "wof:placetype":"locality"
},
  "geometry": {"coordinates":[-72.00814,44.0309],"type":"Point"}
}