{
  "type": "Feature",
  "properties": {
    "gn:admin1_code":"GA",
    "gn:admin2_code":"299.0",
    "gn:asciiname":"Bolen",
    "gn:country_code":"US",
    "gn:dem":53,
    "gn:elevation":"49.0",
    "gn:feature_class":"P",
    "gn:feature_code":"PPL",
    "gn:name":"Bolen",
    "gn:population":0,
    "gn:timezone":"America/New_York",
    "iso:country":"US",
    "name:ceb_x_preferred":[
        "Bolen"
    ],
    "name:ces_x_preferred":[
        "Bolen"
    ],
    "name:deu_x_preferred":[
        "Bolen"
    ],
    "name:fra_x_preferred":[
        "Bolen"
    ],
    "name:slk_x_preferred":[
        "Bolen"
    ],
    "name:swe_x_preferred":[
        "Bolen"
    ],
    "wof:name":"Bolen",
    "wof:placetype":"locality"
},
  "geometry": {"coordinates":[-82.46429999999999,31.38993],"type":"Point"}
}