{
  "type": "Feature",
  "properties": {
    "gn:admin1_code":"VA",
    "gn:admin2_code":"153",
    "gn:asciiname":"Gypsum Hill Estates",
    "gn:country_code":"US",
    "gn:dem":140,
    "gn:elevation":"141.0",
    "gn:feature_class":"P",
    "gn:feature_code":"PPL",
    "gn:name":"Gypsum Hill Estates",
    "gn:population":0,
    "gn:timezone":"America/New_York",
    "iso:country":"US",
    "wof:name":"Gypsum Hill Estates",
    "wof:placetype":"locality"
},
  "geometry": {"coordinates":[-77.61888,38.87039],"type":"Point"}
}