{
  "type": "Feature",
  "properties": {
    "gn:admin1_code":"MD",
    "gn:admin2_code":"3.0",
    "gn:asciiname":"Pig Point",
    "gn:country_code":"US",
    "gn:dem":16,
    "gn:elevation":"14.0",
    "gn:feature_class":"P",
    "gn:feature_code":"PPL",
    "gn:name":"Pig Point",
    "gn:population":0,
    "gn:timezone":"America/New_York",
    "iso:country":"US",
    "name:ceb_x_preferred":[
        "Pig Point"
    ],
    "name:deu_x_preferred":[
        "Pig Point"
    ],
    "name:eng_x_preferred":[
        "Pig Point"
    ],
    "name:nno_x_preferred":[
        "Pig Point"
    ],
    "name:und_x_variant":[
        "Leon"
    ],
    "name:zho_x_preferred":[
        "\u76ae\u683c\u89d2"
    ],
    "wof:name":"Pig Point",
    "wof:placetype":"locality"
},
  "geometry": {"coordinates":[-76.70135999999999,38.79289],"type":"Point"}
}