{
  "type": "Feature",
  "properties": {
    "iso:country":"US",
    "name:ara_x_preferred":[
        "\u062c\u0647\u0627\u0632 \u062d\u0641\u0631"
    ],
    "name:bel_x_preferred":[
        "\u0431\u0443\u0440\u0430\u0432\u0430\u044f \u0432\u044b\u0448\u043a\u0430"
    ],
    "name:dan_x_preferred":[
        "Borerig"
    ],
    "name:deu_x_preferred":[
        "Derrickkran"
    ],
    "name:ell_x_preferred":[
        "\u03a6\u03bf\u03c1\u03c4\u03c9\u03c4\u03ae\u03c1\u03b1\u03c2"
    ],
    "name:eng_x_preferred":[
        "Derrick"
    ],
    "name:eng_x_variant":[
        "derrick"
    ],
    "name:epo_x_preferred":[
        "Argano"
    ],
    "name:fas_x_preferred":[
        "\u062f\u0631\u06cc\u06a9"
    ],
    "name:fra_x_preferred":[
        "Derrick"
    ],
    "name:fra_x_variant":[
        "derrick"
    ],
    "name:gla_x_preferred":[
        "Crann-togail"
    ],
    "name:hrv_x_preferred":[
        "Samarica"
    ],
    "name:ind_x_preferred":[
        "Rig pengeboran"
    ],
    "name:ind_x_variant":[
        "rig pengeboran"
    ],
    "name:ita_x_preferred":[
        "Derrick"
    ],
    "name:ita_x_variant":[
        "derrick"
    ],
    "name:jpn_x_preferred":[
        "\u30c7\u30ea\u30c3\u30af"
    ],
    "name:kaz_x_preferred":[
        "\u0411\u04b1\u0440\u0493\u044b\u043b\u0430\u0443 \u043c\u04b1\u043d\u0430\u0440\u0430\u0441\u044b"
    ],
    "name:nds_x_preferred":[
        "Laadboom"
    ],
    "name:nld_x_preferred":[
        "Laadboom"
    ],
    "name:nno_x_preferred":[
        "Borerigg"
    ],
    "name:nno_x_variant":[
        "borerigg"
    ],
    "name:nob_x_preferred":[
        "boret\u00e5rn"
    ],
    "name:nor_x_preferred":[
        "Boret\u00e5rn"
    ],
    "name:pol_x_preferred":[
        "Bom \u0142adunkowy"
    ],
    "name:por_x_preferred":[
        "Torre de perfura\u00e7\u00e3o"
    ],
    "name:ron_x_preferred":[
        "Big\u0103"
    ],
    "name:rus_x_preferred":[
        "\u041c\u0430\u0447\u0442\u043e\u0432\u044b\u0439 \u043a\u0440\u0430\u043d"
    ],
    "name:rus_x_variant":[
        "\u0411\u0443\u0440\u043e\u0432\u0430\u044f \u0432\u044b\u0448\u043a\u0430",
        "\u0431\u0443\u0440\u043e\u0432\u0430\u044f \u0432\u044b\u0448\u043a\u0430"
    ],
    "name:slv_x_preferred":[
        "vrtalni stolp"
    ],
    "name:spa_x_preferred":[
        "Gr\u00faa Derrick"
    ],
    "name:swe_x_preferred":[
        "RC-borrning"
    ],
    "name:tam_x_preferred":[
        "\u0ba4\u0bc1\u0bb3\u0bc8 \u0baa\u0bca\u0bb1\u0bbf"
    ],
    "name:tuk_x_preferred":[
        "Buraw wy\u015fkasy"
    ],
    "name:ukr_x_preferred":[
        "\u0411\u0443\u0440\u043e\u0432\u0430 \u0432\u0438\u0448\u043a\u0430"
    ],
    "name:zho_x_preferred":[
        "\u5854\u5f0f\u8d77\u91cd\u6a5f"
    ],
    "wd:wordcount":2654,
    "wof:name":"Derrick",
    "wof:placetype":"neighbourhood",
    "wof:population":7,
    "zs:area_m":56275263.892382,
    "zs:blockids":[
        360339511001015
    ],
    "zs:housing10":119,
    "zs:label":"Derrick",
    "zs:pop10":7
},
  "geometry": {"coordinates":[-74.474962,44.324672],"type":"Point"}
}