{
  "type": "Feature",
  "properties": {
    "gn:admin1_code":"SC",
    "gn:admin2_code":"19.0",
    "gn:asciiname":"Point Park Estates",
    "gn:country_code":"US",
    "gn:dem":13,
    "gn:elevation":"5.0",
    "gn:feature_class":"P",
    "gn:feature_code":"PPL",
    "gn:name":"Point Park Estates",
    "gn:population":0,
    "gn:timezone":"America/New_York",
    "iso:country":"US",
    "wof:name":"Point Park Estates",
    "wof:placetype":"locality"
},
  "geometry": {"coordinates":[-80.10648,32.73684],"type":"Point"}
}