{
  "type": "Feature",
  "properties": {
    "gn:admin1_code":"VA",
    "gn:admin2_code":"71",
    "gn:asciiname":"Poplar Hill",
    "gn:country_code":"US",
    "gn:dem":549,
    "gn:elevation":"550.0",
    "gn:feature_class":"P",
    "gn:feature_code":"PPL",
    "gn:name":"Poplar Hill",
    "gn:population":0,
    "gn:timezone":"America/New_York",
    "iso:country":"US",
    "name:ceb_x_preferred":[
        "Poplar Hill"
    ],
    "name:deu_x_preferred":[
        "Poplar Hill"
    ],
    "name:swe_x_preferred":[
        "Poplar Hill"
    ],
    "wof:name":"Poplar Hill",
    "wof:placetype":"locality"
},
  "geometry": {"coordinates":[-80.73895999999998,37.21762],"type":"Point"}
}