{
  "type": "Feature",
  "properties": {
    "gn:admin1_code":"NY",
    "gn:admin2_code":"21.0",
    "gn:admin3_code":"16045.0",
    "gn:asciiname":"Jutkosky Court",
    "gn:country_code":"US",
    "gn:dem":56,
    "gn:elevation":"53.0",
    "gn:feature_class":"P",
    "gn:feature_code":"PPL",
    "gn:name":"Jutkosky Court",
    "gn:population":0,
    "gn:timezone":"America/New_York",
    "iso:country":"US",
    "wof:name":"Jutkosky Court",
    "wof:placetype":"locality"
},
  "geometry": {"coordinates":[-73.74778000000001,42.21472],"type":"Point"}
}