{
  "type": "Feature",
  "properties": {
    "gn:admin1_code":"DE",
    "gn:admin2_code":"5.0",
    "gn:asciiname":"Edgewater",
    "gn:country_code":"US",
    "gn:dem":9,
    "gn:elevation":"7.0",
    "gn:feature_class":"P",
    "gn:feature_code":"PPL",
    "gn:name":"Edgewater",
    "gn:population":0,
    "gn:timezone":"America/New_York",
    "iso:country":"US",
    "name:cat_x_preferred":[
        "Edgewater"
    ],
    "name:ceb_x_preferred":[
        "Edgewater"
    ],
    "name:ces_x_preferred":[
        "Edgewater"
    ],
    "name:deu_x_preferred":[
        "Edgewater"
    ],
    "name:fra_x_preferred":[
        "Edgewater"
    ],
    "name:ita_x_preferred":[
        "Edgewater"
    ],
    "name:nld_x_preferred":[
        "Edgewater"
    ],
    "name:pol_x_preferred":[
        "Edgewater"
    ],
    "name:por_x_preferred":[
        "Edgewater"
    ],
    "name:spa_x_preferred":[
        "Edgewater"
    ],
    "name:srp_x_preferred":[
        "\u0415\u045f\u0432\u043e\u0442\u0435\u0440"
    ],
    "name:swe_x_preferred":[
        "Edgewater"
    ],
    "name:ukr_x_preferred":[
        "\u0415\u0434\u0436\u0432\u043e\u0442\u0435\u0440"
    ],
    "name:vol_x_preferred":[
        "Edgewater"
    ],
    "wof:name":"Edgewater",
    "wof:placetype":"locality"
},
  "geometry": {"coordinates":[-75.20491,38.75317],"type":"Point"}
}