{
  "type": "Feature",
  "properties": {
    "gn:admin1_code":"TX",
    "gn:admin2_code":"147.0",
    "gn:asciiname":"Sowells Bluff",
    "gn:country_code":"US",
    "gn:dem":167,
    "gn:elevation":"160.0",
    "gn:feature_class":"P",
    "gn:feature_code":"PPL",
    "gn:name":"Sowells Bluff",
    "gn:population":0,
    "gn:timezone":"America/Chicago",
    "iso:country":"US",
    "wof:name":"Sowells Bluff",
    "wof:placetype":"locality"
},
  "geometry": {"coordinates":[-96.19498,33.75066],"type":"Point"}
}