{
  "type": "Feature",
  "properties": {
    "gn:admin1_code":"MN",
    "gn:admin2_code":"145.0",
    "gn:admin3_code":"622.0",
    "gn:asciiname":"Shamrock Mobile Home Park",
    "gn:country_code":"US",
    "gn:dem":363,
    "gn:elevation":"363.0",
    "gn:feature_class":"P",
    "gn:feature_code":"PPL",
    "gn:name":"Shamrock Mobile Home Park",
    "gn:population":0,
    "gn:timezone":"America/Chicago",
    "iso:country":"US",
    "wof:name":"Shamrock Mobile Home Park",
    "wof:placetype":"campus"
},
  "geometry": {"coordinates":[-94.57693999999999,45.62833],"type":"Point"}
}