{
  "type": "Feature",
  "properties": {
    "gn:admin1_code":"OK",
    "gn:admin2_code":"9",
    "gn:asciiname":"Mayfield",
    "gn:country_code":"US",
    "gn:dem":620,
    "gn:elevation":"611.0",
    "gn:feature_class":"P",
    "gn:feature_code":"PPL",
    "gn:name":"Mayfield",
    "gn:population":0,
    "gn:timezone":"America/Chicago",
    "iso:country":"US",
    "wof:name":"Mayfield",
    "wof:placetype":"locality"
},
  "geometry": {"coordinates":[-99.87676999999999,35.33894],"type":"Point"}
}