{
  "type": "Feature",
  "properties": {
    "gn:admin1_code":"TX",
    "gn:admin2_code":"215.0",
    "gn:asciiname":"Rush Colonia",
    "gn:country_code":"US",
    "gn:dem":43,
    "gn:elevation":"40.0",
    "gn:feature_class":"P",
    "gn:feature_code":"PPL",
    "gn:name":"Rush Colonia",
    "gn:population":0,
    "gn:timezone":"America/Chicago",
    "iso:country":"US",
    "name:eng_x_preferred":[
        "Rush Colonia"
    ],
    "name:und_x_variant":[
        "Rush Subdivision Colonia"
    ],
    "wof:name":"Rush Colonia",
    "wof:placetype":"locality"
},
  "geometry": {"coordinates":[-98.27418,26.24646],"type":"Point"}
}