{
  "type": "Feature",
  "properties": {
    "gn:admin1_code":"AL",
    "gn:admin2_code":"55",
    "gn:asciiname":"Kyuka",
    "gn:country_code":"US",
    "gn:dem":213,
    "gn:elevation":"213.0",
    "gn:feature_class":"P",
    "gn:feature_code":"PPL",
    "gn:name":"Kyuka",
    "gn:population":0,
    "gn:timezone":"America/Chicago",
    "iso:country":"US",
    "wof:name":"Kyuka",
    "wof:placetype":"locality"
},
  "geometry": {"coordinates":[-86.02108,34.16815],"type":"Point"}
}