{
  "type": "Feature",
  "properties": {
    "gn:admin1_code":"WV",
    "gn:admin2_code":"39.0",
    "gn:asciiname":"Pond Fork",
    "gn:country_code":"US",
    "gn:dem":279,
    "gn:elevation":"270.0",
    "gn:feature_class":"P",
    "gn:feature_code":"PPL",
    "gn:name":"Pond Fork",
    "gn:population":0,
    "gn:timezone":"America/New_York",
    "iso:country":"US",
    "wof:name":"Pond Fork",
    "wof:placetype":"locality"
},
  "geometry": {"coordinates":[-81.31067,38.32594],"type":"Point"}
}