{
  "type": "Feature",
  "properties": {
    "iso:country":"US",
    "name:ara_x_preferred":[
        "\u062f\u0631\u064a\u0633\u062f\u0646"
    ],
    "name:arz_x_preferred":[
        "\u062f\u0631\u064a\u0633\u062f\u0646"
    ],
    "name:cat_x_preferred":[
        "Dresden"
    ],
    "name:che_x_preferred":[
        "\u0414\u0440\u0435\u0437\u0434\u0435\u043d"
    ],
    "name:cym_x_preferred":[
        "Dresden"
    ],
    "name:deu_x_preferred":[
        "Dresden"
    ],
    "name:eng_x_preferred":[
        "Dresden"
    ],
    "name:eus_x_preferred":[
        "Dresden"
    ],
    "name:fra_x_preferred":[
        "Dresden"
    ],
    "name:hat_x_preferred":[
        "Dresden"
    ],
    "name:hun_x_preferred":[
        "Dresden"
    ],
    "name:ita_x_preferred":[
        "Dresden"
    ],
    "name:jpn_x_preferred":[
        "\u30c9\u30ec\u30b9\u30c7\u30f3"
    ],
    "name:kaz_x_preferred":[
        "\u0414\u0440\u0435\u0437\u0434\u044d\u043d"
    ],
    "name:kir_x_preferred":[
        "\u0414\u0440\u0435\u0437\u0434\u044d\u043d"
    ],
    "name:pol_x_preferred":[
        "Dresden"
    ],
    "name:spa_x_preferred":[
        "Dresden"
    ],
    "name:tat_x_preferred":[
        "\u0414\u0440\u0435\u0437\u0434\u0435\u043d"
    ],
    "name:tur_x_preferred":[
        "Dresden"
    ],
    "name:ukr_x_preferred":[
        "\u0414\u0440\u0435\u0437\u0434\u0435\u043d"
    ],
    "name:urd_x_preferred":[
        "\u0688\u0631\u06cc\u0633\u0688\u0646"
    ],
    "name:vol_x_preferred":[
        "Dresden"
    ],
    "qs_pg:aaroncc":"US",
    "qs_pg:name":"Dresden",
    "qs_pg:name_adm0":"United States",
    "qs_pg:name_adm1":"Maine",
    "qs_pg:photos":24,
    "qs_pg:photos_1k":5,
    "qs_pg:photos_9k":1,
    "qs_pg:photos_9r":2,
    "qs_pg:photos_all":61,
    "qs_pg:photos_sr":1,
    "qs_pg:pop_sr":0,
    "qs_pg:qs_pg_placetype":"locality",
    "qs_pg:qs_pg_placetype_gp":"Town",
    "qs_pg:woe_adm0":23424977,
    "woe:adm0_id":23424977,
    "woe:name_adm0":"United States",
    "woe:name_adm1":"Maine",
    "woe:placetype":"Town",
    "wof:coterminous":[
        404475649
    ],
    "wof:name":"Dresden",
    "wof:placetype":"locality",
    "wof:statistical_gore":1
},
  "geometry": {"coordinates":[-69.73924599999999,44.09],"type":"Point"}
}