{
  "type": "Feature",
  "properties": {
    "gn:admin1_code":"TX",
    "gn:admin2_code":"507.0",
    "gn:asciiname":"Camposanto-Elcometa Colonia",
    "gn:country_code":"US",
    "gn:dem":173,
    "gn:elevation":"174.0",
    "gn:feature_class":"P",
    "gn:feature_code":"PPL",
    "gn:name":"Camposanto-Elcometa Colonia",
    "gn:population":0,
    "gn:timezone":"America/Chicago",
    "iso:country":"US",
    "wof:name":"Camposanto-Elcometa Colonia",
    "wof:placetype":"locality"
},
  "geometry": {"coordinates":[-99.83644,28.69831],"type":"Point"}
}