{
  "type": "Feature",
  "properties": {
    "gn:admin1_code":"GA",
    "gn:admin2_code":"223.0",
    "gn:asciiname":"Forest Echo",
    "gn:country_code":"US",
    "gn:dem":349,
    "gn:elevation":"338.0",
    "gn:feature_class":"P",
    "gn:feature_code":"PPL",
    "gn:name":"Forest Echo",
    "gn:population":0,
    "gn:timezone":"America/New_York",
    "iso:country":"US",
    "wof:name":"Forest Echo",
    "wof:placetype":"locality"
},
  "geometry": {"coordinates":[-84.81549,33.89177],"type":"Point"}
}