{
  "type": "Feature",
  "properties": {
    "gn:admin1_code":"GA",
    "gn:admin2_code":"225.0",
    "gn:asciiname":"Biss",
    "gn:country_code":"US",
    "gn:dem":131,
    "gn:elevation":"127.0",
    "gn:feature_class":"P",
    "gn:feature_code":"PPL",
    "gn:name":"Biss",
    "gn:population":0,
    "gn:timezone":"America/New_York",
    "iso:country":"US",
    "wof:name":"Biss",
    "wof:placetype":"locality"
},
  "geometry": {"coordinates":[-83.84574000000001,32.58654],"type":"Point"}
}