{
  "type": "Feature",
  "properties": {
    "gn:admin1_code":"TX",
    "gn:admin2_code":"471",
    "gn:asciiname":"Wesley Grove",
    "gn:country_code":"US",
    "gn:dem":110,
    "gn:elevation":"107.0",
    "gn:feature_class":"P",
    "gn:feature_code":"PPL",
    "gn:name":"Wesley Grove",
    "gn:population":0,
    "gn:timezone":"America/Chicago",
    "iso:country":"US",
    "wof:name":"Wesley Grove",
    "wof:placetype":"locality"
},
  "geometry": {"coordinates":[-95.78912,30.68575],"type":"Point"}
}