{
  "type": "Feature",
  "properties": {
    "iso:country":"US",
    "name:eng_x_preferred":[
        "Sage Oaks"
    ],
    "qs:gn_adm0_cc":"US",
    "qs:gn_local":4152452,
    "qs:gn_nam_loc":"Crystal Beach, Pinellas, Florida, US",
    "qs:gn_namadm1":"FL",
    "qs:local_max":102,
    "qs:local_sum":168,
    "qs:localhoods":2,
    "qs:name":"Sage Oaks",
    "qs:name_adm0":"United States",
    "qs:name_adm1":"Florida",
    "qs:name_adm2":"Pinellas",
    "qs:name_local":"Crystal Beach",
    "qs:photo_max":32,
    "qs:photo_sum":102,
    "qs:placetype":"Suburb",
    "qs:quad_count":10,
    "qs:woe_adm0":23424977,
    "qs:woe_adm1":2347568,
    "qs:woe_adm2":12587854,
    "qs:woe_lau":0,
    "qs:woe_local":2387966,
    "qs:woe_ver":"7.10.0",
    "wof:name":"Sage Oaks",
    "wof:placetype":"neighbourhood",
    "wof:population":3878,
    "zs:blockids":[
        121030272025007,
        121030272021033,
        121030272025001,
        121030272052013,
        121030272063023,
        121030272052002,
        121030272021021,
        121030272061007,
        121030272025008,
        121030272025010,
        121030272025019,
        121030272021030,
        121030272061008,
        121030272025030,
        121030272061002,
        121030272052016,
        121030272061043,
        121030272021017,
        121030272021025,
        121030272021027,
        121030272021016,
        121030272023031,
        121030272023028,
        121030272021026,
        121030272025000,
        121030272061041,
        121030272021028,
        121030272052006,
        121030272025002,
        121030272052001,
        121030272052019,
        121030272021029,
        121030272052000,
        121030272025020,
        121030272021014,
        121030272052010,
        121030272025013,
        121030272025003,
        121030272061042,
        121030272061001,
        121030272025017,
        121030272023030,
        121030272021020,
        121030272025009,
        121030272052003,
        121030272021031,
        121030272052007,
        121030272063013,
        121030272052014,
        121030272021034,
        121030272023032,
        121030272025021,
        121030272021018,
        121030272021032,
        121030272025006,
        121030272021044,
        121030272052017,
        121030272025023,
        121030272061006,
        121030272061004,
        121030272052008,
        121030272052005,
        121030272021009,
        121030272021015,
        121030272052004,
        121030272052012,
        121030272061039,
        121030272061046,
        121030272061005,
        121030272052009,
        121030272025004,
        121030272052018,
        121030272061003,
        121030272021019,
        121030272021013,
        121030272025011,
        121030272021012,
        121030272023029,
        121030272052011,
        121030272063024,
        121030272052015,
        121030272025005,
        121030272061040,
        121030272025012
    ],
    "zs:housing10":1833,
    "zs:pop10":3878
},
  "geometry": {"coordinates":[-82.77490899999999,28.098464],"type":"Point"}
}