{
  "type": "Feature",
  "properties": {
    "iso:country":"US",
    "name:ces_x_preferred":[
        "MacIntyre"
    ],
    "name:deu_x_preferred":[
        "MacIntyre"
    ],
    "name:eng_x_preferred":[
        "Macintyre"
    ],
    "name:fra_x_preferred":[
        "MacIntyre"
    ],
    "wd:wordcount":111,
    "wof:name":"Macintyre",
    "wof:placetype":"neighbourhood",
    "wof:population":3,
    "zs:area_m":176007.861708,
    "zs:blockids":[
        500039706001059
    ],
    "zs:housing10":9,
    "zs:label":"Macintyre",
    "zs:pop10":3
},
  "geometry": {"coordinates":[-73.106009,43.038818],"type":"Point"}
}