{
  "type": "Feature",
  "properties": {
    "iso:country":"US",
    "name:ben_x_preferred":[
        "\u09ae\u09cd\u09af\u09be\u0995\u09bf\u09a8\u09cd\u09a4\u09bf\u09b0"
    ],
    "name:ces_x_preferred":[
        "MacIntyre"
    ],
    "name:deu_x_preferred":[
        "MacIntyre"
    ],
    "name:ell_x_preferred":[
        "\u039c\u03ac\u03ba\u03b9\u03bd\u03c4\u03b1\u03ca\u03c1"
    ],
    "name:eng_x_preferred":[
        "Macintyre"
    ],
    "name:fas_x_preferred":[
        "\u0645\u0627\u06a9\u06cc\u0646\u062a\u0627\u06cc\u0631"
    ],
    "name:fra_x_preferred":[
        "MacIntyre"
    ],
    "name:heb_x_preferred":[
        "\u05de\u05e4\u05e8\u05e5 \u05de\u05e7\u05e0\u05d6\u05d9"
    ],
    "name:hin_x_preferred":[
        "\u092e\u0948\u0915\u093f\u0928\u091f\u093e\u092f\u0930"
    ],
    "name:hun_x_preferred":[
        "Macintyre"
    ],
    "name:ind_x_preferred":[
        "Macintyre"
    ],
    "name:ita_x_preferred":[
        "Macintyre"
    ],
    "name:jpn_x_preferred":[
        "\u30de\u30c3\u30ad\u30f3\u30bf\u30a4\u30a2\u5ddd"
    ],
    "name:kor_x_preferred":[
        "\ub9e4\ud0a8\ud0c0\uc774\uc5b4"
    ],
    "name:pol_x_preferred":[
        "Macintyre"
    ],
    "name:por_x_preferred":[
        "Macintyre"
    ],
    "name:rus_x_preferred":[
        "\u0440\u0435\u043a\u0430 \u041c\u0430\u043a\u0438\u043d\u0442\u0430\u0439\u0440"
    ],
    "name:spa_x_preferred":[
        "Macintyre"
    ],
    "name:tur_x_preferred":[
        "Macintyre"
    ],
    "name:ukr_x_preferred":[
        "\u041c\u0430\u043a\u0456\u043d\u0442\u0430\u0439\u0440"
    ],
    "name:urd_x_preferred":[
        "\u0645\u06cc\u06a9\u0646\u0679\u0627\u0626\u0631"
    ],
    "name:vie_x_preferred":[
        "S\u00f4ng Macintyre"
    ],
    "name:zho_cn_x_preferred":[
        "\u9ea6\u91d1\u592a\u5c14\u6cb3"
    ],
    "name:zho_tw_x_preferred":[
        "\u9ea5\u91d1\u592a\u723e\u6cb3"
    ],
    "wd:wordcount":111,
    "wof:name":"Macintyre",
    "wof:placetype":"neighbourhood",
    "wof:population":3,
    "zs:area_m":176007.861708,
    "zs:blockids":[
        500039706001059
    ],
    "zs:housing10":9,
    "zs:label":"Macintyre",
    "zs:pop10":3
},
  "geometry": {"coordinates":[-73.106009,43.038818],"type":"Point"}
}