{
  "type": "Feature",
  "properties": {
    "gn:admin1_code":"OK",
    "gn:admin2_code":"97.0",
    "gn:asciiname":"Patton",
    "gn:country_code":"US",
    "gn:dem":201,
    "gn:elevation":"201.0",
    "gn:feature_class":"P",
    "gn:feature_code":"PPL",
    "gn:name":"Patton",
    "gn:population":0,
    "gn:timezone":"America/Chicago",
    "iso:country":"US",
    "wof:name":"Patton",
    "wof:placetype":"locality"
},
  "geometry": {"coordinates":[-95.25579999999999,36.47676],"type":"Point"}
}