{
  "type": "Feature",
  "properties": {
    "gn:admin1_code":"AL",
    "gn:admin2_code":"73",
    "gn:asciiname":"Merrywood",
    "gn:country_code":"US",
    "gn:dem":208,
    "gn:elevation":"199.0",
    "gn:feature_class":"P",
    "gn:feature_code":"PPL",
    "gn:name":"Merrywood",
    "gn:population":0,
    "gn:timezone":"America/Chicago",
    "iso:country":"US",
    "wof:name":"Merrywood",
    "wof:placetype":"locality"
},
  "geometry": {"coordinates":[-86.90971999999999,33.58649],"type":"Point"}
}