{
  "type": "Feature",
  "properties": {
    "gn:admin1_code":"MN",
    "gn:admin2_code":"31.0",
    "gn:admin3_code":"17531.0",
    "gn:asciiname":"Hovland",
    "gn:country_code":"US",
    "gn:dem":188,
    "gn:elevation":"186.0",
    "gn:feature_class":"P",
    "gn:feature_code":"PPL",
    "gn:name":"Hovland",
    "gn:population":0,
    "gn:timezone":"America/Chicago",
    "iso:country":"US",
    "name:eng_x_preferred":[
        "Hovland"
    ],
    "name:und_x_variant":[
        "Chicago Bay"
    ],
    "wof:name":"Hovland",
    "wof:placetype":"locality"
},
  "geometry": {"coordinates":[-89.97204000000001,47.83878],"type":"Point"}
}