{
  "type": "Feature",
  "properties": {
    "gn:admin1_code":"MA",
    "gn:admin2_code":"21",
    "gn:admin3_code":"7740.0",
    "gn:asciiname":"Braintree",
    "gn:country_code":"US",
    "gn:dem":32,
    "gn:elevation":"30.0",
    "gn:feature_class":"P",
    "gn:feature_code":"PPL",
    "gn:name":"Braintree",
    "gn:population":0,
    "gn:timezone":"America/New_York",
    "iso:country":"US",
    "name:ara_x_preferred":[
        "\u0628\u0631\u064a\u0646\u062a\u0631\u064a"
    ],
    "name:azb_x_preferred":[
        "\u0628\u0631\u06cc\u0646\u062a\u0631\u06cc"
    ],
    "name:cat_x_preferred":[
        "Braintree"
    ],
    "name:deu_x_preferred":[
        "Braintree"
    ],
    "name:epo_x_preferred":[
        "Braintree"
    ],
    "name:eus_x_preferred":[
        "Braintree"
    ],
    "name:fas_x_preferred":[
        "\u0628\u0631\u06cc\u0646\u062a\u0631\u06cc\u060c \u0645\u0627\u0633\u0627\u0686\u0648\u0633\u062a"
    ],
    "name:fas_x_variant":[
        "\u0628\u0631\u06cc\u0646\u062a\u0631\u06cc"
    ],
    "name:fin_x_preferred":[
        "Braintree"
    ],
    "name:fra_x_preferred":[
        "Braintree"
    ],
    "name:glv_x_preferred":[
        "Braintree"
    ],
    "name:hat_x_preferred":[
        "Braintree"
    ],
    "name:ind_x_preferred":[
        "Braintree"
    ],
    "name:ita_x_preferred":[
        "Braintree"
    ],
    "name:jpn_x_preferred":[
        "\u30d6\u30ec\u30a4\u30f3\u30c4\u30ea\u30fc"
    ],
    "name:kaz_x_preferred":[
        "\u0411\u0440\u044d\u0439\u043d\u0442\u0440\u0438"
    ],
    "name:kir_x_preferred":[
        "\u0411\u0440\u044d\u0439\u043d\u0442\u0440\u0438"
    ],
    "name:mlg_x_preferred":[
        "Braintree"
    ],
    "name:nld_x_preferred":[
        "Braintree"
    ],
    "name:nor_x_preferred":[
        "Braintree"
    ],
    "name:oci_x_preferred":[
        "Braintree"
    ],
    "name:pol_x_preferred":[
        "Braintree"
    ],
    "name:por_x_preferred":[
        "Braintree"
    ],
    "name:spa_x_preferred":[
        "Braintree"
    ],
    "name:srp_x_preferred":[
        "\u0411\u0440\u0435\u0458\u043d\u0442\u0440\u0438"
    ],
    "name:swa_x_preferred":[
        "Braintree"
    ],
    "name:swe_x_preferred":[
        "Braintree"
    ],
    "name:tur_x_preferred":[
        "Braintree"
    ],
    "name:und_x_variant":[
        "Braintree CDP"
    ],
    "name:urd_x_preferred":[
        "\u0628\u0631\u06cc\u0646\u0679\u0631\u06cc\u060c \u0645\u06cc\u0633\u0627\u0686\u0648\u0633\u0679\u0633"
    ],
    "name:urd_x_variant":[
        "\u0628\u0631\u06cc\u0646\u0679\u0631\u06cc"
    ],
    "name:vie_x_preferred":[
        "Braintree"
    ],
    "name:vol_x_preferred":[
        "Braintree"
    ],
    "name:war_x_preferred":[
        "Braintree"
    ],
    "name:zho_x_preferred":[
        "\u5e03\u4f26\u7279\u91cc"
    ],
    "wof:name":"Braintree",
    "wof:placetype":"locality"
},
  "geometry": {"coordinates":[-71.00215,42.20384],"type":"Point"}
}