{
  "type": "Feature",
  "properties": {
    "gn:admin1_code":"MO",
    "gn:admin2_code":"123.0",
    "gn:admin3_code":"5410.0",
    "gn:asciiname":"Allbright",
    "gn:country_code":"US",
    "gn:dem":148,
    "gn:elevation":"148.0",
    "gn:feature_class":"P",
    "gn:feature_code":"PPL",
    "gn:name":"Allbright",
    "gn:population":0,
    "gn:timezone":"America/Chicago",
    "iso:country":"US",
    "name:eng_x_preferred":[
        "Allbright"
    ],
    "name:und_x_variant":[
        "Albright"
    ],
    "wof:name":"Allbright",
    "wof:placetype":"locality"
},
  "geometry": {"coordinates":[-90.22678000000001,37.32894],"type":"Point"}
}