{
  "type": "Feature",
  "properties": {
    "iso:country":"US",
    "name:ara_x_preferred":[
        "\u0635\u062e\u0648\u0631 \u0627\u0644\u063a\u0637\u0627\u0621"
    ],
    "name:deu_x_preferred":[
        "Deckgestein"
    ],
    "name:eng_x_preferred":[
        "Caprock"
    ],
    "name:eng_x_variant":[
        "caprock"
    ],
    "name:fas_x_preferred":[
        "\u067e\u0648\u0634\u200c\u0633\u0646\u06af"
    ],
    "name:fra_x_preferred":[
        "caprock"
    ],
    "name:fra_x_variant":[
        "roche couverture"
    ],
    "name:jpn_x_preferred":[
        "\u30ad\u30e3\u30c3\u30d7\u30ed\u30c3\u30af"
    ],
    "name:nld_x_preferred":[
        "caprock"
    ],
    "name:nno_x_preferred":[
        "Forseglingsbergart"
    ],
    "name:nob_x_preferred":[
        "Takbergart"
    ],
    "name:nor_x_preferred":[
        "Takbergart"
    ],
    "name:por_x_preferred":[
        "Rocha de cobertura"
    ],
    "name:srp_x_preferred":[
        "\u043a\u0435\u043f\u0440\u043e\u043a"
    ],
    "name:ukr_x_preferred":[
        "\u041a\u0435\u043f\u0440\u043e\u043a"
    ],
    "name:vie_x_preferred":[
        "\u0110\u00e1 ch\u1eafn"
    ],
    "wd:wordcount":370,
    "wof:name":"Caprock",
    "wof:placetype":"neighbourhood",
    "wof:population":3532,
    "zs:area_m":2056833.597009,
    "zs:blockids":[
        483030019032004,
        483030021014002,
        483030021012008,
        483030021012011,
        483030021014017,
        483030021014022,
        483030019031009,
        483030019032003,
        483030021011003,
        483030020012025,
        483030021014008,
        483030021014026,
        483030021011010,
        483030021014004,
        483030021014007,
        483030021014024,
        483030021014027,
        483030021014015,
        483030021014042,
        483030021011005,
        483030020012023,
        483030021012006,
        483030021012009,
        483030021011001,
        483030021011011,
        483030019032008,
        483030021012000,
        483030021014016,
        483030021011004,
        483030021014043,
        483030021014037,
        483030021011008,
        483030019032000,
        483030020022030,
        483030021012002,
        483030021014003,
        483030021014010,
        483030021014019,
        483030021012005,
        483030021012010,
        483030020012026,
        483030021012007,
        483030021011002,
        483030021014025,
        483030021011009,
        483030021012003,
        483030021014009,
        483030021011000,
        483030021014018,
        483030021014028,
        483030021013003,
        483030021014029,
        483030021011007
    ],
    "zs:housing10":1615,
    "zs:label":"Caprock",
    "zs:pop10":3532
},
  "geometry": {"coordinates":[-101.88111499999999,33.541374],"type":"Point"}
}