{
  "type": "Feature",
  "properties": {
    "gn:admin1_code":"OH",
    "gn:admin2_code":"67.0",
    "gn:admin3_code":"72361.0",
    "gn:asciiname":"Belleve",
    "gn:country_code":"US",
    "gn:dem":283,
    "gn:elevation":"277.0",
    "gn:feature_class":"P",
    "gn:feature_code":"PPL",
    "gn:name":"Belleve",
    "gn:population":0,
    "gn:timezone":"America/New_York",
    "iso:country":"US",
    "wof:name":"Belleve",
    "wof:placetype":"locality"
},
  "geometry": {"coordinates":[-80.89509,40.24229],"type":"Point"}
}