{
  "type": "Feature",
  "properties": {
    "gn:gn_country":"US",
    "gn:gn_fcode":"PPL",
    "gn:gn_pop":0,
    "iso:country":"US",
    "name:ceb_x_preferred":[
        "Edgefield"
    ],
    "name:deu_x_preferred":[
        "Edgefield"
    ],
    "name:fra_x_preferred":[
        "Edgefield"
    ],
    "name:hun_x_preferred":[
        "Edgefield"
    ],
    "name:ita_x_preferred":[
        "Edgefield"
    ],
    "name:nld_x_preferred":[
        "Edgefield"
    ],
    "name:pol_x_preferred":[
        "Edgefield"
    ],
    "name:por_x_preferred":[
        "Edgefield"
    ],
    "name:srp_x_preferred":[
        "\u0415\u045f\u0444\u0438\u043b\u0434"
    ],
    "name:swe_x_preferred":[
        "Edgefield"
    ],
    "name:vol_x_preferred":[
        "Edgefield"
    ],
    "qs_pg:aaroncc":"US",
    "qs_pg:gn_country":"US",
    "qs_pg:gn_fcode":"PPL",
    "qs_pg:gn_pop":0,
    "qs_pg:name":"Edgefield",
    "qs_pg:name_adm0":"United States",
    "qs_pg:name_adm1":"Virginia",
    "qs_pg:photos":26,
    "qs_pg:photos_1k":5,
    "qs_pg:photos_9k":1,
    "qs_pg:photos_9r":2,
    "qs_pg:photos_all":26,
    "qs_pg:photos_sr":2,
    "qs_pg:pop_sr":0,
    "qs_pg:qs_pg_placetype":"neighbourhood",
    "qs_pg:qs_pg_placetype_gp":"Suburb",
    "qs_pg:woe_adm0":23424977,
    "wof:name":"Edgefield",
    "wof:placetype":"neighbourhood"
},
  "geometry": {"coordinates":[-76.38704048754833,36.88660033764939],"type":"Point"}
}