{
  "type": "Feature",
  "properties": {
    "gn:country":"US",
    "gn:fcode":"PPLX",
    "gn:population":0,
    "iso:country":"US",
    "name:cat_x_preferred":[
        "Rolling Hills"
    ],
    "name:ceb_x_preferred":[
        "Rolling Hills"
    ],
    "name:deu_x_preferred":[
        "Rolling Hills"
    ],
    "name:fra_x_preferred":[
        "Rolling Hills"
    ],
    "name:ita_x_preferred":[
        "Rolling Hills"
    ],
    "name:nld_x_preferred":[
        "Rolling Hills"
    ],
    "name:pol_x_preferred":[
        "Rolling Hills"
    ],
    "name:por_x_preferred":[
        "Rolling Hills"
    ],
    "name:rus_x_preferred":[
        "\u0420\u043e\u043b\u043b\u0438\u043d\u0433-\u0425\u0438\u043b\u0441"
    ],
    "name:srp_x_preferred":[
        "\u0420\u043e\u043b\u0438\u043d\u0433 \u0425\u0438\u043b\u0441"
    ],
    "name:swe_x_preferred":[
        "Rolling Hills"
    ],
    "name:vol_x_preferred":[
        "Rolling Hills"
    ],
    "qs_pg:aaroncc":"US",
    "qs_pg:gn_country":"US",
    "qs_pg:gn_fcode":"PPLX",
    "qs_pg:gn_pop":0,
    "qs_pg:name":"Rolling Hills",
    "qs_pg:name_adm0":"United States",
    "qs_pg:name_adm1":"Alabama",
    "qs_pg:photos":1,
    "qs_pg:photos_1k":1,
    "qs_pg:photos_9k":1,
    "qs_pg:photos_9r":1,
    "qs_pg:photos_all":1,
    "qs_pg:photos_sr":1,
    "qs_pg:pop_sr":0,
    "qs_pg:qs_pg_placetype":"neighbourhood",
    "qs_pg:qs_pg_placetype_gp":"Suburb",
    "qs_pg:woe_adm0":23424977,
    "woe:adm0_id":23424977,
    "woe:name_adm0":"United States",
    "woe:name_adm1":"Alabama",
    "woe:placetype":"Suburb",
    "wof:name":"Rolling Hills",
    "wof:placetype":"neighbourhood"
},
  "geometry": {"coordinates":[-86.18274,32.24709],"type":"Point"}
}