{
  "type": "Feature",
  "properties": {
    "gn:admin1_code":"MS",
    "gn:admin2_code":"59.0",
    "gn:asciiname":"Longhorn Mobile Park",
    "gn:country_code":"US",
    "gn:dem":7,
    "gn:elevation":"5.0",
    "gn:feature_class":"P",
    "gn:feature_code":"PPL",
    "gn:name":"Longhorn Mobile Park",
    "gn:population":0,
    "gn:timezone":"America/Chicago",
    "iso:country":"US",
    "wof:name":"Longhorn Mobile Park",
    "wof:placetype":"locality"
},
  "geometry": {"coordinates":[-88.62496999999998,30.38806],"type":"Point"}
}