{
  "type": "Feature",
  "properties": {
    "gn:admin1_code":"IL",
    "gn:admin2_code":"167",
    "gn:admin3_code":"11046.0",
    "gn:asciiname":"East Springfield",
    "gn:country_code":"US",
    "gn:dem":181,
    "gn:elevation":"183.0",
    "gn:feature_class":"P",
    "gn:feature_code":"PPL",
    "gn:name":"East Springfield",
    "gn:population":0,
    "gn:timezone":"America/Chicago",
    "iso:country":"US",
    "name:deu_x_preferred":[
        "East Springfield"
    ],
    "wof:name":"East Springfield",
    "wof:placetype":"locality"
},
  "geometry": {"coordinates":[-89.62732,39.79811],"type":"Point"}
}