{
  "type": "Feature",
  "properties": {
    "iso:country":"US",
    "name:eng_x_preferred":[
        "Knolls"
    ],
    "wof:name":"Knolls",
    "wof:placetype":"neighbourhood",
    "wof:population":1661,
    "zs:area_m":1766586.022812,
    "zs:blockids":[
        340030614003017,
        340030611004009,
        340030612001030,
        340030611004005,
        340030612002016,
        340030614003014,
        340030614003012,
        340030614003015,
        340030614003011,
        340030611003016,
        340030614003010,
        340030612002017,
        340030611003015,
        340030611003017,
        340030611003014,
        340030612001028,
        340030614003009,
        340030614003019,
        340030613002019,
        340030611004008,
        340030612002012,
        340030614003013,
        340030611004004,
        340030614003008,
        340030614003007,
        340030614003016,
        340030612001027,
        340030612001032,
        340030612001029
    ],
    "zs:housing10":581,
    "zs:label":"Knolls",
    "zs:pop10":1661
},
  "geometry": {"coordinates":[-74.170506,40.994296],"type":"Point"}
}