{
  "type": "Feature",
  "properties": {
    "gn:admin1_code":"TX",
    "gn:admin2_code":"215.0",
    "gn:asciiname":"Sharyland",
    "gn:country_code":"US",
    "gn:dem":45,
    "gn:elevation":"40.0",
    "gn:feature_class":"P",
    "gn:feature_code":"PPL",
    "gn:name":"Sharyland",
    "gn:population":0,
    "gn:timezone":"America/Chicago",
    "iso:country":"US",
    "name:eng_x_preferred":[
        "Sharyland"
    ],
    "name:und_x_variant":[
        "Shayland"
    ],
    "wof:name":"Sharyland",
    "wof:placetype":"locality"
},
  "geometry": {"coordinates":[-98.28807,26.21118],"type":"Point"}
}