{
  "type": "Feature",
  "properties": {
    "gn:elevation":30,
    "iso:country":"US",
    "name:eng_x_preferred":[
        "Ballardvale"
    ],
    "name:fra_x_preferred":[
        "Ballardvale"
    ],
    "name:tur_x_preferred":[
        "Ballardvale"
    ],
    "name:und_x_variant":[
        "Ballardville"
    ],
    "qs:gn_adm0_cc":"US",
    "qs:gn_fcode":"PPL",
    "qs:gn_local":4929055,
    "qs:gn_nam_loc":"andover",
    "qs:gn_namadm1":"MA",
    "qs:gn_name":"Ballardvale",
    "qs:local_max":505,
    "qs:local_sum":1356,
    "qs:localhoods":4,
    "qs:name":"Ballardvale",
    "qs:name_adm0":"United States",
    "qs:name_adm1":"Massachusetts",
    "qs:name_adm2":"Essex",
    "qs:name_local":"Andover",
    "qs:photo_max":245,
    "qs:photo_sum":326,
    "qs:placetype":"Suburb",
    "qs:quad_count":11,
    "qs:woe_adm0":23424977,
    "qs:woe_adm1":2347580,
    "qs:woe_adm2":12588704,
    "qs:woe_lau":0,
    "qs:woe_local":2354645,
    "qs:woe_ver":"7.10.0",
    "wd:wordcount":810,
    "wof:lang":[
        "eng"
    ],
    "wof:name":"Ballardvale",
    "wof:placetype":"neighbourhood",
    "wof:population":2,
    "zs:blockids":[
        250173311012006,
        250173154021019
    ],
    "zs:housing10":1,
    "zs:pop10":2
},
  "geometry": {"coordinates":[-71.159869,42.62754],"type":"Point"}
}