{
  "type": "Feature",
  "properties": {
    "gn:admin1_code":"TN",
    "gn:admin2_code":"81",
    "gn:asciiname":"Crossroads",
    "gn:country_code":"US",
    "gn:dem":178,
    "gn:elevation":"175.0",
    "gn:feature_class":"P",
    "gn:feature_code":"PPL",
    "gn:name":"Crossroads",
    "gn:population":0,
    "gn:timezone":"America/Chicago",
    "iso:country":"US",
    "name:ces_x_preferred":[
        "Crossroads"
    ],
    "name:deu_x_preferred":[
        "Crossroads"
    ],
    "name:eng_x_preferred":[
        "Crossroads"
    ],
    "name:fas_x_preferred":[
        "\u0686\u0647\u0627\u0631\u0631\u0627\u0647"
    ],
    "name:fin_x_preferred":[
        "Crossroads"
    ],
    "name:fra_x_preferred":[
        "Crossroads"
    ],
    "name:heb_x_preferred":[
        "\u05e6\u05d5\u05de\u05ea"
    ],
    "name:ita_x_preferred":[
        "Crossroads"
    ],
    "name:jpn_x_preferred":[
        "\u30af\u30ed\u30b9\u30ed\u30fc\u30c9"
    ],
    "name:kor_x_preferred":[
        "\ud06c\ub85c\uc2a4\ub85c\ub4dc"
    ],
    "name:nld_x_preferred":[
        "Crossroads"
    ],
    "name:nor_x_preferred":[
        "Crossroads"
    ],
    "name:pol_x_preferred":[
        "Crossroads"
    ],
    "name:por_x_preferred":[
        "Crossroads"
    ],
    "name:rus_x_preferred":[
        "\u041f\u0435\u0440\u0435\u043a\u0440\u0451\u0441\u0442\u043a\u0438"
    ],
    "name:spa_x_preferred":[
        "Crossroads"
    ],
    "name:srp_x_preferred":[
        "\u041a\u0440\u043e\u0441 \u0420\u043e\u0443\u0434\u0441"
    ],
    "name:swe_x_preferred":[
        "Crossroads"
    ],
    "name:ukr_x_preferred":[
        "Crossroads"
    ],
    "name:und_x_variant":[
        "Wadesville"
    ],
    "wof:name":"Crossroads",
    "wof:placetype":"locality"
},
  "geometry": {"coordinates":[-87.51724,35.71924],"type":"Point"}
}