{
  "type": "Feature",
  "properties": {
    "iso:country":"US",
    "name:ara_x_preferred":[
        "\u0625\u064a\u0646\u0648\u062e"
    ],
    "name:ceb_x_preferred":[
        "Enoch"
    ],
    "name:ces_x_preferred":[
        "Enoch"
    ],
    "name:deu_x_preferred":[
        "Enoch"
    ],
    "name:eng_x_preferred":[
        "Enoch"
    ],
    "name:fas_x_preferred":[
        "\u062e\u0646\u0648\u062e"
    ],
    "name:fra_x_preferred":[
        "Enoch"
    ],
    "name:fry_x_preferred":[
        "Henoch"
    ],
    "name:ita_x_preferred":[
        "Enoch"
    ],
    "name:kor_x_preferred":[
        "\uc5d0\ub179"
    ],
    "name:nor_x_preferred":[
        "Henok"
    ],
    "name:pol_x_preferred":[
        "Enoch"
    ],
    "name:rus_x_preferred":[
        "\u042d\u043d\u043e\u0445"
    ],
    "name:slk_x_preferred":[
        "Henoch"
    ],
    "name:swe_x_preferred":[
        "Enoch"
    ],
    "name:yid_x_preferred":[
        "\u05d7\u05e0\u05d5\u05da"
    ],
    "qs:gn_adm0_cc":"US",
    "qs:gn_fcode":"PPL",
    "qs:gn_local":5198062,
    "qs:gn_nam_loc":"lincoln",
    "qs:gn_namadm1":"PA",
    "qs:gn_name":"Enoch",
    "qs:local_max":254,
    "qs:local_sum":323,
    "qs:localhoods":3,
    "qs:name":"Enoch",
    "qs:name_adm0":"United States",
    "qs:name_adm1":"Pennsylvania",
    "qs:name_adm2":"Somerset",
    "qs:name_local":"Lincoln",
    "qs:photo_max":250,
    "qs:photo_sum":254,
    "qs:placetype":"Suburb",
    "qs:quad_count":4,
    "qs:woe_adm0":23424977,
    "qs:woe_adm1":2347597,
    "qs:woe_adm2":12589783,
    "qs:woe_lau":0,
    "qs:woe_local":28744602,
    "qs:woe_ver":"7.10.0",
    "wd:wordcount":310,
    "wof:lang":[
        "eng"
    ],
    "wof:name":"Enoch",
    "wof:placetype":"neighbourhood",
    "wof:population":13,
    "zs:blockids":[
        421110207002081,
        421110207002095,
        421110207002074,
        421110207002135,
        421110207002094,
        421110207002082
    ],
    "zs:housing10":6,
    "zs:pop10":13
},
  "geometry": {"coordinates":[-79.100793,40.070551],"type":"Point"}
}