{
  "type": "Feature",
  "properties": {
    "gn:admin1_code":"TX",
    "gn:admin2_code":"293",
    "gn:asciiname":"Munger",
    "gn:country_code":"US",
    "gn:dem":153,
    "gn:elevation":"151.0",
    "gn:feature_class":"P",
    "gn:feature_code":"PPL",
    "gn:name":"Munger",
    "gn:population":0,
    "gn:timezone":"America/Chicago",
    "iso:country":"US",
    "name:ara_x_preferred":[
        "\u0645\u0648\u0646\u062c\u0631"
    ],
    "name:ben_x_preferred":[
        "\u09ae\u09c1\u0999\u09cd\u0997\u09c7\u09b0"
    ],
    "name:bih_x_preferred":[
        "\u092e\u0941\u0901\u0917\u0947\u0930"
    ],
    "name:bpy_x_preferred":[
        "\u09ae\u09c1\u0999\u09cd\u0997\u09be\u09b0"
    ],
    "name:cat_x_preferred":[
        "Monghyr"
    ],
    "name:ceb_x_preferred":[
        "Munger"
    ],
    "name:deu_x_preferred":[
        "Munger"
    ],
    "name:epo_x_preferred":[
        "Monger"
    ],
    "name:fas_x_preferred":[
        "\u0645\u0648\u0646\u06af\u0631"
    ],
    "name:fra_x_preferred":[
        "Munger"
    ],
    "name:guj_x_preferred":[
        "\u0aae\u0ac1\u0a82\u0a97\u0ac7\u0ab0"
    ],
    "name:hin_x_preferred":[
        "\u092e\u0941\u0902\u0917\u0947\u0930"
    ],
    "name:ind_x_preferred":[
        "Munger"
    ],
    "name:ita_x_preferred":[
        "Munger"
    ],
    "name:jpn_x_preferred":[
        "\u30e0\u30f3\u30b2\u30fc\u30eb"
    ],
    "name:mal_x_preferred":[
        "\u0d2e\u0d41\u0d02\u0d17\u0d7c"
    ],
    "name:mar_x_preferred":[
        "\u092e\u0941\u0902\u0917\u0947\u0930"
    ],
    "name:mlg_x_preferred":[
        "Munger"
    ],
    "name:msa_x_preferred":[
        "Munger"
    ],
    "name:new_x_preferred":[
        "\u092e\u0941\u0902\u0917\u0947\u0930"
    ],
    "name:nld_x_preferred":[
        "Munger"
    ],
    "name:ori_x_preferred":[
        "\u0b2e\u0b41\u0b19\u0b4d\u0b17\u0b47\u0b30\u0b4d"
    ],
    "name:pol_x_preferred":[
        "Munger"
    ],
    "name:por_x_preferred":[
        "Munger"
    ],
    "name:rus_x_preferred":[
        "\u041c\u0443\u043d\u0433\u0435\u0440"
    ],
    "name:san_x_preferred":[
        "\u092e\u0941\u0919\u094d\u0917\u0947\u0930"
    ],
    "name:spa_x_preferred":[
        "Munger"
    ],
    "name:srp_x_preferred":[
        "\u041c\u0443\u043d\u0433\u0435\u0440"
    ],
    "name:swe_x_preferred":[
        "Munger"
    ],
    "name:tgl_x_preferred":[
        "Munger"
    ],
    "name:tur_x_preferred":[
        "Munger"
    ],
    "name:ukr_x_preferred":[
        "\u041c\u0443\u043d\u0491\u0435\u0440"
    ],
    "name:urd_x_preferred":[
        "\u0645\u0648\u0646\u06af\u06cc\u0631"
    ],
    "name:vie_x_preferred":[
        "Munger"
    ],
    "name:war_x_preferred":[
        "Munger"
    ],
    "name:zho_x_preferred":[
        "\u8499\u683c\u57c3\u5c14"
    ],
    "wof:name":"Munger",
    "wof:placetype":"locality"
},
  "geometry": {"coordinates":[-96.70638,31.796],"type":"Point"}
}