{
  "type": "Feature",
  "properties": {
    "gn:admin1_code":"NY",
    "gn:admin2_code":"119",
    "gn:admin3_code":"84077.0",
    "gn:asciiname":"Jefferson Valley-Yorktown",
    "gn:country_code":"US",
    "gn:dem":202,
    "gn:elevation":"198.0",
    "gn:feature_class":"P",
    "gn:feature_code":"PPL",
    "gn:name":"Jefferson Valley-Yorktown",
    "gn:population":14142,
    "gn:timezone":"America/New_York",
    "iso:country":"US",
    "name:und_x_variant":[
        "Jefferson Valley-Yorktown CDP",
        "Jefferson Valley-Yorktown"
    ],
    "wof:name":"Jefferson Valley-Yorktown",
    "wof:placetype":"locality",
    "wof:population":14142
},
  "geometry": {"coordinates":[-73.80065999999999,41.31797],"type":"Point"}
}