{
  "type": "Feature",
  "properties": {
    "gn:admin1_code":"GA",
    "gn:admin2_code":"141",
    "gn:asciiname":"Sandy Run",
    "gn:country_code":"US",
    "gn:dem":191,
    "gn:elevation":"184.0",
    "gn:feature_class":"P",
    "gn:feature_code":"PPL",
    "gn:name":"Sandy Run",
    "gn:population":0,
    "gn:timezone":"America/New_York",
    "iso:country":"US",
    "name:ceb_x_preferred":[
        "Sandy Run"
    ],
    "name:deu_x_preferred":[
        "Sandy Run"
    ],
    "wof:name":"Sandy Run",
    "wof:placetype":"locality"
},
  "geometry": {"coordinates":[-83.12821,33.22986],"type":"Point"}
}