{
  "type": "Feature",
  "properties": {
    "gn:admin1_code":"FL",
    "gn:admin2_code":"57",
    "gn:asciiname":"Cattlemans Cove",
    "gn:country_code":"US",
    "gn:dem":41,
    "gn:elevation":"34.0",
    "gn:feature_class":"P",
    "gn:feature_code":"PPL",
    "gn:name":"Cattlemans Cove",
    "gn:population":0,
    "gn:timezone":"America/New_York",
    "iso:country":"US",
    "wof:name":"Cattlemans Cove",
    "wof:placetype":"locality"
},
  "geometry": {"coordinates":[-82.1558,28.0859],"type":"Point"}
}