{
  "type": "Feature",
  "properties": {
    "iso:country":"US",
    "name:eng_x_preferred":[
        "Frush Valley"
    ],
    "name:eng_x_variant":[
        "Frush Vly"
    ],
    "qs:gn_adm0_cc":"US",
    "qs:gn_local":5202700,
    "qs:gn_nam_loc":"Muhlenberg, Berks, Pennsylvania, US",
    "qs:gn_namadm1":"PA",
    "qs:local_max":501,
    "qs:local_sum":514,
    "qs:localhoods":2,
    "qs:name":"Frush Valley",
    "qs:name_adm0":"United States",
    "qs:name_adm1":"Pennsylvania",
    "qs:name_adm2":"Berks",
    "qs:name_local":"Muhlenberg",
    "qs:photo_max":9,
    "qs:photo_sum":13,
    "qs:placetype":"Suburb",
    "qs:quad_count":3,
    "qs:woe_adm0":23424977,
    "qs:woe_adm1":2347597,
    "qs:woe_adm2":12589733,
    "qs:woe_lau":0,
    "qs:woe_local":2456160,
    "qs:woe_ver":"7.10.0",
    "wof:lang":[
        "eng"
    ],
    "wof:name":"Frush Valley",
    "wof:placetype":"neighbourhood",
    "wof:population":1796,
    "zs:blockids":[
        420110124003001,
        420110129001013,
        420110124002021,
        420110129001026,
        420110124002015,
        420110124003018,
        420110129001024,
        420110129001005,
        420110124002018,
        420110124003034,
        420110129001023,
        420110124002023,
        420110124002013,
        420110124003013,
        420110128001000,
        420110129001012,
        420110128001008,
        420110124002024,
        420110124003000,
        420110124002014,
        420110129001022,
        420110124002033,
        420110128001004,
        420110124003012,
        420110129001025,
        420110124002001,
        420110124002016,
        420110129001014,
        420110124002036,
        420110124002037,
        420110124003035,
        420110124002022,
        420110128001005,
        420110129001006,
        420110124003014,
        420110124003015,
        420110124002017
    ],
    "zs:housing10":761,
    "zs:pop10":1796
},
  "geometry": {"coordinates":[-75.913624,40.405293],"type":"Point"}
}