{
  "type": "Feature",
  "properties": {
    "gn:admin1_code":"AL",
    "gn:admin2_code":"55.0",
    "gn:asciiname":"Pulltight",
    "gn:country_code":"US",
    "gn:dem":313,
    "gn:elevation":"311.0",
    "gn:feature_class":"P",
    "gn:feature_code":"PPL",
    "gn:name":"Pulltight",
    "gn:population":0,
    "gn:timezone":"America/Chicago",
    "iso:country":"US",
    "wof:name":"Pulltight",
    "wof:placetype":"locality"
},
  "geometry": {"coordinates":[-86.07080999999999,34.18676],"type":"Point"}
}