{
  "type": "Feature",
  "properties": {
    "gn:admin1_code":"KS",
    "gn:admin2_code":"157.0",
    "gn:admin3_code":"72300.0",
    "gn:asciiname":"Sherdahl",
    "gn:country_code":"US",
    "gn:dem":448,
    "gn:elevation":"447.0",
    "gn:feature_class":"P",
    "gn:feature_code":"PPL",
    "gn:name":"Sherdahl",
    "gn:population":0,
    "gn:timezone":"America/Chicago",
    "iso:country":"US",
    "wof:name":"Sherdahl",
    "wof:placetype":"locality"
},
  "geometry": {"coordinates":[-97.8081,39.85695],"type":"Point"}
}