{
  "type": "Feature",
  "properties": {
    "gn:country":"US",
    "gn:elevation":7,
    "gn:fcode":"PPL",
    "gn:population":0,
    "iso:country":"US",
    "name:eng_x_preferred":[
        "Trots Hills"
    ],
    "name:eng_x_variant":[
        "Trots Hls"
    ],
    "name:und_x_variant":[
        "Trotts Hills"
    ],
    "qs:gn_adm0_cc":"US",
    "qs:gn_fcode":"PPL",
    "qs:gn_local":4944986,
    "qs:gn_nam_loc":"fieldston",
    "qs:gn_namadm1":"MA",
    "qs:gn_name":"Trots Hills",
    "qs:local_max":3195,
    "qs:local_sum":4690,
    "qs:localhoods":23,
    "qs:name":"Trots Hills",
    "qs:name_adm0":"United States",
    "qs:name_adm1":"Massachusetts",
    "qs:name_adm2":"Nantucket",
    "qs:name_local":"Nantucket",
    "qs:photo_max":30,
    "qs:photo_sum":30,
    "qs:placetype":"Suburb",
    "qs:quad_count":1,
    "qs:woe_adm0":23424977,
    "qs:woe_adm1":2347580,
    "qs:woe_adm2":12588709,
    "qs:woe_lau":0,
    "qs:woe_local":2456968,
    "qs:woe_ver":"7.10.0",
    "qs_pg:aaroncc":"US",
    "qs_pg:gn_country":"US",
    "qs_pg:gn_fcode":"PPL",
    "qs_pg:gn_pop":0,
    "qs_pg:name":"Trots Hills",
    "qs_pg:name_adm0":"United States",
    "qs_pg:name_adm1":"Massachusetts",
    "qs_pg:photos":35,
    "qs_pg:photos_1k":7,
    "qs_pg:photos_9k":1,
    "qs_pg:photos_9r":2,
    "qs_pg:photos_all":35,
    "qs_pg:photos_sr":2,
    "qs_pg:pop_sr":0,
    "qs_pg:qs_pg_placetype":"neighbourhood",
    "qs_pg:qs_pg_placetype_gp":"Suburb",
    "qs_pg:woe_adm0":23424977,
    "wof:lang":[
        "eng"
    ],
    "wof:name":"Trots Hills",
    "wof:placetype":"neighbourhood",
    "wof:population":70,
    "zs:blockids":[
        250199503071042,
        250199503071004,
        250199503071017,
        250199503071016,
        250199503071041,
        250199503071034,
        250199503071043,
        250199503071046,
        250199503071215,
        250199503071000,
        250199503071005,
        250199503071011,
        250199503071038,
        250199503071044,
        250199503071013,
        250199503071003,
        250199503071012,
        250199503071039,
        250199503071209,
        250199503071040,
        250199503071045,
        250199503071010,
        250199503071020,
        250199503071037,
        250199503071019,
        250199503071035,
        250199503071007,
        250199503071009,
        250199503071018,
        250199503071008,
        250199503071006,
        250199503071277,
        250199503071217
    ],
    "zs:housing10":255,
    "zs:pop10":70
},
  "geometry": {"coordinates":[-70.150452,41.292255],"type":"Point"}
}