{
  "type": "Feature",
  "properties": {
    "gn:admin1_code":"NC",
    "gn:admin2_code":"25",
    "gn:asciiname":"Centerview",
    "gn:country_code":"US",
    "gn:dem":244,
    "gn:elevation":"241.0",
    "gn:feature_class":"P",
    "gn:feature_code":"PPL",
    "gn:name":"Centerview",
    "gn:population":0,
    "gn:timezone":"America/New_York",
    "iso:country":"US",
    "wof:name":"Centerview",
    "wof:placetype":"locality"
},
  "geometry": {"coordinates":[-80.61839999999999,35.49069],"type":"Point"}
}