{
  "type": "Feature",
  "properties": {
    "gn:admin1_code":"VA",
    "gn:admin2_code":"83",
    "gn:asciiname":"Ingram",
    "gn:country_code":"US",
    "gn:dem":215,
    "gn:elevation":"215.0",
    "gn:feature_class":"P",
    "gn:feature_code":"PPL",
    "gn:name":"Ingram",
    "gn:population":0,
    "gn:timezone":"America/New_York",
    "iso:country":"US",
    "name:fas_x_preferred":[
        "\u0627\u06cc\u0646\u06af\u0631\u0627\u0645"
    ],
    "name:ukr_x_preferred":[
        "\u0406\u043d\u0433\u0440\u0435\u043c"
    ],
    "wof:name":"Ingram",
    "wof:placetype":"locality"
},
  "geometry": {"coordinates":[-79.15835,36.7443],"type":"Point"}
}