{
  "type": "Feature",
  "properties": {
    "gn:admin1_code":"MD",
    "gn:admin2_code":"5.0",
    "gn:asciiname":"Harrisonville",
    "gn:country_code":"US",
    "gn:dem":200,
    "gn:elevation":"200.0",
    "gn:feature_class":"P",
    "gn:feature_code":"PPL",
    "gn:name":"Harrisonville",
    "gn:population":0,
    "gn:timezone":"America/New_York",
    "iso:country":"US",
    "wof:name":"Harrisonville",
    "wof:placetype":"locality"
},
  "geometry": {"coordinates":[-76.83331,39.38594000000001],"type":"Point"}
}