{
  "type": "Feature",
  "properties": {
    "iso:country":"US",
    "name:eng_x_preferred":[
        "Brookstone"
    ],
    "name:fas_x_preferred":[
        "\u0628\u0631\u0648\u06a9\u200c\u0627\u0633\u062a\u0648\u0646"
    ],
    "name:fra_x_preferred":[
        "Brookstone"
    ],
    "name:spa_x_preferred":[
        "Brookstone"
    ],
    "name:zho_x_preferred":[
        "\u5e03\u6d1b\u53f2\u6566\u96f6\u552e\u5e97"
    ],
    "wd:wordcount":1432,
    "wof:name":"Brookstone",
    "wof:placetype":"neighbourhood",
    "wof:population":913,
    "zs:area_m":533925.441421,
    "zs:blockids":[
        481210217232004,
        481210217232001,
        481210217292000,
        481210217423023,
        481210217232005,
        481210217421029,
        481210217421024,
        481210217421028,
        481210217231003,
        481210217421020,
        481210217303002,
        481210217421019,
        481210217421023,
        481210217421021,
        481210217421025,
        481210217232000,
        481210217232009,
        481210217291000,
        481210217423022,
        481210217421022,
        481210217232002,
        481210217232008,
        481210217231004
    ],
    "zs:housing10":334,
    "zs:label":"Brookstone",
    "zs:pop10":913
},
  "geometry": {"coordinates":[-97.034283,33.025912],"type":"Point"}
}