{
  "type": "Feature",
  "properties": {
    "gn:admin1_code":"IL",
    "gn:admin2_code":"67.0",
    "gn:admin3_code":"64876.0",
    "gn:asciiname":"Adrian",
    "gn:country_code":"US",
    "gn:dem":215,
    "gn:elevation":"213.0",
    "gn:feature_class":"P",
    "gn:feature_code":"PPL",
    "gn:name":"Adrian",
    "gn:population":0,
    "gn:timezone":"America/Chicago",
    "iso:country":"US",
    "name:fas_x_preferred":[
        "\u0627\u062f\u0631\u06cc\u0627\u0646"
    ],
    "name:urd_x_preferred":[
        "\u0627\u06cc\u0688\u0631\u06cc\u0646"
    ],
    "wof:name":"Adrian",
    "wof:placetype":"locality"
},
  "geometry": {"coordinates":[-91.16709,40.52088],"type":"Point"}
}