{
  "type": "Feature",
  "properties": {
    "gn:country":"US",
    "gn:fcode":"PPL",
    "gn:population":0,
    "iso:country":"US",
    "name:eng_x_preferred":[
        "Lincoln Center"
    ],
    "name:und_x_variant":[
        "Hayes"
    ],
    "qs_pg:aaroncc":"US",
    "qs_pg:gn_country":"US",
    "qs_pg:gn_fcode":"PPL",
    "qs_pg:gn_pop":0,
    "qs_pg:name":"Lincoln Center",
    "qs_pg:name_adm0":"United States",
    "qs_pg:name_adm1":"Iowa",
    "qs_pg:photos_9r":0,
    "qs_pg:photos_sr":0,
    "qs_pg:pop_sr":0,
    "qs_pg:qs_pg_placetype":"locality",
    "qs_pg:qs_pg_placetype_gp":"Town",
    "qs_pg:woe_adm0":23424977,
    "woe:adm0_id":23424977,
    "woe:name_adm0":"United States",
    "woe:name_adm1":"Iowa",
    "woe:placetype":"Town",
    "wof:name":"Lincoln Center",
    "wof:placetype":"locality"
},
  "geometry": {"coordinates":[-94.87220000000001,41.11582],"type":"Point"}
}