{
  "type": "Feature",
  "properties": {
    "gn:admin1_code":"TX",
    "gn:admin2_code":"465.0",
    "gn:asciiname":"Val Verde Park Colonia",
    "gn:country_code":"US",
    "gn:dem":330,
    "gn:elevation":"329.0",
    "gn:feature_class":"P",
    "gn:feature_code":"PPL",
    "gn:name":"Val Verde Park Colonia",
    "gn:population":0,
    "gn:timezone":"America/Chicago",
    "iso:country":"US",
    "wof:name":"Val Verde Park Colonia",
    "wof:placetype":"locality"
},
  "geometry": {"coordinates":[-100.83926,29.37329],"type":"Point"}
}