{
  "type": "Feature",
  "properties": {
    "gn:admin1_code":"VA",
    "gn:admin2_code":"179.0",
    "gn:asciiname":"Aquia",
    "gn:country_code":"US",
    "gn:dem":21,
    "gn:elevation":"18.0",
    "gn:feature_class":"P",
    "gn:feature_code":"PPL",
    "gn:name":"Aquia",
    "gn:population":0,
    "gn:timezone":"America/New_York",
    "iso:country":"US",
    "name:eng_x_preferred":[
        "Aquia"
    ],
    "name:und_x_variant":[
        "Aquia Station",
        "Acquia"
    ],
    "wof:name":"Aquia",
    "wof:placetype":"locality"
},
  "geometry": {"coordinates":[-77.38665,38.48235],"type":"Point"}
}