{
  "type": "Feature",
  "properties": {
    "gn:admin1_code":"FL",
    "gn:admin2_code":"57",
    "gn:asciiname":"Lone Oak Grove",
    "gn:country_code":"US",
    "gn:dem":34,
    "gn:elevation":"28.0",
    "gn:feature_class":"P",
    "gn:feature_code":"PPL",
    "gn:name":"Lone Oak Grove",
    "gn:population":0,
    "gn:timezone":"America/New_York",
    "iso:country":"US",
    "wof:name":"Lone Oak Grove",
    "wof:placetype":"locality"
},
  "geometry": {"coordinates":[-82.1692,27.9602],"type":"Point"}
}