{
  "type": "Feature",
  "properties": {
    "gn:admin1_code":"TN",
    "gn:admin2_code":"61",
    "gn:asciiname":"Gruetli",
    "gn:country_code":"US",
    "gn:dem":580,
    "gn:elevation":"577.0",
    "gn:feature_class":"P",
    "gn:feature_code":"PPL",
    "gn:name":"Gruetli",
    "gn:population":0,
    "gn:timezone":"America/Chicago",
    "iso:country":"US",
    "wof:name":"Gruetli",
    "wof:placetype":"locality"
},
  "geometry": {"coordinates":[-85.65997,35.37090999999999],"type":"Point"}
}