{
  "type": "Feature",
  "properties": {
    "gn:admin1_code":"MI",
    "gn:admin2_code":"47.0",
    "gn:admin3_code":"86300.0",
    "gn:asciiname":"Patons Corner",
    "gn:country_code":"US",
    "gn:dem":243,
    "gn:elevation":"245.0",
    "gn:feature_class":"P",
    "gn:feature_code":"PPL",
    "gn:name":"Patons Corner",
    "gn:population":0,
    "gn:timezone":"America/Detroit",
    "iso:country":"US",
    "wof:name":"Patons Corner",
    "wof:placetype":"locality"
},
  "geometry": {"coordinates":[-84.9945,45.47168],"type":"Point"}
}