{
  "type": "Feature",
  "properties": {
    "gn:admin1_code":"IA",
    "gn:admin2_code":"17.0",
    "gn:admin3_code":"91440.0",
    "gn:asciiname":"Old Tripoli",
    "gn:country_code":"US",
    "gn:dem":324,
    "gn:elevation":"323.0",
    "gn:feature_class":"P",
    "gn:feature_code":"PPL",
    "gn:name":"Old Tripoli",
    "gn:population":0,
    "gn:timezone":"America/Chicago",
    "iso:country":"US",
    "wof:name":"Old Tripoli",
    "wof:placetype":"locality"
},
  "geometry": {"coordinates":[-92.26546,42.82609],"type":"Point"}
}