{
  "type": "Feature",
  "properties": {
    "gn:admin1_code":"MI",
    "gn:admin2_code":"99.0",
    "gn:admin3_code":"84000.0",
    "gn:asciiname":"Shadylane Mobile Home Estates",
    "gn:country_code":"US",
    "gn:dem":194,
    "gn:elevation":"191.0",
    "gn:feature_class":"P",
    "gn:feature_code":"PPL",
    "gn:name":"Shadylane Mobile Home Estates",
    "gn:population":0,
    "gn:timezone":"America/Detroit",
    "iso:country":"US",
    "wof:name":"Shadylane Mobile Home Estates",
    "wof:placetype":"campus"
},
  "geometry": {"coordinates":[-83.07556,42.46417],"type":"Point"}
}