{
  "type": "Feature",
  "properties": {
    "gn:admin1_code":"MD",
    "gn:admin2_code":"5.0",
    "gn:asciiname":"Patchwork Farms",
    "gn:country_code":"US",
    "gn:dem":163,
    "gn:elevation":"169.0",
    "gn:feature_class":"P",
    "gn:feature_code":"PPL",
    "gn:name":"Patchwork Farms",
    "gn:population":0,
    "gn:timezone":"America/New_York",
    "iso:country":"US",
    "wof:name":"Patchwork Farms",
    "wof:placetype":"locality"
},
  "geometry": {"coordinates":[-76.59275,39.57066],"type":"Point"}
}