{
  "type": "Feature",
  "properties": {
    "gn:admin1_code":"WA",
    "gn:admin2_code":"65.0",
    "gn:asciiname":"Steven's Street Mobile Home Park",
    "gn:country_code":"US",
    "gn:dem":504,
    "gn:elevation":"503.0",
    "gn:feature_class":"P",
    "gn:feature_code":"PPL",
    "gn:name":"Steven's Street Mobile Home Park",
    "gn:population":0,
    "gn:timezone":"America/Los_Angeles",
    "iso:country":"US",
    "wof:name":"Steven's Street Mobile Home Park",
    "wof:placetype":"campus"
},
  "geometry": {"coordinates":[-117.72038000000001,48.26935],"type":"Point"}
}