{
  "type": "Feature",
  "properties": {
    "gn:admin1_code":"MT",
    "gn:admin2_code":"55.0",
    "gn:asciiname":"Nickwall",
    "gn:country_code":"US",
    "gn:dem":623,
    "gn:elevation":"626.0",
    "gn:feature_class":"P",
    "gn:feature_code":"PPL",
    "gn:name":"Nickwall",
    "gn:population":0,
    "gn:timezone":"America/Denver",
    "iso:country":"US",
    "wof:name":"Nickwall",
    "wof:placetype":"locality"
},
  "geometry": {"coordinates":[-105.30692999999999,48.04918],"type":"Point"}
}