{
  "type": "Feature",
  "properties": {
    "gn:country":"US",
    "gn:fcode":"PPL",
    "gn:population":0,
    "iso:country":"US",
    "name:eng_x_preferred":[
        "Avalon Beach"
    ],
    "qs_pg:aaroncc":"US",
    "qs_pg:gn_country":"US",
    "qs_pg:gn_fcode":"PPL",
    "qs_pg:gn_pop":0,
    "qs_pg:name":"Avalon Beach",
    "qs_pg:name_adm0":"United States",
    "qs_pg:name_adm1":"Vermont",
    "qs_pg:photos":25,
    "qs_pg:photos_1k":5,
    "qs_pg:photos_9k":1,
    "qs_pg:photos_9r":1,
    "qs_pg:photos_all":25,
    "qs_pg:photos_sr":1,
    "qs_pg:pop_sr":0,
    "qs_pg:qs_pg_placetype":"neighbourhood",
    "qs_pg:qs_pg_placetype_gp":"Suburb",
    "qs_pg:woe_adm0":23424977,
    "wof:name":"Avalon Beach",
    "wof:placetype":"neighbourhood",
    "wof:population":100,
    "zs:area_m":7975436.953433,
    "zs:blockids":[
        500219636001045,
        500219637001029,
        500219636001059,
        500219636001113,
        500219636001050
    ],
    "zs:housing10":62,
    "zs:label":"Avalon Beach",
    "zs:pop10":100
},
  "geometry": {"coordinates":[-73.24526899999999,43.615547],"type":"Point"}
}