{
  "type": "Feature",
  "properties": {
    "iso:country":"US",
    "name:eng_x_preferred":[
        "Carpenters Way"
    ],
    "wof:name":"Carpenters Way",
    "wof:placetype":"neighbourhood",
    "wof:population":332,
    "zs:area_m":260686.07128,
    "zs:blockids":[
        121050121272004,
        121050121272010,
        121050121272005,
        121050121272006,
        121050121271059,
        121050121273018
    ],
    "zs:housing10":76,
    "zs:label":"Carpenters Way",
    "zs:pop10":332
},
  "geometry": {"coordinates":[-81.97570899999999,28.097049],"type":"Point"}
}