{
  "type": "Feature",
  "properties": {
    "gn:admin1_code":"OH",
    "gn:admin2_code":"83.0",
    "gn:admin3_code":"38668.0",
    "gn:asciiname":"Greer",
    "gn:country_code":"US",
    "gn:dem":285,
    "gn:elevation":"283.0",
    "gn:feature_class":"P",
    "gn:feature_code":"PPL",
    "gn:name":"Greer",
    "gn:population":0,
    "gn:timezone":"America/New_York",
    "iso:country":"US",
    "name:ces_x_preferred":[
        "Greer"
    ],
    "name:deu_x_preferred":[
        "Greer"
    ],
    "name:eng_x_preferred":[
        "Greer"
    ],
    "name:fra_x_preferred":[
        "Greer"
    ],
    "name:heb_x_preferred":[
        "\u05d2\u05e8\u05d9\u05e8"
    ],
    "name:ita_x_preferred":[
        "Greer"
    ],
    "name:kor_x_preferred":[
        "\uadf8\ub9ac\uc5b4"
    ],
    "name:nds_x_preferred":[
        "Greer"
    ],
    "name:nld_x_preferred":[
        "Greer"
    ],
    "name:pol_x_preferred":[
        "Greer"
    ],
    "name:por_x_preferred":[
        "Greer"
    ],
    "name:rus_x_preferred":[
        "\u0413\u0440\u0438\u0440"
    ],
    "name:srp_x_preferred":[
        "\u0413\u0440\u0438\u0440"
    ],
    "name:ukr_x_preferred":[
        "\u0413\u0440\u0456\u0440"
    ],
    "name:und_x_variant":[
        "Greerville",
        "Edlam",
        "Greersville"
    ],
    "name:vol_x_preferred":[
        "Greer"
    ],
    "wof:name":"Greer",
    "wof:placetype":"locality"
},
  "geometry": {"coordinates":[-82.20016,40.52229000000001],"type":"Point"}
}