{
  "type": "Feature",
  "properties": {
    "gn:admin1_code":"AL",
    "gn:admin2_code":"73",
    "gn:asciiname":"Fitzgerald Estates",
    "gn:country_code":"US",
    "gn:dem":200,
    "gn:elevation":"192.0",
    "gn:feature_class":"P",
    "gn:feature_code":"PPL",
    "gn:name":"Fitzgerald Estates",
    "gn:population":0,
    "gn:timezone":"America/Chicago",
    "iso:country":"US",
    "wof:name":"Fitzgerald Estates",
    "wof:placetype":"locality"
},
  "geometry": {"coordinates":[-86.67666,33.70232],"type":"Point"}
}