{
  "type": "Feature",
  "properties": {
    "gn:admin1_code":"WA",
    "gn:admin2_code":"1.0",
    "gn:asciiname":"Ralston",
    "gn:country_code":"US",
    "gn:dem":502,
    "gn:elevation":"507.0",
    "gn:feature_class":"P",
    "gn:feature_code":"PPL",
    "gn:name":"Ralston",
    "gn:population":0,
    "gn:timezone":"America/Los_Angeles",
    "iso:country":"US",
    "wof:name":"Ralston",
    "wof:placetype":"locality"
},
  "geometry": {"coordinates":[-118.34275,46.98376],"type":"Point"}
}