{
  "type": "Feature",
  "properties": {
    "iso:country":"US",
    "name:eng_x_preferred":[
        "Maplecrest Woods"
    ],
    "wof:name":"Maplecrest Woods",
    "wof:placetype":"neighbourhood",
    "wof:population":139,
    "zs:area_m":39261.317951,
    "zs:blockids":[
        530110413271026
    ],
    "zs:housing10":41,
    "zs:label":"Maplecrest Woods",
    "zs:pop10":139
},
  "geometry": {"coordinates":[-122.485496,45.644174],"type":"Point"}
}