{
  "type": "Feature",
  "properties": {
    "gn:admin1_code":"VA",
    "gn:admin2_code":"59",
    "gn:asciiname":"Chesterbrook Gardens",
    "gn:country_code":"US",
    "gn:dem":96,
    "gn:elevation":"90.0",
    "gn:feature_class":"P",
    "gn:feature_code":"PPL",
    "gn:name":"Chesterbrook Gardens",
    "gn:population":0,
    "gn:timezone":"America/New_York",
    "iso:country":"US",
    "wof:name":"Chesterbrook Gardens",
    "wof:placetype":"locality"
},
  "geometry": {"coordinates":[-77.17081,38.91622],"type":"Point"}
}