{
  "type": "Feature",
  "properties": {
    "iso:country":"US",
    "name:eng_x_preferred":[
        "Highland Shore"
    ],
    "wof:name":"Highland Shore",
    "wof:placetype":"neighbourhood",
    "wof:population":245,
    "zs:area_m":2167626.231707,
    "zs:blockids":[
        551390020002033,
        551390020002063,
        551390020002029,
        551390020002060,
        551390020002028,
        551390020002031,
        551390020002032
    ],
    "zs:housing10":100,
    "zs:label":"Highland Shore",
    "zs:pop10":245
},
  "geometry": {"coordinates":[-88.64801799999999,44.04324],"type":"Point"}
}