{
  "type": "Feature",
  "properties": {
    "gn:admin1_code":"SC",
    "gn:admin2_code":"39.0",
    "gn:asciiname":"Cool Branch",
    "gn:country_code":"US",
    "gn:dem":168,
    "gn:elevation":"163.0",
    "gn:feature_class":"P",
    "gn:feature_code":"PPL",
    "gn:name":"Cool Branch",
    "gn:population":0,
    "gn:timezone":"America/New_York",
    "iso:country":"US",
    "wof:name":"Cool Branch",
    "wof:placetype":"locality"
},
  "geometry": {"coordinates":[-81.37954000000001,34.54931],"type":"Point"}
}