{
  "type": "Feature",
  "properties": {
    "gn:admin1_code":"VA",
    "gn:admin2_code":"550.0",
    "gn:asciiname":"Waterway Estates",
    "gn:country_code":"US",
    "gn:dem":8,
    "gn:elevation":"7.0",
    "gn:feature_class":"P",
    "gn:feature_code":"PPL",
    "gn:name":"Waterway Estates",
    "gn:population":0,
    "gn:timezone":"America/New_York",
    "iso:country":"US",
    "wof:name":"Waterway Estates",
    "wof:placetype":"locality"
},
  "geometry": {"coordinates":[-76.18389000000001,36.71694],"type":"Point"}
}