{
  "type": "Feature",
  "properties": {
    "iso:country":"US",
    "name:eng_x_preferred":[
        "Roy"
    ],
    "name:fra_x_preferred":[
        "Roy"
    ],
    "name:hat_x_preferred":[
        "Roy"
    ],
    "qs_pg:aaroncc":"US",
    "qs_pg:name":"Roy",
    "qs_pg:name_adm0":"United States",
    "qs_pg:name_adm1":"Oregon",
    "qs_pg:photos":343,
    "qs_pg:photos_1k":70,
    "qs_pg:photos_9k":2,
    "qs_pg:photos_9r":5,
    "qs_pg:photos_all":343,
    "qs_pg:photos_sr":5,
    "qs_pg:pop_sr":0,
    "qs_pg:qs_pg_placetype":"locality",
    "qs_pg:qs_pg_placetype_gp":"Town",
    "qs_pg:woe_adm0":23424977,
    "woe:adm0_id":23424977,
    "woe:name_adm0":"United States",
    "woe:name_adm1":"Oregon",
    "woe:placetype":"Town",
    "wof:name":"Roy",
    "wof:placetype":"locality"
},
  "geometry": {"coordinates":[-123.06816600000001,45.614922],"type":"Point"}
}