{
  "type": "Feature",
  "properties": {
    "gn:gn_country":"US",
    "gn:gn_fcode":"PPL",
    "gn:gn_pop":0,
    "iso:country":"US",
    "name:eng_x_preferred":[
        "Wilmington Beach"
    ],
    "name:fas_x_preferred":[
        "\u0648\u06cc\u0644\u0645\u06cc\u0646\u06af\u062a\u0648\u0646 \u0628\u06cc\u0686"
    ],
    "name:fra_x_preferred":[
        "Wilmington Beach"
    ],
    "name:spa_x_preferred":[
        "Wilmington Beach"
    ],
    "qs_pg:aaroncc":"US",
    "qs_pg:gn_country":"US",
    "qs_pg:gn_fcode":"PPL",
    "qs_pg:gn_pop":0,
    "qs_pg:name":"Wilmington Beach",
    "qs_pg:name_adm0":"United States",
    "qs_pg:name_adm1":"North Carolina",
    "qs_pg:photos":483,
    "qs_pg:photos_1k":98,
    "qs_pg:photos_9k":2,
    "qs_pg:photos_9r":5,
    "qs_pg:photos_all":483,
    "qs_pg:photos_sr":7,
    "qs_pg:pop_sr":0,
    "qs_pg:qs_pg_placetype":"locality",
    "qs_pg:qs_pg_placetype_gp":"Town",
    "qs_pg:woe_adm0":23424977,
    "woe:adm0_id":23424977,
    "woe:name_adm0":"United States",
    "woe:name_adm1":"North Carolina",
    "woe:placetype":"Town",
    "wof:name":"Wilmington Beach",
    "wof:placetype":"locality"
},
  "geometry": {"coordinates":[-77.8986,34.01878],"type":"Point"}
}