{
  "type": "Feature",
  "properties": {
    "gn:admin1_code":"VA",
    "gn:admin2_code":"85",
    "gn:asciiname":"Rainier Estates",
    "gn:country_code":"US",
    "gn:dem":52,
    "gn:elevation":"49.0",
    "gn:feature_class":"P",
    "gn:feature_code":"PPL",
    "gn:name":"Rainier Estates",
    "gn:population":0,
    "gn:timezone":"America/New_York",
    "iso:country":"US",
    "wof:name":"Rainier Estates",
    "wof:placetype":"locality"
},
  "geometry": {"coordinates":[-77.29942,37.66848],"type":"Point"}
}