{
  "type": "Feature",
  "properties": {
    "gn:admin1_code":"PA",
    "gn:admin2_code":"51.0",
    "gn:admin3_code":"28856.0",
    "gn:asciiname":"Antram",
    "gn:country_code":"US",
    "gn:dem":309,
    "gn:elevation":"307.0",
    "gn:feature_class":"P",
    "gn:feature_code":"PPL",
    "gn:name":"Antram",
    "gn:population":0,
    "gn:timezone":"America/New_York",
    "iso:country":"US",
    "wof:name":"Antram",
    "wof:placetype":"locality"
},
  "geometry": {"coordinates":[-79.91672,39.91174],"type":"Point"}
}