{
  "type": "Feature",
  "properties": {
    "gn:admin1_code":"MO",
    "gn:admin2_code":"111.0",
    "gn:admin3_code":"11152.0",
    "gn:asciiname":"Santuzza",
    "gn:country_code":"US",
    "gn:dem":188,
    "gn:elevation":"183.0",
    "gn:feature_class":"P",
    "gn:feature_code":"PPL",
    "gn:name":"Santuzza",
    "gn:population":0,
    "gn:timezone":"America/Chicago",
    "iso:country":"US",
    "wof:name":"Santuzza",
    "wof:placetype":"locality"
},
  "geometry": {"coordinates":[-91.53431999999999,40.20588],"type":"Point"}
}