{
  "type": "Feature",
  "properties": {
    "iso:country":"US",
    "name:eng_x_preferred":[
        "Vitale Tract"
    ],
    "wof:name":"Vitale Tract",
    "wof:placetype":"neighbourhood",
    "wof:population":182,
    "zs:area_m":86959.303652,
    "zs:blockids":[
        60610208062011,
        60610208052002
    ],
    "zs:housing10":91,
    "zs:label":"Vitale Tract",
    "zs:pop10":182
},
  "geometry": {"coordinates":[-121.284156,38.736697],"type":"Point"}
}