{
  "type": "Feature",
  "properties": {
    "iso:country":"US",
    "name:eng_x_preferred":[
        "Summerbrook Place"
    ],
    "wof:name":"Summerbrook Place",
    "wof:placetype":"neighbourhood",
    "wof:population":399,
    "zs:area_m":15133149.522827,
    "zs:blockids":[
        51430111022061,
        51430111022023,
        51430111022063,
        51430111022029,
        51430111022018,
        51430111022016,
        51430111022024,
        51430111022012
    ],
    "zs:housing10":173,
    "zs:label":"Summerbrook Place",
    "zs:pop10":399
},
  "geometry": {"coordinates":[-94.089288,36.025096],"type":"Point"}
}