{
  "type": "Feature",
  "properties": {
    "gn:admin1_code":"IL",
    "gn:admin2_code":"77",
    "gn:admin3_code":"40104.0",
    "gn:asciiname":"Glenn",
    "gn:country_code":"US",
    "gn:dem":116,
    "gn:elevation":"118.0",
    "gn:feature_class":"P",
    "gn:feature_code":"PPL",
    "gn:name":"Glenn",
    "gn:population":0,
    "gn:timezone":"America/Chicago",
    "iso:country":"US",
    "wof:name":"Glenn",
    "wof:placetype":"locality"
},
  "geometry": {"coordinates":[-89.58065000000001,37.80366],"type":"Point"}
}