{
  "type": "Feature",
  "properties": {
    "gn:country":"US",
    "gn:fcode":"PPL",
    "gn:population":0,
    "iso:country":"US",
    "qs_pg:aaroncc":"US",
    "qs_pg:gn_country":"US",
    "qs_pg:gn_fcode":"PPL",
    "qs_pg:gn_pop":0,
    "qs_pg:name":"Little Jersey",
    "qs_pg:name_adm0":"United States",
    "qs_pg:name_adm1":"Delaware",
    "qs_pg:photos":534,
    "qs_pg:photos_1k":108,
    "qs_pg:photos_9k":2,
    "qs_pg:photos_9r":5,
    "qs_pg:photos_all":534,
    "qs_pg:photos_sr":7,
    "qs_pg:pop_sr":0,
    "qs_pg:qs_pg_placetype":"locality",
    "qs_pg:qs_pg_placetype_gp":"Town",
    "qs_pg:woe_adm0":23424977,
    "woe:adm0_id":23424977,
    "woe:name_adm0":"United States",
    "woe:name_adm1":"Delaware",
    "woe:placetype":"Town",
    "wof:name":"Little Jersey",
    "wof:placetype":"locality"
},
  "geometry": {"coordinates":[-75.71465000000001,39.55706],"type":"Point"}
}