{
  "type": "Feature",
  "properties": {
    "gn:admin1_code":"AR",
    "gn:admin2_code":"3.0",
    "gn:admin3_code":"92277.0",
    "gn:asciiname":"Milo",
    "gn:country_code":"US",
    "gn:dem":40,
    "gn:elevation":"33.0",
    "gn:feature_class":"P",
    "gn:feature_code":"PPL",
    "gn:name":"Milo",
    "gn:population":0,
    "gn:timezone":"America/Chicago",
    "iso:country":"US",
    "name:cat_x_preferred":[
        "Milo"
    ],
    "name:ceb_x_preferred":[
        "Milo"
    ],
    "name:ces_x_preferred":[
        "Milo"
    ],
    "name:deu_x_preferred":[
        "Milo"
    ],
    "name:epo_x_preferred":[
        "Milo"
    ],
    "name:eus_x_preferred":[
        "Milo"
    ],
    "name:fin_x_preferred":[
        "Milo"
    ],
    "name:fra_x_preferred":[
        "Milo"
    ],
    "name:heb_x_preferred":[
        "\u05de\u05d9\u05dc\u05d5"
    ],
    "name:hun_x_preferred":[
        "Milo"
    ],
    "name:ind_x_preferred":[
        "Milo"
    ],
    "name:ita_x_preferred":[
        "Milo"
    ],
    "name:kor_x_preferred":[
        "\ub9c8\uc77c\ub85c"
    ],
    "name:nld_x_preferred":[
        "Milo"
    ],
    "name:pol_x_preferred":[
        "Milo"
    ],
    "name:por_x_preferred":[
        "Milo"
    ],
    "name:rus_x_preferred":[
        "\u041c\u0430\u0439\u043b\u043e"
    ],
    "name:slv_x_preferred":[
        "Milo"
    ],
    "name:spa_x_preferred":[
        "Milo"
    ],
    "name:srp_x_preferred":[
        "\u041c\u0430\u0458\u043b\u043e"
    ],
    "name:swe_x_preferred":[
        "Milo"
    ],
    "name:ukr_x_preferred":[
        "\u041c\u0456\u043b\u043e"
    ],
    "name:vol_x_preferred":[
        "Milo"
    ],
    "wof:name":"Milo",
    "wof:placetype":"locality"
},
  "geometry": {"coordinates":[-91.95013,33.2954],"type":"Point"}
}