{
  "type": "Feature",
  "properties": {
    "gn:admin1_code":"WY",
    "gn:admin2_code":"9.0",
    "gn:asciiname":"Shawnee",
    "gn:country_code":"US",
    "gn:dem":1540,
    "gn:elevation":"1542.0",
    "gn:feature_class":"P",
    "gn:feature_code":"PPL",
    "gn:name":"Shawnee",
    "gn:population":0,
    "gn:timezone":"America/Denver",
    "iso:country":"US",
    "name:fas_x_preferred":[
        "\u0634\u0627\u0648\u0646\u06cc"
    ],
    "name:swe_x_preferred":[
        "Shawnee"
    ],
    "wof:name":"Shawnee",
    "wof:placetype":"locality"
},
  "geometry": {"coordinates":[-105.00969000000001,42.74775],"type":"Point"}
}