{
  "type": "Feature",
  "properties": {
    "gn:admin1_code":"CA",
    "gn:admin2_code":"71.0",
    "gn:asciiname":"Wildhorse Canyon",
    "gn:country_code":"US",
    "gn:dem":1495,
    "gn:elevation":"1497.0",
    "gn:feature_class":"P",
    "gn:feature_code":"PPL",
    "gn:name":"Wildhorse Canyon",
    "gn:population":0,
    "gn:timezone":"America/Los_Angeles",
    "iso:country":"US",
    "wof:name":"Wildhorse Canyon",
    "wof:placetype":"locality"
},
  "geometry": {"coordinates":[-117.61005,34.38806],"type":"Point"}
}