{
  "type": "Feature",
  "properties": {
    "gn:admin1_code":"NH",
    "gn:admin2_code":"9.0",
    "gn:admin3_code":"18740.0",
    "gn:asciiname":"North Dorchester",
    "gn:country_code":"US",
    "gn:dem":402,
    "gn:elevation":"400.0",
    "gn:feature_class":"P",
    "gn:feature_code":"PPL",
    "gn:name":"North Dorchester",
    "gn:population":0,
    "gn:timezone":"America/New_York",
    "iso:country":"US",
    "wof:name":"North Dorchester",
    "wof:placetype":"locality"
},
  "geometry": {"coordinates":[-71.97091999999998,43.80257],"type":"Point"}
}