{
  "type": "Feature",
  "properties": {
    "gn:admin1_code":"VA",
    "gn:admin2_code":"041",
    "gn:asciiname":"Woodmont",
    "gn:country_code":"US",
    "gn:dem":109,
    "gn:elevation":"99.0",
    "gn:feature_class":"P",
    "gn:feature_code":"PPL",
    "gn:name":"Woodmont",
    "gn:population":0,
    "gn:timezone":"America/New_York",
    "iso:country":"US",
    "name:deu_x_preferred":[
        "Woodmont"
    ],
    "name:vol_x_preferred":[
        "Woodmont"
    ],
    "wof:name":"Woodmont",
    "wof:placetype":"locality"
},
  "geometry": {"coordinates":[-77.58582,37.53154],"type":"Point"}
}