{
  "type": "Feature",
  "properties": {
    "gn:admin1_code":"MD",
    "gn:admin2_code":"37.0",
    "gn:asciiname":"Herring Creek",
    "gn:country_code":"US",
    "gn:dem":2,
    "gn:elevation":"3.0",
    "gn:feature_class":"P",
    "gn:feature_code":"PPL",
    "gn:name":"Herring Creek",
    "gn:population":0,
    "gn:timezone":"America/New_York",
    "iso:country":"US",
    "wof:name":"Herring Creek",
    "wof:placetype":"locality"
},
  "geometry": {"coordinates":[-76.54134000000001,38.18624000000001],"type":"Point"}
}