{
  "type": "Feature",
  "properties": {
    "iso:country":"US",
    "name:eng_x_preferred":[
        "Hunting Hills"
    ],
    "wof:name":"Hunting Hills",
    "wof:placetype":"neighbourhood",
    "wof:population":4107,
    "zs:area_m":2759953.450041,
    "zs:blockids":[
        210670034063018,
        210670034062010,
        210670034063002,
        210670034062000,
        210670034063016,
        210670034063000,
        210670034063013,
        210670034063015,
        210670034063008,
        210670034063017,
        210670034063019,
        210670034063012,
        210670034063014,
        210670034063010,
        210670034063007,
        210670034062014,
        210670034063003,
        210670034062013,
        210670034063009,
        210670034063004,
        210670034063001,
        210670034062004
    ],
    "zs:housing10":1671,
    "zs:label":"Hunting Hills",
    "zs:pop10":4107
},
  "geometry": {"coordinates":[-84.45682600000001,37.968225],"type":"Point"}
}