{
  "type": "Feature",
  "properties": {
    "gn:admin1_code":"KY",
    "gn:admin2_code":"33",
    "gn:asciiname":"Lewistown",
    "gn:country_code":"US",
    "gn:dem":147,
    "gn:elevation":"143.0",
    "gn:feature_class":"P",
    "gn:feature_code":"PPL",
    "gn:name":"Lewistown",
    "gn:population":0,
    "gn:timezone":"America/Chicago",
    "iso:country":"US",
    "name:eng_x_preferred":[
        "Lewistown"
    ],
    "name:und_x_variant":[
        "Pleasant Grove",
        "Baker and Carter Settlement"
    ],
    "wof:name":"Lewistown",
    "wof:placetype":"locality"
},
  "geometry": {"coordinates":[-87.80056999999999,37.14283],"type":"Point"}
}