{
  "type": "Feature",
  "properties": {
    "iso:country":"US",
    "name:eng_x_preferred":[
        "Windsor Downs"
    ],
    "qs:gn_adm0_cc":"US",
    "qs:gn_local":5814616,
    "qs:gn_nam_loc":"Vancouver, Clark, Washington, US",
    "qs:gn_namadm1":"WA",
    "qs:local_max":2037,
    "qs:local_sum":14855,
    "qs:localhoods":74,
    "qs:name":"Windsor Downs",
    "qs:name_adm0":"United States",
    "qs:name_adm1":"Washington",
    "qs:name_adm2":"Clark",
    "qs:name_local":"Vancouver",
    "qs:photo_max":82,
    "qs:photo_sum":82,
    "qs:placetype":"Suburb",
    "qs:quad_count":1,
    "qs:woe_adm0":23424977,
    "qs:woe_adm1":2347606,
    "qs:woe_adm2":12590445,
    "qs:woe_lau":0,
    "qs:woe_local":2511258,
    "qs:woe_ver":"7.10.0",
    "wof:name":"Windsor Downs",
    "wof:placetype":"neighbourhood",
    "wof:population":47,
    "zs:blockids":[
        530110407091001
    ],
    "zs:housing10":17,
    "zs:pop10":47
},
  "geometry": {"coordinates":[-122.55935700000001,45.699467],"type":"Point"}
}