{
  "type": "Feature",
  "properties": {
    "gn:country":"US",
    "gn:fcode":"PPL",
    "gn:population":0,
    "iso:country":"US",
    "name:azb_x_preferred":[
        "\u0628\u06cc\u0644\u06cc\u0648\u06cc\u0644"
    ],
    "name:eng_x_preferred":[
        "Baileyville"
    ],
    "name:fas_x_preferred":[
        "\u0628\u06cc\u0644\u06cc\u0648\u06cc\u0644"
    ],
    "name:fra_x_preferred":[
        "Baileyville"
    ],
    "name:lld_x_preferred":[
        "Baileyville"
    ],
    "name:vol_x_preferred":[
        "Baileyville"
    ],
    "name:zho_x_preferred":[
        "\u8c9d\u5229\u7dad\u723e"
    ],
    "qs_pg:aaroncc":"US",
    "qs_pg:gn_country":"US",
    "qs_pg:gn_fcode":"PPL",
    "qs_pg:gn_pop":0,
    "qs_pg:name":"Baileyville",
    "qs_pg:name_adm0":"United States",
    "qs_pg:name_adm1":"Illinois",
    "qs_pg:photos_9k":1,
    "qs_pg:photos_9r":1,
    "qs_pg:photos_all":4,
    "qs_pg:photos_sr":0,
    "qs_pg:pop_sr":5,
    "qs_pg:qs_pg_placetype":"locality",
    "qs_pg:qs_pg_placetype_gp":"Town",
    "qs_pg:woe_adm0":23424977,
    "woe:adm0_id":23424977,
    "woe:name_adm0":"United States",
    "woe:name_adm1":"Illinois",
    "woe:placetype":"Town",
    "wof:name":"Baileyville",
    "wof:placetype":"locality"
},
  "geometry": {"coordinates":[-89.59345,42.19725],"type":"Point"}
}