{
  "type": "Feature",
  "properties": {
    "gn:admin1_code":"ID",
    "gn:admin2_code":"49.0",
    "gn:asciiname":"Asbestos Point",
    "gn:country_code":"US",
    "gn:dem":804,
    "gn:elevation":"789.0",
    "gn:feature_class":"P",
    "gn:feature_code":"PPL",
    "gn:name":"Asbestos Point",
    "gn:population":0,
    "gn:timezone":"America/Los_Angeles",
    "iso:country":"US",
    "wof:name":"Asbestos Point",
    "wof:placetype":"locality"
},
  "geometry": {"coordinates":[-115.94069,45.81795],"type":"Point"}
}