{
  "type": "Feature",
  "properties": {
    "iso:country":"US",
    "name:bar_x_preferred":[
        "Mount Pleasant"
    ],
    "name:cat_x_preferred":[
        "Mount Pleasant"
    ],
    "name:ceb_x_preferred":[
        "Mount Pleasant"
    ],
    "name:ces_x_preferred":[
        "Mount Pleasant"
    ],
    "name:deu_x_preferred":[
        "Mount Pleasant"
    ],
    "name:eng_x_preferred":[
        "Mount Pleasant"
    ],
    "name:fra_x_preferred":[
        "Mount Pleasant"
    ],
    "name:ita_x_preferred":[
        "Mount Pleasant"
    ],
    "name:jpn_x_preferred":[
        "\u30de\u30a6\u30f3\u30c8\u30fb\u30d7\u30ec\u30b6\u30f3\u30c8"
    ],
    "name:kor_x_preferred":[
        "\ub9c8\uc6b4\ud2b8\ud50c\ub808\uc804\ud2b8"
    ],
    "name:mlg_x_preferred":[
        "Mount Pleasant"
    ],
    "name:nld_x_preferred":[
        "Mount Pleasant"
    ],
    "name:nor_x_preferred":[
        "Mount Pleasant"
    ],
    "name:pol_x_preferred":[
        "Mount Pleasant"
    ],
    "name:por_x_preferred":[
        "Mount Pleasant"
    ],
    "name:rus_x_preferred":[
        "\u041c\u0430\u0443\u043d\u0442-\u041f\u043b\u0435\u0437\u0430\u043d\u0442"
    ],
    "name:spa_x_preferred":[
        "Mount Pleasant"
    ],
    "name:srp_x_preferred":[
        "\u041c\u0430\u0443\u043d\u0442 \u041f\u043b\u0435\u0437\u0430\u043d\u0442"
    ],
    "name:swe_x_preferred":[
        "Mount Pleasant"
    ],
    "name:ukr_x_preferred":[
        "\u041c\u0430\u0443\u043d\u0442-\u041f\u043b\u0435\u0437\u0430\u043d\u0442"
    ],
    "name:vol_x_preferred":[
        "Mount Pleasant"
    ],
    "wof:name":"Mount Pleasant",
    "wof:placetype":"neighbourhood",
    "wof:population":532,
    "zs:area_m":49361939.938196,
    "zs:blockids":[
        421070013001017,
        421070013001000,
        421070014001052,
        421070013001027,
        421070014001047,
        421070014001041,
        421070013001025,
        421070014001053,
        421070014001097,
        421070013001009,
        421070013001012,
        421070013001029,
        421070013001022,
        421070014001038,
        421070014001067,
        421070013001005,
        421070013001010,
        421070013001014,
        421070013001028,
        421070009001109,
        421070009005052,
        421070014001046,
        421070013001099,
        421070013001023,
        421070014001039,
        421070011001029,
        421070014001048,
        421070014001064,
        421070014001051,
        421070009005053,
        421070014001043,
        421070013001016,
        421070013001003,
        421070014001057,
        421070013001026,
        421070014001040,
        421070014001045,
        421070014001054,
        421070014001044,
        421070014001066,
        421070014001042,
        421070013001006,
        421070013001011,
        421070013001002,
        421070011001028,
        421070013001015,
        421070013001001,
        421070013001024,
        421070013001004,
        421070014001087,
        421070014001049,
        421070014001080,
        421070013001007,
        421070014001050,
        421070013001013,
        421070009005051
    ],
    "zs:housing10":281,
    "zs:label":"Mount Pleasant",
    "zs:pop10":532
},
  "geometry": {"coordinates":[-76.36258599999999,40.698688],"type":"Point"}
}