{
  "type": "Feature",
  "properties": {
    "gn:admin1_code":"MD",
    "gn:admin2_code":"3.0",
    "gn:asciiname":"Norwich Acres",
    "gn:country_code":"US",
    "gn:dem":15,
    "gn:elevation":"5.0",
    "gn:feature_class":"P",
    "gn:feature_code":"PPL",
    "gn:name":"Norwich Acres",
    "gn:population":0,
    "gn:timezone":"America/New_York",
    "iso:country":"US",
    "wof:name":"Norwich Acres",
    "wof:placetype":"locality"
},
  "geometry": {"coordinates":[-76.50135,39.08955],"type":"Point"}
}