{
  "type": "Feature",
  "properties": {
    "iso:country":"US",
    "name:eng_x_preferred":[
        "Riverbend North 1"
    ],
    "wof:name":"Riverbend North 1",
    "wof:placetype":"neighbourhood",
    "wof:population":1100,
    "zs:area_m":613290.847284,
    "zs:blockids":[
        480850316554016,
        480850316253014,
        480850316253009,
        480850316543022,
        480850316554003,
        480850316543021,
        480850316543012,
        480850316554017,
        480850316554013,
        480850316253002,
        480850316554015,
        480850316253013,
        480850316543020,
        480850316554014,
        480850316554001,
        480850316253011,
        480850316554012,
        480850316554000,
        480850316252009,
        480850316554004,
        480850316554006,
        480850316252010,
        480850316554002,
        480850316252005,
        480850316253006,
        480850316543019
    ],
    "zs:housing10":383,
    "zs:label":"Riverbend North 1",
    "zs:pop10":1100
},
  "geometry": {"coordinates":[-96.77088000000001,33.033724],"type":"Point"}
}