{
  "type": "Feature",
  "properties": {
    "iso:country":"US",
    "name:arg_x_preferred":[
        "El Cerro"
    ],
    "name:cat_x_preferred":[
        "El Cerro"
    ],
    "name:ceb_x_preferred":[
        "El Cerro"
    ],
    "name:eng_x_preferred":[
        "El Cerro"
    ],
    "name:eus_x_preferred":[
        "El Cerro"
    ],
    "name:fra_x_preferred":[
        "El Cerro"
    ],
    "name:haw_x_preferred":[
        "El Cerro"
    ],
    "name:hun_x_preferred":[
        "El Cerro"
    ],
    "name:ina_x_preferred":[
        "El Cerro"
    ],
    "name:ita_x_preferred":[
        "El Cerro"
    ],
    "name:kaz_x_preferred":[
        "\u042d\u043b\u044c-\u0421\u0435\u0440\u0440\u043e"
    ],
    "name:msa_x_preferred":[
        "El Cerro"
    ],
    "name:nld_x_preferred":[
        "El Cerro"
    ],
    "name:oci_x_preferred":[
        "El Cerro"
    ],
    "name:pol_x_preferred":[
        "El Cerro"
    ],
    "name:por_x_preferred":[
        "El Cerro"
    ],
    "name:rus_x_preferred":[
        "\u042d\u043b\u044c-\u0421\u0435\u0440\u0440\u043e"
    ],
    "name:spa_x_preferred":[
        "El Cerro"
    ],
    "name:ukr_x_preferred":[
        "\u0415\u043b\u044c-\u0421\u0435\u0440\u0440\u043e"
    ],
    "name:vie_x_preferred":[
        "El Cerro"
    ],
    "name:war_x_preferred":[
        "El Cerro"
    ],
    "name:zho_x_preferred":[
        "\u57c3\u5c14\u585e\u7f57"
    ],
    "wof:name":"El Cerro",
    "wof:placetype":"neighbourhood",
    "wof:population":457,
    "zs:area_m":312815.546051,
    "zs:blockids":[
        120570043001001,
        120570043001002,
        120570043001004,
        120570043001003,
        120570042001008,
        120570043001000
    ],
    "zs:housing10":169,
    "zs:label":"El Cerro",
    "zs:pop10":457
},
  "geometry": {"coordinates":[-82.472599,27.961325],"type":"Point"}
}