{
  "type": "Feature",
  "properties": {
    "gn:admin1_code":"TN",
    "gn:admin2_code":"179",
    "gn:asciiname":"Meadowbrook Mobile Home Park",
    "gn:country_code":"US",
    "gn:dem":466,
    "gn:elevation":"460.0",
    "gn:feature_class":"P",
    "gn:feature_code":"PPL",
    "gn:name":"Meadowbrook Mobile Home Park",
    "gn:population":0,
    "gn:timezone":"America/New_York",
    "iso:country":"US",
    "wof:name":"Meadowbrook Mobile Home Park",
    "wof:placetype":"campus"
},
  "geometry": {"coordinates":[-82.29167,36.30722],"type":"Point"}
}