{
  "type": "Feature",
  "properties": {
    "gn:admin1_code":"NY",
    "gn:admin2_code":"9.0",
    "gn:admin3_code":"59509.0",
    "gn:asciiname":"Westons Mills",
    "gn:country_code":"US",
    "gn:dem":443,
    "gn:elevation":"439.0",
    "gn:feature_class":"P",
    "gn:feature_code":"PPL",
    "gn:name":"Westons Mills",
    "gn:population":1750,
    "gn:timezone":"America/New_York",
    "iso:country":"US",
    "name:eng_x_preferred":[
        "Westons Mills"
    ],
    "name:und_x_variant":[
        "Westonville",
        "Westons",
        "Weston's Mills",
        "Weston Mills"
    ],
    "wof:name":"Westons Mills",
    "wof:placetype":"locality",
    "wof:population":1750
},
  "geometry": {"coordinates":[-78.37724,42.06229],"type":"Point"}
}