{
  "type": "Feature",
  "properties": {
    "gn:admin1_code":"ME",
    "gn:admin2_code":"5.0",
    "gn:admin3_code":"48820.0",
    "gn:asciiname":"Foggs Corner",
    "gn:country_code":"US",
    "gn:dem":58,
    "gn:elevation":"57.0",
    "gn:feature_class":"P",
    "gn:feature_code":"PPL",
    "gn:name":"Foggs Corner",
    "gn:population":0,
    "gn:timezone":"America/New_York",
    "iso:country":"US",
    "name:eng_x_preferred":[
        "Foggs Corner"
    ],
    "name:und_x_variant":[
        "Fogg's Corners"
    ],
    "wof:name":"Foggs Corner",
    "wof:placetype":"locality"
},
  "geometry": {"coordinates":[-70.24783000000001,43.9373],"type":"Point"}
}