{
  "type": "Feature",
  "properties": {
    "gn:admin1_code":"WA",
    "gn:admin2_code":"5.0",
    "gn:asciiname":"Ethel",
    "gn:country_code":"US",
    "gn:dem":183,
    "gn:elevation":"180.0",
    "gn:feature_class":"P",
    "gn:feature_code":"PPL",
    "gn:name":"Ethel",
    "gn:population":0,
    "gn:timezone":"America/Los_Angeles",
    "iso:country":"US",
    "name:ces_x_preferred":[
        "Ethel"
    ],
    "name:deu_x_preferred":[
        "Ethel"
    ],
    "name:isl_x_preferred":[
        "Ethel"
    ],
    "name:ita_x_preferred":[
        "Ethel"
    ],
    "name:nor_x_preferred":[
        "Ethel"
    ],
    "name:swe_x_preferred":[
        "Ethel"
    ],
    "wof:name":"Ethel",
    "wof:placetype":"locality"
},
  "geometry": {"coordinates":[-119.59808999999998,46.58041],"type":"Point"}
}