{
  "type": "Feature",
  "properties": {
    "gn:admin1_code":"MT",
    "gn:admin2_code":"11.0",
    "gn:asciiname":"Capitol",
    "gn:country_code":"US",
    "gn:dem":966,
    "gn:elevation":"970.0",
    "gn:feature_class":"P",
    "gn:feature_code":"PPL",
    "gn:name":"Capitol",
    "gn:population":0,
    "gn:timezone":"America/Denver",
    "iso:country":"US",
    "name:por_x_preferred":[
        "Capitol"
    ],
    "wof:name":"Capitol",
    "wof:placetype":"locality"
},
  "geometry": {"coordinates":[-104.06549,45.4361],"type":"Point"}
}