{
  "type": "Feature",
  "properties": {
    "gn:admin1_code":"MN",
    "gn:admin2_code":"71.0",
    "gn:admin3_code":"47131.0",
    "gn:asciiname":"Forest Grove",
    "gn:country_code":"US",
    "gn:dem":415,
    "gn:elevation":"415.0",
    "gn:feature_class":"P",
    "gn:feature_code":"PPL",
    "gn:name":"Forest Grove",
    "gn:population":0,
    "gn:timezone":"America/Chicago",
    "iso:country":"US",
    "wof:name":"Forest Grove",
    "wof:placetype":"locality"
},
  "geometry": {"coordinates":[-94.23133,47.97662],"type":"Point"}
}