{
  "type": "Feature",
  "properties": {
    "gn:admin1_code":"VA",
    "gn:admin2_code":"770",
    "gn:asciiname":"Westwood",
    "gn:country_code":"US",
    "gn:dem":331,
    "gn:elevation":"331.0",
    "gn:feature_class":"P",
    "gn:feature_code":"PPL",
    "gn:name":"Westwood",
    "gn:population":0,
    "gn:timezone":"America/New_York",
    "iso:country":"US",
    "name:bar_x_preferred":[
        "Westwood"
    ],
    "name:cat_x_preferred":[
        "Westwood"
    ],
    "name:ceb_x_preferred":[
        "Westwood"
    ],
    "name:ces_x_preferred":[
        "Westwood"
    ],
    "name:deu_x_preferred":[
        "Westwood"
    ],
    "name:est_x_preferred":[
        "Westwood"
    ],
    "name:fin_x_preferred":[
        "Westwood"
    ],
    "name:fra_x_preferred":[
        "Westwood"
    ],
    "name:ita_x_preferred":[
        "Westwood"
    ],
    "name:jpn_x_preferred":[
        "\u30a6\u30a7\u30b9\u30c8\u30a6\u30c3\u30c9"
    ],
    "name:kor_x_preferred":[
        "\uc6e8\uc2a4\ud2b8\uc6b0\ub4dc"
    ],
    "name:nld_x_preferred":[
        "Westwood"
    ],
    "name:pol_x_preferred":[
        "Westwood"
    ],
    "name:por_x_preferred":[
        "Westwood"
    ],
    "name:rus_x_preferred":[
        "\u0423\u044d\u0441\u0442\u0432\u0443\u0434"
    ],
    "name:spa_x_preferred":[
        "Westwood"
    ],
    "name:srp_x_preferred":[
        "\u0412\u0435\u0441\u0442\u0432\u0443\u0434"
    ],
    "name:swa_x_preferred":[
        "Westwood"
    ],
    "name:swe_x_preferred":[
        "Westwood"
    ],
    "name:tur_x_preferred":[
        "Westwood"
    ],
    "name:ukr_x_preferred":[
        "\u0412\u0435\u0441\u0442\u0432\u0443\u0434"
    ],
    "name:urd_x_preferred":[
        "\u0648\u06cc\u0633\u0679\u0648\u0648\u0688"
    ],
    "name:vol_x_preferred":[
        "Westwood"
    ],
    "wof:name":"Westwood",
    "wof:placetype":"locality"
},
  "geometry": {"coordinates":[-79.99670999999999,37.2793],"type":"Point"}
}