{
  "type": "Feature",
  "properties": {
    "iso:country":"US",
    "name:ceb_x_preferred":[
        "Polonia"
    ],
    "name:deu_x_preferred":[
        "Polonia"
    ],
    "name:epo_x_preferred":[
        "Polonia"
    ],
    "name:fra_x_preferred":[
        "Polonia"
    ],
    "name:ita_x_preferred":[
        "Polonia"
    ],
    "name:jpn_x_preferred":[
        "\u30dd\u30ed\u30cb\u30a2"
    ],
    "name:nld_x_preferred":[
        "Polonia"
    ],
    "name:pol_x_preferred":[
        "Polonia"
    ],
    "name:ron_x_preferred":[
        "Polonia"
    ],
    "name:rus_x_preferred":[
        "\u041f\u043e\u043b\u043e\u043d\u0438\u044f"
    ],
    "name:spa_x_preferred":[
        "Polonia"
    ],
    "name:swe_x_preferred":[
        "Polonia"
    ],
    "name:ukr_x_preferred":[
        "\u041f\u043e\u043b\u043e\u043d\u0456\u044f"
    ],
    "wof:name":"Polonia",
    "wof:placetype":"neighbourhood"
},
  "geometry": {"coordinates":[-78.83643784689626,42.89381935272615],"type":"Point"}
}