{
  "type": "Feature",
  "properties": {
    "iso:country":"US",
    "name:ceb_x_preferred":[
        "Springhill"
    ],
    "name:deu_x_preferred":[
        "Springhill"
    ],
    "name:eng_x_preferred":[
        "Springhill"
    ],
    "name:fra_x_preferred":[
        "Springhill"
    ],
    "name:ita_x_preferred":[
        "Springhill"
    ],
    "name:nld_x_preferred":[
        "Springhill"
    ],
    "name:pol_x_preferred":[
        "Springhill"
    ],
    "name:spa_x_preferred":[
        "Springhill"
    ],
    "name:srp_x_preferred":[
        "\u0421\u043f\u0440\u0438\u043d\u0433\u0445\u0438\u043b"
    ],
    "name:swe_x_preferred":[
        "Springhill"
    ],
    "wof:name":"Springhill",
    "wof:placetype":"neighbourhood",
    "wof:population":340,
    "zs:area_m":6148160.425128,
    "zs:blockids":[
        450790103072050,
        450790103062007,
        450790103062004,
        450790103072075,
        450790103072065,
        450790103072048,
        450790103062003,
        450790103072077,
        450790103072054,
        450790103072076
    ],
    "zs:housing10":123,
    "zs:label":"Springhill",
    "zs:pop10":340
},
  "geometry": {"coordinates":[-81.277823,34.179536],"type":"Point"}
}