{
  "type": "Feature",
  "properties": {
    "gn:admin1_code":"FL",
    "gn:admin2_code":"57",
    "gn:asciiname":"Valrico Heights Estates",
    "gn:country_code":"US",
    "gn:dem":33,
    "gn:elevation":"25.0",
    "gn:feature_class":"P",
    "gn:feature_code":"PPL",
    "gn:name":"Valrico Heights Estates",
    "gn:population":0,
    "gn:timezone":"America/New_York",
    "iso:country":"US",
    "wof:name":"Valrico Heights Estates",
    "wof:placetype":"locality"
},
  "geometry": {"coordinates":[-82.2504,27.9498],"type":"Point"}
}