{
  "type": "Feature",
  "properties": {
    "iso:country":"US",
    "name:ast_x_preferred":[
        "Bonnie Comley"
    ],
    "name:cat_x_preferred":[
        "Bonnie Comley"
    ],
    "name:dan_x_preferred":[
        "Bonnie Comley"
    ],
    "name:deu_x_preferred":[
        "Bonnie Comley"
    ],
    "name:eng_x_preferred":[
        "Bonnie Lane"
    ],
    "name:eng_x_variant":[
        "Bonnie Comley"
    ],
    "name:eus_x_preferred":[
        "Bonnie Comley"
    ],
    "name:fin_x_preferred":[
        "Bonnie Comley"
    ],
    "name:fra_x_preferred":[
        "Bonnie Comley"
    ],
    "name:gle_x_preferred":[
        "Bonnie Comley"
    ],
    "name:nld_x_preferred":[
        "Bonnie Comley"
    ],
    "name:nno_x_preferred":[
        "Bonnie Comley"
    ],
    "name:nob_x_preferred":[
        "Bonnie Comley"
    ],
    "name:pap_x_preferred":[
        "Bonnie Comley"
    ],
    "name:por_x_preferred":[
        "Bonnie Comley"
    ],
    "name:rus_x_preferred":[
        "\u0411\u043e\u043d\u043d\u0438 \u041a\u043e\u043c\u043b\u0438"
    ],
    "name:slv_x_preferred":[
        "Bonnie Comley"
    ],
    "name:spa_x_preferred":[
        "Bonnie Comley"
    ],
    "name:sqi_x_preferred":[
        "Bonnie Comley"
    ],
    "name:swe_x_preferred":[
        "Bonnie Comley"
    ],
    "name:yor_x_preferred":[
        "Bonnie Comley"
    ],
    "wd:wordcount":536,
    "wof:name":"Bonnie Lane",
    "wof:placetype":"neighbourhood",
    "wof:population":316,
    "zs:area_m":101055.409748,
    "zs:blockids":[
        490572109002008,
        490572109002007,
        490572109002003,
        490572109002004
    ],
    "zs:housing10":103,
    "zs:label":"Bonnie Lane",
    "zs:pop10":316
},
  "geometry": {"coordinates":[-111.95801299999999,41.18448],"type":"Point"}
}