{
  "type": "Feature",
  "properties": {
    "gn:admin1_code":"SC",
    "gn:admin2_code":"43.0",
    "gn:asciiname":"Live Oaks",
    "gn:country_code":"US",
    "gn:dem":1,
    "gn:elevation":"6.0",
    "gn:feature_class":"P",
    "gn:feature_code":"PPL",
    "gn:name":"Live Oaks",
    "gn:population":0,
    "gn:timezone":"America/New_York",
    "iso:country":"US",
    "wof:name":"Live Oaks",
    "wof:placetype":"locality"
},
  "geometry": {"coordinates":[-79.05393000000002,33.546],"type":"Point"}
}