{
  "type": "Feature",
  "properties": {
    "gn:admin1_code":"IL",
    "gn:admin2_code":"31.0",
    "gn:admin3_code":"53676.0",
    "gn:asciiname":"Fair Oaks",
    "gn:country_code":"US",
    "gn:dem":196,
    "gn:elevation":"193.0",
    "gn:feature_class":"P",
    "gn:feature_code":"PPL",
    "gn:name":"Fair Oaks",
    "gn:population":0,
    "gn:timezone":"America/Chicago",
    "iso:country":"US",
    "name:ceb_x_preferred":[
        "Fair Oaks"
    ],
    "name:deu_x_preferred":[
        "Fair Oaks"
    ],
    "name:hun_x_preferred":[
        "Fair Oaks"
    ],
    "name:ita_x_preferred":[
        "Fair Oaks"
    ],
    "name:nld_x_preferred":[
        "Fair Oaks"
    ],
    "name:pol_x_preferred":[
        "Fair Oaks"
    ],
    "name:por_x_preferred":[
        "Fair Oaks"
    ],
    "name:srp_x_preferred":[
        "\u0424\u0435\u0440 \u041e\u0443\u043a\u0441"
    ],
    "name:ukr_x_preferred":[
        "\u0424\u0435\u0439\u0440-\u041e\u0443\u043a\u0441"
    ],
    "name:vol_x_preferred":[
        "Fair Oaks"
    ],
    "wof:name":"Fair Oaks",
    "wof:placetype":"locality"
},
  "geometry": {"coordinates":[-87.79222,42.14028],"type":"Point"}
}