{
  "type": "Feature",
  "properties": {
    "gn:admin1_code":"ID",
    "gn:admin2_code":"51",
    "gn:asciiname":"Rudy",
    "gn:country_code":"US",
    "gn:dem":1497,
    "gn:elevation":"1499.0",
    "gn:feature_class":"P",
    "gn:feature_code":"PPL",
    "gn:name":"Rudy",
    "gn:population":0,
    "gn:timezone":"America/Boise",
    "iso:country":"US",
    "name:eng_x_preferred":[
        "Rudy"
    ],
    "name:nno_x_preferred":[
        "Rudi"
    ],
    "name:nor_x_preferred":[
        "Rudi"
    ],
    "name:slv_x_preferred":[
        "Rudi"
    ],
    "name:und_x_variant":[
        "Clark"
    ],
    "wof:name":"Rudy",
    "wof:placetype":"locality"
},
  "geometry": {"coordinates":[-111.83329999999999,43.65658],"type":"Point"}
}