{
  "type": "Feature",
  "properties": {
    "gn:admin1_code":"OH",
    "gn:admin2_code":"39.0",
    "gn:admin3_code":"56014.0",
    "gn:asciiname":"Millers Rolling Hills Estates",
    "gn:country_code":"US",
    "gn:dem":214,
    "gn:elevation":"214.0",
    "gn:feature_class":"P",
    "gn:feature_code":"PPL",
    "gn:name":"Millers Rolling Hills Estates",
    "gn:population":0,
    "gn:timezone":"America/New_York",
    "iso:country":"US",
    "wof:name":"Millers Rolling Hills Estates",
    "wof:placetype":"locality"
},
  "geometry": {"coordinates":[-84.37583000000002,41.30361],"type":"Point"}
}