{
  "type": "Feature",
  "properties": {
    "gn:admin1_code":"FL",
    "gn:admin2_code":"111.0",
    "gn:asciiname":"La Buona Vita Mobile Home Park",
    "gn:country_code":"US",
    "gn:dem":9,
    "gn:elevation":"2.0",
    "gn:feature_class":"P",
    "gn:feature_code":"PPL",
    "gn:name":"La Buona Vita Mobile Home Park",
    "gn:population":0,
    "gn:timezone":"America/New_York",
    "iso:country":"US",
    "wof:name":"La Buona Vita Mobile Home Park",
    "wof:placetype":"campus"
},
  "geometry": {"coordinates":[-80.3158,27.3104],"type":"Point"}
}