{
  "type": "Feature",
  "properties": {
    "gn:admin1_code":"KY",
    "gn:admin2_code":"141",
    "gn:asciiname":"Keysburg",
    "gn:country_code":"US",
    "gn:dem":170,
    "gn:elevation":"170.0",
    "gn:feature_class":"P",
    "gn:feature_code":"PPL",
    "gn:name":"Keysburg",
    "gn:population":0,
    "gn:timezone":"America/Chicago",
    "iso:country":"US",
    "wof:name":"Keysburg",
    "wof:placetype":"locality"
},
  "geometry": {"coordinates":[-87.00805,36.65115],"type":"Point"}
}