{
  "type": "Feature",
  "properties": {
    "gn:gn_country":"US",
    "gn:gn_fcode":"PPL",
    "gn:gn_pop":0,
    "iso:country":"US",
    "name:ara_x_preferred":[
        "\u062c\u0628\u0644 \u0646\u064a\u0628\u0648"
    ],
    "name:cat_x_preferred":[
        "Mont Nebo"
    ],
    "name:ceb_x_preferred":[
        "Jabal Nab\u0101"
    ],
    "name:cym_x_preferred":[
        "Mynydd Nebo"
    ],
    "name:deu_x_preferred":[
        "Nebo"
    ],
    "name:epo_x_preferred":[
        "Monto Nebo"
    ],
    "name:eus_x_preferred":[
        "Nebo"
    ],
    "name:fas_x_preferred":[
        "\u06a9\u0648\u0647 \u0646\u0628\u0648"
    ],
    "name:fra_x_preferred":[
        "Mont N\u00e9bo"
    ],
    "name:heb_x_preferred":[
        "\u05d4\u05e8 \u05e0\u05d1\u05d5"
    ],
    "name:hun_x_preferred":[
        "N\u00e9b\u00f3-hegy"
    ],
    "name:hye_x_preferred":[
        "\u0546\u0565\u0562\u0578"
    ],
    "name:ind_x_preferred":[
        "Gunung Nebo"
    ],
    "name:ita_x_preferred":[
        "Monte Nebo"
    ],
    "name:jav_x_preferred":[
        "Gunung N\u00e9bo"
    ],
    "name:jpn_x_preferred":[
        "\u30cd\u30dc\u5c71"
    ],
    "name:lat_x_preferred":[
        "Mons Nabo"
    ],
    "name:lit_x_preferred":[
        "Nebo kalnas"
    ],
    "name:nld_x_preferred":[
        "Neboberg"
    ],
    "name:nno_x_preferred":[
        "Nebo"
    ],
    "name:pol_x_preferred":[
        "G\u00f3ra Nebo"
    ],
    "name:por_x_preferred":[
        "Monte Nebo"
    ],
    "name:rus_x_preferred":[
        "\u041d\u0435\u0432\u043e"
    ],
    "name:spa_x_preferred":[
        "Monte Nebo"
    ],
    "name:swe_x_preferred":[
        "Nebo"
    ],
    "name:tur_x_preferred":[
        "Nibu Da\u011f\u0131"
    ],
    "name:urd_x_preferred":[
        "\u062c\u0628\u0644 \u0646\u06cc\u0628\u0648"
    ],
    "name:zho_x_preferred":[
        "\u5c3c\u6ce2\u5c71"
    ],
    "qs_pg:aaroncc":"US",
    "qs_pg:gn_country":"US",
    "qs_pg:gn_fcode":"PPL",
    "qs_pg:gn_pop":0,
    "qs_pg:name":"Mount Nebo",
    "qs_pg:name_adm0":"United States",
    "qs_pg:name_adm1":"Arkansas",
    "qs_pg:photos":845,
    "qs_pg:photos_1k":171,
    "qs_pg:photos_9k":4,
    "qs_pg:photos_9r":6,
    "qs_pg:photos_all":845,
    "qs_pg:photos_sr":9,
    "qs_pg:pop_sr":0,
    "qs_pg:qs_pg_placetype":"locality",
    "qs_pg:qs_pg_placetype_gp":"Town",
    "qs_pg:woe_adm0":23424977,
    "woe:adm0_id":23424977,
    "woe:name_adm0":"United States",
    "woe:name_adm1":"Arkansas",
    "woe:placetype":"Town",
    "wof:name":"Mount Nebo",
    "wof:placetype":"locality"
},
  "geometry": {"coordinates":[-93.25239999999999,35.21897],"type":"Point"}
}