{
  "type": "Feature",
  "properties": {
    "iso:country":"US",
    "name:eng_x_preferred":[
        "Beacon Ridge"
    ],
    "wof:name":"Beacon Ridge",
    "wof:placetype":"neighbourhood",
    "wof:population":659,
    "zs:area_m":948175.913425,
    "zs:blockids":[
        60133400026022,
        60133400026028,
        60133400026015,
        60133400026025,
        60133400026030,
        60133400026029,
        60133400026018,
        60133400026014,
        60133400026021,
        60133400026017,
        60133400026031,
        60133400026034,
        60133400026032,
        60133400026020,
        60133400026016,
        60133400024003,
        60133400026033,
        60133400024001,
        60133400026019
    ],
    "zs:housing10":348,
    "zs:label":"Beacon Ridge",
    "zs:pop10":659
},
  "geometry": {"coordinates":[-122.08915500000001,37.913625],"type":"Point"}
}