{
  "type": "Feature",
  "properties": {
    "gn:admin1_code":"NY",
    "gn:admin2_code":"63.0",
    "gn:admin3_code":"50232.0",
    "gn:asciiname":"Ridgeview Homes Mobile Home Park",
    "gn:country_code":"US",
    "gn:dem":116,
    "gn:elevation":"117.0",
    "gn:feature_class":"P",
    "gn:feature_code":"PPL",
    "gn:name":"Ridgeview Homes Mobile Home Park",
    "gn:population":0,
    "gn:timezone":"America/New_York",
    "iso:country":"US",
    "wof:name":"Ridgeview Homes Mobile Home Park",
    "wof:placetype":"campus"
},
  "geometry": {"coordinates":[-78.67962,43.22388],"type":"Point"}
}