{
  "type": "Feature",
  "properties": {
    "gn:admin1_code":"FL",
    "gn:admin2_code":"57",
    "gn:asciiname":"Booker T Park",
    "gn:country_code":"US",
    "gn:dem":21,
    "gn:elevation":"16.0",
    "gn:feature_class":"P",
    "gn:feature_code":"PPL",
    "gn:name":"Booker T Park",
    "gn:population":0,
    "gn:timezone":"America/New_York",
    "iso:country":"US",
    "wof:name":"Booker T Park",
    "wof:placetype":"locality"
},
  "geometry": {"coordinates":[-82.41500000000001,27.986],"type":"Point"}
}