{
  "type": "Feature",
  "properties": {
    "gn:admin1_code":"OH",
    "gn:admin2_code":"89.0",
    "gn:admin3_code":"46508.0",
    "gn:asciiname":"Ben",
    "gn:country_code":"US",
    "gn:dem":284,
    "gn:elevation":"282.0",
    "gn:feature_class":"P",
    "gn:feature_code":"PPL",
    "gn:name":"Ben",
    "gn:population":0,
    "gn:timezone":"America/New_York",
    "iso:country":"US",
    "name:ara_x_preferred":[
        "\u0628\u064a\u0646"
    ],
    "name:aze_x_preferred":[
        "Ben"
    ],
    "name:bre_x_preferred":[
        "Ben"
    ],
    "name:deu_x_preferred":[
        "Ben"
    ],
    "name:fin_x_preferred":[
        "Ben"
    ],
    "name:hrv_x_preferred":[
        "Ben"
    ],
    "name:isl_x_preferred":[
        "Ben"
    ],
    "name:ita_x_preferred":[
        "Ben"
    ],
    "name:nld_x_preferred":[
        "Ben"
    ],
    "name:nno_x_preferred":[
        "Ben"
    ],
    "name:nor_x_preferred":[
        "Ben"
    ],
    "name:rus_x_preferred":[
        "\u0411\u0435\u043d"
    ],
    "name:vie_x_preferred":[
        "Ben"
    ],
    "wof:name":"Ben",
    "wof:placetype":"locality"
},
  "geometry": {"coordinates":[-82.30875999999998,40.09173],"type":"Point"}
}