{
  "type": "Feature",
  "properties": {
    "gn:admin1_code":"LA",
    "gn:admin2_code":"81.0",
    "gn:asciiname":"Liberty",
    "gn:country_code":"US",
    "gn:dem":62,
    "gn:elevation":"61.0",
    "gn:feature_class":"P",
    "gn:feature_code":"PPL",
    "gn:name":"Liberty",
    "gn:population":0,
    "gn:timezone":"America/Chicago",
    "iso:country":"US",
    "name:eng_x_preferred":[
        "Liberty"
    ],
    "name:fas_x_preferred":[
        "\u0644\u06cc\u0628\u0631\u062a\u06cc \u0644\u0648\u0626\u06cc\u0632\u06cc\u0627\u0646\u0627"
    ],
    "name:und_x_variant":[
        "Clear"
    ],
    "name:urd_x_preferred":[
        "\u0644\u0628\u0631\u0679\u06cc"
    ],
    "wof:name":"Liberty",
    "wof:placetype":"locality"
},
  "geometry": {"coordinates":[-93.19739,32.07266],"type":"Point"}
}