{
  "type": "Feature",
  "properties": {
    "gn:admin1_code":"MN",
    "gn:admin2_code":"71.0",
    "gn:admin3_code":"47352.0",
    "gn:asciiname":"Fairland",
    "gn:country_code":"US",
    "gn:dem":348,
    "gn:elevation":"347.0",
    "gn:feature_class":"P",
    "gn:feature_code":"PPL",
    "gn:name":"Fairland",
    "gn:population":0,
    "gn:timezone":"America/Chicago",
    "iso:country":"US",
    "wof:name":"Fairland",
    "wof:placetype":"locality"
},
  "geometry": {"coordinates":[-94.15464,48.46746],"type":"Point"}
}