{
  "type": "Feature",
  "properties": {
    "gn:admin1_code":"AL",
    "gn:admin2_code":"21",
    "gn:asciiname":"Ocampo",
    "gn:country_code":"US",
    "gn:dem":171,
    "gn:elevation":"170.0",
    "gn:feature_class":"P",
    "gn:feature_code":"PPL",
    "gn:name":"Ocampo",
    "gn:population":0,
    "gn:timezone":"America/Chicago",
    "iso:country":"US",
    "name:cat_x_preferred":[
        "Ocampo"
    ],
    "name:ceb_x_preferred":[
        "Ocampo"
    ],
    "name:deu_x_preferred":[
        "Ocampo"
    ],
    "name:epo_x_preferred":[
        "Ocampo"
    ],
    "name:fra_x_preferred":[
        "Ocampo"
    ],
    "name:ita_x_preferred":[
        "Ocampo"
    ],
    "name:nds_x_preferred":[
        "Ocampo"
    ],
    "name:por_x_preferred":[
        "Ocampo"
    ],
    "name:rus_x_preferred":[
        "\u041e\u043a\u0430\u043c\u043f\u043e"
    ],
    "name:sco_x_preferred":[
        "Ocampo"
    ],
    "name:spa_x_preferred":[
        "Ocampo"
    ],
    "name:swe_x_preferred":[
        "Ocampo"
    ],
    "name:ukr_x_preferred":[
        "\u041e\u043a\u0430\u043c\u043f\u043e"
    ],
    "wof:name":"Ocampo",
    "wof:placetype":"locality"
},
  "geometry": {"coordinates":[-86.7636,33.03151],"type":"Point"}
}