{
  "type": "Feature",
  "properties": {
    "iso:country":"US",
    "qs_pg:aaroncc":"US",
    "qs_pg:name":"Roseville East",
    "qs_pg:name_adm0":"United States",
    "qs_pg:name_adm1":"California",
    "qs_pg:photos":248,
    "qs_pg:photos_1k":50,
    "qs_pg:photos_9k":1,
    "qs_pg:photos_9r":4,
    "qs_pg:photos_all":248,
    "qs_pg:photos_sr":4,
    "qs_pg:pop_sr":0,
    "qs_pg:qs_pg_placetype":"locality",
    "qs_pg:qs_pg_placetype_gp":"Town",
    "qs_pg:woe_adm0":23424977,
    "woe:adm0_id":23424977,
    "woe:name_adm0":"United States",
    "woe:name_adm1":"California",
    "woe:placetype":"Town",
    "wof:name":"Roseville East",
    "wof:placetype":"locality"
},
  "geometry": {"coordinates":[-121.2503095,38.75676],"type":"Point"}
}