{
  "type": "Feature",
  "properties": {
    "gn:admin1_code":"MD",
    "gn:admin2_code":"3.0",
    "gn:asciiname":"Villa Verdi",
    "gn:country_code":"US",
    "gn:dem":54,
    "gn:elevation":"53.0",
    "gn:feature_class":"P",
    "gn:feature_code":"PPL",
    "gn:name":"Villa Verdi",
    "gn:population":0,
    "gn:timezone":"America/New_York",
    "iso:country":"US",
    "name:fra_x_preferred":[
        "Villa Verdi"
    ],
    "name:ita_x_preferred":[
        "Villa Verdi"
    ],
    "wof:name":"Villa Verdi",
    "wof:placetype":"locality"
},
  "geometry": {"coordinates":[-76.6533,39.08539],"type":"Point"}
}