{
  "type": "Feature",
  "properties": {
    "gn:admin1_code":"MS",
    "gn:admin2_code":"7.0",
    "gn:asciiname":"East Macedonia",
    "gn:country_code":"US",
    "gn:dem":137,
    "gn:elevation":"134.0",
    "gn:feature_class":"P",
    "gn:feature_code":"PPL",
    "gn:name":"East Macedonia",
    "gn:population":0,
    "gn:timezone":"America/Chicago",
    "iso:country":"US",
    "wof:name":"East Macedonia",
    "wof:placetype":"locality"
},
  "geometry": {"coordinates":[-89.3459,33.01568],"type":"Point"}
}