{
  "type": "Feature",
  "properties": {
    "gn:admin1_code":"KY",
    "gn:admin2_code":"53",
    "gn:asciiname":"Shipley",
    "gn:country_code":"US",
    "gn:dem":307,
    "gn:elevation":"305.0",
    "gn:feature_class":"P",
    "gn:feature_code":"PPL",
    "gn:name":"Shipley",
    "gn:population":0,
    "gn:timezone":"America/Chicago",
    "iso:country":"US",
    "name:ceb_x_preferred":[
        "Shipley"
    ],
    "name:deu_x_preferred":[
        "Shipley"
    ],
    "name:fra_x_preferred":[
        "Shipley"
    ],
    "name:ita_x_preferred":[
        "Shipley"
    ],
    "name:nld_x_preferred":[
        "Shipley"
    ],
    "name:pol_x_preferred":[
        "Shipley"
    ],
    "name:swe_x_preferred":[
        "Shipley"
    ],
    "wof:name":"Shipley",
    "wof:placetype":"locality"
},
  "geometry": {"coordinates":[-85.21774000000001,36.66729],"type":"Point"}
}