{
  "type": "Feature",
  "properties": {
    "gn:admin1_code":"MT",
    "gn:admin2_code":"17.0",
    "gn:asciiname":"Beebe",
    "gn:country_code":"US",
    "gn:dem":827,
    "gn:elevation":"829.0",
    "gn:feature_class":"P",
    "gn:feature_code":"PPL",
    "gn:name":"Beebe",
    "gn:population":0,
    "gn:timezone":"America/Denver",
    "iso:country":"US",
    "name:deu_x_preferred":[
        "Beebe"
    ],
    "name:glg_x_preferred":[
        "Beebe"
    ],
    "name:ita_x_preferred":[
        "Beebe"
    ],
    "name:por_x_preferred":[
        "Beebe"
    ],
    "name:spa_x_preferred":[
        "Beebe"
    ],
    "wof:name":"Beebe",
    "wof:placetype":"locality"
},
  "geometry": {"coordinates":[-105.56943,46.05528],"type":"Point"}
}