{
  "type": "Feature",
  "properties": {
    "gn:admin1_code":"MN",
    "gn:admin2_code":"137",
    "gn:admin3_code":"11386.0",
    "gn:asciiname":"Spruce Shadows Mobile Home Park",
    "gn:country_code":"US",
    "gn:dem":478,
    "gn:elevation":"479.0",
    "gn:feature_class":"P",
    "gn:feature_code":"PPL",
    "gn:name":"Spruce Shadows Mobile Home Park",
    "gn:population":0,
    "gn:timezone":"America/Chicago",
    "iso:country":"US",
    "wof:name":"Spruce Shadows Mobile Home Park",
    "wof:placetype":"campus"
},
  "geometry": {"coordinates":[-92.89167,47.48833],"type":"Point"}
}