{
  "type": "Feature",
  "properties": {
    "gn:country":"US",
    "gn:fcode":"PPL",
    "gn:population":0,
    "iso:country":"US",
    "name:azb_x_preferred":[
        "\u0631\u06cc\u062f\u0627\u0644"
    ],
    "name:ceb_x_preferred":[
        "Rydal"
    ],
    "name:eng_x_preferred":[
        "Rydal"
    ],
    "name:fas_x_preferred":[
        "\u0631\u0627\u06cc\u062f\u0644"
    ],
    "name:fra_x_preferred":[
        "Rydal"
    ],
    "name:zho_x_preferred":[
        "\u8cf4\u5fb7\u723e"
    ],
    "qs_pg:aaroncc":"US",
    "qs_pg:gn_country":"US",
    "qs_pg:gn_fcode":"PPL",
    "qs_pg:gn_pop":0,
    "qs_pg:name":"Rydal",
    "qs_pg:name_adm0":"United States",
    "qs_pg:name_adm1":"Georgia",
    "qs_pg:photos":27,
    "qs_pg:photos_1k":5,
    "qs_pg:photos_9k":1,
    "qs_pg:photos_9r":2,
    "qs_pg:photos_all":27,
    "qs_pg:photos_sr":2,
    "qs_pg:pop_sr":0,
    "qs_pg:qs_pg_placetype":"locality",
    "qs_pg:qs_pg_placetype_gp":"Town",
    "qs_pg:woe_adm0":23424977,
    "woe:adm0_id":23424977,
    "woe:name_adm0":"United States",
    "woe:name_adm1":"Georgia",
    "woe:placetype":"Town",
    "wof:name":"Rydal",
    "wof:placetype":"locality",
    "wof:population":4087
},
  "geometry": {"coordinates":[-84.71549,34.33537],"type":"Point"}
}