{
  "type": "Feature",
  "properties": {
    "gn:admin1_code":"TX",
    "gn:admin2_code":"427.0",
    "gn:asciiname":"Rivereno Colonia",
    "gn:country_code":"US",
    "gn:dem":71,
    "gn:elevation":"71.0",
    "gn:feature_class":"P",
    "gn:feature_code":"PPL",
    "gn:name":"Rivereno Colonia",
    "gn:population":0,
    "gn:timezone":"America/Chicago",
    "iso:country":"US",
    "name:eng_x_preferred":[
        "Rivereno Colonia"
    ],
    "name:und_x_variant":[
        "Rivereno Subdivision Colonia"
    ],
    "wof:name":"Rivereno Colonia",
    "wof:placetype":"locality"
},
  "geometry": {"coordinates":[-98.6403,26.30646],"type":"Point"}
}