{
  "type": "Feature",
  "properties": {
    "gn:admin1_code":"MN",
    "gn:admin2_code":"141.0",
    "gn:admin3_code":"5752.0",
    "gn:asciiname":"Big Lake Estates",
    "gn:country_code":"US",
    "gn:dem":281,
    "gn:elevation":"284.0",
    "gn:feature_class":"P",
    "gn:feature_code":"PPL",
    "gn:name":"Big Lake Estates",
    "gn:population":0,
    "gn:timezone":"America/Chicago",
    "iso:country":"US",
    "wof:name":"Big Lake Estates",
    "wof:placetype":"locality"
},
  "geometry": {"coordinates":[-93.74444,45.32639],"type":"Point"}
}