{
  "type": "Feature",
  "properties": {
    "gn:admin1_code":"NE",
    "gn:admin2_code":"161.0",
    "gn:asciiname":"Antioch",
    "gn:country_code":"US",
    "gn:dem":1183,
    "gn:elevation":"1183.0",
    "gn:feature_class":"P",
    "gn:feature_code":"PPL",
    "gn:name":"Antioch",
    "gn:population":0,
    "gn:timezone":"America/Denver",
    "iso:country":"US",
    "wof:name":"Antioch",
    "wof:placetype":"locality"
},
  "geometry": {"coordinates":[-102.58214,42.06831],"type":"Point"}
}