{
  "type": "Feature",
  "properties": {
    "gn:admin1_code":"WA",
    "gn:admin2_code":"35.0",
    "gn:asciiname":"Carrington Mobile Home Park",
    "gn:country_code":"US",
    "gn:dem":82,
    "gn:elevation":"77.0",
    "gn:feature_class":"P",
    "gn:feature_code":"PPL",
    "gn:name":"Carrington Mobile Home Park",
    "gn:population":0,
    "gn:timezone":"America/Los_Angeles",
    "iso:country":"US",
    "wof:name":"Carrington Mobile Home Park",
    "wof:placetype":"campus"
},
  "geometry": {"coordinates":[-122.69582,47.57737],"type":"Point"}
}