{
  "type": "Feature",
  "properties": {
    "gn:admin1_code":"LA",
    "gn:admin2_code":"55.0",
    "gn:asciiname":"Conques Mobile Home Park",
    "gn:country_code":"US",
    "gn:dem":18,
    "gn:elevation":"13.0",
    "gn:feature_class":"P",
    "gn:feature_code":"PPL",
    "gn:name":"Conques Mobile Home Park",
    "gn:population":0,
    "gn:timezone":"America/Chicago",
    "iso:country":"US",
    "wof:name":"Conques Mobile Home Park",
    "wof:placetype":"campus"
},
  "geometry": {"coordinates":[-92.04801999999999,30.28392],"type":"Point"}
}