{
  "type": "Feature",
  "properties": {
    "iso:country":"US",
    "name:eng_x_preferred":[
        "East Delavan"
    ],
    "wof:name":"East Delavan",
    "wof:placetype":"neighbourhood",
    "wof:population":45,
    "zs:area_m":54438.78836,
    "zs:blockids":[
        360290035003010,
        360290035001005
    ],
    "zs:housing10":33,
    "zs:label":"East Delavan",
    "zs:pop10":45
},
  "geometry": {"coordinates":[-78.831221,42.908244],"type":"Point"}
}