{
  "type": "Feature",
  "properties": {
    "gn:country":"US",
    "gn:fcode":"PPL",
    "gn:population":0,
    "iso:country":"US",
    "name:ara_x_preferred":[
        "\u0641\u0627\u0644\u064a\u0631\u0645\u0648"
    ],
    "name:azb_x_preferred":[
        "\u0648\u0644\u0631\u0645\u0648"
    ],
    "name:eng_x_preferred":[
        "Valyermo"
    ],
    "name:fas_x_preferred":[
        "\u0648\u0644\u0631\u0645\u0648"
    ],
    "name:fra_x_preferred":[
        "Valyermo"
    ],
    "name:tur_x_preferred":[
        "Valyermo"
    ],
    "name:vol_x_preferred":[
        "Valyermo"
    ],
    "name:zho_x_preferred":[
        "\u74e6\u723e\u8036\u83ab"
    ],
    "qs_pg:aaroncc":"US",
    "qs_pg:gn_country":"US",
    "qs_pg:gn_fcode":"PPL",
    "qs_pg:gn_pop":0,
    "qs_pg:name":"Valyermo",
    "qs_pg:name_adm0":"United States",
    "qs_pg:name_adm1":"California",
    "qs_pg:photos":637,
    "qs_pg:photos_1k":129,
    "qs_pg:photos_9k":3,
    "qs_pg:photos_9r":5,
    "qs_pg:photos_all":637,
    "qs_pg:photos_sr":8,
    "qs_pg:pop_sr":0,
    "qs_pg:qs_pg_placetype":"locality",
    "qs_pg:qs_pg_placetype_gp":"Town",
    "qs_pg:woe_adm0":23424977,
    "woe:adm0_id":23424977,
    "woe:name_adm0":"United States",
    "woe:name_adm1":"California",
    "woe:placetype":"Town",
    "wof:name":"Valyermo",
    "wof:placetype":"locality"
},
  "geometry": {"coordinates":[-117.85229,34.44611],"type":"Point"}
}