{
  "type": "Feature",
  "properties": {
    "gn:admin1_code":"VA",
    "gn:admin2_code":"5",
    "gn:asciiname":"Jordan Mines",
    "gn:country_code":"US",
    "gn:dem":467,
    "gn:elevation":"457.0",
    "gn:feature_class":"P",
    "gn:feature_code":"PPL",
    "gn:name":"Jordan Mines",
    "gn:population":0,
    "gn:timezone":"America/New_York",
    "iso:country":"US",
    "wof:name":"Jordan Mines",
    "wof:placetype":"locality"
},
  "geometry": {"coordinates":[-80.11589000000002,37.66124],"type":"Point"}
}