{
  "type": "Feature",
  "properties": {
    "iso:country":"US",
    "name:eng_x_preferred":[
        "Neighborhood G"
    ],
    "qs:gn_adm0_cc":"US",
    "qs:gn_local":5388564,
    "qs:gn_nam_loc":"Rohnert Park, Sonoma, California, US",
    "qs:gn_namadm1":"CA",
    "qs:local_max":1145,
    "qs:local_sum":2704,
    "qs:localhoods":9,
    "qs:name":"Neighborhood G",
    "qs:name_adm0":"United States",
    "qs:name_adm1":"California",
    "qs:name_adm2":"Sonoma",
    "qs:name_local":"Rohnert Park",
    "qs:photo_max":185,
    "qs:photo_sum":456,
    "qs:placetype":"Suburb",
    "qs:quad_count":22,
    "qs:woe_adm0":23424977,
    "qs:woe_adm1":2347563,
    "qs:woe_adm2":12587718,
    "qs:woe_lau":0,
    "qs:woe_local":2483970,
    "qs:woe_ver":"7.10.0",
    "wof:name":"Neighborhood G",
    "wof:placetype":"neighbourhood",
    "wof:population":2924,
    "zs:blockids":[
        60971513092001,
        60971513092003,
        60971515023022,
        60971513092015,
        60971515023012,
        60971513071006,
        60971513071000,
        60971513092012,
        60971513092013,
        60971514011084,
        60971513092011,
        60971514024019,
        60971513092009,
        60971513092008,
        60971513092006,
        60971513092017,
        60971513071007,
        60971514011085,
        60971513071003,
        60971514011083,
        60971513092018,
        60971513092000,
        60971513092004,
        60971513092019,
        60971513092020,
        60971513092014,
        60971513092002,
        60971513093001,
        60971515023013,
        60971513092007,
        60971513093000,
        60971513092005,
        60971513092010,
        60971513092016,
        60971513071002
    ],
    "zs:housing10":1058,
    "zs:pop10":2924
},
  "geometry": {"coordinates":[-122.68286000000001,38.366932],"type":"Point"}
}