{
  "type": "Feature",
  "properties": {
    "iso:country":"US",
    "wof:name":"Cahaba Village",
    "wof:placetype":"neighbourhood"
},
  "geometry": {"coordinates":[-86.6074313846468,33.6305829515406],"type":"Point"}
}