{
  "type": "Feature",
  "properties": {
    "gn:country":"US",
    "gn:fcode":"PPL",
    "gn:population":0,
    "iso:country":"US",
    "name:azb_x_preferred":[
        "\u067e\u0631\u0627\u062a\u0648\u0645"
    ],
    "name:eng_x_preferred":[
        "Pratum"
    ],
    "name:fas_x_preferred":[
        "\u067e\u0631\u0627\u062a\u0648\u0645"
    ],
    "name:fra_x_preferred":[
        "Pratum"
    ],
    "name:hat_x_preferred":[
        "Pratum"
    ],
    "name:hun_x_preferred":[
        "Pratum"
    ],
    "name:und_x_variant":[
        "Enger"
    ],
    "name:vol_x_preferred":[
        "Pratum"
    ],
    "qs_pg:aaroncc":"US",
    "qs_pg:gn_country":"US",
    "qs_pg:gn_fcode":"PPL",
    "qs_pg:gn_pop":0,
    "qs_pg:name":"Pratum",
    "qs_pg:name_adm0":"United States",
    "qs_pg:name_adm1":"Oregon",
    "qs_pg:photos":36,
    "qs_pg:photos_1k":7,
    "qs_pg:photos_9k":1,
    "qs_pg:photos_9r":2,
    "qs_pg:photos_all":36,
    "qs_pg:photos_sr":2,
    "qs_pg:pop_sr":0,
    "qs_pg:qs_pg_placetype":"locality",
    "qs_pg:qs_pg_placetype_gp":"Town",
    "qs_pg:woe_adm0":23424977,
    "woe:adm0_id":23424977,
    "woe:name_adm0":"United States",
    "woe:name_adm1":"Oregon",
    "woe:placetype":"Town",
    "wof:name":"Pratum",
    "wof:placetype":"locality"
},
  "geometry": {"coordinates":[-122.87869999999999,44.95901],"type":"Point"}
}