{
  "type": "Feature",
  "properties": {
    "iso:country":"US",
    "name:eng_x_preferred":[
        "Mid Vail"
    ],
    "qs:gn_adm0_cc":"US",
    "qs:gn_local":5442727,
    "qs:gn_nam_loc":"Vail, Eagle, Colorado, US",
    "qs:gn_namadm1":"CO",
    "qs:local_max":3849,
    "qs:local_sum":5490,
    "qs:localhoods":3,
    "qs:name":"Mid Vail",
    "qs:name_adm0":"United States",
    "qs:name_adm1":"Colorado",
    "qs:name_adm2":"Eagle",
    "qs:name_local":"Vail",
    "qs:photo_max":968,
    "qs:photo_sum":1525,
    "qs:placetype":"Suburb",
    "qs:quad_count":34,
    "qs:woe_adm0":23424977,
    "qs:woe_adm1":2347564,
    "qs:woe_adm2":12587746,
    "qs:woe_funk":"Parented by a neighborhood",
    "qs:woe_lau":0,
    "qs:woe_local":2510611,
    "qs:woe_ver":"7.10.0",
    "wof:lang":[
        "eng"
    ],
    "wof:name":"Mid Vail",
    "wof:placetype":"neighbourhood",
    "wof:population":320,
    "zs:blockids":[
        80370007032040,
        80370007021014,
        80370007032065,
        80370007021043,
        80370007021009,
        80370007021038,
        80370007021057,
        80370007021010,
        80370007011045,
        80370007021016,
        80370007021015,
        80370007021011,
        80370007021055,
        80370007021041,
        80370007021028,
        80370007021034,
        80370007021062,
        80370007021036,
        80370007021008,
        80370007021042,
        80370007021061,
        80370007021035,
        80370007021013,
        80370007021039,
        80370007021017,
        80370007021012,
        80370007032042,
        80370007021044,
        80370007021040,
        80370007021018
    ],
    "zs:housing10":1002,
    "zs:pop10":320
},
  "geometry": {"coordinates":[-106.364625,39.639652],"type":"Point"}
}