{
  "type": "Feature",
  "properties": {
    "gn:admin1_code":"MS",
    "gn:admin2_code":"59.0",
    "gn:asciiname":"Baker Mobile Home Park",
    "gn:country_code":"US",
    "gn:dem":10,
    "gn:elevation":"2.0",
    "gn:feature_class":"P",
    "gn:feature_code":"PPL",
    "gn:name":"Baker Mobile Home Park",
    "gn:population":0,
    "gn:timezone":"America/Chicago",
    "iso:country":"US",
    "wof:name":"Baker Mobile Home Park",
    "wof:placetype":"campus"
},
  "geometry": {"coordinates":[-88.54961999999998,30.44472],"type":"Point"}
}