{
  "type": "Feature",
  "properties": {
    "gn:admin1_code":"MO",
    "gn:admin2_code":"43.0",
    "gn:admin3_code":"69320.0",
    "gn:asciiname":"Velsor",
    "gn:country_code":"US",
    "gn:dem":425,
    "gn:elevation":"407.0",
    "gn:feature_class":"P",
    "gn:feature_code":"PPL",
    "gn:name":"Velsor",
    "gn:population":0,
    "gn:timezone":"America/Chicago",
    "iso:country":"US",
    "wof:name":"Velsor",
    "wof:placetype":"locality"
},
  "geometry": {"coordinates":[-93.03573,37.02033],"type":"Point"}
}