{
  "type": "Feature",
  "properties": {
    "gn:admin1_code":"TX",
    "gn:admin2_code":"201.0",
    "gn:asciiname":"San Jacinto Place",
    "gn:country_code":"US",
    "gn:dem":13,
    "gn:elevation":"10.0",
    "gn:feature_class":"P",
    "gn:feature_code":"PPL",
    "gn:name":"San Jacinto Place",
    "gn:population":0,
    "gn:timezone":"America/Chicago",
    "iso:country":"US",
    "wof:name":"San Jacinto Place",
    "wof:placetype":"locality"
},
  "geometry": {"coordinates":[-94.9898,29.8021],"type":"Point"}
}