{
  "type": "Feature",
  "properties": {
    "gn:admin1_code":"MN",
    "gn:admin2_code":"59.0",
    "gn:admin3_code":"2602.0",
    "gn:asciiname":"Isanti Estates",
    "gn:country_code":"US",
    "gn:dem":282,
    "gn:elevation":"284.0",
    "gn:feature_class":"P",
    "gn:feature_code":"PPL",
    "gn:name":"Isanti Estates",
    "gn:population":0,
    "gn:timezone":"America/Chicago",
    "iso:country":"US",
    "wof:name":"Isanti Estates",
    "wof:placetype":"locality"
},
  "geometry": {"coordinates":[-93.23333,45.45472],"type":"Point"}
}