{
  "type": "Feature",
  "properties": {
    "iso:country":"US",
    "name:deu_x_preferred":[
        "Little India"
    ],
    "name:eng_x_preferred":[
        "Little India"
    ],
    "name:msa_x_preferred":[
        "Little India"
    ],
    "name:pan_x_preferred":[
        "\u0a32\u0a3f\u0a1f\u0a32 \u0a07\u0a70\u0a21\u0a40\u0a06"
    ],
    "qs:gn_adm0_cc":"US",
    "qs:gn_local":5324862,
    "qs:gn_nam_loc":"Artesia, Los Angeles, California, US",
    "qs:gn_namadm1":"CA",
    "qs:local_max":652,
    "qs:local_sum":652,
    "qs:localhoods":1,
    "qs:name":"Little India",
    "qs:name_adm0":"United States",
    "qs:name_adm1":"California",
    "qs:name_adm2":"Los Angeles",
    "qs:name_local":"Artesia",
    "qs:photo_max":134,
    "qs:photo_sum":652,
    "qs:placetype":"Suburb",
    "qs:quad_count":30,
    "qs:woe_adm0":23424977,
    "qs:woe_adm1":2347563,
    "qs:woe_adm2":12587688,
    "qs:woe_lau":0,
    "qs:woe_local":2356304,
    "qs:woe_ver":"7.10.0",
    "wd:wordcount":61,
    "wof:name":"Little India",
    "wof:placetype":"neighbourhood",
    "wof:population":2904,
    "zs:blockids":[
        60375549005008,
        60375545222006,
        60375549005006,
        60375549005004,
        60375545212014,
        60375549003001,
        60375549004010,
        60375549004001,
        60375549003004,
        60375545151006,
        60375549005003,
        60375549003000,
        60375549004003,
        60375545222005,
        60375549005005,
        60375549005010,
        60375549005001,
        60375549001004,
        60375545212016,
        60375545212015,
        60375549005002,
        60375549004009,
        60375545212017,
        60375549004000,
        60375545212003,
        60375549003002,
        60375549003003,
        60375549005000,
        60375549001003,
        60375545212002,
        60375545151007,
        60375545222007,
        60375549004002,
        60375549004004,
        60375549005007
    ],
    "zs:housing10":891,
    "zs:pop10":2904
},
  "geometry": {"coordinates":[-118.081715,33.861307],"type":"Point"}
}