{
  "type": "Feature",
  "properties": {
    "gn:admin1_code":"AR",
    "gn:admin2_code":"53.0",
    "gn:admin3_code":"90624.0",
    "gn:asciiname":"Deer Creek",
    "gn:country_code":"US",
    "gn:dem":88,
    "gn:elevation":"82.0",
    "gn:feature_class":"P",
    "gn:feature_code":"PPL",
    "gn:name":"Deer Creek",
    "gn:population":0,
    "gn:timezone":"America/Chicago",
    "iso:country":"US",
    "name:cat_x_preferred":[
        "Deer Creek"
    ],
    "name:deu_x_preferred":[
        "Deer Creek"
    ],
    "name:ita_x_preferred":[
        "Deer Creek"
    ],
    "name:nld_x_preferred":[
        "Deer Creek"
    ],
    "name:pol_x_preferred":[
        "Deer Creek"
    ],
    "name:por_x_preferred":[
        "Deer Creek"
    ],
    "name:rus_x_preferred":[
        "\u0414\u0438\u0440-\u041a\u0440\u0438\u043a"
    ],
    "name:spa_x_preferred":[
        "Deer Creek"
    ],
    "name:srp_x_preferred":[
        "\u0414\u0438\u0440 \u041a\u0440\u0438\u043a"
    ],
    "name:swe_x_preferred":[
        "Deer Creek"
    ],
    "name:ukr_x_preferred":[
        "\u0414\u0456\u0435\u0440-\u041a\u0440\u0456\u043a"
    ],
    "name:vol_x_preferred":[
        "Deer Creek"
    ],
    "wof:name":"Deer Creek",
    "wof:placetype":"locality"
},
  "geometry": {"coordinates":[-92.40349000000001,34.24399],"type":"Point"}
}