{
  "type": "Feature",
  "properties": {
    "gn:admin1_code":"MD",
    "gn:admin2_code":"5.0",
    "gn:asciiname":"Silvergate East",
    "gn:country_code":"US",
    "gn:dem":44,
    "gn:elevation":"37.0",
    "gn:feature_class":"P",
    "gn:feature_code":"PPL",
    "gn:name":"Silvergate East",
    "gn:population":0,
    "gn:timezone":"America/New_York",
    "iso:country":"US",
    "wof:name":"Silvergate East",
    "wof:placetype":"locality"
},
  "geometry": {"coordinates":[-76.48163000000002,39.38622],"type":"Point"}
}