{
  "type": "Feature",
  "properties": {
    "gn:admin1_code":"KY",
    "gn:admin2_code":"135",
    "gn:asciiname":"Kinniconick",
    "gn:country_code":"US",
    "gn:dem":212,
    "gn:elevation":"210.0",
    "gn:feature_class":"P",
    "gn:feature_code":"PPL",
    "gn:name":"Kinniconick",
    "gn:population":0,
    "gn:timezone":"America/New_York",
    "iso:country":"US",
    "wof:name":"Kinniconick",
    "wof:placetype":"locality"
},
  "geometry": {"coordinates":[-83.33796,38.52119],"type":"Point"}
}