{
  "type": "Feature",
  "properties": {
    "gn:admin1_code":"DE",
    "gn:admin2_code":"5.0",
    "gn:asciiname":"Cozy Cove Mobile Home Park",
    "gn:country_code":"US",
    "gn:dem":1,
    "gn:elevation":"1.0",
    "gn:feature_class":"P",
    "gn:feature_code":"PPL",
    "gn:name":"Cozy Cove Mobile Home Park",
    "gn:population":0,
    "gn:timezone":"America/New_York",
    "iso:country":"US",
    "wof:name":"Cozy Cove Mobile Home Park",
    "wof:placetype":"campus"
},
  "geometry": {"coordinates":[-75.12602,38.6265],"type":"Point"}
}