{
  "type": "Feature",
  "properties": {
    "gn:country":"US",
    "gn:fcode":"PPL",
    "gn:population":0,
    "iso:country":"US",
    "name:ces_x_preferred":[
        "Exmoor"
    ],
    "name:cym_x_preferred":[
        "Exmoor"
    ],
    "name:dan_x_preferred":[
        "Exmoor"
    ],
    "name:eng_x_preferred":[
        "Exmoor"
    ],
    "name:est_x_preferred":[
        "Exmoor"
    ],
    "name:fin_x_preferred":[
        "Exmoor"
    ],
    "name:fra_x_preferred":[
        "Exmoor"
    ],
    "name:gle_x_preferred":[
        "Exmoor"
    ],
    "name:hrv_x_preferred":[
        "Exmoor"
    ],
    "name:hye_x_preferred":[
        "\u0537\u0584\u057d\u0574\u0578\u0582\u0580"
    ],
    "name:isl_x_preferred":[
        "Exmoor"
    ],
    "name:nno_x_preferred":[
        "Exmoor"
    ],
    "name:nor_x_preferred":[
        "Exmoor"
    ],
    "name:pnb_x_preferred":[
        "\u0627\u06cc\u06a9\u0633\u0645\u0648\u0631"
    ],
    "name:pol_x_preferred":[
        "Exmoor"
    ],
    "name:rus_x_preferred":[
        "\u042d\u043a\u0441\u043c\u0443\u0440"
    ],
    "name:swe_x_preferred":[
        "Exmoor"
    ],
    "name:zho_x_preferred":[
        "\u57c3\u514b\u65af\u6469\u723e"
    ],
    "qs_pg:aaroncc":"US",
    "qs_pg:gn_country":"US",
    "qs_pg:gn_fcode":"PPL",
    "qs_pg:gn_pop":0,
    "qs_pg:name":"Exmoor",
    "qs_pg:name_adm0":"United States",
    "qs_pg:name_adm1":"Pennsylvania",
    "qs_pg:photos":1,
    "qs_pg:photos_1k":1,
    "qs_pg:photos_9k":1,
    "qs_pg:photos_9r":1,
    "qs_pg:photos_all":1,
    "qs_pg:photos_sr":1,
    "qs_pg:pop_sr":0,
    "qs_pg:qs_pg_placetype":"neighbourhood",
    "qs_pg:qs_pg_placetype_gp":"Suburb",
    "qs_pg:woe_adm0":23424977,
    "wd:wordcount":6533,
    "wof:name":"Exmoor",
    "wof:placetype":"neighbourhood",
    "zs:area_m":10466.139654,
    "zs:blockids":[
        421070039001046
    ],
    "zs:housing10":0,
    "zs:label":"Exmoor",
    "zs:pop10":0
},
  "geometry": {"coordinates":[-76.42823199999999,40.534792],"type":"Point"}
}