{
  "type": "Feature",
  "properties": {
    "gn:admin1_code":"VA",
    "gn:admin2_code":"3",
    "gn:asciiname":"Rugby",
    "gn:country_code":"US",
    "gn:dem":103,
    "gn:elevation":"103.0",
    "gn:feature_class":"P",
    "gn:feature_code":"PPL",
    "gn:name":"Rugby",
    "gn:population":0,
    "gn:timezone":"America/New_York",
    "iso:country":"US",
    "wof:name":"Rugby",
    "wof:placetype":"locality"
},
  "geometry": {"coordinates":[-78.32779000000002,38.01375],"type":"Point"}
}