{
  "type": "Feature",
  "properties": {
    "iso:country":"US",
    "name:eng_x_preferred":[
        "East Woods"
    ],
    "wof:name":"East Woods",
    "wof:placetype":"neighbourhood",
    "wof:population":1863,
    "zs:area_m":14224129.187827,
    "zs:blockids":[
        361190124002004,
        361190125031029,
        361190125032006,
        361190124002000,
        361190124002005,
        361190125032020,
        361190125031019,
        361190124002019,
        361190124002006,
        361190124002002,
        361190124002020,
        361190124002003,
        361190125032003,
        361190125031028,
        361190124002001,
        361190124002008
    ],
    "zs:housing10":771,
    "zs:label":"East Woods",
    "zs:pop10":1863
},
  "geometry": {"coordinates":[-73.531228,41.209674],"type":"Point"}
}