{
  "type": "Feature",
  "properties": {
    "gn:admin1_code":"LA",
    "gn:admin2_code":"101.0",
    "gn:asciiname":"Landry",
    "gn:country_code":"US",
    "gn:dem":6,
    "gn:elevation":"2.0",
    "gn:feature_class":"P",
    "gn:feature_code":"PPL",
    "gn:name":"Landry",
    "gn:population":0,
    "gn:timezone":"America/Chicago",
    "iso:country":"US",
    "name:deu_x_preferred":[
        "Landry"
    ],
    "name:fra_x_preferred":[
        "Landry"
    ],
    "name:jpn_x_preferred":[
        "\u30e9\u30f3\u30c9\u30ea\u30fc"
    ],
    "name:rus_x_preferred":[
        "\u041b\u0430\u043d\u0434\u0440\u0438"
    ],
    "wof:name":"Landry",
    "wof:placetype":"locality"
},
  "geometry": {"coordinates":[-91.66539,29.86937],"type":"Point"}
}