{
  "type": "Feature",
  "properties": {
    "gn:admin1_code":"VA",
    "gn:admin2_code":"103",
    "gn:asciiname":"Senora",
    "gn:country_code":"US",
    "gn:dem":13,
    "gn:elevation":"9.0",
    "gn:feature_class":"P",
    "gn:feature_code":"PPL",
    "gn:name":"Senora",
    "gn:population":0,
    "gn:timezone":"America/New_York",
    "iso:country":"US",
    "wof:name":"Senora",
    "wof:placetype":"locality"
},
  "geometry": {"coordinates":[-76.52105999999998,37.67653],"type":"Point"}
}