{
  "type": "Feature",
  "properties": {
    "gn:admin1_code":"MA",
    "gn:admin2_code":"27.0",
    "gn:admin3_code":"66105.0",
    "gn:asciiname":"Lambs Grove",
    "gn:country_code":"US",
    "gn:dem":264,
    "gn:elevation":"266.0",
    "gn:feature_class":"P",
    "gn:feature_code":"PPL",
    "gn:name":"Lambs Grove",
    "gn:population":0,
    "gn:timezone":"America/New_York",
    "iso:country":"US",
    "wof:name":"Lambs Grove",
    "wof:placetype":"locality"
},
  "geometry": {"coordinates":[-71.96785,42.27509000000001],"type":"Point"}
}