{
  "type": "Feature",
  "properties": {
    "gn:admin1_code":"MD",
    "gn:admin2_code":"9.0",
    "gn:asciiname":"Meadow Oaks",
    "gn:country_code":"US",
    "gn:dem":33,
    "gn:elevation":"31.0",
    "gn:feature_class":"P",
    "gn:feature_code":"PPL",
    "gn:name":"Meadow Oaks",
    "gn:population":0,
    "gn:timezone":"America/New_York",
    "iso:country":"US",
    "wof:name":"Meadow Oaks",
    "wof:placetype":"locality"
},
  "geometry": {"coordinates":[-76.61079000000002,38.57095],"type":"Point"}
}