{
  "type": "Feature",
  "properties": {
    "gn:admin1_code":"LA",
    "gn:admin2_code":"29.0",
    "gn:asciiname":"New Era",
    "gn:country_code":"US",
    "gn:dem":14,
    "gn:elevation":"16.0",
    "gn:feature_class":"P",
    "gn:feature_code":"PPL",
    "gn:name":"New Era",
    "gn:population":0,
    "gn:timezone":"America/Chicago",
    "iso:country":"US",
    "name:ceb_x_preferred":[
        "New Era"
    ],
    "name:deu_x_preferred":[
        "New Era"
    ],
    "name:fin_x_preferred":[
        "New Era"
    ],
    "name:kor_x_preferred":[
        "\ub274\uc5d0\ub77c"
    ],
    "name:nld_x_preferred":[
        "New Era"
    ],
    "name:pol_x_preferred":[
        "New Era"
    ],
    "wof:name":"New Era",
    "wof:placetype":"locality"
},
  "geometry": {"coordinates":[-91.82735,31.36712],"type":"Point"}
}