{
  "type": "Feature",
  "properties": {
    "iso:country":"US",
    "name:eng_x_preferred":[
        "West Winston Manor"
    ],
    "wof:name":"West Winston Manor",
    "wof:placetype":"neighbourhood",
    "wof:population":827,
    "zs:area_m":171450.426401,
    "zs:blockids":[
        60816017003014,
        60816017003012,
        60816017003011,
        60816017003015,
        60816017003016,
        60816017003009,
        60816017003013
    ],
    "zs:housing10":270,
    "zs:label":"West Winston Manor",
    "zs:pop10":827
},
  "geometry": {"coordinates":[-122.460263,37.661275],"type":"Point"}
}