{
  "type": "Feature",
  "properties": {
    "gn:admin1_code":"AL",
    "gn:admin2_code":"89",
    "gn:asciiname":"Fairview",
    "gn:country_code":"US",
    "gn:dem":271,
    "gn:elevation":"268.0",
    "gn:feature_class":"P",
    "gn:feature_code":"PPL",
    "gn:name":"Fairview",
    "gn:population":0,
    "gn:timezone":"America/Chicago",
    "iso:country":"US",
    "name:cat_x_preferred":[
        "Fairview"
    ],
    "name:ceb_x_preferred":[
        "Fairview"
    ],
    "name:ces_x_preferred":[
        "Fairview"
    ],
    "name:dan_x_preferred":[
        "Fairview"
    ],
    "name:deu_x_preferred":[
        "Fairview"
    ],
    "name:fas_x_preferred":[
        "\u0641\u0631\u0648\u06cc\u0648"
    ],
    "name:fin_x_preferred":[
        "Fairview"
    ],
    "name:fra_x_preferred":[
        "Fairview"
    ],
    "name:hun_x_preferred":[
        "Fairview"
    ],
    "name:ido_x_preferred":[
        "Fairview"
    ],
    "name:ita_x_preferred":[
        "Fairview"
    ],
    "name:nld_x_preferred":[
        "Fairview"
    ],
    "name:pol_x_preferred":[
        "Fairview"
    ],
    "name:por_x_preferred":[
        "Fairview"
    ],
    "name:rus_x_preferred":[
        "\u0424\u044d\u0440\u0432\u044c\u044e"
    ],
    "name:sco_x_preferred":[
        "Fairview"
    ],
    "name:slk_x_preferred":[
        "Fairview"
    ],
    "name:spa_x_preferred":[
        "Fairview"
    ],
    "name:srp_x_preferred":[
        "\u0424\u0435\u0440\u0432\u0458\u0443"
    ],
    "name:swe_x_preferred":[
        "Fairview"
    ],
    "name:tur_x_preferred":[
        "Fairview"
    ],
    "name:urd_x_preferred":[
        "\u0641\u06cc\u0626\u0631\u0648\u06cc\u0648"
    ],
    "name:vol_x_preferred":[
        "Fairview"
    ],
    "wof:name":"Fairview",
    "wof:placetype":"locality"
},
  "geometry": {"coordinates":[-86.4736,34.97592],"type":"Point"}
}