{
  "type": "Feature",
  "properties": {
    "gn:admin1_code":"WA",
    "gn:admin2_code":"61.0",
    "gn:asciiname":"Candlewood Estates Mobile Home Park",
    "gn:country_code":"US",
    "gn:dem":179,
    "gn:elevation":"181.0",
    "gn:feature_class":"P",
    "gn:feature_code":"PPL",
    "gn:name":"Candlewood Estates Mobile Home Park",
    "gn:population":0,
    "gn:timezone":"America/Los_Angeles",
    "iso:country":"US",
    "wof:name":"Candlewood Estates Mobile Home Park",
    "wof:placetype":"campus"
},
  "geometry": {"coordinates":[-122.28639,47.84891],"type":"Point"}
}