{
  "type": "Feature",
  "properties": {
    "gn:admin1_code":"MD",
    "gn:admin2_code":"17.0",
    "gn:asciiname":"Redhill Estates",
    "gn:country_code":"US",
    "gn:dem":42,
    "gn:elevation":"41.0",
    "gn:feature_class":"P",
    "gn:feature_code":"PPL",
    "gn:name":"Redhill Estates",
    "gn:population":0,
    "gn:timezone":"America/New_York",
    "iso:country":"US",
    "wof:name":"Redhill Estates",
    "wof:placetype":"locality"
},
  "geometry": {"coordinates":[-77.13081,38.56651],"type":"Point"}
}