{
  "type": "Feature",
  "properties": {
    "gn:admin1_code":"MN",
    "gn:admin2_code":"137.0",
    "gn:admin3_code":"17440.0",
    "gn:asciiname":"McComber",
    "gn:country_code":"US",
    "gn:dem":446,
    "gn:elevation":"448.0",
    "gn:feature_class":"P",
    "gn:feature_code":"PPL",
    "gn:name":"McComber",
    "gn:population":0,
    "gn:timezone":"America/Chicago",
    "iso:country":"US",
    "wof:name":"McComber",
    "wof:placetype":"locality"
},
  "geometry": {"coordinates":[-92.06543000000001,47.8488],"type":"Point"}
}