{
  "type": "Feature",
  "properties": {
    "gn:admin1_code":"GA",
    "gn:admin2_code":"39.0",
    "gn:asciiname":"Fawnwood",
    "gn:country_code":"US",
    "gn:dem":10,
    "gn:elevation":"6.0",
    "gn:feature_class":"P",
    "gn:feature_code":"PPL",
    "gn:name":"Fawnwood",
    "gn:population":0,
    "gn:timezone":"America/New_York",
    "iso:country":"US",
    "wof:name":"Fawnwood",
    "wof:placetype":"locality"
},
  "geometry": {"coordinates":[-81.70676999999998,30.77301],"type":"Point"}
}