{
  "type": "Feature",
  "properties": {
    "gn:admin1_code":"AL",
    "gn:admin2_code":"69",
    "gn:asciiname":"Brown Estates",
    "gn:country_code":"US",
    "gn:dem":105,
    "gn:elevation":"97.0",
    "gn:feature_class":"P",
    "gn:feature_code":"PPL",
    "gn:name":"Brown Estates",
    "gn:population":0,
    "gn:timezone":"America/Chicago",
    "iso:country":"US",
    "wof:name":"Brown Estates",
    "wof:placetype":"locality"
},
  "geometry": {"coordinates":[-85.37966,31.21045],"type":"Point"}
}