{
  "type": "Feature",
  "properties": {
    "gn:admin1_code":"NJ",
    "gn:admin2_code":"9.0",
    "gn:admin3_code":"41610.0",
    "gn:asciiname":"Miami Beach",
    "gn:country_code":"US",
    "gn:dem":3,
    "gn:elevation":"2.0",
    "gn:feature_class":"P",
    "gn:feature_code":"PPL",
    "gn:name":"Miami Beach",
    "gn:population":0,
    "gn:timezone":"America/New_York",
    "iso:country":"US",
    "wof:name":"Miami Beach",
    "wof:placetype":"locality"
},
  "geometry": {"coordinates":[-74.93684,39.03456],"type":"Point"}
}