{
  "type": "Feature",
  "properties": {
    "gn:admin1_code":"AZ",
    "gn:admin2_code":"19.0",
    "gn:asciiname":"Emery Park",
    "gn:country_code":"US",
    "gn:dem":773,
    "gn:elevation":"773.0",
    "gn:feature_class":"P",
    "gn:feature_code":"PPL",
    "gn:name":"Emery Park",
    "gn:population":0,
    "gn:timezone":"America/Phoenix",
    "iso:country":"US",
    "wof:name":"Emery Park",
    "wof:placetype":"locality"
},
  "geometry": {"coordinates":[-110.95592000000001,32.14119],"type":"Point"}
}