{
  "type": "Feature",
  "properties": {
    "gn:admin1_code":"UT",
    "gn:admin2_code":"27.0",
    "gn:asciiname":"Read",
    "gn:country_code":"US",
    "gn:dem":1492,
    "gn:elevation":"1491.0",
    "gn:feature_class":"P",
    "gn:feature_code":"PPL",
    "gn:name":"Read",
    "gn:population":0,
    "gn:timezone":"America/Denver",
    "iso:country":"US",
    "name:ara_x_preferred":[
        "\u0642\u0631\u0623"
    ],
    "name:cat_x_preferred":[
        "Read"
    ],
    "name:deu_x_preferred":[
        "Read"
    ],
    "name:fra_x_preferred":[
        "Read"
    ],
    "name:ita_x_preferred":[
        "Read"
    ],
    "name:pol_x_preferred":[
        "Read"
    ],
    "name:spa_x_preferred":[
        "Read"
    ],
    "wof:name":"Read",
    "wof:placetype":"locality"
},
  "geometry": {"coordinates":[-112.98496000000002,38.57246],"type":"Point"}
}