{
  "type": "Feature",
  "properties": {
    "gn:admin1_code":"GA",
    "gn:admin2_code":"63",
    "gn:asciiname":"Woodland Hills Mobile Home Park",
    "gn:country_code":"US",
    "gn:dem":283,
    "gn:elevation":"278.0",
    "gn:feature_class":"P",
    "gn:feature_code":"PPL",
    "gn:name":"Woodland Hills Mobile Home Park",
    "gn:population":0,
    "gn:timezone":"America/New_York",
    "iso:country":"US",
    "wof:name":"Woodland Hills Mobile Home Park",
    "wof:placetype":"campus"
},
  "geometry": {"coordinates":[-84.42159000000002,33.61678],"type":"Point"}
}