{
  "type": "Feature",
  "properties": {
    "iso:country":"US",
    "name:eng_x_preferred":[
        "Autumn Ridge"
    ],
    "wof:name":"Autumn Ridge",
    "wof:placetype":"neighbourhood",
    "wof:population":1,
    "zs:area_m":204027.379728,
    "zs:blockids":[
        371830541132027,
        371830541132026,
        371830541152002,
        371830541132031
    ],
    "zs:housing10":1,
    "zs:label":"Autumn Ridge",
    "zs:pop10":1
},
  "geometry": {"coordinates":[-78.497615,35.799736],"type":"Point"}
}