{
  "type": "Feature",
  "properties": {
    "gn:admin1_code":"FL",
    "gn:admin2_code":"9.0",
    "gn:asciiname":"Silver Breeze Mobile Home Community",
    "gn:country_code":"US",
    "gn:dem":13,
    "gn:elevation":"11.0",
    "gn:feature_class":"P",
    "gn:feature_code":"PPL",
    "gn:name":"Silver Breeze Mobile Home Community",
    "gn:population":0,
    "gn:timezone":"America/New_York",
    "iso:country":"US",
    "wof:name":"Silver Breeze Mobile Home Community",
    "wof:placetype":"campus"
},
  "geometry": {"coordinates":[-80.81395999999999,28.55669],"type":"Point"}
}