{
  "type": "Feature",
  "properties": {
    "gn:admin1_code":"OH",
    "gn:admin2_code":"173.0",
    "gn:admin3_code":"62162.0",
    "gn:asciiname":"Oak Meadows",
    "gn:country_code":"US",
    "gn:dem":197,
    "gn:elevation":"195.0",
    "gn:feature_class":"P",
    "gn:feature_code":"PPL",
    "gn:name":"Oak Meadows",
    "gn:population":0,
    "gn:timezone":"America/New_York",
    "iso:country":"US",
    "wof:name":"Oak Meadows",
    "wof:placetype":"locality"
},
  "geometry": {"coordinates":[-83.59520999999999,41.53533],"type":"Point"}
}