{
  "type": "Feature",
  "properties": {
    "gn:admin1_code":"GA",
    "gn:admin2_code":"183.0",
    "gn:asciiname":"Noble",
    "gn:country_code":"US",
    "gn:dem":26,
    "gn:elevation":"21.0",
    "gn:feature_class":"P",
    "gn:feature_code":"PPL",
    "gn:name":"Noble",
    "gn:population":0,
    "gn:timezone":"America/New_York",
    "iso:country":"US",
    "name:cat_x_preferred":[
        "Noble"
    ],
    "name:ceb_x_preferred":[
        "Noble"
    ],
    "name:deu_x_preferred":[
        "Noble"
    ],
    "name:fra_x_preferred":[
        "Noble"
    ],
    "name:ita_x_preferred":[
        "Noble"
    ],
    "name:jpn_x_preferred":[
        "\u30ce\u30fc\u30d6\u30eb"
    ],
    "name:nld_x_preferred":[
        "Noble"
    ],
    "name:pol_x_preferred":[
        "Noble"
    ],
    "name:por_x_preferred":[
        "Noble"
    ],
    "name:rus_x_preferred":[
        "\u041d\u043e\u0431\u043b"
    ],
    "name:spa_x_preferred":[
        "Noble"
    ],
    "name:srp_x_preferred":[
        "\u041d\u043e\u0431\u043b"
    ],
    "name:swe_x_preferred":[
        "Noble"
    ],
    "name:ukr_x_preferred":[
        "\u041d\u043e\u0431\u043b"
    ],
    "name:vol_x_preferred":[
        "Noble"
    ],
    "wof:name":"Noble",
    "wof:placetype":"locality"
},
  "geometry": {"coordinates":[-81.92900999999998,31.8466],"type":"Point"}
}