{
  "type": "Feature",
  "properties": {
    "iso:country":"US",
    "name:eng_x_preferred":[
        "Terrace Gables"
    ],
    "wof:name":"Terrace Gables",
    "wof:placetype":"neighbourhood",
    "wof:population":71,
    "zs:area_m":68403.891306,
    "zs:blockids":[
        120570003006009,
        120570003006024,
        120570003006026
    ],
    "zs:housing10":22,
    "zs:label":"Terrace Gables",
    "zs:pop10":71
},
  "geometry": {"coordinates":[-82.426834,28.03447],"type":"Point"}
}