{
  "type": "Feature",
  "properties": {
    "gn:admin1_code":"MD",
    "gn:admin2_code":"41.0",
    "gn:asciiname":"North Bend Estates",
    "gn:country_code":"US",
    "gn:dem":5,
    "gn:elevation":"4.0",
    "gn:feature_class":"P",
    "gn:feature_code":"PPL",
    "gn:name":"North Bend Estates",
    "gn:population":0,
    "gn:timezone":"America/New_York",
    "iso:country":"US",
    "wof:name":"North Bend Estates",
    "wof:placetype":"locality"
},
  "geometry": {"coordinates":[-76.12522,38.78484],"type":"Point"}
}