{
  "type": "Feature",
  "properties": {
    "gn:country":"US",
    "gn:fcode":"PPL",
    "gn:population":0,
    "iso:country":"US",
    "name:azb_x_preferred":[
        "\u0645\u06a9 \u0646\u0648\u0631\u062a"
    ],
    "name:cat_x_preferred":[
        "Mack North"
    ],
    "name:ceb_x_preferred":[
        "Mack North"
    ],
    "name:eng_x_preferred":[
        "Mack North"
    ],
    "name:eus_x_preferred":[
        "Mack North"
    ],
    "name:fas_x_preferred":[
        "\u0645\u06a9 \u0646\u0648\u0631\u062a"
    ],
    "name:fra_x_preferred":[
        "Mack North"
    ],
    "name:nan_x_preferred":[
        "Mack North"
    ],
    "name:nld_x_preferred":[
        "Mack North"
    ],
    "name:por_x_preferred":[
        "Mack North"
    ],
    "name:srp_x_preferred":[
        "\u041c\u0430\u043a \u041d\u043e\u0440\u0442"
    ],
    "name:und_x_variant":[
        "Mack North CDP"
    ],
    "name:urd_x_preferred":[
        "\u0645\u06cc\u06a9 \u0646\u0627\u0631\u062a\u06be\u060c \u0627\u0648\u06c1\u0627\u0626\u06cc\u0648"
    ],
    "name:urd_x_variant":[
        "\u0645\u06cc\u06a9 \u0646\u0627\u0631\u062a\u06be"
    ],
    "name:vol_x_preferred":[
        "Mack North"
    ],
    "qs_pg:aaroncc":"US",
    "qs_pg:gn_country":"US",
    "qs_pg:gn_fcode":"PPL",
    "qs_pg:gn_pop":0,
    "qs_pg:name":"Mack North",
    "qs_pg:name_adm0":"United States",
    "qs_pg:name_adm1":"Ohio",
    "qs_pg:photos":11,
    "qs_pg:photos_1k":2,
    "qs_pg:photos_9k":1,
    "qs_pg:photos_9r":1,
    "qs_pg:photos_all":11,
    "qs_pg:photos_sr":1,
    "qs_pg:pop_sr":0,
    "qs_pg:qs_pg_placetype":"locality",
    "qs_pg:qs_pg_placetype_gp":"Town",
    "qs_pg:woe_adm0":23424977,
    "woe:adm0_id":23424977,
    "woe:name_adm0":"United States",
    "woe:name_adm1":"Ohio",
    "woe:placetype":"Town",
    "wof:name":"Mack North",
    "wof:placetype":"locality"
},
  "geometry": {"coordinates":[-84.67085,39.1651],"type":"Point"}
}