{
  "type": "Feature",
  "properties": {
    "gn:admin1_code":"AZ",
    "gn:admin2_code":"1.0",
    "gn:asciiname":"Richville",
    "gn:country_code":"US",
    "gn:dem":1855,
    "gn:elevation":"1853.0",
    "gn:feature_class":"P",
    "gn:feature_code":"PPL",
    "gn:name":"Richville",
    "gn:population":0,
    "gn:timezone":"America/Phoenix",
    "iso:country":"US",
    "name:bre_x_preferred":[
        "Richville"
    ],
    "name:cat_x_preferred":[
        "Richville"
    ],
    "name:ceb_x_preferred":[
        "Richville"
    ],
    "name:deu_x_preferred":[
        "Richville"
    ],
    "name:fra_x_preferred":[
        "Richville"
    ],
    "name:ita_x_preferred":[
        "Richville"
    ],
    "name:nld_x_preferred":[
        "Richville"
    ],
    "name:pol_x_preferred":[
        "Richville"
    ],
    "name:srp_x_preferred":[
        "\u0420\u0438\u0447\u0432\u0438\u043b"
    ],
    "name:vol_x_preferred":[
        "Richville"
    ],
    "wof:name":"Richville",
    "wof:placetype":"locality"
},
  "geometry": {"coordinates":[-109.35536999999999,34.28615],"type":"Point"}
}