{
  "type": "Feature",
  "properties": {
    "gn:admin1_code":"AL",
    "gn:admin2_code":"121",
    "gn:asciiname":"Embry Crossroads",
    "gn:country_code":"US",
    "gn:dem":150,
    "gn:elevation":"150.0",
    "gn:feature_class":"P",
    "gn:feature_code":"PPL",
    "gn:name":"Embry Crossroads",
    "gn:population":0,
    "gn:timezone":"America/Chicago",
    "iso:country":"US",
    "name:eng_x_preferred":[
        "Embry Crossroads"
    ],
    "name:und_x_variant":[
        "Embrys Crossroad",
        "Embry",
        "Embrys Crossing"
    ],
    "wof:name":"Embry Crossroads",
    "wof:placetype":"locality"
},
  "geometry": {"coordinates":[-86.16109,33.59316],"type":"Point"}
}