{
  "type": "Feature",
  "properties": {
    "gn:admin1_code":"TN",
    "gn:admin2_code":"7.0",
    "gn:asciiname":"Bellview",
    "gn:country_code":"US",
    "gn:dem":532,
    "gn:elevation":"530.0",
    "gn:feature_class":"P",
    "gn:feature_code":"PPL",
    "gn:name":"Bellview",
    "gn:population":0,
    "gn:timezone":"America/Chicago",
    "iso:country":"US",
    "name:deu_x_preferred":[
        "Bellview"
    ],
    "name:eng_x_preferred":[
        "Bellview"
    ],
    "name:und_x_variant":[
        "Farmingdale"
    ],
    "wof:name":"Bellview",
    "wof:placetype":"locality"
},
  "geometry": {"coordinates":[-85.17774,35.74617999999999],"type":"Point"}
}