{
  "type": "Feature",
  "properties": {
    "iso:country":"US",
    "name:eng_x_preferred":[
        "The Overlook at Holly Glen"
    ],
    "wof:name":"The Overlook at Holly Glen",
    "wof:placetype":"neighbourhood",
    "wof:population":4200,
    "zs:area_m":16860392.067221,
    "zs:blockids":[
        371830532072043,
        371830532072063,
        371830532072067,
        371830532072077,
        371830532071089,
        371830532072073,
        371830532071039,
        371830532071054,
        371830532072045,
        371830532072076,
        371830532072064,
        371830532072085,
        371830532071038,
        371830532072071,
        371830532072082,
        371830532072047,
        371830532072061,
        371830532071042,
        371830532061074,
        371830532061028,
        371830532071044,
        371830532071035,
        371830532072065,
        371830532072086,
        371830532072083,
        371830532061041,
        371830532071060,
        371830532061027,
        371830532071041,
        371830532071040,
        371830532071049,
        371830532071036,
        371830532072084,
        371830532071045,
        371830532072066,
        371830532072078,
        371830532061026,
        371830532071026,
        371830532071022,
        371830532072062,
        371830532072070,
        371830532071043,
        371830532071037,
        371830532071025,
        371830532071059,
        371830532072079,
        371830532072074,
        371830532071021,
        371830532072075,
        371830532072044,
        371830532071090,
        371830532072042,
        371830532061025,
        371830532061073,
        371830532072072,
        371830532072080,
        371830532072081,
        371830532072068,
        371830532072069,
        371830532071023
    ],
    "zs:housing10":1429,
    "zs:label":"The Overlook at Holly Glen",
    "zs:pop10":4200
},
  "geometry": {"coordinates":[-78.857439,35.61882],"type":"Point"}
}