{
  "type": "Feature",
  "properties": {
    "iso:country":"US",
    "name:eng_x_preferred":[
        "Bennington Oaks Ii"
    ],
    "wof:name":"Bennington Oaks Ii",
    "wof:placetype":"neighbourhood",
    "wof:population":3785,
    "zs:area_m":4392446.718059,
    "zs:blockids":[
        370210022041018,
        370210022041054,
        370210022041053,
        370210022061017,
        370210022041019,
        370210022042006,
        370210022061019,
        370210022041022,
        370210022042004,
        370210022042007,
        370210022061008,
        370210022042027,
        370210022061014,
        370210022044000,
        370210022044001,
        370210022061018,
        370210022041020,
        370210022044002,
        370210022042028,
        370210022061021,
        370210022061020,
        370210022041052,
        370210022061016,
        370210022041023,
        370210022042026,
        370210022041014
    ],
    "zs:housing10":2432,
    "zs:label":"Bennington Oaks Ii",
    "zs:pop10":3785
},
  "geometry": {"coordinates":[-82.516993,35.508092],"type":"Point"}
}