{
  "type": "Feature",
  "properties": {
    "gn:admin1_code":"AL",
    "gn:admin2_code":"63.0",
    "gn:asciiname":"West Greene",
    "gn:country_code":"US",
    "gn:dem":50,
    "gn:elevation":"50.0",
    "gn:feature_class":"P",
    "gn:feature_code":"PPL",
    "gn:name":"West Greene",
    "gn:population":0,
    "gn:timezone":"America/Chicago",
    "iso:country":"US",
    "name:eng_x_preferred":[
        "West Greene"
    ],
    "name:fas_x_preferred":[
        "\u0648\u0633\u062a \u06af\u0631\u06cc\u0646"
    ],
    "name:und_x_variant":[
        "Hopewell",
        "Boston",
        "Old West Greene",
        "Westgreene"
    ],
    "name:urd_x_preferred":[
        "\u0628\u0648\u0633\u0679\u0646"
    ],
    "name:zho_x_preferred":[
        "\u897f\u683c\u6797"
    ],
    "wof:name":"West Greene",
    "wof:placetype":"locality"
},
  "geometry": {"coordinates":[-88.0853,32.92374],"type":"Point"}
}