{
  "type": "Feature",
  "properties": {
    "gn:admin1_code":"AZ",
    "gn:admin2_code":"15.0",
    "gn:asciiname":"Nagles Crossing",
    "gn:country_code":"US",
    "gn:dem":1370,
    "gn:elevation":"1367.0",
    "gn:feature_class":"P",
    "gn:feature_code":"PPL",
    "gn:name":"Nagles Crossing",
    "gn:population":0,
    "gn:timezone":"America/Phoenix",
    "iso:country":"US",
    "wof:name":"Nagles Crossing",
    "wof:placetype":"locality"
},
  "geometry": {"coordinates":[-112.57964,36.86388],"type":"Point"}
}