{
  "type": "Feature",
  "properties": {
    "gn:admin1_code":"TX",
    "gn:admin2_code":"395.0",
    "gn:asciiname":"Valley Junction",
    "gn:country_code":"US",
    "gn:dem":85,
    "gn:elevation":"84.0",
    "gn:feature_class":"P",
    "gn:feature_code":"PPL",
    "gn:name":"Valley Junction",
    "gn:population":0,
    "gn:timezone":"America/Chicago",
    "iso:country":"US",
    "wof:name":"Valley Junction",
    "wof:placetype":"locality"
},
  "geometry": {"coordinates":[-96.63775,30.84186],"type":"Point"}
}