{
  "type": "Feature",
  "properties": {
    "gn:admin1_code":"FL",
    "gn:admin2_code":"57",
    "gn:asciiname":"Alafia Oaks",
    "gn:country_code":"US",
    "gn:dem":7,
    "gn:elevation":"2.0",
    "gn:feature_class":"P",
    "gn:feature_code":"PPL",
    "gn:name":"Alafia Oaks",
    "gn:population":0,
    "gn:timezone":"America/New_York",
    "iso:country":"US",
    "wof:name":"Alafia Oaks",
    "wof:placetype":"locality"
},
  "geometry": {"coordinates":[-82.3207,27.8687],"type":"Point"}
}