{
  "type": "Feature",
  "properties": {
    "gn:admin1_code":"TN",
    "gn:admin2_code":"39.0",
    "gn:asciiname":"Cherokee Heights",
    "gn:country_code":"US",
    "gn:dem":154,
    "gn:elevation":"143.0",
    "gn:feature_class":"P",
    "gn:feature_code":"PPL",
    "gn:name":"Cherokee Heights",
    "gn:population":0,
    "gn:timezone":"America/Chicago",
    "iso:country":"US",
    "wof:name":"Cherokee Heights",
    "wof:placetype":"locality"
},
  "geometry": {"coordinates":[-88.02781,35.73757],"type":"Point"}
}