{
  "type": "Feature",
  "properties": {
    "iso:country":"US",
    "name:cat_x_preferred":[
        "Clifton"
    ],
    "name:ceb_x_preferred":[
        "Clifton"
    ],
    "name:ces_x_preferred":[
        "Clifton"
    ],
    "name:deu_x_preferred":[
        "Clifton"
    ],
    "name:eng_x_preferred":[
        "Clifton"
    ],
    "name:fas_x_preferred":[
        "\u06a9\u0644\u06cc\u0641\u062a\u0648\u0646"
    ],
    "name:fin_x_preferred":[
        "Clifton"
    ],
    "name:fra_x_preferred":[
        "Clifton"
    ],
    "name:hun_x_preferred":[
        "Clifton"
    ],
    "name:ita_x_preferred":[
        "Clifton"
    ],
    "name:jpn_x_preferred":[
        "\u30af\u30ea\u30d5\u30c8\u30f3"
    ],
    "name:kor_x_preferred":[
        "\ud074\ub9ac\ud504\ud134"
    ],
    "name:nld_x_preferred":[
        "Clifton"
    ],
    "name:pol_x_preferred":[
        "Clifton"
    ],
    "name:por_x_preferred":[
        "Clifton"
    ],
    "name:slk_x_preferred":[
        "Clifton"
    ],
    "name:spa_x_preferred":[
        "Clifton"
    ],
    "name:swe_x_preferred":[
        "Clifton"
    ],
    "name:ukr_x_preferred":[
        "\u041a\u043b\u0456\u0444\u0442\u043e\u043d"
    ],
    "name:vol_x_preferred":[
        "Clifton"
    ],
    "name:zho_x_preferred":[
        "\u514b\u5229\u592b\u9813"
    ],
    "qs:gn_adm0_cc":"US",
    "qs:gn_fcode":"PPL",
    "qs:gn_local":5216895,
    "qs:gn_nam_loc":"upper saint clair",
    "qs:gn_namadm1":"PA",
    "qs:gn_name":"Clifton",
    "qs:local_max":298,
    "qs:local_sum":568,
    "qs:localhoods":4,
    "qs:name":"Clifton",
    "qs:name_adm0":"United States",
    "qs:name_adm1":"Pennsylvania",
    "qs:name_adm2":"Allegheny",
    "qs:name_local":"Upper St. Clair",
    "qs:photo_max":11,
    "qs:photo_sum":21,
    "qs:placetype":"Suburb",
    "qs:quad_count":6,
    "qs:woe_adm0":23424977,
    "qs:woe_adm1":2347597,
    "qs:woe_adm2":12589729,
    "qs:woe_lau":0,
    "qs:woe_local":23417953,
    "qs:woe_ver":"7.10.0",
    "wd:wordcount":589,
    "wof:lang":[
        "eng"
    ],
    "wof:name":"Clifton",
    "wof:placetype":"neighbourhood",
    "wof:population":1434,
    "zs:blockids":[
        420034741021023,
        420034742022003,
        420034742022005,
        420034741021028,
        420034741021027,
        420034742022004,
        420034742022020,
        420034742022001,
        420034742022000,
        420034741022009,
        420034741022022,
        420034741021021,
        420034741021025,
        420034741021019,
        420034741021026,
        420034741021024,
        420034741021020,
        420034741022010,
        420034741022018,
        420034742022019,
        420034741021030,
        420034742022021
    ],
    "zs:housing10":557,
    "zs:pop10":1434
},
  "geometry": {"coordinates":[-80.06910999999999,40.338932],"type":"Point"}
}