{
  "type": "Feature",
  "properties": {
    "gn:admin1_code":"AL",
    "gn:admin2_code":"9",
    "gn:asciiname":"Gurley",
    "gn:country_code":"US",
    "gn:dem":206,
    "gn:elevation":"194.0",
    "gn:feature_class":"P",
    "gn:feature_code":"PPL",
    "gn:name":"Gurley",
    "gn:population":886,
    "gn:timezone":"America/Chicago",
    "iso:country":"US",
    "name:ceb_x_preferred":[
        "Gurley"
    ],
    "name:deu_x_preferred":[
        "Gurley"
    ],
    "name:ido_x_preferred":[
        "Gurley"
    ],
    "name:ita_x_preferred":[
        "Gurley"
    ],
    "name:nld_x_preferred":[
        "Gurley"
    ],
    "name:spa_x_preferred":[
        "Gurley"
    ],
    "name:srp_x_preferred":[
        "\u0413\u0435\u0440\u043b\u0438"
    ],
    "name:vol_x_preferred":[
        "Gurley"
    ],
    "wof:name":"Gurley",
    "wof:placetype":"locality",
    "wof:population":886
},
  "geometry": {"coordinates":[-86.63776999999997,33.77649],"type":"Point"}
}