{
  "type": "Feature",
  "properties": {
    "iso:country":"US",
    "name:eng_x_preferred":[
        "Windemere North"
    ],
    "wof:name":"Windemere North",
    "wof:placetype":"neighbourhood",
    "wof:population":3917,
    "zs:blockids":[
        370690605012060,
        370690605012046,
        370690605011036,
        370690605012019,
        370690605012031,
        370690605012045,
        370690605012021,
        370690605012054,
        370690605012053,
        370690605012040,
        370690605012011,
        370690605012075,
        370690605012025,
        370690605012042,
        370690605012029,
        370690605012049,
        370690605012069,
        370690605012020,
        370690605012038,
        370690605011038,
        370690605012026,
        370690605012000,
        370690605011030,
        370690605012023,
        370690605012041,
        370690605012039,
        370690605012055,
        370690605012067,
        370690605012066,
        370690605012051,
        370690605012071,
        370690605012014,
        370690605012012,
        370690605012070,
        370690605012008,
        370690605011035,
        370690605012013,
        370690605012052,
        370690605012032,
        370690605012043,
        370690605012056,
        370690605012003,
        370690605012028,
        370690605012074,
        370690605012022,
        370690605012002,
        370690605012017,
        370690605012065,
        370690605012016,
        370690605012009,
        370690605012072,
        370690605012018,
        370690605012035,
        370690605012010,
        370690605012048,
        370690605012064,
        370690605012015,
        370690605012034,
        370690605012037,
        370690605012004,
        370690605012036,
        370690605012061,
        370690605012001,
        370690605011034,
        370690605012024,
        370690605012033,
        370690605012050,
        370690605012030,
        370690605012044,
        370690605012047,
        370690605012027,
        370690605012068,
        371830542041020
    ],
    "zs:housing10":1513,
    "zs:label":"Windemere North",
    "zs:pop10":3917
},
  "geometry": {"coordinates":[-78.511399,36.029422],"type":"Point"}
}