{
  "type": "Feature",
  "properties": {
    "gn:admin1_code":"KS",
    "gn:admin2_code":"43.0",
    "gn:admin3_code":"34400.0",
    "gn:asciiname":"Highland",
    "gn:country_code":"US",
    "gn:dem":326,
    "gn:elevation":"320.0",
    "gn:feature_class":"P",
    "gn:feature_code":"PPL",
    "gn:name":"Highland",
    "gn:population":1010,
    "gn:timezone":"America/Chicago",
    "iso:country":"US",
    "name:ara_x_preferred":[
        "\u0647\u0627\u064a\u0644\u0627\u0646\u062f"
    ],
    "name:cat_x_preferred":[
        "Highland"
    ],
    "name:ceb_x_preferred":[
        "Highland"
    ],
    "name:eus_x_preferred":[
        "Highland"
    ],
    "name:fas_x_preferred":[
        "\u0647\u0627\u06cc\u0644\u0646\u062f\u060c \u06a9\u0627\u0646\u0632\u0627\u0633"
    ],
    "name:fas_x_variant":[
        "\u0647\u0627\u06cc\u0644\u0646\u062f"
    ],
    "name:hat_x_preferred":[
        "Highland"
    ],
    "name:hin_x_preferred":[
        "\u0939\u093e\u0908\u0932\u0948\u0902\u0921"
    ],
    "name:ido_x_preferred":[
        "Highland"
    ],
    "name:ind_x_preferred":[
        "Highland"
    ],
    "name:ita_x_preferred":[
        "Highland"
    ],
    "name:mlg_x_preferred":[
        "Highland"
    ],
    "name:nld_x_preferred":[
        "Highland"
    ],
    "name:pol_x_preferred":[
        "Highland"
    ],
    "name:por_x_preferred":[
        "Highland"
    ],
    "name:spa_x_preferred":[
        "Highland"
    ],
    "name:srp_x_preferred":[
        "\u0425\u0430\u0458\u043b\u0430\u043d\u0434"
    ],
    "name:swe_x_preferred":[
        "Highland"
    ],
    "name:tur_x_preferred":[
        "Highland"
    ],
    "name:uzb_x_preferred":[
        "Highland"
    ],
    "name:vie_x_preferred":[
        "Highland"
    ],
    "name:vol_x_preferred":[
        "Highland"
    ],
    "wof:name":"Highland",
    "wof:placetype":"locality",
    "wof:population":1010
},
  "geometry": {"coordinates":[-95.2697,39.85972],"type":"Point"}
}