{
  "type": "Feature",
  "properties": {
    "gn:admin1_code":"OH",
    "gn:admin2_code":"71.0",
    "gn:admin3_code":"43190.0",
    "gn:asciiname":"Lynwood Terrace",
    "gn:country_code":"US",
    "gn:dem":316,
    "gn:elevation":"316.0",
    "gn:feature_class":"P",
    "gn:feature_code":"PPL",
    "gn:name":"Lynwood Terrace",
    "gn:population":0,
    "gn:timezone":"America/New_York",
    "iso:country":"US",
    "wof:name":"Lynwood Terrace",
    "wof:placetype":"locality"
},
  "geometry": {"coordinates":[-83.61055999999998,39.21333],"type":"Point"}
}