{
  "type": "Feature",
  "properties": {
    "gn:country":"US",
    "gn:fcode":"PPL",
    "gn:population":838,
    "iso:country":"US",
    "name:cat_x_preferred":[
        "Sandisfield"
    ],
    "name:ceb_x_preferred":[
        "Sandisfield"
    ],
    "name:deu_x_preferred":[
        "Sandisfield"
    ],
    "name:eng_x_preferred":[
        "Sandisfield"
    ],
    "name:eus_x_preferred":[
        "Sandisfield"
    ],
    "name:fas_x_preferred":[
        "\u0633\u0646\u062f\u06cc\u0633\u0641\u06cc\u0644\u062f\u060c \u0645\u0627\u0633\u0627\u0686\u0648\u0633\u062a"
    ],
    "name:fas_x_variant":[
        "\u0633\u0646\u062f\u06cc\u0633\u0641\u06cc\u0644\u062f"
    ],
    "name:fra_x_preferred":[
        "Sandisfield"
    ],
    "name:hat_x_preferred":[
        "Sandisfield"
    ],
    "name:hun_x_preferred":[
        "Sandisfield"
    ],
    "name:ita_x_preferred":[
        "Sandisfield"
    ],
    "name:kaz_x_preferred":[
        "\u0421\u0430\u043d\u0434\u0438\u0441\u0444\u0438\u043b\u0434"
    ],
    "name:kir_x_preferred":[
        "\u0421\u0430\u043d\u0434\u0438\u0441\u0444\u0438\u043b\u0434"
    ],
    "name:nld_x_preferred":[
        "Sandisfield"
    ],
    "name:pol_x_preferred":[
        "Sandisfield"
    ],
    "name:spa_x_preferred":[
        "Sandisfield"
    ],
    "name:swe_x_preferred":[
        "Sandisfield"
    ],
    "name:vol_x_preferred":[
        "Sandisfield"
    ],
    "qs_pg:aaroncc":"US",
    "qs_pg:gn_country":"US",
    "qs_pg:gn_fcode":"PPL",
    "qs_pg:gn_pop":838,
    "qs_pg:name":"Sandisfield",
    "qs_pg:name_adm0":"United States",
    "qs_pg:name_adm1":"Massachusetts",
    "qs_pg:photos":24,
    "qs_pg:photos_1k":5,
    "qs_pg:photos_9k":1,
    "qs_pg:photos_9r":2,
    "qs_pg:photos_all":29,
    "qs_pg:photos_sr":1,
    "qs_pg:pop_sr":2,
    "qs_pg:qs_pg_placetype":"locality",
    "qs_pg:qs_pg_placetype_gp":"Town",
    "qs_pg:woe_adm0":23424977,
    "woe:adm0_id":23424977,
    "woe:name_adm0":"United States",
    "woe:name_adm1":"Massachusetts",
    "woe:placetype":"Town",
    "wof:name":"Sandisfield",
    "wof:placetype":"locality",
    "wof:population":838
},
  "geometry": {"coordinates":[-73.14315999999999,42.11259],"type":"Point"}
}