{
  "type": "Feature",
  "properties": {
    "gn:country":"US",
    "gn:fcode":"PPL",
    "gn:population":5653,
    "iso:country":"US",
    "name:ara_x_preferred":[
        "\u0645\u0648\u0631\u064a\u0633\u062a\u0627\u0648\u0646"
    ],
    "name:cat_x_preferred":[
        "Morristown"
    ],
    "name:ceb_x_preferred":[
        "Morristown"
    ],
    "name:dan_x_preferred":[
        "Morristown"
    ],
    "name:deu_x_preferred":[
        "Morristown"
    ],
    "name:eng_x_preferred":[
        "Morristown"
    ],
    "name:eus_x_preferred":[
        "Morristown"
    ],
    "name:fra_x_preferred":[
        "Morristown"
    ],
    "name:hat_x_preferred":[
        "Morristown"
    ],
    "name:ita_x_preferred":[
        "Morristown"
    ],
    "name:jpn_x_preferred":[
        "\u30e2\u30ea\u30b9\u30bf\u30a6\u30f3"
    ],
    "name:pol_x_preferred":[
        "Morristown"
    ],
    "name:rus_x_preferred":[
        "\u041c\u043e\u0440\u0440\u0440\u0438\u0441\u0442\u0430\u0443\u043d"
    ],
    "name:spa_x_preferred":[
        "Morristown"
    ],
    "name:swe_x_preferred":[
        "Morristown"
    ],
    "name:und_x_variant":[
        "Morristown Four Corners"
    ],
    "name:uzb_x_preferred":[
        "Morristown"
    ],
    "name:vol_x_preferred":[
        "Morristown"
    ],
    "qs_pg:aaroncc":"US",
    "qs_pg:gn_country":"US",
    "qs_pg:gn_fcode":"PPL",
    "qs_pg:gn_pop":5653,
    "qs_pg:name":"Morristown",
    "qs_pg:name_adm0":"United States",
    "qs_pg:name_adm1":"Vermont",
    "qs_pg:photos":22,
    "qs_pg:photos_1k":4,
    "qs_pg:photos_9k":1,
    "qs_pg:photos_9r":1,
    "qs_pg:photos_all":22,
    "qs_pg:photos_sr":1,
    "qs_pg:pop_sr":5,
    "qs_pg:qs_pg_placetype":"locality",
    "qs_pg:qs_pg_placetype_gp":"Town",
    "qs_pg:woe_adm0":23424977,
    "woe:adm0_id":23424977,
    "woe:name_adm0":"United States",
    "woe:name_adm1":"Vermont",
    "woe:placetype":"Town",
    "wof:name":"Morristown",
    "wof:placetype":"locality",
    "wof:population":5653
},
  "geometry": {"coordinates":[-72.62372999999999,44.55727],"type":"Point"}
}