{
  "type": "Feature",
  "properties": {
    "iso:country":"US",
    "name:eng_x_preferred":[
        "West Park Knolls"
    ],
    "name:eng_x_variant":[
        "West Park Knls"
    ],
    "qs:gn_adm0_cc":"US",
    "qs:gn_local":4905687,
    "qs:gn_nam_loc":"Peoria, Peoria, Illinois, US",
    "qs:gn_namadm1":"IL",
    "qs:local_max":4309,
    "qs:local_sum":14898,
    "qs:localhoods":39,
    "qs:name":"West Park Knolls",
    "qs:name_adm0":"United States",
    "qs:name_adm1":"Illinois",
    "qs:name_adm2":"Peoria",
    "qs:name_local":"Peoria",
    "qs:photo_max":32,
    "qs:photo_sum":197,
    "qs:placetype":"Suburb",
    "qs:quad_count":20,
    "qs:woe_adm0":23424977,
    "qs:woe_adm1":2347572,
    "qs:woe_adm2":12588149,
    "qs:woe_lau":0,
    "qs:woe_local":2470456,
    "qs:woe_ver":"7.10.0",
    "wof:lang":[
        "eng"
    ],
    "wof:name":"West Park Knolls",
    "wof:placetype":"neighbourhood",
    "wof:population":2586,
    "zs:blockids":[
        171430028003014,
        171430030002006,
        171430028003034,
        171430028002018,
        171430028003030,
        171430028002011,
        171430028001008,
        171430030002001,
        171430030005013,
        171430030005007,
        171430030003014,
        171430028002005,
        171430030002004,
        171430030002002,
        171430028003011,
        171430028002001,
        171430028002012,
        171430028001007,
        171430028002020,
        171430028003013,
        171430028002017,
        171430030003019,
        171430030002007,
        171430030003020,
        171430028003000,
        171430030002008,
        171430028002014,
        171430028002013,
        171430028002004,
        171430028002021,
        171430028002002,
        171430028002010,
        171430028003009,
        171430028003023,
        171430028002015,
        171430028001005,
        171430027022001,
        171430028003012,
        171430028003010,
        171430030002003,
        171430027022002,
        171430028002019,
        171430028002009,
        171430028003008,
        171430030005011,
        171430030003018,
        171430030002005,
        171430028002000,
        171430028001001,
        171430028001002,
        171430028001006,
        171430028003026,
        171430028003029,
        171430027022000,
        171430030005010,
        171430030003013,
        171430028002016,
        171430028001003,
        171430030003016,
        171430030003017,
        171430028003024,
        171430028002003,
        171430028003025,
        171430028001009
    ],
    "zs:housing10":1334,
    "zs:pop10":2586
},
  "geometry": {"coordinates":[-89.632094,40.745637],"type":"Point"}
}