{
  "type": "Feature",
  "properties": {
    "gn:admin1_code":"WV",
    "gn:admin2_code":"077",
    "gn:asciiname":"Laurel Run",
    "gn:country_code":"US",
    "gn:dem":464,
    "gn:elevation":"461.0",
    "gn:feature_class":"P",
    "gn:feature_code":"PPL",
    "gn:name":"Laurel Run",
    "gn:population":0,
    "gn:timezone":"America/New_York",
    "iso:country":"US",
    "wof:name":"Laurel Run",
    "wof:placetype":"locality"
},
  "geometry": {"coordinates":[-79.72255,39.65119],"type":"Point"}
}