{
  "type": "Feature",
  "properties": {
    "gn:admin1_code":"NC",
    "gn:admin2_code":"71.0",
    "gn:admin3_code":"91216.0",
    "gn:asciiname":"Monterey Park",
    "gn:country_code":"US",
    "gn:dem":228,
    "gn:elevation":"230.0",
    "gn:feature_class":"P",
    "gn:feature_code":"PPL",
    "gn:name":"Monterey Park",
    "gn:population":0,
    "gn:timezone":"America/New_York",
    "iso:country":"US",
    "name:ceb_x_preferred":[
        "Monterey Park"
    ],
    "name:pol_x_preferred":[
        "Monterey Park"
    ],
    "name:rus_x_preferred":[
        "\u041c\u043e\u043d\u0442\u0435\u0440\u0435\u0439-\u041f\u0430\u0440\u043a"
    ],
    "name:srp_x_preferred":[
        "\u041c\u043e\u043d\u0442\u0435\u0440\u0435\u0458 \u041f\u0430\u0440\u043a"
    ],
    "wof:name":"Monterey Park",
    "wof:placetype":"locality"
},
  "geometry": {"coordinates":[-81.14286,35.29708],"type":"Point"}
}