{
  "type": "Feature",
  "properties": {
    "iso:country":"US",
    "name:eng_x_preferred":[
        "Chestnut Acres"
    ],
    "wof:name":"Chestnut Acres",
    "wof:placetype":"neighbourhood",
    "wof:population":6005,
    "zs:blockids":[
        330150038022007,
        330150038021014,
        330150038021020,
        330150038012014,
        330150039021021,
        330150038022000,
        330150038022001,
        330150038022012,
        330150039021016,
        330150039021018,
        330150038022016,
        330150038022017,
        330150038021015,
        330150038022004,
        330150038022011,
        330150038021013,
        330150038021019,
        330150038022005,
        330150039021013,
        330150038022014,
        330150039021017,
        330150038022006,
        330150038022003,
        330150038022013,
        330150038022008,
        330150039021015,
        330150038022009,
        330150038022010,
        330150038021018,
        330150038022015,
        330150039021022,
        330150039021006,
        330150039021002,
        330150038012015,
        330150038012016,
        330150039021014,
        330150038022002,
        330110121002002,
        330110131004020,
        330110131004006,
        330110131004001,
        330110131003004,
        330110121004007,
        330110121003002,
        330110131004011,
        330110131004019,
        330110121004017,
        330110121003000,
        330110131004033,
        330110131003000,
        330110121004015,
        330110121004016,
        330110121004004,
        330110121004003,
        330110121004002,
        330110131004002,
        330110131004004,
        330110131003006,
        330110121003013,
        330110131004034,
        330110131004000,
        330110131004003,
        330110131004023,
        330110121004018,
        330110131003017,
        330110121002001,
        330110121002000,
        330110121002032,
        330110131003010,
        330110121004005,
        330110131003002,
        330110131004035,
        330110131004005,
        330110131004017,
        330110131004009,
        330110121004000,
        330110131003001,
        330110121004001,
        330110131004008,
        330110131004021,
        330110121004014,
        330110121003006,
        330110121004006,
        330110131004015,
        330110131003005,
        330110131004018,
        330110131003003,
        330110131004007,
        330110131004014,
        330110131004032,
        330110131004022,
        330110131004010
    ],
    "zs:housing10":2090,
    "zs:label":"Chestnut Acres",
    "zs:pop10":6005
},
  "geometry": {"coordinates":[-71.41570900000001,42.83822],"type":"Point"}
}