{
  "type": "Feature",
  "properties": {
    "iso:country":"US",
    "name:azb_x_preferred":[
        "\u0627\u06cc\u0648\u0634\u0627\u0645"
    ],
    "name:bul_x_preferred":[
        "\u0418\u0432\u0448\u0430\u043c"
    ],
    "name:cat_x_preferred":[
        "Evesham"
    ],
    "name:ceb_x_preferred":[
        "Evesham"
    ],
    "name:cym_x_preferred":[
        "Evesham"
    ],
    "name:deu_x_preferred":[
        "Evesham"
    ],
    "name:eng_x_preferred":[
        "Evesham"
    ],
    "name:epo_x_preferred":[
        "Evesham"
    ],
    "name:fas_x_preferred":[
        "\u0627\u06cc\u0648\u0634\u0627\u0645"
    ],
    "name:fin_x_preferred":[
        "Evesham"
    ],
    "name:fra_x_preferred":[
        "Evesham"
    ],
    "name:gle_x_preferred":[
        "Evesham"
    ],
    "name:ita_x_preferred":[
        "Evesham"
    ],
    "name:nld_x_preferred":[
        "Evesham"
    ],
    "name:nno_x_preferred":[
        "Evesham"
    ],
    "name:pol_x_preferred":[
        "Evesham"
    ],
    "name:ron_x_preferred":[
        "Evesham"
    ],
    "name:spa_x_preferred":[
        "Evesham"
    ],
    "name:swe_x_preferred":[
        "Evesham"
    ],
    "name:vol_x_preferred":[
        "Evesham"
    ],
    "qs_pg:aaroncc":"US",
    "qs_pg:name":"Evesham",
    "qs_pg:name_adm0":"United States",
    "qs_pg:name_adm1":"New Jersey",
    "qs_pg:photos":98,
    "qs_pg:photos_1k":20,
    "qs_pg:photos_9k":6,
    "qs_pg:photos_9r":7,
    "qs_pg:photos_all":1262,
    "qs_pg:photos_sr":3,
    "qs_pg:pop_sr":0,
    "qs_pg:qs_pg_placetype":"locality",
    "qs_pg:qs_pg_placetype_gp":"Town",
    "qs_pg:woe_adm0":23424977,
    "woe:adm0_id":23424977,
    "woe:name_adm0":"United States",
    "woe:name_adm1":"New Jersey",
    "woe:placetype":"Town",
    "wof:name":"Evesham",
    "wof:placetype":"locality",
    "wof:statistical_gore":1
},
  "geometry": {"coordinates":[-74.87895,39.850094],"type":"Point"}
}