{
  "type": "Feature",
  "properties": {
    "gn:admin1_code":"KS",
    "gn:admin2_code":"35.0",
    "gn:admin3_code":"67400.0",
    "gn:asciiname":"Maple City",
    "gn:country_code":"US",
    "gn:dem":414,
    "gn:elevation":"409.0",
    "gn:feature_class":"P",
    "gn:feature_code":"PPL",
    "gn:name":"Maple City",
    "gn:population":0,
    "gn:timezone":"America/Chicago",
    "iso:country":"US",
    "name:azb_x_preferred":[
        "\u0645\u06cc\u067e\u0644 \u0633\u06cc\u062a\u06cc"
    ],
    "name:eng_x_preferred":[
        "Maple City"
    ],
    "name:fas_x_preferred":[
        "\u0645\u06cc\u067e\u0644 \u0633\u06cc\u062a\u06cc"
    ],
    "name:und_x_variant":[
        "Clarence",
        "Maple"
    ],
    "name:urd_x_preferred":[
        "\u0645\u06cc\u067e\u0644 \u0633\u0679\u06cc"
    ],
    "name:vol_x_preferred":[
        "Maple City"
    ],
    "name:zho_x_preferred":[
        "\u6885\u666e\u723e\u57ce"
    ],
    "wof:name":"Maple City",
    "wof:placetype":"locality"
},
  "geometry": {"coordinates":[-96.76836,37.05586],"type":"Point"}
}