{
  "type": "Feature",
  "properties": {
    "gn:admin1_code":"AL",
    "gn:admin2_code":"111.0",
    "gn:asciiname":"Potash",
    "gn:country_code":"US",
    "gn:dem":424,
    "gn:elevation":"423.0",
    "gn:feature_class":"P",
    "gn:feature_code":"PPL",
    "gn:name":"Potash",
    "gn:population":0,
    "gn:timezone":"America/Chicago",
    "iso:country":"US",
    "name:afr_x_preferred":[
        "Potas"
    ],
    "name:ara_x_preferred":[
        "\u0628\u0648\u062a\u0627\u0633"
    ],
    "name:deu_x_preferred":[
        "Kalisalz"
    ],
    "name:eus_x_preferred":[
        "Potasa"
    ],
    "name:fas_x_preferred":[
        "\u067e\u062a\u0627\u0634"
    ],
    "name:fra_x_preferred":[
        "Potasse"
    ],
    "name:gle_x_preferred":[
        "Potais"
    ],
    "name:heb_x_preferred":[
        "\u05d0\u05e9\u05dc\u05d2"
    ],
    "name:ind_x_preferred":[
        "Garam abu"
    ],
    "name:nld_x_preferred":[
        "Potas"
    ],
    "name:nor_x_preferred":[
        "Pottaske"
    ],
    "name:oci_x_preferred":[
        "Potassa"
    ],
    "name:pol_x_preferred":[
        "Pota\u017c"
    ],
    "name:rus_x_preferred":[
        "\u041a\u0430\u043b\u0438\u0439\u043d\u0430\u044f \u0441\u043e\u043b\u044c"
    ],
    "name:srp_x_preferred":[
        "Kalijumska \u0111ubriva"
    ],
    "name:swe_x_preferred":[
        "Pottaska"
    ],
    "name:ukr_x_preferred":[
        "\u041a\u0430\u043b\u0456\u0439\u043d\u0456 \u0441\u043e\u043b\u0456"
    ],
    "wof:name":"Potash",
    "wof:placetype":"locality"
},
  "geometry": {"coordinates":[-85.35245,33.27734],"type":"Point"}
}