{
  "type": "Feature",
  "properties": {
    "gn:country":"US",
    "gn:fcode":"PPL",
    "gn:population":3307,
    "iso:country":"US",
    "qs_pg:aaroncc":"US",
    "qs_pg:gn_country":"US",
    "qs_pg:gn_fcode":"PPL",
    "qs_pg:gn_pop":3307,
    "qs_pg:name":"Eastlawn Gardens",
    "qs_pg:name_adm0":"United States",
    "qs_pg:name_adm1":"Pennsylvania",
    "qs_pg:photos_9r":0,
    "qs_pg:photos_sr":0,
    "qs_pg:pop_sr":4,
    "qs_pg:qs_pg_placetype":"neighbourhood",
    "qs_pg:qs_pg_placetype_gp":"Suburb",
    "qs_pg:woe_adm0":23424977,
    "woe:adm0_id":23424977,
    "woe:name_adm0":"United States",
    "woe:name_adm1":"Pennsylvania",
    "woe:placetype":"Suburb",
    "wof:name":"Eastlawn Gardens",
    "wof:placetype":"neighbourhood",
    "wof:population":3307
},
  "geometry": {"coordinates":[-75.29573000000001,40.75065],"type":"Point"}
}