{
  "type": "Feature",
  "properties": {
    "iso:country":"US",
    "name:eng_x_preferred":[
        "Creekside Commons"
    ],
    "wof:name":"Creekside Commons",
    "wof:placetype":"neighbourhood",
    "wof:population":692,
    "zs:area_m":3951159.981752,
    "zs:blockids":[
        191030103023046,
        191030103023064,
        191030103023042,
        191030103023047,
        191030103023051,
        191030103023031,
        191030103023050,
        191030103023048,
        191030103023052,
        191030103023045,
        191030103023049,
        191030103023053,
        191030103023030,
        191030103023069
    ],
    "zs:housing10":278,
    "zs:label":"Creekside Commons",
    "zs:pop10":692
},
  "geometry": {"coordinates":[-91.58425699999999,41.727947],"type":"Point"}
}