{
  "type": "Feature",
  "properties": {
    "gn:country":"US",
    "gn:fcode":"PPL",
    "gn:population":0,
    "iso:country":"US",
    "name:deu_x_preferred":[
        "Claxton"
    ],
    "name:eng_x_preferred":[
        "Claxton"
    ],
    "name:fas_x_preferred":[
        "\u06a9\u0644\u0627\u06a9\u0633\u062a\u0648\u0646"
    ],
    "name:fra_x_preferred":[
        "Claxton"
    ],
    "name:jpn_x_preferred":[
        "\u30af\u30e9\u30af\u30b9\u30c8\u30f3"
    ],
    "name:und_x_variant":[
        "Wilsons"
    ],
    "name:vol_x_preferred":[
        "Claxton"
    ],
    "qs_pg:aaroncc":"US",
    "qs_pg:gn_country":"US",
    "qs_pg:gn_fcode":"PPL",
    "qs_pg:gn_pop":0,
    "qs_pg:name":"Claxton",
    "qs_pg:name_adm0":"United States",
    "qs_pg:name_adm1":"Tennessee",
    "qs_pg:photos_9r":0,
    "qs_pg:photos_sr":0,
    "qs_pg:pop_sr":0,
    "qs_pg:qs_pg_placetype":"locality",
    "qs_pg:qs_pg_placetype_gp":"Town",
    "qs_pg:woe_adm0":23424977,
    "woe:adm0_id":23424977,
    "woe:name_adm0":"United States",
    "woe:name_adm1":"Tennessee",
    "woe:placetype":"Town",
    "wof:name":"Claxton",
    "wof:placetype":"locality"
},
  "geometry": {"coordinates":[-84.10992,36.04175],"type":"Point"}
}