{
  "type": "Feature",
  "properties": {
    "gn:admin1_code":"MD",
    "gn:admin2_code":"21",
    "gn:asciiname":"Discovery-Spring Garden",
    "gn:country_code":"US",
    "gn:dem":95,
    "gn:elevation":"91.0",
    "gn:feature_class":"P",
    "gn:feature_code":"PPL",
    "gn:name":"Discovery-Spring Garden",
    "gn:population":0,
    "gn:timezone":"America/New_York",
    "iso:country":"US",
    "name:azb_x_preferred":[
        "\u062f\u06cc\u0633\u06a9\u0627\u0648\u0631\u06cc-\u0627\u0633\u067e\u0631\u06cc\u0646\u0642 \u0642\u0627\u0631\u062f\u0646"
    ],
    "name:cat_x_preferred":[
        "Discovery-Spring Garden"
    ],
    "name:ceb_x_preferred":[
        "Discovery-Spring Garden"
    ],
    "name:eus_x_preferred":[
        "Discovery-Spring Garden"
    ],
    "name:fas_x_preferred":[
        "\u062f\u06cc\u0633\u06a9\u0627\u0648\u0631\u06cc-\u0627\u0633\u067e\u0631\u06cc\u0646\u06af \u06af\u0627\u0631\u062f\u0646"
    ],
    "name:kaz_x_preferred":[
        "\u0414\u0438\u0441\u043a\u043e\u0432\u044d\u0440\u0438-\u0421\u043f\u0440\u0438\u043d\u0433 \u0413\u0430\u0440\u0434\u044d\u043d"
    ],
    "name:kir_x_preferred":[
        "\u0414\u0438\u0441\u043a\u043e\u0432\u044d\u0440\u0438-\u0421\u043f\u0440\u0438\u043d\u0433 \u0413\u0430\u0440\u0434\u044d\u043d"
    ],
    "name:nld_x_preferred":[
        "Discovery-Spring Garden"
    ],
    "name:por_x_preferred":[
        "Discovery-Spring Garden"
    ],
    "name:srp_x_preferred":[
        "\u0414\u0438\u0441\u043a\u0430\u0432\u0435\u0440\u0438-\u0421\u043f\u0440\u0438\u043d\u0433 \u0413\u0430\u0440\u0434\u0435\u043d"
    ],
    "name:und_x_variant":[
        "Discovery-Spring Garden CDP"
    ],
    "name:uzb_x_preferred":[
        "Discovery-Spring Garden"
    ],
    "name:vol_x_preferred":[
        "Discovery-Spring Garden"
    ],
    "wof:name":"Discovery-Spring Garden",
    "wof:placetype":"locality"
},
  "geometry": {"coordinates":[-77.35915,39.46164],"type":"Point"}
}