{
  "type": "Feature",
  "properties": {
    "gn:admin1_code":"IL",
    "gn:admin2_code":"197",
    "gn:admin3_code":"81035.0",
    "gn:asciiname":"Rose Hill Farms",
    "gn:country_code":"US",
    "gn:dem":205,
    "gn:elevation":"201.0",
    "gn:feature_class":"P",
    "gn:feature_code":"PPL",
    "gn:name":"Rose Hill Farms",
    "gn:population":0,
    "gn:timezone":"America/Chicago",
    "iso:country":"US",
    "wof:name":"Rose Hill Farms",
    "wof:placetype":"locality"
},
  "geometry": {"coordinates":[-88.16806,41.70611],"type":"Point"}
}