{
  "type": "Feature",
  "properties": {
    "iso:country":"US",
    "name:cat_x_preferred":[
        "Bosc Nacional Cherokee"
    ],
    "name:deu_x_preferred":[
        "Cherokee National Forest"
    ],
    "name:eng_x_preferred":[
        "Cherokee Forest"
    ],
    "name:fra_x_preferred":[
        "For\u00eat nationale de Cherokee"
    ],
    "wd:wordcount":591,
    "wof:name":"Cherokee Forest",
    "wof:placetype":"neighbourhood",
    "wof:population":128,
    "zs:area_m":347730.018932,
    "zs:blockids":[
        450770108031012,
        450770108031025,
        450770108031030,
        450770108031048
    ],
    "zs:housing10":66,
    "zs:label":"Cherokee Forest",
    "zs:pop10":128
},
  "geometry": {"coordinates":[-82.602935,34.82273],"type":"Point"}
}