{
  "type": "Feature",
  "properties": {
    "gn:admin1_code":"PA",
    "gn:admin2_code":"11",
    "gn:admin3_code":"86056.0",
    "gn:asciiname":"Country Ridge Estates",
    "gn:country_code":"US",
    "gn:dem":130,
    "gn:elevation":"135.0",
    "gn:feature_class":"P",
    "gn:feature_code":"PPL",
    "gn:name":"Country Ridge Estates",
    "gn:population":0,
    "gn:timezone":"America/New_York",
    "iso:country":"US",
    "wof:name":"Country Ridge Estates",
    "wof:placetype":"locality"
},
  "geometry": {"coordinates":[-76.19299000000002,40.36318],"type":"Point"}
}