{
  "type": "Feature",
  "properties": {
    "gn:gn_country":"US",
    "gn:gn_fcode":"PPL",
    "gn:gn_pop":0,
    "iso:country":"US",
    "name:eng_x_preferred":[
        "Olema"
    ],
    "name:fra_x_preferred":[
        "Olema"
    ],
    "name:jpn_x_preferred":[
        "\u30aa\u30ec\u30de"
    ],
    "name:nld_x_preferred":[
        "Olema"
    ],
    "name:unk_x_variant":[
        "Olemus"
    ],
    "name:vol_x_preferred":[
        "Olema"
    ],
    "qs_pg:aaroncc":"US",
    "qs_pg:gn_country":"US",
    "qs_pg:gn_fcode":"PPL",
    "qs_pg:gn_pop":0,
    "qs_pg:name":"Olema",
    "qs_pg:name_adm0":"United States",
    "qs_pg:name_adm1":"California",
    "qs_pg:photos":3815,
    "qs_pg:photos_1k":773,
    "qs_pg:photos_9k":17,
    "qs_pg:photos_9r":12,
    "qs_pg:photos_all":3815,
    "qs_pg:photos_sr":21,
    "qs_pg:pop_sr":0,
    "qs_pg:qs_pg_placetype":"locality",
    "qs_pg:qs_pg_placetype_gp":"Town",
    "qs_pg:woe_adm0":23424977,
    "woe:adm0_id":23424977,
    "woe:name_adm0":"United States",
    "woe:name_adm1":"California",
    "woe:placetype":"Town",
    "wof:name":"Olema",
    "wof:placetype":"locality"
},
  "geometry": {"coordinates":[-122.78805,38.04076],"type":"Point"}
}