{
  "type": "Feature",
  "properties": {
    "gn:country":"US",
    "gn:fcode":"PPL",
    "gn:population":0,
    "iso:country":"US",
    "name:azb_x_preferred":[
        "\u0627\u0648\u0644\u0645\u0627"
    ],
    "name:eng_x_preferred":[
        "Olema"
    ],
    "name:fas_x_preferred":[
        "\u0627\u0648\u0644\u0645\u0627"
    ],
    "name:fra_x_preferred":[
        "Olema"
    ],
    "name:jpn_x_preferred":[
        "\u30aa\u30ec\u30de"
    ],
    "name:nan_x_preferred":[
        "Olema"
    ],
    "name:nld_x_preferred":[
        "Olema"
    ],
    "name:tur_x_preferred":[
        "Olema"
    ],
    "name:und_x_variant":[
        "Olemus"
    ],
    "name:vol_x_preferred":[
        "Olema"
    ],
    "name:zho_x_preferred":[
        "\u5967\u52d2\u99ac"
    ],
    "qs_pg:aaroncc":"US",
    "qs_pg:gn_country":"US",
    "qs_pg:gn_fcode":"PPL",
    "qs_pg:gn_pop":0,
    "qs_pg:name":"Olema",
    "qs_pg:name_adm0":"United States",
    "qs_pg:name_adm1":"California",
    "qs_pg:photos":3815,
    "qs_pg:photos_1k":773,
    "qs_pg:photos_9k":17,
    "qs_pg:photos_9r":12,
    "qs_pg:photos_all":3815,
    "qs_pg:photos_sr":21,
    "qs_pg:pop_sr":0,
    "qs_pg:qs_pg_placetype":"locality",
    "qs_pg:qs_pg_placetype_gp":"Town",
    "qs_pg:woe_adm0":23424977,
    "woe:adm0_id":23424977,
    "woe:name_adm0":"United States",
    "woe:name_adm1":"California",
    "woe:placetype":"Town",
    "wof:name":"Olema",
    "wof:placetype":"locality"
},
  "geometry": {"coordinates":[-122.78805,38.04076],"type":"Point"}
}