{
  "type": "Feature",
  "properties": {
    "gn:country":"US",
    "gn:fcode":"PPL",
    "gn:population":0,
    "iso:country":"US",
    "name:eng_x_preferred":[
        "Holden"
    ],
    "name:fra_x_preferred":[
        "Holden"
    ],
    "name:und_x_variant":[
        "Coopers Spur"
    ],
    "qs_pg:aaroncc":"US",
    "qs_pg:gn_country":"US",
    "qs_pg:gn_fcode":"PPL",
    "qs_pg:gn_pop":0,
    "qs_pg:name":"Holden",
    "qs_pg:name_adm0":"United States",
    "qs_pg:name_adm1":"Louisiana",
    "qs_pg:photos":23,
    "qs_pg:photos_1k":5,
    "qs_pg:photos_9k":1,
    "qs_pg:photos_9r":1,
    "qs_pg:photos_all":23,
    "qs_pg:photos_sr":1,
    "qs_pg:pop_sr":0,
    "qs_pg:qs_pg_placetype":"locality",
    "qs_pg:qs_pg_placetype_gp":"Town",
    "qs_pg:woe_adm0":23424977,
    "woe:adm0_id":23424977,
    "woe:name_adm0":"United States",
    "woe:name_adm1":"Louisiana",
    "woe:placetype":"Town",
    "wof:name":"Holden",
    "wof:placetype":"locality"
},
  "geometry": {"coordinates":[-90.66925999999999,30.50436],"type":"Point"}
}