{
  "type": "Feature",
  "properties": {
    "gn:elevation":442,
    "iso:country":"US",
    "name:eng_x_preferred":[
        "Wagners Lake"
    ],
    "name:eng_x_variant":[
        "Wagners Lk"
    ],
    "qs:gn_fcode":"PPL",
    "qs:gn_local":0,
    "qs:gn_namadm1":"NE",
    "qs:gn_name":"Wagners Lake",
    "qs:local_max":153,
    "qs:local_sum":153,
    "qs:localhoods":1,
    "qs:name":"Wagners Lake",
    "qs:name_adm0":"United States",
    "qs:name_adm1":"Nebraska",
    "qs:name_adm2":"Platte",
    "qs:name_local":"Columbus",
    "qs:photo_max":105,
    "qs:photo_sum":153,
    "qs:placetype":"Suburb",
    "qs:quad_count":9,
    "qs:woe_adm0":23424977,
    "qs:woe_adm1":2347586,
    "qs:woe_adm2":12589208,
    "qs:woe_lau":0,
    "qs:woe_local":2383654,
    "qs:woe_ver":"7.10.0",
    "wd:wordcount":81,
    "wof:lang":[
        "eng"
    ],
    "wof:name":"Wagners Lake",
    "wof:placetype":"neighbourhood",
    "wof:population":180,
    "zs:blockids":[
        311419652983125,
        311419656002107,
        311419656002143,
        311419656003058,
        311419656002066,
        311419653003022,
        311419653003032,
        311419657003007,
        311419657001022,
        311419656002085,
        311419656002084,
        311419656004059,
        311419657001052,
        311419657004018,
        311419656002050,
        311419657001035,
        311419656002065
    ],
    "zs:housing10":85,
    "zs:pop10":180
},
  "geometry": {"coordinates":[-97.36909,41.424671],"type":"Point"}
}