{
  "type": "Feature",
  "properties": {
    "gn:admin1_code":"WA",
    "gn:admin2_code":"61.0",
    "gn:asciiname":"Hartford",
    "gn:country_code":"US",
    "gn:dem":68,
    "gn:elevation":"69.0",
    "gn:feature_class":"P",
    "gn:feature_code":"PPL",
    "gn:name":"Hartford",
    "gn:population":0,
    "gn:timezone":"America/Los_Angeles",
    "iso:country":"US",
    "wof:name":"Hartford",
    "wof:placetype":"locality"
},
  "geometry": {"coordinates":[-122.05540999999999,48.02204],"type":"Point"}
}