{
  "type": "Feature",
  "properties": {
    "gn:admin1_code":"NY",
    "gn:admin2_code":"17.0",
    "gn:admin3_code":"68055.0",
    "gn:asciiname":"Adams Corner",
    "gn:country_code":"US",
    "gn:dem":419,
    "gn:elevation":"419.0",
    "gn:feature_class":"P",
    "gn:feature_code":"PPL",
    "gn:name":"Adams Corner",
    "gn:population":0,
    "gn:timezone":"America/New_York",
    "iso:country":"US",
    "wof:name":"Adams Corner",
    "wof:placetype":"locality"
},
  "geometry": {"coordinates":[-75.72825,42.42674],"type":"Point"}
}