{
  "type": "Feature",
  "properties": {
    "gn:admin1_code":"PA",
    "gn:admin2_code":"67.0",
    "gn:admin3_code":"77952.0",
    "gn:asciiname":"McCoysville",
    "gn:country_code":"US",
    "gn:dem":182,
    "gn:elevation":"180.0",
    "gn:feature_class":"P",
    "gn:feature_code":"PPL",
    "gn:name":"McCoysville",
    "gn:population":0,
    "gn:timezone":"America/New_York",
    "iso:country":"US",
    "wof:name":"McCoysville",
    "wof:placetype":"locality"
},
  "geometry": {"coordinates":[-77.56777,40.45313],"type":"Point"}
}