{
  "type": "Feature",
  "properties": {
    "gn:admin1_code":"MS",
    "gn:admin2_code":"11.0",
    "gn:asciiname":"Francis",
    "gn:country_code":"US",
    "gn:dem":43,
    "gn:elevation":"48.0",
    "gn:feature_class":"P",
    "gn:feature_code":"PPL",
    "gn:name":"Francis",
    "gn:population":0,
    "gn:timezone":"America/Chicago",
    "iso:country":"US",
    "name:ceb_x_preferred":[
        "Francis"
    ],
    "name:ces_x_preferred":[
        "Francis"
    ],
    "name:deu_x_preferred":[
        "Francis"
    ],
    "name:fra_x_preferred":[
        "Francis"
    ],
    "name:heb_x_preferred":[
        "\u05e4\u05e8\u05e0\u05e1\u05d9\u05e1"
    ],
    "name:isl_x_preferred":[
        "Francis"
    ],
    "name:ita_x_preferred":[
        "Francis"
    ],
    "name:jpn_x_preferred":[
        "\u30d5\u30e9\u30f3\u30b7\u30b9"
    ],
    "name:kor_x_preferred":[
        "\ud504\ub79c\uc2dc\uc2a4"
    ],
    "name:nld_x_preferred":[
        "Francis"
    ],
    "name:pol_x_preferred":[
        "Francis"
    ],
    "name:por_x_preferred":[
        "Francis"
    ],
    "name:rus_x_preferred":[
        "\u0424\u0440\u044d\u043d\u0441\u0438\u0441"
    ],
    "name:spa_x_preferred":[
        "Francis"
    ],
    "name:srp_x_preferred":[
        "\u0424\u0440\u0430\u043d\u0441\u0438\u0441"
    ],
    "name:swe_x_preferred":[
        "Francis"
    ],
    "name:ukr_x_preferred":[
        "\u0424\u0440\u0435\u043d\u0441\u0456\u0441"
    ],
    "name:vol_x_preferred":[
        "Francis"
    ],
    "wof:name":"Francis",
    "wof:placetype":"locality"
},
  "geometry": {"coordinates":[-90.85483000000001,34.08177],"type":"Point"}
}