{
  "type": "Feature",
  "properties": {
    "iso:country":"US",
    "name:arz_x_preferred":[
        "\u0645\u0637\u0627\u0631 \u0628\u0644\u062f\u064a\u0647 \u0628\u0627\u0631\u0646\u0633\u062a\u0627\u0628\u0644"
    ],
    "name:eng_x_preferred":[
        "Barnstable Boardman Polando Airport"
    ],
    "name:eng_x_variant":[
        "HYA",
        "KHYA",
        "Barnstable Municipal Airport",
        "Cape Cod Gateway Airport"
    ],
    "name:fas_x_preferred":[
        "\u0641\u0631\u0648\u062f\u06af\u0627\u0647 \u0634\u0647\u0631\u06cc \u0628\u0627\u0631\u0646\u0633\u062a\u0628\u0644"
    ],
    "name:jpn_x_preferred":[
        "Barnstable\u5e02\u55b6\u7a7a\u6e2f"
    ],
    "name:pol_x_preferred":[
        "Port lotniczy Barnstable"
    ],
    "name:ron_x_preferred":[
        "Aeroportul Municipal Barnstable"
    ],
    "name:tgk_x_preferred":[
        "\u0424\u0443\u0440\u0443\u0434\u0433\u043e\u04b3\u0438 \u0448\u0430\u04b3\u0440\u0435 \u0431\u043e\u0440\u043d\u0441\u0442\u0431\u043b"
    ],
    "name:urd_x_preferred":[
        "\u0628\u0627\u0631\u0646\u0633\u0679\u06cc\u0628\u0644 \u0645\u06cc\u0648\u0646\u0633\u067e\u0644 \u06c1\u0648\u0627\u0626\u06cc \u0627\u0688\u0627"
    ],
    "name:zho_x_preferred":[
        "\u6d77\u6069\u5c3c\u65af"
    ],
    "oa:elevation_ft":"54",
    "oa:type":"medium_airport",
    "wd:wordcount":701,
    "woe:hierarchy":{
        "country_id":23424977,
        "county_id":12588700,
        "planet_id":1,
        "state_id":2347580
    },
    "wof:name":"Barnstable Boardman Polando Airport",
    "wof:placetype":"campus"
},
  "geometry": {"coordinates":[-70.28040300000001,41.6693],"type":"Point"}
}