{
  "type": "Feature",
  "properties": {
    "gn:admin1_code":"AL",
    "gn:admin2_code":"67.0",
    "gn:asciiname":"Screamer",
    "gn:country_code":"US",
    "gn:dem":154,
    "gn:elevation":"148.0",
    "gn:feature_class":"P",
    "gn:feature_code":"PPL",
    "gn:name":"Screamer",
    "gn:population":0,
    "gn:timezone":"America/Chicago",
    "iso:country":"US",
    "name:ara_x_preferred":[
        "\u0635\u064a\u0627\u062d"
    ],
    "name:bre_x_preferred":[
        "Anhimidae"
    ],
    "name:cat_x_preferred":[
        "Anh\u00edmid"
    ],
    "name:ceb_x_preferred":[
        "Anhimidae"
    ],
    "name:ces_x_preferred":[
        "Kami\u0161ovit\u00ed"
    ],
    "name:cym_x_preferred":[
        "Sgrechwyr"
    ],
    "name:dan_x_preferred":[
        "Hyrdefugle"
    ],
    "name:deu_x_preferred":[
        "Wehrv\u00f6gel"
    ],
    "name:epo_x_preferred":[
        "Kriuloj"
    ],
    "name:eus_x_preferred":[
        "Anhimidae"
    ],
    "name:fas_x_preferred":[
        "\u0641\u0631\u06cc\u0627\u062f\u06a9\u0634"
    ],
    "name:fin_x_preferred":[
        "Romiskot"
    ],
    "name:fra_x_preferred":[
        "Anhimidae"
    ],
    "name:heb_x_preferred":[
        "\u05e7\u05de\u05d9\u05e7\u05d9\u05d9\u05dd"
    ],
    "name:hrv_x_preferred":[
        "Anhimidae"
    ],
    "name:hun_x_preferred":[
        "T\u00fcsk\u00e9ssz\u00e1rny\u00famad\u00e1r-f\u00e9l\u00e9k"
    ],
    "name:ita_x_preferred":[
        "Anhimidae"
    ],
    "name:jpn_x_preferred":[
        "\u30b5\u30b1\u30d3\u30c9\u30ea\u79d1"
    ],
    "name:kab_x_preferred":[
        "Amsu\u0263ay"
    ],
    "name:kat_x_preferred":[
        "\u10de\u10d0\u10da\u10d0\u10db\u10d4\u10d3\u10d4\u10d0\u10e1\u10d4\u10d1\u10e0\u10dc\u10d8"
    ],
    "name:kor_x_preferred":[
        "\ub5a0\ub4e4\uc369\uc624\ub9ac\uacfc"
    ],
    "name:kur_x_preferred":[
        "Qaza q\u00eej\u00eener"
    ],
    "name:lit_x_preferred":[
        "Palamed\u0117jos"
    ],
    "name:nav_x_preferred":[
        "Z\u00e9\u00e9zhinii"
    ],
    "name:nds_x_preferred":[
        "Schreevagels"
    ],
    "name:nld_x_preferred":[
        "Hoenderkoeten"
    ],
    "name:nno_x_preferred":[
        "Gjetarfuglfamilien"
    ],
    "name:nor_x_preferred":[
        "Gjeterfugler"
    ],
    "name:pnb_x_preferred":[
        "\u0686\u06cc\u06a9\u0646\u06d2 \u067e\u0646\u0686\u06be\u06cc"
    ],
    "name:pol_x_preferred":[
        "Skrzyd\u0142oszpony"
    ],
    "name:por_x_preferred":[
        "Anhimidae"
    ],
    "name:ron_x_preferred":[
        "Anhimidae"
    ],
    "name:rus_x_preferred":[
        "\u041f\u0430\u043b\u0430\u043c\u0435\u0434\u0435\u0438"
    ],
    "name:spa_x_preferred":[
        "Anhimidae"
    ],
    "name:srp_x_preferred":[
        "\u0412\u0440\u0438\u0448\u0442\u0430\u0432\u0446\u0438"
    ],
    "name:swe_x_preferred":[
        "V\u00e4rnf\u00e5glar"
    ],
    "name:ukr_x_preferred":[
        "\u041f\u0430\u043b\u0430\u043c\u0435\u0434\u0435\u0454\u0432\u0456"
    ],
    "name:war_x_preferred":[
        "Anhimidae"
    ],
    "name:zea_x_preferred":[
        "'Oenderkoeten"
    ],
    "name:zho_x_preferred":[
        "\u53eb\u9e2d\u79d1"
    ],
    "wof:name":"Screamer",
    "wof:placetype":"locality"
},
  "geometry": {"coordinates":[-85.20659999999999,31.66156],"type":"Point"}
}