{
  "type": "Feature",
  "properties": {
    "iso:country":"US",
    "name:eng_x_preferred":[
        "Pohoiki Ahupua`a"
    ],
    "qs:gn_adm0_cc":"US",
    "qs:gn_local":5851916,
    "qs:gn_nam_loc":"Pahoa, Hawaii, Hawaii, US",
    "qs:gn_namadm1":"HI",
    "qs:local_max":959,
    "qs:local_sum":4289,
    "qs:localhoods":12,
    "qs:name":"Pohoiki Ahupua`a",
    "qs:name_adm0":"United States",
    "qs:name_adm1":"Hawaii",
    "qs:name_adm2":"Hawaii",
    "qs:name_local":"Pahoa",
    "qs:photo_max":122,
    "qs:photo_sum":172,
    "qs:placetype":"Suburb",
    "qs:quad_count":8,
    "qs:woe_adm0":23424977,
    "qs:woe_adm1":2347570,
    "qs:woe_adm2":12588029,
    "qs:woe_lau":0,
    "qs:woe_local":2467481,
    "qs:woe_ver":"7.10.0",
    "wof:name":"Pohoiki Ahupua`a",
    "wof:placetype":"neighbourhood",
    "wof:population":52,
    "zs:blockids":[
        150010211012038,
        150010211012026,
        150010211012023,
        150010211012016
    ],
    "zs:housing10":19,
    "zs:pop10":52
},
  "geometry": {"coordinates":[-154.84895900000001,19.460194],"type":"Point"}
}