{
  "type": "Feature",
  "properties": {
    "gn:admin1_code":"IN",
    "gn:admin2_code":"7.0",
    "gn:admin3_code":"77138.0",
    "gn:asciiname":"Lochiel",
    "gn:country_code":"US",
    "gn:dem":245,
    "gn:elevation":"243.0",
    "gn:feature_class":"P",
    "gn:feature_code":"PPL",
    "gn:name":"Lochiel",
    "gn:population":0,
    "gn:timezone":"America/Indiana/Indianapolis",
    "iso:country":"US",
    "name:eng_x_preferred":[
        "Lochiel"
    ],
    "name:und_x_variant":[
        "Kaarland"
    ],
    "wof:name":"Lochiel",
    "wof:placetype":"locality"
},
  "geometry": {"coordinates":[-87.27391,40.66421],"type":"Point"}
}