{
  "type": "Feature",
  "properties": {
    "gn:admin1_code":"AZ",
    "gn:admin2_code":"19.0",
    "gn:asciiname":"Emika",
    "gn:country_code":"US",
    "gn:dem":695,
    "gn:elevation":"696.0",
    "gn:feature_class":"P",
    "gn:feature_code":"PPL",
    "gn:name":"Emika",
    "gn:population":0,
    "gn:timezone":"America/Phoenix",
    "iso:country":"US",
    "name:dan_x_preferred":[
        "Emika"
    ],
    "name:deu_x_preferred":[
        "Emika"
    ],
    "name:eng_x_preferred":[
        "Emika"
    ],
    "name:fra_x_preferred":[
        "Emika"
    ],
    "name:hye_x_preferred":[
        "\u0537\u0574\u056b\u056f\u0561"
    ],
    "name:ita_x_preferred":[
        "Emika"
    ],
    "name:pol_x_preferred":[
        "Emika"
    ],
    "name:rus_x_preferred":[
        "\u042d\u043c\u0438\u043a\u0430"
    ],
    "name:und_x_variant":[
        "Emita"
    ],
    "wof:name":"Emika",
    "wof:placetype":"locality"
},
  "geometry": {"coordinates":[-112.48653,32.43339],"type":"Point"}
}