{
  "type": "Feature",
  "properties": {
    "gn:admin1_code":"VT",
    "gn:admin2_code":"1.0",
    "gn:asciiname":"Bridport",
    "gn:country_code":"US",
    "gn:dem":90,
    "gn:elevation":"92.0",
    "gn:feature_class":"P",
    "gn:feature_code":"PPL",
    "gn:name":"Bridport",
    "gn:population":1215,
    "gn:timezone":"America/New_York",
    "iso:country":"US",
    "name:azb_x_preferred":[
        "\u0628\u0631\u06cc\u062f\u067e\u0648\u0631\u062a"
    ],
    "name:cym_x_preferred":[
        "Bridport"
    ],
    "name:deu_x_preferred":[
        "Bridport"
    ],
    "name:eng_x_preferred":[
        "Bridport"
    ],
    "name:fas_x_preferred":[
        "\u0628\u0631\u06cc\u062f\u067e\u0648\u0631\u062a"
    ],
    "name:fra_x_preferred":[
        "Bridport"
    ],
    "name:ita_x_preferred":[
        "Bridport"
    ],
    "name:lat_x_preferred":[
        "Bridport"
    ],
    "name:nld_x_preferred":[
        "Bridport"
    ],
    "name:nno_x_preferred":[
        "Bridport"
    ],
    "name:pol_x_preferred":[
        "Bridport"
    ],
    "name:ron_x_preferred":[
        "Bridport"
    ],
    "name:rus_x_preferred":[
        "\u0411\u0440\u0438\u0434\u043f\u043e\u0440\u0442"
    ],
    "name:spa_x_preferred":[
        "Bridport"
    ],
    "name:swe_x_preferred":[
        "Bridport"
    ],
    "name:ukr_x_preferred":[
        "\u0411\u0440\u0456\u0434\u043f\u043e\u0440\u0442"
    ],
    "name:und_x_variant":[
        "Birdport"
    ],
    "name:zho_x_preferred":[
        "\u5e03\u91cc\u5fb7\u6ce2\u7279"
    ],
    "wof:name":"Bridport",
    "wof:placetype":"locality",
    "wof:population":1215
},
  "geometry": {"coordinates":[-73.31262,43.98506],"type":"Point"}
}