{
  "type": "Feature",
  "properties": {
    "gn:elevation":7,
    "iso:country":"US",
    "name:eng_x_preferred":[
        "Remsen Mill"
    ],
    "name:eng_x_variant":[
        "Remsen Ml",
        "Remsen Mills"
    ],
    "name:fra_x_preferred":[
        "Remsen Mills"
    ],
    "qs:gn_adm0_cc":"US",
    "qs:gn_fcode":"PPL",
    "qs:gn_local":5105965,
    "qs:gn_nam_loc":"Wall, Monmouth, New Jersey, US",
    "qs:gn_namadm1":"NJ",
    "qs:gn_name":"Remsen Mill",
    "qs:local_max":662,
    "qs:local_sum":2239,
    "qs:localhoods":9,
    "qs:name":"Remsen Mill",
    "qs:name_adm0":"United States",
    "qs:name_adm1":"New Jersey",
    "qs:name_adm2":"Monmouth",
    "qs:name_local":"Wall",
    "qs:photo_max":5,
    "qs:photo_sum":7,
    "qs:placetype":"Suburb",
    "qs:quad_count":3,
    "qs:woe_adm0":23424977,
    "qs:woe_adm1":2347589,
    "qs:woe_adm2":12589270,
    "qs:woe_lau":0,
    "qs:woe_local":26342932,
    "qs:woe_ver":"7.10.0",
    "wd:wordcount":40,
    "wof:lang":[
        "eng"
    ],
    "wof:name":"Remsen Mill",
    "wof:placetype":"neighbourhood",
    "wof:population":1387,
    "zs:blockids":[
        340258080021032,
        340258080011012,
        340258080011027,
        340258080012009,
        340258080011020,
        340258080013037,
        340258080012004,
        340258080021033,
        340258080011018,
        340258080011008,
        340258080012001,
        340258080011026,
        340258080021030,
        340258080021040,
        340258080011010,
        340258080012005,
        340258080012003,
        340258086004000,
        340258080011017,
        340258080011019,
        340258080012002,
        340258080011024,
        340258080021034,
        340258080021023,
        340258080011011,
        340258080012000,
        340258080011007,
        340258080021039,
        340258080021005,
        340258080021036,
        340258080021031,
        340258080011025,
        340258080011013
    ],
    "zs:housing10":583,
    "zs:pop10":1387
},
  "geometry": {"coordinates":[-74.060016,40.201355],"type":"Point"}
}