{
  "type": "Feature",
  "properties": {
    "gn:admin1_code":"NY",
    "gn:admin2_code":"81.0",
    "gn:asciiname":"Old Germania Heights",
    "gn:country_code":"US",
    "gn:dem":29,
    "gn:elevation":"27.0",
    "gn:feature_class":"P",
    "gn:feature_code":"PPL",
    "gn:name":"Old Germania Heights",
    "gn:population":0,
    "gn:timezone":"America/New_York",
    "iso:country":"US",
    "wof:name":"Old Germania Heights",
    "wof:placetype":"locality"
},
  "geometry": {"coordinates":[-73.91417,40.70806],"type":"Point"}
}