{
  "type": "Feature",
  "properties": {
    "gn:admin1_code":"OR",
    "gn:admin2_code":"33",
    "gn:asciiname":"Dryden",
    "gn:country_code":"US",
    "gn:dem":443,
    "gn:elevation":"437.0",
    "gn:feature_class":"P",
    "gn:feature_code":"PPL",
    "gn:name":"Dryden",
    "gn:population":0,
    "gn:timezone":"America/Los_Angeles",
    "iso:country":"US",
    "name:heb_x_preferred":[
        "\u05d3\u05e8\u05d9\u05d9\u05d3\u05df"
    ],
    "name:hun_x_preferred":[
        "Dryden"
    ],
    "wof:name":"Dryden",
    "wof:placetype":"locality"
},
  "geometry": {"coordinates":[-123.53729,42.26956],"type":"Point"}
}