{
  "type": "Feature",
  "properties": {
    "iso:country":"US",
    "name:eng_x_preferred":[
        "Sepe/Miller Safety Harbor Parc"
    ],
    "qs:gn_local":0,
    "qs:local_max":507,
    "qs:local_sum":1089,
    "qs:localhoods":4,
    "qs:name":"Sepe/Miller Safety Harbor Parc",
    "qs:name_adm0":"United States",
    "qs:name_adm1":"Florida",
    "qs:name_adm2":"Lee",
    "qs:name_local":"Captiva",
    "qs:photo_max":157,
    "qs:photo_sum":183,
    "qs:placetype":"Suburb",
    "qs:quad_count":4,
    "qs:woe_adm0":23424977,
    "qs:woe_adm1":2347568,
    "qs:woe_adm2":12587838,
    "qs:woe_lau":0,
    "qs:woe_local":23689700,
    "qs:woe_ver":"7.10.0",
    "wof:name":"Sepe/Miller Safety Harbor Parc",
    "wof:placetype":"neighbourhood",
    "wof:population":58,
    "zs:blockids":[
        120710801002050,
        120710801002051,
        120710801002015,
        120710701013028,
        120710801002009,
        120710801002020,
        120710801002036,
        120710801002063,
        120710801002022,
        120710801002019,
        120710701013030,
        120710801002062,
        120710801002021,
        120710801002031,
        120710801002052,
        120710801002037,
        120710801002064,
        120710801002016,
        120710801002008
    ],
    "zs:housing10":126,
    "zs:pop10":58
},
  "geometry": {"coordinates":[-82.222981,26.605336],"type":"Point"}
}