{
  "type": "Feature",
  "properties": {
    "gn:admin1_code":"AL",
    "gn:admin2_code":"101",
    "gn:asciiname":"Matthews",
    "gn:country_code":"US",
    "gn:dem":80,
    "gn:elevation":"77.0",
    "gn:feature_class":"P",
    "gn:feature_code":"PPL",
    "gn:name":"Matthews",
    "gn:population":593,
    "gn:timezone":"America/Chicago",
    "iso:country":"US",
    "name:eng_x_preferred":[
        "Matthews"
    ],
    "name:fas_x_preferred":[
        "\u0645\u0627\u062a\u06cc\u0648\u0632"
    ],
    "name:zho_x_preferred":[
        "\u99ac\u4fee\u65af"
    ],
    "wof:name":"Matthews",
    "wof:placetype":"locality",
    "wof:population":593
},
  "geometry": {"coordinates":[-86.00385,32.26542],"type":"Point"}
}