{
  "type": "Feature",
  "properties": {
    "gn:admin1_code":"NC",
    "gn:admin2_code":"123",
    "gn:admin3_code":"93848.0",
    "gn:asciiname":"Liberty Hill",
    "gn:country_code":"US",
    "gn:dem":216,
    "gn:elevation":"213.0",
    "gn:feature_class":"P",
    "gn:feature_code":"PPL",
    "gn:name":"Liberty Hill",
    "gn:population":0,
    "gn:timezone":"America/New_York",
    "iso:country":"US",
    "name:ceb_x_preferred":[
        "Liberty Hill"
    ],
    "name:deu_x_preferred":[
        "Liberty Hill"
    ],
    "name:swe_x_preferred":[
        "Liberty Hill"
    ],
    "wof:name":"Liberty Hill",
    "wof:placetype":"locality"
},
  "geometry": {"coordinates":[-79.99589,35.33653],"type":"Point"}
}