{
  "type": "Feature",
  "properties": {
    "gn:country":"US",
    "gn:elevation":214,
    "gn:fcode":"PPL",
    "gn:population":0,
    "iso:country":"US",
    "name:eng_x_preferred":[
        "East Sheffield"
    ],
    "name:eng_x_variant":[
        "E Sheffield"
    ],
    "qs:gn_adm0_cc":"US",
    "qs:gn_fcode":"PPL",
    "qs:gn_local":5281031,
    "qs:gn_nam_loc":"sheffield",
    "qs:gn_namadm1":"MA",
    "qs:gn_name":"East Sheffield",
    "qs:local_max":5,
    "qs:local_sum":5,
    "qs:localhoods":1,
    "qs:name":"East Sheffield",
    "qs:name_adm0":"United States",
    "qs:name_adm1":"Massachusetts",
    "qs:name_adm2":"Berkshire",
    "qs:name_local":"Sheffield",
    "qs:photo_max":1,
    "qs:photo_sum":5,
    "qs:placetype":"Suburb",
    "qs:quad_count":5,
    "qs:woe_adm0":23424977,
    "qs:woe_adm1":2347580,
    "qs:woe_adm2":12588701,
    "qs:woe_lau":0,
    "qs:woe_local":2492070,
    "qs:woe_ver":"7.10.0",
    "qs_pg:aaroncc":"US",
    "qs_pg:gn_country":"US",
    "qs_pg:gn_fcode":"PPL",
    "qs_pg:gn_pop":0,
    "qs_pg:name":"East Sheffield",
    "qs_pg:name_adm0":"United States",
    "qs_pg:name_adm1":"Massachusetts",
    "qs_pg:photos":5,
    "qs_pg:photos_1k":1,
    "qs_pg:photos_9k":1,
    "qs_pg:photos_9r":1,
    "qs_pg:photos_all":5,
    "qs_pg:photos_sr":1,
    "qs_pg:pop_sr":0,
    "qs_pg:qs_pg_placetype":"neighbourhood",
    "qs_pg:qs_pg_placetype_gp":"Suburb",
    "qs_pg:woe_adm0":23424977,
    "wof:lang":[
        "eng"
    ],
    "wof:name":"East Sheffield",
    "wof:placetype":"neighbourhood",
    "wof:population":354,
    "zs:blockids":[
        250039261004035,
        250039261004036,
        250039261004034,
        250039261002024,
        250039261004026,
        250039261003012,
        250039261003049,
        250039261004024,
        250039261004033,
        250039261003041,
        250039261002040,
        250039261002033,
        250039261002035,
        250039261004022,
        250039261002025,
        250039261004019,
        250039261003027,
        250039261004023,
        250039261003047,
        250039261003023,
        250039261002026,
        250039261003035,
        250039261002036,
        250039261004031,
        250039261003040,
        250039261002032,
        250039261004027,
        250039261004030,
        250039261002023,
        250039261003046,
        250039261003050,
        250039261004037,
        250039261003044,
        250039261003011,
        250039261003042,
        250039261003045,
        250039261003029
    ],
    "zs:housing10":182,
    "zs:pop10":354
},
  "geometry": {"coordinates":[-73.32440200000001,42.039094],"type":"Point"}
}