{
  "type": "Feature",
  "properties": {
    "gn:admin1_code":"LA",
    "gn:admin2_code":"127.0",
    "gn:asciiname":"Mars Hill",
    "gn:country_code":"US",
    "gn:dem":63,
    "gn:elevation":"60.0",
    "gn:feature_class":"P",
    "gn:feature_code":"PPL",
    "gn:name":"Mars Hill",
    "gn:population":0,
    "gn:timezone":"America/Chicago",
    "iso:country":"US",
    "name:ceb_x_preferred":[
        "Mars Hill"
    ],
    "name:deu_x_preferred":[
        "Mars Hill"
    ],
    "name:fra_x_preferred":[
        "Mars Hill"
    ],
    "name:ita_x_preferred":[
        "Mars Hill"
    ],
    "name:pol_x_preferred":[
        "Mars Hill"
    ],
    "name:srp_x_preferred":[
        "\u041c\u0430\u0440\u0441 \u0425\u0438\u043b"
    ],
    "name:ukr_x_preferred":[
        "\u041c\u0430\u0440\u0441-\u0413\u0456\u043b\u043b"
    ],
    "name:vol_x_preferred":[
        "Mars Hill"
    ],
    "wof:name":"Mars Hill",
    "wof:placetype":"locality"
},
  "geometry": {"coordinates":[-92.79682,31.71822],"type":"Point"}
}