{
  "type": "Feature",
  "properties": {
    "gn:admin1_code":"OK",
    "gn:admin2_code":"31",
    "gn:asciiname":"Cove Acres",
    "gn:country_code":"US",
    "gn:dem":383,
    "gn:elevation":"379.0",
    "gn:feature_class":"P",
    "gn:feature_code":"PPL",
    "gn:name":"Cove Acres",
    "gn:population":0,
    "gn:timezone":"America/Chicago",
    "iso:country":"US",
    "wof:name":"Cove Acres",
    "wof:placetype":"locality"
},
  "geometry": {"coordinates":[-98.337,34.83146],"type":"Point"}
}