{
  "type": "Feature",
  "properties": {
    "gn:admin1_code":"PA",
    "gn:admin2_code":"51.0",
    "gn:admin3_code":"28792.0",
    "gn:asciiname":"Oliphant Furnace",
    "gn:country_code":"US",
    "gn:dem":363,
    "gn:elevation":"366.0",
    "gn:feature_class":"P",
    "gn:feature_code":"PPL",
    "gn:name":"Oliphant Furnace",
    "gn:population":0,
    "gn:timezone":"America/New_York",
    "iso:country":"US",
    "wof:name":"Oliphant Furnace",
    "wof:placetype":"locality"
},
  "geometry": {"coordinates":[-79.72588,39.8423],"type":"Point"}
}