{
  "type": "Feature",
  "properties": {
    "gn:admin1_code":"TN",
    "gn:admin2_code":"43",
    "gn:asciiname":"Dull",
    "gn:country_code":"US",
    "gn:dem":229,
    "gn:elevation":"226.0",
    "gn:feature_class":"P",
    "gn:feature_code":"PPL",
    "gn:name":"Dull",
    "gn:population":0,
    "gn:timezone":"America/Chicago",
    "iso:country":"US",
    "name:deu_x_preferred":[
        "Dull"
    ],
    "name:nds_x_preferred":[
        "Dull"
    ],
    "wof:name":"Dull",
    "wof:placetype":"locality"
},
  "geometry": {"coordinates":[-87.28529,36.20561],"type":"Point"}
}