{
  "type": "Feature",
  "properties": {
    "iso:country":"US",
    "name:ceb_x_preferred":[
        "Cross Creek"
    ],
    "name:eng_x_preferred":[
        "Cross Creek"
    ],
    "name:fra_x_preferred":[
        "Cross Creek"
    ],
    "name:pol_x_preferred":[
        "Cross Creek"
    ],
    "name:swe_x_preferred":[
        "Cross Creek"
    ],
    "name:ukr_x_preferred":[
        "\u041a\u0440\u043e\u0441\u0441-\u041a\u0440\u0456\u043a"
    ],
    "wd:wordcount":197,
    "wof:name":"Cross Creek",
    "wof:placetype":"neighbourhood",
    "wof:population":1173,
    "zs:area_m":4963525.850895,
    "zs:blockids":[
        470650104351046,
        470650104351043,
        470650104351020,
        470650104352014,
        470650104351023,
        470650104341077,
        470650104351050,
        470650104351022,
        470650106003001,
        470650104351042,
        470650104351045,
        470650104352020,
        470650109031000,
        470650104352015,
        470650109031003,
        470650104351049,
        470650104351048,
        470650109031001,
        470650104352019,
        470650109031002,
        470650106003002,
        470650104351044,
        470650104351047
    ],
    "zs:housing10":513,
    "zs:label":"Cross Creek",
    "zs:pop10":1173
},
  "geometry": {"coordinates":[-85.273965,35.157435],"type":"Point"}
}