{
  "type": "Feature",
  "properties": {
    "gn:country":"US",
    "gn:fcode":"PPL",
    "gn:population":2363,
    "iso:country":"US",
    "name:cat_x_preferred":[
        "Whitefield"
    ],
    "name:deu_x_preferred":[
        "Whitefield"
    ],
    "name:eng_x_preferred":[
        "Whitefield"
    ],
    "name:eus_x_preferred":[
        "Whitefield"
    ],
    "name:fra_x_preferred":[
        "Whitefield"
    ],
    "name:hat_x_preferred":[
        "Whitefield"
    ],
    "name:hun_x_preferred":[
        "Whitefield"
    ],
    "name:ita_x_preferred":[
        "Whitefield"
    ],
    "name:kaz_x_preferred":[
        "\u0423\u0430\u0439\u0442\u0444\u0438\u043b\u0434"
    ],
    "name:kir_x_preferred":[
        "\u0423\u0430\u0439\u0442\u0444\u0438\u043b\u0434"
    ],
    "name:nld_x_preferred":[
        "Whitefield"
    ],
    "name:pol_x_preferred":[
        "Whitefield"
    ],
    "name:spa_x_preferred":[
        "Whitefield"
    ],
    "name:vol_x_preferred":[
        "Whitefield"
    ],
    "qs_pg:aaroncc":"US",
    "qs_pg:gn_country":"US",
    "qs_pg:gn_fcode":"PPL",
    "qs_pg:gn_pop":2363,
    "qs_pg:name":"Whitefield",
    "qs_pg:name_adm0":"United States",
    "qs_pg:name_adm1":"Maine",
    "qs_pg:photos_9k":1,
    "qs_pg:photos_9r":1,
    "qs_pg:photos_all":2,
    "qs_pg:photos_sr":0,
    "qs_pg:pop_sr":4,
    "qs_pg:qs_pg_placetype":"locality",
    "qs_pg:qs_pg_placetype_gp":"Town",
    "qs_pg:woe_adm0":23424977,
    "woe:adm0_id":23424977,
    "woe:name_adm0":"United States",
    "woe:name_adm1":"Maine",
    "woe:placetype":"Town",
    "wof:name":"Whitefield",
    "wof:placetype":"locality",
    "wof:population":2363
},
  "geometry": {"coordinates":[-69.62532,44.17007],"type":"Point"}
}