{
  "type": "Feature",
  "properties": {
    "gn:country":"US",
    "gn:fcode":"PPL",
    "gn:population":0,
    "iso:country":"US",
    "name:ara_x_preferred":[
        "\u0631\u0627\u064a\u0629"
    ],
    "name:cat_x_preferred":[
        "Banderola"
    ],
    "name:deu_x_preferred":[
        "Banner"
    ],
    "name:eng_x_preferred":[
        "Banner"
    ],
    "name:fas_x_preferred":[
        "\u0628\u0646\u0631"
    ],
    "name:fry_x_preferred":[
        "Banier"
    ],
    "name:ind_x_preferred":[
        "Spanduk"
    ],
    "name:jpn_x_preferred":[
        "\u6a2a\u65ad\u5e55"
    ],
    "name:kaz_x_preferred":[
        "\u0411\u0430\u0439\u0440\u0430\u049b"
    ],
    "name:kor_x_preferred":[
        "\ud604\uc218\ub9c9"
    ],
    "name:nld_x_preferred":[
        "Banier"
    ],
    "name:nor_x_preferred":[
        "Banner"
    ],
    "name:scn_x_preferred":[
        "Stinnardu"
    ],
    "name:slv_x_preferred":[
        "Prapor"
    ],
    "name:spa_x_preferred":[
        "Pend\u00f3n"
    ],
    "name:swe_x_preferred":[
        "Baner"
    ],
    "name:tam_x_preferred":[
        "\u0baa\u0ba4\u0bbe\u0b95\u0bc8"
    ],
    "name:ukr_x_preferred":[
        "\u0421\u0442\u044f\u0433"
    ],
    "name:und_x_variant":[
        "Cereal"
    ],
    "qs_pg:aaroncc":"US",
    "qs_pg:gn_country":"US",
    "qs_pg:gn_fcode":"PPL",
    "qs_pg:gn_pop":0,
    "qs_pg:name":"Banner",
    "qs_pg:name_adm0":"United States",
    "qs_pg:name_adm1":"Oklahoma",
    "qs_pg:photos":92,
    "qs_pg:photos_1k":19,
    "qs_pg:photos_9k":1,
    "qs_pg:photos_9r":3,
    "qs_pg:photos_all":92,
    "qs_pg:photos_sr":3,
    "qs_pg:pop_sr":0,
    "qs_pg:qs_pg_placetype":"locality",
    "qs_pg:qs_pg_placetype_gp":"Town",
    "qs_pg:woe_adm0":23424977,
    "woe:adm0_id":23424977,
    "woe:name_adm0":"United States",
    "woe:name_adm1":"Oklahoma",
    "woe:placetype":"Town",
    "wof:name":"Banner",
    "wof:placetype":"locality"
},
  "geometry": {"coordinates":[-97.84894,35.51283],"type":"Point"}
}