{
  "type": "Feature",
  "properties": {
    "gn:admin1_code":"MD",
    "gn:admin2_code":"31.0",
    "gn:asciiname":"Newport Hills",
    "gn:country_code":"US",
    "gn:dem":106,
    "gn:elevation":"103.0",
    "gn:feature_class":"P",
    "gn:feature_code":"PPL",
    "gn:name":"Newport Hills",
    "gn:population":0,
    "gn:timezone":"America/New_York",
    "iso:country":"US",
    "wof:name":"Newport Hills",
    "wof:placetype":"locality"
},
  "geometry": {"coordinates":[-77.07191999999998,39.04066],"type":"Point"}
}