{
  "type": "Feature",
  "properties": {
    "gn:country":"US",
    "gn:fcode":"PPL",
    "gn:population":0,
    "iso:country":"US",
    "name:ara_x_preferred":[
        "\u0622\u0631\u0645\u0633\u062a\u0631\u0648\u0646\u063a"
    ],
    "name:azb_x_preferred":[
        "\u0622\u0631\u0645\u0633\u062a\u0631\u0627\u0646\u0642"
    ],
    "name:eng_x_preferred":[
        "Armstrong"
    ],
    "name:fas_x_preferred":[
        "\u0622\u0631\u0645\u0633\u062a\u0631\u0627\u0646\u06af"
    ],
    "name:fra_x_preferred":[
        "Armstrong"
    ],
    "name:urd_x_preferred":[
        "\u0622\u0631\u0645\u0633\u0679\u0631\u0627\u0646\u06af\u060c \u0627\u0644\u06cc\u0646\u0648\u0627\u0626\u06d2"
    ],
    "name:urd_x_variant":[
        "\u0622\u0631\u0645\u0633\u0679\u0631\u0627\u0646\u06af"
    ],
    "qs_pg:aaroncc":"US",
    "qs_pg:gn_country":"US",
    "qs_pg:gn_fcode":"PPL",
    "qs_pg:gn_pop":0,
    "qs_pg:name":"Armstrong",
    "qs_pg:name_adm0":"United States",
    "qs_pg:name_adm1":"Illinois",
    "qs_pg:photos_9k":1,
    "qs_pg:photos_9r":1,
    "qs_pg:photos_all":13,
    "qs_pg:photos_sr":0,
    "qs_pg:pop_sr":0,
    "qs_pg:qs_pg_placetype":"locality",
    "qs_pg:qs_pg_placetype_gp":"Town",
    "qs_pg:woe_adm0":23424977,
    "woe:adm0_id":23424977,
    "woe:name_adm0":"United States",
    "woe:name_adm1":"Illinois",
    "woe:placetype":"Town",
    "wof:name":"Armstrong",
    "wof:placetype":"locality"
},
  "geometry": {"coordinates":[-87.87781,40.30642],"type":"Point"}
}