{
  "type": "Feature",
  "properties": {
    "gn:admin1_code":"MD",
    "gn:admin2_code":"5.0",
    "gn:asciiname":"Mount Carmel Farms",
    "gn:country_code":"US",
    "gn:dem":196,
    "gn:elevation":"207.0",
    "gn:feature_class":"P",
    "gn:feature_code":"PPL",
    "gn:name":"Mount Carmel Farms",
    "gn:population":0,
    "gn:timezone":"America/New_York",
    "iso:country":"US",
    "wof:name":"Mount Carmel Farms",
    "wof:placetype":"locality"
},
  "geometry": {"coordinates":[-76.72024999999999,39.58066],"type":"Point"}
}