{
  "type": "Feature",
  "properties": {
    "gn:admin1_code":"SC",
    "gn:admin2_code":"45.0",
    "gn:asciiname":"Poinsett",
    "gn:country_code":"US",
    "gn:dem":305,
    "gn:elevation":"306.0",
    "gn:feature_class":"P",
    "gn:feature_code":"PPL",
    "gn:name":"Poinsett",
    "gn:population":0,
    "gn:timezone":"America/New_York",
    "iso:country":"US",
    "name:deu_x_preferred":[
        "Poinsett"
    ],
    "name:rus_x_preferred":[
        "\u041f\u043e\u0439\u043d\u0441\u0435\u0442\u0442"
    ],
    "wof:name":"Poinsett",
    "wof:placetype":"locality"
},
  "geometry": {"coordinates":[-82.43901,34.8579],"type":"Point"}
}