{
  "type": "Feature",
  "properties": {
    "gn:admin1_code":"TN",
    "gn:admin2_code":"141.0",
    "gn:asciiname":"Snow Mayberry Subdivision",
    "gn:country_code":"US",
    "gn:dem":316,
    "gn:elevation":"317.0",
    "gn:feature_class":"P",
    "gn:feature_code":"PPL",
    "gn:name":"Snow Mayberry Subdivision",
    "gn:population":0,
    "gn:timezone":"America/Chicago",
    "iso:country":"US",
    "wof:name":"Snow Mayberry Subdivision",
    "wof:placetype":"locality"
},
  "geometry": {"coordinates":[-85.5847,36.17451],"type":"Point"}
}