{
  "type": "Feature",
  "properties": {
    "iso:country":"US",
    "name:eng_x_preferred":[
        "Dayton View Triangle"
    ],
    "wof:name":"Dayton View Triangle",
    "wof:placetype":"neighbourhood",
    "wof:population":178,
    "zs:area_m":76471.977381,
    "zs:blockids":[
        391130008021001,
        391130008013006,
        391130008013005,
        391130005005000
    ],
    "zs:housing10":166,
    "zs:label":"Dayton View Triangle",
    "zs:pop10":178
},
  "geometry": {"coordinates":[-84.224316,39.782511],"type":"Point"}
}