{
  "type": "Feature",
  "properties": {
    "gn:admin1_code":"AR",
    "gn:admin2_code":"107.0",
    "gn:admin3_code":"93573.0",
    "gn:asciiname":"Modoc",
    "gn:country_code":"US",
    "gn:dem":48,
    "gn:elevation":"50.0",
    "gn:feature_class":"P",
    "gn:feature_code":"PPL",
    "gn:name":"Modoc",
    "gn:population":0,
    "gn:timezone":"America/Chicago",
    "iso:country":"US",
    "name:zho_x_preferred":[
        "\u83ab\u591a\u514b"
    ],
    "wof:name":"Modoc",
    "wof:placetype":"locality"
},
  "geometry": {"coordinates":[-90.77955,34.33594],"type":"Point"}
}