{
  "type": "Feature",
  "properties": {
    "gn:admin1_code":"MN",
    "gn:admin2_code":"61.0",
    "gn:admin3_code":"25892.0",
    "gn:asciiname":"Jurgenson",
    "gn:country_code":"US",
    "gn:dem":420,
    "gn:elevation":"418.0",
    "gn:feature_class":"P",
    "gn:feature_code":"PPL",
    "gn:name":"Jurgenson",
    "gn:population":0,
    "gn:timezone":"America/Chicago",
    "iso:country":"US",
    "wof:name":"Jurgenson",
    "wof:placetype":"locality"
},
  "geometry": {"coordinates":[-93.22964,47.33216],"type":"Point"}
}