{
  "type": "Feature",
  "properties": {
    "gn:admin1_code":"IL",
    "gn:admin2_code":"63.0",
    "gn:admin3_code":"46175.0",
    "gn:asciiname":"Gorman",
    "gn:country_code":"US",
    "gn:dem":171,
    "gn:elevation":"170.0",
    "gn:feature_class":"P",
    "gn:feature_code":"PPL",
    "gn:name":"Gorman",
    "gn:population":0,
    "gn:timezone":"America/Chicago",
    "iso:country":"US",
    "name:cat_x_preferred":[
        "Gorman"
    ],
    "name:ceb_x_preferred":[
        "Gorman"
    ],
    "name:deu_x_preferred":[
        "Gorman"
    ],
    "name:fra_x_preferred":[
        "Gorman"
    ],
    "name:gla_x_preferred":[
        "Gorman"
    ],
    "name:ita_x_preferred":[
        "Gorman"
    ],
    "name:nds_x_preferred":[
        "Gorman"
    ],
    "name:nld_x_preferred":[
        "Gorman"
    ],
    "name:pol_x_preferred":[
        "Gorman"
    ],
    "name:por_x_preferred":[
        "Gorman"
    ],
    "name:rus_x_preferred":[
        "\u0413\u043e\u0440\u043c\u0430\u043d"
    ],
    "name:slv_x_preferred":[
        "Gorman"
    ],
    "name:spa_x_preferred":[
        "Gorman"
    ],
    "name:srp_x_preferred":[
        "\u0413\u043e\u0440\u043c\u0430\u043d"
    ],
    "name:swe_x_preferred":[
        "Gorman"
    ],
    "name:ukr_x_preferred":[
        "\u0413\u043e\u0440\u043c\u0435\u043d"
    ],
    "name:vol_x_preferred":[
        "Gorman"
    ],
    "wof:name":"Gorman",
    "wof:placetype":"locality"
},
  "geometry": {"coordinates":[-88.34173,41.26114000000001],"type":"Point"}
}