{
  "type": "Feature",
  "properties": {
    "gn:admin1_code":"MI",
    "gn:admin2_code":"3.0",
    "gn:admin3_code":"69160.0",
    "gn:asciiname":"Rumely",
    "gn:country_code":"US",
    "gn:dem":321,
    "gn:elevation":"322.0",
    "gn:feature_class":"P",
    "gn:feature_code":"PPL",
    "gn:name":"Rumely",
    "gn:population":0,
    "gn:timezone":"America/Detroit",
    "iso:country":"US",
    "name:deu_x_preferred":[
        "Rumely"
    ],
    "name:eng_x_preferred":[
        "Rumely"
    ],
    "name:und_x_variant":[
        "Rumley"
    ],
    "wof:name":"Rumely",
    "wof:placetype":"locality"
},
  "geometry": {"coordinates":[-87.03319999999999,46.34828],"type":"Point"}
}