{
  "type": "Feature",
  "properties": {
    "gn:country":"US",
    "gn:fcode":"PPL",
    "gn:population":0,
    "iso:country":"US",
    "name:ceb_x_preferred":[
        "Pocasset"
    ],
    "name:deu_x_preferred":[
        "Pocasset"
    ],
    "name:ita_x_preferred":[
        "Pocasset"
    ],
    "name:nld_x_preferred":[
        "Pocasset"
    ],
    "name:pol_x_preferred":[
        "Pocasset"
    ],
    "name:srp_x_preferred":[
        "\u041f\u043e\u043a\u0430\u0441\u0435\u0442"
    ],
    "name:ukr_x_preferred":[
        "\u041f\u043e\u043a\u0430\u0441\u0441\u0435\u0442"
    ],
    "qs_pg:aaroncc":"US",
    "qs_pg:gn_country":"US",
    "qs_pg:gn_fcode":"PPL",
    "qs_pg:gn_pop":0,
    "qs_pg:name":"Pocasset",
    "qs_pg:name_adm0":"United States",
    "qs_pg:name_adm1":"Rhode Island",
    "qs_pg:photos":13,
    "qs_pg:photos_1k":3,
    "qs_pg:photos_9k":1,
    "qs_pg:photos_9r":1,
    "qs_pg:photos_all":13,
    "qs_pg:photos_sr":1,
    "qs_pg:pop_sr":0,
    "qs_pg:qs_pg_placetype":"locality",
    "qs_pg:qs_pg_placetype_gp":"Town",
    "qs_pg:woe_adm0":23424977,
    "woe:adm0_id":23424977,
    "woe:name_adm0":"United States",
    "woe:name_adm1":"Rhode Island",
    "woe:placetype":"Town",
    "wof:name":"Pocasset",
    "wof:placetype":"locality"
},
  "geometry": {"coordinates":[-71.44061000000001,41.75538],"type":"Point"}
}