{
  "type": "Feature",
  "properties": {
    "gn:admin1_code":"TN",
    "gn:admin2_code":"161",
    "gn:asciiname":"Indian Mound",
    "gn:country_code":"US",
    "gn:dem":122,
    "gn:elevation":"115.0",
    "gn:feature_class":"P",
    "gn:feature_code":"PPL",
    "gn:name":"Indian Mound",
    "gn:population":0,
    "gn:timezone":"America/Chicago",
    "iso:country":"US",
    "name:eng_x_preferred":[
        "Indian Mound"
    ],
    "name:und_x_variant":[
        "Mount Indian",
        "Indianmound"
    ],
    "wof:name":"Indian Mound",
    "wof:placetype":"locality"
},
  "geometry": {"coordinates":[-87.69363,36.50088],"type":"Point"}
}