{
  "type": "Feature",
  "properties": {
    "gn:admin1_code":"WV",
    "gn:admin2_code":"19.0",
    "gn:asciiname":"Oakland",
    "gn:country_code":"US",
    "gn:dem":194,
    "gn:elevation":"194.0",
    "gn:feature_class":"P",
    "gn:feature_code":"PPL",
    "gn:name":"Oakland",
    "gn:population":0,
    "gn:timezone":"America/New_York",
    "iso:country":"US",
    "wof:name":"Oakland",
    "wof:placetype":"locality"
},
  "geometry": {"coordinates":[-81.30456,38.17316],"type":"Point"}
}