{
  "type": "Feature",
  "properties": {
    "gn:admin1_code":"VA",
    "gn:admin2_code":"191",
    "gn:asciiname":"Price Hill",
    "gn:country_code":"US",
    "gn:dem":645,
    "gn:elevation":"654.0",
    "gn:feature_class":"P",
    "gn:feature_code":"PPL",
    "gn:name":"Price Hill",
    "gn:population":0,
    "gn:timezone":"America/New_York",
    "iso:country":"US",
    "name:ceb_x_preferred":[
        "Price Hill"
    ],
    "name:deu_x_preferred":[
        "Price Hill"
    ],
    "wof:name":"Price Hill",
    "wof:placetype":"locality"
},
  "geometry": {"coordinates":[-81.75623,36.76039],"type":"Point"}
}