{
  "type": "Feature",
  "properties": {
    "iso:country":"US",
    "name:ceb_x_preferred":[
        "Brownsdale"
    ],
    "name:deu_x_preferred":[
        "Brownsdale"
    ],
    "name:eng_x_preferred":[
        "Brownsdale"
    ],
    "name:hbs_x_preferred":[
        "Braunsdejl"
    ],
    "name:srp_x_preferred":[
        "\u0411\u0440\u0430\u0443\u043d\u0441\u0434\u0435\u0458\u043b"
    ],
    "name:ukr_x_preferred":[
        "\u0411\u0440\u0430\u0443\u043d\u0441\u0434\u0435\u0439\u043b"
    ],
    "qs:gn_adm0_cc":"US",
    "qs:gn_fcode":"PPL",
    "qs:gn_local":5205435,
    "qs:gn_nam_loc":"Penn, Butler, Pennsylvania, US",
    "qs:gn_namadm1":"PA",
    "qs:gn_name":"Brownsdale",
    "qs:local_max":73,
    "qs:local_sum":150,
    "qs:localhoods":4,
    "qs:name":"Brownsdale",
    "qs:name_adm0":"United States",
    "qs:name_adm1":"Pennsylvania",
    "qs:name_adm2":"Butler",
    "qs:name_local":"Penn",
    "qs:photo_max":8,
    "qs:photo_sum":9,
    "qs:placetype":"Suburb",
    "qs:quad_count":2,
    "qs:woe_adm0":23424977,
    "qs:woe_adm1":2347597,
    "qs:woe_adm2":12589737,
    "qs:woe_lau":0,
    "qs:woe_local":28744820,
    "qs:woe_ver":"7.10.0",
    "wof:lang":[
        "eng"
    ],
    "wof:name":"Brownsdale",
    "wof:placetype":"neighbourhood",
    "wof:population":75,
    "zs:blockids":[
        420199116004003,
        420199116004006
    ],
    "zs:housing10":36,
    "zs:pop10":75
},
  "geometry": {"coordinates":[-79.950867,40.779847],"type":"Point"}
}