{
  "type": "Feature",
  "properties": {
    "gn:admin1_code":"AL",
    "gn:admin2_code":"101.0",
    "gn:asciiname":"Stones",
    "gn:country_code":"US",
    "gn:dem":50,
    "gn:elevation":"51.0",
    "gn:feature_class":"P",
    "gn:feature_code":"PPL",
    "gn:name":"Stones",
    "gn:population":0,
    "gn:timezone":"America/Chicago",
    "iso:country":"US",
    "name:eng_x_preferred":[
        "Stones"
    ],
    "name:und_x_variant":[
        "Stones Station"
    ],
    "wof:name":"Stones",
    "wof:placetype":"locality"
},
  "geometry": {"coordinates":[-86.42081,32.33736],"type":"Point"}
}