{
  "type": "Feature",
  "properties": {
    "gn:admin1_code":"WA",
    "gn:admin2_code":"61.0",
    "gn:asciiname":"Alpine Meadows Mobile Home Park",
    "gn:country_code":"US",
    "gn:dem":61,
    "gn:elevation":"64.0",
    "gn:feature_class":"P",
    "gn:feature_code":"PPL",
    "gn:name":"Alpine Meadows Mobile Home Park",
    "gn:population":0,
    "gn:timezone":"America/Los_Angeles",
    "iso:country":"US",
    "wof:name":"Alpine Meadows Mobile Home Park",
    "wof:placetype":"campus"
},
  "geometry": {"coordinates":[-121.68917,47.85431],"type":"Point"}
}