{
  "type": "Feature",
  "properties": {
    "gn:admin1_code":"KY",
    "gn:admin2_code":"141.0",
    "gn:asciiname":"Mosley Pond",
    "gn:country_code":"US",
    "gn:dem":179,
    "gn:elevation":"180.0",
    "gn:feature_class":"P",
    "gn:feature_code":"PPL",
    "gn:name":"Mosley Pond",
    "gn:population":0,
    "gn:timezone":"America/Chicago",
    "iso:country":"US",
    "wof:name":"Mosley Pond",
    "wof:placetype":"locality"
},
  "geometry": {"coordinates":[-87.02746999999999,36.68697],"type":"Point"}
}