{
  "type": "Feature",
  "properties": {
    "gn:elevation":216,
    "iso:country":"US",
    "name:eng_x_preferred":[
        "Port Cargill"
    ],
    "name:eng_x_variant":[
        "Pt Cargill"
    ],
    "name:und_x_variant":[
        "Port Cargil"
    ],
    "qs:gn_adm0_cc":"US",
    "qs:gn_fcode":"PPL",
    "qs:gn_local":5046063,
    "qs:gn_nam_loc":"savage",
    "qs:gn_namadm1":"MN",
    "qs:gn_name":"Port Cargill",
    "qs:local_max":131,
    "qs:local_sum":131,
    "qs:localhoods":1,
    "qs:name":"Port Cargill",
    "qs:name_adm0":"United States",
    "qs:name_adm1":"Minnesota",
    "qs:name_adm2":"Scott",
    "qs:name_local":"Savage",
    "qs:photo_max":38,
    "qs:photo_sum":131,
    "qs:placetype":"Suburb",
    "qs:quad_count":19,
    "qs:woe_adm0":23424977,
    "qs:woe_adm1":2347582,
    "qs:woe_adm2":12588865,
    "qs:woe_lau":0,
    "qs:woe_local":2489289,
    "qs:woe_ver":"7.10.0",
    "wof:lang":[
        "eng"
    ],
    "wof:name":"Port Cargill",
    "wof:placetype":"neighbourhood",
    "wof:population":4000,
    "zs:blockids":[
        270370607091008,
        270370607092000,
        270370607393019,
        270370607391021,
        270370607092013,
        270370607092019,
        270370607391026,
        270370607091010,
        270370607391027,
        270370607092011,
        270370607091000,
        270370607102002,
        270370607102005,
        270370607102021,
        270370607102018,
        270370607091005,
        270370607102029,
        270370607102015,
        270370607102001,
        270370607393018,
        270370607091001,
        270370607391023,
        270370607102048,
        270370607091004,
        270370607391022,
        270370607102004,
        270370607393017,
        270370607092010,
        270370607102016,
        270370607102020,
        270370607092001,
        270370607102006,
        270370607391024,
        270370607092015,
        270370607091003,
        270370607102028,
        270370607102019,
        270370607102014,
        270370607393015,
        270370607091006,
        270370607391025,
        270370607391031,
        270370607391030,
        270370607102022,
        270370607102000,
        270370607092006,
        270370607393020,
        270370607393016,
        270370607091002,
        270370607092014,
        270370607092012,
        270370607102017,
        270370607092018,
        270370607092009,
        270370607092005,
        270370607102003,
        270370607091009
    ],
    "zs:housing10":1376,
    "zs:pop10":4000
},
  "geometry": {"coordinates":[-93.33720099999999,44.779542],"type":"Point"}
}