{
  "type": "Feature",
  "properties": {
    "gn:admin1_code":"FL",
    "gn:admin2_code":"57",
    "gn:asciiname":"Newport Gardens",
    "gn:country_code":"US",
    "gn:dem":18,
    "gn:elevation":"8.0",
    "gn:feature_class":"P",
    "gn:feature_code":"PPL",
    "gn:name":"Newport Gardens",
    "gn:population":0,
    "gn:timezone":"America/New_York",
    "iso:country":"US",
    "wof:name":"Newport Gardens",
    "wof:placetype":"locality"
},
  "geometry": {"coordinates":[-82.46980000000001,28.0206],"type":"Point"}
}