{
  "type": "Feature",
  "properties": {
    "gn:admin1_code":"LA",
    "gn:admin2_code":"41.0",
    "gn:asciiname":"Big Creek",
    "gn:country_code":"US",
    "gn:dem":19,
    "gn:elevation":"14.0",
    "gn:feature_class":"P",
    "gn:feature_code":"PPL",
    "gn:name":"Big Creek",
    "gn:population":0,
    "gn:timezone":"America/Chicago",
    "iso:country":"US",
    "name:ceb_x_preferred":[
        "Big Creek"
    ],
    "name:deu_x_preferred":[
        "Big Creek"
    ],
    "name:fra_x_preferred":[
        "Big Creek"
    ],
    "name:ita_x_preferred":[
        "Big Creek"
    ],
    "name:nds_x_preferred":[
        "Big Creek"
    ],
    "name:nld_x_preferred":[
        "Big Creek"
    ],
    "name:pol_x_preferred":[
        "Big Creek"
    ],
    "name:spa_x_preferred":[
        "Big Creek"
    ],
    "name:srp_x_preferred":[
        "\u0411\u0438\u0433 \u041a\u0440\u0438\u043a"
    ],
    "name:swe_x_preferred":[
        "Big Creek"
    ],
    "name:urd_x_preferred":[
        "\u0628\u06af \u06a9\u0631\u06cc\u06a9"
    ],
    "name:vol_x_preferred":[
        "Big Creek"
    ],
    "wof:name":"Big Creek",
    "wof:placetype":"locality"
},
  "geometry": {"coordinates":[-91.76318000000001,32.29181],"type":"Point"}
}