{
  "type": "Feature",
  "properties": {
    "gn:country":"US",
    "gn:fcode":"PPL",
    "gn:population":0,
    "iso:country":"US",
    "name:cat_x_preferred":[
        "Modena"
    ],
    "name:eng_x_preferred":[
        "Modena"
    ],
    "name:fra_x_preferred":[
        "Modena"
    ],
    "name:zho_x_preferred":[
        "\u83ab\u5fb7\u7d0d"
    ],
    "qs_pg:aaroncc":"US",
    "qs_pg:gn_country":"US",
    "qs_pg:gn_fcode":"PPL",
    "qs_pg:gn_pop":0,
    "qs_pg:name":"Modena",
    "qs_pg:name_adm0":"United States",
    "qs_pg:name_adm1":"Illinois",
    "qs_pg:photos_9k":1,
    "qs_pg:photos_9r":1,
    "qs_pg:photos_all":1,
    "qs_pg:photos_sr":0,
    "qs_pg:pop_sr":0,
    "qs_pg:qs_pg_placetype":"locality",
    "qs_pg:qs_pg_placetype_gp":"Town",
    "qs_pg:woe_adm0":23424977,
    "woe:adm0_id":23424977,
    "woe:name_adm0":"United States",
    "woe:name_adm1":"Illinois",
    "woe:placetype":"Town",
    "wof:name":"Modena",
    "wof:placetype":"locality"
},
  "geometry": {"coordinates":[-89.76316,41.13531],"type":"Point"}
}