{
  "type": "Feature",
  "properties": {
    "gn:admin1_code":"MI",
    "gn:admin2_code":"93.0",
    "gn:admin3_code":"40900.0",
    "gn:asciiname":"Parkers Corners",
    "gn:country_code":"US",
    "gn:dem":296,
    "gn:elevation":"291.0",
    "gn:feature_class":"P",
    "gn:feature_code":"PPL",
    "gn:name":"Parkers Corners",
    "gn:population":0,
    "gn:timezone":"America/Detroit",
    "iso:country":"US",
    "name:eng_x_preferred":[
        "Parkers Corners"
    ],
    "name:und_x_variant":[
        "Iosco"
    ],
    "wof:name":"Parkers Corners",
    "wof:placetype":"locality"
},
  "geometry": {"coordinates":[-84.11329000000001,42.56809000000001],"type":"Point"}
}