{
  "type": "Feature",
  "properties": {
    "gn:country":"US",
    "gn:fcode":"PPL",
    "gn:population":0,
    "iso:country":"US",
    "name:deu_x_preferred":[
        "Spring Mills"
    ],
    "name:eng_x_preferred":[
        "Spring Mills"
    ],
    "qs_pg:aaroncc":"US",
    "qs_pg:gn_country":"US",
    "qs_pg:gn_fcode":"PPL",
    "qs_pg:gn_pop":0,
    "qs_pg:name":"Spring Mills",
    "qs_pg:name_adm0":"United States",
    "qs_pg:name_adm1":"New Jersey",
    "qs_pg:photos":16,
    "qs_pg:photos_1k":3,
    "qs_pg:photos_9k":1,
    "qs_pg:photos_9r":1,
    "qs_pg:photos_all":16,
    "qs_pg:photos_sr":1,
    "qs_pg:pop_sr":0,
    "qs_pg:qs_pg_placetype":"neighbourhood",
    "qs_pg:qs_pg_placetype_gp":"Suburb",
    "qs_pg:woe_adm0":23424977,
    "wd:wordcount":82,
    "wof:name":"Spring Mills",
    "wof:placetype":"neighbourhood",
    "wof:population":1031,
    "zs:area_m":6721757.30836,
    "zs:blockids":[
        340190105002021,
        340190105004001,
        340190105002014,
        340190105002026,
        340190105002020,
        340190105001015,
        340190105002016,
        340190105002023,
        340190105002018,
        340190105002025,
        340190105002027,
        340190105002022,
        340190105001014,
        340190105002028
    ],
    "zs:housing10":379,
    "zs:label":"Spring Mills",
    "zs:pop10":1031
},
  "geometry": {"coordinates":[-75.117216,40.603963],"type":"Point"}
}