{
  "type": "Feature",
  "properties": {
    "iso:country":"US",
    "name:ceb_x_preferred":[
        "Ketchum"
    ],
    "name:deu_x_preferred":[
        "Ketchum"
    ],
    "name:eng_x_preferred":[
        "Ketchum"
    ],
    "name:fra_x_preferred":[
        "Ketchum"
    ],
    "name:hbs_x_preferred":[
        "Ke\u010dam"
    ],
    "name:ita_x_preferred":[
        "Ketchum"
    ],
    "name:nld_x_preferred":[
        "Ketchum"
    ],
    "name:pol_x_preferred":[
        "Ketchum"
    ],
    "name:por_x_preferred":[
        "Ketchum"
    ],
    "name:srp_x_preferred":[
        "\u041a\u0435\u0447\u0430\u043c"
    ],
    "name:ukr_x_preferred":[
        "\u041a\u0435\u0442\u0447\u0430\u043c"
    ],
    "name:und_x_variant":[
        "Riley Plantation"
    ],
    "name:vol_x_preferred":[
        "Ketchum"
    ],
    "qs:gn_adm0_cc":"US",
    "qs:gn_fcode":"PPL",
    "qs:gn_local":4973342,
    "qs:gn_nam_loc":"newry",
    "qs:gn_namadm1":"ME",
    "qs:gn_name":"Ketchum",
    "qs:local_max":384,
    "qs:local_sum":396,
    "qs:localhoods":3,
    "qs:name":"Ketchum",
    "qs:name_adm0":"United States",
    "qs:name_adm1":"Maine",
    "qs:name_adm2":"Oxford",
    "qs:name_local":"Newry",
    "qs:photo_max":78,
    "qs:photo_sum":384,
    "qs:placetype":"Suburb",
    "qs:quad_count":23,
    "qs:woe_adm0":23424977,
    "qs:woe_adm1":2347578,
    "qs:woe_adm2":12588668,
    "qs:woe_lau":0,
    "qs:woe_local":2459623,
    "qs:woe_ver":"7.10.0",
    "wd:wordcount":70,
    "wof:lang":[
        "eng"
    ],
    "wof:name":"Ketchum",
    "wof:placetype":"neighbourhood",
    "wof:population":169,
    "zs:blockids":[
        230179651002086,
        230179651002058,
        230179651002075,
        230179651002079,
        230179651002054,
        230179651002068,
        230179651001393,
        230179651002023,
        230179651002024,
        230179651002084,
        230179651002078,
        230179651002089,
        230179651002029,
        230179651002049,
        230179651002048,
        230179651001389,
        230179651001386,
        230179651002092,
        230179651002072,
        230179651002080,
        230179651002055,
        230179651001379,
        230179651002069,
        230179651002028,
        230179651002041,
        230179651002088,
        230179651002083,
        230179651002027,
        230179651002082,
        230179651001392,
        230179651002091,
        230179651002036,
        230179651002081,
        230179651002032,
        230179651002077,
        230179651002061,
        230179651002067,
        230179651002064,
        230179651001383,
        230179651002071,
        230179651002087,
        230179651002040,
        230179651002090,
        230179651002051,
        230179651002076,
        230179651002059,
        230179651002074,
        230179651001391,
        230179651001380,
        230179651002066
    ],
    "zs:housing10":1163,
    "zs:pop10":169
},
  "geometry": {"coordinates":[-70.85010200000001,44.470837],"type":"Point"}
}