{
  "type": "Feature",
  "properties": {
    "gn:admin1_code":"MO",
    "gn:admin2_code":"179.0",
    "gn:admin3_code":"11530.0",
    "gn:asciiname":"Marcoot",
    "gn:country_code":"US",
    "gn:dem":362,
    "gn:elevation":"353.0",
    "gn:feature_class":"P",
    "gn:feature_code":"PPL",
    "gn:name":"Marcoot",
    "gn:population":0,
    "gn:timezone":"America/Chicago",
    "iso:country":"US",
    "wof:name":"Marcoot",
    "wof:placetype":"locality"
},
  "geometry": {"coordinates":[-91.25847,37.55449],"type":"Point"}
}