{
  "type": "Feature",
  "properties": {
    "iso:country":"US",
    "name:ara_x_preferred":[
        "\u0648\u0627\u0634\u0646\u0637\u0646\u060c \u0643\u0646\u062a\u0627\u0643\u064a"
    ],
    "name:ara_x_variant":[
        "\u0648\u0627\u0634\u0646\u0637\u0646"
    ],
    "name:arz_x_preferred":[
        "\u0648\u0627\u0634\u0646\u0637\u0646"
    ],
    "name:ceb_x_preferred":[
        "Old Washington"
    ],
    "name:eng_x_preferred":[
        "Old Washington"
    ],
    "name:eng_x_variant":[
        "Washington"
    ],
    "name:fra_x_preferred":[
        "Washington"
    ],
    "name:heb_x_preferred":[
        "\u05d5\u05d5\u05e9\u05d9\u05e0\u05d2\u05d8\u05d5\u05df"
    ],
    "name:nld_x_preferred":[
        "Washington"
    ],
    "name:urd_x_preferred":[
        "\u0648\u0627\u0634\u0646\u06af\u0679\u0646\u060c \u06a9\u06cc\u0646\u0679\u06a9\u06cc"
    ],
    "name:urd_x_variant":[
        "\u0648\u0627\u0634\u0646\u06af\u0679\u0646"
    ],
    "wof:lang":[
        "eng"
    ],
    "wof:name":"Old Washington",
    "wof:placetype":"neighbourhood",
    "wof:population":300,
    "zs:blockids":[
        211619604004011,
        211619604004028,
        211619604004030,
        211619604004005,
        211619604004019,
        211619603002031,
        211619603002042
    ],
    "zs:housing10":157,
    "zs:pop10":300
},
  "geometry": {"coordinates":[-83.800642,38.618005],"type":"Point"}
}