{
  "type": "Feature",
  "properties": {
    "iso:country":"US",
    "name:eng_x_preferred":[
        "Guinea Corner"
    ],
    "wof:name":"Guinea Corner",
    "wof:placetype":"neighbourhood",
    "wof:population":88,
    "zs:area_m":568479.170538,
    "zs:blockids":[
        230310253002002
    ],
    "zs:housing10":38,
    "zs:label":"Guinea Corner",
    "zs:pop10":88
},
  "geometry": {"coordinates":[-70.423238,43.45944],"type":"Point"}
}