{
  "type": "Feature",
  "properties": {
    "gn:admin1_code":"WV",
    "gn:admin2_code":"59",
    "gn:asciiname":"Hampden",
    "gn:country_code":"US",
    "gn:dem":338,
    "gn:elevation":"333.0",
    "gn:feature_class":"P",
    "gn:feature_code":"PPL",
    "gn:name":"Hampden",
    "gn:population":0,
    "gn:timezone":"America/New_York",
    "iso:country":"US",
    "wof:name":"Hampden",
    "wof:placetype":"locality"
},
  "geometry": {"coordinates":[-81.94873,37.63955],"type":"Point"}
}