{
  "type": "Feature",
  "properties": {
    "gn:admin1_code":"TX",
    "gn:admin2_code":"401.0",
    "gn:asciiname":"Valley Grove",
    "gn:country_code":"US",
    "gn:dem":134,
    "gn:elevation":"132.0",
    "gn:feature_class":"P",
    "gn:feature_code":"PPL",
    "gn:name":"Valley Grove",
    "gn:population":0,
    "gn:timezone":"America/Chicago",
    "iso:country":"US",
    "wof:name":"Valley Grove",
    "wof:placetype":"locality"
},
  "geometry": {"coordinates":[-94.80855,31.87906],"type":"Point"}
}