{
  "type": "Feature",
  "properties": {
    "gn:gn_country":"US",
    "gn:gn_fcode":"PPL",
    "gn:gn_pop":0,
    "iso:country":"US",
    "name:cat_x_preferred":[
        "Germantown"
    ],
    "name:ceb_x_preferred":[
        "Germantown"
    ],
    "name:deu_x_preferred":[
        "Germantown"
    ],
    "name:fra_x_preferred":[
        "Germantown"
    ],
    "name:ita_x_preferred":[
        "Germantown"
    ],
    "name:kor_x_preferred":[
        "\uc800\uba3c\ud0c0\uc6b4"
    ],
    "name:nld_x_preferred":[
        "Germantown"
    ],
    "name:nor_x_preferred":[
        "Germantown"
    ],
    "name:pol_x_preferred":[
        "Germantown"
    ],
    "name:por_x_preferred":[
        "Germantown"
    ],
    "name:slk_x_preferred":[
        "Germantown"
    ],
    "name:spa_x_preferred":[
        "Germantown"
    ],
    "name:srp_x_preferred":[
        "\u040f\u0435\u0440\u043c\u0430\u043d\u0442\u0430\u0443\u043d"
    ],
    "name:swe_x_preferred":[
        "Germantown"
    ],
    "name:ukr_x_preferred":[
        "\u0414\u0436\u0435\u0440\u043c\u0430\u043d\u0442\u0430\u0443\u043d"
    ],
    "name:vol_x_preferred":[
        "Germantown"
    ],
    "qs_pg:aaroncc":"US",
    "qs_pg:gn_country":"US",
    "qs_pg:gn_fcode":"PPL",
    "qs_pg:gn_pop":0,
    "qs_pg:name":"Germantown",
    "qs_pg:name_adm0":"United States",
    "qs_pg:name_adm1":"South Carolina",
    "qs_pg:photos":216,
    "qs_pg:photos_1k":44,
    "qs_pg:photos_9k":1,
    "qs_pg:photos_9r":4,
    "qs_pg:photos_all":216,
    "qs_pg:photos_sr":4,
    "qs_pg:pop_sr":0,
    "qs_pg:qs_pg_placetype":"locality",
    "qs_pg:qs_pg_placetype_gp":"Town",
    "qs_pg:woe_adm0":23424977,
    "woe:adm0_id":23424977,
    "woe:name_adm0":"United States",
    "woe:name_adm1":"South Carolina",
    "woe:placetype":"Town",
    "wof:name":"Germantown",
    "wof:placetype":"locality"
},
  "geometry": {"coordinates":[-79.44728000000001,33.19545],"type":"Point"}
}