{
  "type": "Feature",
  "properties": {
    "gn:admin1_code":"GA",
    "gn:admin2_code":"195.0",
    "gn:asciiname":"Alvin",
    "gn:country_code":"US",
    "gn:dem":258,
    "gn:elevation":"257.0",
    "gn:feature_class":"P",
    "gn:feature_code":"PPL",
    "gn:name":"Alvin",
    "gn:population":0,
    "gn:timezone":"America/New_York",
    "iso:country":"US",
    "name:ceb_x_preferred":[
        "Alvin"
    ],
    "name:deu_x_preferred":[
        "Alvin"
    ],
    "name:epo_x_preferred":[
        "Alvin"
    ],
    "name:est_x_preferred":[
        "Alvin"
    ],
    "name:fas_x_preferred":[
        "\u0622\u0644\u0648\u06cc\u0646"
    ],
    "name:fra_x_preferred":[
        "Alvin"
    ],
    "name:ita_x_preferred":[
        "Alvin"
    ],
    "name:nld_x_preferred":[
        "Alvin"
    ],
    "name:pol_x_preferred":[
        "Alvin"
    ],
    "name:por_x_preferred":[
        "Alvin"
    ],
    "name:rus_x_preferred":[
        "\u042d\u043b\u0432\u0438\u043d"
    ],
    "name:srp_x_preferred":[
        "\u0410\u043b\u0432\u0438\u043d"
    ],
    "name:swe_x_preferred":[
        "Alvin"
    ],
    "name:ukr_x_preferred":[
        "\u0415\u043b\u0432\u0456\u043d"
    ],
    "name:vol_x_preferred":[
        "Alvin"
    ],
    "wof:name":"Alvin",
    "wof:placetype":"locality"
},
  "geometry": {"coordinates":[-83.32404,34.23427],"type":"Point"}
}