{
  "type": "Feature",
  "properties": {
    "iso:country":"US",
    "name:eng_x_preferred":[
        "Jackson Height"
    ],
    "name:eng_x_variant":[
        "Jackson Heights"
    ],
    "name:urd_x_preferred":[
        "\u062c\u06cc\u06a9\u0633\u0646 \u06c1\u0627\u0626\u0679\u0633"
    ],
    "wof:name":"Jackson Height",
    "wof:placetype":"neighbourhood",
    "wof:population":13,
    "zs:area_m":73365.875931,
    "zs:blockids":[
        120570036001009,
        120570036001003,
        120570036001008
    ],
    "zs:housing10":9,
    "zs:label":"Jackson Height",
    "zs:pop10":13
},
  "geometry": {"coordinates":[-82.41353599999999,27.978769],"type":"Point"}
}