{
  "type": "Feature",
  "properties": {
    "gn:country":"US",
    "gn:fcode":"PPL",
    "gn:population":0,
    "iso:country":"US",
    "name:ceb_x_preferred":[
        "White City"
    ],
    "name:deu_x_preferred":[
        "White City"
    ],
    "name:eng_x_preferred":[
        "White City"
    ],
    "name:fra_x_preferred":[
        "Ville blanche"
    ],
    "name:heb_x_preferred":[
        "\u05d4\u05e2\u05d9\u05e8 \u05d4\u05dc\u05d1\u05e0\u05d4"
    ],
    "name:hin_x_preferred":[
        "\u0939\u094d\u0935\u093e\u0907\u091f \u0938\u093f\u091f\u0940"
    ],
    "name:ita_x_preferred":[
        "White City"
    ],
    "name:kor_x_preferred":[
        "\ud654\uc774\ud2b8\uc2dc\ud2f0"
    ],
    "name:nld_x_preferred":[
        "White City"
    ],
    "name:pol_x_preferred":[
        "White City"
    ],
    "name:por_x_preferred":[
        "White City"
    ],
    "name:spa_x_preferred":[
        "White City"
    ],
    "name:srp_x_preferred":[
        "\u0412\u0430\u0458\u0442 \u0421\u0438\u0442\u0438"
    ],
    "name:swe_x_preferred":[
        "White City"
    ],
    "name:und_x_variant":[
        "Whitetown"
    ],
    "name:urd_x_preferred":[
        "\u0648\u0627\u0626\u0679 \u0633\u0679\u06cc"
    ],
    "name:vie_x_preferred":[
        "White City"
    ],
    "name:vol_x_preferred":[
        "White City"
    ],
    "name:zho_x_preferred":[
        "\u767d\u57ce"
    ],
    "qs_pg:aaroncc":"US",
    "qs_pg:gn_country":"US",
    "qs_pg:gn_fcode":"PPL",
    "qs_pg:gn_pop":0,
    "qs_pg:name":"White City",
    "qs_pg:name_adm0":"United States",
    "qs_pg:name_adm1":"Montana",
    "qs_pg:photos":94,
    "qs_pg:photos_1k":19,
    "qs_pg:photos_9k":1,
    "qs_pg:photos_9r":3,
    "qs_pg:photos_all":94,
    "qs_pg:photos_sr":3,
    "qs_pg:pop_sr":0,
    "qs_pg:qs_pg_placetype":"locality",
    "qs_pg:qs_pg_placetype_gp":"Town",
    "qs_pg:woe_adm0":23424977,
    "woe:adm0_id":23424977,
    "woe:name_adm0":"United States",
    "woe:name_adm1":"Montana",
    "woe:placetype":"Town",
    "wof:name":"White City",
    "wof:placetype":"locality"
},
  "geometry": {"coordinates":[-110.68631999999999,45.30383],"type":"Point"}
}