{
  "type": "Feature",
  "properties": {
    "gn:admin1_code":"MO",
    "gn:admin2_code":"133.0",
    "gn:admin3_code":"64406.0",
    "gn:asciiname":"Pulltight",
    "gn:country_code":"US",
    "gn:dem":96,
    "gn:elevation":"97.0",
    "gn:feature_class":"P",
    "gn:feature_code":"PPL",
    "gn:name":"Pulltight",
    "gn:population":0,
    "gn:timezone":"America/Chicago",
    "iso:country":"US",
    "wof:name":"Pulltight",
    "wof:placetype":"locality"
},
  "geometry": {"coordinates":[-89.31924000000002,36.78256],"type":"Point"}
}