{
  "type": "Feature",
  "properties": {
    "gn:country":"US",
    "gn:fcode":"PPL",
    "gn:population":0,
    "iso:country":"US",
    "name:ceb_x_preferred":[
        "The Pines"
    ],
    "name:deu_x_preferred":[
        "The Pines"
    ],
    "name:eng_x_preferred":[
        "The Pines"
    ],
    "name:swe_x_preferred":[
        "The Pines"
    ],
    "qs_pg:aaroncc":"US",
    "qs_pg:gn_country":"US",
    "qs_pg:gn_fcode":"PPL",
    "qs_pg:gn_pop":0,
    "qs_pg:name":"The Pines",
    "qs_pg:name_adm0":"United States",
    "qs_pg:name_adm1":"Pennsylvania",
    "qs_pg:photos":155,
    "qs_pg:photos_1k":31,
    "qs_pg:photos_9k":1,
    "qs_pg:photos_9r":4,
    "qs_pg:photos_all":155,
    "qs_pg:photos_sr":4,
    "qs_pg:pop_sr":0,
    "qs_pg:qs_pg_placetype":"neighbourhood",
    "qs_pg:qs_pg_placetype_gp":"Suburb",
    "qs_pg:woe_adm0":23424977,
    "wd:wordcount":180,
    "wof:name":"The Pines",
    "wof:placetype":"neighbourhood",
    "wof:population":148,
    "zs:area_m":3169129.955893,
    "zs:blockids":[
        420010306002061,
        420010306002044
    ],
    "zs:housing10":64,
    "zs:label":"The Pines",
    "zs:pop10":148
},
  "geometry": {"coordinates":[-77.108946,39.895266],"type":"Point"}
}