{
  "type": "Feature",
  "properties": {
    "iso:country":"US",
    "name:eng_x_preferred":[
        "Codyville"
    ],
    "wof:name":"Codyville",
    "wof:placetype":"neighbourhood",
    "wof:population":41,
    "zs:area_m":496822.028621,
    "zs:blockids":[
        210279602001042,
        210279602002048
    ],
    "zs:housing10":19,
    "zs:label":"Codyville",
    "zs:pop10":41
},
  "geometry": {"coordinates":[-86.46064200000001,37.788724],"type":"Point"}
}