{
  "type": "Feature",
  "properties": {
    "gn:admin1_code":"NY",
    "gn:admin2_code":"53",
    "gn:admin3_code":"71993.0",
    "gn:asciiname":"Tall Pines Village",
    "gn:country_code":"US",
    "gn:dem":125,
    "gn:elevation":"124.0",
    "gn:feature_class":"P",
    "gn:feature_code":"PPL",
    "gn:name":"Tall Pines Village",
    "gn:population":0,
    "gn:timezone":"America/New_York",
    "iso:country":"US",
    "wof:name":"Tall Pines Village",
    "wof:placetype":"locality"
},
  "geometry": {"coordinates":[-75.92889,43.09472],"type":"Point"}
}