{
  "type": "Feature",
  "properties": {
    "gn:admin1_code":"NY",
    "gn:admin2_code":"17.0",
    "gn:admin3_code":"58288.0",
    "gn:asciiname":"Pitcher Springs",
    "gn:country_code":"US",
    "gn:dem":408,
    "gn:elevation":"407.0",
    "gn:feature_class":"P",
    "gn:feature_code":"PPL",
    "gn:name":"Pitcher Springs",
    "gn:population":0,
    "gn:timezone":"America/New_York",
    "iso:country":"US",
    "wof:name":"Pitcher Springs",
    "wof:placetype":"locality"
},
  "geometry": {"coordinates":[-75.82047,42.59896],"type":"Point"}
}