{
  "type": "Feature",
  "properties": {
    "gn:admin1_code":"GA",
    "gn:admin2_code":"115.0",
    "gn:asciiname":"Lakemoore Heights",
    "gn:country_code":"US",
    "gn:dem":212,
    "gn:elevation":"203.0",
    "gn:feature_class":"P",
    "gn:feature_code":"PPL",
    "gn:name":"Lakemoore Heights",
    "gn:population":0,
    "gn:timezone":"America/New_York",
    "iso:country":"US",
    "wof:name":"Lakemoore Heights",
    "wof:placetype":"locality"
},
  "geometry": {"coordinates":[-85.12523,34.2687],"type":"Point"}
}