{
  "type": "Feature",
  "properties": {
    "gn:admin1_code":"SC",
    "gn:admin2_code":"43.0",
    "gn:asciiname":"Allentown",
    "gn:country_code":"US",
    "gn:dem":22,
    "gn:elevation":"12.0",
    "gn:feature_class":"P",
    "gn:feature_code":"PPL",
    "gn:name":"Allentown",
    "gn:population":0,
    "gn:timezone":"America/New_York",
    "iso:country":"US",
    "name:cat_x_preferred":[
        "Allentown"
    ],
    "name:ceb_x_preferred":[
        "Allentown"
    ],
    "name:ces_x_preferred":[
        "Allentown"
    ],
    "name:deu_x_preferred":[
        "Allentown"
    ],
    "name:epo_x_preferred":[
        "Allentown"
    ],
    "name:fra_x_preferred":[
        "Allentown"
    ],
    "name:ita_x_preferred":[
        "Allentown"
    ],
    "name:jpn_x_preferred":[
        "\u30a2\u30ec\u30f3\u30bf\u30a6\u30f3"
    ],
    "name:nld_x_preferred":[
        "Allentown"
    ],
    "name:pol_x_preferred":[
        "Allentown"
    ],
    "name:por_x_preferred":[
        "Allentown"
    ],
    "name:rus_x_preferred":[
        "\u0410\u043b\u043b\u0435\u043d\u0442\u0430\u0443\u043d"
    ],
    "name:spa_x_preferred":[
        "Allentown"
    ],
    "name:srp_x_preferred":[
        "\u0410\u043b\u0435\u043d\u0442\u0430\u0443\u043d"
    ],
    "name:swe_x_preferred":[
        "Allentown"
    ],
    "name:ukr_x_preferred":[
        "\u0410\u043b\u043b\u0435\u043d\u0442\u0430\u0443\u043d"
    ],
    "name:urd_x_preferred":[
        "\u0627\u06cc\u0644\u0646 \u0679\u0627\u0624\u0646"
    ],
    "name:vol_x_preferred":[
        "Allentown"
    ],
    "name:zho_x_preferred":[
        "\u963f\u4f26\u6566"
    ],
    "wof:name":"Allentown",
    "wof:placetype":"locality"
},
  "geometry": {"coordinates":[-79.35033,33.626],"type":"Point"}
}