{
  "type": "Feature",
  "properties": {
    "iso:country":"US",
    "name:eng_x_preferred":[
        "Glen Echo"
    ],
    "wof:name":"Glen Echo",
    "wof:placetype":"neighbourhood"
},
  "geometry": {"coordinates":[-82.99993071551937,40.0174809595715],"type":"Point"}
}