{
  "type": "Feature",
  "properties": {
    "iso:country":"US",
    "name:eng_x_preferred":[
        "Glen Echo"
    ],
    "name:nld_x_preferred":[
        "Glen Echo"
    ],
    "wof:name":"Glen Echo",
    "wof:placetype":"neighbourhood"
},
  "geometry": {"coordinates":[-82.999931,40.017481],"type":"Point"}
}