{
  "type": "Feature",
  "properties": {
    "iso:country":"US",
    "name:eng_x_preferred":[
        "Killarney Circle"
    ],
    "name:eng_x_variant":[
        "Killarney Cir"
    ],
    "qs:gn_adm0_cc":"US",
    "qs:gn_local":5786882,
    "qs:gn_nam_loc":"Bellevue, King, Washington, US",
    "qs:gn_namadm1":"WA",
    "qs:local_max":5360,
    "qs:local_sum":48946,
    "qs:localhoods":55,
    "qs:name":"Killarney Circle",
    "qs:name_adm0":"United States",
    "qs:name_adm1":"Washington",
    "qs:name_adm2":"King",
    "qs:name_local":"Bellevue",
    "qs:photo_max":122,
    "qs:photo_sum":149,
    "qs:placetype":"Suburb",
    "qs:quad_count":6,
    "qs:woe_adm0":23424977,
    "qs:woe_adm1":2347606,
    "qs:woe_adm2":12590456,
    "qs:woe_lau":0,
    "qs:woe_local":2362031,
    "qs:woe_ver":"7.10.0",
    "wd:elevation":1120.0,
    "wd:wordcount":589,
    "wof:lang":[
        "eng"
    ],
    "wof:name":"Killarney Circle",
    "wof:placetype":"neighbourhood"
},
  "geometry": {"coordinates":[-122.204954,47.591998],"type":"Point"}
}