{
  "type": "Feature",
  "properties": {
    "gn:admin1_code":"FL",
    "gn:admin2_code":"57",
    "gn:asciiname":"Esco Park",
    "gn:country_code":"US",
    "gn:dem":22,
    "gn:elevation":"16.0",
    "gn:feature_class":"P",
    "gn:feature_code":"PPL",
    "gn:name":"Esco Park",
    "gn:population":0,
    "gn:timezone":"America/New_York",
    "iso:country":"US",
    "wof:name":"Esco Park",
    "wof:placetype":"locality"
},
  "geometry": {"coordinates":[-82.40299999999998,28.0043],"type":"Point"}
}