{
  "type": "Feature",
  "properties": {
    "gn:admin1_code":"AR",
    "gn:admin2_code":"143.0",
    "gn:admin3_code":"93123.0",
    "gn:asciiname":"Rhea",
    "gn:country_code":"US",
    "gn:dem":350,
    "gn:elevation":"344.0",
    "gn:feature_class":"P",
    "gn:feature_code":"PPL",
    "gn:name":"Rhea",
    "gn:population":0,
    "gn:timezone":"America/Chicago",
    "iso:country":"US",
    "name:eng_x_preferred":[
        "Rhea"
    ],
    "name:fas_x_preferred":[
        "\u0631\u06cc\u0627"
    ],
    "name:und_x_variant":[
        "Rheas Mills",
        "Rhea Mill"
    ],
    "name:zho_x_preferred":[
        "\u745e\u4e9e"
    ],
    "wof:name":"Rhea",
    "wof:placetype":"locality"
},
  "geometry": {"coordinates":[-94.40299,36.01425],"type":"Point"}
}