{
  "type": "Feature",
  "properties": {
    "gn:admin1_code":"AL",
    "gn:admin2_code":"127",
    "gn:asciiname":"Mount Hope",
    "gn:country_code":"US",
    "gn:dem":103,
    "gn:elevation":"101.0",
    "gn:feature_class":"P",
    "gn:feature_code":"PPL",
    "gn:name":"Mount Hope",
    "gn:population":0,
    "gn:timezone":"America/Chicago",
    "iso:country":"US",
    "name:cat_x_preferred":[
        "Mount Hope"
    ],
    "name:ceb_x_preferred":[
        "Mount Hope"
    ],
    "name:deu_x_preferred":[
        "Mount Hope"
    ],
    "name:fra_x_preferred":[
        "Mont Hope"
    ],
    "name:ita_x_preferred":[
        "Mount Hope"
    ],
    "name:jpn_x_preferred":[
        "\u30de\u30a6\u30f3\u30c8\u30fb\u30db\u30fc\u30d7"
    ],
    "name:nds_x_preferred":[
        "Mount Hope"
    ],
    "name:nld_x_preferred":[
        "Mount Hope"
    ],
    "name:pol_x_preferred":[
        "Mount Hope"
    ],
    "name:por_x_preferred":[
        "Mount Hope"
    ],
    "name:srp_x_preferred":[
        "\u041c\u0430\u0443\u043d\u0442 \u0425\u043e\u0443\u043f"
    ],
    "name:swe_x_preferred":[
        "Mount Hope"
    ],
    "name:ukr_x_preferred":[
        "\u041c\u0430\u0443\u043d\u0442-\u0413\u043e\u0443\u043f"
    ],
    "name:vol_x_preferred":[
        "Mount Hope"
    ],
    "wof:name":"Mount Hope",
    "wof:placetype":"locality"
},
  "geometry": {"coordinates":[-87.24110999999998,33.76927],"type":"Point"}
}