{
  "type": "Feature",
  "properties": {
    "gn:admin1_code":"AK",
    "gn:admin2_code":"290.0",
    "gn:asciiname":"Gost Creek",
    "gn:country_code":"US",
    "gn:dem":46,
    "gn:elevation":"20.0",
    "gn:feature_class":"P",
    "gn:feature_code":"PPL",
    "gn:name":"Gost Creek",
    "gn:population":0,
    "gn:timezone":"America/Anchorage",
    "iso:country":"US",
    "name:eng_x_preferred":[
        "Gost Creek"
    ],
    "name:und_x_variant":[
        "Ghost Creek"
    ],
    "wof:name":"Gost Creek",
    "wof:placetype":"locality"
},
  "geometry": {"coordinates":[-159.78583,62.21056],"type":"Point"}
}