{
  "type": "Feature",
  "properties": {
    "iso:country":"US",
    "name:eng_x_preferred":[
        "Mapledale"
    ],
    "wof:name":"Mapledale",
    "wof:placetype":"neighbourhood",
    "wof:population":4106,
    "zs:area_m":2142362.361516,
    "zs:blockids":[
        261251730002015,
        261251730002001,
        261251730002011,
        261251730002012,
        261251730001031,
        261251730001029,
        261251751006005,
        261251730001004,
        261251751006015,
        261251730002021,
        261251751007004,
        261251730002010,
        261251730002026,
        261251730004000,
        261251730004005,
        261251730002000,
        261251730001007,
        261251730001010,
        261251750003004,
        261251750002017,
        261251750003010,
        261251750002019,
        261251730004014,
        261251730002017,
        261251730002013,
        261251730002019,
        261251730002020,
        261251751006004,
        261251750002004,
        261251730004004,
        261251730001009,
        261251730001006,
        261251730001030,
        261251730001020,
        261251730001027,
        261251730001024,
        261251750002018,
        261251750004007,
        261251730004007,
        261251730004008,
        261251730002014,
        261251730002004,
        261251730004006,
        261251730004010,
        261251730001002,
        261251730001008,
        261251730001011,
        261251730001028,
        261251730001021,
        261251730001003,
        261251751006014,
        261251730003018,
        261251751006002,
        261251750002020,
        261251730002002,
        261251730002025,
        261251730004003,
        261251730004009,
        261251730004012,
        261251750003009,
        261251750002000,
        261251730004015,
        261251730001012,
        261251736001002,
        261251736001001,
        261251730001013,
        261251730001000,
        261251730001005,
        261251751006007,
        261251751006008,
        261251730003017,
        261251730002003,
        261251730002016,
        261251750002003,
        261251750002001,
        261251750003008,
        261251751006006,
        261251730001018,
        261251750002011,
        261251730002007,
        261251730004013,
        261251730002027,
        261251730004011,
        261251750002002,
        261251750002016,
        261251730001001,
        261251750002022,
        261251751007003,
        261251730002018,
        261251750002012,
        261251750002013,
        261251750002014,
        261251750004006,
        261251750003003,
        261251750002015,
        261251730001014,
        261251730001015,
        261251730001022,
        261251730001016,
        261251730001017,
        261251730001023,
        261251751006003
    ],
    "zs:housing10":2024,
    "zs:label":"Mapledale",
    "zs:pop10":4106
},
  "geometry": {"coordinates":[-83.116213,42.466735],"type":"Point"}
}