{
  "type": "Feature",
  "properties": {
    "gn:admin1_code":"TN",
    "gn:admin2_code":"129",
    "gn:asciiname":"Oak Hill",
    "gn:country_code":"US",
    "gn:dem":371,
    "gn:elevation":"361.0",
    "gn:feature_class":"P",
    "gn:feature_code":"PPL",
    "gn:name":"Oak Hill",
    "gn:population":0,
    "gn:timezone":"America/New_York",
    "iso:country":"US",
    "name:ceb_x_preferred":[
        "Oak Hill"
    ],
    "name:deu_x_preferred":[
        "Oak Hill"
    ],
    "name:fas_x_preferred":[
        "\u0627\u0648\u06a9 \u0647\u06cc\u0644"
    ],
    "name:fra_x_preferred":[
        "Oak Hill"
    ],
    "name:ita_x_preferred":[
        "Oak Hill"
    ],
    "name:kor_x_preferred":[
        "\uc624\ud06c\ud790"
    ],
    "name:nld_x_preferred":[
        "Oak Hill"
    ],
    "name:pol_x_preferred":[
        "Oak Hill"
    ],
    "name:por_x_preferred":[
        "Oak Hill"
    ],
    "name:spa_x_preferred":[
        "Oak Hill"
    ],
    "name:srp_x_preferred":[
        "\u041e\u0443\u043a \u0425\u0438\u043b"
    ],
    "name:swe_x_preferred":[
        "Oak Hill"
    ],
    "name:urd_x_preferred":[
        "\u0627\u0648\u06a9 \u06c1\u0644"
    ],
    "name:vol_x_preferred":[
        "Oak Hill"
    ],
    "wof:name":"Oak Hill",
    "wof:placetype":"locality"
},
  "geometry": {"coordinates":[-84.53216,36.16897],"type":"Point"}
}