{
  "type": "Feature",
  "properties": {
    "gn:admin1_code":"IA",
    "gn:admin2_code":"13.0",
    "gn:admin3_code":"94597.0",
    "gn:asciiname":"Castle Hill",
    "gn:country_code":"US",
    "gn:dem":275,
    "gn:elevation":"271.0",
    "gn:feature_class":"P",
    "gn:feature_code":"PPL",
    "gn:name":"Castle Hill",
    "gn:population":0,
    "gn:timezone":"America/Chicago",
    "iso:country":"US",
    "name:ceb_x_preferred":[
        "Castle Hill"
    ],
    "name:deu_x_preferred":[
        "Castle Hill"
    ],
    "name:fra_x_preferred":[
        "Castle Hill"
    ],
    "name:ita_x_preferred":[
        "Castle Hill"
    ],
    "name:mlg_x_preferred":[
        "Castle Hill"
    ],
    "name:nld_x_preferred":[
        "Castle Hill"
    ],
    "name:pol_x_preferred":[
        "Castle Hill"
    ],
    "name:spa_x_preferred":[
        "Castle Hill"
    ],
    "name:swe_x_preferred":[
        "Castle Hill"
    ],
    "name:ukr_x_preferred":[
        "\u041a\u0430\u0441\u043b-\u0413\u0456\u043b\u043b"
    ],
    "wof:name":"Castle Hill",
    "wof:placetype":"locality"
},
  "geometry": {"coordinates":[-92.39622,42.51455],"type":"Point"}
}