{
  "type": "Feature",
  "properties": {
    "gn:admin1_code":"NJ",
    "gn:admin2_code":"7.0",
    "gn:admin3_code":"26820.0",
    "gn:asciiname":"Highland Park",
    "gn:country_code":"US",
    "gn:dem":7,
    "gn:elevation":"6.0",
    "gn:feature_class":"P",
    "gn:feature_code":"PPL",
    "gn:name":"Highland Park",
    "gn:population":0,
    "gn:timezone":"America/New_York",
    "iso:country":"US",
    "name:ara_x_preferred":[
        "\u0647\u0627\u064a\u0644\u0627\u0646\u062f \u0628\u0627\u0631\u0643"
    ],
    "name:cat_x_preferred":[
        "Highland Park"
    ],
    "name:ceb_x_preferred":[
        "Highland Park"
    ],
    "name:deu_x_preferred":[
        "Highland Park"
    ],
    "name:fra_x_preferred":[
        "Highland Park"
    ],
    "name:hrv_x_preferred":[
        "Highland Park"
    ],
    "name:ita_x_preferred":[
        "Highland Park"
    ],
    "name:jpn_x_preferred":[
        "\u30cf\u30a4\u30e9\u30f3\u30c9\u30fb\u30d1\u30fc\u30af"
    ],
    "name:kor_x_preferred":[
        "\ud558\uc77c\ub79c\ub4dc\ud30c\ud06c"
    ],
    "name:nds_x_preferred":[
        "Highland Park"
    ],
    "name:nld_x_preferred":[
        "Highland Park"
    ],
    "name:nor_x_preferred":[
        "Highland Park"
    ],
    "name:pol_x_preferred":[
        "Highland Park"
    ],
    "name:por_x_preferred":[
        "Highland Park"
    ],
    "name:spa_x_preferred":[
        "Highland Park"
    ],
    "name:srp_x_preferred":[
        "\u0425\u0430\u0458\u043b\u0430\u043d\u0434 \u041f\u0430\u0440\u043a"
    ],
    "name:swa_x_preferred":[
        "Highland Park"
    ],
    "name:ukr_x_preferred":[
        "\u0413\u0430\u0439\u043b\u0435\u043d\u0434-\u041f\u0430\u0440\u043a"
    ],
    "name:vol_x_preferred":[
        "Highland Park"
    ],
    "wof:name":"Highland Park",
    "wof:placetype":"locality"
},
  "geometry": {"coordinates":[-75.10795,39.88872],"type":"Point"}
}