{
  "type": "Feature",
  "properties": {
    "gn:admin1_code":"OH",
    "gn:admin2_code":"117.0",
    "gn:admin3_code":"28378.0",
    "gn:asciiname":"Pulaskiville",
    "gn:country_code":"US",
    "gn:dem":410,
    "gn:elevation":"411.0",
    "gn:feature_class":"P",
    "gn:feature_code":"PPL",
    "gn:name":"Pulaskiville",
    "gn:population":0,
    "gn:timezone":"America/New_York",
    "iso:country":"US",
    "wof:name":"Pulaskiville",
    "wof:placetype":"locality"
},
  "geometry": {"coordinates":[-82.71016999999998,40.53395],"type":"Point"}
}