{
  "type": "Feature",
  "properties": {
    "iso:country":"US",
    "name:ast_x_preferred":[
        "Thunder Alley"
    ],
    "name:eng_x_preferred":[
        "Thunder Alley"
    ],
    "name:gle_x_preferred":[
        "Thunder Alley"
    ],
    "name:ita_x_preferred":[
        "Thunder Alley"
    ],
    "wd:wordcount":393,
    "wof:name":"Thunder Alley",
    "wof:placetype":"neighbourhood",
    "wof:population":5159,
    "zs:area_m":1779517.912854,
    "zs:blockids":[
        120860001293004,
        120860001311006,
        120860001311002,
        120860001311000,
        120860001131002,
        120860001311005,
        120860001311009,
        120860001311013,
        120860001233002,
        120860001325001,
        120860001325007,
        120860001292001,
        120860001325003,
        120860001311004,
        120860001311010,
        120860001311001,
        120860001311003,
        120860001325000,
        120860001293001,
        120860001293000,
        120860001325006,
        120860001311007,
        120860001293005,
        120860001293003,
        120860001311011,
        120860001292000,
        120860001311025,
        120860001131001,
        120860001293002,
        120860001311012,
        120860001325002,
        120860001311008
    ],
    "zs:housing10":3824,
    "zs:label":"Thunder Alley",
    "zs:pop10":5159
},
  "geometry": {"coordinates":[-80.13232600000001,25.944988],"type":"Point"}
}