{
  "type": "Feature",
  "properties": {
    "gn:country":"US",
    "gn:fcode":"PPL",
    "gn:population":0,
    "iso:country":"US",
    "name:azb_x_preferred":[
        "\u0632\u0648\u0631\u06cc\u0686"
    ],
    "name:eng_x_preferred":[
        "Zurich"
    ],
    "name:fas_x_preferred":[
        "\u0632\u0648\u0631\u06cc\u062e"
    ],
    "name:fra_x_preferred":[
        "Zurich"
    ],
    "name:tur_x_preferred":[
        "Zurich"
    ],
    "name:und_x_variant":[
        "Alvord"
    ],
    "name:urd_x_preferred":[
        "\u0632\u06cc\u0648\u0631\u062e"
    ],
    "name:zho_x_preferred":[
        "\u8607\u9ece\u4e16"
    ],
    "qs_pg:aaroncc":"US",
    "qs_pg:gn_country":"US",
    "qs_pg:gn_fcode":"PPL",
    "qs_pg:gn_pop":0,
    "qs_pg:name":"Zurich",
    "qs_pg:name_adm0":"United States",
    "qs_pg:name_adm1":"California",
    "qs_pg:photos":104,
    "qs_pg:photos_1k":21,
    "qs_pg:photos_9k":1,
    "qs_pg:photos_9r":3,
    "qs_pg:photos_all":104,
    "qs_pg:photos_sr":3,
    "qs_pg:pop_sr":0,
    "qs_pg:qs_pg_placetype":"locality",
    "qs_pg:qs_pg_placetype_gp":"Town",
    "qs_pg:woe_adm0":23424977,
    "woe:adm0_id":23424977,
    "woe:name_adm0":"United States",
    "woe:name_adm1":"California",
    "woe:placetype":"Town",
    "wof:name":"Zurich",
    "wof:placetype":"locality"
},
  "geometry": {"coordinates":[-118.26009999999999,37.18271],"type":"Point"}
}