{
  "type": "Feature",
  "properties": {
    "gn:country":"US",
    "gn:fcode":"PPL",
    "gn:population":0,
    "iso:country":"US",
    "name:bel_x_preferred":[
        "\u0421\u0442\u044d\u043d\u0442\u0430\u043d"
    ],
    "name:bul_x_preferred":[
        "\u0421\u0442\u0430\u043d\u0442\u044a\u043d"
    ],
    "name:cat_x_preferred":[
        "Stanton"
    ],
    "name:ceb_x_preferred":[
        "Stanton"
    ],
    "name:deu_x_preferred":[
        "Stanton"
    ],
    "name:eng_x_preferred":[
        "Stanton"
    ],
    "name:est_x_preferred":[
        "Stanton"
    ],
    "name:fin_x_preferred":[
        "Stanton"
    ],
    "name:fra_x_preferred":[
        "Stanton"
    ],
    "name:heb_x_preferred":[
        "\u05e1\u05d8\u05e0\u05d8\u05d5\u05df"
    ],
    "name:ita_x_preferred":[
        "Stanton"
    ],
    "name:nds_x_preferred":[
        "Stanton"
    ],
    "name:nld_x_preferred":[
        "Stanton"
    ],
    "name:nor_x_preferred":[
        "Stanton"
    ],
    "name:pol_x_preferred":[
        "Stanton"
    ],
    "name:por_x_preferred":[
        "Stanton"
    ],
    "name:rus_x_preferred":[
        "\u0421\u0442\u044d\u043d\u0442\u043e\u043d"
    ],
    "name:spa_x_preferred":[
        "Stanton"
    ],
    "name:srp_x_preferred":[
        "\u0421\u0442\u0430\u043d\u0442\u043e\u043d"
    ],
    "name:swe_x_preferred":[
        "Stanton"
    ],
    "name:ukr_x_preferred":[
        "\u0421\u0442\u0435\u043d\u0442\u043e\u043d"
    ],
    "name:und_x_variant":[
        "Staunton"
    ],
    "name:vol_x_preferred":[
        "Stanton"
    ],
    "qs_pg:aaroncc":"US",
    "qs_pg:gn_country":"US",
    "qs_pg:gn_fcode":"PPL",
    "qs_pg:gn_pop":0,
    "qs_pg:name":"Stanton",
    "qs_pg:name_adm0":"United States",
    "qs_pg:name_adm1":"New Jersey",
    "qs_pg:photos":1442,
    "qs_pg:photos_1k":292,
    "qs_pg:photos_9k":7,
    "qs_pg:photos_9r":7,
    "qs_pg:photos_all":1482,
    "qs_pg:photos_sr":12,
    "qs_pg:pop_sr":0,
    "qs_pg:qs_pg_placetype":"locality",
    "qs_pg:qs_pg_placetype_gp":"Town",
    "qs_pg:woe_adm0":23424977,
    "woe:adm0_id":23424977,
    "woe:name_adm0":"United States",
    "woe:name_adm1":"New Jersey",
    "woe:placetype":"Town",
    "wof:name":"Stanton",
    "wof:placetype":"locality"
},
  "geometry": {"coordinates":[-74.83766,40.5751],"type":"Point"}
}