{
  "type": "Feature",
  "properties": {
    "gn:country":"US",
    "gn:fcode":"PPL",
    "gn:population":0,
    "iso:country":"US",
    "name:eng_x_preferred":[
        "Boneville"
    ],
    "name:und_x_variant":[
        "Bonesville"
    ],
    "name:zho_x_preferred":[
        "\u535a\u6069\u7dad\u723e"
    ],
    "qs_pg:aaroncc":"US",
    "qs_pg:gn_country":"US",
    "qs_pg:gn_fcode":"PPL",
    "qs_pg:gn_pop":0,
    "qs_pg:name":"Boneville",
    "qs_pg:name_adm0":"United States",
    "qs_pg:name_adm1":"Georgia",
    "qs_pg:photos":2,
    "qs_pg:photos_1k":1,
    "qs_pg:photos_9k":1,
    "qs_pg:photos_9r":1,
    "qs_pg:photos_all":2,
    "qs_pg:photos_sr":1,
    "qs_pg:pop_sr":0,
    "qs_pg:qs_pg_placetype":"locality",
    "qs_pg:qs_pg_placetype_gp":"Town",
    "qs_pg:woe_adm0":23424977,
    "woe:adm0_id":23424977,
    "woe:name_adm0":"United States",
    "woe:name_adm1":"Georgia",
    "woe:placetype":"Town",
    "wof:name":"Boneville",
    "wof:placetype":"locality"
},
  "geometry": {"coordinates":[-82.43874,33.43347],"type":"Point"}
}