{
  "type": "Feature",
  "properties": {
    "gn:admin1_code":"NC",
    "gn:admin2_code":"133",
    "gn:admin3_code":"93976.0",
    "gn:asciiname":"Birchwood Park",
    "gn:country_code":"US",
    "gn:dem":6,
    "gn:elevation":"9.0",
    "gn:feature_class":"P",
    "gn:feature_code":"PPL",
    "gn:name":"Birchwood Park",
    "gn:population":0,
    "gn:timezone":"America/New_York",
    "iso:country":"US",
    "wof:name":"Birchwood Park",
    "wof:placetype":"locality"
},
  "geometry": {"coordinates":[-77.34135000000001,34.76405],"type":"Point"}
}