{
  "type": "Feature",
  "properties": {
    "gn:admin1_code":"MD",
    "gn:admin2_code":"45.0",
    "gn:asciiname":"Truitt",
    "gn:country_code":"US",
    "gn:dem":11,
    "gn:elevation":"11.0",
    "gn:feature_class":"P",
    "gn:feature_code":"PPL",
    "gn:name":"Truitt",
    "gn:population":0,
    "gn:timezone":"America/New_York",
    "iso:country":"US",
    "wof:name":"Truitt",
    "wof:placetype":"locality"
},
  "geometry": {"coordinates":[-75.36519,38.34678],"type":"Point"}
}