{
  "type": "Feature",
  "properties": {
    "gn:admin1_code":"NC",
    "gn:admin2_code":"163.0",
    "gn:admin3_code":"93032.0",
    "gn:asciiname":"Piney Ridge",
    "gn:country_code":"US",
    "gn:dem":48,
    "gn:elevation":"49.0",
    "gn:feature_class":"P",
    "gn:feature_code":"PPL",
    "gn:name":"Piney Ridge",
    "gn:population":0,
    "gn:timezone":"America/New_York",
    "iso:country":"US",
    "wof:name":"Piney Ridge",
    "wof:placetype":"locality"
},
  "geometry": {"coordinates":[-78.34416999999998,34.96767],"type":"Point"}
}