{
  "type": "Feature",
  "properties": {
    "gn:admin1_code":"NM",
    "gn:admin2_code":"27.0",
    "gn:asciiname":"Pine Lodge",
    "gn:country_code":"US",
    "gn:dem":1962,
    "gn:elevation":"1954.0",
    "gn:feature_class":"P",
    "gn:feature_code":"PPL",
    "gn:name":"Pine Lodge",
    "gn:population":0,
    "gn:timezone":"America/Denver",
    "iso:country":"US",
    "wof:name":"Pine Lodge",
    "wof:placetype":"locality"
},
  "geometry": {"coordinates":[-105.24499,33.62314],"type":"Point"}
}