{
  "type": "Feature",
  "properties": {
    "gn:admin1_code":"AR",
    "gn:admin2_code":"73.0",
    "gn:admin3_code":"93201.0",
    "gn:asciiname":"Gin City",
    "gn:country_code":"US",
    "gn:dem":67,
    "gn:elevation":"64.0",
    "gn:feature_class":"P",
    "gn:feature_code":"PPL",
    "gn:name":"Gin City",
    "gn:population":0,
    "gn:timezone":"America/Chicago",
    "iso:country":"US",
    "name:fas_x_preferred":[
        "\u062c\u06cc\u0646 \u0633\u06cc\u062a\u06cc"
    ],
    "name:zho_x_preferred":[
        "\u91d1\u57ce"
    ],
    "wof:name":"Gin City",
    "wof:placetype":"locality"
},
  "geometry": {"coordinates":[-93.72295,33.10708],"type":"Point"}
}