{
  "type": "Feature",
  "properties": {
    "gn:admin1_code":"TX",
    "gn:admin2_code":"147.0",
    "gn:asciiname":"Carson",
    "gn:country_code":"US",
    "gn:dem":177,
    "gn:elevation":"171.0",
    "gn:feature_class":"P",
    "gn:feature_code":"PPL",
    "gn:name":"Carson",
    "gn:population":0,
    "gn:timezone":"America/Chicago",
    "iso:country":"US",
    "name:bul_x_preferred":[
        "\u041a\u0430\u0440\u0441\u044a\u043d"
    ],
    "name:ceb_x_preferred":[
        "Carson"
    ],
    "name:ces_x_preferred":[
        "Carson"
    ],
    "name:deu_x_preferred":[
        "Carson"
    ],
    "name:epo_x_preferred":[
        "Carson"
    ],
    "name:fin_x_preferred":[
        "Carson"
    ],
    "name:fra_x_preferred":[
        "Carson"
    ],
    "name:heb_x_preferred":[
        "\u05e7\u05e8\u05e1\u05d5\u05df"
    ],
    "name:ita_x_preferred":[
        "Carson"
    ],
    "name:jpn_x_preferred":[
        "\u30ab\u30fc\u30bd\u30f3"
    ],
    "name:lav_x_preferred":[
        "K\u0101rsons"
    ],
    "name:nld_x_preferred":[
        "Carson"
    ],
    "name:pol_x_preferred":[
        "Carson"
    ],
    "name:por_x_preferred":[
        "Carson"
    ],
    "name:ron_x_preferred":[
        "Carson"
    ],
    "name:rus_x_preferred":[
        "\u041a\u0430\u0440\u0441\u043e\u043d"
    ],
    "name:srp_x_preferred":[
        "\u041a\u0430\u0440\u0441\u043e\u043d"
    ],
    "name:swa_x_preferred":[
        "Carson"
    ],
    "name:swe_x_preferred":[
        "Carson"
    ],
    "name:tgl_x_preferred":[
        "Carson"
    ],
    "name:ukr_x_preferred":[
        "\u041a\u0430\u0440\u0441\u043e\u043d"
    ],
    "name:vol_x_preferred":[
        "Carson"
    ],
    "wof:name":"Carson",
    "wof:placetype":"locality"
},
  "geometry": {"coordinates":[-96.00581,33.70205],"type":"Point"}
}