{
  "type": "Feature",
  "properties": {
    "iso:country":"US",
    "name:eng_x_preferred":[
        "Oak Springs"
    ],
    "wof:name":"Oak Springs",
    "wof:placetype":"neighbourhood",
    "wof:population":1344,
    "zs:area_m":707020.48407,
    "zs:blockids":[
        484910206021018,
        484910206023008,
        484910206023011,
        484910206023003,
        484910206023020,
        484910206022026,
        484910206023009,
        484910206023002,
        484910206023015,
        484910206023013,
        484910206023014,
        484910206021019,
        484910206023012,
        484910206021020,
        484910206022027,
        484910206021007,
        484910206023010
    ],
    "zs:housing10":462,
    "zs:label":"Oak Springs",
    "zs:pop10":1344
},
  "geometry": {"coordinates":[-97.703973,30.524549],"type":"Point"}
}