{
  "type": "Feature",
  "properties": {
    "gn:admin1_code":"WV",
    "gn:admin2_code":"45",
    "gn:asciiname":"Chambers",
    "gn:country_code":"US",
    "gn:dem":274,
    "gn:elevation":"272.0",
    "gn:feature_class":"P",
    "gn:feature_code":"PPL",
    "gn:name":"Chambers",
    "gn:population":0,
    "gn:timezone":"America/New_York",
    "iso:country":"US",
    "wof:name":"Chambers",
    "wof:placetype":"locality"
},
  "geometry": {"coordinates":[-81.88011999999998,37.82122],"type":"Point"}
}