{
  "type": "Feature",
  "properties": {
    "gn:admin1_code":"MT",
    "gn:admin2_code":"73.0",
    "gn:asciiname":"Birch Creek Colony",
    "gn:country_code":"US",
    "gn:dem":1211,
    "gn:elevation":"1209.0",
    "gn:feature_class":"P",
    "gn:feature_code":"PPL",
    "gn:name":"Birch Creek Colony",
    "gn:population":0,
    "gn:timezone":"America/Denver",
    "iso:country":"US",
    "wof:name":"Birch Creek Colony",
    "wof:placetype":"locality"
},
  "geometry": {"coordinates":[-112.47032,48.24775],"type":"Point"}
}