{
  "type": "Feature",
  "properties": {
    "gn:admin1_code":"MI",
    "gn:admin2_code":"53.0",
    "gn:admin3_code":"51560.0",
    "gn:asciiname":"White City",
    "gn:country_code":"US",
    "gn:dem":408,
    "gn:elevation":"409.0",
    "gn:feature_class":"P",
    "gn:feature_code":"PPL",
    "gn:name":"White City",
    "gn:population":0,
    "gn:timezone":"America/Menominee",
    "iso:country":"US",
    "name:ceb_x_preferred":[
        "White City"
    ],
    "name:deu_x_preferred":[
        "White City"
    ],
    "name:fra_x_preferred":[
        "Ville blanche"
    ],
    "name:heb_x_preferred":[
        "\u05d4\u05e2\u05d9\u05e8 \u05d4\u05dc\u05d1\u05e0\u05d4"
    ],
    "name:hin_x_preferred":[
        "\u0939\u094d\u0935\u093e\u0907\u091f \u0938\u093f\u091f\u0940"
    ],
    "name:ita_x_preferred":[
        "White City"
    ],
    "name:kor_x_preferred":[
        "\ud654\uc774\ud2b8\uc2dc\ud2f0"
    ],
    "name:nld_x_preferred":[
        "White City"
    ],
    "name:pol_x_preferred":[
        "White City"
    ],
    "name:por_x_preferred":[
        "White City"
    ],
    "name:spa_x_preferred":[
        "White City"
    ],
    "name:srp_x_preferred":[
        "\u0412\u0430\u0458\u0442 \u0421\u0438\u0442\u0438"
    ],
    "name:swe_x_preferred":[
        "White City"
    ],
    "name:urd_x_preferred":[
        "\u0648\u0627\u0626\u0679 \u0633\u0679\u06cc"
    ],
    "name:vie_x_preferred":[
        "White City"
    ],
    "name:vol_x_preferred":[
        "White City"
    ],
    "name:zho_x_preferred":[
        "\u767d\u57ce"
    ],
    "wof:name":"White City",
    "wof:placetype":"locality"
},
  "geometry": {"coordinates":[-89.5371,46.41134],"type":"Point"}
}