{
  "type": "Feature",
  "properties": {
    "iso:country":"US",
    "name:eng_x_preferred":[
        "Lake Sherwood Hills"
    ],
    "wof:name":"Lake Sherwood Hills",
    "wof:placetype":"neighbourhood",
    "wof:population":2599,
    "zs:area_m":1748790.569939,
    "zs:blockids":[
        120950149041003,
        120950149041005,
        120950149091008,
        120950149081038,
        120950149041001,
        120950149041016
    ],
    "zs:housing10":1013,
    "zs:label":"Lake Sherwood Hills",
    "zs:pop10":2599
},
  "geometry": {"coordinates":[-81.494063,28.555606],"type":"Point"}
}