{
  "type": "Feature",
  "properties": {
    "gn:admin1_code":"AR",
    "gn:admin2_code":"1.0",
    "gn:admin3_code":"90168.0",
    "gn:asciiname":"Bayou Meto",
    "gn:country_code":"US",
    "gn:dem":61,
    "gn:elevation":"57.0",
    "gn:feature_class":"P",
    "gn:feature_code":"PPL",
    "gn:name":"Bayou Meto",
    "gn:population":0,
    "gn:timezone":"America/Chicago",
    "iso:country":"US",
    "name:eng_x_preferred":[
        "Bayou Meto"
    ],
    "name:und_x_variant":[
        "Bayou Metoe"
    ],
    "name:zho_x_preferred":[
        "\u62dc\u70cf\u6885\u6258"
    ],
    "wof:name":"Bayou Meto",
    "wof:placetype":"locality"
},
  "geometry": {"coordinates":[-91.52124000000001,34.22371],"type":"Point"}
}