{
  "type": "Feature",
  "properties": {
    "iso:country":"US",
    "name:eng_x_preferred":[
        "Merry Acres"
    ],
    "wof:name":"Merry Acres",
    "wof:placetype":"neighbourhood",
    "wof:population":762,
    "zs:area_m":1243633.693275,
    "zs:blockids":[
        130950005022054,
        130950005022032,
        130950006001044,
        130950005022043,
        130950005022051,
        130950005022030,
        130950006001041,
        130950005022033,
        130950005022045,
        130950005022024,
        130950005022050,
        130950005022044,
        130950006001043,
        130950005022046,
        130950009002019,
        130950009002009,
        130950005022011,
        130950009002002,
        130950005022034,
        130950005022020,
        130950005022047,
        130950005022009,
        130950005022023,
        130950009002018,
        130950005022035,
        130950005022055,
        130950005022048,
        130950005022042,
        130950005022040,
        130950005022007,
        130950005022038,
        130950005022022,
        130950006001046,
        130950005022053,
        130950009002025,
        130950005022031,
        130950005022010,
        130950005022039,
        130950005022036,
        130950005022025,
        130950006001042,
        130950006001035,
        130950005022041,
        130950005022037,
        130950005022049,
        130950005022059,
        130950005022021,
        130950009002010,
        130950005022052,
        130950005022005
    ],
    "zs:housing10":382,
    "zs:label":"Merry Acres",
    "zs:pop10":762
},
  "geometry": {"coordinates":[-84.190573,31.589056],"type":"Point"}
}