{
  "type": "Feature",
  "properties": {
    "gn:admin1_code":"MT",
    "gn:admin2_code":"63.0",
    "gn:asciiname":"Westview Park",
    "gn:country_code":"US",
    "gn:dem":988,
    "gn:elevation":"999.0",
    "gn:feature_class":"P",
    "gn:feature_code":"PPL",
    "gn:name":"Westview Park",
    "gn:population":0,
    "gn:timezone":"America/Denver",
    "iso:country":"US",
    "wof:name":"Westview Park",
    "wof:placetype":"locality"
},
  "geometry": {"coordinates":[-114.04261,46.91187],"type":"Point"}
}