{
  "type": "Feature",
  "properties": {
    "gn:admin1_code":"VA",
    "gn:admin2_code":"730",
    "gn:asciiname":"Camelot",
    "gn:country_code":"US",
    "gn:dem":54,
    "gn:elevation":"49.0",
    "gn:feature_class":"P",
    "gn:feature_code":"PPL",
    "gn:name":"Camelot",
    "gn:population":0,
    "gn:timezone":"America/New_York",
    "iso:country":"US",
    "name:afr_x_preferred":[
        "Camelot"
    ],
    "name:ara_x_preferred":[
        "\u0643\u0627\u0645\u064a\u0644\u0648\u062a"
    ],
    "name:bel_x_preferred":[
        "\u041a\u0430\u043c\u0435\u043b\u043e\u0442"
    ],
    "name:bul_x_preferred":[
        "\u041a\u0430\u043c\u0435\u043b\u043e\u0442"
    ],
    "name:cat_x_preferred":[
        "Camelot"
    ],
    "name:ces_x_preferred":[
        "Kamelot"
    ],
    "name:cym_x_preferred":[
        "Camelot"
    ],
    "name:dan_x_preferred":[
        "Camelot"
    ],
    "name:deu_x_preferred":[
        "Camelot"
    ],
    "name:ell_x_preferred":[
        "\u039a\u03ac\u03bc\u03b5\u03bb\u03bf\u03c4"
    ],
    "name:epo_x_preferred":[
        "Kameloto"
    ],
    "name:eus_x_preferred":[
        "Kamelot"
    ],
    "name:fas_x_preferred":[
        "\u06a9\u0645\u0644\u0648\u062a"
    ],
    "name:fin_x_preferred":[
        "Camelot"
    ],
    "name:fra_x_preferred":[
        "Camelot"
    ],
    "name:glg_x_preferred":[
        "Camelot"
    ],
    "name:heb_x_preferred":[
        "\u05e7\u05de\u05dc\u05d5\u05d8"
    ],
    "name:hun_x_preferred":[
        "Camelot"
    ],
    "name:ind_x_preferred":[
        "Camelot"
    ],
    "name:ita_x_preferred":[
        "Camelot"
    ],
    "name:jpn_x_preferred":[
        "\u30ad\u30e3\u30e1\u30ed\u30c3\u30c8"
    ],
    "name:kat_x_preferred":[
        "\u10d9\u10d0\u10db\u10d4\u10da\u10dd\u10e2\u10d8"
    ],
    "name:kor_x_preferred":[
        "\uce74\uba5c\ub86f"
    ],
    "name:kur_x_preferred":[
        "Kamelot"
    ],
    "name:lat_x_preferred":[
        "Camelot"
    ],
    "name:nld_x_preferred":[
        "Camelot"
    ],
    "name:nor_x_preferred":[
        "Camelot"
    ],
    "name:pol_x_preferred":[
        "Camelot"
    ],
    "name:por_x_preferred":[
        "Camelot"
    ],
    "name:rus_x_preferred":[
        "\u041a\u0430\u043c\u0435\u043b\u043e\u0442"
    ],
    "name:sco_x_preferred":[
        "Camelot"
    ],
    "name:slk_x_preferred":[
        "Camelot"
    ],
    "name:spa_x_preferred":[
        "Camelot"
    ],
    "name:swe_x_preferred":[
        "Camelot"
    ],
    "name:tur_x_preferred":[
        "Camelot"
    ],
    "name:ukr_x_preferred":[
        "\u041a\u0430\u043c\u0435\u043b\u043e\u0442"
    ],
    "name:vie_x_preferred":[
        "Camelot"
    ],
    "name:zho_x_preferred":[
        "\u5361\u7f8e\u6d1b"
    ],
    "wof:name":"Camelot",
    "wof:placetype":"locality"
},
  "geometry": {"coordinates":[-77.40526,37.18376],"type":"Point"}
}