{
  "type": "Feature",
  "properties": {
    "gn:admin1_code":"GA",
    "gn:admin2_code":"193",
    "gn:asciiname":"Saint Louis",
    "gn:country_code":"US",
    "gn:dem":125,
    "gn:elevation":"121.0",
    "gn:feature_class":"P",
    "gn:feature_code":"PPL",
    "gn:name":"Saint Louis",
    "gn:population":0,
    "gn:timezone":"America/New_York",
    "iso:country":"US",
    "name:cat_x_preferred":[
        "Saint Louis"
    ],
    "name:ceb_x_preferred":[
        "Saint Louis"
    ],
    "name:ces_x_preferred":[
        "Saint Louis"
    ],
    "name:cym_x_preferred":[
        "Saint Louis"
    ],
    "name:eus_x_preferred":[
        "Saint Louis"
    ],
    "name:fas_x_preferred":[
        "\u0633\u0646\u062a \u0644\u0648\u0626\u06cc\u0633"
    ],
    "name:fin_x_preferred":[
        "Saint Louis"
    ],
    "name:fry_x_preferred":[
        "Saint Louis"
    ],
    "name:heb_x_preferred":[
        "\u05e1\u05e0\u05d8 \u05dc\u05d5\u05d0\u05d9\u05e1"
    ],
    "name:hun_x_preferred":[
        "Saint Louis"
    ],
    "name:jpn_x_preferred":[
        "\u30bb\u30f3\u30c8\u30eb\u30a4\u30b9"
    ],
    "name:kor_x_preferred":[
        "\uc138\uc778\ud2b8\ub8e8\uc774\uc2a4"
    ],
    "name:pol_x_preferred":[
        "Saint Louis"
    ],
    "name:swe_x_preferred":[
        "Saint Louis"
    ],
    "name:tha_x_preferred":[
        "\u0e40\u0e0b\u0e19\u0e15\u0e4c\u0e2b\u0e25\u0e38\u0e22\u0e2a\u0e4c"
    ],
    "name:tur_x_preferred":[
        "Saint Louis"
    ],
    "name:vol_x_preferred":[
        "Saint Louis"
    ],
    "name:zho_x_preferred":[
        "\u5723\u8def\u6613\u65af"
    ],
    "wof:name":"Saint Louis",
    "wof:placetype":"locality"
},
  "geometry": {"coordinates":[-83.86685,32.46543],"type":"Point"}
}