{
  "type": "Feature",
  "properties": {
    "iso:country":"US",
    "name:eng_x_preferred":[
        "Lac Amora"
    ],
    "qs:gn_local":0,
    "qs:local_max":2502,
    "qs:local_sum":10799,
    "qs:localhoods":32,
    "qs:name":"Lac Amora",
    "qs:name_adm0":"United States",
    "qs:name_adm1":"Colorado",
    "qs:name_adm2":"Broomfield",
    "qs:name_local":"Broomfield",
    "qs:photo_max":38,
    "qs:photo_sum":190,
    "qs:placetype":"Suburb",
    "qs:quad_count":12,
    "qs:woe_adm0":23424977,
    "qs:woe_adm1":2347564,
    "qs:woe_adm2":26343011,
    "qs:woe_lau":0,
    "qs:woe_local":2370243,
    "qs:woe_ver":"7.10.0",
    "wof:lang":[
        "eng"
    ],
    "wof:name":"Lac Amora",
    "wof:placetype":"neighbourhood",
    "wof:population":1182,
    "zs:blockids":[
        80140312003014,
        80140312003001,
        80140312003003,
        80140312003010,
        80140312002013,
        80140312003005,
        80140312003009,
        80140312003007,
        80140312003008,
        80140312003013,
        80140312003004,
        80140312003011,
        80140312002012
    ],
    "zs:housing10":448,
    "zs:pop10":1182
},
  "geometry": {"coordinates":[-105.10716499999999,39.932817],"type":"Point"}
}