{
  "type": "Feature",
  "properties": {
    "gn:country":"US",
    "gn:fcode":"PPL",
    "gn:population":0,
    "iso:country":"US",
    "name:eng_x_preferred":[
        "West Louisville"
    ],
    "name:lld_x_preferred":[
        "West Louisville"
    ],
    "qs_pg:aaroncc":"US",
    "qs_pg:gn_country":"US",
    "qs_pg:gn_fcode":"PPL",
    "qs_pg:gn_pop":0,
    "qs_pg:name":"West Louisville",
    "qs_pg:name_adm0":"United States",
    "qs_pg:name_adm1":"Kentucky",
    "qs_pg:photos_9k":1,
    "qs_pg:photos_9r":1,
    "qs_pg:photos_all":11,
    "qs_pg:photos_sr":0,
    "qs_pg:pop_sr":5,
    "qs_pg:qs_pg_placetype":"locality",
    "qs_pg:qs_pg_placetype_gp":"Town",
    "qs_pg:woe_adm0":23424977,
    "woe:adm0_id":23424977,
    "woe:name_adm0":"United States",
    "woe:name_adm1":"Kentucky",
    "woe:placetype":"Town",
    "wof:name":"West Louisville",
    "wof:placetype":"locality"
},
  "geometry": {"coordinates":[-87.28694,37.69671],"type":"Point"}
}