{
  "type": "Feature",
  "properties": {
    "gn:admin1_code":"IL",
    "gn:admin2_code":"89.0",
    "gn:admin3_code":"66430.0",
    "gn:asciiname":"Binnie Hills",
    "gn:country_code":"US",
    "gn:dem":277,
    "gn:elevation":"276.0",
    "gn:feature_class":"P",
    "gn:feature_code":"PPL",
    "gn:name":"Binnie Hills",
    "gn:population":0,
    "gn:timezone":"America/Chicago",
    "iso:country":"US",
    "wof:name":"Binnie Hills",
    "wof:placetype":"locality"
},
  "geometry": {"coordinates":[-88.36369000000001,42.12114],"type":"Point"}
}