{
  "type": "Feature",
  "properties": {
    "gn:admin1_code":"VA",
    "gn:admin2_code":"35",
    "gn:asciiname":"Crooked Oak",
    "gn:country_code":"US",
    "gn:dem":801,
    "gn:elevation":"802.0",
    "gn:feature_class":"P",
    "gn:feature_code":"PPL",
    "gn:name":"Crooked Oak",
    "gn:population":0,
    "gn:timezone":"America/New_York",
    "iso:country":"US",
    "wof:name":"Crooked Oak",
    "wof:placetype":"locality"
},
  "geometry": {"coordinates":[-80.60785,36.72013],"type":"Point"}
}