{
  "type": "Feature",
  "properties": {
    "gn:country":"US",
    "gn:fcode":"PPL",
    "gn:population":0,
    "iso:country":"US",
    "name:ceb_x_preferred":[
        "Hazel Green"
    ],
    "name:deu_x_preferred":[
        "Hazel Green"
    ],
    "name:ita_x_preferred":[
        "Hazel Green"
    ],
    "name:nld_x_preferred":[
        "Hazel Green"
    ],
    "name:pol_x_preferred":[
        "Hazel Green"
    ],
    "name:spa_x_preferred":[
        "Hazel Green"
    ],
    "name:srp_x_preferred":[
        "\u0425\u0435\u0458\u0437\u0435\u043b \u0413\u0440\u0438\u043d"
    ],
    "name:swe_x_preferred":[
        "Hazel Green"
    ],
    "name:vol_x_preferred":[
        "Hazel Green"
    ],
    "qs_pg:aaroncc":"US",
    "qs_pg:gn_country":"US",
    "qs_pg:gn_fcode":"PPL",
    "qs_pg:gn_pop":0,
    "qs_pg:name":"Hazel Green",
    "qs_pg:name_adm0":"United States",
    "qs_pg:name_adm1":"Oregon",
    "qs_pg:photos":46,
    "qs_pg:photos_1k":9,
    "qs_pg:photos_9k":1,
    "qs_pg:photos_9r":2,
    "qs_pg:photos_all":46,
    "qs_pg:photos_sr":2,
    "qs_pg:pop_sr":0,
    "qs_pg:qs_pg_placetype":"locality",
    "qs_pg:qs_pg_placetype_gp":"Town",
    "qs_pg:woe_adm0":23424977,
    "woe:adm0_id":23424977,
    "woe:name_adm0":"United States",
    "woe:name_adm1":"Oregon",
    "woe:placetype":"Town",
    "wof:name":"Hazel Green",
    "wof:placetype":"locality"
},
  "geometry": {"coordinates":[-122.92648,45.0104],"type":"Point"}
}