{
  "type": "Feature",
  "properties": {
    "gn:admin1_code":"VA",
    "gn:admin2_code":"59",
    "gn:asciiname":"Ravensworth Grove",
    "gn:country_code":"US",
    "gn:dem":101,
    "gn:elevation":"96.0",
    "gn:feature_class":"P",
    "gn:feature_code":"PPL",
    "gn:name":"Ravensworth Grove",
    "gn:population":0,
    "gn:timezone":"America/New_York",
    "iso:country":"US",
    "wof:name":"Ravensworth Grove",
    "wof:placetype":"locality"
},
  "geometry": {"coordinates":[-77.21443000000002,38.81789000000001],"type":"Point"}
}