{
  "type": "Feature",
  "properties": {
    "gn:admin1_code":"AL",
    "gn:admin2_code":"73.0",
    "gn:asciiname":"Praco",
    "gn:country_code":"US",
    "gn:dem":106,
    "gn:elevation":"105.0",
    "gn:feature_class":"P",
    "gn:feature_code":"PPL",
    "gn:name":"Praco",
    "gn:population":0,
    "gn:timezone":"America/Chicago",
    "iso:country":"US",
    "wof:name":"Praco",
    "wof:placetype":"locality"
},
  "geometry": {"coordinates":[-87.1125,33.61372],"type":"Point"}
}