{
  "type": "Feature",
  "properties": {
    "gn:admin1_code":"SC",
    "gn:admin2_code":"33.0",
    "gn:asciiname":"Five Forks",
    "gn:country_code":"US",
    "gn:dem":38,
    "gn:elevation":"44.0",
    "gn:feature_class":"P",
    "gn:feature_code":"PPL",
    "gn:name":"Five Forks",
    "gn:population":0,
    "gn:timezone":"America/New_York",
    "iso:country":"US",
    "name:deu_x_preferred":[
        "Five Forks"
    ],
    "wof:name":"Five Forks",
    "wof:placetype":"locality"
},
  "geometry": {"coordinates":[-79.32115,34.47933],"type":"Point"}
}