{
  "type": "Feature",
  "properties": {
    "gn:admin1_code":"FL",
    "gn:admin2_code":"105.0",
    "gn:asciiname":"Lowes Mobile Home Park",
    "gn:country_code":"US",
    "gn:dem":45,
    "gn:elevation":"41.0",
    "gn:feature_class":"P",
    "gn:feature_code":"PPL",
    "gn:name":"Lowes Mobile Home Park",
    "gn:population":0,
    "gn:timezone":"America/New_York",
    "iso:country":"US",
    "wof:name":"Lowes Mobile Home Park",
    "wof:placetype":"campus"
},
  "geometry": {"coordinates":[-81.67801,27.99572],"type":"Point"}
}