{
  "type": "Feature",
  "properties": {
    "iso:country":"US",
    "name:eng_x_preferred":[
        "Makawao Ahupua`a"
    ],
    "qs:gn_adm0_cc":"US",
    "qs:gn_local":5850616,
    "qs:gn_nam_loc":"makawao",
    "qs:gn_namadm1":"HI",
    "qs:local_max":678,
    "qs:local_sum":1469,
    "qs:localhoods":4,
    "qs:name":"Makawao Ahupua`a",
    "qs:name_adm0":"United States",
    "qs:name_adm1":"Hawaii",
    "qs:name_adm2":"Maui",
    "qs:name_local":"Makawao",
    "qs:photo_max":118,
    "qs:photo_sum":257,
    "qs:placetype":"Suburb",
    "qs:quad_count":18,
    "qs:woe_adm0":23424977,
    "qs:woe_adm1":2347570,
    "qs:woe_adm2":12588033,
    "qs:woe_lau":0,
    "qs:woe_local":2444391,
    "qs:woe_ver":"7.10.0",
    "wof:lang":[
        "eng"
    ],
    "wof:name":"Makawao Ahupua`a",
    "wof:placetype":"neighbourhood",
    "wof:population":1593,
    "zs:blockids":[
        150090302011048,
        150090304031003,
        150090304032008,
        150090304031010,
        150090304032006,
        150090304031011,
        150090304031007,
        150090304031004,
        150090304031017,
        150090304031008,
        150090304031002,
        150090304031000,
        150090304031016,
        150090304031001
    ],
    "zs:housing10":663,
    "zs:pop10":1593
},
  "geometry": {"coordinates":[-156.29674600000001,20.841139],"type":"Point"}
}