{
  "type": "Feature",
  "properties": {
    "gn:admin1_code":"KY",
    "gn:admin2_code":"21",
    "gn:asciiname":"Clifton",
    "gn:country_code":"US",
    "gn:dem":259,
    "gn:elevation":"261.0",
    "gn:feature_class":"P",
    "gn:feature_code":"PPL",
    "gn:name":"Clifton",
    "gn:population":0,
    "gn:timezone":"America/New_York",
    "iso:country":"US",
    "wof:name":"Clifton",
    "wof:placetype":"locality"
},
  "geometry": {"coordinates":[-84.68799999999997,37.64952],"type":"Point"}
}