{
  "type": "Feature",
  "properties": {
    "gn:admin1_code":"GA",
    "gn:admin2_code":"87.0",
    "gn:asciiname":"Lynn",
    "gn:country_code":"US",
    "gn:dem":47,
    "gn:elevation":"40.0",
    "gn:feature_class":"P",
    "gn:feature_code":"PPL",
    "gn:name":"Lynn",
    "gn:population":0,
    "gn:timezone":"America/New_York",
    "iso:country":"US",
    "name:bre_x_preferred":[
        "Lynn"
    ],
    "name:ceb_x_preferred":[
        "Lynn"
    ],
    "name:ces_x_preferred":[
        "Lynn"
    ],
    "name:deu_x_preferred":[
        "Lynn"
    ],
    "name:fra_x_preferred":[
        "Lynn"
    ],
    "name:heb_x_preferred":[
        "\u05dc\u05d9\u05df"
    ],
    "name:ita_x_preferred":[
        "Lynn"
    ],
    "name:nld_x_preferred":[
        "Lynn"
    ],
    "name:pol_x_preferred":[
        "Lynn"
    ],
    "name:por_x_preferred":[
        "Lynn"
    ],
    "name:rus_x_preferred":[
        "\u041b\u0438\u043d\u043d"
    ],
    "name:slk_x_preferred":[
        "Lynn"
    ],
    "name:spa_x_preferred":[
        "Lynn"
    ],
    "name:swe_x_preferred":[
        "Lynn"
    ],
    "name:ukr_x_preferred":[
        "\u041b\u0456\u043d\u043d"
    ],
    "name:vol_x_preferred":[
        "Lynn"
    ],
    "name:zho_x_preferred":[
        "Lynn"
    ],
    "wof:name":"Lynn",
    "wof:placetype":"locality"
},
  "geometry": {"coordinates":[-84.61492,30.98046],"type":"Point"}
}