{
  "type": "Feature",
  "properties": {
    "iso:country":"US",
    "name:eng_x_preferred":[
        "Legante Paseo"
    ],
    "wof:name":"Legante Paseo",
    "wof:placetype":"neighbourhood",
    "wof:population":1043,
    "zs:area_m":465290.083317,
    "zs:blockids":[
        40134222222009,
        40134222222005,
        40134222222013,
        40134222221008,
        40134222222015,
        40134222222004,
        40134222221012,
        40134222221011,
        40134222222014,
        40134222222007,
        40134222222002,
        40134222222011,
        40134222222006,
        40134222222001,
        40134222222010,
        40134222222003,
        40134222221010
    ],
    "zs:housing10":389,
    "zs:label":"Legante Paseo",
    "zs:pop10":1043
},
  "geometry": {"coordinates":[-111.86352599999999,33.370626],"type":"Point"}
}