{
  "type": "Feature",
  "properties": {
    "gn:admin1_code":"WV",
    "gn:admin2_code":"95",
    "gn:asciiname":"Big Moses",
    "gn:country_code":"US",
    "gn:dem":228,
    "gn:elevation":"220.0",
    "gn:feature_class":"P",
    "gn:feature_code":"PPL",
    "gn:name":"Big Moses",
    "gn:population":0,
    "gn:timezone":"America/New_York",
    "iso:country":"US",
    "wof:name":"Big Moses",
    "wof:placetype":"locality"
},
  "geometry": {"coordinates":[-80.78426999999998,39.43147],"type":"Point"}
}