{
  "type": "Feature",
  "properties": {
    "gn:admin1_code":"TX",
    "gn:admin2_code":"379.0",
    "gn:asciiname":"Bellview",
    "gn:country_code":"US",
    "gn:dem":136,
    "gn:elevation":"127.0",
    "gn:feature_class":"P",
    "gn:feature_code":"PPL",
    "gn:name":"Bellview",
    "gn:population":0,
    "gn:timezone":"America/Chicago",
    "iso:country":"US",
    "name:deu_x_preferred":[
        "Bellview"
    ],
    "wof:name":"Bellview",
    "wof:placetype":"locality"
},
  "geometry": {"coordinates":[-95.69774,32.78263],"type":"Point"}
}