{
  "type": "Feature",
  "properties": {
    "gn:admin1_code":"ME",
    "gn:admin2_code":"17.0",
    "gn:admin3_code":"55960.0",
    "gn:asciiname":"Cobb Cove",
    "gn:country_code":"US",
    "gn:dem":110,
    "gn:elevation":"106.0",
    "gn:feature_class":"P",
    "gn:feature_code":"PPL",
    "gn:name":"Cobb Cove",
    "gn:population":0,
    "gn:timezone":"America/New_York",
    "iso:country":"US",
    "wof:name":"Cobb Cove",
    "wof:placetype":"locality"
},
  "geometry": {"coordinates":[-70.50284000000001,44.07118],"type":"Point"}
}