{
  "type": "Feature",
  "properties": {
    "gn:admin1_code":"WY",
    "gn:admin2_code":"17.0",
    "gn:asciiname":"Nickelson Place",
    "gn:country_code":"US",
    "gn:dem":1838,
    "gn:elevation":"1835.0",
    "gn:feature_class":"P",
    "gn:feature_code":"PPL",
    "gn:name":"Nickelson Place",
    "gn:population":0,
    "gn:timezone":"America/Denver",
    "iso:country":"US",
    "wof:name":"Nickelson Place",
    "wof:placetype":"locality"
},
  "geometry": {"coordinates":[-108.05371,43.53607],"type":"Point"}
}