{
  "type": "Feature",
  "properties": {
    "gn:admin1_code":"CA",
    "gn:admin2_code":"89.0",
    "gn:asciiname":"Motion",
    "gn:country_code":"US",
    "gn:dem":184,
    "gn:elevation":"182.0",
    "gn:feature_class":"P",
    "gn:feature_code":"PPL",
    "gn:name":"Motion",
    "gn:population":0,
    "gn:timezone":"America/Los_Angeles",
    "iso:country":"US",
    "name:eng_x_preferred":[
        "Motion"
    ],
    "name:und_x_variant":[
        "Camp Bailey",
        "Copley"
    ],
    "name:zho_x_preferred":[
        "\u83ab\u7533"
    ],
    "wof:name":"Motion",
    "wof:placetype":"locality"
},
  "geometry": {"coordinates":[-122.46057,40.67432],"type":"Point"}
}