{
  "type": "Feature",
  "properties": {
    "gn:country":"US",
    "gn:fcode":"PPL",
    "gn:population":0,
    "iso:country":"US",
    "name:cat_x_preferred":[
        "Eastover"
    ],
    "name:ceb_x_preferred":[
        "Eastover"
    ],
    "name:deu_x_preferred":[
        "Eastover"
    ],
    "name:fra_x_preferred":[
        "Eastover"
    ],
    "name:ita_x_preferred":[
        "Eastover"
    ],
    "name:nld_x_preferred":[
        "Eastover"
    ],
    "name:pol_x_preferred":[
        "Eastover"
    ],
    "name:srp_x_preferred":[
        "\u0418\u0441\u0442\u043e\u0432\u0435\u0440"
    ],
    "name:vol_x_preferred":[
        "Eastover"
    ],
    "qs_pg:aaroncc":"US",
    "qs_pg:gn_country":"US",
    "qs_pg:gn_fcode":"PPL",
    "qs_pg:gn_pop":0,
    "qs_pg:name":"Eastover",
    "qs_pg:name_adm0":"United States",
    "qs_pg:name_adm1":"Massachusetts",
    "qs_pg:photos":16,
    "qs_pg:photos_1k":3,
    "qs_pg:photos_9k":1,
    "qs_pg:photos_9r":1,
    "qs_pg:photos_all":16,
    "qs_pg:photos_sr":1,
    "qs_pg:pop_sr":0,
    "qs_pg:qs_pg_placetype":"locality",
    "qs_pg:qs_pg_placetype_gp":"Town",
    "qs_pg:woe_adm0":23424977,
    "woe:adm0_id":23424977,
    "woe:name_adm0":"United States",
    "woe:name_adm1":"Massachusetts",
    "woe:placetype":"Town",
    "wof:name":"Eastover",
    "wof:placetype":"locality"
},
  "geometry": {"coordinates":[-73.25761,42.37092],"type":"Point"}
}