{
  "type": "Feature",
  "properties": {
    "gn:country":"US",
    "gn:fcode":"PPL",
    "gn:population":9190,
    "iso:country":"US",
    "name:azb_x_preferred":[
        "\u0633\u0646\u062a\u0631\u0648\u06cc\u0644"
    ],
    "name:ceb_x_preferred":[
        "Centerville"
    ],
    "name:eng_x_preferred":[
        "Centerville"
    ],
    "name:fas_x_preferred":[
        "\u0633\u0646\u062a\u0631\u0648\u06cc\u0644"
    ],
    "name:fra_x_preferred":[
        "Centerville"
    ],
    "name:tur_x_preferred":[
        "Centerville"
    ],
    "name:ukr_x_preferred":[
        "\u0421\u0435\u043d\u0442\u0435\u0440\u0432\u0456\u043b\u043b"
    ],
    "name:und_x_variant":[
        "Chequaquet"
    ],
    "qs_pg:aaroncc":"US",
    "qs_pg:gn_country":"US",
    "qs_pg:gn_fcode":"PPL",
    "qs_pg:gn_pop":9190,
    "qs_pg:name":"Centerville",
    "qs_pg:name_adm0":"United States",
    "qs_pg:name_adm1":"Massachusetts",
    "qs_pg:photos":240,
    "qs_pg:photos_1k":49,
    "qs_pg:photos_9k":1,
    "qs_pg:photos_9r":4,
    "qs_pg:photos_all":240,
    "qs_pg:photos_sr":4,
    "qs_pg:pop_sr":5,
    "qs_pg:qs_pg_placetype":"locality",
    "qs_pg:qs_pg_placetype_gp":"Town",
    "qs_pg:woe_adm0":23424977,
    "woe:adm0_id":23424977,
    "woe:name_adm0":"United States",
    "woe:name_adm1":"Massachusetts",
    "woe:placetype":"Town",
    "wof:name":"Centerville",
    "wof:placetype":"locality",
    "wof:population":9190
},
  "geometry": {"coordinates":[-70.34808,41.64872],"type":"Point"}
}