{
  "type": "Feature",
  "properties": {
    "gn:admin1_code":"WA",
    "gn:admin2_code":"5.0",
    "gn:asciiname":"North Prosser",
    "gn:country_code":"US",
    "gn:dem":227,
    "gn:elevation":"230.0",
    "gn:feature_class":"P",
    "gn:feature_code":"PPL",
    "gn:name":"North Prosser",
    "gn:population":0,
    "gn:timezone":"America/Los_Angeles",
    "iso:country":"US",
    "wof:name":"North Prosser",
    "wof:placetype":"locality"
},
  "geometry": {"coordinates":[-119.76837,46.23208],"type":"Point"}
}