{
  "type": "Feature",
  "properties": {
    "gn:admin1_code":"MO",
    "gn:admin2_code":"157.0",
    "gn:admin3_code":"74842.0",
    "gn:asciiname":"Calvary Church",
    "gn:country_code":"US",
    "gn:dem":193,
    "gn:elevation":"195.0",
    "gn:feature_class":"P",
    "gn:feature_code":"PPL",
    "gn:name":"Calvary Church",
    "gn:population":0,
    "gn:timezone":"America/Chicago",
    "iso:country":"US",
    "wof:name":"Calvary Church",
    "wof:placetype":"locality"
},
  "geometry": {"coordinates":[-89.77233000000003,37.6695],"type":"Point"}
}