{
  "type": "Feature",
  "properties": {
    "gn:country":"US",
    "gn:fcode":"PPL",
    "gn:population":0,
    "iso:country":"US",
    "name:ceb_x_preferred":[
        "Greenacres"
    ],
    "name:srp_x_preferred":[
        "\u0413\u0440\u0438\u043d\u0435\u0458\u043a\u0435\u0440\u0441"
    ],
    "name:ukr_x_preferred":[
        "\u0413\u0440\u0456\u043d\u0435\u0439\u043a\u0435\u0440\u0441"
    ],
    "qs_pg:aaroncc":"US",
    "qs_pg:gn_country":"US",
    "qs_pg:gn_fcode":"PPL",
    "qs_pg:gn_pop":0,
    "qs_pg:name":"Greenacres",
    "qs_pg:name_adm0":"United States",
    "qs_pg:name_adm1":"Georgia",
    "qs_pg:photos_9r":0,
    "qs_pg:photos_sr":0,
    "qs_pg:pop_sr":0,
    "qs_pg:qs_pg_placetype":"locality",
    "qs_pg:qs_pg_placetype_gp":"Town",
    "qs_pg:woe_adm0":23424977,
    "woe:adm0_id":23424977,
    "woe:name_adm0":"United States",
    "woe:name_adm1":"Georgia",
    "woe:placetype":"Town",
    "wof:name":"Greenacres",
    "wof:placetype":"locality"
},
  "geometry": {"coordinates":[-84.84161,33.88149],"type":"Point"}
}