{
  "type": "Feature",
  "properties": {
    "gn:admin1_code":"GA",
    "gn:admin2_code":"223",
    "gn:asciiname":"Pleasant Hills",
    "gn:country_code":"US",
    "gn:dem":303,
    "gn:elevation":"299.0",
    "gn:feature_class":"P",
    "gn:feature_code":"PPL",
    "gn:name":"Pleasant Hills",
    "gn:population":0,
    "gn:timezone":"America/New_York",
    "iso:country":"US",
    "name:cat_x_preferred":[
        "Pleasant Hills"
    ],
    "name:ceb_x_preferred":[
        "Pleasant Hills"
    ],
    "name:deu_x_preferred":[
        "Pleasant Hills"
    ],
    "name:ita_x_preferred":[
        "Pleasant Hills"
    ],
    "name:nld_x_preferred":[
        "Pleasant Hills"
    ],
    "name:pol_x_preferred":[
        "Pleasant Hills"
    ],
    "name:srp_x_preferred":[
        "\u041f\u043b\u0435\u0437\u0435\u043d\u0442 \u0425\u0438\u043b\u0441"
    ],
    "name:swe_x_preferred":[
        "Pleasant Hills"
    ],
    "name:vol_x_preferred":[
        "Pleasant Hills"
    ],
    "wof:name":"Pleasant Hills",
    "wof:placetype":"locality"
},
  "geometry": {"coordinates":[-84.72577,33.82122],"type":"Point"}
}