{
  "type": "Feature",
  "properties": {
    "gn:country":"US",
    "gn:fcode":"PPL",
    "gn:population":0,
    "iso:country":"US",
    "name:ara_x_preferred":[
        "\u0641\u0627\u0631\u0645\u064a\u0646\u063a\u062a\u0648\u0646"
    ],
    "name:arz_x_preferred":[
        "\u0641\u0627\u0631\u0645\u064a\u0646\u062c\u062a\u0648\u0646"
    ],
    "name:ces_x_preferred":[
        "Farmington"
    ],
    "name:che_x_preferred":[
        "\u0424\u0430\u0440\u043c\u0438\u043d\u0433\u0442\u043e\u043d"
    ],
    "name:deu_x_preferred":[
        "Farmington"
    ],
    "name:eng_x_preferred":[
        "Farmington"
    ],
    "name:eus_x_preferred":[
        "Farmington"
    ],
    "name:fra_x_preferred":[
        "Farmington"
    ],
    "name:hat_x_preferred":[
        "Farmington"
    ],
    "name:hun_x_preferred":[
        "Farmington"
    ],
    "name:ita_x_preferred":[
        "Farmington"
    ],
    "name:jpn_x_preferred":[
        "\u30d5\u30a1\u30fc\u30df\u30f3\u30c8\u30f3"
    ],
    "name:pol_x_preferred":[
        "Farmington"
    ],
    "name:slk_x_preferred":[
        "Farmington"
    ],
    "name:spa_x_preferred":[
        "Farmington"
    ],
    "name:swe_x_preferred":[
        "Farmington"
    ],
    "name:tat_x_preferred":[
        "\u0424\u0430\u0440\u043c\u0438\u043d\u0433\u0442\u043e\u043d"
    ],
    "name:tur_x_preferred":[
        "Farmington"
    ],
    "name:ukr_x_preferred":[
        "\u0424\u0430\u0440\u043c\u0456\u043d\u0433\u0442\u043e\u043d"
    ],
    "name:urd_x_preferred":[
        "\u0641\u0627\u0631\u0645\u0646\u06af\u0679\u0646\u060c \u0646\u06cc\u0648 \u06cc\u0627\u0631\u06a9"
    ],
    "name:urd_x_variant":[
        "\u0641\u0627\u0631\u0645\u0646\u06af\u0679\u0646"
    ],
    "name:uzb_x_preferred":[
        "Farmington"
    ],
    "qs_pg:aaroncc":"US",
    "qs_pg:gn_country":"US",
    "qs_pg:gn_fcode":"PPL",
    "qs_pg:gn_pop":0,
    "qs_pg:name":"Farmington",
    "qs_pg:name_adm0":"United States",
    "qs_pg:name_adm1":"New York",
    "qs_pg:photos":210,
    "qs_pg:photos_1k":43,
    "qs_pg:photos_9k":3,
    "qs_pg:photos_9r":5,
    "qs_pg:photos_all":579,
    "qs_pg:photos_sr":4,
    "qs_pg:pop_sr":0,
    "qs_pg:qs_pg_placetype":"locality",
    "qs_pg:qs_pg_placetype_gp":"Town",
    "qs_pg:woe_adm0":23424977,
    "woe:adm0_id":23424977,
    "woe:name_adm0":"United States",
    "woe:name_adm1":"New York",
    "woe:placetype":"Town",
    "wof:coterminous":[
        404522863
    ],
    "wof:name":"Farmington",
    "wof:placetype":"locality",
    "wof:statistical_gore":1
},
  "geometry": {"coordinates":[-77.32581999999999,42.98367],"type":"Point"}
}