{
  "type": "Feature",
  "properties": {
    "gn:elevation":67,
    "iso:country":"US",
    "name:ceb_x_preferred":[
        "Mame-zima"
    ],
    "name:eng_x_preferred":[
        "Bean Island"
    ],
    "name:eng_x_variant":[
        "Bean Is"
    ],
    "name:nno_x_preferred":[
        "Mame-jima"
    ],
    "name:swe_x_preferred":[
        "Mame-zima"
    ],
    "name:zho_x_preferred":[
        "\u8c46\u5cf6"
    ],
    "qs:gn_adm0_cc":"US",
    "qs:gn_fcode":"PPL",
    "qs:gn_local":5084165,
    "qs:gn_nam_loc":"Candia, Rockingham, New Hampshire, US",
    "qs:gn_namadm1":"NH",
    "qs:gn_name":"Bean Island",
    "qs:local_max":25,
    "qs:local_sum":25,
    "qs:localhoods":1,
    "qs:name":"Bean Island",
    "qs:name_adm0":"United States",
    "qs:name_adm1":"New Hampshire",
    "qs:name_adm2":"Rockingham",
    "qs:name_local":"Candia",
    "qs:photo_max":23,
    "qs:photo_sum":25,
    "qs:placetype":"Suburb",
    "qs:quad_count":3,
    "qs:woe_adm0":23424977,
    "qs:woe_adm1":2347588,
    "qs:woe_adm2":12589255,
    "qs:woe_lau":0,
    "qs:woe_local":2374230,
    "qs:woe_ver":"7.10.0",
    "wd:wordcount":91,
    "wof:lang":[
        "eng"
    ],
    "wof:name":"Bean Island",
    "wof:placetype":"neighbourhood",
    "wof:population":1086,
    "zs:blockids":[
        330150500001025,
        330150500001022,
        330150500001037,
        330150500001005,
        330150550011014,
        330150500001003,
        330150500001008,
        330150550011013,
        330150500001024,
        330150500001006,
        330150550011015,
        330150500001028,
        330150500001002,
        330150500001009,
        330150500001014,
        330150500001029,
        330150500001011,
        330150500001031,
        330150550011005,
        330150550011024,
        330150500001004,
        330150500001023,
        330150500001017,
        330150500001026,
        330150500001007,
        330150500001010,
        330150500001016,
        330150500001015,
        330150550011025,
        330150550011003,
        330150500001012
    ],
    "zs:housing10":434,
    "zs:pop10":1086
},
  "geometry": {"coordinates":[-71.2548,43.059012],"type":"Point"}
}