{
  "type": "Feature",
  "properties": {
    "gn:admin1_code":"TN",
    "gn:admin2_code":"35.0",
    "gn:asciiname":"Browntown",
    "gn:country_code":"US",
    "gn:dem":592,
    "gn:elevation":"593.0",
    "gn:feature_class":"P",
    "gn:feature_code":"PPL",
    "gn:name":"Browntown",
    "gn:population":0,
    "gn:timezone":"America/Chicago",
    "iso:country":"US",
    "name:ceb_x_preferred":[
        "Browntown"
    ],
    "name:deu_x_preferred":[
        "Browntown"
    ],
    "name:srp_x_preferred":[
        "\u0411\u0440\u0430\u0443\u043d\u0442\u0430\u0443\u043d"
    ],
    "wof:name":"Browntown",
    "wof:placetype":"locality"
},
  "geometry": {"coordinates":[-85.20496999999997,35.95923],"type":"Point"}
}