{
  "type": "Feature",
  "properties": {
    "gn:admin1_code":"KY",
    "gn:admin2_code":"51.0",
    "gn:asciiname":"Shepherdtown",
    "gn:country_code":"US",
    "gn:dem":286,
    "gn:elevation":"284.0",
    "gn:feature_class":"P",
    "gn:feature_code":"PPL",
    "gn:name":"Shepherdtown",
    "gn:population":0,
    "gn:timezone":"America/New_York",
    "iso:country":"US",
    "wof:name":"Shepherdtown",
    "wof:placetype":"locality"
},
  "geometry": {"coordinates":[-83.86492,37.28703],"type":"Point"}
}