{
  "type": "Feature",
  "properties": {
    "gn:admin1_code":"FL",
    "gn:admin2_code":"105.0",
    "gn:asciiname":"Achan",
    "gn:country_code":"US",
    "gn:dem":40,
    "gn:elevation":"37.0",
    "gn:feature_class":"P",
    "gn:feature_code":"PPL",
    "gn:name":"Achan",
    "gn:population":0,
    "gn:timezone":"America/New_York",
    "iso:country":"US",
    "name:heb_x_preferred":[
        "\u05e2\u05db\u05df"
    ],
    "wof:name":"Achan",
    "wof:placetype":"locality"
},
  "geometry": {"coordinates":[-81.96841999999999,27.85947],"type":"Point"}
}