{
  "type": "Feature",
  "properties": {
    "iso:country":"US",
    "qs_pg:aaroncc":"US",
    "qs_pg:name":"Northeast Point",
    "qs_pg:name_adm0":"United States",
    "qs_pg:name_adm1":"Alaska",
    "qs_pg:photos":101,
    "qs_pg:photos_1k":20,
    "qs_pg:photos_9k":1,
    "qs_pg:photos_9r":3,
    "qs_pg:photos_all":101,
    "qs_pg:photos_sr":3,
    "qs_pg:pop_sr":0,
    "qs_pg:qs_pg_placetype":"locality",
    "qs_pg:qs_pg_placetype_gp":"Town",
    "qs_pg:woe_adm0":23424977,
    "woe:adm0_id":23424977,
    "woe:name_adm0":"United States",
    "woe:name_adm1":"Alaska",
    "woe:placetype":"Town",
    "wof:name":"Northeast Point",
    "wof:placetype":"locality"
},
  "geometry": {"coordinates":[-170.129299,57.239678],"type":"Point"}
}