{
  "type": "Feature",
  "properties": {
    "gn:admin1_code":"MO",
    "gn:admin2_code":"31.0",
    "gn:admin3_code":"1450.0",
    "gn:asciiname":"Arnsberg",
    "gn:country_code":"US",
    "gn:dem":149,
    "gn:elevation":"146.0",
    "gn:feature_class":"P",
    "gn:feature_code":"PPL",
    "gn:name":"Arnsberg",
    "gn:population":0,
    "gn:timezone":"America/Chicago",
    "iso:country":"US",
    "name:deu_x_preferred":[
        "Arnsberg"
    ],
    "wof:name":"Arnsberg",
    "wof:placetype":"locality"
},
  "geometry": {"coordinates":[-89.77760000000001,37.56977],"type":"Point"}
}