{
  "type": "Feature",
  "properties": {
    "iso:country":"US",
    "wof:name":"Grasseli",
    "wof:placetype":"neighbourhood"
},
  "geometry": {"coordinates":[-86.888040656695,33.45030336768637],"type":"Point"}
}