{
  "type": "Feature",
  "properties": {
    "iso:country":"US",
    "name:eng_x_preferred":[
        "Ledgewood"
    ],
    "wof:name":"Ledgewood",
    "wof:placetype":"neighbourhood",
    "wof:population":1188,
    "zs:area_m":3756617.464275,
    "zs:blockids":[
        330110010001020,
        330110010001033,
        330110010001016,
        330110010001017,
        330110010002006,
        330110010002002,
        330110010001021,
        330110010003003,
        330110010001024,
        330110010001014,
        330110010001032,
        330110010002000,
        330110010001018,
        330110010001022,
        330110010002005,
        330110010003002,
        330110010002004,
        330110010002003,
        330110010001015,
        330110010001023,
        330110010001019,
        330110010002001,
        330110010003004,
        330110010001031,
        330110010002007
    ],
    "zs:housing10":539,
    "zs:label":"Ledgewood",
    "zs:pop10":1188
},
  "geometry": {"coordinates":[-71.396232,42.992236],"type":"Point"}
}