{
  "type": "Feature",
  "properties": {
    "gn:admin1_code":"OH",
    "gn:admin2_code":"53",
    "gn:admin3_code":"31738.0",
    "gn:asciiname":"Fairfield Acres",
    "gn:country_code":"US",
    "gn:dem":207,
    "gn:elevation":"208.0",
    "gn:feature_class":"P",
    "gn:feature_code":"PPL",
    "gn:name":"Fairfield Acres",
    "gn:population":0,
    "gn:timezone":"America/New_York",
    "iso:country":"US",
    "wof:name":"Fairfield Acres",
    "wof:placetype":"locality"
},
  "geometry": {"coordinates":[-82.27571,38.82508],"type":"Point"}
}