{
  "type": "Feature",
  "properties": {
    "gn:gn_country":"US",
    "gn:gn_fcode":"PPL",
    "gn:gn_pop":0,
    "iso:country":"US",
    "name:ceb_x_preferred":[
        "Belin"
    ],
    "name:deu_x_preferred":[
        "Belin"
    ],
    "name:fra_x_preferred":[
        "Belin"
    ],
    "name:glg_x_preferred":[
        "Belin"
    ],
    "name:ita_x_preferred":[
        "Belin"
    ],
    "name:ron_x_preferred":[
        "Belin"
    ],
    "name:slv_x_preferred":[
        "Belin"
    ],
    "name:vie_x_preferred":[
        "Belin"
    ],
    "qs_pg:aaroncc":"US",
    "qs_pg:gn_country":"US",
    "qs_pg:gn_fcode":"PPL",
    "qs_pg:gn_pop":0,
    "qs_pg:name":"Belin",
    "qs_pg:name_adm0":"United States",
    "qs_pg:name_adm1":"South Carolina",
    "qs_pg:photos":21,
    "qs_pg:photos_1k":4,
    "qs_pg:photos_9k":1,
    "qs_pg:photos_9r":1,
    "qs_pg:photos_all":21,
    "qs_pg:photos_sr":1,
    "qs_pg:pop_sr":0,
    "qs_pg:qs_pg_placetype":"locality",
    "qs_pg:qs_pg_placetype_gp":"Town",
    "qs_pg:woe_adm0":23424977,
    "woe:adm0_id":23424977,
    "woe:name_adm0":"United States",
    "woe:name_adm1":"South Carolina",
    "woe:placetype":"Town",
    "wof:name":"Belin",
    "wof:placetype":"locality"
},
  "geometry": {"coordinates":[-79.14364999999999,33.51795],"type":"Point"}
}