{
  "type": "Feature",
  "properties": {
    "gn:admin1_code":"DE",
    "gn:admin2_code":"3.0",
    "gn:asciiname":"Kershaw Acres",
    "gn:country_code":"US",
    "gn:dem":108,
    "gn:elevation":"104.0",
    "gn:feature_class":"P",
    "gn:feature_code":"PPL",
    "gn:name":"Kershaw Acres",
    "gn:population":0,
    "gn:timezone":"America/New_York",
    "iso:country":"US",
    "wof:name":"Kershaw Acres",
    "wof:placetype":"locality"
},
  "geometry": {"coordinates":[-75.51353,39.81733],"type":"Point"}
}