{
  "type": "Feature",
  "properties": {
    "gn:admin1_code":"NM",
    "gn:admin2_code":"17",
    "gn:asciiname":"Big Mill",
    "gn:country_code":"US",
    "gn:dem":1727,
    "gn:elevation":"1725.0",
    "gn:feature_class":"P",
    "gn:feature_code":"PPL",
    "gn:name":"Big Mill",
    "gn:population":0,
    "gn:timezone":"America/Denver",
    "iso:country":"US",
    "wof:name":"Big Mill",
    "wof:placetype":"locality"
},
  "geometry": {"coordinates":[-107.99169999999999,32.65897],"type":"Point"}
}