{
  "type": "Feature",
  "properties": {
    "gn:admin1_code":"SC",
    "gn:admin2_code":"11.0",
    "gn:asciiname":"Reynold",
    "gn:country_code":"US",
    "gn:dem":102,
    "gn:elevation":"97.0",
    "gn:feature_class":"P",
    "gn:feature_code":"PPL",
    "gn:name":"Reynold",
    "gn:population":0,
    "gn:timezone":"America/New_York",
    "iso:country":"US",
    "name:eng_x_preferred":[
        "Reynold"
    ],
    "name:und_x_variant":[
        "Reynolds"
    ],
    "wof:name":"Reynold",
    "wof:placetype":"locality"
},
  "geometry": {"coordinates":[-81.33038000000001,33.36682],"type":"Point"}
}