{
  "type": "Feature",
  "properties": {
    "gn:admin1_code":"FL",
    "gn:admin2_code":"57",
    "gn:asciiname":"Wyndgate",
    "gn:country_code":"US",
    "gn:dem":28,
    "gn:elevation":"17.0",
    "gn:feature_class":"P",
    "gn:feature_code":"PPL",
    "gn:name":"Wyndgate",
    "gn:population":0,
    "gn:timezone":"America/New_York",
    "iso:country":"US",
    "wof:name":"Wyndgate",
    "wof:placetype":"locality"
},
  "geometry": {"coordinates":[-82.4426,28.1003],"type":"Point"}
}