{
  "type": "Feature",
  "properties": {
    "gn:admin1_code":"OR",
    "gn:admin2_code":"49",
    "gn:asciiname":"Ella",
    "gn:country_code":"US",
    "gn:dem":243,
    "gn:elevation":"247.0",
    "gn:feature_class":"P",
    "gn:feature_code":"PPL",
    "gn:name":"Ella",
    "gn:population":0,
    "gn:timezone":"America/Los_Angeles",
    "iso:country":"US",
    "name:ceb_x_preferred":[
        "Ella"
    ],
    "name:deu_x_preferred":[
        "Ella"
    ],
    "name:fra_x_preferred":[
        "Ella"
    ],
    "name:hrv_x_preferred":[
        "Ella"
    ],
    "name:ita_x_preferred":[
        "Ella"
    ],
    "name:lav_x_preferred":[
        "Ella"
    ],
    "name:nld_x_preferred":[
        "Ella"
    ],
    "name:rus_x_preferred":[
        "\u042d\u043b\u043b\u0430"
    ],
    "name:snd_x_preferred":[
        "\u0627\u0650\u0644\u0627"
    ],
    "name:spa_x_preferred":[
        "Ella"
    ],
    "name:swe_x_preferred":[
        "Ella"
    ],
    "name:vie_x_preferred":[
        "Ella"
    ],
    "name:zho_x_preferred":[
        "Ella"
    ],
    "wof:name":"Ella",
    "wof:placetype":"locality"
},
  "geometry": {"coordinates":[-119.80892,45.63124000000001],"type":"Point"}
}