{
  "type": "Feature",
  "properties": {
    "gn:admin1_code":"VA",
    "gn:admin2_code":"191",
    "gn:asciiname":"Drowning Ford",
    "gn:country_code":"US",
    "gn:dem":562,
    "gn:elevation":"563.0",
    "gn:feature_class":"P",
    "gn:feature_code":"PPL",
    "gn:name":"Drowning Ford",
    "gn:population":0,
    "gn:timezone":"America/New_York",
    "iso:country":"US",
    "name:eng_x_preferred":[
        "Drowning Ford"
    ],
    "name:und_x_variant":[
        "Drowning Ford Station"
    ],
    "wof:name":"Drowning Ford",
    "wof:placetype":"locality"
},
  "geometry": {"coordinates":[-81.84095000000001,36.6515],"type":"Point"}
}