{
  "type": "Feature",
  "properties": {
    "gn:country":"US",
    "gn:fcode":"PPL",
    "gn:population":0,
    "iso:country":"US",
    "name:ceb_x_preferred":[
        "El Toro"
    ],
    "name:deu_x_preferred":[
        "El Toro"
    ],
    "name:eng_x_preferred":[
        "El Toro"
    ],
    "name:fra_x_preferred":[
        "El Toro"
    ],
    "name:ita_x_preferred":[
        "El Toro"
    ],
    "name:nld_x_preferred":[
        "El Toro"
    ],
    "name:pol_x_preferred":[
        "El Toro"
    ],
    "name:spa_x_preferred":[
        "El Toro"
    ],
    "name:srp_x_preferred":[
        "\u0415\u043b \u0422\u043e\u0440\u043e"
    ],
    "name:swe_x_preferred":[
        "El Toro"
    ],
    "name:und_x_variant":[
        "Eltoro"
    ],
    "qs_pg:aaroncc":"US",
    "qs_pg:gn_country":"US",
    "qs_pg:gn_fcode":"PPL",
    "qs_pg:gn_pop":0,
    "qs_pg:name":"El Toro",
    "qs_pg:name_adm0":"United States",
    "qs_pg:name_adm1":"California",
    "qs_pg:photos":264,
    "qs_pg:photos_1k":53,
    "qs_pg:photos_9k":1,
    "qs_pg:photos_9r":4,
    "qs_pg:photos_all":264,
    "qs_pg:photos_sr":5,
    "qs_pg:pop_sr":7,
    "qs_pg:qs_pg_placetype":"locality",
    "qs_pg:qs_pg_placetype_gp":"Town",
    "qs_pg:woe_adm0":23424977,
    "woe:adm0_id":23424977,
    "woe:name_adm0":"United States",
    "woe:name_adm1":"California",
    "woe:placetype":"Town",
    "wof:name":"El Toro",
    "wof:placetype":"locality"
},
  "geometry": {"coordinates":[-117.68366,33.64697],"type":"Point"}
}