{
  "type": "Feature",
  "properties": {
    "gn:admin1_code":"IN",
    "gn:admin2_code":"151.0",
    "gn:admin3_code":"57240.0",
    "gn:asciiname":"Russels Point",
    "gn:country_code":"US",
    "gn:dem":273,
    "gn:elevation":"275.0",
    "gn:feature_class":"P",
    "gn:feature_code":"PPL",
    "gn:name":"Russels Point",
    "gn:population":0,
    "gn:timezone":"America/Indiana/Indianapolis",
    "iso:country":"US",
    "wof:name":"Russels Point",
    "wof:placetype":"locality"
},
  "geometry": {"coordinates":[-84.92413000000001,41.55394],"type":"Point"}
}