{
  "type": "Feature",
  "properties": {
    "gn:country":"US",
    "gn:fcode":"ADMD",
    "gn:population":0,
    "iso:country":"US",
    "name:ara_x_preferred":[
        "\u0633\u062a\u064a\u0644\u0627"
    ],
    "name:azb_x_preferred":[
        "\u0627\u06cc\u0633\u062a\u0644\u0627"
    ],
    "name:che_x_preferred":[
        "\u0421\u0442\u0435\u043b\u043b\u0430"
    ],
    "name:eng_x_preferred":[
        "Stella"
    ],
    "name:eus_x_preferred":[
        "Stella"
    ],
    "name:fra_x_preferred":[
        "Stella"
    ],
    "name:hat_x_preferred":[
        "Stella"
    ],
    "name:hun_x_preferred":[
        "Stella"
    ],
    "name:mal_x_preferred":[
        "\u0d38\u0d4d\u0d31\u0d4d\u0d31\u0d46\u0d32\u0d4d\u0d32"
    ],
    "name:pol_x_preferred":[
        "Stella"
    ],
    "name:spa_x_preferred":[
        "Stella"
    ],
    "name:tat_x_preferred":[
        "\u0421\u0442\u0435\u043b\u043b\u0430"
    ],
    "name:ukr_x_preferred":[
        "\u0421\u0442\u0435\u043b\u043b\u0430"
    ],
    "name:vie_x_preferred":[
        "Stella"
    ],
    "qs_pg:aaroncc":"US",
    "qs_pg:gn_country":"US",
    "qs_pg:gn_fcode":"ADMD",
    "qs_pg:gn_pop":0,
    "qs_pg:name":"Stella",
    "qs_pg:name_adm0":"United States",
    "qs_pg:name_adm1":"Wisconsin",
    "qs_pg:photos":9,
    "qs_pg:photos_1k":2,
    "qs_pg:photos_9k":1,
    "qs_pg:photos_9r":1,
    "qs_pg:photos_all":9,
    "qs_pg:photos_sr":1,
    "qs_pg:pop_sr":0,
    "qs_pg:qs_pg_placetype":"locality",
    "qs_pg:qs_pg_placetype_gp":"Town",
    "qs_pg:woe_adm0":23424977,
    "woe:adm0_id":23424977,
    "woe:name_adm0":"United States",
    "woe:name_adm1":"Wisconsin",
    "woe:placetype":"Town",
    "wof:coterminous":[
        404494761
    ],
    "wof:name":"Stella",
    "wof:placetype":"locality",
    "wof:population":647,
    "wof:statistical_gore":1
},
  "geometry": {"coordinates":[-89.23679,45.67718],"type":"Point"}
}