{
  "type": "Feature",
  "properties": {
    "gn:admin1_code":"PA",
    "gn:admin2_code":"15.0",
    "gn:admin3_code":"71312.0",
    "gn:asciiname":"Huffs Corner",
    "gn:country_code":"US",
    "gn:dem":453,
    "gn:elevation":"453.0",
    "gn:feature_class":"P",
    "gn:feature_code":"PPL",
    "gn:name":"Huffs Corner",
    "gn:population":0,
    "gn:timezone":"America/New_York",
    "iso:country":"US",
    "wof:name":"Huffs Corner",
    "wof:placetype":"locality"
},
  "geometry": {"coordinates":[-76.60661,41.88785],"type":"Point"}
}