{
  "type": "Feature",
  "properties": {
    "gn:admin1_code":"MD",
    "gn:admin2_code":"21.0",
    "gn:asciiname":"New Market West",
    "gn:country_code":"US",
    "gn:dem":146,
    "gn:elevation":"143.0",
    "gn:feature_class":"P",
    "gn:feature_code":"PPL",
    "gn:name":"New Market West",
    "gn:population":0,
    "gn:timezone":"America/New_York",
    "iso:country":"US",
    "wof:name":"New Market West",
    "wof:placetype":"locality"
},
  "geometry": {"coordinates":[-77.28054,39.38871],"type":"Point"}
}