{
  "type": "Feature",
  "properties": {
    "gn:elevation":274,
    "iso:country":"US",
    "name:eng_x_preferred":[
        "Greenmont"
    ],
    "name:und_x_variant":[
        "Watervleit"
    ],
    "qs:gn_adm0_cc":"US",
    "qs:gn_fcode":"PPLX",
    "qs:gn_local":4509884,
    "qs:gn_nam_loc":"Dayton, Montgomery, Ohio, US",
    "qs:gn_namadm1":"OH",
    "qs:gn_name":"Greenmont",
    "qs:local_max":11923,
    "qs:local_sum":38490,
    "qs:localhoods":42,
    "qs:name":"Greenmont",
    "qs:name_adm0":"United States",
    "qs:name_adm1":"Ohio",
    "qs:name_adm2":"Montgomery",
    "qs:name_local":"Dayton",
    "qs:photo_max":70,
    "qs:photo_sum":323,
    "qs:placetype":"Suburb",
    "qs:quad_count":15,
    "qs:woe_adm0":23424977,
    "qs:woe_adm1":2347594,
    "qs:woe_adm2":12589583,
    "qs:woe_lau":0,
    "qs:woe_local":2389876,
    "qs:woe_ver":"7.10.0",
    "wof:lang":[
        "eng"
    ],
    "wof:name":"Greenmont",
    "wof:placetype":"neighbourhood",
    "wof:population":1501,
    "zs:blockids":[
        390572104011028,
        390572104011002,
        390572104011021,
        390572104011029,
        390572104011022,
        390572104011023,
        390572104011024,
        390572104011006,
        390572104011008,
        390572104011009,
        390572104011010,
        390572104011012,
        390572104011030,
        390572104011031,
        390572104011016,
        390572104011025,
        390572104011005,
        390572104011003,
        390572104011007,
        390572104011011,
        390572104011013,
        390572104011017,
        390572104011015
    ],
    "zs:housing10":1151,
    "zs:pop10":1501
},
  "geometry": {"coordinates":[-84.114363,39.706149],"type":"Point"}
}