{
  "type": "Feature",
  "properties": {
    "gn:admin1_code":"SC",
    "gn:admin2_code":"83.0",
    "gn:asciiname":"Spring Hills",
    "gn:country_code":"US",
    "gn:dem":274,
    "gn:elevation":"274.0",
    "gn:feature_class":"P",
    "gn:feature_code":"PPL",
    "gn:name":"Spring Hills",
    "gn:population":0,
    "gn:timezone":"America/New_York",
    "iso:country":"US",
    "wof:name":"Spring Hills",
    "wof:placetype":"locality"
},
  "geometry": {"coordinates":[-81.97372,35.03373],"type":"Point"}
}