{
  "type": "Feature",
  "properties": {
    "gn:admin1_code":"TX",
    "gn:admin2_code":"395",
    "gn:asciiname":"Headsville",
    "gn:country_code":"US",
    "gn:dem":146,
    "gn:elevation":"146.0",
    "gn:feature_class":"P",
    "gn:feature_code":"PPL",
    "gn:name":"Headsville",
    "gn:population":0,
    "gn:timezone":"America/Chicago",
    "iso:country":"US",
    "wof:name":"Headsville",
    "wof:placetype":"locality"
},
  "geometry": {"coordinates":[-96.49581000000001,31.26129],"type":"Point"}
}