{
  "type": "Feature",
  "properties": {
    "gn:admin1_code":"TN",
    "gn:admin2_code":"59.0",
    "gn:asciiname":"Bird Hill",
    "gn:country_code":"US",
    "gn:dem":352,
    "gn:elevation":"345.0",
    "gn:feature_class":"P",
    "gn:feature_code":"PPL",
    "gn:name":"Bird Hill",
    "gn:population":0,
    "gn:timezone":"America/New_York",
    "iso:country":"US",
    "name:eng_x_preferred":[
        "Bird Hill"
    ],
    "name:und_x_variant":[
        "Birds Hill"
    ],
    "wof:name":"Bird Hill",
    "wof:placetype":"locality"
},
  "geometry": {"coordinates":[-83.11544000000001,36.12482],"type":"Point"}
}