{
  "type": "Feature",
  "properties": {
    "gn:admin1_code":"FL",
    "gn:admin2_code":"57",
    "gn:asciiname":"Durant Woods",
    "gn:country_code":"US",
    "gn:dem":29,
    "gn:elevation":"26.0",
    "gn:feature_class":"P",
    "gn:feature_code":"PPL",
    "gn:name":"Durant Woods",
    "gn:population":0,
    "gn:timezone":"America/New_York",
    "iso:country":"US",
    "wof:name":"Durant Woods",
    "wof:placetype":"locality"
},
  "geometry": {"coordinates":[-82.2238,27.9066],"type":"Point"}
}