{
  "type": "Feature",
  "properties": {
    "gn:admin1_code":"OH",
    "gn:admin2_code":"33",
    "gn:asciiname":"Meadowood Estates Mobile Home Park",
    "gn:country_code":"US",
    "gn:dem":351,
    "gn:elevation":"353.0",
    "gn:feature_class":"P",
    "gn:feature_code":"PPL",
    "gn:name":"Meadowood Estates Mobile Home Park",
    "gn:population":0,
    "gn:timezone":"America/New_York",
    "iso:country":"US",
    "wof:name":"Meadowood Estates Mobile Home Park",
    "wof:placetype":"campus"
},
  "geometry": {"coordinates":[-82.72750000000001,40.79],"type":"Point"}
}