{
  "type": "Feature",
  "properties": {
    "gn:admin1_code":"AR",
    "gn:admin2_code":"11.0",
    "gn:admin3_code":"91185.0",
    "gn:asciiname":"Blanchton",
    "gn:country_code":"US",
    "gn:dem":32,
    "gn:elevation":"25.0",
    "gn:feature_class":"P",
    "gn:feature_code":"PPL",
    "gn:name":"Blanchton",
    "gn:population":0,
    "gn:timezone":"America/Chicago",
    "iso:country":"US",
    "wof:name":"Blanchton",
    "wof:placetype":"locality"
},
  "geometry": {"coordinates":[-92.08708,33.24179],"type":"Point"}
}