{
  "type": "Feature",
  "properties": {
    "gn:admin1_code":"PA",
    "gn:admin2_code":"91",
    "gn:admin3_code":"44920.0",
    "gn:asciiname":"Foulkeways",
    "gn:country_code":"US",
    "gn:dem":125,
    "gn:elevation":"123.0",
    "gn:feature_class":"P",
    "gn:feature_code":"PPL",
    "gn:name":"Foulkeways",
    "gn:population":0,
    "gn:timezone":"America/New_York",
    "iso:country":"US",
    "wof:name":"Foulkeways",
    "wof:placetype":"locality"
},
  "geometry": {"coordinates":[-75.2518,40.2026],"type":"Point"}
}