{
  "type": "Feature",
  "properties": {
    "gn:admin1_code":"MD",
    "gn:admin2_code":"13.0",
    "gn:asciiname":"Walnut Ridge",
    "gn:country_code":"US",
    "gn:dem":253,
    "gn:elevation":"265.0",
    "gn:feature_class":"P",
    "gn:feature_code":"PPL",
    "gn:name":"Walnut Ridge",
    "gn:population":0,
    "gn:timezone":"America/New_York",
    "iso:country":"US",
    "name:ceb_x_preferred":[
        "Walnut Ridge"
    ],
    "name:deu_x_preferred":[
        "Walnut Ridge"
    ],
    "name:ita_x_preferred":[
        "Walnut Ridge"
    ],
    "wof:name":"Walnut Ridge",
    "wof:placetype":"locality"
},
  "geometry": {"coordinates":[-76.96915,39.55288],"type":"Point"}
}