{
  "type": "Feature",
  "properties": {
    "gn:admin1_code":"PA",
    "gn:admin2_code":"37.0",
    "gn:admin3_code":"37360.0",
    "gn:asciiname":"Polkville",
    "gn:country_code":"US",
    "gn:dem":366,
    "gn:elevation":"360.0",
    "gn:feature_class":"P",
    "gn:feature_code":"PPL",
    "gn:name":"Polkville",
    "gn:population":0,
    "gn:timezone":"America/New_York",
    "iso:country":"US",
    "name:ceb_x_preferred":[
        "Polkville"
    ],
    "name:deu_x_preferred":[
        "Polkville"
    ],
    "name:ita_x_preferred":[
        "Polkville"
    ],
    "name:nld_x_preferred":[
        "Polkville"
    ],
    "name:pol_x_preferred":[
        "Polkville"
    ],
    "name:por_x_preferred":[
        "Polkville"
    ],
    "name:spa_x_preferred":[
        "Polkville"
    ],
    "name:srp_x_preferred":[
        "\u041f\u043e\u043b\u043a\u0432\u0438\u043b"
    ],
    "name:swe_x_preferred":[
        "Polkville"
    ],
    "wof:name":"Polkville",
    "wof:placetype":"locality"
},
  "geometry": {"coordinates":[-76.43300000000001,41.23453],"type":"Point"}
}