{
  "type": "Feature",
  "properties": {
    "gn:country":"US",
    "gn:fcode":"PPL",
    "gn:population":0,
    "iso:country":"US",
    "name:eng_x_preferred":[
        "Camp Neyati"
    ],
    "qs_pg:aaroncc":"US",
    "qs_pg:gn_country":"US",
    "qs_pg:gn_fcode":"PPL",
    "qs_pg:gn_pop":0,
    "qs_pg:name":"Camp Neyati",
    "qs_pg:name_adm0":"United States",
    "qs_pg:name_adm1":"Massachusetts",
    "qs_pg:photos":6,
    "qs_pg:photos_1k":1,
    "qs_pg:photos_9k":1,
    "qs_pg:photos_9r":1,
    "qs_pg:photos_all":6,
    "qs_pg:photos_sr":1,
    "qs_pg:pop_sr":0,
    "qs_pg:qs_pg_placetype":"neighbourhood",
    "qs_pg:qs_pg_placetype_gp":"Suburb",
    "qs_pg:woe_adm0":23424977,
    "wof:name":"Camp Neyati",
    "wof:placetype":"neighbourhood",
    "wof:population":91,
    "zs:area_m":1235715.03511,
    "zs:blockids":[
        250277351003043,
        250277351003051,
        250277351003048,
        250277351003044,
        250277351003049,
        250277351003050
    ],
    "zs:housing10":32,
    "zs:label":"Camp Neyati",
    "zs:pop10":91
},
  "geometry": {"coordinates":[-71.935543,42.212245],"type":"Point"}
}