{
  "type": "Feature",
  "properties": {
    "gn:gn_country":"US",
    "gn:gn_fcode":"PPL",
    "gn:gn_pop":0,
    "iso:country":"US",
    "name:ceb_x_preferred":[
        "Hammond"
    ],
    "name:deu_x_preferred":[
        "Hammond"
    ],
    "name:fin_x_preferred":[
        "Hammond"
    ],
    "name:fra_x_preferred":[
        "Hammond"
    ],
    "name:heb_x_preferred":[
        "\u05d4\u05d0\u05de\u05d5\u05e0\u05d3"
    ],
    "name:ita_x_preferred":[
        "Hammond"
    ],
    "name:jpn_x_preferred":[
        "\u30cf\u30e2\u30f3\u30c9"
    ],
    "name:kor_x_preferred":[
        "\ud574\uba3c\ub4dc"
    ],
    "name:nld_x_preferred":[
        "Hammond"
    ],
    "name:pol_x_preferred":[
        "Hammond"
    ],
    "name:por_x_preferred":[
        "Hammond"
    ],
    "name:rus_x_preferred":[
        "\u0425\u0430\u043c\u043c\u043e\u043d\u0434"
    ],
    "name:spa_x_preferred":[
        "Hammond"
    ],
    "name:srp_x_preferred":[
        "\u0425\u0430\u043c\u043e\u043d\u0434"
    ],
    "name:swe_x_preferred":[
        "Hammond"
    ],
    "name:ukr_x_preferred":[
        "\u0413\u0430\u043c\u043c\u043e\u043d\u0434"
    ],
    "name:vol_x_preferred":[
        "Hammond"
    ],
    "qs_pg:aaroncc":"US",
    "qs_pg:gn_country":"US",
    "qs_pg:gn_fcode":"PPL",
    "qs_pg:gn_pop":0,
    "qs_pg:name":"Hammond",
    "qs_pg:name_adm0":"United States",
    "qs_pg:name_adm1":"California",
    "qs_pg:photos":378,
    "qs_pg:photos_1k":77,
    "qs_pg:photos_9k":2,
    "qs_pg:photos_9r":5,
    "qs_pg:photos_all":378,
    "qs_pg:photos_sr":6,
    "qs_pg:pop_sr":0,
    "qs_pg:qs_pg_placetype":"locality",
    "qs_pg:qs_pg_placetype_gp":"Town",
    "qs_pg:woe_adm0":23424977,
    "woe:adm0_id":23424977,
    "woe:name_adm0":"United States",
    "woe:name_adm1":"California",
    "woe:placetype":"Town",
    "wof:name":"Hammond",
    "wof:placetype":"locality"
},
  "geometry": {"coordinates":[-118.86121,36.4655],"type":"Point"}
}