{
  "type": "Feature",
  "properties": {
    "gn:admin1_code":"KS",
    "gn:admin2_code":"21.0",
    "gn:admin3_code":"25100.0",
    "gn:asciiname":"East Galena",
    "gn:country_code":"US",
    "gn:dem":299,
    "gn:elevation":"296.0",
    "gn:feature_class":"P",
    "gn:feature_code":"PPL",
    "gn:name":"East Galena",
    "gn:population":0,
    "gn:timezone":"America/Chicago",
    "iso:country":"US",
    "wof:name":"East Galena",
    "wof:placetype":"locality"
},
  "geometry": {"coordinates":[-94.62912,37.07284],"type":"Point"}
}