{
  "type": "Feature",
  "properties": {
    "iso:country":"US",
    "name:ast_x_preferred":[
        "Ligonia"
    ],
    "name:bul_x_preferred":[
        "Ligonia"
    ],
    "name:deu_x_preferred":[
        "Ligonia"
    ],
    "name:eng_x_preferred":[
        "Ligonia"
    ],
    "name:fra_x_preferred":[
        "Ligonia"
    ],
    "name:ita_x_preferred":[
        "Ligonia"
    ],
    "name:lat_x_preferred":[
        "Ligonia"
    ],
    "name:nld_x_preferred":[
        "Ligonia"
    ],
    "name:rus_x_preferred":[
        "Ligonia"
    ],
    "name:spa_x_preferred":[
        "Ligonia"
    ],
    "name:ukr_x_preferred":[
        "Ligonia"
    ],
    "name:vie_x_preferred":[
        "Ligonia"
    ],
    "qs:gn_adm0_cc":"US",
    "qs:gn_fcode":"PPL",
    "qs:gn_local":4979244,
    "qs:gn_nam_loc":"south portland",
    "qs:gn_namadm1":"ME",
    "qs:gn_name":"Ligonia",
    "qs:local_max":2232,
    "qs:local_sum":4330,
    "qs:localhoods":8,
    "qs:name":"Ligonia",
    "qs:name_adm0":"United States",
    "qs:name_adm1":"Maine",
    "qs:name_adm2":"Cumberland",
    "qs:name_local":"South Portland",
    "qs:photo_max":21,
    "qs:photo_sum":65,
    "qs:placetype":"Suburb",
    "qs:quad_count":17,
    "qs:woe_adm0":23424977,
    "qs:woe_adm1":2347578,
    "qs:woe_adm2":12588662,
    "qs:woe_lau":0,
    "qs:woe_local":2496642,
    "qs:woe_ver":"7.10.0",
    "wd:wordcount":16,
    "wof:lang":[
        "eng"
    ],
    "wof:name":"Ligonia",
    "wof:placetype":"neighbourhood",
    "wof:population":2005,
    "zs:blockids":[
        230050030004025,
        230050030004111,
        230050030004031,
        230050030004115,
        230050030004032,
        230050030004075,
        230050030004023,
        230050030004034,
        230050030004024,
        230050030004078,
        230050030004027,
        230050030004074,
        230050030004012,
        230050030004113,
        230050030004112,
        230050030004114,
        230050030004035,
        230050030004029,
        230050030004022
    ],
    "zs:housing10":807,
    "zs:pop10":2005
},
  "geometry": {"coordinates":[-70.28733099999999,43.636882],"type":"Point"}
}