{
  "type": "Feature",
  "properties": {
    "gn:country":"US",
    "gn:fcode":"PPL",
    "gn:population":0,
    "iso:country":"US",
    "name:ceb_x_preferred":[
        "Polkville"
    ],
    "name:deu_x_preferred":[
        "Polkville"
    ],
    "name:eng_x_preferred":[
        "Polkville"
    ],
    "name:hbs_x_preferred":[
        "Polkvil"
    ],
    "name:ita_x_preferred":[
        "Polkville"
    ],
    "name:nld_x_preferred":[
        "Polkville"
    ],
    "name:pol_x_preferred":[
        "Polkville"
    ],
    "name:por_x_preferred":[
        "Polkville"
    ],
    "name:spa_x_preferred":[
        "Polkville"
    ],
    "name:srp_x_preferred":[
        "\u041f\u043e\u043b\u043a\u0432\u0438\u043b"
    ],
    "name:swe_x_preferred":[
        "Polkville"
    ],
    "qs_pg:aaroncc":"US",
    "qs_pg:gn_country":"US",
    "qs_pg:gn_fcode":"PPL",
    "qs_pg:gn_pop":0,
    "qs_pg:name":"Polkville",
    "qs_pg:name_adm0":"United States",
    "qs_pg:name_adm1":"New York",
    "qs_pg:photos":17,
    "qs_pg:photos_1k":3,
    "qs_pg:photos_9k":1,
    "qs_pg:photos_9r":1,
    "qs_pg:photos_all":17,
    "qs_pg:photos_sr":1,
    "qs_pg:pop_sr":0,
    "qs_pg:qs_pg_placetype":"neighbourhood",
    "qs_pg:qs_pg_placetype_gp":"Suburb",
    "qs_pg:woe_adm0":23424977,
    "woe:adm0_id":23424977,
    "woe:name_adm0":"United States",
    "woe:name_adm1":"New York",
    "woe:placetype":"Suburb",
    "wof:name":"Polkville",
    "wof:placetype":"neighbourhood",
    "wof:population":447
},
  "geometry": {"coordinates":[-76.03131,43.0934],"type":"Point"}
}