{
  "type": "Feature",
  "properties": {
    "iso:country":"US",
    "name:eng_x_preferred":[
        "JPA"
    ],
    "qs:gn_adm0_cc":"US",
    "qs:gn_local":4752031,
    "qs:gn_nam_loc":"Charlottesville, Charlottesville, Virginia, US",
    "qs:gn_namadm1":"VA",
    "qs:local_max":5518,
    "qs:local_sum":30406,
    "qs:localhoods":28,
    "qs:name":"JPA",
    "qs:name_adm0":"United States",
    "qs:name_adm1":"Virginia",
    "qs:name_adm2":"Charlottesville City",
    "qs:name_local":"Charlottesville",
    "qs:photo_max":405,
    "qs:photo_sum":1102,
    "qs:placetype":"Suburb",
    "qs:quad_count":25,
    "qs:woe_adm0":23424977,
    "qs:woe_adm1":2347605,
    "qs:woe_adm2":12590328,
    "qs:woe_lau":0,
    "qs:woe_local":2378489,
    "qs:woe_ver":"7.10.0",
    "wof:lang":[
        "eng"
    ],
    "wof:name":"Jpa",
    "wof:placetype":"neighbourhood",
    "wof:population":4253,
    "zs:blockids":[
        515400006002018,
        515400006002016,
        515400006001009,
        515400006001012,
        515400006002019,
        515400006001004,
        515400006002001,
        515400006001020,
        515400006002010,
        515400006002011,
        515400006001022,
        515400006001010,
        515400006001019,
        515400006001017,
        515400006001027,
        515400006001008,
        515400006002017,
        515400006002014,
        515400005022000,
        515400006001016,
        515400006001018,
        515400006002012,
        515400005022005,
        515400006001021,
        515400006001015,
        515400006002002,
        515400006001023,
        515400006001014,
        515400006002000,
        515400006002015,
        515400006002013,
        515400006001013,
        515400006001011,
        515400006001028,
        515400006001005,
        515400006002009
    ],
    "zs:housing10":1765,
    "zs:pop10":4253
},
  "geometry": {"coordinates":[-78.511544,38.029164],"type":"Point"}
}