{
  "type": "Feature",
  "properties": {
    "gn:admin1_code":"AR",
    "gn:admin2_code":"5.0",
    "gn:admin3_code":"93669.0",
    "gn:asciiname":"Sycamore Spring",
    "gn:country_code":"US",
    "gn:dem":230,
    "gn:elevation":"231.0",
    "gn:feature_class":"P",
    "gn:feature_code":"PPL",
    "gn:name":"Sycamore Spring",
    "gn:population":0,
    "gn:timezone":"America/Chicago",
    "iso:country":"US",
    "wof:name":"Sycamore Spring",
    "wof:placetype":"locality"
},
  "geometry": {"coordinates":[-92.24903999999999,36.29868],"type":"Point"}
}