{
  "type": "Feature",
  "properties": {
    "gn:admin1_code":"TX",
    "gn:admin2_code":"271.0",
    "gn:asciiname":"Pinto",
    "gn:country_code":"US",
    "gn:dem":320,
    "gn:elevation":"320.0",
    "gn:feature_class":"P",
    "gn:feature_code":"PPL",
    "gn:name":"Pinto",
    "gn:population":0,
    "gn:timezone":"America/Chicago",
    "iso:country":"US",
    "name:ces_x_preferred":[
        "Pinto"
    ],
    "name:deu_x_preferred":[
        "Pinto"
    ],
    "name:sco_x_preferred":[
        "Pinto"
    ],
    "wof:name":"Pinto",
    "wof:placetype":"locality"
},
  "geometry": {"coordinates":[-100.58842,29.28135],"type":"Point"}
}