{
  "type": "Feature",
  "properties": {
    "gn:admin1_code":"NY",
    "gn:admin2_code":"71.0",
    "gn:admin3_code":"50848.0",
    "gn:asciiname":"Butter Hill Estates",
    "gn:country_code":"US",
    "gn:dem":36,
    "gn:elevation":"39.0",
    "gn:feature_class":"P",
    "gn:feature_code":"PPL",
    "gn:name":"Butter Hill Estates",
    "gn:population":0,
    "gn:timezone":"America/New_York",
    "iso:country":"US",
    "wof:name":"Butter Hill Estates",
    "wof:placetype":"locality"
},
  "geometry": {"coordinates":[-74.03721999999998,41.46111],"type":"Point"}
}