{
  "type": "Feature",
  "properties": {
    "gn:admin1_code":"RI",
    "gn:admin2_code":"3.0",
    "gn:admin3_code":"74300.0",
    "gn:asciiname":"Palace Garden",
    "gn:country_code":"US",
    "gn:dem":-2,
    "gn:elevation":"18.0",
    "gn:feature_class":"P",
    "gn:feature_code":"PPL",
    "gn:name":"Palace Garden",
    "gn:population":0,
    "gn:timezone":"America/New_York",
    "iso:country":"US",
    "name:eng_x_preferred":[
        "Palace Garden"
    ],
    "name:und_x_variant":[
        "Bakers Garden",
        "Palace Gardens",
        "Chopequonset Garden"
    ],
    "wof:name":"Palace Garden",
    "wof:placetype":"locality"
},
  "geometry": {"coordinates":[-71.40089,41.74232],"type":"Point"}
}