{
  "type": "Feature",
  "properties": {
    "gn:admin1_code":"MO",
    "gn:admin2_code":"111.0",
    "gn:admin3_code":"19468.0",
    "gn:asciiname":"Ten Mile",
    "gn:country_code":"US",
    "gn:dem":199,
    "gn:elevation":"201.0",
    "gn:feature_class":"P",
    "gn:feature_code":"PPL",
    "gn:name":"Ten Mile",
    "gn:population":0,
    "gn:timezone":"America/Chicago",
    "iso:country":"US",
    "name:deu_x_preferred":[
        "Ten Mile"
    ],
    "name:fra_x_preferred":[
        "Ten Mile"
    ],
    "name:pol_x_preferred":[
        "Ten Mile"
    ],
    "wof:name":"Ten Mile",
    "wof:placetype":"locality"
},
  "geometry": {"coordinates":[-91.64322,40.07754],"type":"Point"}
}