{
  "type": "Feature",
  "properties": {
    "gn:admin1_code":"SC",
    "gn:admin2_code":"67.0",
    "gn:asciiname":"Turner Place",
    "gn:country_code":"US",
    "gn:dem":17,
    "gn:elevation":"22.0",
    "gn:feature_class":"P",
    "gn:feature_code":"PPL",
    "gn:name":"Turner Place",
    "gn:population":0,
    "gn:timezone":"America/New_York",
    "iso:country":"US",
    "wof:name":"Turner Place",
    "wof:placetype":"locality"
},
  "geometry": {"coordinates":[-79.39421999999998,34.1996],"type":"Point"}
}