{
  "type": "Feature",
  "properties": {
    "gn:elevation":403,
    "iso:country":"US",
    "name:ceb_x_preferred":[
        "Townsend"
    ],
    "name:ces_x_preferred":[
        "Townsend"
    ],
    "name:deu_x_preferred":[
        "Townsend"
    ],
    "name:eng_x_preferred":[
        "Townsend"
    ],
    "name:fra_x_preferred":[
        "Townsend"
    ],
    "name:hbs_x_preferred":[
        "Taunsend"
    ],
    "name:ita_x_preferred":[
        "Townsend"
    ],
    "name:jpn_x_preferred":[
        "\u30bf\u30a6\u30f3\u30bc\u30f3\u30c8"
    ],
    "name:kor_x_preferred":[
        "\ud0c0\uc6b4\uc820\ub4dc"
    ],
    "name:nld_x_preferred":[
        "Townsend"
    ],
    "name:pol_x_preferred":[
        "Townsend"
    ],
    "name:por_x_preferred":[
        "Townsend"
    ],
    "name:rus_x_preferred":[
        "\u0422\u0430\u0443\u043d\u0441\u0435\u043d\u0434"
    ],
    "name:spa_x_preferred":[
        "Townsend"
    ],
    "name:srp_x_preferred":[
        "\u0422\u0430\u0443\u043d\u0441\u0435\u043d\u0434"
    ],
    "name:swe_x_preferred":[
        "Townsend"
    ],
    "name:ukr_x_preferred":[
        "\u0422\u0430\u0443\u043d\u0441\u0435\u043d\u0434"
    ],
    "name:vol_x_preferred":[
        "Townsend"
    ],
    "qs:gn_adm0_cc":"US",
    "qs:gn_fcode":"PPL",
    "qs:gn_local":5115113,
    "qs:gn_nam_loc":"Dix, Schuyler, New York, US",
    "qs:gn_namadm1":"NY",
    "qs:gn_name":"Townsend",
    "qs:local_max":26,
    "qs:local_sum":26,
    "qs:localhoods":1,
    "qs:name":"Townsend",
    "qs:name_adm0":"United States",
    "qs:name_adm1":"New York",
    "qs:name_adm2":"Schuyler",
    "qs:name_local":"Dix",
    "qs:photo_max":18,
    "qs:photo_sum":26,
    "qs:placetype":"Suburb",
    "qs:quad_count":4,
    "qs:woe_adm0":23424977,
    "qs:woe_adm1":2347591,
    "qs:woe_adm2":12589359,
    "qs:woe_lau":0,
    "qs:woe_local":28744559,
    "qs:woe_ver":"7.10.0",
    "wof:lang":[
        "eng"
    ],
    "wof:name":"Townsend",
    "wof:placetype":"neighbourhood",
    "wof:population":57,
    "zs:blockids":[
        360979504003010,
        360979504003009,
        360979504003007,
        360979504003011,
        360979504003006,
        360979504003008,
        360979504003004,
        360979504003013
    ],
    "zs:housing10":21,
    "zs:pop10":57
},
  "geometry": {"coordinates":[-76.95944,42.367911],"type":"Point"}
}