{
  "type": "Feature",
  "properties": {
    "gn:admin1_code":"AL",
    "gn:admin2_code":"129",
    "gn:asciiname":"Bigbee",
    "gn:country_code":"US",
    "gn:dem":40,
    "gn:elevation":"31.0",
    "gn:feature_class":"P",
    "gn:feature_code":"PPL",
    "gn:name":"Bigbee",
    "gn:population":0,
    "gn:timezone":"America/Chicago",
    "iso:country":"US",
    "name:deu_x_preferred":[
        "Bigbee"
    ],
    "wof:name":"Bigbee",
    "wof:placetype":"locality"
},
  "geometry": {"coordinates":[-88.1664,31.61405],"type":"Point"}
}