{
  "type": "Feature",
  "properties": {
    "gn:elevation":26,
    "iso:country":"US",
    "name:eng_x_preferred":[
        "Northwest Woods"
    ],
    "name:eng_x_variant":[
        "NW Woods"
    ],
    "qs:gn_adm0_cc":"US",
    "qs:gn_fcode":"PPLX",
    "qs:gn_local":4200671,
    "qs:gn_nam_loc":"Hinesville, Liberty, Georgia, US",
    "qs:gn_namadm1":"GA",
    "qs:gn_name":"Northwest Woods",
    "qs:local_max":38,
    "qs:local_sum":104,
    "qs:localhoods":5,
    "qs:name":"Northwest Woods",
    "qs:name_adm0":"United States",
    "qs:name_adm1":"Georgia",
    "qs:name_adm2":"Liberty",
    "qs:name_local":"Hinesville",
    "qs:photo_max":38,
    "qs:photo_sum":38,
    "qs:placetype":"Suburb",
    "qs:quad_count":1,
    "qs:woe_adm0":23424977,
    "qs:woe_adm1":2347569,
    "qs:woe_adm2":12587958,
    "qs:woe_lau":0,
    "qs:woe_local":2422431,
    "qs:woe_ver":"7.10.0",
    "wof:lang":[
        "eng"
    ],
    "wof:name":"Northwest Woods",
    "wof:placetype":"neighbourhood",
    "wof:population":4687,
    "zs:blockids":[
        131790102051007,
        131790102072003,
        131790102071000,
        131790102051001,
        131790102071002,
        131790102072009,
        131790102072006,
        131790102072008,
        131790102051004,
        131790102051013,
        131790102051012,
        131790102072011,
        131790102051005,
        131790102072012,
        131790102072005,
        131790102072001,
        131790102022014,
        131790102072002,
        131790102051002,
        131790102072007,
        131790102051011,
        131790102051006,
        131790102072017,
        131790102072000,
        131790102052020,
        131790102052021,
        131790102072004,
        131790102051009,
        131790102051010,
        131790102051003,
        131790102051021,
        131790102022015,
        131790102051000,
        131790102072010,
        131790102071004
    ],
    "zs:housing10":1973,
    "zs:pop10":4687
},
  "geometry": {"coordinates":[-81.624298,31.825066],"type":"Point"}
}