{
  "type": "Feature",
  "properties": {
    "gn:admin1_code":"SC",
    "gn:admin2_code":"63.0",
    "gn:asciiname":"Saluda Hills",
    "gn:country_code":"US",
    "gn:dem":78,
    "gn:elevation":"75.0",
    "gn:feature_class":"P",
    "gn:feature_code":"PPL",
    "gn:name":"Saluda Hills",
    "gn:population":0,
    "gn:timezone":"America/New_York",
    "iso:country":"US",
    "wof:name":"Saluda Hills",
    "wof:placetype":"locality"
},
  "geometry": {"coordinates":[-81.10536999999999,34.01099],"type":"Point"}
}