{
  "type": "Feature",
  "properties": {
    "gn:admin1_code":"ID",
    "gn:admin2_code":"65",
    "gn:asciiname":"Sunnydell",
    "gn:country_code":"US",
    "gn:dem":1515,
    "gn:elevation":"1513.0",
    "gn:feature_class":"P",
    "gn:feature_code":"PPL",
    "gn:name":"Sunnydell",
    "gn:population":0,
    "gn:timezone":"America/Boise",
    "iso:country":"US",
    "wof:name":"Sunnydell",
    "wof:placetype":"locality"
},
  "geometry": {"coordinates":[-111.75496,43.68436],"type":"Point"}
}