{
  "type": "Feature",
  "properties": {
    "gn:admin1_code":"WI",
    "gn:admin2_code":"43.0",
    "gn:admin3_code":"55200.0",
    "gn:asciiname":"Evergreen Terrace",
    "gn:country_code":"US",
    "gn:dem":209,
    "gn:elevation":"210.0",
    "gn:feature_class":"P",
    "gn:feature_code":"PPL",
    "gn:name":"Evergreen Terrace",
    "gn:population":0,
    "gn:timezone":"America/Chicago",
    "iso:country":"US",
    "name:deu_x_preferred":[
        "Evergreen Terrace"
    ],
    "name:fra_x_preferred":[
        "Evergreen Terrace"
    ],
    "name:ita_x_preferred":[
        "Evergreen Terrace"
    ],
    "name:nld_x_preferred":[
        "Evergreen Terrace"
    ],
    "name:nor_x_preferred":[
        "Evergreen Terrace"
    ],
    "name:por_x_preferred":[
        "Evergreen Terrace"
    ],
    "name:spa_x_preferred":[
        "Evergreen Terrace"
    ],
    "wof:name":"Evergreen Terrace",
    "wof:placetype":"locality"
},
  "geometry": {"coordinates":[-90.43556,43.18722],"type":"Point"}
}