{
  "type": "Feature",
  "properties": {
    "gn:admin1_code":"AZ",
    "gn:admin2_code":"13.0",
    "gn:asciiname":"Continental Village",
    "gn:country_code":"US",
    "gn:dem":416,
    "gn:elevation":"416.0",
    "gn:feature_class":"P",
    "gn:feature_code":"PPL",
    "gn:name":"Continental Village",
    "gn:population":0,
    "gn:timezone":"America/Phoenix",
    "iso:country":"US",
    "wof:name":"Continental Village",
    "wof:placetype":"locality"
},
  "geometry": {"coordinates":[-111.85875,33.56949],"type":"Point"}
}