{
  "type": "Feature",
  "properties": {
    "gn:admin1_code":"TX",
    "gn:admin2_code":"483.0",
    "gn:asciiname":"Bellco",
    "gn:country_code":"US",
    "gn:dem":761,
    "gn:elevation":"761.0",
    "gn:feature_class":"P",
    "gn:feature_code":"PPL",
    "gn:name":"Bellco",
    "gn:population":0,
    "gn:timezone":"America/Chicago",
    "iso:country":"US",
    "wof:name":"Bellco",
    "wof:placetype":"locality"
},
  "geometry": {"coordinates":[-100.5093,35.3806],"type":"Point"}
}