{
  "type": "Feature",
  "properties": {
    "iso:country":"US",
    "name:eng_x_preferred":[
        "Woodpark 1"
    ],
    "wof:name":"Woodpark 1",
    "wof:placetype":"neighbourhood",
    "wof:population":1088,
    "zs:area_m":861314.451324,
    "zs:blockids":[
        480850316261023,
        480850316243009,
        480850316243010,
        480850316261014,
        480850318072001,
        480850318073013,
        480850316261018,
        480850316261030,
        480850316243012,
        480850316242021,
        480850316261027,
        480850318072000,
        480850316261009,
        480850316261019,
        480850316261029,
        480850318073014,
        480850316261008,
        480850316261013,
        480850316261020,
        480850316261028,
        480850318073016,
        480850318072002,
        480850318071009,
        480850316261011,
        480850316261012,
        480850316242020,
        480850318073015,
        480850316242022,
        480850316243004,
        480850316261001,
        480850316261015,
        480850316261017,
        480850316261010,
        480850316243011,
        480850316261016,
        480850316261002,
        480850318073017
    ],
    "zs:housing10":460,
    "zs:label":"Woodpark 1",
    "zs:pop10":1088
},
  "geometry": {"coordinates":[-96.748676,33.020195],"type":"Point"}
}