{
  "type": "Feature",
  "properties": {
    "gn:admin1_code":"DE",
    "gn:admin2_code":"5.0",
    "gn:asciiname":"Byewood Manor",
    "gn:country_code":"US",
    "gn:dem":3,
    "gn:elevation":"3.0",
    "gn:feature_class":"P",
    "gn:feature_code":"PPL",
    "gn:name":"Byewood Manor",
    "gn:population":0,
    "gn:timezone":"America/New_York",
    "iso:country":"US",
    "wof:name":"Byewood Manor",
    "wof:placetype":"locality"
},
  "geometry": {"coordinates":[-75.11963,38.56039000000001],"type":"Point"}
}