{
  "type": "Feature",
  "properties": {
    "gn:admin1_code":"VA",
    "gn:admin2_code":"179.0",
    "gn:asciiname":"Brandy Hills",
    "gn:country_code":"US",
    "gn:dem":114,
    "gn:elevation":"102.0",
    "gn:feature_class":"P",
    "gn:feature_code":"PPL",
    "gn:name":"Brandy Hills",
    "gn:population":0,
    "gn:timezone":"America/New_York",
    "iso:country":"US",
    "wof:name":"Brandy Hills",
    "wof:placetype":"locality"
},
  "geometry": {"coordinates":[-77.59829999999999,38.4467],"type":"Point"}
}