{
  "type": "Feature",
  "properties": {
    "gn:elevation":486,
    "iso:country":"US",
    "name:eng_x_preferred":[
        "Camp Taconic"
    ],
    "qs:gn_adm0_cc":"US",
    "qs:gn_fcode":"PPL",
    "qs:gn_local":4939561,
    "qs:gn_nam_loc":"hinsdale",
    "qs:gn_namadm1":"MA",
    "qs:gn_name":"Camp Taconic",
    "qs:local_max":2,
    "qs:local_sum":2,
    "qs:localhoods":1,
    "qs:name":"Camp Taconic",
    "qs:name_adm0":"United States",
    "qs:name_adm1":"Massachusetts",
    "qs:name_adm2":"Berkshire",
    "qs:name_local":"Hinsdale",
    "qs:photo_max":1,
    "qs:photo_sum":2,
    "qs:placetype":"Suburb",
    "qs:quad_count":2,
    "qs:woe_adm0":23424977,
    "qs:woe_adm1":2347580,
    "qs:woe_adm2":12588701,
    "qs:woe_lau":0,
    "qs:woe_local":2422457,
    "qs:woe_ver":"7.10.0",
    "wof:lang":[
        "eng"
    ],
    "wof:name":"Camp Taconic",
    "wof:placetype":"neighbourhood",
    "wof:population":273,
    "zs:blockids":[
        250039323002022,
        250039323002028,
        250039323002088,
        250039323002020,
        250039323002085,
        250039323002018,
        250039323002024,
        250039323002084,
        250039323002023,
        250039323002021,
        250039323002089,
        250039323002027,
        250039323002026,
        250039323002087,
        250039323002017,
        250039323002019,
        250039323002025
    ],
    "zs:housing10":244,
    "zs:pop10":273
},
  "geometry": {"coordinates":[-73.089294,42.453861],"type":"Point"}
}