{
  "type": "Feature",
  "properties": {
    "gn:admin1_code":"WA",
    "gn:admin2_code":"61",
    "gn:asciiname":"Cathan",
    "gn:country_code":"US",
    "gn:dem":117,
    "gn:elevation":"107.0",
    "gn:feature_class":"P",
    "gn:feature_code":"PPL",
    "gn:name":"Cathan",
    "gn:population":0,
    "gn:timezone":"America/Los_Angeles",
    "iso:country":"US",
    "name:rus_x_preferred":[
        "\u041a\u0430\u0442\u0430\u043d"
    ],
    "name:und_x_variant":[
        "Cathan CDP",
        "Cathan"
    ],
    "wof:name":"Cathan",
    "wof:placetype":"locality"
},
  "geometry": {"coordinates":[-122.2822,48.11179],"type":"Point"}
}