{
  "type": "Feature",
  "properties": {
    "gn:admin1_code":"TX",
    "gn:admin2_code":"409",
    "gn:asciiname":"Crescent Center",
    "gn:country_code":"US",
    "gn:dem":15,
    "gn:elevation":"13.0",
    "gn:feature_class":"P",
    "gn:feature_code":"PPL",
    "gn:name":"Crescent Center",
    "gn:population":0,
    "gn:timezone":"America/Chicago",
    "iso:country":"US",
    "wof:name":"Crescent Center",
    "wof:placetype":"locality"
},
  "geometry": {"coordinates":[-97.32221,27.87975],"type":"Point"}
}