{
  "type": "Feature",
  "properties": {
    "gn:admin1_code":"CA",
    "gn:admin2_code":"39.0",
    "gn:asciiname":"Ahwahnee Estates",
    "gn:country_code":"US",
    "gn:dem":695,
    "gn:elevation":"697.0",
    "gn:feature_class":"P",
    "gn:feature_code":"PPL",
    "gn:name":"Ahwahnee Estates",
    "gn:population":0,
    "gn:timezone":"America/Los_Angeles",
    "iso:country":"US",
    "name:fas_x_preferred":[
        "\u0627\u06cc\u0627\u0644\u062a \u0627\u0647\u0648\u0627\u0647\u0646\u06cc"
    ],
    "name:spa_x_preferred":[
        "Ahwahnee Estates"
    ],
    "name:zho_x_preferred":[
        "\u963f\u8d6b\u74e6\u5c3c\u838a\u5712"
    ],
    "wof:name":"Ahwahnee Estates",
    "wof:placetype":"locality"
},
  "geometry": {"coordinates":[-119.70377000000001,37.37078],"type":"Point"}
}