{
  "type": "Feature",
  "properties": {
    "gn:country":"US",
    "gn:fcode":"ADMD",
    "gn:population":0,
    "iso:country":"US",
    "name:bar_x_preferred":[
        "Turbot Township"
    ],
    "name:deu_x_preferred":[
        "Turbot Township"
    ],
    "name:eng_x_preferred":[
        "Turbot Township"
    ],
    "name:eng_x_variant":[
        "Township of Turbot"
    ],
    "name:fra_x_preferred":[
        "Turbot Township"
    ],
    "name:jpn_x_preferred":[
        "\u30bf\u30fc\u30dc\u30c3\u30c8\u90e1\u533a"
    ],
    "name:spa_x_preferred":[
        "Municipio de Turbot"
    ],
    "name:und_x_variant":[
        "Turbut Township"
    ],
    "name:vie_x_preferred":[
        "Turbot"
    ],
    "qs_pg:aaroncc":"US",
    "qs_pg:gn_country":"US",
    "qs_pg:gn_fcode":"ADMD",
    "qs_pg:gn_pop":0,
    "qs_pg:name":"Turbot",
    "qs_pg:name_adm0":"United States",
    "qs_pg:name_adm1":"Pennsylvania",
    "qs_pg:photos":35,
    "qs_pg:photos_1k":7,
    "qs_pg:photos_9k":1,
    "qs_pg:photos_9r":2,
    "qs_pg:photos_all":35,
    "qs_pg:photos_sr":2,
    "qs_pg:pop_sr":0,
    "qs_pg:qs_pg_placetype":"locality",
    "qs_pg:qs_pg_placetype_gp":"Town",
    "qs_pg:woe_adm0":23424977,
    "woe:adm0_id":23424977,
    "woe:name_adm0":"United States",
    "woe:name_adm1":"Pennsylvania",
    "woe:placetype":"Town",
    "wof:name":"Turbot",
    "wof:placetype":"locality"
},
  "geometry": {"coordinates":[-76.79968,41.03342],"type":"Point"}
}