{
  "type": "Feature",
  "properties": {
    "gn:admin1_code":"AL",
    "gn:admin2_code":"79.0",
    "gn:asciiname":"Reynolds",
    "gn:country_code":"US",
    "gn:dem":184,
    "gn:elevation":"185.0",
    "gn:feature_class":"P",
    "gn:feature_code":"PPL",
    "gn:name":"Reynolds",
    "gn:population":0,
    "gn:timezone":"America/Chicago",
    "iso:country":"US",
    "name:cat_x_preferred":[
        "Reynolds"
    ],
    "name:ceb_x_preferred":[
        "Reynolds"
    ],
    "name:ces_x_preferred":[
        "Reynolds"
    ],
    "name:deu_x_preferred":[
        "Reynolds"
    ],
    "name:epo_x_preferred":[
        "Reynolds"
    ],
    "name:fas_x_preferred":[
        "\u0631\u06cc\u0646\u0648\u0644\u062f\u0632"
    ],
    "name:fin_x_preferred":[
        "Reynolds"
    ],
    "name:fra_x_preferred":[
        "Reynolds"
    ],
    "name:heb_x_preferred":[
        "\u05e8\u05d9\u05d9\u05e0\u05d5\u05dc\u05d3\u05e1"
    ],
    "name:ita_x_preferred":[
        "Reynolds"
    ],
    "name:jpn_x_preferred":[
        "\u30ec\u30a4\u30ce\u30eb\u30ba"
    ],
    "name:lav_x_preferred":[
        "Renoldss"
    ],
    "name:nld_x_preferred":[
        "Reynolds"
    ],
    "name:pol_x_preferred":[
        "Reynolds"
    ],
    "name:por_x_preferred":[
        "Reynolds"
    ],
    "name:rus_x_preferred":[
        "Reynolds"
    ],
    "name:spa_x_preferred":[
        "Reynolds"
    ],
    "name:srp_x_preferred":[
        "\u0420\u0435\u043d\u043e\u043b\u0434\u0441"
    ],
    "name:swe_x_preferred":[
        "Reynolds"
    ],
    "name:ukr_x_preferred":[
        "Reynolds"
    ],
    "name:vol_x_preferred":[
        "Reynolds"
    ],
    "wof:name":"Reynolds",
    "wof:placetype":"locality"
},
  "geometry": {"coordinates":[-87.17279000000001,34.63315],"type":"Point"}
}