{
  "type": "Feature",
  "properties": {
    "gn:country":"US",
    "gn:fcode":"PPL",
    "gn:population":11165,
    "iso:country":"US",
    "name:ara_x_preferred":[
        "\u062f\u0648\u062f\u0644\u064a"
    ],
    "name:arz_x_preferred":[
        "\u062f\u0648\u062f\u0644\u0649"
    ],
    "name:azb_x_preferred":[
        "\u062f\u0648\u062f\u0644\u0626\u06cc"
    ],
    "name:ben_x_preferred":[
        "\u09a1\u09c1\u09a1\u09b2\u09c7"
    ],
    "name:cat_x_preferred":[
        "Dudley"
    ],
    "name:ceb_x_preferred":[
        "Dudley"
    ],
    "name:che_x_preferred":[
        "\u0414\u0430\u0434\u043b\u0438"
    ],
    "name:cym_x_preferred":[
        "Dudley"
    ],
    "name:deu_x_preferred":[
        "Dudley"
    ],
    "name:ell_x_preferred":[
        "\u039d\u03c4\u03ac\u03bd\u03c4\u03bb\u03b5\u03ca"
    ],
    "name:eng_x_preferred":[
        "Dudley"
    ],
    "name:eus_x_preferred":[
        "Dudley"
    ],
    "name:fas_x_preferred":[
        "\u062f\u0627\u062f\u0644\u06cc\u060c \u0645\u0627\u0633\u0627\u0686\u0648\u0633\u062a"
    ],
    "name:fas_x_variant":[
        "\u062f\u0627\u062f\u0644\u06cc"
    ],
    "name:fra_x_preferred":[
        "Dudley"
    ],
    "name:hat_x_preferred":[
        "Dudley"
    ],
    "name:heb_x_preferred":[
        "\u05d3\u05d0\u05d3\u05dc\u05d9"
    ],
    "name:hin_x_preferred":[
        "\u0921\u0921\u0932\u0940"
    ],
    "name:hun_x_preferred":[
        "Dudley"
    ],
    "name:ind_x_preferred":[
        "Dudley"
    ],
    "name:ita_x_preferred":[
        "Dudley"
    ],
    "name:jpn_x_preferred":[
        "\u30c0\u30c9\u30ea\u30fc"
    ],
    "name:kaz_x_preferred":[
        "\u0414\u0430\u0434\u043b\u044d\u0439"
    ],
    "name:kir_x_preferred":[
        "\u0414\u0430\u0434\u043b\u044d\u0439"
    ],
    "name:nld_x_preferred":[
        "Dudley"
    ],
    "name:pol_x_preferred":[
        "Dudley"
    ],
    "name:por_x_preferred":[
        "Dudley"
    ],
    "name:ron_x_preferred":[
        "Dudley"
    ],
    "name:spa_x_preferred":[
        "Dudley"
    ],
    "name:tat_x_preferred":[
        "\u0414\u0430\u0434\u043b\u0438"
    ],
    "name:tur_x_preferred":[
        "Dudley"
    ],
    "name:ukr_x_preferred":[
        "\u0414\u0430\u0434\u043b\u0456"
    ],
    "name:und_x_variant":[
        "Dudley Centre"
    ],
    "name:urd_x_preferred":[
        "\u0688\u0688\u0644\u06cc"
    ],
    "name:vie_x_preferred":[
        "Dudley"
    ],
    "name:vol_x_preferred":[
        "Dudley"
    ],
    "qs_pg:aaroncc":"US",
    "qs_pg:gn_country":"US",
    "qs_pg:gn_fcode":"PPL",
    "qs_pg:gn_pop":11165,
    "qs_pg:name":"Dudley",
    "qs_pg:name_adm0":"United States",
    "qs_pg:name_adm1":"Massachusetts",
    "qs_pg:photos":134,
    "qs_pg:photos_1k":27,
    "qs_pg:photos_9k":1,
    "qs_pg:photos_9r":4,
    "qs_pg:photos_all":249,
    "qs_pg:photos_sr":3,
    "qs_pg:pop_sr":6,
    "qs_pg:qs_pg_placetype":"locality",
    "qs_pg:qs_pg_placetype_gp":"Town",
    "qs_pg:woe_adm0":23424977,
    "woe:adm0_id":23424977,
    "woe:name_adm0":"United States",
    "woe:name_adm1":"Massachusetts",
    "woe:placetype":"Town",
    "wof:name":"Dudley",
    "wof:placetype":"locality",
    "wof:population":11165
},
  "geometry": {"coordinates":[-71.93007,42.0451],"type":"Point"}
}