{
  "type": "Feature",
  "properties": {
    "gn:admin1_code":"OH",
    "gn:admin2_code":"61",
    "gn:admin3_code":"1980.0",
    "gn:asciiname":"Huntcrest Acres",
    "gn:country_code":"US",
    "gn:dem":257,
    "gn:elevation":"255.0",
    "gn:feature_class":"P",
    "gn:feature_code":"PPL",
    "gn:name":"Huntcrest Acres",
    "gn:population":0,
    "gn:timezone":"America/New_York",
    "iso:country":"US",
    "wof:name":"Huntcrest Acres",
    "wof:placetype":"locality"
},
  "geometry": {"coordinates":[-84.33633,39.08117],"type":"Point"}
}