{
  "type": "Feature",
  "properties": {
    "gn:admin1_code":"MO",
    "gn:admin2_code":"69.0",
    "gn:admin3_code":"14338.0",
    "gn:asciiname":"Cotton Plant",
    "gn:country_code":"US",
    "gn:dem":76,
    "gn:elevation":"77.0",
    "gn:feature_class":"P",
    "gn:feature_code":"PPL",
    "gn:name":"Cotton Plant",
    "gn:population":0,
    "gn:timezone":"America/Chicago",
    "iso:country":"US",
    "wof:name":"Cotton Plant",
    "wof:placetype":"locality"
},
  "geometry": {"coordinates":[-90.0912,36.09007],"type":"Point"}
}