{
  "type": "Feature",
  "properties": {
    "iso:country":"US",
    "name:eng_x_preferred":[
        "Royal Oaks"
    ],
    "qs:gn_adm0_cc":"US",
    "qs:gn_local":4719457,
    "qs:gn_nam_loc":"plano",
    "qs:gn_namadm1":"TX",
    "qs:local_max":1456,
    "qs:local_sum":11683,
    "qs:localhoods":39,
    "qs:name":"Royal Oaks",
    "qs:name_adm0":"United States",
    "qs:name_adm1":"Texas",
    "qs:name_adm2":"Collin",
    "qs:name_local":"Plano",
    "qs:photo_max":296,
    "qs:photo_sum":852,
    "qs:placetype":"Suburb",
    "qs:quad_count":37,
    "qs:woe_adm0":23424977,
    "qs:woe_adm1":2347602,
    "qs:woe_adm2":12590049,
    "qs:woe_lau":0,
    "qs:woe_local":2473475,
    "qs:woe_ver":"7.10.0",
    "wof:name":"Royal Oaks",
    "wof:placetype":"neighbourhood",
    "wof:population":2616,
    "zs:blockids":[
        480850320081031,
        480850320082005,
        480850320083001,
        480850320082008,
        480850320083003,
        480850320081020,
        480850320082002,
        480850320081023,
        480850320082007,
        480850320081039,
        480850320081038,
        480850320081034,
        480850320082001,
        480850320082010,
        480850320082018,
        480850320082017,
        480850320082004,
        480850320082014,
        480850320082006,
        480850320081001,
        480850320081040,
        480850320081030,
        480850320082015,
        480850320082009,
        480850320081003,
        480850320082003,
        480850320081024,
        480850320081041,
        480850320081027,
        480850320081032,
        480850320081042,
        480850320082011,
        480850320081022,
        480850320081033,
        480850320081035,
        480850320081043,
        480850320082013,
        480850320083002,
        480850320083000,
        480850320082000,
        480850320082016,
        480850320082012,
        480850320081021
    ],
    "zs:housing10":1024,
    "zs:pop10":2616
},
  "geometry": {"coordinates":[-96.668813,33.04502],"type":"Point"}
}