{
  "type": "Feature",
  "properties": {
    "gn:admin1_code":"OH",
    "gn:admin2_code":"117.0",
    "gn:admin3_code":"11248.0",
    "gn:asciiname":"Climax",
    "gn:country_code":"US",
    "gn:dem":315,
    "gn:elevation":"315.0",
    "gn:feature_class":"P",
    "gn:feature_code":"PPL",
    "gn:name":"Climax",
    "gn:population":0,
    "gn:timezone":"America/New_York",
    "iso:country":"US",
    "name:cat_x_preferred":[
        "Climax"
    ],
    "name:ceb_x_preferred":[
        "Climax"
    ],
    "name:ces_x_preferred":[
        "Climax"
    ],
    "name:deu_x_preferred":[
        "Climax"
    ],
    "name:fra_x_preferred":[
        "Climax"
    ],
    "name:ita_x_preferred":[
        "Climax"
    ],
    "name:kor_x_preferred":[
        "\ud074\ub77c\uc774\ub9e5\uc2a4"
    ],
    "name:nld_x_preferred":[
        "Climax"
    ],
    "name:nor_x_preferred":[
        "Climax"
    ],
    "name:pol_x_preferred":[
        "Climax"
    ],
    "name:por_x_preferred":[
        "Climax"
    ],
    "name:rus_x_preferred":[
        "\u041a\u043b\u0430\u0439\u043c\u0430\u043a\u0441"
    ],
    "name:scn_x_preferred":[
        "Climax"
    ],
    "name:swe_x_preferred":[
        "Climax"
    ],
    "name:ukr_x_preferred":[
        "\u041a\u043b\u0456\u043c\u0430\u043a\u0441"
    ],
    "name:vol_x_preferred":[
        "Climax"
    ],
    "wof:name":"Climax",
    "wof:placetype":"locality"
},
  "geometry": {"coordinates":[-82.88795999999998,40.63061],"type":"Point"}
}