{
  "type": "Feature",
  "properties": {
    "gn:admin1_code":"DE",
    "gn:admin2_code":"5.0",
    "gn:asciiname":"Buck Hill Landing",
    "gn:country_code":"US",
    "gn:dem":2,
    "gn:elevation":"1.0",
    "gn:feature_class":"P",
    "gn:feature_code":"PPL",
    "gn:name":"Buck Hill Landing",
    "gn:population":0,
    "gn:timezone":"America/New_York",
    "iso:country":"US",
    "name:eng_x_preferred":[
        "Buck Hill Landing"
    ],
    "name:und_x_variant":[
        "Buck Landing"
    ],
    "wof:name":"Buck Hill Landing",
    "wof:placetype":"locality"
},
  "geometry": {"coordinates":[-75.22185,38.55984],"type":"Point"}
}