{
  "type": "Feature",
  "properties": {
    "gn:admin1_code":"NY",
    "gn:admin2_code":"97",
    "gn:admin3_code":"12914.0",
    "gn:asciiname":"Wildwood Mobile Home Park",
    "gn:country_code":"US",
    "gn:dem":358,
    "gn:elevation":"359.0",
    "gn:feature_class":"P",
    "gn:feature_code":"PPL",
    "gn:name":"Wildwood Mobile Home Park",
    "gn:population":0,
    "gn:timezone":"America/New_York",
    "iso:country":"US",
    "wof:name":"Wildwood Mobile Home Park",
    "wof:placetype":"campus"
},
  "geometry": {"coordinates":[-76.73860999999999,42.30139000000001],"type":"Point"}
}