{
  "type": "Feature",
  "properties": {
    "iso:country":"US",
    "name:eng_x_preferred":[
        "Shadow Lakes"
    ],
    "wof:name":"Shadow Lakes",
    "wof:placetype":"neighbourhood",
    "wof:population":478,
    "zs:area_m":429971.859335,
    "zs:blockids":[
        120710403092026,
        120710403092024,
        120710403092023,
        120710403092027,
        120710403092025,
        120710403092028
    ],
    "zs:housing10":231,
    "zs:label":"Shadow Lakes",
    "zs:pop10":478
},
  "geometry": {"coordinates":[-81.62059000000001,26.598026],"type":"Point"}
}