{
  "type": "Feature",
  "properties": {
    "gn:admin1_code":"VA",
    "gn:admin2_code":"19",
    "gn:asciiname":"Oakview",
    "gn:country_code":"US",
    "gn:dem":260,
    "gn:elevation":"256.0",
    "gn:feature_class":"P",
    "gn:feature_code":"PPL",
    "gn:name":"Oakview",
    "gn:population":0,
    "gn:timezone":"America/New_York",
    "iso:country":"US",
    "wof:name":"Oakview",
    "wof:placetype":"locality"
},
  "geometry": {"coordinates":[-79.26224999999999,37.36125],"type":"Point"}
}