{
  "type": "Feature",
  "properties": {
    "gn:admin1_code":"MD",
    "gn:admin2_code":"29.0",
    "gn:asciiname":"Runnymeade Estates",
    "gn:country_code":"US",
    "gn:dem":15,
    "gn:elevation":"18.0",
    "gn:feature_class":"P",
    "gn:feature_code":"PPL",
    "gn:name":"Runnymeade Estates",
    "gn:population":0,
    "gn:timezone":"America/New_York",
    "iso:country":"US",
    "wof:name":"Runnymeade Estates",
    "wof:placetype":"locality"
},
  "geometry": {"coordinates":[-76.03106,39.28761],"type":"Point"}
}