{
  "type": "Feature",
  "properties": {
    "gn:admin1_code":"FL",
    "gn:admin2_code":"31.0",
    "gn:asciiname":"Continental Village Mobile Home Park",
    "gn:country_code":"US",
    "gn:dem":10,
    "gn:elevation":"7.0",
    "gn:feature_class":"P",
    "gn:feature_code":"PPL",
    "gn:name":"Continental Village Mobile Home Park",
    "gn:population":0,
    "gn:timezone":"America/New_York",
    "iso:country":"US",
    "wof:name":"Continental Village Mobile Home Park",
    "wof:placetype":"campus"
},
  "geometry": {"coordinates":[-81.7209,30.1988],"type":"Point"}
}