{
  "type": "Feature",
  "properties": {
    "gn:admin1_code":"IN",
    "gn:admin2_code":"171.0",
    "gn:admin3_code":"51264.0",
    "gn:asciiname":"Romine Corner",
    "gn:country_code":"US",
    "gn:dem":174,
    "gn:elevation":"173.0",
    "gn:feature_class":"P",
    "gn:feature_code":"PPL",
    "gn:name":"Romine Corner",
    "gn:population":0,
    "gn:timezone":"America/Indiana/Indianapolis",
    "iso:country":"US",
    "wof:name":"Romine Corner",
    "wof:placetype":"locality"
},
  "geometry": {"coordinates":[-87.43307,40.14198],"type":"Point"}
}