{
  "type": "Feature",
  "properties": {
    "gn:admin1_code":"OK",
    "gn:admin2_code":"121",
    "gn:asciiname":"Bug Tussle",
    "gn:country_code":"US",
    "gn:dem":188,
    "gn:elevation":"183.0",
    "gn:feature_class":"P",
    "gn:feature_code":"PPL",
    "gn:name":"Bug Tussle",
    "gn:population":0,
    "gn:timezone":"America/Chicago",
    "iso:country":"US",
    "wof:name":"Bug Tussle",
    "wof:placetype":"locality"
},
  "geometry": {"coordinates":[-95.68998999999999,35.03093],"type":"Point"}
}