{
  "type": "Feature",
  "properties": {
    "gn:admin1_code":"KY",
    "gn:admin2_code":"97",
    "gn:asciiname":"Garnett",
    "gn:country_code":"US",
    "gn:dem":217,
    "gn:elevation":"216.0",
    "gn:feature_class":"P",
    "gn:feature_code":"PPL",
    "gn:name":"Garnett",
    "gn:population":0,
    "gn:timezone":"America/New_York",
    "iso:country":"US",
    "name:deu_x_preferred":[
        "Garnett"
    ],
    "name:fra_x_preferred":[
        "Garnett"
    ],
    "name:ita_x_preferred":[
        "Garnett"
    ],
    "name:lav_x_preferred":[
        "G\u0101rnets"
    ],
    "name:nld_x_preferred":[
        "Garnett"
    ],
    "name:rus_x_preferred":[
        "\u0413\u0430\u0440\u043d\u0435\u0442\u0442"
    ],
    "name:swe_x_preferred":[
        "Garnett"
    ],
    "name:ukr_x_preferred":[
        "\u0413\u0430\u0440\u043d\u0435\u0442\u0442"
    ],
    "wof:name":"Garnett",
    "wof:placetype":"locality"
},
  "geometry": {"coordinates":[-84.32744,38.45924],"type":"Point"}
}