{
  "type": "Feature",
  "properties": {
    "gn:admin1_code":"KS",
    "gn:admin2_code":"15.0",
    "gn:admin3_code":"56200.0",
    "gn:asciiname":"Salter",
    "gn:country_code":"US",
    "gn:dem":390,
    "gn:elevation":"387.0",
    "gn:feature_class":"P",
    "gn:feature_code":"PPL",
    "gn:name":"Salter",
    "gn:population":0,
    "gn:timezone":"America/Chicago",
    "iso:country":"US",
    "name:ceb_x_preferred":[
        "Salter"
    ],
    "name:deu_x_preferred":[
        "Salter"
    ],
    "name:fra_x_preferred":[
        "Salter"
    ],
    "name:swe_x_preferred":[
        "Salter"
    ],
    "wof:name":"Salter",
    "wof:placetype":"locality"
},
  "geometry": {"coordinates":[-97.04476,37.61391],"type":"Point"}
}