{
  "type": "Feature",
  "properties": {
    "gn:country":"US",
    "gn:fcode":"PPL",
    "gn:population":0,
    "iso:country":"US",
    "name:ben_x_preferred":[
        "\u09aa\u09bf\u09b2\u09be\u09b0"
    ],
    "name:ell_x_preferred":[
        "\u03a0\u03b9\u03bb\u03ac\u03c1"
    ],
    "name:eng_x_preferred":[
        "Pilar"
    ],
    "name:fra_x_preferred":[
        "Pilar"
    ],
    "name:heb_x_preferred":[
        "\u05e4\u05d9\u05dc\u05d0\u05e8"
    ],
    "name:hin_x_preferred":[
        "\u092a\u093f\u0932\u0930"
    ],
    "name:hun_x_preferred":[
        "Pilar"
    ],
    "name:ind_x_preferred":[
        "Pilar"
    ],
    "name:spa_x_preferred":[
        "Pilar"
    ],
    "name:swe_x_preferred":[
        "Pilar"
    ],
    "name:und_x_variant":[
        "Cieneguilla"
    ],
    "name:vie_x_preferred":[
        "Pilar"
    ],
    "qs_pg:aaroncc":"US",
    "qs_pg:gn_country":"US",
    "qs_pg:gn_fcode":"PPL",
    "qs_pg:gn_pop":0,
    "qs_pg:name":"Pilar",
    "qs_pg:name_adm0":"United States",
    "qs_pg:name_adm1":"New Mexico",
    "qs_pg:photos":463,
    "qs_pg:photos_1k":94,
    "qs_pg:photos_9k":2,
    "qs_pg:photos_9r":5,
    "qs_pg:photos_all":463,
    "qs_pg:photos_sr":7,
    "qs_pg:pop_sr":5,
    "qs_pg:qs_pg_placetype":"locality",
    "qs_pg:qs_pg_placetype_gp":"Town",
    "qs_pg:woe_adm0":23424977,
    "woe:adm0_id":23424977,
    "woe:name_adm0":"United States",
    "woe:name_adm1":"New Mexico",
    "woe:placetype":"Town",
    "wof:name":"Pilar",
    "wof:placetype":"locality"
},
  "geometry": {"coordinates":[-105.78807,36.26975],"type":"Point"}
}