{
  "type": "Feature",
  "properties": {
    "gn:country":"US",
    "gn:fcode":"PPL",
    "gn:population":0,
    "iso:country":"US",
    "qs_pg:aaroncc":"US",
    "qs_pg:gn_country":"US",
    "qs_pg:gn_fcode":"PPL",
    "qs_pg:gn_pop":0,
    "qs_pg:name":"West Kingston",
    "qs_pg:name_adm0":"United States",
    "qs_pg:name_adm1":"Rhode Island",
    "qs_pg:photos":352,
    "qs_pg:photos_1k":71,
    "qs_pg:photos_9k":2,
    "qs_pg:photos_9r":5,
    "qs_pg:photos_all":352,
    "qs_pg:photos_sr":6,
    "qs_pg:pop_sr":9,
    "qs_pg:qs_pg_placetype":"locality",
    "qs_pg:qs_pg_placetype_gp":"Town",
    "qs_pg:woe_adm0":23424977,
    "woe:adm0_id":23424977,
    "woe:name_adm0":"United States",
    "woe:name_adm1":"Rhode Island",
    "woe:placetype":"Town",
    "wof:name":"West Kingston",
    "wof:placetype":"locality"
},
  "geometry": {"coordinates":[-71.55145,41.48316],"type":"Point"}
}