{
  "type": "Feature",
  "properties": {
    "gn:country":"US",
    "gn:fcode":"PPL",
    "gn:population":0,
    "iso:country":"US",
    "name:ara_x_preferred":[
        "\u0644\u064a\u0645\u064a\u0646\u063a\u062a\u0648\u0646"
    ],
    "name:cat_x_preferred":[
        "Lemington"
    ],
    "name:che_x_preferred":[
        "\u041b\u0435\u043c\u0438\u043d\u0433\u0442\u043e\u043d"
    ],
    "name:cym_x_preferred":[
        "Lemington"
    ],
    "name:deu_x_preferred":[
        "Lemington"
    ],
    "name:eng_x_preferred":[
        "Lemington"
    ],
    "name:eng_x_variant":[
        "Mossy Head"
    ],
    "name:eus_x_preferred":[
        "Lemington"
    ],
    "name:fas_x_preferred":[
        "\u0644\u0645\u06cc\u0646\u06af\u062a\u0648\u0646"
    ],
    "name:fra_x_preferred":[
        "Lemington"
    ],
    "name:hat_x_preferred":[
        "Lemington"
    ],
    "name:ita_x_preferred":[
        "Lemington"
    ],
    "name:pol_x_preferred":[
        "Lemington"
    ],
    "name:spa_x_preferred":[
        "Lemington"
    ],
    "name:tat_x_preferred":[
        "\u041b\u0435\u043c\u0438\u043d\u0433\u0442\u043e\u043d"
    ],
    "name:tur_x_preferred":[
        "Lemington"
    ],
    "name:ukr_x_preferred":[
        "\u041b\u0435\u043c\u0456\u043d\u0433\u0442\u043e\u043d"
    ],
    "name:uzb_x_preferred":[
        "Lemington"
    ],
    "name:vol_x_preferred":[
        "Lemington"
    ],
    "qs_pg:aaroncc":"US",
    "qs_pg:gn_country":"US",
    "qs_pg:gn_fcode":"PPL",
    "qs_pg:gn_pop":0,
    "qs_pg:name":"Lemington",
    "qs_pg:name_adm0":"United States",
    "qs_pg:name_adm1":"Vermont",
    "qs_pg:photos":25,
    "qs_pg:photos_1k":5,
    "qs_pg:photos_9k":1,
    "qs_pg:photos_9r":1,
    "qs_pg:photos_all":25,
    "qs_pg:photos_sr":1,
    "qs_pg:pop_sr":0,
    "qs_pg:qs_pg_placetype":"locality",
    "qs_pg:qs_pg_placetype_gp":"Town",
    "qs_pg:woe_adm0":23424977,
    "woe:adm0_id":23424977,
    "woe:name_adm0":"United States",
    "woe:name_adm1":"Vermont",
    "woe:placetype":"Town",
    "wof:name":"Lemington",
    "wof:placetype":"locality"
},
  "geometry": {"coordinates":[-71.55092,44.8581],"type":"Point"}
}