{
  "type": "Feature",
  "properties": {
    "iso:country":"US",
    "name:eng_x_preferred":[
        "Bradford Center"
    ],
    "wof:name":"Bradford Center",
    "wof:placetype":"neighbourhood",
    "wof:population":140,
    "zs:area_m":8778286.169769,
    "zs:blockids":[
        330130405003084,
        330130405003097,
        330130405003133,
        330130405003131,
        330130405003085,
        330130405003098
    ],
    "zs:housing10":68,
    "zs:label":"Bradford Center",
    "zs:pop10":140
},
  "geometry": {"coordinates":[-71.97931199999999,43.249374],"type":"Point"}
}