{
  "type": "Feature",
  "properties": {
    "gn:admin1_code":"FL",
    "gn:admin2_code":"86",
    "gn:asciiname":"Andover Census Designated Place (historical)",
    "gn:country_code":"US",
    "gn:dem":19,
    "gn:elevation":"1.0",
    "gn:feature_class":"P",
    "gn:feature_code":"PPL",
    "gn:name":"Andover  (historical)",
    "gn:population":0,
    "gn:timezone":"America/New_York",
    "iso:country":"US",
    "name:und_x_variant":[
        "Andover (historical)"
    ],
    "wof:name":"Andover Census Designated Place (historical)",
    "wof:placetype":"locality"
},
  "geometry": {"coordinates":[-80.21332,25.96609],"type":"Point"}
}