{
  "type": "Feature",
  "properties": {
    "iso:country":"US",
    "name:eng_x_preferred":[
        "Bramblewood"
    ],
    "wof:name":"Bramblewood",
    "wof:placetype":"neighbourhood",
    "wof:population":1588,
    "zs:area_m":764176.898947,
    "zs:blockids":[
        180973201052015,
        180973201052018,
        180973101043018,
        180973201052016,
        180973201052021,
        180973101043022,
        180973101043000,
        180973101043005,
        180973201052019,
        180973101043020,
        180973101043016,
        180973201052017,
        180973201052020,
        180973101043019
    ],
    "zs:housing10":1050,
    "zs:label":"Bramblewood",
    "zs:pop10":1588
},
  "geometry": {"coordinates":[-86.199916,39.92226],"type":"Point"}
}