{
  "type": "Feature",
  "properties": {
    "iso:country":"US",
    "name:eng_x_preferred":[
        "Regency Lakes"
    ],
    "qs:gn_adm0_cc":"US",
    "qs:gn_local":4169014,
    "qs:gn_nam_loc":"Pompano Beach, Broward, Florida, US",
    "qs:gn_namadm1":"FL",
    "qs:local_max":2428,
    "qs:local_sum":12719,
    "qs:localhoods":35,
    "qs:name":"Regency Lakes",
    "qs:name_adm0":"United States",
    "qs:name_adm1":"Florida",
    "qs:name_adm2":"Broward",
    "qs:name_local":"Pompano Beach",
    "qs:photo_max":29,
    "qs:photo_sum":119,
    "qs:placetype":"Suburb",
    "qs:quad_count":14,
    "qs:woe_adm0":23424977,
    "qs:woe_adm1":2347568,
    "qs:woe_adm2":12587808,
    "qs:woe_lau":0,
    "qs:woe_local":2474897,
    "qs:woe_ver":"7.10.0",
    "wof:name":"Regency Lakes",
    "wof:placetype":"neighbourhood",
    "wof:population":7606,
    "zs:blockids":[
        120110106091016,
        120110106091018,
        120110106091006,
        120110106091010,
        120110106071002,
        120110106103020,
        120110106091026,
        120110106091017,
        120110106091001,
        120110106103024,
        120110106091002,
        120110106103028,
        120110106011008,
        120110106103017,
        120110106071007,
        120110106103027,
        120110106091021,
        120110106091019,
        120110106091003,
        120110106091014,
        120110106091005,
        120110106091020,
        120110106071003,
        120110106071006,
        120110106071001,
        120110106091007,
        120110106103019,
        120110106091023,
        120110106091004,
        120110106011006,
        120110106011000,
        120110106071004,
        120110106091015,
        120110106091022,
        120110106103029,
        120110106011005,
        120110106071000,
        120110106071005,
        120110106011001,
        120110106011007,
        120110106011003,
        120110106103022,
        120110106091009,
        120110106091012,
        120110106091008,
        120110106103018
    ],
    "zs:housing10":2999,
    "zs:pop10":7606
},
  "geometry": {"coordinates":[-80.198981,26.306108],"type":"Point"}
}