{
  "type": "Feature",
  "properties": {
    "gn:gn_country":"US",
    "gn:gn_fcode":"PPLX",
    "gn:gn_pop":0,
    "iso:country":"US",
    "name:ceb_x_preferred":[
        "West Hills"
    ],
    "name:deu_x_preferred":[
        "West Hills"
    ],
    "name:kor_x_preferred":[
        "\uc6e8\uc2a4\ud2b8\ud790\uc2a4"
    ],
    "name:nld_x_preferred":[
        "West Hills"
    ],
    "name:pol_x_preferred":[
        "West Hills"
    ],
    "name:rus_x_preferred":[
        "\u0423\u044d\u0441\u0442-\u0425\u0438\u043b\u043b\u0437"
    ],
    "name:srp_x_preferred":[
        "\u0412\u0435\u0441\u0442 \u0425\u0438\u043b\u0441"
    ],
    "name:vol_x_preferred":[
        "West Hills"
    ],
    "qs_pg:aaroncc":"US",
    "qs_pg:gn_country":"US",
    "qs_pg:gn_fcode":"PPLX",
    "qs_pg:gn_pop":0,
    "qs_pg:name":"West Hills",
    "qs_pg:name_adm0":"United States",
    "qs_pg:name_adm1":"Tennessee",
    "qs_pg:photos":1181,
    "qs_pg:photos_1k":239,
    "qs_pg:photos_9k":5,
    "qs_pg:photos_9r":7,
    "qs_pg:photos_all":1181,
    "qs_pg:photos_sr":11,
    "qs_pg:pop_sr":0,
    "qs_pg:qs_pg_placetype":"neighbourhood",
    "qs_pg:qs_pg_placetype_gp":"Suburb",
    "qs_pg:woe_adm0":23424977,
    "woe:adm0_id":23424977,
    "woe:name_adm0":"United States",
    "woe:name_adm1":"Tennessee",
    "woe:placetype":"Suburb",
    "wof:name":"West Hills",
    "wof:placetype":"neighbourhood"
},
  "geometry": {"coordinates":[-83.35628,36.19815],"type":"Point"}
}