{
  "type": "Feature",
  "properties": {
    "gn:country":"US",
    "gn:fcode":"PPL",
    "gn:population":0,
    "iso:country":"US",
    "name:eng_x_preferred":[
        "Comargo"
    ],
    "name:fra_x_preferred":[
        "Comargo"
    ],
    "name:zho_x_preferred":[
        "\u79d1\u99ac\u6208"
    ],
    "qs_pg:aaroncc":"US",
    "qs_pg:gn_country":"US",
    "qs_pg:gn_fcode":"PPL",
    "qs_pg:gn_pop":0,
    "qs_pg:name":"Comargo",
    "qs_pg:name_adm0":"United States",
    "qs_pg:name_adm1":"Kentucky",
    "qs_pg:photos":60,
    "qs_pg:photos_1k":12,
    "qs_pg:photos_9k":1,
    "qs_pg:photos_9r":2,
    "qs_pg:photos_all":60,
    "qs_pg:photos_sr":2,
    "qs_pg:pop_sr":0,
    "qs_pg:qs_pg_placetype":"locality",
    "qs_pg:qs_pg_placetype_gp":"Town",
    "qs_pg:woe_adm0":23424977,
    "woe:adm0_id":23424977,
    "woe:name_adm0":"United States",
    "woe:name_adm1":"Kentucky",
    "woe:placetype":"Town",
    "wof:name":"Comargo",
    "wof:placetype":"locality"
},
  "geometry": {"coordinates":[-84.54133,36.67758],"type":"Point"}
}