{
  "type": "Feature",
  "properties": {
    "gn:admin1_code":"MO",
    "gn:admin2_code":"71.0",
    "gn:admin3_code":"12754.0",
    "gn:asciiname":"Piney Park",
    "gn:country_code":"US",
    "gn:dem":231,
    "gn:elevation":"227.0",
    "gn:feature_class":"P",
    "gn:feature_code":"PPL",
    "gn:name":"Piney Park",
    "gn:population":0,
    "gn:timezone":"America/Chicago",
    "iso:country":"US",
    "name:eng_x_preferred":[
        "Piney Park"
    ],
    "name:und_x_variant":[
        "Piny Bluff Park",
        "Piney Bluff Park"
    ],
    "wof:name":"Piney Park",
    "wof:placetype":"locality"
},
  "geometry": {"coordinates":[-90.94292,38.30116],"type":"Point"}
}