{
  "type": "Feature",
  "properties": {
    "gn:admin1_code":"VA",
    "gn:admin2_code":"161",
    "gn:asciiname":"Glenvar East",
    "gn:country_code":"US",
    "gn:dem":375,
    "gn:elevation":"378.0",
    "gn:feature_class":"P",
    "gn:feature_code":"PPL",
    "gn:name":"Glenvar East",
    "gn:population":0,
    "gn:timezone":"America/New_York",
    "iso:country":"US",
    "wof:name":"Glenvar East",
    "wof:placetype":"locality"
},
  "geometry": {"coordinates":[-80.13726,37.28208],"type":"Point"}
}