{
  "type": "Feature",
  "properties": {
    "gn:country":"US",
    "gn:elevation":95,
    "gn:fcode":"PPL",
    "gn:population":0,
    "iso:country":"US",
    "name:eng_x_preferred":[
        "Greenway Downs"
    ],
    "qs:gn_adm0_cc":"US",
    "qs:gn_fcode":"PPL",
    "qs:gn_local":4758390,
    "qs:gn_nam_loc":"Falls Church, Falls Church, Virginia, US",
    "qs:gn_namadm1":"VA",
    "qs:gn_name":"Greenway Downs",
    "qs:local_max":1281,
    "qs:local_sum":6475,
    "qs:localhoods":12,
    "qs:name":"Greenway Downs",
    "qs:name_adm0":"United States",
    "qs:name_adm1":"Virginia",
    "qs:name_adm2":"Fairfax",
    "qs:name_local":"Falls Church",
    "qs:photo_max":283,
    "qs:photo_sum":1117,
    "qs:placetype":"Suburb",
    "qs:quad_count":25,
    "qs:woe_adm0":23424977,
    "qs:woe_adm1":2347605,
    "qs:woe_adm2":12590343,
    "qs:woe_lau":0,
    "qs:woe_local":2402144,
    "qs:woe_ver":"7.10.0",
    "qs_pg:aaroncc":"US",
    "qs_pg:gn_country":"US",
    "qs_pg:gn_fcode":"PPL",
    "qs_pg:gn_pop":0,
    "qs_pg:name":"Greenway Downs",
    "qs_pg:name_adm0":"United States",
    "qs_pg:name_adm1":"Virginia",
    "qs_pg:photos":935,
    "qs_pg:photos_1k":189,
    "qs_pg:photos_9k":4,
    "qs_pg:photos_9r":6,
    "qs_pg:photos_all":935,
    "qs_pg:photos_sr":10,
    "qs_pg:pop_sr":0,
    "qs_pg:qs_pg_placetype":"neighbourhood",
    "qs_pg:qs_pg_placetype_gp":"Suburb",
    "qs_pg:woe_adm0":23424977,
    "wd:wordcount":2011,
    "wof:name":"Greenway Downs",
    "wof:placetype":"neighbourhood",
    "wof:population":1160,
    "zs:blockids":[
        516105003001018,
        516105002003018,
        516105003001022,
        516105003001029,
        516105002003016,
        516105002003013,
        516105002003023,
        516105002003021,
        516105002004002,
        516105002003017,
        516105003001006,
        516105002003022,
        516105002003019,
        516105002003026,
        516105002003025,
        516105002003015,
        516105002003012,
        516105001001028,
        516105003001017,
        516105002004014,
        516105003001021,
        516105003001020
    ],
    "zs:housing10":546,
    "zs:pop10":1160
},
  "geometry": {"coordinates":[-77.174696,38.881119],"type":"Point"}
}