{
  "type": "Feature",
  "properties": {
    "gn:admin1_code":"SC",
    "gn:admin2_code":"39.0",
    "gn:asciiname":"Taylors Creek",
    "gn:country_code":"US",
    "gn:dem":80,
    "gn:elevation":"82.0",
    "gn:feature_class":"P",
    "gn:feature_code":"PPL",
    "gn:name":"Taylors Creek",
    "gn:population":0,
    "gn:timezone":"America/New_York",
    "iso:country":"US",
    "wof:name":"Taylors Creek",
    "wof:placetype":"locality"
},
  "geometry": {"coordinates":[-80.88314,34.44265],"type":"Point"}
}