{
  "type": "Feature",
  "properties": {
    "gn:country":"US",
    "gn:fcode":"PPL",
    "gn:population":0,
    "iso:country":"US",
    "name:ceb_x_preferred":[
        "Chat"
    ],
    "name:deu_x_preferred":[
        "Chat"
    ],
    "name:fra_x_preferred":[
        "Chat"
    ],
    "name:nld_x_preferred":[
        "Chatten"
    ],
    "name:oci_x_preferred":[
        "Chat"
    ],
    "name:rus_x_preferred":[
        "\u0427\u0430\u0442"
    ],
    "name:slk_x_preferred":[
        "Chat"
    ],
    "name:swe_x_preferred":[
        "Chat"
    ],
    "name:ukr_x_preferred":[
        "\u0427\u0430\u0442"
    ],
    "qs_pg:aaroncc":"US",
    "qs_pg:gn_country":"US",
    "qs_pg:gn_fcode":"PPL",
    "qs_pg:gn_pop":0,
    "qs_pg:name":"Chat",
    "qs_pg:name_adm0":"United States",
    "qs_pg:name_adm1":"Texas",
    "qs_pg:photos":18,
    "qs_pg:photos_1k":4,
    "qs_pg:photos_9k":1,
    "qs_pg:photos_9r":1,
    "qs_pg:photos_all":18,
    "qs_pg:photos_sr":1,
    "qs_pg:pop_sr":0,
    "qs_pg:qs_pg_placetype":"locality",
    "qs_pg:qs_pg_placetype_gp":"Town",
    "qs_pg:woe_adm0":23424977,
    "woe:adm0_id":23424977,
    "woe:name_adm0":"United States",
    "woe:name_adm1":"Texas",
    "woe:placetype":"Town",
    "wof:name":"Chat",
    "wof:placetype":"locality"
},
  "geometry": {"coordinates":[-97.08973,31.94377],"type":"Point"}
}