{
  "type": "Feature",
  "properties": {
    "iso:country":"US",
    "name:eng_x_preferred":[
        "Leisure World"
    ],
    "wof:name":"Leisure World",
    "wof:placetype":"neighbourhood",
    "zs:area_m":1467097.73006,
    "zs:blockids":[
        60379800071017,
        60379800071002,
        60379800071003,
        60379800071000,
        60375776041001,
        60379800071011,
        60379800071012,
        60379800071004,
        60379800071001
    ],
    "zs:housing10":0,
    "zs:label":"Leisure World",
    "zs:pop10":0
},
  "geometry": {"coordinates":[-118.08396399999999,33.766876],"type":"Point"}
}