{
  "type": "Feature",
  "properties": {
    "gn:elevation":43,
    "iso:country":"US",
    "name:eng_x_preferred":[
        "Hardingville"
    ],
    "name:fra_x_preferred":[
        "Hardingville"
    ],
    "name:und_x_variant":[
        "Red Lion"
    ],
    "qs:gn_adm0_cc":"US",
    "qs:gn_fcode":"PPL",
    "qs:gn_local":4354193,
    "qs:gn_nam_loc":"elk",
    "qs:gn_namadm1":"NJ",
    "qs:gn_name":"Hardingville",
    "qs:local_max":187,
    "qs:local_sum":187,
    "qs:localhoods":1,
    "qs:name":"Hardingville",
    "qs:name_adm0":"United States",
    "qs:name_adm1":"New Jersey",
    "qs:name_adm2":"Gloucester",
    "qs:name_local":"Elk",
    "qs:photo_max":185,
    "qs:photo_sum":187,
    "qs:placetype":"Suburb",
    "qs:quad_count":3,
    "qs:woe_adm0":23424977,
    "qs:woe_adm1":2347589,
    "qs:woe_adm2":12589265,
    "qs:woe_lau":0,
    "qs:woe_local":28745332,
    "qs:woe_ver":"7.10.0",
    "wd:wordcount":37,
    "wof:lang":[
        "eng"
    ],
    "wof:name":"Hardingville",
    "wof:placetype":"neighbourhood",
    "wof:population":369,
    "zs:blockids":[
        340155019003023,
        340155019003015,
        340155019001000,
        340155019002048,
        340155019003020,
        340155019002014,
        340155019002045,
        340155019003021,
        340155019003024,
        340155019002049,
        340155019001001,
        340155019003026,
        340155019003014,
        340155019002046
    ],
    "zs:housing10":139,
    "zs:pop10":369
},
  "geometry": {"coordinates":[-75.148139,39.672146],"type":"Point"}
}