{
  "type": "Feature",
  "properties": {
    "gn:admin1_code":"AR",
    "gn:admin2_code":"123.0",
    "gn:admin3_code":"92340.0",
    "gn:asciiname":"Crow Creek",
    "gn:country_code":"US",
    "gn:dem":70,
    "gn:elevation":"72.0",
    "gn:feature_class":"P",
    "gn:feature_code":"PPL",
    "gn:name":"Crow Creek",
    "gn:population":0,
    "gn:timezone":"America/Chicago",
    "iso:country":"US",
    "name:ceb_x_preferred":[
        "Crow Creek"
    ],
    "name:spa_x_preferred":[
        "Crow Creek"
    ],
    "name:swe_x_preferred":[
        "Crow Creek"
    ],
    "wof:name":"Crow Creek",
    "wof:placetype":"locality"
},
  "geometry": {"coordinates":[-90.73650000000001,35.01259],"type":"Point"}
}