{
  "type": "Feature",
  "properties": {
    "gn:admin1_code":"MD",
    "gn:admin2_code":"29.0",
    "gn:asciiname":"Bigwoods",
    "gn:country_code":"US",
    "gn:dem":22,
    "gn:elevation":"22.0",
    "gn:feature_class":"P",
    "gn:feature_code":"PPL",
    "gn:name":"Bigwoods",
    "gn:population":0,
    "gn:timezone":"America/New_York",
    "iso:country":"US",
    "wof:name":"Bigwoods",
    "wof:placetype":"locality"
},
  "geometry": {"coordinates":[-76.04245,39.28567],"type":"Point"}
}