{
  "type": "Feature",
  "properties": {
    "iso:country":"US",
    "name:eng_x_preferred":[
        "Saylor Heights"
    ],
    "wof:name":"Saylor Heights",
    "wof:placetype":"neighbourhood",
    "wof:population":964,
    "zs:area_m":1124634.287141,
    "zs:blockids":[
        191530102031022,
        191530105004008,
        191530102031028,
        191530102031057,
        191530102031104,
        191530102031027,
        191530102031061,
        191530102031058,
        191530102031026,
        191530102031062,
        191530105004025,
        191530102031107,
        191530102031105,
        191530102031103,
        191530102031106,
        191530102031025
    ],
    "zs:housing10":348,
    "zs:label":"Saylor Heights",
    "zs:pop10":964
},
  "geometry": {"coordinates":[-93.624365,41.691923],"type":"Point"}
}