{
  "type": "Feature",
  "properties": {
    "gn:admin1_code":"MO",
    "gn:admin2_code":"139.0",
    "gn:admin3_code":"44228.0",
    "gn:asciiname":"Egbert",
    "gn:country_code":"US",
    "gn:dem":273,
    "gn:elevation":"273.0",
    "gn:feature_class":"P",
    "gn:feature_code":"PPL",
    "gn:name":"Egbert",
    "gn:population":0,
    "gn:timezone":"America/Chicago",
    "iso:country":"US",
    "name:jpn_x_preferred":[
        "\u30a8\u30b0\u30d0\u30fc\u30c8"
    ],
    "name:nld_x_preferred":[
        "Egbert"
    ],
    "name:pol_x_preferred":[
        "Egbert"
    ],
    "wof:name":"Egbert",
    "wof:placetype":"locality"
},
  "geometry": {"coordinates":[-91.6335,38.75977],"type":"Point"}
}