{
  "type": "Feature",
  "properties": {
    "gn:country":"US",
    "gn:fcode":"PPL",
    "gn:population":0,
    "iso:country":"US",
    "name:ara_x_preferred":[
        "\u0628\u0648\u0646\u0627\u0644"
    ],
    "name:cat_x_preferred":[
        "Pownal"
    ],
    "name:che_x_preferred":[
        "\u041f\u0430\u0443\u043d\u0430\u043b"
    ],
    "name:cym_x_preferred":[
        "Pownal"
    ],
    "name:deu_x_preferred":[
        "Pownal"
    ],
    "name:eng_x_preferred":[
        "Pownal"
    ],
    "name:eus_x_preferred":[
        "Pownal"
    ],
    "name:fra_x_preferred":[
        "Pownal"
    ],
    "name:hat_x_preferred":[
        "Pownal"
    ],
    "name:ita_x_preferred":[
        "Pownal"
    ],
    "name:jpn_x_preferred":[
        "\u30dd\u30fc\u30ca\u30eb"
    ],
    "name:lld_x_preferred":[
        "Pownal"
    ],
    "name:pol_x_preferred":[
        "Pownal"
    ],
    "name:spa_x_preferred":[
        "Pownal"
    ],
    "name:swe_x_preferred":[
        "Pownal"
    ],
    "name:tat_x_preferred":[
        "\u041f\u0430\u0443\u043d\u0430\u043b"
    ],
    "name:tur_x_preferred":[
        "Pownal"
    ],
    "name:ukr_x_preferred":[
        "\u041f\u0430\u0443\u043d\u0430\u043b"
    ],
    "name:uzb_x_preferred":[
        "Pownal"
    ],
    "name:vol_x_preferred":[
        "Pownal"
    ],
    "name:vol_x_variant":[
        "Epworth Heights"
    ],
    "qs_pg:aaroncc":"US",
    "qs_pg:gn_country":"US",
    "qs_pg:gn_fcode":"PPL",
    "qs_pg:gn_pop":0,
    "qs_pg:name":"Pownal",
    "qs_pg:name_adm0":"United States",
    "qs_pg:name_adm1":"Vermont",
    "qs_pg:photos":447,
    "qs_pg:photos_1k":91,
    "qs_pg:photos_9k":2,
    "qs_pg:photos_9r":5,
    "qs_pg:photos_all":447,
    "qs_pg:photos_sr":6,
    "qs_pg:pop_sr":5,
    "qs_pg:qs_pg_placetype":"locality",
    "qs_pg:qs_pg_placetype_gp":"Town",
    "qs_pg:woe_adm0":23424977,
    "woe:adm0_id":23424977,
    "woe:name_adm0":"United States",
    "woe:name_adm1":"Vermont",
    "woe:placetype":"Town",
    "wof:coterminous":[
        404527471
    ],
    "wof:name":"Pownal",
    "wof:placetype":"locality",
    "wof:population":3460,
    "wof:statistical_gore":1
},
  "geometry": {"coordinates":[-73.23594,42.76564],"type":"Point"}
}