{
  "type": "Feature",
  "properties": {
    "gn:admin1_code":"LA",
    "gn:admin2_code":"77.0",
    "gn:asciiname":"Williamsport",
    "gn:country_code":"US",
    "gn:dem":20,
    "gn:elevation":"15.0",
    "gn:feature_class":"P",
    "gn:feature_code":"PPL",
    "gn:name":"Williamsport",
    "gn:population":0,
    "gn:timezone":"America/Chicago",
    "iso:country":"US",
    "name:ara_x_preferred":[
        "\u0648\u064a\u0644\u064a\u0627\u0645\u0633\u0628\u0648\u0631\u062a"
    ],
    "name:ben_x_preferred":[
        "\u0989\u0987\u09b2\u09bf\u09df\u09be\u09ae\u09b8\u09cd\u09aa\u09cb\u09b0\u09cd\u099f"
    ],
    "name:ceb_x_preferred":[
        "Williamsport"
    ],
    "name:deu_x_preferred":[
        "Williamsport"
    ],
    "name:fra_x_preferred":[
        "Williamsport"
    ],
    "name:hin_x_preferred":[
        "\u0935\u093f\u0932\u093f\u092f\u092e\u0938\u094d\u092a\u094b\u0930\u094d\u091f"
    ],
    "name:ido_x_preferred":[
        "Williamsport"
    ],
    "name:ind_x_preferred":[
        "Williamsport"
    ],
    "name:ita_x_preferred":[
        "Williamsport"
    ],
    "name:jpn_x_preferred":[
        "\u30a6\u30a3\u30ea\u30a2\u30e0\u30ba\u30dd\u30fc\u30c8"
    ],
    "name:kor_x_preferred":[
        "\uc70c\ub9ac\uc5c4\uc2a4\ud3ec\ud2b8"
    ],
    "name:nld_x_preferred":[
        "Williamsport"
    ],
    "name:pol_x_preferred":[
        "Williamsport"
    ],
    "name:rus_x_preferred":[
        "\u0423\u0438\u043b\u044c\u044f\u043c\u0441\u043f\u043e\u0440\u0442"
    ],
    "name:spa_x_preferred":[
        "Williamsport"
    ],
    "name:srp_x_preferred":[
        "\u0412\u0438\u043b\u0438\u0458\u0430\u043c\u0441\u043f\u043e\u0440\u0442"
    ],
    "name:swe_x_preferred":[
        "Williamsport"
    ],
    "name:urd_x_preferred":[
        "\u0648\u0644\u06cc\u0645\u0632\u067e\u0648\u0631\u0679"
    ],
    "name:vol_x_preferred":[
        "Williamsport"
    ],
    "wof:name":"Williamsport",
    "wof:placetype":"locality"
},
  "geometry": {"coordinates":[-91.66734,30.89518],"type":"Point"}
}