{
  "type": "Feature",
  "properties": {
    "gn:admin1_code":"VA",
    "gn:admin2_code":"33",
    "gn:asciiname":"Jones Corner",
    "gn:country_code":"US",
    "gn:dem":60,
    "gn:elevation":"57.0",
    "gn:feature_class":"P",
    "gn:feature_code":"PPL",
    "gn:name":"Jones Corner",
    "gn:population":0,
    "gn:timezone":"America/New_York",
    "iso:country":"US",
    "wof:name":"Jones Corner",
    "wof:placetype":"locality"
},
  "geometry": {"coordinates":[-77.19109,38.0268],"type":"Point"}
}