{
  "type": "Feature",
  "properties": {
    "gn:admin1_code":"MD",
    "gn:admin2_code":"43.0",
    "gn:asciiname":"Fortney Mobile Home Park",
    "gn:country_code":"US",
    "gn:dem":198,
    "gn:elevation":"200.0",
    "gn:feature_class":"P",
    "gn:feature_code":"PPL",
    "gn:name":"Fortney Mobile Home Park",
    "gn:population":0,
    "gn:timezone":"America/New_York",
    "iso:country":"US",
    "wof:name":"Fortney Mobile Home Park",
    "wof:placetype":"campus"
},
  "geometry": {"coordinates":[-77.7186,39.70537],"type":"Point"}
}