{
  "type": "Feature",
  "properties": {
    "gn:admin1_code":"KY",
    "gn:admin2_code":"99",
    "gn:asciiname":"Glen Lily",
    "gn:country_code":"US",
    "gn:dem":195,
    "gn:elevation":"192.0",
    "gn:feature_class":"P",
    "gn:feature_code":"PPL",
    "gn:name":"Glen Lily",
    "gn:population":0,
    "gn:timezone":"America/Chicago",
    "iso:country":"US",
    "wof:name":"Glen Lily",
    "wof:placetype":"locality"
},
  "geometry": {"coordinates":[-85.79441,37.30783],"type":"Point"}
}