{
  "type": "Feature",
  "properties": {
    "gn:admin1_code":"VT",
    "gn:admin2_code":"21.0",
    "gn:admin3_code":"61300.0",
    "gn:asciiname":"Pinecrest Acres",
    "gn:country_code":"US",
    "gn:dem":259,
    "gn:elevation":"262.0",
    "gn:feature_class":"P",
    "gn:feature_code":"PPL",
    "gn:name":"Pinecrest Acres",
    "gn:population":0,
    "gn:timezone":"America/New_York",
    "iso:country":"US",
    "wof:name":"Pinecrest Acres",
    "wof:placetype":"locality"
},
  "geometry": {"coordinates":[-72.95594,43.65368],"type":"Point"}
}