{
  "type": "Feature",
  "properties": {
    "gn:admin1_code":"MS",
    "gn:admin2_code":"87.0",
    "gn:asciiname":"Penns",
    "gn:country_code":"US",
    "gn:dem":93,
    "gn:elevation":"89.0",
    "gn:feature_class":"P",
    "gn:feature_code":"PPL",
    "gn:name":"Penns",
    "gn:population":0,
    "gn:timezone":"America/Chicago",
    "iso:country":"US",
    "name:eng_x_preferred":[
        "Penns"
    ],
    "name:und_x_variant":[
        "Penns Station",
        "Penn"
    ],
    "name:vol_x_preferred":[
        "Penns"
    ],
    "wof:name":"Penns",
    "wof:placetype":"locality"
},
  "geometry": {"coordinates":[-88.63588,33.35234000000001],"type":"Point"}
}