{
  "type": "Feature",
  "properties": {
    "gn:admin1_code":"LA",
    "gn:admin2_code":"81.0",
    "gn:asciiname":"Harmon",
    "gn:country_code":"US",
    "gn:dem":46,
    "gn:elevation":"42.0",
    "gn:feature_class":"P",
    "gn:feature_code":"PPL",
    "gn:name":"Harmon",
    "gn:population":0,
    "gn:timezone":"America/Chicago",
    "iso:country":"US",
    "wof:name":"Harmon",
    "wof:placetype":"locality"
},
  "geometry": {"coordinates":[-93.43044999999999,32.06599],"type":"Point"}
}