{
  "type": "Feature",
  "properties": {
    "gn:country":"US",
    "gn:fcode":"PPL",
    "gn:population":0,
    "iso:country":"US",
    "name:ara_x_preferred":[
        "\u0647\u0627\u064a\u0632"
    ],
    "name:ben_x_preferred":[
        "\u09b9\u09c7\u099c"
    ],
    "name:ell_x_preferred":[
        "\u03a7\u03ad\u03b9\u03c2"
    ],
    "name:eng_x_preferred":[
        "Hayes"
    ],
    "name:fra_x_preferred":[
        "Hayes"
    ],
    "name:hin_x_preferred":[
        "\u0939\u0947\u0938"
    ],
    "name:hun_x_preferred":[
        "Hayes"
    ],
    "name:ind_x_preferred":[
        "Hayes"
    ],
    "name:kor_x_preferred":[
        "\ud5e4\uc774\uc988"
    ],
    "name:tur_x_preferred":[
        "Hayes"
    ],
    "name:urd_x_preferred":[
        "\u06c1\u0627\u0626\u06cc\u0633"
    ],
    "name:vie_x_preferred":[
        "S\u00f4ng Hayes"
    ],
    "name:zho_cn_x_preferred":[
        "\u6d77\u8036\u65af\u6cb3"
    ],
    "name:zho_tw_x_preferred":[
        "\u6d77\u4f0a\u65af\u6cb3"
    ],
    "qs_pg:aaroncc":"US",
    "qs_pg:gn_country":"US",
    "qs_pg:gn_fcode":"PPL",
    "qs_pg:gn_pop":0,
    "qs_pg:name":"Hayes",
    "qs_pg:name_adm0":"United States",
    "qs_pg:name_adm1":"Illinois",
    "qs_pg:photos":15,
    "qs_pg:photos_1k":3,
    "qs_pg:photos_9k":1,
    "qs_pg:photos_9r":1,
    "qs_pg:photos_all":15,
    "qs_pg:photos_sr":1,
    "qs_pg:pop_sr":0,
    "qs_pg:qs_pg_placetype":"locality",
    "qs_pg:qs_pg_placetype_gp":"Town",
    "qs_pg:woe_adm0":23424977,
    "woe:adm0_id":23424977,
    "woe:name_adm0":"United States",
    "woe:name_adm1":"Illinois",
    "woe:placetype":"Town",
    "wof:name":"Hayes",
    "wof:placetype":"locality"
},
  "geometry": {"coordinates":[-88.28116,39.86253],"type":"Point"}
}