{
  "type": "Feature",
  "properties": {
    "gn:admin1_code":"AK",
    "gn:admin2_code":"20.0",
    "gn:asciiname":"Anchor Terrace",
    "gn:country_code":"US",
    "gn:dem":29,
    "gn:elevation":"9.0",
    "gn:feature_class":"P",
    "gn:feature_code":"PPL",
    "gn:name":"Anchor Terrace",
    "gn:population":0,
    "gn:timezone":"America/Anchorage",
    "iso:country":"US",
    "wof:name":"Anchor Terrace",
    "wof:placetype":"locality"
},
  "geometry": {"coordinates":[-149.89444,61.20278],"type":"Point"}
}