{
  "type": "Feature",
  "properties": {
    "gn:admin1_code":"MD",
    "gn:admin2_code":"19.0",
    "gn:asciiname":"Riverton",
    "gn:country_code":"US",
    "gn:dem":1,
    "gn:elevation":"1.0",
    "gn:feature_class":"P",
    "gn:feature_code":"PPL",
    "gn:name":"Riverton",
    "gn:population":0,
    "gn:timezone":"America/New_York",
    "iso:country":"US",
    "name:ara_x_preferred":[
        "\u0631\u064a\u0641\u0631\u062a\u0648\u0646"
    ],
    "name:ceb_x_preferred":[
        "Riverton"
    ],
    "name:ces_x_preferred":[
        "Riverton"
    ],
    "name:deu_x_preferred":[
        "Riverton"
    ],
    "name:fin_x_preferred":[
        "Riverton"
    ],
    "name:fra_x_preferred":[
        "Riverton"
    ],
    "name:heb_x_preferred":[
        "\u05e8\u05d9\u05d1\u05e8\u05d8\u05d5\u05df"
    ],
    "name:isl_x_preferred":[
        "Riverton"
    ],
    "name:ita_x_preferred":[
        "Riverton"
    ],
    "name:kor_x_preferred":[
        "\ub9ac\ubc84\ud134"
    ],
    "name:nld_x_preferred":[
        "Riverton"
    ],
    "name:pol_x_preferred":[
        "Riverton"
    ],
    "name:por_x_preferred":[
        "Riverton"
    ],
    "name:rus_x_preferred":[
        "\u0420\u0438\u0432\u0435\u0440\u0442\u043e\u043d"
    ],
    "name:spa_x_preferred":[
        "Riverton"
    ],
    "name:srp_x_preferred":[
        "\u0420\u0438\u0432\u0435\u0440\u0442\u043e\u043d"
    ],
    "name:swe_x_preferred":[
        "Riverton"
    ],
    "name:urd_x_preferred":[
        "\u0631\u06cc\u0648\u0631\u0679\u0646"
    ],
    "name:vol_x_preferred":[
        "Riverton"
    ],
    "name:zho_x_preferred":[
        "\u91cc\u5f17\u987f"
    ],
    "wof:name":"Riverton",
    "wof:placetype":"locality"
},
  "geometry": {"coordinates":[-76.248,38.5779],"type":"Point"}
}