{
  "type": "Feature",
  "properties": {
    "gn:admin1_code":"OH",
    "gn:admin2_code":"161.0",
    "gn:admin3_code":"43372.0",
    "gn:asciiname":"Stemen's Mobile Manor",
    "gn:country_code":"US",
    "gn:dem":249,
    "gn:elevation":"248.0",
    "gn:feature_class":"P",
    "gn:feature_code":"PPL",
    "gn:name":"Stemen's Mobile Manor",
    "gn:population":0,
    "gn:timezone":"America/New_York",
    "iso:country":"US",
    "wof:name":"Stemen's Mobile Manor",
    "wof:placetype":"locality"
},
  "geometry": {"coordinates":[-84.60833000000002,40.77278],"type":"Point"}
}