{
  "type": "Feature",
  "properties": {
    "iso:country":"US",
    "name:eng_x_preferred":[
        "Schilling Addition"
    ],
    "wof:name":"Schilling Addition",
    "wof:placetype":"neighbourhood",
    "wof:population":21,
    "zs:area_m":48064.672474,
    "zs:blockids":[
        540879630002022,
        540879630004024
    ],
    "zs:housing10":14,
    "zs:label":"Schilling Addition",
    "zs:pop10":21
},
  "geometry": {"coordinates":[-81.35124,38.802959],"type":"Point"}
}