{
  "type": "Feature",
  "properties": {
    "gn:admin1_code":"AR",
    "gn:admin2_code":"117.0",
    "gn:admin3_code":"91698.0",
    "gn:asciiname":"Hickory Plains",
    "gn:country_code":"US",
    "gn:dem":77,
    "gn:elevation":"76.0",
    "gn:feature_class":"P",
    "gn:feature_code":"PPL",
    "gn:name":"Hickory Plains",
    "gn:population":0,
    "gn:timezone":"America/Chicago",
    "iso:country":"US",
    "name:fas_x_preferred":[
        "\u0647\u06cc\u06a9\u0648\u0631\u06cc \u067e\u0644\u06cc\u0646\u0632"
    ],
    "name:zho_x_preferred":[
        "\u5e0c\u79d1\u91cc\u666e\u840a\u6069\u65af"
    ],
    "wof:name":"Hickory Plains",
    "wof:placetype":"locality"
},
  "geometry": {"coordinates":[-91.7368,34.99009],"type":"Point"}
}