{
  "type": "Feature",
  "properties": {
    "gn:admin1_code":"KY",
    "gn:admin2_code":"93",
    "gn:asciiname":"Old Stephensburg",
    "gn:country_code":"US",
    "gn:dem":209,
    "gn:elevation":"209.0",
    "gn:feature_class":"P",
    "gn:feature_code":"PPL",
    "gn:name":"Old Stephensburg",
    "gn:population":0,
    "gn:timezone":"America/New_York",
    "iso:country":"US",
    "wof:name":"Old Stephensburg",
    "wof:placetype":"locality"
},
  "geometry": {"coordinates":[-86.02024,37.61451],"type":"Point"}
}