{
  "type": "Feature",
  "properties": {
    "gn:country":"US",
    "gn:fcode":"PPL",
    "gn:population":0,
    "iso:country":"US",
    "name:azb_x_preferred":[
        "\u0686\u0646\u0633\u0644\u0631\u0632\u0648\u06cc\u0644"
    ],
    "name:eng_x_preferred":[
        "Chancellorsville"
    ],
    "name:fas_x_preferred":[
        "\u0686\u0646\u0633\u0644\u0631\u0632\u0648\u06cc\u0644"
    ],
    "name:fra_x_preferred":[
        "Chancellorsville"
    ],
    "name:nld_x_preferred":[
        "Chancellorsville"
    ],
    "name:nob_x_preferred":[
        "Chancellorsville"
    ],
    "name:swe_x_preferred":[
        "Chancellorsville"
    ],
    "name:vol_x_preferred":[
        "Chancellorsville"
    ],
    "qs_pg:aaroncc":"US",
    "qs_pg:gn_country":"US",
    "qs_pg:gn_fcode":"PPL",
    "qs_pg:gn_pop":0,
    "qs_pg:name":"Chancellorsville",
    "qs_pg:name_adm0":"United States",
    "qs_pg:name_adm1":"Virginia",
    "qs_pg:photos":303,
    "qs_pg:photos_1k":61,
    "qs_pg:photos_9k":1,
    "qs_pg:photos_9r":5,
    "qs_pg:photos_all":303,
    "qs_pg:photos_sr":5,
    "qs_pg:pop_sr":0,
    "qs_pg:qs_pg_placetype":"locality",
    "qs_pg:qs_pg_placetype_gp":"Town",
    "qs_pg:woe_adm0":23424977,
    "woe:adm0_id":23424977,
    "woe:name_adm0":"United States",
    "woe:name_adm1":"Virginia",
    "woe:placetype":"Town",
    "wof:name":"Chancellorsville",
    "wof:placetype":"locality"
},
  "geometry": {"coordinates":[-77.63442999999999,38.30846],"type":"Point"}
}