{
  "type": "Feature",
  "properties": {
    "gn:admin1_code":"MD",
    "gn:admin2_code":"27.0",
    "gn:asciiname":"West Elkridge",
    "gn:country_code":"US",
    "gn:dem":70,
    "gn:elevation":"67.0",
    "gn:feature_class":"P",
    "gn:feature_code":"PPL",
    "gn:name":"West Elkridge",
    "gn:population":28734,
    "gn:timezone":"America/New_York",
    "iso:country":"US",
    "wof:name":"West Elkridge",
    "wof:placetype":"locality",
    "wof:population":28734
},
  "geometry": {"coordinates":[-76.72691999999998,39.20705],"type":"Point"}
}