{
  "type": "Feature",
  "properties": {
    "gn:admin1_code":"OK",
    "gn:admin2_code":"131.0",
    "gn:asciiname":"Oowala",
    "gn:country_code":"US",
    "gn:dem":204,
    "gn:elevation":"206.0",
    "gn:feature_class":"P",
    "gn:feature_code":"PPL",
    "gn:name":"Oowala",
    "gn:population":0,
    "gn:timezone":"America/Chicago",
    "iso:country":"US",
    "wof:name":"Oowala",
    "wof:placetype":"locality"
},
  "geometry": {"coordinates":[-95.6147,36.42343],"type":"Point"}
}