{
  "type": "Feature",
  "properties": {
    "gn:admin1_code":"MO",
    "gn:admin2_code":"221.0",
    "gn:admin3_code":"75040.0",
    "gn:asciiname":"Robidoux",
    "gn:country_code":"US",
    "gn:dem":243,
    "gn:elevation":"241.0",
    "gn:feature_class":"P",
    "gn:feature_code":"PPL",
    "gn:name":"Robidoux",
    "gn:population":0,
    "gn:timezone":"America/Chicago",
    "iso:country":"US",
    "wof:name":"Robidoux",
    "wof:placetype":"locality"
},
  "geometry": {"coordinates":[-90.76846,38.05227],"type":"Point"}
}