{
  "type": "Feature",
  "properties": {
    "gn:gn_country":"US",
    "gn:gn_fcode":"PPL",
    "gn:gn_pop":0,
    "iso:country":"US",
    "name:ceb_x_preferred":[
        "Gaylord"
    ],
    "name:deu_x_preferred":[
        "Gaylord"
    ],
    "name:fra_x_preferred":[
        "Gaylord"
    ],
    "name:ita_x_preferred":[
        "Gaylord"
    ],
    "name:kor_x_preferred":[
        "\uac8c\uc77c\ub85c\ub4dc"
    ],
    "name:nld_x_preferred":[
        "Gaylord"
    ],
    "name:pol_x_preferred":[
        "Gaylord"
    ],
    "name:por_x_preferred":[
        "Gaylord"
    ],
    "name:spa_x_preferred":[
        "Gaylord"
    ],
    "name:srp_x_preferred":[
        "\u0413\u0435\u0458\u043b\u043e\u0440\u0434"
    ],
    "name:ukr_x_preferred":[
        "\u0413\u0435\u0439\u043b\u043e\u0440\u0434"
    ],
    "name:vol_x_preferred":[
        "Gaylord"
    ],
    "qs_pg:aaroncc":"US",
    "qs_pg:gn_country":"US",
    "qs_pg:gn_fcode":"PPL",
    "qs_pg:gn_pop":0,
    "qs_pg:name":"Gaylord",
    "qs_pg:name_adm0":"United States",
    "qs_pg:name_adm1":"Texas",
    "qs_pg:photos":53,
    "qs_pg:photos_1k":11,
    "qs_pg:photos_9k":1,
    "qs_pg:photos_9r":2,
    "qs_pg:photos_all":53,
    "qs_pg:photos_sr":2,
    "qs_pg:pop_sr":0,
    "qs_pg:qs_pg_placetype":"locality",
    "qs_pg:qs_pg_placetype_gp":"Town",
    "qs_pg:woe_adm0":23424977,
    "woe:adm0_id":23424977,
    "woe:name_adm0":"United States",
    "woe:name_adm1":"Texas",
    "woe:placetype":"Town",
    "wof:name":"Gaylord",
    "wof:placetype":"locality"
},
  "geometry": {"coordinates":[-100.44070000000001,36.4417],"type":"Point"}
}