{
  "type": "Feature",
  "properties": {
    "gn:admin1_code":"FL",
    "gn:admin2_code":"61.0",
    "gn:asciiname":"Fischer's Corner Trailer Park",
    "gn:country_code":"US",
    "gn:dem":10,
    "gn:elevation":"3.0",
    "gn:feature_class":"P",
    "gn:feature_code":"PPL",
    "gn:name":"Fischer's Corner Trailer Park",
    "gn:population":0,
    "gn:timezone":"America/New_York",
    "iso:country":"US",
    "wof:name":"Fischer's Corner Trailer Park",
    "wof:placetype":"campus"
},
  "geometry": {"coordinates":[-80.45699999999999,27.7904],"type":"Point"}
}