{
  "type": "Feature",
  "properties": {
    "gn:admin1_code":"PA",
    "gn:admin2_code":"73.0",
    "gn:admin3_code":"53064.0",
    "gn:asciiname":"Sunset Valley",
    "gn:country_code":"US",
    "gn:dem":282,
    "gn:elevation":"276.0",
    "gn:feature_class":"P",
    "gn:feature_code":"PPL",
    "gn:name":"Sunset Valley",
    "gn:population":0,
    "gn:timezone":"America/New_York",
    "iso:country":"US",
    "wof:name":"Sunset Valley",
    "wof:placetype":"locality"
},
  "geometry": {"coordinates":[-80.30923,41.06756],"type":"Point"}
}