{
  "type": "Feature",
  "properties": {
    "gn:admin1_code":"AR",
    "gn:admin2_code":"123.0",
    "gn:admin3_code":"91680.0",
    "gn:asciiname":"Greasy Corner",
    "gn:country_code":"US",
    "gn:dem":61,
    "gn:elevation":"61.0",
    "gn:feature_class":"P",
    "gn:feature_code":"PPL",
    "gn:name":"Greasy Corner",
    "gn:population":0,
    "gn:timezone":"America/Chicago",
    "iso:country":"US",
    "name:eng_x_preferred":[
        "Greasy Corner"
    ],
    "name:fas_x_preferred":[
        "\u06af\u0631\u06cc\u0633\u06cc \u06a9\u0648\u0631\u0646\u0631"
    ],
    "name:und_x_variant":[
        "Mack's Corner"
    ],
    "name:zho_x_preferred":[
        "\u683c\u91cc\u897f\u79d1\u7d0d"
    ],
    "wof:name":"Greasy Corner",
    "wof:placetype":"locality"
},
  "geometry": {"coordinates":[-90.44843,35.00732],"type":"Point"}
}