{
  "type": "Feature",
  "properties": {
    "gn:admin1_code":"TN",
    "gn:admin2_code":"63",
    "gn:asciiname":"Panther Lake",
    "gn:country_code":"US",
    "gn:dem":386,
    "gn:elevation":"382.0",
    "gn:feature_class":"P",
    "gn:feature_code":"PPL",
    "gn:name":"Panther Lake",
    "gn:population":0,
    "gn:timezone":"America/New_York",
    "iso:country":"US",
    "wof:name":"Panther Lake",
    "wof:placetype":"locality"
},
  "geometry": {"coordinates":[-83.38767,36.19287],"type":"Point"}
}