{
  "type": "Feature",
  "properties": {
    "gn:country":"US",
    "gn:fcode":"PPL",
    "gn:population":0,
    "iso:country":"US",
    "name:azb_x_preferred":[
        "\u0628\u0644\u0627\u0641 \u062f\u06cc\u0644"
    ],
    "name:eng_x_preferred":[
        "Bluff Dale"
    ],
    "name:fas_x_preferred":[
        "\u0628\u0644\u0627\u0641 \u062f\u06cc\u0644"
    ],
    "name:fra_x_preferred":[
        "Bluff Dale"
    ],
    "name:lld_x_preferred":[
        "Bluff Dale"
    ],
    "name:vol_x_preferred":[
        "Bluff Dale"
    ],
    "name:zho_x_preferred":[
        "\u5e03\u62c9\u592b\u6234\u5c14"
    ],
    "qs_pg:aaroncc":"US",
    "qs_pg:gn_country":"US",
    "qs_pg:gn_fcode":"PPL",
    "qs_pg:gn_pop":0,
    "qs_pg:name":"Bluff Dale",
    "qs_pg:name_adm0":"United States",
    "qs_pg:name_adm1":"Texas",
    "qs_pg:photos":162,
    "qs_pg:photos_1k":33,
    "qs_pg:photos_9k":1,
    "qs_pg:photos_9r":4,
    "qs_pg:photos_all":162,
    "qs_pg:photos_sr":4,
    "qs_pg:pop_sr":5,
    "qs_pg:qs_pg_placetype":"locality",
    "qs_pg:qs_pg_placetype_gp":"Town",
    "qs_pg:woe_adm0":23424977,
    "woe:adm0_id":23424977,
    "woe:name_adm0":"United States",
    "woe:name_adm1":"Texas",
    "woe:placetype":"Town",
    "wof:name":"Bluff Dale",
    "wof:placetype":"locality"
},
  "geometry": {"coordinates":[-98.02143,32.35097],"type":"Point"}
}