{
  "type": "Feature",
  "properties": {
    "gn:admin1_code":"MD",
    "gn:admin2_code":"45.0",
    "gn:asciiname":"Hampton Court",
    "gn:country_code":"US",
    "gn:dem":20,
    "gn:elevation":"18.0",
    "gn:feature_class":"P",
    "gn:feature_code":"PPL",
    "gn:name":"Hampton Court",
    "gn:population":0,
    "gn:timezone":"America/New_York",
    "iso:country":"US",
    "wof:name":"Hampton Court",
    "wof:placetype":"locality"
},
  "geometry": {"coordinates":[-75.49769999999999,38.44151],"type":"Point"}
}