{
  "type": "Feature",
  "properties": {
    "gn:admin1_code":"GA",
    "gn:admin2_code":"245",
    "gn:asciiname":"Rain Tree",
    "gn:country_code":"US",
    "gn:dem":132,
    "gn:elevation":"128.0",
    "gn:feature_class":"P",
    "gn:feature_code":"PPL",
    "gn:name":"Rain Tree",
    "gn:population":0,
    "gn:timezone":"America/New_York",
    "iso:country":"US",
    "wof:name":"Rain Tree",
    "wof:placetype":"locality"
},
  "geometry": {"coordinates":[-82.07011999999997,33.3732],"type":"Point"}
}