{
  "type": "Feature",
  "properties": {
    "iso:country":"US",
    "name:eng_x_preferred":[
        "Lakeside Manor"
    ],
    "wof:name":"Lakeside Manor",
    "wof:placetype":"neighbourhood",
    "wof:population":274,
    "zs:area_m":183908.332598,
    "zs:blockids":[
        240450002001027,
        240450002001016,
        240450002001005,
        240450002001023,
        240450002001003,
        240450002001024,
        240450002001017
    ],
    "zs:housing10":111,
    "zs:label":"Lakeside Manor",
    "zs:pop10":274
},
  "geometry": {"coordinates":[-75.593126,38.379005],"type":"Point"}
}