{
  "type": "Feature",
  "properties": {
    "gn:elevation":6,
    "iso:country":"US",
    "name:eng_x_preferred":[
        "Shimmo"
    ],
    "name:und_x_variant":[
        "Shimmoah"
    ],
    "qs:gn_adm0_cc":"US",
    "qs:gn_fcode":"PPL",
    "qs:gn_local":4944986,
    "qs:gn_nam_loc":"fieldston",
    "qs:gn_namadm1":"MA",
    "qs:gn_name":"Shimmo",
    "qs:local_max":3195,
    "qs:local_sum":4690,
    "qs:localhoods":23,
    "qs:name":"Shimmo",
    "qs:name_adm0":"United States",
    "qs:name_adm1":"Massachusetts",
    "qs:name_adm2":"Nantucket",
    "qs:name_local":"Nantucket",
    "qs:photo_max":147,
    "qs:photo_sum":302,
    "qs:placetype":"Suburb",
    "qs:quad_count":12,
    "qs:woe_adm0":23424977,
    "qs:woe_adm1":2347580,
    "qs:woe_adm2":12588709,
    "qs:woe_lau":0,
    "qs:woe_local":2456968,
    "qs:woe_ver":"7.10.0",
    "wof:lang":[
        "eng"
    ],
    "wof:name":"Shimmo",
    "wof:placetype":"neighbourhood",
    "wof:population":173,
    "zs:blockids":[
        250199505002159,
        250199505002275,
        250199505002165,
        250199505002133,
        250199505002263,
        250199505002164,
        250199505002204,
        250199505002130,
        250199505002167,
        250199505002262,
        250199505002123,
        250199505002166,
        250199504002008,
        250199505002150,
        250199505002119,
        250199505002128,
        250199505002127,
        250199505002203,
        250199505002254,
        250199505002132,
        250199505002121,
        250199505002125,
        250199505002129,
        250199505002126,
        250199505002103,
        250199505002220,
        250199505002205,
        250199505002122,
        250199505002149,
        250199505002206,
        250199505002151,
        250199505002161,
        250199505002134,
        250199504002007,
        250199505002131,
        250199505002148,
        250199505002273,
        250199505002124
    ],
    "zs:housing10":393,
    "zs:pop10":173
},
  "geometry": {"coordinates":[-70.08528099999999,41.2886],"type":"Point"}
}