{
  "type": "Feature",
  "properties": {
    "gn:admin1_code":"TX",
    "gn:admin2_code":"67.0",
    "gn:asciiname":"Bryans Mill",
    "gn:country_code":"US",
    "gn:dem":104,
    "gn:elevation":"98.0",
    "gn:feature_class":"P",
    "gn:feature_code":"PPL",
    "gn:name":"Bryans Mill",
    "gn:population":0,
    "gn:timezone":"America/Chicago",
    "iso:country":"US",
    "wof:name":"Bryans Mill",
    "wof:placetype":"locality"
},
  "geometry": {"coordinates":[-94.49798,33.23512],"type":"Point"}
}