{
  "type": "Feature",
  "properties": {
    "iso:country":"US",
    "name:eng_x_preferred":[
        "Sunray West"
    ],
    "wof:name":"Sunray West",
    "wof:placetype":"neighbourhood",
    "wof:population":3394,
    "zs:area_m":976879.165003,
    "zs:blockids":[
        120860002025014,
        120860002023014,
        120860002025006,
        120860002025013,
        120860002023006,
        120860002025002,
        120860002023000,
        120860002021007,
        120860002025010,
        120860002021014,
        120860097053001,
        120860002022002,
        120860002025022,
        120860002025015,
        120860002023007,
        120860002025016,
        120860002023013,
        120860002021011,
        120860002025020,
        120860002025001,
        120860002023009,
        120860002021010,
        120860002025003,
        120860002023015,
        120860002142003,
        120860097051003,
        120860002025018,
        120860002142000,
        120860002142002,
        120860002025008,
        120860002025011,
        120860002025004,
        120860002025019,
        120860002025021,
        120860002023001,
        120860002025026,
        120860002025024,
        120860002025007,
        120860002023012,
        120860002142005,
        120860002025027,
        120860002025005,
        120860002025009,
        120860002025012,
        120860002023011,
        120860002142004
    ],
    "zs:housing10":1478,
    "zs:label":"Sunray West",
    "zs:pop10":3394
},
  "geometry": {"coordinates":[-80.16830899999999,25.939683],"type":"Point"}
}