{
  "type": "Feature",
  "properties": {
    "iso:country":"US",
    "name:cat_x_preferred":[
        "Grandview"
    ],
    "name:ceb_x_preferred":[
        "Grandview"
    ],
    "name:deu_x_preferred":[
        "Grandview"
    ],
    "name:eng_x_preferred":[
        "Grandview"
    ],
    "name:fin_x_preferred":[
        "Grandview"
    ],
    "name:fra_x_preferred":[
        "Grandview"
    ],
    "name:ita_x_preferred":[
        "Grandview"
    ],
    "name:kor_x_preferred":[
        "\uadf8\ub79c\ub4dc\ubdf0"
    ],
    "name:nld_x_preferred":[
        "Grandview"
    ],
    "name:pol_x_preferred":[
        "Grandview"
    ],
    "name:srp_x_preferred":[
        "\u0413\u0440\u0430\u043d\u0434\u0432\u0458\u0443"
    ],
    "name:swe_x_preferred":[
        "Grandview"
    ],
    "name:ukr_x_preferred":[
        "\u0413\u0440\u0430\u043d\u0434\u0432'\u044e"
    ],
    "name:vol_x_preferred":[
        "Grandview"
    ],
    "name:zho_x_preferred":[
        "\u683c\u5170\u5fb7\u7ef4\u5c24"
    ],
    "wof:name":"Grandview",
    "wof:placetype":"neighbourhood",
    "wof:population":1445,
    "zs:area_m":5956538.487637,
    "zs:blockids":[
        180950015002033,
        180950015001021,
        180950015002013,
        180950015002019,
        180950017001001,
        180950015002007,
        180950017001021,
        180950015002034,
        180950015003010,
        180950015001014,
        180950015002020,
        180950015003017,
        180950015002005,
        180950015002000,
        180950015003013,
        180950015003014,
        180950017001002,
        180950015002012,
        180950015002002,
        180950015003030,
        180950015001022,
        180950015001028,
        180950015001024,
        180950017001000,
        180950015001029,
        180950015002001,
        180950015002031,
        180950015002016,
        180950015001013,
        180950015002015,
        180950015002032,
        180950015001025,
        180950015001023,
        180950015002022,
        180950015003008,
        180950015003012,
        180950015003005,
        180950015002006,
        180950017001020,
        180950015002011,
        180950015002018,
        180950015002021,
        180950017001012,
        180950015001012,
        180950015002014
    ],
    "zs:housing10":689,
    "zs:label":"Grandview",
    "zs:pop10":1445
},
  "geometry": {"coordinates":[-85.715621,40.11939],"type":"Point"}
}