{
  "type": "Feature",
  "properties": {
    "gn:admin1_code":"MD",
    "gn:admin2_code":"43.0",
    "gn:asciiname":"Friendship Park",
    "gn:country_code":"US",
    "gn:dem":178,
    "gn:elevation":"177.0",
    "gn:feature_class":"P",
    "gn:feature_code":"PPL",
    "gn:name":"Friendship Park",
    "gn:population":0,
    "gn:timezone":"America/New_York",
    "iso:country":"US",
    "name:ceb_x_preferred":[
        "Friendship Park"
    ],
    "name:swe_x_preferred":[
        "Friendship Park"
    ],
    "wof:name":"Friendship Park",
    "wof:placetype":"locality"
},
  "geometry": {"coordinates":[-77.76888000000002,39.61315],"type":"Point"}
}