{
  "type": "Feature",
  "properties": {
    "gn:admin1_code":"DE",
    "gn:admin2_code":"5.0",
    "gn:asciiname":"Breezewood",
    "gn:country_code":"US",
    "gn:dem":11,
    "gn:elevation":"8.0",
    "gn:feature_class":"P",
    "gn:feature_code":"PPL",
    "gn:name":"Breezewood",
    "gn:population":0,
    "gn:timezone":"America/New_York",
    "iso:country":"US",
    "wof:name":"Breezewood",
    "wof:placetype":"locality"
},
  "geometry": {"coordinates":[-75.13018000000002,38.72039],"type":"Point"}
}