{
  "type": "Feature",
  "properties": {
    "gn:admin1_code":"MD",
    "gn:admin2_code":"37.0",
    "gn:asciiname":"Maryland Manor",
    "gn:country_code":"US",
    "gn:dem":34,
    "gn:elevation":"34.0",
    "gn:feature_class":"P",
    "gn:feature_code":"PPL",
    "gn:name":"Maryland Manor",
    "gn:population":0,
    "gn:timezone":"America/New_York",
    "iso:country":"US",
    "name:urd_x_preferred":[
        "\u0645\u06cc\u0631\u06cc \u0644\u06cc\u0646\u0688 \u0645\u06cc\u0646\u0648\u0631"
    ],
    "wof:name":"Maryland Manor",
    "wof:placetype":"locality"
},
  "geometry": {"coordinates":[-76.50245,38.29346],"type":"Point"}
}