{
  "type": "Feature",
  "properties": {
    "gn:country":"US",
    "gn:fcode":"PPL",
    "gn:population":0,
    "iso:country":"US",
    "name:ara_x_preferred":[
        "\u0625\u064a\u0631\u0644"
    ],
    "name:bel_x_preferred":[
        "\u042d\u0440\u043b"
    ],
    "name:cat_x_preferred":[
        "Earl"
    ],
    "name:ces_x_preferred":[
        "Earl"
    ],
    "name:dan_x_preferred":[
        "Earl"
    ],
    "name:deu_x_preferred":[
        "Earl"
    ],
    "name:fas_x_preferred":[
        "\u0627\u0631\u0644"
    ],
    "name:fra_x_preferred":[
        "Earl"
    ],
    "name:gla_x_preferred":[
        "Iarla"
    ],
    "name:gle_x_preferred":[
        "Iarla"
    ],
    "name:hrv_x_preferred":[
        "Earl"
    ],
    "name:kat_x_preferred":[
        "\u10d4\u10e0\u10da\u10d8"
    ],
    "name:kor_x_preferred":[
        "\uc601\uad6d \ubc31\uc791"
    ],
    "name:lit_x_preferred":[
        "Erlas"
    ],
    "name:nld_x_preferred":[
        "Earl"
    ],
    "name:pol_x_preferred":[
        "Earl"
    ],
    "name:rus_x_preferred":[
        "\u042d\u0440\u043b"
    ],
    "name:snd_x_preferred":[
        "\u0627\u0631\u0644"
    ],
    "name:spa_x_preferred":[
        "Earl"
    ],
    "name:swe_x_preferred":[
        "Earl"
    ],
    "name:tgl_x_preferred":[
        "Erl"
    ],
    "name:tha_x_preferred":[
        "\u0e40\u0e2d\u0e34\u0e23\u0e4c\u0e25"
    ],
    "name:tur_x_preferred":[
        "Earl"
    ],
    "name:ukr_x_preferred":[
        "\u0415\u0440\u043b"
    ],
    "name:urd_x_preferred":[
        "\u0627\u0631\u0644"
    ],
    "qs_pg:aaroncc":"US",
    "qs_pg:gn_country":"US",
    "qs_pg:gn_fcode":"PPL",
    "qs_pg:gn_pop":0,
    "qs_pg:name":"Earl",
    "qs_pg:name_adm0":"United States",
    "qs_pg:name_adm1":"Washington",
    "qs_pg:photos":4,
    "qs_pg:photos_1k":1,
    "qs_pg:photos_9k":1,
    "qs_pg:photos_9r":1,
    "qs_pg:photos_all":4,
    "qs_pg:photos_sr":1,
    "qs_pg:pop_sr":0,
    "qs_pg:qs_pg_placetype":"locality",
    "qs_pg:qs_pg_placetype_gp":"Town",
    "qs_pg:woe_adm0":23424977,
    "woe:adm0_id":23424977,
    "woe:name_adm0":"United States",
    "woe:name_adm1":"Washington",
    "woe:placetype":"Town",
    "wof:name":"Earl",
    "wof:placetype":"locality"
},
  "geometry": {"coordinates":[-118.37943,47.55182],"type":"Point"}
}