{
  "type": "Feature",
  "properties": {
    "gn:admin1_code":"FL",
    "gn:admin2_code":"57",
    "gn:asciiname":"Hollington Oaks",
    "gn:country_code":"US",
    "gn:dem":36,
    "gn:elevation":"28.0",
    "gn:feature_class":"P",
    "gn:feature_code":"PPL",
    "gn:name":"Hollington Oaks",
    "gn:population":0,
    "gn:timezone":"America/New_York",
    "iso:country":"US",
    "wof:name":"Hollington Oaks",
    "wof:placetype":"locality"
},
  "geometry": {"coordinates":[-82.26700000000002,27.9072],"type":"Point"}
}