{
  "type": "Feature",
  "properties": {
    "gn:admin1_code":"WV",
    "gn:admin2_code":"109",
    "gn:asciiname":"Glover",
    "gn:country_code":"US",
    "gn:dem":375,
    "gn:elevation":"372.0",
    "gn:feature_class":"P",
    "gn:feature_code":"PPL",
    "gn:name":"Glover",
    "gn:population":0,
    "gn:timezone":"America/New_York",
    "iso:country":"US",
    "wof:name":"Glover",
    "wof:placetype":"locality"
},
  "geometry": {"coordinates":[-81.59039,37.5865],"type":"Point"}
}