{
  "type": "Feature",
  "properties": {
    "gn:country":"US",
    "gn:fcode":"PPL",
    "gn:population":0,
    "iso:country":"US",
    "name:azb_x_preferred":[
        "\u062c\u06cc\u0645\u0632\u0648\u06cc\u0644"
    ],
    "name:deu_x_preferred":[
        "Jamesville"
    ],
    "name:eng_x_preferred":[
        "Jamesville"
    ],
    "name:fas_x_preferred":[
        "\u062c\u06cc\u0645\u0632\u0648\u06cc\u0644"
    ],
    "name:fra_x_preferred":[
        "Jamesville"
    ],
    "name:jpn_x_preferred":[
        "\u30cb\u30e5\u30fc\u30e8\u30fc\u30af\u5dde"
    ],
    "name:nld_x_preferred":[
        "Jamesville"
    ],
    "name:rus_x_preferred":[
        "\u0414\u0436\u0435\u0439\u043d\u0441\u0432\u0438\u043b\u043b"
    ],
    "name:swe_x_preferred":[
        "Jamesville"
    ],
    "name:tur_x_preferred":[
        "Jamesville"
    ],
    "name:und_x_variant":[
        "Sinai"
    ],
    "name:urd_x_preferred":[
        "\u062c\u0645\u0633\u0648\u0644\u0644\u06d2\u060c \u0646\u06cc\u0648 \u06cc\u0627\u0631\u06a9"
    ],
    "name:urd_x_variant":[
        "\u062c\u0645\u0633\u0648\u0644\u0644\u06d2"
    ],
    "name:vol_x_preferred":[
        "Jamesville"
    ],
    "qs_pg:aaroncc":"US",
    "qs_pg:gn_country":"US",
    "qs_pg:gn_fcode":"PPL",
    "qs_pg:gn_pop":0,
    "qs_pg:name":"Jamesville",
    "qs_pg:name_adm0":"United States",
    "qs_pg:name_adm1":"New York",
    "qs_pg:photos":757,
    "qs_pg:photos_1k":153,
    "qs_pg:photos_9k":3,
    "qs_pg:photos_9r":6,
    "qs_pg:photos_all":757,
    "qs_pg:photos_sr":9,
    "qs_pg:pop_sr":5,
    "qs_pg:qs_pg_placetype":"locality",
    "qs_pg:qs_pg_placetype_gp":"Town",
    "qs_pg:woe_adm0":23424977,
    "woe:adm0_id":23424977,
    "woe:name_adm0":"United States",
    "woe:name_adm1":"New York",
    "woe:placetype":"Town",
    "wof:name":"Jamesville",
    "wof:placetype":"locality"
},
  "geometry": {"coordinates":[-76.07159,42.99201],"type":"Point"}
}