{
  "type": "Feature",
  "properties": {
    "gn:admin1_code":"NM",
    "gn:admin2_code":"47.0",
    "gn:asciiname":"San Geronimo",
    "gn:country_code":"US",
    "gn:dem":2066,
    "gn:elevation":"2070.0",
    "gn:feature_class":"P",
    "gn:feature_code":"PPL",
    "gn:name":"San Geronimo",
    "gn:population":0,
    "gn:timezone":"America/Denver",
    "iso:country":"US",
    "name:eng_x_preferred":[
        "San Geronimo"
    ],
    "name:fra_x_preferred":[
        "V\u00e9n\u00e9rable G\u00e9ronimo"
    ],
    "name:und_x_variant":[
        "Geronimo",
        "Lesperance"
    ],
    "wof:name":"San Geronimo",
    "wof:placetype":"locality"
},
  "geometry": {"coordinates":[-105.39529,35.58004000000001],"type":"Point"}
}