{
  "type": "Feature",
  "properties": {
    "gn:admin1_code":"PA",
    "gn:admin2_code":"77.0",
    "gn:admin3_code":"79288.0",
    "gn:asciiname":"Spring Valley",
    "gn:country_code":"US",
    "gn:dem":118,
    "gn:elevation":"114.0",
    "gn:feature_class":"P",
    "gn:feature_code":"PPL",
    "gn:name":"Spring Valley",
    "gn:population":0,
    "gn:timezone":"America/New_York",
    "iso:country":"US",
    "name:cat_x_preferred":[
        "Spring Valley"
    ],
    "name:ceb_x_preferred":[
        "Spring Valley"
    ],
    "name:deu_x_preferred":[
        "Spring Valley"
    ],
    "name:fra_x_preferred":[
        "Spring Valley"
    ],
    "name:ita_x_preferred":[
        "Spring Valley"
    ],
    "name:jpn_x_preferred":[
        "\u30b9\u30d7\u30ea\u30f3\u30b0\u30d0\u30ec\u30fc"
    ],
    "name:kor_x_preferred":[
        "\uc2a4\ud504\ub9c1\ubc38\ub9ac"
    ],
    "name:nld_x_preferred":[
        "Spring Valley"
    ],
    "name:pol_x_preferred":[
        "Spring Valley"
    ],
    "name:por_x_preferred":[
        "Spring Valley"
    ],
    "name:rus_x_preferred":[
        "\u0421\u043f\u0440\u0438\u043d\u0433-\u0412\u0430\u043b\u043b\u0438"
    ],
    "name:spa_x_preferred":[
        "Spring Valley"
    ],
    "name:srp_x_preferred":[
        "\u0421\u043f\u0440\u0438\u043d\u0433 \u0412\u0430\u043b\u0438"
    ],
    "name:urd_x_preferred":[
        "\u0633\u067e\u0631\u0646\u06af \u0648\u06cc\u0644\u06cc"
    ],
    "name:vol_x_preferred":[
        "Spring Valley"
    ],
    "wof:name":"Spring Valley",
    "wof:placetype":"locality"
},
  "geometry": {"coordinates":[-75.35879,40.5526],"type":"Point"}
}