{
  "type": "Feature",
  "properties": {
    "gn:admin1_code":"FL",
    "gn:admin2_code":"57",
    "gn:asciiname":"Moneta",
    "gn:country_code":"US",
    "gn:dem":14,
    "gn:elevation":"7.0",
    "gn:feature_class":"P",
    "gn:feature_code":"PPL",
    "gn:name":"Moneta",
    "gn:population":0,
    "gn:timezone":"America/New_York",
    "iso:country":"US",
    "name:bre_x_preferred":[
        "Moneta"
    ],
    "name:ces_x_preferred":[
        "Moneta"
    ],
    "name:deu_x_preferred":[
        "Moneta"
    ],
    "name:epo_x_preferred":[
        "Moneta"
    ],
    "name:est_x_preferred":[
        "Moneta"
    ],
    "name:jpn_x_preferred":[
        "\u30e2\u30cd\u30fc\u30bf"
    ],
    "name:kor_x_preferred":[
        "\ubaa8\ub124\ud0c0"
    ],
    "name:pol_x_preferred":[
        "Moneta"
    ],
    "name:por_x_preferred":[
        "Moneta"
    ],
    "name:rus_x_preferred":[
        "\u042e\u043d\u043e\u043d\u0430 \u041c\u043e\u043d\u0435\u0442\u0430"
    ],
    "name:spa_x_preferred":[
        "Moneta"
    ],
    "name:swe_x_preferred":[
        "Moneta"
    ],
    "name:tur_x_preferred":[
        "Moneta"
    ],
    "name:ukr_x_preferred":[
        "\u041c\u043e\u043d\u0435\u0442\u0430"
    ],
    "wof:name":"Moneta",
    "wof:placetype":"locality"
},
  "geometry": {"coordinates":[-82.4875,27.9548],"type":"Point"}
}