{
  "type": "Feature",
  "properties": {
    "gn:admin1_code":"PA",
    "gn:admin2_code":"11",
    "gn:admin3_code":"24384.0",
    "gn:asciiname":"Lorane Orchards",
    "gn:country_code":"US",
    "gn:dem":79,
    "gn:elevation":"80.0",
    "gn:feature_class":"P",
    "gn:feature_code":"PPL",
    "gn:name":"Lorane Orchards",
    "gn:population":0,
    "gn:timezone":"America/New_York",
    "iso:country":"US",
    "wof:name":"Lorane Orchards",
    "wof:placetype":"locality"
},
  "geometry": {"coordinates":[-75.8575,40.29398],"type":"Point"}
}