{
  "type": "Feature",
  "properties": {
    "gn:admin1_code":"PA",
    "gn:admin2_code":"59.0",
    "gn:admin3_code":"64512.0",
    "gn:asciiname":"Durbin",
    "gn:country_code":"US",
    "gn:dem":294,
    "gn:elevation":"272.0",
    "gn:feature_class":"P",
    "gn:feature_code":"PPL",
    "gn:name":"Durbin",
    "gn:population":0,
    "gn:timezone":"America/New_York",
    "iso:country":"US",
    "name:ceb_x_preferred":[
        "Durbin"
    ],
    "name:deu_x_preferred":[
        "Durbin"
    ],
    "name:fra_x_preferred":[
        "Durbin"
    ],
    "name:ita_x_preferred":[
        "Durbin"
    ],
    "name:nld_x_preferred":[
        "Durbin"
    ],
    "name:pol_x_preferred":[
        "Durbin"
    ],
    "name:por_x_preferred":[
        "Durbin"
    ],
    "name:swe_x_preferred":[
        "Durbin"
    ],
    "wof:name":"Durbin",
    "wof:placetype":"locality"
},
  "geometry": {"coordinates":[-80.48479,39.91813],"type":"Point"}
}