{
  "type": "Feature",
  "properties": {
    "gn:elevation":213,
    "iso:country":"US",
    "name:eng_x_preferred":[
        "Rebel Acres"
    ],
    "qs:gn_adm0_cc":"US",
    "qs:gn_fcode":"PPL",
    "qs:gn_local":4651648,
    "qs:gn_nam_loc":"Pulaski, Giles, Tennessee, US",
    "qs:gn_namadm1":"TN",
    "qs:gn_name":"Rebel Acres",
    "qs:local_max":1470,
    "qs:local_sum":1470,
    "qs:localhoods":1,
    "qs:name":"Rebel Acres",
    "qs:name_adm0":"United States",
    "qs:name_adm1":"Tennessee",
    "qs:name_adm2":"Giles",
    "qs:name_local":"Pulaski",
    "qs:photo_max":557,
    "qs:photo_sum":1470,
    "qs:placetype":"Suburb",
    "qs:quad_count":13,
    "qs:woe_adm0":23424977,
    "qs:woe_adm1":2347601,
    "qs:woe_adm2":12589939,
    "qs:woe_lau":0,
    "qs:woe_local":2477197,
    "qs:woe_ver":"7.10.0",
    "wof:lang":[
        "eng"
    ],
    "wof:name":"Rebel Acres",
    "wof:placetype":"neighbourhood"
},
  "geometry": {"coordinates":[-87.030582,35.198772],"type":"Point"}
}