{
  "type": "Feature",
  "properties": {
    "gn:gn_country":"US",
    "gn:gn_fcode":"PPL",
    "gn:gn_pop":0,
    "iso:country":"US",
    "name:arg_x_preferred":[
        "Mart\u00edn"
    ],
    "name:aze_x_preferred":[
        "Martin"
    ],
    "name:bel_x_preferred":[
        "\u041c\u0430\u0440\u0446\u0456\u043d"
    ],
    "name:bos_x_preferred":[
        "Martin"
    ],
    "name:bul_x_preferred":[
        "\u041c\u0430\u0440\u0442\u0438\u043d"
    ],
    "name:cat_x_preferred":[
        "Martin"
    ],
    "name:ceb_x_preferred":[
        "Martin"
    ],
    "name:ces_x_preferred":[
        "Martin"
    ],
    "name:deu_x_preferred":[
        "Martin"
    ],
    "name:eus_x_preferred":[
        "Martin"
    ],
    "name:fas_x_preferred":[
        "\u0645\u0627\u0631\u062a\u06cc\u0646"
    ],
    "name:fin_x_preferred":[
        "Martin"
    ],
    "name:fra_x_preferred":[
        "Martin"
    ],
    "name:frr_x_preferred":[
        "Martin"
    ],
    "name:gle_x_preferred":[
        "Martin"
    ],
    "name:heb_x_preferred":[
        "\u05de\u05e8\u05d8\u05d9\u05df"
    ],
    "name:hrv_x_preferred":[
        "Martin"
    ],
    "name:hun_x_preferred":[
        "Martin"
    ],
    "name:ita_x_preferred":[
        "Martin"
    ],
    "name:jpn_x_preferred":[
        "\u30de\u30fc\u30c6\u30a3\u30f3"
    ],
    "name:lav_x_preferred":[
        "M\u0101rtins"
    ],
    "name:lim_x_preferred":[
        "Martin"
    ],
    "name:lit_x_preferred":[
        "Martin"
    ],
    "name:nld_x_preferred":[
        "Martin"
    ],
    "name:nor_x_preferred":[
        "Martin"
    ],
    "name:pol_x_preferred":[
        "Martin"
    ],
    "name:por_x_preferred":[
        "Martin"
    ],
    "name:ron_x_preferred":[
        "Martin"
    ],
    "name:rus_x_preferred":[
        "\u041c\u0430\u0440\u0442\u0438\u043d"
    ],
    "name:slk_x_preferred":[
        "Martin"
    ],
    "name:slv_x_preferred":[
        "Martin"
    ],
    "name:srp_x_preferred":[
        "\u041c\u0430\u0440\u0442\u0438\u043d"
    ],
    "name:swe_x_preferred":[
        "Martin"
    ],
    "name:tel_x_preferred":[
        "\u0c2e\u0c3e\u0c30\u0c4d\u0c1f\u0c3f\u0c28\u0c4d"
    ],
    "name:tur_x_preferred":[
        "Martin"
    ],
    "name:ukr_x_preferred":[
        "\u041c\u0430\u0440\u0442\u0456\u043d"
    ],
    "name:urd_x_preferred":[
        "\u0645\u0627\u0631\u0679\u0646"
    ],
    "name:vie_x_preferred":[
        "Martin"
    ],
    "name:vol_x_preferred":[
        "Martin"
    ],
    "name:war_x_preferred":[
        "Martin"
    ],
    "qs_pg:aaroncc":"US",
    "qs_pg:gn_country":"US",
    "qs_pg:gn_fcode":"PPL",
    "qs_pg:gn_pop":0,
    "qs_pg:name":"Martin",
    "qs_pg:name_adm0":"United States",
    "qs_pg:name_adm1":"Nevada",
    "qs_pg:photos":62,
    "qs_pg:photos_1k":13,
    "qs_pg:photos_9k":1,
    "qs_pg:photos_9r":2,
    "qs_pg:photos_all":62,
    "qs_pg:photos_sr":2,
    "qs_pg:pop_sr":0,
    "qs_pg:qs_pg_placetype":"locality",
    "qs_pg:qs_pg_placetype_gp":"Town",
    "qs_pg:woe_adm0":23424977,
    "woe:adm0_id":23424977,
    "woe:name_adm0":"United States",
    "woe:name_adm1":"Nevada",
    "woe:placetype":"Town",
    "wof:name":"Martin",
    "wof:placetype":"locality"
},
  "geometry": {"coordinates":[-119.87186,39.60408],"type":"Point"}
}