{
  "type": "Feature",
  "properties": {
    "gn:admin1_code":"SC",
    "gn:admin2_code":"43.0",
    "gn:asciiname":"Woodville Acres",
    "gn:country_code":"US",
    "gn:dem":-1,
    "gn:elevation":"2.0",
    "gn:feature_class":"P",
    "gn:feature_code":"PPL",
    "gn:name":"Woodville Acres",
    "gn:population":0,
    "gn:timezone":"America/New_York",
    "iso:country":"US",
    "wof:name":"Woodville Acres",
    "wof:placetype":"locality"
},
  "geometry": {"coordinates":[-79.13588,33.46267],"type":"Point"}
}