{
  "type": "Feature",
  "properties": {
    "gn:country":"US",
    "gn:fcode":"PPL",
    "gn:population":0,
    "iso:country":"US",
    "name:cat_x_preferred":[
        "Kendrick"
    ],
    "name:ceb_x_preferred":[
        "Kendrick"
    ],
    "name:deu_x_preferred":[
        "Kendrick"
    ],
    "name:fas_x_preferred":[
        "\u06a9\u0646\u062f\u0631\u06cc\u06a9"
    ],
    "name:fra_x_preferred":[
        "Kendrick"
    ],
    "name:ita_x_preferred":[
        "Kendrick"
    ],
    "name:nld_x_preferred":[
        "Kendrick"
    ],
    "name:pol_x_preferred":[
        "Kendrick"
    ],
    "name:por_x_preferred":[
        "Kendrick"
    ],
    "name:rus_x_preferred":[
        "\u041a\u0435\u043d\u0434\u0440\u0438\u043a"
    ],
    "name:srp_x_preferred":[
        "\u041a\u0435\u043d\u0434\u0440\u0438\u043a"
    ],
    "name:swe_x_preferred":[
        "Kendrick"
    ],
    "name:ukr_x_preferred":[
        "\u041a\u0435\u043d\u0434\u0440\u0438\u043a"
    ],
    "name:vol_x_preferred":[
        "Kendrick"
    ],
    "qs_pg:aaroncc":"US",
    "qs_pg:gn_country":"US",
    "qs_pg:gn_fcode":"PPL",
    "qs_pg:gn_pop":0,
    "qs_pg:name":"Kendrick",
    "qs_pg:name_adm0":"United States",
    "qs_pg:name_adm1":"Florida",
    "qs_pg:photos":68,
    "qs_pg:photos_1k":14,
    "qs_pg:photos_9k":1,
    "qs_pg:photos_9r":2,
    "qs_pg:photos_all":68,
    "qs_pg:photos_sr":2,
    "qs_pg:pop_sr":5,
    "qs_pg:qs_pg_placetype":"locality",
    "qs_pg:qs_pg_placetype_gp":"Town",
    "qs_pg:woe_adm0":23424977,
    "woe:adm0_id":23424977,
    "woe:name_adm0":"United States",
    "woe:name_adm1":"Florida",
    "woe:placetype":"Town",
    "wof:name":"Kendrick",
    "wof:placetype":"locality"
},
  "geometry": {"coordinates":[-82.16786999999999,29.25359],"type":"Point"}
}