{
  "type": "Feature",
  "properties": {
    "iso:country":"US",
    "name:eng_x_preferred":[
        "Windward Heights"
    ],
    "name:fra_x_preferred":[
        "La Migration des c\u0153urs"
    ],
    "wof:name":"Windward Heights",
    "wof:placetype":"neighbourhood",
    "wof:population":80,
    "zs:area_m":526554.575171,
    "zs:blockids":[
        420199109004016,
        420199109004018,
        420199109003009,
        420199109004006,
        420199109003017,
        420199109003018,
        420199109003020,
        420199109004014,
        420199109004019,
        420199109004015,
        420199109004009,
        420199109004017,
        420199109004013,
        420199109004042,
        420199109004023,
        420199109004027,
        420199109003019,
        420199109004012
    ],
    "zs:housing10":49,
    "zs:label":"Windward Heights",
    "zs:pop10":80
},
  "geometry": {"coordinates":[-79.906459,40.898815],"type":"Point"}
}