{
  "type": "Feature",
  "properties": {
    "gn:admin1_code":"GA",
    "gn:admin2_code":"139",
    "gn:asciiname":"Pinecrest Heights",
    "gn:country_code":"US",
    "gn:dem":358,
    "gn:elevation":"362.0",
    "gn:feature_class":"P",
    "gn:feature_code":"PPL",
    "gn:name":"Pinecrest Heights",
    "gn:population":0,
    "gn:timezone":"America/New_York",
    "iso:country":"US",
    "wof:name":"Pinecrest Heights",
    "wof:placetype":"locality"
},
  "geometry": {"coordinates":[-83.88963000000003,34.32621],"type":"Point"}
}