{
  "type": "Feature",
  "properties": {
    "gn:admin1_code":"AR",
    "gn:admin2_code":"61.0",
    "gn:admin3_code":"92643.0",
    "gn:asciiname":"Briar",
    "gn:country_code":"US",
    "gn:dem":147,
    "gn:elevation":"140.0",
    "gn:feature_class":"P",
    "gn:feature_code":"PPL",
    "gn:name":"Briar",
    "gn:population":0,
    "gn:timezone":"America/Chicago",
    "iso:country":"US",
    "wof:name":"Briar",
    "wof:placetype":"locality"
},
  "geometry": {"coordinates":[-93.8738,34.08789],"type":"Point"}
}