{
  "type": "Feature",
  "properties": {
    "iso:country":"US",
    "name:ceb_x_preferred":[
        "Union Square"
    ],
    "name:deu_x_preferred":[
        "Union Square"
    ],
    "name:eus_x_preferred":[
        "Union Square"
    ],
    "name:fra_x_preferred":[
        "Union Square"
    ],
    "name:ita_x_preferred":[
        "Union Square"
    ],
    "name:jpn_x_preferred":[
        "\u30e6\u30cb\u30aa\u30f3\u30b9\u30af\u30a8\u30a2"
    ],
    "name:kor_x_preferred":[
        "\uc720\ub2c8\uc5b8 \uc2a4\ud018\uc5b4"
    ],
    "name:nld_x_preferred":[
        "Union Square"
    ],
    "name:rus_x_preferred":[
        "\u042e\u043d\u0438\u043e\u043d-\u0441\u043a\u0432\u0435\u0440"
    ],
    "name:swe_x_preferred":[
        "Union Square"
    ],
    "qs_pg:aaroncc":"US",
    "qs_pg:name":"Union Square",
    "qs_pg:name_adm0":"United States",
    "qs_pg:name_adm1":"Pennsylvania",
    "qs_pg:photos":1,
    "qs_pg:photos_1k":1,
    "qs_pg:photos_9k":1,
    "qs_pg:photos_9r":1,
    "qs_pg:photos_all":1,
    "qs_pg:photos_sr":1,
    "qs_pg:pop_sr":0,
    "qs_pg:qs_pg_placetype":"neighbourhood",
    "qs_pg:qs_pg_placetype_gp":"Suburb",
    "qs_pg:woe_adm0":23424977,
    "woe:adm0_id":23424977,
    "woe:name_adm0":"United States",
    "woe:name_adm1":"Pennsylvania",
    "woe:placetype":"Suburb",
    "wof:name":"Union Square",
    "wof:placetype":"neighbourhood"
},
  "geometry": {"coordinates":[-76.454977,40.129525],"type":"Point"}
}