{
  "type": "Feature",
  "properties": {
    "gn:admin1_code":"MS",
    "gn:admin2_code":"85.0",
    "gn:asciiname":"Cobbs",
    "gn:country_code":"US",
    "gn:dem":127,
    "gn:elevation":"122.0",
    "gn:feature_class":"P",
    "gn:feature_code":"PPL",
    "gn:name":"Cobbs",
    "gn:population":0,
    "gn:timezone":"America/Chicago",
    "iso:country":"US",
    "wof:name":"Cobbs",
    "wof:placetype":"locality"
},
  "geometry": {"coordinates":[-90.57454,31.55989000000001],"type":"Point"}
}