{
  "type": "Feature",
  "properties": {
    "iso:country":"US",
    "name:eng_x_preferred":[
        "The Parks of Corinth"
    ],
    "wof:name":"The Parks of Corinth",
    "wof:placetype":"neighbourhood",
    "wof:population":1296,
    "zs:area_m":2797328.384093,
    "zs:blockids":[
        481210214042003,
        481210214041048,
        481210214042006,
        481210214042004,
        481210214041036,
        481210214041040,
        481210214042007,
        481210214042009,
        481210214042033,
        481210214042005,
        481210214041035,
        481210214041044,
        481210214042029,
        481210214042020,
        481210214041041,
        481210214042048,
        481210214041046,
        481210214042001,
        481210214041038,
        481210214041047,
        481210214041032,
        481210214041034,
        481210214042002,
        481210214042028,
        481210214042027,
        481210214041033,
        481210214041049
    ],
    "zs:housing10":452,
    "zs:label":"The Parks of Corinth",
    "zs:pop10":1296
},
  "geometry": {"coordinates":[-97.048126,33.152575],"type":"Point"}
}