{
  "type": "Feature",
  "properties": {
    "iso:country":"US",
    "name:eng_x_preferred":[
        "Bluemont Lakes"
    ],
    "wof:name":"Bluemont Lakes",
    "wof:placetype":"neighbourhood",
    "wof:population":648,
    "zs:area_m":494895.20985,
    "zs:blockids":[
        380170103051006,
        380170103051007,
        380170103051009,
        380170103051000,
        380170103051008,
        380170103051010,
        380170103051011
    ],
    "zs:housing10":310,
    "zs:label":"Bluemont Lakes",
    "zs:pop10":648
},
  "geometry": {"coordinates":[-96.838917,46.840585],"type":"Point"}
}