{
  "type": "Feature",
  "properties": {
    "gn:gn_country":"US",
    "gn:gn_fcode":"PPL",
    "gn:gn_pop":0,
    "iso:country":"US",
    "name:ceb_x_preferred":[
        "Francis"
    ],
    "name:ces_x_preferred":[
        "Francis"
    ],
    "name:deu_x_preferred":[
        "Francis"
    ],
    "name:fra_x_preferred":[
        "Francis"
    ],
    "name:heb_x_preferred":[
        "\u05e4\u05e8\u05e0\u05e1\u05d9\u05e1"
    ],
    "name:isl_x_preferred":[
        "Francis"
    ],
    "name:ita_x_preferred":[
        "Francis"
    ],
    "name:jpn_x_preferred":[
        "\u30d5\u30e9\u30f3\u30b7\u30b9"
    ],
    "name:kor_x_preferred":[
        "\ud504\ub79c\uc2dc\uc2a4"
    ],
    "name:nld_x_preferred":[
        "Francis"
    ],
    "name:pol_x_preferred":[
        "Francis"
    ],
    "name:por_x_preferred":[
        "Francis"
    ],
    "name:rus_x_preferred":[
        "\u0424\u0440\u044d\u043d\u0441\u0438\u0441"
    ],
    "name:spa_x_preferred":[
        "Francis"
    ],
    "name:srp_x_preferred":[
        "\u0424\u0440\u0430\u043d\u0441\u0438\u0441"
    ],
    "name:swe_x_preferred":[
        "Francis"
    ],
    "name:ukr_x_preferred":[
        "\u0424\u0440\u0435\u043d\u0441\u0456\u0441"
    ],
    "name:vol_x_preferred":[
        "Francis"
    ],
    "qs_pg:aaroncc":"US",
    "qs_pg:gn_country":"US",
    "qs_pg:gn_fcode":"PPL",
    "qs_pg:gn_pop":0,
    "qs_pg:name":"Francis",
    "qs_pg:name_adm0":"United States",
    "qs_pg:name_adm1":"Florida",
    "qs_pg:photos_9k":1,
    "qs_pg:photos_9r":1,
    "qs_pg:photos_all":3,
    "qs_pg:photos_sr":0,
    "qs_pg:pop_sr":0,
    "qs_pg:qs_pg_placetype":"locality",
    "qs_pg:qs_pg_placetype_gp":"Town",
    "qs_pg:woe_adm0":23424977,
    "woe:adm0_id":23424977,
    "woe:name_adm0":"United States",
    "woe:name_adm1":"Florida",
    "woe:placetype":"Town",
    "wof:name":"Francis",
    "wof:placetype":"locality"
},
  "geometry": {"coordinates":[-81.70786,29.63441],"type":"Point"}
}