{
  "type": "Feature",
  "properties": {
    "gn:admin1_code":"OH",
    "gn:admin2_code":"35.0",
    "gn:admin3_code":"16000.0",
    "gn:asciiname":"Manhattan Beach",
    "gn:country_code":"US",
    "gn:dem":185,
    "gn:elevation":"182.0",
    "gn:feature_class":"P",
    "gn:feature_code":"PPL",
    "gn:name":"Manhattan Beach",
    "gn:population":0,
    "gn:timezone":"America/New_York",
    "iso:country":"US",
    "name:bul_x_preferred":[
        "\u041c\u0430\u043d\u0445\u0430\u0442\u044a\u043d \u0411\u0438\u0439\u0447"
    ],
    "name:ceb_x_preferred":[
        "Manhattan Beach"
    ],
    "name:fra_x_preferred":[
        "Manhattan Beach"
    ],
    "name:heb_x_preferred":[
        "\u05de\u05e0\u05d4\u05d8\u05df \u05d1\u05d9\u05e5'"
    ],
    "name:ita_x_preferred":[
        "Manhattan Beach"
    ],
    "name:nld_x_preferred":[
        "Manhattan Beach"
    ],
    "name:pol_x_preferred":[
        "Manhattan Beach"
    ],
    "name:por_x_preferred":[
        "Manhattan Beach"
    ],
    "name:rus_x_preferred":[
        "\u041c\u0430\u043d\u0445\u044d\u0442\u0442\u0435\u043d-\u0411\u0438\u0447"
    ],
    "name:srp_x_preferred":[
        "\u041c\u0435\u043d\u0445\u0435\u0442\u043d \u0411\u0438\u0447"
    ],
    "name:ukr_x_preferred":[
        "\u041c\u0430\u043d\u0433\u0435\u0442\u0442\u0435\u043d-\u0411\u0456\u0447"
    ],
    "name:vol_x_preferred":[
        "Manhattan Beach"
    ],
    "wof:name":"Manhattan Beach",
    "wof:placetype":"locality"
},
  "geometry": {"coordinates":[-81.57679,41.57505],"type":"Point"}
}