{
  "type": "Feature",
  "properties": {
    "gn:admin1_code":"MO",
    "gn:admin2_code":"173.0",
    "gn:admin3_code":"14482.0",
    "gn:asciiname":"Flint Hill",
    "gn:country_code":"US",
    "gn:dem":155,
    "gn:elevation":"152.0",
    "gn:feature_class":"P",
    "gn:feature_code":"PPL",
    "gn:name":"Flint Hill",
    "gn:population":0,
    "gn:timezone":"America/Chicago",
    "iso:country":"US",
    "name:ceb_x_preferred":[
        "Flint Hill"
    ],
    "name:deu_x_preferred":[
        "Flint Hill"
    ],
    "name:eng_x_preferred":[
        "Flint Hill"
    ],
    "name:pol_x_preferred":[
        "Flint Hill"
    ],
    "name:srp_x_preferred":[
        "\u0424\u043b\u0438\u043d\u0442 \u0425\u0438\u043b"
    ],
    "name:swe_x_preferred":[
        "Flint Hill"
    ],
    "name:und_x_variant":[
        "Flinthill Salt River",
        "Salt River"
    ],
    "wof:name":"Flint Hill",
    "wof:placetype":"locality"
},
  "geometry": {"coordinates":[-91.38321000000001,39.62393],"type":"Point"}
}