{
  "type": "Feature",
  "properties": {
    "gn:admin1_code":"TN",
    "gn:admin2_code":"105.0",
    "gn:asciiname":"Sugarlimb",
    "gn:country_code":"US",
    "gn:dem":277,
    "gn:elevation":"275.0",
    "gn:feature_class":"P",
    "gn:feature_code":"PPL",
    "gn:name":"Sugarlimb",
    "gn:population":0,
    "gn:timezone":"America/New_York",
    "iso:country":"US",
    "name:eng_x_preferred":[
        "Sugarlimb"
    ],
    "name:und_x_variant":[
        "Browder"
    ],
    "wof:name":"Sugarlimb",
    "wof:placetype":"locality"
},
  "geometry": {"coordinates":[-84.31048,35.77091],"type":"Point"}
}