{
  "type": "Feature",
  "properties": {
    "iso:country":"US",
    "name:eng_x_preferred":[
        "Cadillac Heights"
    ],
    "name:nld_x_preferred":[
        "Cadillac Heights"
    ],
    "wd:wordcount":503,
    "wof:name":"Cadillac Heights",
    "wof:placetype":"neighbourhood",
    "wof:population":1473,
    "zs:area_m":1762759.238668,
    "zs:blockids":[
        450770112031015,
        450770112043005,
        450770112031016,
        450770112043000,
        450770112031014,
        450770112031017,
        450770112043002,
        450770112043006,
        450770112043001,
        450770112031011
    ],
    "zs:housing10":605,
    "zs:label":"Cadillac Heights",
    "zs:pop10":1473
},
  "geometry": {"coordinates":[-82.80592799999999,34.695589],"type":"Point"}
}