{
  "type": "Feature",
  "properties": {
    "gn:admin1_code":"OH",
    "gn:admin2_code":"65.0",
    "gn:admin3_code":"6866.0",
    "gn:asciiname":"Bridgeport",
    "gn:country_code":"US",
    "gn:dem":274,
    "gn:elevation":"276.0",
    "gn:feature_class":"P",
    "gn:feature_code":"PPL",
    "gn:name":"Bridgeport",
    "gn:population":0,
    "gn:timezone":"America/New_York",
    "iso:country":"US",
    "wof:name":"Bridgeport",
    "wof:placetype":"locality"
},
  "geometry": {"coordinates":[-83.60186999999998,40.74589],"type":"Point"}
}