{
  "type": "Feature",
  "properties": {
    "gn:country":"US",
    "gn:fcode":"ADMD",
    "gn:population":0,
    "iso:country":"US",
    "name:ara_x_preferred":[
        "\u0628\u0644\u062f\u0629 \u0628\u0627\u064a\u0646 \u0631\u064a\u0641\u0631"
    ],
    "name:eng_x_preferred":[
        "Pine River Township"
    ],
    "name:spa_x_preferred":[
        "Municipio de Pine River"
    ],
    "name:urd_x_preferred":[
        "\u067e\u0627\u0626\u0646 \u0631\u06cc\u0648\u0631 \u0679\u0627\u0624\u0646 \u0634\u067e"
    ],
    "name:vie_x_preferred":[
        "X\u00e3 Pine River"
    ],
    "qs_pg:aaroncc":"US",
    "qs_pg:gn_country":"US",
    "qs_pg:gn_fcode":"ADMD",
    "qs_pg:gn_pop":0,
    "qs_pg:name":"Pine River",
    "qs_pg:name_adm0":"United States",
    "qs_pg:name_adm1":"Michigan",
    "qs_pg:photos_9k":1,
    "qs_pg:photos_9r":1,
    "qs_pg:photos_all":22,
    "qs_pg:photos_sr":0,
    "qs_pg:pop_sr":0,
    "qs_pg:qs_pg_placetype":"locality",
    "qs_pg:qs_pg_placetype_gp":"Town",
    "qs_pg:woe_adm0":23424977,
    "woe:adm0_id":23424977,
    "woe:name_adm0":"United States",
    "woe:name_adm1":"Michigan",
    "woe:placetype":"Town",
    "wof:name":"Pine River",
    "wof:placetype":"locality"
},
  "geometry": {"coordinates":[-84.67195,43.42975],"type":"Point"}
}