{
  "type": "Feature",
  "properties": {
    "gn:admin1_code":"IL",
    "gn:admin2_code":"187.0",
    "gn:admin3_code":"72065.0",
    "gn:asciiname":"Shaw",
    "gn:country_code":"US",
    "gn:dem":194,
    "gn:elevation":"195.0",
    "gn:feature_class":"P",
    "gn:feature_code":"PPL",
    "gn:name":"Shaw",
    "gn:population":0,
    "gn:timezone":"America/Chicago",
    "iso:country":"US",
    "name:bel_x_preferred":[
        "\u0428\u043e\u0443"
    ],
    "name:ceb_x_preferred":[
        "Shaw"
    ],
    "name:ces_x_preferred":[
        "Shaw"
    ],
    "name:deu_x_preferred":[
        "Shaw"
    ],
    "name:fin_x_preferred":[
        "Shaw"
    ],
    "name:fra_x_preferred":[
        "Shaw"
    ],
    "name:hun_x_preferred":[
        "Shaw"
    ],
    "name:ita_x_preferred":[
        "Shaw"
    ],
    "name:lav_x_preferred":[
        "Shaw"
    ],
    "name:nds_x_preferred":[
        "Shaw"
    ],
    "name:nld_x_preferred":[
        "Shaw"
    ],
    "name:pol_x_preferred":[
        "Shaw"
    ],
    "name:por_x_preferred":[
        "Shaw"
    ],
    "name:rus_x_preferred":[
        "\u0428\u043e\u0443"
    ],
    "name:slk_x_preferred":[
        "Shaw"
    ],
    "name:spa_x_preferred":[
        "Shaw"
    ],
    "name:swe_x_preferred":[
        "Shaw"
    ],
    "name:tur_x_preferred":[
        "Shaw"
    ],
    "name:ukr_x_preferred":[
        "\u0428\u043e\u0443"
    ],
    "name:vol_x_preferred":[
        "Shaw"
    ],
    "wof:name":"Shaw",
    "wof:placetype":"locality"
},
  "geometry": {"coordinates":[-90.63708,41.04587],"type":"Point"}
}