{
  "type": "Feature",
  "properties": {
    "gn:admin1_code":"MD",
    "gn:admin2_code":"21.0",
    "gn:asciiname":"Rattle Ridge",
    "gn:country_code":"US",
    "gn:dem":231,
    "gn:elevation":"236.0",
    "gn:feature_class":"P",
    "gn:feature_code":"PPL",
    "gn:name":"Rattle Ridge",
    "gn:population":0,
    "gn:timezone":"America/New_York",
    "iso:country":"US",
    "wof:name":"Rattle Ridge",
    "wof:placetype":"locality"
},
  "geometry": {"coordinates":[-77.21109,39.33622],"type":"Point"}
}