{
  "type": "Feature",
  "properties": {
    "gn:country":"US",
    "gn:fcode":"ADMD",
    "gn:population":0,
    "iso:country":"US",
    "name:cym_x_preferred":[
        "East Greenwich Township"
    ],
    "name:eng_x_preferred":[
        "East Greenwich Township"
    ],
    "name:fas_x_preferred":[
        "\u06af\u0631\u06cc\u0646\u0648\u06cc\u0686 \u0634\u0631\u0642\u06cc\u060c \u0646\u06cc\u0648\u062c\u0631\u0633\u06cc"
    ],
    "name:fas_x_variant":[
        "\u06af\u0631\u06cc\u0646\u0648\u06cc\u0686 \u0634\u0631\u0642\u06cc"
    ],
    "name:hat_x_preferred":[
        "East Greenwich"
    ],
    "name:ita_x_preferred":[
        "East Greenwich"
    ],
    "name:jpn_x_preferred":[
        "\u30a4\u30fc\u30b9\u30c8\u30fb\u30b0\u30ea\u30cb\u30c3\u30b8\u90e1\u533a"
    ],
    "name:spa_x_preferred":[
        "Municipio de East Greenwich"
    ],
    "name:ukr_x_preferred":[
        "\u0406\u0441\u0442-\u0413\u0440\u0456\u043d\u0432\u0456\u0447 \u0422\u0430\u0443\u043d\u0448\u0438\u043f"
    ],
    "name:zho_x_preferred":[
        "\u4e1c\u683c\u6797\u5c3c\u6cbb"
    ],
    "qs_pg:aaroncc":"US",
    "qs_pg:gn_country":"US",
    "qs_pg:gn_fcode":"ADMD",
    "qs_pg:gn_pop":0,
    "qs_pg:name":"East Greenwich",
    "qs_pg:name_adm0":"United States",
    "qs_pg:name_adm1":"New Jersey",
    "qs_pg:photos_9k":1,
    "qs_pg:photos_9r":1,
    "qs_pg:photos_all":1,
    "qs_pg:photos_sr":0,
    "qs_pg:pop_sr":0,
    "qs_pg:qs_pg_placetype":"locality",
    "qs_pg:qs_pg_placetype_gp":"Town",
    "qs_pg:woe_adm0":23424977,
    "woe:adm0_id":23424977,
    "woe:name_adm0":"United States",
    "woe:name_adm1":"New Jersey",
    "woe:placetype":"Town",
    "wof:coterminous":[
        404478173
    ],
    "wof:name":"East Greenwich",
    "wof:placetype":"locality",
    "wof:statistical_gore":1
},
  "geometry": {"coordinates":[-75.25796,39.79178],"type":"Point"}
}