{
  "type": "Feature",
  "properties": {
    "gn:country":"US",
    "gn:fcode":"ADMD",
    "gn:population":0,
    "iso:country":"US",
    "name:eng_x_preferred":[
        "East Greenwich Township"
    ],
    "name:fas_x_preferred":[
        "\u06af\u0631\u06cc\u0646\u0648\u06cc\u0686 \u0634\u0631\u0642\u06cc\u060c \u0646\u06cc\u0648\u062c\u0631\u0633\u06cc"
    ],
    "name:fas_x_variant":[
        "\u06af\u0631\u06cc\u0646\u0648\u06cc\u0686 \u0634\u0631\u0642\u06cc"
    ],
    "name:hat_x_preferred":[
        "East Greenwich"
    ],
    "name:ita_x_preferred":[
        "East Greenwich"
    ],
    "name:spa_x_preferred":[
        "Municipio de East Greenwich"
    ],
    "qs_pg:aaroncc":"US",
    "qs_pg:gn_country":"US",
    "qs_pg:gn_fcode":"ADMD",
    "qs_pg:gn_pop":0,
    "qs_pg:name":"East Greenwich",
    "qs_pg:name_adm0":"United States",
    "qs_pg:name_adm1":"New Jersey",
    "qs_pg:photos_9k":1,
    "qs_pg:photos_9r":1,
    "qs_pg:photos_all":1,
    "qs_pg:photos_sr":0,
    "qs_pg:pop_sr":0,
    "qs_pg:qs_pg_placetype":"locality",
    "qs_pg:qs_pg_placetype_gp":"Town",
    "qs_pg:woe_adm0":23424977,
    "woe:adm0_id":23424977,
    "woe:name_adm0":"United States",
    "woe:name_adm1":"New Jersey",
    "woe:placetype":"Town",
    "wof:name":"East Greenwich",
    "wof:placetype":"locality"
},
  "geometry": {"coordinates":[-75.25796,39.79178],"type":"Point"}
}