{
  "type": "Feature",
  "properties": {
    "gn:admin1_code":"PA",
    "gn:admin2_code":"43.0",
    "gn:admin3_code":"45056.0",
    "gn:asciiname":"Rockford Heights",
    "gn:country_code":"US",
    "gn:dem":148,
    "gn:elevation":"142.0",
    "gn:feature_class":"P",
    "gn:feature_code":"PPL",
    "gn:name":"Rockford Heights",
    "gn:population":0,
    "gn:timezone":"America/New_York",
    "iso:country":"US",
    "wof:name":"Rockford Heights",
    "wof:placetype":"locality"
},
  "geometry": {"coordinates":[-76.76969,40.33509],"type":"Point"}
}