{
  "type": "Feature",
  "properties": {
    "iso:country":"US",
    "name:eng_x_preferred":[
        "Bear Hill"
    ],
    "wof:name":"Bear Hill",
    "wof:placetype":"neighbourhood",
    "wof:population":2968,
    "zs:area_m":1727820.987641,
    "zs:blockids":[
        250173372011012,
        250173372011009,
        250173352003017,
        250173341002035,
        250173344005024,
        250173344005008,
        250173372021018,
        250173352003001,
        250173352003014,
        250173352003000,
        250173352003024,
        250173352003004,
        250173352003023,
        250173344005019,
        250173352003007,
        250173372011005,
        250173372021005,
        250173344005013,
        250173341002037,
        250173344005020,
        250173352003008,
        250173352003025,
        250173372024003,
        250173344005018,
        250173352003028,
        250173372011008,
        250173344005010,
        250173372021002,
        250173341002036,
        250173352003020,
        250173352003009,
        250173372011007,
        250173344005022,
        250173372011006,
        250173372021019,
        250173352003022,
        250173344005014,
        250173344005025,
        250173344005023,
        250173344005017,
        250173372021000,
        250173352003010,
        250173352003021,
        250173372011000,
        250173344005011,
        250173372011003,
        250173372011002,
        250173344005015,
        250173352001007,
        250173344005012,
        250173372011010,
        250173372021001,
        250173352003026,
        250173352001006,
        250173352003005,
        250173352003006,
        250173352003016,
        250173372011001,
        250173372024000,
        250173352003003,
        250173372011004,
        250173341002038,
        250173344005021,
        250173352003015,
        250173352003002,
        250173344005016,
        250173352003027,
        250173352001020
    ],
    "zs:housing10":1639,
    "zs:label":"Bear Hill",
    "zs:pop10":2968
},
  "geometry": {"coordinates":[-71.096998,42.502712],"type":"Point"}
}