{
  "type": "Feature",
  "properties": {
    "gn:admin1_code":"MI",
    "gn:admin2_code":"81",
    "gn:admin3_code":"31240.0",
    "gn:asciiname":"Green Meadow Village Mobile Home Park",
    "gn:country_code":"US",
    "gn:dem":206,
    "gn:elevation":"205.0",
    "gn:feature_class":"P",
    "gn:feature_code":"PPL",
    "gn:name":"Green Meadow Village Mobile Home Park",
    "gn:population":0,
    "gn:timezone":"America/Detroit",
    "iso:country":"US",
    "wof:name":"Green Meadow Village Mobile Home Park",
    "wof:placetype":"campus"
},
  "geometry": {"coordinates":[-85.65916999999997,42.85222],"type":"Point"}
}