{
  "type": "Feature",
  "properties": {
    "gn:admin1_code":"PA",
    "gn:admin2_code":"29.0",
    "gn:admin3_code":"84192.0",
    "gn:asciiname":"Oakland",
    "gn:country_code":"US",
    "gn:dem":90,
    "gn:elevation":"88.0",
    "gn:feature_class":"P",
    "gn:feature_code":"PPL",
    "gn:name":"Oakland",
    "gn:population":0,
    "gn:timezone":"America/New_York",
    "iso:country":"US",
    "wof:name":"Oakland",
    "wof:placetype":"locality"
},
  "geometry": {"coordinates":[-75.6416,40.02038],"type":"Point"}
}