{
  "type": "Feature",
  "properties": {
    "gn:admin1_code":"VA",
    "gn:admin2_code":"89",
    "gn:asciiname":"Sheffield Terrace",
    "gn:country_code":"US",
    "gn:dem":235,
    "gn:elevation":"237.0",
    "gn:feature_class":"P",
    "gn:feature_code":"PPL",
    "gn:name":"Sheffield Terrace",
    "gn:population":0,
    "gn:timezone":"America/New_York",
    "iso:country":"US",
    "wof:name":"Sheffield Terrace",
    "wof:placetype":"locality"
},
  "geometry": {"coordinates":[-79.85504,36.60847],"type":"Point"}
}