{
  "type": "Feature",
  "properties": {
    "gn:admin1_code":"KY",
    "gn:admin2_code":"29.0",
    "gn:asciiname":"Whitfield",
    "gn:country_code":"US",
    "gn:dem":218,
    "gn:elevation":"220.0",
    "gn:feature_class":"P",
    "gn:feature_code":"PPL",
    "gn:name":"Whitfield",
    "gn:population":0,
    "gn:timezone":"America/New_York",
    "iso:country":"US",
    "wof:name":"Whitfield",
    "wof:placetype":"locality"
},
  "geometry": {"coordinates":[-85.47051,38.09618],"type":"Point"}
}