{
  "type": "Feature",
  "properties": {
    "gn:admin1_code":"NE",
    "gn:admin2_code":"89.0",
    "gn:admin3_code":"19280.0",
    "gn:asciiname":"Stafford",
    "gn:country_code":"US",
    "gn:dem":582,
    "gn:elevation":"580.0",
    "gn:feature_class":"P",
    "gn:feature_code":"PPL",
    "gn:name":"Stafford",
    "gn:population":0,
    "gn:timezone":"America/Chicago",
    "iso:country":"US",
    "wof:name":"Stafford",
    "wof:placetype":"locality"
},
  "geometry": {"coordinates":[-98.44701999999999,42.32834],"type":"Point"}
}