{
  "type": "Feature",
  "properties": {
    "gn:admin1_code":"MO",
    "gn:admin2_code":"179.0",
    "gn:admin3_code":"43598.0",
    "gn:asciiname":"Redford",
    "gn:country_code":"US",
    "gn:dem":215,
    "gn:elevation":"213.0",
    "gn:feature_class":"P",
    "gn:feature_code":"PPL",
    "gn:name":"Redford",
    "gn:population":0,
    "gn:timezone":"America/Chicago",
    "iso:country":"US",
    "name:vol_x_preferred":[
        "Redford"
    ],
    "wof:name":"Redford",
    "wof:placetype":"locality"
},
  "geometry": {"coordinates":[-90.89846,37.32005],"type":"Point"}
}