{
  "type": "Feature",
  "properties": {
    "gn:admin1_code":"AZ",
    "gn:admin2_code":"13.0",
    "gn:asciiname":"Paradise Valley Mobilhome Park",
    "gn:country_code":"US",
    "gn:dem":442,
    "gn:elevation":"440.0",
    "gn:feature_class":"P",
    "gn:feature_code":"PPL",
    "gn:name":"Paradise Valley Mobilhome Park",
    "gn:population":0,
    "gn:timezone":"America/Phoenix",
    "iso:country":"US",
    "wof:name":"Paradise Valley Mobilhome Park",
    "wof:placetype":"locality"
},
  "geometry": {"coordinates":[-112.01765,33.63532],"type":"Point"}
}