{
  "type": "Feature",
  "properties": {
    "iso:country":"US",
    "name:ara_x_preferred":[
        "\u062f\u064a\u0643\u0633\u0648\u0646"
    ],
    "name:bel_x_preferred":[
        "\u0414\u044b\u043a\u0441\u0430\u043d"
    ],
    "name:cat_x_preferred":[
        "Dixon"
    ],
    "name:ceb_x_preferred":[
        "Dixon"
    ],
    "name:ces_x_preferred":[
        "Dixon"
    ],
    "name:deu_x_preferred":[
        "Dixon"
    ],
    "name:eng_x_preferred":[
        "Dixon"
    ],
    "name:fin_x_preferred":[
        "Dixon"
    ],
    "name:fra_x_preferred":[
        "Dixon"
    ],
    "name:glg_x_preferred":[
        "Dixon"
    ],
    "name:heb_x_preferred":[
        "\u05d3\u05d9\u05e7\u05e1\u05d5\u05df"
    ],
    "name:ita_x_preferred":[
        "Dixon"
    ],
    "name:jpn_x_preferred":[
        "\u30c7\u30a3\u30af\u30bd\u30f3"
    ],
    "name:nld_x_preferred":[
        "Dixon"
    ],
    "name:pol_x_preferred":[
        "Dixon"
    ],
    "name:por_x_preferred":[
        "Dixon"
    ],
    "name:rus_x_preferred":[
        "\u0414\u0438\u043a\u0441\u043e\u043d"
    ],
    "name:spa_x_preferred":[
        "Dixon"
    ],
    "name:srp_x_preferred":[
        "\u0414\u0438\u043a\u0441\u043e\u043d"
    ],
    "name:swe_x_preferred":[
        "Dixon"
    ],
    "name:ukr_x_preferred":[
        "\u0414\u0456\u043a\u0441\u043e\u043d"
    ],
    "name:urd_x_preferred":[
        "\u0688\u06a9\u0633\u0646"
    ],
    "name:vol_x_preferred":[
        "Dixon"
    ],
    "name:zho_x_preferred":[
        "\u8fea\u514b\u68ee"
    ],
    "wof:name":"Dixon",
    "wof:placetype":"neighbourhood",
    "wof:population":620,
    "zs:area_m":29186885.359795,
    "zs:blockids":[
        421314004002022,
        421314004002047,
        421314004003000,
        421314004002002,
        421314004002001,
        421314004002048,
        421314004003053,
        421314004002003,
        421314004002079,
        421314004002026,
        421314004003010,
        421314004002078,
        421314004002050,
        421314004003009,
        421314004002004,
        421314004002027,
        421314004002023,
        421314004003013
    ],
    "zs:housing10":261,
    "zs:label":"Dixon",
    "zs:pop10":620
},
  "geometry": {"coordinates":[-75.883673,41.550864],"type":"Point"}
}