{
  "type": "Feature",
  "properties": {
    "gn:elevation":1290,
    "iso:country":"US",
    "name:eng_x_preferred":[
        "Klenkes Addition"
    ],
    "qs:gn_adm0_cc":"US",
    "qs:gn_fcode":"PPLX",
    "qs:gn_local":5780993,
    "qs:gn_nam_loc":"Salt Lake City, Salt Lake, Utah, US",
    "qs:gn_namadm1":"UT",
    "qs:gn_name":"Klenkes Addition",
    "qs:local_max":24997,
    "qs:local_sum":103616,
    "qs:localhoods":160,
    "qs:name":"Klenkes Addition",
    "qs:name_adm0":"United States",
    "qs:name_adm1":"Utah",
    "qs:name_adm2":"Salt Lake",
    "qs:name_local":"Salt Lake City",
    "qs:photo_max":9,
    "qs:photo_sum":23,
    "qs:placetype":"Suburb",
    "qs:quad_count":5,
    "qs:woe_adm0":23424977,
    "qs:woe_adm1":2347603,
    "qs:woe_adm2":12590278,
    "qs:woe_lau":0,
    "qs:woe_local":2487610,
    "qs:woe_ver":"7.10.0",
    "wof:lang":[
        "eng"
    ],
    "wof:name":"Klenkes Addition",
    "wof:placetype":"neighbourhood",
    "wof:population":6,
    "zs:blockids":[
        490351028021030
    ],
    "zs:housing10":1,
    "zs:pop10":6
},
  "geometry": {"coordinates":[-111.91688000000001,40.725696],"type":"Point"}
}