{
  "type": "Feature",
  "properties": {
    "gn:admin1_code":"NC",
    "gn:admin2_code":"97",
    "gn:admin3_code":"91076.0",
    "gn:asciiname":"Eufola",
    "gn:country_code":"US",
    "gn:dem":244,
    "gn:elevation":"245.0",
    "gn:feature_class":"P",
    "gn:feature_code":"PPL",
    "gn:name":"Eufola",
    "gn:population":0,
    "gn:timezone":"America/New_York",
    "iso:country":"US",
    "name:eng_x_preferred":[
        "Eufola"
    ],
    "name:und_x_variant":[
        "Deep Cut",
        "Eufoa"
    ],
    "wof:name":"Eufola",
    "wof:placetype":"locality"
},
  "geometry": {"coordinates":[-80.98591,35.72235999999999],"type":"Point"}
}