{
  "type": "Feature",
  "properties": {
    "gn:admin1_code":"TX",
    "gn:admin2_code":"457.0",
    "gn:asciiname":"Rockland",
    "gn:country_code":"US",
    "gn:dem":45,
    "gn:elevation":"40.0",
    "gn:feature_class":"P",
    "gn:feature_code":"PPL",
    "gn:name":"Rockland",
    "gn:population":0,
    "gn:timezone":"America/Chicago",
    "iso:country":"US",
    "name:ara_x_preferred":[
        "\u0631\u0648\u0643\u0644\u0627\u0646\u062f"
    ],
    "name:cat_x_preferred":[
        "Rockland"
    ],
    "name:ceb_x_preferred":[
        "Rockland"
    ],
    "name:ces_x_preferred":[
        "Rockland"
    ],
    "name:deu_x_preferred":[
        "Rockland"
    ],
    "name:fra_x_preferred":[
        "Rockland"
    ],
    "name:ita_x_preferred":[
        "Rockland"
    ],
    "name:kat_x_preferred":[
        "\u10e0\u10dd\u10d9\u10da\u10d4\u10dc\u10d3\u10d8"
    ],
    "name:nld_x_preferred":[
        "Rockland"
    ],
    "name:pol_x_preferred":[
        "Rockland"
    ],
    "name:por_x_preferred":[
        "Rockland"
    ],
    "name:rus_x_preferred":[
        "\u0420\u043e\u043a\u043b\u0435\u043d\u0434"
    ],
    "name:spa_x_preferred":[
        "Rockland"
    ],
    "name:srp_x_preferred":[
        "\u0420\u043e\u043a\u043b\u0430\u043d\u0434"
    ],
    "name:swe_x_preferred":[
        "Rockland"
    ],
    "name:vol_x_preferred":[
        "Rockland"
    ],
    "wof:name":"Rockland",
    "wof:placetype":"locality"
},
  "geometry": {"coordinates":[-94.38159,31.01519],"type":"Point"}
}