{
  "type": "Feature",
  "properties": {
    "gn:admin1_code":"LA",
    "gn:admin2_code":"33.0",
    "gn:asciiname":"Jones Creek",
    "gn:country_code":"US",
    "gn:dem":16,
    "gn:elevation":"12.0",
    "gn:feature_class":"P",
    "gn:feature_code":"PPL",
    "gn:name":"Jones Creek",
    "gn:population":0,
    "gn:timezone":"America/Chicago",
    "iso:country":"US",
    "wof:name":"Jones Creek",
    "wof:placetype":"locality"
},
  "geometry": {"coordinates":[-91.01482,30.41269],"type":"Point"}
}