{
  "type": "Feature",
  "properties": {
    "gn:admin1_code":"MO",
    "gn:admin2_code":"205.0",
    "gn:admin3_code":"36134.0",
    "gn:asciiname":"Lakenan",
    "gn:country_code":"US",
    "gn:dem":222,
    "gn:elevation":"221.0",
    "gn:feature_class":"P",
    "gn:feature_code":"PPL",
    "gn:name":"Lakenan",
    "gn:population":0,
    "gn:timezone":"America/Chicago",
    "iso:country":"US",
    "wof:name":"Lakenan",
    "wof:placetype":"locality"
},
  "geometry": {"coordinates":[-91.95099999999999,39.67226],"type":"Point"}
}