{
  "type": "Feature",
  "properties": {
    "iso:country":"US",
    "name:eng_x_preferred":[
        "Rowell Place"
    ],
    "wof:name":"Rowell Place",
    "wof:placetype":"neighbourhood",
    "wof:population":280,
    "zs:area_m":2742945.764563,
    "zs:blockids":[
        120570140031036,
        120570140131041,
        120570140031105,
        120570140131052,
        120570140131028,
        120570140031022,
        120570140031028,
        120570140131043,
        120570140031103,
        120570140131054,
        120570140031019,
        120570140031038,
        120570140031029,
        120570140131026,
        120570140131045,
        120570140031117,
        120570140122029,
        120570140031097,
        120570140031104,
        120570140131038,
        120570140031107,
        120570140122012,
        120570140031110,
        120570140131040,
        120570140131024,
        120570140031033,
        120570140122026,
        120570140131034,
        120570140031017,
        120570140131035,
        120570140031102,
        120570140031119,
        120570140122027,
        120570140131039,
        120570140122015,
        120570140122028,
        120570140131046,
        120570140131050,
        120570140031025,
        120570140131053,
        120570140131048,
        120570140131025,
        120570140131031,
        120570140131030,
        120570140031024,
        120570140031101,
        120570140122030,
        120570140031037,
        120570140031035,
        120570140131013,
        120570140131047,
        120570140131029,
        120570140031106,
        120570140031108,
        120570140131036,
        120570140031122,
        120570140031018,
        120570140031118,
        120570140122013,
        120570140031039,
        120570140031020,
        120570140122011,
        120570140131022,
        120570140031115,
        120570140031026,
        120570140131032,
        120570140031113,
        120570140131051,
        120570140131044,
        120570140131049,
        120570140131037,
        120570140031027,
        120570140031116,
        120570140122010,
        120570140122014,
        120570140031109,
        120570140131027,
        120570140131033
    ],
    "zs:housing10":118,
    "zs:label":"Rowell Place",
    "zs:pop10":280
},
  "geometry": {"coordinates":[-82.39493400000001,27.669526],"type":"Point"}
}