{
  "type": "Feature",
  "properties": {
    "gn:admin1_code":"WV",
    "gn:admin2_code":"45",
    "gn:asciiname":"Hensley Heights",
    "gn:country_code":"US",
    "gn:dem":229,
    "gn:elevation":"231.0",
    "gn:feature_class":"P",
    "gn:feature_code":"PPL",
    "gn:name":"Hensley Heights",
    "gn:population":0,
    "gn:timezone":"America/New_York",
    "iso:country":"US",
    "wof:name":"Hensley Heights",
    "wof:placetype":"locality"
},
  "geometry": {"coordinates":[-81.87956,37.72927],"type":"Point"}
}