{
  "type": "Feature",
  "properties": {
    "gn:admin1_code":"GA",
    "gn:admin2_code":"47.0",
    "gn:asciiname":"Keith",
    "gn:country_code":"US",
    "gn:dem":271,
    "gn:elevation":"271.0",
    "gn:feature_class":"P",
    "gn:feature_code":"PPL",
    "gn:name":"Keith",
    "gn:population":0,
    "gn:timezone":"America/New_York",
    "iso:country":"US",
    "name:eng_x_preferred":[
        "Keith"
    ],
    "name:und_x_variant":[
        "Catoosa"
    ],
    "wof:name":"Keith",
    "wof:placetype":"locality"
},
  "geometry": {"coordinates":[-85.04189000000002,34.91813],"type":"Point"}
}