{
  "type": "Feature",
  "properties": {
    "iso:country":"US",
    "name:eng_x_preferred":[
        "Gand View"
    ],
    "wof:name":"Gand View",
    "wof:placetype":"neighbourhood",
    "wof:population":3738,
    "zs:area_m":1630424.383115,
    "zs:blockids":[
        120570021002017,
        120570021003011,
        120570021003009,
        120570020002027,
        120570020001026,
        120570020003022,
        120570020003021,
        120570021002022,
        120570021003000,
        120570021003014,
        120570021003010,
        120570021003006,
        120570020003003,
        120570020002007,
        120570020002003,
        120570020002023,
        120570020002021,
        120570020003023,
        120570031003003,
        120570020003001,
        120570020003013,
        120570022002022,
        120570021003003,
        120570022003000,
        120570021003002,
        120570021002024,
        120570021002006,
        120570021002012,
        120570021002021,
        120570021002002,
        120570021001023,
        120570021002025,
        120570021003001,
        120570021003008,
        120570031002002,
        120570020001024,
        120570020002006,
        120570020002024,
        120570021003019,
        120570020003009,
        120570020003008,
        120570031003005,
        120570020003007,
        120570021002011,
        120570021002014,
        120570020002026,
        120570021003007,
        120570021003017,
        120570021003020,
        120570020001032,
        120570020002005,
        120570020002014,
        120570020002013,
        120570020002022,
        120570020003010,
        120570031003004,
        120570020003024,
        120570020003012,
        120570031002003,
        120570020003017,
        120570021003012,
        120570021003013,
        120570021003025,
        120570021002009,
        120570021002010,
        120570021002015,
        120570021002019,
        120570021003018,
        120570021003021,
        120570020002018,
        120570020002016,
        120570020002019,
        120570020002015,
        120570020001031,
        120570020002008,
        120570020003006,
        120570020003005,
        120570020003014,
        120570021002026,
        120570021003016,
        120570021002020,
        120570021001024,
        120570021003005,
        120570021003026,
        120570031002000,
        120570020001025,
        120570021002016,
        120570020002020,
        120570020003018,
        120570020002029,
        120570021002008,
        120570031003008,
        120570020003011,
        120570020003020,
        120570020002009,
        120570020002017,
        120570020002012,
        120570020002028,
        120570022002021,
        120570021002023,
        120570022002023,
        120570021002000,
        120570020003028,
        120570021002027,
        120570021002028,
        120570021003015,
        120570020002004,
        120570020002025,
        120570020003019,
        120570020003002,
        120570021002013,
        120570021002001,
        120570021002018
    ],
    "zs:housing10":1515,
    "zs:label":"Gand View",
    "zs:pop10":3738
},
  "geometry": {"coordinates":[-82.443946,27.986786],"type":"Point"}
}