{
  "type": "Feature",
  "properties": {
    "gn:admin1_code":"OK",
    "gn:admin2_code":"113.0",
    "gn:asciiname":"Strohm",
    "gn:country_code":"US",
    "gn:dem":320,
    "gn:elevation":"321.0",
    "gn:feature_class":"P",
    "gn:feature_code":"PPL",
    "gn:name":"Strohm",
    "gn:population":0,
    "gn:timezone":"America/Chicago",
    "iso:country":"US",
    "wof:name":"Strohm",
    "wof:placetype":"locality"
},
  "geometry": {"coordinates":[-96.55558000000001,36.64311],"type":"Point"}
}