{
  "type": "Feature",
  "properties": {
    "gn:gn_country":"US",
    "gn:gn_fcode":"PPLX",
    "gn:gn_pop":0,
    "iso:country":"US",
    "name:cat_x_preferred":[
        "Westfield"
    ],
    "name:ceb_x_preferred":[
        "Westfield"
    ],
    "name:deu_x_preferred":[
        "Westfield"
    ],
    "name:fra_x_preferred":[
        "Westfield"
    ],
    "name:ita_x_preferred":[
        "Westfield"
    ],
    "name:jpn_x_preferred":[
        "\u30a6\u30a7\u30b9\u30c8\u30d5\u30a3\u30fc\u30eb\u30c9"
    ],
    "name:kor_x_preferred":[
        "\uc6e8\uc2a4\ud2b8\ud544\ub4dc"
    ],
    "name:nld_x_preferred":[
        "Westfield"
    ],
    "name:pol_x_preferred":[
        "Westfield"
    ],
    "name:por_x_preferred":[
        "Westfield"
    ],
    "name:ron_x_preferred":[
        "Westfield"
    ],
    "name:rus_x_preferred":[
        "\u0423\u044d\u0441\u0442\u0444\u0438\u043b\u0434"
    ],
    "name:sco_x_preferred":[
        "Westfield"
    ],
    "name:spa_x_preferred":[
        "Westfield"
    ],
    "name:srp_x_preferred":[
        "\u0412\u0435\u0441\u0442\u0444\u0438\u043b\u0434"
    ],
    "name:swe_x_preferred":[
        "Westfield"
    ],
    "name:urd_x_preferred":[
        "\u0648\u06cc\u0633\u0679 \u0641\u06cc\u0644\u0688"
    ],
    "name:vol_x_preferred":[
        "Westfield"
    ],
    "qs_pg:aaroncc":"US",
    "qs_pg:gn_country":"US",
    "qs_pg:gn_fcode":"PPLX",
    "qs_pg:gn_pop":0,
    "qs_pg:name":"Westfield",
    "qs_pg:name_adm0":"United States",
    "qs_pg:name_adm1":"Georgia",
    "qs_pg:photos":1,
    "qs_pg:photos_1k":1,
    "qs_pg:photos_9k":1,
    "qs_pg:photos_9r":1,
    "qs_pg:photos_all":1,
    "qs_pg:photos_sr":1,
    "qs_pg:pop_sr":0,
    "qs_pg:qs_pg_placetype":"neighbourhood",
    "qs_pg:qs_pg_placetype_gp":"Suburb",
    "qs_pg:woe_adm0":23424977,
    "woe:adm0_id":23424977,
    "woe:name_adm0":"United States",
    "woe:name_adm1":"Georgia",
    "woe:placetype":"Suburb",
    "wof:name":"Westfield",
    "wof:placetype":"neighbourhood"
},
  "geometry": {"coordinates":[-83.71102,32.81292],"type":"Point"}
}