{
  "type": "Feature",
  "properties": {
    "gn:admin1_code":"AR",
    "gn:admin2_code":"89.0",
    "gn:asciiname":"Pine Branch",
    "gn:country_code":"US",
    "gn:dem":262,
    "gn:elevation":"261.0",
    "gn:feature_class":"P",
    "gn:feature_code":"PPL",
    "gn:name":"Pine Branch",
    "gn:population":0,
    "gn:timezone":"America/Chicago",
    "iso:country":"US",
    "wof:name":"Pine Branch",
    "wof:placetype":"locality"
},
  "geometry": {"coordinates":[-92.69691,36.47507],"type":"Point"}
}