{
  "type": "Feature",
  "properties": {
    "iso:country":"US",
    "name:eng_x_preferred":[
        "Hickory Heights"
    ],
    "wof:name":"Hickory Heights",
    "wof:placetype":"neighbourhood",
    "wof:population":19,
    "zs:area_m":437304.315492,
    "zs:blockids":[
        470999604011045,
        470999604011066
    ],
    "zs:housing10":10,
    "zs:label":"Hickory Heights",
    "zs:pop10":19
},
  "geometry": {"coordinates":[-87.299576,35.240014],"type":"Point"}
}