{
  "type": "Feature",
  "properties": {
    "gn:admin1_code":"LA",
    "gn:admin2_code":"33.0",
    "gn:asciiname":"Sunnybrook",
    "gn:country_code":"US",
    "gn:dem":20,
    "gn:elevation":"14.0",
    "gn:feature_class":"P",
    "gn:feature_code":"PPL",
    "gn:name":"Sunnybrook",
    "gn:population":0,
    "gn:timezone":"America/Chicago",
    "iso:country":"US",
    "name:deu_x_preferred":[
        "Sunnybrook"
    ],
    "wof:name":"Sunnybrook",
    "wof:placetype":"locality"
},
  "geometry": {"coordinates":[-91.08705,30.49297],"type":"Point"}
}