{
  "type": "Feature",
  "properties": {
    "gn:admin1_code":"NY",
    "gn:admin2_code":"73",
    "gn:admin3_code":"27958.0",
    "gn:asciiname":"Heritage Estates",
    "gn:country_code":"US",
    "gn:dem":155,
    "gn:elevation":"156.0",
    "gn:feature_class":"P",
    "gn:feature_code":"PPL",
    "gn:name":"Heritage Estates",
    "gn:population":0,
    "gn:timezone":"America/New_York",
    "iso:country":"US",
    "wof:name":"Heritage Estates",
    "wof:placetype":"locality"
},
  "geometry": {"coordinates":[-78.18222,43.25444],"type":"Point"}
}