{
  "type": "Feature",
  "properties": {
    "gn:elevation":64,
    "iso:country":"US",
    "name:arz_x_preferred":[
        "\u0645\u0637\u0627\u0631 \u0648\u064a\u0633\u062a \u0645\u0645\u0641\u064a\u0633 \u0627\u0644\u0645\u062d\u0644\u0649"
    ],
    "name:ceb_x_preferred":[
        "West Memphis Municipal Airport"
    ],
    "name:eng_x_preferred":[
        "West Memphis Municipal Airport"
    ],
    "name:eng_x_variant":[
        "AWM",
        "KAWM"
    ],
    "name:fas_x_preferred":[
        "\u0641\u0631\u0648\u062f\u06af\u0627\u0647 \u0634\u0647\u0631\u06cc \u0648\u0633\u062a \u0645\u0645\u0641\u06cc\u0633"
    ],
    "name:jpn_x_preferred":[
        "\u30a6\u30a8\u30b9\u30c8\u30e1\u30f3\u30d5\u30a3\u30b9\u5e02\u55b6\u7a7a\u6e2f"
    ],
    "name:ron_x_preferred":[
        "Aeroportul Municipal West Memphis"
    ],
    "name:tgk_x_preferred":[
        "\u0424\u0443\u0440\u0443\u0434\u0433\u043e\u04b3\u0438 \u0448\u0430\u04b3\u0440\u0435 \u0432\u0438\u0441\u0442 \u043c\u043c\u0444\u0438\u0441"
    ],
    "name:urd_x_preferred":[
        "\u0648\u06cc\u0633\u0679 \u0645\u06cc\u0645\u0641\u0633 \u0645\u06cc\u0648\u0646\u0633\u067e\u0644 \u06c1\u0648\u0627\u0626\u06cc \u0627\u0688\u0627"
    ],
    "name:zho_x_preferred":[
        "\u897f\u5b5f\u83f2\u65af\u5e02\u7acb\u6a5f\u5834"
    ],
    "oa:elevation_ft":"212",
    "oa:type":"small_airport",
    "wd:wordcount":229,
    "woe:hierarchy":{
        "country_id":23424977,
        "county_id":12587612,
        "planet_id":1,
        "state_id":2347562
    },
    "wof:name":"West Memphis Municipal Airport",
    "wof:placetype":"campus"
},
  "geometry": {"coordinates":[-90.234398,35.135101],"type":"Point"}
}