{
  "type": "Feature",
  "properties": {
    "gn:admin1_code":"AL",
    "gn:admin2_code":"33",
    "gn:asciiname":"Lane Springs",
    "gn:country_code":"US",
    "gn:dem":141,
    "gn:elevation":"138.0",
    "gn:feature_class":"P",
    "gn:feature_code":"PPL",
    "gn:name":"Lane Springs",
    "gn:population":0,
    "gn:timezone":"America/Chicago",
    "iso:country":"US",
    "name:eng_x_preferred":[
        "Lane Springs"
    ],
    "name:und_x_variant":[
        "Hurst"
    ],
    "wof:name":"Lane Springs",
    "wof:placetype":"locality"
},
  "geometry": {"coordinates":[-87.98087,34.83425],"type":"Point"}
}