{
  "type": "Feature",
  "properties": {
    "gn:admin1_code":"PA",
    "gn:admin2_code":"125.0",
    "gn:admin3_code":"12224.0",
    "gn:asciiname":"Binnstown",
    "gn:country_code":"US",
    "gn:dem":280,
    "gn:elevation":"278.0",
    "gn:feature_class":"P",
    "gn:feature_code":"PPL",
    "gn:name":"Binnstown",
    "gn:population":0,
    "gn:timezone":"America/New_York",
    "iso:country":"US",
    "wof:name":"Binnstown",
    "wof:placetype":"locality"
},
  "geometry": {"coordinates":[-79.96755,40.01535],"type":"Point"}
}