{
  "type": "Feature",
  "properties": {
    "gn:admin1_code":"LA",
    "gn:admin2_code":"15.0",
    "gn:asciiname":"Lagas",
    "gn:country_code":"US",
    "gn:dem":50,
    "gn:elevation":"46.0",
    "gn:feature_class":"P",
    "gn:feature_code":"PPL",
    "gn:name":"Lagas",
    "gn:population":0,
    "gn:timezone":"America/Chicago",
    "iso:country":"US",
    "wof:name":"Lagas",
    "wof:placetype":"locality"
},
  "geometry": {"coordinates":[-93.56268,32.35877],"type":"Point"}
}