{
  "type": "Feature",
  "properties": {
    "gn:admin1_code":"KS",
    "gn:admin2_code":"91",
    "gn:admin3_code":"17850.0",
    "gn:asciiname":"Bosworth Mobile Home Park",
    "gn:country_code":"US",
    "gn:dem":259,
    "gn:elevation":"253.0",
    "gn:feature_class":"P",
    "gn:feature_code":"PPL",
    "gn:name":"Bosworth Mobile Home Park",
    "gn:population":0,
    "gn:timezone":"America/Chicago",
    "iso:country":"US",
    "wof:name":"Bosworth Mobile Home Park",
    "wof:placetype":"campus"
},
  "geometry": {"coordinates":[-94.97150000000001,38.97881],"type":"Point"}
}