{
  "type": "Feature",
  "properties": {
    "iso:country":"US",
    "name:eng_x_preferred":[
        "Bassett Place"
    ],
    "qs:gn_adm0_cc":"US",
    "qs:gn_local":4110486,
    "qs:gn_nam_loc":"Fayetteville, Washington, Arkansas, US",
    "qs:gn_namadm1":"AR",
    "qs:local_max":702,
    "qs:local_sum":3365,
    "qs:localhoods":17,
    "qs:name":"Bassett Place",
    "qs:name_adm0":"United States",
    "qs:name_adm1":"Arkansas",
    "qs:name_adm2":"Washington",
    "qs:name_local":"Fayetteville",
    "qs:photo_max":84,
    "qs:photo_sum":142,
    "qs:placetype":"Suburb",
    "qs:quad_count":11,
    "qs:woe_adm0":23424977,
    "qs:woe_adm1":2347562,
    "qs:woe_adm2":12587666,
    "qs:woe_lau":0,
    "qs:woe_local":2402731,
    "qs:woe_ver":"7.10.0",
    "wd:wordcount":230,
    "wof:lang":[
        "eng"
    ],
    "wof:name":"Bassett Place",
    "wof:placetype":"neighbourhood",
    "wof:population":510,
    "zs:blockids":[
        51430101063056,
        51430101061010,
        51430101063039,
        51430101063050,
        51430101063068,
        51430101063036,
        51430101063055,
        51430105033102,
        51430105033120,
        51430101063040,
        51430101063069,
        51430105033115,
        51430105033142,
        51430105033121,
        51430105033116,
        51430101063035,
        51430101063044,
        51430105033113,
        51430101063046,
        51430101063038,
        51430105033143,
        51430101063042,
        51430101063027,
        51430105033118,
        51430105033119,
        51430101063013,
        51430101063054,
        51430101063047,
        51430101063028,
        51430101061012,
        51430105033144,
        51430101061007,
        51430101063029,
        51430101063031,
        51430101063037,
        51430101063051,
        51430101061006,
        51430101061011,
        51430105033114,
        51430101063041,
        51430101063043,
        51430101061000,
        51430105033117,
        51430101063048,
        51430101063067,
        51430101063033,
        51430101063066,
        51430101063030,
        51430101063034
    ],
    "zs:housing10":423,
    "zs:pop10":510
},
  "geometry": {"coordinates":[-94.145764,36.121044],"type":"Point"}
}