{
  "type": "Feature",
  "properties": {
    "iso:country":"US",
    "wof:name":"Colonial Square",
    "wof:placetype":"neighbourhood"
},
  "geometry": {"coordinates":[-83.69741552947626,42.23668394347331],"type":"Point"}
}