{
  "type": "Feature",
  "properties": {
    "gn:admin1_code":"TX",
    "gn:admin2_code":"295.0",
    "gn:asciiname":"Coburn",
    "gn:country_code":"US",
    "gn:dem":827,
    "gn:elevation":"823.0",
    "gn:feature_class":"P",
    "gn:feature_code":"PPL",
    "gn:name":"Coburn",
    "gn:population":0,
    "gn:timezone":"America/Chicago",
    "iso:country":"US",
    "name:ces_x_preferred":[
        "Coburn"
    ],
    "name:deu_x_preferred":[
        "Coburn"
    ],
    "name:fra_x_preferred":[
        "Coburn"
    ],
    "name:ita_x_preferred":[
        "Coburn"
    ],
    "name:jpn_x_preferred":[
        "\u30b3\u30d0\u30fc\u30f3"
    ],
    "name:nld_x_preferred":[
        "Coburn"
    ],
    "name:pol_x_preferred":[
        "Coburn"
    ],
    "name:srp_x_preferred":[
        "\u041a\u043e\u0431\u0435\u0440\u043d"
    ],
    "wof:name":"Coburn",
    "wof:placetype":"locality"
},
  "geometry": {"coordinates":[-100.15346,36.06643],"type":"Point"}
}