{
  "type": "Feature",
  "properties": {
    "gn:admin1_code":"KY",
    "gn:admin2_code":"209",
    "gn:asciiname":"Mallard Point",
    "gn:country_code":"US",
    "gn:dem":281,
    "gn:elevation":"275.0",
    "gn:feature_class":"P",
    "gn:feature_code":"PPL",
    "gn:name":"Mallard Point",
    "gn:population":0,
    "gn:timezone":"America/New_York",
    "iso:country":"US",
    "wof:name":"Mallard Point",
    "wof:placetype":"locality"
},
  "geometry": {"coordinates":[-84.57605,38.31785],"type":"Point"}
}