{
  "type": "Feature",
  "properties": {
    "gn:admin1_code":"OH",
    "gn:admin2_code":"17",
    "gn:admin3_code":"49840.0",
    "gn:asciiname":"Bon Veue",
    "gn:country_code":"US",
    "gn:dem":196,
    "gn:elevation":"196.0",
    "gn:feature_class":"P",
    "gn:feature_code":"PPL",
    "gn:name":"Bon Veue",
    "gn:population":0,
    "gn:timezone":"America/New_York",
    "iso:country":"US",
    "wof:name":"Bon Veue",
    "wof:placetype":"locality"
},
  "geometry": {"coordinates":[-84.41500000000001,39.49917],"type":"Point"}
}