{
  "type": "Feature",
  "properties": {
    "gn:admin1_code":"KY",
    "gn:admin2_code":"101",
    "gn:asciiname":"Tunnel Hill",
    "gn:country_code":"US",
    "gn:dem":136,
    "gn:elevation":"135.0",
    "gn:feature_class":"P",
    "gn:feature_code":"PPL",
    "gn:name":"Tunnel Hill",
    "gn:population":0,
    "gn:timezone":"America/Chicago",
    "iso:country":"US",
    "name:ceb_x_preferred":[
        "Tunnel Hill"
    ],
    "name:deu_x_preferred":[
        "Tunnel Hill"
    ],
    "name:vol_x_preferred":[
        "Tunnel Hill"
    ],
    "wof:name":"Tunnel Hill",
    "wof:placetype":"locality"
},
  "geometry": {"coordinates":[-87.64112,37.68421],"type":"Point"}
}