{
  "type": "Feature",
  "properties": {
    "gn:admin1_code":"NY",
    "gn:admin2_code":"17.0",
    "gn:admin3_code":"18619.0",
    "gn:asciiname":"Blackesley Corner",
    "gn:country_code":"US",
    "gn:dem":465,
    "gn:elevation":"465.0",
    "gn:feature_class":"P",
    "gn:feature_code":"PPL",
    "gn:name":"Blackesley Corner",
    "gn:population":0,
    "gn:timezone":"America/New_York",
    "iso:country":"US",
    "wof:name":"Blackesley Corner",
    "wof:placetype":"locality"
},
  "geometry": {"coordinates":[-75.60074,42.26591],"type":"Point"}
}