{
  "type": "Feature",
  "properties": {
    "gn:admin1_code":"SC",
    "gn:admin2_code":"5.0",
    "gn:asciiname":"Seigling",
    "gn:country_code":"US",
    "gn:dem":65,
    "gn:elevation":"64.0",
    "gn:feature_class":"P",
    "gn:feature_code":"PPL",
    "gn:name":"Seigling",
    "gn:population":0,
    "gn:timezone":"America/New_York",
    "iso:country":"US",
    "name:eng_x_preferred":[
        "Seigling"
    ],
    "name:und_x_variant":[
        "Seiglingville"
    ],
    "wof:name":"Seigling",
    "wof:placetype":"locality"
},
  "geometry": {"coordinates":[-81.31511,33.04432],"type":"Point"}
}