{
  "type": "Feature",
  "properties": {
    "gn:admin1_code":"GA",
    "gn:admin2_code":"289.0",
    "gn:asciiname":"Huber",
    "gn:country_code":"US",
    "gn:dem":86,
    "gn:elevation":"83.0",
    "gn:feature_class":"P",
    "gn:feature_code":"PPL",
    "gn:name":"Huber",
    "gn:population":0,
    "gn:timezone":"America/New_York",
    "iso:country":"US",
    "name:ces_x_preferred":[
        "Huber"
    ],
    "name:deu_x_preferred":[
        "Huber"
    ],
    "name:eng_x_preferred":[
        "Huber"
    ],
    "name:fra_x_preferred":[
        "Huber"
    ],
    "name:jpn_x_preferred":[
        "\u30d5\u30fc\u30d0\u30fc"
    ],
    "name:rus_x_preferred":[
        "\u0425\u0443\u0431\u0435\u0440"
    ],
    "name:slv_x_preferred":[
        "Huber"
    ],
    "name:ukr_x_preferred":[
        "\u0413\u0443\u0431\u0435\u0440"
    ],
    "name:und_x_variant":[
        "Philip",
        "Philip Station"
    ],
    "wof:name":"Huber",
    "wof:placetype":"locality"
},
  "geometry": {"coordinates":[-83.55629,32.70431],"type":"Point"}
}