{
  "type": "Feature",
  "properties": {
    "gn:admin1_code":"WV",
    "gn:admin2_code":"99",
    "gn:asciiname":"Ardel",
    "gn:country_code":"US",
    "gn:dem":179,
    "gn:elevation":"180.0",
    "gn:feature_class":"P",
    "gn:feature_code":"PPL",
    "gn:name":"Ardel",
    "gn:population":0,
    "gn:timezone":"America/New_York",
    "iso:country":"US",
    "name:eng_x_preferred":[
        "Ardel"
    ],
    "name:fas_x_preferred":[
        "\u0622\u0631\u062f\u0644"
    ],
    "name:und_x_variant":[
        "Herbert",
        "Big Creek"
    ],
    "wof:name":"Ardel",
    "wof:placetype":"locality"
},
  "geometry": {"coordinates":[-82.45543000000001,38.27064],"type":"Point"}
}