{
  "type": "Feature",
  "properties": {
    "gn:admin1_code":"IA",
    "gn:admin2_code":"101.0",
    "gn:admin3_code":"94401.0",
    "gn:asciiname":"Merrimac",
    "gn:country_code":"US",
    "gn:dem":182,
    "gn:elevation":"180.0",
    "gn:feature_class":"P",
    "gn:feature_code":"PPL",
    "gn:name":"Merrimac",
    "gn:population":0,
    "gn:timezone":"America/Chicago",
    "iso:country":"US",
    "name:cat_x_preferred":[
        "Merrimac"
    ],
    "name:ceb_x_preferred":[
        "Merrimac"
    ],
    "name:deu_x_preferred":[
        "Merrimac"
    ],
    "name:eng_x_preferred":[
        "Merrimac"
    ],
    "name:fra_x_preferred":[
        "Merrimac"
    ],
    "name:ita_x_preferred":[
        "Merrimac"
    ],
    "name:nld_x_preferred":[
        "Merrimac"
    ],
    "name:pol_x_preferred":[
        "Merrimac"
    ],
    "name:srp_x_preferred":[
        "\u041c\u0435\u0440\u0438\u043c\u0430\u043a"
    ],
    "name:swe_x_preferred":[
        "Merrimac"
    ],
    "name:und_x_variant":[
        "Merrimack"
    ],
    "name:vol_x_preferred":[
        "Merrimac"
    ],
    "wof:name":"Merrimac",
    "wof:placetype":"locality"
},
  "geometry": {"coordinates":[-91.71878,41.08724],"type":"Point"}
}