{
  "type": "Feature",
  "properties": {
    "iso:country":"US",
    "name:afr_x_preferred":[
        "MacAindrais"
    ],
    "name:ara_x_preferred":[
        "\u0648\u064a\u0646\u062f\u064a \u0648\u0648\u062f"
    ],
    "name:arz_x_preferred":[
        "\u0648\u064a\u0646\u062f\u0649 \u0648\u0648\u062f"
    ],
    "name:ast_x_preferred":[
        "Wendy Wood"
    ],
    "name:cym_x_preferred":[
        "Wendy Wood"
    ],
    "name:dan_x_preferred":[
        "Wendy Wood"
    ],
    "name:deu_x_preferred":[
        "Wendy Wood"
    ],
    "name:eng_x_preferred":[
        "Wendy Wood"
    ],
    "name:fin_x_preferred":[
        "Wendy Wood"
    ],
    "name:fra_x_preferred":[
        "Wendy Wood"
    ],
    "name:gle_x_preferred":[
        "Wendy Wood"
    ],
    "name:ibo_x_preferred":[
        "Wendy Wood"
    ],
    "name:nno_x_preferred":[
        "Wendy Wood"
    ],
    "name:nob_x_preferred":[
        "Wendy Wood"
    ],
    "name:slv_x_preferred":[
        "Wendy Wood"
    ],
    "name:spa_x_preferred":[
        "Wendy Wood"
    ],
    "name:sqi_x_preferred":[
        "Wendy Wood"
    ],
    "name:swe_x_preferred":[
        "Wendy Wood"
    ],
    "name:und_x_variant":[
        "Windy Wood"
    ],
    "name:vie_x_preferred":[
        "Wendy Wood"
    ],
    "wd:wordcount":802,
    "wof:name":"Wendy Wood",
    "wof:placetype":"neighbourhood",
    "wof:population":1033,
    "zs:blockids":[
        11210103023007,
        11210103023011,
        11210103021089,
        11210103023010,
        11210103023008,
        11210103021088,
        11210103023012,
        11210103023015,
        11210103023014,
        11210103023009,
        11210103023013,
        11150402042044,
        11150402042042,
        11150402042043,
        11150402042040,
        11150402042014
    ],
    "zs:housing10":498,
    "zs:label":"Wendy Wood",
    "zs:pop10":1033
},
  "geometry": {"coordinates":[-86.218391,33.539217],"type":"Point"}
}