{
  "type": "Feature",
  "properties": {
    "gn:admin1_code":"WV",
    "gn:admin2_code":"25",
    "gn:asciiname":"Brantville",
    "gn:country_code":"US",
    "gn:dem":705,
    "gn:elevation":"704.0",
    "gn:feature_class":"P",
    "gn:feature_code":"PPL",
    "gn:name":"Brantville",
    "gn:population":0,
    "gn:timezone":"America/New_York",
    "iso:country":"US",
    "name:eng_x_preferred":[
        "Brantville"
    ],
    "name:und_x_variant":[
        "Branville"
    ],
    "wof:name":"Brantville",
    "wof:placetype":"locality"
},
  "geometry": {"coordinates":[-80.43424,37.90401],"type":"Point"}
}