{
  "type": "Feature",
  "properties": {
    "iso:country":"US",
    "name:eng_x_preferred":[
        "Fern-Ridge"
    ],
    "qs:gn_adm0_cc":"US",
    "qs:gn_local":5004188,
    "qs:gn_nam_loc":"Oak Park, Oakland, Michigan, US",
    "qs:gn_namadm1":"MI",
    "qs:local_max":424,
    "qs:local_sum":776,
    "qs:localhoods":4,
    "qs:name":"Fern-Ridge",
    "qs:name_adm0":"United States",
    "qs:name_adm1":"Michigan",
    "qs:name_adm2":"Oakland",
    "qs:name_local":"Oak Park",
    "qs:photo_max":98,
    "qs:photo_sum":140,
    "qs:placetype":"Suburb",
    "qs:quad_count":12,
    "qs:woe_adm0":23424977,
    "qs:woe_adm1":2347581,
    "qs:woe_adm2":12588776,
    "qs:woe_lau":0,
    "qs:woe_local":2463171,
    "qs:woe_ver":"7.10.0",
    "wd:wordcount":45,
    "wof:lang":[
        "eng"
    ],
    "wof:name":"Fern-Ridge",
    "wof:placetype":"neighbourhood",
    "wof:population":2918,
    "zs:blockids":[
        261251712001007,
        261251712001009,
        261251716002006,
        261251716002000,
        261251716002004,
        261251712002005,
        261251711003019,
        261251716002011,
        261251711003005,
        261251716001000,
        261251716002007,
        261251712002010,
        261251711003016,
        261251716001013,
        261251712003004,
        261251716001014,
        261251712003003,
        261251711003014,
        261251711003013,
        261251711003017,
        261251712003002,
        261251712003000,
        261251716002002,
        261251712002004,
        261251712003008,
        261251712003009,
        261251712002009,
        261251712001003,
        261251712001006,
        261251712001008,
        261251712001000,
        261251711003006,
        261251712003006,
        261251712001002,
        261251711003018,
        261251711003003,
        261251712001001,
        261251716002005,
        261251716002001,
        261251711003004,
        261251712002011,
        261251711003015,
        261251712003005,
        261251712003001,
        261251712003007,
        261251716002003
    ],
    "zs:housing10":1324,
    "zs:pop10":2918
},
  "geometry": {"coordinates":[-83.160512,42.462353],"type":"Point"}
}