{
  "type": "Feature",
  "properties": {
    "gn:admin1_code":"WV",
    "gn:admin2_code":"71",
    "gn:asciiname":"Brushy Run",
    "gn:country_code":"US",
    "gn:dem":386,
    "gn:elevation":"389.0",
    "gn:feature_class":"P",
    "gn:feature_code":"PPL",
    "gn:name":"Brushy Run",
    "gn:population":0,
    "gn:timezone":"America/New_York",
    "iso:country":"US",
    "name:azb_x_preferred":[
        "\u0628\u0631\u0627\u0634\u06cc \u0631\u0627\u0646"
    ],
    "name:eng_x_preferred":[
        "Brushy Run"
    ],
    "name:fas_x_preferred":[
        "\u0628\u0631\u0627\u0634\u06cc \u0631\u0627\u0646"
    ],
    "name:und_x_variant":[
        "Brushyrun"
    ],
    "name:vol_x_preferred":[
        "Brushy Run"
    ],
    "wof:name":"Brushy Run",
    "wof:placetype":"locality"
},
  "geometry": {"coordinates":[-79.24754,38.83761],"type":"Point"}
}