{
  "type": "Feature",
  "properties": {
    "gn:admin1_code":"UT",
    "gn:admin2_code":"7.0",
    "gn:asciiname":"Dragerton",
    "gn:country_code":"US",
    "gn:dem":1911,
    "gn:elevation":"1906.0",
    "gn:feature_class":"P",
    "gn:feature_code":"PPL",
    "gn:name":"Dragerton",
    "gn:population":0,
    "gn:timezone":"America/Denver",
    "iso:country":"US",
    "wof:name":"Dragerton",
    "wof:placetype":"locality"
},
  "geometry": {"coordinates":[-110.42127000000001,39.54247],"type":"Point"}
}