{
  "type": "Feature",
  "properties": {
    "gn:admin1_code":"MT",
    "gn:admin2_code":"87.0",
    "gn:asciiname":"Bascom",
    "gn:country_code":"US",
    "gn:dem":893,
    "gn:elevation":"885.0",
    "gn:feature_class":"P",
    "gn:feature_code":"PPL",
    "gn:name":"Bascom",
    "gn:population":0,
    "gn:timezone":"America/Denver",
    "iso:country":"US",
    "name:fas_x_preferred":[
        "\u0628\u0633\u06a9\u0627\u0645"
    ],
    "wof:name":"Bascom",
    "wof:placetype":"locality"
},
  "geometry": {"coordinates":[-107.75342999999999,46.62609000000001],"type":"Point"}
}