{
  "type": "Feature",
  "properties": {
    "gn:admin1_code":"SC",
    "gn:admin2_code":"45.0",
    "gn:asciiname":"Belle Terre Acres",
    "gn:country_code":"US",
    "gn:dem":264,
    "gn:elevation":"250.0",
    "gn:feature_class":"P",
    "gn:feature_code":"PPL",
    "gn:name":"Belle Terre Acres",
    "gn:population":0,
    "gn:timezone":"America/New_York",
    "iso:country":"US",
    "wof:name":"Belle Terre Acres",
    "wof:placetype":"locality"
},
  "geometry": {"coordinates":[-82.41679000000001,34.72456],"type":"Point"}
}