{
  "type": "Feature",
  "properties": {
    "iso:country":"US",
    "name:eng_x_preferred":[
        "Escalante Crossing"
    ],
    "wof:name":"Escalante Crossing",
    "wof:placetype":"neighbourhood",
    "wof:population":343,
    "zs:area_m":2332746.327482,
    "zs:blockids":[
        80679707034054,
        80679711001154,
        80679711001143,
        80679711001156,
        80679711001120,
        80679711001130,
        80679711001128,
        80679711001137,
        80679711001116,
        80679711001125,
        80679711001142,
        80679711001118,
        80679711001136,
        80679711001124,
        80679711001095,
        80679711001152,
        80679711001129,
        80679707013110,
        80679711001144,
        80679711001117,
        80679711001126,
        80679707013109,
        80679711001119,
        80679711001121,
        80679711001141,
        80679711001127,
        80679711001138,
        80679711001151,
        80679711001135,
        80679707013108,
        80679711001131,
        80679711001158,
        80679711001150,
        80679711001153,
        80679711001164,
        80679711001132,
        80679711001159,
        80679711001140,
        80679711001155,
        80679711001139,
        80679711001133,
        80679711001163
    ],
    "zs:housing10":210,
    "zs:label":"Escalante Crossing",
    "zs:pop10":343
},
  "geometry": {"coordinates":[-107.86174699999999,37.227228],"type":"Point"}
}