{
  "type": "Feature",
  "properties": {
    "gn:admin1_code":"MS",
    "gn:admin2_code":"79.0",
    "gn:asciiname":"Bertice",
    "gn:country_code":"US",
    "gn:dem":122,
    "gn:elevation":"122.0",
    "gn:feature_class":"P",
    "gn:feature_code":"PPL",
    "gn:name":"Bertice",
    "gn:population":0,
    "gn:timezone":"America/Chicago",
    "iso:country":"US",
    "name:eng_x_preferred":[
        "Bertice"
    ],
    "name:und_x_variant":[
        "McDonald"
    ],
    "wof:name":"Bertice",
    "wof:placetype":"locality"
},
  "geometry": {"coordinates":[-89.67785000000001,32.62375],"type":"Point"}
}