{
  "type": "Feature",
  "properties": {
    "gn:admin1_code":"NM",
    "gn:admin2_code":"53",
    "gn:asciiname":"Dusty",
    "gn:country_code":"US",
    "gn:dem":1960,
    "gn:elevation":"1961.0",
    "gn:feature_class":"P",
    "gn:feature_code":"PPL",
    "gn:name":"Dusty",
    "gn:population":0,
    "gn:timezone":"America/Denver",
    "iso:country":"US",
    "name:deu_x_preferred":[
        "Dusty"
    ],
    "wof:name":"Dusty",
    "wof:placetype":"locality"
},
  "geometry": {"coordinates":[-107.65586999999999,33.62701],"type":"Point"}
}