{
  "type": "Feature",
  "properties": {
    "gn:country":"US",
    "gn:fcode":"PPL",
    "gn:population":0,
    "iso:country":"US",
    "name:cym_x_preferred":[
        "Eltopia"
    ],
    "name:deu_x_preferred":[
        "Eltopia"
    ],
    "name:eng_x_preferred":[
        "Eltopia"
    ],
    "name:fra_x_preferred":[
        "Eltopia"
    ],
    "name:hun_x_preferred":[
        "Eltopia"
    ],
    "name:nld_x_preferred":[
        "Eltopia"
    ],
    "name:spa_x_preferred":[
        "Eltopia"
    ],
    "name:und_x_variant":[
        "Hell to Pay"
    ],
    "qs_pg:aaroncc":"US",
    "qs_pg:gn_country":"US",
    "qs_pg:gn_fcode":"PPL",
    "qs_pg:gn_pop":0,
    "qs_pg:name":"Eltopia",
    "qs_pg:name_adm0":"United States",
    "qs_pg:name_adm1":"Washington",
    "qs_pg:photos":23,
    "qs_pg:photos_1k":5,
    "qs_pg:photos_9k":1,
    "qs_pg:photos_9r":1,
    "qs_pg:photos_all":23,
    "qs_pg:photos_sr":1,
    "qs_pg:pop_sr":5,
    "qs_pg:qs_pg_placetype":"locality",
    "qs_pg:qs_pg_placetype_gp":"Town",
    "qs_pg:woe_adm0":23424977,
    "woe:adm0_id":23424977,
    "woe:name_adm0":"United States",
    "woe:name_adm1":"Washington",
    "woe:placetype":"Town",
    "wof:name":"Eltopia",
    "wof:placetype":"locality"
},
  "geometry": {"coordinates":[-119.01723,46.45875],"type":"Point"}
}