{
  "type": "Feature",
  "properties": {
    "gn:admin1_code":"VA",
    "gn:admin2_code":"69",
    "gn:asciiname":"Canterburg",
    "gn:country_code":"US",
    "gn:dem":209,
    "gn:elevation":"212.0",
    "gn:feature_class":"P",
    "gn:feature_code":"PPL",
    "gn:name":"Canterburg",
    "gn:population":0,
    "gn:timezone":"America/New_York",
    "iso:country":"US",
    "wof:name":"Canterburg",
    "wof:placetype":"locality"
},
  "geometry": {"coordinates":[-78.18416999999999,39.04677],"type":"Point"}
}