{
  "type": "Feature",
  "properties": {
    "iso:country":"US",
    "name:ckb_x_preferred":[
        "\u0633\u06cc\u0646\u06af\u0627\u067e\u0648\u0631"
    ],
    "name:eng_x_preferred":[
        "Downtown Core"
    ],
    "name:fas_x_preferred":[
        "\u0645\u0631\u06a9\u0632 \u0634\u0647\u0631 \u0633\u0646\u06af\u0627\u067e\u0648\u0631"
    ],
    "name:fra_x_preferred":[
        "Downtown Core"
    ],
    "name:msa_x_preferred":[
        "Downtown Core"
    ],
    "name:mzn_x_preferred":[
        "\u0633\u0646\u06af\u0627\u067e\u0648\u0631"
    ],
    "name:nau_x_preferred":[
        "Downtown Core"
    ],
    "name:nor_x_preferred":[
        "Downtown Core"
    ],
    "name:por_x_preferred":[
        "\u00c1rea Central de Cingapura"
    ],
    "name:spa_x_preferred":[
        "Downtown Core"
    ],
    "name:tam_x_preferred":[
        "\u0ba8\u0b95\u0bb0 \u0ba8\u0b9f\u0bc1\u0bb5\u0bae\u0bcd"
    ],
    "name:tha_x_preferred":[
        "\u0e14\u0e32\u0e27\u0e19\u0e4c\u0e17\u0e32\u0e27\u0e19\u0e4c\u0e04\u0e2d\u0e23\u0e4c"
    ],
    "name:urd_x_preferred":[
        "\u0645\u0631\u06a9\u0632\u06cc \u0633\u0646\u06af\u0627\u067e\u0648\u0631"
    ],
    "name:vie_x_preferred":[
        "Downtown Core"
    ],
    "name:zho_x_preferred":[
        "\u5e02\u4e2d\u5fc3"
    ],
    "qs:gn_adm0_cc":"US",
    "qs:gn_local":5341704,
    "qs:gn_nam_loc":"davis",
    "qs:gn_namadm1":"CA",
    "qs:local_max":3506,
    "qs:local_sum":14075,
    "qs:localhoods":32,
    "qs:name":"Downtown Core",
    "qs:name_adm0":"United States",
    "qs:name_adm1":"California",
    "qs:name_adm2":"Yolo",
    "qs:name_local":"Davis",
    "qs:photo_max":289,
    "qs:photo_sum":289,
    "qs:placetype":"Suburb",
    "qs:quad_count":1,
    "qs:woe_adm0":23424977,
    "qs:woe_adm1":2347563,
    "qs:woe_adm2":12587726,
    "qs:woe_lau":0,
    "qs:woe_local":2389646,
    "qs:woe_ver":"7.10.0",
    "wd:wordcount":399,
    "wof:lang":[
        "eng"
    ],
    "wof:name":"Downtown Core",
    "wof:placetype":"neighbourhood",
    "wof:population":153,
    "zs:blockids":[
        61130107014023,
        61130107014018,
        61130107014027,
        61130107014017,
        61130107014028,
        61130107014016,
        61130107014026,
        61130107014029,
        61130107014030,
        61130107014005,
        61130107014032,
        61130107014025,
        61130107014022,
        61130107014031,
        61130107014024
    ],
    "zs:housing10":92,
    "zs:pop10":153
},
  "geometry": {"coordinates":[-121.740875,38.542793],"type":"Point"}
}