{
  "type": "Feature",
  "properties": {
    "iso:country":"US",
    "name:ara_x_preferred":[
        "\u0628\u0631\u0627\u064a\u062a\u0648\u0646"
    ],
    "name:cat_x_preferred":[
        "Brighton"
    ],
    "name:deu_x_preferred":[
        "Brighton"
    ],
    "name:eng_x_preferred":[
        "Brighton"
    ],
    "name:eus_x_preferred":[
        "Brighton"
    ],
    "name:fra_x_preferred":[
        "Brighton"
    ],
    "name:hat_x_preferred":[
        "Brighton"
    ],
    "name:ita_x_preferred":[
        "Brighton"
    ],
    "name:nld_x_preferred":[
        "Brighton"
    ],
    "name:pol_x_preferred":[
        "Brighton"
    ],
    "name:spa_x_preferred":[
        "Brighton"
    ],
    "name:swe_x_preferred":[
        "Brighton"
    ],
    "name:urd_x_preferred":[
        "\u0628\u0631\u0627\u0626\u0679\u0646\u060c \u0648\u0631\u0645\u0648\u0646\u0679"
    ],
    "name:urd_x_variant":[
        "\u0628\u0631\u0627\u0626\u0679\u0646"
    ],
    "name:uzb_x_preferred":[
        "Brighton"
    ],
    "name:vol_x_preferred":[
        "Brighton"
    ],
    "qs_pg:aaroncc":"US",
    "qs_pg:name":"Brighton",
    "qs_pg:name_adm0":"United States",
    "qs_pg:name_adm1":"Vermont",
    "qs_pg:photos":70,
    "qs_pg:photos_1k":14,
    "qs_pg:photos_9k":1,
    "qs_pg:photos_9r":2,
    "qs_pg:photos_all":73,
    "qs_pg:photos_sr":2,
    "qs_pg:pop_sr":0,
    "qs_pg:qs_pg_placetype":"locality",
    "qs_pg:qs_pg_placetype_gp":"Town",
    "qs_pg:woe_adm0":23424977,
    "woe:adm0_id":23424977,
    "woe:name_adm0":"United States",
    "woe:name_adm1":"Vermont",
    "woe:placetype":"Town",
    "wof:name":"Brighton",
    "wof:placetype":"locality"
},
  "geometry": {"coordinates":[-71.881957,44.814951],"type":"Point"}
}