{
  "type": "Feature",
  "properties": {
    "gn:admin1_code":"WA",
    "gn:admin2_code":"61.0",
    "gn:asciiname":"Atlasta Mobile Park",
    "gn:country_code":"US",
    "gn:dem":154,
    "gn:elevation":"156.0",
    "gn:feature_class":"P",
    "gn:feature_code":"PPL",
    "gn:name":"Atlasta Mobile Park",
    "gn:population":0,
    "gn:timezone":"America/Los_Angeles",
    "iso:country":"US",
    "wof:name":"Atlasta Mobile Park",
    "wof:placetype":"locality"
},
  "geometry": {"coordinates":[-122.26984,47.87557],"type":"Point"}
}