{
  "type": "Feature",
  "properties": {
    "gn:admin1_code":"MS",
    "gn:admin2_code":"29.0",
    "gn:asciiname":"Dentville",
    "gn:country_code":"US",
    "gn:dem":86,
    "gn:elevation":"81.0",
    "gn:feature_class":"P",
    "gn:feature_code":"PPL",
    "gn:name":"Dentville",
    "gn:population":0,
    "gn:timezone":"America/Chicago",
    "iso:country":"US",
    "name:eng_x_preferred":[
        "Dentville"
    ],
    "name:und_x_variant":[
        "Pine Bluff"
    ],
    "wof:name":"Dentville",
    "wof:placetype":"locality"
},
  "geometry": {"coordinates":[-90.55537,31.95988],"type":"Point"}
}