{
  "type": "Feature",
  "properties": {
    "gn:admin1_code":"MO",
    "gn:admin2_code":"209.0",
    "gn:admin3_code":"75004.0",
    "gn:asciiname":"Union City",
    "gn:country_code":"US",
    "gn:dem":413,
    "gn:elevation":"408.0",
    "gn:feature_class":"P",
    "gn:feature_code":"PPL",
    "gn:name":"Union City",
    "gn:population":0,
    "gn:timezone":"America/Chicago",
    "iso:country":"US",
    "name:vol_x_preferred":[
        "Union City"
    ],
    "wof:name":"Union City",
    "wof:placetype":"locality"
},
  "geometry": {"coordinates":[-93.46575,36.97894],"type":"Point"}
}