{
  "type": "Feature",
  "properties": {
    "gn:admin1_code":"FL",
    "gn:admin2_code":"99",
    "gn:asciiname":"Fremd Village-Padgett Island",
    "gn:country_code":"US",
    "gn:dem":7,
    "gn:elevation":"4.0",
    "gn:feature_class":"P",
    "gn:feature_code":"PPL",
    "gn:name":"Fremd Village-Padgett Island",
    "gn:population":0,
    "gn:timezone":"America/New_York",
    "iso:country":"US",
    "name:ceb_x_preferred":[
        "Fremd Village-Padgett Island"
    ],
    "name:new_x_preferred":[
        "\u092b\u094d\u0930\u0947\u092e\u094d\u0921 \u092d\u093f\u0932\u0947\u091c \u092a\u094d\u092f\u093e\u091c\u0947\u091f \u0906\u0907\u0932\u094d\u092f\u093e\u0928\u094d\u0921"
    ],
    "name:nld_x_preferred":[
        "Fremd Village-Padgett Island"
    ],
    "name:por_x_preferred":[
        "Fremd Village-Padgett Island"
    ],
    "name:rus_x_preferred":[
        "\u0424\u0440\u0435\u043c\u0434-\u0412\u0438\u043b\u0438\u0434\u0436-\u041f\u0430\u0434\u0436\u0435\u0442\u0442-\u0410\u0439\u043b\u0435\u043d\u0434"
    ],
    "name:und_x_variant":[
        "Fremd Village-Padgett Island CDP"
    ],
    "name:uzb_x_preferred":[
        "Fremd Village-Padgett Island"
    ],
    "name:zho_x_preferred":[
        "\u5f17\u502b\u5fb7-\u5e15\u5947\u7279\u5cf6"
    ],
    "wof:name":"Fremd Village-Padgett Island",
    "wof:placetype":"locality"
},
  "geometry": {"coordinates":[-80.65496,26.8048],"type":"Point"}
}