{
  "type": "Feature",
  "properties": {
    "iso:country":"US",
    "name:eng_x_preferred":[
        "Park Grove"
    ],
    "wof:name":"Park Grove",
    "wof:placetype":"neighbourhood",
    "wof:population":3447,
    "zs:area_m":5263560.91588,
    "zs:blockids":[
        370810154023010,
        370810154023013,
        370810154023008,
        370810154024061,
        370810154023021,
        370810127051031,
        370810154023011,
        370810119051003,
        370810127052024,
        370810127052019,
        370810127052004,
        370810154023007,
        370810127042001,
        370810127051001,
        370810127041007,
        370810127052006,
        370810154023023,
        370810127051011,
        370810127052002,
        370810127051023,
        370810127052009,
        370810154023017,
        370810154023018,
        370810154023002,
        370810154023020,
        370810154023005,
        370810154023015,
        370810154023019,
        370810154023000,
        370810127041012,
        370810127051017,
        370810127051019,
        370810127051022,
        370810127052003,
        370810127052005,
        370810128031006,
        370810127042000,
        370810154023003,
        370810154023004,
        370810127051028,
        370810127051016,
        370810127052010,
        370810127052001,
        370810154023012,
        370810154024063,
        370810154023025,
        370810127052008,
        370810154023031,
        370810154024062,
        370810154023016,
        370810154023009,
        370810127051012,
        370810154023001,
        370810154024066,
        370810154023006,
        370810127051018,
        370810127052007,
        370810127051020,
        370810127041008,
        370810127042002,
        370810127051029,
        370810154024067,
        370810154023022,
        370810154023014
    ],
    "zs:housing10":1541,
    "zs:label":"Park Grove",
    "zs:pop10":3447
},
  "geometry": {"coordinates":[-79.74583800000001,36.117521],"type":"Point"}
}