{
  "type": "Feature",
  "properties": {
    "gn:admin1_code":"ME",
    "gn:admin2_code":"25.0",
    "gn:admin3_code":"64850.0",
    "gn:asciiname":"Johnson Corner",
    "gn:country_code":"US",
    "gn:dem":92,
    "gn:elevation":"92.0",
    "gn:feature_class":"P",
    "gn:feature_code":"PPL",
    "gn:name":"Johnson Corner",
    "gn:population":0,
    "gn:timezone":"America/New_York",
    "iso:country":"US",
    "wof:name":"Johnson Corner",
    "wof:placetype":"locality"
},
  "geometry": {"coordinates":[-69.32144,44.90978],"type":"Point"}
}