{
  "type": "Feature",
  "properties": {
    "iso:country":"US",
    "name:eng_x_preferred":[
        "Biscayne Park"
    ],
    "wd:wordcount":11,
    "wof:name":"Biscayne Park",
    "wof:placetype":"neighbourhood",
    "wof:population":123,
    "zs:area_m":22433.474685,
    "zs:blockids":[
        120860003081023
    ],
    "zs:housing10":59,
    "zs:label":"Biscayne Park",
    "zs:pop10":123
},
  "geometry": {"coordinates":[-80.19539399999999,25.884887],"type":"Point"}
}