{
  "type": "Feature",
  "properties": {
    "gn:admin1_code":"TX",
    "gn:admin2_code":"215",
    "gn:asciiname":"Edinburg Acres Colonia",
    "gn:country_code":"US",
    "gn:dem":31,
    "gn:elevation":"26.0",
    "gn:feature_class":"P",
    "gn:feature_code":"PPL",
    "gn:name":"Edinburg Acres Colonia",
    "gn:population":0,
    "gn:timezone":"America/Chicago",
    "iso:country":"US",
    "wof:name":"Edinburg Acres Colonia",
    "wof:placetype":"locality"
},
  "geometry": {"coordinates":[-98.09028000000001,26.38146],"type":"Point"}
}