{
  "type": "Feature",
  "properties": {
    "gn:admin1_code":"NY",
    "gn:admin2_code":"119.0",
    "gn:admin3_code":"84077.0",
    "gn:asciiname":"Croton Heights",
    "gn:country_code":"US",
    "gn:dem":169,
    "gn:elevation":"159.0",
    "gn:feature_class":"P",
    "gn:feature_code":"PPL",
    "gn:name":"Croton Heights",
    "gn:population":0,
    "gn:timezone":"America/New_York",
    "iso:country":"US",
    "wof:name":"Croton Heights",
    "wof:placetype":"locality"
},
  "geometry": {"coordinates":[-73.78346999999999,41.24676],"type":"Point"}
}