{
  "type": "Feature",
  "properties": {
    "gn:admin1_code":"FL",
    "gn:admin2_code":"127.0",
    "gn:asciiname":"Volusia",
    "gn:country_code":"US",
    "gn:dem":18,
    "gn:elevation":"5.0",
    "gn:feature_class":"P",
    "gn:feature_code":"PPL",
    "gn:name":"Volusia",
    "gn:population":0,
    "gn:timezone":"America/New_York",
    "iso:country":"US",
    "name:azb_x_preferred":[
        "\u0648\u0644\u0648\u0634\u0627"
    ],
    "name:fas_x_preferred":[
        "\u0648\u0644\u0648\u0634\u0627"
    ],
    "name:fra_x_preferred":[
        "Volusia"
    ],
    "name:vol_x_preferred":[
        "Volusia"
    ],
    "name:zho_x_preferred":[
        "\u798f\u797f\u559c\u96c5"
    ],
    "wof:name":"Volusia",
    "wof:placetype":"locality"
},
  "geometry": {"coordinates":[-81.5209,29.16859],"type":"Point"}
}