{
  "type": "Feature",
  "properties": {
    "gn:country":"US",
    "gn:fcode":"PPL",
    "gn:population":0,
    "iso:country":"US",
    "name:ara_x_preferred":[
        "\u0628\u0644\u0645\u0648\u0646\u062a"
    ],
    "name:bar_x_preferred":[
        "Belmont"
    ],
    "name:bre_x_preferred":[
        "Belmont"
    ],
    "name:cat_x_preferred":[
        "Belmont"
    ],
    "name:ceb_x_preferred":[
        "Belmont"
    ],
    "name:deu_x_preferred":[
        "Belmont"
    ],
    "name:epo_x_preferred":[
        "Belmont"
    ],
    "name:est_x_preferred":[
        "Belmont"
    ],
    "name:fas_x_preferred":[
        "\u0628\u0644\u0645\u0648\u0646\u062a"
    ],
    "name:fin_x_preferred":[
        "Belmont"
    ],
    "name:fra_x_preferred":[
        "Belmont"
    ],
    "name:heb_x_preferred":[
        "\u05d1\u05dc\u05de\u05d5\u05e0\u05d8"
    ],
    "name:hun_x_preferred":[
        "Belmont"
    ],
    "name:ita_x_preferred":[
        "Belmont"
    ],
    "name:jpn_x_preferred":[
        "\u30d9\u30eb\u30e2\u30f3\u30c9"
    ],
    "name:mlg_x_preferred":[
        "Belmont"
    ],
    "name:nds_x_preferred":[
        "Belmont"
    ],
    "name:nld_x_preferred":[
        "Belmont"
    ],
    "name:nor_x_preferred":[
        "Belmont"
    ],
    "name:oci_x_preferred":[
        "B\u00e8lmont"
    ],
    "name:pms_x_preferred":[
        "Belmont"
    ],
    "name:pol_x_preferred":[
        "Belmont"
    ],
    "name:por_x_preferred":[
        "Belmont"
    ],
    "name:ron_x_preferred":[
        "Belmont"
    ],
    "name:rus_x_preferred":[
        "\u0411\u0435\u043b\u043c\u043e\u043d\u0442"
    ],
    "name:slk_x_preferred":[
        "Belmont"
    ],
    "name:slv_x_preferred":[
        "Belmont"
    ],
    "name:spa_x_preferred":[
        "Belmont"
    ],
    "name:srp_x_preferred":[
        "\u0411\u0435\u043b\u043c\u043e\u043d\u0442"
    ],
    "name:swa_x_preferred":[
        "Belmont"
    ],
    "name:swe_x_preferred":[
        "Belmont"
    ],
    "name:ukr_x_preferred":[
        "\u0411\u0435\u043b\u043c\u043e\u043d\u0442"
    ],
    "name:vol_x_preferred":[
        "Belmont"
    ],
    "qs_pg:aaroncc":"US",
    "qs_pg:gn_country":"US",
    "qs_pg:gn_fcode":"PPL",
    "qs_pg:gn_pop":0,
    "qs_pg:name":"Belmont",
    "qs_pg:name_adm0":"United States",
    "qs_pg:name_adm1":"Maryland",
    "qs_pg:photos":19,
    "qs_pg:photos_1k":4,
    "qs_pg:photos_9k":1,
    "qs_pg:photos_9r":1,
    "qs_pg:photos_all":19,
    "qs_pg:photos_sr":1,
    "qs_pg:pop_sr":0,
    "qs_pg:qs_pg_placetype":"locality",
    "qs_pg:qs_pg_placetype_gp":"Town",
    "qs_pg:woe_adm0":23424977,
    "woe:adm0_id":23424977,
    "woe:name_adm0":"United States",
    "woe:name_adm1":"Maryland",
    "woe:placetype":"Town",
    "wof:name":"Belmont",
    "wof:placetype":"locality"
},
  "geometry": {"coordinates":[-76.75386,39.30733],"type":"Point"}
}