{
  "type": "Feature",
  "properties": {
    "gn:admin1_code":"OH",
    "gn:admin2_code":"35.0",
    "gn:admin3_code":"83622.0",
    "gn:asciiname":"Bradley Woods",
    "gn:country_code":"US",
    "gn:dem":240,
    "gn:elevation":"226.0",
    "gn:feature_class":"P",
    "gn:feature_code":"PPL",
    "gn:name":"Bradley Woods",
    "gn:population":0,
    "gn:timezone":"America/New_York",
    "iso:country":"US",
    "wof:name":"Bradley Woods",
    "wof:placetype":"locality"
},
  "geometry": {"coordinates":[-81.96120000000001,41.4187],"type":"Point"}
}