{
  "type": "Feature",
  "properties": {
    "gn:admin1_code":"NC",
    "gn:admin2_code":"81",
    "gn:admin3_code":"91656.0",
    "gn:asciiname":"Greesons Crossroads",
    "gn:country_code":"US",
    "gn:dem":222,
    "gn:elevation":"215.0",
    "gn:feature_class":"P",
    "gn:feature_code":"PPL",
    "gn:name":"Greesons Crossroads",
    "gn:population":0,
    "gn:timezone":"America/New_York",
    "iso:country":"US",
    "wof:name":"Greesons Crossroads",
    "wof:placetype":"locality"
},
  "geometry": {"coordinates":[-79.63864000000002,36.03486],"type":"Point"}
}