{
  "type": "Feature",
  "properties": {
    "gn:admin1_code":"TX",
    "gn:admin2_code":"141.0",
    "gn:asciiname":"Gurdev Colonia",
    "gn:country_code":"US",
    "gn:dem":1113,
    "gn:elevation":"1115.0",
    "gn:feature_class":"P",
    "gn:feature_code":"PPL",
    "gn:name":"Gurdev Colonia",
    "gn:population":0,
    "gn:timezone":"America/Denver",
    "iso:country":"US",
    "wof:name":"Gurdev Colonia",
    "wof:placetype":"locality"
},
  "geometry": {"coordinates":[-106.27665,31.664],"type":"Point"}
}