{
  "type": "Feature",
  "properties": {
    "gn:admin1_code":"ME",
    "gn:admin2_code":"19.0",
    "gn:admin3_code":"44270.0",
    "gn:asciiname":"Jordan Mills",
    "gn:country_code":"US",
    "gn:dem":66,
    "gn:elevation":"65.0",
    "gn:feature_class":"P",
    "gn:feature_code":"PPL",
    "gn:name":"Jordan Mills",
    "gn:population":0,
    "gn:timezone":"America/New_York",
    "iso:country":"US",
    "name:ita_x_preferred":[
        "Jordan Mills"
    ],
    "wof:name":"Jordan Mills",
    "wof:placetype":"locality"
},
  "geometry": {"coordinates":[-68.37919000000001,45.55339],"type":"Point"}
}