{
  "type": "Feature",
  "properties": {
    "gn:admin1_code":"KY",
    "gn:admin2_code":"167",
    "gn:asciiname":"Riverview Estates",
    "gn:country_code":"US",
    "gn:dem":259,
    "gn:elevation":"257.0",
    "gn:feature_class":"P",
    "gn:feature_code":"PPL",
    "gn:name":"Riverview Estates",
    "gn:population":0,
    "gn:timezone":"America/New_York",
    "iso:country":"US",
    "wof:name":"Riverview Estates",
    "wof:placetype":"locality"
},
  "geometry": {"coordinates":[-84.8694,37.75674],"type":"Point"}
}