{
  "type": "Feature",
  "properties": {
    "iso:country":"US",
    "name:eng_x_preferred":[
        "Condie"
    ],
    "name:fra_x_preferred":[
        "Condy"
    ],
    "wd:wordcount":150,
    "wof:name":"Condie",
    "wof:placetype":"neighbourhood",
    "wof:population":116,
    "zs:area_m":84996.335223,
    "zs:blockids":[
        490351135381000,
        490351134101016
    ],
    "zs:housing10":33,
    "zs:label":"Condie",
    "zs:pop10":116
},
  "geometry": {"coordinates":[-112.003771,40.682645],"type":"Point"}
}