{
  "type": "Feature",
  "properties": {
    "gn:country":"US",
    "gn:fcode":"PPL",
    "gn:population":0,
    "iso:country":"US",
    "name:ara_x_preferred":[
        "\u0632\u0642\u0627\u0642"
    ],
    "name:cat_x_preferred":[
        "Carrer\u00f3"
    ],
    "name:dan_x_preferred":[
        "Str\u00e6de"
    ],
    "name:epo_x_preferred":[
        "Strateto"
    ],
    "name:fas_x_preferred":[
        "\u06a9\u0648\u0686\u0647"
    ],
    "name:fra_x_preferred":[
        "Ruelle"
    ],
    "name:heb_x_preferred":[
        "\u05e1\u05de\u05d8\u05d4"
    ],
    "name:ido_x_preferred":[
        "Aleo"
    ],
    "name:ind_x_preferred":[
        "Gang"
    ],
    "name:ita_x_preferred":[
        "Vicolo"
    ],
    "name:lim_x_preferred":[
        "Gats"
    ],
    "name:nld_x_preferred":[
        "Steeg"
    ],
    "name:ron_x_preferred":[
        "Stradel\u0103"
    ],
    "name:spa_x_preferred":[
        "Callej\u00f3n"
    ],
    "name:swe_x_preferred":[
        "Gr\u00e4nd"
    ],
    "name:tur_x_preferred":[
        "Dar sokak"
    ],
    "qs_pg:aaroncc":"US",
    "qs_pg:gn_country":"US",
    "qs_pg:gn_fcode":"PPL",
    "qs_pg:gn_pop":0,
    "qs_pg:name":"Alley",
    "qs_pg:name_adm0":"United States",
    "qs_pg:name_adm1":"Missouri",
    "qs_pg:photos":132,
    "qs_pg:photos_1k":27,
    "qs_pg:photos_9k":1,
    "qs_pg:photos_9r":3,
    "qs_pg:photos_all":132,
    "qs_pg:photos_sr":3,
    "qs_pg:pop_sr":0,
    "qs_pg:qs_pg_placetype":"locality",
    "qs_pg:qs_pg_placetype_gp":"Town",
    "qs_pg:woe_adm0":23424977,
    "woe:adm0_id":23424977,
    "woe:name_adm0":"United States",
    "woe:name_adm1":"Missouri",
    "woe:placetype":"Town",
    "wof:name":"Alley",
    "wof:placetype":"locality"
},
  "geometry": {"coordinates":[-91.44347,37.15227],"type":"Point"}
}