{
  "type": "Feature",
  "properties": {
    "gn:admin1_code":"AR",
    "gn:admin2_code":"75.0",
    "gn:admin3_code":"90582.0",
    "gn:asciiname":"Whiskerville",
    "gn:country_code":"US",
    "gn:dem":79,
    "gn:elevation":"79.0",
    "gn:feature_class":"P",
    "gn:feature_code":"PPL",
    "gn:name":"Whiskerville",
    "gn:population":0,
    "gn:timezone":"America/Chicago",
    "iso:country":"US",
    "wof:name":"Whiskerville",
    "wof:placetype":"locality"
},
  "geometry": {"coordinates":[-90.81317,36.11979],"type":"Point"}
}