{
  "type": "Feature",
  "properties": {
    "gn:admin1_code":"GA",
    "gn:admin2_code":"201.0",
    "gn:asciiname":"Bellview",
    "gn:country_code":"US",
    "gn:dem":48,
    "gn:elevation":"43.0",
    "gn:feature_class":"P",
    "gn:feature_code":"PPL",
    "gn:name":"Bellview",
    "gn:population":0,
    "gn:timezone":"America/New_York",
    "iso:country":"US",
    "name:deu_x_preferred":[
        "Bellview"
    ],
    "name:eng_x_preferred":[
        "Bellview"
    ],
    "name:und_x_variant":[
        "Bait"
    ],
    "wof:name":"Bellview",
    "wof:placetype":"locality"
},
  "geometry": {"coordinates":[-84.59936,31.15741],"type":"Point"}
}