{
  "type": "Feature",
  "properties": {
    "gn:admin1_code":"IN",
    "gn:admin2_code":"105.0",
    "gn:admin3_code":"78542.0",
    "gn:asciiname":"Elwren",
    "gn:country_code":"US",
    "gn:dem":259,
    "gn:elevation":"256.0",
    "gn:feature_class":"P",
    "gn:feature_code":"PPL",
    "gn:name":"Elwren",
    "gn:population":0,
    "gn:timezone":"America/Indiana/Indianapolis",
    "iso:country":"US",
    "wof:name":"Elwren",
    "wof:placetype":"locality"
},
  "geometry": {"coordinates":[-86.66972,39.10866],"type":"Point"}
}