{
  "type": "Feature",
  "properties": {
    "gn:admin1_code":"GA",
    "gn:admin2_code":"305",
    "gn:asciiname":"Drawdy",
    "gn:country_code":"US",
    "gn:dem":41,
    "gn:elevation":"35.0",
    "gn:feature_class":"P",
    "gn:feature_code":"PPL",
    "gn:name":"Drawdy",
    "gn:population":0,
    "gn:timezone":"America/New_York",
    "iso:country":"US",
    "wof:name":"Drawdy",
    "wof:placetype":"locality"
},
  "geometry": {"coordinates":[-81.91928,31.6266],"type":"Point"}
}