{
  "type": "Feature",
  "properties": {
    "iso:country":"US",
    "name:eng_x_preferred":[
        "Fairfield Commons"
    ],
    "wof:name":"Fairfield Commons",
    "wof:placetype":"neighbourhood",
    "zs:area_m":54189.613451,
    "zs:blockids":[
        281059506012031,
        281059506012030
    ],
    "zs:housing10":0,
    "zs:label":"Fairfield Commons",
    "zs:pop10":0
},
  "geometry": {"coordinates":[-88.79704099999999,33.438282],"type":"Point"}
}