{
  "type": "Feature",
  "properties": {
    "gn:admin1_code":"MI",
    "gn:admin2_code":"53.0",
    "gn:admin3_code":"84380.0",
    "gn:asciiname":"Thayer",
    "gn:country_code":"US",
    "gn:dem":479,
    "gn:elevation":"480.0",
    "gn:feature_class":"P",
    "gn:feature_code":"PPL",
    "gn:name":"Thayer",
    "gn:population":0,
    "gn:timezone":"America/Menominee",
    "iso:country":"US",
    "wof:name":"Thayer",
    "wof:placetype":"locality"
},
  "geometry": {"coordinates":[-89.46209,46.32911],"type":"Point"}
}