{
  "type": "Feature",
  "properties": {
    "gn:admin1_code":"GA",
    "gn:admin2_code":"217.0",
    "gn:asciiname":"Dialtown",
    "gn:country_code":"US",
    "gn:dem":247,
    "gn:elevation":"245.0",
    "gn:feature_class":"P",
    "gn:feature_code":"PPL",
    "gn:name":"Dialtown",
    "gn:population":0,
    "gn:timezone":"America/New_York",
    "iso:country":"US",
    "wof:name":"Dialtown",
    "wof:placetype":"locality"
},
  "geometry": {"coordinates":[-83.86324,33.64734],"type":"Point"}
}