{
  "type": "Feature",
  "properties": {
    "gn:admin1_code":"TN",
    "gn:admin2_code":"75.0",
    "gn:asciiname":"Christmasville",
    "gn:country_code":"US",
    "gn:dem":102,
    "gn:elevation":"98.0",
    "gn:feature_class":"P",
    "gn:feature_code":"PPL",
    "gn:name":"Christmasville",
    "gn:population":0,
    "gn:timezone":"America/Chicago",
    "iso:country":"US",
    "wof:name":"Christmasville",
    "wof:placetype":"locality"
},
  "geometry": {"coordinates":[-89.29507,35.68285],"type":"Point"}
}