{
  "type": "Feature",
  "properties": {
    "iso:country":"US",
    "name:eng_x_preferred":[
        "Lake Ruth Villa"
    ],
    "wof:name":"Lake Ruth Villa",
    "wof:placetype":"neighbourhood",
    "wof:population":1135,
    "zs:area_m":1481941.090576,
    "zs:blockids":[
        121050141253026,
        121050141252002,
        121050141253014,
        121050141252001,
        121050141252020,
        121050141252018,
        121050141252026,
        121050141252027,
        121050141252043,
        121050141252024,
        121050141253000,
        121050141253022,
        121050141252040,
        121050141252044,
        121050141211075,
        121050141253024,
        121050141253018,
        121050141252009,
        121050141252042,
        121050141253016,
        121050141211092,
        121050141252030,
        121050141252016,
        121050141252000,
        121050141253013,
        121050141253021,
        121050141252003,
        121050141252045,
        121050141252017,
        121050141252019,
        121050141252046,
        121050141252025,
        121050141253020,
        121050141253023,
        121050141253027,
        121050141252023,
        121050141252028,
        121050141252039,
        121050141252029,
        121050141252032,
        121050141253001,
        121050141253011,
        121050141253010,
        121050141253009,
        121050141253019,
        121050141252021,
        121050141252022,
        121050141253012,
        121050141253017
    ],
    "zs:housing10":441,
    "zs:label":"Lake Ruth Villa",
    "zs:pop10":1135
},
  "geometry": {"coordinates":[-81.61568800000001,28.025546],"type":"Point"}
}