{
  "type": "Feature",
  "properties": {
    "gn:admin1_code":"PA",
    "gn:admin2_code":"113.0",
    "gn:admin3_code":"13000.0",
    "gn:asciiname":"Shinerville",
    "gn:country_code":"US",
    "gn:dem":608,
    "gn:elevation":"603.0",
    "gn:feature_class":"P",
    "gn:feature_code":"PPL",
    "gn:name":"Shinerville",
    "gn:population":0,
    "gn:timezone":"America/New_York",
    "iso:country":"US",
    "name:eng_x_preferred":[
        "Shinerville"
    ],
    "name:und_x_variant":[
        "Shinersville"
    ],
    "wof:name":"Shinerville",
    "wof:placetype":"locality"
},
  "geometry": {"coordinates":[-76.38188000000002,41.48758],"type":"Point"}
}