{
  "type": "Feature",
  "properties": {
    "gn:admin1_code":"NV",
    "gn:admin2_code":"1.0",
    "gn:asciiname":"Dixie Valley",
    "gn:country_code":"US",
    "gn:dem":1049,
    "gn:elevation":"1047.0",
    "gn:feature_class":"P",
    "gn:feature_code":"PPL",
    "gn:name":"Dixie Valley",
    "gn:population":0,
    "gn:timezone":"America/Los_Angeles",
    "iso:country":"US",
    "name:eng_x_preferred":[
        "Dixie Valley"
    ],
    "name:por_x_preferred":[
        "Dixie Valley"
    ],
    "name:spa_x_preferred":[
        "Dixie Valley"
    ],
    "name:und_x_variant":[
        "Dixie Valley Settlement"
    ],
    "name:vol_x_preferred":[
        "Dixie Valley"
    ],
    "wof:name":"Dixie Valley",
    "wof:placetype":"locality"
},
  "geometry": {"coordinates":[-118.08069,39.6877],"type":"Point"}
}