{
  "type": "Feature",
  "properties": {
    "gn:admin1_code":"ME",
    "gn:admin2_code":"3.0",
    "gn:admin3_code":"26735.0",
    "gn:asciiname":"Upper Frenchville",
    "gn:country_code":"US",
    "gn:dem":157,
    "gn:elevation":"158.0",
    "gn:feature_class":"P",
    "gn:feature_code":"PPL",
    "gn:name":"Upper Frenchville",
    "gn:population":0,
    "gn:timezone":"America/New_York",
    "iso:country":"US",
    "wof:name":"Upper Frenchville",
    "wof:placetype":"locality"
},
  "geometry": {"coordinates":[-68.42449000000001,47.28004],"type":"Point"}
}