{
  "type": "Feature",
  "properties": {
    "gn:admin1_code":"FL",
    "gn:admin2_code":"105.0",
    "gn:asciiname":"Oak Meadows Mobile Home Park",
    "gn:country_code":"US",
    "gn:dem":39,
    "gn:elevation":"33.0",
    "gn:feature_class":"P",
    "gn:feature_code":"PPL",
    "gn:name":"Oak Meadows Mobile Home Park",
    "gn:population":0,
    "gn:timezone":"America/New_York",
    "iso:country":"US",
    "wof:name":"Oak Meadows Mobile Home Park",
    "wof:placetype":"campus"
},
  "geometry": {"coordinates":[-81.59488,28.11265],"type":"Point"}
}