{
  "type": "Feature",
  "properties": {
    "gn:admin1_code":"IN",
    "gn:admin2_code":"37.0",
    "gn:admin3_code":"31324.0",
    "gn:asciiname":"Kellerville",
    "gn:country_code":"US",
    "gn:dem":192,
    "gn:elevation":"189.0",
    "gn:feature_class":"P",
    "gn:feature_code":"PPL",
    "gn:name":"Kellerville",
    "gn:population":0,
    "gn:timezone":"America/Indiana/Vincennes",
    "iso:country":"US",
    "wof:name":"Kellerville",
    "wof:placetype":"locality"
},
  "geometry": {"coordinates":[-86.83166,38.48172],"type":"Point"}
}