{
  "type": "Feature",
  "properties": {
    "gn:admin1_code":"OH",
    "gn:admin2_code":"33",
    "gn:asciiname":"Mobile Manor Park",
    "gn:country_code":"US",
    "gn:dem":349,
    "gn:elevation":"351.0",
    "gn:feature_class":"P",
    "gn:feature_code":"PPL",
    "gn:name":"Mobile Manor Park",
    "gn:population":0,
    "gn:timezone":"America/New_York",
    "iso:country":"US",
    "wof:name":"Mobile Manor Park",
    "wof:placetype":"locality"
},
  "geometry": {"coordinates":[-82.73166999999999,40.78917],"type":"Point"}
}