{
  "type": "Feature",
  "properties": {
    "gn:admin1_code":"VA",
    "gn:admin2_code":"147.0",
    "gn:asciiname":"Allens Mill",
    "gn:country_code":"US",
    "gn:dem":168,
    "gn:elevation":"164.0",
    "gn:feature_class":"P",
    "gn:feature_code":"PPL",
    "gn:name":"Allens Mill",
    "gn:population":0,
    "gn:timezone":"America/New_York",
    "iso:country":"US",
    "name:fas_x_preferred":[
        "\u0627\u0644\u06cc\u0646\u0633 \u0645\u06cc\u0644"
    ],
    "wof:name":"Allens Mill",
    "wof:placetype":"locality"
},
  "geometry": {"coordinates":[-78.55221999999998,37.28043],"type":"Point"}
}