{
  "type": "Feature",
  "properties": {
    "iso:country":"US",
    "name:eng_x_preferred":[
        "Prellude 80"
    ],
    "wof:name":"Prellude 80",
    "wof:placetype":"neighbourhood",
    "zs:area_m":8465.335725,
    "zs:blockids":[
        121030259002002
    ],
    "zs:housing10":0,
    "zs:label":"Prellude 80",
    "zs:pop10":0
},
  "geometry": {"coordinates":[-82.802082,27.960036],"type":"Point"}
}