{
  "type": "Feature",
  "properties": {
    "iso:country":"US",
    "name:ceb_x_preferred":[
        "Desert Rock Airport"
    ],
    "name:eng_x_preferred":[
        "Desert Rock Airport"
    ],
    "name:eng_x_variant":[
        "NV65",
        "DRA",
        "KDRA"
    ],
    "name:fas_x_preferred":[
        "\u0641\u0631\u0648\u062f\u06af\u0627\u0647 \u062f\u0632\u0631\u062a \u0631\u0627\u06a9"
    ],
    "name:ron_x_preferred":[
        "Aeroportul Desert Rock"
    ],
    "name:swe_x_preferred":[
        "Desert Rock Airport"
    ],
    "name:tgk_x_preferred":[
        "\u0424\u0443\u0440\u0443\u0434\u0433\u043e\u04b3\u0438 \u0434\u0437\u0440\u0442 \u0440\u043e\u043a"
    ],
    "name:zho_x_preferred":[
        "\u6c99\u6f20\u77f3\u6a5f\u5834"
    ],
    "oa:elevation_ft":"3314",
    "oa:type":"medium_airport",
    "wd:wordcount":106,
    "woe:hierarchy":{
        "country_id":23424977,
        "county_id":12589243,
        "planet_id":1,
        "state_id":2347587
    },
    "wof:name":"Desert Rock Airport",
    "wof:placetype":"campus"
},
  "geometry": {"coordinates":[-116.03277799999999,36.619444],"type":"Point"}
}