{
  "type": "Feature",
  "properties": {
    "gn:admin1_code":"IN",
    "gn:admin2_code":"121.0",
    "gn:admin3_code":"460.0",
    "gn:asciiname":"Piattsville",
    "gn:country_code":"US",
    "gn:dem":205,
    "gn:elevation":"192.0",
    "gn:feature_class":"P",
    "gn:feature_code":"PPL",
    "gn:name":"Piattsville",
    "gn:population":0,
    "gn:timezone":"America/Indiana/Indianapolis",
    "iso:country":"US",
    "name:eng_x_preferred":[
        "Piattsville"
    ],
    "name:und_x_variant":[
        "Van Ness Town"
    ],
    "wof:name":"Piattsville",
    "wof:placetype":"locality"
},
  "geometry": {"coordinates":[-87.12585,39.70449],"type":"Point"}
}