{
  "type": "Feature",
  "properties": {
    "gn:admin1_code":"CA",
    "gn:admin2_code":"19.0",
    "gn:asciiname":"Wildflower",
    "gn:country_code":"US",
    "gn:dem":83,
    "gn:elevation":"82.0",
    "gn:feature_class":"P",
    "gn:feature_code":"PPL",
    "gn:name":"Wildflower",
    "gn:population":0,
    "gn:timezone":"America/Los_Angeles",
    "iso:country":"US",
    "name:eng_x_preferred":[
        "Wildflower"
    ],
    "name:und_x_variant":[
        "Wild Flower"
    ],
    "name:zho_x_preferred":[
        "\u61f7\u5fb7\u5f17\u52de\u723e"
    ],
    "wof:name":"Wildflower",
    "wof:placetype":"locality"
},
  "geometry": {"coordinates":[-119.68319,36.50384],"type":"Point"}
}