{
  "type": "Feature",
  "properties": {
    "iso:country":"US",
    "name:bel_x_preferred":[
        "\u041f\u0440\u043e\u0432\u0456\u0434\u044d\u043d\u0441"
    ],
    "name:bre_x_preferred":[
        "Providence"
    ],
    "name:cat_x_preferred":[
        "Providence"
    ],
    "name:ceb_x_preferred":[
        "Providence"
    ],
    "name:ces_x_preferred":[
        "Providence"
    ],
    "name:dan_x_preferred":[
        "Providence"
    ],
    "name:deu_x_preferred":[
        "Providence"
    ],
    "name:eng_x_preferred":[
        "Providence"
    ],
    "name:epo_x_preferred":[
        "Providenco"
    ],
    "name:fin_x_preferred":[
        "Providence"
    ],
    "name:fra_x_preferred":[
        "Providence"
    ],
    "name:hun_x_preferred":[
        "Providence"
    ],
    "name:ita_x_preferred":[
        "Providence"
    ],
    "name:jpn_x_preferred":[
        "\u30d7\u30ed\u30d3\u30c7\u30f3\u30b9"
    ],
    "name:kor_x_preferred":[
        "\ud504\ub85c\ube44\ub358\uc2a4"
    ],
    "name:nld_x_preferred":[
        "Providence"
    ],
    "name:oci_x_preferred":[
        "Providence"
    ],
    "name:pol_x_preferred":[
        "Providence"
    ],
    "name:por_x_preferred":[
        "Providence"
    ],
    "name:rus_x_preferred":[
        "\u041f\u0440\u043e\u0432\u0438\u0434\u0435\u043d\u0441"
    ],
    "name:sco_x_preferred":[
        "Providence"
    ],
    "name:slk_x_preferred":[
        "Providence"
    ],
    "name:spa_x_preferred":[
        "Providence"
    ],
    "name:srp_x_preferred":[
        "\u041f\u0440\u043e\u0432\u0438\u0434\u0435\u043d\u0441"
    ],
    "name:swe_x_preferred":[
        "Providence"
    ],
    "name:tur_x_preferred":[
        "Providence"
    ],
    "name:ukr_x_preferred":[
        "\u041f\u0440\u043e\u0432\u0456\u0434\u0435\u043d\u0441"
    ],
    "name:urd_x_preferred":[
        "\u067e\u0631\u0648\u0648\u06cc\u0688\u0646\u0633"
    ],
    "name:vol_x_preferred":[
        "Providence"
    ],
    "name:zho_x_preferred":[
        "\u666e\u7f57\u7ef4\u767b\u65af"
    ],
    "wof:name":"Providence",
    "wof:placetype":"neighbourhood",
    "wof:population":4784,
    "zs:area_m":2403371.180253,
    "zs:blockids":[
        470370190043009,
        470370190063005,
        470370190063008,
        470370190043008,
        470370190041005,
        470370190043004,
        470370190043001,
        470370190043002,
        470370189023000,
        470370190032004,
        470370190043007,
        470370190041002,
        470370190033005,
        470370190032005,
        470370190043005,
        470370190041003,
        470370190041004,
        470370190033004,
        470370190063010,
        470370190032006,
        470370190043003,
        470370190063006,
        470370190063009,
        470370190033002,
        470370190033006,
        470370190041000,
        470370190041001,
        470370190043000,
        470370190043006
    ],
    "zs:housing10":1680,
    "zs:label":"Providence",
    "zs:pop10":4784
},
  "geometry": {"coordinates":[-86.71583800000001,36.074844],"type":"Point"}
}