{
  "type": "Feature",
  "properties": {
    "iso:country":"US",
    "name:eng_x_preferred":[
        "Fairmount"
    ],
    "wof:name":"Fairmount",
    "wof:placetype":"neighbourhood"
},
  "geometry": {"coordinates":[-92.18520903611426,46.73086443038245],"type":"Point"}
}