{
  "type": "Feature",
  "properties": {
    "gn:admin1_code":"TX",
    "gn:admin2_code":"231",
    "gn:asciiname":"Hendrix",
    "gn:country_code":"US",
    "gn:dem":168,
    "gn:elevation":"162.0",
    "gn:feature_class":"P",
    "gn:feature_code":"PPL",
    "gn:name":"Hendrix",
    "gn:population":0,
    "gn:timezone":"America/Chicago",
    "iso:country":"US",
    "wof:name":"Hendrix",
    "wof:placetype":"locality"
},
  "geometry": {"coordinates":[-96.23497999999999,33.02179],"type":"Point"}
}