{
  "type": "Feature",
  "properties": {
    "iso:country":"US",
    "name:eng_x_preferred":[
        "Lusk District"
    ],
    "wof:name":"Lusk District",
    "wof:placetype":"neighbourhood"
},
  "geometry": {"coordinates":[-116.21305739216511,43.60695476262654],"type":"Point"}
}