{
  "type": "Feature",
  "properties": {
    "gn:admin1_code":"VA",
    "gn:admin2_code":"29",
    "gn:asciiname":"Eldridge Mill",
    "gn:country_code":"US",
    "gn:dem":117,
    "gn:elevation":"107.0",
    "gn:feature_class":"P",
    "gn:feature_code":"PPL",
    "gn:name":"Eldridge Mill",
    "gn:population":0,
    "gn:timezone":"America/New_York",
    "iso:country":"US",
    "name:eng_x_preferred":[
        "Eldridge Mill"
    ],
    "name:und_x_variant":[
        "Eldridge's Mill",
        "Eldridges Mill"
    ],
    "wof:name":"Eldridge Mill",
    "wof:placetype":"locality"
},
  "geometry": {"coordinates":[-78.46084,37.60987],"type":"Point"}
}