{
  "type": "Feature",
  "properties": {
    "iso:country":"US",
    "name:eng_x_preferred":[
        "Rolling Green"
    ],
    "wof:name":"Rolling Green",
    "wof:placetype":"neighbourhood",
    "zs:area_m":38178.076461,
    "zs:blockids":[
        191530104052023,
        191530104053007
    ],
    "zs:housing10":0,
    "zs:label":"Rolling Green",
    "zs:pop10":0
},
  "geometry": {"coordinates":[-93.734706,41.62974],"type":"Point"}
}