{
  "type": "Feature",
  "properties": {
    "gn:admin1_code":"TX",
    "gn:admin2_code":"493",
    "gn:asciiname":"Dewees",
    "gn:country_code":"US",
    "gn:dem":133,
    "gn:elevation":"131.0",
    "gn:feature_class":"P",
    "gn:feature_code":"PPL",
    "gn:name":"Dewees",
    "gn:population":0,
    "gn:timezone":"America/Chicago",
    "iso:country":"US",
    "wof:name":"Dewees",
    "wof:placetype":"locality"
},
  "geometry": {"coordinates":[-98.17223,29.02053],"type":"Point"}
}