{
  "type": "Feature",
  "properties": {
    "gn:admin1_code":"AL",
    "gn:admin2_code":"57",
    "gn:asciiname":"Pea Ridge",
    "gn:country_code":"US",
    "gn:dem":184,
    "gn:elevation":"183.0",
    "gn:feature_class":"P",
    "gn:feature_code":"PPL",
    "gn:name":"Pea Ridge",
    "gn:population":0,
    "gn:timezone":"America/Chicago",
    "iso:country":"US",
    "name:cat_x_preferred":[
        "Pea Ridge"
    ],
    "name:ceb_x_preferred":[
        "Pea Ridge"
    ],
    "name:deu_x_preferred":[
        "Pea Ridge"
    ],
    "name:ita_x_preferred":[
        "Pea Ridge"
    ],
    "name:nld_x_preferred":[
        "Pea Ridge"
    ],
    "name:pol_x_preferred":[
        "Pea Ridge"
    ],
    "name:por_x_preferred":[
        "Pea Ridge"
    ],
    "name:srp_x_preferred":[
        "\u041f\u0438 \u0420\u0438\u045f"
    ],
    "name:vol_x_preferred":[
        "Pea Ridge"
    ],
    "wof:name":"Pea Ridge",
    "wof:placetype":"locality"
},
  "geometry": {"coordinates":[-87.57001,33.73344],"type":"Point"}
}