{
  "type": "Feature",
  "properties": {
    "gn:admin1_code":"MD",
    "gn:admin2_code":"25.0",
    "gn:asciiname":"Big Woods",
    "gn:country_code":"US",
    "gn:dem":132,
    "gn:elevation":"135.0",
    "gn:feature_class":"P",
    "gn:feature_code":"PPL",
    "gn:name":"Big Woods",
    "gn:population":0,
    "gn:timezone":"America/New_York",
    "iso:country":"US",
    "wof:name":"Big Woods",
    "wof:placetype":"locality"
},
  "geometry": {"coordinates":[-76.31050999999999,39.56011],"type":"Point"}
}