{
  "type": "Feature",
  "properties": {
    "gn:country":"US",
    "gn:fcode":"PPLX",
    "gn:population":0,
    "iso:country":"US",
    "qs_pg:aaroncc":"US",
    "qs_pg:gn_country":"US",
    "qs_pg:gn_fcode":"PPLX",
    "qs_pg:gn_pop":0,
    "qs_pg:name":"Oak Ridge North",
    "qs_pg:name_adm0":"United States",
    "qs_pg:name_adm1":"Illinois",
    "qs_pg:photos":555,
    "qs_pg:photos_1k":112,
    "qs_pg:photos_9k":2,
    "qs_pg:photos_9r":5,
    "qs_pg:photos_all":555,
    "qs_pg:photos_sr":8,
    "qs_pg:pop_sr":0,
    "qs_pg:qs_pg_placetype":"neighbourhood",
    "qs_pg:qs_pg_placetype_gp":"Suburb",
    "qs_pg:woe_adm0":23424977,
    "woe:adm0_id":23424977,
    "woe:name_adm0":"United States",
    "woe:name_adm1":"Illinois",
    "woe:placetype":"Suburb",
    "wof:name":"Oak Ridge North",
    "wof:placetype":"neighbourhood"
},
  "geometry": {"coordinates":[-88.08897,42.16475],"type":"Point"}
}