{
  "type": "Feature",
  "properties": {
    "iso:country":"US",
    "name:eng_x_preferred":[
        "North of Foothill"
    ],
    "wof:name":"North of Foothill",
    "wof:placetype":"neighbourhood",
    "wof:population":9319,
    "zs:blockids":[
        60710008121022,
        60710020152013,
        60710020152012,
        60710020152017,
        60710020152005,
        60710020152007,
        60710008121020,
        60710008121018,
        60710020151019,
        60710020151015,
        60710020161011,
        60710008121014,
        60710008121013,
        60710020162001,
        60710020162006,
        60710020151010,
        60710020152008,
        60710020161001,
        60710020151013,
        60710020151017,
        60710008121011,
        60710008121023,
        60710008121010,
        60710008121008,
        60710020162002,
        60710020161000,
        60710020152014,
        60710020151003,
        60710020161005,
        60710020152010,
        60710008121024,
        60710008121026,
        60710008121017,
        60710008121000,
        60710020273002,
        60710020162007,
        60710020151004,
        60710020151014,
        60710020152016,
        60710020161007,
        60710020161009,
        60710020161014,
        60710020161004,
        60710020151016,
        60710020152011,
        60710020152001,
        60710020152006,
        60710008121025,
        60710008121021,
        60710008121012,
        60710008121001,
        60710008121019,
        60710020161003,
        60710020151002,
        60710020273003,
        60710020151012,
        60710020161006,
        60710020161002,
        60710008121016,
        60710020151011,
        60710020152015,
        60710020152004,
        60710020152002,
        60710020152009,
        60710020161013,
        60710020161012,
        60710020152003,
        60710008122001,
        60710008192025,
        60710008122000,
        60710008121015,
        60710008121009,
        60710020162003,
        60710020162004,
        60710020162000,
        60710020151018,
        60710020151008,
        60710020151001,
        60710020162005,
        60710020161008,
        60710020161010,
        60710020152000,
        60374002051067,
        60374002051071,
        60374002051089,
        60374002051073,
        60374002051076,
        60374002051074
    ],
    "zs:housing10":3080,
    "zs:label":"North of Foothill",
    "zs:pop10":9319
},
  "geometry": {"coordinates":[-117.692241,34.145481],"type":"Point"}
}