{
  "type": "Feature",
  "properties": {
    "gn:admin1_code":"OH",
    "gn:admin2_code":"133.0",
    "gn:admin3_code":"24584.0",
    "gn:asciiname":"Bloody Corners",
    "gn:country_code":"US",
    "gn:dem":336,
    "gn:elevation":"335.0",
    "gn:feature_class":"P",
    "gn:feature_code":"PPL",
    "gn:name":"Bloody Corners",
    "gn:population":0,
    "gn:timezone":"America/New_York",
    "iso:country":"US",
    "wof:name":"Bloody Corners",
    "wof:placetype":"locality"
},
  "geometry": {"coordinates":[-81.12175999999999,41.11756],"type":"Point"}
}