{
  "type": "Feature",
  "properties": {
    "gn:admin1_code":"KS",
    "gn:admin2_code":"205.0",
    "gn:admin3_code":"49675.0",
    "gn:asciiname":"Hilford",
    "gn:country_code":"US",
    "gn:dem":252,
    "gn:elevation":"247.0",
    "gn:feature_class":"P",
    "gn:feature_code":"PPL",
    "gn:name":"Hilford",
    "gn:population":0,
    "gn:timezone":"America/Chicago",
    "iso:country":"US",
    "wof:name":"Hilford",
    "wof:placetype":"locality"
},
  "geometry": {"coordinates":[-95.67665,37.44978],"type":"Point"}
}