{
  "type": "Feature",
  "properties": {
    "gn:admin1_code":"AR",
    "gn:admin2_code":"141.0",
    "gn:admin3_code":"93984.0",
    "gn:asciiname":"Alread",
    "gn:country_code":"US",
    "gn:dem":513,
    "gn:elevation":"512.0",
    "gn:feature_class":"P",
    "gn:feature_code":"PPL",
    "gn:name":"Alread",
    "gn:population":0,
    "gn:timezone":"America/Chicago",
    "iso:country":"US",
    "name:zho_x_preferred":[
        "\u963f\u91cc\u5fb7"
    ],
    "wof:name":"Alread",
    "wof:placetype":"locality"
},
  "geometry": {"coordinates":[-92.67989,35.63286],"type":"Point"}
}