{
  "type": "Feature",
  "properties": {
    "iso:country":"US",
    "name:eng_x_preferred":[
        "Rocky Springs"
    ],
    "wof:name":"Rocky Springs",
    "wof:placetype":"neighbourhood",
    "wof:population":78,
    "zs:area_m":306209.75806,
    "zs:blockids":[
        240217512033009
    ],
    "zs:housing10":33,
    "zs:label":"Rocky Springs",
    "zs:pop10":78
},
  "geometry": {"coordinates":[-77.46099599999999,39.450983],"type":"Point"}
}