{
  "type": "Feature",
  "properties": {
    "gn:admin1_code":"AR",
    "gn:admin2_code":"47.0",
    "gn:admin3_code":"92454.0",
    "gn:asciiname":"South Ozark",
    "gn:country_code":"US",
    "gn:dem":122,
    "gn:elevation":"116.0",
    "gn:feature_class":"P",
    "gn:feature_code":"PPL",
    "gn:name":"South Ozark",
    "gn:population":0,
    "gn:timezone":"America/Chicago",
    "iso:country":"US",
    "wof:name":"South Ozark",
    "wof:placetype":"locality"
},
  "geometry": {"coordinates":[-93.83103,35.48036],"type":"Point"}
}