{
  "type": "Feature",
  "properties": {
    "gn:admin1_code":"NC",
    "gn:admin2_code":"57",
    "gn:admin3_code":"90328.0",
    "gn:asciiname":"Jubilee",
    "gn:country_code":"US",
    "gn:dem":242,
    "gn:elevation":"241.0",
    "gn:feature_class":"P",
    "gn:feature_code":"PPL",
    "gn:name":"Jubilee",
    "gn:population":0,
    "gn:timezone":"America/New_York",
    "iso:country":"US",
    "name:dan_x_preferred":[
        "Jubil\u00e6um"
    ],
    "name:deu_x_preferred":[
        "Jubil\u00e4um"
    ],
    "name:fra_x_preferred":[
        "Jubil\u00e9"
    ],
    "name:mhr_x_preferred":[
        "\u041b\u04f1\u043c\u0433\u0435\u0447\u0435"
    ],
    "name:nld_x_preferred":[
        "Jubileum"
    ],
    "name:pol_x_preferred":[
        "Jubileusz"
    ],
    "name:rus_x_preferred":[
        "\u042e\u0431\u0438\u043b\u0435\u0439"
    ],
    "name:swe_x_preferred":[
        "Jubileum"
    ],
    "name:ukr_x_preferred":[
        "\u042e\u0432\u0456\u043b\u0435\u0439"
    ],
    "wof:name":"Jubilee",
    "wof:placetype":"locality"
},
  "geometry": {"coordinates":[-80.42617,35.76319],"type":"Point"}
}