{
  "type": "Feature",
  "properties": {
    "iso:country":"US",
    "name:eng_x_preferred":[
        "Toccoa Rg Letourneau Field Airport"
    ],
    "name:eng_x_variant":[
        "TOC",
        "KTOC"
    ],
    "oa:elevation_ft":"996",
    "oa:type":"small_airport",
    "woe:hierarchy":{
        "country_id":23424977,
        "county_id":12587996,
        "planet_id":1,
        "state_id":2347569
    },
    "wof:name":"Toccoa Rg Letourneau Field Airport",
    "wof:placetype":"campus"
},
  "geometry": {"coordinates":[-83.296388888889,34.592777777778],"type":"Point"}
}