{
  "type": "Feature",
  "properties": {
    "gn:admin1_code":"AL",
    "gn:admin2_code":"3.0",
    "gn:asciiname":"River Park",
    "gn:country_code":"US",
    "gn:dem":17,
    "gn:elevation":"6.0",
    "gn:feature_class":"P",
    "gn:feature_code":"PPL",
    "gn:name":"River Park",
    "gn:population":0,
    "gn:timezone":"America/Chicago",
    "iso:country":"US",
    "name:ceb_x_preferred":[
        "River Park"
    ],
    "name:swe_x_preferred":[
        "River Park"
    ],
    "wof:name":"River Park",
    "wof:placetype":"locality"
},
  "geometry": {"coordinates":[-87.81193,30.45075],"type":"Point"}
}