{
  "type": "Feature",
  "properties": {
    "iso:country":"US",
    "name:eng_x_preferred":[
        "Bloomingville"
    ],
    "name:fra_x_preferred":[
        "Bloomingville"
    ],
    "name:jpn_x_preferred":[
        "\u30d6\u30eb\u30fc\u30df\u30f3\u30b0\u30f4\u30a3\u30eb"
    ],
    "name:lld_x_preferred":[
        "Bloomingville"
    ],
    "name:und_x_variant":[
        "Blommingville"
    ],
    "name:vol_x_preferred":[
        "Bloomingville"
    ],
    "qs:gn_fcode":"PPL",
    "qs:gn_local":0,
    "qs:gn_namadm1":"OH",
    "qs:gn_name":"Bloomingville",
    "qs:local_max":5301,
    "qs:local_sum":8576,
    "qs:localhoods":9,
    "qs:name":"Bloomingville",
    "qs:name_adm0":"United States",
    "qs:name_adm1":"Ohio",
    "qs:name_adm2":"Erie",
    "qs:name_local":"Sandusky",
    "qs:photo_max":1,
    "qs:photo_sum":1,
    "qs:placetype":"Suburb",
    "qs:quad_count":1,
    "qs:woe_adm0":23424977,
    "qs:woe_adm1":2347594,
    "qs:woe_adm2":12589548,
    "qs:woe_lau":0,
    "qs:woe_local":2488533,
    "qs:woe_ver":"7.10.0",
    "wd:wordcount":365,
    "wof:lang":[
        "eng"
    ],
    "wof:name":"Bloomingville",
    "wof:placetype":"neighbourhood",
    "wof:population":53,
    "zs:blockids":[
        390430418001069
    ],
    "zs:housing10":21,
    "zs:pop10":53
},
  "geometry": {"coordinates":[-82.735291,41.345886],"type":"Point"}
}