{
  "type": "Feature",
  "properties": {
    "gn:admin1_code":"FL",
    "gn:admin2_code":"55.0",
    "gn:asciiname":"Lake Gardens Mobile Home Park",
    "gn:country_code":"US",
    "gn:dem":31,
    "gn:elevation":"26.0",
    "gn:feature_class":"P",
    "gn:feature_code":"PPL",
    "gn:name":"Lake Gardens Mobile Home Park",
    "gn:population":0,
    "gn:timezone":"America/New_York",
    "iso:country":"US",
    "wof:name":"Lake Gardens Mobile Home Park",
    "wof:placetype":"campus"
},
  "geometry": {"coordinates":[-81.35129999999999,27.304],"type":"Point"}
}