{
  "type": "Feature",
  "properties": {
    "gn:admin1_code":"VA",
    "gn:admin2_code":"161",
    "gn:asciiname":"La Bellevue",
    "gn:country_code":"US",
    "gn:dem":379,
    "gn:elevation":"381.0",
    "gn:feature_class":"P",
    "gn:feature_code":"PPL",
    "gn:name":"La Bellevue",
    "gn:population":0,
    "gn:timezone":"America/New_York",
    "iso:country":"US",
    "wof:name":"La Bellevue",
    "wof:placetype":"locality"
},
  "geometry": {"coordinates":[-79.89948000000003,37.32375],"type":"Point"}
}