{
  "type": "Feature",
  "properties": {
    "gn:admin1_code":"SC",
    "gn:admin2_code":"89.0",
    "gn:asciiname":"Gourdin",
    "gn:country_code":"US",
    "gn:dem":31,
    "gn:elevation":"22.0",
    "gn:feature_class":"P",
    "gn:feature_code":"PPL",
    "gn:name":"Gourdin",
    "gn:population":0,
    "gn:timezone":"America/New_York",
    "iso:country":"US",
    "name:eng_x_preferred":[
        "Gourdin"
    ],
    "name:und_x_variant":[
        "Gourdins Depot"
    ],
    "wof:name":"Gourdin",
    "wof:placetype":"locality"
},
  "geometry": {"coordinates":[-79.89591,33.4835],"type":"Point"}
}