{
  "type": "Feature",
  "properties": {
    "gn:admin1_code":"DE",
    "gn:admin2_code":"5.0",
    "gn:asciiname":"Springfield Crossroads",
    "gn:country_code":"US",
    "gn:dem":12,
    "gn:elevation":"12.0",
    "gn:feature_class":"P",
    "gn:feature_code":"PPL",
    "gn:name":"Springfield Crossroads",
    "gn:population":0,
    "gn:timezone":"America/New_York",
    "iso:country":"US",
    "name:eng_x_preferred":[
        "Springfield Crossroads"
    ],
    "name:und_x_variant":[
        "Springfield"
    ],
    "name:zho_x_preferred":[
        "\u65af\u666e\u6797\u83f2\u723e\u5fb7\u514b\u7f85\u65af\u7f85\u8332"
    ],
    "wof:name":"Springfield Crossroads",
    "wof:placetype":"locality"
},
  "geometry": {"coordinates":[-75.30769000000002,38.68261],"type":"Point"}
}