{
  "type": "Feature",
  "properties": {
    "gn:admin1_code":"WA",
    "gn:admin2_code":"53.0",
    "gn:asciiname":"Rhododendron Park",
    "gn:country_code":"US",
    "gn:dem":195,
    "gn:elevation":"193.0",
    "gn:feature_class":"P",
    "gn:feature_code":"PPL",
    "gn:name":"Rhododendron Park",
    "gn:population":0,
    "gn:timezone":"America/Los_Angeles",
    "iso:country":"US",
    "wof:name":"Rhododendron Park",
    "wof:placetype":"locality"
},
  "geometry": {"coordinates":[-122.16095,47.15177],"type":"Point"}
}