{
  "type": "Feature",
  "properties": {
    "gn:admin1_code":"GA",
    "gn:admin2_code":"251",
    "gn:asciiname":"Sheppards",
    "gn:country_code":"US",
    "gn:dem":53,
    "gn:elevation":"48.0",
    "gn:feature_class":"P",
    "gn:feature_code":"PPL",
    "gn:name":"Sheppards",
    "gn:population":0,
    "gn:timezone":"America/New_York",
    "iso:country":"US",
    "name:eng_x_preferred":[
        "Sheppards"
    ],
    "name:und_x_variant":[
        "Shepard",
        "Sheppard"
    ],
    "wof:name":"Sheppards",
    "wof:placetype":"locality"
},
  "geometry": {"coordinates":[-81.53511,32.63739],"type":"Point"}
}