{
  "type": "Feature",
  "properties": {
    "gn:admin1_code":"IA",
    "gn:admin2_code":"123.0",
    "gn:admin3_code":"94722.0",
    "gn:asciiname":"Tioga",
    "gn:country_code":"US",
    "gn:dem":243,
    "gn:elevation":"244.0",
    "gn:feature_class":"P",
    "gn:feature_code":"PPL",
    "gn:name":"Tioga",
    "gn:population":0,
    "gn:timezone":"America/Chicago",
    "iso:country":"US",
    "wof:name":"Tioga",
    "wof:placetype":"locality"
},
  "geometry": {"coordinates":[-92.42241,41.29695],"type":"Point"}
}