{
  "type": "Feature",
  "properties": {
    "gn:admin1_code":"VA",
    "gn:admin2_code":"93",
    "gn:asciiname":"Burwell Bay",
    "gn:country_code":"US",
    "gn:dem":15,
    "gn:elevation":"0.0",
    "gn:feature_class":"P",
    "gn:feature_code":"PPL",
    "gn:name":"Burwell Bay",
    "gn:population":0,
    "gn:timezone":"America/New_York",
    "iso:country":"US",
    "wof:name":"Burwell Bay",
    "wof:placetype":"locality"
},
  "geometry": {"coordinates":[-76.66829,37.05543],"type":"Point"}
}