{
  "type": "Feature",
  "properties": {
    "gn:admin1_code":"AR",
    "gn:admin2_code":"119.0",
    "gn:admin3_code":"91731.0",
    "gn:asciiname":"Rolling Hills",
    "gn:country_code":"US",
    "gn:dem":121,
    "gn:elevation":"119.0",
    "gn:feature_class":"P",
    "gn:feature_code":"PPL",
    "gn:name":"Rolling Hills",
    "gn:population":0,
    "gn:timezone":"America/Chicago",
    "iso:country":"US",
    "name:cat_x_preferred":[
        "Rolling Hills"
    ],
    "name:ceb_x_preferred":[
        "Rolling Hills"
    ],
    "name:deu_x_preferred":[
        "Rolling Hills"
    ],
    "name:fra_x_preferred":[
        "Rolling Hills"
    ],
    "name:ita_x_preferred":[
        "Rolling Hills"
    ],
    "name:nld_x_preferred":[
        "Rolling Hills"
    ],
    "name:pol_x_preferred":[
        "Rolling Hills"
    ],
    "name:por_x_preferred":[
        "Rolling Hills"
    ],
    "name:rus_x_preferred":[
        "\u0420\u043e\u043b\u043b\u0438\u043d\u0433-\u0425\u0438\u043b\u0441"
    ],
    "name:srp_x_preferred":[
        "\u0420\u043e\u043b\u0438\u043d\u0433 \u0425\u0438\u043b\u0441"
    ],
    "name:swe_x_preferred":[
        "Rolling Hills"
    ],
    "name:vol_x_preferred":[
        "Rolling Hills"
    ],
    "wof:name":"Rolling Hills",
    "wof:placetype":"locality"
},
  "geometry": {"coordinates":[-92.1057,34.95898],"type":"Point"}
}