{
  "type": "Feature",
  "properties": {
    "iso:country":"US",
    "name:eng_x_preferred":[
        "Steel Point"
    ],
    "wof:name":"Steel Point",
    "wof:placetype":"neighbourhood",
    "zs:area_m":159104.233921,
    "zs:blockids":[
        90010740001034,
        90010740001035,
        90010740001036,
        90010740002021
    ],
    "zs:housing10":0,
    "zs:label":"Steel Point",
    "zs:pop10":0
},
  "geometry": {"coordinates":[-73.181483,41.176373],"type":"Point"}
}