{
  "type": "Feature",
  "properties": {
    "gn:admin1_code":"NC",
    "gn:admin2_code":"183.0",
    "gn:admin3_code":"92440.0",
    "gn:asciiname":"McCullers",
    "gn:country_code":"US",
    "gn:dem":118,
    "gn:elevation":"118.0",
    "gn:feature_class":"P",
    "gn:feature_code":"PPL",
    "gn:name":"McCullers",
    "gn:population":0,
    "gn:timezone":"America/New_York",
    "iso:country":"US",
    "name:eng_x_preferred":[
        "McCullers"
    ],
    "name:und_x_variant":[
        "McCuller"
    ],
    "wof:name":"McCullers",
    "wof:placetype":"locality"
},
  "geometry": {"coordinates":[-78.69584,35.66099000000001],"type":"Point"}
}