{
  "type": "Feature",
  "properties": {
    "gn:admin1_code":"OH",
    "gn:admin2_code":"21.0",
    "gn:admin3_code":"69078.0",
    "gn:asciiname":"Meadows of North Lewisburg",
    "gn:country_code":"US",
    "gn:dem":348,
    "gn:elevation":"348.0",
    "gn:feature_class":"P",
    "gn:feature_code":"PPL",
    "gn:name":"Meadows of North Lewisburg",
    "gn:population":0,
    "gn:timezone":"America/New_York",
    "iso:country":"US",
    "wof:name":"Meadows of North Lewisburg",
    "wof:placetype":"locality"
},
  "geometry": {"coordinates":[-83.56860999999998,40.21333],"type":"Point"}
}