{
  "type": "Feature",
  "properties": {
    "iso:country":"US",
    "name:eng_x_preferred":[
        "Lynn Pointe"
    ],
    "wof:name":"Lynn Pointe",
    "wof:placetype":"neighbourhood",
    "wof:population":1513,
    "zs:area_m":942960.874083,
    "zs:blockids":[
        371830537262014,
        371830537251011,
        371830537251018,
        371830537251017,
        371830537251020,
        371830537262002,
        371830537262013,
        371830537251008,
        371830537252026,
        371830537251023,
        371830537262003,
        371830537251006,
        371830537251007,
        371830537262005,
        371830537251024,
        371830537262001,
        371830537262004
    ],
    "zs:housing10":794,
    "zs:label":"Lynn Pointe",
    "zs:pop10":1513
},
  "geometry": {"coordinates":[-78.715138,35.874496],"type":"Point"}
}