{
  "type": "Feature",
  "properties": {
    "gn:admin1_code":"MA",
    "gn:admin2_code":"17.0",
    "gn:admin3_code":"61590.0",
    "gn:asciiname":"Woodsville",
    "gn:country_code":"US",
    "gn:dem":90,
    "gn:elevation":"83.0",
    "gn:feature_class":"P",
    "gn:feature_code":"PPL",
    "gn:name":"Woodsville",
    "gn:population":0,
    "gn:timezone":"America/New_York",
    "iso:country":"US",
    "name:deu_x_preferred":[
        "Woodsville"
    ],
    "name:eng_x_preferred":[
        "Woodsville"
    ],
    "name:srp_x_preferred":[
        "\u0411\u043e\u0434\u0441\u0432\u0438\u043b"
    ],
    "name:und_x_variant":[
        "Woods Village"
    ],
    "wof:name":"Woodsville",
    "wof:placetype":"locality"
},
  "geometry": {"coordinates":[-71.62451,42.57342],"type":"Point"}
}