{
  "type": "Feature",
  "properties": {
    "iso:country":"US",
    "name:eng_x_preferred":[
        "Emerald Green"
    ],
    "wof:name":"Emerald Green",
    "wof:placetype":"neighbourhood",
    "wof:population":2344,
    "zs:area_m":37041406.937049,
    "zs:blockids":[
        361059513003025,
        361059513001085,
        361059517002009,
        361059513001084,
        361059517003038,
        361059517001067,
        361059517001084,
        361059517002012,
        361059517002034,
        361059517003043,
        361059517002051,
        361059517002044,
        361059517001076,
        361059513003020,
        361059513003023,
        361059517002027,
        361059517002033,
        361059513001082,
        361059513003011,
        361059517002013,
        361059517002014,
        361059517002053,
        361059513003015,
        361059517004104,
        361059513003018,
        361059513003016,
        361059513001078,
        361059517002011,
        361059517002017,
        361059517003037,
        361059517002037,
        361059517001075,
        361059513001079,
        361059513003003,
        361059517001070,
        361059517002019,
        361059517002031,
        361059517001086,
        361059513003017,
        361059517001061,
        361059517001074,
        361059517001078,
        361059517002042,
        361059517001069,
        361059517002049,
        361059513001081,
        361059517002036,
        361059517002022,
        361059517002029,
        361059517003042,
        361059517002040,
        361059517002045,
        361059517002004,
        361059517002054,
        361059517003045,
        361059513003022,
        361059517001079,
        361059517002000,
        361059517002035,
        361059513003012,
        361059517003034,
        361059517002041,
        361059517002028,
        361059517001081,
        361059517002003,
        361059513003024,
        361059513001083,
        361059517003036,
        361059513003019,
        361059513001080,
        361059513001077,
        361059517001077,
        361059513003021,
        361059517001085,
        361059513003010,
        361059517002038,
        361059517001001,
        361059513003033,
        361059517001071,
        361059517001062,
        361059517002048,
        361059517002052,
        361059517002006,
        361059517002043,
        361059517003044,
        361059513003014,
        361059517001083,
        361059517001065,
        361059517002018,
        361059517002039,
        361059517001072,
        361059517002021,
        361059517002005,
        361059517002020,
        361059517002032,
        361059513001088,
        361059517002047,
        361059517002023,
        361059513003032,
        361059517002007,
        361059517001068,
        361059517001082,
        361059517001063,
        361059517001064,
        361059517001073,
        361059517002008,
        361059517002030,
        361059517002015,
        361059517002046,
        361059517002016,
        361059517002050,
        361059517002010,
        361059517003039,
        361059517003046,
        361059517002024,
        361059517002001
    ],
    "zs:housing10":1810,
    "zs:label":"Emerald Green",
    "zs:pop10":2344
},
  "geometry": {"coordinates":[-74.589241,41.601773],"type":"Point"}
}