{
  "type": "Feature",
  "properties": {
    "iso:country":"US",
    "name:eng_x_preferred":[
        "Bronxville Manor"
    ],
    "qs:gn_adm0_cc":"US",
    "qs:gn_local":5116118,
    "qs:gn_nam_loc":"Eastchester, Westchester, New York, US",
    "qs:gn_namadm1":"NY",
    "qs:local_max":896,
    "qs:local_sum":1134,
    "qs:localhoods":4,
    "qs:name":"Bronxville Manor",
    "qs:name_adm0":"United States",
    "qs:name_adm1":"New York",
    "qs:name_adm2":"Westchester",
    "qs:name_local":"Eastchester",
    "qs:photo_max":65,
    "qs:photo_sum":130,
    "qs:placetype":"Suburb",
    "qs:quad_count":7,
    "qs:woe_adm0":23424977,
    "qs:woe_adm1":2347591,
    "qs:woe_adm2":12589371,
    "qs:woe_lau":0,
    "qs:woe_local":2396381,
    "qs:woe_ver":"7.10.0",
    "wof:lang":[
        "eng"
    ],
    "wof:name":"Bronxville Manor",
    "wof:placetype":"neighbourhood",
    "wof:population":1708,
    "zs:blockids":[
        361190052003013,
        361190052003011,
        361190068024009,
        361190052003008,
        361190052003005,
        361190052001020,
        361190052003000,
        361190052001005,
        361190068024011,
        361190068024020,
        361190066001007,
        361190068024006,
        361190052001004,
        361190052001019,
        361190052001002,
        361190066001011,
        361190066001009,
        361190068024012,
        361190068024008,
        361190066001006,
        361190068024018,
        361190066001008,
        361190068024021,
        361190066001000,
        361190068024004,
        361190066001013,
        361190052003010,
        361190068024005,
        361190052001021,
        361190068024010,
        361190068024019,
        361190066001001,
        361190066002005,
        361190052003012,
        361190066001012,
        361190052003007,
        361190066005000,
        361190066001002,
        361190066001010,
        361190052001007
    ],
    "zs:housing10":587,
    "zs:pop10":1708
},
  "geometry": {"coordinates":[-73.80202199999999,40.935598],"type":"Point"}
}