{
  "type": "Feature",
  "properties": {
    "gn:admin1_code":"OH",
    "gn:admin2_code":"171.0",
    "gn:admin3_code":"8630.0",
    "gn:asciiname":"Bridgewater Center",
    "gn:country_code":"US",
    "gn:dem":277,
    "gn:elevation":"278.0",
    "gn:feature_class":"P",
    "gn:feature_code":"PPL",
    "gn:name":"Bridgewater Center",
    "gn:population":0,
    "gn:timezone":"America/New_York",
    "iso:country":"US",
    "name:eng_x_preferred":[
        "Bridgewater Center"
    ],
    "name:und_x_variant":[
        "Bridgewater"
    ],
    "wof:name":"Bridgewater Center",
    "wof:placetype":"locality"
},
  "geometry": {"coordinates":[-84.63079,41.65811],"type":"Point"}
}