{
  "type": "Feature",
  "properties": {
    "gn:admin1_code":"AR",
    "gn:admin2_code":"27.0",
    "gn:admin3_code":"93822.0",
    "gn:asciiname":"Bright",
    "gn:country_code":"US",
    "gn:dem":114,
    "gn:elevation":"111.0",
    "gn:feature_class":"P",
    "gn:feature_code":"PPL",
    "gn:name":"Bright",
    "gn:population":0,
    "gn:timezone":"America/Chicago",
    "iso:country":"US",
    "name:cat_x_preferred":[
        "Bright"
    ],
    "name:ceb_x_preferred":[
        "Bright"
    ],
    "name:deu_x_preferred":[
        "Bright"
    ],
    "name:fra_x_preferred":[
        "Bright"
    ],
    "name:ita_x_preferred":[
        "Bright"
    ],
    "name:jpn_x_preferred":[
        "\u30d6\u30e9\u30a4\u30c8"
    ],
    "name:kor_x_preferred":[
        "\ube0c\ub77c\uc774\ud2b8"
    ],
    "name:nld_x_preferred":[
        "Bright"
    ],
    "name:pol_x_preferred":[
        "Bright"
    ],
    "name:rus_x_preferred":[
        "\u0411\u0440\u0430\u0439\u0442"
    ],
    "name:swe_x_preferred":[
        "Bright"
    ],
    "name:ukr_x_preferred":[
        "\u0411\u0440\u0430\u0439\u0442"
    ],
    "wof:name":"Bright",
    "wof:placetype":"locality"
},
  "geometry": {"coordinates":[-93.31905999999999,33.41957],"type":"Point"}
}