{
  "type": "Feature",
  "properties": {
    "gn:admin1_code":"FL",
    "gn:admin2_code":"11.0",
    "gn:asciiname":"Taylor's Trailer Park",
    "gn:country_code":"US",
    "gn:dem":9,
    "gn:elevation":"2.0",
    "gn:feature_class":"P",
    "gn:feature_code":"PPL",
    "gn:name":"Taylor's Trailer Park",
    "gn:population":0,
    "gn:timezone":"America/New_York",
    "iso:country":"US",
    "wof:name":"Taylor's Trailer Park",
    "wof:placetype":"campus"
},
  "geometry": {"coordinates":[-80.20419,26.04745],"type":"Point"}
}