{
  "type": "Feature",
  "properties": {
    "gn:admin1_code":"NY",
    "gn:admin2_code":"45.0",
    "gn:admin3_code":"16100.0",
    "gn:asciiname":"Rainbow Shores Mobile Home Park",
    "gn:country_code":"US",
    "gn:dem":88,
    "gn:elevation":"92.0",
    "gn:feature_class":"P",
    "gn:feature_code":"PPL",
    "gn:name":"Rainbow Shores Mobile Home Park",
    "gn:population":0,
    "gn:timezone":"America/New_York",
    "iso:country":"US",
    "wof:name":"Rainbow Shores Mobile Home Park",
    "wof:placetype":"campus"
},
  "geometry": {"coordinates":[-76.03614,44.26011],"type":"Point"}
}