{
  "type": "Feature",
  "properties": {
    "iso:country":"US",
    "name:ceb_x_preferred":[
        "Newhall"
    ],
    "name:deu_x_preferred":[
        "Newhall"
    ],
    "name:fas_x_preferred":[
        "\u0646\u06cc\u0648\u0647\u0627\u0644"
    ],
    "name:fra_x_preferred":[
        "Newhall"
    ],
    "name:ita_x_preferred":[
        "Newhall"
    ],
    "name:nld_x_preferred":[
        "Newhall"
    ],
    "name:pol_x_preferred":[
        "Newhall"
    ],
    "name:swe_x_preferred":[
        "Newhall"
    ],
    "wof:name":"Newhall",
    "wof:placetype":"neighbourhood"
},
  "geometry": {"coordinates":[-72.92687368875401,41.33688281311387],"type":"Point"}
}