{
  "type": "Feature",
  "properties": {
    "gn:country":"US",
    "gn:fcode":"PPL",
    "gn:population":0,
    "iso:country":"US",
    "name:eng_x_preferred":[
        "Manoa"
    ],
    "name:fra_x_preferred":[
        "M\u0101noa"
    ],
    "name:haw_x_preferred":[
        "M\u0101noa"
    ],
    "name:ilo_x_preferred":[
        "Manoa"
    ],
    "name:jpn_x_preferred":[
        "\u30de\u30ce\u30a2"
    ],
    "name:nor_x_preferred":[
        "Manoa"
    ],
    "name:por_x_preferred":[
        "Manoa"
    ],
    "name:und_x_variant":[
        "Monoa"
    ],
    "qs_pg:aaroncc":"US",
    "qs_pg:gn_country":"US",
    "qs_pg:gn_fcode":"PPL",
    "qs_pg:gn_pop":0,
    "qs_pg:name":"Manoa",
    "qs_pg:name_adm0":"United States",
    "qs_pg:name_adm1":"Pennsylvania",
    "qs_pg:photos":10,
    "qs_pg:photos_1k":2,
    "qs_pg:photos_9k":1,
    "qs_pg:photos_9r":1,
    "qs_pg:photos_all":10,
    "qs_pg:photos_sr":1,
    "qs_pg:pop_sr":0,
    "qs_pg:qs_pg_placetype":"locality",
    "qs_pg:qs_pg_placetype_gp":"Town",
    "qs_pg:woe_adm0":23424977,
    "woe:adm0_id":23424977,
    "woe:name_adm0":"United States",
    "woe:name_adm1":"Pennsylvania",
    "woe:placetype":"Town",
    "wof:name":"Manoa",
    "wof:placetype":"locality"
},
  "geometry": {"coordinates":[-75.31797,39.9765],"type":"Point"}
}