{
  "type": "Feature",
  "properties": {
    "gn:admin1_code":"TX",
    "gn:admin2_code":"373.0",
    "gn:asciiname":"Crystal Lakes Country Estates",
    "gn:country_code":"US",
    "gn:dem":100,
    "gn:elevation":"94.0",
    "gn:feature_class":"P",
    "gn:feature_code":"PPL",
    "gn:name":"Crystal Lakes Country Estates",
    "gn:population":0,
    "gn:timezone":"America/Chicago",
    "iso:country":"US",
    "wof:name":"Crystal Lakes Country Estates",
    "wof:placetype":"locality"
},
  "geometry": {"coordinates":[-94.875,30.70833],"type":"Point"}
}