{
  "type": "Feature",
  "properties": {
    "gn:admin1_code":"LA",
    "gn:admin2_code":"79.0",
    "gn:asciiname":"Shady Oaks",
    "gn:country_code":"US",
    "gn:dem":44,
    "gn:elevation":"48.0",
    "gn:feature_class":"P",
    "gn:feature_code":"PPL",
    "gn:name":"Shady Oaks",
    "gn:population":0,
    "gn:timezone":"America/Chicago",
    "iso:country":"US",
    "wof:name":"Shady Oaks",
    "wof:placetype":"locality"
},
  "geometry": {"coordinates":[-92.3468,31.30602],"type":"Point"}
}