{
  "type": "Feature",
  "properties": {
    "gn:elevation":640,
    "iso:country":"US",
    "name:eng_x_preferred":[
        "Pinnacle Peak Heights V-Vi"
    ],
    "qs:gn_adm0_cc":"US",
    "qs:gn_fcode":"PPL",
    "qs:gn_local":5313457,
    "qs:gn_nam_loc":"Scottsdale, Maricopa, Arizona, US",
    "qs:gn_namadm1":"AZ",
    "qs:gn_name":"Pinnacle Peak Heights V-VI",
    "qs:local_max":12909,
    "qs:local_sum":40041,
    "qs:localhoods":43,
    "qs:name":"Pinnacle Peak Heights V-Vi",
    "qs:name_adm0":"United States",
    "qs:name_adm1":"Arizona",
    "qs:name_adm2":"Maricopa",
    "qs:name_local":"Scottsdale",
    "qs:photo_max":1,
    "qs:photo_sum":1,
    "qs:placetype":"Suburb",
    "qs:quad_count":1,
    "qs:woe_adm0":23424977,
    "qs:woe_adm1":2347561,
    "qs:woe_adm2":12587587,
    "qs:woe_funk":"Parented by a neighborhood",
    "qs:woe_lau":0,
    "qs:woe_local":2490057,
    "qs:woe_ver":"7.10.0",
    "wof:lang":[
        "eng"
    ],
    "wof:name":"Pinnacle Peak Heights V-Vi",
    "wof:placetype":"neighbourhood",
    "wof:population":304,
    "zs:blockids":[
        40132168514019,
        40132168512000,
        40132168514022
    ],
    "zs:housing10":147,
    "zs:pop10":304
},
  "geometry": {"coordinates":[-111.871033,33.685497],"type":"Point"}
}