{
  "type": "Feature",
  "properties": {
    "gn:elevation":18,
    "iso:country":"US",
    "name:eng_x_preferred":[
        "Carmantown"
    ],
    "qs:gn_adm0_cc":"US",
    "qs:gn_fcode":"PPL",
    "qs:gn_local":5098765,
    "qs:gn_nam_loc":"hamilton",
    "qs:gn_namadm1":"NJ",
    "qs:gn_name":"Carmantown",
    "qs:local_max":565,
    "qs:local_sum":568,
    "qs:localhoods":3,
    "qs:name":"Carmantown",
    "qs:name_adm0":"United States",
    "qs:name_adm1":"New Jersey",
    "qs:name_adm2":"Atlantic",
    "qs:name_local":"Hamilton",
    "qs:photo_max":1,
    "qs:photo_sum":2,
    "qs:placetype":"Suburb",
    "qs:quad_count":2,
    "qs:woe_adm0":23424977,
    "qs:woe_adm1":2347589,
    "qs:woe_adm2":12589258,
    "qs:woe_funk":"Grouping neighborhood",
    "qs:woe_lau":0,
    "qs:woe_local":28745534,
    "qs:woe_ver":"7.10.0",
    "wof:lang":[
        "eng"
    ],
    "wof:name":"Carmantown",
    "wof:placetype":"neighbourhood",
    "wof:population":30,
    "zs:blockids":[
        340010114011207,
        340010114011261,
        340010114011257
    ],
    "zs:housing10":11,
    "zs:pop10":30
},
  "geometry": {"coordinates":[-74.687805,39.510399],"type":"Point"}
}