{
  "type": "Feature",
  "properties": {
    "gn:admin1_code":"CO",
    "gn:admin2_code":"121.0",
    "gn:asciiname":"Cope",
    "gn:country_code":"US",
    "gn:dem":1348,
    "gn:elevation":"1342.0",
    "gn:feature_class":"P",
    "gn:feature_code":"PPL",
    "gn:name":"Cope",
    "gn:population":0,
    "gn:timezone":"America/Denver",
    "iso:country":"US",
    "name:azb_x_preferred":[
        "\u06a9\u0648\u067e"
    ],
    "name:fas_x_preferred":[
        "\u06a9\u0648\u067e"
    ],
    "name:vol_x_preferred":[
        "Cope"
    ],
    "name:zho_x_preferred":[
        "\u79d1\u666e"
    ],
    "wof:name":"Cope",
    "wof:placetype":"locality"
},
  "geometry": {"coordinates":[-102.85104,39.66388],"type":"Point"}
}