{
  "type": "Feature",
  "properties": {
    "gn:admin1_code":"KY",
    "gn:admin2_code":"3",
    "gn:asciiname":"Eubanks Ford",
    "gn:country_code":"US",
    "gn:dem":179,
    "gn:elevation":"177.0",
    "gn:feature_class":"P",
    "gn:feature_code":"PPL",
    "gn:name":"Eubanks Ford",
    "gn:population":0,
    "gn:timezone":"America/Chicago",
    "iso:country":"US",
    "wof:name":"Eubanks Ford",
    "wof:placetype":"locality"
},
  "geometry": {"coordinates":[-86.4136,36.69254],"type":"Point"}
}