{
  "type": "Feature",
  "properties": {
    "gn:country":"US",
    "gn:fcode":"PPL",
    "gn:population":0,
    "iso:country":"US",
    "qs_pg:aaroncc":"US",
    "qs_pg:gn_country":"US",
    "qs_pg:gn_fcode":"PPL",
    "qs_pg:gn_pop":0,
    "qs_pg:name":"Devils Slide",
    "qs_pg:name_adm0":"United States",
    "qs_pg:name_adm1":"Utah",
    "qs_pg:photos":43,
    "qs_pg:photos_1k":9,
    "qs_pg:photos_9k":1,
    "qs_pg:photos_9r":2,
    "qs_pg:photos_all":43,
    "qs_pg:photos_sr":2,
    "qs_pg:pop_sr":5,
    "qs_pg:qs_pg_placetype":"locality",
    "qs_pg:qs_pg_placetype_gp":"Town",
    "qs_pg:woe_adm0":23424977,
    "woe:adm0_id":23424977,
    "woe:name_adm0":"United States",
    "woe:name_adm1":"Utah",
    "woe:placetype":"Town",
    "wof:name":"Devils Slide",
    "wof:placetype":"locality"
},
  "geometry": {"coordinates":[-111.54326,41.06356],"type":"Point"}
}