{
  "type": "Feature",
  "properties": {
    "gn:admin1_code":"OH",
    "gn:admin2_code":"51.0",
    "gn:admin3_code":"87024.0",
    "gn:asciiname":"South Delta",
    "gn:country_code":"US",
    "gn:dem":214,
    "gn:elevation":"214.0",
    "gn:feature_class":"P",
    "gn:feature_code":"PPL",
    "gn:name":"South Delta",
    "gn:population":0,
    "gn:timezone":"America/New_York",
    "iso:country":"US",
    "name:eng_x_preferred":[
        "South Delta"
    ],
    "name:und_x_variant":[
        "Delta Station"
    ],
    "wof:name":"South Delta",
    "wof:placetype":"locality"
},
  "geometry": {"coordinates":[-83.99995,41.55533],"type":"Point"}
}