{
  "type": "Feature",
  "properties": {
    "gn:admin1_code":"MD",
    "gn:admin2_code":"9.0",
    "gn:asciiname":"Scientists Cliffs",
    "gn:country_code":"US",
    "gn:dem":31,
    "gn:elevation":"32.0",
    "gn:feature_class":"P",
    "gn:feature_code":"PPL",
    "gn:name":"Scientists Cliffs",
    "gn:population":0,
    "gn:timezone":"America/New_York",
    "iso:country":"US",
    "name:eng_x_preferred":[
        "Scientists Cliffs"
    ],
    "name:und_x_variant":[
        "Annes Aggravation",
        "Flippos Folly",
        "Pathologists Quagmire",
        "Scientists Cliff"
    ],
    "wof:name":"Scientists Cliffs",
    "wof:placetype":"locality"
},
  "geometry": {"coordinates":[-76.51329,38.51762],"type":"Point"}
}