{
  "type": "Feature",
  "properties": {
    "gn:admin1_code":"TN",
    "gn:admin2_code":"143",
    "gn:asciiname":"Morgan Springs",
    "gn:country_code":"US",
    "gn:dem":606,
    "gn:elevation":"600.0",
    "gn:feature_class":"P",
    "gn:feature_code":"PPL",
    "gn:name":"Morgan Springs",
    "gn:population":0,
    "gn:timezone":"America/New_York",
    "iso:country":"US",
    "name:eng_x_preferred":[
        "Morgan Springs"
    ],
    "name:und_x_variant":[
        "Scarborough Springs"
    ],
    "wof:name":"Morgan Springs",
    "wof:placetype":"locality"
},
  "geometry": {"coordinates":[-85.1019,35.56146],"type":"Point"}
}