{
  "type": "Feature",
  "properties": {
    "gn:admin1_code":"TX",
    "gn:admin2_code":"135.0",
    "gn:asciiname":"Scharbauer City",
    "gn:country_code":"US",
    "gn:dem":911,
    "gn:elevation":"911.0",
    "gn:feature_class":"P",
    "gn:feature_code":"PPL",
    "gn:name":"Scharbauer City",
    "gn:population":0,
    "gn:timezone":"America/Chicago",
    "iso:country":"US",
    "wof:name":"Scharbauer City",
    "wof:placetype":"locality"
},
  "geometry": {"coordinates":[-102.43042,32.02373],"type":"Point"}
}