{
  "type": "Feature",
  "properties": {
    "gn:admin1_code":"VA",
    "gn:admin2_code":"45",
    "gn:asciiname":"Craig Springs",
    "gn:country_code":"US",
    "gn:dem":593,
    "gn:elevation":"587.0",
    "gn:feature_class":"P",
    "gn:feature_code":"PPL",
    "gn:name":"Craig Springs",
    "gn:population":0,
    "gn:timezone":"America/New_York",
    "iso:country":"US",
    "name:eng_x_preferred":[
        "Craig Springs"
    ],
    "name:und_x_variant":[
        "Craig Healing Springs",
        "Craig Healing Spring"
    ],
    "wof:name":"Craig Springs",
    "wof:placetype":"locality"
},
  "geometry": {"coordinates":[-80.292,37.48485],"type":"Point"}
}