{
  "type": "Feature",
  "properties": {
    "gn:admin1_code":"WI",
    "gn:admin2_code":"73.0",
    "gn:admin3_code":"36325.0",
    "gn:asciiname":"Cherokee",
    "gn:country_code":"US",
    "gn:dem":392,
    "gn:elevation":"388.0",
    "gn:feature_class":"P",
    "gn:feature_code":"PPL",
    "gn:name":"Cherokee",
    "gn:population":0,
    "gn:timezone":"America/Chicago",
    "iso:country":"US",
    "name:fas_x_preferred":[
        "\u0686\u0631\u0648\u06a9\u06cc"
    ],
    "wof:name":"Cherokee",
    "wof:placetype":"locality"
},
  "geometry": {"coordinates":[-90.21791,44.90219],"type":"Point"}
}