{
  "type": "Feature",
  "properties": {
    "gn:admin1_code":"MN",
    "gn:admin2_code":"61.0",
    "gn:admin3_code":"2044.0",
    "gn:asciiname":"Bergville",
    "gn:country_code":"US",
    "gn:dem":429,
    "gn:elevation":"430.0",
    "gn:feature_class":"P",
    "gn:feature_code":"PPL",
    "gn:name":"Bergville",
    "gn:population":0,
    "gn:timezone":"America/Chicago",
    "iso:country":"US",
    "wof:name":"Bergville",
    "wof:placetype":"locality"
},
  "geometry": {"coordinates":[-94.26439000000001,47.78745],"type":"Point"}
}