{
  "type": "Feature",
  "properties": {
    "gn:country":"US",
    "gn:fcode":"PPL",
    "gn:population":0,
    "iso:country":"US",
    "name:ara_x_preferred":[
        "\u062f\u064a\u0648\u064a"
    ],
    "name:cat_x_preferred":[
        "Dewey"
    ],
    "name:ceb_x_preferred":[
        "Dewey"
    ],
    "name:ces_x_preferred":[
        "Dewey"
    ],
    "name:deu_x_preferred":[
        "Dewey"
    ],
    "name:eng_x_preferred":[
        "Dewey"
    ],
    "name:epo_x_preferred":[
        "Dewey"
    ],
    "name:fas_x_preferred":[
        "\u062f\u06cc\u0648\u06cc\u06cc"
    ],
    "name:fin_x_preferred":[
        "Dewey"
    ],
    "name:fra_x_preferred":[
        "Dewey"
    ],
    "name:heb_x_preferred":[
        "\u05d3\u05d9\u05d5\u05d0\u05d9"
    ],
    "name:ita_x_preferred":[
        "Dewey"
    ],
    "name:jpn_x_preferred":[
        "\u30c7\u30e5\u30fc\u30a4"
    ],
    "name:nds_x_preferred":[
        "Dewey"
    ],
    "name:nld_x_preferred":[
        "Dewey"
    ],
    "name:nno_x_preferred":[
        "Dewey"
    ],
    "name:nor_x_preferred":[
        "Dewey"
    ],
    "name:pol_x_preferred":[
        "Dewey"
    ],
    "name:por_x_preferred":[
        "Dewey"
    ],
    "name:rus_x_preferred":[
        "\u0414\u044c\u044e\u0438"
    ],
    "name:spa_x_preferred":[
        "Dewey"
    ],
    "name:srp_x_preferred":[
        "\u0414\u0458\u0443\u0438"
    ],
    "name:swe_x_preferred":[
        "Dewey"
    ],
    "name:tur_x_preferred":[
        "Dewey"
    ],
    "name:ukr_x_preferred":[
        "\u0414\u044c\u044e\u0457"
    ],
    "name:und_x_variant":[
        "Gibraltar"
    ],
    "qs_pg:aaroncc":"US",
    "qs_pg:gn_country":"US",
    "qs_pg:gn_fcode":"PPL",
    "qs_pg:gn_pop":0,
    "qs_pg:name":"Dewey",
    "qs_pg:name_adm0":"United States",
    "qs_pg:name_adm1":"Washington",
    "qs_pg:photos":76,
    "qs_pg:photos_1k":15,
    "qs_pg:photos_9k":1,
    "qs_pg:photos_9r":3,
    "qs_pg:photos_all":76,
    "qs_pg:photos_sr":3,
    "qs_pg:pop_sr":0,
    "qs_pg:qs_pg_placetype":"locality",
    "qs_pg:qs_pg_placetype_gp":"Town",
    "qs_pg:woe_adm0":23424977,
    "woe:adm0_id":23424977,
    "woe:name_adm0":"United States",
    "woe:name_adm1":"Washington",
    "woe:placetype":"Town",
    "wof:name":"Dewey",
    "wof:placetype":"locality"
},
  "geometry": {"coordinates":[-122.60850000000001,48.4251],"type":"Point"}
}