{
  "type": "Feature",
  "properties": {
    "gn:admin1_code":"AZ",
    "gn:admin2_code":"19.0",
    "gn:asciiname":"Cammie's Foothills Vista Mobile Home Park",
    "gn:country_code":"US",
    "gn:dem":735,
    "gn:elevation":"733.0",
    "gn:feature_class":"P",
    "gn:feature_code":"PPL",
    "gn:name":"Cammie's Foothills Vista Mobile Home Park",
    "gn:population":0,
    "gn:timezone":"America/Phoenix",
    "iso:country":"US",
    "wof:name":"Cammie's Foothills Vista Mobile Home Park",
    "wof:placetype":"campus"
},
  "geometry": {"coordinates":[-110.90721000000001,32.26674000000001],"type":"Point"}
}