{
  "type": "Feature",
  "properties": {
    "iso:country":"US",
    "name:eng_x_preferred":[
        "Fairfax"
    ],
    "name:eng_x_variant":[
        "Fairfax District"
    ],
    "name:und_x_variant":[
        "Fairfax Industrial District"
    ],
    "qs:gn_fcode":"PPL",
    "qs:gn_local":0,
    "qs:gn_nam_loc":"Kansas City, Wyandotte, Kansas, US",
    "qs:gn_namadm1":"KS",
    "qs:gn_name":"Fairfax",
    "qs:local_max":4300,
    "qs:local_sum":10961,
    "qs:localhoods":23,
    "qs:name":"Fairfax",
    "qs:name_adm0":"United States",
    "qs:name_adm1":"Kansas",
    "qs:name_adm2":"Wyandotte",
    "qs:name_local":"Kansas City",
    "qs:photo_max":102,
    "qs:photo_sum":269,
    "qs:placetype":"Suburb",
    "qs:quad_count":22,
    "qs:woe_adm0":23424977,
    "qs:woe_adm1":2347575,
    "qs:woe_adm2":12588475,
    "qs:woe_lau":0,
    "qs:woe_local":2430632,
    "qs:woe_ver":"7.10.0",
    "wof:lang":[
        "eng"
    ],
    "wof:name":"Fairfax",
    "wof:placetype":"neighbourhood",
    "zs:blockids":[
        290470221002104,
        290470221002098
    ],
    "zs:housing10":0,
    "zs:pop10":0
},
  "geometry": {"coordinates":[-94.609318,39.145368],"type":"Point"}
}