{
  "type": "Feature",
  "properties": {
    "gn:admin1_code":"PA",
    "gn:admin2_code":"107.0",
    "gn:admin3_code":"53376.0",
    "gn:asciiname":"Duncott",
    "gn:country_code":"US",
    "gn:dem":238,
    "gn:elevation":"237.0",
    "gn:feature_class":"P",
    "gn:feature_code":"PPL",
    "gn:name":"Duncott",
    "gn:population":0,
    "gn:timezone":"America/New_York",
    "iso:country":"US",
    "name:azb_x_preferred":[
        "\u062f\u0627\u0646\u06a9\u0627\u062a"
    ],
    "name:cat_x_preferred":[
        "Duncott"
    ],
    "name:eus_x_preferred":[
        "Duncott"
    ],
    "name:fas_x_preferred":[
        "\u062f\u0627\u0646\u06a9\u0627\u062a"
    ],
    "name:mlg_x_preferred":[
        "Duncott"
    ],
    "name:spa_x_preferred":[
        "Duncott"
    ],
    "name:vol_x_preferred":[
        "Duncott"
    ],
    "wof:name":"Duncott",
    "wof:placetype":"locality"
},
  "geometry": {"coordinates":[-76.24356,40.71203],"type":"Point"}
}