{
  "type": "Feature",
  "properties": {
    "iso:country":"US",
    "name:deu_x_preferred":[
        "Poplar Hall"
    ],
    "wof:name":"Poplar Hall",
    "wof:placetype":"neighbourhood"
},
  "geometry": {"coordinates":[-76.21658065446668,36.85051646677256],"type":"Point"}
}