{
  "type": "Feature",
  "properties": {
    "gn:admin1_code":"AZ",
    "gn:admin2_code":"7.0",
    "gn:asciiname":"Mountain Shadows Mobile Trailer Resort",
    "gn:country_code":"US",
    "gn:dem":1500,
    "gn:elevation":"1501.0",
    "gn:feature_class":"P",
    "gn:feature_code":"PPL",
    "gn:name":"Mountain Shadows Mobile Trailer Resort",
    "gn:population":0,
    "gn:timezone":"America/Phoenix",
    "iso:country":"US",
    "wof:name":"Mountain Shadows Mobile Trailer Resort",
    "wof:placetype":"locality"
},
  "geometry": {"coordinates":[-111.32526,34.23287],"type":"Point"}
}