{
  "type": "Feature",
  "properties": {
    "gn:admin1_code":"TN",
    "gn:admin2_code":"93",
    "gn:asciiname":"Northridge Estates",
    "gn:country_code":"US",
    "gn:dem":329,
    "gn:elevation":"328.0",
    "gn:feature_class":"P",
    "gn:feature_code":"PPL",
    "gn:name":"Northridge Estates",
    "gn:population":0,
    "gn:timezone":"America/New_York",
    "iso:country":"US",
    "wof:name":"Northridge Estates",
    "wof:placetype":"locality"
},
  "geometry": {"coordinates":[-83.92944,36.05861],"type":"Point"}
}