{
  "type": "Feature",
  "properties": {
    "gn:admin1_code":"OH",
    "gn:admin2_code":"113",
    "gn:admin3_code":"77504.0",
    "gn:asciiname":"Catalpa Grove Mobile Home Park",
    "gn:country_code":"US",
    "gn:dem":244,
    "gn:elevation":"241.0",
    "gn:feature_class":"P",
    "gn:feature_code":"PPL",
    "gn:name":"Catalpa Grove Mobile Home Park",
    "gn:population":0,
    "gn:timezone":"America/New_York",
    "iso:country":"US",
    "wof:name":"Catalpa Grove Mobile Home Park",
    "wof:placetype":"campus"
},
  "geometry": {"coordinates":[-84.27194,39.78972],"type":"Point"}
}