{
  "type": "Feature",
  "properties": {
    "iso:country":"US",
    "name:deu_x_preferred":[
        "Towne"
    ],
    "name:eng_x_preferred":[
        "Towne & Country"
    ],
    "wof:name":"Towne & Country",
    "wof:placetype":"neighbourhood",
    "wof:population":1630,
    "zs:area_m":2441221.307371,
    "zs:blockids":[
        121050118221007,
        121050118221010,
        121050118221008,
        121050118221020,
        121050118221012,
        121050118361008,
        121050118361010,
        121050118361003,
        121050106031006,
        121050118361007,
        121050119012026,
        121050106031004,
        121050118221009,
        121050118212016,
        121050118221019,
        121050118221016,
        121050119012025,
        121050118361000,
        121050118361011,
        121050118361002,
        121050118221011,
        121050118361009,
        121050118361027
    ],
    "zs:housing10":648,
    "zs:label":"Towne & Country",
    "zs:pop10":1630
},
  "geometry": {"coordinates":[-81.952789,27.975614],"type":"Point"}
}