{
  "type": "Feature",
  "properties": {
    "gn:admin1_code":"AR",
    "gn:admin2_code":"139.0",
    "gn:admin3_code":"93650.0",
    "gn:asciiname":"Dodge City",
    "gn:country_code":"US",
    "gn:dem":69,
    "gn:elevation":"63.0",
    "gn:feature_class":"P",
    "gn:feature_code":"PPL",
    "gn:name":"Dodge City",
    "gn:population":0,
    "gn:timezone":"America/Chicago",
    "iso:country":"US",
    "name:ben_x_preferred":[
        "\u09a1\u099c \u09b8\u09bf\u099f\u09bf"
    ],
    "name:ell_x_preferred":[
        "\u039d\u03c4\u03bf\u03c4\u03b6 \u03a3\u03af\u03c4\u03b9"
    ],
    "name:hin_x_preferred":[
        "\u0921\u0949\u091c \u0938\u093f\u091f\u0940"
    ],
    "name:ind_x_preferred":[
        "Dodge City"
    ],
    "wof:name":"Dodge City",
    "wof:placetype":"locality"
},
  "geometry": {"coordinates":[-92.96849,33.01958],"type":"Point"}
}