{
  "type": "Feature",
  "properties": {
    "gn:admin1_code":"SD",
    "gn:admin2_code":"5.0",
    "gn:admin3_code":"13060.0",
    "gn:asciiname":"Prairie Villa Mobile Court",
    "gn:country_code":"US",
    "gn:dem":393,
    "gn:elevation":"395.0",
    "gn:feature_class":"P",
    "gn:feature_code":"PPL",
    "gn:name":"Prairie Villa Mobile Court",
    "gn:population":0,
    "gn:timezone":"America/Chicago",
    "iso:country":"US",
    "wof:name":"Prairie Villa Mobile Court",
    "wof:placetype":"locality"
},
  "geometry": {"coordinates":[-98.25315000000001,44.32915],"type":"Point"}
}