{
  "type": "Feature",
  "properties": {
    "gn:admin1_code":"IN",
    "gn:admin2_code":"057",
    "gn:admin3_code":"22612.0",
    "gn:asciiname":"The Anchorage",
    "gn:country_code":"US",
    "gn:dem":254,
    "gn:elevation":"251.0",
    "gn:feature_class":"P",
    "gn:feature_code":"PPL",
    "gn:name":"The Anchorage",
    "gn:population":0,
    "gn:timezone":"America/Indiana/Indianapolis",
    "iso:country":"US",
    "name:ceb_x_preferred":[
        "The Anchorage"
    ],
    "name:deu_x_preferred":[
        "The Anchorage"
    ],
    "name:swe_x_preferred":[
        "The Anchorage"
    ],
    "wof:name":"The Anchorage",
    "wof:placetype":"locality"
},
  "geometry": {"coordinates":[-85.94499999999999,39.93667],"type":"Point"}
}