{
  "type": "Feature",
  "properties": {
    "iso:country":"US",
    "name:eng_x_preferred":[
        "Kings Crossroads"
    ],
    "wof:name":"Kings Crossroads",
    "wof:placetype":"neighbourhood",
    "wof:population":3164,
    "zs:area_m":23742992.83935,
    "zs:blockids":[
        370810159021078,
        370810159011070,
        370810159021084,
        370810159021003,
        370810159011058,
        370810159021019,
        370810159011073,
        370810159021002,
        370810159012057,
        370810159011065,
        370810159011076,
        370810159021024,
        370810159021022,
        370810159021016,
        370810159012059,
        370810159011069,
        370810159021026,
        370810159021091,
        370810159021081,
        370810159021023,
        370810159011072,
        370810159012033,
        370810159012055,
        370810159012062,
        370810159021025,
        370810159012061,
        370810159021004,
        370810159021020,
        370810159021007,
        370810159011074,
        370810159021083,
        370810159021001,
        370810159012060,
        370810159021005,
        370810159012058,
        370810159021014,
        370810159012056,
        370810159021006,
        370810159011075,
        370810159021013,
        370810159021009,
        370810159021011,
        370810159021012,
        370810159021085,
        370810159021018,
        370810159021010,
        370810159021027,
        370810159021086,
        370810159011071,
        370810159021015,
        370810159021017,
        370810159021090
    ],
    "zs:housing10":1178,
    "zs:label":"Kings Crossroads",
    "zs:pop10":3164
},
  "geometry": {"coordinates":[-79.992093,36.207632],"type":"Point"}
}