{
  "type": "Feature",
  "properties": {
    "gn:admin1_code":"FL",
    "gn:admin2_code":"57",
    "gn:asciiname":"Ridgeland Ranch",
    "gn:country_code":"US",
    "gn:dem":19,
    "gn:elevation":"12.0",
    "gn:feature_class":"P",
    "gn:feature_code":"PPL",
    "gn:name":"Ridgeland Ranch",
    "gn:population":0,
    "gn:timezone":"America/New_York",
    "iso:country":"US",
    "wof:name":"Ridgeland Ranch",
    "wof:placetype":"locality"
},
  "geometry": {"coordinates":[-82.44240000000001,28.0312],"type":"Point"}
}