{
  "type": "Feature",
  "properties": {
    "gn:admin1_code":"NY",
    "gn:admin2_code":"17.0",
    "gn:admin3_code":"68110.0",
    "gn:asciiname":"Bonney",
    "gn:country_code":"US",
    "gn:dem":461,
    "gn:elevation":"458.0",
    "gn:feature_class":"P",
    "gn:feature_code":"PPL",
    "gn:name":"Bonney",
    "gn:population":0,
    "gn:timezone":"America/New_York",
    "iso:country":"US",
    "name:ceb_x_preferred":[
        "Bonney"
    ],
    "name:deu_x_preferred":[
        "Bonney"
    ],
    "name:fra_x_preferred":[
        "Bonney"
    ],
    "name:ita_x_preferred":[
        "Bonney"
    ],
    "name:por_x_preferred":[
        "Bonney"
    ],
    "name:swe_x_preferred":[
        "Bonney"
    ],
    "wof:name":"Bonney",
    "wof:placetype":"locality"
},
  "geometry": {"coordinates":[-75.67102,42.72146],"type":"Point"}
}