{
  "type": "Feature",
  "properties": {
    "gn:admin1_code":"IN",
    "gn:admin2_code":"85.0",
    "gn:admin3_code":"61578.0",
    "gn:asciiname":"Clunette",
    "gn:country_code":"US",
    "gn:dem":263,
    "gn:elevation":"261.0",
    "gn:feature_class":"P",
    "gn:feature_code":"PPL",
    "gn:name":"Clunette",
    "gn:population":0,
    "gn:timezone":"America/Indiana/Indianapolis",
    "iso:country":"US",
    "name:eng_x_preferred":[
        "Clunette"
    ],
    "name:und_x_variant":[
        "North Galveston"
    ],
    "wof:name":"Clunette",
    "wof:placetype":"locality"
},
  "geometry": {"coordinates":[-85.92277,41.31977],"type":"Point"}
}