{
  "type": "Feature",
  "properties": {
    "gn:admin1_code":"TX",
    "gn:admin2_code":"213",
    "gn:asciiname":"Evelyn",
    "gn:country_code":"US",
    "gn:dem":114,
    "gn:elevation":"110.0",
    "gn:feature_class":"P",
    "gn:feature_code":"PPL",
    "gn:name":"Evelyn",
    "gn:population":0,
    "gn:timezone":"America/Chicago",
    "iso:country":"US",
    "wof:name":"Evelyn",
    "wof:placetype":"locality"
},
  "geometry": {"coordinates":[-95.53274,32.30709],"type":"Point"}
}