{
  "type": "Feature",
  "properties": {
    "gn:admin1_code":"NV",
    "gn:admin2_code":"1.0",
    "gn:asciiname":"Cold Springs",
    "gn:country_code":"US",
    "gn:dem":1694,
    "gn:elevation":"1696.0",
    "gn:feature_class":"P",
    "gn:feature_code":"PPL",
    "gn:name":"Cold Springs",
    "gn:population":0,
    "gn:timezone":"America/Los_Angeles",
    "iso:country":"US",
    "name:ceb_x_preferred":[
        "Cold Springs"
    ],
    "name:deu_x_preferred":[
        "Cold Springs"
    ],
    "name:eng_x_preferred":[
        "Cold Springs"
    ],
    "name:ita_x_preferred":[
        "Cold Springs"
    ],
    "name:nld_x_preferred":[
        "Cold Springs"
    ],
    "name:pol_x_preferred":[
        "Cold Springs"
    ],
    "name:spa_x_preferred":[
        "Cold Springs"
    ],
    "name:srp_x_preferred":[
        "\u041a\u043e\u043b\u0434 \u0421\u043f\u0440\u0438\u043d\u0433"
    ],
    "name:und_x_variant":[
        "Cold Creek"
    ],
    "wof:name":"Cold Springs",
    "wof:placetype":"locality"
},
  "geometry": {"coordinates":[-117.83928,39.41214],"type":"Point"}
}