{
  "type": "Feature",
  "properties": {
    "gn:admin1_code":"PA",
    "gn:admin2_code":"33.0",
    "gn:admin3_code":"4888.0",
    "gn:asciiname":"Rosebud",
    "gn:country_code":"US",
    "gn:dem":441,
    "gn:elevation":"440.0",
    "gn:feature_class":"P",
    "gn:feature_code":"PPL",
    "gn:name":"Rosebud",
    "gn:population":0,
    "gn:timezone":"America/New_York",
    "iso:country":"US",
    "name:cat_x_preferred":[
        "Rosebud"
    ],
    "name:ceb_x_preferred":[
        "Rosebud"
    ],
    "name:deu_x_preferred":[
        "Rosebud"
    ],
    "name:eng_x_preferred":[
        "Rosebud"
    ],
    "name:fra_x_preferred":[
        "Rosebud"
    ],
    "name:heb_x_preferred":[
        "\u05e8\u05d5\u05d6\u05d1\u05d0\u05d3"
    ],
    "name:ita_x_preferred":[
        "Rosebud"
    ],
    "name:mlg_x_preferred":[
        "Rosebud"
    ],
    "name:nld_x_preferred":[
        "Rosebud"
    ],
    "name:pol_x_preferred":[
        "Rosebud"
    ],
    "name:por_x_preferred":[
        "Rosebud"
    ],
    "name:srp_x_preferred":[
        "\u0420\u043e\u0443\u0437\u0431\u0430\u0434"
    ],
    "name:swe_x_preferred":[
        "Rosebud"
    ],
    "name:ukr_x_preferred":[
        "\u0420\u043e\u0443\u0437\u0431\u0430\u0434"
    ],
    "name:und_x_variant":[
        "Rose Bud"
    ],
    "name:vol_x_preferred":[
        "Rosebud"
    ],
    "wof:name":"Rosebud",
    "wof:placetype":"locality"
},
  "geometry": {"coordinates":[-78.54141,40.75423],"type":"Point"}
}