{
  "type": "Feature",
  "properties": {
    "iso:country":"US",
    "name:deu_x_preferred":[
        "Sutton Place"
    ],
    "name:eng_x_preferred":[
        "Sutton Place"
    ],
    "name:jpn_x_preferred":[
        "\u30b5\u30c3\u30c8\u30f3\u30fb\u30d7\u30ec\u30a4\u30b9"
    ],
    "wd:wordcount":51,
    "wof:name":"Sutton Place",
    "wof:placetype":"neighbourhood",
    "wof:population":651,
    "zs:area_m":308285.718825,
    "zs:blockids":[
        320030025043003,
        320030027073000,
        320030027062000,
        320030027073001
    ],
    "zs:housing10":345,
    "zs:label":"Sutton Place",
    "zs:pop10":651
},
  "geometry": {"coordinates":[-115.120667,36.101803],"type":"Point"}
}