{
  "type": "Feature",
  "properties": {
    "gn:admin1_code":"FL",
    "gn:admin2_code":"57",
    "gn:asciiname":"The Groves North",
    "gn:country_code":"US",
    "gn:dem":34,
    "gn:elevation":"23.0",
    "gn:feature_class":"P",
    "gn:feature_code":"PPL",
    "gn:name":"The Groves North",
    "gn:population":0,
    "gn:timezone":"America/New_York",
    "iso:country":"US",
    "wof:name":"The Groves North",
    "wof:placetype":"locality"
},
  "geometry": {"coordinates":[-82.2838,27.9885],"type":"Point"}
}