{
  "type": "Feature",
  "properties": {
    "iso:country":"US",
    "name:eng_x_preferred":[
        "Canyon Vista"
    ],
    "qs:gn_adm0_cc":"US",
    "qs:gn_local":5378771,
    "qs:gn_nam_loc":"Oceanside, San Diego, California, US",
    "qs:gn_namadm1":"CA",
    "qs:local_max":7986,
    "qs:local_sum":17087,
    "qs:localhoods":20,
    "qs:name":"Canyon Vista",
    "qs:name_adm0":"United States",
    "qs:name_adm1":"California",
    "qs:name_adm2":"San Diego",
    "qs:name_local":"Oceanside",
    "qs:photo_max":94,
    "qs:photo_sum":183,
    "qs:placetype":"Suburb",
    "qs:quad_count":11,
    "qs:woe_adm0":23424977,
    "qs:woe_adm1":2347563,
    "qs:woe_adm2":12587706,
    "qs:woe_lau":0,
    "qs:woe_local":2464118,
    "qs:woe_ver":"7.10.0",
    "wof:lang":[
        "eng"
    ],
    "wof:name":"Canyon Vista",
    "wof:placetype":"neighbourhood",
    "wof:population":6452,
    "zs:blockids":[
        60730185072007,
        60730185072004,
        60730185072005,
        60730185072009,
        60730185132015,
        60730185072002,
        60730185072000,
        60730185072008,
        60730185132009,
        60730185072018,
        60730185132012,
        60730185132014,
        60730185141021,
        60730185074001,
        60730185132038,
        60730185074006,
        60730185074019,
        60730185132011,
        60730185141015,
        60730185132018,
        60730185132000,
        60730185074021,
        60730185072012,
        60730185074005,
        60730185074018,
        60730185072017,
        60730185132017,
        60730185074020,
        60730185074000,
        60730185072014,
        60730185141022,
        60730185074003,
        60730185074004,
        60730185074007,
        60730185132010,
        60730185074027,
        60730185132013,
        60730185074010,
        60730185141012,
        60730185072010,
        60730185072013,
        60730185132016,
        60730185072006,
        60730185074002,
        60730185074008,
        60730185074011,
        60730185072011,
        60730185072016,
        60730185072001,
        60730185072003,
        60730185072015
    ],
    "zs:housing10":2046,
    "zs:pop10":6452
},
  "geometry": {"coordinates":[-117.30741500000001,33.221998],"type":"Point"}
}