{
  "type": "Feature",
  "properties": {
    "gn:country":"US",
    "gn:fcode":"PPL",
    "gn:population":0,
    "iso:country":"US",
    "name:ben_x_preferred":[
        "\u09ad\u09be\u09b0\u09cd\u09a8\u09a8"
    ],
    "name:cat_x_preferred":[
        "Vernon"
    ],
    "name:ceb_x_preferred":[
        "Vernon"
    ],
    "name:deu_x_preferred":[
        "Vernon"
    ],
    "name:ell_x_preferred":[
        "\u0392\u03ad\u03c1\u03bd\u03bf\u03bd"
    ],
    "name:eng_x_preferred":[
        "Vernon"
    ],
    "name:epo_x_preferred":[
        "Vernon"
    ],
    "name:fin_x_preferred":[
        "Vernon"
    ],
    "name:fra_x_preferred":[
        "Vernon"
    ],
    "name:hin_x_preferred":[
        "\u0935\u0930\u094d\u0928\u094b\u0928"
    ],
    "name:hun_x_preferred":[
        "Vernon"
    ],
    "name:ind_x_preferred":[
        "Vernon"
    ],
    "name:ita_x_preferred":[
        "Vernon"
    ],
    "name:jpn_x_preferred":[
        "\u30f4\u30a1\u30fc\u30ce\u30f3"
    ],
    "name:kor_x_preferred":[
        "\ubc84\ub17c"
    ],
    "name:nds_x_preferred":[
        "Vernon"
    ],
    "name:nld_x_preferred":[
        "Vernon"
    ],
    "name:oci_x_preferred":[
        "Vernon"
    ],
    "name:pms_x_preferred":[
        "Vernon"
    ],
    "name:pol_x_preferred":[
        "Vernon"
    ],
    "name:por_x_preferred":[
        "Vernon"
    ],
    "name:ron_x_preferred":[
        "Vernon"
    ],
    "name:rus_x_preferred":[
        "\u0412\u0435\u0440\u043d\u043e\u043d"
    ],
    "name:slk_x_preferred":[
        "Vernon"
    ],
    "name:spa_x_preferred":[
        "Vernon"
    ],
    "name:srp_x_preferred":[
        "\u0412\u0435\u0440\u043d\u043e\u043d"
    ],
    "name:swa_x_preferred":[
        "Vernon"
    ],
    "name:swe_x_preferred":[
        "Vernon"
    ],
    "name:ukr_x_preferred":[
        "\u0412\u0435\u0440\u043d\u043e\u043d"
    ],
    "name:und_x_variant":[
        "Olson City"
    ],
    "name:urd_x_preferred":[
        "\u0648\u0631\u0646\u0648\u0646"
    ],
    "name:vol_x_preferred":[
        "Vernon"
    ],
    "name:war_x_preferred":[
        "Vernon"
    ],
    "name:zho_x_preferred":[
        "Vernon"
    ],
    "qs_pg:aaroncc":"US",
    "qs_pg:gn_country":"US",
    "qs_pg:gn_fcode":"PPL",
    "qs_pg:gn_pop":0,
    "qs_pg:name":"Vernon",
    "qs_pg:name_adm0":"United States",
    "qs_pg:name_adm1":"Idaho",
    "qs_pg:photos":147,
    "qs_pg:photos_1k":30,
    "qs_pg:photos_9k":1,
    "qs_pg:photos_9r":3,
    "qs_pg:photos_all":147,
    "qs_pg:photos_sr":3,
    "qs_pg:pop_sr":0,
    "qs_pg:qs_pg_placetype":"locality",
    "qs_pg:qs_pg_placetype_gp":"Town",
    "qs_pg:woe_adm0":23424977,
    "woe:adm0_id":23424977,
    "woe:name_adm0":"United States",
    "woe:name_adm1":"Idaho",
    "woe:placetype":"Town",
    "wof:name":"Vernon",
    "wof:placetype":"locality"
},
  "geometry": {"coordinates":[-116.16095,43.5885],"type":"Point"}
}