{
  "type": "Feature",
  "properties": {
    "gn:admin1_code":"WV",
    "gn:admin2_code":"11",
    "gn:asciiname":"Edgemont",
    "gn:country_code":"US",
    "gn:dem":167,
    "gn:elevation":"168.0",
    "gn:feature_class":"P",
    "gn:feature_code":"PPL",
    "gn:name":"Edgemont",
    "gn:population":0,
    "gn:timezone":"America/New_York",
    "iso:country":"US",
    "name:ceb_x_preferred":[
        "Edgemont"
    ],
    "name:deu_x_preferred":[
        "Edgemont"
    ],
    "name:pol_x_preferred":[
        "Edgemont"
    ],
    "name:spa_x_preferred":[
        "Edgemont"
    ],
    "name:srp_x_preferred":[
        "\u0415\u045f\u043c\u043e\u043d\u0442"
    ],
    "name:ukr_x_preferred":[
        "\u0415\u0434\u0436\u043c\u043e\u043d\u0442"
    ],
    "wof:name":"Edgemont",
    "wof:placetype":"locality"
},
  "geometry": {"coordinates":[-82.36376,38.43342],"type":"Point"}
}