{
  "type": "Feature",
  "properties": {
    "gn:admin1_code":"AR",
    "gn:admin2_code":"97.0",
    "gn:asciiname":"Chasewood Landing",
    "gn:country_code":"US",
    "gn:dem":216,
    "gn:elevation":"201.0",
    "gn:feature_class":"P",
    "gn:feature_code":"PPL",
    "gn:name":"Chasewood Landing",
    "gn:population":0,
    "gn:timezone":"America/Chicago",
    "iso:country":"US",
    "wof:name":"Chasewood Landing",
    "wof:placetype":"locality"
},
  "geometry": {"coordinates":[-93.67381,34.63343],"type":"Point"}
}