{
  "type": "Feature",
  "properties": {
    "gn:admin1_code":"WV",
    "gn:admin2_code":"17",
    "gn:asciiname":"Miletus",
    "gn:country_code":"US",
    "gn:dem":284,
    "gn:elevation":"281.0",
    "gn:feature_class":"P",
    "gn:feature_code":"PPL",
    "gn:name":"Miletus",
    "gn:population":0,
    "gn:timezone":"America/New_York",
    "iso:country":"US",
    "wof:name":"Miletus",
    "wof:placetype":"locality"
},
  "geometry": {"coordinates":[-80.58870999999998,39.23064],"type":"Point"}
}