{
  "type": "Feature",
  "properties": {
    "gn:country":"US",
    "gn:fcode":"PPL",
    "gn:population":0,
    "iso:country":"US",
    "name:ara_x_preferred":[
        "\u062a\u0631\u064a\u0644\u0648\u0631\u060c \u0645\u064a\u0632\u0648\u0631\u064a"
    ],
    "name:ara_x_variant":[
        "\u062a\u0631\u064a\u0644\u0648\u0631"
    ],
    "name:eng_x_preferred":[
        "Treloar"
    ],
    "name:fra_x_preferred":[
        "Treloar"
    ],
    "name:vol_x_preferred":[
        "Treloar"
    ],
    "qs_pg:aaroncc":"US",
    "qs_pg:gn_country":"US",
    "qs_pg:gn_fcode":"PPL",
    "qs_pg:gn_pop":0,
    "qs_pg:name":"Treloar",
    "qs_pg:name_adm0":"United States",
    "qs_pg:name_adm1":"Missouri",
    "qs_pg:photos":98,
    "qs_pg:photos_1k":20,
    "qs_pg:photos_9k":1,
    "qs_pg:photos_9r":3,
    "qs_pg:photos_all":98,
    "qs_pg:photos_sr":3,
    "qs_pg:pop_sr":0,
    "qs_pg:qs_pg_placetype":"locality",
    "qs_pg:qs_pg_placetype_gp":"Town",
    "qs_pg:woe_adm0":23424977,
    "woe:adm0_id":23424977,
    "woe:name_adm0":"United States",
    "woe:name_adm1":"Missouri",
    "woe:placetype":"Town",
    "wof:name":"Treloar",
    "wof:placetype":"locality"
},
  "geometry": {"coordinates":[-91.18792999999999,38.64449],"type":"Point"}
}