{
  "type": "Feature",
  "properties": {
    "gn:admin1_code":"NE",
    "gn:admin2_code":"25.0",
    "gn:admin3_code":"92398.0",
    "gn:asciiname":"HiVue Mobile Home Park",
    "gn:country_code":"US",
    "gn:dem":348,
    "gn:elevation":"345.0",
    "gn:feature_class":"P",
    "gn:feature_code":"PPL",
    "gn:name":"HiVue Mobile Home Park",
    "gn:population":0,
    "gn:timezone":"America/Chicago",
    "iso:country":"US",
    "wof:name":"HiVue Mobile Home Park",
    "wof:placetype":"campus"
},
  "geometry": {"coordinates":[-95.90723,41.01667],"type":"Point"}
}