{
  "type": "Feature",
  "properties": {
    "gn:admin1_code":"SC",
    "gn:admin2_code":"43.0",
    "gn:asciiname":"Mount Tabor",
    "gn:country_code":"US",
    "gn:dem":0,
    "gn:elevation":"5.0",
    "gn:feature_class":"P",
    "gn:feature_code":"PPL",
    "gn:name":"Mount Tabor",
    "gn:population":0,
    "gn:timezone":"America/New_York",
    "iso:country":"US",
    "name:amh_x_preferred":[
        "\u12f0\u1265\u1228 \u1273\u1266\u122d"
    ],
    "name:ara_x_preferred":[
        "\u062c\u0628\u0644 \u0637\u0627\u0628\u0648\u0631"
    ],
    "name:bre_x_preferred":[
        "Tabor"
    ],
    "name:bul_x_preferred":[
        "\u0422\u0430\u0432\u043e\u0440"
    ],
    "name:cat_x_preferred":[
        "Mont Tabor"
    ],
    "name:ceb_x_preferred":[
        "Mount Tabor"
    ],
    "name:ces_x_preferred":[
        "T\u00e1bor"
    ],
    "name:deu_x_preferred":[
        "Berg Tabor"
    ],
    "name:epo_x_preferred":[
        "Monto Tabor"
    ],
    "name:eus_x_preferred":[
        "Tabor"
    ],
    "name:fas_x_preferred":[
        "\u06a9\u0648\u0647 \u062a\u0627\u0628\u0648\u0631"
    ],
    "name:fin_x_preferred":[
        "Taaborin vuori"
    ],
    "name:fra_x_preferred":[
        "Mont Thabor"
    ],
    "name:fry_x_preferred":[
        "Tabor"
    ],
    "name:heb_x_preferred":[
        "\u05d4\u05e8 \u05ea\u05d1\u05d5\u05e8"
    ],
    "name:hrv_x_preferred":[
        "Gora Tabor"
    ],
    "name:hun_x_preferred":[
        "T\u00e1bor-hegy"
    ],
    "name:hye_x_preferred":[
        "\u0539\u0561\u0562\u0578\u0580 \u056c\u0565\u057c"
    ],
    "name:ind_x_preferred":[
        "Gunung Tabor"
    ],
    "name:ita_x_preferred":[
        "Monte Tabor"
    ],
    "name:jpn_x_preferred":[
        "\u30bf\u30dc\u30eb\u5c71"
    ],
    "name:kat_x_preferred":[
        "\u10d7\u10d0\u10d1\u10dd\u10e0\u10d8\u10e1 \u10db\u10d7\u10d0"
    ],
    "name:kor_x_preferred":[
        "\ud0c0\ubcf4\ub974\uc0b0"
    ],
    "name:lad_x_preferred":[
        "Har Tabor"
    ],
    "name:lit_x_preferred":[
        "Taboro kalnas"
    ],
    "name:mal_x_preferred":[
        "\u0d24\u0d3e\u0d2c\u0d4b\u0d7c \u0d2e\u0d32"
    ],
    "name:nld_x_preferred":[
        "Taborberg"
    ],
    "name:nno_x_preferred":[
        "Tabor"
    ],
    "name:nor_x_preferred":[
        "Tabor"
    ],
    "name:pol_x_preferred":[
        "G\u00f3ra Tabor"
    ],
    "name:por_x_preferred":[
        "Monte Tabor"
    ],
    "name:ron_x_preferred":[
        "Muntele Tabor"
    ],
    "name:rus_x_preferred":[
        "\u0424\u0430\u0432\u043e\u0440"
    ],
    "name:slk_x_preferred":[
        "T\u00e1bor"
    ],
    "name:slv_x_preferred":[
        "Tabor"
    ],
    "name:spa_x_preferred":[
        "Monte Tabor"
    ],
    "name:srd_x_preferred":[
        "Tabor"
    ],
    "name:srp_x_preferred":[
        "\u0422\u0430\u0432\u043e\u0440"
    ],
    "name:swe_x_preferred":[
        "Tabor"
    ],
    "name:tam_x_preferred":[
        "\u0ba4\u0bbe\u0baa\u0bcb\u0bb0\u0bcd \u0bae\u0bb2\u0bc8"
    ],
    "name:ukr_x_preferred":[
        "\u0424\u0430\u0432\u043e\u0440"
    ],
    "name:urd_x_preferred":[
        "\u06a9\u0648\u06c1 \u062a\u0628\u0648\u0631"
    ],
    "name:vie_x_preferred":[
        "N\u00fai Tabor"
    ],
    "name:yid_x_preferred":[
        "\u05d4\u05e8 \u05ea\u05d1\u05d5\u05e8"
    ],
    "name:zho_x_preferred":[
        "\u5854\u6c83\u723e\u5c71"
    ],
    "wof:name":"Mount Tabor",
    "wof:placetype":"locality"
},
  "geometry": {"coordinates":[-79.19476999999998,33.61795],"type":"Point"}
}