{
  "type": "Feature",
  "properties": {
    "gn:elevation":309,
    "iso:country":"US",
    "name:ara_x_preferred":[
        "\u0643\u064a\u0631\u0628\u064a"
    ],
    "name:cat_x_preferred":[
        "Kirby"
    ],
    "name:ceb_x_preferred":[
        "Kirby"
    ],
    "name:deu_x_preferred":[
        "Kirby"
    ],
    "name:eng_x_preferred":[
        "Kirby"
    ],
    "name:epo_x_preferred":[
        "Kirby"
    ],
    "name:fin_x_preferred":[
        "Kirby"
    ],
    "name:fra_x_preferred":[
        "Kirby"
    ],
    "name:hbs_x_preferred":[
        "Kirbi"
    ],
    "name:hun_x_preferred":[
        "Kirby"
    ],
    "name:ita_x_preferred":[
        "Kirby"
    ],
    "name:jpn_x_preferred":[
        "\u30ab\u30fc\u30d3\u30fc"
    ],
    "name:lat_x_preferred":[
        "Kirby"
    ],
    "name:nld_x_preferred":[
        "Kirby"
    ],
    "name:pol_x_preferred":[
        "Kirby"
    ],
    "name:por_x_preferred":[
        "Kirby"
    ],
    "name:rus_x_preferred":[
        "Kirby"
    ],
    "name:spa_x_preferred":[
        "Kirby"
    ],
    "name:srp_x_preferred":[
        "\u041a\u0438\u0440\u0431\u0438"
    ],
    "name:swe_x_preferred":[
        "Kirby"
    ],
    "name:ukr_x_preferred":[
        "\u041a\u0435\u0440\u0431\u0456"
    ],
    "name:und_x_variant":[
        "Newtown"
    ],
    "name:vol_x_preferred":[
        "Kirby"
    ],
    "qs:gn_adm0_cc":"US",
    "qs:gn_fcode":"PPL",
    "qs:gn_local":5219346,
    "qs:gn_nam_loc":"shallmar",
    "qs:gn_namadm1":"PA",
    "qs:gn_name":"Kirby",
    "qs:local_max":4,
    "qs:local_sum":4,
    "qs:localhoods":1,
    "qs:name":"Kirby",
    "qs:name_adm0":"United States",
    "qs:name_adm1":"Pennsylvania",
    "qs:name_adm2":"Greene",
    "qs:name_local":"Whiteley",
    "qs:photo_max":3,
    "qs:photo_sum":4,
    "qs:placetype":"Suburb",
    "qs:quad_count":2,
    "qs:woe_adm0":23424977,
    "qs:woe_adm1":2347597,
    "qs:woe_adm2":12589757,
    "qs:woe_lau":0,
    "qs:woe_local":28744886,
    "qs:woe_ver":"7.10.0",
    "wd:wordcount":345,
    "wof:lang":[
        "eng"
    ],
    "wof:name":"Kirby",
    "wof:placetype":"neighbourhood"
},
  "geometry": {"coordinates":[-80.098572,39.81592],"type":"Point"}
}