{
  "type": "Feature",
  "properties": {
    "gn:elevation":398,
    "iso:country":"US",
    "name:eng_x_preferred":[
        "Honby"
    ],
    "qs:gn_adm0_cc":"US",
    "qs:gn_fcode":"PPL",
    "qs:gn_local":5393049,
    "qs:gn_nam_loc":"Santa Clarita, Los Angeles, California, US",
    "qs:gn_namadm1":"CA",
    "qs:gn_name":"Honby",
    "qs:local_max":957,
    "qs:local_sum":5875,
    "qs:localhoods":19,
    "qs:name":"Honby",
    "qs:name_adm0":"United States",
    "qs:name_adm1":"California",
    "qs:name_adm2":"Los Angeles",
    "qs:name_local":"Santa Clarita",
    "qs:photo_max":97,
    "qs:photo_sum":243,
    "qs:placetype":"Suburb",
    "qs:quad_count":10,
    "qs:woe_adm0":23424977,
    "qs:woe_adm1":2347563,
    "qs:woe_adm2":12587688,
    "qs:woe_funk":"Parented by a neighborhood",
    "qs:woe_lau":0,
    "qs:woe_local":2488845,
    "qs:woe_ver":"7.10.0",
    "wof:lang":[
        "eng"
    ],
    "wof:name":"Honby",
    "wof:placetype":"neighbourhood",
    "wof:population":1360,
    "zs:blockids":[
        60379200301015,
        60379200314006,
        60379200301017,
        60379200301018,
        60379200301002,
        60379200301004,
        60379200314007,
        60379200301016,
        60379200314009,
        60379200314010,
        60379203142036,
        60379200301003,
        60379203142021,
        60379200301019,
        60379200314008
    ],
    "zs:housing10":433,
    "zs:pop10":1360
},
  "geometry": {"coordinates":[-118.496488,34.414694],"type":"Point"}
}