{
  "type": "Feature",
  "properties": {
    "iso:country":"US",
    "name:eng_x_preferred":[
        "Fort McIntosh"
    ],
    "wd:wordcount":28,
    "wof:name":"Fort McIntosh",
    "wof:placetype":"neighbourhood",
    "wof:population":165,
    "zs:area_m":311803.584635,
    "zs:blockids":[
        484790019002073,
        484790019002018,
        484790019002044,
        484790019002075,
        484790019002074,
        484790019002077,
        484790019002010,
        484790019002012,
        484790019002043,
        484790019002017
    ],
    "zs:housing10":12,
    "zs:label":"Fort McIntosh",
    "zs:pop10":165
},
  "geometry": {"coordinates":[-99.520791,27.505734],"type":"Point"}
}