{
  "type": "Feature",
  "properties": {
    "gn:admin1_code":"TX",
    "gn:admin2_code":"167.0",
    "gn:asciiname":"Century Oaks Estates",
    "gn:country_code":"US",
    "gn:dem":10,
    "gn:elevation":"8.0",
    "gn:feature_class":"P",
    "gn:feature_code":"PPL",
    "gn:name":"Century Oaks Estates",
    "gn:population":0,
    "gn:timezone":"America/Chicago",
    "iso:country":"US",
    "wof:name":"Century Oaks Estates",
    "wof:placetype":"locality"
},
  "geometry": {"coordinates":[-95.1722,29.4946],"type":"Point"}
}