{
  "type": "Feature",
  "properties": {
    "gn:admin1_code":"MO",
    "gn:admin2_code":"3.0",
    "gn:admin3_code":"62534.0",
    "gn:asciiname":"Kodiak",
    "gn:country_code":"US",
    "gn:dem":303,
    "gn:elevation":"304.0",
    "gn:feature_class":"P",
    "gn:feature_code":"PPL",
    "gn:name":"Kodiak",
    "gn:population":0,
    "gn:timezone":"America/Chicago",
    "iso:country":"US",
    "name:aze_x_preferred":[
        "Kadyak"
    ],
    "name:ben_x_preferred":[
        "\u0995\u09cb\u09a1\u09bf\u09df\u09be\u0995"
    ],
    "name:ces_x_preferred":[
        "Kodiak"
    ],
    "name:deu_x_preferred":[
        "Kodiak"
    ],
    "name:ell_x_preferred":[
        "\u039a\u03cc\u03bd\u03c4\u03b9\u03b1\u03ba"
    ],
    "name:fas_x_preferred":[
        "\u06a9\u0648\u062f\u06cc\u0627\u06a9"
    ],
    "name:fra_x_preferred":[
        "Kodiak"
    ],
    "name:heb_x_preferred":[
        "\u05e7\u05d5\u05d3\u05d9\u05d0\u05e7"
    ],
    "name:hin_x_preferred":[
        "\u0915\u094b\u0921\u093f\u092f\u093e\u0915"
    ],
    "name:hun_x_preferred":[
        "Kodiak"
    ],
    "name:ind_x_preferred":[
        "Kodiak"
    ],
    "name:ita_x_preferred":[
        "Kodiak"
    ],
    "name:kor_x_preferred":[
        "\ucf54\ub514\uc561"
    ],
    "name:nld_x_preferred":[
        "Kodiak"
    ],
    "name:pol_x_preferred":[
        "Kodiak"
    ],
    "name:rus_x_preferred":[
        "\u041a\u0430\u0434\u044c\u044f\u043a"
    ],
    "name:slk_x_preferred":[
        "Kodiak"
    ],
    "name:spa_x_preferred":[
        "Kodiak"
    ],
    "name:swe_x_preferred":[
        "Kodiak"
    ],
    "name:vie_x_preferred":[
        "Kodiak"
    ],
    "wof:name":"Kodiak",
    "wof:placetype":"locality"
},
  "geometry": {"coordinates":[-94.75718999999999,39.95194],"type":"Point"}
}