{
  "type": "Feature",
  "properties": {
    "gn:admin1_code":"NY",
    "gn:admin2_code":"63.0",
    "gn:admin3_code":"43093.0",
    "gn:asciiname":"Village Mobile Home Park",
    "gn:country_code":"US",
    "gn:dem":184,
    "gn:elevation":"184.0",
    "gn:feature_class":"P",
    "gn:feature_code":"PPL",
    "gn:name":"Village Mobile Home Park",
    "gn:population":0,
    "gn:timezone":"America/New_York",
    "iso:country":"US",
    "wof:name":"Village Mobile Home Park",
    "wof:placetype":"campus"
},
  "geometry": {"coordinates":[-78.6906,43.12961],"type":"Point"}
}