{
  "type": "Feature",
  "properties": {
    "gn:admin1_code":"KY",
    "gn:admin2_code":"195",
    "gn:asciiname":"Argo",
    "gn:country_code":"US",
    "gn:dem":272,
    "gn:elevation":"272.0",
    "gn:feature_class":"P",
    "gn:feature_code":"PPL",
    "gn:name":"Argo",
    "gn:population":0,
    "gn:timezone":"America/New_York",
    "iso:country":"US",
    "name:fas_x_preferred":[
        "\u0622\u0631\u06af\u0648"
    ],
    "wof:name":"Argo",
    "wof:placetype":"locality"
},
  "geometry": {"coordinates":[-82.06318,37.48066],"type":"Point"}
}