{
  "type": "Feature",
  "properties": {
    "iso:country":"US",
    "name:eng_x_preferred":[
        "Lexington Park at Amberly"
    ],
    "qs:gn_adm0_cc":"US",
    "qs:gn_local":4459467,
    "qs:gn_nam_loc":"Cary, Wake, North Carolina, US",
    "qs:gn_namadm1":"NC",
    "qs:local_max":1353,
    "qs:local_sum":11778,
    "qs:localhoods":52,
    "qs:name":"Lexington Park at Amberly",
    "qs:name_adm0":"United States",
    "qs:name_adm1":"North Carolina",
    "qs:name_adm2":"Wake",
    "qs:name_local":"Cary",
    "qs:photo_max":2,
    "qs:photo_sum":4,
    "qs:placetype":"Suburb",
    "qs:quad_count":2,
    "qs:woe_adm0":23424977,
    "qs:woe_adm1":2347592,
    "qs:woe_adm2":12589465,
    "qs:woe_lau":0,
    "qs:woe_local":2375810,
    "qs:woe_ver":"7.10.0",
    "wof:name":"Lexington Park at Amberly",
    "wof:placetype":"neighbourhood",
    "wof:population":515,
    "zs:blockids":[
        370370207011040,
        370370207011043,
        370370207011042,
        370370207011044,
        370370207011041
    ],
    "zs:housing10":311,
    "zs:pop10":515
},
  "geometry": {"coordinates":[-78.914795,35.813358],"type":"Point"}
}