{
  "type": "Feature",
  "properties": {
    "gn:admin1_code":"AL",
    "gn:admin2_code":"73.0",
    "gn:asciiname":"Penfield Heights",
    "gn:country_code":"US",
    "gn:dem":247,
    "gn:elevation":"242.0",
    "gn:feature_class":"P",
    "gn:feature_code":"PPL",
    "gn:name":"Penfield Heights",
    "gn:population":0,
    "gn:timezone":"America/Chicago",
    "iso:country":"US",
    "wof:name":"Penfield Heights",
    "wof:placetype":"locality"
},
  "geometry": {"coordinates":[-86.72971,33.59427],"type":"Point"}
}