{
  "type": "Feature",
  "properties": {
    "iso:country":"US",
    "name:ceb_x_preferred":[
        "Lake Forest"
    ],
    "name:deu_x_preferred":[
        "Lake Forest"
    ],
    "name:eng_x_preferred":[
        "Lake Forest"
    ],
    "name:fas_x_preferred":[
        "\u0644\u06cc\u06a9 \u0641\u0627\u0631\u0633\u062a"
    ],
    "name:fra_x_preferred":[
        "Lake Forest"
    ],
    "name:ita_x_preferred":[
        "Lake Forest"
    ],
    "name:jpn_x_preferred":[
        "\u30ec\u30a4\u30af\u30d5\u30a9\u30ec\u30b9\u30c8"
    ],
    "name:kor_x_preferred":[
        "\ub808\uc774\ud06c\ud3ec\ub9ac\uc2a4\ud2b8"
    ],
    "name:nld_x_preferred":[
        "Lake Forest"
    ],
    "name:pol_x_preferred":[
        "Lake Forest"
    ],
    "name:por_x_preferred":[
        "Lake Forest"
    ],
    "name:spa_x_preferred":[
        "Lake Forest"
    ],
    "name:srp_x_preferred":[
        "\u041b\u0435\u0458\u043a \u0424\u043e\u0440\u0438\u0441\u0442"
    ],
    "name:swe_x_preferred":[
        "Lake Forest"
    ],
    "name:ukr_x_preferred":[
        "\u041b\u0435\u0439\u043a-\u0424\u043e\u0440\u0435\u0441\u0442"
    ],
    "name:urd_x_preferred":[
        "\u0644\u06cc\u06a9 \u0641\u0627\u0631\u0633\u0679"
    ],
    "name:vol_x_preferred":[
        "Lake Forest"
    ],
    "wd:wordcount":105,
    "wof:name":"Lake Forest",
    "wof:placetype":"neighbourhood",
    "wof:population":2985,
    "zs:area_m":15894023.278993,
    "zs:blockids":[
        11010054081008,
        11010054084008,
        11010054082038,
        11010054084007,
        11010054084015,
        11010054082009,
        11010054084004,
        11010054083005,
        11010054082003,
        11010054084003,
        11010054084012,
        11010054083000,
        11010054083001,
        11010054084005,
        11010054081040,
        11010054081005,
        11010054084000,
        11010054084001,
        11010054084006,
        11010054084014,
        11010054084010,
        11010054081013,
        11010054084017,
        11010054084002,
        11010054084016,
        11010054084013,
        11010054081035,
        11010054081006,
        11010054081007,
        11010054084009,
        11010054084011
    ],
    "zs:housing10":1308,
    "zs:label":"Lake Forest",
    "zs:pop10":2985
},
  "geometry": {"coordinates":[-86.164885,32.420976],"type":"Point"}
}