{
  "type": "Feature",
  "properties": {
    "gn:admin1_code":"CA",
    "gn:admin2_code":"65.0",
    "gn:asciiname":"Valle de los Caballos",
    "gn:country_code":"US",
    "gn:dem":445,
    "gn:elevation":"448.0",
    "gn:feature_class":"P",
    "gn:feature_code":"PPL",
    "gn:name":"Valle de los Caballos",
    "gn:population":0,
    "gn:timezone":"America/Los_Angeles",
    "iso:country":"US",
    "wof:name":"Valle de los Caballos",
    "wof:placetype":"locality"
},
  "geometry": {"coordinates":[-117.04086,33.52531],"type":"Point"}
}