{
  "type": "Feature",
  "properties": {
    "gn:country":"US",
    "gn:fcode":"PPL",
    "gn:population":0,
    "iso:country":"US",
    "name:cym_x_preferred":[
        "Eastport"
    ],
    "name:eng_x_preferred":[
        "Eastport"
    ],
    "name:fra_x_preferred":[
        "Eastport"
    ],
    "name:zho_x_preferred":[
        "\u4f0a\u65af\u7279\u6ce2\u7279"
    ],
    "qs_pg:aaroncc":"US",
    "qs_pg:gn_country":"US",
    "qs_pg:gn_fcode":"PPL",
    "qs_pg:gn_pop":0,
    "qs_pg:name":"Eastport",
    "qs_pg:name_adm0":"United States",
    "qs_pg:name_adm1":"Idaho",
    "qs_pg:photos":10,
    "qs_pg:photos_1k":2,
    "qs_pg:photos_9k":1,
    "qs_pg:photos_9r":1,
    "qs_pg:photos_all":10,
    "qs_pg:photos_sr":1,
    "qs_pg:pop_sr":5,
    "qs_pg:qs_pg_placetype":"locality",
    "qs_pg:qs_pg_placetype_gp":"Town",
    "qs_pg:woe_adm0":23424977,
    "woe:adm0_id":23424977,
    "woe:name_adm0":"United States",
    "woe:name_adm1":"Idaho",
    "woe:placetype":"Town",
    "wof:name":"Eastport",
    "wof:placetype":"locality"
},
  "geometry": {"coordinates":[-116.18131,48.9994],"type":"Point"}
}