{
  "type": "Feature",
  "properties": {
    "gn:admin1_code":"VA",
    "gn:admin2_code":"51",
    "gn:asciiname":"West Dante",
    "gn:country_code":"US",
    "gn:dem":589,
    "gn:elevation":"578.0",
    "gn:feature_class":"P",
    "gn:feature_code":"PPL",
    "gn:name":"West Dante",
    "gn:population":0,
    "gn:timezone":"America/New_York",
    "iso:country":"US",
    "wof:name":"West Dante",
    "wof:placetype":"locality"
},
  "geometry": {"coordinates":[-82.32153000000002,36.97899],"type":"Point"}
}