{
  "type": "Feature",
  "properties": {
    "gn:admin1_code":"LA",
    "gn:admin2_code":"15.0",
    "gn:asciiname":"Leslie",
    "gn:country_code":"US",
    "gn:dem":67,
    "gn:elevation":"62.0",
    "gn:feature_class":"P",
    "gn:feature_code":"PPL",
    "gn:name":"Leslie",
    "gn:population":0,
    "gn:timezone":"America/Chicago",
    "iso:country":"US",
    "name:ceb_x_preferred":[
        "Leslie"
    ],
    "name:deu_x_preferred":[
        "Leslie"
    ],
    "name:fin_x_preferred":[
        "Leslie"
    ],
    "name:fra_x_preferred":[
        "Leslie"
    ],
    "name:ita_x_preferred":[
        "Leslie"
    ],
    "name:jpn_x_preferred":[
        "\u30ec\u30b9\u30ea\u30fc"
    ],
    "name:lat_x_preferred":[
        "Leslius"
    ],
    "name:nds_x_preferred":[
        "Leslie"
    ],
    "name:nld_x_preferred":[
        "Leslie"
    ],
    "name:pol_x_preferred":[
        "Leslie"
    ],
    "name:por_x_preferred":[
        "Leslie"
    ],
    "name:rus_x_preferred":[
        "\u041b\u0435\u0441\u043b\u0438"
    ],
    "name:spa_x_preferred":[
        "Leslie"
    ],
    "name:srp_x_preferred":[
        "\u041b\u0435\u0441\u043b\u0438"
    ],
    "name:swe_x_preferred":[
        "Leslie"
    ],
    "name:ukr_x_preferred":[
        "\u041b\u0435\u0441\u043b\u0456"
    ],
    "name:vol_x_preferred":[
        "Leslie"
    ],
    "wof:name":"Leslie",
    "wof:placetype":"locality"
},
  "geometry": {"coordinates":[-93.48323000000001,32.58876],"type":"Point"}
}