{
  "type": "Feature",
  "properties": {
    "iso:country":"US",
    "name:bre_x_preferred":[
        "Xavier"
    ],
    "name:deu_x_preferred":[
        "Xavier"
    ],
    "name:eng_x_preferred":[
        "Xavier"
    ],
    "name:eus_x_preferred":[
        "Xabier"
    ],
    "name:fra_x_preferred":[
        "Xavier"
    ],
    "name:ita_x_preferred":[
        "Xavier"
    ],
    "name:jpn_x_preferred":[
        "\u30b7\u30e3\u30d3\u30a8\u30eb"
    ],
    "name:kor_x_preferred":[
        "\uc0ac\ube44\uc5d0\ub974"
    ],
    "name:nld_x_preferred":[
        "Xavier"
    ],
    "name:por_x_preferred":[
        "Xavier"
    ],
    "name:rus_x_preferred":[
        "\u041a\u0441\u0430\u0432\u044c\u0435"
    ],
    "name:spa_x_preferred":[
        "Xavier"
    ],
    "name:swe_x_preferred":[
        "Xavier"
    ],
    "wd:wordcount":183,
    "wof:name":"Xavier",
    "wof:placetype":"neighbourhood",
    "wof:population":207,
    "zs:area_m":493893.436509,
    "zs:blockids":[
        201030705004015,
        201030705004017,
        201030705004019,
        201030705004016,
        201030705004035,
        201030711021015,
        201030705004018,
        201030705004034,
        201030705004033
    ],
    "zs:housing10":37,
    "zs:label":"Xavier",
    "zs:pop10":207
},
  "geometry": {"coordinates":[-94.908242,39.276172],"type":"Point"}
}