{
  "type": "Feature",
  "properties": {
    "gn:admin1_code":"TX",
    "gn:admin2_code":"493.0",
    "gn:asciiname":"Nockenut",
    "gn:country_code":"US",
    "gn:dem":154,
    "gn:elevation":"152.0",
    "gn:feature_class":"P",
    "gn:feature_code":"PPL",
    "gn:name":"Nockenut",
    "gn:population":0,
    "gn:timezone":"America/Chicago",
    "iso:country":"US",
    "wof:name":"Nockenut",
    "wof:placetype":"locality"
},
  "geometry": {"coordinates":[-97.91167,29.34635],"type":"Point"}
}