{
  "type": "Feature",
  "properties": {
    "gn:admin1_code":"VA",
    "gn:admin2_code":"47",
    "gn:asciiname":"Homeland",
    "gn:country_code":"US",
    "gn:dem":153,
    "gn:elevation":"153.0",
    "gn:feature_class":"P",
    "gn:feature_code":"PPL",
    "gn:name":"Homeland",
    "gn:population":0,
    "gn:timezone":"America/New_York",
    "iso:country":"US",
    "name:ara_x_preferred":[
        "\u0648\u0637\u0646"
    ],
    "name:arc_x_preferred":[
        "\u0721\u072c\u0710"
    ],
    "name:arz_x_preferred":[
        "\u0648\u0637\u0646"
    ],
    "name:ben_x_preferred":[
        "\u099c\u09a8\u09cd\u09ae\u09ad\u09c2\u09ae\u09bf"
    ],
    "name:epo_x_preferred":[
        "Hejmo"
    ],
    "name:est_x_preferred":[
        "Kodumaa"
    ],
    "name:fas_x_preferred":[
        "\u0645\u06cc\u0647\u0646"
    ],
    "name:hye_x_preferred":[
        "\u0540\u0561\u0575\u0580\u0565\u0576\u056b\u0584"
    ],
    "name:kan_x_preferred":[
        "\u0ca4\u0cbe\u0caf\u0cbf\u0ca8\u0cbe\u0ca1\u0cc1"
    ],
    "name:nld_x_preferred":[
        "Thuisland"
    ],
    "name:rus_x_preferred":[
        "\u0420\u043e\u0434\u0438\u043d\u0430"
    ],
    "name:sin_x_preferred":[
        "\u0db1\u0dd2\u0da2\u0db6\u0dd2\u0db8"
    ],
    "name:sqi_x_preferred":[
        "M\u00ebm\u00ebdheu"
    ],
    "wof:name":"Homeland",
    "wof:placetype":"locality"
},
  "geometry": {"coordinates":[-78.03222,38.60984000000001],"type":"Point"}
}