{
  "type": "Feature",
  "properties": {
    "gn:country":"US",
    "gn:fcode":"PPL",
    "gn:population":0,
    "iso:country":"US",
    "name:cym_x_preferred":[
        "Nemah"
    ],
    "name:deu_x_preferred":[
        "Nemah"
    ],
    "name:eng_x_preferred":[
        "Nemah"
    ],
    "name:fas_x_preferred":[
        "\u0646\u06cc\u0645\u0627\u0647"
    ],
    "name:hun_x_preferred":[
        "Nemah"
    ],
    "name:nld_x_preferred":[
        "Nemah"
    ],
    "qs_pg:aaroncc":"US",
    "qs_pg:gn_country":"US",
    "qs_pg:gn_fcode":"PPL",
    "qs_pg:gn_pop":0,
    "qs_pg:name":"Nemah",
    "qs_pg:name_adm0":"United States",
    "qs_pg:name_adm1":"Washington",
    "qs_pg:photos":232,
    "qs_pg:photos_1k":47,
    "qs_pg:photos_9k":1,
    "qs_pg:photos_9r":4,
    "qs_pg:photos_all":232,
    "qs_pg:photos_sr":4,
    "qs_pg:pop_sr":5,
    "qs_pg:qs_pg_placetype":"locality",
    "qs_pg:qs_pg_placetype_gp":"Town",
    "qs_pg:woe_adm0":23424977,
    "woe:adm0_id":23424977,
    "woe:name_adm0":"United States",
    "woe:name_adm1":"Washington",
    "woe:placetype":"Town",
    "wof:name":"Nemah",
    "wof:placetype":"locality"
},
  "geometry": {"coordinates":[-123.88599000000001,46.51204],"type":"Point"}
}