{
  "type": "Feature",
  "properties": {
    "iso:country":"US",
    "name:cym_x_preferred":[
        "Wilton"
    ],
    "name:eng_x_preferred":[
        "Wilton"
    ],
    "name:fra_x_preferred":[
        "Wilton"
    ],
    "qs_pg:aaroncc":"US",
    "qs_pg:name":"Wilton",
    "qs_pg:name_adm0":"United States",
    "qs_pg:name_adm1":"North Carolina",
    "qs_pg:photos":13,
    "qs_pg:photos_1k":3,
    "qs_pg:photos_9k":1,
    "qs_pg:photos_9r":1,
    "qs_pg:photos_all":13,
    "qs_pg:photos_sr":1,
    "qs_pg:pop_sr":0,
    "qs_pg:qs_pg_placetype":"locality",
    "qs_pg:qs_pg_placetype_gp":"Town",
    "qs_pg:woe_adm0":23424977,
    "woe:adm0_id":23424977,
    "woe:name_adm0":"United States",
    "woe:name_adm1":"North Carolina",
    "woe:placetype":"Town",
    "wof:name":"Wilton",
    "wof:placetype":"locality"
},
  "geometry": {"coordinates":[-78.578338,36.147855],"type":"Point"}
}