{
  "type": "Feature",
  "properties": {
    "gn:country":"US",
    "gn:fcode":"PPL",
    "gn:population":0,
    "iso:country":"US",
    "name:azb_x_preferred":[
        "\u0641\u06cc\u0634\u062a\u0631\u0627\u067e"
    ],
    "name:eng_x_preferred":[
        "Fishtrap"
    ],
    "name:fas_x_preferred":[
        "\u0641\u06cc\u0634\u062a\u0631\u0627\u067e"
    ],
    "name:fra_x_preferred":[
        "Fishtrap"
    ],
    "name:und_x_variant":[
        "Sims Trap"
    ],
    "name:zho_x_preferred":[
        "\u83f2\u4ec0\u7279\u62c9\u666e"
    ],
    "qs_pg:aaroncc":"US",
    "qs_pg:gn_country":"US",
    "qs_pg:gn_fcode":"PPL",
    "qs_pg:gn_pop":0,
    "qs_pg:name":"Fishtrap",
    "qs_pg:name_adm0":"United States",
    "qs_pg:name_adm1":"Alabama",
    "qs_pg:photos":30,
    "qs_pg:photos_1k":6,
    "qs_pg:photos_9k":1,
    "qs_pg:photos_9r":2,
    "qs_pg:photos_all":30,
    "qs_pg:photos_sr":2,
    "qs_pg:pop_sr":0,
    "qs_pg:qs_pg_placetype":"locality",
    "qs_pg:qs_pg_placetype_gp":"Town",
    "qs_pg:woe_adm0":23424977,
    "woe:adm0_id":23424977,
    "woe:name_adm0":"United States",
    "woe:name_adm1":"Alabama",
    "woe:placetype":"Town",
    "wof:name":"Fishtrap",
    "wof:placetype":"locality"
},
  "geometry": {"coordinates":[-86.24053000000001,33.49038],"type":"Point"}
}