{
  "type": "Feature",
  "properties": {
    "gn:admin1_code":"TX",
    "gn:admin2_code":"61.0",
    "gn:asciiname":"Channel Lots Colonia",
    "gn:country_code":"US",
    "gn:dem":3,
    "gn:elevation":"1.0",
    "gn:feature_class":"P",
    "gn:feature_code":"PPL",
    "gn:name":"Channel Lots Colonia",
    "gn:population":0,
    "gn:timezone":"America/Chicago",
    "iso:country":"US",
    "wof:name":"Channel Lots Colonia",
    "wof:placetype":"locality"
},
  "geometry": {"coordinates":[-97.42331,26.34424000000001],"type":"Point"}
}