{
  "type": "Feature",
  "properties": {
    "gn:admin1_code":"PA",
    "gn:admin2_code":"37.0",
    "gn:admin3_code":"50704.0",
    "gn:asciiname":"Grovania",
    "gn:country_code":"US",
    "gn:dem":189,
    "gn:elevation":"190.0",
    "gn:feature_class":"P",
    "gn:feature_code":"PPL",
    "gn:name":"Grovania",
    "gn:population":0,
    "gn:timezone":"America/New_York",
    "iso:country":"US",
    "wof:name":"Grovania",
    "wof:placetype":"locality"
},
  "geometry": {"coordinates":[-76.52495,40.97398],"type":"Point"}
}