{
  "type": "Feature",
  "properties": {
    "gn:admin1_code":"MI",
    "gn:admin2_code":"109.0",
    "gn:admin3_code":"75350.0",
    "gn:asciiname":"Faunus",
    "gn:country_code":"US",
    "gn:dem":291,
    "gn:elevation":"293.0",
    "gn:feature_class":"P",
    "gn:feature_code":"PPL",
    "gn:name":"Faunus",
    "gn:population":0,
    "gn:timezone":"America/Menominee",
    "iso:country":"US",
    "wof:name":"Faunus",
    "wof:placetype":"locality"
},
  "geometry": {"coordinates":[-87.50901999999998,45.89246],"type":"Point"}
}