{
  "type": "Feature",
  "properties": {
    "gn:admin1_code":"TX",
    "gn:admin2_code":"463.0",
    "gn:asciiname":"Trio",
    "gn:country_code":"US",
    "gn:dem":323,
    "gn:elevation":"324.0",
    "gn:feature_class":"P",
    "gn:feature_code":"PPL",
    "gn:name":"Trio",
    "gn:population":0,
    "gn:timezone":"America/Chicago",
    "iso:country":"US",
    "name:ceb_x_preferred":[
        "Tr\u00edo"
    ],
    "name:ces_x_preferred":[
        "Trio"
    ],
    "name:dan_x_preferred":[
        "Trio"
    ],
    "name:deu_x_preferred":[
        "Trio"
    ],
    "name:fra_x_preferred":[
        "Trio"
    ],
    "name:fry_x_preferred":[
        "Trio"
    ],
    "name:glg_x_preferred":[
        "Tr\u00edo"
    ],
    "name:heb_x_preferred":[
        "\u05d8\u05e8\u05d9\u05d5"
    ],
    "name:hrv_x_preferred":[
        "Trio"
    ],
    "name:hun_x_preferred":[
        "Trio"
    ],
    "name:ind_x_preferred":[
        "Trio"
    ],
    "name:ita_x_preferred":[
        "Trio"
    ],
    "name:jpn_x_preferred":[
        "\u30c8\u30ea\u30aa"
    ],
    "name:kor_x_preferred":[
        "\ud2b8\ub9ac\uc624"
    ],
    "name:ltz_x_preferred":[
        "Trio"
    ],
    "name:nds_x_preferred":[
        "Trio"
    ],
    "name:nld_x_preferred":[
        "Trio"
    ],
    "name:pol_x_preferred":[
        "Trio"
    ],
    "name:por_x_preferred":[
        "Trio"
    ],
    "name:rus_x_preferred":[
        "\u0422\u0440\u0438\u043e"
    ],
    "name:slk_x_preferred":[
        "Trio"
    ],
    "name:spa_x_preferred":[
        "Tr\u00edo"
    ],
    "name:srp_x_preferred":[
        "\u0422\u0440\u0438\u043e"
    ],
    "name:swe_x_preferred":[
        "Tr\u00edo"
    ],
    "name:ukr_x_preferred":[
        "\u0422\u0440\u0456\u043e"
    ],
    "wof:name":"Trio",
    "wof:placetype":"locality"
},
  "geometry": {"coordinates":[-99.55838,29.40246],"type":"Point"}
}