{
  "type": "Feature",
  "properties": {
    "gn:admin1_code":"FL",
    "gn:admin2_code":"111.0",
    "gn:asciiname":"Sunland Gardens",
    "gn:country_code":"US",
    "gn:dem":11,
    "gn:elevation":"6.0",
    "gn:feature_class":"P",
    "gn:feature_code":"PPL",
    "gn:name":"Sunland Gardens",
    "gn:population":0,
    "gn:timezone":"America/New_York",
    "iso:country":"US",
    "wof:name":"Sunland Gardens",
    "wof:placetype":"locality"
},
  "geometry": {"coordinates":[-80.36199999999999,27.46282],"type":"Point"}
}