{
  "type": "Feature",
  "properties": {
    "iso:country":"US",
    "name:eng_x_preferred":[
        "West Sullivan"
    ],
    "name:eng_x_variant":[
        "W Sullivan"
    ],
    "qs:gn_fcode":"PPL",
    "qs:gn_local":0,
    "qs:gn_namadm1":"ME",
    "qs:gn_name":"West Sullivan",
    "qs:local_max":36,
    "qs:local_sum":54,
    "qs:localhoods":2,
    "qs:name":"West Sullivan",
    "qs:name_adm0":"United States",
    "qs:name_adm1":"Maine",
    "qs:name_adm2":"Hancock",
    "qs:name_local":"Sullivan",
    "qs:photo_max":7,
    "qs:photo_sum":18,
    "qs:placetype":"Suburb",
    "qs:quad_count":4,
    "qs:woe_adm0":23424977,
    "qs:woe_adm1":2347578,
    "qs:woe_adm2":12588664,
    "qs:woe_lau":0,
    "qs:woe_local":2501430,
    "qs:woe_ver":"7.10.0",
    "wof:lang":[
        "eng"
    ],
    "wof:name":"West Sullivan",
    "wof:placetype":"neighbourhood",
    "wof:population":1252,
    "zs:blockids":[
        230099657002063,
        230099657001099,
        230099657002061,
        230099667004022,
        230099667004037,
        230099657002068,
        230099667004026,
        230099667004012,
        230099657002093,
        230099657002076,
        230099657002081,
        230099657002084,
        230099667004024,
        230099667004006,
        230099657002056,
        230099657002064,
        230099657002071,
        230099667004002,
        230099667004016,
        230099667004011,
        230099667004000,
        230099657002069,
        230099657002088,
        230099657002085,
        230099657002055,
        230099657002060,
        230099657002083,
        230099657001100,
        230099657001132,
        230099657002092,
        230099657001050,
        230099667004014,
        230099657002074,
        230099667004019,
        230099667004056,
        230099667004048,
        230099657002067,
        230099657002066,
        230099657002095,
        230099667004045,
        230099667004036,
        230099657002080,
        230099657002094,
        230099667004005,
        230099667004004,
        230099667004038,
        230099657002073,
        230099667004003,
        230099667004033,
        230099667004010,
        230099667004018,
        230099657002082,
        230099667004020,
        230099657002070,
        230099657002077,
        230099657002079,
        230099667004001,
        230099657002090,
        230099657002111,
        230099667004021,
        230099657002137,
        230099657002102,
        230099657002087,
        230099657002075,
        230099657002086,
        230099657002062,
        230099667004046,
        230099657002089,
        230099667004025,
        230099657001048,
        230099657002059,
        230099667004007,
        230099657002100,
        230099667004040,
        230099667004047,
        230099667004013,
        230099667004008,
        230099667004009,
        230099667004017,
        230099657002072
    ],
    "zs:housing10":744,
    "zs:pop10":1252
},
  "geometry": {"coordinates":[-68.223877,44.526103],"type":"Point"}
}