{
  "type": "Feature",
  "properties": {
    "gn:admin1_code":"OK",
    "gn:admin2_code":"55",
    "gn:asciiname":"Lake Creek",
    "gn:country_code":"US",
    "gn:dem":510,
    "gn:elevation":"506.0",
    "gn:feature_class":"P",
    "gn:feature_code":"PPL",
    "gn:name":"Lake Creek",
    "gn:population":0,
    "gn:timezone":"America/Chicago",
    "iso:country":"US",
    "name:ceb_x_preferred":[
        "Lake Creek"
    ],
    "name:deu_x_preferred":[
        "Lake Creek"
    ],
    "name:pol_x_preferred":[
        "Lake Creek"
    ],
    "name:swe_x_preferred":[
        "Lake Creek"
    ],
    "name:vol_x_preferred":[
        "Lake Creek"
    ],
    "wof:name":"Lake Creek",
    "wof:placetype":"locality"
},
  "geometry": {"coordinates":[-99.41342,35.0295],"type":"Point"}
}