{
  "type": "Feature",
  "properties": {
    "iso:country":"US",
    "name:ceb_x_preferred":[
        "Seven Hills"
    ],
    "name:eng_x_preferred":[
        "Seven Hills"
    ],
    "name:ita_x_preferred":[
        "Seven Hills"
    ],
    "name:nds_x_preferred":[
        "Seven Hills"
    ],
    "name:swe_x_preferred":[
        "Seven Hills"
    ],
    "name:ukr_x_preferred":[
        "\u0421\u0435\u0432\u0435\u043d-\u0413\u0456\u043b\u043b\u0441"
    ],
    "wof:name":"Seven Hills",
    "wof:placetype":"neighbourhood",
    "wof:population":83,
    "zs:area_m":256134.847025,
    "zs:blockids":[
        371950005011021,
        371950005011062,
        371950005011052,
        371950004002001,
        371950001003011
    ],
    "zs:housing10":38,
    "zs:label":"Seven Hills",
    "zs:pop10":83
},
  "geometry": {"coordinates":[-77.926957,35.736326],"type":"Point"}
}