{
  "type": "Feature",
  "properties": {
    "gn:country":"US",
    "gn:fcode":"PPL",
    "gn:population":0,
    "iso:country":"US",
    "name:ara_x_preferred":[
        "\u0643\u0648\u0646\u062c\u0627\u0631\u0649"
    ],
    "name:ben_x_preferred":[
        "\u0995\u0982\u0997\u09be\u09b0\u09c0"
    ],
    "name:deu_x_preferred":[
        "Congaree River"
    ],
    "name:ell_x_preferred":[
        "\u039a\u03bf\u03bd\u03b3\u03ba\u03b1\u03c1\u03af"
    ],
    "name:eng_x_preferred":[
        "Congaree"
    ],
    "name:fas_x_preferred":[
        "\u06a9\u0646\u06af\u0627\u0631\u06cc"
    ],
    "name:heb_x_preferred":[
        "\u05e7\u05d5\u05e0\u05d2\u05d0\u05e8\u05d9\u05d9"
    ],
    "name:hin_x_preferred":[
        "\u0915\u094b\u0902\u0917\u093e\u0930\u0940"
    ],
    "name:hun_x_preferred":[
        "Congaree"
    ],
    "name:ind_x_preferred":[
        "Congaree"
    ],
    "name:ita_x_preferred":[
        "Congaree"
    ],
    "name:kor_x_preferred":[
        "\ucf69\uac00\ub9ac"
    ],
    "name:nld_x_preferred":[
        "Congaree"
    ],
    "name:pol_x_preferred":[
        "Congaree"
    ],
    "name:por_x_preferred":[
        "Congaree"
    ],
    "name:rus_x_preferred":[
        "\u041a\u043e\u043d\u0433\u0430\u0440\u0438"
    ],
    "name:swe_x_preferred":[
        "Congaree"
    ],
    "name:ukr_x_preferred":[
        "\u041a\u043e\u043d\u0433\u0435\u0440\u0456"
    ],
    "name:und_x_variant":[
        "Grovewood"
    ],
    "name:urd_x_preferred":[
        "\u06a9\u0648\u0646\u06af\u0627\u0631\u06cc"
    ],
    "name:vie_x_preferred":[
        "S\u00f4ng Congaree"
    ],
    "name:zho_cn_x_preferred":[
        "\u5eb7\u52a0\u91cc\u6cb3"
    ],
    "name:zho_tw_x_preferred":[
        "\u5eb7\u52a0\u91cc\u6cb3"
    ],
    "qs_pg:aaroncc":"US",
    "qs_pg:gn_country":"US",
    "qs_pg:gn_fcode":"PPL",
    "qs_pg:gn_pop":0,
    "qs_pg:name":"Congaree",
    "qs_pg:name_adm0":"United States",
    "qs_pg:name_adm1":"South Carolina",
    "qs_pg:photos":171,
    "qs_pg:photos_1k":35,
    "qs_pg:photos_9k":1,
    "qs_pg:photos_9r":4,
    "qs_pg:photos_all":171,
    "qs_pg:photos_sr":4,
    "qs_pg:pop_sr":0,
    "qs_pg:qs_pg_placetype":"locality",
    "qs_pg:qs_pg_placetype_gp":"Town",
    "qs_pg:woe_adm0":23424977,
    "woe:adm0_id":23424977,
    "woe:name_adm0":"United States",
    "woe:name_adm1":"South Carolina",
    "woe:placetype":"Town",
    "wof:name":"Congaree",
    "wof:placetype":"locality"
},
  "geometry": {"coordinates":[-80.79509,33.9046],"type":"Point"}
}