{
  "type": "Feature",
  "properties": {
    "gn:admin1_code":"MD",
    "gn:admin2_code":"5.0",
    "gn:asciiname":"Essexshire Gate",
    "gn:country_code":"US",
    "gn:dem":5,
    "gn:elevation":"5.0",
    "gn:feature_class":"P",
    "gn:feature_code":"PPL",
    "gn:name":"Essexshire Gate",
    "gn:population":0,
    "gn:timezone":"America/New_York",
    "iso:country":"US",
    "wof:name":"Essexshire Gate",
    "wof:placetype":"locality"
},
  "geometry": {"coordinates":[-76.44968,39.3065],"type":"Point"}
}