{
  "type": "Feature",
  "properties": {
    "iso:country":"US",
    "name:eng_x_preferred":[
        "Verda Vista"
    ],
    "wof:name":"Verda Vista",
    "wof:placetype":"neighbourhood",
    "wof:population":579,
    "zs:area_m":548873.927695,
    "zs:blockids":[
        530110412052020,
        530110430001012,
        530110430001001,
        530110431004002,
        530110430001005,
        530110430001021,
        530110430001004,
        530110412053003,
        530110430001006,
        530110430001010,
        530110430001011
    ],
    "zs:housing10":269,
    "zs:label":"Verda Vista",
    "zs:pop10":579
},
  "geometry": {"coordinates":[-122.59451900000001,45.629477],"type":"Point"}
}