{
  "type": "Feature",
  "properties": {
    "gn:country":"US",
    "gn:fcode":"PPL",
    "gn:population":0,
    "iso:country":"US",
    "name:azb_x_preferred":[
        "\u0628\u0648\u06cc\u0644\u0632\u062a\u0648\u0646"
    ],
    "name:eng_x_preferred":[
        "Boyleston"
    ],
    "name:fas_x_preferred":[
        "\u0628\u0648\u06cc\u0644\u0633\u062a\u0648\u0646"
    ],
    "name:fra_x_preferred":[
        "Boyleston"
    ],
    "name:und_x_variant":[
        "Boylestown"
    ],
    "name:zho_x_preferred":[
        "\u535a\u4f0a\u723e\u65af\u9813"
    ],
    "qs_pg:aaroncc":"US",
    "qs_pg:gn_country":"US",
    "qs_pg:gn_fcode":"PPL",
    "qs_pg:gn_pop":0,
    "qs_pg:name":"Boyleston",
    "qs_pg:name_adm0":"United States",
    "qs_pg:name_adm1":"Indiana",
    "qs_pg:photos":16,
    "qs_pg:photos_1k":3,
    "qs_pg:photos_9k":1,
    "qs_pg:photos_9r":1,
    "qs_pg:photos_all":16,
    "qs_pg:photos_sr":1,
    "qs_pg:pop_sr":0,
    "qs_pg:qs_pg_placetype":"locality",
    "qs_pg:qs_pg_placetype_gp":"Town",
    "qs_pg:woe_adm0":23424977,
    "woe:adm0_id":23424977,
    "woe:name_adm0":"United States",
    "woe:name_adm1":"Indiana",
    "woe:placetype":"Town",
    "wof:name":"Boyleston",
    "wof:placetype":"locality"
},
  "geometry": {"coordinates":[-86.39472000000001,40.28643],"type":"Point"}
}