{
  "type": "Feature",
  "properties": {
    "iso:country":"US",
    "name:cat_x_preferred":[
        "Kirkwood"
    ],
    "name:ceb_x_preferred":[
        "Kirkwood"
    ],
    "name:deu_x_preferred":[
        "Kirkwood"
    ],
    "name:eng_x_preferred":[
        "Kirkwood"
    ],
    "name:fra_x_preferred":[
        "Kirkwood"
    ],
    "name:ita_x_preferred":[
        "Kirkwood"
    ],
    "name:jpn_x_preferred":[
        "\u30ab\u30fc\u30af\u30a6\u30c3\u30c9"
    ],
    "name:kor_x_preferred":[
        "\ucee4\ud06c\uc6b0\ub4dc"
    ],
    "name:nld_x_preferred":[
        "Kirkwood"
    ],
    "name:pol_x_preferred":[
        "Kirkwood"
    ],
    "name:por_x_preferred":[
        "Kirkwood"
    ],
    "name:rus_x_preferred":[
        "\u041a\u0438\u0440\u043a\u0432\u0443\u0434"
    ],
    "name:srp_x_preferred":[
        "\u041a\u0438\u0440\u043a\u0432\u0443\u0434"
    ],
    "name:swe_x_preferred":[
        "Kirkwood"
    ],
    "name:ukr_x_preferred":[
        "\u041a\u0456\u0440\u043a\u0432\u0443\u0434"
    ],
    "name:vol_x_preferred":[
        "Kirkwood"
    ],
    "wof:name":"Kirkwood",
    "wof:placetype":"neighbourhood",
    "wof:population":914,
    "zs:area_m":4177599.04149,
    "zs:blockids":[
        132150102012019,
        132150102012020
    ],
    "zs:housing10":286,
    "zs:label":"Kirkwood",
    "zs:pop10":914
},
  "geometry": {"coordinates":[-84.997497,32.561305],"type":"Point"}
}