{
  "type": "Feature",
  "properties": {
    "gn:country":"US",
    "gn:fcode":"PPL",
    "gn:population":0,
    "iso:country":"US",
    "name:ceb_x_preferred":[
        "Kingsville"
    ],
    "name:deu_x_preferred":[
        "Kingsville"
    ],
    "name:fin_x_preferred":[
        "Kingsville"
    ],
    "name:fra_x_preferred":[
        "Kingsville"
    ],
    "name:ita_x_preferred":[
        "Kingsville"
    ],
    "name:kor_x_preferred":[
        "\ud0b9\uc2a4\ube4c"
    ],
    "name:mlg_x_preferred":[
        "Kingsville"
    ],
    "name:nld_x_preferred":[
        "Kingsville"
    ],
    "name:pol_x_preferred":[
        "Kingsville"
    ],
    "name:por_x_preferred":[
        "Kingsville"
    ],
    "name:rus_x_preferred":[
        "\u041a\u0438\u043d\u0433\u0441\u0432\u0438\u043b\u043b"
    ],
    "name:spa_x_preferred":[
        "Kingsville"
    ],
    "name:srp_x_preferred":[
        "\u041a\u0438\u043d\u0433\u0441\u0432\u0438\u043b"
    ],
    "name:swe_x_preferred":[
        "Kingsville"
    ],
    "name:vol_x_preferred":[
        "Kingsville"
    ],
    "qs_pg:aaroncc":"US",
    "qs_pg:gn_country":"US",
    "qs_pg:gn_fcode":"PPL",
    "qs_pg:gn_pop":0,
    "qs_pg:name":"Kingsville",
    "qs_pg:name_adm0":"United States",
    "qs_pg:name_adm1":"Pennsylvania",
    "qs_pg:photos":20,
    "qs_pg:photos_1k":4,
    "qs_pg:photos_9k":1,
    "qs_pg:photos_9r":1,
    "qs_pg:photos_all":20,
    "qs_pg:photos_sr":1,
    "qs_pg:pop_sr":0,
    "qs_pg:qs_pg_placetype":"neighbourhood",
    "qs_pg:qs_pg_placetype_gp":"Suburb",
    "qs_pg:woe_adm0":23424977,
    "woe:adm0_id":23424977,
    "woe:name_adm0":"United States",
    "woe:name_adm1":"Pennsylvania",
    "woe:placetype":"Suburb",
    "wof:name":"Kingsville",
    "wof:placetype":"neighbourhood"
},
  "geometry": {"coordinates":[-79.26393,41.13173],"type":"Point"}
}