{
  "type": "Feature",
  "properties": {
    "iso:country":"US",
    "name:arg_x_preferred":[
        "Peralta"
    ],
    "name:cat_x_preferred":[
        "Peralta"
    ],
    "name:ceb_x_preferred":[
        "Peralta"
    ],
    "name:deu_x_preferred":[
        "Peralta"
    ],
    "name:eng_x_preferred":[
        "Peralta"
    ],
    "name:fra_x_preferred":[
        "Peralta"
    ],
    "name:ita_x_preferred":[
        "Peralta"
    ],
    "name:nld_x_preferred":[
        "Peralta"
    ],
    "name:por_x_preferred":[
        "Peralta"
    ],
    "name:rus_x_preferred":[
        "\u041f\u0435\u0440\u0430\u043b\u044c\u0442\u0430"
    ],
    "name:spa_x_preferred":[
        "Peralta"
    ],
    "name:swe_x_preferred":[
        "Peralta"
    ],
    "name:tgl_x_preferred":[
        "Peralta"
    ],
    "name:ukr_x_preferred":[
        "\u041f\u0435\u0440\u0430\u043b\u044c\u0442\u0430"
    ],
    "name:zho_yue_x_preferred":[
        "\u76ae\u62c9\u723e\u5854"
    ],
    "wd:wordcount":160,
    "wof:name":"Peralta",
    "wof:placetype":"neighbourhood",
    "wof:population":622,
    "zs:area_m":1376876.512205,
    "zs:blockids":[
        350490001011029,
        350490001011033,
        350490001011032,
        350490001011038,
        350490001011036,
        350490001011037,
        350490105001039,
        350490001011031,
        350490001011023
    ],
    "zs:housing10":531,
    "zs:label":"Peralta",
    "zs:pop10":622
},
  "geometry": {"coordinates":[-105.916903,35.691864],"type":"Point"}
}