{
  "type": "Feature",
  "properties": {
    "gn:admin1_code":"MT",
    "gn:admin2_code":"93.0",
    "gn:asciiname":"Valley Vista Mobile Home Community",
    "gn:country_code":"US",
    "gn:dem":1694,
    "gn:elevation":"1697.0",
    "gn:feature_class":"P",
    "gn:feature_code":"PPL",
    "gn:name":"Valley Vista Mobile Home Community",
    "gn:population":0,
    "gn:timezone":"America/Denver",
    "iso:country":"US",
    "wof:name":"Valley Vista Mobile Home Community",
    "wof:placetype":"campus"
},
  "geometry": {"coordinates":[-112.51474,45.94715],"type":"Point"}
}