{
  "type": "Feature",
  "properties": {
    "iso:country":"US",
    "name:ceb_x_preferred":[
        "North Cove"
    ],
    "name:eng_x_preferred":[
        "North Cove"
    ],
    "name:nld_x_preferred":[
        "North Cove"
    ],
    "name:pol_x_preferred":[
        "North Cove"
    ],
    "name:swe_x_preferred":[
        "North Cove"
    ],
    "wd:wordcount":884,
    "wof:name":"North Cove",
    "wof:placetype":"neighbourhood",
    "wof:population":396,
    "zs:area_m":3188878.760291,
    "zs:blockids":[
        511990510002001,
        511990510001056,
        511990510001094,
        511990510001057,
        511990510003020,
        511990510001092,
        511990510001065,
        511990510001061,
        511990510003019,
        511990510002008,
        511990510002000,
        511990510001054,
        511990510001071,
        511990510003021,
        511990510001072,
        511990510003023,
        511990510002010,
        511990510001070,
        511990510001067,
        511990510001082,
        511990510001068,
        511990510001096,
        511990510003024,
        511990510003022,
        511990510001062,
        511990510001060,
        511990510001084,
        511990510002009,
        511990510001058,
        511990510002005,
        511990510001093,
        511990510003025,
        511990510001083,
        511990510001077,
        511990510001066,
        511990510001095
    ],
    "zs:housing10":157,
    "zs:label":"North Cove",
    "zs:pop10":396
},
  "geometry": {"coordinates":[-76.708411,37.358373],"type":"Point"}
}