{
  "type": "Feature",
  "properties": {
    "gn:admin1_code":"VT",
    "gn:admin2_code":"19.0",
    "gn:admin3_code":"30175.0",
    "gn:asciiname":"Tolman Corner",
    "gn:country_code":"US",
    "gn:dem":449,
    "gn:elevation":"449.0",
    "gn:feature_class":"P",
    "gn:feature_code":"PPL",
    "gn:name":"Tolman Corner",
    "gn:population":0,
    "gn:timezone":"America/New_York",
    "iso:country":"US",
    "name:eng_x_preferred":[
        "Tolman Corner"
    ],
    "name:und_x_variant":[
        "Tolman",
        "Tolmans Corner"
    ],
    "wof:name":"Tolman Corner",
    "wof:placetype":"locality"
},
  "geometry": {"coordinates":[-72.30677,44.56755],"type":"Point"}
}