{
  "type": "Feature",
  "properties": {
    "gn:country":"US",
    "gn:fcode":"PPL",
    "gn:population":0,
    "iso:country":"US",
    "name:azb_x_preferred":[
        "\u0628\u06cc\u0642 \u0641\u0648\u0631"
    ],
    "name:deu_x_preferred":[
        "Big Four"
    ],
    "name:eng_x_preferred":[
        "Big Four"
    ],
    "name:fas_x_preferred":[
        "\u0628\u06cc\u06af \u0641\u0648\u0631"
    ],
    "name:fra_x_preferred":[
        "Big Four"
    ],
    "name:spa_x_preferred":[
        "Big Four"
    ],
    "name:und_x_variant":[
        "Cirrus"
    ],
    "name:vol_x_preferred":[
        "Big Four"
    ],
    "qs_pg:aaroncc":"US",
    "qs_pg:gn_country":"US",
    "qs_pg:gn_fcode":"PPL",
    "qs_pg:gn_pop":0,
    "qs_pg:name":"Big Four",
    "qs_pg:name_adm0":"United States",
    "qs_pg:name_adm1":"West Virginia",
    "qs_pg:photos":37,
    "qs_pg:photos_1k":7,
    "qs_pg:photos_9k":1,
    "qs_pg:photos_9r":2,
    "qs_pg:photos_all":37,
    "qs_pg:photos_sr":2,
    "qs_pg:pop_sr":0,
    "qs_pg:qs_pg_placetype":"locality",
    "qs_pg:qs_pg_placetype_gp":"Town",
    "qs_pg:woe_adm0":23424977,
    "woe:adm0_id":23424977,
    "woe:name_adm0":"United States",
    "woe:name_adm1":"West Virginia",
    "woe:placetype":"Town",
    "wof:name":"Big Four",
    "wof:placetype":"locality"
},
  "geometry": {"coordinates":[-81.52066000000001,37.41484],"type":"Point"}
}