{
  "type": "Feature",
  "properties": {
    "gn:country":"US",
    "gn:elevation":37,
    "gn:fcode":"PPL",
    "gn:population":0,
    "iso:country":"US",
    "name:cat_x_preferred":[
        "Lodi"
    ],
    "name:ceb_x_preferred":[
        "Lodi"
    ],
    "name:deu_x_preferred":[
        "Lodi"
    ],
    "name:eng_x_preferred":[
        "Lodi"
    ],
    "name:est_x_preferred":[
        "Lodi"
    ],
    "name:fas_x_preferred":[
        "\u0644\u0648\u062f\u06cc"
    ],
    "name:fin_x_preferred":[
        "Lodi"
    ],
    "name:fra_x_preferred":[
        "Lodi"
    ],
    "name:ita_x_preferred":[
        "Lodi"
    ],
    "name:nld_x_preferred":[
        "Lodi"
    ],
    "name:pms_x_preferred":[
        "Lodi"
    ],
    "name:pol_x_preferred":[
        "Lodi"
    ],
    "name:por_x_preferred":[
        "Lodi"
    ],
    "name:spa_x_preferred":[
        "Lodi"
    ],
    "name:swe_x_preferred":[
        "Lodi"
    ],
    "name:ukr_x_preferred":[
        "\u041b\u043e\u0434\u0456"
    ],
    "name:vol_x_preferred":[
        "Lodi"
    ],
    "qs_pg:aaroncc":"US",
    "qs_pg:gn_country":"US",
    "qs_pg:gn_fcode":"PPL",
    "qs_pg:gn_pop":0,
    "qs_pg:name":"Lodi",
    "qs_pg:name_adm0":"United States",
    "qs_pg:name_adm1":"Pennsylvania",
    "qs_pg:photos":303,
    "qs_pg:photos_1k":61,
    "qs_pg:photos_9k":1,
    "qs_pg:photos_9r":5,
    "qs_pg:photos_all":303,
    "qs_pg:photos_sr":5,
    "qs_pg:pop_sr":0,
    "qs_pg:qs_pg_placetype":"neighbourhood",
    "qs_pg:qs_pg_placetype_gp":"Suburb",
    "qs_pg:woe_adm0":23424977,
    "woe:adm0_id":23424977,
    "woe:name_adm0":"United States",
    "woe:name_adm1":"Pennsylvania",
    "woe:placetype":"Suburb",
    "wof:name":"Lodi",
    "wof:placetype":"neighbourhood",
    "wof:population":452
},
  "geometry": {"coordinates":[-75.08405999999999,40.55149],"type":"Point"}
}