{
  "type": "Feature",
  "properties": {
    "gn:admin1_code":"NY",
    "gn:admin2_code":"101.0",
    "gn:admin3_code":"11946.0",
    "gn:asciiname":"Green Meadow Acres Mobile Home Park",
    "gn:country_code":"US",
    "gn:dem":323,
    "gn:elevation":"329.0",
    "gn:feature_class":"P",
    "gn:feature_code":"PPL",
    "gn:name":"Green Meadow Acres Mobile Home Park",
    "gn:population":0,
    "gn:timezone":"America/New_York",
    "iso:country":"US",
    "wof:name":"Green Meadow Acres Mobile Home Park",
    "wof:placetype":"campus"
},
  "geometry": {"coordinates":[-77.21526,42.27173],"type":"Point"}
}