{
  "type": "Feature",
  "properties": {
    "gn:country":"US",
    "gn:fcode":"PPL",
    "gn:population":0,
    "iso:country":"US",
    "name:cat_x_preferred":[
        "Ward"
    ],
    "name:ceb_x_preferred":[
        "Ward"
    ],
    "name:ces_x_preferred":[
        "Ward"
    ],
    "name:deu_x_preferred":[
        "Ward"
    ],
    "name:fin_x_preferred":[
        "Ward"
    ],
    "name:fra_x_preferred":[
        "Ward"
    ],
    "name:ita_x_preferred":[
        "Ward"
    ],
    "name:jpn_x_preferred":[
        "\u30a6\u30a9\u30fc\u30c9"
    ],
    "name:nld_x_preferred":[
        "Ward"
    ],
    "name:pol_x_preferred":[
        "Ward"
    ],
    "name:por_x_preferred":[
        "Ward"
    ],
    "name:rus_x_preferred":[
        "\u0423\u043e\u0440\u0434"
    ],
    "name:slk_x_preferred":[
        "Ward"
    ],
    "name:swe_x_preferred":[
        "Ward"
    ],
    "name:urd_x_preferred":[
        "\u0648\u0627\u0631\u0688"
    ],
    "name:vol_x_preferred":[
        "Ward"
    ],
    "qs_pg:aaroncc":"US",
    "qs_pg:gn_country":"US",
    "qs_pg:gn_fcode":"PPL",
    "qs_pg:gn_pop":0,
    "qs_pg:name":"Ward",
    "qs_pg:name_adm0":"United States",
    "qs_pg:name_adm1":"New York",
    "qs_pg:photos":21,
    "qs_pg:photos_1k":4,
    "qs_pg:photos_9k":1,
    "qs_pg:photos_9r":1,
    "qs_pg:photos_all":24,
    "qs_pg:photos_sr":1,
    "qs_pg:pop_sr":0,
    "qs_pg:qs_pg_placetype":"locality",
    "qs_pg:qs_pg_placetype_gp":"Town",
    "qs_pg:woe_adm0":23424977,
    "woe:adm0_id":23424977,
    "woe:name_adm0":"United States",
    "woe:name_adm1":"New York",
    "woe:placetype":"Town",
    "wof:name":"Ward",
    "wof:placetype":"locality"
},
  "geometry": {"coordinates":[-77.50888,42.36424],"type":"Point"}
}