{
  "type": "Feature",
  "properties": {
    "gn:country":"US",
    "gn:fcode":"ADMD",
    "gn:population":0,
    "iso:country":"US",
    "name:ara_x_preferred":[
        "\u0623\u0648\u062a\u064a\u0633\u0641\u064a\u0644\u062f"
    ],
    "name:cat_x_preferred":[
        "Otisfield"
    ],
    "name:che_x_preferred":[
        "\u041e\u0442\u0438\u0441\u0444\u0438\u043b\u0434"
    ],
    "name:cym_x_preferred":[
        "Otisfield"
    ],
    "name:deu_x_preferred":[
        "Otisfield"
    ],
    "name:eng_x_preferred":[
        "Otisfield"
    ],
    "name:eus_x_preferred":[
        "Otisfield"
    ],
    "name:fra_x_preferred":[
        "Otisfield"
    ],
    "name:hat_x_preferred":[
        "Otisfield"
    ],
    "name:hun_x_preferred":[
        "Otisfield"
    ],
    "name:ita_x_preferred":[
        "Otisfield"
    ],
    "name:jpn_x_preferred":[
        "\u30aa\u30fc\u30c6\u30a3\u30b9\u30d5\u30a3\u30fc\u30eb\u30c9"
    ],
    "name:kaz_x_preferred":[
        "\u041e\u0442\u0438\u0441\u0444\u0438\u043b\u0434"
    ],
    "name:kir_x_preferred":[
        "\u041e\u0442\u0438\u0441\u0444\u0438\u043b\u0434"
    ],
    "name:nld_x_preferred":[
        "Otisfield"
    ],
    "name:pol_x_preferred":[
        "Otisfield"
    ],
    "name:spa_x_preferred":[
        "Otisfield"
    ],
    "name:swe_x_preferred":[
        "Otisfield"
    ],
    "name:tat_x_preferred":[
        "\u041e\u0442\u0438\u0441\u0444\u0438\u043b\u0434"
    ],
    "name:tur_x_preferred":[
        "Otisfield"
    ],
    "name:ukr_x_preferred":[
        "\u041e\u0442\u0456\u0441\u0444\u0456\u043b\u0434"
    ],
    "name:vol_x_preferred":[
        "Otisfield"
    ],
    "qs_pg:aaroncc":"US",
    "qs_pg:gn_country":"US",
    "qs_pg:gn_fcode":"ADMD",
    "qs_pg:gn_pop":0,
    "qs_pg:name":"Otisfield",
    "qs_pg:name_adm0":"United States",
    "qs_pg:name_adm1":"Maine",
    "qs_pg:photos":8,
    "qs_pg:photos_1k":2,
    "qs_pg:photos_9k":1,
    "qs_pg:photos_9r":3,
    "qs_pg:photos_all":98,
    "qs_pg:photos_sr":1,
    "qs_pg:pop_sr":0,
    "qs_pg:qs_pg_placetype":"locality",
    "qs_pg:qs_pg_placetype_gp":"Town",
    "qs_pg:woe_adm0":23424977,
    "woe:adm0_id":23424977,
    "woe:name_adm0":"United States",
    "woe:name_adm1":"Maine",
    "woe:placetype":"Town",
    "wof:coterminous":[
        404475761
    ],
    "wof:name":"Otisfield",
    "wof:placetype":"locality",
    "wof:population":1762,
    "wof:statistical_gore":1
},
  "geometry": {"coordinates":[-70.54944,44.09062],"type":"Point"}
}