{
  "type": "Feature",
  "properties": {
    "gn:admin1_code":"MD",
    "gn:admin2_code":"3.0",
    "gn:asciiname":"Benfield",
    "gn:country_code":"US",
    "gn:dem":41,
    "gn:elevation":"38.0",
    "gn:feature_class":"P",
    "gn:feature_code":"PPL",
    "gn:name":"Benfield",
    "gn:population":0,
    "gn:timezone":"America/New_York",
    "iso:country":"US",
    "wof:name":"Benfield",
    "wof:placetype":"locality"
},
  "geometry": {"coordinates":[-76.62219,39.08872],"type":"Point"}
}