{
  "type": "Feature",
  "properties": {
    "gn:admin1_code":"WV",
    "gn:admin2_code":"33",
    "gn:asciiname":"Lake Floyd",
    "gn:country_code":"US",
    "gn:dem":331,
    "gn:elevation":"327.0",
    "gn:feature_class":"P",
    "gn:feature_code":"PPL",
    "gn:name":"Lake Floyd",
    "gn:population":0,
    "gn:timezone":"America/New_York",
    "iso:country":"US",
    "wof:name":"Lake Floyd",
    "wof:placetype":"locality"
},
  "geometry": {"coordinates":[-80.50731999999998,39.2862],"type":"Point"}
}