{
  "type": "Feature",
  "properties": {
    "gn:admin1_code":"TX",
    "gn:admin2_code":"61.0",
    "gn:asciiname":"Bonnaville Terrace Colonia",
    "gn:country_code":"US",
    "gn:dem":16,
    "gn:elevation":"11.0",
    "gn:feature_class":"P",
    "gn:feature_code":"PPL",
    "gn:name":"Bonnaville Terrace Colonia",
    "gn:population":0,
    "gn:timezone":"America/Chicago",
    "iso:country":"US",
    "wof:name":"Bonnaville Terrace Colonia",
    "wof:placetype":"locality"
},
  "geometry": {"coordinates":[-97.71026999999999,26.22924],"type":"Point"}
}