{
  "type": "Feature",
  "properties": {
    "gn:admin1_code":"CT",
    "gn:admin2_code":"3.0",
    "gn:admin3_code":"4300.0",
    "gn:asciiname":"Turkey Hill",
    "gn:country_code":"US",
    "gn:dem":109,
    "gn:elevation":"105.0",
    "gn:feature_class":"P",
    "gn:feature_code":"PPL",
    "gn:name":"Turkey Hill",
    "gn:population":0,
    "gn:timezone":"America/New_York",
    "iso:country":"US",
    "name:ceb_x_preferred":[
        "Turkey Hill"
    ],
    "wof:name":"Turkey Hill",
    "wof:placetype":"locality"
},
  "geometry": {"coordinates":[-72.78565,41.61565],"type":"Point"}
}