{
  "type": "Feature",
  "properties": {
    "gn:admin1_code":"MI",
    "gn:admin2_code":"163.0",
    "gn:admin3_code":"81660.0",
    "gn:asciiname":"Roulo",
    "gn:country_code":"US",
    "gn:dem":205,
    "gn:elevation":"206.0",
    "gn:feature_class":"P",
    "gn:feature_code":"PPL",
    "gn:name":"Roulo",
    "gn:population":0,
    "gn:timezone":"America/Detroit",
    "iso:country":"US",
    "wof:name":"Roulo",
    "wof:placetype":"locality"
},
  "geometry": {"coordinates":[-83.48326999999998,42.19004],"type":"Point"}
}