{
  "type": "Feature",
  "properties": {
    "gn:admin1_code":"TX",
    "gn:admin2_code":"121",
    "gn:asciiname":"Drop",
    "gn:country_code":"US",
    "gn:dem":234,
    "gn:elevation":"231.0",
    "gn:feature_class":"P",
    "gn:feature_code":"PPL",
    "gn:name":"Drop",
    "gn:population":0,
    "gn:timezone":"America/Chicago",
    "iso:country":"US",
    "name:ces_x_preferred":[
        "Drop"
    ],
    "name:dan_x_preferred":[
        "Drop"
    ],
    "name:deu_x_preferred":[
        "Drop"
    ],
    "name:fin_x_preferred":[
        "Drop"
    ],
    "name:fra_x_preferred":[
        "Drop"
    ],
    "name:ita_x_preferred":[
        "Drop"
    ],
    "name:jpn_x_preferred":[
        "\u30c9\u30ed\u30c3\u30d7"
    ],
    "name:nor_x_preferred":[
        "Dr\u00e5pe"
    ],
    "wof:name":"Drop",
    "wof:placetype":"locality"
},
  "geometry": {"coordinates":[-97.35585,33.13095],"type":"Point"}
}