{
  "type": "Feature",
  "properties": {
    "iso:country":"US",
    "name:eng_x_preferred":[
        "Riverside Addition"
    ],
    "wof:name":"Riverside Addition",
    "wof:placetype":"neighbourhood",
    "wof:population":67,
    "zs:area_m":26121.864474,
    "zs:blockids":[
        490572005005013
    ],
    "zs:housing10":28,
    "zs:label":"Riverside Addition",
    "zs:pop10":67
},
  "geometry": {"coordinates":[-111.96652400000001,41.237187],"type":"Point"}
}