{
  "type": "Feature",
  "properties": {
    "gn:admin1_code":"LA",
    "gn:admin2_code":"57.0",
    "gn:asciiname":"Rousseau",
    "gn:country_code":"US",
    "gn:dem":4,
    "gn:elevation":"2.0",
    "gn:feature_class":"P",
    "gn:feature_code":"PPL",
    "gn:name":"Rousseau",
    "gn:population":0,
    "gn:timezone":"America/Chicago",
    "iso:country":"US",
    "wof:name":"Rousseau",
    "wof:placetype":"locality"
},
  "geometry": {"coordinates":[-90.72259,29.76354000000001],"type":"Point"}
}