{
  "type": "Feature",
  "properties": {
    "gn:admin1_code":"SC",
    "gn:admin2_code":"47.0",
    "gn:asciiname":"Druid Hills",
    "gn:country_code":"US",
    "gn:dem":197,
    "gn:elevation":"196.0",
    "gn:feature_class":"P",
    "gn:feature_code":"PPL",
    "gn:name":"Druid Hills",
    "gn:population":0,
    "gn:timezone":"America/New_York",
    "iso:country":"US",
    "wof:name":"Druid Hills",
    "wof:placetype":"locality"
},
  "geometry": {"coordinates":[-82.1854,34.22984],"type":"Point"}
}