{
  "type": "Feature",
  "properties": {
    "gn:admin1_code":"TN",
    "gn:admin2_code":"105",
    "gn:asciiname":"Eaton Forest",
    "gn:country_code":"US",
    "gn:dem":284,
    "gn:elevation":"281.0",
    "gn:feature_class":"P",
    "gn:feature_code":"PPL",
    "gn:name":"Eaton Forest",
    "gn:population":0,
    "gn:timezone":"America/New_York",
    "iso:country":"US",
    "wof:name":"Eaton Forest",
    "wof:placetype":"locality"
},
  "geometry": {"coordinates":[-84.31826,35.8348],"type":"Point"}
}