{
  "type": "Feature",
  "properties": {
    "gn:admin1_code":"FL",
    "gn:admin2_code":"57",
    "gn:asciiname":"The Retreat at Tampa Palms",
    "gn:country_code":"US",
    "gn:dem":22,
    "gn:elevation":"10.0",
    "gn:feature_class":"P",
    "gn:feature_code":"PPL",
    "gn:name":"The Retreat at Tampa Palms",
    "gn:population":0,
    "gn:timezone":"America/New_York",
    "iso:country":"US",
    "wof:name":"The Retreat at Tampa Palms",
    "wof:placetype":"locality"
},
  "geometry": {"coordinates":[-82.3887,28.1128],"type":"Point"}
}