{
  "type": "Feature",
  "properties": {
    "gn:admin1_code":"MD",
    "gn:admin2_code":"31.0",
    "gn:asciiname":"Silver Crest",
    "gn:country_code":"US",
    "gn:dem":196,
    "gn:elevation":"206.0",
    "gn:feature_class":"P",
    "gn:feature_code":"PPL",
    "gn:name":"Silver Crest",
    "gn:population":0,
    "gn:timezone":"America/New_York",
    "iso:country":"US",
    "wof:name":"Silver Crest",
    "wof:placetype":"locality"
},
  "geometry": {"coordinates":[-77.17081999999998,39.26538],"type":"Point"}
}