{
  "type": "Feature",
  "properties": {
    "iso:country":"US",
    "name:eng_x_preferred":[
        "Brentwood Hills"
    ],
    "wof:name":"Brentwood Hills",
    "wof:placetype":"neighbourhood",
    "wof:population":1477,
    "zs:area_m":1316487.358201,
    "zs:blockids":[
        120570133051004,
        120570133123008,
        120570133123012,
        120570133123011,
        120570133051002,
        120570133123006,
        120570133123004,
        120570133123021,
        120570133123016,
        120570133123010,
        120570133123014,
        120570133123007,
        120570133123020,
        120570133123017,
        120570133051005,
        120570133123005
    ],
    "zs:housing10":495,
    "zs:label":"Brentwood Hills",
    "zs:pop10":1477
},
  "geometry": {"coordinates":[-82.26512700000001,27.926201],"type":"Point"}
}