{
  "type": "Feature",
  "properties": {
    "gn:admin1_code":"OH",
    "gn:admin2_code":"133",
    "gn:admin3_code":"53858.0",
    "gn:asciiname":"Homestead Manor",
    "gn:country_code":"US",
    "gn:dem":301,
    "gn:elevation":"305.0",
    "gn:feature_class":"P",
    "gn:feature_code":"PPL",
    "gn:name":"Homestead Manor",
    "gn:population":0,
    "gn:timezone":"America/New_York",
    "iso:country":"US",
    "wof:name":"Homestead Manor",
    "wof:placetype":"locality"
},
  "geometry": {"coordinates":[-81.07528000000001,41.27472],"type":"Point"}
}