{
  "type": "Feature",
  "properties": {
    "gn:admin1_code":"MN",
    "gn:admin2_code":"111.0",
    "gn:admin3_code":"46060.0",
    "gn:asciiname":"Mills Manor Mobile Home Park",
    "gn:country_code":"US",
    "gn:dem":431,
    "gn:elevation":"430.0",
    "gn:feature_class":"P",
    "gn:feature_code":"PPL",
    "gn:name":"Mills Manor Mobile Home Park",
    "gn:population":0,
    "gn:timezone":"America/Chicago",
    "iso:country":"US",
    "wof:name":"Mills Manor Mobile Home Park",
    "wof:placetype":"campus"
},
  "geometry": {"coordinates":[-95.37582999999999,46.51806],"type":"Point"}
}