{
  "type": "Feature",
  "properties": {
    "gn:admin1_code":"NC",
    "gn:admin2_code":"169",
    "gn:admin3_code":"93016.0",
    "gn:asciiname":"Amostown",
    "gn:country_code":"US",
    "gn:dem":309,
    "gn:elevation":"307.0",
    "gn:feature_class":"P",
    "gn:feature_code":"PPL",
    "gn:name":"Amostown",
    "gn:population":0,
    "gn:timezone":"America/New_York",
    "iso:country":"US",
    "name:eng_x_preferred":[
        "Amostown"
    ],
    "name:und_x_variant":[
        "Amos Town"
    ],
    "wof:name":"Amostown",
    "wof:placetype":"locality"
},
  "geometry": {"coordinates":[-80.05421,36.5243],"type":"Point"}
}