{
  "type": "Feature",
  "properties": {
    "gn:admin1_code":"FL",
    "gn:admin2_code":"27.0",
    "gn:asciiname":"Jerrys Park Mobile Home Park",
    "gn:country_code":"US",
    "gn:dem":23,
    "gn:elevation":"18.0",
    "gn:feature_class":"P",
    "gn:feature_code":"PPL",
    "gn:name":"Jerrys Park Mobile Home Park",
    "gn:population":0,
    "gn:timezone":"America/New_York",
    "iso:country":"US",
    "wof:name":"Jerrys Park Mobile Home Park",
    "wof:placetype":"campus"
},
  "geometry": {"coordinates":[-81.8425,27.2578],"type":"Point"}
}