{
  "type": "Feature",
  "properties": {
    "gn:country":"US",
    "gn:fcode":"PPL",
    "gn:population":1350,
    "iso:country":"US",
    "name:ara_x_preferred":[
        "\u0625\u064a\u0633\u062a \u0645\u0627\u062a\u0634\u064a\u0627\u0633"
    ],
    "name:cat_x_preferred":[
        "East Machias"
    ],
    "name:ceb_x_preferred":[
        "East Machias"
    ],
    "name:deu_x_preferred":[
        "East Machias"
    ],
    "name:eng_x_preferred":[
        "East Machias"
    ],
    "name:eus_x_preferred":[
        "East Machias"
    ],
    "name:fra_x_preferred":[
        "East Machias"
    ],
    "name:hat_x_preferred":[
        "East Machias"
    ],
    "name:hun_x_preferred":[
        "East Machias"
    ],
    "name:ita_x_preferred":[
        "East Machias"
    ],
    "name:kaz_x_preferred":[
        "\u0418\u0441\u0442 \u041c\u0430\u0447\u0438\u0430\u0441"
    ],
    "name:kir_x_preferred":[
        "\u0418\u0441\u0442 \u041c\u0430\u0447\u0438\u0430\u0441"
    ],
    "name:nld_x_preferred":[
        "East Machias"
    ],
    "name:pol_x_preferred":[
        "East Machias"
    ],
    "name:spa_x_preferred":[
        "East Machias"
    ],
    "name:vol_x_preferred":[
        "East Machias"
    ],
    "qs_pg:aaroncc":"US",
    "qs_pg:gn_country":"US",
    "qs_pg:gn_fcode":"PPL",
    "qs_pg:gn_pop":1350,
    "qs_pg:name":"East Machias",
    "qs_pg:name_adm0":"United States",
    "qs_pg:name_adm1":"Maine",
    "qs_pg:photos":56,
    "qs_pg:photos_1k":11,
    "qs_pg:photos_9k":1,
    "qs_pg:photos_9r":2,
    "qs_pg:photos_all":68,
    "qs_pg:photos_sr":2,
    "qs_pg:pop_sr":3,
    "qs_pg:qs_pg_placetype":"locality",
    "qs_pg:qs_pg_placetype_gp":"Town",
    "qs_pg:woe_adm0":23424977,
    "woe:adm0_id":23424977,
    "woe:name_adm0":"United States",
    "woe:name_adm1":"Maine",
    "woe:placetype":"Town",
    "wof:name":"East Machias",
    "wof:placetype":"locality",
    "wof:population":1350
},
  "geometry": {"coordinates":[-67.38999,44.73924],"type":"Point"}
}