{
  "type": "Feature",
  "properties": {
    "iso:country":"US",
    "name:eng_x_preferred":[
        "Cimarron Hill"
    ],
    "name:eng_x_variant":[
        "Cimarron Hl",
        "Madigan"
    ],
    "qs:gn_adm0_cc":"US",
    "qs:gn_local":5405380,
    "qs:local_max":3963,
    "qs:local_sum":13042,
    "qs:localhoods":29,
    "qs:name":"Cimarron Hill",
    "qs:name_adm0":"United States",
    "qs:name_adm1":"California",
    "qs:name_adm2":"Solano",
    "qs:name_local":"Vallejo",
    "qs:photo_max":269,
    "qs:photo_sum":651,
    "qs:placetype":"Suburb",
    "qs:quad_count":20,
    "qs:woe_adm0":23424977,
    "qs:woe_adm1":2347563,
    "qs:woe_adm2":12587717,
    "qs:woe_lau":0,
    "qs:woe_local":2510744,
    "qs:woe_ver":"7.10.0",
    "wof:lang":[
        "eng"
    ],
    "wof:name":"Cimarron Hill",
    "wof:placetype":"neighbourhood",
    "wof:population":43,
    "zs:blockids":[
        60552010031041,
        60552010031039,
        60552010031040,
        60552010042000,
        60552010031042,
        60552010031045
    ],
    "zs:housing10":14,
    "zs:pop10":43
},
  "geometry": {"coordinates":[-122.227451,38.148445],"type":"Point"}
}