{
  "type": "Feature",
  "properties": {
    "gn:admin1_code":"FL",
    "gn:admin2_code":"57",
    "gn:asciiname":"Lago Whispers",
    "gn:country_code":"US",
    "gn:dem":19,
    "gn:elevation":"17.0",
    "gn:feature_class":"P",
    "gn:feature_code":"PPL",
    "gn:name":"Lago Whispers",
    "gn:population":0,
    "gn:timezone":"America/New_York",
    "iso:country":"US",
    "wof:name":"Lago Whispers",
    "wof:placetype":"locality"
},
  "geometry": {"coordinates":[-82.2881,28.0548],"type":"Point"}
}