{
  "type": "Feature",
  "properties": {
    "gn:admin1_code":"CT",
    "gn:admin2_code":"1.0",
    "gn:admin3_code":"18500.0",
    "gn:asciiname":"Ta'agan Point",
    "gn:country_code":"US",
    "gn:dem":144,
    "gn:elevation":"138.0",
    "gn:feature_class":"P",
    "gn:feature_code":"PPL",
    "gn:name":"Ta'agan Point",
    "gn:population":0,
    "gn:timezone":"America/New_York",
    "iso:country":"US",
    "wof:name":"Ta'agan Point",
    "wof:placetype":"locality"
},
  "geometry": {"coordinates":[-73.45318,41.43759],"type":"Point"}
}