{
  "type": "Feature",
  "properties": {
    "gn:admin1_code":"WI",
    "gn:admin2_code":"5.0",
    "gn:admin3_code":"58950.0",
    "gn:asciiname":"Tuscobia",
    "gn:country_code":"US",
    "gn:dem":358,
    "gn:elevation":"361.0",
    "gn:feature_class":"P",
    "gn:feature_code":"PPL",
    "gn:name":"Tuscobia",
    "gn:population":0,
    "gn:timezone":"America/Chicago",
    "iso:country":"US",
    "name:fas_x_preferred":[
        "\u062a\u0648\u0633\u06a9\u0628\u06cc\u0627"
    ],
    "name:urd_x_preferred":[
        "\u0679\u0633\u06a9\u0648\u0628\u06cc\u0627"
    ],
    "wof:name":"Tuscobia",
    "wof:placetype":"locality"
},
  "geometry": {"coordinates":[-91.75823,45.5669],"type":"Point"}
}