{
  "type": "Feature",
  "properties": {
    "gn:admin1_code":"KY",
    "gn:admin2_code":"235",
    "gn:asciiname":"Rain",
    "gn:country_code":"US",
    "gn:dem":327,
    "gn:elevation":"316.0",
    "gn:feature_class":"P",
    "gn:feature_code":"PPL",
    "gn:name":"Rain",
    "gn:population":0,
    "gn:timezone":"America/New_York",
    "iso:country":"US",
    "name:eng_x_preferred":[
        "Rain"
    ],
    "name:und_x_variant":[
        "Locust Grove"
    ],
    "wof:name":"Rain",
    "wof:placetype":"locality"
},
  "geometry": {"coordinates":[-83.94493,36.72064],"type":"Point"}
}