{
  "type": "Feature",
  "properties": {
    "gn:admin1_code":"KY",
    "gn:admin2_code":"67",
    "gn:asciiname":"Clays Ferry",
    "gn:country_code":"US",
    "gn:dem":197,
    "gn:elevation":"176.0",
    "gn:feature_class":"P",
    "gn:feature_code":"PPL",
    "gn:name":"Clays Ferry",
    "gn:population":0,
    "gn:timezone":"America/New_York",
    "iso:country":"US",
    "wof:name":"Clays Ferry",
    "wof:placetype":"locality"
},
  "geometry": {"coordinates":[-84.34096,37.88403],"type":"Point"}
}