{
  "type": "Feature",
  "properties": {
    "iso:country":"US",
    "name:ceb_x_preferred":[
        "Fisk"
    ],
    "name:dan_x_preferred":[
        "Fisk"
    ],
    "name:deu_x_preferred":[
        "Fisk"
    ],
    "name:eng_x_preferred":[
        "Fisk"
    ],
    "name:fin_x_preferred":[
        "Fisk"
    ],
    "name:fra_x_preferred":[
        "Fisk"
    ],
    "name:ita_x_preferred":[
        "Fisk"
    ],
    "name:jpn_x_preferred":[
        "\u30d5\u30a3\u30b9\u30af"
    ],
    "name:nld_x_preferred":[
        "Fisk"
    ],
    "name:por_x_preferred":[
        "Fisk"
    ],
    "name:rus_x_preferred":[
        "\u0424\u0438\u0441\u043a"
    ],
    "name:swe_x_preferred":[
        "Fisk"
    ],
    "wd:wordcount":35,
    "wof:name":"Fisk",
    "wof:placetype":"neighbourhood",
    "wof:population":531,
    "zs:area_m":29246348.905248,
    "zs:blockids":[
        551390020004030,
        551390020004082,
        551390020004026,
        551390020004019,
        551390020004004,
        551390020004051,
        551390020004043,
        551390020004068,
        551390020004069,
        551390020004066,
        551390020004039,
        551390020004086,
        551390020004024,
        551390020004008,
        551390020004044,
        551390020004045,
        551390020004036,
        551390020004038,
        551390020004070,
        551390020004155,
        551390020004156,
        551390020004021,
        551390020004146,
        551390020004029,
        551390020004059,
        551390020004060,
        551390020004157,
        551390020004022,
        551390020004037,
        551390020004028,
        551390020004057,
        551390020004031,
        551390020004018,
        551390020004052,
        551390020004067,
        551390020004040,
        551390020004025,
        551390020004065,
        551390020004003,
        551390020004027,
        551390020004084,
        551390020004053,
        551390020004083,
        551390020004042,
        551390020004147,
        551390020004079,
        551390020004071,
        551390020004080,
        551390020004081,
        551390020004032,
        551390020004141,
        551390020004139,
        551390020004041,
        551390020004023,
        551390020004033,
        551390020004034,
        551390020004064,
        551390020004047,
        551390020004058,
        551390020004061,
        551390020004035,
        551390020004085,
        551390020004020
    ],
    "zs:housing10":219,
    "zs:label":"Fisk",
    "zs:pop10":531
},
  "geometry": {"coordinates":[-88.66726300000001,43.947796],"type":"Point"}
}