{
  "type": "Feature",
  "properties": {
    "gn:admin1_code":"NV",
    "gn:admin2_code":"5.0",
    "gn:asciiname":"Lincoln Park",
    "gn:country_code":"US",
    "gn:dem":1909,
    "gn:elevation":"1906.0",
    "gn:feature_class":"P",
    "gn:feature_code":"PPL",
    "gn:name":"Lincoln Park",
    "gn:population":0,
    "gn:timezone":"America/Los_Angeles",
    "iso:country":"US",
    "name:epo_x_preferred":[
        "Parko Lincoln"
    ],
    "name:eus_x_preferred":[
        "Lincoln Park"
    ],
    "name:fas_x_preferred":[
        "\u067e\u0627\u0631\u06a9 \u0644\u06cc\u0646\u06a9\u0644\u0646"
    ],
    "name:jpn_x_preferred":[
        "\u30ea\u30f3\u30ab\u30fc\u30f3\u30fb\u30d1\u30fc\u30af"
    ],
    "name:kor_x_preferred":[
        "\ub9c1\ucee8 \uacf5\uc6d0"
    ],
    "name:nld_x_preferred":[
        "Lincoln Park"
    ],
    "name:nor_x_preferred":[
        "Lincoln Park"
    ],
    "name:por_x_preferred":[
        "Lincoln Park"
    ],
    "name:spa_x_preferred":[
        "Lincoln Park"
    ],
    "name:zho_x_preferred":[
        "\u6797\u80af\u516c\u56ed"
    ],
    "wof:name":"Lincoln Park",
    "wof:placetype":"locality"
},
  "geometry": {"coordinates":[-119.94823999999998,39.03963],"type":"Point"}
}