{
  "type": "Feature",
  "properties": {
    "gn:admin1_code":"VA",
    "gn:admin2_code":"79.0",
    "gn:asciiname":"Amicus",
    "gn:country_code":"US",
    "gn:dem":150,
    "gn:elevation":"152.0",
    "gn:feature_class":"P",
    "gn:feature_code":"PPL",
    "gn:name":"Amicus",
    "gn:population":0,
    "gn:timezone":"America/New_York",
    "iso:country":"US",
    "name:eng_x_preferred":[
        "Amicus"
    ],
    "name:und_x_variant":[
        "Americus"
    ],
    "wof:name":"Amicus",
    "wof:placetype":"locality"
},
  "geometry": {"coordinates":[-78.48000999999999,38.25569],"type":"Point"}
}