{
  "type": "Feature",
  "properties": {
    "gn:admin1_code":"FL",
    "gn:admin2_code":"83.0",
    "gn:asciiname":"Terry's Mobile Home Park",
    "gn:country_code":"US",
    "gn:dem":33,
    "gn:elevation":"23.0",
    "gn:feature_class":"P",
    "gn:feature_code":"PPL",
    "gn:name":"Terry's Mobile Home Park",
    "gn:population":0,
    "gn:timezone":"America/New_York",
    "iso:country":"US",
    "wof:name":"Terry's Mobile Home Park",
    "wof:placetype":"campus"
},
  "geometry": {"coordinates":[-82.01983,29.03058],"type":"Point"}
}