{
  "type": "Feature",
  "properties": {
    "gn:admin1_code":"MO",
    "gn:admin2_code":"9.0",
    "gn:admin3_code":"37142.0",
    "gn:asciiname":"Leann",
    "gn:country_code":"US",
    "gn:dem":347,
    "gn:elevation":"346.0",
    "gn:feature_class":"P",
    "gn:feature_code":"PPL",
    "gn:name":"Leann",
    "gn:population":0,
    "gn:timezone":"America/Chicago",
    "iso:country":"US",
    "name:eng_x_preferred":[
        "Leann"
    ],
    "name:und_x_variant":[
        "Marmaduke"
    ],
    "wof:name":"Leann",
    "wof:placetype":"locality"
},
  "geometry": {"coordinates":[-93.6902,36.81284],"type":"Point"}
}