{
  "type": "Feature",
  "properties": {
    "gn:admin1_code":"PA",
    "gn:admin2_code":"51.0",
    "gn:admin3_code":"73240.0",
    "gn:asciiname":"Gans",
    "gn:country_code":"US",
    "gn:dem":301,
    "gn:elevation":"301.0",
    "gn:feature_class":"P",
    "gn:feature_code":"PPL",
    "gn:name":"Gans",
    "gn:population":0,
    "gn:timezone":"America/New_York",
    "iso:country":"US",
    "wof:name":"Gans",
    "wof:placetype":"locality"
},
  "geometry": {"coordinates":[-79.82422,39.74286],"type":"Point"}
}