{
  "type": "Feature",
  "properties": {
    "gn:admin1_code":"MD",
    "gn:admin2_code":"45.0",
    "gn:asciiname":"Overbrook Manor",
    "gn:country_code":"US",
    "gn:dem":10,
    "gn:elevation":"10.0",
    "gn:feature_class":"P",
    "gn:feature_code":"PPL",
    "gn:name":"Overbrook Manor",
    "gn:population":0,
    "gn:timezone":"America/New_York",
    "iso:country":"US",
    "wof:name":"Overbrook Manor",
    "wof:placetype":"locality"
},
  "geometry": {"coordinates":[-75.59993,38.39262],"type":"Point"}
}