{
  "type": "Feature",
  "properties": {
    "iso:country":"US",
    "name:eng_x_preferred":[
        "Ozona Village Improvement Society"
    ],
    "wof:name":"Ozona Village Improvement Society",
    "wof:placetype":"neighbourhood",
    "wof:population":4117,
    "zs:area_m":7078222.578072,
    "zs:blockids":[
        121030272105010,
        121030272022020,
        121030272022005,
        121030272022008,
        121030272105000,
        121030272103009,
        121030272103011,
        121030272104002,
        121030272103013,
        121030272022010,
        121030272103008,
        121030272022027,
        121030272105007,
        121030272101013,
        121030272105006,
        121030272022001,
        121030272022037,
        121030272022009,
        121030272022026,
        121030272022018,
        121030272074012,
        121030272103018,
        121030272105019,
        121030272101001,
        121030272022028,
        121030272101006,
        121030272022003,
        121030272024027,
        121030272022002,
        121030272022015,
        121030272022042,
        121030272105001,
        121030272101010,
        121030272104005,
        121030272103004,
        121030272101005,
        121030272103007,
        121030272101019,
        121030272101012,
        121030272022023,
        121030272022036,
        121030272105004,
        121030272105008,
        121030272101002,
        121030272103001,
        121030272103012,
        121030272103014,
        121030272101009,
        121030272101039,
        121030272022024,
        121030272022034,
        121030272022013,
        121030272022038,
        121030272022025,
        121030272103010,
        121030272101007,
        121030272101016,
        121030272024025,
        121030272105003,
        121030272101008,
        121030272103015,
        121030272101000,
        121030272022041,
        121030272022012,
        121030272074011,
        121030272074010,
        121030272101014,
        121030272101017,
        121030272022029,
        121030272022021,
        121030272024024,
        121030272101018,
        121030272022014,
        121030272105013,
        121030272022004,
        121030272022011,
        121030272022030,
        121030272022031,
        121030272103003,
        121030272105012,
        121030272104004,
        121030272103019,
        121030272103000,
        121030272105005,
        121030272022000,
        121030272101015,
        121030272022022,
        121030272022017,
        121030272022007,
        121030272024026,
        121030272074009,
        121030272105002,
        121030272104003,
        121030272104006,
        121030272103016,
        121030272103002,
        121030272103021,
        121030272105011,
        121030272101003,
        121030272022033,
        121030272022016,
        121030272101011,
        121030272105009,
        121030272022019,
        121030272022039,
        121030272022006,
        121030272105014,
        121030272022032,
        121030272103017,
        121030272101004,
        121030272103005,
        121030272104007,
        121030272103020,
        121030272101024,
        121030272083003,
        121030272105015,
        121030272101045
    ],
    "zs:housing10":2711,
    "zs:label":"Ozona Village Improvement Society",
    "zs:pop10":4117
},
  "geometry": {"coordinates":[-82.781419,28.068814],"type":"Point"}
}