{
  "type": "Feature",
  "properties": {
    "iso:country":"US",
    "name:deu_x_preferred":[
        "Arbuckle"
    ],
    "name:eng_x_preferred":[
        "Arbuckle"
    ],
    "name:fra_x_preferred":[
        "Arbuckle"
    ],
    "name:nld_x_preferred":[
        "Arbuckle"
    ],
    "name:pol_x_preferred":[
        "Arbuckle"
    ],
    "qs:gn_adm0_cc":"US",
    "qs:gn_fcode":"PPL",
    "qs:gn_local":5178259,
    "qs:gn_nam_loc":"Amity, Erie, Pennsylvania, US",
    "qs:gn_namadm1":"PA",
    "qs:gn_name":"Arbuckle",
    "qs:local_max":15,
    "qs:local_sum":15,
    "qs:localhoods":1,
    "qs:name":"Arbuckle",
    "qs:name_adm0":"United States",
    "qs:name_adm1":"Pennsylvania",
    "qs:name_adm2":"Erie",
    "qs:name_local":"Amity",
    "qs:photo_max":13,
    "qs:photo_sum":15,
    "qs:placetype":"Suburb",
    "qs:quad_count":2,
    "qs:woe_adm0":23424977,
    "qs:woe_adm1":2347597,
    "qs:woe_adm2":12589752,
    "qs:woe_lau":0,
    "qs:woe_local":28744630,
    "qs:woe_ver":"7.10.0",
    "wd:wordcount":130,
    "wof:lang":[
        "eng"
    ],
    "wof:name":"Arbuckle",
    "wof:placetype":"neighbourhood",
    "wof:population":986,
    "zs:blockids":[
        420490112014046,
        420490118013019,
        420490112014015,
        420490118013039,
        420490118013020,
        420490112014047,
        420490121002053,
        420490118013034,
        420490121002040,
        420490120011041,
        420490118013035,
        420490112014014,
        420490112014045,
        420490120011034,
        420490118013015,
        420490120011044,
        420490121002037,
        420490118013014,
        420490121002002,
        420490121002052,
        420490121002036,
        420490120011047,
        420490121002003,
        420490112014013,
        420490118013017,
        420490118013037,
        420490120011033,
        420490112014049,
        420490112014018,
        420490118013036,
        420490121002038,
        420490121002001,
        420490118013016,
        420490118013040,
        420490120011046
    ],
    "zs:housing10":374,
    "zs:pop10":986
},
  "geometry": {"coordinates":[-79.900085,42.002366],"type":"Point"}
}