{
  "type": "Feature",
  "properties": {
    "gn:admin1_code":"FL",
    "gn:admin2_code":"57",
    "gn:asciiname":"Central Court",
    "gn:country_code":"US",
    "gn:dem":26,
    "gn:elevation":"14.0",
    "gn:feature_class":"P",
    "gn:feature_code":"PPL",
    "gn:name":"Central Court",
    "gn:population":0,
    "gn:timezone":"America/New_York",
    "iso:country":"US",
    "wof:name":"Central Court",
    "wof:placetype":"locality"
},
  "geometry": {"coordinates":[-82.4559,27.9688],"type":"Point"}
}