{
  "type": "Feature",
  "properties": {
    "gn:admin1_code":"WV",
    "gn:admin2_code":"109.0",
    "gn:asciiname":"Steeles",
    "gn:country_code":"US",
    "gn:dem":349,
    "gn:elevation":"341.0",
    "gn:feature_class":"P",
    "gn:feature_code":"PPL",
    "gn:name":"Steeles",
    "gn:population":0,
    "gn:timezone":"America/New_York",
    "iso:country":"US",
    "name:eng_x_preferred":[
        "Steeles"
    ],
    "name:und_x_variant":[
        "Trap Fork"
    ],
    "wof:name":"Steeles",
    "wof:placetype":"locality"
},
  "geometry": {"coordinates":[-81.77539,37.539],"type":"Point"}
}