{
  "type": "Feature",
  "properties": {
    "gn:admin1_code":"NV",
    "gn:admin2_code":"31.0",
    "gn:asciiname":"Deep Hole",
    "gn:country_code":"US",
    "gn:dem":1199,
    "gn:elevation":"1197.0",
    "gn:feature_class":"P",
    "gn:feature_code":"PPL",
    "gn:name":"Deep Hole",
    "gn:population":0,
    "gn:timezone":"America/Los_Angeles",
    "iso:country":"US",
    "name:ceb_x_preferred":[
        "Deep Hole"
    ],
    "name:eng_x_preferred":[
        "Deep Hole"
    ],
    "name:swe_x_preferred":[
        "Deep Hole"
    ],
    "name:und_x_variant":[
        "Deephole"
    ],
    "wof:name":"Deep Hole",
    "wof:placetype":"locality"
},
  "geometry": {"coordinates":[-119.48325,40.71907],"type":"Point"}
}