{
  "type": "Feature",
  "properties": {
    "gn:admin1_code":"FL",
    "gn:admin2_code":"83.0",
    "gn:asciiname":"Silver Oaks Mobile Home Park",
    "gn:country_code":"US",
    "gn:dem":24,
    "gn:elevation":"22.0",
    "gn:feature_class":"P",
    "gn:feature_code":"PPL",
    "gn:name":"Silver Oaks Mobile Home Park",
    "gn:population":0,
    "gn:timezone":"America/New_York",
    "iso:country":"US",
    "wof:name":"Silver Oaks Mobile Home Park",
    "wof:placetype":"campus"
},
  "geometry": {"coordinates":[-82.06478,29.07247000000001],"type":"Point"}
}