{
  "type": "Feature",
  "properties": {
    "gn:admin1_code":"TX",
    "gn:admin2_code":"285.0",
    "gn:asciiname":"Sweet Home",
    "gn:country_code":"US",
    "gn:dem":92,
    "gn:elevation":"87.0",
    "gn:feature_class":"P",
    "gn:feature_code":"PPL",
    "gn:name":"Sweet Home",
    "gn:population":0,
    "gn:timezone":"America/Chicago",
    "iso:country":"US",
    "name:ceb_x_preferred":[
        "Sweet Home"
    ],
    "name:deu_x_preferred":[
        "Sweet Home"
    ],
    "name:hun_x_preferred":[
        "Sweet Home"
    ],
    "name:ita_x_preferred":[
        "Sweet Home"
    ],
    "name:jpn_x_preferred":[
        "\u30b9\u30a6\u30a3\u30fc\u30c8\u30fb\u30db\u30fc\u30e0"
    ],
    "name:kor_x_preferred":[
        "\uc2a4\uc704\ud2b8 \ud648"
    ],
    "name:nld_x_preferred":[
        "Sweet Home"
    ],
    "name:pol_x_preferred":[
        "Sweet Home"
    ],
    "name:por_x_preferred":[
        "Sweet Home"
    ],
    "name:srp_x_preferred":[
        "\u0421\u0432\u0438\u0442 \u0425\u043e\u0443\u043c"
    ],
    "name:vol_x_preferred":[
        "Sweet Home"
    ],
    "wof:name":"Sweet Home",
    "wof:placetype":"locality"
},
  "geometry": {"coordinates":[-97.07165000000001,29.34524],"type":"Point"}
}