{
  "type": "Feature",
  "properties": {
    "gn:admin1_code":"WA",
    "gn:admin2_code":"61.0",
    "gn:asciiname":"Sands 55 Plus Mobile Park",
    "gn:country_code":"US",
    "gn:dem":23,
    "gn:elevation":"20.0",
    "gn:feature_class":"P",
    "gn:feature_code":"PPL",
    "gn:name":"Sands 55 Plus Mobile Park",
    "gn:population":0,
    "gn:timezone":"America/Los_Angeles",
    "iso:country":"US",
    "wof:name":"Sands 55 Plus Mobile Park",
    "wof:placetype":"locality"
},
  "geometry": {"coordinates":[-122.18176,48.09832],"type":"Point"}
}