{
  "type": "Feature",
  "properties": {
    "gn:admin1_code":"AK",
    "gn:admin2_code":"290.0",
    "gn:asciiname":"Iditarod",
    "gn:country_code":"US",
    "gn:dem":53,
    "gn:elevation":"46.0",
    "gn:feature_class":"P",
    "gn:feature_code":"PPL",
    "gn:name":"Iditarod",
    "gn:population":0,
    "gn:timezone":"America/Anchorage",
    "iso:country":"US",
    "name:azb_x_preferred":[
        "\u0622\u06cc\u062f\u06cc\u062a\u0631\u0627\u062f"
    ],
    "name:deu_x_preferred":[
        "Iditarod"
    ],
    "name:eng_x_preferred":[
        "Iditarod"
    ],
    "name:fas_x_preferred":[
        "\u0622\u06cc\u062f\u06cc\u062a\u0631\u0627\u062f"
    ],
    "name:fra_x_preferred":[
        "Iditarod"
    ],
    "name:pol_x_preferred":[
        "Iditarod"
    ],
    "name:und_x_variant":[
        "Ididarod",
        "Hwdedhot"
    ],
    "wof:name":"Iditarod",
    "wof:placetype":"locality"
},
  "geometry": {"coordinates":[-158.09528,62.54444],"type":"Point"}
}