{
  "type": "Feature",
  "properties": {
    "gn:admin1_code":"TN",
    "gn:admin2_code":"55.0",
    "gn:asciiname":"Vinta Mill",
    "gn:country_code":"US",
    "gn:dem":194,
    "gn:elevation":"186.0",
    "gn:feature_class":"P",
    "gn:feature_code":"PPL",
    "gn:name":"Vinta Mill",
    "gn:population":0,
    "gn:timezone":"America/Chicago",
    "iso:country":"US",
    "wof:name":"Vinta Mill",
    "wof:placetype":"locality"
},
  "geometry": {"coordinates":[-86.93916999999998,35.0698],"type":"Point"}
}