{
  "type": "Feature",
  "properties": {
    "gn:admin1_code":"OH",
    "gn:admin2_code":"115.0",
    "gn:admin3_code":"87066.0",
    "gn:asciiname":"Deavertown",
    "gn:country_code":"US",
    "gn:dem":289,
    "gn:elevation":"287.0",
    "gn:feature_class":"P",
    "gn:feature_code":"PPL",
    "gn:name":"Deavertown",
    "gn:population":0,
    "gn:timezone":"America/New_York",
    "iso:country":"US",
    "name:eng_x_preferred":[
        "Deavertown"
    ],
    "name:und_x_variant":[
        "Beaver Town",
        "New Market"
    ],
    "wof:name":"Deavertown",
    "wof:placetype":"locality"
},
  "geometry": {"coordinates":[-82.03792,39.73424],"type":"Point"}
}