{
  "type": "Feature",
  "properties": {
    "gn:admin1_code":"WA",
    "gn:admin2_code":"53.0",
    "gn:asciiname":"Excelsior",
    "gn:country_code":"US",
    "gn:dem":99,
    "gn:elevation":"99.0",
    "gn:feature_class":"P",
    "gn:feature_code":"PPL",
    "gn:name":"Excelsior",
    "gn:population":0,
    "gn:timezone":"America/Los_Angeles",
    "iso:country":"US",
    "name:bar_x_preferred":[
        "Excelsior"
    ],
    "name:ceb_x_preferred":[
        "Excelsior"
    ],
    "name:ces_x_preferred":[
        "Excelsior"
    ],
    "name:deu_x_preferred":[
        "Excelsior"
    ],
    "name:epo_x_preferred":[
        "Ekscelsior"
    ],
    "name:eus_x_preferred":[
        "Excelsior"
    ],
    "name:fin_x_preferred":[
        "Excelsior"
    ],
    "name:fra_x_preferred":[
        "Excelsior"
    ],
    "name:ita_x_preferred":[
        "Excelsior"
    ],
    "name:jpn_x_preferred":[
        "\u30a8\u30af\u30bb\u30eb\u30b7\u30aa\u30fc\u30eb"
    ],
    "name:nld_x_preferred":[
        "Excelsior"
    ],
    "name:pol_x_preferred":[
        "Excelsior"
    ],
    "name:ron_x_preferred":[
        "Excelsior"
    ],
    "name:rus_x_preferred":[
        "Excelsior"
    ],
    "name:slk_x_preferred":[
        "Excelsior"
    ],
    "name:spa_x_preferred":[
        "Excelsior"
    ],
    "name:swe_x_preferred":[
        "Excelsior"
    ],
    "name:ukr_x_preferred":[
        "\u0415\u043a\u0441\u0435\u043b\u0441\u0456\u043e\u0440"
    ],
    "name:vol_x_preferred":[
        "Excelsior"
    ],
    "wof:name":"Excelsior",
    "wof:placetype":"locality"
},
  "geometry": {"coordinates":[-122.45596,47.20315],"type":"Point"}
}