{
  "type": "Feature",
  "properties": {
    "gn:admin1_code":"TN",
    "gn:admin2_code":"55",
    "gn:asciiname":"Crescent View",
    "gn:country_code":"US",
    "gn:dem":206,
    "gn:elevation":"206.0",
    "gn:feature_class":"P",
    "gn:feature_code":"PPL",
    "gn:name":"Crescent View",
    "gn:population":0,
    "gn:timezone":"America/Chicago",
    "iso:country":"US",
    "wof:name":"Crescent View",
    "wof:placetype":"locality"
},
  "geometry": {"coordinates":[-87.02306,35.15286],"type":"Point"}
}