{
  "type": "Feature",
  "properties": {
    "gn:admin1_code":"KS",
    "gn:admin2_code":"169.0",
    "gn:admin3_code":"62700.0",
    "gn:asciiname":"Prairie Village Mobile Home Park",
    "gn:country_code":"US",
    "gn:dem":380,
    "gn:elevation":"375.0",
    "gn:feature_class":"P",
    "gn:feature_code":"PPL",
    "gn:name":"Prairie Village Mobile Home Park",
    "gn:population":0,
    "gn:timezone":"America/Chicago",
    "iso:country":"US",
    "wof:name":"Prairie Village Mobile Home Park",
    "wof:placetype":"campus"
},
  "geometry": {"coordinates":[-97.63265,38.81779],"type":"Point"}
}