{
  "type": "Feature",
  "properties": {
    "gn:admin1_code":"OR",
    "gn:admin2_code":"9.0",
    "gn:asciiname":"McNulty",
    "gn:country_code":"US",
    "gn:dem":38,
    "gn:elevation":"35.0",
    "gn:feature_class":"P",
    "gn:feature_code":"PPL",
    "gn:name":"McNulty",
    "gn:population":0,
    "gn:timezone":"America/Los_Angeles",
    "iso:country":"US",
    "wof:name":"McNulty",
    "wof:placetype":"locality"
},
  "geometry": {"coordinates":[-122.84177,45.84039],"type":"Point"}
}