{
  "type": "Feature",
  "properties": {
    "gn:admin1_code":"OK",
    "gn:admin2_code":"101.0",
    "gn:asciiname":"Yahola",
    "gn:country_code":"US",
    "gn:dem":170,
    "gn:elevation":"168.0",
    "gn:feature_class":"P",
    "gn:feature_code":"PPL",
    "gn:name":"Yahola",
    "gn:population":0,
    "gn:timezone":"America/Chicago",
    "iso:country":"US",
    "wof:name":"Yahola",
    "wof:placetype":"locality"
},
  "geometry": {"coordinates":[-95.60692,35.7626],"type":"Point"}
}