{
  "type": "Feature",
  "properties": {
    "gn:elevation":359,
    "iso:country":"US",
    "name:eng_x_preferred":[
        "Overlook Heights"
    ],
    "name:eng_x_variant":[
        "Overlook Hts"
    ],
    "qs:gn_adm0_cc":"US",
    "qs:gn_fcode":"PPL",
    "qs:gn_local":5189467,
    "qs:gn_nam_loc":"Ferguson, Centre, Pennsylvania, US",
    "qs:gn_namadm1":"PA",
    "qs:gn_name":"Overlook Heights",
    "qs:local_max":3630,
    "qs:local_sum":7016,
    "qs:localhoods":7,
    "qs:name":"Overlook Heights",
    "qs:name_adm0":"United States",
    "qs:name_adm1":"Pennsylvania",
    "qs:name_adm2":"Centre",
    "qs:name_local":"Ferguson",
    "qs:photo_max":276,
    "qs:photo_sum":919,
    "qs:placetype":"Suburb",
    "qs:quad_count":37,
    "qs:woe_adm0":23424977,
    "qs:woe_adm1":2347597,
    "qs:woe_adm2":12589741,
    "qs:woe_funk":"Grouping neighborhood",
    "qs:woe_lau":0,
    "qs:woe_local":28745481,
    "qs:woe_ver":"7.10.0",
    "wof:lang":[
        "eng"
    ],
    "wof:name":"Overlook Heights",
    "wof:placetype":"neighbourhood",
    "wof:population":5020,
    "zs:blockids":[
        420270115021001,
        420270113002003,
        420270115021009,
        420270113002006,
        420270113002001,
        420270113005000,
        420270113005001,
        420270113002005,
        420270113002002,
        420270113002007
    ],
    "zs:housing10":2451,
    "zs:pop10":5020
},
  "geometry": {"coordinates":[-77.891413,40.810008],"type":"Point"}
}