{
  "type": "Feature",
  "properties": {
    "iso:country":"US",
    "name:eng_x_preferred":[
        "Lambshire Downs"
    ],
    "wof:name":"Lambshire Downs",
    "wof:placetype":"neighbourhood",
    "wof:population":497,
    "zs:area_m":99866.106651,
    "zs:blockids":[
        371830537142026,
        371830537142030
    ],
    "zs:housing10":243,
    "zs:label":"Lambshire Downs",
    "zs:pop10":497
},
  "geometry": {"coordinates":[-78.68310700000001,35.862518],"type":"Point"}
}