{
  "type": "Feature",
  "properties": {
    "gn:admin1_code":"AR",
    "gn:admin2_code":"139.0",
    "gn:admin3_code":"93966.0",
    "gn:asciiname":"Wesson",
    "gn:country_code":"US",
    "gn:dem":75,
    "gn:elevation":"66.0",
    "gn:feature_class":"P",
    "gn:feature_code":"PPL",
    "gn:name":"Wesson",
    "gn:population":0,
    "gn:timezone":"America/Chicago",
    "iso:country":"US",
    "name:deu_x_preferred":[
        "Wesson"
    ],
    "name:fra_x_preferred":[
        "Wesson"
    ],
    "name:nds_x_preferred":[
        "Wesson"
    ],
    "name:pol_x_preferred":[
        "Wesson"
    ],
    "name:por_x_preferred":[
        "Wesson"
    ],
    "wof:name":"Wesson",
    "wof:placetype":"locality"
},
  "geometry": {"coordinates":[-92.76266,33.11541],"type":"Point"}
}