{
  "type": "Feature",
  "properties": {
    "gn:admin1_code":"MD",
    "gn:admin2_code":"13.0",
    "gn:asciiname":"Rocky Acres",
    "gn:country_code":"US",
    "gn:dem":183,
    "gn:elevation":"183.0",
    "gn:feature_class":"P",
    "gn:feature_code":"PPL",
    "gn:name":"Rocky Acres",
    "gn:population":0,
    "gn:timezone":"America/New_York",
    "iso:country":"US",
    "wof:name":"Rocky Acres",
    "wof:placetype":"locality"
},
  "geometry": {"coordinates":[-76.93692,39.47288],"type":"Point"}
}