{
  "type": "Feature",
  "properties": {
    "gn:admin1_code":"VA",
    "gn:admin2_code":"41",
    "gn:asciiname":"Brookwood Estates",
    "gn:country_code":"US",
    "gn:dem":95,
    "gn:elevation":"89.0",
    "gn:feature_class":"P",
    "gn:feature_code":"PPL",
    "gn:name":"Brookwood Estates",
    "gn:population":0,
    "gn:timezone":"America/New_York",
    "iso:country":"US",
    "wof:name":"Brookwood Estates",
    "wof:placetype":"locality"
},
  "geometry": {"coordinates":[-77.5686,37.52959],"type":"Point"}
}