{
  "type": "Feature",
  "properties": {
    "iso:country":"US",
    "name:deu_x_preferred":[
        "Barclay"
    ],
    "name:fin_x_preferred":[
        "Barclay"
    ],
    "name:fra_x_preferred":[
        "Barclay"
    ],
    "name:ita_x_preferred":[
        "Barclay"
    ],
    "name:nld_x_preferred":[
        "Barclay"
    ],
    "name:pol_x_preferred":[
        "Barclay"
    ],
    "name:por_x_preferred":[
        "Barclay"
    ],
    "name:rus_x_preferred":[
        "\u0411\u0430\u0440\u043a\u043b\u0430\u0439"
    ],
    "name:srp_x_preferred":[
        "\u0411\u0430\u0440\u043a\u043b\u0435\u0458"
    ],
    "name:swe_x_preferred":[
        "Barclay"
    ],
    "name:ukr_x_preferred":[
        "\u0411\u0430\u0440\u043a\u043b\u0430\u0439"
    ],
    "wof:name":"Barclay",
    "wof:placetype":"neighbourhood"
},
  "geometry": {"coordinates":[-76.52348940117481,37.07217235705604],"type":"Point"}
}