{
  "type": "Feature",
  "properties": {
    "gn:admin1_code":"MS",
    "gn:admin2_code":"47.0",
    "gn:asciiname":"Rolling Heights Mobile Estates",
    "gn:country_code":"US",
    "gn:dem":10,
    "gn:elevation":"9.0",
    "gn:feature_class":"P",
    "gn:feature_code":"PPL",
    "gn:name":"Rolling Heights Mobile Estates",
    "gn:population":0,
    "gn:timezone":"America/Chicago",
    "iso:country":"US",
    "wof:name":"Rolling Heights Mobile Estates",
    "wof:placetype":"campus"
},
  "geometry": {"coordinates":[-88.91278,30.44228],"type":"Point"}
}