{
  "type": "Feature",
  "properties": {
    "gn:admin1_code":"GA",
    "gn:admin2_code":"35.0",
    "gn:asciiname":"McMichael Crossroads",
    "gn:country_code":"US",
    "gn:dem":224,
    "gn:elevation":"224.0",
    "gn:feature_class":"P",
    "gn:feature_code":"PPL",
    "gn:name":"McMichael Crossroads",
    "gn:population":0,
    "gn:timezone":"America/New_York",
    "iso:country":"US",
    "wof:name":"McMichael Crossroads",
    "wof:placetype":"locality"
},
  "geometry": {"coordinates":[-83.96519000000001,33.33401],"type":"Point"}
}