{
  "type": "Feature",
  "properties": {
    "gn:admin1_code":"TN",
    "gn:admin2_code":"131.0",
    "gn:asciiname":"Shofner",
    "gn:country_code":"US",
    "gn:dem":95,
    "gn:elevation":"94.0",
    "gn:feature_class":"P",
    "gn:feature_code":"PPL",
    "gn:name":"Shofner",
    "gn:population":0,
    "gn:timezone":"America/Chicago",
    "iso:country":"US",
    "wof:name":"Shofner",
    "wof:placetype":"locality"
},
  "geometry": {"coordinates":[-88.98116999999998,36.40284000000001],"type":"Point"}
}