{
  "type": "Feature",
  "properties": {
    "gn:admin1_code":"TX",
    "gn:admin2_code":"61.0",
    "gn:asciiname":"Boca Chica and Medford Colonia",
    "gn:country_code":"US",
    "gn:dem":9,
    "gn:elevation":"6.0",
    "gn:feature_class":"P",
    "gn:feature_code":"PPL",
    "gn:name":"Boca Chica and Medford Colonia",
    "gn:population":0,
    "gn:timezone":"America/Chicago",
    "iso:country":"US",
    "name:eng_x_preferred":[
        "Boca Chica and Medford Colonia"
    ],
    "name:und_x_variant":[
        "Boca Chica & Medford Colonia"
    ],
    "wof:name":"Boca Chica and Medford Colonia",
    "wof:placetype":"locality"
},
  "geometry": {"coordinates":[-97.40137,25.91841],"type":"Point"}
}