{
  "type": "Feature",
  "properties": {
    "gn:admin1_code":"ND",
    "gn:admin2_code":"69.0",
    "gn:admin3_code":"23940.0",
    "gn:asciiname":"Silva",
    "gn:country_code":"US",
    "gn:dem":479,
    "gn:elevation":"482.0",
    "gn:feature_class":"P",
    "gn:feature_code":"PPL",
    "gn:name":"Silva",
    "gn:population":0,
    "gn:timezone":"America/Chicago",
    "iso:country":"US",
    "name:ces_x_preferred":[
        "Silva"
    ],
    "name:deu_x_preferred":[
        "Silva"
    ],
    "name:fin_x_preferred":[
        "Silva"
    ],
    "name:fra_x_preferred":[
        "Silva"
    ],
    "name:glg_x_preferred":[
        "Silva"
    ],
    "name:nld_x_preferred":[
        "Silva"
    ],
    "name:por_x_preferred":[
        "Silva"
    ],
    "name:spa_x_preferred":[
        "Silva"
    ],
    "name:ukr_x_preferred":[
        "\u0421\u0456\u043b\u0432\u0430"
    ],
    "name:zho_x_preferred":[
        "\u5e2d\u5c14\u74e6"
    ],
    "wof:name":"Silva",
    "wof:placetype":"locality"
},
  "geometry": {"coordinates":[-99.91847,48.16889000000001],"type":"Point"}
}