{
  "type": "Feature",
  "properties": {
    "iso:country":"US",
    "name:eng_x_preferred":[
        "Cumberland Hills"
    ],
    "wof:name":"Cumberland Hills",
    "wof:placetype":"neighbourhood",
    "zs:area_m":221682.639058,
    "zs:blockids":[
        471650212014006
    ],
    "zs:housing10":0,
    "zs:label":"Cumberland Hills",
    "zs:pop10":0
},
  "geometry": {"coordinates":[-86.571834,36.279794],"type":"Point"}
}