{
  "type": "Feature",
  "properties": {
    "gn:admin1_code":"NH",
    "gn:admin2_code":"15.0",
    "gn:admin3_code":"62900.0",
    "gn:asciiname":"Portsmouth Mobile Homes",
    "gn:country_code":"US",
    "gn:dem":15,
    "gn:elevation":"12.0",
    "gn:feature_class":"P",
    "gn:feature_code":"PPL",
    "gn:name":"Portsmouth Mobile Homes",
    "gn:population":0,
    "gn:timezone":"America/New_York",
    "iso:country":"US",
    "wof:name":"Portsmouth Mobile Homes",
    "wof:placetype":"campus"
},
  "geometry": {"coordinates":[-70.79478,43.02064],"type":"Point"}
}