{
  "type": "Feature",
  "properties": {
    "gn:admin1_code":"WA",
    "gn:admin2_code":"31.0",
    "gn:asciiname":"Coyle",
    "gn:country_code":"US",
    "gn:dem":55,
    "gn:elevation":"43.0",
    "gn:feature_class":"P",
    "gn:feature_code":"PPL",
    "gn:name":"Coyle",
    "gn:population":0,
    "gn:timezone":"America/Los_Angeles",
    "iso:country":"US",
    "name:eng_x_preferred":[
        "Coyle"
    ],
    "name:und_x_variant":[
        "Fisherman's Bay"
    ],
    "wof:name":"Coyle",
    "wof:placetype":"locality"
},
  "geometry": {"coordinates":[-122.80544,47.69787],"type":"Point"}
}