{
  "type": "Feature",
  "properties": {
    "iso:country":"US",
    "name:eng_x_preferred":[
        "Masonic Heights"
    ],
    "wof:name":"Masonic Heights",
    "wof:placetype":"neighbourhood",
    "wof:population":1326,
    "zs:area_m":1276964.332614,
    "zs:blockids":[
        260992503003015,
        260992503003014,
        260992503003002,
        260992418001072,
        260992503003006,
        260992503003011,
        260992503003008,
        260992503003001,
        260992503001002,
        260992503003004,
        260992503003005,
        260992503003003,
        260992418001073,
        260992503003012,
        260992503003000,
        260992503001006,
        260992503003010,
        260992418001074,
        260992503003013,
        260992503003019,
        260992503003009,
        260992503003007,
        260992503002002
    ],
    "zs:housing10":858,
    "zs:label":"Masonic Heights",
    "zs:pop10":1326
},
  "geometry": {"coordinates":[-82.89564300000001,42.535774],"type":"Point"}
}