{
  "type": "Feature",
  "properties": {
    "gn:admin1_code":"AR",
    "gn:admin2_code":"47.0",
    "gn:admin3_code":"90111.0",
    "gn:asciiname":"Meg",
    "gn:country_code":"US",
    "gn:dem":147,
    "gn:elevation":"146.0",
    "gn:feature_class":"P",
    "gn:feature_code":"PPL",
    "gn:name":"Meg",
    "gn:population":0,
    "gn:timezone":"America/Chicago",
    "iso:country":"US",
    "name:ita_x_preferred":[
        "Meg"
    ],
    "wof:name":"Meg",
    "wof:placetype":"locality"
},
  "geometry": {"coordinates":[-93.88825,35.40425],"type":"Point"}
}