{
  "type": "Feature",
  "properties": {
    "iso:country":"US",
    "name:eng_x_preferred":[
        "Bel Mira at Califia"
    ],
    "wof:name":"Bel Mira at Califia",
    "wof:placetype":"neighbourhood",
    "zs:area_m":838857.249122,
    "zs:blockids":[
        60590320572002,
        60590320572003
    ],
    "zs:housing10":0,
    "zs:label":"Bel Mira at Califia",
    "zs:pop10":0
},
  "geometry": {"coordinates":[-117.63553899999999,33.579316],"type":"Point"}
}