{
  "type": "Feature",
  "properties": {
    "gn:admin1_code":"MI",
    "gn:admin2_code":"107.0",
    "gn:admin3_code":"38540.0",
    "gn:asciiname":"Sylvester",
    "gn:country_code":"US",
    "gn:dem":297,
    "gn:elevation":"299.0",
    "gn:feature_class":"P",
    "gn:feature_code":"PPL",
    "gn:name":"Sylvester",
    "gn:population":0,
    "gn:timezone":"America/Detroit",
    "iso:country":"US",
    "name:ell_x_preferred":[
        "\u03a3\u03b9\u03bb\u03b2\u03ad\u03c3\u03c4\u03c1\u03bf\u03c2"
    ],
    "name:fin_x_preferred":[
        "Sylvester"
    ],
    "name:jpn_x_preferred":[
        "\u30b7\u30eb\u30f4\u30a7\u30b9\u30bf\u30fc"
    ],
    "name:rus_x_preferred":[
        "\u0421\u0438\u043b\u044c\u0432\u0435\u0441\u0442\u0440"
    ],
    "name:srp_x_preferred":[
        "\u0421\u0438\u043b\u0432\u0435\u0441\u0442\u0435\u0440"
    ],
    "name:swe_x_preferred":[
        "Sylvester"
    ],
    "name:ukr_x_preferred":[
        "\u0421\u0438\u043b\u044c\u0432\u0435\u0441\u0442\u0440"
    ],
    "wof:name":"Sylvester",
    "wof:placetype":"locality"
},
  "geometry": {"coordinates":[-85.25448,43.53975],"type":"Point"}
}