{
  "type": "Feature",
  "properties": {
    "gn:admin1_code":"AL",
    "gn:admin2_code":"13.0",
    "gn:asciiname":"Ridgeville",
    "gn:country_code":"US",
    "gn:dem":146,
    "gn:elevation":"142.0",
    "gn:feature_class":"P",
    "gn:feature_code":"PPL",
    "gn:name":"Ridgeville",
    "gn:population":0,
    "gn:timezone":"America/Chicago",
    "iso:country":"US",
    "name:ceb_x_preferred":[
        "Ridgeville"
    ],
    "name:deu_x_preferred":[
        "Ridgeville"
    ],
    "name:eng_x_preferred":[
        "Ridgeville"
    ],
    "name:fra_x_preferred":[
        "Ridgeville"
    ],
    "name:ind_x_preferred":[
        "Ridgeville"
    ],
    "name:ita_x_preferred":[
        "Ridgeville"
    ],
    "name:nld_x_preferred":[
        "Ridgeville"
    ],
    "name:pol_x_preferred":[
        "Ridgeville"
    ],
    "name:srp_x_preferred":[
        "\u0420\u0438\u045f\u0432\u0438\u043b"
    ],
    "name:ukr_x_preferred":[
        "\u0420\u0438\u0434\u0436\u0432\u0456\u043b\u043b"
    ],
    "name:und_x_variant":[
        "The Ridge",
        "Ernests Store"
    ],
    "name:vol_x_preferred":[
        "Ridgeville"
    ],
    "wof:name":"Ridgeville",
    "wof:placetype":"locality"
},
  "geometry": {"coordinates":[-86.84026,31.92515],"type":"Point"}
}