{
  "type": "Feature",
  "properties": {
    "gn:admin1_code":"VA",
    "gn:admin2_code":"25",
    "gn:asciiname":"Edmunds Store",
    "gn:country_code":"US",
    "gn:dem":121,
    "gn:elevation":"121.0",
    "gn:feature_class":"P",
    "gn:feature_code":"PPL",
    "gn:name":"Edmunds Store",
    "gn:population":0,
    "gn:timezone":"America/New_York",
    "iso:country":"US",
    "name:eng_x_preferred":[
        "Edmunds Store"
    ],
    "name:und_x_variant":[
        "Edmund's Store"
    ],
    "wof:name":"Edmunds Store",
    "wof:placetype":"locality"
},
  "geometry": {"coordinates":[-77.94194,36.87654000000001],"type":"Point"}
}