{
  "type": "Feature",
  "properties": {
    "gn:admin1_code":"CO",
    "gn:admin2_code":"125.0",
    "gn:asciiname":"Robb",
    "gn:country_code":"US",
    "gn:dem":1136,
    "gn:elevation":"1135.0",
    "gn:feature_class":"P",
    "gn:feature_code":"PPL",
    "gn:name":"Robb",
    "gn:population":0,
    "gn:timezone":"America/Denver",
    "iso:country":"US",
    "wof:name":"Robb",
    "wof:placetype":"locality"
},
  "geometry": {"coordinates":[-102.37187,40.10249],"type":"Point"}
}