{
  "type": "Feature",
  "properties": {
    "gn:admin1_code":"FL",
    "gn:admin2_code":"71.0",
    "gn:asciiname":"Serendipity Mobile Home Park",
    "gn:country_code":"US",
    "gn:dem":6,
    "gn:elevation":"4.0",
    "gn:feature_class":"P",
    "gn:feature_code":"PPL",
    "gn:name":"Serendipity Mobile Home Park",
    "gn:population":0,
    "gn:timezone":"America/New_York",
    "iso:country":"US",
    "wof:name":"Serendipity Mobile Home Park",
    "wof:placetype":"campus"
},
  "geometry": {"coordinates":[-81.91081,26.693],"type":"Point"}
}