{
  "type": "Feature",
  "properties": {
    "gn:admin1_code":"MD",
    "gn:admin2_code":"33.0",
    "gn:asciiname":"New England Estates",
    "gn:country_code":"US",
    "gn:dem":70,
    "gn:elevation":"68.0",
    "gn:feature_class":"P",
    "gn:feature_code":"PPL",
    "gn:name":"New England Estates",
    "gn:population":0,
    "gn:timezone":"America/New_York",
    "iso:country":"US",
    "wof:name":"New England Estates",
    "wof:placetype":"locality"
},
  "geometry": {"coordinates":[-76.92636,38.73762],"type":"Point"}
}