{
  "type": "Feature",
  "properties": {
    "gn:admin1_code":"MD",
    "gn:admin2_code":"35.0",
    "gn:asciiname":"Earles Branch",
    "gn:country_code":"US",
    "gn:dem":20,
    "gn:elevation":"18.0",
    "gn:feature_class":"P",
    "gn:feature_code":"PPL",
    "gn:name":"Earles Branch",
    "gn:population":0,
    "gn:timezone":"America/New_York",
    "iso:country":"US",
    "wof:name":"Earles Branch",
    "wof:placetype":"locality"
},
  "geometry": {"coordinates":[-76.0955,39.06372],"type":"Point"}
}