{
  "type": "Feature",
  "properties": {
    "gn:elevation":295,
    "iso:country":"US",
    "name:eng_x_preferred":[
        "Oak Crest"
    ],
    "name:eng_x_variant":[
        "Oak Crst"
    ],
    "qs:gn_adm0_cc":"US",
    "qs:gn_fcode":"PPL",
    "qs:gn_local":4499612,
    "qs:gn_nam_loc":"Winston-Salem, Forsyth, North Carolina, US",
    "qs:gn_namadm1":"NC",
    "qs:gn_name":"Oak Crest",
    "qs:local_max":8632,
    "qs:local_sum":30180,
    "qs:localhoods":45,
    "qs:name":"Oak Crest",
    "qs:name_adm0":"United States",
    "qs:name_adm1":"North Carolina",
    "qs:name_adm2":"Forsyth",
    "qs:name_local":"Winston-Salem",
    "qs:photo_max":178,
    "qs:photo_sum":896,
    "qs:placetype":"Suburb",
    "qs:quad_count":48,
    "qs:woe_adm0":23424977,
    "qs:woe_adm1":2347592,
    "qs:woe_adm2":12589407,
    "qs:woe_funk":"Parented by a neighborhood",
    "qs:woe_lau":0,
    "qs:woe_local":2522292,
    "qs:woe_ver":"7.10.0",
    "wd:wordcount":157,
    "wof:name":"Oak Crest",
    "wof:placetype":"neighbourhood",
    "wof:population":1581,
    "zs:blockids":[
        370670027031011,
        370670027032008,
        370670013001002,
        370670027031007,
        370670013002001,
        370670013001000,
        370670027031012,
        370670027032011,
        370670013001001,
        370670027031018,
        370670013002005,
        370670027031010,
        370670013002003,
        370670027031017,
        370670027031008,
        370670027032020,
        370670013001003,
        370670027031016,
        370670027031015,
        370670013002002,
        370670027032007,
        370670014002015,
        370670027031009
    ],
    "zs:housing10":547,
    "zs:pop10":1581
},
  "geometry": {"coordinates":[-80.27904100000001,36.136768],"type":"Point"}
}