{
  "type": "Feature",
  "properties": {
    "iso:country":"US",
    "name:eng_x_preferred":[
        "South Monroe"
    ],
    "qs:gn_adm0_cc":"US",
    "qs:gn_local":4174715,
    "qs:local_max":3782,
    "qs:local_sum":15801,
    "qs:localhoods":39,
    "qs:name":"South Monroe",
    "qs:name_adm0":"United States",
    "qs:name_adm1":"Florida",
    "qs:name_adm2":"Leon",
    "qs:name_local":"Tallahassee",
    "qs:photo_max":22,
    "qs:photo_sum":53,
    "qs:placetype":"Suburb",
    "qs:quad_count":7,
    "qs:woe_adm0":23424977,
    "qs:woe_adm1":2347568,
    "qs:woe_adm2":12587839,
    "qs:woe_lau":0,
    "qs:woe_local":2503713,
    "qs:woe_ver":"7.10.0",
    "wof:lang":[
        "eng"
    ],
    "wof:name":"South Monroe",
    "wof:placetype":"neighbourhood",
    "wof:population":4314,
    "zs:blockids":[
        120730010021001,
        120730010011036,
        120730003021006,
        120730003011061,
        120730003022036,
        120730003022035,
        120730003022033,
        120730010021022,
        120730010012000,
        120730010012006,
        120730003011058,
        120730003021018,
        120730003022032,
        120730003021010,
        120730003021008,
        120730010012003,
        120730010012004,
        120730003011055,
        120730010011002,
        120730010021002,
        120730003011063,
        120730003011060,
        120730003021015,
        120730003022031,
        120730003022034,
        120730003021002,
        120730010021023,
        120730003021014,
        120730010021024,
        120730003011057,
        120730010012001,
        120730003021019,
        120730003022021,
        120730010021025,
        120730003021004,
        120730010011000,
        120730010011003,
        120730010011035,
        120730003031013,
        120730010011037,
        120730003011053,
        120730003021017,
        120730003022026,
        120730003022024,
        120730010012002,
        120730018023031,
        120730003022029,
        120730010011033,
        120730003021001,
        120730018023014,
        120730003011056,
        120730010011034,
        120730010011001,
        120730010021000,
        120730003021016,
        120730003011059,
        120730003011062,
        120730003022025,
        120730003022022,
        120730003022030
    ],
    "zs:housing10":1975,
    "zs:pop10":4314
},
  "geometry": {"coordinates":[-84.270993,30.415921],"type":"Point"}
}