{
  "type": "Feature",
  "properties": {
    "gn:admin1_code":"GA",
    "gn:admin2_code":"97.0",
    "gn:asciiname":"Aline Estates",
    "gn:country_code":"US",
    "gn:dem":310,
    "gn:elevation":"305.0",
    "gn:feature_class":"P",
    "gn:feature_code":"PPL",
    "gn:name":"Aline Estates",
    "gn:population":0,
    "gn:timezone":"America/New_York",
    "iso:country":"US",
    "wof:name":"Aline Estates",
    "wof:placetype":"locality"
},
  "geometry": {"coordinates":[-84.79855000000001,33.66261],"type":"Point"}
}