{
  "type": "Feature",
  "properties": {
    "gn:admin1_code":"FL",
    "gn:admin2_code":"57",
    "gn:asciiname":"Huntington Woods",
    "gn:country_code":"US",
    "gn:dem":39,
    "gn:elevation":"33.0",
    "gn:feature_class":"P",
    "gn:feature_code":"PPL",
    "gn:name":"Huntington Woods",
    "gn:population":0,
    "gn:timezone":"America/New_York",
    "iso:country":"US",
    "wof:name":"Huntington Woods",
    "wof:placetype":"locality"
},
  "geometry": {"coordinates":[-82.26260000000001,27.9055],"type":"Point"}
}