{
  "type": "Feature",
  "properties": {
    "gn:admin1_code":"VA",
    "gn:admin2_code":"69",
    "gn:asciiname":"Gordondale",
    "gn:country_code":"US",
    "gn:dem":207,
    "gn:elevation":"208.0",
    "gn:feature_class":"P",
    "gn:feature_code":"PPL",
    "gn:name":"Gordondale",
    "gn:population":0,
    "gn:timezone":"America/New_York",
    "iso:country":"US",
    "wof:name":"Gordondale",
    "wof:placetype":"locality"
},
  "geometry": {"coordinates":[-78.09999999999999,39.30316],"type":"Point"}
}