{
  "type": "Feature",
  "properties": {
    "gn:admin1_code":"ME",
    "gn:admin2_code":"15.0",
    "gn:admin3_code":"48645.0",
    "gn:asciiname":"Sheepscot",
    "gn:country_code":"US",
    "gn:dem":11,
    "gn:elevation":"10.0",
    "gn:feature_class":"P",
    "gn:feature_code":"PPL",
    "gn:name":"Sheepscot",
    "gn:population":0,
    "gn:timezone":"America/New_York",
    "iso:country":"US",
    "name:eng_x_preferred":[
        "Sheepscot"
    ],
    "name:und_x_variant":[
        "Shipscot",
        "Shepscooke",
        "Sheepscott",
        "Shippscutt"
    ],
    "wof:name":"Sheepscot",
    "wof:placetype":"locality"
},
  "geometry": {"coordinates":[-69.60616,44.04952],"type":"Point"}
}