{
  "type": "Feature",
  "properties": {
    "gn:admin1_code":"KS",
    "gn:admin2_code":"27.0",
    "gn:admin3_code":"13625.0",
    "gn:asciiname":"Country Gardens Mobile Home Park",
    "gn:country_code":"US",
    "gn:dem":368,
    "gn:elevation":"365.0",
    "gn:feature_class":"P",
    "gn:feature_code":"PPL",
    "gn:name":"Country Gardens Mobile Home Park",
    "gn:population":0,
    "gn:timezone":"America/Chicago",
    "iso:country":"US",
    "wof:name":"Country Gardens Mobile Home Park",
    "wof:placetype":"campus"
},
  "geometry": {"coordinates":[-97.11265,39.3715],"type":"Point"}
}