{
  "type": "Feature",
  "properties": {
    "iso:country":"US",
    "name:eng_x_preferred":[
        "Constitution Hills"
    ],
    "name:unk_x_variant":[
        "Constitution Hills"
    ],
    "qs:gn_adm0_cc":"US",
    "qs:gn_local":4853828,
    "qs:gn_nam_loc":"Des Moines, Polk, Iowa, US",
    "qs:gn_namadm1":"IA",
    "qs:local_max":12745,
    "qs:local_sum":45077,
    "qs:localhoods":63,
    "qs:name":"Constitution Hills",
    "qs:name_adm0":"United States",
    "qs:name_adm1":"Iowa",
    "qs:name_adm2":"Polk",
    "qs:name_local":"Des Moines",
    "qs:photo_max":101,
    "qs:photo_sum":273,
    "qs:placetype":"Suburb",
    "qs:quad_count":8,
    "qs:woe_adm0":23424977,
    "qs:woe_adm1":2347574,
    "qs:woe_adm2":12588348,
    "qs:woe_lau":0,
    "qs:woe_local":2391446,
    "qs:woe_ver":"7.10.0",
    "wof:lang":[
        "eng"
    ],
    "wof:name":"Constitution Hills",
    "wof:placetype":"neighbourhood",
    "wof:population":1226,
    "zs:blockids":[
        191530053002035,
        191530108032031,
        191530108042031,
        191530053002056,
        191530053002048,
        191530053002058,
        191530053002001,
        191530108042042,
        191530108032019,
        191530108032029,
        191530108042041,
        191530053002028,
        191530108032018,
        191530053002055,
        191530053002066,
        191530108042038,
        191530053002029,
        191530108032012,
        191530108032035,
        191530108032014,
        191530108032013,
        191530108032033,
        191530108042036,
        191530053002031,
        191530108042043,
        191530108042047,
        191530108042067,
        191530108042066,
        191530108032034,
        191530108032032,
        191530108042029,
        191530053002059,
        191530053002067,
        191530108042046,
        191530053002030,
        191530053002026,
        191530108032015,
        191530108032028,
        191530053002002,
        191530108042037,
        191530053002038,
        191530108032016,
        191530108042030,
        191530053002068,
        191530108042028,
        191530108042040,
        191530108042045,
        191530053002000,
        191530053002027,
        191530053002065,
        191530108042032,
        191530108042039,
        191530053002020,
        191530108042033,
        191530053002034,
        191530053002054,
        191530053002057,
        191530108042044,
        191530108032030,
        191530108022007
    ],
    "zs:housing10":465,
    "zs:pop10":1226
},
  "geometry": {"coordinates":[-93.524119,41.588112],"type":"Point"}
}