{
  "type": "Feature",
  "properties": {
    "gn:elevation":1409,
    "iso:country":"US",
    "name:eng_x_preferred":[
        "Lark Circle"
    ],
    "name:eng_x_variant":[
        "Lark Cir"
    ],
    "qs:gn_adm0_cc":"US",
    "qs:gn_fcode":"PPLX",
    "qs:gn_local":5779206,
    "qs:gn_nam_loc":"Ogden, Weber, Utah, US",
    "qs:gn_namadm1":"UT",
    "qs:gn_name":"Lark Circle",
    "qs:local_max":3320,
    "qs:local_sum":9934,
    "qs:localhoods":47,
    "qs:name":"Lark Circle",
    "qs:name_adm0":"United States",
    "qs:name_adm1":"Utah",
    "qs:name_adm2":"Weber",
    "qs:name_local":"Ogden",
    "qs:photo_max":145,
    "qs:photo_sum":226,
    "qs:placetype":"Suburb",
    "qs:quad_count":11,
    "qs:woe_adm0":23424977,
    "qs:woe_adm1":2347603,
    "qs:woe_adm2":12590289,
    "qs:woe_lau":0,
    "qs:woe_local":2464337,
    "qs:woe_ver":"7.10.0",
    "wof:name":"Lark Circle",
    "wof:placetype":"neighbourhood",
    "wof:population":273,
    "zs:blockids":[
        490572015004012,
        490572015003025,
        490572015003014,
        490572015003002,
        490572015004008,
        490572015004011,
        490572015003003,
        490572015003015,
        490572015003001,
        490572015003000,
        490572015003013
    ],
    "zs:housing10":112,
    "zs:pop10":273
},
  "geometry": {"coordinates":[-111.943864,41.192682],"type":"Point"}
}