{
  "type": "Feature",
  "properties": {
    "gn:admin1_code":"DE",
    "gn:admin2_code":"3.0",
    "gn:asciiname":"Christina Manor",
    "gn:country_code":"US",
    "gn:dem":52,
    "gn:elevation":"49.0",
    "gn:feature_class":"P",
    "gn:feature_code":"PPL",
    "gn:name":"Christina Manor",
    "gn:population":0,
    "gn:timezone":"America/New_York",
    "iso:country":"US",
    "wof:name":"Christina Manor",
    "wof:placetype":"locality"
},
  "geometry": {"coordinates":[-75.78716,39.67928],"type":"Point"}
}