{
  "type": "Feature",
  "properties": {
    "gn:admin1_code":"VA",
    "gn:admin2_code":"109",
    "gn:asciiname":"Oakland",
    "gn:country_code":"US",
    "gn:dem":141,
    "gn:elevation":"142.0",
    "gn:feature_class":"P",
    "gn:feature_code":"PPL",
    "gn:name":"Oakland",
    "gn:population":0,
    "gn:timezone":"America/New_York",
    "iso:country":"US",
    "wof:name":"Oakland",
    "wof:placetype":"locality"
},
  "geometry": {"coordinates":[-78.04555000000001,38.08847],"type":"Point"}
}