{
  "type": "Feature",
  "properties": {
    "gn:admin1_code":"GA",
    "gn:admin2_code":"113",
    "gn:asciiname":"Wynnmeade",
    "gn:country_code":"US",
    "gn:dem":266,
    "gn:elevation":"256.0",
    "gn:feature_class":"P",
    "gn:feature_code":"PPL",
    "gn:name":"Wynnmeade",
    "gn:population":0,
    "gn:timezone":"America/New_York",
    "iso:country":"US",
    "wof:name":"Wynnmeade",
    "wof:placetype":"locality"
},
  "geometry": {"coordinates":[-84.61243,33.40567],"type":"Point"}
}