{
  "type": "Feature",
  "properties": {
    "gn:admin1_code":"NH",
    "gn:admin2_code":"11.0",
    "gn:admin3_code":"50740.0",
    "gn:asciiname":"Klondike Corner",
    "gn:country_code":"US",
    "gn:dem":178,
    "gn:elevation":"172.0",
    "gn:feature_class":"P",
    "gn:feature_code":"PPL",
    "gn:name":"Klondike Corner",
    "gn:population":0,
    "gn:timezone":"America/New_York",
    "iso:country":"US",
    "wof:name":"Klondike Corner",
    "wof:placetype":"locality"
},
  "geometry": {"coordinates":[-71.62090000000001,42.95564],"type":"Point"}
}