{
  "type": "Feature",
  "properties": {
    "gn:admin1_code":"AR",
    "gn:admin2_code":"43.0",
    "gn:admin3_code":"90132.0",
    "gn:asciiname":"Baxter",
    "gn:country_code":"US",
    "gn:dem":43,
    "gn:elevation":"40.0",
    "gn:feature_class":"P",
    "gn:feature_code":"PPL",
    "gn:name":"Baxter",
    "gn:population":0,
    "gn:timezone":"America/Chicago",
    "iso:country":"US",
    "name:ceb_x_preferred":[
        "Baxter"
    ],
    "name:ces_x_preferred":[
        "Baxter"
    ],
    "name:deu_x_preferred":[
        "Baxter"
    ],
    "name:eng_x_preferred":[
        "Baxter"
    ],
    "name:fra_x_preferred":[
        "Baxter"
    ],
    "name:ido_x_preferred":[
        "Baxter"
    ],
    "name:ita_x_preferred":[
        "Baxter"
    ],
    "name:jpn_x_preferred":[
        "\u30d0\u30af\u30b9\u30bf\u30fc"
    ],
    "name:nds_x_preferred":[
        "Baxter"
    ],
    "name:nld_x_preferred":[
        "Baxter"
    ],
    "name:pol_x_preferred":[
        "Baxter"
    ],
    "name:por_x_preferred":[
        "Baxter"
    ],
    "name:spa_x_preferred":[
        "Baxter"
    ],
    "name:srp_x_preferred":[
        "\u0411\u0430\u043a\u0441\u0442\u0435\u0440"
    ],
    "name:swe_x_preferred":[
        "Baxter"
    ],
    "name:und_x_variant":[
        "Bartholomew"
    ],
    "name:vol_x_preferred":[
        "Baxter"
    ],
    "wof:name":"Baxter",
    "wof:placetype":"locality"
},
  "geometry": {"coordinates":[-91.49706999999999,33.52928],"type":"Point"}
}