{
  "type": "Feature",
  "properties": {
    "gn:country":"US",
    "gn:fcode":"PPL",
    "gn:population":0,
    "iso:country":"US",
    "name:eng_x_preferred":[
        "Port Clyde"
    ],
    "name:fra_x_preferred":[
        "Port Clyde"
    ],
    "name:ita_x_preferred":[
        "Port Clyde"
    ],
    "name:pol_x_preferred":[
        "Port Clyde"
    ],
    "name:rus_x_preferred":[
        "\u041f\u043e\u0440\u0442-\u041a\u043b\u0430\u0439\u0434"
    ],
    "name:und_x_variant":[
        "Herring Gut"
    ],
    "qs_pg:aaroncc":"US",
    "qs_pg:gn_country":"US",
    "qs_pg:gn_fcode":"PPL",
    "qs_pg:gn_pop":0,
    "qs_pg:name":"Port Clyde",
    "qs_pg:name_adm0":"United States",
    "qs_pg:name_adm1":"Maine",
    "qs_pg:photos":1106,
    "qs_pg:photos_1k":224,
    "qs_pg:photos_9k":5,
    "qs_pg:photos_9r":7,
    "qs_pg:photos_all":1106,
    "qs_pg:photos_sr":11,
    "qs_pg:pop_sr":5,
    "qs_pg:qs_pg_placetype":"locality",
    "qs_pg:qs_pg_placetype_gp":"Town",
    "qs_pg:woe_adm0":23424977,
    "woe:adm0_id":23424977,
    "woe:name_adm0":"United States",
    "woe:name_adm1":"Maine",
    "woe:placetype":"Town",
    "wof:name":"Port Clyde",
    "wof:placetype":"locality"
},
  "geometry": {"coordinates":[-69.25282,43.92731],"type":"Point"}
}