{
  "type": "Feature",
  "properties": {
    "gn:admin1_code":"MN",
    "gn:admin2_code":"119.0",
    "gn:admin3_code":"24254.0",
    "gn:asciiname":"Maple Bay",
    "gn:country_code":"US",
    "gn:dem":359,
    "gn:elevation":"359.0",
    "gn:feature_class":"P",
    "gn:feature_code":"PPL",
    "gn:name":"Maple Bay",
    "gn:population":0,
    "gn:timezone":"America/Chicago",
    "iso:country":"US",
    "name:fas_x_preferred":[
        "\u0645\u067e\u0644 \u0628\u06cc"
    ],
    "name:ita_x_preferred":[
        "Maple Bay"
    ],
    "wof:name":"Maple Bay",
    "wof:placetype":"locality"
},
  "geometry": {"coordinates":[-96.22505,47.6358],"type":"Point"}
}