{
  "type": "Feature",
  "properties": {
    "gn:admin1_code":"NC",
    "gn:admin2_code":"27",
    "gn:admin3_code":"91780.0",
    "gn:asciiname":"British Woods",
    "gn:country_code":"US",
    "gn:dem":345,
    "gn:elevation":"338.0",
    "gn:feature_class":"P",
    "gn:feature_code":"PPL",
    "gn:name":"British Woods",
    "gn:population":0,
    "gn:timezone":"America/New_York",
    "iso:country":"US",
    "wof:name":"British Woods",
    "wof:placetype":"locality"
},
  "geometry": {"coordinates":[-81.5376,35.89819],"type":"Point"}
}