{
  "type": "Feature",
  "properties": {
    "gn:admin1_code":"OH",
    "gn:admin2_code":"37.0",
    "gn:admin3_code":"32354.0",
    "gn:asciiname":"Olwine Mobile Home Park",
    "gn:country_code":"US",
    "gn:dem":314,
    "gn:elevation":"315.0",
    "gn:feature_class":"P",
    "gn:feature_code":"PPL",
    "gn:name":"Olwine Mobile Home Park",
    "gn:population":0,
    "gn:timezone":"America/New_York",
    "iso:country":"US",
    "wof:name":"Olwine Mobile Home Park",
    "wof:placetype":"campus"
},
  "geometry": {"coordinates":[-84.61111,40.09167],"type":"Point"}
}