{
  "type": "Feature",
  "properties": {
    "gn:admin1_code":"AZ",
    "gn:admin2_code":"7.0",
    "gn:asciiname":"Oxbow Estates Mobile Home Park",
    "gn:country_code":"US",
    "gn:dem":1423,
    "gn:elevation":"1426.0",
    "gn:feature_class":"P",
    "gn:feature_code":"PPL",
    "gn:name":"Oxbow Estates Mobile Home Park",
    "gn:population":0,
    "gn:timezone":"America/Phoenix",
    "iso:country":"US",
    "wof:name":"Oxbow Estates Mobile Home Park",
    "wof:placetype":"campus"
},
  "geometry": {"coordinates":[-111.25882,34.25713],"type":"Point"}
}