{
  "type": "Feature",
  "properties": {
    "iso:country":"US",
    "name:eng_x_preferred":[
        "Highview Knoll"
    ],
    "wof:name":"Highview Knoll",
    "wof:placetype":"neighbourhood",
    "wof:population":51,
    "zs:area_m":306637.550202,
    "zs:blockids":[
        191030103021024
    ],
    "zs:housing10":22,
    "zs:label":"Highview Knoll",
    "zs:pop10":51
},
  "geometry": {"coordinates":[-91.54779000000001,41.702052],"type":"Point"}
}