{
  "type": "Feature",
  "properties": {
    "gn:country":"US",
    "gn:fcode":"PPL",
    "gn:population":0,
    "iso:country":"US",
    "name:cat_x_preferred":[
        "Marlboro"
    ],
    "name:ceb_x_preferred":[
        "Marlboro"
    ],
    "name:deu_x_preferred":[
        "Marlboro"
    ],
    "name:eng_x_preferred":[
        "Marlboro"
    ],
    "name:fra_x_preferred":[
        "Marlboro"
    ],
    "name:fry_x_preferred":[
        "Marlboro"
    ],
    "name:ind_x_preferred":[
        "Marlboro"
    ],
    "name:ita_x_preferred":[
        "Marlboro"
    ],
    "name:mkd_x_preferred":[
        "\u041c\u0430\u0440\u043b\u0431\u043e\u0440\u043e"
    ],
    "name:nld_x_preferred":[
        "Marlboro"
    ],
    "name:pol_x_preferred":[
        "Marlboro"
    ],
    "name:por_x_preferred":[
        "Marlboro"
    ],
    "name:rus_x_preferred":[
        "\u041c\u0430\u043b\u044c\u0431\u043e\u0440\u043e"
    ],
    "name:swa_x_preferred":[
        "Marlboro"
    ],
    "name:swe_x_preferred":[
        "Marlboro"
    ],
    "name:und_x_variant":[
        "Marlboro Center"
    ],
    "name:vol_x_preferred":[
        "Marlboro"
    ],
    "qs_pg:aaroncc":"US",
    "qs_pg:gn_country":"US",
    "qs_pg:gn_fcode":"PPL",
    "qs_pg:gn_pop":0,
    "qs_pg:name":"Marlboro",
    "qs_pg:name_adm0":"United States",
    "qs_pg:name_adm1":"Vermont",
    "qs_pg:photos":408,
    "qs_pg:photos_1k":83,
    "qs_pg:photos_9k":2,
    "qs_pg:photos_9r":5,
    "qs_pg:photos_all":484,
    "qs_pg:photos_sr":6,
    "qs_pg:pop_sr":0,
    "qs_pg:qs_pg_placetype":"locality",
    "qs_pg:qs_pg_placetype_gp":"Town",
    "qs_pg:woe_adm0":23424977,
    "woe:adm0_id":23424977,
    "woe:name_adm0":"United States",
    "woe:name_adm1":"Vermont",
    "woe:placetype":"Town",
    "wof:coterminous":[
        404527091
    ],
    "wof:name":"Marlboro",
    "wof:placetype":"locality",
    "wof:statistical_gore":1
},
  "geometry": {"coordinates":[-72.72593000000001,42.85953],"type":"Point"}
}