{
  "type": "Feature",
  "properties": {
    "iso:country":"US",
    "name:deu_x_preferred":[
        "McAlpin"
    ],
    "name:eng_x_preferred":[
        "Mcalpin"
    ],
    "wd:wordcount":83,
    "wof:name":"Mcalpin",
    "wof:placetype":"neighbourhood",
    "wof:population":145,
    "zs:area_m":5429971.615091,
    "zs:blockids":[
        540330321021012,
        540330320002250,
        540330320002274,
        540330321021025,
        540330320002280,
        540330320002266,
        540330320002267,
        540330320002255,
        540330320002271,
        540330321021018,
        540330321021015,
        540330321021019,
        540330320002276,
        540330321021029,
        540330320002265,
        540330321021013,
        540330321021016,
        540330320002281,
        540330320002037,
        540330320002273,
        540330320002277,
        540330320002275,
        540330320002284,
        540330320002278,
        540330320002272,
        540330321021017,
        540330321021014,
        540330321021008,
        540330320002036,
        540330320002262
    ],
    "zs:housing10":84,
    "zs:label":"Mcalpin",
    "zs:pop10":145
},
  "geometry": {"coordinates":[-80.240314,39.324434],"type":"Point"}
}