{
  "type": "Feature",
  "properties": {
    "gn:admin1_code":"NM",
    "gn:admin2_code":"61.0",
    "gn:asciiname":"Los Trujillos",
    "gn:country_code":"US",
    "gn:dem":1464,
    "gn:elevation":"1464.0",
    "gn:feature_class":"P",
    "gn:feature_code":"PPL",
    "gn:name":"Los Trujillos",
    "gn:population":0,
    "gn:timezone":"America/Denver",
    "iso:country":"US",
    "wof:name":"Los Trujillos",
    "wof:placetype":"locality"
},
  "geometry": {"coordinates":[-106.76085999999999,34.64673],"type":"Point"}
}