{
  "type": "Feature",
  "properties": {
    "gn:admin1_code":"WI",
    "gn:admin2_code":"75.0",
    "gn:admin3_code":"64275.0",
    "gn:asciiname":"Miles",
    "gn:country_code":"US",
    "gn:dem":201,
    "gn:elevation":"204.0",
    "gn:feature_class":"P",
    "gn:feature_code":"PPL",
    "gn:name":"Miles",
    "gn:population":0,
    "gn:timezone":"America/Chicago",
    "iso:country":"US",
    "name:fas_x_preferred":[
        "\u0645\u0627\u06cc\u0644\u0632"
    ],
    "name:urd_x_preferred":[
        "\u0645\u0627\u0626\u0644\u0632"
    ],
    "wof:name":"Miles",
    "wof:placetype":"locality"
},
  "geometry": {"coordinates":[-87.729,45.2272],"type":"Point"}
}