{
  "type": "Feature",
  "properties": {
    "iso:country":"US",
    "name:eng_x_preferred":[
        "Adobe Row"
    ],
    "qs:gn_adm0_cc":"US",
    "qs:gn_local":5525577,
    "qs:local_max":2907,
    "qs:local_sum":11142,
    "qs:localhoods":33,
    "qs:name":"Adobe Row",
    "qs:name_adm0":"United States",
    "qs:name_adm1":"Texas",
    "qs:name_adm2":"Lubbock",
    "qs:name_local":"Lubbock",
    "qs:photo_max":290,
    "qs:photo_sum":494,
    "qs:placetype":"Suburb",
    "qs:quad_count":11,
    "qs:woe_adm0":23424977,
    "qs:woe_adm1":2347602,
    "qs:woe_adm2":12590158,
    "qs:woe_lau":0,
    "qs:woe_local":2442818,
    "qs:woe_ver":"7.10.0",
    "wof:name":"Adobe Row",
    "wof:placetype":"neighbourhood",
    "wof:population":3587,
    "zs:blockids":[
        483030015012012,
        483030015012009,
        483030015012014,
        483030015012008,
        483030005004015,
        483030005004007,
        483030016021011,
        483030015012018,
        483030005001003,
        483030015012006,
        483030005004002,
        483030005001005,
        483030005002047,
        483030015012005,
        483030016021000,
        483030015012003,
        483030015011004,
        483030015011016,
        483030016021010,
        483030005004016,
        483030015012011,
        483030015012010,
        483030015012007,
        483030015011005,
        483030015011006,
        483030016021008,
        483030005004001,
        483030005002044,
        483030005004005,
        483030015012002,
        483030015012001,
        483030015012013,
        483030016021009,
        483030005004013,
        483030005004014,
        483030015012004,
        483030005004006,
        483030015012000
    ],
    "zs:housing10":379,
    "zs:pop10":3587
},
  "geometry": {"coordinates":[-101.883922,33.580158],"type":"Point"}
}