{
  "type": "Feature",
  "properties": {
    "gn:admin1_code":"MI",
    "gn:admin2_code":"69",
    "gn:admin3_code":"61340.0",
    "gn:asciiname":"Oscoda Mobile Home Park",
    "gn:country_code":"US",
    "gn:dem":182,
    "gn:elevation":"183.0",
    "gn:feature_class":"P",
    "gn:feature_code":"PPL",
    "gn:name":"Oscoda Mobile Home Park",
    "gn:population":0,
    "gn:timezone":"America/Detroit",
    "iso:country":"US",
    "wof:name":"Oscoda Mobile Home Park",
    "wof:placetype":"campus"
},
  "geometry": {"coordinates":[-83.33055999999998,44.46667],"type":"Point"}
}