{
  "type": "Feature",
  "properties": {
    "gn:country":"US",
    "gn:fcode":"PPL",
    "gn:population":0,
    "iso:country":"US",
    "name:azb_x_preferred":[
        "\u0628\u0631\u0627\u0646\u062f\u06cc\u0648\u06cc\u0646"
    ],
    "name:eng_x_preferred":[
        "Brandywine"
    ],
    "name:fas_x_preferred":[
        "\u0628\u0631\u0627\u0646\u062f\u06cc\u200c\u0648\u0627\u06cc\u0646"
    ],
    "name:fra_x_preferred":[
        "Brandywine"
    ],
    "name:und_x_variant":[
        "Brandywine Cross Roads"
    ],
    "name:zho_x_preferred":[
        "\u5e03\u862d\u8fea\u842c"
    ],
    "qs_pg:aaroncc":"US",
    "qs_pg:gn_country":"US",
    "qs_pg:gn_fcode":"PPL",
    "qs_pg:gn_pop":0,
    "qs_pg:name":"Brandywine",
    "qs_pg:name_adm0":"United States",
    "qs_pg:name_adm1":"Delaware",
    "qs_pg:photos":33,
    "qs_pg:photos_1k":7,
    "qs_pg:photos_9k":1,
    "qs_pg:photos_9r":2,
    "qs_pg:photos_all":33,
    "qs_pg:photos_sr":2,
    "qs_pg:pop_sr":0,
    "qs_pg:qs_pg_placetype":"locality",
    "qs_pg:qs_pg_placetype_gp":"Town",
    "qs_pg:woe_adm0":23424977,
    "woe:adm0_id":23424977,
    "woe:name_adm0":"United States",
    "woe:name_adm1":"Delaware",
    "woe:placetype":"Town",
    "wof:name":"Brandywine",
    "wof:placetype":"locality"
},
  "geometry": {"coordinates":[-75.53437,39.82956],"type":"Point"}
}