{
  "type": "Feature",
  "properties": {
    "gn:admin1_code":"VA",
    "gn:admin2_code":"85.0",
    "gn:asciiname":"Alexanders Corner",
    "gn:country_code":"US",
    "gn:dem":51,
    "gn:elevation":"52.0",
    "gn:feature_class":"P",
    "gn:feature_code":"PPL",
    "gn:name":"Alexanders Corner",
    "gn:population":0,
    "gn:timezone":"America/New_York",
    "iso:country":"US",
    "wof:name":"Alexanders Corner",
    "wof:placetype":"locality"
},
  "geometry": {"coordinates":[-77.22303000000002,37.58681],"type":"Point"}
}