{
  "type": "Feature",
  "properties": {
    "iso:country":"US",
    "name:eng_x_preferred":[
        "Bear Ranch"
    ],
    "qs:gn_adm0_cc":"US",
    "qs:gn_local":5420241,
    "qs:gn_nam_loc":"Durango, La Plata, Colorado, US",
    "qs:gn_namadm1":"CO",
    "qs:local_max":1579,
    "qs:local_sum":2274,
    "qs:localhoods":12,
    "qs:name":"Bear Ranch",
    "qs:name_adm0":"United States",
    "qs:name_adm1":"Colorado",
    "qs:name_adm2":"La Plata",
    "qs:name_local":"Durango",
    "qs:photo_max":14,
    "qs:photo_sum":39,
    "qs:placetype":"Suburb",
    "qs:quad_count":11,
    "qs:woe_adm0":23424977,
    "qs:woe_adm1":2347564,
    "qs:woe_adm2":12587760,
    "qs:woe_lau":0,
    "qs:woe_local":2394672,
    "qs:woe_ver":"7.10.0",
    "wd:wordcount":1315,
    "wof:name":"Bear Ranch",
    "wof:placetype":"neighbourhood",
    "wof:population":32,
    "zs:blockids":[
        80679707042094,
        80679707042087,
        80679707042113
    ],
    "zs:housing10":72,
    "zs:pop10":32
},
  "geometry": {"coordinates":[-107.812006,37.531007],"type":"Point"}
}