{
  "type": "Feature",
  "properties": {
    "gn:admin1_code":"TX",
    "gn:admin2_code":"5.0",
    "gn:asciiname":"Prairie Grove",
    "gn:country_code":"US",
    "gn:dem":83,
    "gn:elevation":"69.0",
    "gn:feature_class":"P",
    "gn:feature_code":"PPL",
    "gn:name":"Prairie Grove",
    "gn:population":0,
    "gn:timezone":"America/Chicago",
    "iso:country":"US",
    "name:ceb_x_preferred":[
        "Prairie Grove"
    ],
    "name:deu_x_preferred":[
        "Prairie Grove"
    ],
    "name:ita_x_preferred":[
        "Prairie Grove"
    ],
    "name:nld_x_preferred":[
        "Prairie Grove"
    ],
    "name:pol_x_preferred":[
        "Prairie Grove"
    ],
    "name:srp_x_preferred":[
        "\u041f\u0440\u0435\u0440\u0438 \u0413\u0440\u043e\u0443\u0432"
    ],
    "name:vol_x_preferred":[
        "Prairie Grove"
    ],
    "wof:name":"Prairie Grove",
    "wof:placetype":"locality"
},
  "geometry": {"coordinates":[-94.71937,31.16936],"type":"Point"}
}