{
  "type": "Feature",
  "properties": {
    "gn:admin1_code":"AL",
    "gn:admin2_code":"1",
    "gn:asciiname":"Old Kingston",
    "gn:country_code":"US",
    "gn:dem":129,
    "gn:elevation":"124.0",
    "gn:feature_class":"P",
    "gn:feature_code":"PPL",
    "gn:name":"Old Kingston",
    "gn:population":0,
    "gn:timezone":"America/Chicago",
    "iso:country":"US",
    "name:eng_x_preferred":[
        "Old Kingston"
    ],
    "name:und_x_variant":[
        "Kingston"
    ],
    "wof:name":"Old Kingston",
    "wof:placetype":"locality"
},
  "geometry": {"coordinates":[-86.60081,32.57374],"type":"Point"}
}