{
  "type": "Feature",
  "properties": {
    "gn:admin1_code":"MN",
    "gn:admin2_code":"61.0",
    "gn:admin3_code":"46582.0",
    "gn:asciiname":"Orth",
    "gn:country_code":"US",
    "gn:dem":444,
    "gn:elevation":"442.0",
    "gn:feature_class":"P",
    "gn:feature_code":"PPL",
    "gn:name":"Orth",
    "gn:population":0,
    "gn:timezone":"America/Chicago",
    "iso:country":"US",
    "wof:name":"Orth",
    "wof:placetype":"locality"
},
  "geometry": {"coordinates":[-94.31523,47.83912],"type":"Point"}
}