{
  "type": "Feature",
  "properties": {
    "iso:country":"US",
    "name:eng_x_preferred":[
        "Hidden Pines at Countryside"
    ],
    "qs:gn_adm0_cc":"US",
    "qs:gn_local":4151316,
    "qs:gn_nam_loc":"Clearwater, Pinellas, Florida, US",
    "qs:gn_namadm1":"FL",
    "qs:local_max":3877,
    "qs:local_sum":12898,
    "qs:localhoods":27,
    "qs:name":"Hidden Pines at Countryside",
    "qs:name_adm0":"United States",
    "qs:name_adm1":"Florida",
    "qs:name_adm2":"Pinellas",
    "qs:name_local":"Clearwater",
    "qs:photo_max":24,
    "qs:photo_sum":59,
    "qs:placetype":"Suburb",
    "qs:quad_count":6,
    "qs:woe_adm0":23424977,
    "qs:woe_adm1":2347568,
    "qs:woe_adm2":12587854,
    "qs:woe_lau":0,
    "qs:woe_local":2381303,
    "qs:woe_ver":"7.10.0",
    "wof:lang":[
        "eng"
    ],
    "wof:name":"Hidden Pines at Countryside",
    "wof:placetype":"neighbourhood",
    "wof:population":2523,
    "zs:blockids":[
        121030268201015,
        121030268201017,
        121030268201006,
        121030268201011,
        121030269101001,
        121030269042024,
        121030268121004,
        121030269042014,
        121030269043050,
        121030269041020,
        121030268201013,
        121030269042032,
        121030268201025,
        121030269041015,
        121030269042022,
        121030269042017,
        121030269042003,
        121030269101000,
        121030268201012,
        121030269042012,
        121030269041019,
        121030268201020,
        121030268201019,
        121030269042013,
        121030269042016,
        121030269042027,
        121030269042000,
        121030269043049,
        121030269042005,
        121030268201018,
        121030269042015,
        121030268201021,
        121030269042019,
        121030269042025,
        121030269041024,
        121030269042002,
        121030269042018,
        121030269101004,
        121030269042007,
        121030269042026,
        121030268201002,
        121030269043048,
        121030269042006,
        121030269042008,
        121030269041021,
        121030269042011,
        121030269042001,
        121030268201022,
        121030268201001,
        121030269041023,
        121030269101002,
        121030269043051,
        121030268201000,
        121030269042028,
        121030269042020,
        121030269042009,
        121030269041022,
        121030269042033,
        121030268201016,
        121030269042021,
        121030269042010,
        121030268201008,
        121030269042023,
        121030269042004,
        121030268201004
    ],
    "zs:housing10":1719,
    "zs:pop10":2523
},
  "geometry": {"coordinates":[-82.73794599999999,28.024955],"type":"Point"}
}