{
  "type": "Feature",
  "properties": {
    "gn:admin1_code":"WA",
    "gn:admin2_code":"59.0",
    "gn:asciiname":"Ericson View Tracts",
    "gn:country_code":"US",
    "gn:dem":396,
    "gn:elevation":"387.0",
    "gn:feature_class":"P",
    "gn:feature_code":"PPL",
    "gn:name":"Ericson View Tracts",
    "gn:population":0,
    "gn:timezone":"America/Los_Angeles",
    "iso:country":"US",
    "wof:name":"Ericson View Tracts",
    "wof:placetype":"locality"
},
  "geometry": {"coordinates":[-121.60007,45.72651],"type":"Point"}
}