{
  "type": "Feature",
  "properties": {
    "gn:admin1_code":"PA",
    "gn:admin2_code":"5.0",
    "gn:admin3_code":"46976.0",
    "gn:asciiname":"Fordview",
    "gn:country_code":"US",
    "gn:dem":287,
    "gn:elevation":"290.0",
    "gn:feature_class":"P",
    "gn:feature_code":"PPL",
    "gn:name":"Fordview",
    "gn:population":0,
    "gn:timezone":"America/New_York",
    "iso:country":"US",
    "name:eng_x_preferred":[
        "Fordview"
    ],
    "name:und_x_variant":[
        "Ford View",
        "Lenape Heights"
    ],
    "wof:name":"Fordview",
    "wof:placetype":"locality"
},
  "geometry": {"coordinates":[-79.52282,40.77034],"type":"Point"}
}