{
  "type": "Feature",
  "properties": {
    "gn:admin1_code":"FL",
    "gn:admin2_code":"57",
    "gn:asciiname":"Sugar Cane Acres",
    "gn:country_code":"US",
    "gn:dem":31,
    "gn:elevation":"22.0",
    "gn:feature_class":"P",
    "gn:feature_code":"PPL",
    "gn:name":"Sugar Cane Acres",
    "gn:population":0,
    "gn:timezone":"America/New_York",
    "iso:country":"US",
    "wof:name":"Sugar Cane Acres",
    "wof:placetype":"locality"
},
  "geometry": {"coordinates":[-82.1837,27.9569],"type":"Point"}
}