{
  "type": "Feature",
  "properties": {
    "gn:country":"US",
    "gn:fcode":"PPL",
    "gn:population":0,
    "iso:country":"US",
    "name:bre_x_preferred":[
        "Angelo"
    ],
    "name:deu_x_preferred":[
        "Angelo"
    ],
    "name:eng_x_preferred":[
        "Angelo"
    ],
    "name:fas_x_preferred":[
        "\u0622\u0646\u062c\u0644\u0648"
    ],
    "name:ita_x_preferred":[
        "Angelo"
    ],
    "name:nld_x_preferred":[
        "Angelo"
    ],
    "name:nor_x_preferred":[
        "Angelo"
    ],
    "name:pol_x_preferred":[
        "Anio\u0142"
    ],
    "qs_pg:aaroncc":"US",
    "qs_pg:gn_country":"US",
    "qs_pg:gn_fcode":"PPL",
    "qs_pg:gn_pop":0,
    "qs_pg:name":"Angelo",
    "qs_pg:name_adm0":"United States",
    "qs_pg:name_adm1":"Wisconsin",
    "qs_pg:photos":332,
    "qs_pg:photos_1k":67,
    "qs_pg:photos_9k":1,
    "qs_pg:photos_9r":5,
    "qs_pg:photos_all":332,
    "qs_pg:photos_sr":5,
    "qs_pg:pop_sr":0,
    "qs_pg:qs_pg_placetype":"locality",
    "qs_pg:qs_pg_placetype_gp":"Town",
    "qs_pg:woe_adm0":23424977,
    "woe:adm0_id":23424977,
    "woe:name_adm0":"United States",
    "woe:name_adm1":"Wisconsin",
    "woe:placetype":"Town",
    "wof:coterminous":[
        404494283
    ],
    "wof:name":"Angelo",
    "wof:placetype":"locality",
    "wof:statistical_gore":1
},
  "geometry": {"coordinates":[-90.77791000000001,43.9708],"type":"Point"}
}