{
  "type": "Feature",
  "properties": {
    "gn:admin1_code":"NC",
    "gn:admin2_code":"155",
    "gn:admin3_code":"91940.0",
    "gn:asciiname":"Lone Oak Mobile Home Park",
    "gn:country_code":"US",
    "gn:dem":38,
    "gn:elevation":"44.0",
    "gn:feature_class":"P",
    "gn:feature_code":"PPL",
    "gn:name":"Lone Oak Mobile Home Park",
    "gn:population":0,
    "gn:timezone":"America/New_York",
    "iso:country":"US",
    "wof:name":"Lone Oak Mobile Home Park",
    "wof:placetype":"campus"
},
  "geometry": {"coordinates":[-78.97539999999999,34.6257],"type":"Point"}
}