{
  "type": "Feature",
  "properties": {
    "gn:admin1_code":"NC",
    "gn:admin2_code":"67",
    "gn:admin3_code":"94068.0",
    "gn:asciiname":"Glen High Estates",
    "gn:country_code":"US",
    "gn:dem":270,
    "gn:elevation":"264.0",
    "gn:feature_class":"P",
    "gn:feature_code":"PPL",
    "gn:name":"Glen High Estates",
    "gn:population":0,
    "gn:timezone":"America/New_York",
    "iso:country":"US",
    "wof:name":"Glen High Estates",
    "wof:placetype":"locality"
},
  "geometry": {"coordinates":[-80.14421,36.08208],"type":"Point"}
}