{
  "type": "Feature",
  "properties": {
    "gn:admin1_code":"DE",
    "gn:admin2_code":"1.0",
    "gn:asciiname":"Reeves Crossing",
    "gn:country_code":"US",
    "gn:dem":14,
    "gn:elevation":"12.0",
    "gn:feature_class":"P",
    "gn:feature_code":"PPL",
    "gn:name":"Reeves Crossing",
    "gn:population":0,
    "gn:timezone":"America/New_York",
    "iso:country":"US",
    "wof:name":"Reeves Crossing",
    "wof:placetype":"locality"
},
  "geometry": {"coordinates":[-75.57798000000003,38.98345],"type":"Point"}
}