{
  "type": "Feature",
  "properties": {
    "gn:admin1_code":"FL",
    "gn:admin2_code":"57",
    "gn:asciiname":"Walden Lake Fairway Estates",
    "gn:country_code":"US",
    "gn:dem":42,
    "gn:elevation":"35.0",
    "gn:feature_class":"P",
    "gn:feature_code":"PPL",
    "gn:name":"Walden Lake Fairway Estates",
    "gn:population":0,
    "gn:timezone":"America/New_York",
    "iso:country":"US",
    "wof:name":"Walden Lake Fairway Estates",
    "wof:placetype":"locality"
},
  "geometry": {"coordinates":[-82.1435,27.9941],"type":"Point"}
}