{
  "type": "Feature",
  "properties": {
    "iso:country":"US",
    "name:deu_x_preferred":[
        "Fisherville"
    ],
    "name:eng_x_preferred":[
        "Fisherville"
    ],
    "qs:gn_adm0_cc":"US",
    "qs:gn_local":4255673,
    "qs:gn_nam_loc":"Chandler, Warrick, Indiana, US",
    "qs:gn_namadm1":"IN",
    "qs:local_max":54,
    "qs:local_sum":54,
    "qs:localhoods":1,
    "qs:name":"Fisherville",
    "qs:name_adm0":"United States",
    "qs:name_adm1":"Indiana",
    "qs:name_adm2":"Warrick",
    "qs:name_local":"Chandler",
    "qs:photo_max":32,
    "qs:photo_sum":54,
    "qs:placetype":"Suburb",
    "qs:quad_count":13,
    "qs:woe_adm0":23424977,
    "qs:woe_adm1":2347573,
    "qs:woe_adm2":12588266,
    "qs:woe_lau":0,
    "qs:woe_local":2378003,
    "qs:woe_ver":"7.10.0",
    "wd:wordcount":43,
    "wof:lang":[
        "eng"
    ],
    "wof:name":"Fisherville",
    "wof:placetype":"neighbourhood",
    "wof:population":661,
    "zs:blockids":[
        181730303002029,
        181730305001017,
        181730304002006,
        181730304003023,
        181730304003009,
        181730304003019,
        181730303002080,
        181730303002030,
        181730304002013,
        181730303002028,
        181730303002035,
        181730304003006,
        181730305001014,
        181730303002054,
        181730304002021
    ],
    "zs:housing10":254,
    "zs:pop10":661
},
  "geometry": {"coordinates":[-87.362517,38.056862],"type":"Point"}
}