{
  "type": "Feature",
  "properties": {
    "gn:admin1_code":"SC",
    "gn:admin2_code":"79.0",
    "gn:asciiname":"Elm Abode",
    "gn:country_code":"US",
    "gn:dem":92,
    "gn:elevation":"83.0",
    "gn:feature_class":"P",
    "gn:feature_code":"PPL",
    "gn:name":"Elm Abode",
    "gn:population":0,
    "gn:timezone":"America/New_York",
    "iso:country":"US",
    "wof:name":"Elm Abode",
    "wof:placetype":"locality"
},
  "geometry": {"coordinates":[-81.08176,34.03182],"type":"Point"}
}