{
  "type": "Feature",
  "properties": {
    "gn:elevation":76,
    "iso:country":"US",
    "name:ceb_x_preferred":[
        "Grove Hill"
    ],
    "name:deu_x_preferred":[
        "Grove Hill"
    ],
    "name:eng_x_preferred":[
        "Grove Hill"
    ],
    "name:eng_x_variant":[
        "Grove Hl"
    ],
    "name:swe_x_preferred":[
        "Grove Hill"
    ],
    "qs:gn_adm0_cc":"US",
    "qs:gn_fcode":"PPLX",
    "qs:gn_local":4076784,
    "qs:gn_namadm1":"AL",
    "qs:gn_name":"Grove Hill",
    "qs:local_max":2993,
    "qs:local_sum":14433,
    "qs:localhoods":45,
    "qs:name":"Grove Hill",
    "qs:name_adm0":"United States",
    "qs:name_adm1":"Alabama",
    "qs:name_adm2":"Montgomery",
    "qs:name_local":"Montgomery",
    "qs:photo_max":51,
    "qs:photo_sum":149,
    "qs:placetype":"Suburb",
    "qs:quad_count":14,
    "qs:woe_adm0":23424977,
    "qs:woe_adm1":2347559,
    "qs:woe_adm2":12587537,
    "qs:woe_funk":"Parented by a neighborhood",
    "qs:woe_lau":0,
    "qs:woe_local":2453369,
    "qs:woe_ver":"7.10.0",
    "wd:wordcount":96,
    "wof:lang":[
        "eng"
    ],
    "wof:name":"Grove Hill",
    "wof:placetype":"neighbourhood",
    "wof:population":1890,
    "zs:blockids":[
        11010015001002,
        11010033011009,
        11010016002020,
        11010016002022,
        11010016002037,
        11010016002023,
        11010033011013,
        11010017003005,
        11010017003011,
        11010015001000,
        11010016002045,
        11010017003007,
        11010033011011,
        11010033011012,
        11010017003012,
        11010017004036,
        11010016002027,
        11010033011000,
        11010033012002,
        11010033011014,
        11010016002000,
        11010033011019,
        11010033011008,
        11010017003004,
        11010033011010,
        11010017004050,
        11010016002041,
        11010016002039,
        11010016002026,
        11010015001005,
        11010016002046,
        11010016001010,
        11010033011015,
        11010033012000,
        11010016002025,
        11010016001009,
        11010016002048,
        11010017003024,
        11010015001012,
        11010017003025,
        11010017003009,
        11010016002040,
        11010033011001,
        11010033011007,
        11010016002038,
        11010016002024,
        11010015001006,
        11010017003008,
        11010033012001,
        11010016002021,
        11010033011005,
        11010016002049,
        11010033011006,
        11010033012003,
        11010033011018,
        11010015001010
    ],
    "zs:housing10":869,
    "zs:pop10":1890
},
  "geometry": {"coordinates":[-86.270072,32.366787],"type":"Point"}
}