{
  "type": "Feature",
  "properties": {
    "gn:admin1_code":"WA",
    "gn:admin2_code":"23.0",
    "gn:asciiname":"Ping",
    "gn:country_code":"US",
    "gn:dem":425,
    "gn:elevation":"427.0",
    "gn:feature_class":"P",
    "gn:feature_code":"PPL",
    "gn:name":"Ping",
    "gn:population":0,
    "gn:timezone":"America/Los_Angeles",
    "iso:country":"US",
    "name:ces_x_preferred":[
        "Ping"
    ],
    "name:dan_x_preferred":[
        "Ping"
    ],
    "name:deu_x_preferred":[
        "Ping"
    ],
    "name:est_x_preferred":[
        "Ping"
    ],
    "name:fra_x_preferred":[
        "Ping"
    ],
    "name:ind_x_preferred":[
        "Ping"
    ],
    "name:ita_x_preferred":[
        "Ping"
    ],
    "name:nld_x_preferred":[
        "Ping"
    ],
    "name:nno_x_preferred":[
        "Ping"
    ],
    "name:nor_x_preferred":[
        "Ping"
    ],
    "name:swe_x_preferred":[
        "Ping"
    ],
    "name:zho_x_preferred":[
        "Ping"
    ],
    "wof:name":"Ping",
    "wof:placetype":"locality"
},
  "geometry": {"coordinates":[-117.66880999999999,46.66404],"type":"Point"}
}