{
  "type": "Feature",
  "properties": {
    "gn:admin1_code":"WA",
    "gn:admin2_code":"23.0",
    "gn:asciiname":"Ping",
    "gn:country_code":"US",
    "gn:dem":425,
    "gn:elevation":"427.0",
    "gn:feature_class":"P",
    "gn:feature_code":"PPL",
    "gn:name":"Ping",
    "gn:population":0,
    "gn:timezone":"America/Los_Angeles",
    "iso:country":"US",
    "name:ara_x_preferred":[
        "\u0628\u064a\u0646\u063a"
    ],
    "name:ben_x_preferred":[
        "\u09aa\u09bf\u0982"
    ],
    "name:ces_x_preferred":[
        "Ping"
    ],
    "name:dan_x_preferred":[
        "Ping"
    ],
    "name:deu_x_preferred":[
        "Ping"
    ],
    "name:ell_x_preferred":[
        "\u03a0\u03b9\u03bd\u03b3\u03ba"
    ],
    "name:est_x_preferred":[
        "Ping"
    ],
    "name:fas_x_preferred":[
        "\u067e\u06cc\u0646\u06af"
    ],
    "name:fra_x_preferred":[
        "Ping"
    ],
    "name:hin_x_preferred":[
        "\u092a\u093f\u0902\u0917 "
    ],
    "name:hun_x_preferred":[
        "Ping"
    ],
    "name:ind_x_preferred":[
        "Ping"
    ],
    "name:ita_x_preferred":[
        "Ping"
    ],
    "name:nld_x_preferred":[
        "Ping"
    ],
    "name:nno_x_preferred":[
        "Ping"
    ],
    "name:nor_x_preferred":[
        "Ping"
    ],
    "name:por_x_preferred":[
        "Ping"
    ],
    "name:spa_x_preferred":[
        "Ping"
    ],
    "name:swe_x_preferred":[
        "Ping"
    ],
    "name:tur_x_preferred":[
        "Ping"
    ],
    "name:ukr_x_preferred":[
        "\u041f\u0456\u043d\u0433"
    ],
    "name:zho_cn_x_preferred":[
        "\u6e44\u5e73\u6cb3"
    ],
    "name:zho_tw_x_preferred":[
        "\u6ff1\u6cb3"
    ],
    "name:zho_x_preferred":[
        "Ping"
    ],
    "wof:name":"Ping",
    "wof:placetype":"locality"
},
  "geometry": {"coordinates":[-117.66880999999999,46.66404],"type":"Point"}
}