{
  "type": "Feature",
  "properties": {
    "gn:country":"US",
    "gn:fcode":"PPL",
    "gn:population":0,
    "iso:country":"US",
    "name:ara_x_preferred":[
        "\u0628\u0627\u0631\u0644\u0648"
    ],
    "name:cat_x_preferred":[
        "Barlow"
    ],
    "name:ceb_x_preferred":[
        "Barlow"
    ],
    "name:ces_x_preferred":[
        "Barlow"
    ],
    "name:deu_x_preferred":[
        "Barlow"
    ],
    "name:fas_x_preferred":[
        "\u0628\u0627\u0631\u0644\u0648"
    ],
    "name:fra_x_preferred":[
        "Barlow"
    ],
    "name:heb_x_preferred":[
        "\u05d1\u05d0\u05e8\u05dc\u05d5"
    ],
    "name:hun_x_preferred":[
        "Barlow"
    ],
    "name:ita_x_preferred":[
        "Barlow"
    ],
    "name:jpn_x_preferred":[
        "\u30d0\u30ed\u30fc"
    ],
    "name:nld_x_preferred":[
        "Barlow"
    ],
    "name:pol_x_preferred":[
        "Barlow"
    ],
    "name:por_x_preferred":[
        "Barlow"
    ],
    "name:rus_x_preferred":[
        "\u0411\u0430\u0440\u043b\u043e\u0443"
    ],
    "name:slv_x_preferred":[
        "Barlow"
    ],
    "name:spa_x_preferred":[
        "Barlow"
    ],
    "name:srp_x_preferred":[
        "\u0411\u0430\u0440\u043b\u043e\u0443"
    ],
    "name:swe_x_preferred":[
        "Barlow"
    ],
    "name:ukr_x_preferred":[
        "\u0411\u0430\u0440\u043b\u043e\u0443"
    ],
    "name:vol_x_preferred":[
        "Barlow"
    ],
    "qs_pg:aaroncc":"US",
    "qs_pg:gn_country":"US",
    "qs_pg:gn_fcode":"PPL",
    "qs_pg:gn_pop":0,
    "qs_pg:name":"Barlow",
    "qs_pg:name_adm0":"United States",
    "qs_pg:name_adm1":"California",
    "qs_pg:photos":11,
    "qs_pg:photos_1k":2,
    "qs_pg:photos_9k":1,
    "qs_pg:photos_9r":1,
    "qs_pg:photos_all":11,
    "qs_pg:photos_sr":1,
    "qs_pg:pop_sr":0,
    "qs_pg:qs_pg_placetype":"locality",
    "qs_pg:qs_pg_placetype_gp":"Town",
    "qs_pg:woe_adm0":23424977,
    "woe:adm0_id":23424977,
    "woe:name_adm0":"United States",
    "woe:name_adm1":"California",
    "woe:placetype":"Town",
    "wof:name":"Barlow",
    "wof:placetype":"locality"
},
  "geometry": {"coordinates":[-122.8586,38.42491],"type":"Point"}
}