{
  "type": "Feature",
  "properties": {
    "iso:country":"US",
    "name:eng_x_preferred":[
        "Kauhiula Ahupua`a"
    ],
    "wof:name":"Kauhiula Ahupua`a",
    "wof:placetype":"neighbourhood",
    "wof:population":373,
    "zs:area_m":7932939.214142,
    "zs:blockids":[
        150010202021024,
        150010202021217,
        150010202021219,
        150010202022006,
        150010202021013,
        150010202021215,
        150010202022018,
        150010202022023,
        150010202022031,
        150010202021211,
        150010202021030,
        150010202021210,
        150010202021272,
        150010202021007,
        150010202022019,
        150010202022017,
        150010202021218,
        150010202022007,
        150010202021201,
        150010202021214,
        150010202022020,
        150010202021262,
        150010202021254,
        150010202021117,
        150010202021220,
        150010202021256,
        150010202021202,
        150010202021198,
        150010202021191,
        150010202022022,
        150010202022021,
        150010202021193,
        150010202021187,
        150010202021212,
        150010202021018,
        150010202022033,
        150010202021031,
        150010201001359,
        150010202021200,
        150010202022005,
        150010202022009,
        150010202022032,
        150010202021195,
        150010202021206,
        150010202021192,
        150010202022025,
        150010201001003,
        150010202022008,
        150010202022024,
        150010202021003,
        150010202021194,
        150010202021004,
        150010202021019,
        150010202021213,
        150010202021118,
        150010201001360,
        150010202021204,
        150010202021205,
        150010202021197,
        150010202021196,
        150010202021216,
        150010202021012,
        150010202021188,
        150010202021000,
        150010202022037,
        150010202021199
    ],
    "zs:housing10":136,
    "zs:label":"Kauhiula Ahupua`a",
    "zs:pop10":373
},
  "geometry": {"coordinates":[-155.11183299999999,19.753396],"type":"Point"}
}