{
  "type": "Feature",
  "properties": {
    "iso:country":"US",
    "name:cat_x_preferred":[
        "Kerr"
    ],
    "name:ceb_x_preferred":[
        "Kerr"
    ],
    "name:ces_x_preferred":[
        "Kerr"
    ],
    "name:deu_x_preferred":[
        "Kerr"
    ],
    "name:eng_x_preferred":[
        "Kerr"
    ],
    "name:fin_x_preferred":[
        "Kerr"
    ],
    "name:ita_x_preferred":[
        "Kerr"
    ],
    "name:lav_x_preferred":[
        "Kerr"
    ],
    "name:nds_x_preferred":[
        "Kerr"
    ],
    "name:nld_x_preferred":[
        "Kerr"
    ],
    "name:pol_x_preferred":[
        "Kerr"
    ],
    "name:por_x_preferred":[
        "Kerr"
    ],
    "name:ron_x_preferred":[
        "Kerr"
    ],
    "name:rus_x_preferred":[
        "\u041a\u0435\u0440\u0440"
    ],
    "name:spa_x_preferred":[
        "Kerr"
    ],
    "name:swe_x_preferred":[
        "Kerr"
    ],
    "name:ukr_x_preferred":[
        "\u041a\u0435\u0440\u0440"
    ],
    "name:vol_x_preferred":[
        "Kerr"
    ],
    "wof:name":"Kerr",
    "wof:placetype":"neighbourhood",
    "wof:population":207,
    "zs:area_m":12046803.992944,
    "zs:blockids":[
        271370121001107,
        271370121002001,
        271370121001114,
        271370121002002,
        271370121001110,
        271370121001111,
        271370121001115,
        271370121002003,
        271370121002019,
        271370121001113,
        271370121001108,
        271370121001109,
        271370121001112,
        271370121001054,
        271370121002021,
        271370121001117,
        271370121001120
    ],
    "zs:housing10":120,
    "zs:label":"Kerr",
    "zs:pop10":207
},
  "geometry": {"coordinates":[-92.987908,47.431067],"type":"Point"}
}