{
  "type": "Feature",
  "properties": {
    "gn:admin1_code":"AL",
    "gn:admin2_code":"109",
    "gn:asciiname":"Dogwood Acres",
    "gn:country_code":"US",
    "gn:dem":131,
    "gn:elevation":"131.0",
    "gn:feature_class":"P",
    "gn:feature_code":"PPL",
    "gn:name":"Dogwood Acres",
    "gn:population":0,
    "gn:timezone":"America/Chicago",
    "iso:country":"US",
    "wof:name":"Dogwood Acres",
    "wof:placetype":"locality"
},
  "geometry": {"coordinates":[-86.05773000000001,31.7071],"type":"Point"}
}