{
  "type": "Feature",
  "properties": {
    "gn:admin1_code":"CT",
    "gn:admin2_code":"5.0",
    "gn:admin3_code":"51350.0",
    "gn:asciiname":"Nepaug",
    "gn:country_code":"US",
    "gn:dem":175,
    "gn:elevation":"168.0",
    "gn:feature_class":"P",
    "gn:feature_code":"PPL",
    "gn:name":"Nepaug",
    "gn:population":0,
    "gn:timezone":"America/New_York",
    "iso:country":"US",
    "name:eng_x_preferred":[
        "Nepaug"
    ],
    "name:und_x_variant":[
        "Nepaug Village"
    ],
    "wof:name":"Nepaug",
    "wof:placetype":"locality"
},
  "geometry": {"coordinates":[-72.99899000000001,41.82982],"type":"Point"}
}