{
  "type": "Feature",
  "properties": {
    "gn:admin1_code":"GA",
    "gn:admin2_code":"113",
    "gn:asciiname":"Tamerlane",
    "gn:country_code":"US",
    "gn:dem":254,
    "gn:elevation":"251.0",
    "gn:feature_class":"P",
    "gn:feature_code":"PPL",
    "gn:name":"Tamerlane",
    "gn:population":0,
    "gn:timezone":"America/New_York",
    "iso:country":"US",
    "wof:name":"Tamerlane",
    "wof:placetype":"locality"
},
  "geometry": {"coordinates":[-84.53825999999999,33.3629],"type":"Point"}
}