{
  "type": "Feature",
  "properties": {
    "gn:elevation":107,
    "iso:country":"US",
    "name:arz_x_preferred":[
        "\u0645\u0637\u0627\u0631 \u0648\u0633\u0637 \u062c\u0648\u0631\u062c\u064a\u0627 \u0627\u0644\u0627\u0642\u0644\u064a\u0645\u0649"
    ],
    "name:ceb_x_preferred":[
        "Middle Georgia Regional Airport"
    ],
    "name:eng_x_preferred":[
        "Middle Georgia Regional Airport"
    ],
    "name:eng_x_variant":[
        "MCN",
        "KMCN"
    ],
    "name:fas_x_preferred":[
        "\u0641\u0631\u0648\u062f\u06af\u0627\u0647 \u0645\u0646\u0637\u0642\u0647\u200c\u0627\u06cc \u0645\u06cc\u062f\u0644 \u062c\u0631\u062c\u06cc\u0627"
    ],
    "name:jpn_x_preferred":[
        "Middle Georgia\u5730\u57df\u7a7a\u6e2f"
    ],
    "name:ron_x_preferred":[
        "Aeroportul Regional Middle Georgia"
    ],
    "name:tgk_x_preferred":[
        "\u0424\u0443\u0440\u0443\u0434\u0433\u043e\u04b3\u0438 \u043c\u0430\u043d\u0442\u0430\u049b\u0430\u200c\u0438\u0439 \u043c\u0438\u0434\u043b \u04b7\u0440\u04b7\u0438\u043e"
    ],
    "name:urd_x_preferred":[
        "\u0645\u0688\u0644 \u062c\u0627\u0631\u062c\u06cc\u0627 \u0631\u06cc\u062c\u0646\u0644 \u06c1\u0648\u0627\u0626\u06cc \u0627\u0688\u0627"
    ],
    "oa:elevation_ft":"354",
    "oa:type":"medium_airport",
    "wd:wordcount":1350,
    "woe:hierarchy":{
        "country_id":23424977,
        "county_id":12587880,
        "planet_id":1,
        "state_id":2347569
    },
    "wof:name":"Middle Georgia Regional Airport",
    "wof:placetype":"campus"
},
  "geometry": {"coordinates":[-83.64919999999999,32.692799],"type":"Point"}
}