{
  "type": "Feature",
  "properties": {
    "gn:admin1_code":"KY",
    "gn:admin2_code":"131.0",
    "gn:asciiname":"Yeaddiss",
    "gn:country_code":"US",
    "gn:dem":355,
    "gn:elevation":"343.0",
    "gn:feature_class":"P",
    "gn:feature_code":"PPL",
    "gn:name":"Yeaddiss",
    "gn:population":0,
    "gn:timezone":"America/New_York",
    "iso:country":"US",
    "wof:name":"Yeaddiss",
    "wof:placetype":"locality"
},
  "geometry": {"coordinates":[-83.21767,37.0687],"type":"Point"}
}