{
  "type": "Feature",
  "properties": {
    "gn:admin1_code":"OR",
    "gn:admin2_code":"25.0",
    "gn:asciiname":"Trout Creek",
    "gn:country_code":"US",
    "gn:dem":1381,
    "gn:elevation":"1385.0",
    "gn:feature_class":"P",
    "gn:feature_code":"PPL",
    "gn:name":"Trout Creek",
    "gn:population":0,
    "gn:timezone":"America/Los_Angeles",
    "iso:country":"US",
    "name:ceb_x_preferred":[
        "Trout Creek"
    ],
    "name:swe_x_preferred":[
        "Trout Creek"
    ],
    "wof:name":"Trout Creek",
    "wof:placetype":"locality"
},
  "geometry": {"coordinates":[-118.93994000000001,43.9271],"type":"Point"}
}