{
  "type": "Feature",
  "properties": {
    "iso:country":"US",
    "name:deu_x_preferred":[
        "Condit"
    ],
    "name:eng_x_preferred":[
        "Condit"
    ],
    "name:fra_x_preferred":[
        "Condit"
    ],
    "name:swe_x_preferred":[
        "Condit"
    ],
    "wd:wordcount":85,
    "wof:name":"Condit",
    "wof:placetype":"neighbourhood",
    "wof:population":1846,
    "zs:area_m":1444111.860823,
    "zs:blockids":[
        60133410002001,
        60133490001018,
        60133410002016,
        60133410002019,
        60133490001017,
        60133410003003,
        60133410002003,
        60133410002004,
        60133410003002,
        60133410003009,
        60133490001021,
        60133410002010,
        60133410003007,
        60133490001028,
        60133490001019,
        60133410003004,
        60133410003013,
        60133410002012,
        60133410002008,
        60133410003012,
        60133490001014,
        60133410002009,
        60133410003006,
        60133410002033,
        60133410002020,
        60133410001004,
        60133410002007,
        60133490001020,
        60133410003011,
        60133410002002,
        60133410002023,
        60133410003010,
        60133410003017,
        60133410002014,
        60133410003008,
        60133490001022,
        60133410002005
    ],
    "zs:housing10":699,
    "zs:label":"Condit",
    "zs:pop10":1846
},
  "geometry": {"coordinates":[-122.08856,37.892441],"type":"Point"}
}