{
  "type": "Feature",
  "properties": {
    "gn:admin1_code":"IN",
    "gn:admin2_code":"119.0",
    "gn:admin3_code":"38142.0",
    "gn:asciiname":"Hubbell",
    "gn:country_code":"US",
    "gn:dem":161,
    "gn:elevation":"161.0",
    "gn:feature_class":"P",
    "gn:feature_code":"PPL",
    "gn:name":"Hubbell",
    "gn:population":0,
    "gn:timezone":"America/Indiana/Indianapolis",
    "iso:country":"US",
    "name:eng_x_preferred":[
        "Hubbell"
    ],
    "name:und_x_variant":[
        "Hubbells Station"
    ],
    "wof:name":"Hubbell",
    "wof:placetype":"locality"
},
  "geometry": {"coordinates":[-87.01223,39.1831],"type":"Point"}
}