{
  "type": "Feature",
  "properties": {
    "iso:country":"US",
    "name:deu_x_preferred":[
        "Howey"
    ],
    "name:eng_x_preferred":[
        "Howey"
    ],
    "name:pol_x_preferred":[
        "Howey"
    ],
    "name:rus_x_preferred":[
        "\u0425\u0430\u0443\u0438"
    ],
    "wd:wordcount":30,
    "wof:name":"Howey",
    "wof:placetype":"neighbourhood",
    "wof:population":545,
    "zs:area_m":5374889.695949,
    "zs:blockids":[
        120690311031034,
        120690311031058,
        120690311024176,
        120690311031028,
        120690311031023,
        120690311031013,
        120690311031035,
        120690311031025,
        120690311024178,
        120690311031021,
        120690311031032,
        120690311031022,
        120690311031015,
        120690311031014,
        120690311031033,
        120690311024185,
        120690311024229,
        120690311031026,
        120690311031011,
        120690311031036,
        120690311031012,
        120690311031183,
        120690311031017,
        120690311031190,
        120690311031189,
        120690311031001,
        120690311031024,
        120690311031016,
        120690311031192,
        120690311024228
    ],
    "zs:housing10":268,
    "zs:label":"Howey",
    "zs:pop10":545
},
  "geometry": {"coordinates":[-81.764143,28.719834],"type":"Point"}
}