{
  "type": "Feature",
  "properties": {
    "gn:admin1_code":"MN",
    "gn:admin2_code":"71.0",
    "gn:admin3_code":"61433.0",
    "gn:asciiname":"Margie",
    "gn:country_code":"US",
    "gn:dem":387,
    "gn:elevation":"387.0",
    "gn:feature_class":"P",
    "gn:feature_code":"PPL",
    "gn:name":"Margie",
    "gn:population":0,
    "gn:timezone":"America/Chicago",
    "iso:country":"US",
    "wof:name":"Margie",
    "wof:placetype":"locality"
},
  "geometry": {"coordinates":[-93.93992,48.09523],"type":"Point"}
}