{
  "type": "Feature",
  "properties": {
    "gn:admin1_code":"VA",
    "gn:admin2_code":"95.0",
    "gn:asciiname":"Lafayette Square",
    "gn:country_code":"US",
    "gn:dem":21,
    "gn:elevation":"16.0",
    "gn:feature_class":"P",
    "gn:feature_code":"PPL",
    "gn:name":"Lafayette Square",
    "gn:population":0,
    "gn:timezone":"America/New_York",
    "iso:country":"US",
    "name:ceb_x_preferred":[
        "Lafayette Square"
    ],
    "name:deu_x_preferred":[
        "Lafayette Square"
    ],
    "name:fra_x_preferred":[
        "Lafayette Square"
    ],
    "wof:name":"Lafayette Square",
    "wof:placetype":"locality"
},
  "geometry": {"coordinates":[-76.75694,37.3125],"type":"Point"}
}