{
  "type": "Feature",
  "properties": {
    "gn:country":"US",
    "gn:fcode":"PPL",
    "gn:population":0,
    "iso:country":"US",
    "name:deu_x_preferred":[
        "Hulbert"
    ],
    "name:fra_x_preferred":[
        "Hulbert"
    ],
    "name:ita_x_preferred":[
        "Hulbert"
    ],
    "name:nld_x_preferred":[
        "Hulbert"
    ],
    "name:pol_x_preferred":[
        "Hulbert"
    ],
    "name:por_x_preferred":[
        "Hulbert"
    ],
    "qs_pg:aaroncc":"US",
    "qs_pg:gn_country":"US",
    "qs_pg:gn_fcode":"PPL",
    "qs_pg:gn_pop":0,
    "qs_pg:name":"Hulbert",
    "qs_pg:name_adm0":"United States",
    "qs_pg:name_adm1":"Michigan",
    "qs_pg:photos_9k":1,
    "qs_pg:photos_9r":1,
    "qs_pg:photos_all":9,
    "qs_pg:photos_sr":0,
    "qs_pg:pop_sr":5,
    "qs_pg:qs_pg_placetype":"locality",
    "qs_pg:qs_pg_placetype_gp":"Town",
    "qs_pg:woe_adm0":23424977,
    "woe:adm0_id":23424977,
    "woe:name_adm0":"United States",
    "woe:name_adm1":"Michigan",
    "woe:placetype":"Town",
    "wof:name":"Hulbert",
    "wof:placetype":"locality"
},
  "geometry": {"coordinates":[-85.15009000000001,46.35418],"type":"Point"}
}