{
  "type": "Feature",
  "properties": {
    "gn:admin1_code":"AZ",
    "gn:admin2_code":"13.0",
    "gn:asciiname":"Bosque",
    "gn:country_code":"US",
    "gn:dem":292,
    "gn:elevation":"299.0",
    "gn:feature_class":"P",
    "gn:feature_code":"PPL",
    "gn:name":"Bosque",
    "gn:population":0,
    "gn:timezone":"America/Phoenix",
    "iso:country":"US",
    "wof:name":"Bosque",
    "wof:placetype":"locality"
},
  "geometry": {"coordinates":[-112.59822,32.96643],"type":"Point"}
}