{
  "type": "Feature",
  "properties": {
    "gn:admin1_code":"FL",
    "gn:admin2_code":"89.0",
    "gn:asciiname":"Ratliff",
    "gn:country_code":"US",
    "gn:dem":4,
    "gn:elevation":"5.0",
    "gn:feature_class":"P",
    "gn:feature_code":"PPL",
    "gn:name":"Ratliff",
    "gn:population":0,
    "gn:timezone":"America/New_York",
    "iso:country":"US",
    "wof:name":"Ratliff",
    "wof:placetype":"locality"
},
  "geometry": {"coordinates":[-81.8001,30.50774],"type":"Point"}
}