{
  "type": "Feature",
  "properties": {
    "gn:admin1_code":"NY",
    "gn:admin2_code":"83.0",
    "gn:admin3_code":"71102.0",
    "gn:asciiname":"North Stephentown",
    "gn:country_code":"US",
    "gn:dem":340,
    "gn:elevation":"339.0",
    "gn:feature_class":"P",
    "gn:feature_code":"PPL",
    "gn:name":"North Stephentown",
    "gn:population":0,
    "gn:timezone":"America/New_York",
    "iso:country":"US",
    "wof:name":"North Stephentown",
    "wof:placetype":"locality"
},
  "geometry": {"coordinates":[-73.36955,42.59703],"type":"Point"}
}