{
  "type": "Feature",
  "properties": {
    "gn:admin1_code":"MD",
    "gn:admin2_code":"21.0",
    "gn:asciiname":"Mountville",
    "gn:country_code":"US",
    "gn:dem":222,
    "gn:elevation":"214.0",
    "gn:feature_class":"P",
    "gn:feature_code":"PPL",
    "gn:name":"Mountville",
    "gn:population":0,
    "gn:timezone":"America/New_York",
    "iso:country":"US",
    "name:ceb_x_preferred":[
        "Mountville"
    ],
    "name:deu_x_preferred":[
        "Mountville"
    ],
    "name:ita_x_preferred":[
        "Mountville"
    ],
    "name:nld_x_preferred":[
        "Mountville"
    ],
    "name:pol_x_preferred":[
        "Mountville"
    ],
    "name:por_x_preferred":[
        "Mountville"
    ],
    "name:srp_x_preferred":[
        "\u041c\u0430\u0443\u043d\u0442\u0432\u0438\u043b"
    ],
    "name:vol_x_preferred":[
        "Mountville"
    ],
    "wof:name":"Mountville",
    "wof:placetype":"locality"
},
  "geometry": {"coordinates":[-77.51749000000002,39.34399000000001],"type":"Point"}
}