{
  "type": "Feature",
  "properties": {
    "gn:country":"US",
    "gn:fcode":"PPL",
    "gn:population":0,
    "iso:country":"US",
    "name:eng_x_preferred":[
        "Chamberlain"
    ],
    "name:jpn_x_preferred":[
        "\u30c1\u30a7\u30f3\u30d0\u30ec\u30f3"
    ],
    "name:tur_x_preferred":[
        "Chamberlain"
    ],
    "qs_pg:aaroncc":"US",
    "qs_pg:gn_country":"US",
    "qs_pg:gn_fcode":"PPL",
    "qs_pg:gn_pop":0,
    "qs_pg:name":"Chamberlain",
    "qs_pg:name_adm0":"United States",
    "qs_pg:name_adm1":"Maine",
    "qs_pg:photos":489,
    "qs_pg:photos_1k":99,
    "qs_pg:photos_9k":2,
    "qs_pg:photos_9r":5,
    "qs_pg:photos_all":489,
    "qs_pg:photos_sr":7,
    "qs_pg:pop_sr":0,
    "qs_pg:qs_pg_placetype":"locality",
    "qs_pg:qs_pg_placetype_gp":"Town",
    "qs_pg:woe_adm0":23424977,
    "woe:adm0_id":23424977,
    "woe:name_adm0":"United States",
    "woe:name_adm1":"Maine",
    "woe:placetype":"Town",
    "wof:name":"Chamberlain",
    "wof:placetype":"locality"
},
  "geometry": {"coordinates":[-69.47727,43.89203],"type":"Point"}
}