{
  "type": "Feature",
  "properties": {
    "gn:admin1_code":"GA",
    "gn:admin2_code":"157.0",
    "gn:asciiname":"Holly Springs",
    "gn:country_code":"US",
    "gn:dem":282,
    "gn:elevation":"284.0",
    "gn:feature_class":"P",
    "gn:feature_code":"PPL",
    "gn:name":"Holly Springs",
    "gn:population":0,
    "gn:timezone":"America/New_York",
    "iso:country":"US",
    "name:bar_x_preferred":[
        "Holly Springs"
    ],
    "name:ceb_x_preferred":[
        "Holly Springs"
    ],
    "name:deu_x_preferred":[
        "Holly Springs"
    ],
    "name:fas_x_preferred":[
        "\u0647\u0627\u0644\u06cc \u0627\u0633\u067e\u0631\u06cc\u0646\u06af\u0632"
    ],
    "name:ita_x_preferred":[
        "Holly Springs"
    ],
    "name:nld_x_preferred":[
        "Holly Springs"
    ],
    "name:pol_x_preferred":[
        "Holly Springs"
    ],
    "name:por_x_preferred":[
        "Holly Springs"
    ],
    "name:spa_x_preferred":[
        "Holly Springs"
    ],
    "name:srp_x_preferred":[
        "\u0425\u043e\u043b\u0438 \u0421\u043f\u0440\u0438\u043d\u0433\u0441"
    ],
    "name:swe_x_preferred":[
        "Holly Springs"
    ],
    "name:vol_x_preferred":[
        "Holly Springs"
    ],
    "wof:name":"Holly Springs",
    "wof:placetype":"locality"
},
  "geometry": {"coordinates":[-83.63821999999998,34.23511],"type":"Point"}
}