{
  "type": "Feature",
  "properties": {
    "gn:admin1_code":"UT",
    "gn:admin2_code":"21.0",
    "gn:asciiname":"Beryl",
    "gn:country_code":"US",
    "gn:dem":1570,
    "gn:elevation":"1571.0",
    "gn:feature_class":"P",
    "gn:feature_code":"PPL",
    "gn:name":"Beryl",
    "gn:population":0,
    "gn:timezone":"America/Denver",
    "iso:country":"US",
    "name:azb_x_preferred":[
        "\u0628\u0631\u06cc\u0644"
    ],
    "name:fas_x_preferred":[
        "\u0628\u0631\u06cc\u0644"
    ],
    "name:hat_x_preferred":[
        "Beryl"
    ],
    "name:nav_x_preferred":[
        "Ts\u00e9gh\u00e1di\u02bcn\u00edd\u00edn\u00ed"
    ],
    "name:vol_x_preferred":[
        "Beryl"
    ],
    "wof:name":"Beryl",
    "wof:placetype":"locality"
},
  "geometry": {"coordinates":[-113.66136000000002,37.8958],"type":"Point"}
}