{
  "type": "Feature",
  "properties": {
    "gn:admin1_code":"NY",
    "gn:admin2_code":"19.0",
    "gn:admin3_code":"3221.0",
    "gn:asciiname":"Thomasville",
    "gn:country_code":"US",
    "gn:dem":201,
    "gn:elevation":"207.0",
    "gn:feature_class":"P",
    "gn:feature_code":"PPL",
    "gn:name":"Thomasville",
    "gn:population":0,
    "gn:timezone":"America/New_York",
    "iso:country":"US",
    "name:ceb_x_preferred":[
        "Thomasville"
    ],
    "name:deu_x_preferred":[
        "Thomasville"
    ],
    "name:fra_x_preferred":[
        "Thomasville"
    ],
    "name:ita_x_preferred":[
        "Thomasville"
    ],
    "name:jpn_x_preferred":[
        "\u30c8\u30fc\u30de\u30b9\u30d3\u30eb"
    ],
    "name:kor_x_preferred":[
        "\ud1a0\uba38\uc2a4\ube4c"
    ],
    "name:nld_x_preferred":[
        "Thomasville"
    ],
    "name:pol_x_preferred":[
        "Thomasville"
    ],
    "name:por_x_preferred":[
        "Thomasville"
    ],
    "name:srp_x_preferred":[
        "\u0422\u043e\u043c\u0430\u0441\u0432\u0438\u043b"
    ],
    "name:vol_x_preferred":[
        "Thomasville"
    ],
    "wof:name":"Thomasville",
    "wof:placetype":"locality"
},
  "geometry": {"coordinates":[-73.61403,44.47477],"type":"Point"}
}