{
  "type": "Feature",
  "properties": {
    "iso:country":"US",
    "name:eng_x_preferred":[
        "L'Lago"
    ],
    "wof:name":"L'Lago",
    "wof:placetype":"neighbourhood",
    "wof:population":127,
    "zs:area_m":2230004.428472,
    "zs:blockids":[
        120570115041007
    ],
    "zs:housing10":55,
    "zs:label":"L'Lago",
    "zs:pop10":127
},
  "geometry": {"coordinates":[-82.58511900000001,28.154386],"type":"Point"}
}