{
  "type": "Feature",
  "properties": {
    "iso:country":"US",
    "name:eng_x_preferred":[
        "Maple Glen Hollow"
    ],
    "wof:name":"Maple Glen Hollow",
    "wof:placetype":"neighbourhood",
    "wof:population":950,
    "zs:area_m":1868439.544024,
    "zs:blockids":[
        420912005061012,
        420912014092000,
        420912005072018,
        420912014092001,
        420912005072017,
        420912005061011
    ],
    "zs:housing10":295,
    "zs:label":"Maple Glen Hollow",
    "zs:pop10":950
},
  "geometry": {"coordinates":[-75.171708,40.180744],"type":"Point"}
}