{
  "type": "Feature",
  "properties": {
    "iso:country":"US",
    "name:bre_x_preferred":[
        "Dora"
    ],
    "name:ceb_x_preferred":[
        "Dora"
    ],
    "name:ces_x_preferred":[
        "Dora"
    ],
    "name:deu_x_preferred":[
        "Dora"
    ],
    "name:eng_x_preferred":[
        "Dora"
    ],
    "name:est_x_preferred":[
        "Dora"
    ],
    "name:fin_x_preferred":[
        "Dora"
    ],
    "name:fra_x_preferred":[
        "Dora"
    ],
    "name:hbs_x_preferred":[
        "Dora"
    ],
    "name:heb_x_preferred":[
        "\u05d3\u05d5\u05e8\u05d4"
    ],
    "name:hun_x_preferred":[
        "Dora"
    ],
    "name:ind_x_preferred":[
        "Dora"
    ],
    "name:ita_x_preferred":[
        "Dora"
    ],
    "name:jpn_x_preferred":[
        "\u30c9\u30e9"
    ],
    "name:nld_x_preferred":[
        "Dora"
    ],
    "name:pol_x_preferred":[
        "Dora"
    ],
    "name:por_x_preferred":[
        "Dora"
    ],
    "name:ron_x_preferred":[
        "Dora"
    ],
    "name:rus_x_preferred":[
        "\u0414\u043e\u0440\u0430"
    ],
    "name:slk_x_preferred":[
        "Dora"
    ],
    "name:spa_x_preferred":[
        "Dora"
    ],
    "name:swe_x_preferred":[
        "Dora"
    ],
    "name:ukr_x_preferred":[
        "\u0414\u043e\u0440\u0430"
    ],
    "name:vol_x_preferred":[
        "Dora"
    ],
    "wd:wordcount":418,
    "wof:name":"Dora",
    "wof:placetype":"neighbourhood",
    "zs:area_m":10939.374664,
    "zs:blockids":[
        420599708002043
    ],
    "zs:housing10":0,
    "zs:label":"Dora",
    "zs:pop10":0
},
  "geometry": {"coordinates":[-79.914288,39.789168],"type":"Point"}
}