{
  "type": "Feature",
  "properties": {
    "gn:admin1_code":"GA",
    "gn:admin2_code":"33.0",
    "gn:asciiname":"Hancock Landing",
    "gn:country_code":"US",
    "gn:dem":40,
    "gn:elevation":"28.0",
    "gn:feature_class":"P",
    "gn:feature_code":"PPL",
    "gn:name":"Hancock Landing",
    "gn:population":0,
    "gn:timezone":"America/New_York",
    "iso:country":"US",
    "name:eng_x_preferred":[
        "Hancock Landing"
    ],
    "name:und_x_variant":[
        "Hancock",
        "Hancocks Landing"
    ],
    "wof:name":"Hancock Landing",
    "wof:placetype":"locality"
},
  "geometry": {"coordinates":[-81.764,33.15932],"type":"Point"}
}