{
  "type": "Feature",
  "properties": {
    "gn:admin1_code":"FL",
    "gn:admin2_code":"101.0",
    "gn:asciiname":"Trilcoochee",
    "gn:country_code":"US",
    "gn:dem":29,
    "gn:elevation":"21.0",
    "gn:feature_class":"P",
    "gn:feature_code":"PPL",
    "gn:name":"Trilcoochee",
    "gn:population":0,
    "gn:timezone":"America/New_York",
    "iso:country":"US",
    "wof:name":"Trilcoochee",
    "wof:placetype":"locality"
},
  "geometry": {"coordinates":[-82.18314000000002,28.46389000000001],"type":"Point"}
}