{
  "type": "Feature",
  "properties": {
    "gn:gn_country":"US",
    "gn:gn_fcode":"PPL",
    "gn:gn_pop":0,
    "iso:country":"US",
    "name:eng_x_preferred":[
        "Blackwells Corner"
    ],
    "name:fas_x_preferred":[
        "\u0628\u0644\u06a9\u0648\u0644\u0632 \u06a9\u0648\u0631\u0646\u0631"
    ],
    "name:fra_x_preferred":[
        "Blackwells Corner"
    ],
    "name:pol_x_preferred":[
        "Blackwells Corner"
    ],
    "name:zho_x_preferred":[
        "\u5e03\u840a\u514b\u5a01\u723e\u65af\u89d2"
    ],
    "qs_pg:aaroncc":"US",
    "qs_pg:gn_country":"US",
    "qs_pg:gn_fcode":"PPL",
    "qs_pg:gn_pop":0,
    "qs_pg:name":"Blackwells Corner",
    "qs_pg:name_adm0":"United States",
    "qs_pg:name_adm1":"California",
    "qs_pg:photos":49,
    "qs_pg:photos_1k":10,
    "qs_pg:photos_9k":1,
    "qs_pg:photos_9r":2,
    "qs_pg:photos_all":49,
    "qs_pg:photos_sr":2,
    "qs_pg:pop_sr":0,
    "qs_pg:qs_pg_placetype":"locality",
    "qs_pg:qs_pg_placetype_gp":"Town",
    "qs_pg:woe_adm0":23424977,
    "woe:adm0_id":23424977,
    "woe:name_adm0":"United States",
    "woe:name_adm1":"California",
    "woe:placetype":"Town",
    "wof:name":"Blackwells Corner",
    "wof:placetype":"locality"
},
  "geometry": {"coordinates":[-119.86790999999999,35.61496],"type":"Point"}
}