{
  "type": "Feature",
  "properties": {
    "gn:admin1_code":"AL",
    "gn:admin2_code":"81",
    "gn:asciiname":"Moffits Mill",
    "gn:country_code":"US",
    "gn:dem":125,
    "gn:elevation":"112.0",
    "gn:feature_class":"P",
    "gn:feature_code":"PPL",
    "gn:name":"Moffits Mill",
    "gn:population":0,
    "gn:timezone":"America/Chicago",
    "iso:country":"US",
    "wof:name":"Moffits Mill",
    "wof:placetype":"locality"
},
  "geometry": {"coordinates":[-85.18522,32.51014],"type":"Point"}
}