{
  "type": "Feature",
  "properties": {
    "gn:country":"US",
    "gn:fcode":"PPL",
    "gn:population":0,
    "iso:country":"US",
    "name:bel_x_preferred":[
        "\u0422\u043e\u043c\u043f\u0441\u0430\u043d"
    ],
    "name:bul_x_preferred":[
        "\u0422\u043e\u043c\u043f\u0441\u044a\u043d"
    ],
    "name:cat_x_preferred":[
        "Thompson"
    ],
    "name:ceb_x_preferred":[
        "Thompson"
    ],
    "name:ces_x_preferred":[
        "Thompson"
    ],
    "name:deu_x_preferred":[
        "Thompson"
    ],
    "name:fin_x_preferred":[
        "Thompson"
    ],
    "name:fra_x_preferred":[
        "Thompson"
    ],
    "name:heb_x_preferred":[
        "\u05ea\u05d5\u05de\u05e4\u05e1\u05d5\u05df"
    ],
    "name:hrv_x_preferred":[
        "Thompson"
    ],
    "name:ita_x_preferred":[
        "Thompson"
    ],
    "name:jpn_x_preferred":[
        "\u30c8\u30f3\u30d7\u30bd\u30f3"
    ],
    "name:kor_x_preferred":[
        "\ud1b0\uc2a8"
    ],
    "name:kor_x_variant":[
        "\ud1b0\ud504\uc2a8"
    ],
    "name:lav_x_preferred":[
        "Tompsons"
    ],
    "name:nld_x_preferred":[
        "Thompson"
    ],
    "name:nor_x_preferred":[
        "Thompson"
    ],
    "name:pol_x_preferred":[
        "Thompson"
    ],
    "name:por_x_preferred":[
        "Thompson"
    ],
    "name:ron_x_preferred":[
        "Thompson"
    ],
    "name:rus_x_preferred":[
        "\u0422\u043e\u043c\u043f\u0441\u043e\u043d"
    ],
    "name:slv_x_preferred":[
        "Thompson"
    ],
    "name:spa_x_preferred":[
        "Thompson"
    ],
    "name:srp_x_preferred":[
        "\u0422\u043e\u043c\u043f\u0441\u043e\u043d"
    ],
    "name:swe_x_preferred":[
        "Thompson"
    ],
    "name:tur_x_preferred":[
        "Thompson"
    ],
    "name:ukr_x_preferred":[
        "\u0422\u043e\u043c\u043f\u0441\u043e\u043d"
    ],
    "name:urd_x_preferred":[
        "\u062a\u06be\u0627\u0645\u067e\u0633\u0646"
    ],
    "name:vie_x_preferred":[
        "S\u00f4ng Thompson"
    ],
    "name:vie_x_variant":[
        "Thompson"
    ],
    "name:vol_x_preferred":[
        "Thompson"
    ],
    "name:zho_x_preferred":[
        "\u6c64\u666e\u68ee"
    ],
    "qs_pg:aaroncc":"US",
    "qs_pg:gn_country":"US",
    "qs_pg:gn_fcode":"PPL",
    "qs_pg:gn_pop":0,
    "qs_pg:name":"Thompson",
    "qs_pg:name_adm0":"United States",
    "qs_pg:name_adm1":"Delaware",
    "qs_pg:photos":19,
    "qs_pg:photos_1k":4,
    "qs_pg:photos_9k":1,
    "qs_pg:photos_9r":1,
    "qs_pg:photos_all":19,
    "qs_pg:photos_sr":1,
    "qs_pg:pop_sr":0,
    "qs_pg:qs_pg_placetype":"locality",
    "qs_pg:qs_pg_placetype_gp":"Town",
    "qs_pg:woe_adm0":23424977,
    "woe:adm0_id":23424977,
    "woe:name_adm0":"United States",
    "woe:name_adm1":"Delaware",
    "woe:placetype":"Town",
    "wof:name":"Thompson",
    "wof:placetype":"locality"
},
  "geometry": {"coordinates":[-75.75660000000001,39.72928],"type":"Point"}
}