{
  "type": "Feature",
  "properties": {
    "gn:admin1_code":"MD",
    "gn:admin2_code":"27.0",
    "gn:asciiname":"Pfister Mobile Home Park",
    "gn:country_code":"US",
    "gn:dem":69,
    "gn:elevation":"66.0",
    "gn:feature_class":"P",
    "gn:feature_code":"PPL",
    "gn:name":"Pfister Mobile Home Park",
    "gn:population":0,
    "gn:timezone":"America/New_York",
    "iso:country":"US",
    "wof:name":"Pfister Mobile Home Park",
    "wof:placetype":"campus"
},
  "geometry": {"coordinates":[-76.82831,39.11594],"type":"Point"}
}