{
  "type": "Feature",
  "properties": {
    "gn:admin1_code":"MT",
    "gn:admin2_code":"67.0",
    "gn:asciiname":"Brisbin",
    "gn:country_code":"US",
    "gn:dem":1429,
    "gn:elevation":"1432.0",
    "gn:feature_class":"P",
    "gn:feature_code":"PPL",
    "gn:name":"Brisbin",
    "gn:population":0,
    "gn:timezone":"America/Denver",
    "iso:country":"US",
    "name:deu_x_preferred":[
        "Brisbin"
    ],
    "name:fra_x_preferred":[
        "Brisbin"
    ],
    "name:nld_x_preferred":[
        "Brisbin"
    ],
    "wof:name":"Brisbin",
    "wof:placetype":"locality"
},
  "geometry": {"coordinates":[-110.60854,45.52299],"type":"Point"}
}