{
  "type": "Feature",
  "properties": {
    "iso:country":"US",
    "name:eng_x_preferred":[
        "North Agawam"
    ],
    "name:eng_x_variant":[
        "N Agawam"
    ],
    "qs:gn_adm0_cc":"US",
    "qs:gn_local":4928788,
    "qs:gn_nam_loc":"Agawam, Hampden, Massachusetts, US",
    "qs:gn_namadm1":"MA",
    "qs:local_max":844,
    "qs:local_sum":980,
    "qs:localhoods":3,
    "qs:name":"North Agawam",
    "qs:name_adm0":"United States",
    "qs:name_adm1":"Massachusetts",
    "qs:name_adm2":"Hampden",
    "qs:name_local":"Agawam",
    "qs:photo_max":108,
    "qs:photo_sum":844,
    "qs:placetype":"Suburb",
    "qs:quad_count":26,
    "qs:woe_adm0":23424977,
    "qs:woe_adm1":2347580,
    "qs:woe_adm2":12588706,
    "qs:woe_lau":0,
    "qs:woe_local":2352237,
    "qs:woe_ver":"7.10.0",
    "wof:lang":[
        "eng"
    ],
    "wof:name":"North Agawam",
    "wof:placetype":"neighbourhood",
    "wof:population":2293,
    "zs:blockids":[
        250138123002011,
        250138132091029,
        250138123004010,
        250138132072012,
        250138132071001,
        250138132071041,
        250138123001074,
        250138123002020,
        250138123001073,
        250138123004020,
        250138132091031,
        250138123001069,
        250138123001041,
        250138123001077,
        250138123001064,
        250138123001065,
        250138123001067,
        250138123001062,
        250138123002010,
        250138123004016,
        250138123001078,
        250138123001079,
        250138132071042,
        250138123002015,
        250138132072013,
        250138123004009,
        250138132072019,
        250138132071039,
        250138123004017,
        250138123004022,
        250138132091030,
        250138132072009,
        250138123002019,
        250138123001070,
        250138123001071,
        250138123002016,
        250138123004011,
        250138132071022,
        250138123004019,
        250138123004018,
        250138123001036,
        250138123002012,
        250138123001040,
        250138123001042,
        250138132073000,
        250138132072014,
        250138123004021,
        250138132071000,
        250138123004015,
        250138132072010,
        250138123001072,
        250138123001037,
        250138123001076,
        250138132091032,
        250138123004012,
        250138123002017,
        250138123004014,
        250138123001039,
        250138123001075,
        250138123001066,
        250138123002014,
        250138123002018,
        250138123004013
    ],
    "zs:housing10":1174,
    "zs:pop10":2293
},
  "geometry": {"coordinates":[-72.619175,42.092195],"type":"Point"}
}