{
  "type": "Feature",
  "properties": {
    "gn:admin1_code":"NC",
    "gn:admin2_code":"65.0",
    "gn:asciiname":"Suggs Crossroads",
    "gn:country_code":"US",
    "gn:dem":30,
    "gn:elevation":"31.0",
    "gn:feature_class":"P",
    "gn:feature_code":"PPL",
    "gn:name":"Suggs Crossroads",
    "gn:population":0,
    "gn:timezone":"America/New_York",
    "iso:country":"US",
    "wof:name":"Suggs Crossroads",
    "wof:placetype":"locality"
},
  "geometry": {"coordinates":[-77.58358,35.82155],"type":"Point"}
}