{
  "type": "Feature",
  "properties": {
    "gn:admin1_code":"NC",
    "gn:admin2_code":"175.0",
    "gn:admin3_code":"90928.0",
    "gn:asciiname":"Sherwood Terrace",
    "gn:country_code":"US",
    "gn:dem":836,
    "gn:elevation":"824.0",
    "gn:feature_class":"P",
    "gn:feature_code":"PPL",
    "gn:name":"Sherwood Terrace",
    "gn:population":0,
    "gn:timezone":"America/New_York",
    "iso:country":"US",
    "wof:name":"Sherwood Terrace",
    "wof:placetype":"locality"
},
  "geometry": {"coordinates":[-82.67429,35.14623],"type":"Point"}
}