{
  "type": "Feature",
  "properties": {
    "gn:admin1_code":"GA",
    "gn:admin2_code":"193",
    "gn:asciiname":"Travelers Rest",
    "gn:country_code":"US",
    "gn:dem":104,
    "gn:elevation":"98.0",
    "gn:feature_class":"P",
    "gn:feature_code":"PPL",
    "gn:name":"Travelers Rest",
    "gn:population":0,
    "gn:timezone":"America/New_York",
    "iso:country":"US",
    "name:eng_x_preferred":[
        "Travelers Rest"
    ],
    "name:fra_x_preferred":[
        "Travelers Rest"
    ],
    "name:und_x_variant":[
        "Bristol"
    ],
    "wof:name":"Travelers Rest",
    "wof:placetype":"locality"
},
  "geometry": {"coordinates":[-84.0288,32.28127],"type":"Point"}
}