{
  "type": "Feature",
  "properties": {
    "gn:admin1_code":"MA",
    "gn:admin2_code":"23.0",
    "gn:admin3_code":"33920.0",
    "gn:asciiname":"Lakeview Heights",
    "gn:country_code":"US",
    "gn:dem":8,
    "gn:elevation":"30.0",
    "gn:feature_class":"P",
    "gn:feature_code":"PPL",
    "gn:name":"Lakeview Heights",
    "gn:population":0,
    "gn:timezone":"America/New_York",
    "iso:country":"US",
    "name:deu_x_preferred":[
        "Lakeview Heights"
    ],
    "wof:name":"Lakeview Heights",
    "wof:placetype":"locality"
},
  "geometry": {"coordinates":[-70.95643000000003,41.80149],"type":"Point"}
}