{
  "type": "Feature",
  "properties": {
    "gn:admin1_code":"OK",
    "gn:admin2_code":"65",
    "gn:asciiname":"Hess",
    "gn:country_code":"US",
    "gn:dem":408,
    "gn:elevation":"405.0",
    "gn:feature_class":"P",
    "gn:feature_code":"PPL",
    "gn:name":"Hess",
    "gn:population":0,
    "gn:timezone":"America/Chicago",
    "iso:country":"US",
    "name:bel_x_preferred":[
        "\u0413\u0435\u0441"
    ],
    "name:ces_x_preferred":[
        "Hess"
    ],
    "name:deu_x_preferred":[
        "Hess"
    ],
    "name:fas_x_preferred":[
        "\u0647\u0633"
    ],
    "name:fin_x_preferred":[
        "Hess"
    ],
    "name:fra_x_preferred":[
        "Hess"
    ],
    "name:hun_x_preferred":[
        "Hess"
    ],
    "name:ita_x_preferred":[
        "Hess"
    ],
    "name:lav_x_preferred":[
        "Hess"
    ],
    "name:nld_x_preferred":[
        "Hess"
    ],
    "name:pol_x_preferred":[
        "Hess"
    ],
    "name:por_x_preferred":[
        "Hess"
    ],
    "name:ron_x_preferred":[
        "Hess"
    ],
    "name:rus_x_preferred":[
        "\u0425\u0435\u0441\u0441"
    ],
    "name:slk_x_preferred":[
        "Hess"
    ],
    "name:slv_x_preferred":[
        "Hess"
    ],
    "name:spa_x_preferred":[
        "Hess"
    ],
    "name:swe_x_preferred":[
        "Hess"
    ],
    "name:ukr_x_preferred":[
        "\u0413\u0435\u0441\u0441"
    ],
    "wof:name":"Hess",
    "wof:placetype":"locality"
},
  "geometry": {"coordinates":[-99.27231,34.4648],"type":"Point"}
}