{
  "type": "Feature",
  "properties": {
    "gn:country":"US",
    "gn:fcode":"PPL",
    "gn:population":0,
    "iso:country":"US",
    "name:azb_x_preferred":[
        "\u06cc\u0627\u0646\u06a9\u06cc \u0631\u0648\u0646"
    ],
    "name:eng_x_preferred":[
        "Yankee Run"
    ],
    "name:zho_x_preferred":[
        "\u63da\u57fa\u6717"
    ],
    "qs_pg:aaroncc":"US",
    "qs_pg:gn_country":"US",
    "qs_pg:gn_fcode":"PPL",
    "qs_pg:gn_pop":0,
    "qs_pg:name":"Yankee Run",
    "qs_pg:name_adm0":"United States",
    "qs_pg:name_adm1":"Kansas",
    "qs_pg:photos":48,
    "qs_pg:photos_1k":10,
    "qs_pg:photos_9k":1,
    "qs_pg:photos_9r":2,
    "qs_pg:photos_all":48,
    "qs_pg:photos_sr":2,
    "qs_pg:pop_sr":0,
    "qs_pg:qs_pg_placetype":"locality",
    "qs_pg:qs_pg_placetype_gp":"Town",
    "qs_pg:woe_adm0":23424977,
    "woe:adm0_id":23424977,
    "woe:name_adm0":"United States",
    "woe:name_adm1":"Kansas",
    "woe:placetype":"Town",
    "wof:name":"Yankee Run",
    "wof:placetype":"locality"
},
  "geometry": {"coordinates":[-98.01699000000001,38.6514],"type":"Point"}
}