{
  "type": "Feature",
  "properties": {
    "gn:admin1_code":"NC",
    "gn:admin2_code":"165",
    "gn:admin3_code":"93132.0",
    "gn:asciiname":"Hasty",
    "gn:country_code":"US",
    "gn:dem":65,
    "gn:elevation":"60.0",
    "gn:feature_class":"P",
    "gn:feature_code":"PPL",
    "gn:name":"Hasty",
    "gn:population":0,
    "gn:timezone":"America/New_York",
    "iso:country":"US",
    "name:deu_x_preferred":[
        "Hasty"
    ],
    "wof:name":"Hasty",
    "wof:placetype":"locality"
},
  "geometry": {"coordinates":[-79.4781,34.69044],"type":"Point"}
}