{
  "type": "Feature",
  "properties": {
    "gn:admin1_code":"MO",
    "gn:admin2_code":"149.0",
    "gn:admin3_code":"27640.0",
    "gn:asciiname":"Hollis",
    "gn:country_code":"US",
    "gn:dem":273,
    "gn:elevation":"272.0",
    "gn:feature_class":"P",
    "gn:feature_code":"PPL",
    "gn:name":"Hollis",
    "gn:population":0,
    "gn:timezone":"America/Chicago",
    "iso:country":"US",
    "name:cat_x_preferred":[
        "Hollis"
    ],
    "name:ceb_x_preferred":[
        "Hollis"
    ],
    "name:deu_x_preferred":[
        "Hollis"
    ],
    "name:fra_x_preferred":[
        "Hollis"
    ],
    "name:ita_x_preferred":[
        "Hollis"
    ],
    "name:kor_x_preferred":[
        "\ud640\ub9ac\uc2a4"
    ],
    "name:nds_x_preferred":[
        "Hollis"
    ],
    "name:nld_x_preferred":[
        "Hollis"
    ],
    "name:pol_x_preferred":[
        "Hollis"
    ],
    "name:por_x_preferred":[
        "Hollis"
    ],
    "name:srp_x_preferred":[
        "\u0425\u0430\u043b\u0438\u0441"
    ],
    "name:swe_x_preferred":[
        "Hollis"
    ],
    "name:ukr_x_preferred":[
        "\u0413\u043e\u043b\u043b\u0456\u0441"
    ],
    "name:vol_x_preferred":[
        "Hollis"
    ],
    "wof:name":"Hollis",
    "wof:placetype":"locality"
},
  "geometry": {"coordinates":[-91.30513000000001,36.7045],"type":"Point"}
}