{
  "type": "Feature",
  "properties": {
    "iso:country":"US",
    "name:eng_x_preferred":[
        "Ballagh Heights"
    ],
    "wof:name":"Ballagh Heights",
    "wof:placetype":"neighbourhood",
    "wof:population":315,
    "zs:area_m":397717.318818,
    "zs:blockids":[
        191530107033004,
        191530107033007,
        191530107031005
    ],
    "zs:housing10":184,
    "zs:label":"Ballagh Heights",
    "zs:pop10":315
},
  "geometry": {"coordinates":[-93.479423,41.647037],"type":"Point"}
}