{
  "type": "Feature",
  "properties": {
    "gn:admin1_code":"FL",
    "gn:admin2_code":"63.0",
    "gn:asciiname":"Dellwood",
    "gn:country_code":"US",
    "gn:dem":36,
    "gn:elevation":"32.0",
    "gn:feature_class":"P",
    "gn:feature_code":"PPL",
    "gn:name":"Dellwood",
    "gn:population":0,
    "gn:timezone":"America/Chicago",
    "iso:country":"US",
    "name:ceb_x_preferred":[
        "Dellwood"
    ],
    "name:deu_x_preferred":[
        "Dellwood"
    ],
    "name:fra_x_preferred":[
        "Dellwood"
    ],
    "name:ido_x_preferred":[
        "Dellwood"
    ],
    "name:ita_x_preferred":[
        "Dellwood"
    ],
    "name:nld_x_preferred":[
        "Dellwood"
    ],
    "name:pol_x_preferred":[
        "Dellwood"
    ],
    "name:srp_x_preferred":[
        "\u0414\u0435\u043b\u0432\u0443\u0434"
    ],
    "name:vol_x_preferred":[
        "Dellwood"
    ],
    "wof:name":"Dellwood",
    "wof:placetype":"locality"
},
  "geometry": {"coordinates":[-85.04965,30.8238],"type":"Point"}
}