{
  "type": "Feature",
  "properties": {
    "iso:country":"US",
    "name:eng_x_preferred":[
        "Fawn Hill"
    ],
    "wof:name":"Fawn Hill",
    "wof:placetype":"neighbourhood",
    "wof:population":813,
    "zs:area_m":16961091.919445,
    "zs:blockids":[
        80770014023093,
        80770014022011,
        80770015023048,
        80770015023064,
        80770015023103,
        80770015014153,
        80770015023058,
        80770015023034,
        80770014022015,
        80770014023018,
        80770015023032,
        80770015023061,
        80770014023058,
        80770015023054,
        80770015023038,
        80770015023039,
        80770015014145,
        80770015023125,
        80770014022019,
        80770015014146,
        80770014023004,
        80770014023003,
        80770014022018,
        80770014022035,
        80770015014156,
        80770014022013,
        80770015014152,
        80770015023126,
        80770015023055,
        80770015014148,
        80770014022017,
        80770015023059,
        80770015023093,
        80770015014147,
        80770014023059,
        80770015023041,
        80770015023121,
        80770015023033,
        80770014023000,
        80770015023122,
        80770015023050,
        80770015023044,
        80770014023085,
        80770014023086,
        80770014022012,
        80770014022014,
        80770015023063,
        80770015023123,
        80770015023046,
        80770014023002,
        80770014023084,
        80770015023145,
        80770015023047,
        80770015023062,
        80770015023120,
        80770014022016,
        80770015023056,
        80770014023087,
        80770015023052,
        80770015023043,
        80770015023060,
        80770015014123,
        80770015023049,
        80770015014158,
        80770015023124,
        80770015023051,
        80770015023040,
        80770015023053,
        80770015023045,
        80770014023001,
        80770014022020,
        80770015014144,
        80770015014137,
        80770015023057,
        80770015023042
    ],
    "zs:housing10":335,
    "zs:label":"Fawn Hill",
    "zs:pop10":813
},
  "geometry": {"coordinates":[-108.69824199999999,39.12181],"type":"Point"}
}