{
  "type": "Feature",
  "properties": {
    "gn:admin1_code":"VA",
    "gn:admin2_code":"093",
    "gn:asciiname":"Boaz",
    "gn:country_code":"US",
    "gn:dem":31,
    "gn:elevation":"25.0",
    "gn:feature_class":"P",
    "gn:feature_code":"PPL",
    "gn:name":"Boaz",
    "gn:population":0,
    "gn:timezone":"America/New_York",
    "iso:country":"US",
    "name:ara_x_preferred":[
        "\u0628\u0648\u0639\u0632"
    ],
    "name:bod_x_preferred":[
        "\u0f54\u0f7c\u0f0b\u0f68\u0f0b\u0f5f\u0f72\u0f0d"
    ],
    "name:bre_x_preferred":[
        "Boaz"
    ],
    "name:cat_x_preferred":[
        "Booz"
    ],
    "name:ces_x_preferred":[
        "B\u00f3az"
    ],
    "name:deu_x_preferred":[
        "Boas"
    ],
    "name:ell_x_preferred":[
        "\u0392\u03bf\u03cc\u03b6"
    ],
    "name:eus_x_preferred":[
        "Booz"
    ],
    "name:fas_x_preferred":[
        "\u0628\u0648\u0639\u0632"
    ],
    "name:fra_x_preferred":[
        "Boaz"
    ],
    "name:heb_x_preferred":[
        "\u05d1\u05e2\u05d6"
    ],
    "name:hye_x_preferred":[
        "\u0532\u0578\u0578\u057d"
    ],
    "name:ind_x_preferred":[
        "Boas"
    ],
    "name:jpn_x_preferred":[
        "\u30dc\u30a2\u30ba"
    ],
    "name:mlg_x_preferred":[
        "Boaza"
    ],
    "name:nld_x_preferred":[
        "Boaz"
    ],
    "name:nor_x_preferred":[
        "Boas"
    ],
    "name:pol_x_preferred":[
        "Booz"
    ],
    "name:por_x_preferred":[
        "Boaz"
    ],
    "name:rus_x_preferred":[
        "\u0412\u043e\u043e\u0437"
    ],
    "name:spa_x_preferred":[
        "Booz"
    ],
    "name:swe_x_preferred":[
        "Boas"
    ],
    "name:ukr_x_preferred":[
        "\u0411\u043e\u0430\u0437"
    ],
    "name:urd_x_preferred":[
        "\u0628\u0648\u0639\u0632"
    ],
    "name:wol_x_preferred":[
        "Bowas"
    ],
    "name:zho_x_preferred":[
        "\u6ce2\u963f\u65af"
    ],
    "wof:name":"Boaz",
    "wof:placetype":"locality"
},
  "geometry": {"coordinates":[-76.76161999999999,36.74682],"type":"Point"}
}