{
  "type": "Feature",
  "properties": {
    "gn:admin1_code":"VA",
    "gn:admin2_code":"179.0",
    "gn:asciiname":"Stonefield",
    "gn:country_code":"US",
    "gn:dem":46,
    "gn:elevation":"44.0",
    "gn:feature_class":"P",
    "gn:feature_code":"PPL",
    "gn:name":"Stonefield",
    "gn:population":0,
    "gn:timezone":"America/New_York",
    "iso:country":"US",
    "name:deu_x_preferred":[
        "Stonefield"
    ],
    "name:jpn_x_preferred":[
        "\u30b9\u30c8\u30fc\u30f3\u30d5\u30a3\u30fc\u30eb\u30c9"
    ],
    "wof:name":"Stonefield",
    "wof:placetype":"locality"
},
  "geometry": {"coordinates":[-77.389,38.4358],"type":"Point"}
}