{
  "type": "Feature",
  "properties": {
    "gn:admin1_code":"TX",
    "gn:admin2_code":"293.0",
    "gn:asciiname":"Ben Hur",
    "gn:country_code":"US",
    "gn:dem":148,
    "gn:elevation":"143.0",
    "gn:feature_class":"P",
    "gn:feature_code":"PPL",
    "gn:name":"Ben Hur",
    "gn:population":0,
    "gn:timezone":"America/Chicago",
    "iso:country":"US",
    "name:azb_x_preferred":[
        "\u0628\u0646 \u0647\u0648\u0631"
    ],
    "name:eng_x_preferred":[
        "Ben Hur"
    ],
    "name:fas_x_preferred":[
        "\u0628\u0646 \u0647\u0648\u0631"
    ],
    "name:ron_x_preferred":[
        "Ben Hur"
    ],
    "name:und_x_variant":[
        "Benhur"
    ],
    "wof:name":"Ben Hur",
    "wof:placetype":"locality"
},
  "geometry": {"coordinates":[-96.72776,31.51045],"type":"Point"}
}