{
  "type": "Feature",
  "properties": {
    "gn:country":"US",
    "gn:fcode":"PPL",
    "gn:population":0,
    "iso:country":"US",
    "name:bel_x_preferred":[
        "\u041c\u0435\u0434\u0444\u0430\u0440\u0434"
    ],
    "name:cat_x_preferred":[
        "Medford"
    ],
    "name:ceb_x_preferred":[
        "Medford"
    ],
    "name:deu_x_preferred":[
        "Medford"
    ],
    "name:eng_x_preferred":[
        "Medford"
    ],
    "name:fra_x_preferred":[
        "Medford"
    ],
    "name:heb_x_preferred":[
        "\u05de\u05d3\u05e4\u05d5\u05e8\u05d3"
    ],
    "name:ita_x_preferred":[
        "Medford"
    ],
    "name:jpn_x_preferred":[
        "\u30e1\u30c9\u30d5\u30a9\u30fc\u30c9"
    ],
    "name:kor_x_preferred":[
        "\uba54\ub4dc\ud37c\ub4dc"
    ],
    "name:nld_x_preferred":[
        "Medford"
    ],
    "name:pol_x_preferred":[
        "Medford"
    ],
    "name:por_x_preferred":[
        "Medford"
    ],
    "name:rus_x_preferred":[
        "\u041c\u0435\u0434\u0444\u043e\u0440\u0434"
    ],
    "name:spa_x_preferred":[
        "Medford"
    ],
    "name:srp_x_preferred":[
        "\u041c\u0435\u0434\u0444\u043e\u0440\u0434"
    ],
    "name:swe_x_preferred":[
        "Medford"
    ],
    "name:ukr_x_preferred":[
        "\u041c\u0435\u0434\u0444\u043e\u0440\u0434"
    ],
    "name:und_x_variant":[
        "Ross"
    ],
    "name:urd_x_preferred":[
        "\u0645\u06cc\u0688\u0641\u0648\u0631\u0688"
    ],
    "name:vol_x_preferred":[
        "Medford"
    ],
    "qs_pg:aaroncc":"US",
    "qs_pg:gn_country":"US",
    "qs_pg:gn_fcode":"PPL",
    "qs_pg:gn_pop":0,
    "qs_pg:name":"Medford",
    "qs_pg:name_adm0":"United States",
    "qs_pg:name_adm1":"Tennessee",
    "qs_pg:photos":46,
    "qs_pg:photos_1k":9,
    "qs_pg:photos_9k":1,
    "qs_pg:photos_9r":2,
    "qs_pg:photos_all":46,
    "qs_pg:photos_sr":2,
    "qs_pg:pop_sr":0,
    "qs_pg:qs_pg_placetype":"locality",
    "qs_pg:qs_pg_placetype_gp":"Town",
    "qs_pg:woe_adm0":23424977,
    "woe:adm0_id":23424977,
    "woe:name_adm0":"United States",
    "woe:name_adm1":"Tennessee",
    "woe:placetype":"Town",
    "wof:name":"Medford",
    "wof:placetype":"locality"
},
  "geometry": {"coordinates":[-84.14381,36.18119],"type":"Point"}
}