{
  "type": "Feature",
  "properties": {
    "gn:admin1_code":"TN",
    "gn:admin2_code":"165.0",
    "gn:asciiname":"Angeltown",
    "gn:country_code":"US",
    "gn:dem":274,
    "gn:elevation":"273.0",
    "gn:feature_class":"P",
    "gn:feature_code":"PPL",
    "gn:name":"Angeltown",
    "gn:population":0,
    "gn:timezone":"America/Chicago",
    "iso:country":"US",
    "name:eng_x_preferred":[
        "Angeltown"
    ],
    "name:und_x_variant":[
        "Angle"
    ],
    "wof:name":"Angeltown",
    "wof:placetype":"locality"
},
  "geometry": {"coordinates":[-86.34971,36.54727000000001],"type":"Point"}
}