{
  "type": "Feature",
  "properties": {
    "gn:admin1_code":"AL",
    "gn:admin2_code":"55",
    "gn:asciiname":"Burns Park",
    "gn:country_code":"US",
    "gn:dem":161,
    "gn:elevation":"164.0",
    "gn:feature_class":"P",
    "gn:feature_code":"PPL",
    "gn:name":"Burns Park",
    "gn:population":0,
    "gn:timezone":"America/Chicago",
    "iso:country":"US",
    "name:ceb_x_preferred":[
        "Burns Park"
    ],
    "name:swe_x_preferred":[
        "Burns Park"
    ],
    "wof:name":"Burns Park",
    "wof:placetype":"locality"
},
  "geometry": {"coordinates":[-85.95164,33.97954],"type":"Point"}
}