{
  "type": "Feature",
  "properties": {
    "gn:admin1_code":"NY",
    "gn:admin2_code":"17.0",
    "gn:admin3_code":"30422.0",
    "gn:asciiname":"Page Brook",
    "gn:country_code":"US",
    "gn:dem":310,
    "gn:elevation":"310.0",
    "gn:feature_class":"P",
    "gn:feature_code":"PPL",
    "gn:name":"Page Brook",
    "gn:population":0,
    "gn:timezone":"America/New_York",
    "iso:country":"US",
    "wof:name":"Page Brook",
    "wof:placetype":"locality"
},
  "geometry": {"coordinates":[-75.76491,42.25841],"type":"Point"}
}