{
  "type": "Feature",
  "properties": {
    "gn:admin1_code":"AL",
    "gn:admin2_code":"133",
    "gn:asciiname":"German Crossing",
    "gn:country_code":"US",
    "gn:dem":231,
    "gn:elevation":"228.0",
    "gn:feature_class":"P",
    "gn:feature_code":"PPL",
    "gn:name":"German Crossing",
    "gn:population":0,
    "gn:timezone":"America/Chicago",
    "iso:country":"US",
    "wof:name":"German Crossing",
    "wof:placetype":"locality"
},
  "geometry": {"coordinates":[-87.56585,34.0526],"type":"Point"}
}