{
  "type": "Feature",
  "properties": {
    "gn:admin1_code":"IL",
    "gn:admin2_code":"31.0",
    "gn:admin3_code":"53676.0",
    "gn:asciiname":"Little Orchard Subdivision",
    "gn:country_code":"US",
    "gn:dem":200,
    "gn:elevation":"196.0",
    "gn:feature_class":"P",
    "gn:feature_code":"PPL",
    "gn:name":"Little Orchard Subdivision",
    "gn:population":0,
    "gn:timezone":"America/Chicago",
    "iso:country":"US",
    "wof:name":"Little Orchard Subdivision",
    "wof:placetype":"locality"
},
  "geometry": {"coordinates":[-87.78944,42.12889000000001],"type":"Point"}
}