{
  "type": "Feature",
  "properties": {
    "gn:admin1_code":"WI",
    "gn:admin2_code":"5.0",
    "gn:admin3_code":"67375.0",
    "gn:asciiname":"Dobie",
    "gn:country_code":"US",
    "gn:dem":356,
    "gn:elevation":"357.0",
    "gn:feature_class":"P",
    "gn:feature_code":"PPL",
    "gn:name":"Dobie",
    "gn:population":0,
    "gn:timezone":"America/Chicago",
    "iso:country":"US",
    "wof:name":"Dobie",
    "wof:placetype":"locality"
},
  "geometry": {"coordinates":[-91.6835,45.5519],"type":"Point"}
}