{
  "type": "Feature",
  "properties": {
    "iso:country":"US",
    "name:eng_x_preferred":[
        "Venture Properties II"
    ],
    "name:unk_x_variant":[
        "Venture Properties II"
    ],
    "qs:gn_adm0_cc":"US",
    "qs:gn_local":4793846,
    "qs:gn_nam_loc":"Williamsburg, Williamsburg, Virginia, US",
    "qs:gn_namadm1":"VA",
    "qs:local_max":4420,
    "qs:local_sum":14022,
    "qs:localhoods":28,
    "qs:name":"Venture Properties II",
    "qs:name_adm0":"United States",
    "qs:name_adm1":"Virginia",
    "qs:name_adm2":"James City",
    "qs:name_local":"Williamsburg",
    "qs:photo_max":24,
    "qs:photo_sum":66,
    "qs:placetype":"Suburb",
    "qs:quad_count":8,
    "qs:woe_adm0":23424977,
    "qs:woe_adm1":2347605,
    "qs:woe_adm2":12590369,
    "qs:woe_lau":0,
    "qs:woe_local":2520842,
    "qs:woe_ver":"7.10.0",
    "wof:lang":[
        "eng"
    ],
    "wof:name":"Venture Properties II",
    "wof:placetype":"neighbourhood",
    "wof:population":28,
    "zs:blockids":[
        511990510003148,
        511990510003012,
        511990510003158,
        511990510003188,
        511990510003010,
        511990510003187,
        511990510003155,
        511990510003145,
        511990510003192,
        511990510003189,
        511990510003194,
        511990510003195,
        511990510003149,
        511990510003146,
        511990510003153,
        511990510003190,
        511990510003193,
        511990510003143,
        511990510003140,
        511990510003157,
        511990510003139,
        511990510003014,
        511990510003142,
        511990510003144,
        511990510003018,
        511990510003147,
        511990510003152,
        511990510003006,
        511990510003191,
        511990510003156,
        511990510003159,
        511990510003160,
        511990510003011,
        511990510003141,
        511990510003151,
        511990510003154,
        511990510003150
    ],
    "zs:housing10":13,
    "zs:pop10":28
},
  "geometry": {"coordinates":[-76.75556,37.343251],"type":"Point"}
}