{
  "type": "Feature",
  "properties": {
    "iso:country":"US",
    "name:deu_x_preferred":[
        "Chavez"
    ],
    "name:eng_x_preferred":[
        "Chavez"
    ],
    "name:fra_x_preferred":[
        "Ch\u00e1vez"
    ],
    "name:heb_x_preferred":[
        "\u05e6'\u05d0\u05d1\u05e1"
    ],
    "name:ita_x_preferred":[
        "Ch\u00e1vez"
    ],
    "name:kor_x_preferred":[
        "\ucc28\ubca0\uc2a4"
    ],
    "name:nld_x_preferred":[
        "Ch\u00e1vez"
    ],
    "name:pol_x_preferred":[
        "Ch\u00e1vez"
    ],
    "name:por_x_preferred":[
        "Ch\u00e1vez"
    ],
    "name:rus_x_preferred":[
        "\u0427\u0430\u0432\u0435\u0441"
    ],
    "name:spa_x_preferred":[
        "Ch\u00e1vez"
    ],
    "wd:wordcount":103,
    "wof:name":"Chavez",
    "wof:placetype":"neighbourhood",
    "wof:population":150,
    "zs:area_m":919770.25233,
    "zs:blockids":[
        80140313001024,
        80140305004012,
        80140305004000
    ],
    "zs:housing10":58,
    "zs:label":"Chavez",
    "zs:pop10":150
},
  "geometry": {"coordinates":[-105.03879999999999,39.960726],"type":"Point"}
}