{
  "type": "Feature",
  "properties": {
    "gn:country":"US",
    "gn:fcode":"PPL",
    "gn:population":0,
    "iso:country":"US",
    "name:eng_x_preferred":[
        "Groveland"
    ],
    "name:zho_x_preferred":[
        "\u683c\u7f85\u592b\u862d"
    ],
    "qs_pg:aaroncc":"US",
    "qs_pg:gn_country":"US",
    "qs_pg:gn_fcode":"PPL",
    "qs_pg:gn_pop":0,
    "qs_pg:name":"Groveland",
    "qs_pg:name_adm0":"United States",
    "qs_pg:name_adm1":"Indiana",
    "qs_pg:photos":37,
    "qs_pg:photos_1k":7,
    "qs_pg:photos_9k":1,
    "qs_pg:photos_9r":2,
    "qs_pg:photos_all":37,
    "qs_pg:photos_sr":2,
    "qs_pg:pop_sr":0,
    "qs_pg:qs_pg_placetype":"locality",
    "qs_pg:qs_pg_placetype_gp":"Town",
    "qs_pg:woe_adm0":23424977,
    "woe:adm0_id":23424977,
    "woe:name_adm0":"United States",
    "woe:name_adm1":"Indiana",
    "woe:placetype":"Town",
    "wof:name":"Groveland",
    "wof:placetype":"locality"
},
  "geometry": {"coordinates":[-86.72001,39.7606],"type":"Point"}
}