{
  "type": "Feature",
  "properties": {
    "iso:country":"US",
    "name:eng_x_preferred":[
        "Brittan Heights"
    ],
    "qs:gn_adm0_cc":"US",
    "qs:gn_local":5391760,
    "qs:gn_nam_loc":"San Carlos, San Mateo, California, US",
    "qs:gn_namadm1":"CA",
    "qs:local_max":2658,
    "qs:local_sum":6464,
    "qs:localhoods":9,
    "qs:name":"Brittan Heights",
    "qs:name_adm0":"United States",
    "qs:name_adm1":"California",
    "qs:name_adm2":"San Mateo",
    "qs:name_local":"San Carlos",
    "qs:photo_max":28,
    "qs:photo_sum":44,
    "qs:placetype":"Suburb",
    "qs:quad_count":8,
    "qs:woe_adm0":23424977,
    "qs:woe_adm1":2347563,
    "qs:woe_adm2":12587710,
    "qs:woe_lau":0,
    "qs:woe_local":2487878,
    "qs:woe_ver":"7.10.0",
    "wof:lang":[
        "eng"
    ],
    "wof:name":"Brittan Heights",
    "wof:placetype":"neighbourhood",
    "wof:population":1172,
    "zs:blockids":[
        60816094001040,
        60816094001016,
        60816094001004,
        60816094001022,
        60816094001008,
        60816092012012,
        60816094001006,
        60816094001017,
        60816094001020,
        60816094001018,
        60816094001007,
        60816094001019,
        60816094001005,
        60816092012011
    ],
    "zs:housing10":415,
    "zs:pop10":1172
},
  "geometry": {"coordinates":[-122.270545,37.501152],"type":"Point"}
}