{
  "type": "Feature",
  "properties": {
    "gn:admin1_code":"FL",
    "gn:admin2_code":"57",
    "gn:asciiname":"Hidden Lakes Estates",
    "gn:country_code":"US",
    "gn:dem":18,
    "gn:elevation":"13.0",
    "gn:feature_class":"P",
    "gn:feature_code":"PPL",
    "gn:name":"Hidden Lakes Estates",
    "gn:population":0,
    "gn:timezone":"America/New_York",
    "iso:country":"US",
    "wof:name":"Hidden Lakes Estates",
    "wof:placetype":"locality"
},
  "geometry": {"coordinates":[-82.27679999999999,27.8872],"type":"Point"}
}