{
  "type": "Feature",
  "properties": {
    "gn:country":"US",
    "gn:fcode":"PPL",
    "gn:population":1839,
    "iso:country":"US",
    "name:azb_x_preferred":[
        "\u06a9\u0627\u0645\u067e\u06cc\u0648\u0646"
    ],
    "name:cat_x_preferred":[
        "Campion"
    ],
    "name:ceb_x_preferred":[
        "Campion"
    ],
    "name:cym_x_preferred":[
        "Campion"
    ],
    "name:eng_x_preferred":[
        "Campion"
    ],
    "name:fas_x_preferred":[
        "\u06a9\u0627\u0645\u067e\u06cc\u0648\u0646"
    ],
    "name:fra_x_preferred":[
        "Campion"
    ],
    "name:ita_x_preferred":[
        "Campion"
    ],
    "name:nan_x_preferred":[
        "Campion"
    ],
    "name:new_x_preferred":[
        "\u0915\u094d\u092f\u093e\u092e\u094d\u092a\u093f\u092f\u0928"
    ],
    "name:nld_x_preferred":[
        "Campion"
    ],
    "name:por_x_preferred":[
        "Campion"
    ],
    "name:srp_x_preferred":[
        "\u041a\u0430\u043c\u043f\u0438\u043e\u043d"
    ],
    "name:vol_x_preferred":[
        "Campion"
    ],
    "name:zho_x_preferred":[
        "\u574e\u76ae\u6602"
    ],
    "qs_pg:aaroncc":"US",
    "qs_pg:gn_country":"US",
    "qs_pg:gn_fcode":"PPL",
    "qs_pg:gn_pop":1839,
    "qs_pg:name":"Campion",
    "qs_pg:name_adm0":"United States",
    "qs_pg:name_adm1":"Colorado",
    "qs_pg:photos":57,
    "qs_pg:photos_1k":12,
    "qs_pg:photos_9k":1,
    "qs_pg:photos_9r":2,
    "qs_pg:photos_all":57,
    "qs_pg:photos_sr":2,
    "qs_pg:pop_sr":3,
    "qs_pg:qs_pg_placetype":"locality",
    "qs_pg:qs_pg_placetype_gp":"Town",
    "qs_pg:woe_adm0":23424977,
    "woe:adm0_id":23424977,
    "woe:name_adm0":"United States",
    "woe:name_adm1":"Colorado",
    "woe:placetype":"Town",
    "wof:name":"Campion",
    "wof:placetype":"locality",
    "wof:population":1839
},
  "geometry": {"coordinates":[-105.07776,40.34943],"type":"Point"}
}