{
  "type": "Feature",
  "properties": {
    "gn:country":"US",
    "gn:fcode":"PPL",
    "gn:population":0,
    "iso:country":"US",
    "name:eng_x_preferred":[
        "Fernridge"
    ],
    "name:und_x_variant":[
        "Fern Ridge"
    ],
    "qs_pg:aaroncc":"US",
    "qs_pg:gn_country":"US",
    "qs_pg:gn_fcode":"PPL",
    "qs_pg:gn_pop":0,
    "qs_pg:name":"Fernridge",
    "qs_pg:name_adm0":"United States",
    "qs_pg:name_adm1":"Missouri",
    "qs_pg:photos":199,
    "qs_pg:photos_1k":40,
    "qs_pg:photos_9k":1,
    "qs_pg:photos_9r":4,
    "qs_pg:photos_all":199,
    "qs_pg:photos_sr":4,
    "qs_pg:pop_sr":0,
    "qs_pg:qs_pg_placetype":"locality",
    "qs_pg:qs_pg_placetype_gp":"Town",
    "qs_pg:woe_adm0":23424977,
    "woe:adm0_id":23424977,
    "woe:name_adm0":"United States",
    "woe:name_adm1":"Missouri",
    "woe:placetype":"Town",
    "wof:name":"Fernridge",
    "wof:placetype":"locality"
},
  "geometry": {"coordinates":[-90.47762,38.68089],"type":"Point"}
}