{
  "type": "Feature",
  "properties": {
    "gn:admin1_code":"OH",
    "gn:admin2_code":"107.0",
    "gn:admin3_code":"38724.0",
    "gn:asciiname":"Abbeywood Estates",
    "gn:country_code":"US",
    "gn:dem":267,
    "gn:elevation":"266.0",
    "gn:feature_class":"P",
    "gn:feature_code":"PPL",
    "gn:name":"Abbeywood Estates",
    "gn:population":0,
    "gn:timezone":"America/New_York",
    "iso:country":"US",
    "wof:name":"Abbeywood Estates",
    "wof:placetype":"locality"
},
  "geometry": {"coordinates":[-84.58471999999998,40.55583],"type":"Point"}
}