{
  "type": "Feature",
  "properties": {
    "gn:admin1_code":"CA",
    "gn:admin2_code":"23.0",
    "gn:asciiname":"Glendale",
    "gn:country_code":"US",
    "gn:dem":28,
    "gn:elevation":"28.0",
    "gn:feature_class":"P",
    "gn:feature_code":"PPL",
    "gn:name":"Glendale",
    "gn:population":0,
    "gn:timezone":"America/Los_Angeles",
    "iso:country":"US",
    "name:aze_x_preferred":[
        "Qlendeyl"
    ],
    "name:bar_x_preferred":[
        "Glendale"
    ],
    "name:bel_x_preferred":[
        "\u0413\u043b\u0435\u043d\u0434\u044d\u0439\u043b"
    ],
    "name:bul_x_preferred":[
        "\u0413\u043b\u0435\u043d\u0434\u0435\u0439\u043b"
    ],
    "name:cat_x_preferred":[
        "Glendale"
    ],
    "name:ceb_x_preferred":[
        "Glendale"
    ],
    "name:ces_x_preferred":[
        "Glendale"
    ],
    "name:dan_x_preferred":[
        "Glendale"
    ],
    "name:deu_x_preferred":[
        "Glendale"
    ],
    "name:eng_x_preferred":[
        "Glendale"
    ],
    "name:est_x_preferred":[
        "Glendale"
    ],
    "name:fas_x_preferred":[
        "\u06af\u0644\u0646\u062f\u06cc\u0644"
    ],
    "name:fin_x_preferred":[
        "Glendale"
    ],
    "name:fra_x_preferred":[
        "Glendale"
    ],
    "name:glg_x_preferred":[
        "Glendale"
    ],
    "name:heb_x_preferred":[
        "\u05d2\u05dc\u05e0\u05d3\u05d9\u05d9\u05dc"
    ],
    "name:hrv_x_preferred":[
        "Glendale"
    ],
    "name:hun_x_preferred":[
        "Glendale"
    ],
    "name:ido_x_preferred":[
        "Glendale"
    ],
    "name:ita_x_preferred":[
        "Glendale"
    ],
    "name:jpn_x_preferred":[
        "\u30b0\u30ec\u30f3\u30c7\u30fc\u30eb"
    ],
    "name:kor_x_preferred":[
        "\uae00\ub80c\ub370\uc77c"
    ],
    "name:mlg_x_preferred":[
        "Glendale"
    ],
    "name:nld_x_preferred":[
        "Glendale"
    ],
    "name:nor_x_preferred":[
        "Glendale"
    ],
    "name:pol_x_preferred":[
        "Glendale"
    ],
    "name:por_x_preferred":[
        "Glendale"
    ],
    "name:rus_x_preferred":[
        "\u0413\u043b\u0435\u043d\u0434\u0435\u0439\u043b"
    ],
    "name:slk_x_preferred":[
        "Glendale"
    ],
    "name:spa_x_preferred":[
        "Glendale"
    ],
    "name:srp_x_preferred":[
        "\u0413\u043b\u0435\u043d\u0434\u0435\u0458\u043b"
    ],
    "name:swa_x_preferred":[
        "Glendale"
    ],
    "name:swe_x_preferred":[
        "Glendale"
    ],
    "name:szl_x_preferred":[
        "Glendale"
    ],
    "name:tha_x_preferred":[
        "\u0e40\u0e01\u0e25\u0e47\u0e19\u0e40\u0e14\u0e25"
    ],
    "name:tur_x_preferred":[
        "Glendale"
    ],
    "name:ukr_x_preferred":[
        "\u0413\u043b\u0435\u043d\u0434\u0435\u0439\u043b"
    ],
    "name:und_x_variant":[
        "Stockholm"
    ],
    "name:urd_x_preferred":[
        "\u06af\u0644\u06cc\u0646\u0688\u06cc\u0644"
    ],
    "name:vol_x_preferred":[
        "Glendale"
    ],
    "wof:name":"Glendale",
    "wof:placetype":"locality"
},
  "geometry": {"coordinates":[-124.01701,40.89985],"type":"Point"}
}