{
  "type": "Feature",
  "properties": {
    "iso:country":"US",
    "qs_pg:aaroncc":"US",
    "qs_pg:name":"Huffakers",
    "qs_pg:name_adm0":"United States",
    "qs_pg:name_adm1":"Nevada",
    "qs_pg:photos":51,
    "qs_pg:photos_1k":10,
    "qs_pg:photos_9k":1,
    "qs_pg:photos_9r":2,
    "qs_pg:photos_all":51,
    "qs_pg:photos_sr":2,
    "qs_pg:pop_sr":0,
    "qs_pg:qs_pg_placetype":"locality",
    "qs_pg:qs_pg_placetype_gp":"Town",
    "qs_pg:woe_adm0":23424977,
    "woe:adm0_id":23424977,
    "woe:name_adm0":"United States",
    "woe:name_adm1":"Nevada",
    "woe:placetype":"Town",
    "wof:name":"Huffakers",
    "wof:placetype":"locality"
},
  "geometry": {"coordinates":[-119.777334,39.452205],"type":"Point"}
}