{
  "type": "Feature",
  "properties": {
    "gn:country":"US",
    "gn:fcode":"PPL",
    "gn:population":828,
    "iso:country":"US",
    "name:ara_x_preferred":[
        "\u063a\u064a\u0644\u0633\u0648\u0645"
    ],
    "name:cat_x_preferred":[
        "Gilsum"
    ],
    "name:ceb_x_preferred":[
        "Gilsum"
    ],
    "name:deu_x_preferred":[
        "Gilsum"
    ],
    "name:eng_x_preferred":[
        "Gilsum"
    ],
    "name:fra_x_preferred":[
        "Gilsum"
    ],
    "name:hat_x_preferred":[
        "Gilsum"
    ],
    "name:ita_x_preferred":[
        "Gilsum"
    ],
    "name:kaz_x_preferred":[
        "\u0413\u0438\u043b\u0441\u0443\u043c"
    ],
    "name:kir_x_preferred":[
        "\u0413\u0438\u043b\u0441\u0443\u043c"
    ],
    "name:nld_x_preferred":[
        "Gilsum"
    ],
    "name:pol_x_preferred":[
        "Gilsum"
    ],
    "name:spa_x_preferred":[
        "Gilsum"
    ],
    "name:swe_x_preferred":[
        "Gilsum"
    ],
    "name:und_x_variant":[
        "Boyle"
    ],
    "name:urd_x_preferred":[
        "\u06af\u0644\u0633\u0645\u060c \u0646\u06cc\u0648 \u06c1\u06cc\u0645\u067e\u0634\u0627\u0626\u0631"
    ],
    "name:urd_x_variant":[
        "\u06af\u0644\u0633\u0645"
    ],
    "name:vol_x_preferred":[
        "Gilsum"
    ],
    "name:war_x_preferred":[
        "Gilsum"
    ],
    "qs_pg:aaroncc":"US",
    "qs_pg:gn_country":"US",
    "qs_pg:gn_fcode":"PPL",
    "qs_pg:gn_pop":828,
    "qs_pg:name":"Gilsum",
    "qs_pg:name_adm0":"United States",
    "qs_pg:name_adm1":"New Hampshire",
    "qs_pg:photos":52,
    "qs_pg:photos_1k":11,
    "qs_pg:photos_9k":1,
    "qs_pg:photos_9r":2,
    "qs_pg:photos_all":52,
    "qs_pg:photos_sr":2,
    "qs_pg:pop_sr":2,
    "qs_pg:qs_pg_placetype":"locality",
    "qs_pg:qs_pg_placetype_gp":"Town",
    "qs_pg:woe_adm0":23424977,
    "woe:adm0_id":23424977,
    "woe:name_adm0":"United States",
    "woe:name_adm1":"New Hampshire",
    "woe:placetype":"Town",
    "wof:name":"Gilsum",
    "wof:placetype":"locality",
    "wof:population":828
},
  "geometry": {"coordinates":[-72.26286,43.04841],"type":"Point"}
}