{
  "type": "Feature",
  "properties": {
    "iso:country":"US",
    "name:eng_x_preferred":[
        "Oaks West"
    ],
    "wof:name":"Oaks West",
    "wof:placetype":"neighbourhood",
    "wof:population":2580,
    "zs:area_m":2736571.846507,
    "zs:blockids":[
        370810126071014,
        370810126071016,
        370810126171002,
        370810126171010,
        370810126071015,
        370810126071010,
        370810126071023,
        370810126071013,
        370810165021006,
        370810165021005,
        370810165021004,
        370810126071006,
        370810126171006,
        370810126171007,
        370810126171017,
        370810126071005,
        370810126071027,
        370810126071011,
        370810126071024,
        370810126071026,
        370810126071007,
        370810126171018,
        370810126071025,
        370810126171021,
        370810165021000,
        370810126071020,
        370810126071019,
        370810126171009,
        370810126071012,
        370810126071021,
        370810126071008,
        370810126071009,
        370810126171003,
        370810126071029,
        370810165021001
    ],
    "zs:housing10":961,
    "zs:label":"Oaks West",
    "zs:pop10":2580
},
  "geometry": {"coordinates":[-79.88010300000001,36.040315],"type":"Point"}
}