{
  "type": "Feature",
  "properties": {
    "gn:admin1_code":"MT",
    "gn:admin2_code":"71.0",
    "gn:asciiname":"Ashfield",
    "gn:country_code":"US",
    "gn:dem":678,
    "gn:elevation":"681.0",
    "gn:feature_class":"P",
    "gn:feature_code":"PPL",
    "gn:name":"Ashfield",
    "gn:population":0,
    "gn:timezone":"America/Denver",
    "iso:country":"US",
    "name:cat_x_preferred":[
        "Ashfield"
    ],
    "name:ceb_x_preferred":[
        "Ashfield"
    ],
    "name:deu_x_preferred":[
        "Ashfield"
    ],
    "name:eng_x_preferred":[
        "Ashfield"
    ],
    "name:fra_x_preferred":[
        "Ashfield"
    ],
    "name:ita_x_preferred":[
        "Ashfield"
    ],
    "name:nld_x_preferred":[
        "Ashfield"
    ],
    "name:pol_x_preferred":[
        "Ashfield"
    ],
    "name:por_x_preferred":[
        "Ashfield"
    ],
    "name:spa_x_preferred":[
        "Ashfield"
    ],
    "name:swe_x_preferred":[
        "Ashfield"
    ],
    "name:und_x_variant":[
        "Archfield",
        "Ashford",
        "Ashland"
    ],
    "name:vol_x_preferred":[
        "Ashfield"
    ],
    "wof:name":"Ashfield",
    "wof:placetype":"locality"
},
  "geometry": {"coordinates":[-107.47398,48.46194000000001],"type":"Point"}
}