{
  "type": "Feature",
  "properties": {
    "iso:country":"US",
    "name:eng_x_preferred":[
        "Two Mile Creek"
    ],
    "wof:name":"Two Mile Creek",
    "wof:placetype":"neighbourhood",
    "zs:area_m":488108.547867,
    "zs:blockids":[
        80130137012003
    ],
    "zs:housing10":0,
    "zs:label":"Two Mile Creek",
    "zs:pop10":0
},
  "geometry": {"coordinates":[-105.297605,40.052089],"type":"Point"}
}