{
  "type": "Feature",
  "properties": {
    "gn:country":"US",
    "gn:fcode":"PPL",
    "gn:population":0,
    "iso:country":"US",
    "name:deu_x_preferred":[
        "Astral"
    ],
    "name:fra_x_preferred":[
        "Astral"
    ],
    "name:jpn_x_preferred":[
        "\u30a2\u30b9\u30c8\u30e9\u30eb"
    ],
    "name:por_x_preferred":[
        "Astral"
    ],
    "name:ron_x_preferred":[
        "Astral"
    ],
    "name:rus_x_preferred":[
        "\u0410\u0441\u0442\u0440\u0430\u043b"
    ],
    "name:ukr_x_preferred":[
        "\u0410\u0441\u0442\u0440\u0430\u043b"
    ],
    "qs_pg:aaroncc":"US",
    "qs_pg:gn_country":"US",
    "qs_pg:gn_fcode":"PPL",
    "qs_pg:gn_pop":0,
    "qs_pg:name":"Astral",
    "qs_pg:name_adm0":"United States",
    "qs_pg:name_adm1":"Pennsylvania",
    "qs_pg:photos":2,
    "qs_pg:photos_1k":1,
    "qs_pg:photos_9k":1,
    "qs_pg:photos_9r":1,
    "qs_pg:photos_all":2,
    "qs_pg:photos_sr":1,
    "qs_pg:pop_sr":0,
    "qs_pg:qs_pg_placetype":"neighbourhood",
    "qs_pg:qs_pg_placetype_gp":"Suburb",
    "qs_pg:woe_adm0":23424977,
    "woe:adm0_id":23424977,
    "woe:name_adm0":"United States",
    "woe:name_adm1":"Pennsylvania",
    "woe:placetype":"Suburb",
    "wof:name":"Astral",
    "wof:placetype":"neighbourhood"
},
  "geometry": {"coordinates":[-79.77200000000001,41.34395],"type":"Point"}
}