{
  "type": "Feature",
  "properties": {
    "gn:admin1_code":"IN",
    "gn:admin2_code":"125.0",
    "gn:admin3_code":"44640.0",
    "gn:asciiname":"Rumble",
    "gn:country_code":"US",
    "gn:dem":155,
    "gn:elevation":"155.0",
    "gn:feature_class":"P",
    "gn:feature_code":"PPL",
    "gn:name":"Rumble",
    "gn:population":0,
    "gn:timezone":"America/Indiana/Petersburg",
    "iso:country":"US",
    "name:eng_x_preferred":[
        "Rumble"
    ],
    "name:und_x_variant":[
        "Rumble Town"
    ],
    "wof:name":"Rumble",
    "wof:placetype":"locality"
},
  "geometry": {"coordinates":[-87.34279000000002,38.43588],"type":"Point"}
}