{
  "type": "Feature",
  "properties": {
    "gn:admin1_code":"MN",
    "gn:admin2_code":"139.0",
    "gn:admin3_code":"59350.0",
    "gn:asciiname":"Valley Haven Mobile Home Park",
    "gn:country_code":"US",
    "gn:dem":219,
    "gn:elevation":"215.0",
    "gn:feature_class":"P",
    "gn:feature_code":"PPL",
    "gn:name":"Valley Haven Mobile Home Park",
    "gn:population":0,
    "gn:timezone":"America/Chicago",
    "iso:country":"US",
    "wof:name":"Valley Haven Mobile Home Park",
    "wof:placetype":"campus"
},
  "geometry": {"coordinates":[-93.50611000000001,44.80278],"type":"Point"}
}