{
  "type": "Feature",
  "properties": {
    "gn:admin1_code":"SC",
    "gn:admin2_code":"67.0",
    "gn:asciiname":"Friendship",
    "gn:country_code":"US",
    "gn:dem":10,
    "gn:elevation":"15.0",
    "gn:feature_class":"P",
    "gn:feature_code":"PPL",
    "gn:name":"Friendship",
    "gn:population":0,
    "gn:timezone":"America/New_York",
    "iso:country":"US",
    "name:eng_x_preferred":[
        "Friendship"
    ],
    "name:und_x_variant":[
        "Friend"
    ],
    "wof:name":"Friendship",
    "wof:placetype":"locality"
},
  "geometry": {"coordinates":[-79.43533000000002,34.01683],"type":"Point"}
}