{
  "type": "Feature",
  "properties": {
    "iso:country":"US",
    "name:ara_x_preferred":[
        "\u062f\u062a\u0634 \u0647\u0646\u0631\u064a"
    ],
    "name:arz_x_preferred":[
        "\u062f\u062a\u0634 \u0647\u0646\u0631\u0649"
    ],
    "name:ast_x_preferred":[
        "Dutch Henry"
    ],
    "name:cat_x_preferred":[
        "Dutch Henry"
    ],
    "name:deu_x_preferred":[
        "Dutch Henry"
    ],
    "name:eng_x_preferred":[
        "Dutch Henry"
    ],
    "name:fin_x_preferred":[
        "Dutch Henry"
    ],
    "name:fra_x_preferred":[
        "Dutch Henry"
    ],
    "name:gle_x_preferred":[
        "Dutch Henry"
    ],
    "name:ita_x_preferred":[
        "Dutch Henry"
    ],
    "name:nld_x_preferred":[
        "Dutch Henry"
    ],
    "name:pap_x_preferred":[
        "Dutch Henry"
    ],
    "name:slv_x_preferred":[
        "Dutch Henry"
    ],
    "name:spa_x_preferred":[
        "Dutch Henry"
    ],
    "name:sqi_x_preferred":[
        "Dutch Henry"
    ],
    "wd:wordcount":37,
    "wof:name":"Dutch Henry",
    "wof:placetype":"neighbourhood",
    "zs:area_m":17714927.863726,
    "zs:blockids":[
        300310015002216,
        300310015002246,
        300310015002253,
        300310015002258,
        300310015002238,
        300310015002212,
        300310015002213,
        300310015002201,
        300310015002202,
        300310015002248,
        300310015002508,
        300310015002208,
        300310015002210,
        300310015002509,
        300310015002209,
        300310015002184,
        300310015002251,
        300310015002239,
        300310015002211,
        300310015002257,
        300310015002260
    ],
    "zs:housing10":72,
    "zs:label":"Dutch Henry",
    "zs:pop10":0
},
  "geometry": {"coordinates":[-111.216785,44.745415],"type":"Point"}
}