{
  "type": "Feature",
  "properties": {
    "gn:admin1_code":"LA",
    "gn:admin2_code":"75.0",
    "gn:asciiname":"Ollie",
    "gn:country_code":"US",
    "gn:dem":3,
    "gn:elevation":"2.0",
    "gn:feature_class":"P",
    "gn:feature_code":"PPL",
    "gn:name":"Ollie",
    "gn:population":0,
    "gn:timezone":"America/Chicago",
    "iso:country":"US",
    "wof:name":"Ollie",
    "wof:placetype":"locality"
},
  "geometry": {"coordinates":[-90.01756999999998,29.74299],"type":"Point"}
}