{
  "type": "Feature",
  "properties": {
    "gn:admin1_code":"GA",
    "gn:admin2_code":"63.0",
    "gn:asciiname":"Haven Park",
    "gn:country_code":"US",
    "gn:dem":278,
    "gn:elevation":"269.0",
    "gn:feature_class":"P",
    "gn:feature_code":"PPL",
    "gn:name":"Haven Park",
    "gn:population":0,
    "gn:timezone":"America/New_York",
    "iso:country":"US",
    "wof:name":"Haven Park",
    "wof:placetype":"locality"
},
  "geometry": {"coordinates":[-84.31631,33.60455],"type":"Point"}
}