{
  "type": "Feature",
  "properties": {
    "gn:admin1_code":"OH",
    "gn:admin2_code":"57",
    "gn:admin3_code":"86772.0",
    "gn:asciiname":"Pinewood Village",
    "gn:country_code":"US",
    "gn:dem":277,
    "gn:elevation":"277.0",
    "gn:feature_class":"P",
    "gn:feature_code":"PPL",
    "gn:name":"Pinewood Village",
    "gn:population":0,
    "gn:timezone":"America/New_York",
    "iso:country":"US",
    "wof:name":"Pinewood Village",
    "wof:placetype":"locality"
},
  "geometry": {"coordinates":[-83.93528000000001,39.70028],"type":"Point"}
}