{
  "type": "Feature",
  "properties": {
    "gn:admin1_code":"KY",
    "gn:admin2_code":"129",
    "gn:asciiname":"Heidelberg",
    "gn:country_code":"US",
    "gn:dem":212,
    "gn:elevation":"219.0",
    "gn:feature_class":"P",
    "gn:feature_code":"PPL",
    "gn:name":"Heidelberg",
    "gn:population":0,
    "gn:timezone":"America/New_York",
    "iso:country":"US",
    "wof:name":"Heidelberg",
    "wof:placetype":"locality"
},
  "geometry": {"coordinates":[-83.77880999999999,37.55536],"type":"Point"}
}