{
  "type": "Feature",
  "properties": {
    "gn:elevation":24,
    "iso:country":"US",
    "name:eng_x_preferred":[
        "Farrington Lake Heights"
    ],
    "name:eng_x_variant":[
        "Farrington Lake Hts"
    ],
    "name:fra_x_preferred":[
        "Farrington Lake Heights"
    ],
    "qs:gn_adm0_cc":"US",
    "qs:gn_fcode":"PPL",
    "qs:gn_local":5097402,
    "qs:gn_nam_loc":"East Brunswick, Middlesex, New Jersey, US",
    "qs:gn_namadm1":"NJ",
    "qs:gn_name":"Farrington Lake Heights",
    "qs:local_max":326,
    "qs:local_sum":1302,
    "qs:localhoods":12,
    "qs:name":"Farrington Lake Heights",
    "qs:name_adm0":"United States",
    "qs:name_adm1":"New Jersey",
    "qs:name_adm2":"Middlesex",
    "qs:name_local":"East Brunswick",
    "qs:photo_max":88,
    "qs:photo_sum":168,
    "qs:placetype":"Suburb",
    "qs:quad_count":8,
    "qs:woe_adm0":23424977,
    "qs:woe_adm1":2347589,
    "qs:woe_adm2":12589269,
    "qs:woe_funk":"Parented by a neighborhood",
    "qs:woe_lau":0,
    "qs:woe_local":22664085,
    "qs:woe_ver":"7.10.0",
    "wd:wordcount":40,
    "wof:lang":[
        "eng"
    ],
    "wof:name":"Farrington Lake Heights",
    "wof:placetype":"neighbourhood",
    "wof:population":2007,
    "zs:blockids":[
        340230062062007,
        340230062062023,
        340230062062020,
        340230066011009,
        340230066011022,
        340230066011007,
        340230066011025,
        340230066011026,
        340230066011010,
        340230066011008,
        340230066011020,
        340230066011014,
        340230062062002,
        340230062062025,
        340230066012001,
        340230066011017,
        340230066011016,
        340230066011002,
        340230066011021,
        340230062062013,
        340230062062024,
        340230066011006,
        340230066012006,
        340230062062008,
        340230066011019,
        340230066011005,
        340230066011013,
        340230066011015,
        340230066011003,
        340230066011011,
        340230066011018,
        340230062062019,
        340230062062026,
        340230066011004,
        340230066011012,
        340230062062028
    ],
    "zs:housing10":700,
    "zs:pop10":2007
},
  "geometry": {"coordinates":[-74.46162099999999,40.440117],"type":"Point"}
}