{
  "type": "Feature",
  "properties": {
    "gn:admin1_code":"NC",
    "gn:admin2_code":"119.0",
    "gn:asciiname":"Ballantyne East",
    "gn:country_code":"US",
    "gn:dem":194,
    "gn:feature_class":"P",
    "gn:feature_code":"PPL",
    "gn:name":"Ballantyne East",
    "gn:population":0,
    "gn:timezone":"America/New_York",
    "iso:country":"US",
    "wof:name":"Ballantyne East",
    "wof:placetype":"locality"
},
  "geometry": {"coordinates":[-80.83792,35.05016],"type":"Point"}
}