{
  "type": "Feature",
  "properties": {
    "gn:elevation":37,
    "iso:country":"US",
    "name:eng_x_preferred":[
        "Cole Mill"
    ],
    "name:eng_x_variant":[
        "Cole Ml"
    ],
    "qs:gn_adm0_cc":"US",
    "qs:gn_fcode":"PPL",
    "qs:gn_local":4932388,
    "qs:gn_nam_loc":"Carver, Plymouth, Massachusetts, US",
    "qs:gn_namadm1":"MA",
    "qs:gn_name":"Cole Mill",
    "qs:local_max":174,
    "qs:local_sum":281,
    "qs:localhoods":2,
    "qs:name":"Cole Mill",
    "qs:name_adm0":"United States",
    "qs:name_adm1":"Massachusetts",
    "qs:name_adm2":"Plymouth",
    "qs:name_local":"Carver",
    "qs:photo_max":58,
    "qs:photo_sum":107,
    "qs:placetype":"Suburb",
    "qs:quad_count":2,
    "qs:woe_adm0":23424977,
    "qs:woe_adm1":2347580,
    "qs:woe_adm2":12588711,
    "qs:woe_lau":0,
    "qs:woe_local":2375773,
    "qs:woe_ver":"7.10.0",
    "wof:lang":[
        "eng"
    ],
    "wof:name":"Cole Mill",
    "wof:placetype":"neighbourhood"
},
  "geometry": {"coordinates":[-70.807693,41.926027],"type":"Point"}
}