{
  "type": "Feature",
  "properties": {
    "gn:admin1_code":"CO",
    "gn:admin2_code":"45.0",
    "gn:asciiname":"Carbonera",
    "gn:country_code":"US",
    "gn:dem":1693,
    "gn:elevation":"1681.0",
    "gn:feature_class":"P",
    "gn:feature_code":"PPL",
    "gn:name":"Carbonera",
    "gn:population":0,
    "gn:timezone":"America/Denver",
    "iso:country":"US",
    "name:ceb_x_preferred":[
        "Carbonera"
    ],
    "name:ita_x_preferred":[
        "Carbonera"
    ],
    "name:lat_x_preferred":[
        "Carbonera"
    ],
    "name:lmo_x_preferred":[
        "Carbonera"
    ],
    "name:spa_x_preferred":[
        "Carbonera"
    ],
    "name:srp_x_preferred":[
        "Carbonera"
    ],
    "name:swe_x_preferred":[
        "Carbonera"
    ],
    "wof:name":"Carbonera",
    "wof:placetype":"locality"
},
  "geometry": {"coordinates":[-108.959,39.45887000000001],"type":"Point"}
}