{
  "type": "Feature",
  "properties": {
    "gn:admin1_code":"IN",
    "gn:admin2_code":"53.0",
    "gn:admin3_code":"25378.0",
    "gn:asciiname":"Westwood Square",
    "gn:country_code":"US",
    "gn:dem":260,
    "gn:elevation":"258.0",
    "gn:feature_class":"P",
    "gn:feature_code":"PPL",
    "gn:name":"Westwood Square",
    "gn:population":0,
    "gn:timezone":"America/Indiana/Indianapolis",
    "iso:country":"US",
    "wof:name":"Westwood Square",
    "wof:placetype":"locality"
},
  "geometry": {"coordinates":[-85.69441999999999,40.55893],"type":"Point"}
}