{
  "type": "Feature",
  "properties": {
    "gn:admin1_code":"NM",
    "gn:admin2_code":"17",
    "gn:asciiname":"Edgal Place",
    "gn:country_code":"US",
    "gn:dem":1632,
    "gn:elevation":"1635.0",
    "gn:feature_class":"P",
    "gn:feature_code":"PPL",
    "gn:name":"Edgal Place",
    "gn:population":0,
    "gn:timezone":"America/Denver",
    "iso:country":"US",
    "name:eng_x_preferred":[
        "Edgal Place"
    ],
    "name:und_x_variant":[
        "Edgar Place"
    ],
    "wof:name":"Edgal Place",
    "wof:placetype":"locality"
},
  "geometry": {"coordinates":[-108.58172,32.68091],"type":"Point"}
}