{
  "type": "Feature",
  "properties": {
    "iso:country":"US",
    "name:eng_x_preferred":[
        "Kuckville"
    ],
    "wof:name":"Kuckville",
    "wof:placetype":"neighbourhood",
    "wof:population":65,
    "zs:area_m":4119870.951828,
    "zs:blockids":[
        360734012002013,
        360734013003053
    ],
    "zs:housing10":25,
    "zs:label":"Kuckville",
    "zs:pop10":65
},
  "geometry": {"coordinates":[-78.23841,43.355118],"type":"Point"}
}