{
  "type": "Feature",
  "properties": {
    "gn:admin1_code":"GA",
    "gn:admin2_code":"207.0",
    "gn:asciiname":"Bolingbroke",
    "gn:country_code":"US",
    "gn:dem":178,
    "gn:elevation":"173.0",
    "gn:feature_class":"P",
    "gn:feature_code":"PPL",
    "gn:name":"Bolingbroke",
    "gn:population":0,
    "gn:timezone":"America/New_York",
    "iso:country":"US",
    "name:eng_x_preferred":[
        "Bolingbroke"
    ],
    "name:und_x_variant":[
        "Crawfords Station",
        "Colaparchee",
        "Prattsville",
        "Crawfords Crossing",
        "Prattville",
        "Stallings Store"
    ],
    "name:vol_x_preferred":[
        "Bolingbroke"
    ],
    "wof:name":"Bolingbroke",
    "wof:placetype":"locality"
},
  "geometry": {"coordinates":[-83.80324,32.9493],"type":"Point"}
}