{
  "type": "Feature",
  "properties": {
    "gn:admin1_code":"UT",
    "gn:admin2_code":"35.0",
    "gn:asciiname":"Landon Village",
    "gn:country_code":"US",
    "gn:dem":1369,
    "gn:elevation":"1363.0",
    "gn:feature_class":"P",
    "gn:feature_code":"PPL",
    "gn:name":"Landon Village",
    "gn:population":0,
    "gn:timezone":"America/Denver",
    "iso:country":"US",
    "wof:name":"Landon Village",
    "wof:placetype":"locality"
},
  "geometry": {"coordinates":[-111.87021,40.61134000000001],"type":"Point"}
}