{
  "type": "Feature",
  "properties": {
    "iso:country":"US",
    "name:eng_x_preferred":[
        "Glenallen"
    ],
    "qs:gn_adm0_cc":"US",
    "qs:gn_fcode":"PPL",
    "qs:gn_local":4369596,
    "qs:gn_nam_loc":"Silver Spring, Montgomery, Maryland, US",
    "qs:gn_namadm1":"MD",
    "qs:gn_name":"Glenallen",
    "qs:local_max":5273,
    "qs:local_sum":19137,
    "qs:localhoods":40,
    "qs:name":"Glenallen",
    "qs:name_adm0":"United States",
    "qs:name_adm1":"Maryland",
    "qs:name_adm2":"Montgomery",
    "qs:name_local":"Silver Spring",
    "qs:photo_max":1750,
    "qs:photo_sum":5273,
    "qs:placetype":"Suburb",
    "qs:quad_count":32,
    "qs:woe_adm0":23424977,
    "qs:woe_adm1":2347579,
    "qs:woe_adm2":12588691,
    "qs:woe_lau":0,
    "qs:woe_local":2493761,
    "qs:woe_ver":"7.10.0",
    "wof:lang":[
        "eng"
    ],
    "wof:name":"Glenallen",
    "wof:placetype":"neighbourhood",
    "wof:population":2617,
    "zs:blockids":[
        240317032072001,
        240317032081010,
        240317032072012,
        240317032072008,
        240317032072011,
        240317032072010,
        240317015061007,
        240317032072004,
        240317032072014,
        240317032072003,
        240317032072015,
        240317032072005,
        240317032123015,
        240317015073011,
        240317032081009,
        240317032072002,
        240317015061008,
        240317015073007,
        240317032081000,
        240317015061006,
        240317015073008,
        240317015073010,
        240317032072006,
        240317032081008,
        240317015063012,
        240317015073009,
        240317015061009,
        240317015073006,
        240317015061010,
        240317032072000,
        240317032072013,
        240317032072007,
        240317032072009,
        240317032072019
    ],
    "zs:housing10":957,
    "zs:pop10":2617
},
  "geometry": {"coordinates":[-77.035731,39.058656],"type":"Point"}
}