{
  "type": "Feature",
  "properties": {
    "gn:admin1_code":"IL",
    "gn:admin2_code":"197.0",
    "gn:admin3_code":"79059.0",
    "gn:asciiname":"Claus",
    "gn:country_code":"US",
    "gn:dem":226,
    "gn:elevation":"227.0",
    "gn:feature_class":"P",
    "gn:feature_code":"PPL",
    "gn:name":"Claus",
    "gn:population":0,
    "gn:timezone":"America/Chicago",
    "iso:country":"US",
    "wof:name":"Claus",
    "wof:placetype":"locality"
},
  "geometry": {"coordinates":[-87.61004,41.36976],"type":"Point"}
}