{
  "type": "Feature",
  "properties": {
    "iso:country":"US",
    "name:ara_x_preferred":[
        "\u0646\u0628\u0627\u062a \u0627\u0644\u0646\u0641\u0644"
    ],
    "name:bel_x_preferred":[
        "\u0422\u0440\u044b\u043b\u0456\u0441\u043d\u0456\u043a"
    ],
    "name:cat_x_preferred":[
        "Shamrock"
    ],
    "name:ces_x_preferred":[
        "Shamrock"
    ],
    "name:dan_x_preferred":[
        "Shamrock"
    ],
    "name:deu_x_preferred":[
        "Shamrock"
    ],
    "name:epo_x_preferred":[
        "Shamrock"
    ],
    "name:fas_x_preferred":[
        "\u0628\u0631\u06af \u0634\u0628\u062f\u0631"
    ],
    "name:fra_x_preferred":[
        "Tr\u00e8fle irlandais"
    ],
    "name:gle_x_preferred":[
        "Seamr\u00f3g"
    ],
    "name:hrv_x_preferred":[
        "Shamrock"
    ],
    "name:ita_x_preferred":[
        "Shamrock"
    ],
    "name:jpn_x_preferred":[
        "\u30b7\u30e3\u30e0\u30ed\u30c3\u30af"
    ],
    "name:lat_x_preferred":[
        "Chambroch"
    ],
    "name:nld_x_preferred":[
        "Shamrock"
    ],
    "name:pol_x_preferred":[
        "Shamrock"
    ],
    "name:por_x_preferred":[
        "Shamrock"
    ],
    "name:rus_x_preferred":[
        "\u0422\u0440\u0438\u043b\u0438\u0441\u0442\u043d\u0438\u043a"
    ],
    "name:spa_x_preferred":[
        "Shamrock"
    ],
    "name:swe_x_preferred":[
        "Shamrock"
    ],
    "name:szl_x_preferred":[
        "Shamrock"
    ],
    "name:vie_x_preferred":[
        "Shamrock"
    ],
    "wof:name":"Shamrock",
    "wof:placetype":"neighbourhood"
},
  "geometry": {"coordinates":[-80.78629675232851,35.24008363539916],"type":"Point"}
}