{
  "type": "Feature",
  "properties": {
    "gn:admin1_code":"VA",
    "gn:admin2_code":"171",
    "gn:asciiname":"Kern Springs",
    "gn:country_code":"US",
    "gn:dem":438,
    "gn:elevation":"435.0",
    "gn:feature_class":"P",
    "gn:feature_code":"PPL",
    "gn:name":"Kern Springs",
    "gn:population":0,
    "gn:timezone":"America/New_York",
    "iso:country":"US",
    "name:eng_x_preferred":[
        "Kern Springs"
    ],
    "name:und_x_variant":[
        "Kerns Springs"
    ],
    "wof:name":"Kern Springs",
    "wof:placetype":"locality"
},
  "geometry": {"coordinates":[-78.59474,38.92733],"type":"Point"}
}