{
  "type": "Feature",
  "properties": {
    "gn:admin1_code":"IN",
    "gn:admin2_code":"161.0",
    "gn:admin3_code":"43452.0",
    "gn:asciiname":"Dunlapsville",
    "gn:country_code":"US",
    "gn:dem":238,
    "gn:elevation":"236.0",
    "gn:feature_class":"P",
    "gn:feature_code":"PPL",
    "gn:name":"Dunlapsville",
    "gn:population":0,
    "gn:timezone":"America/Indiana/Indianapolis",
    "iso:country":"US",
    "wof:name":"Dunlapsville",
    "wof:placetype":"locality"
},
  "geometry": {"coordinates":[-84.99356999999998,39.59088],"type":"Point"}
}