{
  "type": "Feature",
  "properties": {
    "iso:country":"US",
    "name:eng_x_preferred":[
        "Brookstone"
    ],
    "name:fas_x_preferred":[
        "\u0628\u0631\u0648\u06a9\u200c\u0627\u0633\u062a\u0648\u0646"
    ],
    "name:fra_x_preferred":[
        "Brookstone"
    ],
    "name:spa_x_preferred":[
        "Brookstone"
    ],
    "name:zho_x_preferred":[
        "\u5e03\u6d1b\u53f2\u6566\u96f6\u552e\u5e97"
    ],
    "wd:wordcount":1432,
    "wof:name":"Brookstone",
    "wof:placetype":"neighbourhood",
    "zs:area_m":70214.539765,
    "zs:blockids":[
        51430105033147,
        51430105033139,
        51430105033152
    ],
    "zs:housing10":0,
    "zs:label":"Brookstone",
    "zs:pop10":0
},
  "geometry": {"coordinates":[-94.149776,36.116474],"type":"Point"}
}