{
  "type": "Feature",
  "properties": {
    "gn:admin1_code":"GA",
    "gn:admin2_code":"181.0",
    "gn:asciiname":"Leverett",
    "gn:country_code":"US",
    "gn:dem":146,
    "gn:elevation":"144.0",
    "gn:feature_class":"P",
    "gn:feature_code":"PPL",
    "gn:name":"Leverett",
    "gn:population":0,
    "gn:timezone":"America/New_York",
    "iso:country":"US",
    "name:deu_x_preferred":[
        "Leverett"
    ],
    "name:fra_x_preferred":[
        "Leverett"
    ],
    "wof:name":"Leverett",
    "wof:placetype":"locality"
},
  "geometry": {"coordinates":[-82.39095999999998,33.81068],"type":"Point"}
}