{
  "type": "Feature",
  "properties": {
    "gn:admin1_code":"VT",
    "gn:admin2_code":"21.0",
    "gn:admin3_code":"11950.0",
    "gn:asciiname":"Ransomvale",
    "gn:country_code":"US",
    "gn:dem":211,
    "gn:elevation":"216.0",
    "gn:feature_class":"P",
    "gn:feature_code":"PPL",
    "gn:name":"Ransomvale",
    "gn:population":0,
    "gn:timezone":"America/New_York",
    "iso:country":"US",
    "wof:name":"Ransomvale",
    "wof:placetype":"locality"
},
  "geometry": {"coordinates":[-73.1315,43.65757],"type":"Point"}
}