{
  "type": "Feature",
  "properties": {
    "gn:admin1_code":"KY",
    "gn:admin2_code":"31",
    "gn:asciiname":"Grancer",
    "gn:country_code":"US",
    "gn:dem":146,
    "gn:elevation":"135.0",
    "gn:feature_class":"P",
    "gn:feature_code":"PPL",
    "gn:name":"Grancer",
    "gn:population":0,
    "gn:timezone":"America/Chicago",
    "iso:country":"US",
    "wof:name":"Grancer",
    "wof:placetype":"locality"
},
  "geometry": {"coordinates":[-86.54609000000001,37.30894],"type":"Point"}
}