{
  "type": "Feature",
  "properties": {
    "gn:admin1_code":"IN",
    "gn:admin2_code":"081",
    "gn:admin3_code":"83924.0",
    "gn:asciiname":"Golden Grove",
    "gn:country_code":"US",
    "gn:dem":234,
    "gn:elevation":"231.0",
    "gn:feature_class":"P",
    "gn:feature_code":"PPL",
    "gn:name":"Golden Grove",
    "gn:population":0,
    "gn:timezone":"America/Indiana/Indianapolis",
    "iso:country":"US",
    "name:ceb_x_preferred":[
        "Golden Grove"
    ],
    "name:deu_x_preferred":[
        "Golden Grove"
    ],
    "name:ita_x_preferred":[
        "Golden Grove"
    ],
    "name:mlg_x_preferred":[
        "Golden Grove"
    ],
    "name:nld_x_preferred":[
        "Golden Grove"
    ],
    "name:spa_x_preferred":[
        "Golden Grove"
    ],
    "name:swe_x_preferred":[
        "Golden Grove"
    ],
    "wof:name":"Golden Grove",
    "wof:placetype":"locality"
},
  "geometry": {"coordinates":[-86.18222,39.57139],"type":"Point"}
}