{
  "type": "Feature",
  "properties": {
    "gn:admin1_code":"TX",
    "gn:admin2_code":"331",
    "gn:asciiname":"New Clarkson",
    "gn:country_code":"US",
    "gn:dem":121,
    "gn:elevation":"120.0",
    "gn:feature_class":"P",
    "gn:feature_code":"PPL",
    "gn:name":"New Clarkson",
    "gn:population":0,
    "gn:timezone":"America/Chicago",
    "iso:country":"US",
    "wof:name":"New Clarkson",
    "wof:placetype":"locality"
},
  "geometry": {"coordinates":[-96.90554,31.00602],"type":"Point"}
}