{
  "type": "Feature",
  "properties": {
    "iso:country":"US",
    "name:eng_x_preferred":[
        "Vallejo Heights"
    ],
    "name:eng_x_variant":[
        "Vallejo Hts"
    ],
    "qs:gn_adm0_cc":"US",
    "qs:gn_local":5405380,
    "qs:local_max":3963,
    "qs:local_sum":13042,
    "qs:localhoods":29,
    "qs:name":"Vallejo Heights",
    "qs:name_adm0":"United States",
    "qs:name_adm1":"California",
    "qs:name_adm2":"Solano",
    "qs:name_local":"Vallejo",
    "qs:photo_max":14,
    "qs:photo_sum":36,
    "qs:placetype":"Suburb",
    "qs:quad_count":7,
    "qs:woe_adm0":23424977,
    "qs:woe_adm1":2347563,
    "qs:woe_adm2":12587717,
    "qs:woe_funk":"Grouping neighborhood",
    "qs:woe_lau":0,
    "qs:woe_local":2510744,
    "qs:woe_ver":"7.10.0",
    "wof:name":"Vallejo Heights",
    "wof:placetype":"neighbourhood",
    "wof:population":2336,
    "zs:blockids":[
        60952517012010,
        60952517012003,
        60952517012013,
        60952517012027,
        60952517011022,
        60952517021006,
        60952517012000,
        60952517011005,
        60952517011016,
        60952517012002,
        60952517012024,
        60952517011017,
        60952517011011,
        60952517012009,
        60952517012011,
        60952517012023,
        60952516002011,
        60952517011007,
        60952517011000,
        60952517012012,
        60952517012008,
        60952517012006,
        60952517012025,
        60952517012022,
        60952517011004,
        60952517012004,
        60952517012005,
        60952517012007,
        60952517012021,
        60952516002017,
        60952517012029,
        60952517012031,
        60952517011001,
        60952508011134,
        60952517012001,
        60952517011006,
        60952516002009
    ],
    "zs:housing10":1120,
    "zs:pop10":2336
},
  "geometry": {"coordinates":[-122.259827,38.114344],"type":"Point"}
}