{
  "type": "Feature",
  "properties": {
    "iso:country":"US",
    "name:eng_x_preferred":[
        "Orange Shores"
    ],
    "name:eng_x_variant":[
        "Orange Home"
    ],
    "name:und_x_variant":[
        "Orangehome"
    ],
    "wof:name":"Orange Shores",
    "wof:placetype":"neighbourhood",
    "wof:population":301,
    "zs:area_m":1624608.184804,
    "zs:blockids":[
        121050135001069,
        121050135002066,
        121050135002027,
        121050135002065,
        121050135001073,
        121050135001070,
        121050135001074,
        121050135001034,
        121050135001071,
        121050135002016,
        121050135002015,
        121050135002026,
        121050135001072,
        121050135002071,
        121050135002022,
        121050135001037
    ],
    "zs:housing10":178,
    "zs:label":"Orange Shores",
    "zs:pop10":301
},
  "geometry": {"coordinates":[-81.744451,28.052347],"type":"Point"}
}