{
  "type": "Feature",
  "properties": {
    "iso:country":"US",
    "name:eng_x_preferred":[
        "Mohican Township"
    ],
    "wof:name":"Mohican Township",
    "wof:placetype":"neighbourhood",
    "wof:population":22,
    "zs:area_m":273029.704501,
    "zs:blockids":[
        390059709002028,
        390059709002065
    ],
    "zs:housing10":11,
    "zs:label":"Mohican Township",
    "zs:pop10":22
},
  "geometry": {"coordinates":[-82.19994,40.805511],"type":"Point"}
}