{
  "type": "Feature",
  "properties": {
    "gn:gn_country":"US",
    "gn:gn_fcode":"PPL",
    "gn:gn_pop":0,
    "iso:country":"US",
    "name:eng_x_preferred":[
        "White Oak"
    ],
    "name:fra_x_preferred":[
        "White Oak"
    ],
    "name:unk_x_variant":[
        "Cooperstown"
    ],
    "name:urd_x_preferred":[
        "\u0648\u0627\u0626\u0679 \u0627\u0648\u06a9\u060c \u0631\u0627\u0644\u06cc \u06a9\u0627\u0624\u0646\u0679\u06cc\u060c \u0645\u063a\u0631\u0628\u06cc \u0648\u0631\u062c\u06cc\u0646\u06cc\u0627"
    ],
    "qs_pg:aaroncc":"US",
    "qs_pg:gn_country":"US",
    "qs_pg:gn_fcode":"PPL",
    "qs_pg:gn_pop":0,
    "qs_pg:name":"White Oak",
    "qs_pg:name_adm0":"United States",
    "qs_pg:name_adm1":"West Virginia",
    "qs_pg:photos":5,
    "qs_pg:photos_1k":1,
    "qs_pg:photos_9k":1,
    "qs_pg:photos_9r":1,
    "qs_pg:photos_all":5,
    "qs_pg:photos_sr":1,
    "qs_pg:pop_sr":0,
    "qs_pg:qs_pg_placetype":"locality",
    "qs_pg:qs_pg_placetype_gp":"Town",
    "qs_pg:woe_adm0":23424977,
    "woe:adm0_id":23424977,
    "woe:name_adm0":"United States",
    "woe:name_adm1":"West Virginia",
    "woe:placetype":"Town",
    "wof:name":"White Oak",
    "wof:placetype":"locality"
},
  "geometry": {"coordinates":[-81.07286999999999,37.69289],"type":"Point"}
}