{
  "type": "Feature",
  "properties": {
    "gn:elevation":364,
    "iso:country":"US",
    "name:eng_x_preferred":[
        "Stewartsville"
    ],
    "qs:gn_adm0_cc":"US",
    "qs:gn_fcode":"PPL",
    "qs:gn_local":5203693,
    "qs:gn_nam_loc":"North Huntingdon, Westmoreland, Pennsylvania, US",
    "qs:gn_namadm1":"PA",
    "qs:gn_name":"Stewartsville",
    "qs:local_max":40,
    "qs:local_sum":81,
    "qs:localhoods":4,
    "qs:name":"Stewartsville",
    "qs:name_adm0":"United States",
    "qs:name_adm1":"Pennsylvania",
    "qs:name_adm2":"Westmoreland",
    "qs:name_local":"North Huntingdon",
    "qs:photo_max":1,
    "qs:photo_sum":1,
    "qs:placetype":"Suburb",
    "qs:quad_count":1,
    "qs:woe_adm0":23424977,
    "qs:woe_adm1":2347597,
    "qs:woe_adm2":12589792,
    "qs:woe_lau":0,
    "qs:woe_local":26342964,
    "qs:woe_ver":"7.10.0",
    "wof:lang":[
        "eng"
    ],
    "wof:name":"Stewartsville",
    "wof:placetype":"neighbourhood",
    "wof:population":3679,
    "zs:blockids":[
        421298033012005,
        421298033011011,
        421298032001086,
        421298033011014,
        421298033013011,
        421298033011015,
        421298032001085,
        421298033013027,
        421298033011013,
        421298033012006,
        421298033012010,
        421298033013019,
        421298033012012,
        421298033013026,
        421298033013029,
        421298033012008,
        421298033012003,
        421298033011017,
        421298033011012,
        421298033011016,
        421298033012011,
        421298033013025,
        421298033012007,
        421298033013024,
        421298033012004,
        421298033012009,
        421298033012013,
        421298033012000,
        421298033013022,
        421298033013023,
        421298033013028
    ],
    "zs:housing10":1590,
    "zs:pop10":3679
},
  "geometry": {"coordinates":[-79.76348900000001,40.344452],"type":"Point"}
}