{
  "type": "Feature",
  "properties": {
    "gn:admin1_code":"WV",
    "gn:admin2_code":"25",
    "gn:asciiname":"Anjean",
    "gn:country_code":"US",
    "gn:dem":818,
    "gn:elevation":"818.0",
    "gn:feature_class":"P",
    "gn:feature_code":"PPL",
    "gn:name":"Anjean",
    "gn:population":0,
    "gn:timezone":"America/New_York",
    "iso:country":"US",
    "name:fas_x_preferred":[
        "\u0627\u0646\u062c\u06cc\u0646"
    ],
    "wof:name":"Anjean",
    "wof:placetype":"locality"
},
  "geometry": {"coordinates":[-80.63314,38.02012],"type":"Point"}
}