{
  "type": "Feature",
  "properties": {
    "gn:admin1_code":"TX",
    "gn:admin2_code":"373.0",
    "gn:asciiname":"Snow Hill",
    "gn:country_code":"US",
    "gn:dem":83,
    "gn:elevation":"76.0",
    "gn:feature_class":"P",
    "gn:feature_code":"PPL",
    "gn:name":"Snow Hill",
    "gn:population":0,
    "gn:timezone":"America/Chicago",
    "iso:country":"US",
    "name:ceb_x_preferred":[
        "Snow Hill"
    ],
    "name:deu_x_preferred":[
        "Snow Hill"
    ],
    "name:fra_x_preferred":[
        "Snow Hill"
    ],
    "name:ita_x_preferred":[
        "Snow Hill"
    ],
    "name:nld_x_preferred":[
        "Snow Hill"
    ],
    "name:pol_x_preferred":[
        "Snow Hill"
    ],
    "name:rus_x_preferred":[
        "\u0421\u043d\u043e\u0443-\u0425\u0438\u043b\u043b"
    ],
    "name:srp_x_preferred":[
        "\u0421\u043d\u043e\u0443 \u0425\u0438\u043b"
    ],
    "name:swe_x_preferred":[
        "Snow Hill"
    ],
    "name:vol_x_preferred":[
        "Snow Hill"
    ],
    "wof:name":"Snow Hill",
    "wof:placetype":"locality"
},
  "geometry": {"coordinates":[-94.8091,30.9938],"type":"Point"}
}