{
  "type": "Feature",
  "properties": {
    "gn:admin1_code":"FL",
    "gn:admin2_code":"105.0",
    "gn:asciiname":"Lone Pine Mobile Home Park",
    "gn:country_code":"US",
    "gn:dem":47,
    "gn:elevation":"37.0",
    "gn:feature_class":"P",
    "gn:feature_code":"PPL",
    "gn:name":"Lone Pine Mobile Home Park",
    "gn:population":0,
    "gn:timezone":"America/New_York",
    "iso:country":"US",
    "wof:name":"Lone Pine Mobile Home Park",
    "wof:placetype":"campus"
},
  "geometry": {"coordinates":[-81.89482,28.04339],"type":"Point"}
}