{
  "type": "Feature",
  "properties": {
    "gn:admin1_code":"WV",
    "gn:admin2_code":"97",
    "gn:asciiname":"Frenchton",
    "gn:country_code":"US",
    "gn:dem":456,
    "gn:elevation":"455.0",
    "gn:feature_class":"P",
    "gn:feature_code":"PPL",
    "gn:name":"Frenchton",
    "gn:population":0,
    "gn:timezone":"America/New_York",
    "iso:country":"US",
    "name:eng_x_preferred":[
        "Frenchton"
    ],
    "name:und_x_variant":[
        "French Town",
        "Beachtown",
        "Beech Town",
        "Frenchtown",
        "Beechtown"
    ],
    "wof:name":"Frenchton",
    "wof:placetype":"locality"
},
  "geometry": {"coordinates":[-80.35647,38.87288],"type":"Point"}
}