{
  "type": "Feature",
  "properties": {
    "gn:admin1_code":"AZ",
    "gn:admin2_code":"13.0",
    "gn:asciiname":"Hohokam Village",
    "gn:country_code":"US",
    "gn:dem":383,
    "gn:elevation":"382.0",
    "gn:feature_class":"P",
    "gn:feature_code":"PPL",
    "gn:name":"Hohokam Village",
    "gn:population":0,
    "gn:timezone":"America/Phoenix",
    "iso:country":"US",
    "wof:name":"Hohokam Village",
    "wof:placetype":"locality"
},
  "geometry": {"coordinates":[-111.82013999999999,33.4406],"type":"Point"}
}