{
  "type": "Feature",
  "properties": {
    "gn:gn_country":"US",
    "gn:gn_fcode":"PPL",
    "gn:gn_pop":0,
    "iso:country":"US",
    "name:bre_x_preferred":[
        "Stella"
    ],
    "name:ceb_x_preferred":[
        "Stella"
    ],
    "name:ces_x_preferred":[
        "Stella"
    ],
    "name:deu_x_preferred":[
        "Stella"
    ],
    "name:est_x_preferred":[
        "Stella"
    ],
    "name:fas_x_preferred":[
        "\u0627\u0633\u062a\u0644\u0627"
    ],
    "name:fin_x_preferred":[
        "Stella"
    ],
    "name:fra_x_preferred":[
        "Stella"
    ],
    "name:hun_x_preferred":[
        "Stella"
    ],
    "name:ita_x_preferred":[
        "Stella"
    ],
    "name:jpn_x_preferred":[
        "\u30b9\u30c6\u30e9"
    ],
    "name:kor_x_preferred":[
        "\uc2a4\ud154\ub77c"
    ],
    "name:nld_x_preferred":[
        "Stella"
    ],
    "name:pol_x_preferred":[
        "Stella"
    ],
    "name:por_x_preferred":[
        "Stella"
    ],
    "name:rus_x_preferred":[
        "Stella"
    ],
    "name:spa_x_preferred":[
        "Stella"
    ],
    "name:swe_x_preferred":[
        "Stella"
    ],
    "name:vol_x_preferred":[
        "Stella"
    ],
    "qs_pg:aaroncc":"US",
    "qs_pg:gn_country":"US",
    "qs_pg:gn_fcode":"PPL",
    "qs_pg:gn_pop":0,
    "qs_pg:name":"Stella",
    "qs_pg:name_adm0":"United States",
    "qs_pg:name_adm1":"Arkansas",
    "qs_pg:photos":3,
    "qs_pg:photos_1k":1,
    "qs_pg:photos_9k":1,
    "qs_pg:photos_9r":1,
    "qs_pg:photos_all":3,
    "qs_pg:photos_sr":1,
    "qs_pg:pop_sr":0,
    "qs_pg:qs_pg_placetype":"neighbourhood",
    "qs_pg:qs_pg_placetype_gp":"Suburb",
    "qs_pg:woe_adm0":23424977,
    "woe:adm0_id":23424977,
    "woe:name_adm0":"United States",
    "woe:name_adm1":"Arkansas",
    "woe:placetype":"Suburb",
    "wof:name":"Stella",
    "wof:placetype":"neighbourhood"
},
  "geometry": {"coordinates":[-91.80042,36.0109],"type":"Point"}
}