{
  "type": "Feature",
  "properties": {
    "gn:admin1_code":"LA",
    "gn:admin2_code":"15.0",
    "gn:asciiname":"Shady Park",
    "gn:country_code":"US",
    "gn:dem":68,
    "gn:elevation":"60.0",
    "gn:feature_class":"P",
    "gn:feature_code":"PPL",
    "gn:name":"Shady Park",
    "gn:population":0,
    "gn:timezone":"America/Chicago",
    "iso:country":"US",
    "wof:name":"Shady Park",
    "wof:placetype":"locality"
},
  "geometry": {"coordinates":[-93.57711999999999,32.55709],"type":"Point"}
}