{
  "type": "Feature",
  "properties": {
    "gn:admin1_code":"NE",
    "gn:admin2_code":"149.0",
    "gn:asciiname":"Duff",
    "gn:country_code":"US",
    "gn:dem":766,
    "gn:elevation":"763.0",
    "gn:feature_class":"P",
    "gn:feature_code":"PPL",
    "gn:name":"Duff",
    "gn:population":0,
    "gn:timezone":"America/Chicago",
    "iso:country":"US",
    "wof:name":"Duff",
    "wof:placetype":"locality"
},
  "geometry": {"coordinates":[-99.60429000000001,42.2025],"type":"Point"}
}