{
  "type": "Feature",
  "properties": {
    "gn:admin1_code":"TX",
    "gn:admin2_code":"25.0",
    "gn:asciiname":"Oaks",
    "gn:country_code":"US",
    "gn:dem":114,
    "gn:elevation":"108.0",
    "gn:feature_class":"P",
    "gn:feature_code":"PPL",
    "gn:name":"Oaks",
    "gn:population":0,
    "gn:timezone":"America/Chicago",
    "iso:country":"US",
    "name:ceb_x_preferred":[
        "Oaks"
    ],
    "name:deu_x_preferred":[
        "Oaks"
    ],
    "name:fra_x_preferred":[
        "Oaks"
    ],
    "name:ita_x_preferred":[
        "Oaks"
    ],
    "name:jpn_x_preferred":[
        "\u30aa\u30fc\u30af\u30b9"
    ],
    "name:nds_x_preferred":[
        "Oaks"
    ],
    "name:nld_x_preferred":[
        "Oaks"
    ],
    "name:pol_x_preferred":[
        "Oaks"
    ],
    "name:spa_x_preferred":[
        "Oaks"
    ],
    "name:srp_x_preferred":[
        "\u041e\u0443\u043a\u0441"
    ],
    "name:vol_x_preferred":[
        "Oaks"
    ],
    "wof:name":"Oaks",
    "wof:placetype":"locality"
},
  "geometry": {"coordinates":[-98.03167000000001,28.60888],"type":"Point"}
}