{
  "type": "Feature",
  "properties": {
    "gn:admin1_code":"TN",
    "gn:admin2_code":"71",
    "gn:asciiname":"Hookers Bend",
    "gn:country_code":"US",
    "gn:dem":128,
    "gn:elevation":"123.0",
    "gn:feature_class":"P",
    "gn:feature_code":"PPL",
    "gn:name":"Hookers Bend",
    "gn:population":0,
    "gn:timezone":"America/Chicago",
    "iso:country":"US",
    "name:eng_x_preferred":[
        "Hookers Bend"
    ],
    "name:und_x_variant":[
        "Cravens",
        "Antioch"
    ],
    "wof:name":"Hookers Bend",
    "wof:placetype":"locality"
},
  "geometry": {"coordinates":[-88.21531,35.32063],"type":"Point"}
}