{
  "type": "Feature",
  "properties": {
    "gn:admin1_code":"DE",
    "gn:admin2_code":"5.0",
    "gn:asciiname":"Coverdale Crossroads",
    "gn:country_code":"US",
    "gn:dem":9,
    "gn:elevation":"10.0",
    "gn:feature_class":"P",
    "gn:feature_code":"PPL",
    "gn:name":"Coverdale Crossroads",
    "gn:population":0,
    "gn:timezone":"America/New_York",
    "iso:country":"US",
    "name:eng_x_preferred":[
        "Coverdale Crossroads"
    ],
    "name:und_x_variant":[
        "Collins Cross Roads",
        "Bethels",
        "Oakel",
        "Cloverdale Crossroads",
        "Passwaters Cross Road",
        "Bethel Cross Roads",
        "Lafertys Cross Roads"
    ],
    "wof:name":"Coverdale Crossroads",
    "wof:placetype":"locality"
},
  "geometry": {"coordinates":[-75.53104,38.71039],"type":"Point"}
}