{
  "type": "Feature",
  "properties": {
    "iso:country":"US",
    "name:eng_x_preferred":[
        "Bridgewater Club"
    ],
    "wof:name":"Bridgewater Club",
    "wof:placetype":"neighbourhood",
    "wof:population":195,
    "zs:area_m":706818.256234,
    "zs:blockids":[
        180571105072051,
        180571105072052
    ],
    "zs:housing10":68,
    "zs:label":"Bridgewater Club",
    "zs:pop10":195
},
  "geometry": {"coordinates":[-86.09524500000001,40.019161],"type":"Point"}
}