{
  "type": "Feature",
  "properties": {
    "iso:country":"US",
    "name:eng_x_preferred":[
        "Nicholas Heights"
    ],
    "wof:name":"Nicholas Heights",
    "wof:placetype":"neighbourhood",
    "wof:population":239,
    "zs:area_m":271772.191722,
    "zs:blockids":[
        121050130021027,
        121050130021028,
        121050130021036,
        121050130021034,
        121050130021032,
        121050130021033,
        121050131021092,
        121050130021035,
        121050130021030,
        121050130021022,
        121050130021023
    ],
    "zs:housing10":128,
    "zs:label":"Nicholas Heights",
    "zs:pop10":239
},
  "geometry": {"coordinates":[-81.79161499999999,28.064301],"type":"Point"}
}