{
  "type": "Feature",
  "properties": {
    "gn:country":"US",
    "gn:fcode":"PPL",
    "gn:population":0,
    "iso:country":"US",
    "name:azb_x_preferred":[
        "\u0648\u0648\u062f\u0631\u0648\u0648"
    ],
    "name:eng_x_preferred":[
        "Woodrow"
    ],
    "name:fas_x_preferred":[
        "\u0648\u0648\u062f\u0631\u0648"
    ],
    "name:fra_x_preferred":[
        "Woodrow"
    ],
    "name:vol_x_preferred":[
        "Woodrow"
    ],
    "name:zho_x_preferred":[
        "\u4f0d\u5fb7\u7f85"
    ],
    "qs_pg:aaroncc":"US",
    "qs_pg:gn_country":"US",
    "qs_pg:gn_fcode":"PPL",
    "qs_pg:gn_pop":0,
    "qs_pg:name":"Woodrow",
    "qs_pg:name_adm0":"United States",
    "qs_pg:name_adm1":"Colorado",
    "qs_pg:photos_9k":1,
    "qs_pg:photos_9r":1,
    "qs_pg:photos_all":1,
    "qs_pg:photos_sr":0,
    "qs_pg:pop_sr":5,
    "qs_pg:qs_pg_placetype":"locality",
    "qs_pg:qs_pg_placetype_gp":"Town",
    "qs_pg:woe_adm0":23424977,
    "woe:adm0_id":23424977,
    "woe:name_adm0":"United States",
    "woe:name_adm1":"Colorado",
    "woe:placetype":"Town",
    "wof:name":"Woodrow",
    "wof:placetype":"locality"
},
  "geometry": {"coordinates":[-103.59161,39.98832],"type":"Point"}
}