{
  "type": "Feature",
  "properties": {
    "gn:admin1_code":"AL",
    "gn:admin2_code":"69",
    "gn:asciiname":"Chateau Estates",
    "gn:country_code":"US",
    "gn:dem":97,
    "gn:elevation":"86.0",
    "gn:feature_class":"P",
    "gn:feature_code":"PPL",
    "gn:name":"Chateau Estates",
    "gn:population":0,
    "gn:timezone":"America/Chicago",
    "iso:country":"US",
    "wof:name":"Chateau Estates",
    "wof:placetype":"locality"
},
  "geometry": {"coordinates":[-85.43549,31.24795],"type":"Point"}
}