{
  "type": "Feature",
  "properties": {
    "gn:admin1_code":"MI",
    "gn:admin2_code":"109.0",
    "gn:admin3_code":"44360.0",
    "gn:asciiname":"Longrie",
    "gn:country_code":"US",
    "gn:dem":222,
    "gn:elevation":"222.0",
    "gn:feature_class":"P",
    "gn:feature_code":"PPL",
    "gn:name":"Longrie",
    "gn:population":0,
    "gn:timezone":"America/Menominee",
    "iso:country":"US",
    "wof:name":"Longrie",
    "wof:placetype":"locality"
},
  "geometry": {"coordinates":[-87.72511,45.40581],"type":"Point"}
}