{
  "type": "Feature",
  "properties": {
    "iso:country":"US",
    "name:deu_x_preferred":[
        "Kendall Square"
    ],
    "name:ell_x_preferred":[
        "\u03a0\u03bb\u03b1\u03c4\u03b5\u03af\u03b1 \u039a\u03ad\u03bd\u03c4\u03b1\u03bb\u03bb"
    ],
    "name:eng_x_preferred":[
        "Kendall Square"
    ],
    "name:eng_x_variant":[
        "Kendall Sq",
        "Kendallsquare"
    ],
    "name:fra_x_preferred":[
        "Kendall Square"
    ],
    "name:jpn_x_preferred":[
        "\u30b1\u30f3\u30c9\u30fc\u30eb\u30fb\u30b9\u30af\u30a8\u30a2"
    ],
    "name:nld_x_preferred":[
        "Kendall Square"
    ],
    "name:por_x_preferred":[
        "Kendall Square"
    ],
    "name:spa_x_preferred":[
        "Kendall Square"
    ],
    "name:swe_x_preferred":[
        "Kendall Square"
    ],
    "name:zho_x_preferred":[
        "\u80af\u5fb7\u723e\u5ee3\u5834"
    ],
    "name:zho_x_variant":[
        "\u54c8\u4f5b\u5927\u5b66"
    ],
    "wof:name":"Kendall Square",
    "wof:placetype":"microhood"
},
  "geometry": {"coordinates":[-71.089067,42.363523],"type":"Point"}
}