{
  "type": "Feature",
  "properties": {
    "iso:country":"US",
    "name:ell_x_preferred":[
        "\u03a0\u03bb\u03b1\u03c4\u03b5\u03af\u03b1 \u039a\u03ad\u03bd\u03c4\u03b1\u03bb\u03bb"
    ],
    "name:eng_x_preferred":[
        "Kendall Square"
    ],
    "name:eng_x_variant":[
        "Kendall Sq",
        "Kendallsquare"
    ],
    "name:fra_x_preferred":[
        "Kendall Square"
    ],
    "name:zho_x_preferred":[
        "\u80af\u5fb7\u723e\u5ee3\u5834"
    ],
    "name:zho_x_variant":[
        "\u54c8\u4f5b\u5927\u5b66"
    ],
    "wof:name":"Kendall Square",
    "wof:placetype":"microhood"
},
  "geometry": {"coordinates":[-71.08906660848497,42.36352294729265],"type":"Point"}
}