{
  "type": "Feature",
  "properties": {
    "gn:admin1_code":"IL",
    "gn:admin2_code":"77.0",
    "gn:admin3_code":"56276.0",
    "gn:asciiname":"Sato",
    "gn:country_code":"US",
    "gn:dem":143,
    "gn:elevation":"142.0",
    "gn:feature_class":"P",
    "gn:feature_code":"PPL",
    "gn:name":"Sato",
    "gn:population":0,
    "gn:timezone":"America/Chicago",
    "iso:country":"US",
    "name:eng_x_preferred":[
        "Sato"
    ],
    "name:und_x_variant":[
        "Ora",
        "Gassville"
    ],
    "wof:name":"Sato",
    "wof:placetype":"locality"
},
  "geometry": {"coordinates":[-89.43065,37.90894],"type":"Point"}
}