{
  "type": "Feature",
  "properties": {
    "iso:country":"US",
    "name:eng_x_preferred":[
        "Meadow Ridge"
    ],
    "wof:name":"Meadow Ridge",
    "wof:placetype":"neighbourhood",
    "wof:population":1109,
    "zs:area_m":1098225.505306,
    "zs:blockids":[
        371830527071014,
        371830527071017,
        371830527072001,
        371830527072008,
        371830527043018,
        371830527051003,
        371830527043021,
        371830527043022,
        371830527043017,
        371830527043019,
        371830527072007,
        371830527051026,
        371830527072004,
        371830527072009,
        371830527071015,
        371830527072005,
        371830527072012,
        371830527051000,
        371830527072010,
        371830527071016,
        371830527051002,
        371830527071007,
        371830527072002,
        371830527043020,
        371830527071003,
        371830527072003,
        371830527051001
    ],
    "zs:housing10":509,
    "zs:label":"Meadow Ridge",
    "zs:pop10":1109
},
  "geometry": {"coordinates":[-78.58461200000001,35.837211],"type":"Point"}
}