{
  "type": "Feature",
  "properties": {
    "gn:admin1_code":"AR",
    "gn:admin2_code":"35.0",
    "gn:admin3_code":"93033.0",
    "gn:asciiname":"Galet",
    "gn:country_code":"US",
    "gn:dem":63,
    "gn:elevation":"65.0",
    "gn:feature_class":"P",
    "gn:feature_code":"PPL",
    "gn:name":"Galet",
    "gn:population":0,
    "gn:timezone":"America/Chicago",
    "iso:country":"US",
    "wof:name":"Galet",
    "wof:placetype":"locality"
},
  "geometry": {"coordinates":[-90.21315,35.11537],"type":"Point"}
}