{
  "type": "Feature",
  "properties": {
    "gn:admin1_code":"TN",
    "gn:admin2_code":"167.0",
    "gn:asciiname":"Peckerwood Point",
    "gn:country_code":"US",
    "gn:dem":137,
    "gn:elevation":"135.0",
    "gn:feature_class":"P",
    "gn:feature_code":"PPL",
    "gn:name":"Peckerwood Point",
    "gn:population":0,
    "gn:timezone":"America/Chicago",
    "iso:country":"US",
    "wof:name":"Peckerwood Point",
    "wof:placetype":"locality"
},
  "geometry": {"coordinates":[-89.88203,35.45175],"type":"Point"}
}