{
  "type": "Feature",
  "properties": {
    "gn:admin1_code":"MD",
    "gn:admin2_code":"25.0",
    "gn:asciiname":"Rutledge",
    "gn:country_code":"US",
    "gn:dem":182,
    "gn:elevation":"179.0",
    "gn:feature_class":"P",
    "gn:feature_code":"PPL",
    "gn:name":"Rutledge",
    "gn:population":0,
    "gn:timezone":"America/New_York",
    "iso:country":"US",
    "name:ceb_x_preferred":[
        "Rutledge"
    ],
    "name:deu_x_preferred":[
        "Rutledge"
    ],
    "name:fra_x_preferred":[
        "Rutledge"
    ],
    "name:ita_x_preferred":[
        "Rutledge"
    ],
    "name:jpn_x_preferred":[
        "\u30e9\u30c8\u30ea\u30c3\u30b8"
    ],
    "name:nld_x_preferred":[
        "Rutledge"
    ],
    "name:pol_x_preferred":[
        "Rutledge"
    ],
    "name:por_x_preferred":[
        "Rutledge"
    ],
    "name:rus_x_preferred":[
        "\u0420\u0430\u0442\u043b\u0435\u0434\u0436"
    ],
    "name:srp_x_preferred":[
        "\u0420\u0430\u0442\u043b\u0435\u045f"
    ],
    "name:swe_x_preferred":[
        "Rutledge"
    ],
    "name:vol_x_preferred":[
        "Rutledge"
    ],
    "wof:name":"Rutledge",
    "wof:placetype":"locality"
},
  "geometry": {"coordinates":[-76.49608000000001,39.55705],"type":"Point"}
}