{
  "type": "Feature",
  "properties": {
    "gn:gn_country":"US",
    "gn:gn_fcode":"PPL",
    "gn:gn_pop":0,
    "iso:country":"US",
    "name:bre_x_preferred":[
        "Reunion"
    ],
    "name:cat_x_preferred":[
        "Reuni\u00f3"
    ],
    "name:ces_x_preferred":[
        "Reunion"
    ],
    "name:deu_x_preferred":[
        "Reunion"
    ],
    "name:fin_x_preferred":[
        "Reunion"
    ],
    "name:fra_x_preferred":[
        "R\u00e9union"
    ],
    "name:glg_x_preferred":[
        "Reuni\u00f3n"
    ],
    "name:hun_x_preferred":[
        "Reunion"
    ],
    "name:ita_x_preferred":[
        "Reunion"
    ],
    "name:nld_x_preferred":[
        "Reunion"
    ],
    "name:nor_x_preferred":[
        "Reunion"
    ],
    "name:pol_x_preferred":[
        "R\u00e9union"
    ],
    "name:por_x_preferred":[
        "Reuni\u00e3o"
    ],
    "name:rus_x_preferred":[
        "\u0420\u0435\u044e\u043d\u044c\u043e\u043d"
    ],
    "name:spa_x_preferred":[
        "Reuni\u00f3n"
    ],
    "name:swe_x_preferred":[
        "Reunion"
    ],
    "name:tur_x_preferred":[
        "Reunion"
    ],
    "qs_pg:aaroncc":"US",
    "qs_pg:gn_country":"US",
    "qs_pg:gn_fcode":"PPL",
    "qs_pg:gn_pop":0,
    "qs_pg:name":"Reunion",
    "qs_pg:name_adm0":"United States",
    "qs_pg:name_adm1":"Florida",
    "qs_pg:photos":351,
    "qs_pg:photos_1k":71,
    "qs_pg:photos_9k":2,
    "qs_pg:photos_9r":5,
    "qs_pg:photos_all":351,
    "qs_pg:photos_sr":6,
    "qs_pg:pop_sr":0,
    "qs_pg:qs_pg_placetype":"locality",
    "qs_pg:qs_pg_placetype_gp":"Town",
    "qs_pg:woe_adm0":23424977,
    "woe:adm0_id":23424977,
    "woe:name_adm0":"United States",
    "woe:name_adm1":"Florida",
    "woe:placetype":"Town",
    "wof:name":"Reunion",
    "wof:placetype":"locality"
},
  "geometry": {"coordinates":[-81.60813,28.28029],"type":"Point"}
}