{
  "type": "Feature",
  "properties": {
    "gn:country":"US",
    "gn:fcode":"PPL",
    "gn:population":0,
    "iso:country":"US",
    "name:ceb_x_preferred":[
        "Moline"
    ],
    "name:deu_x_preferred":[
        "Moline"
    ],
    "name:fra_x_preferred":[
        "Moline"
    ],
    "name:ita_x_preferred":[
        "Moline"
    ],
    "name:nld_x_preferred":[
        "Moline"
    ],
    "name:pol_x_preferred":[
        "Moline"
    ],
    "name:por_x_preferred":[
        "Moline"
    ],
    "name:spa_x_preferred":[
        "Moline"
    ],
    "name:srp_x_preferred":[
        "Moline"
    ],
    "name:swe_x_preferred":[
        "Moline"
    ],
    "name:ukr_x_preferred":[
        "\u041c\u043e\u043b\u0456\u043d"
    ],
    "name:vol_x_preferred":[
        "Moline"
    ],
    "qs_pg:aaroncc":"US",
    "qs_pg:gn_country":"US",
    "qs_pg:gn_fcode":"PPL",
    "qs_pg:gn_pop":0,
    "qs_pg:name":"Moline",
    "qs_pg:name_adm0":"United States",
    "qs_pg:name_adm1":"Michigan",
    "qs_pg:photos":54,
    "qs_pg:photos_1k":11,
    "qs_pg:photos_9k":1,
    "qs_pg:photos_9r":2,
    "qs_pg:photos_all":54,
    "qs_pg:photos_sr":2,
    "qs_pg:pop_sr":0,
    "qs_pg:qs_pg_placetype":"locality",
    "qs_pg:qs_pg_placetype_gp":"Town",
    "qs_pg:woe_adm0":23424977,
    "woe:adm0_id":23424977,
    "woe:name_adm0":"United States",
    "woe:name_adm1":"Michigan",
    "woe:placetype":"Town",
    "wof:name":"Moline",
    "wof:placetype":"locality"
},
  "geometry": {"coordinates":[-85.66391,42.7392],"type":"Point"}
}