{
  "type": "Feature",
  "properties": {
    "iso:country":"US",
    "name:eng_x_preferred":[
        "Arbor Crossing"
    ],
    "name:eng_x_variant":[
        "Arbor Xing"
    ],
    "qs:gn_adm0_cc":"US",
    "qs:gn_fcode":"PPLX",
    "qs:gn_local":4049979,
    "qs:gn_nam_loc":"Birmingham, Jefferson, Alabama, US",
    "qs:gn_namadm1":"AL",
    "qs:gn_name":"Arbor Crossing",
    "qs:local_max":5643,
    "qs:local_sum":38742,
    "qs:localhoods":77,
    "qs:name":"Arbor Crossing",
    "qs:name_adm0":"United States",
    "qs:name_adm1":"Alabama",
    "qs:name_adm2":"Jefferson",
    "qs:name_local":"Birmingham",
    "qs:photo_max":181,
    "qs:photo_sum":203,
    "qs:placetype":"Suburb",
    "qs:quad_count":5,
    "qs:woe_adm0":23424977,
    "qs:woe_adm1":2347559,
    "qs:woe_adm2":12587523,
    "qs:woe_lau":0,
    "qs:woe_local":2364559,
    "qs:woe_ver":"7.10.0",
    "wof:name":"Arbor Crossing",
    "wof:placetype":"neighbourhood",
    "wof:population":2849,
    "zs:blockids":[
        10730144041051,
        10730144041047,
        10730129155036,
        10730129155018,
        10730129155028,
        10730144043007,
        10730144041056,
        10730129155014,
        10730144043017,
        10730129155034,
        10730129155016,
        10730129141022,
        10730144043009,
        10730144043002,
        10730129141028,
        10730144043008,
        10730129155032,
        10730144041057,
        10730144041016,
        10730129141038,
        10730144043016,
        10730129155030,
        10730144042007,
        10730129141027,
        10730129141040,
        10730129153000,
        10730129141042,
        10730129155015,
        10730129141025,
        10730129155020,
        10730144043001,
        10730144041048,
        10730144043000,
        10730129141039,
        10730144041013,
        10730144043006,
        10730144041054,
        10730129141045,
        10730144041055,
        10730129141029,
        10730144042000,
        10730129155029,
        10730144041049,
        10730144043003,
        10730129155035,
        10730129155025,
        10730129151014,
        10730129155021,
        10730129155033,
        10730144043012,
        10730144043010,
        10730144043004,
        10730129155024,
        10730129141026,
        10730129141041,
        10730129155031,
        10730129141024,
        10730144041050,
        10730129155023,
        10730129155017,
        10730129155022,
        10730144042008,
        10730129153002,
        10730129155002,
        10730144041052,
        10730129141048,
        10730129141047,
        10730129153001,
        10730129155027,
        10730144042006,
        10730144041053,
        10730129153004,
        10730129141044,
        10730144043005,
        10730129155019,
        10730144043011,
        10730129141043
    ],
    "zs:housing10":1320,
    "zs:pop10":2849
},
  "geometry": {"coordinates":[-86.819885,33.43774],"type":"Point"}
}