{
  "type": "Feature",
  "properties": {
    "gn:admin1_code":"OH",
    "gn:admin2_code":"77",
    "gn:admin3_code":"57302.0",
    "gn:asciiname":"Eastowne Mobile Home Estates",
    "gn:country_code":"US",
    "gn:dem":219,
    "gn:elevation":"220.0",
    "gn:feature_class":"P",
    "gn:feature_code":"PPL",
    "gn:name":"Eastowne Mobile Home Estates",
    "gn:population":0,
    "gn:timezone":"America/New_York",
    "iso:country":"US",
    "wof:name":"Eastowne Mobile Home Estates",
    "wof:placetype":"campus"
},
  "geometry": {"coordinates":[-82.60361,41.24917],"type":"Point"}
}