{
  "type": "Feature",
  "properties": {
    "iso:country":"US",
    "name:deu_x_preferred":[
        "PanAmSat"
    ],
    "name:eng_x_preferred":[
        "PanAmSat"
    ],
    "name:fas_x_preferred":[
        "\u067e\u0627\u0646\u200c\u0627\u0645\u200c\u0633\u062a"
    ],
    "name:fra_x_preferred":[
        "PanAmSat"
    ],
    "name:glg_x_preferred":[
        "PanAmSat"
    ],
    "name:heb_x_preferred":[
        "PanAmSat"
    ],
    "name:jpn_x_preferred":[
        "\u30d1\u30f3\u30ca\u30e0\u30b5\u30c3\u30c8"
    ],
    "name:nld_x_preferred":[
        "PanAmSat"
    ],
    "name:por_x_preferred":[
        "PanAmSat"
    ],
    "wd:wordcount":617,
    "wof:name":"PanAmSat",
    "wof:placetype":"neighbourhood",
    "zs:area_m":101116.459008,
    "zs:blockids":[
        61110003021026
    ],
    "zs:housing10":0,
    "zs:label":"PanAmSat",
    "zs:pop10":0
},
  "geometry": {"coordinates":[-118.899518,34.399434],"type":"Point"}
}