{
  "type": "Feature",
  "properties": {
    "gn:admin1_code":"NC",
    "gn:admin2_code":"183.0",
    "gn:admin3_code":"91772.0",
    "gn:asciiname":"Alexanger Place",
    "gn:country_code":"US",
    "gn:dem":119,
    "gn:feature_class":"P",
    "gn:feature_code":"PPL",
    "gn:name":"Alexanger Place",
    "gn:population":0,
    "gn:timezone":"America/New_York",
    "iso:country":"US",
    "wof:name":"Alexanger Place",
    "wof:placetype":"locality"
},
  "geometry": {"coordinates":[-78.77351999999998,35.91359],"type":"Point"}
}