{
  "type": "Feature",
  "properties": {
    "gn:admin1_code":"TX",
    "gn:admin2_code":"61",
    "gn:asciiname":"Graham Colonia",
    "gn:country_code":"US",
    "gn:dem":14,
    "gn:elevation":"9.0",
    "gn:feature_class":"P",
    "gn:feature_code":"PPL",
    "gn:name":"Graham Colonia",
    "gn:population":0,
    "gn:timezone":"America/Chicago",
    "iso:country":"US",
    "wof:name":"Graham Colonia",
    "wof:placetype":"locality"
},
  "geometry": {"coordinates":[-97.60916,26.10647],"type":"Point"}
}