{
  "type": "Feature",
  "properties": {
    "gn:admin1_code":"AL",
    "gn:admin2_code":"117.0",
    "gn:asciiname":"Straven",
    "gn:country_code":"US",
    "gn:dem":155,
    "gn:elevation":"156.0",
    "gn:feature_class":"P",
    "gn:feature_code":"PPL",
    "gn:name":"Straven",
    "gn:population":0,
    "gn:timezone":"America/Chicago",
    "iso:country":"US",
    "name:eng_x_preferred":[
        "Straven"
    ],
    "name:und_x_variant":[
        "Stravon",
        "Birmont"
    ],
    "wof:name":"Straven",
    "wof:placetype":"locality"
},
  "geometry": {"coordinates":[-86.88970999999999,33.21955999999999],"type":"Point"}
}