{
  "type": "Feature",
  "properties": {
    "gn:admin1_code":"OH",
    "gn:admin2_code":"113",
    "gn:admin3_code":"37912.0",
    "gn:asciiname":"Shady Acres Mobile Home Court",
    "gn:country_code":"US",
    "gn:dem":277,
    "gn:elevation":"280.0",
    "gn:feature_class":"P",
    "gn:feature_code":"PPL",
    "gn:name":"Shady Acres Mobile Home Court",
    "gn:population":0,
    "gn:timezone":"America/New_York",
    "iso:country":"US",
    "wof:name":"Shady Acres Mobile Home Court",
    "wof:placetype":"campus"
},
  "geometry": {"coordinates":[-84.39389,39.7325],"type":"Point"}
}