{
  "type": "Feature",
  "properties": {
    "gn:admin1_code":"VA",
    "gn:admin2_code":"57",
    "gn:asciiname":"Wildwood Beach",
    "gn:country_code":"US",
    "gn:dem":4,
    "gn:elevation":"6.0",
    "gn:feature_class":"P",
    "gn:feature_code":"PPL",
    "gn:name":"Wildwood Beach",
    "gn:population":0,
    "gn:timezone":"America/New_York",
    "iso:country":"US",
    "wof:name":"Wildwood Beach",
    "wof:placetype":"locality"
},
  "geometry": {"coordinates":[-76.74024,37.80653],"type":"Point"}
}