{
  "type": "Feature",
  "properties": {
    "gn:admin1_code":"AR",
    "gn:admin2_code":"129.0",
    "gn:asciiname":"Baker",
    "gn:country_code":"US",
    "gn:dem":369,
    "gn:elevation":"369.0",
    "gn:feature_class":"P",
    "gn:feature_code":"PPL",
    "gn:name":"Baker",
    "gn:population":0,
    "gn:timezone":"America/Chicago",
    "iso:country":"US",
    "name:als_x_preferred":[
        "B\u00e4cker"
    ],
    "name:ara_x_preferred":[
        "\u062e\u0628\u0627\u0632"
    ],
    "name:bar_x_preferred":[
        "Beck"
    ],
    "name:ben_x_preferred":[
        "\u09b0\u09c1\u099f\u09bf\u0995\u09be\u09b0"
    ],
    "name:bod_x_preferred":[
        "\u0f42\u0f7c\u0f0b\u0f62\u0f7a\u0f0b\u0f56\u0f5f\u0f7c\u0f0b\u0f58\u0f41\u0f53\u0f0d"
    ],
    "name:cat_x_preferred":[
        "Flequer"
    ],
    "name:ces_x_preferred":[
        "Peka\u0159"
    ],
    "name:dan_x_preferred":[
        "Bager"
    ],
    "name:deu_x_preferred":[
        "B\u00e4cker"
    ],
    "name:diq_x_preferred":[
        "F\u0131runci"
    ],
    "name:est_x_preferred":[
        "Pagar"
    ],
    "name:eus_x_preferred":[
        "Okin"
    ],
    "name:fas_x_preferred":[
        "\u0646\u0627\u0646\u0648\u0627"
    ],
    "name:fra_x_preferred":[
        "Boulanger"
    ],
    "name:fry_x_preferred":[
        "Bakker"
    ],
    "name:gle_x_preferred":[
        "B\u00e1ic\u00e9ir"
    ],
    "name:heb_x_preferred":[
        "\u05d0\u05d5\u05e4\u05d4"
    ],
    "name:hrv_x_preferred":[
        "Pekar"
    ],
    "name:hun_x_preferred":[
        "P\u00e9k"
    ],
    "name:hye_x_preferred":[
        "\u0540\u0561\u0581\u0569\u0578\u0582\u056d"
    ],
    "name:ind_x_preferred":[
        "Tukang roti"
    ],
    "name:ita_x_preferred":[
        "Panettiere"
    ],
    "name:jpn_x_preferred":[
        "\u88fd\u30d1\u30f3"
    ],
    "name:kor_x_preferred":[
        "\uc81c\ube75\uc0ac"
    ],
    "name:lat_x_preferred":[
        "Pistor"
    ],
    "name:lmo_x_preferred":[
        "Prestinee"
    ],
    "name:myv_x_preferred":[
        "\u041a\u0448\u0438\u043f\u0430\u043d\u0438\u0446\u044f"
    ],
    "name:nld_x_preferred":[
        "Bakker"
    ],
    "name:nor_x_preferred":[
        "Baker"
    ],
    "name:oci_x_preferred":[
        "Forni\u00e8r"
    ],
    "name:pcd_x_preferred":[
        "Boulindger"
    ],
    "name:pdc_x_preferred":[
        "Beckerschapp"
    ],
    "name:pol_x_preferred":[
        "Piekarz"
    ],
    "name:por_x_preferred":[
        "Padeiro"
    ],
    "name:que_x_preferred":[
        "T'anta ruraq"
    ],
    "name:rus_x_preferred":[
        "\u041f\u0435\u043a\u0430\u0440\u044c"
    ],
    "name:scn_x_preferred":[
        "Furnaru"
    ],
    "name:spa_x_preferred":[
        "Panadero"
    ],
    "name:srp_x_preferred":[
        "\u041f\u0435\u043a\u0430\u0440"
    ],
    "name:swe_x_preferred":[
        "Bagare"
    ],
    "name:tur_x_preferred":[
        "F\u0131r\u0131nc\u0131"
    ],
    "name:ukr_x_preferred":[
        "\u041f\u0435\u043a\u0430\u0440"
    ],
    "name:zho_x_preferred":[
        "\u9eb5\u5305\u5e2b"
    ],
    "wof:name":"Baker",
    "wof:placetype":"locality"
},
  "geometry": {"coordinates":[-92.59766,35.91369],"type":"Point"}
}