{
  "type": "Feature",
  "properties": {
    "gn:admin1_code":"AL",
    "gn:admin2_code":"9.0",
    "gn:asciiname":"Royal",
    "gn:country_code":"US",
    "gn:dem":226,
    "gn:elevation":"230.0",
    "gn:feature_class":"P",
    "gn:feature_code":"PPL",
    "gn:name":"Royal",
    "gn:population":0,
    "gn:timezone":"America/Chicago",
    "iso:country":"US",
    "name:cat_x_preferred":[
        "Royal"
    ],
    "name:ceb_x_preferred":[
        "Royal"
    ],
    "name:deu_x_preferred":[
        "Royal"
    ],
    "name:fin_x_preferred":[
        "Royal"
    ],
    "name:fra_x_preferred":[
        "Royal"
    ],
    "name:heb_x_preferred":[
        "\u05e8\u05d5\u05d9\u05d0\u05dc"
    ],
    "name:ita_x_preferred":[
        "Royal"
    ],
    "name:jpn_x_preferred":[
        "\u30ed\u30a4\u30e4\u30eb"
    ],
    "name:nld_x_preferred":[
        "Royal"
    ],
    "name:pol_x_preferred":[
        "Royal"
    ],
    "name:por_x_preferred":[
        "Royal"
    ],
    "name:ron_x_preferred":[
        "Royal"
    ],
    "name:rus_x_preferred":[
        "Royal"
    ],
    "name:srp_x_preferred":[
        "\u0420\u043e\u0458\u0430\u043b"
    ],
    "name:swe_x_preferred":[
        "Royal"
    ],
    "name:urd_x_preferred":[
        "\u0631\u0627\u0626\u0644"
    ],
    "name:vol_x_preferred":[
        "Royal"
    ],
    "wof:name":"Royal",
    "wof:placetype":"locality"
},
  "geometry": {"coordinates":[-86.50220999999998,34.07204],"type":"Point"}
}