{
  "type": "Feature",
  "properties": {
    "iso:country":"US",
    "wof:name":"NECKO",
    "wof:placetype":"neighbourhood"
},
  "geometry": {"coordinates":[-83.01841293307068,39.99142368123895],"type":"Point"}
}