{
  "type": "Feature",
  "properties": {
    "gn:admin1_code":"AZ",
    "gn:admin2_code":"19.0",
    "gn:asciiname":"Ak Chut Vaya",
    "gn:country_code":"US",
    "gn:dem":743,
    "gn:elevation":"742.0",
    "gn:feature_class":"P",
    "gn:feature_code":"PPL",
    "gn:name":"Ak Chut Vaya",
    "gn:population":0,
    "gn:timezone":"America/Phoenix",
    "iso:country":"US",
    "wof:name":"Ak Chut Vaya",
    "wof:placetype":"locality"
},
  "geometry": {"coordinates":[-111.80956,31.63064],"type":"Point"}
}