{
  "type": "Feature",
  "properties": {
    "iso:country":"US",
    "name:eng_x_preferred":[
        "Villa San Miguel"
    ],
    "qs:gn_adm0_cc":"US",
    "qs:gn_local":5490263,
    "qs:gn_nam_loc":"Santa Fe, Santa Fe, New Mexico, US",
    "qs:gn_namadm1":"NM",
    "qs:local_max":8972,
    "qs:local_sum":19509,
    "qs:localhoods":43,
    "qs:name":"Villa San Miguel",
    "qs:name_adm0":"United States",
    "qs:name_adm1":"New Mexico",
    "qs:name_adm2":"Santa Fe",
    "qs:name_local":"Santa Fe",
    "qs:photo_max":181,
    "qs:photo_sum":205,
    "qs:placetype":"Suburb",
    "qs:quad_count":8,
    "qs:woe_adm0":23424977,
    "qs:woe_adm1":2347590,
    "qs:woe_adm2":12589305,
    "qs:woe_lau":0,
    "qs:woe_local":2488867,
    "qs:woe_ver":"7.10.0",
    "wof:name":"Villa San Miguel",
    "wof:placetype":"neighbourhood",
    "wof:population":3021,
    "zs:blockids":[
        350490011031002,
        350490011022004,
        350490011021014,
        350490011021005,
        350490011021011,
        350490011051006,
        350490011051001,
        350490011021003,
        350490011051008,
        350490011051009,
        350490011031010,
        350490011021013,
        350490011031001,
        350490011051010,
        350490011051021,
        350490011021012,
        350490011021009,
        350490011051000,
        350490011031003,
        350490011031004,
        350490011021007,
        350490011021001,
        350490011021006,
        350490011021015,
        350490011021000,
        350490011021002,
        350490011021010,
        350490011031007,
        350490011031009,
        350490011022003,
        350490011031000,
        350490011022007,
        350490011021008,
        350490011021004,
        350490011031008
    ],
    "zs:housing10":1680,
    "zs:pop10":3021
},
  "geometry": {"coordinates":[-105.95074,35.649707],"type":"Point"}
}