{
  "type": "Feature",
  "properties": {
    "gn:admin1_code":"GA",
    "gn:admin2_code":"135",
    "gn:asciiname":"Timber Trace",
    "gn:country_code":"US",
    "gn:dem":294,
    "gn:elevation":"292.0",
    "gn:feature_class":"P",
    "gn:feature_code":"PPL",
    "gn:name":"Timber Trace",
    "gn:population":0,
    "gn:timezone":"America/New_York",
    "iso:country":"US",
    "wof:name":"Timber Trace",
    "wof:placetype":"locality"
},
  "geometry": {"coordinates":[-84.05297,33.83344],"type":"Point"}
}