{
  "type": "Feature",
  "properties": {
    "gn:admin1_code":"FL",
    "gn:admin2_code":"35.0",
    "gn:asciiname":"Bimini",
    "gn:country_code":"US",
    "gn:dem":10,
    "gn:elevation":"6.0",
    "gn:feature_class":"P",
    "gn:feature_code":"PPL",
    "gn:name":"Bimini",
    "gn:population":0,
    "gn:timezone":"America/New_York",
    "iso:country":"US",
    "name:hun_x_preferred":[
        "Bimini"
    ],
    "name:zho_x_preferred":[
        "\u6bd4\u7c73\u5c3c"
    ],
    "wof:name":"Bimini",
    "wof:placetype":"locality"
},
  "geometry": {"coordinates":[-81.35562,29.48247],"type":"Point"}
}