{
  "type": "Feature",
  "properties": {
    "gn:country":"US",
    "gn:fcode":"PPL",
    "gn:population":0,
    "iso:country":"US",
    "name:bul_x_preferred":[
        "\u041d\u044e\u0431\u0440\u0438\u0434\u0436"
    ],
    "name:ceb_x_preferred":[
        "Newbridge"
    ],
    "name:ces_x_preferred":[
        "Newbridge"
    ],
    "name:cym_x_preferred":[
        "Newbridge"
    ],
    "name:deu_x_preferred":[
        "Newbridge"
    ],
    "name:eng_x_preferred":[
        "Newbridge"
    ],
    "name:fra_x_preferred":[
        "Newbridge"
    ],
    "name:kor_x_preferred":[
        "\ub274\ube0c\ub9ac\uc9c0"
    ],
    "name:nld_x_preferred":[
        "Newbridge"
    ],
    "name:pol_x_preferred":[
        "Newbridge"
    ],
    "name:slk_x_preferred":[
        "Newbridge"
    ],
    "name:swe_x_preferred":[
        "Newbridge"
    ],
    "name:und_x_variant":[
        "New Bridge"
    ],
    "qs_pg:aaroncc":"US",
    "qs_pg:gn_country":"US",
    "qs_pg:gn_fcode":"PPL",
    "qs_pg:gn_pop":0,
    "qs_pg:name":"Newbridge",
    "qs_pg:name_adm0":"United States",
    "qs_pg:name_adm1":"Pennsylvania",
    "qs_pg:photos":3,
    "qs_pg:photos_1k":1,
    "qs_pg:photos_9k":1,
    "qs_pg:photos_9r":1,
    "qs_pg:photos_all":3,
    "qs_pg:photos_sr":1,
    "qs_pg:pop_sr":0,
    "qs_pg:qs_pg_placetype":"neighbourhood",
    "qs_pg:qs_pg_placetype_gp":"Suburb",
    "qs_pg:woe_adm0":23424977,
    "woe:adm0_id":23424977,
    "woe:name_adm0":"United States",
    "woe:name_adm1":"Pennsylvania",
    "woe:placetype":"Suburb",
    "wof:name":"Newbridge",
    "wof:placetype":"neighbourhood",
    "wof:population":245
},
  "geometry": {"coordinates":[-77.72638000000001,40.14675],"type":"Point"}
}