{
  "type": "Feature",
  "properties": {
    "gn:admin1_code":"VA",
    "gn:admin2_code":"157",
    "gn:asciiname":"Laurel Mills",
    "gn:country_code":"US",
    "gn:dem":125,
    "gn:elevation":"122.0",
    "gn:feature_class":"P",
    "gn:feature_code":"PPL",
    "gn:name":"Laurel Mills",
    "gn:population":0,
    "gn:timezone":"America/New_York",
    "iso:country":"US",
    "name:eng_x_preferred":[
        "Laurel Mills"
    ],
    "name:und_x_variant":[
        "Laurel Hills",
        "Roberts's Mill"
    ],
    "wof:name":"Laurel Mills",
    "wof:placetype":"locality"
},
  "geometry": {"coordinates":[-78.08915999999998,38.64818],"type":"Point"}
}