{
  "type": "Feature",
  "properties": {
    "gn:admin1_code":"DE",
    "gn:admin2_code":"5.0",
    "gn:asciiname":"Bossard Property",
    "gn:country_code":"US",
    "gn:dem":13,
    "gn:elevation":"10.0",
    "gn:feature_class":"P",
    "gn:feature_code":"PPL",
    "gn:name":"Bossard Property",
    "gn:population":0,
    "gn:timezone":"America/New_York",
    "iso:country":"US",
    "wof:name":"Bossard Property",
    "wof:placetype":"locality"
},
  "geometry": {"coordinates":[-75.63271,38.65178],"type":"Point"}
}