{
  "type": "Feature",
  "properties": {
    "gn:admin1_code":"UT",
    "gn:admin2_code":"39.0",
    "gn:asciiname":"Hill Top",
    "gn:country_code":"US",
    "gn:dem":1966,
    "gn:elevation":"1964.0",
    "gn:feature_class":"P",
    "gn:feature_code":"PPL",
    "gn:name":"Hill Top",
    "gn:population":0,
    "gn:timezone":"America/Denver",
    "iso:country":"US",
    "name:deu_x_preferred":[
        "Hill Top"
    ],
    "name:pol_x_preferred":[
        "Hill Top"
    ],
    "wof:name":"Hill Top",
    "wof:placetype":"locality"
},
  "geometry": {"coordinates":[-111.47019,39.71468],"type":"Point"}
}