{
  "type": "Feature",
  "properties": {
    "gn:admin1_code":"TN",
    "gn:admin2_code":"145.0",
    "gn:asciiname":"Anglers Cove",
    "gn:country_code":"US",
    "gn:dem":240,
    "gn:elevation":"232.0",
    "gn:feature_class":"P",
    "gn:feature_code":"PPL",
    "gn:name":"Anglers Cove",
    "gn:population":0,
    "gn:timezone":"America/New_York",
    "iso:country":"US",
    "wof:name":"Anglers Cove",
    "wof:placetype":"locality"
},
  "geometry": {"coordinates":[-84.53188,35.82035],"type":"Point"}
}