{
  "type": "Feature",
  "properties": {
    "gn:admin1_code":"NC",
    "gn:admin2_code":"29",
    "gn:admin3_code":"93044.0",
    "gn:asciiname":"Johnsons Corner",
    "gn:country_code":"US",
    "gn:dem":6,
    "gn:elevation":"3.0",
    "gn:feature_class":"P",
    "gn:feature_code":"PPL",
    "gn:name":"Johnsons Corner",
    "gn:population":0,
    "gn:timezone":"America/New_York",
    "iso:country":"US",
    "wof:name":"Johnsons Corner",
    "wof:placetype":"locality"
},
  "geometry": {"coordinates":[-76.29855000000001,36.4346],"type":"Point"}
}