{
  "type": "Feature",
  "properties": {
    "gn:admin1_code":"NC",
    "gn:admin2_code":"19",
    "gn:admin3_code":"92324.0",
    "gn:asciiname":"Hooper Hill",
    "gn:country_code":"US",
    "gn:dem":13,
    "gn:elevation":"13.0",
    "gn:feature_class":"P",
    "gn:feature_code":"PPL",
    "gn:name":"Hooper Hill",
    "gn:population":0,
    "gn:timezone":"America/New_York",
    "iso:country":"US",
    "wof:name":"Hooper Hill",
    "wof:placetype":"locality"
},
  "geometry": {"coordinates":[-78.07555000000001,34.33017],"type":"Point"}
}