{
  "type": "Feature",
  "properties": {
    "gn:admin1_code":"OK",
    "gn:admin2_code":"25.0",
    "gn:asciiname":"Conrad",
    "gn:country_code":"US",
    "gn:dem":1196,
    "gn:elevation":"1198.0",
    "gn:feature_class":"P",
    "gn:feature_code":"PPL",
    "gn:name":"Conrad",
    "gn:population":0,
    "gn:timezone":"America/Chicago",
    "iso:country":"US",
    "name:cat_x_preferred":[
        "Conrad"
    ],
    "name:ceb_x_preferred":[
        "Conrad"
    ],
    "name:ces_x_preferred":[
        "Conrad"
    ],
    "name:deu_x_preferred":[
        "Conrad"
    ],
    "name:fin_x_preferred":[
        "Conrad"
    ],
    "name:fra_x_preferred":[
        "Conrad"
    ],
    "name:heb_x_preferred":[
        "\u05e7\u05d5\u05e0\u05e8\u05d3"
    ],
    "name:hun_x_preferred":[
        "Conrad"
    ],
    "name:ita_x_preferred":[
        "Conrad"
    ],
    "name:kor_x_preferred":[
        "\ucf58\ub798\ub4dc"
    ],
    "name:nld_x_preferred":[
        "Conrad"
    ],
    "name:pol_x_preferred":[
        "Conrad"
    ],
    "name:por_x_preferred":[
        "Conrad"
    ],
    "name:spa_x_preferred":[
        "Conrad"
    ],
    "name:swe_x_preferred":[
        "Conrad"
    ],
    "name:vol_x_preferred":[
        "Conrad"
    ],
    "wof:name":"Conrad",
    "wof:placetype":"locality"
},
  "geometry": {"coordinates":[-102.37351,36.6153],"type":"Point"}
}