{
  "type": "Feature",
  "properties": {
    "gn:country":"US",
    "gn:fcode":"PPL",
    "gn:population":0,
    "iso:country":"US",
    "name:deu_x_preferred":[
        "West Newton"
    ],
    "name:eng_x_preferred":[
        "West Newton"
    ],
    "name:fra_x_preferred":[
        "West Newton"
    ],
    "name:jpn_x_preferred":[
        "\u30a6\u30a7\u30b9\u30c8\u30fb\u30cb\u30e5\u30fc\u30c8\u30f3"
    ],
    "name:zho_x_preferred":[
        "\u897f\u725b\u9813\u5340"
    ],
    "qs_pg:aaroncc":"US",
    "qs_pg:gn_country":"US",
    "qs_pg:gn_fcode":"PPL",
    "qs_pg:gn_pop":0,
    "qs_pg:name":"West Newton",
    "qs_pg:name_adm0":"United States",
    "qs_pg:name_adm1":"Massachusetts",
    "qs_pg:photos":214,
    "qs_pg:photos_1k":43,
    "qs_pg:photos_9k":1,
    "qs_pg:photos_9r":4,
    "qs_pg:photos_all":214,
    "qs_pg:photos_sr":4,
    "qs_pg:pop_sr":0,
    "qs_pg:qs_pg_placetype":"locality",
    "qs_pg:qs_pg_placetype_gp":"Town",
    "qs_pg:woe_adm0":23424977,
    "woe:adm0_id":23424977,
    "woe:name_adm0":"United States",
    "woe:name_adm1":"Massachusetts",
    "woe:placetype":"Town",
    "wof:name":"West Newton",
    "wof:placetype":"locality"
},
  "geometry": {"coordinates":[-71.23283000000001,42.3501],"type":"Point"}
}