{
  "type": "Feature",
  "properties": {
    "gn:admin1_code":"ID",
    "gn:admin2_code":"73",
    "gn:asciiname":"Riddle",
    "gn:country_code":"US",
    "gn:dem":1636,
    "gn:elevation":"1636.0",
    "gn:feature_class":"P",
    "gn:feature_code":"PPL",
    "gn:name":"Riddle",
    "gn:population":0,
    "gn:timezone":"America/Boise",
    "iso:country":"US",
    "name:fas_x_preferred":[
        "\u0631\u06cc\u062f\u0644"
    ],
    "wof:name":"Riddle",
    "wof:placetype":"locality"
},
  "geometry": {"coordinates":[-116.11038000000001,42.18684],"type":"Point"}
}