{
  "type": "Feature",
  "properties": {
    "gn:admin1_code":"GA",
    "gn:admin2_code":"63.0",
    "gn:asciiname":"Mundys Mill",
    "gn:country_code":"US",
    "gn:dem":258,
    "gn:elevation":"257.0",
    "gn:feature_class":"P",
    "gn:feature_code":"PPL",
    "gn:name":"Mundys Mill",
    "gn:population":0,
    "gn:timezone":"America/New_York",
    "iso:country":"US",
    "wof:name":"Mundys Mill",
    "wof:placetype":"locality"
},
  "geometry": {"coordinates":[-84.38937,33.49010999999999],"type":"Point"}
}