{
  "type": "Feature",
  "properties": {
    "gn:admin1_code":"OH",
    "gn:admin2_code":"153.0",
    "gn:asciiname":"Forest Lake Estates",
    "gn:country_code":"US",
    "gn:dem":335,
    "gn:elevation":"331.0",
    "gn:feature_class":"P",
    "gn:feature_code":"PPL",
    "gn:name":"Forest Lake Estates",
    "gn:population":0,
    "gn:timezone":"America/New_York",
    "iso:country":"US",
    "wof:name":"Forest Lake Estates",
    "wof:placetype":"locality"
},
  "geometry": {"coordinates":[-81.4954,40.9267],"type":"Point"}
}