{
  "type": "Feature",
  "properties": {
    "gn:admin1_code":"NJ",
    "gn:admin2_code":"33.0",
    "gn:admin3_code":"10610.0",
    "gn:asciiname":"Biddles Landing",
    "gn:country_code":"US",
    "gn:dem":10,
    "gn:elevation":"3.0",
    "gn:feature_class":"P",
    "gn:feature_code":"PPL",
    "gn:name":"Biddles Landing",
    "gn:population":0,
    "gn:timezone":"America/New_York",
    "iso:country":"US",
    "wof:name":"Biddles Landing",
    "wof:placetype":"locality"
},
  "geometry": {"coordinates":[-75.46547,39.67567],"type":"Point"}
}