{
  "type": "Feature",
  "properties": {
    "gn:country":"US",
    "gn:fcode":"PPL",
    "gn:population":0,
    "iso:country":"US",
    "name:ceb_x_preferred":[
        "Blackwell"
    ],
    "name:ces_x_preferred":[
        "Blackwell"
    ],
    "name:deu_x_preferred":[
        "Blackwell"
    ],
    "name:fra_x_preferred":[
        "Blackwell"
    ],
    "name:ita_x_preferred":[
        "Blackwell"
    ],
    "name:jpn_x_preferred":[
        "\u30d6\u30e9\u30c3\u30af\u30a6\u30a7\u30eb"
    ],
    "name:nds_x_preferred":[
        "Blackwell"
    ],
    "name:nld_x_preferred":[
        "Blackwell"
    ],
    "name:pol_x_preferred":[
        "Blackwell"
    ],
    "name:por_x_preferred":[
        "Blackwell"
    ],
    "name:rus_x_preferred":[
        "\u0411\u043b\u044d\u043a\u0443\u044d\u043b\u043b"
    ],
    "name:srp_x_preferred":[
        "\u0411\u043b\u0435\u043a\u0432\u0435\u043b"
    ],
    "name:swe_x_preferred":[
        "Blackwell"
    ],
    "name:ukr_x_preferred":[
        "\u0411\u043b\u0435\u043a\u0432\u0435\u043b\u043b"
    ],
    "name:vol_x_preferred":[
        "Blackwell"
    ],
    "qs_pg:aaroncc":"US",
    "qs_pg:gn_country":"US",
    "qs_pg:gn_fcode":"PPL",
    "qs_pg:gn_pop":0,
    "qs_pg:name":"Blackwell",
    "qs_pg:name_adm0":"United States",
    "qs_pg:name_adm1":"North Carolina",
    "qs_pg:photos":27,
    "qs_pg:photos_1k":5,
    "qs_pg:photos_9k":1,
    "qs_pg:photos_9r":2,
    "qs_pg:photos_all":27,
    "qs_pg:photos_sr":2,
    "qs_pg:pop_sr":0,
    "qs_pg:qs_pg_placetype":"locality",
    "qs_pg:qs_pg_placetype_gp":"Town",
    "qs_pg:woe_adm0":23424977,
    "woe:adm0_id":23424977,
    "woe:name_adm0":"United States",
    "woe:name_adm1":"North Carolina",
    "woe:placetype":"Town",
    "wof:name":"Blackwell",
    "wof:placetype":"locality"
},
  "geometry": {"coordinates":[-79.46362999999999,36.44264],"type":"Point"}
}