{
  "type": "Feature",
  "properties": {
    "gn:admin1_code":"NC",
    "gn:admin2_code":"37",
    "gn:admin3_code":"91428.0",
    "gn:asciiname":"Haywood",
    "gn:country_code":"US",
    "gn:dem":78,
    "gn:elevation":"75.0",
    "gn:feature_class":"P",
    "gn:feature_code":"PPL",
    "gn:name":"Haywood",
    "gn:population":0,
    "gn:timezone":"America/New_York",
    "iso:country":"US",
    "name:eng_x_preferred":[
        "Haywood"
    ],
    "name:und_x_variant":[
        "Lyons",
        "Haywoodsborough"
    ],
    "name:vol_x_preferred":[
        "Haywood"
    ],
    "wof:name":"Haywood",
    "wof:placetype":"locality"
},
  "geometry": {"coordinates":[-79.0639,35.62015],"type":"Point"}
}