{
  "type": "Feature",
  "properties": {
    "iso:country":"US",
    "qs_pg:aaroncc":"US",
    "qs_pg:name":"San Carlos Contract Branch",
    "qs_pg:name_adm0":"United States",
    "qs_pg:name_adm1":"Florida",
    "qs_pg:photos":44,
    "qs_pg:photos_1k":9,
    "qs_pg:photos_9k":1,
    "qs_pg:photos_9r":2,
    "qs_pg:photos_all":44,
    "qs_pg:photos_sr":2,
    "qs_pg:pop_sr":0,
    "qs_pg:qs_pg_placetype":"locality",
    "qs_pg:qs_pg_placetype_gp":"Town",
    "qs_pg:woe_adm0":23424977,
    "woe:adm0_id":23424977,
    "woe:name_adm0":"United States",
    "woe:name_adm1":"Florida",
    "woe:placetype":"Town",
    "wof:name":"San Carlos Contract Branch",
    "wof:placetype":"locality"
},
  "geometry": {"coordinates":[-81.912989,26.501297],"type":"Point"}
}