{
  "type": "Feature",
  "properties": {
    "gn:admin1_code":"KY",
    "gn:admin2_code":"45",
    "gn:asciiname":"Phil",
    "gn:country_code":"US",
    "gn:dem":237,
    "gn:elevation":"237.0",
    "gn:feature_class":"P",
    "gn:feature_code":"PPL",
    "gn:name":"Phil",
    "gn:population":0,
    "gn:timezone":"America/New_York",
    "iso:country":"US",
    "wof:name":"Phil",
    "wof:placetype":"locality"
},
  "geometry": {"coordinates":[-84.95356,37.21535],"type":"Point"}
}