{
  "type": "Feature",
  "properties": {
    "gn:admin1_code":"VA",
    "gn:admin2_code":"5",
    "gn:asciiname":"Clifdale",
    "gn:country_code":"US",
    "gn:dem":553,
    "gn:elevation":"536.0",
    "gn:feature_class":"P",
    "gn:feature_code":"PPL",
    "gn:name":"Clifdale",
    "gn:population":0,
    "gn:timezone":"America/New_York",
    "iso:country":"US",
    "wof:name":"Clifdale",
    "wof:placetype":"locality"
},
  "geometry": {"coordinates":[-80.01478,37.68068],"type":"Point"}
}