{
  "type": "Feature",
  "properties": {
    "gn:admin1_code":"AR",
    "gn:admin2_code":"111.0",
    "gn:admin3_code":"92229.0",
    "gn:asciiname":"Joyland",
    "gn:country_code":"US",
    "gn:dem":64,
    "gn:elevation":"65.0",
    "gn:feature_class":"P",
    "gn:feature_code":"PPL",
    "gn:name":"Joyland",
    "gn:population":0,
    "gn:timezone":"America/Chicago",
    "iso:country":"US",
    "name:ces_x_preferred":[
        "Joyland"
    ],
    "name:ita_x_preferred":[
        "Joyland"
    ],
    "wof:name":"Joyland",
    "wof:placetype":"locality"
},
  "geometry": {"coordinates":[-90.44898999999999,35.47425],"type":"Point"}
}