{
  "type": "Feature",
  "properties": {
    "gn:admin1_code":"CA",
    "gn:admin2_code":"77.0",
    "gn:asciiname":"Bardi",
    "gn:country_code":"US",
    "gn:dem":12,
    "gn:elevation":"16.0",
    "gn:feature_class":"P",
    "gn:feature_code":"PPL",
    "gn:name":"Bardi",
    "gn:population":0,
    "gn:timezone":"America/Los_Angeles",
    "iso:country":"US",
    "name:ceb_x_preferred":[
        "Bardi"
    ],
    "name:deu_x_preferred":[
        "Bardi"
    ],
    "name:eng_x_preferred":[
        "Bardi"
    ],
    "name:fra_x_preferred":[
        "Bardi"
    ],
    "name:glg_x_preferred":[
        "Bardi"
    ],
    "name:hye_x_preferred":[
        "\u0532\u0561\u0580\u0564\u056b"
    ],
    "name:ita_x_preferred":[
        "Bardi"
    ],
    "name:jpn_x_preferred":[
        "\u30d0\u30eb\u30c7\u30a3"
    ],
    "name:nld_x_preferred":[
        "Bardi"
    ],
    "name:pol_x_preferred":[
        "Bardi"
    ],
    "name:slv_x_preferred":[
        "Bardi"
    ],
    "name:swe_x_preferred":[
        "Bardi"
    ],
    "name:und_x_variant":[
        "Weston"
    ],
    "name:uzb_x_preferred":[
        "Bardi"
    ],
    "name:vie_x_preferred":[
        "Bardi"
    ],
    "wof:name":"Bardi",
    "wof:placetype":"locality"
},
  "geometry": {"coordinates":[-121.16522000000001,37.76465],"type":"Point"}
}