{
  "type": "Feature",
  "properties": {
    "gn:admin1_code":"OH",
    "gn:admin2_code":"25",
    "gn:admin3_code":"28224.0",
    "gn:asciiname":"Utopia",
    "gn:country_code":"US",
    "gn:dem":154,
    "gn:elevation":"151.0",
    "gn:feature_class":"P",
    "gn:feature_code":"PPL",
    "gn:name":"Utopia",
    "gn:population":0,
    "gn:timezone":"America/New_York",
    "iso:country":"US",
    "name:eng_x_preferred":[
        "Utopia"
    ],
    "name:spa_x_preferred":[
        "Colonia Utop\u00eda"
    ],
    "name:swe_x_preferred":[
        "Utopia"
    ],
    "name:und_x_variant":[
        "South Utopia"
    ],
    "name:vol_x_preferred":[
        "Utopia"
    ],
    "wof:name":"Utopia",
    "wof:placetype":"locality"
},
  "geometry": {"coordinates":[-84.05714999999999,38.77618],"type":"Point"}
}