{
  "type": "Feature",
  "properties": {
    "gn:admin1_code":"UT",
    "gn:admin2_code":"35.0",
    "gn:asciiname":"American Towers Condominium",
    "gn:country_code":"US",
    "gn:dem":1321,
    "gn:elevation":"1309.0",
    "gn:feature_class":"P",
    "gn:feature_code":"PPL",
    "gn:name":"American Towers Condominium",
    "gn:population":0,
    "gn:timezone":"America/Denver",
    "iso:country":"US",
    "wof:name":"American Towers Condominium",
    "wof:placetype":"locality"
},
  "geometry": {"coordinates":[-111.89243999999999,40.7655],"type":"Point"}
}