{
  "type": "Feature",
  "properties": {
    "gn:admin1_code":"NY",
    "gn:admin2_code":"5.0",
    "gn:asciiname":"Castle Hill Houses",
    "gn:country_code":"US",
    "gn:dem":13,
    "gn:elevation":"9.0",
    "gn:feature_class":"P",
    "gn:feature_code":"PPL",
    "gn:name":"Castle Hill Houses",
    "gn:population":0,
    "gn:timezone":"America/New_York",
    "iso:country":"US",
    "wof:name":"Castle Hill Houses",
    "wof:placetype":"locality"
},
  "geometry": {"coordinates":[-73.84971999999998,40.81861],"type":"Point"}
}