{
  "type": "Feature",
  "properties": {
    "gn:country":"US",
    "gn:fcode":"PPL",
    "gn:population":0,
    "iso:country":"US",
    "name:cat_x_preferred":[
        "Ramsey"
    ],
    "name:ceb_x_preferred":[
        "Ramsey"
    ],
    "name:ces_x_preferred":[
        "Ramsey"
    ],
    "name:deu_x_preferred":[
        "Ramsey"
    ],
    "name:eng_x_preferred":[
        "Ramsey"
    ],
    "name:eus_x_preferred":[
        "Ramsey"
    ],
    "name:fas_x_preferred":[
        "\u0631\u0645\u0632\u06cc"
    ],
    "name:fin_x_preferred":[
        "Ramsey"
    ],
    "name:fra_x_preferred":[
        "Ramsey"
    ],
    "name:heb_x_preferred":[
        "\u05e8\u05de\u05d6\u05d9"
    ],
    "name:ita_x_preferred":[
        "Ramsey"
    ],
    "name:nds_x_preferred":[
        "Ramsey"
    ],
    "name:nld_x_preferred":[
        "Ramsey"
    ],
    "name:pol_x_preferred":[
        "Ramsey"
    ],
    "name:por_x_preferred":[
        "Ramsey"
    ],
    "name:rus_x_preferred":[
        "\u0420\u0430\u043c\u0437\u0430\u0439"
    ],
    "name:slk_x_preferred":[
        "Ramsey"
    ],
    "name:spa_x_preferred":[
        "Ramsey"
    ],
    "name:srp_x_preferred":[
        "\u0420\u0435\u043c\u0437\u0438"
    ],
    "name:swa_x_preferred":[
        "Ramsey"
    ],
    "name:swe_x_preferred":[
        "Ramsey"
    ],
    "name:ukr_x_preferred":[
        "\u0420\u0435\u043c\u0441\u0456"
    ],
    "name:urd_x_preferred":[
        "\u0631\u06cc\u0645\u0633\u06cc"
    ],
    "name:vol_x_preferred":[
        "Ramsey"
    ],
    "qs_pg:aaroncc":"US",
    "qs_pg:gn_country":"US",
    "qs_pg:gn_fcode":"PPL",
    "qs_pg:gn_pop":0,
    "qs_pg:name":"Ramsey",
    "qs_pg:name_adm0":"United States",
    "qs_pg:name_adm1":"Virginia",
    "qs_pg:photos":2,
    "qs_pg:photos_1k":1,
    "qs_pg:photos_9k":1,
    "qs_pg:photos_9r":1,
    "qs_pg:photos_all":2,
    "qs_pg:photos_sr":1,
    "qs_pg:pop_sr":0,
    "qs_pg:qs_pg_placetype":"neighbourhood",
    "qs_pg:qs_pg_placetype_gp":"Suburb",
    "qs_pg:woe_adm0":23424977,
    "woe:adm0_id":23424977,
    "woe:name_adm0":"United States",
    "woe:name_adm1":"Virginia",
    "woe:placetype":"Suburb",
    "wof:name":"Ramsey",
    "wof:placetype":"neighbourhood",
    "wof:population":155
},
  "geometry": {"coordinates":[-82.59488,36.9401],"type":"Point"}
}