{
  "type": "Feature",
  "properties": {
    "iso:country":"US",
    "name:eng_x_preferred":[
        "South Highlands"
    ],
    "name:eng_x_variant":[
        "South Eastern Highlands"
    ],
    "name:spa_x_preferred":[
        "Tierras altas del Sudeste"
    ],
    "name:zho_x_preferred":[
        "\u6771\u5357\u9ad8\u5730"
    ],
    "wd:wordcount":1575,
    "wof:name":"South Highlands",
    "wof:placetype":"neighbourhood",
    "zs:area_m":39445.471909,
    "zs:blockids":[
        130210126003032,
        130210129001019,
        130210126003031
    ],
    "zs:housing10":0,
    "zs:label":"South Highlands",
    "zs:pop10":0
},
  "geometry": {"coordinates":[-83.667811,32.789934],"type":"Point"}
}