{
  "type": "Feature",
  "properties": {
    "gn:admin1_code":"OH",
    "gn:admin2_code":"127.0",
    "gn:admin3_code":"51520.0",
    "gn:asciiname":"Buckingham",
    "gn:country_code":"US",
    "gn:dem":228,
    "gn:elevation":"225.0",
    "gn:feature_class":"P",
    "gn:feature_code":"PPL",
    "gn:name":"Buckingham",
    "gn:population":0,
    "gn:timezone":"America/New_York",
    "iso:country":"US",
    "name:ara_x_preferred":[
        "\u0628\u0627\u0643\u0646\u063a\u0647\u0627\u0645"
    ],
    "name:azb_x_preferred":[
        "\u0628\u0627\u06a9\u06cc\u0646\u0642\u0647\u0627\u0645"
    ],
    "name:bar_x_preferred":[
        "Buckingham"
    ],
    "name:cat_x_preferred":[
        "Buckingham"
    ],
    "name:cym_x_preferred":[
        "Buckingham"
    ],
    "name:dan_x_preferred":[
        "Buckingham"
    ],
    "name:deu_x_preferred":[
        "Buckingham"
    ],
    "name:eng_x_preferred":[
        "Buckingham"
    ],
    "name:fas_x_preferred":[
        "\u0628\u0627\u06a9\u06cc\u0646\u06af\u0647\u0627\u0645"
    ],
    "name:fra_x_preferred":[
        "Buckingham"
    ],
    "name:gle_x_preferred":[
        "Buckingham"
    ],
    "name:glg_x_preferred":[
        "Buckingham"
    ],
    "name:ita_x_preferred":[
        "Buckingham"
    ],
    "name:lat_x_preferred":[
        "Buckinghamia"
    ],
    "name:nld_x_preferred":[
        "Buckingham"
    ],
    "name:nno_x_preferred":[
        "Buckingham"
    ],
    "name:nor_x_preferred":[
        "Buckingham"
    ],
    "name:pol_x_preferred":[
        "Buckingham"
    ],
    "name:por_x_preferred":[
        "Buckingham"
    ],
    "name:ron_x_preferred":[
        "Buckingham"
    ],
    "name:rus_x_preferred":[
        "\u0411\u0430\u043a\u0438\u043d\u0433\u0435\u043c"
    ],
    "name:spa_x_preferred":[
        "Buckingham"
    ],
    "name:swe_x_preferred":[
        "Buckingham"
    ],
    "name:und_x_variant":[
        "Comly"
    ],
    "name:urd_x_preferred":[
        "\u0628\u06a9\u0646\u06af\u06be\u0645"
    ],
    "name:vie_x_preferred":[
        "Buckingham"
    ],
    "name:vol_x_preferred":[
        "Buckingham"
    ],
    "name:zho_x_preferred":[
        "\u767d\u91d1\u6f22"
    ],
    "wof:name":"Buckingham",
    "wof:placetype":"locality"
},
  "geometry": {"coordinates":[-82.13764999999999,39.59174],"type":"Point"}
}