{
  "type": "Feature",
  "properties": {
    "gn:admin1_code":"WV",
    "gn:admin2_code":"61",
    "gn:asciiname":"Jakes Run",
    "gn:country_code":"US",
    "gn:dem":320,
    "gn:elevation":"308.0",
    "gn:feature_class":"P",
    "gn:feature_code":"PPL",
    "gn:name":"Jakes Run",
    "gn:population":0,
    "gn:timezone":"America/New_York",
    "iso:country":"US",
    "name:eng_x_preferred":[
        "Jakes Run"
    ],
    "name:fas_x_preferred":[
        "\u062c\u06cc\u06a9\u0633 \u0631\u0627\u0646"
    ],
    "name:und_x_variant":[
        "Statler Run"
    ],
    "name:urd_x_preferred":[
        "\u062c\u0627\u06a9\u0633 \u0631\u0646"
    ],
    "wof:name":"Jakes Run",
    "wof:placetype":"locality"
},
  "geometry": {"coordinates":[-80.17118000000001,39.65814],"type":"Point"}
}