{
  "type": "Feature",
  "properties": {
    "iso:country":"US",
    "name:ceb_x_preferred":[
        "Parkside"
    ],
    "name:deu_x_preferred":[
        "Parkside"
    ],
    "name:eng_x_preferred":[
        "Parkside"
    ],
    "name:swe_x_preferred":[
        "Parkside"
    ],
    "wof:name":"Parkside",
    "wof:placetype":"neighbourhood",
    "wof:population":6655,
    "zs:area_m":2269732.309043,
    "zs:blockids":[
        80010093221000,
        80010093221023,
        80010093221003,
        80010093271006,
        80010093222019,
        80010093222020,
        80010093045003,
        80010093045008,
        80010093162016,
        80010093162014,
        80010093162011,
        80010093221022,
        80010093221013,
        80010093162001,
        80010093222023,
        80010093221006,
        80010093271011,
        80010093221008,
        80010093221011,
        80010093162006,
        80010093271009,
        80010093162005,
        80010093221009,
        80010093162000,
        80010093271007,
        80010093221020,
        80010093222025,
        80010093221001,
        80010093221010,
        80010093272022,
        80010093221017,
        80010093221004,
        80010093222021,
        80010093222012,
        80010093222015,
        80010093271017,
        80010093222029,
        80010093222001,
        80010093222003,
        80010093222009,
        80010093221024,
        80010093221021,
        80010093221012,
        80010093221014,
        80010093045001,
        80010093221007,
        80010093222010,
        80010093222024,
        80010093222016,
        80010093222026,
        80010093221018,
        80010093045005,
        80010093162002,
        80010093045011,
        80010093222031,
        80010093222018,
        80010093222027,
        80010093221015,
        80010093271012,
        80010093271013,
        80010093271015,
        80010093222011,
        80010093272023,
        80010093222030,
        80010093222002,
        80010093222005,
        80010093222004,
        80010093045013,
        80010093221016,
        80010093222000,
        80010093222022,
        80010093221019,
        80010093221002,
        80010093271008,
        80010093222013,
        80010093272020,
        80010093045004,
        80010093045012,
        80010093161012,
        80010093222006,
        80010093222007,
        80010093162015,
        80010093222017,
        80010093222014,
        80010093221005,
        80010093162003,
        80010093222028,
        80010093222008,
        80010093271014,
        80010093045006,
        80010093272021,
        80010093272024,
        80010093045007
    ],
    "zs:housing10":2532,
    "zs:label":"Parkside",
    "zs:pop10":6655
},
  "geometry": {"coordinates":[-105.010598,39.879696],"type":"Point"}
}