{
  "type": "Feature",
  "properties": {
    "gn:elevation":61,
    "iso:country":"US",
    "name:eng_x_preferred":[
        "Memorial Heights"
    ],
    "name:eng_x_variant":[
        "Memorial Hts"
    ],
    "qs:gn_adm0_cc":"US",
    "qs:gn_fcode":"PPLX",
    "qs:gn_local":4076784,
    "qs:gn_namadm1":"AL",
    "qs:gn_name":"Memorial Heights",
    "qs:local_max":2993,
    "qs:local_sum":14433,
    "qs:localhoods":45,
    "qs:name":"Memorial Heights",
    "qs:name_adm0":"United States",
    "qs:name_adm1":"Alabama",
    "qs:name_adm2":"Montgomery",
    "qs:name_local":"Montgomery",
    "qs:photo_max":39,
    "qs:photo_sum":91,
    "qs:placetype":"Suburb",
    "qs:quad_count":6,
    "qs:woe_adm0":23424977,
    "qs:woe_adm1":2347559,
    "qs:woe_adm2":12587537,
    "qs:woe_lau":0,
    "qs:woe_local":2453369,
    "qs:woe_ver":"7.10.0",
    "wof:lang":[
        "eng"
    ],
    "wof:name":"Memorial Heights",
    "wof:placetype":"neighbourhood",
    "wof:population":4781,
    "zs:blockids":[
        11010024002006,
        11010030002043,
        11010030002052,
        11010030003008,
        11010024004001,
        11010011006003,
        11010024003005,
        11010024003006,
        11010024001010,
        11010024001011,
        11010030002033,
        11010030002050,
        11010024004009,
        11010030002046,
        11010060004019,
        11010030002045,
        11010030002035,
        11010030003003,
        11010030003009,
        11010024001012,
        11010024004005,
        11010011006001,
        11010024003011,
        11010024003008,
        11010024002004,
        11010024002002,
        11010060004009,
        11010030002048,
        11010030002042,
        11010011006007,
        11010060004026,
        11010024001008,
        11010030003007,
        11010024004007,
        11010030002047,
        11010024004000,
        11010024004006,
        11010024003001,
        11010024003009,
        11010024004008,
        11010024001009,
        11010024002005,
        11010011006006,
        11010030002023,
        11010011006008,
        11010024004003,
        11010024003000,
        11010061002002,
        11010024002009,
        11010024004010,
        11010061002001,
        11010011006005,
        11010030002032,
        11010060004018,
        11010030003002,
        11010060004020,
        11010011006002,
        11010024004002,
        11010030003001,
        11010024003004,
        11010030002038,
        11010030003006,
        11010024003010,
        11010024003007,
        11010030003000,
        11010030002037,
        11010024003002,
        11010024003003,
        11010030002049,
        11010030002044,
        11010030002051,
        11010030003010,
        11010030003005,
        11010010002036,
        11010024001007,
        11010060004036,
        11010030002036,
        11010030002034,
        11010030003004,
        11010024004004,
        11010024002007,
        11010024002008,
        11010024002001
    ],
    "zs:housing10":1949,
    "zs:pop10":4781
},
  "geometry": {"coordinates":[-86.344404,32.342472],"type":"Point"}
}