{
  "type": "Feature",
  "properties": {
    "gn:admin1_code":"FL",
    "gn:admin2_code":"57",
    "gn:asciiname":"Marys Woods",
    "gn:country_code":"US",
    "gn:dem":30,
    "gn:elevation":"17.0",
    "gn:feature_class":"P",
    "gn:feature_code":"PPL",
    "gn:name":"Marys Woods",
    "gn:population":0,
    "gn:timezone":"America/New_York",
    "iso:country":"US",
    "wof:name":"Marys Woods",
    "wof:placetype":"locality"
},
  "geometry": {"coordinates":[-82.2419,28.0822],"type":"Point"}
}