{
  "type": "Feature",
  "properties": {
    "gn:admin1_code":"OH",
    "gn:admin2_code":"99",
    "gn:admin3_code":"74124.0",
    "gn:asciiname":"J And H Mobile Home Park",
    "gn:country_code":"US",
    "gn:dem":341,
    "gn:elevation":"344.0",
    "gn:feature_class":"P",
    "gn:feature_code":"PPL",
    "gn:name":"J And H Mobile Home Park",
    "gn:population":0,
    "gn:timezone":"America/New_York",
    "iso:country":"US",
    "wof:name":"J And H Mobile Home Park",
    "wof:placetype":"campus"
},
  "geometry": {"coordinates":[-80.53028,40.90917],"type":"Point"}
}