{
  "type": "Feature",
  "properties": {
    "gn:elevation":143,
    "iso:country":"US",
    "name:bel_x_preferred":[
        "\u041c\u044e\u0440\u044d\u0439"
    ],
    "name:bul_x_preferred":[
        "\u041c\u044a\u0440\u0438"
    ],
    "name:cat_x_preferred":[
        "Murray"
    ],
    "name:ceb_x_preferred":[
        "Murray"
    ],
    "name:ces_x_preferred":[
        "Murray"
    ],
    "name:deu_x_preferred":[
        "Murray"
    ],
    "name:eng_x_preferred":[
        "Murray"
    ],
    "name:est_x_preferred":[
        "Murray"
    ],
    "name:fin_x_preferred":[
        "Murray"
    ],
    "name:fra_x_preferred":[
        "Murray"
    ],
    "name:ita_x_preferred":[
        "Murray"
    ],
    "name:kor_x_preferred":[
        "\uba38\ub9ac"
    ],
    "name:lav_x_preferred":[
        "Murray"
    ],
    "name:nld_x_preferred":[
        "Murray"
    ],
    "name:pol_x_preferred":[
        "Murray"
    ],
    "name:por_x_preferred":[
        "Murray"
    ],
    "name:ron_x_preferred":[
        "Murray"
    ],
    "name:rus_x_preferred":[
        "\u041c\u044e\u0440\u0440\u0435\u0439"
    ],
    "name:slk_x_preferred":[
        "Murray"
    ],
    "name:slv_x_preferred":[
        "Murray"
    ],
    "name:spa_x_preferred":[
        "Murray"
    ],
    "name:swe_x_preferred":[
        "Murray"
    ],
    "name:ukr_x_preferred":[
        "\u041c\u044e\u0440\u0440\u0435\u0439"
    ],
    "name:vol_x_preferred":[
        "Murray"
    ],
    "qs:gn_adm0_cc":"US",
    "qs:gn_fcode":"PPL",
    "qs:gn_local":5216710,
    "qs:gn_nam_loc":"Union, Lebanon, Pennsylvania, US",
    "qs:gn_namadm1":"PA",
    "qs:gn_name":"Murray",
    "qs:local_max":305,
    "qs:local_sum":399,
    "qs:localhoods":4,
    "qs:name":"Murray",
    "qs:name_adm0":"United States",
    "qs:name_adm1":"Pennsylvania",
    "qs:name_adm2":"Lebanon",
    "qs:name_local":"Union",
    "qs:photo_max":302,
    "qs:photo_sum":305,
    "qs:placetype":"Suburb",
    "qs:quad_count":3,
    "qs:woe_adm0":23424977,
    "qs:woe_adm1":2347597,
    "qs:woe_adm2":12589765,
    "qs:woe_lau":0,
    "qs:woe_local":28745622,
    "qs:woe_ver":"7.10.0",
    "wof:lang":[
        "eng"
    ],
    "wof:name":"Murray",
    "wof:placetype":"neighbourhood",
    "wof:population":109,
    "zs:blockids":[
        420750021001023,
        420750021001025,
        420750021001024,
        420750021001022,
        420750021001002,
        420750021001020,
        420750021001011,
        420750021001027,
        420750021001019
    ],
    "zs:housing10":56,
    "zs:pop10":109
},
  "geometry": {"coordinates":[-76.51276900000001,40.512704],"type":"Point"}
}