{
  "type": "Feature",
  "properties": {
    "iso:country":"US",
    "name:eng_x_preferred":[
        "H\u00e4lawa Ahupua`a"
    ],
    "wof:name":"H\u00e4lawa Ahupua`a",
    "wof:placetype":"neighbourhood",
    "zs:area_m":604355.456562,
    "zs:blockids":[
        150090317002092
    ],
    "zs:housing10":0,
    "zs:label":"H\u00e4lawa Ahupua`a",
    "zs:pop10":0
},
  "geometry": {"coordinates":[-156.79319599999999,21.170514],"type":"Point"}
}