{
  "type": "Feature",
  "properties": {
    "gn:admin1_code":"NM",
    "gn:admin2_code":"17",
    "gn:asciiname":"Hext Place",
    "gn:country_code":"US",
    "gn:dem":1538,
    "gn:elevation":"1539.0",
    "gn:feature_class":"P",
    "gn:feature_code":"PPL",
    "gn:name":"Hext Place",
    "gn:population":0,
    "gn:timezone":"America/Denver",
    "iso:country":"US",
    "wof:name":"Hext Place",
    "wof:placetype":"locality"
},
  "geometry": {"coordinates":[-108.92867,32.8159],"type":"Point"}
}