{
  "type": "Feature",
  "properties": {
    "gn:admin1_code":"WY",
    "gn:admin2_code":"7.0",
    "gn:asciiname":"Oil Springs",
    "gn:country_code":"US",
    "gn:dem":2015,
    "gn:elevation":"2012.0",
    "gn:feature_class":"P",
    "gn:feature_code":"PPL",
    "gn:name":"Oil Springs",
    "gn:population":0,
    "gn:timezone":"America/Denver",
    "iso:country":"US",
    "name:ceb_x_preferred":[
        "Oil Springs"
    ],
    "name:fra_x_preferred":[
        "Oil Springs"
    ],
    "name:swe_x_preferred":[
        "Oil Springs"
    ],
    "wof:name":"Oil Springs",
    "wof:placetype":"locality"
},
  "geometry": {"coordinates":[-106.26752,41.99108],"type":"Point"}
}