{
  "type": "Feature",
  "properties": {
    "gn:admin1_code":"FL",
    "gn:admin2_code":"57",
    "gn:asciiname":"Armenia Gardens",
    "gn:country_code":"US",
    "gn:dem":24,
    "gn:elevation":"12.0",
    "gn:feature_class":"P",
    "gn:feature_code":"PPL",
    "gn:name":"Armenia Gardens",
    "gn:population":0,
    "gn:timezone":"America/New_York",
    "iso:country":"US",
    "wof:name":"Armenia Gardens",
    "wof:placetype":"locality"
},
  "geometry": {"coordinates":[-82.48560000000001,27.9915],"type":"Point"}
}