{
  "type": "Feature",
  "properties": {
    "iso:country":"US",
    "name:arz_x_preferred":[
        "\u0633\u0643\u0648\u062a\u0649 \u0647\u064a\u0644"
    ],
    "name:ast_x_preferred":[
        "Scotti Hill"
    ],
    "name:cat_x_preferred":[
        "Scotti Hill"
    ],
    "name:cym_x_preferred":[
        "Scotti Hill"
    ],
    "name:dan_x_preferred":[
        "Scotti Hill"
    ],
    "name:deu_x_preferred":[
        "Scotti Hill"
    ],
    "name:eng_x_preferred":[
        "Scotty Hills"
    ],
    "name:eng_x_variant":[
        "Scotti Hill"
    ],
    "name:fin_x_preferred":[
        "Scotti Hill"
    ],
    "name:fra_x_preferred":[
        "Scotti Hill"
    ],
    "name:gle_x_preferred":[
        "Scotti Hill"
    ],
    "name:ita_x_preferred":[
        "Scotti Hill"
    ],
    "name:jpn_x_preferred":[
        "\u30b9\u30b3\u30c3\u30c6\u30a3\u30fb\u30d2\u30eb"
    ],
    "name:nld_x_preferred":[
        "Scotti Hill"
    ],
    "name:nno_x_preferred":[
        "Scotti Hill"
    ],
    "name:nob_x_preferred":[
        "Scotti Hill"
    ],
    "name:pap_x_preferred":[
        "Scotti Hill"
    ],
    "name:por_x_preferred":[
        "Scotti Hill"
    ],
    "name:slv_x_preferred":[
        "Scotti Hill"
    ],
    "name:spa_x_preferred":[
        "Scotti Hill"
    ],
    "name:sqi_x_preferred":[
        "Scotti Hill"
    ],
    "name:swe_x_preferred":[
        "Scotti Hill"
    ],
    "name:tam_x_preferred":[
        "\u0bb8\u0bcd\u0b95\u0bbe\u0b9f\u0bcd \u0bb9\u0bbf\u0bb2\u0bcd"
    ],
    "name:vie_x_preferred":[
        "Scotti Hill"
    ],
    "wd:wordcount":466,
    "wof:name":"Scotty Hills",
    "wof:placetype":"neighbourhood",
    "wof:population":1581,
    "zs:area_m":2483662.706448,
    "zs:blockids":[
        370510021003002,
        370510021001015,
        370510007011000,
        370510021003015,
        370510007012009,
        370510021003022,
        370510007012013,
        370510021003013,
        370510021001017,
        370510021003021,
        370510007011009,
        370510007011010,
        370510007012014,
        370510021001016,
        370510021001018,
        370510007011001,
        370510007012005,
        370510021003012,
        370510007012015,
        370510021003003,
        370510021003014,
        370510007012007,
        370510007012006,
        370510007012011,
        370510021001026,
        370510021001025,
        370510021001019
    ],
    "zs:housing10":665,
    "zs:label":"Scotty Hills",
    "zs:pop10":1581
},
  "geometry": {"coordinates":[-78.93425999999999,35.067672],"type":"Point"}
}