{
  "type": "Feature",
  "properties": {
    "gn:admin1_code":"NM",
    "gn:admin2_code":"47.0",
    "gn:asciiname":"Trout Springs",
    "gn:country_code":"US",
    "gn:dem":2163,
    "gn:elevation":"2153.0",
    "gn:feature_class":"P",
    "gn:feature_code":"PPL",
    "gn:name":"Trout Springs",
    "gn:population":0,
    "gn:timezone":"America/Denver",
    "iso:country":"US",
    "wof:name":"Trout Springs",
    "wof:placetype":"locality"
},
  "geometry": {"coordinates":[-105.34057,35.65976],"type":"Point"}
}