{
  "type": "Feature",
  "properties": {
    "gn:admin1_code":"VA",
    "gn:admin2_code":"83",
    "gn:asciiname":"Ridgeway",
    "gn:country_code":"US",
    "gn:dem":197,
    "gn:elevation":"195.0",
    "gn:feature_class":"P",
    "gn:feature_code":"PPL",
    "gn:name":"Ridgeway",
    "gn:population":0,
    "gn:timezone":"America/New_York",
    "iso:country":"US",
    "name:ara_x_preferred":[
        "\u0631\u064a\u062f\u062c\u0648\u0627\u064a"
    ],
    "name:cat_x_preferred":[
        "Ridgeway"
    ],
    "name:ceb_x_preferred":[
        "Ridgeway"
    ],
    "name:deu_x_preferred":[
        "Ridgeway"
    ],
    "name:fra_x_preferred":[
        "Ridgeway"
    ],
    "name:ita_x_preferred":[
        "Ridgeway"
    ],
    "name:nds_x_preferred":[
        "Ridgeway"
    ],
    "name:nld_x_preferred":[
        "Ridgeway"
    ],
    "name:pol_x_preferred":[
        "Ridgeway"
    ],
    "name:por_x_preferred":[
        "Ridgeway"
    ],
    "name:rus_x_preferred":[
        "\u0420\u0438\u0434\u0436\u0443\u044d\u0439"
    ],
    "name:srp_x_preferred":[
        "\u0420\u0438\u045f\u0432\u0435\u0458"
    ],
    "name:swe_x_preferred":[
        "Ridgeway"
    ],
    "name:vol_x_preferred":[
        "Ridgeway"
    ],
    "wof:name":"Ridgeway",
    "wof:placetype":"locality"
},
  "geometry": {"coordinates":[-79.14390999999998,36.8068],"type":"Point"}
}