{
  "type": "Feature",
  "properties": {
    "gn:admin1_code":"IL",
    "gn:admin2_code":"21",
    "gn:admin3_code":"4325.0",
    "gn:asciiname":"Clarksdale",
    "gn:country_code":"US",
    "gn:dem":192,
    "gn:elevation":"191.0",
    "gn:feature_class":"P",
    "gn:feature_code":"PPL",
    "gn:name":"Clarksdale",
    "gn:population":0,
    "gn:timezone":"America/Chicago",
    "iso:country":"US",
    "name:fas_x_preferred":[
        "\u06a9\u0644\u0627\u0631\u06a9\u0633\u200c\u062f\u06cc\u0644"
    ],
    "name:fra_x_preferred":[
        "Clarksdale"
    ],
    "name:urd_x_preferred":[
        "\u06a9\u0644\u0627\u0631\u06a9\u0633\u0688\u06cc\u0644"
    ],
    "name:vol_x_preferred":[
        "Clarksdale"
    ],
    "wof:name":"Clarksdale",
    "wof:placetype":"locality"
},
  "geometry": {"coordinates":[-89.36787,39.48977],"type":"Point"}
}