{
  "type": "Feature",
  "properties": {
    "iso:country":"US",
    "name:eng_x_preferred":[
        "Meadowbrook Heights"
    ],
    "wof:name":"Meadowbrook Heights",
    "wof:placetype":"neighbourhood",
    "wof:population":651,
    "zs:area_m":703077.226182,
    "zs:blockids":[
        510479305022008,
        510479305022050,
        510479305022006,
        510479305022002,
        510479305022048
    ],
    "zs:housing10":267,
    "zs:label":"Meadowbrook Heights",
    "zs:pop10":651
},
  "geometry": {"coordinates":[-78.004896,38.460331],"type":"Point"}
}