{
  "type": "Feature",
  "properties": {
    "gn:admin1_code":"TX",
    "gn:admin2_code":"225",
    "gn:asciiname":"Harrison Town",
    "gn:country_code":"US",
    "gn:dem":114,
    "gn:elevation":"113.0",
    "gn:feature_class":"P",
    "gn:feature_code":"PPL",
    "gn:name":"Harrison Town",
    "gn:population":0,
    "gn:timezone":"America/Chicago",
    "iso:country":"US",
    "wof:name":"Harrison Town",
    "wof:placetype":"locality"
},
  "geometry": {"coordinates":[-95.223,31.40129],"type":"Point"}
}