{
  "type": "Feature",
  "properties": {
    "gn:admin1_code":"WA",
    "gn:admin2_code":"9.0",
    "gn:asciiname":"Old Royal",
    "gn:country_code":"US",
    "gn:dem":66,
    "gn:elevation":"59.0",
    "gn:feature_class":"P",
    "gn:feature_code":"PPL",
    "gn:name":"Old Royal",
    "gn:population":0,
    "gn:timezone":"America/Los_Angeles",
    "iso:country":"US",
    "wof:name":"Old Royal",
    "wof:placetype":"locality"
},
  "geometry": {"coordinates":[-124.45855,48.17924],"type":"Point"}
}