{
  "type": "Feature",
  "properties": {
    "gn:admin1_code":"MI",
    "gn:admin2_code":"19.0",
    "gn:admin3_code":"44240.0",
    "gn:asciiname":"Chimney Corners Resort",
    "gn:country_code":"US",
    "gn:dem":191,
    "gn:elevation":"183.0",
    "gn:feature_class":"P",
    "gn:feature_code":"PPL",
    "gn:name":"Chimney Corners Resort",
    "gn:population":0,
    "gn:timezone":"America/Detroit",
    "iso:country":"US",
    "wof:name":"Chimney Corners Resort",
    "wof:placetype":"locality"
},
  "geometry": {"coordinates":[-86.20787,44.68972],"type":"Point"}
}