{
  "type": "Feature",
  "properties": {
    "iso:country":"US",
    "name:eng_x_preferred":[
        "Stoney Run"
    ],
    "qs_pg:aaroncc":"US",
    "qs_pg:name":"Stoney Run",
    "qs_pg:name_adm0":"United States",
    "qs_pg:name_adm1":"Virginia",
    "qs_pg:photos":27,
    "qs_pg:photos_1k":5,
    "qs_pg:photos_9k":1,
    "qs_pg:photos_9r":2,
    "qs_pg:photos_all":27,
    "qs_pg:photos_sr":2,
    "qs_pg:pop_sr":0,
    "qs_pg:qs_pg_placetype":"neighbourhood",
    "qs_pg:qs_pg_placetype_gp":"Suburb",
    "qs_pg:woe_adm0":23424977,
    "wof:name":"Stoney Run",
    "wof:placetype":"neighbourhood",
    "wof:population":2526,
    "zs:area_m":1651308.716935,
    "zs:blockids":[
        517000322251001,
        517000322251004,
        517000322251013,
        517000322251015,
        517000322251010,
        517000322251012,
        517000322251009,
        517000322251000,
        517000322242003,
        517000322242010,
        517000322251011,
        517000322251002,
        517000322251014,
        517000322251003,
        517000322242017,
        517000322242002,
        517000322242019,
        517000322242001,
        517000322242018,
        517000322242016,
        517000322261044,
        517000322251008,
        517000322242013,
        517000322242004,
        517000322242000,
        517000322242009,
        517000322242015,
        517000322242005
    ],
    "zs:housing10":1047,
    "zs:label":"Stoney Run",
    "zs:pop10":2526
},
  "geometry": {"coordinates":[-76.542863,37.139353],"type":"Point"}
}