{
  "type": "Feature",
  "properties": {
    "gn:admin1_code":"PA",
    "gn:admin2_code":"5.0",
    "gn:admin3_code":"63712.0",
    "gn:asciiname":"Charlestown",
    "gn:country_code":"US",
    "gn:dem":355,
    "gn:elevation":"345.0",
    "gn:feature_class":"P",
    "gn:feature_code":"PPL",
    "gn:name":"Charlestown",
    "gn:population":0,
    "gn:timezone":"America/New_York",
    "iso:country":"US",
    "name:bre_x_preferred":[
        "Charlestown"
    ],
    "name:cat_x_preferred":[
        "Charlestown"
    ],
    "name:ceb_x_preferred":[
        "Charlestown"
    ],
    "name:deu_x_preferred":[
        "Charlestown"
    ],
    "name:est_x_preferred":[
        "Charlestown"
    ],
    "name:eus_x_preferred":[
        "Charlestown"
    ],
    "name:fin_x_preferred":[
        "Charlestown"
    ],
    "name:fra_x_preferred":[
        "Charlestown"
    ],
    "name:hun_x_preferred":[
        "Charlestown"
    ],
    "name:ita_x_preferred":[
        "Charlestown"
    ],
    "name:jpn_x_preferred":[
        "\u30c1\u30e3\u30fc\u30eb\u30ba\u30bf\u30a6\u30f3"
    ],
    "name:kor_x_preferred":[
        "\ucc30\uc2a4\ud0c0\uc6b4"
    ],
    "name:mlg_x_preferred":[
        "Charlestown"
    ],
    "name:nld_x_preferred":[
        "Charlestown"
    ],
    "name:pol_x_preferred":[
        "Charlestown"
    ],
    "name:por_x_preferred":[
        "Charlestown"
    ],
    "name:rus_x_preferred":[
        "\u0427\u0430\u0440\u043b\u0441\u0442\u0430\u0443\u043d"
    ],
    "name:slv_x_preferred":[
        "Charlestown"
    ],
    "name:spa_x_preferred":[
        "Charlestown"
    ],
    "name:srp_x_preferred":[
        "\u0427\u0430\u0440\u043b\u0441\u0442\u0430\u0443\u043d"
    ],
    "name:swe_x_preferred":[
        "Charlestown"
    ],
    "name:ukr_x_preferred":[
        "\u0427\u0430\u0440\u043b\u0441\u0442\u0430\u0443\u043d"
    ],
    "name:urd_x_preferred":[
        "\u0686\u0627\u0631\u0644\u0633 \u0679\u0627\u0624\u0646"
    ],
    "name:vep_x_preferred":[
        "\u010carlstaun"
    ],
    "name:vol_x_preferred":[
        "Charlestown"
    ],
    "name:zho_x_preferred":[
        "\u67e5\u5c14\u65af\u6566"
    ],
    "wof:name":"Charlestown",
    "wof:placetype":"locality"
},
  "geometry": {"coordinates":[-79.25615000000001,40.96062],"type":"Point"}
}