{
  "type": "Feature",
  "properties": {
    "iso:country":"US",
    "name:eng_x_preferred":[
        "Windsor Forest"
    ],
    "wof:name":"Windsor Forest",
    "wof:placetype":"neighbourhood",
    "wof:population":1516,
    "zs:area_m":2146436.879992,
    "zs:blockids":[
        510950802061007,
        510950803013040,
        510950802061012,
        510950802061011,
        510950802061018,
        510950803013039,
        510950802061009,
        510950802061010,
        510950802061047,
        510950802061017,
        510950802061016,
        510950803013037,
        510950803013038,
        510950802061015,
        510950802061013,
        510950802061008,
        510950802062000
    ],
    "zs:housing10":618,
    "zs:label":"Windsor Forest",
    "zs:pop10":1516
},
  "geometry": {"coordinates":[-76.75985300000001,37.304334],"type":"Point"}
}