{
  "type": "Feature",
  "properties": {
    "gn:elevation":4,
    "iso:country":"US",
    "name:deu_x_preferred":[
        "Green Oaks"
    ],
    "name:eng_x_preferred":[
        "Green Oaks"
    ],
    "qs:gn_fcode":"PPLX",
    "qs:gn_local":0,
    "qs:gn_namadm1":"VA",
    "qs:gn_name":"Green Lakes",
    "qs:local_max":816,
    "qs:local_sum":10636,
    "qs:localhoods":48,
    "qs:name":"Green Oaks",
    "qs:name_adm0":"United States",
    "qs:name_adm1":"Virginia",
    "qs:name_adm2":"Newport News City",
    "qs:name_local":"Newport News",
    "qs:photo_max":53,
    "qs:photo_sum":153,
    "qs:placetype":"Suburb",
    "qs:quad_count":13,
    "qs:woe_adm0":23424977,
    "qs:woe_adm1":2347605,
    "qs:woe_adm2":12590390,
    "qs:woe_lau":0,
    "qs:woe_local":2459618,
    "qs:woe_ver":"7.10.0",
    "wd:wordcount":21,
    "wof:lang":[
        "eng"
    ],
    "wof:name":"Green Oaks",
    "wof:placetype":"neighbourhood",
    "wof:population":5635,
    "zs:blockids":[
        517000316013006,
        517000315001018,
        517000316013000,
        517000316022011,
        517000316013009,
        517000314001012,
        517000316023025,
        517000316014001,
        517000316013008,
        517000316014007,
        517000314001008,
        517000316014011,
        517000315001021,
        517000314001011,
        517000314001022,
        517000316011031,
        517000316011035,
        517000316013002,
        517000316014004,
        517000316014014,
        517000316011037,
        517000315001016,
        517000315001020,
        517000316022008,
        517000316011032,
        517000316011034,
        517000316012002,
        517000316012008,
        517000314001015,
        517000316014005,
        517000315001022,
        517000314001004,
        517000316012000,
        517000314001007,
        517000316012003,
        517000316013005,
        517000316011030,
        517000316014000,
        517000316011038,
        517000316013007,
        517000316012004,
        517000316021012,
        517000314001006,
        517000314001002,
        517000314001005,
        517000316013003,
        517000316012005,
        517000316014006,
        517000314001000,
        517000316022009,
        517000316012006,
        517000316014008,
        517000316013010,
        517000314001003,
        517000316014015,
        517000315001019,
        517000315001023,
        517000316023028,
        517000316013004,
        517000314001023,
        517000316014012,
        517000316014002,
        517000315001012,
        517000316021013,
        517000314001001,
        517000316011033,
        517000316012007,
        517000316012001,
        517000316013001,
        517000316014013,
        517000314001013,
        517000316014010,
        517000316014003
    ],
    "zs:housing10":2571,
    "zs:pop10":5635
},
  "geometry": {"coordinates":[-76.46503199999999,37.048962],"type":"Point"}
}