{
  "type": "Feature",
  "properties": {
    "gn:admin1_code":"KY",
    "gn:admin2_code":"163",
    "gn:asciiname":"Haysville",
    "gn:country_code":"US",
    "gn:dem":208,
    "gn:elevation":"210.0",
    "gn:feature_class":"P",
    "gn:feature_code":"PPL",
    "gn:name":"Haysville",
    "gn:population":0,
    "gn:timezone":"America/New_York",
    "iso:country":"US",
    "name:deu_x_preferred":[
        "Haysville"
    ],
    "name:eng_x_preferred":[
        "Haysville"
    ],
    "name:fra_x_preferred":[
        "Haysville"
    ],
    "name:ita_x_preferred":[
        "Haysville"
    ],
    "name:nld_x_preferred":[
        "Haysville"
    ],
    "name:pol_x_preferred":[
        "Haysville"
    ],
    "name:spa_x_preferred":[
        "Haysville"
    ],
    "name:swe_x_preferred":[
        "Haysville"
    ],
    "name:und_x_variant":[
        "Haynesville"
    ],
    "name:vol_x_preferred":[
        "Haysville"
    ],
    "wof:name":"Haysville",
    "wof:placetype":"locality"
},
  "geometry": {"coordinates":[-86.24247,37.9034],"type":"Point"}
}