{
  "type": "Feature",
  "properties": {
    "gn:admin1_code":"PA",
    "gn:admin2_code":"69.0",
    "gn:admin3_code":"5696.0",
    "gn:asciiname":"Marshbrook",
    "gn:country_code":"US",
    "gn:dem":373,
    "gn:elevation":"371.0",
    "gn:feature_class":"P",
    "gn:feature_code":"PPL",
    "gn:name":"Marshbrook",
    "gn:population":0,
    "gn:timezone":"America/New_York",
    "iso:country":"US",
    "name:bar_x_preferred":[
        "Marshbrook"
    ],
    "name:cym_x_preferred":[
        "Marshbrook"
    ],
    "name:pol_x_preferred":[
        "Marshbrook"
    ],
    "wof:name":"Marshbrook",
    "wof:placetype":"locality"
},
  "geometry": {"coordinates":[-75.67740999999999,41.6373],"type":"Point"}
}