{
  "type": "Feature",
  "properties": {
    "gn:admin1_code":"PA",
    "gn:admin2_code":"29",
    "gn:admin3_code":"83080.0",
    "gn:asciiname":"Kirby Woods",
    "gn:country_code":"US",
    "gn:dem":134,
    "gn:elevation":"133.0",
    "gn:feature_class":"P",
    "gn:feature_code":"PPL",
    "gn:name":"Kirby Woods",
    "gn:population":0,
    "gn:timezone":"America/New_York",
    "iso:country":"US",
    "wof:name":"Kirby Woods",
    "wof:placetype":"locality"
},
  "geometry": {"coordinates":[-75.60250000000001,39.9762],"type":"Point"}
}