{
  "type": "Feature",
  "properties": {
    "gn:admin1_code":"NE",
    "gn:admin2_code":"55.0",
    "gn:asciiname":"Rellers Park",
    "gn:country_code":"US",
    "gn:dem":349,
    "gn:elevation":"348.0",
    "gn:feature_class":"P",
    "gn:feature_code":"PPL",
    "gn:name":"Rellers Park",
    "gn:population":0,
    "gn:timezone":"America/Chicago",
    "iso:country":"US",
    "wof:name":"Rellers Park",
    "wof:placetype":"locality"
},
  "geometry": {"coordinates":[-96.30029999999999,41.3825],"type":"Point"}
}