{
  "type": "Feature",
  "properties": {
    "gn:admin1_code":"GA",
    "gn:admin2_code":"243.0",
    "gn:asciiname":"Carnegie",
    "gn:country_code":"US",
    "gn:dem":123,
    "gn:elevation":"120.0",
    "gn:feature_class":"P",
    "gn:feature_code":"PPL",
    "gn:name":"Carnegie",
    "gn:population":0,
    "gn:timezone":"America/New_York",
    "iso:country":"US",
    "name:bul_x_preferred":[
        "\u041a\u0430\u0440\u043d\u0435\u0433\u0438"
    ],
    "name:ceb_x_preferred":[
        "Carnegie"
    ],
    "name:dan_x_preferred":[
        "Carnegie"
    ],
    "name:deu_x_preferred":[
        "Carnegie"
    ],
    "name:eng_x_preferred":[
        "Carnegie"
    ],
    "name:fas_x_preferred":[
        "\u06a9\u0627\u0631\u0646\u06af\u06cc"
    ],
    "name:fin_x_preferred":[
        "Carnegie"
    ],
    "name:fra_x_preferred":[
        "Carnegie"
    ],
    "name:heb_x_preferred":[
        "\u05e7\u05e8\u05e0\u05d2\u05d9"
    ],
    "name:ita_x_preferred":[
        "Carnegie"
    ],
    "name:jpn_x_preferred":[
        "\u30ab\u30fc\u30cd\u30ae\u30fc"
    ],
    "name:kor_x_preferred":[
        "\uce74\ub124\uae30"
    ],
    "name:mlg_x_preferred":[
        "Carnegie"
    ],
    "name:nld_x_preferred":[
        "Carnegie"
    ],
    "name:nor_x_preferred":[
        "Carnegie"
    ],
    "name:pol_x_preferred":[
        "Carnegie"
    ],
    "name:por_x_preferred":[
        "Carnegie"
    ],
    "name:rus_x_preferred":[
        "\u041a\u0430\u0440\u043d\u0435\u0433\u0438"
    ],
    "name:spa_x_preferred":[
        "Carnegie"
    ],
    "name:srp_x_preferred":[
        "\u041a\u0430\u0440\u043d\u0435\u0433\u0438"
    ],
    "name:swe_x_preferred":[
        "Carnegie"
    ],
    "name:ukr_x_preferred":[
        "\u041a\u0430\u0440\u043d\u0435\u0491\u0456"
    ],
    "name:und_x_variant":[
        "Grubbs"
    ],
    "name:vol_x_preferred":[
        "Carnegie"
    ],
    "name:zho_x_preferred":[
        "\u5361\u5167\u57fa"
    ],
    "wof:name":"Carnegie",
    "wof:placetype":"locality"
},
  "geometry": {"coordinates":[-84.77909,31.64295],"type":"Point"}
}