{
  "type": "Feature",
  "properties": {
    "gn:admin1_code":"AR",
    "gn:admin2_code":"107.0",
    "gn:admin3_code":"90273.0",
    "gn:asciiname":"Kingtown",
    "gn:country_code":"US",
    "gn:dem":54,
    "gn:elevation":"55.0",
    "gn:feature_class":"P",
    "gn:feature_code":"PPL",
    "gn:name":"Kingtown",
    "gn:population":0,
    "gn:timezone":"America/Chicago",
    "iso:country":"US",
    "wof:name":"Kingtown",
    "wof:placetype":"locality"
},
  "geometry": {"coordinates":[-90.89149999999999,34.49677],"type":"Point"}
}