{
  "type": "Feature",
  "properties": {
    "gn:country":"US",
    "gn:fcode":"PPL",
    "gn:population":0,
    "iso:country":"US",
    "name:ara_x_preferred":[
        "\u0643\u0631\u0627\u064a\u063a"
    ],
    "name:azb_x_preferred":[
        "\u06a9\u0631\u06cc\u0642"
    ],
    "name:ben_x_preferred":[
        "\u0995\u09cd\u09b0\u09c7\u0997"
    ],
    "name:ell_x_preferred":[
        "\u039a\u03c1\u03b5\u03b3\u03ba"
    ],
    "name:eng_x_preferred":[
        "Craig"
    ],
    "name:fas_x_preferred":[
        "\u06a9\u0631\u06cc\u06af"
    ],
    "name:fra_x_preferred":[
        "Craig"
    ],
    "name:heb_x_preferred":[
        "\u05e7\u05e8\u05d9\u05d9\u05d2"
    ],
    "name:hin_x_preferred":[
        "\u0915\u094d\u0930\u0947\u0917"
    ],
    "name:ind_x_preferred":[
        "Craig"
    ],
    "name:jpn_x_preferred":[
        "\u30af\u30ec\u30a4\u30b0"
    ],
    "name:kor_x_preferred":[
        "\ud06c\ub808\uc774\uadf8"
    ],
    "name:rus_x_preferred":[
        "\u041a\u0440\u0435\u0439\u0433"
    ],
    "name:urd_x_preferred":[
        "\u06a9\u0631\u06cc\u06af\u060c \u0627\u0646\u0688\u06cc\u0627\u0646\u0627"
    ],
    "name:urd_x_variant":[
        "\u06a9\u0631\u06cc\u06af"
    ],
    "name:zho_x_preferred":[
        "\u514b\u96f7\u683c"
    ],
    "qs_pg:aaroncc":"US",
    "qs_pg:gn_country":"US",
    "qs_pg:gn_fcode":"PPL",
    "qs_pg:gn_pop":0,
    "qs_pg:name":"Craig",
    "qs_pg:name_adm0":"United States",
    "qs_pg:name_adm1":"Indiana",
    "qs_pg:photos":84,
    "qs_pg:photos_1k":17,
    "qs_pg:photos_9k":1,
    "qs_pg:photos_9r":3,
    "qs_pg:photos_all":84,
    "qs_pg:photos_sr":3,
    "qs_pg:pop_sr":0,
    "qs_pg:qs_pg_placetype":"locality",
    "qs_pg:qs_pg_placetype_gp":"Town",
    "qs_pg:woe_adm0":23424977,
    "woe:adm0_id":23424977,
    "woe:name_adm0":"United States",
    "woe:name_adm1":"Indiana",
    "woe:placetype":"Town",
    "wof:name":"Craig",
    "wof:placetype":"locality"
},
  "geometry": {"coordinates":[-85.51942,39.33227],"type":"Point"}
}