{
  "type": "Feature",
  "properties": {
    "gn:country":"US",
    "gn:fcode":"PPL",
    "gn:population":0,
    "iso:country":"US",
    "name:ara_x_preferred":[
        "\u0643\u0631\u0627\u064a\u063a"
    ],
    "name:azb_x_preferred":[
        "\u06a9\u0631\u06cc\u0642"
    ],
    "name:eng_x_preferred":[
        "Craig"
    ],
    "name:fas_x_preferred":[
        "\u06a9\u0631\u06cc\u06af"
    ],
    "name:fra_x_preferred":[
        "Craig"
    ],
    "name:urd_x_preferred":[
        "\u06a9\u0631\u06cc\u06af\u060c \u0627\u0646\u0688\u06cc\u0627\u0646\u0627"
    ],
    "name:urd_x_variant":[
        "\u06a9\u0631\u06cc\u06af"
    ],
    "qs_pg:aaroncc":"US",
    "qs_pg:gn_country":"US",
    "qs_pg:gn_fcode":"PPL",
    "qs_pg:gn_pop":0,
    "qs_pg:name":"Craig",
    "qs_pg:name_adm0":"United States",
    "qs_pg:name_adm1":"Indiana",
    "qs_pg:photos":84,
    "qs_pg:photos_1k":17,
    "qs_pg:photos_9k":1,
    "qs_pg:photos_9r":3,
    "qs_pg:photos_all":84,
    "qs_pg:photos_sr":3,
    "qs_pg:pop_sr":0,
    "qs_pg:qs_pg_placetype":"locality",
    "qs_pg:qs_pg_placetype_gp":"Town",
    "qs_pg:woe_adm0":23424977,
    "woe:adm0_id":23424977,
    "woe:name_adm0":"United States",
    "woe:name_adm1":"Indiana",
    "woe:placetype":"Town",
    "wof:name":"Craig",
    "wof:placetype":"locality"
},
  "geometry": {"coordinates":[-85.51942,39.33227],"type":"Point"}
}