{
  "type": "Feature",
  "properties": {
    "gn:admin1_code":"NY",
    "gn:admin2_code":"73.0",
    "gn:admin3_code":"49286.0",
    "gn:asciiname":"Brockville",
    "gn:country_code":"US",
    "gn:dem":144,
    "gn:elevation":"138.0",
    "gn:feature_class":"P",
    "gn:feature_code":"PPL",
    "gn:name":"Brockville",
    "gn:population":0,
    "gn:timezone":"America/New_York",
    "iso:country":"US",
    "name:ara_x_preferred":[
        "\u0628\u0631\u0648\u0643\u0641\u064a\u0644"
    ],
    "name:bel_x_preferred":[
        "\u0411\u0440\u043e\u043a\u0432\u0456\u043b"
    ],
    "name:ceb_x_preferred":[
        "Brockville"
    ],
    "name:deu_x_preferred":[
        "Brockville"
    ],
    "name:fas_x_preferred":[
        "\u0628\u0631\u0627\u06a9\u0648\u06cc\u0644"
    ],
    "name:fin_x_preferred":[
        "Brockville"
    ],
    "name:fra_x_preferred":[
        "Brockville"
    ],
    "name:heb_x_preferred":[
        "\u05d1\u05e8\u05d5\u05e7\u05d5\u05d5\u05d9\u05dc"
    ],
    "name:hun_x_preferred":[
        "Brockville"
    ],
    "name:ind_x_preferred":[
        "Brockville"
    ],
    "name:ita_x_preferred":[
        "Brockville"
    ],
    "name:jpn_x_preferred":[
        "\u30d6\u30ed\u30c3\u30af\u30d3\u30eb"
    ],
    "name:lit_x_preferred":[
        "Brukvailas"
    ],
    "name:pnb_x_preferred":[
        "\u0628\u0631\u0648\u06a9 \u0648\u0644\u06d2"
    ],
    "name:pol_x_preferred":[
        "Brockville"
    ],
    "name:por_x_preferred":[
        "Brockville"
    ],
    "name:rus_x_preferred":[
        "\u0411\u0440\u043e\u043a\u0432\u0438\u043b\u043b"
    ],
    "name:spa_x_preferred":[
        "Brockville"
    ],
    "name:sqi_x_preferred":[
        "Brockville"
    ],
    "name:srp_x_preferred":[
        "\u0411\u0440\u043e\u043a\u0432\u0438\u043b"
    ],
    "name:swe_x_preferred":[
        "Brockville"
    ],
    "name:tur_x_preferred":[
        "Brockville"
    ],
    "name:ukr_x_preferred":[
        "\u0411\u0440\u043e\u043a\u0432\u0456\u043b"
    ],
    "name:urd_x_preferred":[
        "\u0628\u0631\u0648\u06a9-\u0648\u0644"
    ],
    "name:vol_x_preferred":[
        "Brockville"
    ],
    "name:zho_x_preferred":[
        "\u5e03\u7f85\u514b\u7dad\u723e"
    ],
    "wof:name":"Brockville",
    "wof:placetype":"locality"
},
  "geometry": {"coordinates":[-78.09057,43.26117],"type":"Point"}
}