{
  "type": "Feature",
  "properties": {
    "iso:country":"US",
    "name:eng_x_preferred":[
        "South Attica"
    ],
    "name:eng_x_variant":[
        "S Attica"
    ],
    "qs:gn_adm0_cc":"US",
    "qs:gn_local":5107486,
    "qs:gn_nam_loc":"Attica, Wyoming, New York, US",
    "qs:gn_namadm1":"NY",
    "qs:local_max":1,
    "qs:local_sum":1,
    "qs:localhoods":1,
    "qs:name":"South Attica",
    "qs:name_adm0":"United States",
    "qs:name_adm1":"New York",
    "qs:name_adm2":"Wyoming",
    "qs:name_local":"Attica",
    "qs:photo_max":1,
    "qs:photo_sum":1,
    "qs:placetype":"Suburb",
    "qs:quad_count":1,
    "qs:woe_adm0":23424977,
    "qs:woe_adm1":2347591,
    "qs:woe_adm2":12589372,
    "qs:woe_lau":0,
    "qs:woe_local":2357171,
    "qs:woe_ver":"7.10.0",
    "wof:lang":[
        "eng"
    ],
    "wof:name":"South Attica",
    "wof:placetype":"neighbourhood"
},
  "geometry": {"coordinates":[-78.26385500000001,42.793385],"type":"Point"}
}