{
  "type": "Feature",
  "properties": {
    "gn:admin1_code":"NC",
    "gn:admin2_code":"171",
    "gn:admin3_code":"90984.0",
    "gn:asciiname":"Ash Hill",
    "gn:country_code":"US",
    "gn:dem":334,
    "gn:elevation":"334.0",
    "gn:feature_class":"P",
    "gn:feature_code":"PPL",
    "gn:name":"Ash Hill",
    "gn:population":0,
    "gn:timezone":"America/New_York",
    "iso:country":"US",
    "name:eng_x_preferred":[
        "Ash Hill"
    ],
    "name:und_x_variant":[
        "Ashhill"
    ],
    "name:vol_x_preferred":[
        "Ash Hill"
    ],
    "wof:name":"Ash Hill",
    "wof:placetype":"locality"
},
  "geometry": {"coordinates":[-80.57311999999997,36.39319],"type":"Point"}
}