{
  "type": "Feature",
  "properties": {
    "gn:admin1_code":"AL",
    "gn:admin2_code":"51",
    "gn:asciiname":"Falkner",
    "gn:country_code":"US",
    "gn:dem":201,
    "gn:elevation":"196.0",
    "gn:feature_class":"P",
    "gn:feature_code":"PPL",
    "gn:name":"Falkner",
    "gn:population":0,
    "gn:timezone":"America/Chicago",
    "iso:country":"US",
    "name:deu_x_preferred":[
        "Falkner"
    ],
    "name:ita_x_preferred":[
        "Falkner"
    ],
    "name:spa_x_preferred":[
        "Falkner"
    ],
    "wof:name":"Falkner",
    "wof:placetype":"locality"
},
  "geometry": {"coordinates":[-86.05024,32.69541],"type":"Point"}
}