{
  "type": "Feature",
  "properties": {
    "gn:admin1_code":"VA",
    "gn:admin2_code":"161",
    "gn:asciiname":"Manwaring Manor",
    "gn:country_code":"US",
    "gn:dem":368,
    "gn:elevation":"371.0",
    "gn:feature_class":"P",
    "gn:feature_code":"PPL",
    "gn:name":"Manwaring Manor",
    "gn:population":0,
    "gn:timezone":"America/New_York",
    "iso:country":"US",
    "wof:name":"Manwaring Manor",
    "wof:placetype":"locality"
},
  "geometry": {"coordinates":[-80.0117,37.20903],"type":"Point"}
}