{
  "type": "Feature",
  "properties": {
    "iso:country":"US",
    "name:ces_x_preferred":[
        "Lake Point Tower"
    ],
    "name:deu_x_preferred":[
        "Lake Point Tower"
    ],
    "name:eng_x_preferred":[
        "Lake Point"
    ],
    "name:eus_x_preferred":[
        "Lake Point Tower"
    ],
    "name:fin_x_preferred":[
        "Lake Point Tower"
    ],
    "name:fra_x_preferred":[
        "Lake Point Tower"
    ],
    "name:lit_x_preferred":[
        "Lake Point Tower"
    ],
    "name:nld_x_preferred":[
        "Lake Point Tower"
    ],
    "name:spa_x_preferred":[
        "Lake Point Tower"
    ],
    "name:zho_x_preferred":[
        "\u6e56\u5fc3\u5927\u5ec8"
    ],
    "wd:wordcount":1057,
    "wof:name":"Lake Point",
    "wof:placetype":"neighbourhood",
    "wof:population":57,
    "zs:area_m":760844.586717,
    "zs:blockids":[
        371830529031020,
        371830529031022
    ],
    "zs:housing10":30,
    "zs:label":"Lake Point",
    "zs:pop10":57
},
  "geometry": {"coordinates":[-78.618284,35.65985],"type":"Point"}
}