{
  "type": "Feature",
  "properties": {
    "gn:admin1_code":"KY",
    "gn:admin2_code":"95",
    "gn:asciiname":"Black Bottom",
    "gn:country_code":"US",
    "gn:dem":466,
    "gn:elevation":"460.0",
    "gn:feature_class":"P",
    "gn:feature_code":"PPL",
    "gn:name":"Black Bottom",
    "gn:population":0,
    "gn:timezone":"America/New_York",
    "iso:country":"US",
    "wof:name":"Black Bottom",
    "wof:placetype":"locality"
},
  "geometry": {"coordinates":[-83.08017,36.90898],"type":"Point"}
}