{
  "type": "Feature",
  "properties": {
    "gn:admin1_code":"FL",
    "gn:admin2_code":"13.0",
    "gn:asciiname":"Fisher Corner",
    "gn:country_code":"US",
    "gn:dem":36,
    "gn:elevation":"29.0",
    "gn:feature_class":"P",
    "gn:feature_code":"PPL",
    "gn:name":"Fisher Corner",
    "gn:population":0,
    "gn:timezone":"America/Chicago",
    "iso:country":"US",
    "name:zho_x_preferred":[
        "\u83f2\u820d\u723e\u89d2"
    ],
    "wof:name":"Fisher Corner",
    "wof:placetype":"locality"
},
  "geometry": {"coordinates":[-85.2152,30.38158],"type":"Point"}
}