{
  "type": "Feature",
  "properties": {
    "gn:admin1_code":"MS",
    "gn:admin2_code":"23.0",
    "gn:asciiname":"De Soto",
    "gn:country_code":"US",
    "gn:dem":66,
    "gn:elevation":"64.0",
    "gn:feature_class":"P",
    "gn:feature_code":"PPL",
    "gn:name":"De Soto",
    "gn:population":0,
    "gn:timezone":"America/Chicago",
    "iso:country":"US",
    "wof:name":"De Soto",
    "wof:placetype":"locality"
},
  "geometry": {"coordinates":[-88.71338,31.97376],"type":"Point"}
}