{
  "type": "Feature",
  "properties": {
    "gn:gn_country":"US",
    "gn:gn_fcode":"PPL",
    "gn:gn_pop":0,
    "iso:country":"US",
    "name:ceb_x_preferred":[
        "Webb"
    ],
    "name:ces_x_preferred":[
        "Webb"
    ],
    "name:deu_x_preferred":[
        "Webb"
    ],
    "name:fin_x_preferred":[
        "Webb"
    ],
    "name:fra_x_preferred":[
        "Webb"
    ],
    "name:ita_x_preferred":[
        "Webb"
    ],
    "name:jpn_x_preferred":[
        "\u30a6\u30a7\u30c3\u30d6"
    ],
    "name:kaz_x_preferred":[
        "\u0412\u0435\u0431\u0431"
    ],
    "name:nld_x_preferred":[
        "Webb"
    ],
    "name:pol_x_preferred":[
        "Webb"
    ],
    "name:por_x_preferred":[
        "Webb"
    ],
    "name:rus_x_preferred":[
        "\u0423\u044d\u0431\u0431"
    ],
    "name:spa_x_preferred":[
        "Webb"
    ],
    "name:swe_x_preferred":[
        "Webb"
    ],
    "name:ukr_x_preferred":[
        "\u0412\u0435\u0431\u0431"
    ],
    "name:vol_x_preferred":[
        "Webb"
    ],
    "qs_pg:aaroncc":"US",
    "qs_pg:gn_country":"US",
    "qs_pg:gn_fcode":"PPL",
    "qs_pg:gn_pop":0,
    "qs_pg:name":"Webb",
    "qs_pg:name_adm0":"United States",
    "qs_pg:name_adm1":"Arizona",
    "qs_pg:photos":70,
    "qs_pg:photos_1k":14,
    "qs_pg:photos_9k":1,
    "qs_pg:photos_9r":2,
    "qs_pg:photos_all":70,
    "qs_pg:photos_sr":2,
    "qs_pg:pop_sr":0,
    "qs_pg:qs_pg_placetype":"locality",
    "qs_pg:qs_pg_placetype_gp":"Town",
    "qs_pg:woe_adm0":23424977,
    "woe:adm0_id":23424977,
    "woe:name_adm0":"United States",
    "woe:name_adm1":"Arizona",
    "woe:placetype":"Town",
    "wof:name":"Webb",
    "wof:placetype":"locality"
},
  "geometry": {"coordinates":[-112.36709999999999,33.55254],"type":"Point"}
}