{
  "type": "Feature",
  "properties": {
    "gn:admin1_code":"AL",
    "gn:admin2_code":"73",
    "gn:asciiname":"Parker Heights",
    "gn:country_code":"US",
    "gn:dem":187,
    "gn:elevation":"188.0",
    "gn:feature_class":"P",
    "gn:feature_code":"PPL",
    "gn:name":"Parker Heights",
    "gn:population":0,
    "gn:timezone":"America/Chicago",
    "iso:country":"US",
    "wof:name":"Parker Heights",
    "wof:placetype":"locality"
},
  "geometry": {"coordinates":[-86.75138000000003,33.55622],"type":"Point"}
}