{
  "type": "Feature",
  "properties": {
    "iso:country":"US",
    "name:eng_x_preferred":[
        "Lake Mangonia"
    ],
    "qs:gn_adm0_cc":"US",
    "qs:gn_local":4177887,
    "qs:gn_nam_loc":"West Palm Beach, Palm Beach, Florida, US",
    "qs:gn_namadm1":"FL",
    "qs:local_max":6364,
    "qs:local_sum":19609,
    "qs:localhoods":20,
    "qs:name":"Lake Mangonia",
    "qs:name_adm0":"United States",
    "qs:name_adm1":"Florida",
    "qs:name_adm2":"Palm Beach",
    "qs:name_local":"West Palm Beach",
    "qs:photo_max":4,
    "qs:photo_sum":10,
    "qs:placetype":"Suburb",
    "qs:quad_count":5,
    "qs:woe_adm0":23424977,
    "qs:woe_adm1":2347568,
    "qs:woe_adm2":12587852,
    "qs:woe_lau":0,
    "qs:woe_local":2517521,
    "qs:woe_ver":"7.10.0",
    "wof:name":"Lake Mangonia",
    "wof:placetype":"neighbourhood",
    "wof:population":2679,
    "zs:blockids":[
        120990018021005,
        120990018022008,
        120990018021006,
        120990018022002,
        120990018023007,
        120990018022011,
        120990018021003,
        120990018023000,
        120990018022009,
        120990018021004,
        120990018022004,
        120990018023004,
        120990018022003,
        120990018022005,
        120990018023003,
        120990018021007,
        120990018023010,
        120990018022007,
        120990018022012,
        120990018022006,
        120990018021008,
        120990018022010
    ],
    "zs:housing10":2147,
    "zs:pop10":2679
},
  "geometry": {"coordinates":[-80.074585,26.741317],"type":"Point"}
}