{
  "type": "Feature",
  "properties": {
    "gn:admin1_code":"KY",
    "gn:admin2_code":"117",
    "gn:asciiname":"Oak Ridge",
    "gn:country_code":"US",
    "gn:dem":269,
    "gn:elevation":"271.0",
    "gn:feature_class":"P",
    "gn:feature_code":"PPL",
    "gn:name":"Oak Ridge",
    "gn:population":0,
    "gn:timezone":"America/New_York",
    "iso:country":"US",
    "name:cat_x_preferred":[
        "Oak Ridge"
    ],
    "name:ceb_x_preferred":[
        "Oak Ridge"
    ],
    "name:deu_x_preferred":[
        "Oak Ridge"
    ],
    "name:eus_x_preferred":[
        "Oak Ridge"
    ],
    "name:fra_x_preferred":[
        "Oak Ridge"
    ],
    "name:hun_x_preferred":[
        "Oak Ridge"
    ],
    "name:ita_x_preferred":[
        "Oak Ridge"
    ],
    "name:nld_x_preferred":[
        "Oak Ridge"
    ],
    "name:nor_x_preferred":[
        "Oak Ridge"
    ],
    "name:pol_x_preferred":[
        "Oak Ridge"
    ],
    "name:por_x_preferred":[
        "Oak Ridge"
    ],
    "name:rus_x_preferred":[
        "\u041e\u043a-\u0420\u0438\u0434\u0436"
    ],
    "name:spa_x_preferred":[
        "Oak Ridge"
    ],
    "name:srp_x_preferred":[
        "\u041e\u0443\u043a \u0420\u0438\u045f"
    ],
    "name:swe_x_preferred":[
        "Oak Ridge"
    ],
    "name:ukr_x_preferred":[
        "\u041e\u0443\u043a-\u0420\u0438\u0434\u0436"
    ],
    "name:vol_x_preferred":[
        "Oak Ridge"
    ],
    "wof:name":"Oak Ridge",
    "wof:placetype":"locality"
},
  "geometry": {"coordinates":[-84.50383000000002,38.96895],"type":"Point"}
}