{
  "type": "Feature",
  "properties": {
    "gn:country":"US",
    "gn:fcode":"PPL",
    "gn:population":0,
    "iso:country":"US",
    "name:eng_x_preferred":[
        "Seiad Valley"
    ],
    "name:fra_x_preferred":[
        "Seiad Valley"
    ],
    "name:tur_x_preferred":[
        "Seiad Valley"
    ],
    "name:vol_x_preferred":[
        "Seiad Valley"
    ],
    "name:zho_x_preferred":[
        "\u585e\u4e9e\u5fb7\u8c37"
    ],
    "qs_pg:aaroncc":"US",
    "qs_pg:gn_country":"US",
    "qs_pg:gn_fcode":"PPL",
    "qs_pg:gn_pop":0,
    "qs_pg:name":"Seiad Valley",
    "qs_pg:name_adm0":"United States",
    "qs_pg:name_adm1":"California",
    "qs_pg:photos_9r":0,
    "qs_pg:photos_sr":0,
    "qs_pg:pop_sr":0,
    "qs_pg:qs_pg_placetype":"locality",
    "qs_pg:qs_pg_placetype_gp":"Town",
    "qs_pg:woe_adm0":23424977,
    "woe:adm0_id":23424977,
    "woe:name_adm0":"United States",
    "woe:name_adm1":"California",
    "woe:placetype":"Town",
    "wof:name":"Seiad Valley",
    "wof:placetype":"locality"
},
  "geometry": {"coordinates":[-123.19255,41.84041],"type":"Point"}
}