{
  "type": "Feature",
  "properties": {
    "gn:admin1_code":"MS",
    "gn:admin2_code":"33.0",
    "gn:asciiname":"Lake View",
    "gn:country_code":"US",
    "gn:dem":71,
    "gn:elevation":"69.0",
    "gn:feature_class":"P",
    "gn:feature_code":"PPL",
    "gn:name":"Lake View",
    "gn:population":0,
    "gn:timezone":"America/Chicago",
    "iso:country":"US",
    "name:eng_x_preferred":[
        "Lake View"
    ],
    "name:fas_x_preferred":[
        "\u0644\u06cc\u06a9 \u0648\u06cc\u0648"
    ],
    "name:und_x_variant":[
        "Lakeview"
    ],
    "name:urd_x_preferred":[
        "\u0644\u06cc\u06a9 \u0648\u06cc\u0648"
    ],
    "wof:name":"Lake View",
    "wof:placetype":"locality"
},
  "geometry": {"coordinates":[-90.13982,34.98898],"type":"Point"}
}