{
  "type": "Feature",
  "properties": {
    "iso:country":"US",
    "name:eng_x_preferred":[
        "Jackson Corners"
    ],
    "wof:name":"Jackson Corners",
    "wof:placetype":"neighbourhood",
    "wof:population":336,
    "zs:blockids":[
        360270900002072,
        360270900002011,
        360270900002044,
        360270900002012,
        360270900002026,
        360270900002025,
        360270900002073,
        360270900002013,
        360210018001076,
        360210018001075,
        360210018001077
    ],
    "zs:housing10":196,
    "zs:label":"Jackson Corners",
    "zs:pop10":336
},
  "geometry": {"coordinates":[-73.754616,42.010168],"type":"Point"}
}