{
  "type": "Feature",
  "properties": {
    "gn:country":"US",
    "gn:fcode":"PPL",
    "gn:population":0,
    "iso:country":"US",
    "name:azb_x_preferred":[
        "\u0645\u0648\u0631"
    ],
    "name:deu_x_preferred":[
        "Moore"
    ],
    "name:eng_x_preferred":[
        "Moore"
    ],
    "name:fas_x_preferred":[
        "\u0645\u0648\u0631"
    ],
    "name:fra_x_preferred":[
        "Moore"
    ],
    "name:ita_x_preferred":[
        "Moore"
    ],
    "name:spa_x_preferred":[
        "Moore"
    ],
    "name:tur_x_preferred":[
        "Moore"
    ],
    "name:vol_x_preferred":[
        "Moore"
    ],
    "qs_pg:aaroncc":"US",
    "qs_pg:gn_country":"US",
    "qs_pg:gn_fcode":"PPL",
    "qs_pg:gn_pop":0,
    "qs_pg:name":"Moore",
    "qs_pg:name_adm0":"United States",
    "qs_pg:name_adm1":"South Carolina",
    "qs_pg:photos":159,
    "qs_pg:photos_1k":32,
    "qs_pg:photos_9k":1,
    "qs_pg:photos_9r":4,
    "qs_pg:photos_all":159,
    "qs_pg:photos_sr":4,
    "qs_pg:pop_sr":5,
    "qs_pg:qs_pg_placetype":"locality",
    "qs_pg:qs_pg_placetype_gp":"Town",
    "qs_pg:woe_adm0":23424977,
    "woe:adm0_id":23424977,
    "woe:name_adm0":"United States",
    "woe:name_adm1":"South Carolina",
    "woe:placetype":"Town",
    "wof:name":"Moore",
    "wof:placetype":"locality"
},
  "geometry": {"coordinates":[-81.99205000000001,34.83346],"type":"Point"}
}