{
  "type": "Feature",
  "properties": {
    "gn:admin1_code":"IN",
    "gn:admin2_code":"125.0",
    "gn:admin3_code":"46062.0",
    "gn:asciiname":"Bartons Location",
    "gn:country_code":"US",
    "gn:dem":128,
    "gn:elevation":"129.0",
    "gn:feature_class":"P",
    "gn:feature_code":"PPL",
    "gn:name":"Bartons Location",
    "gn:population":0,
    "gn:timezone":"America/Indiana/Petersburg",
    "iso:country":"US",
    "wof:name":"Bartons Location",
    "wof:placetype":"locality"
},
  "geometry": {"coordinates":[-87.33946,38.52922],"type":"Point"}
}