{
  "type": "Feature",
  "properties": {
    "gn:admin1_code":"NY",
    "gn:admin2_code":"107.0",
    "gn:admin3_code":"4671.0",
    "gn:asciiname":"Glencairn",
    "gn:country_code":"US",
    "gn:dem":338,
    "gn:elevation":"337.0",
    "gn:feature_class":"P",
    "gn:feature_code":"PPL",
    "gn:name":"Glencairn",
    "gn:population":0,
    "gn:timezone":"America/New_York",
    "iso:country":"US",
    "name:ceb_x_preferred":[
        "Glencairn"
    ],
    "name:fra_x_preferred":[
        "Glencairn"
    ],
    "wof:name":"Glencairn",
    "wof:placetype":"locality"
},
  "geometry": {"coordinates":[-76.48966,42.07896],"type":"Point"}
}