{
  "type": "Feature",
  "properties": {
    "gn:admin1_code":"MI",
    "gn:admin2_code":"115.0",
    "gn:admin3_code":"7720.0",
    "gn:asciiname":"Newport Farms Mobile Home Community",
    "gn:country_code":"US",
    "gn:dem":182,
    "gn:elevation":"182.0",
    "gn:feature_class":"P",
    "gn:feature_code":"PPL",
    "gn:name":"Newport Farms Mobile Home Community",
    "gn:population":0,
    "gn:timezone":"America/Detroit",
    "iso:country":"US",
    "wof:name":"Newport Farms Mobile Home Community",
    "wof:placetype":"campus"
},
  "geometry": {"coordinates":[-83.3325,42.00778],"type":"Point"}
}