{
  "type": "Feature",
  "properties": {
    "iso:country":"US",
    "name:epo_x_preferred":[
        "Fortika\u0135o Cove"
    ],
    "name:mar_x_preferred":[
        "\u0915\u094b\u0935\u094d\u0939 \u092b\u094b\u0930\u094d\u091f"
    ],
    "name:nld_x_preferred":[
        "Cove Fort"
    ],
    "qs_pg:aaroncc":"US",
    "qs_pg:name":"Cove Fort",
    "qs_pg:name_adm0":"United States",
    "qs_pg:name_adm1":"Utah",
    "qs_pg:photos":335,
    "qs_pg:photos_1k":68,
    "qs_pg:photos_9k":1,
    "qs_pg:photos_9r":5,
    "qs_pg:photos_all":335,
    "qs_pg:photos_sr":5,
    "qs_pg:pop_sr":0,
    "qs_pg:qs_pg_placetype":"locality",
    "qs_pg:qs_pg_placetype_gp":"Town",
    "qs_pg:woe_adm0":23424977,
    "woe:adm0_id":23424977,
    "woe:name_adm0":"United States",
    "woe:name_adm1":"Utah",
    "woe:placetype":"Town",
    "wof:name":"Cove Fort",
    "wof:placetype":"locality"
},
  "geometry": {"coordinates":[-112.582182,38.600777],"type":"Point"}
}