{
  "type": "Feature",
  "properties": {
    "gn:country":"US",
    "gn:fcode":"PPL",
    "gn:population":0,
    "iso:country":"US",
    "name:ceb_x_preferred":[
        "Central"
    ],
    "name:deu_x_preferred":[
        "Central"
    ],
    "name:est_x_preferred":[
        "Central"
    ],
    "name:fas_x_preferred":[
        "\u0645\u0631\u06a9\u0632\u06cc"
    ],
    "name:fra_x_preferred":[
        "Central"
    ],
    "name:heb_x_preferred":[
        "\u05de\u05e8\u05db\u05d6"
    ],
    "name:hun_x_preferred":[
        "K\u00f6z\u00e9p"
    ],
    "name:ita_x_preferred":[
        "Central"
    ],
    "name:jpn_x_preferred":[
        "\u30bb\u30f3\u30c8\u30e9\u30eb"
    ],
    "name:kor_x_preferred":[
        "\uc13c\ud2b8\ub7f4"
    ],
    "name:nld_x_preferred":[
        "Central"
    ],
    "name:pol_x_preferred":[
        "Central"
    ],
    "name:por_x_preferred":[
        "Central"
    ],
    "name:rus_x_preferred":[
        "\u0426\u0435\u043d\u0442\u0440\u0430\u043b\u044c"
    ],
    "name:slk_x_preferred":[
        "Centr\u00e1l"
    ],
    "name:spa_x_preferred":[
        "Central"
    ],
    "name:swe_x_preferred":[
        "Central"
    ],
    "name:tam_x_preferred":[
        "\u0b9a\u0bc6\u0ba9\u0bcd\u0b9f\u0bcd\u0bb0\u0bb2\u0bcd"
    ],
    "name:tha_x_preferred":[
        "\u0e01\u0e25\u0e32\u0e07"
    ],
    "name:ukr_x_preferred":[
        "\u0421\u0435\u043d\u0442\u0440\u0430\u043b"
    ],
    "name:vol_x_preferred":[
        "Central"
    ],
    "name:zho_x_preferred":[
        "\u4e2d"
    ],
    "qs_pg:aaroncc":"US",
    "qs_pg:gn_country":"US",
    "qs_pg:gn_fcode":"PPL",
    "qs_pg:gn_pop":0,
    "qs_pg:name":"Central",
    "qs_pg:name_adm0":"United States",
    "qs_pg:name_adm1":"Pennsylvania",
    "qs_pg:photos":184,
    "qs_pg:photos_1k":37,
    "qs_pg:photos_9k":1,
    "qs_pg:photos_9r":4,
    "qs_pg:photos_all":184,
    "qs_pg:photos_sr":4,
    "qs_pg:pop_sr":0,
    "qs_pg:qs_pg_placetype":"neighbourhood",
    "qs_pg:qs_pg_placetype_gp":"Suburb",
    "qs_pg:woe_adm0":23424977,
    "woe:adm0_id":23424977,
    "woe:name_adm0":"United States",
    "woe:name_adm1":"Pennsylvania",
    "woe:placetype":"Suburb",
    "wof:name":"Central",
    "wof:placetype":"neighbourhood"
},
  "geometry": {"coordinates":[-79.58504000000001,40.17757],"type":"Point"}
}