{
  "type": "Feature",
  "properties": {
    "gn:admin1_code":"MN",
    "gn:admin2_code":"99.0",
    "gn:admin3_code":"53584.0",
    "gn:asciiname":"Nicolville",
    "gn:country_code":"US",
    "gn:dem":380,
    "gn:elevation":"379.0",
    "gn:feature_class":"P",
    "gn:feature_code":"PPL",
    "gn:name":"Nicolville",
    "gn:population":0,
    "gn:timezone":"America/Chicago",
    "iso:country":"US",
    "wof:name":"Nicolville",
    "wof:placetype":"locality"
},
  "geometry": {"coordinates":[-92.87824000000001,43.67469000000001],"type":"Point"}
}