{
  "type": "Feature",
  "properties": {
    "gn:admin1_code":"GA",
    "gn:admin2_code":"255",
    "gn:asciiname":"Zetella",
    "gn:country_code":"US",
    "gn:dem":264,
    "gn:elevation":"262.0",
    "gn:feature_class":"P",
    "gn:feature_code":"PPL",
    "gn:name":"Zetella",
    "gn:population":0,
    "gn:timezone":"America/New_York",
    "iso:country":"US",
    "wof:name":"Zetella",
    "wof:placetype":"locality"
},
  "geometry": {"coordinates":[-84.38215,33.24095],"type":"Point"}
}