{
  "type": "Feature",
  "properties": {
    "gn:admin1_code":"FL",
    "gn:admin2_code":"57",
    "gn:asciiname":"Torrens",
    "gn:country_code":"US",
    "gn:dem":40,
    "gn:elevation":"36.0",
    "gn:feature_class":"P",
    "gn:feature_code":"PPL",
    "gn:name":"Torrens",
    "gn:population":0,
    "gn:timezone":"America/New_York",
    "iso:country":"US",
    "name:deu_x_preferred":[
        "Torrens"
    ],
    "name:fra_x_preferred":[
        "Torrens"
    ],
    "name:kor_x_preferred":[
        "\ud1a0\ub7f0\uc2a4"
    ],
    "name:lav_x_preferred":[
        "Torrens"
    ],
    "name:pol_x_preferred":[
        "Torrens"
    ],
    "name:rus_x_preferred":[
        "\u0422\u043e\u0440\u0440\u0435\u043d\u0441"
    ],
    "name:spa_x_preferred":[
        "Torrens"
    ],
    "name:ukr_x_preferred":[
        "\u0422\u043e\u0440\u0440\u0435\u043d\u0441"
    ],
    "wof:name":"Torrens",
    "wof:placetype":"locality"
},
  "geometry": {"coordinates":[-82.28,27.7683],"type":"Point"}
}