{
  "type": "Feature",
  "properties": {
    "gn:admin1_code":"MI",
    "gn:admin2_code":"107",
    "gn:admin3_code":"8320.0",
    "gn:asciiname":"Circle Drive Mobile Home Park",
    "gn:country_code":"US",
    "gn:dem":275,
    "gn:elevation":"274.0",
    "gn:feature_class":"P",
    "gn:feature_code":"PPL",
    "gn:name":"Circle Drive Mobile Home Park",
    "gn:population":0,
    "gn:timezone":"America/Detroit",
    "iso:country":"US",
    "wof:name":"Circle Drive Mobile Home Park",
    "wof:placetype":"campus"
},
  "geometry": {"coordinates":[-85.45139,43.64722],"type":"Point"}
}