{
  "type": "Feature",
  "properties": {
    "gn:admin1_code":"NY",
    "gn:admin2_code":"105.0",
    "gn:admin3_code":"16661.0",
    "gn:asciiname":"East Cochecton",
    "gn:country_code":"US",
    "gn:dem":396,
    "gn:elevation":"400.0",
    "gn:feature_class":"P",
    "gn:feature_code":"PPL",
    "gn:name":"East Cochecton",
    "gn:population":0,
    "gn:timezone":"America/New_York",
    "iso:country":"US",
    "wof:name":"East Cochecton",
    "wof:placetype":"locality"
},
  "geometry": {"coordinates":[-75.01572,41.71537],"type":"Point"}
}