{
  "type": "Feature",
  "properties": {
    "iso:country":"US",
    "name:eng_x_preferred":[
        "Sylvan Terrace"
    ],
    "wof:name":"Sylvan Terrace",
    "wof:placetype":"neighbourhood",
    "zs:area_m":2870.769332,
    "zs:blockids":[
        130510034002023
    ],
    "zs:housing10":0,
    "zs:label":"Sylvan Terrace",
    "zs:pop10":0
},
  "geometry": {"coordinates":[-81.10878099999999,32.035159],"type":"Point"}
}