{
  "type": "Feature",
  "properties": {
    "iso:country":"US",
    "name:eng_x_preferred":[
        "Adams City"
    ],
    "wof:name":"Adams City",
    "wof:placetype":"neighbourhood",
    "zs:area_m":21337.992069,
    "zs:blockids":[
        80010089011050,
        80010089011057
    ],
    "zs:housing10":0,
    "zs:label":"Adams City",
    "zs:pop10":0
},
  "geometry": {"coordinates":[-104.944536,39.828742],"type":"Point"}
}