{
  "type": "Feature",
  "properties": {
    "iso:country":"US",
    "name:ceb_x_preferred":[
        "Holly Hill"
    ],
    "name:deu_x_preferred":[
        "Holly Hill"
    ],
    "name:eng_x_preferred":[
        "Holly Hill"
    ],
    "name:ita_x_preferred":[
        "Holly Hill"
    ],
    "name:nld_x_preferred":[
        "Holly Hill"
    ],
    "name:pol_x_preferred":[
        "Holly Hill"
    ],
    "name:por_x_preferred":[
        "Holly Hill"
    ],
    "name:spa_x_preferred":[
        "Holly Hill"
    ],
    "name:srp_x_preferred":[
        "\u0425\u043e\u043b\u0438 \u0425\u0438\u043b"
    ],
    "name:swe_x_preferred":[
        "Holly Hill"
    ],
    "name:ukr_x_preferred":[
        "\u0413\u043e\u043b\u043b\u0456-\u0413\u0456\u043b\u043b"
    ],
    "name:vol_x_preferred":[
        "Holly Hill"
    ],
    "wd:wordcount":44,
    "wof:name":"Holly Hill",
    "wof:placetype":"neighbourhood",
    "zs:area_m":18759.566429,
    "zs:blockids":[
        121050124031022,
        121050124031147
    ],
    "zs:housing10":0,
    "zs:label":"Holly Hill",
    "zs:pop10":0
},
  "geometry": {"coordinates":[-81.666027,28.301526],"type":"Point"}
}