{
  "type": "Feature",
  "properties": {
    "gn:admin1_code":"KY",
    "gn:admin2_code":"139",
    "gn:asciiname":"Pinckneyville",
    "gn:country_code":"US",
    "gn:dem":109,
    "gn:elevation":"107.0",
    "gn:feature_class":"P",
    "gn:feature_code":"PPL",
    "gn:name":"Pinckneyville",
    "gn:population":0,
    "gn:timezone":"America/Chicago",
    "iso:country":"US",
    "wof:name":"Pinckneyville",
    "wof:placetype":"locality"
},
  "geometry": {"coordinates":[-88.23975,37.18728],"type":"Point"}
}