{
  "type": "Feature",
  "properties": {
    "gn:admin1_code":"GA",
    "gn:admin2_code":"253.0",
    "gn:asciiname":"Green Acres Subdivision",
    "gn:country_code":"US",
    "gn:dem":46,
    "gn:elevation":"40.0",
    "gn:feature_class":"P",
    "gn:feature_code":"PPL",
    "gn:name":"Green Acres Subdivision",
    "gn:population":0,
    "gn:timezone":"America/New_York",
    "iso:country":"US",
    "wof:name":"Green Acres Subdivision",
    "wof:placetype":"locality"
},
  "geometry": {"coordinates":[-84.87992,30.98935],"type":"Point"}
}