{
  "type": "Feature",
  "properties": {
    "iso:country":"US",
    "name:eng_x_preferred":[
        "Oak Wood Heights"
    ],
    "wof:name":"Oak Wood Heights",
    "wof:placetype":"neighbourhood",
    "wof:population":66,
    "zs:area_m":44020.647499,
    "zs:blockids":[
        490572015001014,
        490572015001010
    ],
    "zs:housing10":32,
    "zs:label":"Oak Wood Heights",
    "zs:pop10":66
},
  "geometry": {"coordinates":[-111.94483200000001,41.206213],"type":"Point"}
}