{
  "type": "Feature",
  "properties": {
    "gn:admin1_code":"CA",
    "gn:admin2_code":"35.0",
    "gn:asciiname":"Leonard",
    "gn:country_code":"US",
    "gn:dem":1276,
    "gn:elevation":"1275.0",
    "gn:feature_class":"P",
    "gn:feature_code":"PPL",
    "gn:name":"Leonard",
    "gn:population":0,
    "gn:timezone":"America/Los_Angeles",
    "iso:country":"US",
    "name:ara_x_preferred":[
        "\u0644\u064a\u0648\u0646\u0627\u0631\u062f"
    ],
    "name:dan_x_preferred":[
        "Leonard"
    ],
    "name:deu_x_preferred":[
        "Leonard"
    ],
    "name:fin_x_preferred":[
        "Leonard"
    ],
    "name:heb_x_preferred":[
        "\u05dc\u05d0\u05d5\u05e0\u05e8\u05d3"
    ],
    "name:isl_x_preferred":[
        "Leonard"
    ],
    "name:nld_x_preferred":[
        "Leonard"
    ],
    "name:nno_x_preferred":[
        "Leonard"
    ],
    "name:nor_x_preferred":[
        "Leonard"
    ],
    "name:pol_x_preferred":[
        "Leonard"
    ],
    "name:ron_x_preferred":[
        "Leonard"
    ],
    "name:slk_x_preferred":[
        "Leonard"
    ],
    "name:slv_x_preferred":[
        "Leonard"
    ],
    "name:swe_x_preferred":[
        "Leonard"
    ],
    "wof:name":"Leonard",
    "wof:placetype":"locality"
},
  "geometry": {"coordinates":[-121.0308,41.13461],"type":"Point"}
}