{
  "type": "Feature",
  "properties": {
    "gn:admin1_code":"MO",
    "gn:admin2_code":"219.0",
    "gn:admin3_code":"57692.0",
    "gn:asciiname":"Macedonia Neighborhood",
    "gn:country_code":"US",
    "gn:dem":278,
    "gn:elevation":"275.0",
    "gn:feature_class":"P",
    "gn:feature_code":"PPL",
    "gn:name":"Macedonia Neighborhood",
    "gn:population":0,
    "gn:timezone":"America/Chicago",
    "iso:country":"US",
    "wof:name":"Macedonia Neighborhood",
    "wof:placetype":"locality"
},
  "geometry": {"coordinates":[-91.19904,38.76116],"type":"Point"}
}