{
  "type": "Feature",
  "properties": {
    "gn:country":"US",
    "gn:fcode":"PPL",
    "gn:population":0,
    "iso:country":"US",
    "name:eng_x_preferred":[
        "Flagg Center"
    ],
    "name:fas_x_preferred":[
        "\u0641\u0644\u0627\u06af \u0633\u0646\u062a\u0631"
    ],
    "name:fra_x_preferred":[
        "Flagg Center"
    ],
    "name:und_x_variant":[
        "Kyte River"
    ],
    "name:vol_x_preferred":[
        "Flagg Center"
    ],
    "qs_pg:aaroncc":"US",
    "qs_pg:gn_country":"US",
    "qs_pg:gn_fcode":"PPL",
    "qs_pg:gn_pop":0,
    "qs_pg:name":"Flag Center",
    "qs_pg:name_adm0":"United States",
    "qs_pg:name_adm1":"Illinois",
    "qs_pg:photos":113,
    "qs_pg:photos_1k":23,
    "qs_pg:photos_9k":1,
    "qs_pg:photos_9r":3,
    "qs_pg:photos_all":113,
    "qs_pg:photos_sr":3,
    "qs_pg:pop_sr":0,
    "qs_pg:qs_pg_placetype":"locality",
    "qs_pg:qs_pg_placetype_gp":"Town",
    "qs_pg:woe_adm0":23424977,
    "woe:adm0_id":23424977,
    "woe:name_adm0":"United States",
    "woe:name_adm1":"Illinois",
    "woe:placetype":"Town",
    "wof:name":"Flag Center",
    "wof:placetype":"locality"
},
  "geometry": {"coordinates":[-89.12232,41.94058],"type":"Point"}
}