{
  "type": "Feature",
  "properties": {
    "gn:country":"US",
    "gn:fcode":"PPL",
    "gn:population":0,
    "iso:country":"US",
    "name:eng_x_preferred":[
        "Bull Tavern"
    ],
    "qs_pg:aaroncc":"US",
    "qs_pg:gn_country":"US",
    "qs_pg:gn_fcode":"PPL",
    "qs_pg:gn_pop":0,
    "qs_pg:name":"Bull Tavern",
    "qs_pg:name_adm0":"United States",
    "qs_pg:name_adm1":"Pennsylvania",
    "qs_pg:photos":20,
    "qs_pg:photos_1k":4,
    "qs_pg:photos_9k":1,
    "qs_pg:photos_9r":1,
    "qs_pg:photos_all":20,
    "qs_pg:photos_sr":1,
    "qs_pg:pop_sr":0,
    "qs_pg:qs_pg_placetype":"neighbourhood",
    "qs_pg:qs_pg_placetype_gp":"Suburb",
    "qs_pg:woe_adm0":23424977,
    "wof:name":"Bull Tavern",
    "wof:placetype":"neighbourhood",
    "wof:population":1464,
    "zs:area_m":3093855.676134,
    "zs:blockids":[
        420293005011018,
        420293005011016,
        420293005012033,
        420293005012047,
        420293005012034,
        420293005012030,
        420293005012035,
        420293005012031,
        420293005021013,
        420293005011014,
        420293005011039,
        420293005012046,
        420293005011015,
        420293005012029,
        420293005012032,
        420293005011017
    ],
    "zs:housing10":500,
    "zs:label":"Bull Tavern",
    "zs:pop10":1464
},
  "geometry": {"coordinates":[-75.493207,40.106098],"type":"Point"}
}