{
  "type": "Feature",
  "properties": {
    "gn:admin1_code":"TX",
    "gn:admin2_code":"25",
    "gn:asciiname":"Monteola",
    "gn:country_code":"US",
    "gn:dem":152,
    "gn:elevation":"149.0",
    "gn:feature_class":"P",
    "gn:feature_code":"PPL",
    "gn:name":"Monteola",
    "gn:population":0,
    "gn:timezone":"America/Chicago",
    "iso:country":"US",
    "wof:name":"Monteola",
    "wof:placetype":"locality"
},
  "geometry": {"coordinates":[-97.91584,28.69776],"type":"Point"}
}