{
  "type": "Feature",
  "properties": {
    "gn:elevation":15,
    "iso:country":"US",
    "name:eng_x_preferred":[
        "Orangeland"
    ],
    "qs:gn_adm0_cc":"US",
    "qs:gn_fcode":"PPL",
    "qs:gn_local":4148757,
    "qs:gn_nam_loc":"Brandon, Hillsborough, Florida, US",
    "qs:gn_namadm1":"FL",
    "qs:gn_name":"Orangeland",
    "qs:local_max":581,
    "qs:local_sum":1252,
    "qs:localhoods":7,
    "qs:name":"Orangeland",
    "qs:name_adm0":"United States",
    "qs:name_adm1":"Florida",
    "qs:name_adm2":"Hillsborough",
    "qs:name_local":"Brandon",
    "qs:photo_max":42,
    "qs:photo_sum":118,
    "qs:placetype":"Suburb",
    "qs:quad_count":10,
    "qs:woe_adm0":23424977,
    "qs:woe_adm1":2347568,
    "qs:woe_adm2":12587831,
    "qs:woe_lau":0,
    "qs:woe_local":2368145,
    "qs:woe_ver":"7.10.0",
    "wof:lang":[
        "eng"
    ],
    "wof:name":"Orangeland",
    "wof:placetype":"neighbourhood",
    "wof:population":3800,
    "zs:blockids":[
        120570122121001,
        120570122111037,
        120570133151015,
        120570122133000,
        120570122121007,
        120570122121026,
        120570133161010,
        120570133151014,
        120570133161006,
        120570122133007,
        120570122121027,
        120570122121005,
        120570133161000,
        120570122121023,
        120570122121016,
        120570122121006,
        120570122121008,
        120570133161011,
        120570122121009,
        120570122121003,
        120570133151013,
        120570122121020,
        120570133161005,
        120570133161009,
        120570122111038,
        120570122133006,
        120570122133001,
        120570122121011,
        120570122121010,
        120570122121002,
        120570122121024,
        120570122121004,
        120570122121000,
        120570133161008,
        120570122121012
    ],
    "zs:housing10":1598,
    "zs:pop10":3800
},
  "geometry": {"coordinates":[-82.324386,27.939131],"type":"Point"}
}