{
  "type": "Feature",
  "properties": {
    "gn:admin1_code":"TN",
    "gn:admin2_code":"63",
    "gn:asciiname":"Nenny",
    "gn:country_code":"US",
    "gn:dem":379,
    "gn:elevation":"383.0",
    "gn:feature_class":"P",
    "gn:feature_code":"PPL",
    "gn:name":"Nenny",
    "gn:population":0,
    "gn:timezone":"America/New_York",
    "iso:country":"US",
    "wof:name":"Nenny",
    "wof:placetype":"locality"
},
  "geometry": {"coordinates":[-83.14461,36.24454],"type":"Point"}
}