{
  "type": "Feature",
  "properties": {
    "gn:admin1_code":"VA",
    "gn:admin2_code":"69",
    "gn:asciiname":"Indian Lake",
    "gn:country_code":"US",
    "gn:dem":231,
    "gn:elevation":"234.0",
    "gn:feature_class":"P",
    "gn:feature_code":"PPL",
    "gn:name":"Indian Lake",
    "gn:population":0,
    "gn:timezone":"America/New_York",
    "iso:country":"US",
    "name:ceb_x_preferred":[
        "Indian Lake"
    ],
    "name:deu_x_preferred":[
        "Indian Lake"
    ],
    "name:ita_x_preferred":[
        "Indian Lake"
    ],
    "name:nld_x_preferred":[
        "Indian Lake"
    ],
    "name:pol_x_preferred":[
        "Indian Lake"
    ],
    "name:por_x_preferred":[
        "Indian Lake"
    ],
    "name:srp_x_preferred":[
        "\u0418\u043d\u0434\u0438\u0458\u0430\u043d \u041b\u0435\u0458\u043a"
    ],
    "name:swe_x_preferred":[
        "Indian Lake"
    ],
    "name:ukr_x_preferred":[
        "\u0406\u043d\u0434\u0456\u0430\u043d-\u041b\u0435\u0439\u043a"
    ],
    "name:vol_x_preferred":[
        "Indian Lake"
    ],
    "wof:name":"Indian Lake",
    "wof:placetype":"locality"
},
  "geometry": {"coordinates":[-78.28166999999998,39.23927],"type":"Point"}
}