{
  "type": "Feature",
  "properties": {
    "gn:admin1_code":"VA",
    "gn:admin2_code":"710",
    "gn:asciiname":"Merrimack Park",
    "gn:country_code":"US",
    "gn:dem":4,
    "gn:elevation":"4.0",
    "gn:feature_class":"P",
    "gn:feature_code":"PPL",
    "gn:name":"Merrimack Park",
    "gn:population":0,
    "gn:timezone":"America/New_York",
    "iso:country":"US",
    "wof:name":"Merrimack Park",
    "wof:placetype":"locality"
},
  "geometry": {"coordinates":[-76.27271999999998,36.94015],"type":"Point"}
}