{
  "type": "Feature",
  "properties": {
    "iso:country":"US",
    "name:eng_x_preferred":[
        "Firewheel"
    ],
    "name:eng_x_variant":[
        "The Firewheel"
    ],
    "qs:gn_adm0_cc":"US",
    "qs:gn_local":4693003,
    "qs:gn_namadm1":"TX",
    "qs:local_max":1623,
    "qs:local_sum":8153,
    "qs:localhoods":20,
    "qs:name":"Firewheel",
    "qs:name_adm0":"United States",
    "qs:name_adm1":"Texas",
    "qs:name_adm2":"Dallas",
    "qs:name_local":"Garland",
    "qs:photo_max":1160,
    "qs:photo_sum":1623,
    "qs:placetype":"Suburb",
    "qs:quad_count":33,
    "qs:woe_adm0":23424977,
    "qs:woe_adm1":2347602,
    "qs:woe_adm2":12590063,
    "qs:woe_funk":"Parented by a neighborhood",
    "qs:woe_lau":0,
    "qs:woe_local":2408980,
    "qs:woe_ver":"7.10.0",
    "wof:lang":[
        "eng"
    ],
    "wof:name":"Firewheel",
    "wof:placetype":"neighbourhood",
    "wof:population":3763,
    "zs:blockids":[
        481130190433005,
        481130190433004,
        481130190433024,
        481130190433023,
        481130190422001,
        481130190433052,
        481130190433060,
        481130190433035,
        481130190433026,
        481130190433034,
        481130190433008,
        481130190433010,
        481130190433001,
        481130190433011,
        481130190421036,
        481130190433031,
        481130190433048,
        481130190433015,
        481130190422002,
        481130190271003,
        481130190273000,
        481130190433032,
        481130190433006,
        481130190433002,
        481130190271002,
        481130190433038,
        481130190422051,
        481130190421003,
        481130190433012,
        481130190432010,
        481130190433029,
        481130190433039,
        481130190433037,
        481130190421052,
        481130190422050,
        481130190271000,
        481130190433028,
        481130190433054,
        481130190433045,
        481130190271004,
        481130190433040,
        481130190433041,
        481130190271005,
        481130190433025,
        481130190433027,
        481130190433020,
        481130190433017,
        481130190273001,
        481130190271001,
        481130190433013,
        481130190432018,
        481130190433046,
        481130190433003,
        481130190421082,
        481130190421006,
        481130190422000,
        481130190421039,
        481130190433000,
        481130190433018,
        481130190433016,
        481130190432019,
        481130190421054,
        481130190433042,
        481130190433030,
        481130190433055,
        481130190433014,
        481130190433019,
        481130190421053,
        481130190433047,
        481130190433009,
        481130190421002,
        481130190433007,
        481130190433036,
        481130190433044,
        481130190433033,
        481130190433022,
        481130190433021
    ],
    "zs:housing10":1567,
    "zs:pop10":3763
},
  "geometry": {"coordinates":[-96.637913,32.959417],"type":"Point"}
}