{
  "type": "Feature",
  "properties": {
    "gn:admin1_code":"LA",
    "gn:admin2_code":"109.0",
    "gn:asciiname":"Zacarter",
    "gn:country_code":"US",
    "gn:dem":3,
    "gn:elevation":"2.0",
    "gn:feature_class":"P",
    "gn:feature_code":"PPL",
    "gn:name":"Zacarter",
    "gn:population":0,
    "gn:timezone":"America/Chicago",
    "iso:country":"US",
    "wof:name":"Zacarter",
    "wof:placetype":"locality"
},
  "geometry": {"coordinates":[-91.02982,29.66549],"type":"Point"}
}