{
  "type": "Feature",
  "properties": {
    "gn:country":"US",
    "gn:fcode":"PPL",
    "gn:population":0,
    "iso:country":"US",
    "name:eng_x_preferred":[
        "Jefferson Springs"
    ],
    "name:und_x_variant":[
        "Sulphur Springs"
    ],
    "qs_pg:aaroncc":"US",
    "qs_pg:gn_country":"US",
    "qs_pg:gn_fcode":"PPL",
    "qs_pg:gn_pop":0,
    "qs_pg:name":"Jefferson Springs",
    "qs_pg:name_adm0":"United States",
    "qs_pg:name_adm1":"Tennessee",
    "qs_pg:photos":31,
    "qs_pg:photos_1k":6,
    "qs_pg:photos_9k":1,
    "qs_pg:photos_9r":2,
    "qs_pg:photos_all":31,
    "qs_pg:photos_sr":2,
    "qs_pg:pop_sr":0,
    "qs_pg:qs_pg_placetype":"locality",
    "qs_pg:qs_pg_placetype_gp":"Town",
    "qs_pg:woe_adm0":23424977,
    "woe:adm0_id":23424977,
    "woe:name_adm0":"United States",
    "woe:name_adm1":"Tennessee",
    "woe:placetype":"Town",
    "wof:name":"Jefferson Springs",
    "wof:placetype":"locality"
},
  "geometry": {"coordinates":[-86.45833,36.00145],"type":"Point"}
}