{
  "type": "Feature",
  "properties": {
    "gn:admin1_code":"SC",
    "gn:admin2_code":"43.0",
    "gn:asciiname":"Saint Pauls",
    "gn:country_code":"US",
    "gn:dem":0,
    "gn:elevation":"3.0",
    "gn:feature_class":"P",
    "gn:feature_code":"PPL",
    "gn:name":"Saint Pauls",
    "gn:population":0,
    "gn:timezone":"America/New_York",
    "iso:country":"US",
    "wof:name":"Saint Pauls",
    "wof:placetype":"locality"
},
  "geometry": {"coordinates":[-79.18559999999999,33.576],"type":"Point"}
}