{
  "type": "Feature",
  "properties": {
    "gn:admin1_code":"SC",
    "gn:admin2_code":"51.0",
    "gn:asciiname":"Brookgate",
    "gn:country_code":"US",
    "gn:dem":0,
    "gn:elevation":"6.0",
    "gn:feature_class":"P",
    "gn:feature_code":"PPL",
    "gn:name":"Brookgate",
    "gn:population":0,
    "gn:timezone":"America/New_York",
    "iso:country":"US",
    "wof:name":"Brookgate",
    "wof:placetype":"locality"
},
  "geometry": {"coordinates":[-78.96225,33.716],"type":"Point"}
}