{
  "type": "Feature",
  "properties": {
    "iso:country":"US",
    "name:eng_x_preferred":[
        "The Almond Grove"
    ],
    "qs:gn_local":0,
    "qs:local_max":2188,
    "qs:local_sum":7492,
    "qs:localhoods":14,
    "qs:name":"The Almond Grove",
    "qs:name_adm0":"United States",
    "qs:name_adm1":"California",
    "qs:name_adm2":"Santa Clara",
    "qs:name_local":"Los Gatos",
    "qs:photo_max":638,
    "qs:photo_sum":942,
    "qs:placetype":"Suburb",
    "qs:quad_count":9,
    "qs:woe_adm0":23424977,
    "qs:woe_adm1":2347563,
    "qs:woe_adm2":12587712,
    "qs:woe_lau":0,
    "qs:woe_local":2442121,
    "qs:woe_ver":"7.10.0",
    "wof:lang":[
        "eng"
    ],
    "wof:name":"The Almond Grove",
    "wof:placetype":"neighbourhood",
    "wof:population":1069,
    "zs:blockids":[
        60855070011021,
        60855070012038,
        60855070011057,
        60855070011026,
        60855070011001,
        60855070011049,
        60855070011050,
        60855070011007,
        60855070011024,
        60855070011028,
        60855070011009,
        60855070011000,
        60855070011038,
        60855070011016,
        60855070011010,
        60855070011002,
        60855070012060,
        60855070011025,
        60855070011051,
        60855070011023,
        60855070011022,
        60855070011054,
        60855070011006,
        60855070011017,
        60855070012063,
        60855070011043,
        60855070011004,
        60855070011053,
        60855070011052,
        60855070011020,
        60855070011058,
        60855070011036,
        60855070011037,
        60855070011034,
        60855070011015,
        60855070011005,
        60855070011027,
        60855070011014,
        60855070011008,
        60855070011035
    ],
    "zs:housing10":579,
    "zs:pop10":1069
},
  "geometry": {"coordinates":[-121.98429299999999,37.226942],"type":"Point"}
}