{
  "type": "Feature",
  "properties": {
    "gn:admin1_code":"IL",
    "gn:admin2_code":"3.0",
    "gn:asciiname":"Willard",
    "gn:country_code":"US",
    "gn:dem":99,
    "gn:elevation":"98.0",
    "gn:feature_class":"P",
    "gn:feature_code":"PPL",
    "gn:name":"Willard",
    "gn:population":0,
    "gn:timezone":"America/Chicago",
    "iso:country":"US",
    "wof:name":"Willard",
    "wof:placetype":"locality"
},
  "geometry": {"coordinates":[-89.3523,37.08644],"type":"Point"}
}