{
  "type": "Feature",
  "properties": {
    "iso:country":"US",
    "name:eng_x_preferred":[
        "Woodbine/Wyatt"
    ],
    "wof:name":"Woodbine/Wyatt",
    "wof:placetype":"neighbourhood",
    "wof:population":143,
    "zs:area_m":88895.839481,
    "zs:blockids":[
        511210205004040
    ],
    "zs:housing10":48,
    "zs:label":"Woodbine/Wyatt",
    "zs:pop10":143
},
  "geometry": {"coordinates":[-80.40457600000001,37.263653],"type":"Point"}
}