{
  "type": "Feature",
  "properties": {
    "gn:elevation":16,
    "iso:country":"US",
    "name:ceb_x_preferred":[
        "Battle Point"
    ],
    "name:deu_x_preferred":[
        "Battle Point"
    ],
    "name:eng_x_preferred":[
        "Battle Point"
    ],
    "name:eng_x_variant":[
        "Battle Pt"
    ],
    "name:nld_x_preferred":[
        "Battle Point"
    ],
    "name:nno_x_preferred":[
        "Battle Point"
    ],
    "name:swe_x_preferred":[
        "Battle Point"
    ],
    "name:zho_x_preferred":[
        "\u5df4\u7279\u723e\u89d2"
    ],
    "qs:gn_adm0_cc":"US",
    "qs:gn_fcode":"PPL",
    "qs:gn_local":5816320,
    "qs:gn_nam_loc":"Bainbridge Island, Kitsap, Washington, US",
    "qs:gn_namadm1":"WA",
    "qs:gn_name":"Battle Point",
    "qs:local_max":1604,
    "qs:local_sum":7231,
    "qs:localhoods":17,
    "qs:name":"Battle Point",
    "qs:name_adm0":"United States",
    "qs:name_adm1":"Washington",
    "qs:name_adm2":"Kitsap",
    "qs:name_local":"Bainbridge Island",
    "qs:photo_max":53,
    "qs:photo_sum":142,
    "qs:placetype":"Suburb",
    "qs:quad_count":14,
    "qs:woe_adm0":23424977,
    "qs:woe_adm1":2347606,
    "qs:woe_adm2":12590457,
    "qs:woe_lau":0,
    "qs:woe_local":2358364,
    "qs:woe_ver":"7.10.0",
    "wd:wordcount":139,
    "wof:lang":[
        "eng"
    ],
    "wof:name":"Battle Point",
    "wof:placetype":"neighbourhood",
    "wof:population":510,
    "zs:blockids":[
        530350908003023,
        530350908003005,
        530350908003017
    ],
    "zs:housing10":224,
    "zs:pop10":510
},
  "geometry": {"coordinates":[-122.567694,47.658266],"type":"Point"}
}