{
  "type": "Feature",
  "properties": {
    "iso:country":"US",
    "name:eng_x_preferred":[
        "Canyon Crest"
    ],
    "name:eng_x_variant":[
        "Canyon Crst"
    ],
    "qs:gn_adm0_cc":"US",
    "qs:gn_local":5771826,
    "qs:gn_nam_loc":"Bountiful, Davis, Utah, US",
    "qs:gn_namadm1":"UT",
    "qs:local_max":402,
    "qs:local_sum":1171,
    "qs:localhoods":9,
    "qs:name":"Canyon Crest",
    "qs:name_adm0":"United States",
    "qs:name_adm1":"Utah",
    "qs:name_adm2":"Davis",
    "qs:name_local":"Bountiful",
    "qs:photo_max":23,
    "qs:photo_sum":95,
    "qs:placetype":"Suburb",
    "qs:quad_count":12,
    "qs:woe_adm0":23424977,
    "qs:woe_adm1":2347603,
    "qs:woe_adm2":12590266,
    "qs:woe_lau":0,
    "qs:woe_local":2367288,
    "qs:woe_ver":"7.10.0",
    "wof:name":"Canyon Crest",
    "wof:placetype":"neighbourhood",
    "wof:population":595,
    "zs:blockids":[
        490111264022023,
        490111268011005,
        490111264022022,
        490111268011006,
        490111268011014,
        490111264022033,
        490111264022035,
        490111264022024,
        490111264022089,
        490111268011003,
        490111264022046,
        490111268011012
    ],
    "zs:housing10":185,
    "zs:pop10":595
},
  "geometry": {"coordinates":[-111.842985,40.872704],"type":"Point"}
}