{
  "type": "Feature",
  "properties": {
    "gn:admin1_code":"NC",
    "gn:admin2_code":"191.0",
    "gn:admin3_code":"90384.0",
    "gn:asciiname":"South Haven",
    "gn:country_code":"US",
    "gn:dem":57,
    "gn:elevation":"54.0",
    "gn:feature_class":"P",
    "gn:feature_code":"PPL",
    "gn:name":"South Haven",
    "gn:population":0,
    "gn:timezone":"America/New_York",
    "iso:country":"US",
    "name:cat_x_preferred":[
        "South Haven"
    ],
    "name:ceb_x_preferred":[
        "South Haven"
    ],
    "name:deu_x_preferred":[
        "South Haven"
    ],
    "name:ita_x_preferred":[
        "South Haven"
    ],
    "name:nld_x_preferred":[
        "South Haven"
    ],
    "name:pol_x_preferred":[
        "South Haven"
    ],
    "name:por_x_preferred":[
        "South Haven"
    ],
    "name:srp_x_preferred":[
        "\u0421\u0430\u0443\u0442 \u0425\u0435\u0458\u0432\u0435\u043d"
    ],
    "name:tur_x_preferred":[
        "South Haven"
    ],
    "name:vol_x_preferred":[
        "South Haven"
    ],
    "wof:name":"South Haven",
    "wof:placetype":"locality"
},
  "geometry": {"coordinates":[-78.01554,35.2835],"type":"Point"}
}