{
  "type": "Feature",
  "properties": {
    "gn:country":"US",
    "gn:elevation":320,
    "gn:fcode":"PPL",
    "gn:population":0,
    "iso:country":"US",
    "name:eng_x_preferred":[
        "Ackerville"
    ],
    "name:fas_x_preferred":[
        "\u0627\u06cc\u06a9\u0631\u0648\u06cc\u0644"
    ],
    "name:fra_x_preferred":[
        "Ackerville"
    ],
    "qs_pg:aaroncc":"US",
    "qs_pg:gn_country":"US",
    "qs_pg:gn_fcode":"PPL",
    "qs_pg:gn_pop":0,
    "qs_pg:name":"Ackerville",
    "qs_pg:name_adm0":"United States",
    "qs_pg:name_adm1":"Wisconsin",
    "qs_pg:photos":139,
    "qs_pg:photos_1k":28,
    "qs_pg:photos_9k":1,
    "qs_pg:photos_9r":3,
    "qs_pg:photos_all":139,
    "qs_pg:photos_sr":3,
    "qs_pg:pop_sr":0,
    "qs_pg:qs_pg_placetype":"neighbourhood",
    "qs_pg:qs_pg_placetype_gp":"Suburb",
    "qs_pg:woe_adm0":23424977,
    "woe:adm0_id":23424977,
    "woe:name_adm0":"United States",
    "woe:name_adm1":"Wisconsin",
    "woe:placetype":"Suburb",
    "wof:name":"Ackerville",
    "wof:placetype":"neighbourhood",
    "wof:population":2473
},
  "geometry": {"coordinates":[-88.25815,43.31],"type":"Point"}
}