{
  "type": "Feature",
  "properties": {
    "iso:country":"US",
    "name:arz_x_preferred":[
        "\u0645\u0637\u0627\u0631 \u0645\u0642\u0627\u0637\u0639\u0647 \u0646\u0627\u062a\u0634\u064a\u0632 \u0622\u062f\u0627\u0645\u0632"
    ],
    "name:ceb_x_preferred":[
        "Hardy-Anders Field Natchez-Adams County Airport"
    ],
    "name:eng_x_preferred":[
        "Hardy-Anders Field Airport"
    ],
    "name:eng_x_variant":[
        "HEZ",
        "KHEZ",
        "Natchez-Adams County Airport"
    ],
    "name:fas_x_preferred":[
        "\u0641\u0631\u0648\u062f\u06af\u0627\u0647 \u0634\u0647\u0631\u0633\u062a\u0627\u0646 \u0646\u0627\u062a\u0686\u0632\u2013\u0622\u062f\u0627\u0645\u0632"
    ],
    "name:fas_x_variant":[
        "\u0641\u0631\u0648\u062f\u06af\u0627\u0647 \u0646\u0627\u062a\u0686\u0632\u2013\u0622\u062f\u0627\u0645\u0632 \u06a9\u0627\u0646\u062a\u06cc"
    ],
    "name:jpn_x_preferred":[
        "Natchez-Adams\u90e1\u7a7a\u6e2f"
    ],
    "name:ron_x_preferred":[
        "Aeroportul Natchez-Adams County"
    ],
    "name:tgk_x_preferred":[
        "\u0424\u0443\u0440\u0443\u0434\u0433\u043e\u04b3\u0438 \u043d\u043e\u0442\u0447\u0437\u2013\u043e\u0434\u043e\u043c\u0437 \u043a\u043e\u043d"
    ],
    "name:urd_x_preferred":[
        "\u0646\u0686\u0632\u2013\u0627\u06cc\u0688\u0645\u0632 \u06a9\u0627\u0624\u0646\u0679\u06cc \u06c1\u0648\u0627\u0626\u06cc \u0627\u0688\u0627"
    ],
    "oa:elevation_ft":"272",
    "oa:type":"small_airport",
    "woe:hierarchy":{
        "country_id":23424977,
        "county_id":12588884,
        "planet_id":1,
        "state_id":2347583
    },
    "wof:name":"Hardy-Anders Field Airport",
    "wof:placetype":"campus"
},
  "geometry": {"coordinates":[-91.297222,31.613611],"type":"Point"}
}