{
  "type": "Feature",
  "properties": {
    "gn:admin1_code":"KY",
    "gn:admin2_code":"27",
    "gn:asciiname":"Glen Dean",
    "gn:country_code":"US",
    "gn:dem":149,
    "gn:elevation":"146.0",
    "gn:feature_class":"P",
    "gn:feature_code":"PPL",
    "gn:name":"Glen Dean",
    "gn:population":0,
    "gn:timezone":"America/Chicago",
    "iso:country":"US",
    "wof:name":"Glen Dean",
    "wof:placetype":"locality"
},
  "geometry": {"coordinates":[-86.54109,37.65339],"type":"Point"}
}