{
  "type": "Feature",
  "properties": {
    "gn:admin1_code":"AR",
    "gn:admin2_code":"47.0",
    "gn:admin3_code":"94005.0",
    "gn:asciiname":"Sutherland Crossroads",
    "gn:country_code":"US",
    "gn:dem":254,
    "gn:elevation":"249.0",
    "gn:feature_class":"P",
    "gn:feature_code":"PPL",
    "gn:name":"Sutherland Crossroads",
    "gn:population":0,
    "gn:timezone":"America/Chicago",
    "iso:country":"US",
    "wof:name":"Sutherland Crossroads",
    "wof:placetype":"locality"
},
  "geometry": {"coordinates":[-93.77075000000001,35.53481],"type":"Point"}
}