{
  "type": "Feature",
  "properties": {
    "gn:admin1_code":"CA",
    "gn:admin2_code":"89.0",
    "gn:asciiname":"Cloverdale",
    "gn:country_code":"US",
    "gn:dem":271,
    "gn:elevation":"271.0",
    "gn:feature_class":"P",
    "gn:feature_code":"PPL",
    "gn:name":"Cloverdale",
    "gn:population":0,
    "gn:timezone":"America/Los_Angeles",
    "iso:country":"US",
    "name:ceb_x_preferred":[
        "Cloverdale"
    ],
    "name:deu_x_preferred":[
        "Cloverdale"
    ],
    "name:fra_x_preferred":[
        "Cloverdale"
    ],
    "name:ita_x_preferred":[
        "Cloverdale"
    ],
    "name:nld_x_preferred":[
        "Cloverdale"
    ],
    "name:pol_x_preferred":[
        "Cloverdale"
    ],
    "name:por_x_preferred":[
        "Cloverdale"
    ],
    "name:rus_x_preferred":[
        "\u041a\u043b\u043e\u0432\u0435\u0440\u0434\u0435\u0439\u043b"
    ],
    "name:spa_x_preferred":[
        "Cloverdale"
    ],
    "name:srp_x_preferred":[
        "\u041a\u043b\u043e\u0432\u0435\u0440\u0434\u0435\u0458\u043b"
    ],
    "name:swe_x_preferred":[
        "Cloverdale"
    ],
    "name:ukr_x_preferred":[
        "\u041a\u043b\u043e\u0443\u0432\u0435\u0440\u0434\u0435\u0439\u043b"
    ],
    "name:vol_x_preferred":[
        "Cloverdale"
    ],
    "wof:name":"Cloverdale",
    "wof:placetype":"locality"
},
  "geometry": {"coordinates":[-122.47584000000001,40.47348],"type":"Point"}
}