{
  "type": "Feature",
  "properties": {
    "iso:country":"US",
    "name:bar_x_preferred":[
        "Bloomingdale"
    ],
    "name:cat_x_preferred":[
        "Bloomingdale"
    ],
    "name:ceb_x_preferred":[
        "Bloomingdale"
    ],
    "name:ces_x_preferred":[
        "Bloomingdale"
    ],
    "name:deu_x_preferred":[
        "Bloomingdale"
    ],
    "name:eng_x_preferred":[
        "Bloomingdale"
    ],
    "name:fra_x_preferred":[
        "Bloomingdale"
    ],
    "name:ita_x_preferred":[
        "Bloomingdale"
    ],
    "name:kor_x_preferred":[
        "\ube14\ub8e8\ubc0d\ub370\uc77c"
    ],
    "name:nld_x_preferred":[
        "Bloomingdale"
    ],
    "name:pol_x_preferred":[
        "Bloomingdale"
    ],
    "name:por_x_preferred":[
        "Bloomingdale"
    ],
    "name:srp_x_preferred":[
        "\u0411\u043b\u0443\u043c\u0438\u043d\u0433\u0434\u0435\u0458\u043b"
    ],
    "name:ukr_x_preferred":[
        "\u0411\u043b\u0443\u043c\u0456\u043d\u0433\u0434\u0435\u0439\u043b"
    ],
    "name:urd_x_preferred":[
        "\u0628\u0644\u0648\u0645\u0646\u06af\u0688\u06cc\u0644"
    ],
    "name:vol_x_preferred":[
        "Bloomingdale"
    ],
    "wof:name":"Bloomingdale",
    "wof:placetype":"neighbourhood",
    "wof:population":1344,
    "zs:area_m":2333009.52703,
    "zs:blockids":[
        420710118042014,
        420710118033008,
        420710118031001,
        420710118042013,
        420710118042000,
        420710118031008,
        420710118033007,
        420710118031007,
        420710118031015,
        420710118031012,
        420710118033009,
        420710118033003,
        420710118031014,
        420710118031009,
        420710118042004,
        420710118031016,
        420710118033004,
        420710118033000,
        420710118033001,
        420710118042006,
        420710118033006,
        420710118031013,
        420710118031011,
        420710118042001,
        420710118033002,
        420710118031010
    ],
    "zs:housing10":511,
    "zs:label":"Bloomingdale",
    "zs:pop10":1344
},
  "geometry": {"coordinates":[-76.29868999999999,40.087922],"type":"Point"}
}