{
  "type": "Feature",
  "properties": {
    "gn:admin1_code":"AR",
    "gn:admin2_code":"43.0",
    "gn:admin3_code":"93786.0",
    "gn:asciiname":"Lewis",
    "gn:country_code":"US",
    "gn:dem":59,
    "gn:elevation":"56.0",
    "gn:feature_class":"P",
    "gn:feature_code":"PPL",
    "gn:name":"Lewis",
    "gn:population":0,
    "gn:timezone":"America/Chicago",
    "iso:country":"US",
    "name:bel_x_preferred":[
        "\u041b\u044c\u044e\u0456\u0441"
    ],
    "name:bre_x_preferred":[
        "Lewis"
    ],
    "name:cat_x_preferred":[
        "Lewis"
    ],
    "name:ceb_x_preferred":[
        "Lewis"
    ],
    "name:ces_x_preferred":[
        "Lewis"
    ],
    "name:dan_x_preferred":[
        "Lewis"
    ],
    "name:deu_x_preferred":[
        "Lewis"
    ],
    "name:eng_x_preferred":[
        "Lewis"
    ],
    "name:est_x_preferred":[
        "Lewis"
    ],
    "name:fin_x_preferred":[
        "Lewis"
    ],
    "name:fra_x_preferred":[
        "Lewis"
    ],
    "name:heb_x_preferred":[
        "\u05dc\u05d5\u05d0\u05d9\u05e1"
    ],
    "name:ita_x_preferred":[
        "Lewis"
    ],
    "name:kor_x_preferred":[
        "\ub8e8\uc774\uc2a4"
    ],
    "name:lav_x_preferred":[
        "L\u016biss"
    ],
    "name:lit_x_preferred":[
        "Lewis"
    ],
    "name:nld_x_preferred":[
        "Lewis"
    ],
    "name:nor_x_preferred":[
        "Lewis"
    ],
    "name:pol_x_preferred":[
        "Lewis"
    ],
    "name:por_x_preferred":[
        "Lewis"
    ],
    "name:rus_x_preferred":[
        "\u041b\u044c\u044e\u0438\u0441"
    ],
    "name:spa_x_preferred":[
        "Lewis"
    ],
    "name:srp_x_preferred":[
        "\u041b\u0443\u0438\u0441"
    ],
    "name:swe_x_preferred":[
        "Lewis"
    ],
    "name:ukr_x_preferred":[
        "\u041b\u044c\u044e\u0457\u0441"
    ],
    "name:und_x_variant":[
        "Lewis Spur"
    ],
    "name:vie_x_preferred":[
        "Lewis"
    ],
    "name:vol_x_preferred":[
        "Lewis"
    ],
    "name:zho_x_preferred":[
        "\u5218\u6613\u65af"
    ],
    "wof:name":"Lewis",
    "wof:placetype":"locality"
},
  "geometry": {"coordinates":[-91.79096,33.48761],"type":"Point"}
}