{
  "type": "Feature",
  "properties": {
    "gn:admin1_code":"IL",
    "gn:admin2_code":"89.0",
    "gn:admin3_code":"23087.0",
    "gn:asciiname":"Williamsburg Green",
    "gn:country_code":"US",
    "gn:dem":279,
    "gn:elevation":"275.0",
    "gn:feature_class":"P",
    "gn:feature_code":"PPL",
    "gn:name":"Williamsburg Green",
    "gn:population":0,
    "gn:timezone":"America/Chicago",
    "iso:country":"US",
    "wof:name":"Williamsburg Green",
    "wof:placetype":"locality"
},
  "geometry": {"coordinates":[-88.35202,42.03058],"type":"Point"}
}