{
  "type": "Feature",
  "properties": {
    "iso:country":"US",
    "name:eng_x_preferred":[
        "Warm Springs Mesa"
    ],
    "qs:gn_adm0_cc":"US",
    "qs:gn_local":5586437,
    "qs:local_max":3422,
    "qs:local_sum":26185,
    "qs:localhoods":36,
    "qs:name":"Warm Springs Mesa",
    "qs:name_adm0":"United States",
    "qs:name_adm1":"Idaho",
    "qs:name_adm2":"Ada",
    "qs:name_local":"Boise",
    "qs:photo_max":91,
    "qs:photo_sum":543,
    "qs:placetype":"Suburb",
    "qs:quad_count":35,
    "qs:woe_adm0":23424977,
    "qs:woe_adm1":2347571,
    "qs:woe_adm2":12588034,
    "qs:woe_lau":0,
    "qs:woe_local":2366355,
    "qs:woe_ver":"7.10.0",
    "wof:lang":[
        "eng"
    ],
    "wof:name":"Warm Springs Mesa",
    "wof:placetype":"neighbourhood",
    "wof:population":2808,
    "zs:blockids":[
        160010008042018,
        160010007021057,
        160010007021032,
        160010008042015,
        160010008051000,
        160010008042033,
        160010007021044,
        160010008051042,
        160010007021000,
        160010007021028,
        160010007021033,
        160010101001153,
        160010007021029,
        160010007021034,
        160010007021048,
        160010007021030,
        160010007021022,
        160010008051003,
        160010008042020,
        160010008051041,
        160010007021026,
        160010008052002,
        160010007021019,
        160010007021021,
        160010008052001,
        160010007021024,
        160010007021025,
        160010007021068,
        160010007021031,
        160010007021066,
        160010007021023,
        160010008042024,
        160010007021062,
        160010007021058,
        160010007021001,
        160010007021018,
        160010007021052,
        160010008041022,
        160010007021061,
        160010007021067
    ],
    "zs:housing10":1339,
    "zs:pop10":2808
},
  "geometry": {"coordinates":[-116.14919,43.586247],"type":"Point"}
}