{
  "type": "Feature",
  "properties": {
    "gn:elevation":8,
    "iso:country":"US",
    "name:bar_x_preferred":[
        "Northwood"
    ],
    "name:cat_x_preferred":[
        "Northwood"
    ],
    "name:ceb_x_preferred":[
        "Northwood"
    ],
    "name:deu_x_preferred":[
        "Northwood"
    ],
    "name:eng_x_preferred":[
        "Northwood"
    ],
    "name:fin_x_preferred":[
        "Northwood"
    ],
    "name:fra_x_preferred":[
        "Northwood"
    ],
    "name:hun_x_preferred":[
        "Northwood"
    ],
    "name:ita_x_preferred":[
        "Northwood"
    ],
    "name:jpn_x_preferred":[
        "\u30ce\u30fc\u30b9\u30a6\u30c3\u30c9"
    ],
    "name:kor_x_preferred":[
        "\ub178\uc2a4\uc6b0\ub4dc"
    ],
    "name:nld_x_preferred":[
        "Northwood"
    ],
    "name:pol_x_preferred":[
        "Northwood"
    ],
    "name:por_x_preferred":[
        "Northwood"
    ],
    "name:rus_x_preferred":[
        "\u041d\u043e\u0440\u0442\u0432\u0443\u0434"
    ],
    "name:srp_x_preferred":[
        "\u041d\u043e\u0440\u0442\u0432\u0443\u0434"
    ],
    "name:swe_x_preferred":[
        "Northwood"
    ],
    "name:vol_x_preferred":[
        "Northwood"
    ],
    "qs:gn_adm0_cc":"US",
    "qs:gn_fcode":"PPLX",
    "qs:gn_local":4588718,
    "qs:gn_nam_loc":"Myrtle Beach, Horry, South Carolina, US",
    "qs:gn_namadm1":"SC",
    "qs:gn_name":"Northwood",
    "qs:local_max":9308,
    "qs:local_sum":20973,
    "qs:localhoods":17,
    "qs:name":"Northwood",
    "qs:name_adm0":"United States",
    "qs:name_adm1":"South Carolina",
    "qs:name_adm2":"Horry",
    "qs:name_local":"Myrtle Beach",
    "qs:photo_max":476,
    "qs:photo_sum":534,
    "qs:placetype":"Suburb",
    "qs:quad_count":9,
    "qs:woe_adm0":23424977,
    "qs:woe_adm1":2347599,
    "qs:woe_adm2":12589825,
    "qs:woe_lau":0,
    "qs:woe_local":2456750,
    "qs:woe_ver":"7.10.0",
    "wof:name":"Northwood",
    "wof:placetype":"neighbourhood",
    "wof:population":411,
    "zs:blockids":[
        450510503031064,
        450510503031077,
        450510503031100,
        450510603081114,
        450510503031070,
        450510503031063,
        450510503031079,
        450510503031073,
        450510501022016,
        450510603081109,
        450510603081101,
        450510503031069,
        450510603081115,
        450510503031062,
        450510503031059,
        450510503031061,
        450510603081107,
        450510503031076,
        450510501022017,
        450510503031078,
        450510503031081,
        450510603081177,
        450510603081108,
        450510503031068,
        450510501022022,
        450510503031065,
        450510603081110,
        450510503031072,
        450510503031074,
        450510503031080,
        450510503031082,
        450510503031066,
        450510603081112,
        450510503031075,
        450510603081113,
        450510603081178,
        450510603081106
    ],
    "zs:housing10":313,
    "zs:pop10":411
},
  "geometry": {"coordinates":[-78.823627,33.758024],"type":"Point"}
}