{
  "type": "Feature",
  "properties": {
    "gn:admin1_code":"WV",
    "gn:admin2_code":"85.0",
    "gn:asciiname":"Washburn",
    "gn:country_code":"US",
    "gn:dem":235,
    "gn:elevation":"229.0",
    "gn:feature_class":"P",
    "gn:feature_code":"PPL",
    "gn:name":"Washburn",
    "gn:population":0,
    "gn:timezone":"America/New_York",
    "iso:country":"US",
    "wof:name":"Washburn",
    "wof:placetype":"locality"
},
  "geometry": {"coordinates":[-81.04678,39.1423],"type":"Point"}
}