{
  "type": "Feature",
  "properties": {
    "gn:admin1_code":"AL",
    "gn:admin2_code":"55",
    "gn:asciiname":"Liberty Hill",
    "gn:country_code":"US",
    "gn:dem":329,
    "gn:elevation":"329.0",
    "gn:feature_class":"P",
    "gn:feature_code":"PPL",
    "gn:name":"Liberty Hill",
    "gn:population":0,
    "gn:timezone":"America/Chicago",
    "iso:country":"US",
    "name:ceb_x_preferred":[
        "Liberty Hill"
    ],
    "name:deu_x_preferred":[
        "Liberty Hill"
    ],
    "name:swe_x_preferred":[
        "Liberty Hill"
    ],
    "wof:name":"Liberty Hill",
    "wof:placetype":"locality"
},
  "geometry": {"coordinates":[-86.03025,34.17787],"type":"Point"}
}