{
  "type": "Feature",
  "properties": {
    "gn:country":"US",
    "gn:fcode":"PPL",
    "gn:population":0,
    "iso:country":"US",
    "name:azb_x_preferred":[
        "\u0631\u06cc\u06a9\u0633\u0644\u06cc\u0648"
    ],
    "name:eng_x_preferred":[
        "Rixlew"
    ],
    "name:fas_x_preferred":[
        "\u0631\u06cc\u06a9\u0633\u200c\u0644\u0648"
    ],
    "name:fra_x_preferred":[
        "Rixlew"
    ],
    "name:vol_x_preferred":[
        "Rixlew"
    ],
    "qs_pg:aaroncc":"US",
    "qs_pg:gn_country":"US",
    "qs_pg:gn_fcode":"PPL",
    "qs_pg:gn_pop":0,
    "qs_pg:name":"Rixlew",
    "qs_pg:name_adm0":"United States",
    "qs_pg:name_adm1":"Virginia",
    "qs_pg:photos":28,
    "qs_pg:photos_1k":6,
    "qs_pg:photos_9k":1,
    "qs_pg:photos_9r":2,
    "qs_pg:photos_all":28,
    "qs_pg:photos_sr":2,
    "qs_pg:pop_sr":0,
    "qs_pg:qs_pg_placetype":"locality",
    "qs_pg:qs_pg_placetype_gp":"Town",
    "qs_pg:woe_adm0":23424977,
    "woe:adm0_id":23424977,
    "woe:name_adm0":"United States",
    "woe:name_adm1":"Virginia",
    "woe:placetype":"Town",
    "wof:name":"Rixlew",
    "wof:placetype":"locality"
},
  "geometry": {"coordinates":[-77.50582,38.76095],"type":"Point"}
}