{
  "type": "Feature",
  "properties": {
    "gn:admin1_code":"SC",
    "gn:admin2_code":"53.0",
    "gn:asciiname":"Ricetown",
    "gn:country_code":"US",
    "gn:dem":14,
    "gn:elevation":"10.0",
    "gn:feature_class":"P",
    "gn:feature_code":"PPL",
    "gn:name":"Ricetown",
    "gn:population":0,
    "gn:timezone":"America/New_York",
    "iso:country":"US",
    "name:eng_x_preferred":[
        "Ricetown"
    ],
    "name:und_x_variant":[
        "Riceshire"
    ],
    "wof:name":"Ricetown",
    "wof:placetype":"locality"
},
  "geometry": {"coordinates":[-80.96677,32.51713],"type":"Point"}
}