{
  "type": "Feature",
  "properties": {
    "gn:admin1_code":"VA",
    "gn:admin2_code":"107",
    "gn:asciiname":"Burns Crossroads",
    "gn:country_code":"US",
    "gn:dem":116,
    "gn:elevation":"117.0",
    "gn:feature_class":"P",
    "gn:feature_code":"PPL",
    "gn:name":"Burns Crossroads",
    "gn:population":0,
    "gn:timezone":"America/New_York",
    "iso:country":"US",
    "wof:name":"Burns Crossroads",
    "wof:placetype":"locality"
},
  "geometry": {"coordinates":[-77.54444000000002,38.90956],"type":"Point"}
}