{
  "type": "Feature",
  "properties": {
    "gn:admin1_code":"PA",
    "gn:admin2_code":"91.0",
    "gn:admin3_code":"44976.0",
    "gn:asciiname":"Cynwyd",
    "gn:country_code":"US",
    "gn:dem":86,
    "gn:elevation":"78.0",
    "gn:feature_class":"P",
    "gn:feature_code":"PPL",
    "gn:name":"Cynwyd",
    "gn:population":0,
    "gn:timezone":"America/New_York",
    "iso:country":"US",
    "name:ceb_x_preferred":[
        "Cynwyd"
    ],
    "name:swe_x_preferred":[
        "Cynwyd"
    ],
    "wof:name":"Cynwyd",
    "wof:placetype":"locality"
},
  "geometry": {"coordinates":[-75.23,40.0109],"type":"Point"}
}