{
  "type": "Feature",
  "properties": {
    "gn:gn_country":"US",
    "gn:gn_fcode":"PPL",
    "gn:gn_pop":0,
    "iso:country":"US",
    "name:deu_x_preferred":[
        "Hildreth"
    ],
    "name:pol_x_preferred":[
        "Hildreth"
    ],
    "name:por_x_preferred":[
        "Hildreth"
    ],
    "name:rus_x_preferred":[
        "\u0425\u0438\u043b\u0434\u0440\u0435\u0442"
    ],
    "name:swe_x_preferred":[
        "Hildreth"
    ],
    "qs_pg:aaroncc":"US",
    "qs_pg:gn_country":"US",
    "qs_pg:gn_fcode":"PPL",
    "qs_pg:gn_pop":0,
    "qs_pg:name":"Hildreth",
    "qs_pg:name_adm0":"United States",
    "qs_pg:name_adm1":"Florida",
    "qs_pg:photos":969,
    "qs_pg:photos_1k":196,
    "qs_pg:photos_9k":4,
    "qs_pg:photos_9r":6,
    "qs_pg:photos_all":969,
    "qs_pg:photos_sr":10,
    "qs_pg:pop_sr":0,
    "qs_pg:qs_pg_placetype":"locality",
    "qs_pg:qs_pg_placetype_gp":"Town",
    "qs_pg:woe_adm0":23424977,
    "woe:adm0_id":23424977,
    "woe:name_adm0":"United States",
    "woe:name_adm1":"Florida",
    "woe:placetype":"Town",
    "wof:name":"Hildreth",
    "wof:placetype":"locality"
},
  "geometry": {"coordinates":[-82.80540000000001,29.95273],"type":"Point"}
}