{
  "type": "Feature",
  "properties": {
    "gn:admin1_code":"FL",
    "gn:admin2_code":"87.0",
    "gn:asciiname":"Paradise Point Mobile Home Park",
    "gn:country_code":"US",
    "gn:dem":6,
    "gn:elevation":"1.0",
    "gn:feature_class":"P",
    "gn:feature_code":"PPL",
    "gn:name":"Paradise Point Mobile Home Park",
    "gn:population":0,
    "gn:timezone":"America/New_York",
    "iso:country":"US",
    "wof:name":"Paradise Point Mobile Home Park",
    "wof:placetype":"campus"
},
  "geometry": {"coordinates":[-80.48981999999999,25.04368],"type":"Point"}
}