{
  "type": "Feature",
  "properties": {
    "gn:admin1_code":"PA",
    "gn:admin2_code":"91",
    "gn:admin3_code":"50640.0",
    "gn:asciiname":"Heather Knoll",
    "gn:country_code":"US",
    "gn:dem":135,
    "gn:elevation":"136.0",
    "gn:feature_class":"P",
    "gn:feature_code":"PPL",
    "gn:name":"Heather Knoll",
    "gn:population":0,
    "gn:timezone":"America/New_York",
    "iso:country":"US",
    "wof:name":"Heather Knoll",
    "wof:placetype":"locality"
},
  "geometry": {"coordinates":[-75.2285,40.2607],"type":"Point"}
}