{
  "type": "Feature",
  "properties": {
    "gn:admin1_code":"OH",
    "gn:admin2_code":"105",
    "gn:admin3_code":"42336.0",
    "gn:asciiname":"Spiller",
    "gn:country_code":"US",
    "gn:dem":213,
    "gn:elevation":"214.0",
    "gn:feature_class":"P",
    "gn:feature_code":"PPL",
    "gn:name":"Spiller",
    "gn:population":0,
    "gn:timezone":"America/New_York",
    "iso:country":"US",
    "name:deu_x_preferred":[
        "Cristiano Spiller"
    ],
    "name:fra_x_preferred":[
        "Spiller"
    ],
    "name:ita_x_preferred":[
        "Spiller"
    ],
    "name:nld_x_preferred":[
        "Spiller"
    ],
    "name:pol_x_preferred":[
        "Spiller"
    ],
    "name:spa_x_preferred":[
        "Spiller"
    ],
    "name:swe_x_preferred":[
        "Spiller"
    ],
    "name:tha_x_preferred":[
        "\u0e2a\u0e1b\u0e34\u0e25\u0e40\u0e25\u0e2d\u0e23\u0e4c"
    ],
    "wof:name":"Spiller",
    "wof:placetype":"locality"
},
  "geometry": {"coordinates":[-81.83986,38.99369],"type":"Point"}
}