{
  "type": "Feature",
  "properties": {
    "gn:elevation":276,
    "iso:country":"US",
    "name:eng_x_preferred":[
        "Clearview Heights"
    ],
    "name:eng_x_variant":[
        "Clearview Hts"
    ],
    "qs:gn_fcode":"PPLX",
    "qs:gn_local":0,
    "qs:gn_namadm1":"TN",
    "qs:gn_name":"Clearview Heights",
    "qs:local_max":3359,
    "qs:local_sum":4173,
    "qs:localhoods":4,
    "qs:name":"Clearview Heights",
    "qs:name_adm0":"United States",
    "qs:name_adm1":"Tennessee",
    "qs:name_adm2":"Lawrence",
    "qs:name_local":"Lawrenceburg",
    "qs:photo_max":2823,
    "qs:photo_sum":3359,
    "qs:placetype":"Suburb",
    "qs:quad_count":10,
    "qs:woe_adm0":23424977,
    "qs:woe_adm1":2347601,
    "qs:woe_adm2":12589961,
    "qs:woe_lau":0,
    "qs:woe_local":2437294,
    "qs:woe_ver":"7.10.0",
    "wof:name":"Clearview Heights",
    "wof:placetype":"neighbourhood",
    "wof:population":660,
    "zs:blockids":[
        470999605011050,
        470999605011035,
        470999605011043,
        470999605011067,
        470999605023017,
        470999605011052,
        470999605011058,
        470999605011041,
        470999605011047,
        470999605023024,
        470999605011048,
        470999605011039,
        470999605011051,
        470999605011057,
        470999605011059,
        470999605011075,
        470999605011042,
        470999605011056,
        470999605011049,
        470999605011040,
        470999605011060
    ],
    "zs:housing10":287,
    "zs:pop10":660
},
  "geometry": {"coordinates":[-87.35075500000001,35.246375],"type":"Point"}
}