{
  "type": "Feature",
  "properties": {
    "iso:country":"US",
    "name:eng_x_preferred":[
        "South East End"
    ],
    "wof:name":"South East End",
    "wof:placetype":"neighbourhood"
},
  "geometry": {"coordinates":[-85.63768677313183,42.9376083904635],"type":"Point"}
}