{
  "type": "Feature",
  "properties": {
    "gn:admin1_code":"TN",
    "gn:admin2_code":"147",
    "gn:asciiname":"Crunk",
    "gn:country_code":"US",
    "gn:dem":212,
    "gn:elevation":"208.0",
    "gn:feature_class":"P",
    "gn:feature_code":"PPL",
    "gn:name":"Crunk",
    "gn:population":0,
    "gn:timezone":"America/Chicago",
    "iso:country":"US",
    "name:bel_x_preferred":[
        "\u041a\u0440\u0430\u043d\u043a"
    ],
    "name:bul_x_preferred":[
        "\u041a\u0440\u044a\u043d\u043a"
    ],
    "name:ces_x_preferred":[
        "Crunk"
    ],
    "name:dan_x_preferred":[
        "Crunk"
    ],
    "name:deu_x_preferred":[
        "Crunk"
    ],
    "name:fas_x_preferred":[
        "\u06a9\u0631\u0627\u0646\u06a9"
    ],
    "name:fin_x_preferred":[
        "Crunk"
    ],
    "name:fra_x_preferred":[
        "Crunk"
    ],
    "name:heb_x_preferred":[
        "\u05e7\u05e8\u05d0\u05e0\u05e7"
    ],
    "name:ita_x_preferred":[
        "Crunk"
    ],
    "name:jpn_x_preferred":[
        "\u30af\u30e9\u30f3\u30af"
    ],
    "name:nld_x_preferred":[
        "Crunk"
    ],
    "name:pol_x_preferred":[
        "Crunk"
    ],
    "name:por_x_preferred":[
        "Crunk"
    ],
    "name:rus_x_preferred":[
        "\u041a\u0440\u0430\u043d\u043a"
    ],
    "name:sco_x_preferred":[
        "Crunk"
    ],
    "name:slk_x_preferred":[
        "Crunk"
    ],
    "name:spa_x_preferred":[
        "Crunk"
    ],
    "name:swe_x_preferred":[
        "Crunk"
    ],
    "name:tha_x_preferred":[
        "\u0e04\u0e23\u0e31\u0e07\u0e01\u0e4c"
    ],
    "name:tur_x_preferred":[
        "Crunk"
    ],
    "wof:name":"Crunk",
    "wof:placetype":"locality"
},
  "geometry": {"coordinates":[-86.89361,36.42394],"type":"Point"}
}