{
  "type": "Feature",
  "properties": {
    "iso:country":"US",
    "name:eng_x_preferred":[
        "Captain's Bay"
    ],
    "wof:name":"Captain's Bay",
    "wof:placetype":"neighbourhood",
    "zs:area_m":6854668.567965,
    "zs:blockids":[
        120710501041017,
        120710501041014,
        120710501041016,
        120710501041018,
        120710501041007,
        120710501041020,
        120710501041019,
        120710501041021,
        120710501041001,
        120710501041006,
        120710501041009,
        120710501041013,
        120710501041008,
        120710501041002,
        120710501041010,
        120710501041011,
        120710501041012,
        120710501041003,
        120710501041004,
        120710501041015,
        120710501041005
    ],
    "zs:housing10":0,
    "zs:label":"Captain's Bay",
    "zs:pop10":0
},
  "geometry": {"coordinates":[-81.868515,26.433475],"type":"Point"}
}