{
  "type": "Feature",
  "properties": {
    "gn:admin1_code":"LA",
    "gn:admin2_code":"33.0",
    "gn:asciiname":"The Myrtles",
    "gn:country_code":"US",
    "gn:dem":16,
    "gn:elevation":"10.0",
    "gn:feature_class":"P",
    "gn:feature_code":"PPL",
    "gn:name":"The Myrtles",
    "gn:population":0,
    "gn:timezone":"America/Chicago",
    "iso:country":"US",
    "wof:name":"The Myrtles",
    "wof:placetype":"locality"
},
  "geometry": {"coordinates":[-91.1126,30.36547],"type":"Point"}
}