{
  "type": "Feature",
  "properties": {
    "gn:admin1_code":"IA",
    "gn:admin2_code":"5.0",
    "gn:admin3_code":"91290.0",
    "gn:asciiname":"Ion",
    "gn:country_code":"US",
    "gn:dem":208,
    "gn:elevation":"208.0",
    "gn:feature_class":"P",
    "gn:feature_code":"PPL",
    "gn:name":"Ion",
    "gn:population":0,
    "gn:timezone":"America/Chicago",
    "iso:country":"US",
    "name:fas_x_preferred":[
        "\u0627\u06cc\u0648\u0646"
    ],
    "name:fra_x_preferred":[
        "Ion"
    ],
    "wof:name":"Ion",
    "wof:placetype":"locality"
},
  "geometry": {"coordinates":[-91.26208,43.11276],"type":"Point"}
}