{
  "type": "Feature",
  "properties": {
    "gn:admin1_code":"PA",
    "gn:admin2_code":"121.0",
    "gn:admin3_code":"61552.0",
    "gn:asciiname":"Sunville",
    "gn:country_code":"US",
    "gn:dem":441,
    "gn:elevation":"437.0",
    "gn:feature_class":"P",
    "gn:feature_code":"PPL",
    "gn:name":"Sunville",
    "gn:population":0,
    "gn:timezone":"America/New_York",
    "iso:country":"US",
    "wof:name":"Sunville",
    "wof:placetype":"locality"
},
  "geometry": {"coordinates":[-79.83478000000002,41.552],"type":"Point"}
}