{
  "type": "Feature",
  "properties": {
    "gn:admin1_code":"SC",
    "gn:admin2_code":"85.0",
    "gn:asciiname":"Walnut Hills",
    "gn:country_code":"US",
    "gn:dem":55,
    "gn:elevation":"54.0",
    "gn:feature_class":"P",
    "gn:feature_code":"PPL",
    "gn:name":"Walnut Hills",
    "gn:population":0,
    "gn:timezone":"America/New_York",
    "iso:country":"US",
    "name:ceb_x_preferred":[
        "Walnut Hills"
    ],
    "wof:name":"Walnut Hills",
    "wof:placetype":"locality"
},
  "geometry": {"coordinates":[-80.34564,33.9496],"type":"Point"}
}