{
  "type": "Feature",
  "properties": {
    "gn:admin1_code":"VA",
    "gn:admin2_code":"161",
    "gn:asciiname":"Wynmere",
    "gn:country_code":"US",
    "gn:dem":352,
    "gn:elevation":"349.0",
    "gn:feature_class":"P",
    "gn:feature_code":"PPL",
    "gn:name":"Wynmere",
    "gn:population":0,
    "gn:timezone":"America/New_York",
    "iso:country":"US",
    "wof:name":"Wynmere",
    "wof:placetype":"locality"
},
  "geometry": {"coordinates":[-80.0217,37.24625],"type":"Point"}
}