{
  "type": "Feature",
  "properties": {
    "gn:elevation":119,
    "iso:country":"US",
    "name:eng_x_preferred":[
        "Booths Corner"
    ],
    "name:eng_x_variant":[
        "Booths Cor"
    ],
    "name:fra_x_preferred":[
        "Booths Corner"
    ],
    "name:und_x_variant":[
        "Booth Corner"
    ],
    "qs:gn_adm0_cc":"US",
    "qs:gn_fcode":"PPL",
    "qs:gn_local":4556543,
    "qs:gn_nam_loc":"Bethel, Delaware, Pennsylvania, US",
    "qs:gn_namadm1":"PA",
    "qs:gn_name":"Booths Corner",
    "qs:local_max":61,
    "qs:local_sum":77,
    "qs:localhoods":2,
    "qs:name":"Booths Corner",
    "qs:name_adm0":"United States",
    "qs:name_adm1":"Pennsylvania",
    "qs:name_adm2":"Delaware",
    "qs:name_local":"Bethel",
    "qs:photo_max":5,
    "qs:photo_sum":16,
    "qs:placetype":"Suburb",
    "qs:quad_count":5,
    "qs:woe_adm0":23424977,
    "qs:woe_adm1":2347597,
    "qs:woe_adm2":12589750,
    "qs:woe_funk":"Parented by a neighborhood",
    "qs:woe_lau":0,
    "qs:woe_local":28745635,
    "qs:woe_ver":"7.10.0",
    "wd:wordcount":91,
    "wof:lang":[
        "eng"
    ],
    "wof:name":"Booths Corner",
    "wof:placetype":"neighbourhood",
    "wof:population":1991,
    "zs:blockids":[
        420454104003002,
        420454104001012,
        420454104001015,
        420454104003012,
        420454104002035,
        420454104002008,
        420454104002034,
        420454104003003,
        420454104003013,
        420454104001011,
        420454104003011,
        420454104003004,
        420454104003005,
        420454104002014,
        420454104002040,
        420454104001019,
        420454104001014,
        420454104001022,
        420454104001013,
        420454104001010,
        420454104001009,
        420454104001020,
        420454104001021
    ],
    "zs:housing10":692,
    "zs:pop10":1991
},
  "geometry": {"coordinates":[-75.49324,39.841496],"type":"Point"}
}