{
  "type": "Feature",
  "properties": {
    "gn:admin1_code":"TX",
    "gn:admin2_code":"5.0",
    "gn:asciiname":"Cedar Grove",
    "gn:country_code":"US",
    "gn:dem":112,
    "gn:elevation":"103.0",
    "gn:feature_class":"P",
    "gn:feature_code":"PPL",
    "gn:name":"Cedar Grove",
    "gn:population":0,
    "gn:timezone":"America/Chicago",
    "iso:country":"US",
    "name:ceb_x_preferred":[
        "Cedar Grove"
    ],
    "name:deu_x_preferred":[
        "Cedar Grove"
    ],
    "name:ita_x_preferred":[
        "Cedar Grove"
    ],
    "name:kor_x_preferred":[
        "\uc2dc\ub354\uadf8\ub85c\ube0c"
    ],
    "name:nld_x_preferred":[
        "Cedar Grove"
    ],
    "name:pol_x_preferred":[
        "Cedar Grove"
    ],
    "name:por_x_preferred":[
        "Cedar Grove"
    ],
    "name:spa_x_preferred":[
        "Cedar Grove"
    ],
    "name:srp_x_preferred":[
        "\u0421\u0438\u0434\u0430\u0440 \u0413\u0440\u043e\u0443\u0432"
    ],
    "name:swe_x_preferred":[
        "Cedar Grove"
    ],
    "name:ukr_x_preferred":[
        "\u0421\u0456\u0434\u0430\u0440-\u0413\u0440\u043e\u0443\u0432"
    ],
    "name:vol_x_preferred":[
        "Cedar Grove"
    ],
    "wof:name":"Cedar Grove",
    "wof:placetype":"locality"
},
  "geometry": {"coordinates":[-94.73299,31.38491],"type":"Point"}
}