{
  "type": "Feature",
  "properties": {
    "gn:admin1_code":"NY",
    "gn:admin2_code":"83.0",
    "gn:admin3_code":"58805.0",
    "gn:asciiname":"Ives Corner",
    "gn:country_code":"US",
    "gn:dem":288,
    "gn:elevation":"283.0",
    "gn:feature_class":"P",
    "gn:feature_code":"PPL",
    "gn:name":"Ives Corner",
    "gn:population":0,
    "gn:timezone":"America/New_York",
    "iso:country":"US",
    "wof:name":"Ives Corner",
    "wof:placetype":"locality"
},
  "geometry": {"coordinates":[-73.52566999999998,42.68563],"type":"Point"}
}