{
  "type": "Feature",
  "properties": {
    "gn:admin1_code":"VA",
    "gn:admin2_code":"550",
    "gn:asciiname":"Riverdale",
    "gn:country_code":"US",
    "gn:dem":7,
    "gn:elevation":"4.0",
    "gn:feature_class":"P",
    "gn:feature_code":"PPL",
    "gn:name":"Riverdale",
    "gn:population":0,
    "gn:timezone":"America/New_York",
    "iso:country":"US",
    "name:ara_x_preferred":[
        "\u0631\u064a\u0641\u0631\u062f\u064a\u0644"
    ],
    "name:cat_x_preferred":[
        "Riverdale"
    ],
    "name:ceb_x_preferred":[
        "Riverdale"
    ],
    "name:ces_x_preferred":[
        "Riverdale"
    ],
    "name:deu_x_preferred":[
        "Riverdale"
    ],
    "name:fra_x_preferred":[
        "Riverdale"
    ],
    "name:ita_x_preferred":[
        "Riverdale"
    ],
    "name:kor_x_preferred":[
        "\ub9ac\ubc84\ub370\uc77c"
    ],
    "name:nld_x_preferred":[
        "Riverdale"
    ],
    "name:pol_x_preferred":[
        "Riverdale"
    ],
    "name:por_x_preferred":[
        "Riverdale"
    ],
    "name:rus_x_preferred":[
        "\u0420\u0438\u0432\u0435\u0440\u0434\u0435\u0439\u043b"
    ],
    "name:srp_x_preferred":[
        "\u0420\u0438\u0432\u0435\u0440\u0434\u0435\u0458\u043b"
    ],
    "name:ukr_x_preferred":[
        "\u0420\u0456\u0432\u0435\u0440\u0434\u0435\u0439\u043b"
    ],
    "name:vol_x_preferred":[
        "Riverdale"
    ],
    "wof:name":"Riverdale",
    "wof:placetype":"locality"
},
  "geometry": {"coordinates":[-76.24744,36.80987],"type":"Point"}
}