{
  "type": "Feature",
  "properties": {
    "iso:country":"US",
    "name:bel_x_preferred":[
        "\u0428\u044b\u043b\u0430"
    ],
    "name:cat_x_preferred":[
        "Shiloh"
    ],
    "name:ceb_x_preferred":[
        "Shiloh"
    ],
    "name:deu_x_preferred":[
        "Shiloh"
    ],
    "name:eng_x_preferred":[
        "Shiloh"
    ],
    "name:fra_x_preferred":[
        "Shiloh"
    ],
    "name:heb_x_preferred":[
        "\u05e9\u05d9\u05dc\u05d4"
    ],
    "name:ita_x_preferred":[
        "Shiloh"
    ],
    "name:nld_x_preferred":[
        "Shiloh"
    ],
    "name:pol_x_preferred":[
        "Shiloh"
    ],
    "name:rus_x_preferred":[
        "\u0428\u0438\u043b\u043e"
    ],
    "name:spa_x_preferred":[
        "Shiloh"
    ],
    "name:srp_x_preferred":[
        "\u0428\u0430\u0458\u043b\u043e"
    ],
    "name:swe_x_preferred":[
        "Shiloh"
    ],
    "name:ukr_x_preferred":[
        "\u0428\u0438\u043b\u043e"
    ],
    "name:vol_x_preferred":[
        "Shiloh"
    ],
    "wof:name":"Shiloh",
    "wof:placetype":"neighbourhood",
    "wof:population":1092,
    "zs:blockids":[
        230010400002032,
        230010400002027,
        230010400002046,
        230010400002034,
        230010400002030,
        230010400002026,
        230010400002033,
        230010400002031,
        230050113001003,
        230050113001000,
        230050113001005,
        230050113001002,
        230050113001004,
        230050113001001,
        230239703011010
    ],
    "zs:housing10":443,
    "zs:label":"Shiloh",
    "zs:pop10":1092
},
  "geometry": {"coordinates":[-70.012108,43.980019],"type":"Point"}
}