{
  "type": "Feature",
  "properties": {
    "iso:country":"US",
    "name:arz_x_preferred":[
        "\u0645\u0637\u0627\u0631 \u062f\u0631\u0627\u062c\u0648\u0646 \u0645\u064a\u0644\u0631 \u0633\u064a\u0646\u062a\u0631\u0627\u0644 \u062a\u0643\u0633\u0627\u0633 \u0627\u0644\u0627\u0642\u0644\u064a\u0645\u0649"
    ],
    "name:ceb_x_preferred":[
        "Draughon-Miller Central Texas Regional Airport"
    ],
    "name:eng_x_preferred":[
        "Draughon-Miller Central Texas Regional Airport"
    ],
    "name:eng_x_variant":[
        "TPL",
        "KTPL"
    ],
    "name:fas_x_preferred":[
        "\u0641\u0631\u0648\u062f\u06af\u0627\u0647 \u062f\u0631\u0627\u06af\u0648\u0646-\u0645\u06cc\u0644\u0631 \u0645\u0646\u0637\u0642\u0647 \u0645\u0631\u06a9\u0632\u06cc \u062a\u06af\u0632\u0627\u0633"
    ],
    "name:jpn_x_preferred":[
        "Draughon-Miller Central Texas\u5730\u57df\u7a7a\u6e2f"
    ],
    "name:ron_x_preferred":[
        "Aeroportul Regional Draughon-Miller Central Texas"
    ],
    "name:tgk_x_preferred":[
        "\u0424\u0443\u0440\u0443\u0434\u0433\u043e\u04b3\u0438 \u0434\u0440\u043e\u0433\u0443\u043d-\u043c\u0435\u043b\u0438\u0440 \u043c\u0430\u043d\u0442\u0430\u049b\u0430 \u043c\u0430\u0440\u043a\u0430\u0437\u0435 \u0442\u0438\u0433\u0437\u043e\u0441"
    ],
    "name:urd_x_preferred":[
        "\u0688\u0631\u0627\u06c1\u0648\u0646\u2013\u0645\u0644\u0631 \u0633\u06cc\u0646\u0679\u0631\u0644 \u0679\u06cc\u06a9\u0633\u0627\u0633 \u0631\u06cc\u062c\u0646\u0644 \u0627\u06cc\u0626\u0631\u067e\u0648\u0631\u0679"
    ],
    "oa:elevation_ft":"682",
    "oa:type":"medium_airport",
    "wd:wordcount":693,
    "woe:hierarchy":{
        "country_id":23424977,
        "county_id":12590020,
        "planet_id":1,
        "state_id":2347602
    },
    "wof:name":"Draughon-Miller Central Texas Regional Airport",
    "wof:placetype":"campus"
},
  "geometry": {"coordinates":[-97.407799,31.1525],"type":"Point"}
}