{
  "type": "Feature",
  "properties": {
    "gn:admin1_code":"OH",
    "gn:admin2_code":"21.0",
    "gn:admin3_code":"33796.0",
    "gn:asciiname":"Springhills",
    "gn:country_code":"US",
    "gn:dem":321,
    "gn:elevation":"321.0",
    "gn:feature_class":"P",
    "gn:feature_code":"PPL",
    "gn:name":"Springhills",
    "gn:population":0,
    "gn:timezone":"America/New_York",
    "iso:country":"US",
    "name:eng_x_preferred":[
        "Springhills"
    ],
    "name:und_x_variant":[
        "Middleburg",
        "West Middleburg",
        "Springhills Village",
        "Springhill",
        "Spring Hills"
    ],
    "name:vol_x_preferred":[
        "Springhills"
    ],
    "wof:name":"Springhills",
    "wof:placetype":"locality"
},
  "geometry": {"coordinates":[-83.86966,40.25561],"type":"Point"}
}