{
  "type": "Feature",
  "properties": {
    "gn:admin1_code":"SC",
    "gn:admin2_code":"51.0",
    "gn:asciiname":"Floyds Crossroads",
    "gn:country_code":"US",
    "gn:dem":16,
    "gn:elevation":"22.0",
    "gn:feature_class":"P",
    "gn:feature_code":"PPL",
    "gn:name":"Floyds Crossroads",
    "gn:population":0,
    "gn:timezone":"America/New_York",
    "iso:country":"US",
    "name:eng_x_preferred":[
        "Floyds Crossroads"
    ],
    "name:und_x_variant":[
        "Floyds"
    ],
    "wof:name":"Floyds Crossroads",
    "wof:placetype":"locality"
},
  "geometry": {"coordinates":[-79.10754,34.21461],"type":"Point"}
}