{
  "type": "Feature",
  "properties": {
    "gn:admin1_code":"FL",
    "gn:admin2_code":"57",
    "gn:asciiname":"Garden Grove",
    "gn:country_code":"US",
    "gn:dem":25,
    "gn:elevation":"21.0",
    "gn:feature_class":"P",
    "gn:feature_code":"PPL",
    "gn:name":"Garden Grove",
    "gn:population":0,
    "gn:timezone":"America/New_York",
    "iso:country":"US",
    "name:ceb_x_preferred":[
        "Garden Grove"
    ],
    "name:ces_x_preferred":[
        "Garden Grove"
    ],
    "name:deu_x_preferred":[
        "Garden Grove"
    ],
    "name:fra_x_preferred":[
        "Garden Grove"
    ],
    "name:ita_x_preferred":[
        "Garden Grove"
    ],
    "name:pol_x_preferred":[
        "Garden Grove"
    ],
    "name:por_x_preferred":[
        "Garden Grove"
    ],
    "name:srp_x_preferred":[
        "\u0413\u0430\u0440\u0434\u0435\u043d \u0413\u0440\u043e\u0443\u0432"
    ],
    "name:swe_x_preferred":[
        "Garden Grove"
    ],
    "name:szl_x_preferred":[
        "Garden Grove"
    ],
    "name:ukr_x_preferred":[
        "\u0413\u0430\u0440\u0434\u0435\u043d-\u0413\u0440\u043e\u0443\u0432"
    ],
    "name:vie_x_preferred":[
        "Garden Grove"
    ],
    "name:vol_x_preferred":[
        "Garden Grove"
    ],
    "wof:name":"Garden Grove",
    "wof:placetype":"locality"
},
  "geometry": {"coordinates":[-82.47620000000001,28.144],"type":"Point"}
}