{
  "type": "Feature",
  "properties": {
    "gn:admin1_code":"MD",
    "gn:admin2_code":"3.0",
    "gn:asciiname":"Blackwalnut Cove",
    "gn:country_code":"US",
    "gn:dem":8,
    "gn:elevation":"3.0",
    "gn:feature_class":"P",
    "gn:feature_code":"PPL",
    "gn:name":"Blackwalnut Cove",
    "gn:population":0,
    "gn:timezone":"America/New_York",
    "iso:country":"US",
    "wof:name":"Blackwalnut Cove",
    "wof:placetype":"locality"
},
  "geometry": {"coordinates":[-76.48024000000002,38.93761],"type":"Point"}
}