{
  "type": "Feature",
  "properties": {
    "gn:admin1_code":"FL",
    "gn:admin2_code":"11.0",
    "gn:asciiname":"Crystal Lake",
    "gn:country_code":"US",
    "gn:dem":9,
    "gn:elevation":"4.0",
    "gn:feature_class":"P",
    "gn:feature_code":"PPL",
    "gn:name":"Crystal Lake",
    "gn:population":0,
    "gn:timezone":"America/New_York",
    "iso:country":"US",
    "name:cat_x_preferred":[
        "Crystal Lake"
    ],
    "name:ceb_x_preferred":[
        "Crystal Lake"
    ],
    "name:deu_x_preferred":[
        "Crystal Lake"
    ],
    "name:fra_x_preferred":[
        "Crystal Lake"
    ],
    "name:ita_x_preferred":[
        "Crystal Lake"
    ],
    "name:nld_x_preferred":[
        "Crystal Lake"
    ],
    "name:pol_x_preferred":[
        "Crystal Lake"
    ],
    "name:por_x_preferred":[
        "Crystal Lake"
    ],
    "name:spa_x_preferred":[
        "Crystal Lake"
    ],
    "name:srp_x_preferred":[
        "\u041a\u0440\u0438\u0441\u0442\u0430\u043b \u041b\u0435\u0458\u043a"
    ],
    "name:swe_x_preferred":[
        "Crystal Lake"
    ],
    "name:ukr_x_preferred":[
        "\u041a\u0440\u0438\u0441\u0442\u0430\u043b-\u041b\u0435\u0439\u043a"
    ],
    "name:vol_x_preferred":[
        "Crystal Lake"
    ],
    "wof:name":"Crystal Lake",
    "wof:placetype":"locality"
},
  "geometry": {"coordinates":[-80.14004,26.28564],"type":"Point"}
}