{
  "type": "Feature",
  "properties": {
    "gn:admin1_code":"ME",
    "gn:admin2_code":"3.0",
    "gn:admin3_code":"33385.0",
    "gn:asciiname":"Hodgdon Corners",
    "gn:country_code":"US",
    "gn:dem":145,
    "gn:elevation":"145.0",
    "gn:feature_class":"P",
    "gn:feature_code":"PPL",
    "gn:name":"Hodgdon Corners",
    "gn:population":0,
    "gn:timezone":"America/New_York",
    "iso:country":"US",
    "wof:name":"Hodgdon Corners",
    "wof:placetype":"locality"
},
  "geometry": {"coordinates":[-67.85918000000001,46.04228],"type":"Point"}
}