{
  "type": "Feature",
  "properties": {
    "gn:admin1_code":"MS",
    "gn:admin2_code":"27.0",
    "gn:asciiname":"Hillhouse",
    "gn:country_code":"US",
    "gn:dem":47,
    "gn:elevation":"47.0",
    "gn:feature_class":"P",
    "gn:feature_code":"PPL",
    "gn:name":"Hillhouse",
    "gn:population":0,
    "gn:timezone":"America/Chicago",
    "iso:country":"US",
    "wof:name":"Hillhouse",
    "wof:placetype":"locality"
},
  "geometry": {"coordinates":[-90.81816000000001,34.12566],"type":"Point"}
}