{
  "type": "Feature",
  "properties": {
    "gn:admin1_code":"VA",
    "gn:admin2_code":"95",
    "gn:asciiname":"Centerville",
    "gn:country_code":"US",
    "gn:dem":38,
    "gn:elevation":"31.0",
    "gn:feature_class":"P",
    "gn:feature_code":"PPL",
    "gn:name":"Centerville",
    "gn:population":0,
    "gn:timezone":"America/New_York",
    "iso:country":"US",
    "name:cat_x_preferred":[
        "Centerville"
    ],
    "name:ceb_x_preferred":[
        "Centerville"
    ],
    "name:ces_x_preferred":[
        "Centerville"
    ],
    "name:deu_x_preferred":[
        "Centerville"
    ],
    "name:fra_x_preferred":[
        "Centerville"
    ],
    "name:ido_x_preferred":[
        "Centerville"
    ],
    "name:ita_x_preferred":[
        "Centerville"
    ],
    "name:nld_x_preferred":[
        "Centerville"
    ],
    "name:pol_x_preferred":[
        "Centerville"
    ],
    "name:por_x_preferred":[
        "Centerville"
    ],
    "name:rus_x_preferred":[
        "\u0421\u0435\u043d\u0442\u0435\u0440\u0432\u0438\u043b\u043b"
    ],
    "name:spa_x_preferred":[
        "Centerville"
    ],
    "name:srp_x_preferred":[
        "\u0421\u0435\u043d\u0442\u0435\u0440\u0432\u0438\u043b"
    ],
    "name:swe_x_preferred":[
        "Centerville"
    ],
    "name:urd_x_preferred":[
        "\u0633\u06cc\u0646\u0679\u0631\u0648\u06cc\u0644"
    ],
    "name:vol_x_preferred":[
        "Centerville"
    ],
    "wof:name":"Centerville",
    "wof:placetype":"locality"
},
  "geometry": {"coordinates":[-76.78913,37.31681],"type":"Point"}
}