{
  "type": "Feature",
  "properties": {
    "gn:admin1_code":"CT",
    "gn:admin2_code":"9.0",
    "gn:admin3_code":"52070.0",
    "gn:asciiname":"Raynham",
    "gn:country_code":"US",
    "gn:dem":24,
    "gn:elevation":"28.0",
    "gn:feature_class":"P",
    "gn:feature_code":"PPL",
    "gn:name":"Raynham",
    "gn:population":0,
    "gn:timezone":"America/New_York",
    "iso:country":"US",
    "name:ceb_x_preferred":[
        "Raynham"
    ],
    "name:deu_x_preferred":[
        "Raynham"
    ],
    "name:ita_x_preferred":[
        "Raynham"
    ],
    "name:nld_x_preferred":[
        "Raynham"
    ],
    "name:pol_x_preferred":[
        "Raynham"
    ],
    "name:swe_x_preferred":[
        "Raynham"
    ],
    "name:vol_x_preferred":[
        "Raynham"
    ],
    "wof:name":"Raynham",
    "wof:placetype":"locality"
},
  "geometry": {"coordinates":[-72.89649,41.27482],"type":"Point"}
}