{
  "type": "Feature",
  "properties": {
    "gn:elevation":258,
    "iso:country":"US",
    "name:bel_x_preferred":[
        "\u041f\u0430\u045e\u044d\u043b"
    ],
    "name:cat_x_preferred":[
        "Powell"
    ],
    "name:ceb_x_preferred":[
        "Powell"
    ],
    "name:ces_x_preferred":[
        "Powell"
    ],
    "name:deu_x_preferred":[
        "Powell"
    ],
    "name:ell_x_preferred":[
        "\u03a0\u03ac\u03bf\u03c5\u03b5\u03bb"
    ],
    "name:eng_x_preferred":[
        "Powell"
    ],
    "name:epo_x_preferred":[
        "Powell"
    ],
    "name:est_x_preferred":[
        "Powell"
    ],
    "name:fin_x_preferred":[
        "Powell"
    ],
    "name:fra_x_preferred":[
        "Powell"
    ],
    "name:heb_x_preferred":[
        "\u05e4\u05d0\u05d5\u05d5\u05dc"
    ],
    "name:ind_x_preferred":[
        "Powell"
    ],
    "name:ita_x_preferred":[
        "Powell"
    ],
    "name:jpn_x_preferred":[
        "\u30d1\u30a6\u30a8\u30eb"
    ],
    "name:lav_x_preferred":[
        "Powell"
    ],
    "name:lit_x_preferred":[
        "Powell"
    ],
    "name:nld_x_preferred":[
        "Powell"
    ],
    "name:pol_x_preferred":[
        "Powell"
    ],
    "name:por_x_preferred":[
        "Powell"
    ],
    "name:rus_x_preferred":[
        "\u041f\u0430\u0443\u044d\u043b\u043b"
    ],
    "name:slv_x_preferred":[
        "Powell"
    ],
    "name:srp_x_preferred":[
        "\u041f\u0430\u0443\u0435\u043b"
    ],
    "name:swe_x_preferred":[
        "Powell"
    ],
    "name:ukr_x_preferred":[
        "\u041f\u0430\u0443\u0435\u043b\u043b"
    ],
    "name:vol_x_preferred":[
        "Powell"
    ],
    "name:zho_x_preferred":[
        "\u9b91\u5a01\u723e"
    ],
    "qs:gn_adm0_cc":"US",
    "qs:gn_fcode":"PPL",
    "qs:gn_local":5059429,
    "qs:gn_nam_loc":"Grand Forks, Grand Forks, North Dakota, US",
    "qs:gn_namadm1":"ND",
    "qs:gn_name":"Powell",
    "qs:local_max":845,
    "qs:local_sum":850,
    "qs:localhoods":2,
    "qs:name":"Powell",
    "qs:name_adm0":"United States",
    "qs:name_adm1":"North Dakota",
    "qs:name_adm2":"Grand Forks",
    "qs:name_local":"Grand Forks",
    "qs:photo_max":3,
    "qs:photo_sum":5,
    "qs:placetype":"Suburb",
    "qs:quad_count":3,
    "qs:woe_adm0":23424977,
    "qs:woe_adm1":2347593,
    "qs:woe_adm2":12589491,
    "qs:woe_lau":0,
    "qs:woe_local":2412788,
    "qs:woe_ver":"7.10.0",
    "wof:lang":[
        "eng"
    ],
    "wof:name":"Powell",
    "wof:placetype":"neighbourhood",
    "wof:population":135,
    "zs:blockids":[
        380350117002163,
        380350117002033,
        380350117002036,
        380350117002009,
        380350117002032,
        380350117002011,
        380350117002037,
        380350117002038,
        380350117002035
    ],
    "zs:housing10":52,
    "zs:pop10":135
},
  "geometry": {"coordinates":[-97.17791699999999,47.924809],"type":"Point"}
}