{
  "type": "Feature",
  "properties": {
    "gn:admin1_code":"IL",
    "gn:admin2_code":"197",
    "gn:admin3_code":"21241.0",
    "gn:asciiname":"Stonegate",
    "gn:country_code":"US",
    "gn:dem":233,
    "gn:elevation":"234.0",
    "gn:feature_class":"P",
    "gn:feature_code":"PPL",
    "gn:name":"Stonegate",
    "gn:population":0,
    "gn:timezone":"America/Chicago",
    "iso:country":"US",
    "wof:name":"Stonegate",
    "wof:placetype":"locality"
},
  "geometry": {"coordinates":[-88.03333000000001,41.70083],"type":"Point"}
}