{
  "type": "Feature",
  "properties": {
    "gn:admin1_code":"OH",
    "gn:admin2_code":"75.0",
    "gn:admin3_code":"67286.0",
    "gn:asciiname":"Miley Crossroads",
    "gn:country_code":"US",
    "gn:dem":351,
    "gn:elevation":"352.0",
    "gn:feature_class":"P",
    "gn:feature_code":"PPL",
    "gn:name":"Miley Crossroads",
    "gn:population":0,
    "gn:timezone":"America/New_York",
    "iso:country":"US",
    "wof:name":"Miley Crossroads",
    "wof:placetype":"locality"
},
  "geometry": {"coordinates":[-82.08793,40.62423],"type":"Point"}
}