{
  "type": "Feature",
  "properties": {
    "gn:admin1_code":"CA",
    "gn:admin2_code":"35.0",
    "gn:asciiname":"Pine Town",
    "gn:country_code":"US",
    "gn:dem":1551,
    "gn:elevation":"1551.0",
    "gn:feature_class":"P",
    "gn:feature_code":"PPL",
    "gn:name":"Pine Town",
    "gn:population":0,
    "gn:timezone":"America/Los_Angeles",
    "iso:country":"US",
    "name:eng_x_preferred":[
        "Pine Town"
    ],
    "name:und_x_variant":[
        "Old Town"
    ],
    "name:zho_x_preferred":[
        "\u6d3e\u6069\u93ae"
    ],
    "wof:name":"Pine Town",
    "wof:placetype":"locality"
},
  "geometry": {"coordinates":[-120.99079,40.30406],"type":"Point"}
}