{
  "type": "Feature",
  "properties": {
    "iso:country":"US",
    "name:eng_x_preferred":[
        "Herricks"
    ],
    "qs:gn_adm0_cc":"US",
    "qs:gn_fcode":"PPL",
    "qs:gn_local":4959371,
    "qs:gn_nam_loc":"brooksville",
    "qs:gn_namadm1":"ME",
    "qs:gn_name":"Herricks",
    "qs:local_max":77,
    "qs:local_sum":165,
    "qs:localhoods":4,
    "qs:name":"Herricks",
    "qs:name_adm0":"United States",
    "qs:name_adm1":"Maine",
    "qs:name_adm2":"Hancock",
    "qs:name_local":"Brooksville",
    "qs:photo_max":14,
    "qs:photo_sum":27,
    "qs:placetype":"Suburb",
    "qs:quad_count":7,
    "qs:woe_adm0":23424977,
    "qs:woe_adm1":2347578,
    "qs:woe_adm2":12588664,
    "qs:woe_lau":0,
    "qs:woe_local":2370130,
    "qs:woe_ver":"7.10.0",
    "wof:lang":[
        "eng"
    ],
    "wof:name":"Herricks",
    "wof:placetype":"neighbourhood",
    "wof:population":145,
    "zs:blockids":[
        230099665002035,
        230099665003054,
        230099665002034,
        230099665003056,
        230099665002045,
        230099665002026,
        230099665002046,
        230099665002040,
        230099665002068,
        230099665002017,
        230099665002019,
        230099665003053,
        230099665003106,
        230099665002066,
        230099665003051,
        230099665002041,
        230099665002027,
        230099665002042,
        230099665003105,
        230099665002044,
        230099665002028,
        230099665002064,
        230099665002043,
        230099665003052,
        230099665003049,
        230099665003048,
        230099665003047,
        230099665003055,
        230099665002039,
        230099665002065,
        230099665002067,
        230099665002031,
        230099665002029,
        230099665002033,
        230099665003117,
        230099665002020,
        230099665002069,
        230099665002037,
        230099665002036,
        230099665002038,
        230099665002032,
        230099665002030,
        230099665003116,
        230099665003050
    ],
    "zs:housing10":183,
    "zs:pop10":145
},
  "geometry": {"coordinates":[-68.686626,44.320574],"type":"Point"}
}