{
  "type": "Feature",
  "properties": {
    "iso:country":"US",
    "name:ceb_x_preferred":[
        "Crown Point"
    ],
    "name:deu_x_preferred":[
        "Crown Point"
    ],
    "name:eng_x_preferred":[
        "Crown Point"
    ],
    "name:fra_x_preferred":[
        "Crown Point"
    ],
    "name:ita_x_preferred":[
        "Crown Point"
    ],
    "name:nld_x_preferred":[
        "Crown Point"
    ],
    "name:pol_x_preferred":[
        "Crown Point"
    ],
    "name:rus_x_preferred":[
        "\u041a\u0440\u0430\u0443\u043d-\u041f\u043e\u0439\u043d\u0442"
    ],
    "name:snd_x_preferred":[
        "\u06aa\u0631\u0627\u0624\u0646 \u067e\u0648\u0627\u0626\u0646\u067d"
    ],
    "name:srp_x_preferred":[
        "\u041a\u0440\u0430\u0443\u043d \u041f\u043e\u0458\u043d\u0442"
    ],
    "name:swe_x_preferred":[
        "Crown Point"
    ],
    "name:ukr_x_preferred":[
        "\u041a\u0440\u0430\u0443\u043d-\u041f\u043e\u0439\u043d\u0442"
    ],
    "name:urd_x_preferred":[
        "\u06a9\u0631\u0627\u0624\u0646 \u067e\u0648\u0627\u0626\u0646\u0679"
    ],
    "name:vol_x_preferred":[
        "Crown Point"
    ],
    "wof:name":"Crown Point",
    "wof:placetype":"neighbourhood",
    "wof:population":1250,
    "zs:area_m":296387.840335,
    "zs:blockids":[
        517100070011063,
        517100070011053,
        517100070011068,
        517100070011055,
        517100070011054,
        517100070011067,
        517100070011010,
        517100070011048,
        517100070011052,
        517100070011071,
        517100070011009,
        517100070011057,
        517100070011024,
        517100070011012,
        517100070011005,
        517100070011069,
        517100070011019,
        517100070011064,
        517100070011017,
        517100070011020,
        517100070011060,
        517100070011051,
        517100070011018,
        517100070011056,
        517100070011016,
        517100070011061,
        517100070011023,
        517100070011015,
        517100070011011,
        517100070011059,
        517100070011065,
        517100070011006,
        517100070011004,
        517100070011066,
        517100070011047,
        517100070011062,
        517100070011002,
        517100070011049,
        517100070011050,
        517100070011022,
        517100070011003,
        517100070011058,
        517100070011008,
        517100070011070
    ],
    "zs:housing10":459,
    "zs:label":"Crown Point",
    "zs:pop10":1250
},
  "geometry": {"coordinates":[-76.220061,36.85969],"type":"Point"}
}