{
  "type": "Feature",
  "properties": {
    "gn:admin1_code":"MA",
    "gn:admin2_code":"13.0",
    "gn:admin3_code":"840.0",
    "gn:asciiname":"Shea Corner",
    "gn:country_code":"US",
    "gn:dem":66,
    "gn:elevation":"64.0",
    "gn:feature_class":"P",
    "gn:feature_code":"PPL",
    "gn:name":"Shea Corner",
    "gn:population":0,
    "gn:timezone":"America/New_York",
    "iso:country":"US",
    "wof:name":"Shea Corner",
    "wof:placetype":"locality"
},
  "geometry": {"coordinates":[-72.70093,42.04176],"type":"Point"}
}