{
  "type": "Feature",
  "properties": {
    "iso:country":"US",
    "name:eng_x_preferred":[
        "Eastern South Hill"
    ],
    "name:eng_x_variant":[
        "Eastern South Hl"
    ],
    "qs:gn_adm0_cc":"US",
    "qs:gn_local":5122432,
    "qs:gn_nam_loc":"Ithaca, Tompkins, New York, US",
    "qs:gn_namadm1":"NY",
    "qs:local_max":6849,
    "qs:local_sum":28362,
    "qs:localhoods":22,
    "qs:name":"Eastern South Hill",
    "qs:name_adm0":"United States",
    "qs:name_adm1":"New York",
    "qs:name_adm2":"Tompkins",
    "qs:name_local":"Ithaca",
    "qs:photo_max":21,
    "qs:photo_sum":24,
    "qs:placetype":"Suburb",
    "qs:quad_count":2,
    "qs:woe_adm0":23424977,
    "qs:woe_adm1":2347591,
    "qs:woe_adm2":12589366,
    "qs:woe_funk":"Grouping neighborhood",
    "qs:woe_lau":0,
    "qs:woe_local":2427936,
    "qs:woe_ver":"7.10.0",
    "wof:lang":[
        "eng"
    ],
    "wof:name":"Eastern South Hill",
    "wof:placetype":"neighbourhood",
    "wof:population":1472,
    "zs:blockids":[
        361090012001000,
        361090011001009,
        361090011001004,
        361090011002007,
        361090011002008,
        361090011001036,
        361090011002009,
        361090011003010,
        361090011001002,
        361090011001007,
        361090011003009,
        361090011001010,
        361090012001001,
        361090011002006,
        361090011001011,
        361090011001008,
        361090011001003,
        361090011001001
    ],
    "zs:housing10":514,
    "zs:pop10":1472
},
  "geometry": {"coordinates":[-76.490589,42.430555],"type":"Point"}
}