{
  "type": "Feature",
  "properties": {
    "gn:admin1_code":"IL",
    "gn:admin2_code":"163",
    "gn:admin3_code":"12210.0",
    "gn:asciiname":"Briar Hill",
    "gn:country_code":"US",
    "gn:dem":184,
    "gn:elevation":"175.0",
    "gn:feature_class":"P",
    "gn:feature_code":"PPL",
    "gn:name":"Briar Hill",
    "gn:population":0,
    "gn:timezone":"America/Chicago",
    "iso:country":"US",
    "name:ceb_x_preferred":[
        "Briar Hill"
    ],
    "name:mlg_x_preferred":[
        "Briar Hill"
    ],
    "wof:name":"Briar Hill",
    "wof:placetype":"locality"
},
  "geometry": {"coordinates":[-90.06316,38.57311],"type":"Point"}
}