{
  "type": "Feature",
  "properties": {
    "gn:country":"US",
    "gn:fcode":"PPL",
    "gn:population":0,
    "iso:country":"US",
    "name:ceb_x_preferred":[
        "Dick"
    ],
    "name:ces_x_preferred":[
        "Dick"
    ],
    "name:deu_x_preferred":[
        "Dick"
    ],
    "name:epo_x_preferred":[
        "Dick"
    ],
    "name:fin_x_preferred":[
        "Dick"
    ],
    "name:fra_x_preferred":[
        "Dick"
    ],
    "name:heb_x_preferred":[
        "\u05d3\u05d9\u05e7"
    ],
    "name:ita_x_preferred":[
        "Dick"
    ],
    "name:jpn_x_preferred":[
        "\u30c7\u30a3\u30c3\u30af"
    ],
    "name:nor_x_preferred":[
        "Dick"
    ],
    "name:pol_x_preferred":[
        "Dick"
    ],
    "name:rus_x_preferred":[
        "\u0414\u0438\u043a"
    ],
    "name:swe_x_preferred":[
        "Dick"
    ],
    "name:ukr_x_preferred":[
        "\u0414\u0456\u043a"
    ],
    "qs_pg:aaroncc":"US",
    "qs_pg:gn_country":"US",
    "qs_pg:gn_fcode":"PPL",
    "qs_pg:gn_pop":0,
    "qs_pg:name":"Dick",
    "qs_pg:name_adm0":"United States",
    "qs_pg:name_adm1":"Pennsylvania",
    "qs_pg:photos":10,
    "qs_pg:photos_1k":2,
    "qs_pg:photos_9k":1,
    "qs_pg:photos_9r":1,
    "qs_pg:photos_all":10,
    "qs_pg:photos_sr":1,
    "qs_pg:pop_sr":0,
    "qs_pg:qs_pg_placetype":"neighbourhood",
    "qs_pg:qs_pg_placetype_gp":"Suburb",
    "qs_pg:woe_adm0":23424977,
    "woe:adm0_id":23424977,
    "woe:name_adm0":"United States",
    "woe:name_adm1":"Pennsylvania",
    "woe:placetype":"Suburb",
    "wof:name":"Dick",
    "wof:placetype":"neighbourhood"
},
  "geometry": {"coordinates":[-79.73532,40.25813],"type":"Point"}
}