{
  "type": "Feature",
  "properties": {
    "iso:country":"US",
    "name:eng_x_preferred":[
        "Central Ave"
    ],
    "name:eng_x_variant":[
        "S Ashland"
    ],
    "qs:gn_adm0_cc":"US",
    "qs:gn_local":4297983,
    "qs:gn_nam_loc":"Lexington, Fayette, Kentucky, US",
    "qs:gn_namadm1":"KY",
    "qs:local_max":4034,
    "qs:local_sum":30708,
    "qs:localhoods":91,
    "qs:name":"Central Ave",
    "qs:name_adm0":"United States",
    "qs:name_adm1":"Kentucky",
    "qs:name_adm2":"Fayette",
    "qs:name_local":"Lexington",
    "qs:photo_max":33,
    "qs:photo_sum":44,
    "qs:placetype":"Suburb",
    "qs:quad_count":4,
    "qs:woe_adm0":23424977,
    "qs:woe_adm1":2347576,
    "qs:woe_adm2":12588509,
    "qs:woe_lau":0,
    "qs:woe_local":2438841,
    "qs:woe_ver":"7.10.0",
    "wd:wordcount":132,
    "wof:lang":[
        "eng"
    ],
    "wof:name":"Central Ave",
    "wof:placetype":"neighbourhood",
    "wof:population":1191,
    "zs:blockids":[
        210670006003026,
        210670006003014,
        210670006003009,
        210670005001014,
        210670006003027,
        210670006003030,
        210670005003008,
        210670006003011,
        210670006002009,
        210670006003018,
        210670006003021,
        210670006003031,
        210670006003013,
        210670007002000,
        210670006003015,
        210670006003028,
        210670007002001,
        210670006003010,
        210670005001015,
        210670006003029,
        210670006002014,
        210670006003017,
        210670006003025,
        210670007001008,
        210670006003024,
        210670006003012,
        210670006003016,
        210670006003019,
        210670006003023,
        210670006003022,
        210670006002013
    ],
    "zs:housing10":744,
    "zs:pop10":1191
},
  "geometry": {"coordinates":[-84.483918,38.033846],"type":"Point"}
}