{
  "type": "Feature",
  "properties": {
    "gn:admin1_code":"AL",
    "gn:admin2_code":"7.0",
    "gn:asciiname":"Thomas Mill",
    "gn:country_code":"US",
    "gn:dem":122,
    "gn:elevation":"122.0",
    "gn:feature_class":"P",
    "gn:feature_code":"PPL",
    "gn:name":"Thomas Mill",
    "gn:population":0,
    "gn:timezone":"America/Chicago",
    "iso:country":"US",
    "wof:name":"Thomas Mill",
    "wof:placetype":"locality"
},
  "geometry": {"coordinates":[-86.95832,32.97373],"type":"Point"}
}