{
  "type": "Feature",
  "properties": {
    "gn:admin1_code":"MS",
    "gn:admin2_code":"69.0",
    "gn:asciiname":"Kipling",
    "gn:country_code":"US",
    "gn:dem":93,
    "gn:elevation":"90.0",
    "gn:feature_class":"P",
    "gn:feature_code":"PPL",
    "gn:name":"Kipling",
    "gn:population":0,
    "gn:timezone":"America/Chicago",
    "iso:country":"US",
    "wof:name":"Kipling",
    "wof:placetype":"locality"
},
  "geometry": {"coordinates":[-88.64838,32.67236],"type":"Point"}
}