{
  "type": "Feature",
  "properties": {
    "gn:admin1_code":"AR",
    "gn:admin2_code":"129.0",
    "gn:asciiname":"Lone Pine",
    "gn:country_code":"US",
    "gn:dem":366,
    "gn:elevation":"366.0",
    "gn:feature_class":"P",
    "gn:feature_code":"PPL",
    "gn:name":"Lone Pine",
    "gn:population":0,
    "gn:timezone":"America/Chicago",
    "iso:country":"US",
    "name:deu_x_preferred":[
        "Lone Pine"
    ],
    "name:pol_x_preferred":[
        "Lone Pine"
    ],
    "wof:name":"Lone Pine",
    "wof:placetype":"locality"
},
  "geometry": {"coordinates":[-92.56265999999999,35.97313],"type":"Point"}
}