{
  "type": "Feature",
  "properties": {
    "gn:admin1_code":"MO",
    "gn:admin2_code":"203.0",
    "gn:admin3_code":"52274.0",
    "gn:asciiname":"Shannondale",
    "gn:country_code":"US",
    "gn:dem":353,
    "gn:elevation":"349.0",
    "gn:feature_class":"P",
    "gn:feature_code":"PPL",
    "gn:name":"Shannondale",
    "gn:population":0,
    "gn:timezone":"America/Chicago",
    "iso:country":"US",
    "name:deu_x_preferred":[
        "Shannondale"
    ],
    "wof:name":"Shannondale",
    "wof:placetype":"locality"
},
  "geometry": {"coordinates":[-91.43764,37.39005],"type":"Point"}
}