{
  "type": "Feature",
  "properties": {
    "iso:country":"US",
    "name:abk_x_preferred":[
        "\u0414\u0438\u0435\u0433\u043e \u0412\u0435\u043b\u0430\u0441\u043a\u0435\u0441"
    ],
    "name:afr_x_preferred":[
        "Diego Vel\u00e1zquez"
    ],
    "name:als_x_preferred":[
        "Diego Rodr\u00edguez de Silva y Vel\u00e1zquez"
    ],
    "name:ara_x_preferred":[
        "\u062f\u064a\u064a\u063a\u0648 \u0641\u064a\u0644\u0627\u062b\u0643\u064a\u062b"
    ],
    "name:arg_x_preferred":[
        "Diego Vel\u00e1zquez"
    ],
    "name:arz_x_preferred":[
        "\u062f\u064a\u064a\u062c\u0648 \u0641\u064a\u0644\u0627\u062b\u0643\u064a\u0632"
    ],
    "name:ast_x_preferred":[
        "Diego Vel\u00e1zquez"
    ],
    "name:aze_x_preferred":[
        "Dieqo Velaskes"
    ],
    "name:bak_x_preferred":[
        "\u0414\u0438\u0435\u0433\u043e \u0412\u0435\u043b\u0430\u0441\u043a\u0435\u0441"
    ],
    "name:bar_x_preferred":[
        "Diego Vel\u00e1zquez"
    ],
    "name:eng_x_preferred":[
        "Velasquez"
    ],
    "wof:name":"Velasquez",
    "wof:placetype":"neighbourhood",
    "wof:population":714,
    "zs:area_m":663407.016613,
    "zs:blockids":[
        490351116001034,
        490351117011001,
        490351116001033,
        490351116001021,
        490351117011000,
        490351116001035,
        490351117013005
    ],
    "zs:housing10":277,
    "zs:label":"Velasquez",
    "zs:pop10":714
},
  "geometry": {"coordinates":[-111.88855599999999,40.694694],"type":"Point"}
}