{
  "type": "Feature",
  "properties": {
    "gn:admin1_code":"AL",
    "gn:admin2_code":"9",
    "gn:asciiname":"Hendrick Mill",
    "gn:country_code":"US",
    "gn:dem":178,
    "gn:elevation":"172.0",
    "gn:feature_class":"P",
    "gn:feature_code":"PPL",
    "gn:name":"Hendrick Mill",
    "gn:population":0,
    "gn:timezone":"America/Chicago",
    "iso:country":"US",
    "wof:name":"Hendrick Mill",
    "wof:placetype":"locality"
},
  "geometry": {"coordinates":[-86.56888000000002,33.87593],"type":"Point"}
}