{
  "type": "Feature",
  "properties": {
    "gn:admin1_code":"WI",
    "gn:admin2_code":"119.0",
    "gn:admin3_code":"15450.0",
    "gn:asciiname":"Hughey",
    "gn:country_code":"US",
    "gn:dem":389,
    "gn:elevation":"390.0",
    "gn:feature_class":"P",
    "gn:feature_code":"PPL",
    "gn:name":"Hughey",
    "gn:population":0,
    "gn:timezone":"America/Chicago",
    "iso:country":"US",
    "wof:name":"Hughey",
    "wof:placetype":"locality"
},
  "geometry": {"coordinates":[-90.70013,45.24858],"type":"Point"}
}