{
  "type": "Feature",
  "properties": {
    "gn:admin1_code":"NC",
    "gn:admin2_code":"91.0",
    "gn:admin3_code":"91968.0",
    "gn:asciiname":"Riddicks Landing",
    "gn:country_code":"US",
    "gn:dem":8,
    "gn:elevation":"1.0",
    "gn:feature_class":"P",
    "gn:feature_code":"PPL",
    "gn:name":"Riddicks Landing",
    "gn:population":0,
    "gn:timezone":"America/New_York",
    "iso:country":"US",
    "wof:name":"Riddicks Landing",
    "wof:placetype":"locality"
},
  "geometry": {"coordinates":[-76.92551999999998,36.53126],"type":"Point"}
}