{
  "type": "Feature",
  "properties": {
    "gn:admin1_code":"PA",
    "gn:admin2_code":"75.0",
    "gn:admin3_code":"21224.0",
    "gn:asciiname":"Harper Tavern",
    "gn:country_code":"US",
    "gn:dem":117,
    "gn:elevation":"116.0",
    "gn:feature_class":"P",
    "gn:feature_code":"PPL",
    "gn:name":"Harper Tavern",
    "gn:population":0,
    "gn:timezone":"America/New_York",
    "iso:country":"US",
    "name:fas_x_preferred":[
        "\u0647\u0627\u0631\u067e\u0631 \u062a\u0627\u0648\u0631\u0646"
    ],
    "name:pdc_x_preferred":[
        "Harper Tavern"
    ],
    "wof:name":"Harper Tavern",
    "wof:placetype":"locality"
},
  "geometry": {"coordinates":[-76.57774000000001,40.40398],"type":"Point"}
}