{
  "type": "Feature",
  "properties": {
    "gn:admin1_code":"FL",
    "gn:admin2_code":"99.0",
    "gn:asciiname":"Jamaica Bay Mobile Home Park",
    "gn:country_code":"US",
    "gn:dem":11,
    "gn:elevation":"5.0",
    "gn:feature_class":"P",
    "gn:feature_code":"PPL",
    "gn:name":"Jamaica Bay Mobile Home Park",
    "gn:population":0,
    "gn:timezone":"America/New_York",
    "iso:country":"US",
    "wof:name":"Jamaica Bay Mobile Home Park",
    "wof:placetype":"campus"
},
  "geometry": {"coordinates":[-80.1191,26.5431],"type":"Point"}
}