{
  "type": "Feature",
  "properties": {
    "gn:admin1_code":"MN",
    "gn:admin2_code":"157.0",
    "gn:admin3_code":"69178.0",
    "gn:asciiname":"Theilman",
    "gn:country_code":"US",
    "gn:dem":235,
    "gn:elevation":"235.0",
    "gn:feature_class":"P",
    "gn:feature_code":"PPL",
    "gn:name":"Theilman",
    "gn:population":0,
    "gn:timezone":"America/Chicago",
    "iso:country":"US",
    "wof:name":"Theilman",
    "wof:placetype":"locality"
},
  "geometry": {"coordinates":[-92.19212,44.28913],"type":"Point"}
}