{
  "type": "Feature",
  "properties": {
    "gn:admin1_code":"OH",
    "gn:admin2_code":"15.0",
    "gn:admin3_code":"61770.0",
    "gn:asciiname":"Chasetown",
    "gn:country_code":"US",
    "gn:dem":286,
    "gn:elevation":"287.0",
    "gn:feature_class":"P",
    "gn:feature_code":"PPL",
    "gn:name":"Chasetown",
    "gn:population":0,
    "gn:timezone":"America/New_York",
    "iso:country":"US",
    "name:ceb_x_preferred":[
        "Chasetown"
    ],
    "name:pol_x_preferred":[
        "Chasetown"
    ],
    "name:swe_x_preferred":[
        "Chasetown"
    ],
    "wof:name":"Chasetown",
    "wof:placetype":"locality"
},
  "geometry": {"coordinates":[-83.93186999999998,39.16062],"type":"Point"}
}