{
  "type": "Feature",
  "properties": {
    "gn:admin1_code":"PA",
    "gn:admin2_code":"59.0",
    "gn:admin3_code":"27408.0",
    "gn:asciiname":"Rees Mill",
    "gn:country_code":"US",
    "gn:dem":298,
    "gn:elevation":"290.0",
    "gn:feature_class":"P",
    "gn:feature_code":"PPL",
    "gn:name":"Rees Mill",
    "gn:population":0,
    "gn:timezone":"America/New_York",
    "iso:country":"US",
    "wof:name":"Rees Mill",
    "wof:placetype":"locality"
},
  "geometry": {"coordinates":[-80.22311999999999,39.91202],"type":"Point"}
}