{
  "type": "Feature",
  "properties": {
    "gn:admin1_code":"VA",
    "gn:admin2_code":"177.0",
    "gn:asciiname":"Meadows Park",
    "gn:country_code":"US",
    "gn:dem":92,
    "gn:elevation":"95.0",
    "gn:feature_class":"P",
    "gn:feature_code":"PPL",
    "gn:name":"Meadows Park",
    "gn:population":0,
    "gn:timezone":"America/New_York",
    "iso:country":"US",
    "wof:name":"Meadows Park",
    "wof:placetype":"locality"
},
  "geometry": {"coordinates":[-77.556,38.277],"type":"Point"}
}