{
  "type": "Feature",
  "properties": {
    "iso:country":"US",
    "name:eng_x_preferred":[
        "Worthington Farms"
    ],
    "name:fra_x_preferred":[
        "Worthington Farms"
    ],
    "wd:wordcount":46,
    "wof:name":"Worthington Farms",
    "wof:placetype":"neighbourhood",
    "wof:population":316,
    "zs:area_m":438135.832496,
    "zs:blockids":[
        510411002093000,
        510411002092004
    ],
    "zs:housing10":120,
    "zs:label":"Worthington Farms",
    "zs:pop10":316
},
  "geometry": {"coordinates":[-77.536384,37.481157],"type":"Point"}
}