{
  "type": "Feature",
  "properties": {
    "gn:admin1_code":"NY",
    "gn:admin2_code":"7",
    "gn:admin3_code":"17772.0",
    "gn:asciiname":"Fountain Blue Mobile Home Park",
    "gn:country_code":"US",
    "gn:dem":284,
    "gn:elevation":"282.0",
    "gn:feature_class":"P",
    "gn:feature_code":"PPL",
    "gn:name":"Fountain Blue Mobile Home Park",
    "gn:population":0,
    "gn:timezone":"America/New_York",
    "iso:country":"US",
    "wof:name":"Fountain Blue Mobile Home Park",
    "wof:placetype":"campus"
},
  "geometry": {"coordinates":[-75.78055999999999,42.00611],"type":"Point"}
}