{
  "type": "Feature",
  "properties": {
    "gn:admin1_code":"MI",
    "gn:admin2_code":"51.0",
    "gn:admin3_code":"73140.0",
    "gn:asciiname":"Skeels",
    "gn:country_code":"US",
    "gn:dem":304,
    "gn:elevation":"305.0",
    "gn:feature_class":"P",
    "gn:feature_code":"PPL",
    "gn:name":"Skeels",
    "gn:population":0,
    "gn:timezone":"America/Detroit",
    "iso:country":"US",
    "wof:name":"Skeels",
    "wof:placetype":"locality"
},
  "geometry": {"coordinates":[-84.58668,44.09002],"type":"Point"}
}