{
  "type": "Feature",
  "properties": {
    "gn:country":"US",
    "gn:fcode":"PPL",
    "gn:population":0,
    "iso:country":"US",
    "name:ceb_x_preferred":[
        "Countryside"
    ],
    "name:che_x_preferred":[
        "\u041a\u0430\u043d\u0442\u0440\u0438\u0421\u0430\u0439\u0434"
    ],
    "name:cym_x_preferred":[
        "CountrySide"
    ],
    "name:deu_x_preferred":[
        "Countryside"
    ],
    "name:eng_x_preferred":[
        "Countryside"
    ],
    "name:fra_x_preferred":[
        "Countryside"
    ],
    "name:gle_x_preferred":[
        "Countryside"
    ],
    "name:ita_x_preferred":[
        "Countryside"
    ],
    "name:lld_x_preferred":[
        "Countryside"
    ],
    "name:pol_x_preferred":[
        "Countryside"
    ],
    "name:spa_x_preferred":[
        "Countryside"
    ],
    "name:srp_x_preferred":[
        "\u041a\u0430\u043d\u0442\u0440\u0438\u0441\u0430\u0458\u0434"
    ],
    "name:tat_x_preferred":[
        "\u041a\u0430\u043d\u0442\u0440\u0438\u0421\u0430\u0439\u0434"
    ],
    "name:ukr_x_preferred":[
        "\u041a\u0430\u043d\u0442\u0440\u0456\u0421\u0430\u0439\u0434"
    ],
    "qs_pg:aaroncc":"US",
    "qs_pg:gn_country":"US",
    "qs_pg:gn_fcode":"PPL",
    "qs_pg:gn_pop":0,
    "qs_pg:name":"Country Side",
    "qs_pg:name_adm0":"United States",
    "qs_pg:name_adm1":"Maryland",
    "qs_pg:photos":193,
    "qs_pg:photos_1k":39,
    "qs_pg:photos_9k":1,
    "qs_pg:photos_9r":4,
    "qs_pg:photos_all":193,
    "qs_pg:photos_sr":4,
    "qs_pg:pop_sr":0,
    "qs_pg:qs_pg_placetype":"locality",
    "qs_pg:qs_pg_placetype_gp":"Town",
    "qs_pg:woe_adm0":23424977,
    "woe:adm0_id":23424977,
    "woe:name_adm0":"United States",
    "woe:name_adm1":"Maryland",
    "woe:placetype":"Town",
    "wof:name":"Country Side",
    "wof:placetype":"locality"
},
  "geometry": {"coordinates":[-77.41915,39.3626],"type":"Point"}
}