{
  "type": "Feature",
  "properties": {
    "gn:admin1_code":"GA",
    "gn:admin2_code":"109.0",
    "gn:asciiname":"Bay Branch",
    "gn:country_code":"US",
    "gn:dem":59,
    "gn:elevation":"58.0",
    "gn:feature_class":"P",
    "gn:feature_code":"PPL",
    "gn:name":"Bay Branch",
    "gn:population":0,
    "gn:timezone":"America/New_York",
    "iso:country":"US",
    "name:eng_x_preferred":[
        "Bay Branch"
    ],
    "name:und_x_variant":[
        "Bull Creek"
    ],
    "wof:name":"Bay Branch",
    "wof:placetype":"locality"
},
  "geometry": {"coordinates":[-81.97566999999999,32.08658],"type":"Point"}
}