{
  "type": "Feature",
  "properties": {
    "gn:admin1_code":"GA",
    "gn:admin2_code":"67.0",
    "gn:asciiname":"Cherokee Hills",
    "gn:country_code":"US",
    "gn:dem":327,
    "gn:elevation":"325.0",
    "gn:feature_class":"P",
    "gn:feature_code":"PPL",
    "gn:name":"Cherokee Hills",
    "gn:population":0,
    "gn:timezone":"America/New_York",
    "iso:country":"US",
    "wof:name":"Cherokee Hills",
    "wof:placetype":"locality"
},
  "geometry": {"coordinates":[-84.56938000000002,33.78427],"type":"Point"}
}