{
  "type": "Feature",
  "properties": {
    "gn:admin1_code":"WA",
    "gn:admin2_code":"35.0",
    "gn:asciiname":"Olympic View Mobile Manor",
    "gn:country_code":"US",
    "gn:dem":55,
    "gn:elevation":"54.0",
    "gn:feature_class":"P",
    "gn:feature_code":"PPL",
    "gn:name":"Olympic View Mobile Manor",
    "gn:population":0,
    "gn:timezone":"America/Los_Angeles",
    "iso:country":"US",
    "wof:name":"Olympic View Mobile Manor",
    "wof:placetype":"locality"
},
  "geometry": {"coordinates":[-122.62237,47.40871],"type":"Point"}
}