{
  "type": "Feature",
  "properties": {
    "gn:admin1_code":"MO",
    "gn:admin2_code":"173.0",
    "gn:admin3_code":"65378.0",
    "gn:asciiname":"Huntington",
    "gn:country_code":"US",
    "gn:dem":226,
    "gn:elevation":"222.0",
    "gn:feature_class":"P",
    "gn:feature_code":"PPL",
    "gn:name":"Huntington",
    "gn:population":0,
    "gn:timezone":"America/Chicago",
    "iso:country":"US",
    "name:bel_x_preferred":[
        "\u0425\u0430\u043d\u0442\u044b\u043d\u0433\u0442\u0430\u043d"
    ],
    "name:bul_x_preferred":[
        "\u0425\u044a\u043d\u0442\u0438\u043d\u0433\u0442\u044a\u043d"
    ],
    "name:cat_x_preferred":[
        "Huntington"
    ],
    "name:ceb_x_preferred":[
        "Huntington"
    ],
    "name:ces_x_preferred":[
        "Huntington"
    ],
    "name:deu_x_preferred":[
        "Huntington"
    ],
    "name:fas_x_preferred":[
        "\u0647\u0627\u0646\u062a\u06cc\u0646\u06af\u062a\u0648\u0646"
    ],
    "name:fin_x_preferred":[
        "Huntington"
    ],
    "name:fra_x_preferred":[
        "Huntington"
    ],
    "name:heb_x_preferred":[
        "\u05d4\u05e0\u05d8\u05d9\u05e0\u05d2\u05d8\u05d5\u05df"
    ],
    "name:hun_x_preferred":[
        "Huntington"
    ],
    "name:ita_x_preferred":[
        "Huntington"
    ],
    "name:jpn_x_preferred":[
        "\u30cf\u30f3\u30c6\u30a3\u30f3\u30c8\u30f3"
    ],
    "name:kor_x_preferred":[
        "\ud5cc\ud305\ud134"
    ],
    "name:nld_x_preferred":[
        "Huntington"
    ],
    "name:nor_x_preferred":[
        "Huntington"
    ],
    "name:pol_x_preferred":[
        "Huntington"
    ],
    "name:por_x_preferred":[
        "Huntington"
    ],
    "name:ron_x_preferred":[
        "Huntington"
    ],
    "name:rus_x_preferred":[
        "\u0425\u0430\u043d\u0442\u0438\u043d\u0433\u0442\u043e\u043d"
    ],
    "name:spa_x_preferred":[
        "Huntington"
    ],
    "name:srp_x_preferred":[
        "\u0425\u0430\u043d\u0442\u0438\u043d\u0433\u0442\u043e\u043d"
    ],
    "name:swa_x_preferred":[
        "Huntington"
    ],
    "name:swe_x_preferred":[
        "Huntington"
    ],
    "name:tur_x_preferred":[
        "Huntington"
    ],
    "name:ukr_x_preferred":[
        "\u0413\u0430\u043d\u0442\u0456\u043d\u0433\u0442\u043e\u043d"
    ],
    "name:vol_x_preferred":[
        "Huntington"
    ],
    "name:zho_x_preferred":[
        "\u4ea8\u5ef7\u9813"
    ],
    "wof:name":"Huntington",
    "wof:placetype":"locality"
},
  "geometry": {"coordinates":[-91.59877,39.66143],"type":"Point"}
}