{
  "type": "Feature",
  "properties": {
    "gn:admin1_code":"VA",
    "gn:admin2_code":"147",
    "gn:asciiname":"Five Forks",
    "gn:country_code":"US",
    "gn:dem":177,
    "gn:elevation":"169.0",
    "gn:feature_class":"P",
    "gn:feature_code":"PPL",
    "gn:name":"Five Forks",
    "gn:population":0,
    "gn:timezone":"America/New_York",
    "iso:country":"US",
    "name:deu_x_preferred":[
        "Five Forks"
    ],
    "name:eng_x_preferred":[
        "Five Forks"
    ],
    "name:und_x_variant":[
        "Fiveforks"
    ],
    "wof:name":"Five Forks",
    "wof:placetype":"locality"
},
  "geometry": {"coordinates":[-78.57694000000002,37.23821],"type":"Point"}
}