{
  "type": "Feature",
  "properties": {
    "gn:admin1_code":"WV",
    "gn:admin2_code":"27",
    "gn:asciiname":"Bubbling Spring",
    "gn:country_code":"US",
    "gn:dem":259,
    "gn:elevation":"256.0",
    "gn:feature_class":"P",
    "gn:feature_code":"PPL",
    "gn:name":"Bubbling Spring",
    "gn:population":0,
    "gn:timezone":"America/New_York",
    "iso:country":"US",
    "name:ang_x_preferred":[
        "Bubbling Spring"
    ],
    "name:azb_x_preferred":[
        "\u0628\u0627\u0628\u0644\u06cc\u0646\u0642 \u0627\u0633\u067e\u0631\u06cc\u0646\u0642"
    ],
    "name:eng_x_preferred":[
        "Bubbling Spring"
    ],
    "name:fas_x_preferred":[
        "\u0628\u0627\u0628\u0644\u06cc\u0646\u06af \u0627\u0633\u067e\u0631\u06cc\u0646\u06af"
    ],
    "name:und_x_variant":[
        "Bubbling Spring Camps",
        "Crystal Spring",
        "Cacapon Bubbling Spring Camps"
    ],
    "name:vol_x_preferred":[
        "Bubbling Spring"
    ],
    "wof:name":"Bubbling Spring",
    "wof:placetype":"locality"
},
  "geometry": {"coordinates":[-78.45806,39.25427],"type":"Point"}
}