{
  "type": "Feature",
  "properties": {
    "gn:admin1_code":"AL",
    "gn:admin2_code":"105",
    "gn:asciiname":"Curbville",
    "gn:country_code":"US",
    "gn:dem":138,
    "gn:elevation":"126.0",
    "gn:feature_class":"P",
    "gn:feature_code":"PPL",
    "gn:name":"Curbville",
    "gn:population":0,
    "gn:timezone":"America/Chicago",
    "iso:country":"US",
    "wof:name":"Curbville",
    "wof:placetype":"locality"
},
  "geometry": {"coordinates":[-87.37195,32.70707],"type":"Point"}
}