{
  "type": "Feature",
  "properties": {
    "gn:country":"US",
    "gn:fcode":"PPL",
    "gn:population":0,
    "iso:country":"US",
    "name:eng_x_preferred":[
        "Hume"
    ],
    "name:fra_x_preferred":[
        "Hume"
    ],
    "name:tur_x_preferred":[
        "Hume"
    ],
    "name:und_x_variant":[
        "Humes"
    ],
    "name:zho_x_preferred":[
        "\u4ea8\u59c6"
    ],
    "qs_pg:aaroncc":"US",
    "qs_pg:gn_country":"US",
    "qs_pg:gn_fcode":"PPL",
    "qs_pg:gn_pop":0,
    "qs_pg:name":"Hume",
    "qs_pg:name_adm0":"United States",
    "qs_pg:name_adm1":"California",
    "qs_pg:photos":1499,
    "qs_pg:photos_1k":304,
    "qs_pg:photos_9k":7,
    "qs_pg:photos_9r":7,
    "qs_pg:photos_all":1499,
    "qs_pg:photos_sr":12,
    "qs_pg:pop_sr":0,
    "qs_pg:qs_pg_placetype":"locality",
    "qs_pg:qs_pg_placetype_gp":"Town",
    "qs_pg:woe_adm0":23424977,
    "woe:adm0_id":23424977,
    "woe:name_adm0":"United States",
    "woe:name_adm1":"California",
    "woe:placetype":"Town",
    "wof:name":"Hume",
    "wof:placetype":"locality"
},
  "geometry": {"coordinates":[-118.91372,36.78495],"type":"Point"}
}