{
  "type": "Feature",
  "properties": {
    "gn:country":"US",
    "gn:fcode":"PPL",
    "gn:population":0,
    "iso:country":"US",
    "name:azb_x_preferred":[
        "\u0628\u0627\u062a\u0644\u0642\u0631\u0648\u0646\u062f"
    ],
    "name:eng_x_preferred":[
        "Battleground"
    ],
    "name:fas_x_preferred":[
        "\u0628\u062a\u0644\u06af\u0631\u0627\u0646\u062f"
    ],
    "name:fra_x_preferred":[
        "Battleground"
    ],
    "name:spa_x_preferred":[
        "Battleground"
    ],
    "name:und_x_variant":[
        "Sheatsville"
    ],
    "name:zho_x_preferred":[
        "\u4f2f\u5716\u683c\u52de\u5fb7"
    ],
    "qs_pg:aaroncc":"US",
    "qs_pg:gn_country":"US",
    "qs_pg:gn_fcode":"PPL",
    "qs_pg:gn_pop":0,
    "qs_pg:name":"Battleground",
    "qs_pg:name_adm0":"United States",
    "qs_pg:name_adm1":"Alabama",
    "qs_pg:photos_9r":0,
    "qs_pg:photos_sr":0,
    "qs_pg:pop_sr":0,
    "qs_pg:qs_pg_placetype":"locality",
    "qs_pg:qs_pg_placetype_gp":"Town",
    "qs_pg:woe_adm0":23424977,
    "woe:adm0_id":23424977,
    "woe:name_adm0":"United States",
    "woe:name_adm1":"Alabama",
    "woe:placetype":"Town",
    "wof:name":"Battleground",
    "wof:placetype":"locality"
},
  "geometry": {"coordinates":[-86.99639999999999,34.30454],"type":"Point"}
}