{
  "type": "Feature",
  "properties": {
    "gn:admin1_code":"KS",
    "gn:admin2_code":"107.0",
    "gn:admin3_code":"12350.0",
    "gn:asciiname":"Dunlay",
    "gn:country_code":"US",
    "gn:dem":292,
    "gn:elevation":"290.0",
    "gn:feature_class":"P",
    "gn:feature_code":"PPL",
    "gn:name":"Dunlay",
    "gn:population":0,
    "gn:timezone":"America/Chicago",
    "iso:country":"US",
    "wof:name":"Dunlay",
    "wof:placetype":"locality"
},
  "geometry": {"coordinates":[-94.99747000000001,38.25836],"type":"Point"}
}