{
  "type": "Feature",
  "properties": {
    "gn:admin1_code":"FL",
    "gn:admin2_code":"57",
    "gn:asciiname":"Oaks at Riverview",
    "gn:country_code":"US",
    "gn:dem":19,
    "gn:elevation":"8.0",
    "gn:feature_class":"P",
    "gn:feature_code":"PPL",
    "gn:name":"Oaks at Riverview",
    "gn:population":0,
    "gn:timezone":"America/New_York",
    "iso:country":"US",
    "wof:name":"Oaks at Riverview",
    "wof:placetype":"locality"
},
  "geometry": {"coordinates":[-82.4572,28.0173],"type":"Point"}
}