{
  "type": "Feature",
  "properties": {
    "gn:country":"US",
    "gn:fcode":"PPL",
    "gn:population":0,
    "iso:country":"US",
    "name:ara_x_preferred":[
        "\u0641\u064a\u0631\u0634\u064a\u0631"
    ],
    "name:azb_x_preferred":[
        "\u0648\u0631\u0634\u06cc\u0631"
    ],
    "name:cat_x_preferred":[
        "Vershire"
    ],
    "name:che_x_preferred":[
        "\u0412\u0435\u0440\u0448\u0438\u0440"
    ],
    "name:cym_x_preferred":[
        "Vershire"
    ],
    "name:deu_x_preferred":[
        "Vershire"
    ],
    "name:eng_x_preferred":[
        "Vershire"
    ],
    "name:fra_x_preferred":[
        "Vershire"
    ],
    "name:hat_x_preferred":[
        "Vershire"
    ],
    "name:ita_x_preferred":[
        "Vershire"
    ],
    "name:pol_x_preferred":[
        "Vershire"
    ],
    "name:spa_x_preferred":[
        "Vershire"
    ],
    "name:tat_x_preferred":[
        "\u0412\u0435\u0440\u0448\u0438\u0440"
    ],
    "name:tur_x_preferred":[
        "Vershire"
    ],
    "name:ukr_x_preferred":[
        "\u0412\u0435\u0440\u0448\u0438\u0440"
    ],
    "name:und_x_variant":[
        "Vershire Village"
    ],
    "name:uzb_x_preferred":[
        "Vershire"
    ],
    "name:vol_x_preferred":[
        "Vershire"
    ],
    "qs_pg:aaroncc":"US",
    "qs_pg:gn_country":"US",
    "qs_pg:gn_fcode":"PPL",
    "qs_pg:gn_pop":0,
    "qs_pg:name":"Vershire",
    "qs_pg:name_adm0":"United States",
    "qs_pg:name_adm1":"Vermont",
    "qs_pg:photos":20,
    "qs_pg:photos_1k":4,
    "qs_pg:photos_9k":1,
    "qs_pg:photos_9r":2,
    "qs_pg:photos_all":49,
    "qs_pg:photos_sr":1,
    "qs_pg:pop_sr":0,
    "qs_pg:qs_pg_placetype":"locality",
    "qs_pg:qs_pg_placetype_gp":"Town",
    "qs_pg:woe_adm0":23424977,
    "woe:adm0_id":23424977,
    "woe:name_adm0":"United States",
    "woe:name_adm1":"Vermont",
    "woe:placetype":"Town",
    "wof:name":"Vershire",
    "wof:placetype":"locality"
},
  "geometry": {"coordinates":[-72.32259999999999,43.96979],"type":"Point"}
}