{
  "type": "Feature",
  "properties": {
    "gn:country":"US",
    "gn:fcode":"PPL",
    "gn:population":0,
    "iso:country":"US",
    "name:deu_x_preferred":[
        "Wendt"
    ],
    "name:eng_x_preferred":[
        "Wendt"
    ],
    "name:fin_x_preferred":[
        "Wendt"
    ],
    "name:fra_x_preferred":[
        "Wendt"
    ],
    "name:ita_x_preferred":[
        "Wendt"
    ],
    "name:nld_x_preferred":[
        "Wendt"
    ],
    "name:rus_x_preferred":[
        "\u0412\u0435\u043d\u0434\u0442"
    ],
    "qs_pg:aaroncc":"US",
    "qs_pg:gn_country":"US",
    "qs_pg:gn_fcode":"PPL",
    "qs_pg:gn_pop":0,
    "qs_pg:name":"Wendt",
    "qs_pg:name_adm0":"United States",
    "qs_pg:name_adm1":"Texas",
    "qs_pg:photos":604,
    "qs_pg:photos_1k":122,
    "qs_pg:photos_9k":3,
    "qs_pg:photos_9r":5,
    "qs_pg:photos_all":604,
    "qs_pg:photos_sr":8,
    "qs_pg:pop_sr":0,
    "qs_pg:qs_pg_placetype":"neighbourhood",
    "qs_pg:qs_pg_placetype_gp":"Suburb",
    "qs_pg:woe_adm0":23424977,
    "woe:adm0_id":23424977,
    "woe:name_adm0":"United States",
    "woe:name_adm1":"Texas",
    "woe:placetype":"Suburb",
    "wof:name":"Wendt",
    "wof:placetype":"neighbourhood",
    "wof:population":588
},
  "geometry": {"coordinates":[-96.89998,29.90634],"type":"Point"}
}