{
  "type": "Feature",
  "properties": {
    "gn:admin1_code":"WV",
    "gn:admin2_code":"23",
    "gn:asciiname":"Medley",
    "gn:country_code":"US",
    "gn:dem":319,
    "gn:elevation":"322.0",
    "gn:feature_class":"P",
    "gn:feature_code":"PPL",
    "gn:name":"Medley",
    "gn:population":0,
    "gn:timezone":"America/New_York",
    "iso:country":"US",
    "name:fas_x_preferred":[
        "\u0645\u062f\u0644\u06cc"
    ],
    "name:vol_x_preferred":[
        "Medley"
    ],
    "wof:name":"Medley",
    "wof:placetype":"locality"
},
  "geometry": {"coordinates":[-79.05781,39.17622],"type":"Point"}
}