{
  "type": "Feature",
  "properties": {
    "gn:country":"US",
    "gn:fcode":"PPL",
    "gn:population":1013,
    "iso:country":"US",
    "name:ara_x_preferred":[
        "\u0644\u0648\u0641\u064a\u0644"
    ],
    "name:cat_x_preferred":[
        "Lovell"
    ],
    "name:deu_x_preferred":[
        "Lovell"
    ],
    "name:eng_x_preferred":[
        "Lovell"
    ],
    "name:eus_x_preferred":[
        "Lovell"
    ],
    "name:fra_x_preferred":[
        "Lovell"
    ],
    "name:hat_x_preferred":[
        "Lovell"
    ],
    "name:hun_x_preferred":[
        "Lovell"
    ],
    "name:ita_x_preferred":[
        "Lovell"
    ],
    "name:kaz_x_preferred":[
        "\u041b\u0430\u0432\u044d\u043b\u043b"
    ],
    "name:kir_x_preferred":[
        "\u041b\u0430\u0432\u044d\u043b\u043b"
    ],
    "name:pol_x_preferred":[
        "Lovell"
    ],
    "name:spa_x_preferred":[
        "Lovell"
    ],
    "name:swe_x_preferred":[
        "Lovell"
    ],
    "name:und_x_variant":[
        "Lovell Village"
    ],
    "name:vol_x_preferred":[
        "Lovell"
    ],
    "qs_pg:aaroncc":"US",
    "qs_pg:gn_country":"US",
    "qs_pg:gn_fcode":"PPL",
    "qs_pg:gn_pop":1013,
    "qs_pg:name":"Lovell",
    "qs_pg:name_adm0":"United States",
    "qs_pg:name_adm1":"Maine",
    "qs_pg:photos":124,
    "qs_pg:photos_1k":25,
    "qs_pg:photos_9k":1,
    "qs_pg:photos_9r":4,
    "qs_pg:photos_all":173,
    "qs_pg:photos_sr":3,
    "qs_pg:pop_sr":3,
    "qs_pg:qs_pg_placetype":"locality",
    "qs_pg:qs_pg_placetype_gp":"Town",
    "qs_pg:woe_adm0":23424977,
    "woe:adm0_id":23424977,
    "woe:name_adm0":"United States",
    "woe:name_adm1":"Maine",
    "woe:placetype":"Town",
    "wof:name":"Lovell",
    "wof:placetype":"locality",
    "wof:population":1013
},
  "geometry": {"coordinates":[-70.89173,44.12674],"type":"Point"}
}