{
  "type": "Feature",
  "properties": {
    "gn:admin1_code":"AK",
    "gn:admin2_code":"20.0",
    "gn:asciiname":"City View",
    "gn:country_code":"US",
    "gn:dem":45,
    "gn:elevation":"39.0",
    "gn:feature_class":"P",
    "gn:feature_code":"PPL",
    "gn:name":"City View",
    "gn:population":0,
    "gn:timezone":"America/Anchorage",
    "iso:country":"US",
    "wof:name":"City View",
    "wof:placetype":"locality"
},
  "geometry": {"coordinates":[-149.83056000000005,61.20444000000001],"type":"Point"}
}