{
  "type": "Feature",
  "properties": {
    "gn:admin1_code":"CA",
    "gn:admin2_code":"37",
    "gn:asciiname":"Hidden Springs",
    "gn:country_code":"US",
    "gn:dem":959,
    "gn:elevation":"954.0",
    "gn:feature_class":"P",
    "gn:feature_code":"PPL",
    "gn:name":"Hidden Springs",
    "gn:population":0,
    "gn:timezone":"America/Los_Angeles",
    "iso:country":"US",
    "wof:name":"Hidden Springs",
    "wof:placetype":"locality"
},
  "geometry": {"coordinates":[-118.13118,34.31833],"type":"Point"}
}