{
  "type": "Feature",
  "properties": {
    "gn:gn_country":"US",
    "gn:gn_fcode":"PPL",
    "gn:gn_pop":0,
    "iso:country":"US",
    "name:bre_x_preferred":[
        "Stewart"
    ],
    "name:ceb_x_preferred":[
        "Stewart"
    ],
    "name:deu_x_preferred":[
        "Stewart"
    ],
    "name:eng_x_preferred":[
        "Stewart"
    ],
    "name:fin_x_preferred":[
        "Stewart"
    ],
    "name:fra_x_preferred":[
        "Stewart"
    ],
    "name:ita_x_preferred":[
        "Stewart"
    ],
    "name:lav_x_preferred":[
        "Stjuarts"
    ],
    "name:nld_x_preferred":[
        "Stewart"
    ],
    "name:pol_x_preferred":[
        "Stewart"
    ],
    "name:por_x_preferred":[
        "Stewart"
    ],
    "name:rus_x_preferred":[
        "Stewart"
    ],
    "name:slv_x_preferred":[
        "Stewart"
    ],
    "name:spa_x_preferred":[
        "Stewart"
    ],
    "name:swe_x_preferred":[
        "Stewart"
    ],
    "name:unk_x_variant":[
        "Stewartsville"
    ],
    "name:vie_x_preferred":[
        "Stewart"
    ],
    "name:vol_x_preferred":[
        "Stewart"
    ],
    "name:zho_x_preferred":[
        "\u65af\u5716\u723e\u7279"
    ],
    "qs_pg:aaroncc":"US",
    "qs_pg:gn_country":"US",
    "qs_pg:gn_fcode":"PPL",
    "qs_pg:gn_pop":0,
    "qs_pg:name":"Stewart",
    "qs_pg:name_adm0":"United States",
    "qs_pg:name_adm1":"Kentucky",
    "qs_pg:photos":33,
    "qs_pg:photos_1k":7,
    "qs_pg:photos_9k":1,
    "qs_pg:photos_9r":2,
    "qs_pg:photos_all":33,
    "qs_pg:photos_sr":2,
    "qs_pg:pop_sr":0,
    "qs_pg:qs_pg_placetype":"locality",
    "qs_pg:qs_pg_placetype_gp":"Town",
    "qs_pg:woe_adm0":23424977,
    "woe:adm0_id":23424977,
    "woe:name_adm0":"United States",
    "woe:name_adm1":"Kentucky",
    "woe:placetype":"Town",
    "wof:name":"Stewart",
    "wof:placetype":"locality"
},
  "geometry": {"coordinates":[-85.00829,37.69118],"type":"Point"}
}