{
  "type": "Feature",
  "properties": {
    "gn:admin1_code":"IA",
    "gn:admin2_code":"127.0",
    "gn:admin3_code":"92700.0",
    "gn:asciiname":"Van Cleve",
    "gn:country_code":"US",
    "gn:dem":322,
    "gn:elevation":"319.0",
    "gn:feature_class":"P",
    "gn:feature_code":"PPL",
    "gn:name":"Van Cleve",
    "gn:population":0,
    "gn:timezone":"America/Chicago",
    "iso:country":"US",
    "name:fra_x_preferred":[
        "Van Cleve"
    ],
    "wof:name":"Van Cleve",
    "wof:placetype":"locality"
},
  "geometry": {"coordinates":[-93.01909000000001,41.93138],"type":"Point"}
}