{
  "type": "Feature",
  "properties": {
    "iso:country":"US",
    "name:eng_x_preferred":[
        "North Salinas"
    ],
    "qs:gn_adm0_cc":"US",
    "qs:gn_local":5391295,
    "qs:gn_nam_loc":"Salinas, Monterey, California, US",
    "qs:gn_namadm1":"CA",
    "qs:local_max":1278,
    "qs:local_sum":3113,
    "qs:localhoods":15,
    "qs:name":"North Salinas",
    "qs:name_adm0":"United States",
    "qs:name_adm1":"California",
    "qs:name_adm2":"Monterey",
    "qs:name_local":"Salinas",
    "qs:photo_max":117,
    "qs:photo_sum":321,
    "qs:placetype":"Suburb",
    "qs:quad_count":21,
    "qs:woe_adm0":23424977,
    "qs:woe_adm1":2347563,
    "qs:woe_adm2":12587696,
    "qs:woe_funk":"Grouping neighborhood",
    "qs:woe_lau":0,
    "qs:woe_local":2487460,
    "qs:woe_ver":"7.10.0",
    "wof:lang":[
        "eng"
    ],
    "wof:name":"North Salinas",
    "wof:placetype":"neighbourhood",
    "wof:population":13289,
    "zs:blockids":[
        60530105042007,
        60530003001009,
        60530002001005,
        60530002003003,
        60530003001007,
        60530003001004,
        60530002001001,
        60530002001002,
        60530001022015,
        60530001022012,
        60530001023023,
        60530001023010,
        60530002001003,
        60530001021009,
        60530002003004,
        60530001021010,
        60530001031003,
        60530001032008,
        60530001032002,
        60530001022016,
        60530001032000,
        60530002003011,
        60530002003012,
        60530001022023,
        60530002003005,
        60530001022022,
        60530001022024,
        60530105042008,
        60530003001008,
        60530003001017,
        60530001032005,
        60530002001006,
        60530105042009,
        60530003001000,
        60530003001012,
        60530105042006,
        60530001023017,
        60530001032001,
        60530001032009,
        60530001023001,
        60530001023006,
        60530001023014,
        60530001022017,
        60530001031004,
        60530003001019,
        60530001031001,
        60530001023022,
        60530001023008,
        60530001022021,
        60530001021011,
        60530002003000,
        60530003001016,
        60530003001014,
        60530003001010,
        60530001031002,
        60530001023009,
        60530001023005,
        60530001032010,
        60530001023002,
        60530001023007,
        60530001023000,
        60530001023016,
        60530001022020,
        60530002001000,
        60530001022018,
        60530003001011,
        60530002002002,
        60530002002003,
        60530001023018,
        60530001031000,
        60530001023019,
        60530001023020,
        60530001032004,
        60530002001004,
        60530001023015,
        60530001022019,
        60530002003002,
        60530001023011,
        60530001023004,
        60530003001015,
        60530003001013,
        60530003001018,
        60530001022014,
        60530001023021,
        60530001032011,
        60530001023003,
        60530001023012,
        60530001023013
    ],
    "zs:housing10":4149,
    "zs:pop10":13289
},
  "geometry": {"coordinates":[-121.654793,36.7105],"type":"Point"}
}