{
  "type": "Feature",
  "properties": {
    "gn:admin1_code":"VT",
    "gn:admin2_code":"5.0",
    "gn:admin3_code":"2875.0",
    "gn:asciiname":"West Barnet",
    "gn:country_code":"US",
    "gn:dem":270,
    "gn:elevation":"272.0",
    "gn:feature_class":"P",
    "gn:feature_code":"PPL",
    "gn:name":"West Barnet",
    "gn:population":0,
    "gn:timezone":"America/New_York",
    "iso:country":"US",
    "name:eng_x_preferred":[
        "West Barnet"
    ],
    "name:und_x_variant":[
        "Brocks Mills"
    ],
    "wof:name":"West Barnet",
    "wof:placetype":"locality"
},
  "geometry": {"coordinates":[-72.13731999999997,44.31006],"type":"Point"}
}