{
  "type": "Feature",
  "properties": {
    "gn:admin1_code":"MO",
    "gn:admin2_code":"123.0",
    "gn:admin3_code":"11962.0",
    "gn:asciiname":"Castor Station",
    "gn:country_code":"US",
    "gn:dem":207,
    "gn:elevation":"203.0",
    "gn:feature_class":"P",
    "gn:feature_code":"PPL",
    "gn:name":"Castor Station",
    "gn:population":0,
    "gn:timezone":"America/Chicago",
    "iso:country":"US",
    "name:ara_x_preferred":[
        "\u0643\u0627\u0633\u062a\u0648\u0631 \u0633\u062a\u064a\u0634\u0646"
    ],
    "name:vol_x_preferred":[
        "Castor Station"
    ],
    "wof:name":"Castor Station",
    "wof:placetype":"locality"
},
  "geometry": {"coordinates":[-90.16956,37.52783],"type":"Point"}
}