{
  "type": "Feature",
  "properties": {
    "gn:admin1_code":"WA",
    "gn:admin2_code":"27.0",
    "gn:asciiname":"Fuller",
    "gn:country_code":"US",
    "gn:dem":40,
    "gn:elevation":"33.0",
    "gn:feature_class":"P",
    "gn:feature_code":"PPL",
    "gn:name":"Fuller",
    "gn:population":0,
    "gn:timezone":"America/Los_Angeles",
    "iso:country":"US",
    "name:cat_x_preferred":[
        "Fuller"
    ],
    "name:ces_x_preferred":[
        "Fuller"
    ],
    "name:deu_x_preferred":[
        "Fuller"
    ],
    "name:fin_x_preferred":[
        "Fuller"
    ],
    "name:fra_x_preferred":[
        "Fuller"
    ],
    "name:heb_x_preferred":[
        "\u05e4\u05d5\u05dc\u05e8"
    ],
    "name:ita_x_preferred":[
        "Fuller"
    ],
    "name:jpn_x_preferred":[
        "\u30d5\u30e9\u30fc"
    ],
    "name:spa_x_preferred":[
        "Fuller"
    ],
    "name:zho_x_preferred":[
        "\u5bcc\u52d2"
    ],
    "wof:name":"Fuller",
    "wof:placetype":"locality"
},
  "geometry": {"coordinates":[-123.47099,46.97399],"type":"Point"}
}