{
  "type": "Feature",
  "properties": {
    "gn:admin1_code":"FL",
    "gn:admin2_code":"57",
    "gn:asciiname":"Gallery Gardens",
    "gn:country_code":"US",
    "gn:dem":19,
    "gn:elevation":"9.0",
    "gn:feature_class":"P",
    "gn:feature_code":"PPL",
    "gn:name":"Gallery Gardens",
    "gn:population":0,
    "gn:timezone":"America/New_York",
    "iso:country":"US",
    "wof:name":"Gallery Gardens",
    "wof:placetype":"locality"
},
  "geometry": {"coordinates":[-82.2906,27.8998],"type":"Point"}
}