{
  "type": "Feature",
  "properties": {
    "gn:country":"US",
    "gn:fcode":"PPL",
    "gn:population":3254,
    "iso:country":"US",
    "name:cat_x_preferred":[
        "Sunapee"
    ],
    "name:ceb_x_preferred":[
        "Sunapee"
    ],
    "name:che_x_preferred":[
        "\u0421\u0430\u043d\u0430\u043f\u0438"
    ],
    "name:cym_x_preferred":[
        "Sunapee"
    ],
    "name:deu_x_preferred":[
        "Sunapee"
    ],
    "name:eng_x_preferred":[
        "Sunapee"
    ],
    "name:eus_x_preferred":[
        "Sunapee"
    ],
    "name:fra_x_preferred":[
        "Sunapee"
    ],
    "name:hat_x_preferred":[
        "Sunapee"
    ],
    "name:hun_x_preferred":[
        "Sunapee"
    ],
    "name:ita_x_preferred":[
        "Sunapee"
    ],
    "name:jpn_x_preferred":[
        "\u30b5\u30ca\u30d4\u30fc"
    ],
    "name:kaz_x_preferred":[
        "\u0421\u0430\u043d\u0430\u043f\u0438"
    ],
    "name:kir_x_preferred":[
        "\u0421\u0430\u043d\u0430\u043f\u0438"
    ],
    "name:nld_x_preferred":[
        "Sunapee"
    ],
    "name:pol_x_preferred":[
        "Sunapee"
    ],
    "name:rup_x_preferred":[
        "Sunapee"
    ],
    "name:spa_x_preferred":[
        "Sunapee"
    ],
    "name:swe_x_preferred":[
        "Sunapee"
    ],
    "name:tat_x_preferred":[
        "\u0421\u0430\u043d\u0430\u043f\u0438"
    ],
    "name:tur_x_preferred":[
        "Sunapee"
    ],
    "name:ukr_x_preferred":[
        "\u0421\u0430\u043d\u0430\u043f\u0456"
    ],
    "name:und_x_variant":[
        "Corey's Town"
    ],
    "name:urd_x_preferred":[
        "\u0633\u0646\u0627\u067e\u06cc\u060c \u0646\u06cc\u0648 \u06c1\u06cc\u0645\u067e\u0634\u0627\u0626\u0631"
    ],
    "name:urd_x_variant":[
        "\u0633\u0646\u0627\u067e\u06cc"
    ],
    "name:vol_x_preferred":[
        "Sunapee"
    ],
    "name:war_x_preferred":[
        "Sunapee"
    ],
    "qs_pg:aaroncc":"US",
    "qs_pg:gn_country":"US",
    "qs_pg:gn_fcode":"PPL",
    "qs_pg:gn_pop":3254,
    "qs_pg:name":"Sunapee",
    "qs_pg:name_adm0":"United States",
    "qs_pg:name_adm1":"New Hampshire",
    "qs_pg:photos":374,
    "qs_pg:photos_1k":76,
    "qs_pg:photos_9k":2,
    "qs_pg:photos_9r":5,
    "qs_pg:photos_all":515,
    "qs_pg:photos_sr":6,
    "qs_pg:pop_sr":4,
    "qs_pg:qs_pg_placetype":"locality",
    "qs_pg:qs_pg_placetype_gp":"Town",
    "qs_pg:woe_adm0":23424977,
    "woe:adm0_id":23424977,
    "woe:name_adm0":"United States",
    "woe:name_adm1":"New Hampshire",
    "woe:placetype":"Town",
    "wof:coterminous":[
        404476737
    ],
    "wof:name":"Sunapee",
    "wof:placetype":"locality",
    "wof:population":3254,
    "wof:statistical_gore":1
},
  "geometry": {"coordinates":[-72.08786000000001,43.38757],"type":"Point"}
}