{
  "type": "Feature",
  "properties": {
    "gn:admin1_code":"MA",
    "gn:admin2_code":"23.0",
    "gn:admin3_code":"79530.0",
    "gn:asciiname":"Winslow Estates",
    "gn:country_code":"US",
    "gn:dem":37,
    "gn:elevation":"35.0",
    "gn:feature_class":"P",
    "gn:feature_code":"PPL",
    "gn:name":"Winslow Estates",
    "gn:population":0,
    "gn:timezone":"America/New_York",
    "iso:country":"US",
    "wof:name":"Winslow Estates",
    "wof:placetype":"locality"
},
  "geometry": {"coordinates":[-70.91393000000002,42.08205],"type":"Point"}
}