{
  "type": "Feature",
  "properties": {
    "gn:country":"US",
    "gn:fcode":"PPL",
    "gn:population":0,
    "iso:country":"US",
    "name:ben_x_preferred":[
        "\u09a6\u09c7\u09b2\u09be\u0993\u09df\u09be\u09b0"
    ],
    "name:cym_x_preferred":[
        "Delaware"
    ],
    "name:eng_x_preferred":[
        "Delaware"
    ],
    "name:fra_x_preferred":[
        "Delaware"
    ],
    "name:ind_x_preferred":[
        "Delaware"
    ],
    "name:urd_x_preferred":[
        "\u0688\u06cc\u0644\u0627\u0648\u06cc\u0626\u0631"
    ],
    "qs_pg:aaroncc":"US",
    "qs_pg:gn_country":"US",
    "qs_pg:gn_fcode":"PPL",
    "qs_pg:gn_pop":0,
    "qs_pg:name":"Delaware",
    "qs_pg:name_adm0":"United States",
    "qs_pg:name_adm1":"Michigan",
    "qs_pg:photos":70,
    "qs_pg:photos_1k":14,
    "qs_pg:photos_9k":1,
    "qs_pg:photos_9r":2,
    "qs_pg:photos_all":70,
    "qs_pg:photos_sr":2,
    "qs_pg:pop_sr":0,
    "qs_pg:qs_pg_placetype":"locality",
    "qs_pg:qs_pg_placetype_gp":"Town",
    "qs_pg:woe_adm0":23424977,
    "woe:adm0_id":23424977,
    "woe:name_adm0":"United States",
    "woe:name_adm1":"Michigan",
    "woe:placetype":"Town",
    "wof:name":"Delaware",
    "wof:placetype":"locality"
},
  "geometry": {"coordinates":[-88.09594,47.42102],"type":"Point"}
}