{
  "type": "Feature",
  "properties": {
    "gn:admin1_code":"TN",
    "gn:admin2_code":"63",
    "gn:asciiname":"Indian HIlls",
    "gn:country_code":"US",
    "gn:dem":348,
    "gn:elevation":"341.0",
    "gn:feature_class":"P",
    "gn:feature_code":"PPL",
    "gn:name":"Indian HIlls",
    "gn:population":0,
    "gn:timezone":"America/New_York",
    "iso:country":"US",
    "wof:name":"Indian HIlls",
    "wof:placetype":"locality"
},
  "geometry": {"coordinates":[-83.32184000000002,36.27815],"type":"Point"}
}