{
  "type": "Feature",
  "properties": {
    "iso:country":"US",
    "name:eng_x_preferred":[
        "Carrington Patio"
    ],
    "name:hye_x_preferred":[
        "\u053d\u0578\u057d\u0565 \u053c\u0578\u0582\u056b\u057d \u053f\u0578\u0582\u0587\u0561\u057d\u056b \u0569\u0561\u0576\u0563\u0561\u0580\u0561\u0576"
    ],
    "name:spa_x_preferred":[
        "Museo Jos\u00e9 Luis Cuevas"
    ],
    "wof:name":"Carrington Patio",
    "wof:placetype":"neighbourhood",
    "wof:population":845,
    "zs:area_m":546418.426982,
    "zs:blockids":[
        121030273182007,
        121030273182005,
        121030273182011
    ],
    "zs:housing10":492,
    "zs:label":"Carrington Patio",
    "zs:pop10":845
},
  "geometry": {"coordinates":[-82.714726,28.052051],"type":"Point"}
}