{
  "type": "Feature",
  "properties": {
    "gn:gn_country":"US",
    "gn:gn_fcode":"PPL",
    "gn:gn_pop":0,
    "iso:country":"US",
    "name:dan_x_preferred":[
        "Calico"
    ],
    "name:deu_x_preferred":[
        "Calico"
    ],
    "name:eng_x_preferred":[
        "Calico"
    ],
    "name:fra_x_preferred":[
        "Calico"
    ],
    "name:ita_x_preferred":[
        "Calico"
    ],
    "name:jpn_x_preferred":[
        "\u30ad\u30e3\u30ea\u30b3\u30fb\u30b4\u30fc\u30b9\u30c8\u30bf\u30a6\u30f3"
    ],
    "name:kor_x_preferred":[
        "\uce98\ub9ac\ucf54"
    ],
    "name:nan_x_preferred":[
        "Calico"
    ],
    "name:nld_x_preferred":[
        "Calico"
    ],
    "name:pol_x_preferred":[
        "Calico"
    ],
    "name:por_x_preferred":[
        "Calico"
    ],
    "name:spa_x_preferred":[
        "Calico"
    ],
    "name:swe_x_preferred":[
        "Calico"
    ],
    "name:vol_x_preferred":[
        "Calico"
    ],
    "qs_pg:aaroncc":"US",
    "qs_pg:gn_country":"US",
    "qs_pg:gn_fcode":"PPL",
    "qs_pg:gn_pop":0,
    "qs_pg:name":"Calico",
    "qs_pg:name_adm0":"United States",
    "qs_pg:name_adm1":"California",
    "qs_pg:photos":4307,
    "qs_pg:photos_1k":873,
    "qs_pg:photos_9k":19,
    "qs_pg:photos_9r":13,
    "qs_pg:photos_all":4307,
    "qs_pg:photos_sr":23,
    "qs_pg:pop_sr":0,
    "qs_pg:qs_pg_placetype":"locality",
    "qs_pg:qs_pg_placetype_gp":"Town",
    "qs_pg:woe_adm0":23424977,
    "woe:adm0_id":23424977,
    "woe:name_adm0":"United States",
    "woe:name_adm1":"California",
    "woe:placetype":"Town",
    "wof:name":"Calico",
    "wof:placetype":"locality"
},
  "geometry": {"coordinates":[-116.86503999999999,34.94887],"type":"Point"}
}