{
  "type": "Feature",
  "properties": {
    "gn:admin1_code":"GA",
    "gn:admin2_code":"97",
    "gn:asciiname":"White Oak Estates",
    "gn:country_code":"US",
    "gn:dem":347,
    "gn:elevation":"338.0",
    "gn:feature_class":"P",
    "gn:feature_code":"PPL",
    "gn:name":"White Oak Estates",
    "gn:population":0,
    "gn:timezone":"America/New_York",
    "iso:country":"US",
    "wof:name":"White Oak Estates",
    "wof:placetype":"locality"
},
  "geometry": {"coordinates":[-84.81215999999998,33.69178],"type":"Point"}
}