{
  "type": "Feature",
  "properties": {
    "gn:admin1_code":"TN",
    "gn:admin2_code":"7",
    "gn:asciiname":"Hickory Grove",
    "gn:country_code":"US",
    "gn:dem":606,
    "gn:elevation":"605.0",
    "gn:feature_class":"P",
    "gn:feature_code":"PPL",
    "gn:name":"Hickory Grove",
    "gn:population":0,
    "gn:timezone":"America/Chicago",
    "iso:country":"US",
    "name:ceb_x_preferred":[
        "Hickory Grove"
    ],
    "name:deu_x_preferred":[
        "Hickory Grove"
    ],
    "name:ita_x_preferred":[
        "Hickory Grove"
    ],
    "name:pol_x_preferred":[
        "Hickory Grove"
    ],
    "wof:name":"Hickory Grove",
    "wof:placetype":"locality"
},
  "geometry": {"coordinates":[-85.20079,35.47062000000001],"type":"Point"}
}