{
  "type": "Feature",
  "properties": {
    "gn:admin1_code":"NM",
    "gn:admin2_code":"31.0",
    "gn:asciiname":"Page",
    "gn:country_code":"US",
    "gn:dem":2410,
    "gn:elevation":"2412.0",
    "gn:feature_class":"P",
    "gn:feature_code":"PPL",
    "gn:name":"Page",
    "gn:population":0,
    "gn:timezone":"America/Denver",
    "iso:country":"US",
    "name:bel_x_preferred":[
        "\u041f\u044d\u0439\u0434\u0436"
    ],
    "name:ceb_x_preferred":[
        "Page"
    ],
    "name:ces_x_preferred":[
        "Page"
    ],
    "name:deu_x_preferred":[
        "Page"
    ],
    "name:est_x_preferred":[
        "Page"
    ],
    "name:fas_x_preferred":[
        "\u0635\u0641\u062d\u0647"
    ],
    "name:fin_x_preferred":[
        "Page"
    ],
    "name:fra_x_preferred":[
        "Page"
    ],
    "name:heb_x_preferred":[
        "\u05e4\u05d9\u05d9\u05d2'"
    ],
    "name:hun_x_preferred":[
        "Page"
    ],
    "name:ita_x_preferred":[
        "Page"
    ],
    "name:jpn_x_preferred":[
        "\u30da\u30fc\u30b8"
    ],
    "name:kor_x_preferred":[
        "\ud398\uc774\uc9c0"
    ],
    "name:lav_x_preferred":[
        "Page"
    ],
    "name:nds_x_preferred":[
        "Page"
    ],
    "name:nld_x_preferred":[
        "Page"
    ],
    "name:nor_x_preferred":[
        "Page"
    ],
    "name:pol_x_preferred":[
        "Page"
    ],
    "name:por_x_preferred":[
        "Page"
    ],
    "name:pus_x_preferred":[
        "\u0645\u062e"
    ],
    "name:rus_x_preferred":[
        "\u041f\u0435\u0439\u0434\u0436"
    ],
    "name:slv_x_preferred":[
        "Page"
    ],
    "name:spa_x_preferred":[
        "Page"
    ],
    "name:srp_x_preferred":[
        "\u041f\u0435\u0458\u045f"
    ],
    "name:swe_x_preferred":[
        "Page"
    ],
    "name:tur_x_preferred":[
        "Sayfa"
    ],
    "name:ukr_x_preferred":[
        "\u041f\u0435\u0439\u0434\u0436"
    ],
    "name:urd_x_preferred":[
        "\u067e\u06cc\u062c"
    ],
    "name:vol_x_preferred":[
        "Page"
    ],
    "wof:name":"Page",
    "wof:placetype":"locality"
},
  "geometry": {"coordinates":[-108.44063,35.32114],"type":"Point"}
}