{
  "type": "Feature",
  "properties": {
    "gn:admin1_code":"TX",
    "gn:admin2_code":"203",
    "gn:asciiname":"Darco",
    "gn:country_code":"US",
    "gn:dem":96,
    "gn:elevation":"91.0",
    "gn:feature_class":"P",
    "gn:feature_code":"PPL",
    "gn:name":"Darco",
    "gn:population":0,
    "gn:timezone":"America/Chicago",
    "iso:country":"US",
    "name:deu_x_preferred":[
        "Darco Gellert"
    ],
    "name:fra_x_preferred":[
        "Darco"
    ],
    "name:ita_x_preferred":[
        "Darco"
    ],
    "name:zho_x_preferred":[
        "Darco"
    ],
    "wof:name":"Darco",
    "wof:placetype":"locality"
},
  "geometry": {"coordinates":[-94.43576,32.40904],"type":"Point"}
}