{
  "type": "Feature",
  "properties": {
    "gn:elevation":1518,
    "iso:country":"US",
    "name:eng_x_preferred":[
        "Huachuca Terrace"
    ],
    "name:eng_x_variant":[
        "Huachuca Ter"
    ],
    "qs:gn_fcode":"PPL",
    "qs:gn_local":0,
    "qs:gn_namadm1":"AZ",
    "qs:gn_name":"Huachuca Terrace",
    "qs:local_max":373,
    "qs:local_sum":489,
    "qs:localhoods":5,
    "qs:name":"Huachuca Terrace",
    "qs:name_adm0":"United States",
    "qs:name_adm1":"Arizona",
    "qs:name_adm2":"Cochise",
    "qs:name_local":"Bisbee",
    "qs:photo_max":1,
    "qs:photo_sum":2,
    "qs:placetype":"Suburb",
    "qs:quad_count":2,
    "qs:woe_adm0":23424977,
    "qs:woe_adm1":2347561,
    "qs:woe_adm2":12587581,
    "qs:woe_lau":0,
    "qs:woe_local":2364620,
    "qs:woe_ver":"7.10.0",
    "wof:name":"Huachuca Terrace",
    "wof:placetype":"neighbourhood",
    "wof:population":1569,
    "zs:blockids":[
        40030012001096,
        40030012001082,
        40030012001066,
        40030012001063,
        40030012001069,
        40030012002002,
        40030012002011,
        40030012001112,
        40030021001066,
        40030012001107,
        40030012001095,
        40030012001061,
        40030012001084,
        40030012001072,
        40030021001004,
        40030012001092,
        40030012001099,
        40030012001080,
        40030012001113,
        40030012001058,
        40030021001001,
        40030012001098,
        40030012003027,
        40030021001064,
        40030012001062,
        40030012001060,
        40030012001114,
        40030012002000,
        40030012001068,
        40030012001088,
        40030012001093,
        40030021001006,
        40030021001003,
        40030012003028,
        40030021001063,
        40030012001115,
        40030012002012,
        40030021001000,
        40030012001064,
        40030012002008,
        40030012002001,
        40030012001089,
        40030021001005,
        40030012002004,
        40030012001097,
        40030012001071,
        40030021001062,
        40030021001065,
        40030012002026,
        40030012001054,
        40030012001067,
        40030012001073,
        40030012002009,
        40030021001061,
        40030012001091,
        40030012001083,
        40030021001070,
        40030021001098,
        40030021001002,
        40030021001071,
        40030012002005,
        40030012002010,
        40030012002013,
        40030012001070,
        40030012001111,
        40030012001110,
        40030012001057,
        40030021001099,
        40030012001085,
        40030012001065,
        40030012002006,
        40030012002007,
        40030012002003,
        40030012002021,
        40030021001072
    ],
    "zs:housing10":679,
    "zs:pop10":1569
},
  "geometry": {"coordinates":[-109.926453,31.388813],"type":"Point"}
}