{
  "type": "Feature",
  "properties": {
    "gn:admin1_code":"MI",
    "gn:admin2_code":"149.0",
    "gn:admin3_code":"86940.0",
    "gn:asciiname":"Klingers",
    "gn:country_code":"US",
    "gn:dem":263,
    "gn:elevation":"262.0",
    "gn:feature_class":"P",
    "gn:feature_code":"PPL",
    "gn:name":"Klingers",
    "gn:population":0,
    "gn:timezone":"America/Detroit",
    "iso:country":"US",
    "wof:name":"Klingers",
    "wof:placetype":"locality"
},
  "geometry": {"coordinates":[-85.5261,41.79311],"type":"Point"}
}