{
  "type": "Feature",
  "properties": {
    "gn:admin1_code":"CO",
    "gn:admin2_code":"85.0",
    "gn:asciiname":"Houser Cow Camp",
    "gn:country_code":"US",
    "gn:dem":2613,
    "gn:elevation":"2596.0",
    "gn:feature_class":"P",
    "gn:feature_code":"PPL",
    "gn:name":"Houser Cow Camp",
    "gn:population":0,
    "gn:timezone":"America/Denver",
    "iso:country":"US",
    "wof:name":"Houser Cow Camp",
    "wof:placetype":"locality"
},
  "geometry": {"coordinates":[-108.30564,38.32943],"type":"Point"}
}