{
  "type": "Feature",
  "properties": {
    "gn:country":"US",
    "gn:fcode":"PPL",
    "gn:population":288649,
    "iso:country":"US",
    "name:azb_x_preferred":[
        "\u0622\u06cc\u0631\u0648\u0646\u0648\u06cc\u0644"
    ],
    "name:ceb_x_preferred":[
        "Ironville"
    ],
    "name:eng_x_preferred":[
        "Ironville"
    ],
    "name:fas_x_preferred":[
        "\u0622\u06cc\u0631\u0648\u0646\u0648\u06cc\u0644"
    ],
    "name:fra_x_preferred":[
        "Ironville"
    ],
    "name:lld_x_preferred":[
        "Ironville"
    ],
    "name:vol_x_preferred":[
        "Ironville"
    ],
    "name:zho_x_preferred":[
        "\u827e\u6069\u7dad\u723e"
    ],
    "qs_pg:aaroncc":"US",
    "qs_pg:gn_country":"US",
    "qs_pg:gn_fcode":"PPL",
    "qs_pg:gn_pop":288649,
    "qs_pg:name":"Ironville",
    "qs_pg:name_adm0":"United States",
    "qs_pg:name_adm1":"Kentucky",
    "qs_pg:photos_9r":0,
    "qs_pg:photos_sr":0,
    "qs_pg:pop_sr":10,
    "qs_pg:qs_pg_placetype":"locality",
    "qs_pg:qs_pg_placetype_gp":"Town",
    "qs_pg:woe_adm0":23424977,
    "woe:adm0_id":23424977,
    "woe:name_adm0":"United States",
    "woe:name_adm1":"Kentucky",
    "woe:placetype":"Town",
    "wof:name":"Ironville",
    "wof:placetype":"locality",
    "wof:population":288649
},
  "geometry": {"coordinates":[-82.69238,38.45647],"type":"Point"}
}