{
  "type": "Feature",
  "properties": {
    "iso:country":"US",
    "name:eng_x_preferred":[
        "33rd Street Industrial"
    ],
    "wof:name":"33rd Street Industrial",
    "wof:placetype":"neighbourhood",
    "zs:area_m":104782.8054,
    "zs:blockids":[
        120950146061001
    ],
    "zs:housing10":0,
    "zs:label":"33rd Street Industrial",
    "zs:pop10":0
},
  "geometry": {"coordinates":[-81.426788,28.504296],"type":"Point"}
}