{
  "type": "Feature",
  "properties": {
    "gn:admin1_code":"VA",
    "gn:admin2_code":"85",
    "gn:asciiname":"Burnside Farms",
    "gn:country_code":"US",
    "gn:dem":57,
    "gn:elevation":"53.0",
    "gn:feature_class":"P",
    "gn:feature_code":"PPL",
    "gn:name":"Burnside Farms",
    "gn:population":0,
    "gn:timezone":"America/New_York",
    "iso:country":"US",
    "wof:name":"Burnside Farms",
    "wof:placetype":"locality"
},
  "geometry": {"coordinates":[-77.39386999999998,37.62626],"type":"Point"}
}