{
  "type": "Feature",
  "properties": {
    "gn:admin1_code":"MO",
    "gn:admin2_code":"25.0",
    "gn:admin3_code":"52400.0",
    "gn:asciiname":"Easterville",
    "gn:country_code":"US",
    "gn:dem":282,
    "gn:elevation":"281.0",
    "gn:feature_class":"P",
    "gn:feature_code":"PPL",
    "gn:name":"Easterville",
    "gn:population":0,
    "gn:timezone":"America/Chicago",
    "iso:country":"US",
    "wof:name":"Easterville",
    "wof:placetype":"locality"
},
  "geometry": {"coordinates":[-93.8991,39.62723],"type":"Point"}
}