{
  "type": "Feature",
  "properties": {
    "gn:admin1_code":"AR",
    "gn:admin2_code":"93.0",
    "gn:admin3_code":"92664.0",
    "gn:asciiname":"Clearwater",
    "gn:country_code":"US",
    "gn:dem":74,
    "gn:elevation":"72.0",
    "gn:feature_class":"P",
    "gn:feature_code":"PPL",
    "gn:name":"Clearwater",
    "gn:population":0,
    "gn:timezone":"America/Chicago",
    "iso:country":"US",
    "name:bul_x_preferred":[
        "\u041a\u043b\u0438\u044a\u0440\u0443\u043e\u0442\u044a\u0440"
    ],
    "name:cat_x_preferred":[
        "Clearwater"
    ],
    "name:ceb_x_preferred":[
        "Clearwater"
    ],
    "name:deu_x_preferred":[
        "Clearwater"
    ],
    "name:fas_x_preferred":[
        "\u06a9\u0644\u06cc\u0631\u0648\u0627\u062a\u0631"
    ],
    "name:fin_x_preferred":[
        "Clearwater"
    ],
    "name:fra_x_preferred":[
        "Clearwater"
    ],
    "name:hun_x_preferred":[
        "Clearwater"
    ],
    "name:ido_x_preferred":[
        "Clearwater"
    ],
    "name:ita_x_preferred":[
        "Clearwater"
    ],
    "name:kor_x_preferred":[
        "\ud074\ub9ac\uc5b4\uc6cc\ud130"
    ],
    "name:nld_x_preferred":[
        "Clearwater"
    ],
    "name:pol_x_preferred":[
        "Clearwater"
    ],
    "name:por_x_preferred":[
        "Clearwater"
    ],
    "name:rus_x_preferred":[
        "\u041a\u043b\u0438\u0440\u0443\u043e\u0442\u0435\u0440"
    ],
    "name:spa_x_preferred":[
        "Clearwater"
    ],
    "name:srp_x_preferred":[
        "\u041a\u043b\u0438\u0440\u0432\u043e\u0442\u0435\u0440"
    ],
    "name:swe_x_preferred":[
        "Clearwater"
    ],
    "name:ukr_x_preferred":[
        "\u041a\u043b\u0456\u0440\u0432\u043e\u0442\u0435\u0440"
    ],
    "name:urd_x_preferred":[
        "\u06a9\u0644\u06cc\u0626\u0631\u0648\u0627\u0679\u0631"
    ],
    "name:vol_x_preferred":[
        "Clearwater"
    ],
    "wof:name":"Clearwater",
    "wof:placetype":"locality"
},
  "geometry": {"coordinates":[-90.25704,35.92341],"type":"Point"}
}