{
  "type": "Feature",
  "properties": {
    "gn:admin1_code":"MO",
    "gn:admin2_code":"27.0",
    "gn:admin3_code":"10414.0",
    "gn:asciiname":"Dixie",
    "gn:country_code":"US",
    "gn:dem":247,
    "gn:elevation":"250.0",
    "gn:feature_class":"P",
    "gn:feature_code":"PPL",
    "gn:name":"Dixie",
    "gn:population":0,
    "gn:timezone":"America/Chicago",
    "iso:country":"US",
    "name:ara_x_preferred":[
        "\u062f\u0643\u0633\u064a"
    ],
    "name:bre_x_preferred":[
        "Dixie"
    ],
    "name:cat_x_preferred":[
        "Dixie"
    ],
    "name:deu_x_preferred":[
        "Dixieland"
    ],
    "name:eml_x_preferred":[
        "Dixie"
    ],
    "name:est_x_preferred":[
        "Dixie"
    ],
    "name:fas_x_preferred":[
        "\u062f\u06cc\u06a9\u0633\u06cc"
    ],
    "name:fra_x_preferred":[
        "Dixie"
    ],
    "name:hun_x_preferred":[
        "Dixie"
    ],
    "name:ita_x_preferred":[
        "Dixie"
    ],
    "name:jpn_x_preferred":[
        "\u30c7\u30a3\u30ad\u30b7\u30fc"
    ],
    "name:nld_x_preferred":[
        "Dixie"
    ],
    "name:nor_x_preferred":[
        "Dixie"
    ],
    "name:pol_x_preferred":[
        "Dixie"
    ],
    "name:por_x_preferred":[
        "Dixie"
    ],
    "name:rus_x_preferred":[
        "\u0414\u0438\u043a\u0441\u0438"
    ],
    "name:spa_x_preferred":[
        "Dixie"
    ],
    "name:srp_x_preferred":[
        "\u0414\u0438\u043a\u0441\u0438"
    ],
    "name:swe_x_preferred":[
        "Dixie"
    ],
    "name:zho_x_preferred":[
        "\u8fea\u514b\u897f"
    ],
    "wof:name":"Dixie",
    "wof:placetype":"locality"
},
  "geometry": {"coordinates":[-92.00935,38.71893],"type":"Point"}
}