{
  "type": "Feature",
  "properties": {
    "gn:admin1_code":"KY",
    "gn:admin2_code":"27",
    "gn:asciiname":"McCoy",
    "gn:country_code":"US",
    "gn:dem":219,
    "gn:elevation":"221.0",
    "gn:feature_class":"P",
    "gn:feature_code":"PPL",
    "gn:name":"McCoy",
    "gn:population":0,
    "gn:timezone":"America/Chicago",
    "iso:country":"US",
    "name:ces_x_preferred":[
        "McCoy"
    ],
    "name:deu_x_preferred":[
        "McCoy"
    ],
    "name:epo_x_preferred":[
        "McCoy"
    ],
    "name:fra_x_preferred":[
        "McCoy"
    ],
    "name:heb_x_preferred":[
        "\u05de\u05e7\u05d5\u05d9"
    ],
    "name:ita_x_preferred":[
        "McCoy"
    ],
    "name:jpn_x_preferred":[
        "\u30de\u30c3\u30b3\u30a4"
    ],
    "name:kor_x_preferred":[
        "\ub9e4\ucf54\uc774"
    ],
    "name:por_x_preferred":[
        "McCoy"
    ],
    "name:rus_x_preferred":[
        "\u041c\u0430\u043a\u043a\u043e\u0439"
    ],
    "name:spa_x_preferred":[
        "McCoy"
    ],
    "name:ukr_x_preferred":[
        "\u041c\u0430\u043a\u043a\u043e\u0439"
    ],
    "wof:name":"McCoy",
    "wof:placetype":"locality"
},
  "geometry": {"coordinates":[-86.38164,37.61867],"type":"Point"}
}