{
  "type": "Feature",
  "properties": {
    "iso:country":"US",
    "name:bar_x_preferred":[
        "Bellevue"
    ],
    "name:bre_x_preferred":[
        "Bellevue"
    ],
    "name:bul_x_preferred":[
        "\u0411\u0435\u043b\u0432\u044e"
    ],
    "name:cat_x_preferred":[
        "Bellevue"
    ],
    "name:ceb_x_preferred":[
        "Bellevue"
    ],
    "name:dan_x_preferred":[
        "Bellevue"
    ],
    "name:deu_x_preferred":[
        "Bellevue"
    ],
    "name:eng_x_preferred":[
        "Bellevue"
    ],
    "name:epo_x_preferred":[
        "Bellevue"
    ],
    "name:eus_x_preferred":[
        "Bellevue"
    ],
    "name:fas_x_preferred":[
        "\u0628\u0644\u0648\u06cc\u0648"
    ],
    "name:fin_x_preferred":[
        "Bellevue"
    ],
    "name:fra_x_preferred":[
        "Bellevue"
    ],
    "name:ita_x_preferred":[
        "Bellevue"
    ],
    "name:jpn_x_preferred":[
        "\u30d9\u30eb\u30d3\u30e5\u30fc"
    ],
    "name:nld_x_preferred":[
        "Bellevue"
    ],
    "name:nor_x_preferred":[
        "Bellevue"
    ],
    "name:pol_x_preferred":[
        "Bellevue"
    ],
    "name:por_x_preferred":[
        "Bellevue"
    ],
    "name:rus_x_preferred":[
        "\u0411\u0435\u043b\u044c\u0432\u044e"
    ],
    "name:spa_x_preferred":[
        "Bellevue"
    ],
    "name:swe_x_preferred":[
        "Bellevue"
    ],
    "name:ukr_x_preferred":[
        "\u0411\u0435\u043b\u044c\u0432\u044e"
    ],
    "name:vol_x_preferred":[
        "Bellevue"
    ],
    "name:zho_x_preferred":[
        "\u8d1d\u5c14\u7ef4\u5c24"
    ],
    "wof:name":"Bellevue",
    "wof:placetype":"neighbourhood",
    "wof:population":766,
    "zs:area_m":1008316.919558,
    "zs:blockids":[
        130210118004015,
        130210118003001,
        130210118004010,
        130210118004012,
        130210118004009,
        130210118004016,
        130210118003013,
        130210118004004,
        130210118004017,
        130210118004003,
        130210118004014,
        130210118003007,
        130210121011030,
        130210118004007,
        130210118003000,
        130210121022037,
        130210121022036,
        130210118003008,
        130210118003002,
        130210118004005,
        130210118004013,
        130210118004011
    ],
    "zs:housing10":404,
    "zs:label":"Bellevue",
    "zs:pop10":766
},
  "geometry": {"coordinates":[-83.686567,32.864129],"type":"Point"}
}