{
  "type": "Feature",
  "properties": {
    "gn:admin1_code":"IL",
    "gn:admin2_code":"69",
    "gn:asciiname":"Karbers Ridge",
    "gn:country_code":"US",
    "gn:dem":181,
    "gn:elevation":"183.0",
    "gn:feature_class":"P",
    "gn:feature_code":"PPL",
    "gn:name":"Karbers Ridge",
    "gn:population":0,
    "gn:timezone":"America/Chicago",
    "iso:country":"US",
    "name:eng_x_preferred":[
        "Karbers Ridge"
    ],
    "name:und_x_variant":[
        "Karber's Ridge"
    ],
    "wof:name":"Karbers Ridge",
    "wof:placetype":"locality"
},
  "geometry": {"coordinates":[-88.33337,37.57977],"type":"Point"}
}