{
  "type": "Feature",
  "properties": {
    "iso:country":"US",
    "name:eng_x_preferred":[
        "Westshore"
    ],
    "wof:name":"Westshore",
    "wof:placetype":"neighbourhood",
    "wof:population":279,
    "zs:area_m":142440.195916,
    "zs:blockids":[
        61110059073002,
        61110059073023,
        61110059073011,
        61110059073003,
        61110059073020,
        61110059073021,
        61110059073008,
        61110059072006,
        61110059073007,
        61110059073004
    ],
    "zs:housing10":153,
    "zs:label":"Westshore",
    "zs:pop10":279
},
  "geometry": {"coordinates":[-118.83709500000001,34.146289],"type":"Point"}
}