{
  "type": "Feature",
  "properties": {
    "iso:country":"US",
    "name:eng_x_preferred":[
        "Riverview Crest"
    ],
    "wof:name":"Riverview Crest",
    "wof:placetype":"neighbourhood",
    "wof:population":1716,
    "zs:area_m":4547937.763435,
    "zs:blockids":[
        120570134122016,
        120570139081001,
        120570139081007,
        120570139081012,
        120570139081023,
        120570138061000,
        120570138022002,
        120570139081006,
        120570139082006,
        120570139082012,
        120570139081003,
        120570139081000,
        120570139082009,
        120570139082015,
        120570139082004,
        120570139081020,
        120570138022005,
        120570139081015,
        120570139081008,
        120570139081009,
        120570139082013,
        120570139082008,
        120570139082010,
        120570134122021,
        120570139081019,
        120570138022003,
        120570138022004,
        120570139081010,
        120570139082011,
        120570139081018,
        120570139081005,
        120570139082035,
        120570138061003,
        120570139081011,
        120570139081016,
        120570139082040,
        120570139082020,
        120570139081021,
        120570139081024,
        120570139082003,
        120570139081004,
        120570134122020,
        120570139081002,
        120570139082034,
        120570139082007,
        120570139081017,
        120570139081022
    ],
    "zs:housing10":1149,
    "zs:label":"Riverview Crest",
    "zs:pop10":1716
},
  "geometry": {"coordinates":[-82.327933,27.854276],"type":"Point"}
}