{
  "type": "Feature",
  "properties": {
    "iso:country":"US",
    "name:deu_x_preferred":[
        "Boggs"
    ],
    "name:fra_x_preferred":[
        "Boggs"
    ],
    "name:ita_x_preferred":[
        "Boggs"
    ],
    "name:jpn_x_preferred":[
        "\u30dc\u30c3\u30b0\u30b9"
    ],
    "name:pol_x_preferred":[
        "Boggs"
    ],
    "name:rus_x_preferred":[
        "\u0411\u043e\u0433\u0433\u0441"
    ],
    "name:ukr_x_preferred":[
        "\u0411\u043e\u0433\u0433\u0441"
    ],
    "qs_pg:aaroncc":"US",
    "qs_pg:name":"Boggs",
    "qs_pg:name_adm0":"United States",
    "qs_pg:name_adm1":"Pennsylvania",
    "qs_pg:photos":12,
    "qs_pg:photos_1k":2,
    "qs_pg:photos_9k":1,
    "qs_pg:photos_9r":2,
    "qs_pg:photos_all":31,
    "qs_pg:photos_sr":1,
    "qs_pg:pop_sr":0,
    "qs_pg:qs_pg_placetype":"locality",
    "qs_pg:qs_pg_placetype_gp":"Town",
    "qs_pg:woe_adm0":23424977,
    "woe:adm0_id":23424977,
    "woe:name_adm0":"United States",
    "woe:name_adm1":"Pennsylvania",
    "woe:placetype":"Town",
    "wof:name":"Boggs",
    "wof:placetype":"locality"
},
  "geometry": {"coordinates":[-77.81831750000001,40.993245],"type":"Point"}
}