{
  "type": "Feature",
  "properties": {
    "gn:admin1_code":"SC",
    "gn:admin2_code":"89.0",
    "gn:asciiname":"Rock Bluff",
    "gn:country_code":"US",
    "gn:dem":19,
    "gn:elevation":"14.0",
    "gn:feature_class":"P",
    "gn:feature_code":"PPL",
    "gn:name":"Rock Bluff",
    "gn:population":0,
    "gn:timezone":"America/New_York",
    "iso:country":"US",
    "wof:name":"Rock Bluff",
    "wof:placetype":"locality"
},
  "geometry": {"coordinates":[-79.81285,33.60572],"type":"Point"}
}