{
  "type": "Feature",
  "properties": {
    "gn:admin1_code":"OH",
    "gn:admin2_code":"63.0",
    "gn:admin3_code":"6362.0",
    "gn:asciiname":"West Independence",
    "gn:country_code":"US",
    "gn:dem":255,
    "gn:elevation":"254.0",
    "gn:feature_class":"P",
    "gn:feature_code":"PPL",
    "gn:name":"West Independence",
    "gn:population":0,
    "gn:timezone":"America/New_York",
    "iso:country":"US",
    "name:eng_x_preferred":[
        "West Independence"
    ],
    "name:und_x_variant":[
        "Independence"
    ],
    "wof:name":"West Independence",
    "wof:placetype":"locality"
},
  "geometry": {"coordinates":[-83.44104,41.07672],"type":"Point"}
}