{
  "type": "Feature",
  "properties": {
    "gn:admin1_code":"AR",
    "gn:admin2_code":"103.0",
    "gn:asciiname":"Tates Bluff",
    "gn:country_code":"US",
    "gn:dem":64,
    "gn:elevation":"61.0",
    "gn:feature_class":"P",
    "gn:feature_code":"PPL",
    "gn:name":"Tates Bluff",
    "gn:population":0,
    "gn:timezone":"America/Chicago",
    "iso:country":"US",
    "name:fas_x_preferred":[
        "\u062a\u06cc\u062a\u0633 \u0628\u0644\u0627\u0641"
    ],
    "name:zho_x_preferred":[
        "\u6cf0\u8328\u5e03\u62c9\u592b"
    ],
    "wof:name":"Tates Bluff",
    "wof:placetype":"locality"
},
  "geometry": {"coordinates":[-92.901,33.79899],"type":"Point"}
}