{
  "type": "Feature",
  "properties": {
    "gn:country":"US",
    "gn:fcode":"PPL",
    "gn:population":0,
    "iso:country":"US",
    "name:ben_x_preferred":[
        "\u09b8\u09cd\u099f\u09c7\u09ab\u09c7\u09a8\u09ad\u09bf\u09b2\u09c7"
    ],
    "name:ceb_x_preferred":[
        "Stephenville"
    ],
    "name:deu_x_preferred":[
        "Stephenville"
    ],
    "name:ell_x_preferred":[
        "\u03a3\u03c4\u03ad\u03c6\u03b5\u03bd\u03b2\u03b9\u03bb"
    ],
    "name:eng_x_preferred":[
        "Stephenville"
    ],
    "name:fas_x_preferred":[
        "\u0627\u0633\u062a\u0641\u0646 \u0648\u06cc\u0644"
    ],
    "name:heb_x_preferred":[
        "\u05e1\u05d8\u05e4\u05e0\u05d5\u05d5\u05d9\u05dc"
    ],
    "name:hin_x_preferred":[
        "\u0938\u094d\u091f\u0940\u092b\u093c\u0947\u0928\u0935\u093f\u0932\u093e"
    ],
    "name:hun_x_preferred":[
        "Stephenville"
    ],
    "name:ind_x_preferred":[
        "Stephenville"
    ],
    "name:ita_x_preferred":[
        "Stephenville"
    ],
    "name:jpn_x_preferred":[
        "\u30b9\u30c6\u30a3\u30fc\u30d6\u30f3\u30d3\u30eb"
    ],
    "name:kor_x_preferred":[
        "\uc2a4\ud2f0\ube10\ube4c"
    ],
    "name:nld_x_preferred":[
        "Stephenville"
    ],
    "name:pol_x_preferred":[
        "Stephenville"
    ],
    "name:spa_x_preferred":[
        "Stephenville"
    ],
    "name:swe_x_preferred":[
        "Stephenville"
    ],
    "name:tur_x_preferred":[
        "Stephenville"
    ],
    "name:und_x_variant":[
        "Stephensville"
    ],
    "name:urd_x_preferred":[
        "\u0627\u0633\u0679\u06cc\u0641\u0646\u0648\u0644\u06d2"
    ],
    "name:vie_x_preferred":[
        "Stephenville"
    ],
    "qs_pg:aaroncc":"US",
    "qs_pg:gn_country":"US",
    "qs_pg:gn_fcode":"PPL",
    "qs_pg:gn_pop":0,
    "qs_pg:name":"Stephenville",
    "qs_pg:name_adm0":"United States",
    "qs_pg:name_adm1":"Louisiana",
    "qs_pg:photos":45,
    "qs_pg:photos_1k":9,
    "qs_pg:photos_9k":1,
    "qs_pg:photos_9r":2,
    "qs_pg:photos_all":45,
    "qs_pg:photos_sr":2,
    "qs_pg:pop_sr":0,
    "qs_pg:qs_pg_placetype":"locality",
    "qs_pg:qs_pg_placetype_gp":"Town",
    "qs_pg:woe_adm0":23424977,
    "woe:adm0_id":23424977,
    "woe:name_adm0":"United States",
    "woe:name_adm1":"Louisiana",
    "woe:placetype":"Town",
    "wof:name":"Stephenville",
    "wof:placetype":"locality"
},
  "geometry": {"coordinates":[-91.16594000000001,29.77826],"type":"Point"}
}