{
  "type": "Feature",
  "properties": {
    "gn:gn_country":"US",
    "gn:gn_fcode":"PPL",
    "gn:gn_pop":0,
    "iso:country":"US",
    "name:ceb_x_preferred":[
        "Stephenville"
    ],
    "name:deu_x_preferred":[
        "Stephenville"
    ],
    "name:eng_x_preferred":[
        "Stephenville"
    ],
    "name:ita_x_preferred":[
        "Stephenville"
    ],
    "name:nld_x_preferred":[
        "Stephenville"
    ],
    "name:pol_x_preferred":[
        "Stephenville"
    ],
    "name:swe_x_preferred":[
        "Stephenville"
    ],
    "name:unk_x_variant":[
        "Stephensville"
    ],
    "qs_pg:aaroncc":"US",
    "qs_pg:gn_country":"US",
    "qs_pg:gn_fcode":"PPL",
    "qs_pg:gn_pop":0,
    "qs_pg:name":"Stephenville",
    "qs_pg:name_adm0":"United States",
    "qs_pg:name_adm1":"Louisiana",
    "qs_pg:photos":45,
    "qs_pg:photos_1k":9,
    "qs_pg:photos_9k":1,
    "qs_pg:photos_9r":2,
    "qs_pg:photos_all":45,
    "qs_pg:photos_sr":2,
    "qs_pg:pop_sr":0,
    "qs_pg:qs_pg_placetype":"locality",
    "qs_pg:qs_pg_placetype_gp":"Town",
    "qs_pg:woe_adm0":23424977,
    "woe:adm0_id":23424977,
    "woe:name_adm0":"United States",
    "woe:name_adm1":"Louisiana",
    "woe:placetype":"Town",
    "wof:name":"Stephenville",
    "wof:placetype":"locality"
},
  "geometry": {"coordinates":[-91.16594000000001,29.77826],"type":"Point"}
}