{
  "type": "Feature",
  "properties": {
    "gn:admin1_code":"WV",
    "gn:admin2_code":"77",
    "gn:asciiname":"Bretz",
    "gn:country_code":"US",
    "gn:dem":550,
    "gn:elevation":"551.0",
    "gn:feature_class":"P",
    "gn:feature_code":"PPL",
    "gn:name":"Bretz",
    "gn:population":0,
    "gn:timezone":"America/New_York",
    "iso:country":"US",
    "name:deu_x_preferred":[
        "Bretz"
    ],
    "name:ita_x_preferred":[
        "Bretz"
    ],
    "name:rus_x_preferred":[
        "\u0411\u0440\u0435\u0442\u0446"
    ],
    "wof:name":"Bretz",
    "wof:placetype":"locality"
},
  "geometry": {"coordinates":[-79.80060999999998,39.54231],"type":"Point"}
}