{
  "type": "Feature",
  "properties": {
    "gn:country":"US",
    "gn:fcode":"PPL",
    "gn:population":0,
    "iso:country":"US",
    "name:deu_x_preferred":[
        "Tapiola"
    ],
    "name:eng_x_preferred":[
        "Tapiola"
    ],
    "name:eus_x_preferred":[
        "Tapiola"
    ],
    "name:fin_x_preferred":[
        "Tapiola"
    ],
    "name:fra_x_preferred":[
        "Tapiola"
    ],
    "name:nld_x_preferred":[
        "Tapiola"
    ],
    "name:pol_x_preferred":[
        "Tapiola"
    ],
    "name:rus_x_preferred":[
        "\u0422\u0430\u043f\u0438\u043e\u043b\u0430"
    ],
    "name:spa_x_preferred":[
        "Tapiola"
    ],
    "name:swe_x_preferred":[
        "Hagalund"
    ],
    "name:tur_x_preferred":[
        "Tapiola"
    ],
    "qs_pg:aaroncc":"US",
    "qs_pg:gn_country":"US",
    "qs_pg:gn_fcode":"PPL",
    "qs_pg:gn_pop":0,
    "qs_pg:name":"Tapiola",
    "qs_pg:name_adm0":"United States",
    "qs_pg:name_adm1":"Michigan",
    "qs_pg:photos":5,
    "qs_pg:photos_1k":1,
    "qs_pg:photos_9k":1,
    "qs_pg:photos_9r":1,
    "qs_pg:photos_all":5,
    "qs_pg:photos_sr":1,
    "qs_pg:pop_sr":0,
    "qs_pg:qs_pg_placetype":"neighbourhood",
    "qs_pg:qs_pg_placetype_gp":"Suburb",
    "qs_pg:woe_adm0":23424977,
    "wd:wordcount":2814,
    "wof:name":"Tapiola",
    "wof:placetype":"neighbourhood",
    "wof:population":118,
    "zs:area_m":14310898.746846,
    "zs:blockids":[
        260610007003105,
        260610010003063,
        260610010003069,
        260610010003062,
        260610010003066,
        260610007003106,
        260610010003064,
        260610010003057
    ],
    "zs:housing10":76,
    "zs:label":"Tapiola",
    "zs:pop10":118
},
  "geometry": {"coordinates":[-88.634912,46.9243],"type":"Point"}
}