{
  "type": "Feature",
  "properties": {
    "gn:admin1_code":"WY",
    "gn:admin2_code":"45.0",
    "gn:asciiname":"Clay Spur",
    "gn:country_code":"US",
    "gn:dem":1277,
    "gn:elevation":"1276.0",
    "gn:feature_class":"P",
    "gn:feature_code":"PPL",
    "gn:name":"Clay Spur",
    "gn:population":0,
    "gn:timezone":"America/Denver",
    "iso:country":"US",
    "wof:name":"Clay Spur",
    "wof:placetype":"locality"
},
  "geometry": {"coordinates":[-104.47633999999999,44.02248],"type":"Point"}
}