{
  "type": "Feature",
  "properties": {
    "gn:admin1_code":"AZ",
    "gn:admin2_code":"13.0",
    "gn:asciiname":"Liberty Mobile Home Park",
    "gn:country_code":"US",
    "gn:dem":453,
    "gn:elevation":"457.0",
    "gn:feature_class":"P",
    "gn:feature_code":"PPL",
    "gn:name":"Liberty Mobile Home Park",
    "gn:population":0,
    "gn:timezone":"America/Phoenix",
    "iso:country":"US",
    "wof:name":"Liberty Mobile Home Park",
    "wof:placetype":"campus"
},
  "geometry": {"coordinates":[-112.02515,33.66782],"type":"Point"}
}