{
  "type": "Feature",
  "properties": {
    "gn:country":"US",
    "gn:fcode":"PPL",
    "gn:population":0,
    "iso:country":"US",
    "name:azb_x_preferred":[
        "\u0622\u0644\u06a9\u0633\u06cc\u0633"
    ],
    "name:eng_x_preferred":[
        "Alexis"
    ],
    "name:fas_x_preferred":[
        "\u0627\u0644\u06a9\u0633\u06cc\u0633\u060c \u06a9\u0627\u0631\u0648\u0644\u06cc\u0646\u0627 \u0634\u0645\u0627\u0644\u06cc"
    ],
    "name:fas_x_variant":[
        "\u0627\u0644\u06a9\u0633\u06cc\u0633"
    ],
    "name:fra_x_preferred":[
        "Alexis"
    ],
    "name:lld_x_preferred":[
        "Alexis"
    ],
    "name:und_x_variant":[
        "Alex's Cross Roads"
    ],
    "qs_pg:aaroncc":"US",
    "qs_pg:gn_country":"US",
    "qs_pg:gn_fcode":"PPL",
    "qs_pg:gn_pop":0,
    "qs_pg:name":"Alexis",
    "qs_pg:name_adm0":"United States",
    "qs_pg:name_adm1":"North Carolina",
    "qs_pg:photos_9k":1,
    "qs_pg:photos_9r":1,
    "qs_pg:photos_all":19,
    "qs_pg:photos_sr":0,
    "qs_pg:pop_sr":0,
    "qs_pg:qs_pg_placetype":"locality",
    "qs_pg:qs_pg_placetype_gp":"Town",
    "qs_pg:woe_adm0":23424977,
    "woe:adm0_id":23424977,
    "woe:name_adm0":"United States",
    "woe:name_adm1":"North Carolina",
    "woe:placetype":"Town",
    "wof:name":"Alexis",
    "wof:placetype":"locality"
},
  "geometry": {"coordinates":[-81.11785999999999,35.39986],"type":"Point"}
}