{
  "type": "Feature",
  "properties": {
    "gn:admin1_code":"UT",
    "gn:admin2_code":"57.0",
    "gn:asciiname":"The Meadows PRUD",
    "gn:country_code":"US",
    "gn:dem":1472,
    "gn:elevation":"1470.0",
    "gn:feature_class":"P",
    "gn:feature_code":"PPL",
    "gn:name":"The Meadows PRUD",
    "gn:population":0,
    "gn:timezone":"America/Denver",
    "iso:country":"US",
    "wof:name":"The Meadows PRUD",
    "wof:placetype":"locality"
},
  "geometry": {"coordinates":[-111.93383,41.16022],"type":"Point"}
}