{
  "type": "Feature",
  "properties": {
    "iso:country":"US",
    "name:ceb_x_preferred":[
        "Green Lake"
    ],
    "name:deu_x_preferred":[
        "Green Lake"
    ],
    "name:epo_x_preferred":[
        "Verda Lago"
    ],
    "name:fra_x_preferred":[
        "Green Lake"
    ],
    "name:ita_x_preferred":[
        "Green Lake"
    ],
    "name:nld_x_preferred":[
        "Green Lake"
    ],
    "name:pol_x_preferred":[
        "Green Lake"
    ],
    "name:rus_x_preferred":[
        "\u0413\u0440\u0438\u043d-\u041b\u0435\u0439\u043a"
    ],
    "name:srp_x_preferred":[
        "\u0413\u0440\u0438\u043d \u041b\u0435\u0458\u043a"
    ],
    "name:swe_x_preferred":[
        "Green Lake"
    ],
    "name:ukr_x_preferred":[
        "\u0413\u0440\u0456\u043d-\u041b\u0435\u0439\u043a"
    ],
    "qs_pg:aaroncc":"US",
    "qs_pg:name":"Green Lake",
    "qs_pg:name_adm0":"United States",
    "qs_pg:name_adm1":"Utah",
    "qs_pg:photos":203,
    "qs_pg:photos_1k":41,
    "qs_pg:photos_9k":1,
    "qs_pg:photos_9r":4,
    "qs_pg:photos_all":203,
    "qs_pg:photos_sr":4,
    "qs_pg:pop_sr":0,
    "qs_pg:qs_pg_placetype":"locality",
    "qs_pg:qs_pg_placetype_gp":"Town",
    "qs_pg:woe_adm0":23424977,
    "woe:adm0_id":23424977,
    "woe:name_adm0":"United States",
    "woe:name_adm1":"Utah",
    "woe:placetype":"Town",
    "wof:name":"Green Lake",
    "wof:placetype":"locality"
},
  "geometry": {"coordinates":[-109.56037600000001,40.891788],"type":"Point"}
}