{
  "type": "Feature",
  "properties": {
    "gn:elevation":46,
    "iso:country":"US",
    "name:arz_x_preferred":[
        "\u0627\u064a\u0644\u064a\u0627\u0645\u0646\u0627 \u0627\u064a\u0631\u067e\u0648\u0631\u062a"
    ],
    "name:ceb_x_preferred":[
        "Iliamna Airport"
    ],
    "name:cym_x_preferred":[
        "Maes Awyr Iliamna"
    ],
    "name:eng_x_preferred":[
        "Iliamna Airport"
    ],
    "name:eng_x_variant":[
        "ILI",
        "PAIL"
    ],
    "name:fas_x_preferred":[
        "\u0641\u0631\u0648\u062f\u06af\u0627\u0647 \u0627\u06cc\u0644\u06cc\u0627\u0645\u0646\u0627"
    ],
    "name:fra_x_preferred":[
        "a\u00e9rodrome d'Iliamna"
    ],
    "name:ron_x_preferred":[
        "Aeroportul Iliamna"
    ],
    "name:rus_x_preferred":[
        "\u0418\u043b\u0438\u0430\u043c\u043d\u0430"
    ],
    "name:rus_x_variant":[
        "\u0418\u043b\u043b\u0430\u043c\u043d\u0430"
    ],
    "name:tgk_x_preferred":[
        "\u0424\u0443\u0440\u0443\u0434\u0433\u043e\u04b3\u0438 \u043e\u0438\u043b\u0438\u043e\u043c\u043d\u043e"
    ],
    "oa:elevation_ft":"192",
    "oa:type":"medium_airport",
    "wd:wordcount":223,
    "woe:hierarchy":{
        "country_id":23424977,
        "county_id":12587567,
        "planet_id":1,
        "state_id":2347560
    },
    "wof:name":"Iliamna Airport",
    "wof:placetype":"campus"
},
  "geometry": {"coordinates":[-154.91099600000001,59.754398],"type":"Point"}
}