{
  "type": "Feature",
  "properties": {
    "gn:admin1_code":"PA",
    "gn:admin2_code":"11",
    "gn:admin3_code":"24384.0",
    "gn:asciiname":"Grist Mill Farms",
    "gn:country_code":"US",
    "gn:dem":95,
    "gn:elevation":"91.0",
    "gn:feature_class":"P",
    "gn:feature_code":"PPL",
    "gn:name":"Grist Mill Farms",
    "gn:population":0,
    "gn:timezone":"America/New_York",
    "iso:country":"US",
    "wof:name":"Grist Mill Farms",
    "wof:placetype":"locality"
},
  "geometry": {"coordinates":[-75.85259000000001,40.31385],"type":"Point"}
}