{
  "type": "Feature",
  "properties": {
    "gn:admin1_code":"CO",
    "gn:admin2_code":"89.0",
    "gn:asciiname":"Ayer",
    "gn:country_code":"US",
    "gn:dem":1394,
    "gn:elevation":"1397.0",
    "gn:feature_class":"P",
    "gn:feature_code":"PPL",
    "gn:name":"Ayer",
    "gn:population":0,
    "gn:timezone":"America/Denver",
    "iso:country":"US",
    "name:arg_x_preferred":[
        "Ayer"
    ],
    "name:cat_x_preferred":[
        "Ayer"
    ],
    "name:ceb_x_preferred":[
        "Ayer"
    ],
    "name:deu_x_preferred":[
        "Ayer"
    ],
    "name:fas_x_preferred":[
        "\u0622\u06cc\u0631"
    ],
    "name:fra_x_preferred":[
        "Ayer"
    ],
    "name:ita_x_preferred":[
        "Ayer"
    ],
    "name:nld_x_preferred":[
        "Ayer"
    ],
    "name:pol_x_preferred":[
        "Ayer"
    ],
    "name:rus_x_preferred":[
        "\u0410\u0439\u0435\u0440"
    ],
    "name:spa_x_preferred":[
        "Ayer"
    ],
    "name:swe_x_preferred":[
        "Ayer"
    ],
    "name:vol_x_preferred":[
        "Ayer"
    ],
    "wof:name":"Ayer",
    "wof:placetype":"locality"
},
  "geometry": {"coordinates":[-103.84634,37.75807],"type":"Point"}
}