{
  "type": "Feature",
  "properties": {
    "gn:admin1_code":"MD",
    "gn:admin2_code":"13.0",
    "gn:asciiname":"Whistling Ridge Estates",
    "gn:country_code":"US",
    "gn:dem":181,
    "gn:elevation":"184.0",
    "gn:feature_class":"P",
    "gn:feature_code":"PPL",
    "gn:name":"Whistling Ridge Estates",
    "gn:population":0,
    "gn:timezone":"America/New_York",
    "iso:country":"US",
    "wof:name":"Whistling Ridge Estates",
    "wof:placetype":"locality"
},
  "geometry": {"coordinates":[-77.08026,39.60982],"type":"Point"}
}