{
  "type": "Feature",
  "properties": {
    "gn:admin1_code":"TX",
    "gn:admin2_code":"271.0",
    "gn:asciiname":"Amanda",
    "gn:country_code":"US",
    "gn:dem":327,
    "gn:elevation":"328.0",
    "gn:feature_class":"P",
    "gn:feature_code":"PPL",
    "gn:name":"Amanda",
    "gn:population":0,
    "gn:timezone":"America/Chicago",
    "iso:country":"US",
    "name:bel_x_preferred":[
        "\u0410\u043c\u0430\u043d\u0434\u0430"
    ],
    "name:ces_x_preferred":[
        "Amanda"
    ],
    "name:dan_x_preferred":[
        "Amanda"
    ],
    "name:deu_x_preferred":[
        "Amanda"
    ],
    "name:fao_x_preferred":[
        "Amanda"
    ],
    "name:fin_x_preferred":[
        "Amanda"
    ],
    "name:hun_x_preferred":[
        "Amanda"
    ],
    "name:isl_x_preferred":[
        "Amanda"
    ],
    "name:ita_x_preferred":[
        "Amanda"
    ],
    "name:lat_x_preferred":[
        "Amanda"
    ],
    "name:nld_x_preferred":[
        "Amanda"
    ],
    "name:nno_x_preferred":[
        "Amanda"
    ],
    "name:nor_x_preferred":[
        "Amanda"
    ],
    "name:pol_x_preferred":[
        "Amanda"
    ],
    "name:rus_x_preferred":[
        "\u0410\u043c\u0430\u043d\u0434\u0430"
    ],
    "name:slv_x_preferred":[
        "Amanda"
    ],
    "name:spa_x_preferred":[
        "Amanda"
    ],
    "name:swe_x_preferred":[
        "Amanda"
    ],
    "wof:name":"Amanda",
    "wof:placetype":"locality"
},
  "geometry": {"coordinates":[-100.65787,29.3719],"type":"Point"}
}