{
  "type": "Feature",
  "properties": {
    "gn:admin1_code":"AZ",
    "gn:admin2_code":"25.0",
    "gn:asciiname":"Cherry",
    "gn:country_code":"US",
    "gn:dem":1530,
    "gn:elevation":"1526.0",
    "gn:feature_class":"P",
    "gn:feature_code":"PPL",
    "gn:name":"Cherry",
    "gn:population":0,
    "gn:timezone":"America/Phoenix",
    "iso:country":"US",
    "name:fra_x_preferred":[
        "Cherry"
    ],
    "name:ron_x_preferred":[
        "Cherry"
    ],
    "name:zho_x_preferred":[
        "\u5fb9\u91cc"
    ],
    "wof:name":"Cherry",
    "wof:placetype":"locality"
},
  "geometry": {"coordinates":[-112.04182,34.58808],"type":"Point"}
}