{
  "type": "Feature",
  "properties": {
    "iso:country":"US",
    "name:eng_x_preferred":[
        "Governor's Square"
    ],
    "wd:wordcount":256,
    "wof:name":"Governor's Square",
    "wof:placetype":"neighbourhood",
    "wof:population":570,
    "zs:blockids":[
        510950802021000,
        518303703003004,
        518303703003002,
        518303703003005,
        518303703003006,
        518303703003020,
        518303703003000,
        518303703003003,
        518303703003010,
        518303703003008
    ],
    "zs:housing10":327,
    "zs:label":"Governor's Square",
    "zs:pop10":570
},
  "geometry": {"coordinates":[-76.732102,37.274113],"type":"Point"}
}