{
  "type": "Feature",
  "properties": {
    "gn:country":"US",
    "gn:fcode":"PPL",
    "gn:population":0,
    "iso:country":"US",
    "name:eng_x_preferred":[
        "Mesilla Park"
    ],
    "name:fra_x_preferred":[
        "Mesilla Park"
    ],
    "name:nld_x_preferred":[
        "Mesilla Park"
    ],
    "qs_pg:aaroncc":"US",
    "qs_pg:gn_country":"US",
    "qs_pg:gn_fcode":"PPL",
    "qs_pg:gn_pop":0,
    "qs_pg:name":"Mesilla Park",
    "qs_pg:name_adm0":"United States",
    "qs_pg:name_adm1":"New Mexico",
    "qs_pg:photos_9k":1,
    "qs_pg:photos_9r":1,
    "qs_pg:photos_all":1,
    "qs_pg:photos_sr":0,
    "qs_pg:pop_sr":0,
    "qs_pg:qs_pg_placetype":"locality",
    "qs_pg:qs_pg_placetype_gp":"Town",
    "qs_pg:woe_adm0":23424977,
    "woe:adm0_id":23424977,
    "woe:name_adm0":"United States",
    "woe:name_adm1":"New Mexico",
    "woe:placetype":"Town",
    "wof:name":"Mesilla Park",
    "wof:placetype":"locality"
},
  "geometry": {"coordinates":[-106.76667,32.27593],"type":"Point"}
}