{
  "type": "Feature",
  "properties": {
    "gn:admin1_code":"MD",
    "gn:admin2_code":"17.0",
    "gn:asciiname":"Oakland Estates",
    "gn:country_code":"US",
    "gn:dem":49,
    "gn:elevation":"48.0",
    "gn:feature_class":"P",
    "gn:feature_code":"PPL",
    "gn:name":"Oakland Estates",
    "gn:population":0,
    "gn:timezone":"America/New_York",
    "iso:country":"US",
    "wof:name":"Oakland Estates",
    "wof:placetype":"locality"
},
  "geometry": {"coordinates":[-76.96581,38.51595],"type":"Point"}
}