{
  "type": "Feature",
  "properties": {
    "gn:admin1_code":"VA",
    "gn:admin2_code":"195.0",
    "gn:asciiname":"Banner",
    "gn:country_code":"US",
    "gn:dem":621,
    "gn:elevation":"615.0",
    "gn:feature_class":"P",
    "gn:feature_code":"PPL",
    "gn:name":"Banner",
    "gn:population":0,
    "gn:timezone":"America/New_York",
    "iso:country":"US",
    "name:fas_x_preferred":[
        "\u0628\u0646\u0631"
    ],
    "wof:name":"Banner",
    "wof:placetype":"locality"
},
  "geometry": {"coordinates":[-82.42959,36.94955],"type":"Point"}
}