{
  "type": "Feature",
  "properties": {
    "gn:country":"US",
    "gn:fcode":"ADMD",
    "gn:population":0,
    "iso:country":"US",
    "name:ara_x_preferred":[
        "\u0628\u0644\u062f\u0629 \u0647\u064a\u0648\u0645"
    ],
    "name:eng_x_preferred":[
        "Hume Township"
    ],
    "name:fas_x_preferred":[
        "\u0646\u0627\u062d\u06cc\u0647 \u0647\u06cc\u0648\u0645"
    ],
    "name:spa_x_preferred":[
        "Municipio de Hume"
    ],
    "name:vie_x_preferred":[
        "X\u00e3 Hume"
    ],
    "qs_pg:aaroncc":"US",
    "qs_pg:gn_country":"US",
    "qs_pg:gn_fcode":"ADMD",
    "qs_pg:gn_pop":0,
    "qs_pg:name":"Hume",
    "qs_pg:name_adm0":"United States",
    "qs_pg:name_adm1":"Michigan",
    "qs_pg:photos":85,
    "qs_pg:photos_1k":17,
    "qs_pg:photos_9k":1,
    "qs_pg:photos_9r":3,
    "qs_pg:photos_all":85,
    "qs_pg:photos_sr":3,
    "qs_pg:pop_sr":0,
    "qs_pg:qs_pg_placetype":"locality",
    "qs_pg:qs_pg_placetype_gp":"Town",
    "qs_pg:woe_adm0":23424977,
    "woe:adm0_id":23424977,
    "woe:name_adm0":"United States",
    "woe:name_adm1":"Michigan",
    "woe:placetype":"Town",
    "wof:name":"Hume",
    "wof:placetype":"locality"
},
  "geometry": {"coordinates":[-83.06189000000001,43.97363],"type":"Point"}
}