{
  "type": "Feature",
  "properties": {
    "iso:country":"US",
    "name:ceb_x_preferred":[
        "Rancho Viejo"
    ],
    "name:deu_x_preferred":[
        "Rancho Viejo"
    ],
    "name:eng_x_preferred":[
        "Rancho Viejo"
    ],
    "name:ita_x_preferred":[
        "Rancho Viejo"
    ],
    "name:srp_x_preferred":[
        "\u0420\u0430\u043d\u0447\u043e \u0412\u0438\u0458\u0435\u0445\u043e"
    ],
    "name:swe_x_preferred":[
        "Rancho Viejo"
    ],
    "wof:name":"Rancho Viejo",
    "wof:placetype":"neighbourhood",
    "wof:population":219,
    "zs:area_m":64693.002494,
    "zs:blockids":[
        80010092021006,
        80010092021005
    ],
    "zs:housing10":78,
    "zs:label":"Rancho Viejo",
    "zs:pop10":219
},
  "geometry": {"coordinates":[-104.96420000000001,39.869421],"type":"Point"}
}