{
  "type": "Feature",
  "properties": {
    "gn:admin1_code":"MD",
    "gn:admin2_code":"9.0",
    "gn:asciiname":"Planters Wharf",
    "gn:country_code":"US",
    "gn:dem":21,
    "gn:elevation":"15.0",
    "gn:feature_class":"P",
    "gn:feature_code":"PPL",
    "gn:name":"Planters Wharf",
    "gn:population":0,
    "gn:timezone":"America/New_York",
    "iso:country":"US",
    "wof:name":"Planters Wharf",
    "wof:placetype":"locality"
},
  "geometry": {"coordinates":[-76.48579000000002,38.42707],"type":"Point"}
}