{
  "type": "Feature",
  "properties": {
    "iso:country":"US",
    "name:eng_x_preferred":[
        "Merritt Acres"
    ],
    "wof:name":"Merritt Acres",
    "wof:placetype":"neighbourhood",
    "wof:population":355,
    "zs:area_m":406409.500667,
    "zs:blockids":[
        350010035013001,
        350010035011045,
        350010035012025,
        350010035013029,
        350010035011046
    ],
    "zs:housing10":146,
    "zs:label":"Merritt Acres",
    "zs:pop10":355
},
  "geometry": {"coordinates":[-106.630797,35.147435],"type":"Point"}
}