{
  "type": "Feature",
  "properties": {
    "gn:admin1_code":"TX",
    "gn:admin2_code":"61",
    "gn:asciiname":"Houston Road East Colonia",
    "gn:country_code":"US",
    "gn:dem":9,
    "gn:elevation":"5.0",
    "gn:feature_class":"P",
    "gn:feature_code":"PPL",
    "gn:name":"Houston Road East Colonia",
    "gn:population":0,
    "gn:timezone":"America/Chicago",
    "iso:country":"US",
    "wof:name":"Houston Road East Colonia",
    "wof:placetype":"locality"
},
  "geometry": {"coordinates":[-97.38415000000001,25.92536],"type":"Point"}
}