{
  "type": "Feature",
  "properties": {
    "gn:admin1_code":"SC",
    "gn:admin2_code":"63.0",
    "gn:asciiname":"Priceville",
    "gn:country_code":"US",
    "gn:dem":148,
    "gn:elevation":"147.0",
    "gn:feature_class":"P",
    "gn:feature_code":"PPL",
    "gn:name":"Priceville",
    "gn:population":0,
    "gn:timezone":"America/New_York",
    "iso:country":"US",
    "wof:name":"Priceville",
    "wof:placetype":"locality"
},
  "geometry": {"coordinates":[-81.40926999999998,33.99875],"type":"Point"}
}