{
  "type": "Feature",
  "properties": {
    "gn:admin1_code":"ND",
    "gn:admin2_code":"7.0",
    "gn:admin3_code":"57710.0",
    "gn:asciiname":"Six Mile Corner",
    "gn:country_code":"US",
    "gn:dem":805,
    "gn:elevation":"804.0",
    "gn:feature_class":"P",
    "gn:feature_code":"PPL",
    "gn:name":"Six Mile Corner",
    "gn:population":0,
    "gn:timezone":"America/Denver",
    "iso:country":"US",
    "wof:name":"Six Mile Corner",
    "wof:placetype":"locality"
},
  "geometry": {"coordinates":[-103.19073,46.98057],"type":"Point"}
}