{
  "type": "Feature",
  "properties": {
    "gn:admin1_code":"CO",
    "gn:admin2_code":"85",
    "gn:asciiname":"Vancorum",
    "gn:country_code":"US",
    "gn:dem":1637,
    "gn:elevation":"1628.0",
    "gn:feature_class":"P",
    "gn:feature_code":"PPL",
    "gn:name":"Vancorum",
    "gn:population":0,
    "gn:timezone":"America/Denver",
    "iso:country":"US",
    "wof:name":"Vancorum",
    "wof:placetype":"locality"
},
  "geometry": {"coordinates":[-108.59565000000001,38.23166],"type":"Point"}
}