{
  "type": "Feature",
  "properties": {
    "gn:country":"US",
    "gn:fcode":"PPL",
    "gn:population":0,
    "iso:country":"US",
    "name:cym_x_preferred":[
        "Colts Neck Township"
    ],
    "name:deu_x_preferred":[
        "Colts Neck"
    ],
    "name:eng_x_preferred":[
        "Colts Neck Township"
    ],
    "name:eng_x_variant":[
        "Colts Neck"
    ],
    "name:fas_x_preferred":[
        "\u06a9\u0648\u0644\u062a\u0633 \u0646\u06a9\u060c \u0646\u06cc\u0648\u062c\u0631\u0633\u06cc"
    ],
    "name:fas_x_variant":[
        "\u06a9\u0648\u0644\u062a\u0633 \u0646\u06a9"
    ],
    "name:hat_x_preferred":[
        "Colts Neck"
    ],
    "name:heb_x_preferred":[
        "\u05e7\u05d5\u05dc\u05d8\u05e1 \u05e0\u05e7"
    ],
    "name:ita_x_preferred":[
        "Colts Neck"
    ],
    "name:jpn_x_preferred":[
        "\u30b3\u30eb\u30c4\u30cd\u30c3\u30af"
    ],
    "name:kaz_x_preferred":[
        "\u041a\u043e\u043b\u0442\u0441 \u041d\u044d\u043a\u0422\u0430\u0443\u043d\u0448\u0438\u043f"
    ],
    "name:kir_x_preferred":[
        "\u041a\u043e\u043b\u0442\u0441 \u041d\u044d\u043a\u0422\u0430\u0443\u043d\u0448\u0438\u043f"
    ],
    "name:spa_x_preferred":[
        "Municipio de Colts Neck"
    ],
    "name:swa_x_preferred":[
        "Colts Neck Township"
    ],
    "name:tam_x_preferred":[
        "\u0b95\u0bca\u0bb2\u0bcd\u0b9f\u0bcd\u0b9a\u0bc1 \u0ba8\u0bc6\u0b95\u0bcd \u0ba8\u0b95\u0bb0\u0bbf\u0baf\u0bae\u0bcd"
    ],
    "name:ukr_x_preferred":[
        "\u041a\u043e\u043b\u0442\u0441-\u041d\u0435\u043a \u0422\u0430\u0443\u043d\u0448\u0438\u043f"
    ],
    "name:und_x_variant":[
        "Colt's Neck"
    ],
    "name:zho_x_preferred":[
        "\u79d1\u723e\u8328\u5167\u514b\u93ae\u5340"
    ],
    "name:zul_x_preferred":[
        "UVinasi"
    ],
    "qs_pg:aaroncc":"US",
    "qs_pg:gn_country":"US",
    "qs_pg:gn_fcode":"PPL",
    "qs_pg:gn_pop":0,
    "qs_pg:name":"Colts Neck",
    "qs_pg:name_adm0":"United States",
    "qs_pg:name_adm1":"New Jersey",
    "qs_pg:photos":351,
    "qs_pg:photos_1k":71,
    "qs_pg:photos_9k":2,
    "qs_pg:photos_9r":5,
    "qs_pg:photos_all":542,
    "qs_pg:photos_sr":6,
    "qs_pg:pop_sr":5,
    "qs_pg:qs_pg_placetype":"locality",
    "qs_pg:qs_pg_placetype_gp":"Town",
    "qs_pg:woe_adm0":23424977,
    "woe:adm0_id":23424977,
    "woe:name_adm0":"United States",
    "woe:name_adm1":"New Jersey",
    "woe:placetype":"Town",
    "wof:coterminous":[
        404478335
    ],
    "wof:name":"Colts Neck",
    "wof:placetype":"locality",
    "wof:statistical_gore":1
},
  "geometry": {"coordinates":[-74.17237,40.28761],"type":"Point"}
}