{
  "type": "Feature",
  "properties": {
    "gn:elevation":30,
    "iso:country":"US",
    "name:cym_x_preferred":[
        "Maes Awyr Rhyngwladol Ketchikan"
    ],
    "name:deu_x_preferred":[
        "Ketchikan International Airport"
    ],
    "name:eng_x_preferred":[
        "Ketchikan International Airport"
    ],
    "name:eng_x_variant":[
        "KTN",
        "PAKT"
    ],
    "name:fas_x_preferred":[
        "\u0641\u0631\u0648\u062f\u06af\u0627\u0647 \u0628\u06cc\u0646\u200c\u0627\u0644\u0645\u0644\u0644\u06cc \u06a9\u0686\u06cc\u06a9\u0627\u0646"
    ],
    "name:jpn_x_preferred":[
        "\u30b1\u30c1\u30ab\u30f3\u56fd\u969b\u7a7a\u6e2f"
    ],
    "name:ron_x_preferred":[
        "Aeroportul Ketchikan"
    ],
    "name:rus_x_preferred":[
        "\u041a\u0435\u0442\u0447\u0438\u043a\u0430\u043d"
    ],
    "name:spa_x_preferred":[
        "Aeropuerto Internacional de Ketchikan"
    ],
    "name:tgk_x_preferred":[
        "\u0424\u0443\u0440\u0443\u0434\u0433\u043e\u04b3\u0438 \u0431\u0438\u043d\u200c\u0430\u043b\u043c\u0438\u043b\u0430\u043b\u04e3 \u043a\u0447\u0438\u043a\u043e\u043d"
    ],
    "name:zho_x_preferred":[
        "\u514b\u5947\u574e\u56fd\u9645\u673a\u573a"
    ],
    "oa:elevation_ft":"89",
    "oa:type":"medium_airport",
    "wd:wordcount":1578,
    "woe:hierarchy":{
        "country_id":23424977,
        "county_id":12587565,
        "planet_id":1,
        "state_id":2347560
    },
    "wof:name":"Ketchikan International Airport",
    "wof:placetype":"campus"
},
  "geometry": {"coordinates":[-131.71400399999999,55.355598],"type":"Point"}
}