{
  "type": "Feature",
  "properties": {
    "iso:country":"US",
    "name:eng_x_preferred":[
        "Wallkill Camp"
    ],
    "name:eng_x_variant":[
        "Wallkill Cp"
    ],
    "qs:gn_adm0_cc":"US",
    "qs:gn_fcode":"PPL",
    "qs:gn_local":5118235,
    "qs:gn_nam_loc":"Gardiner, Ulster, New York, US",
    "qs:gn_namadm1":"NY",
    "qs:gn_name":"Wallkill Camp",
    "qs:local_max":2112,
    "qs:local_sum":2611,
    "qs:localhoods":9,
    "qs:name":"Wallkill Camp",
    "qs:name_adm0":"United States",
    "qs:name_adm1":"New York",
    "qs:name_adm2":"Ulster",
    "qs:name_local":"Gardiner",
    "qs:photo_max":4,
    "qs:photo_sum":13,
    "qs:placetype":"Suburb",
    "qs:quad_count":8,
    "qs:woe_adm0":23424977,
    "qs:woe_adm1":2347591,
    "qs:woe_adm2":12589367,
    "qs:woe_lau":0,
    "qs:woe_local":2408858,
    "qs:woe_ver":"7.10.0",
    "wof:lang":[
        "eng"
    ],
    "wof:name":"Wallkill Camp",
    "wof:placetype":"neighbourhood",
    "wof:population":905,
    "zs:blockids":[
        361119542002015,
        361119542002030,
        361119542002028,
        361119542002031,
        361119542002016,
        361119542002020,
        361119542002029
    ],
    "zs:housing10":383,
    "zs:pop10":905
},
  "geometry": {"coordinates":[-74.16384100000001,41.714403],"type":"Point"}
}