{
  "type": "Feature",
  "properties": {
    "gn:admin1_code":"VA",
    "gn:admin2_code":"185",
    "gn:asciiname":"Harman",
    "gn:country_code":"US",
    "gn:dem":663,
    "gn:elevation":"658.0",
    "gn:feature_class":"P",
    "gn:feature_code":"PPL",
    "gn:name":"Harman",
    "gn:population":0,
    "gn:timezone":"America/New_York",
    "iso:country":"US",
    "name:ceb_x_preferred":[
        "Harman"
    ],
    "name:ces_x_preferred":[
        "Harman"
    ],
    "name:deu_x_preferred":[
        "Harman"
    ],
    "name:eng_x_preferred":[
        "Harman"
    ],
    "name:ita_x_preferred":[
        "Harman"
    ],
    "name:nld_x_preferred":[
        "Harman"
    ],
    "name:pol_x_preferred":[
        "Harman"
    ],
    "name:por_x_preferred":[
        "Harman"
    ],
    "name:rus_x_preferred":[
        "\u0425\u0430\u0440\u043c\u0430\u043d"
    ],
    "name:tur_x_preferred":[
        "Harman"
    ],
    "name:und_x_variant":[
        "Harmon"
    ],
    "wof:name":"Harman",
    "wof:placetype":"locality"
},
  "geometry": {"coordinates":[-81.70733,37.15984],"type":"Point"}
}