{
  "type": "Feature",
  "properties": {
    "gn:elevation":201,
    "iso:country":"US",
    "name:eng_x_preferred":[
        "Country Club Forest"
    ],
    "name:eng_x_variant":[
        "Country Club Frst"
    ],
    "qs:gn_adm0_cc":"US",
    "qs:gn_fcode":"PPLX",
    "qs:gn_local":4458228,
    "qs:gn_nam_loc":"Burlington, Alamance, North Carolina, US",
    "qs:gn_namadm1":"NC",
    "qs:gn_name":"Country Club Forest",
    "qs:local_max":1187,
    "qs:local_sum":3552,
    "qs:localhoods":20,
    "qs:name":"Country Club Forest",
    "qs:name_adm0":"United States",
    "qs:name_adm1":"North Carolina",
    "qs:name_adm2":"Alamance",
    "qs:name_local":"Burlington",
    "qs:photo_max":46,
    "qs:photo_sum":62,
    "qs:placetype":"Suburb",
    "qs:quad_count":4,
    "qs:woe_adm0":23424977,
    "qs:woe_adm1":2347592,
    "qs:woe_adm2":12589374,
    "qs:woe_lau":0,
    "qs:woe_local":2372069,
    "qs:woe_ver":"7.10.0",
    "wof:lang":[
        "eng"
    ],
    "wof:name":"Country Club Forest",
    "wof:placetype":"neighbourhood",
    "wof:population":768,
    "zs:blockids":[
        370010206012029,
        370010206012022,
        370010206012026,
        370010206013032,
        370010206012028,
        370010206012020,
        370010206013028,
        370010206013031,
        370010206012012,
        370010206013021,
        370010206012013,
        370010206012024,
        370010206013027,
        370010206012027,
        370010206013022,
        370010206012025,
        370010206012001,
        370010206012011,
        370010206012014,
        370010206012017,
        370010206012021
    ],
    "zs:housing10":328,
    "zs:pop10":768
},
  "geometry": {"coordinates":[-79.487279,36.080217],"type":"Point"}
}