{
  "type": "Feature",
  "properties": {
    "gn:admin1_code":"MS",
    "gn:admin2_code":"105.0",
    "gn:asciiname":"Bugh",
    "gn:country_code":"US",
    "gn:dem":101,
    "gn:elevation":"98.0",
    "gn:feature_class":"P",
    "gn:feature_code":"PPL",
    "gn:name":"Bugh",
    "gn:population":0,
    "gn:timezone":"America/Chicago",
    "iso:country":"US",
    "wof:name":"Bugh",
    "wof:placetype":"locality"
},
  "geometry": {"coordinates":[-89.00173000000002,33.36623],"type":"Point"}
}