{
  "type": "Feature",
  "properties": {
    "gn:admin1_code":"TN",
    "gn:admin2_code":"185",
    "gn:asciiname":"Eastland",
    "gn:country_code":"US",
    "gn:dem":508,
    "gn:elevation":"503.0",
    "gn:feature_class":"P",
    "gn:feature_code":"PPL",
    "gn:name":"Eastland",
    "gn:population":0,
    "gn:timezone":"America/Chicago",
    "iso:country":"US",
    "wof:name":"Eastland",
    "wof:placetype":"locality"
},
  "geometry": {"coordinates":[-85.23690999999999,35.89812],"type":"Point"}
}