{
  "type": "Feature",
  "properties": {
    "gn:admin1_code":"MD",
    "gn:admin2_code":"3.0",
    "gn:asciiname":"Solley Park",
    "gn:country_code":"US",
    "gn:dem":22,
    "gn:elevation":"21.0",
    "gn:feature_class":"P",
    "gn:feature_code":"PPL",
    "gn:name":"Solley Park",
    "gn:population":0,
    "gn:timezone":"America/New_York",
    "iso:country":"US",
    "wof:name":"Solley Park",
    "wof:placetype":"locality"
},
  "geometry": {"coordinates":[-76.55051999999998,39.1815],"type":"Point"}
}