{
  "type": "Feature",
  "properties": {
    "gn:admin1_code":"AR",
    "gn:admin2_code":"129.0",
    "gn:asciiname":"Woolum",
    "gn:country_code":"US",
    "gn:dem":208,
    "gn:elevation":"203.0",
    "gn:feature_class":"P",
    "gn:feature_code":"PPL",
    "gn:name":"Woolum",
    "gn:population":0,
    "gn:timezone":"America/Chicago",
    "iso:country":"US",
    "name:eng_x_preferred":[
        "Woolum"
    ],
    "name:und_x_variant":[
        "Wolem"
    ],
    "wof:name":"Woolum",
    "wof:placetype":"locality"
},
  "geometry": {"coordinates":[-92.8835,35.9723],"type":"Point"}
}