{
  "type": "Feature",
  "properties": {
    "gn:admin1_code":"TX",
    "gn:admin2_code":"215.0",
    "gn:asciiname":"Peter Gort Colonia",
    "gn:country_code":"US",
    "gn:dem":25,
    "gn:elevation":"22.0",
    "gn:feature_class":"P",
    "gn:feature_code":"PPL",
    "gn:name":"Peter Gort Colonia",
    "gn:population":0,
    "gn:timezone":"America/Chicago",
    "iso:country":"US",
    "name:eng_x_preferred":[
        "Peter Gort Colonia"
    ],
    "name:und_x_variant":[
        "Peter Gort Subdivision Colonia"
    ],
    "wof:name":"Peter Gort Colonia",
    "wof:placetype":"locality"
},
  "geometry": {"coordinates":[-98.02723,26.27229],"type":"Point"}
}