{
  "type": "Feature",
  "properties": {
    "gn:admin1_code":"FL",
    "gn:admin2_code":"9.0",
    "gn:asciiname":"Groveland Mobile Home Park",
    "gn:country_code":"US",
    "gn:dem":8,
    "gn:elevation":"5.0",
    "gn:feature_class":"P",
    "gn:feature_code":"PPL",
    "gn:name":"Groveland Mobile Home Park",
    "gn:population":0,
    "gn:timezone":"America/New_York",
    "iso:country":"US",
    "wof:name":"Groveland Mobile Home Park",
    "wof:placetype":"campus"
},
  "geometry": {"coordinates":[-80.705,28.1166],"type":"Point"}
}