{
  "type": "Feature",
  "properties": {
    "gn:admin1_code":"NY",
    "gn:admin2_code":"89.0",
    "gn:admin3_code":"58266.0",
    "gn:asciiname":"Jayville",
    "gn:country_code":"US",
    "gn:dem":343,
    "gn:elevation":"344.0",
    "gn:feature_class":"P",
    "gn:feature_code":"PPL",
    "gn:name":"Jayville",
    "gn:population":0,
    "gn:timezone":"America/New_York",
    "iso:country":"US",
    "wof:name":"Jayville",
    "wof:placetype":"locality"
},
  "geometry": {"coordinates":[-75.18825,44.15673],"type":"Point"}
}