{
  "type": "Feature",
  "properties": {
    "gn:admin1_code":"KY",
    "gn:admin2_code":"55",
    "gn:asciiname":"Tribune",
    "gn:country_code":"US",
    "gn:dem":131,
    "gn:elevation":"132.0",
    "gn:feature_class":"P",
    "gn:feature_code":"PPL",
    "gn:name":"Tribune",
    "gn:population":0,
    "gn:timezone":"America/Chicago",
    "iso:country":"US",
    "name:eng_x_preferred":[
        "Tribune"
    ],
    "name:und_x_variant":[
        "Hillsdale",
        "Hills Chapel"
    ],
    "wof:name":"Tribune",
    "wof:placetype":"locality"
},
  "geometry": {"coordinates":[-87.99195999999998,37.34783],"type":"Point"}
}