{
  "type": "Feature",
  "properties": {
    "iso:country":"US",
    "name:als_x_preferred":[
        "Pagny-l\u00e8s-Goin"
    ],
    "name:cat_x_preferred":[
        "Pagny-l\u00e8s-Goin"
    ],
    "name:ceb_x_preferred":[
        "Pagny-l\u00e8s-Goin"
    ],
    "name:deu_x_preferred":[
        "Pagny-l\u00e8s-Goin"
    ],
    "name:eng_x_preferred":[
        "Goin Acres"
    ],
    "name:eus_x_preferred":[
        "Pagny-l\u00e8s-Goin"
    ],
    "name:fas_x_preferred":[
        "\u067e\u0627\u0646\u06cc-\u0644\u0647-\u06af\u0648\u0626\u0646"
    ],
    "name:fra_x_preferred":[
        "Pagny-l\u00e8s-Goin"
    ],
    "name:hun_x_preferred":[
        "Pagny-l\u00e8s-Goin"
    ],
    "name:ita_x_preferred":[
        "Pagny-l\u00e8s-Goin"
    ],
    "name:spa_x_preferred":[
        "Pagny-l\u00e8s-Goin"
    ],
    "wof:name":"Goin Acres",
    "wof:placetype":"neighbourhood",
    "wof:population":1570,
    "zs:area_m":893117.89418,
    "zs:blockids":[
        530110417001003,
        530110418001012,
        530110417002003,
        530110410112012,
        530110411103011,
        530110411103033,
        530110418001013,
        530110418001011,
        530110411103029,
        530110417002000,
        530110417001000,
        530110417002002,
        530110417001006,
        530110411103013,
        530110417001002,
        530110411103012,
        530110410112018,
        530110417001005,
        530110418001008,
        530110417001007,
        530110417001008,
        530110417001010,
        530110418001000,
        530110410112017,
        530110417002001,
        530110411103028,
        530110411103030,
        530110418001010,
        530110418001009,
        530110411103031,
        530110411103032,
        530110417001004,
        530110418001007,
        530110411103010
    ],
    "zs:housing10":634,
    "zs:label":"Goin Acres",
    "zs:pop10":1570
},
  "geometry": {"coordinates":[-122.63675600000001,45.648329],"type":"Point"}
}