{
  "type": "Feature",
  "properties": {
    "gn:admin1_code":"AR",
    "gn:admin2_code":"85.0",
    "gn:admin3_code":"94131.0",
    "gn:asciiname":"Kingwood Addition",
    "gn:country_code":"US",
    "gn:dem":105,
    "gn:elevation":"98.0",
    "gn:feature_class":"P",
    "gn:feature_code":"PPL",
    "gn:name":"Kingwood Addition",
    "gn:population":0,
    "gn:timezone":"America/Chicago",
    "iso:country":"US",
    "wof:name":"Kingwood Addition",
    "wof:placetype":"locality"
},
  "geometry": {"coordinates":[-92.00209,34.93231],"type":"Point"}
}