{
  "type": "Feature",
  "properties": {
    "iso:country":"US",
    "name:eng_x_preferred":[
        "Fair Grounds Townhouses"
    ],
    "wof:name":"Fair Grounds Townhouses",
    "wof:placetype":"neighbourhood",
    "wof:population":386,
    "zs:area_m":393474.753486,
    "zs:blockids":[
        80519637005049,
        80519637005078,
        80519637005047,
        80519637005079,
        80519637005052,
        80519637005043,
        80519637005084,
        80519637005090,
        80519637005086,
        80519637005089,
        80519637005085,
        80519637005051,
        80519637005032,
        80519637005044,
        80519637005046,
        80519637005091,
        80519637005082,
        80519637005048,
        80519637005105,
        80519637005081,
        80519637005094,
        80519637005106,
        80519637005042,
        80519637005093,
        80519637005077,
        80519637005083,
        80519637005092,
        80519637005080,
        80519637005050,
        80519637005096
    ],
    "zs:housing10":189,
    "zs:label":"Fair Grounds Townhouses",
    "zs:pop10":386
},
  "geometry": {"coordinates":[-106.931482,38.540635],"type":"Point"}
}