{
  "type": "Feature",
  "properties": {
    "gn:elevation":91,
    "iso:country":"US",
    "name:eng_x_preferred":[
        "South Barrington"
    ],
    "name:eng_x_variant":[
        "S Barrington"
    ],
    "qs:gn_adm0_cc":"US",
    "qs:gn_fcode":"PPL",
    "qs:gn_local":5083023,
    "qs:gn_nam_loc":"barrington",
    "qs:gn_namadm1":"NH",
    "qs:gn_name":"South Barrington",
    "qs:local_max":229,
    "qs:local_sum":495,
    "qs:localhoods":3,
    "qs:name":"South Barrington",
    "qs:name_adm0":"United States",
    "qs:name_adm1":"New Hampshire",
    "qs:name_adm2":"Strafford",
    "qs:name_local":"Barrington",
    "qs:photo_max":211,
    "qs:photo_sum":229,
    "qs:placetype":"Suburb",
    "qs:quad_count":4,
    "qs:woe_adm0":23424977,
    "qs:woe_adm1":2347588,
    "qs:woe_adm2":12589256,
    "qs:woe_lau":0,
    "qs:woe_local":2359569,
    "qs:woe_ver":"7.10.0",
    "wof:lang":[
        "eng"
    ],
    "wof:name":"South Barrington",
    "wof:placetype":"neighbourhood",
    "wof:population":1094,
    "zs:blockids":[
        330170850003039,
        330170850005003,
        330170850003048,
        330170850003028,
        330170850003030,
        330170850003024,
        330170850003036,
        330170850005041,
        330170850003033,
        330170850005009,
        330170850003046,
        330170850003029,
        330170850003034,
        330170850003035,
        330170850005011,
        330170850003040,
        330170850003026,
        330170850005008,
        330170850005007,
        330170850003038,
        330170850003032,
        330170850003023,
        330170850003047,
        330170850003025,
        330170850003041,
        330170850003037
    ],
    "zs:housing10":511,
    "zs:pop10":1094
},
  "geometry": {"coordinates":[-71.050651,43.165771],"type":"Point"}
}