{
  "type": "Feature",
  "properties": {
    "gn:country":"US",
    "gn:fcode":"PPL",
    "gn:population":0,
    "iso:country":"US",
    "name:ceb_x_preferred":[
        "Stillwater"
    ],
    "name:deu_x_preferred":[
        "Stillwater"
    ],
    "name:fin_x_preferred":[
        "Stillwater"
    ],
    "name:fra_x_preferred":[
        "Stillwater"
    ],
    "name:ita_x_preferred":[
        "Stillwater"
    ],
    "name:jpn_x_preferred":[
        "\u30b9\u30c6\u30a3\u30eb\u30a6\u30a9\u30fc\u30bf\u30fc"
    ],
    "name:kor_x_preferred":[
        "\uc2a4\ud2f8\uc6cc\ud130"
    ],
    "name:nld_x_preferred":[
        "Stillwater"
    ],
    "name:pol_x_preferred":[
        "Stillwater"
    ],
    "name:por_x_preferred":[
        "Stillwater"
    ],
    "name:rus_x_preferred":[
        "\u0421\u0442\u0438\u043b\u043b\u0443\u043e\u0442\u0435\u0440"
    ],
    "name:srp_x_preferred":[
        "\u0421\u0442\u0438\u043b\u0432\u043e\u0442\u0435\u0440"
    ],
    "name:swe_x_preferred":[
        "Stillwater"
    ],
    "name:vol_x_preferred":[
        "Stillwater"
    ],
    "name:zho_x_preferred":[
        "\u65af\u8482\u5c14\u6c83\u7279"
    ],
    "qs_pg:aaroncc":"US",
    "qs_pg:gn_country":"US",
    "qs_pg:gn_fcode":"PPL",
    "qs_pg:gn_pop":0,
    "qs_pg:name":"Stillwater",
    "qs_pg:name_adm0":"United States",
    "qs_pg:name_adm1":"New Hampshire",
    "qs_pg:photos":393,
    "qs_pg:photos_1k":80,
    "qs_pg:photos_9k":2,
    "qs_pg:photos_9r":5,
    "qs_pg:photos_all":393,
    "qs_pg:photos_sr":6,
    "qs_pg:pop_sr":0,
    "qs_pg:qs_pg_placetype":"locality",
    "qs_pg:qs_pg_placetype_gp":"Town",
    "qs_pg:woe_adm0":23424977,
    "woe:adm0_id":23424977,
    "woe:name_adm0":"United States",
    "woe:name_adm1":"New Hampshire",
    "woe:placetype":"Town",
    "wof:name":"Stillwater",
    "wof:placetype":"locality"
},
  "geometry": {"coordinates":[-71.46952,44.11868],"type":"Point"}
}