{
  "type": "Feature",
  "properties": {
    "iso:country":"US",
    "name:eng_x_preferred":[
        "Brittany Trace"
    ],
    "qs:gn_local":0,
    "qs:local_max":569,
    "qs:local_sum":1823,
    "qs:localhoods":15,
    "qs:name":"Brittany Trace",
    "qs:name_adm0":"United States",
    "qs:name_adm1":"North Carolina",
    "qs:name_adm2":"Wake",
    "qs:name_local":"Apex",
    "qs:photo_max":42,
    "qs:photo_sum":121,
    "qs:placetype":"Suburb",
    "qs:quad_count":6,
    "qs:woe_adm0":23424977,
    "qs:woe_adm1":2347592,
    "qs:woe_adm2":12589465,
    "qs:woe_lau":0,
    "qs:woe_local":2355220,
    "qs:woe_ver":"7.10.0",
    "wof:name":"Brittany Trace",
    "wof:placetype":"neighbourhood",
    "wof:population":458,
    "zs:blockids":[
        371830534163012,
        371830534163003,
        371830534163007,
        371830534161064,
        371830534163001,
        371830534163000,
        371830534163004,
        371830534163002,
        371830534182013,
        371830534182011,
        371830534182012,
        371830534181028,
        371830534181029,
        371830534163011,
        371830534163010,
        371830534181034,
        371830534181032
    ],
    "zs:housing10":196,
    "zs:pop10":458
},
  "geometry": {"coordinates":[-78.85077699999999,35.732301],"type":"Point"}
}