{
  "type": "Feature",
  "properties": {
    "gn:admin1_code":"TN",
    "gn:admin2_code":"29",
    "gn:asciiname":"Holttown",
    "gn:country_code":"US",
    "gn:dem":315,
    "gn:elevation":"311.0",
    "gn:feature_class":"P",
    "gn:feature_code":"PPL",
    "gn:name":"Holttown",
    "gn:population":0,
    "gn:timezone":"America/New_York",
    "iso:country":"US",
    "wof:name":"Holttown",
    "wof:placetype":"locality"
},
  "geometry": {"coordinates":[-83.20544,36.07787],"type":"Point"}
}