{
  "type": "Feature",
  "properties": {
    "gn:admin1_code":"NM",
    "gn:admin2_code":"9",
    "gn:asciiname":"Gallaher",
    "gn:country_code":"US",
    "gn:dem":1313,
    "gn:elevation":"1312.0",
    "gn:feature_class":"P",
    "gn:feature_code":"PPL",
    "gn:name":"Gallaher",
    "gn:population":0,
    "gn:timezone":"America/Denver",
    "iso:country":"US",
    "name:deu_x_preferred":[
        "Gallaher"
    ],
    "wof:name":"Gallaher",
    "wof:placetype":"locality"
},
  "geometry": {"coordinates":[-103.29689999999999,34.40285],"type":"Point"}
}