{
  "type": "Feature",
  "properties": {
    "gn:admin1_code":"OH",
    "gn:admin2_code":"169.0",
    "gn:admin3_code":"11276.0",
    "gn:asciiname":"Golden Corners",
    "gn:country_code":"US",
    "gn:dem":365,
    "gn:elevation":"366.0",
    "gn:feature_class":"P",
    "gn:feature_code":"PPL",
    "gn:name":"Golden Corners",
    "gn:population":0,
    "gn:timezone":"America/New_York",
    "iso:country":"US",
    "wof:name":"Golden Corners",
    "wof:placetype":"locality"
},
  "geometry": {"coordinates":[-81.98181,40.91506],"type":"Point"}
}