{
  "type": "Feature",
  "properties": {
    "gn:admin1_code":"NC",
    "gn:admin2_code":"159",
    "gn:admin3_code":"91160.0",
    "gn:asciiname":"Franklin",
    "gn:country_code":"US",
    "gn:dem":240,
    "gn:elevation":"240.0",
    "gn:feature_class":"P",
    "gn:feature_code":"PPL",
    "gn:name":"Franklin",
    "gn:population":3619,
    "gn:timezone":"America/New_York",
    "iso:country":"US",
    "name:als_x_preferred":[
        "Franklin"
    ],
    "name:bel_x_preferred":[
        "\u0424\u0440\u0430\u043d\u043a\u043b\u0456\u043d"
    ],
    "name:bul_x_preferred":[
        "\u0424\u0440\u0430\u043d\u043a\u043b\u0438\u043d"
    ],
    "name:cat_x_preferred":[
        "Franklin"
    ],
    "name:ceb_x_preferred":[
        "Franklin"
    ],
    "name:ces_x_preferred":[
        "Franklin"
    ],
    "name:dan_x_preferred":[
        "Franklin"
    ],
    "name:deu_x_preferred":[
        "Franklin"
    ],
    "name:eng_x_preferred":[
        "Franklin"
    ],
    "name:est_x_preferred":[
        "Franklin"
    ],
    "name:fas_x_preferred":[
        "\u0641\u0631\u0627\u0646\u06a9\u0644\u06cc\u0646"
    ],
    "name:fin_x_preferred":[
        "Franklin"
    ],
    "name:fra_x_preferred":[
        "Franklin"
    ],
    "name:heb_x_preferred":[
        "\u05e4\u05e8\u05e0\u05e7\u05dc\u05d9\u05df"
    ],
    "name:hun_x_preferred":[
        "Franklin"
    ],
    "name:ita_x_preferred":[
        "Franklin"
    ],
    "name:jpn_x_preferred":[
        "\u30d5\u30e9\u30f3\u30af\u30ea\u30f3"
    ],
    "name:kat_x_preferred":[
        "\u10e4\u10e0\u10d0\u10dc\u10d9\u10da\u10d8\u10dc\u10d8"
    ],
    "name:kor_x_preferred":[
        "\ud504\ub7ad\ud074\ub9b0"
    ],
    "name:lav_x_preferred":[
        "Franklins"
    ],
    "name:nld_x_preferred":[
        "Franklin"
    ],
    "name:nor_x_preferred":[
        "Franklin"
    ],
    "name:pol_x_preferred":[
        "Franklin"
    ],
    "name:por_x_preferred":[
        "Franklin"
    ],
    "name:ron_x_preferred":[
        "Franklin"
    ],
    "name:rus_x_preferred":[
        "\u0424\u0440\u0430\u043d\u043a\u043b\u0438\u043d"
    ],
    "name:spa_x_preferred":[
        "Franklin"
    ],
    "name:srp_x_preferred":[
        "\u0424\u0440\u0435\u043d\u043a\u043b\u0438\u043d"
    ],
    "name:swe_x_preferred":[
        "Franklin"
    ],
    "name:tur_x_preferred":[
        "Franklin"
    ],
    "name:ukr_x_preferred":[
        "\u0424\u0440\u0430\u043d\u043a\u043b\u0456\u043d"
    ],
    "name:und_x_variant":[
        "Franklinville"
    ],
    "name:urd_x_preferred":[
        "\u0641\u0631\u06cc\u0646\u06a9\u0644\u0646"
    ],
    "name:vol_x_preferred":[
        "Franklin"
    ],
    "name:war_x_preferred":[
        "Franklin"
    ],
    "name:zho_x_preferred":[
        "\u5bcc\u5170\u514b\u6797"
    ],
    "wof:name":"Franklin",
    "wof:placetype":"locality",
    "wof:population":3619
},
  "geometry": {"coordinates":[-80.49894999999999,35.72125],"type":"Point"}
}