{
  "type": "Feature",
  "properties": {
    "iso:country":"US",
    "name:deu_x_preferred":[
        "Honolulu Hale"
    ],
    "name:jpn_x_preferred":[
        "\u30db\u30ce\u30eb\u30eb\u30fb\u30cf\u30ec"
    ],
    "qs_pg:aaroncc":"US",
    "qs_pg:name":"Honolulu Hale",
    "qs_pg:name_adm0":"United States",
    "qs_pg:name_adm1":"Hawaii",
    "qs_pg:photos":143,
    "qs_pg:photos_1k":29,
    "qs_pg:photos_9k":1,
    "qs_pg:photos_9r":3,
    "qs_pg:photos_all":143,
    "qs_pg:photos_sr":3,
    "qs_pg:pop_sr":0,
    "qs_pg:qs_pg_placetype":"locality",
    "qs_pg:qs_pg_placetype_gp":"Town",
    "qs_pg:woe_adm0":23424977,
    "woe:adm0_id":23424977,
    "woe:name_adm0":"United States",
    "woe:name_adm1":"Hawaii",
    "woe:placetype":"Town",
    "wof:name":"Honolulu Hale",
    "wof:placetype":"locality"
},
  "geometry": {"coordinates":[-157.853622,21.304088],"type":"Point"}
}