{
  "type": "Feature",
  "properties": {
    "gn:admin1_code":"WI",
    "gn:admin2_code":"27.0",
    "gn:admin3_code":"11275.0",
    "gn:asciiname":"Rolling Prairie",
    "gn:country_code":"US",
    "gn:dem":286,
    "gn:elevation":"283.0",
    "gn:feature_class":"P",
    "gn:feature_code":"PPL",
    "gn:name":"Rolling Prairie",
    "gn:population":0,
    "gn:timezone":"America/Chicago",
    "iso:country":"US",
    "wof:name":"Rolling Prairie",
    "wof:placetype":"locality"
},
  "geometry": {"coordinates":[-88.73427,43.45916],"type":"Point"}
}