{
  "type": "Feature",
  "properties": {
    "gn:gn_country":"US",
    "gn:gn_fcode":"PPL",
    "gn:gn_pop":266,
    "gn:population":266,
    "iso:country":"US",
    "name:bel_x_preferred":[
        "\u0428\u044b\u043b\u0430"
    ],
    "name:cat_x_preferred":[
        "Shiloh"
    ],
    "name:ceb_x_preferred":[
        "Shiloh"
    ],
    "name:deu_x_preferred":[
        "Shiloh"
    ],
    "name:fra_x_preferred":[
        "Shiloh"
    ],
    "name:heb_x_preferred":[
        "\u05e9\u05d9\u05dc\u05d4"
    ],
    "name:ita_x_preferred":[
        "Shiloh"
    ],
    "name:nld_x_preferred":[
        "Shiloh"
    ],
    "name:pol_x_preferred":[
        "Shiloh"
    ],
    "name:rus_x_preferred":[
        "\u0428\u0438\u043b\u043e"
    ],
    "name:spa_x_preferred":[
        "Shiloh"
    ],
    "name:srp_x_preferred":[
        "\u0428\u0430\u0458\u043b\u043e"
    ],
    "name:swe_x_preferred":[
        "Shiloh"
    ],
    "name:ukr_x_preferred":[
        "\u0428\u0438\u043b\u043e"
    ],
    "name:vol_x_preferred":[
        "Shiloh"
    ],
    "qs_pg:aaroncc":"US",
    "qs_pg:gn_country":"US",
    "qs_pg:gn_fcode":"PPL",
    "qs_pg:gn_pop":266,
    "qs_pg:name":"Shiloh",
    "qs_pg:photos_9r":0,
    "qs_pg:photos_sr":0,
    "qs_pg:pop_sr":2,
    "qs_pg:qs_pg_placetype":"locality",
    "wof:name":"Shiloh",
    "wof:placetype":"locality",
    "wof:population":266
},
  "geometry": {"coordinates":[-85.6033,34.83508],"type":"Point"}
}