{
  "type": "Feature",
  "properties": {
    "gn:admin1_code":"CA",
    "gn:admin2_code":"49.0",
    "gn:asciiname":"Lookout Junction",
    "gn:country_code":"US",
    "gn:dem":1299,
    "gn:elevation":"1294.0",
    "gn:feature_class":"P",
    "gn:feature_code":"PPL",
    "gn:name":"Lookout Junction",
    "gn:population":0,
    "gn:timezone":"America/Los_Angeles",
    "iso:country":"US",
    "name:zho_x_preferred":[
        "\u76e7\u514b\u6b50\u7279\u7ae0\u514b\u7533"
    ],
    "wof:name":"Lookout Junction",
    "wof:placetype":"locality"
},
  "geometry": {"coordinates":[-121.2347,41.2585],"type":"Point"}
}