{
  "type": "Feature",
  "properties": {
    "gn:admin1_code":"NY",
    "gn:admin2_code":"123.0",
    "gn:admin3_code":"6002.0",
    "gn:asciiname":"Havens Corner",
    "gn:country_code":"US",
    "gn:dem":337,
    "gn:elevation":"340.0",
    "gn:feature_class":"P",
    "gn:feature_code":"PPL",
    "gn:name":"Havens Corner",
    "gn:population":0,
    "gn:timezone":"America/New_York",
    "iso:country":"US",
    "wof:name":"Havens Corner",
    "wof:placetype":"locality"
},
  "geometry": {"coordinates":[-77.08914,42.71729000000001],"type":"Point"}
}