{
  "type": "Feature",
  "properties": {
    "gn:admin1_code":"AL",
    "gn:admin2_code":"73",
    "gn:asciiname":"Oakwood",
    "gn:country_code":"US",
    "gn:dem":154,
    "gn:elevation":"150.0",
    "gn:feature_class":"P",
    "gn:feature_code":"PPL",
    "gn:name":"Oakwood",
    "gn:population":0,
    "gn:timezone":"America/Chicago",
    "iso:country":"US",
    "name:cat_x_preferred":[
        "Oakwood"
    ],
    "name:ceb_x_preferred":[
        "Oakwood"
    ],
    "name:deu_x_preferred":[
        "Oakwood"
    ],
    "name:fas_x_preferred":[
        "\u0627\u0648\u0627\u06a9\u0648\u0648\u062f"
    ],
    "name:fra_x_preferred":[
        "Oakwood"
    ],
    "name:ita_x_preferred":[
        "Oakwood"
    ],
    "name:kor_x_preferred":[
        "\uc624\ud06c\uc6b0\ub4dc"
    ],
    "name:nld_x_preferred":[
        "Oakwood"
    ],
    "name:pol_x_preferred":[
        "Oakwood"
    ],
    "name:por_x_preferred":[
        "Oakwood"
    ],
    "name:spa_x_preferred":[
        "Oakwood"
    ],
    "name:srp_x_preferred":[
        "\u041e\u0443\u043a\u0432\u0443\u0434"
    ],
    "name:swe_x_preferred":[
        "Oakwood"
    ],
    "name:urd_x_preferred":[
        "\u0627\u0648\u06a9\u0648\u0648\u0688"
    ],
    "name:vol_x_preferred":[
        "Oakwood"
    ],
    "wof:name":"Oakwood",
    "wof:placetype":"locality"
},
  "geometry": {"coordinates":[-86.96444,33.39067],"type":"Point"}
}