{
  "type": "Feature",
  "properties": {
    "gn:admin1_code":"TN",
    "gn:admin2_code":"179",
    "gn:asciiname":"Maison",
    "gn:country_code":"US",
    "gn:dem":574,
    "gn:elevation":"571.0",
    "gn:feature_class":"P",
    "gn:feature_code":"PPL",
    "gn:name":"Maison",
    "gn:population":0,
    "gn:timezone":"America/New_York",
    "iso:country":"US",
    "name:ceb_x_preferred":[
        "Maison"
    ],
    "name:ces_x_preferred":[
        "Maison"
    ],
    "name:deu_x_preferred":[
        "Maison"
    ],
    "name:fra_x_preferred":[
        "Maison"
    ],
    "name:nld_x_preferred":[
        "Maison"
    ],
    "name:oci_x_preferred":[
        "Ostal"
    ],
    "name:rus_x_preferred":[
        "\u041c\u044d\u0437\u043e\u043d"
    ],
    "wof:name":"Maison",
    "wof:placetype":"locality"
},
  "geometry": {"coordinates":[-82.42236,36.29038],"type":"Point"}
}