{
  "type": "Feature",
  "properties": {
    "gn:admin1_code":"TX",
    "gn:admin2_code":"389.0",
    "gn:asciiname":"Worsham",
    "gn:country_code":"US",
    "gn:dem":803,
    "gn:elevation":"801.0",
    "gn:feature_class":"P",
    "gn:feature_code":"PPL",
    "gn:name":"Worsham",
    "gn:population":0,
    "gn:timezone":"America/Chicago",
    "iso:country":"US",
    "wof:name":"Worsham",
    "wof:placetype":"locality"
},
  "geometry": {"coordinates":[-103.53017,31.36291],"type":"Point"}
}