{
  "type": "Feature",
  "properties": {
    "gn:admin1_code":"VA",
    "gn:admin2_code":"161",
    "gn:asciiname":"Timberidge Acres",
    "gn:country_code":"US",
    "gn:dem":316,
    "gn:elevation":"312.0",
    "gn:feature_class":"P",
    "gn:feature_code":"PPL",
    "gn:name":"Timberidge Acres",
    "gn:population":0,
    "gn:timezone":"America/New_York",
    "iso:country":"US",
    "wof:name":"Timberidge Acres",
    "wof:placetype":"locality"
},
  "geometry": {"coordinates":[-79.89281,37.27153],"type":"Point"}
}