{
  "type": "Feature",
  "properties": {
    "gn:admin1_code":"FL",
    "gn:admin2_code":"23.0",
    "gn:asciiname":"Wilburn",
    "gn:country_code":"US",
    "gn:dem":66,
    "gn:elevation":"61.0",
    "gn:feature_class":"P",
    "gn:feature_code":"PPL",
    "gn:name":"Wilburn",
    "gn:population":0,
    "gn:timezone":"America/New_York",
    "iso:country":"US",
    "wof:name":"Wilburn",
    "wof:placetype":"locality"
},
  "geometry": {"coordinates":[-82.57873000000002,30.19079],"type":"Point"}
}