{
  "type": "Feature",
  "properties": {
    "gn:country":"US",
    "gn:fcode":"PPL",
    "gn:population":0,
    "iso:country":"US",
    "name:deu_x_preferred":[
        "Borgarfj\u00f6r\u00f0ur"
    ],
    "name:eng_x_preferred":[
        "Main Settlement"
    ],
    "name:eus_x_preferred":[
        "Borgarfjar\u00f0arhreppur"
    ],
    "name:fra_x_preferred":[
        "Borgarfjar\u00f0arhreppur"
    ],
    "name:isl_x_preferred":[
        "Borgarfjar\u00f0arhreppur"
    ],
    "name:ita_x_preferred":[
        "Borgarfj\u00f6r\u00f0ur"
    ],
    "name:nld_x_preferred":[
        "Borgarfjar\u00f0arhreppur"
    ],
    "name:nor_x_preferred":[
        "Borgarfjar\u00f0arhreppur"
    ],
    "name:sme_x_preferred":[
        "Borgarfjar\u00f0arhreppur"
    ],
    "name:spa_x_preferred":[
        "Borgarfjar\u00f0arhreppur"
    ],
    "name:sqi_x_preferred":[
        "Borgarfjardarhreppur"
    ],
    "name:und_x_variant":[
        "Carroll"
    ],
    "qs_pg:aaroncc":"US",
    "qs_pg:gn_country":"US",
    "qs_pg:gn_fcode":"PPL",
    "qs_pg:gn_pop":0,
    "qs_pg:name":"Main Settlement",
    "qs_pg:name_adm0":"United States",
    "qs_pg:name_adm1":"New York",
    "qs_pg:photos":2,
    "qs_pg:photos_1k":1,
    "qs_pg:photos_9k":1,
    "qs_pg:photos_9r":1,
    "qs_pg:photos_all":2,
    "qs_pg:photos_sr":1,
    "qs_pg:pop_sr":0,
    "qs_pg:qs_pg_placetype":"neighbourhood",
    "qs_pg:qs_pg_placetype_gp":"Suburb",
    "qs_pg:woe_adm0":23424977,
    "woe:adm0_id":23424977,
    "woe:name_adm0":"United States",
    "woe:name_adm1":"New York",
    "woe:placetype":"Suburb",
    "wof:name":"Main Settlement",
    "wof:placetype":"neighbourhood",
    "wof:population":27
},
  "geometry": {"coordinates":[-78.31417999999999,42.0134],"type":"Point"}
}