{
  "type": "Feature",
  "properties": {
    "gn:admin1_code":"MD",
    "gn:admin2_code":"9.0",
    "gn:asciiname":"Hillside Manor",
    "gn:country_code":"US",
    "gn:dem":37,
    "gn:elevation":"32.0",
    "gn:feature_class":"P",
    "gn:feature_code":"PPL",
    "gn:name":"Hillside Manor",
    "gn:population":0,
    "gn:timezone":"America/New_York",
    "iso:country":"US",
    "wof:name":"Hillside Manor",
    "wof:placetype":"locality"
},
  "geometry": {"coordinates":[-76.51994999999999,38.49151],"type":"Point"}
}