{
  "type": "Feature",
  "properties": {
    "gn:country":"US",
    "gn:fcode":"PPL",
    "gn:population":0,
    "iso:country":"US",
    "name:ara_x_preferred":[
        "\u0641\u0627\u0644\u064a \u0628\u0627\u0631\u0643"
    ],
    "name:eng_x_preferred":[
        "Valley Park"
    ],
    "name:fas_x_preferred":[
        "\u0648\u0644\u06cc \u067e\u0627\u0631\u06a9\u060c \u0645\u06cc\u0633\u06cc\u0633\u06cc\u067e\u06cc"
    ],
    "name:fas_x_variant":[
        "\u0648\u0644\u06cc \u067e\u0627\u0631\u06a9"
    ],
    "name:fra_x_preferred":[
        "Valley Park"
    ],
    "name:lld_x_preferred":[
        "Valley Park"
    ],
    "name:und_x_variant":[
        "Halpins"
    ],
    "name:urd_x_preferred":[
        "\u0648\u06cc\u0644\u06cc \u067e\u0627\u0631\u06a9\u060c \u0645\u0633\u06cc\u0633\u067e\u06cc"
    ],
    "name:urd_x_variant":[
        "\u0648\u06cc\u0644\u06cc \u067e\u0627\u0631\u06a9"
    ],
    "qs_pg:aaroncc":"US",
    "qs_pg:gn_country":"US",
    "qs_pg:gn_fcode":"PPL",
    "qs_pg:gn_pop":0,
    "qs_pg:name":"Valley Park",
    "qs_pg:name_adm0":"United States",
    "qs_pg:name_adm1":"Mississippi",
    "qs_pg:photos_9r":0,
    "qs_pg:photos_sr":0,
    "qs_pg:pop_sr":5,
    "qs_pg:qs_pg_placetype":"locality",
    "qs_pg:qs_pg_placetype_gp":"Town",
    "qs_pg:woe_adm0":23424977,
    "woe:adm0_id":23424977,
    "woe:name_adm0":"United States",
    "woe:name_adm1":"Mississippi",
    "woe:placetype":"Town",
    "wof:name":"Valley Park",
    "wof:placetype":"locality"
},
  "geometry": {"coordinates":[-90.86677,32.63347],"type":"Point"}
}