{
  "type": "Feature",
  "properties": {
    "iso:country":"US",
    "name:eng_x_preferred":[
        "Goodman Heights"
    ],
    "wof:name":"Goodman Heights",
    "wof:placetype":"neighbourhood",
    "wof:population":685,
    "zs:area_m":1030249.496395,
    "zs:blockids":[
        370250405004005,
        370250405004004,
        370250405004009,
        370250421022021,
        370250421022019
    ],
    "zs:housing10":255,
    "zs:label":"Goodman Heights",
    "zs:pop10":685
},
  "geometry": {"coordinates":[-80.58112199999999,35.363122],"type":"Point"}
}