{
  "type": "Feature",
  "properties": {
    "gn:admin1_code":"AL",
    "gn:admin2_code":"25",
    "gn:asciiname":"Choctaw Bluff",
    "gn:country_code":"US",
    "gn:dem":56,
    "gn:elevation":"49.0",
    "gn:feature_class":"P",
    "gn:feature_code":"PPL",
    "gn:name":"Choctaw Bluff",
    "gn:population":0,
    "gn:timezone":"America/Chicago",
    "iso:country":"US",
    "wof:name":"Choctaw Bluff",
    "wof:placetype":"locality"
},
  "geometry": {"coordinates":[-87.78888000000001,31.38878],"type":"Point"}
}