{
  "type": "Feature",
  "properties": {
    "gn:admin1_code":"KY",
    "gn:admin2_code":"185",
    "gn:asciiname":"Liro",
    "gn:country_code":"US",
    "gn:dem":273,
    "gn:elevation":"272.0",
    "gn:feature_class":"P",
    "gn:feature_code":"PPL",
    "gn:name":"Liro",
    "gn:population":0,
    "gn:timezone":"America/New_York",
    "iso:country":"US",
    "name:ceb_x_preferred":[
        "Liro"
    ],
    "name:deu_x_preferred":[
        "Liro"
    ],
    "name:epo_x_preferred":[
        "Liro"
    ],
    "name:fra_x_preferred":[
        "Liro"
    ],
    "name:ido_x_preferred":[
        "Liro"
    ],
    "name:ita_x_preferred":[
        "Liro"
    ],
    "name:nld_x_preferred":[
        "Liro"
    ],
    "name:swe_x_preferred":[
        "Liro"
    ],
    "wof:name":"Liro",
    "wof:placetype":"locality"
},
  "geometry": {"coordinates":[-85.33856999999998,38.40118],"type":"Point"}
}