{
  "type": "Feature",
  "properties": {
    "gn:admin1_code":"GA",
    "gn:admin2_code":"231",
    "gn:asciiname":"Pedenville",
    "gn:country_code":"US",
    "gn:dem":234,
    "gn:elevation":"233.0",
    "gn:feature_class":"P",
    "gn:feature_code":"PPL",
    "gn:name":"Pedenville",
    "gn:population":0,
    "gn:timezone":"America/New_York",
    "iso:country":"US",
    "wof:name":"Pedenville",
    "wof:placetype":"locality"
},
  "geometry": {"coordinates":[-84.49630999999999,33.1229],"type":"Point"}
}