{
  "type": "Feature",
  "properties": {
    "gn:admin1_code":"ID",
    "gn:admin2_code":"83.0",
    "gn:asciiname":"Duncan Place",
    "gn:country_code":"US",
    "gn:dem":1643,
    "gn:elevation":"1643.0",
    "gn:feature_class":"P",
    "gn:feature_code":"PPL",
    "gn:name":"Duncan Place",
    "gn:population":0,
    "gn:timezone":"America/Boise",
    "iso:country":"US",
    "wof:name":"Duncan Place",
    "wof:placetype":"locality"
},
  "geometry": {"coordinates":[-114.80976,42.03547],"type":"Point"}
}