{
  "type": "Feature",
  "properties": {
    "gn:admin1_code":"OH",
    "gn:admin2_code":"41",
    "gn:admin3_code":"21469.0",
    "gn:asciiname":"Central Mobile Home Park",
    "gn:country_code":"US",
    "gn:dem":272,
    "gn:elevation":"272.0",
    "gn:feature_class":"P",
    "gn:feature_code":"PPL",
    "gn:name":"Central Mobile Home Park",
    "gn:population":0,
    "gn:timezone":"America/New_York",
    "iso:country":"US",
    "wof:name":"Central Mobile Home Park",
    "wof:placetype":"campus"
},
  "geometry": {"coordinates":[-83.06639,40.29111],"type":"Point"}
}