{
  "type": "Feature",
  "properties": {
    "gn:admin1_code":"PA",
    "gn:admin2_code":"129.0",
    "gn:admin3_code":"72256.0",
    "gn:asciiname":"Jacobs Creek",
    "gn:country_code":"US",
    "gn:dem":243,
    "gn:elevation":"240.0",
    "gn:feature_class":"P",
    "gn:feature_code":"PPL",
    "gn:name":"Jacobs Creek",
    "gn:population":0,
    "gn:timezone":"America/New_York",
    "iso:country":"US",
    "name:ceb_x_preferred":[
        "Jacobs Creek"
    ],
    "name:swe_x_preferred":[
        "Jacobs Creek"
    ],
    "wof:name":"Jacobs Creek",
    "wof:placetype":"locality"
},
  "geometry": {"coordinates":[-79.74171,40.13313],"type":"Point"}
}