{
  "type": "Feature",
  "properties": {
    "gn:country":"US",
    "gn:fcode":"PPL",
    "gn:population":0,
    "iso:country":"US",
    "name:eng_x_preferred":[
        "Canaan Center"
    ],
    "name:und_x_variant":[
        "Canaan Centre"
    ],
    "qs_pg:aaroncc":"US",
    "qs_pg:gn_country":"US",
    "qs_pg:gn_fcode":"PPL",
    "qs_pg:gn_pop":0,
    "qs_pg:name":"Canaan Center",
    "qs_pg:name_adm0":"United States",
    "qs_pg:name_adm1":"New Hampshire",
    "qs_pg:photos":554,
    "qs_pg:photos_1k":112,
    "qs_pg:photos_9k":2,
    "qs_pg:photos_9r":5,
    "qs_pg:photos_all":554,
    "qs_pg:photos_sr":8,
    "qs_pg:pop_sr":0,
    "qs_pg:qs_pg_placetype":"neighbourhood",
    "qs_pg:qs_pg_placetype_gp":"Suburb",
    "qs_pg:woe_adm0":23424977,
    "wof:name":"Canaan Center",
    "wof:placetype":"neighbourhood",
    "wof:population":1297,
    "zs:area_m":85618171.929124,
    "zs:blockids":[
        330099614003000,
        330099614001032,
        330099614003002,
        330099614003021,
        330099609001161,
        330099609002004,
        330099616012003,
        330099616012000,
        330099614003030,
        330099614003007,
        330099614003027,
        330099616012001,
        330099614003008,
        330099614003006,
        330099609001140,
        330099614003016,
        330099616012004,
        330099614003031,
        330099614003024,
        330099609001142,
        330099616012055,
        330099614003001,
        330099614001029,
        330099614003005,
        330099616012061,
        330099614003022,
        330099614003011,
        330099614003019,
        330099614003029,
        330099614003017,
        330099614001006,
        330099609001141,
        330099614003009,
        330099616012060,
        330099614001033,
        330099614003020,
        330099616012056,
        330099609001143,
        330099609001144,
        330099609001031,
        330099609003006,
        330099616012059,
        330099614003004,
        330099614003028,
        330099614001035,
        330099614003014,
        330099614003023,
        330099614003047,
        330099609001160,
        330099609002002,
        330099609001153,
        330099616012012,
        330099614003038,
        330099609003003,
        330099614003026,
        330099614003013,
        330099609001136,
        330099614001007,
        330099614001008,
        330099609001035,
        330099609001137,
        330099609001036,
        330099609001030,
        330099609001145,
        330099616012057,
        330099616012054,
        330099614003010,
        330099614003018,
        330099614001034,
        330099616012058,
        330099609001028,
        330099609001029,
        330099614002000,
        330099616012002,
        330099614003003,
        330099614001009,
        330099614003025
    ],
    "zs:housing10":735,
    "zs:label":"Canaan Center",
    "zs:pop10":1297
},
  "geometry": {"coordinates":[-72.0728,43.702185],"type":"Point"}
}