{
  "type": "Feature",
  "properties": {
    "gn:elevation":645,
    "iso:country":"US",
    "name:ceb_x_preferred":[
        "Milltown"
    ],
    "name:deu_x_preferred":[
        "Milltown"
    ],
    "name:eng_x_preferred":[
        "Milltown"
    ],
    "name:fra_x_preferred":[
        "Milltown"
    ],
    "name:ita_x_preferred":[
        "Milltown"
    ],
    "name:nld_x_preferred":[
        "Milltown"
    ],
    "name:pol_x_preferred":[
        "Milltown"
    ],
    "name:por_x_preferred":[
        "Milltown"
    ],
    "name:rus_x_preferred":[
        "\u041c\u0438\u043b\u0442\u0430\u0443\u043d"
    ],
    "name:srp_x_preferred":[
        "\u041c\u0438\u043b\u0442\u0430\u0443\u043d"
    ],
    "name:swe_x_preferred":[
        "Milltown"
    ],
    "name:ukr_x_preferred":[
        "\u041c\u0456\u043b\u043b\u0442\u0430\u0443\u043d"
    ],
    "name:unk_x_variant":[
        "Milltown"
    ],
    "name:vol_x_preferred":[
        "Milltown"
    ],
    "qs:gn_fcode":"PPL",
    "qs:gn_local":0,
    "qs:gn_namadm1":"NC",
    "qs:gn_name":"Milltown",
    "qs:local_max":132,
    "qs:local_sum":132,
    "qs:localhoods":1,
    "qs:name":"Milltown",
    "qs:name_adm0":"United States",
    "qs:name_adm1":"North Carolina",
    "qs:name_adm2":"Graham",
    "qs:name_local":"Robbinsville",
    "qs:photo_max":32,
    "qs:photo_sum":132,
    "qs:placetype":"Suburb",
    "qs:quad_count":14,
    "qs:woe_adm0":23424977,
    "qs:woe_adm1":2347592,
    "qs:woe_adm2":12589411,
    "qs:woe_lau":0,
    "qs:woe_local":2482649,
    "qs:woe_ver":"7.10.0",
    "wof:lang":[
        "eng"
    ],
    "wof:name":"Milltown",
    "wof:placetype":"neighbourhood",
    "wof:population":1065,
    "zs:blockids":[
        370759202002063,
        370759203003009,
        370759203003024,
        370759203003033,
        370759203002049,
        370759203003010,
        370759203003001,
        370759203003006,
        370759203003017,
        370759203003002,
        370759202001000,
        370759203003045,
        370759203003023,
        370759203003042,
        370759203003016,
        370759202001031,
        370759203003031,
        370759203003020,
        370759203003029,
        370759203003055,
        370759203003015,
        370759203002038,
        370759203003026,
        370759203003007,
        370759203003008
    ],
    "zs:housing10":620,
    "zs:pop10":1065
},
  "geometry": {"coordinates":[-83.80582200000001,35.324098],"type":"Point"}
}