{
  "type": "Feature",
  "properties": {
    "gn:admin1_code":"TX",
    "gn:admin2_code":"229.0",
    "gn:asciiname":"Cornudas",
    "gn:country_code":"US",
    "gn:dem":1312,
    "gn:elevation":"1313.0",
    "gn:feature_class":"P",
    "gn:feature_code":"PPL",
    "gn:name":"Cornudas",
    "gn:population":0,
    "gn:timezone":"America/Denver",
    "iso:country":"US",
    "name:azb_x_preferred":[
        "\u06a9\u0648\u0631\u0646\u06cc\u062f\u0627\u0633"
    ],
    "name:fas_x_preferred":[
        "\u06a9\u0648\u0631\u0646\u06cc\u062f\u0627\u0633"
    ],
    "name:spa_x_preferred":[
        "Cornudas"
    ],
    "wof:name":"Cornudas",
    "wof:placetype":"locality"
},
  "geometry": {"coordinates":[-105.47107,31.77983],"type":"Point"}
}