{
  "type": "Feature",
  "properties": {
    "iso:country":"US",
    "name:eng_x_preferred":[
        "Lake Hunter Heights"
    ],
    "wof:name":"Lake Hunter Heights",
    "wof:placetype":"neighbourhood",
    "wof:population":1885,
    "zs:area_m":1545584.31475,
    "zs:blockids":[
        121050108002005,
        121050108002017,
        121050108002014,
        121050108002018,
        121050108002031,
        121050108001093,
        121050108002004,
        121050108002038,
        121050108001073,
        121050108001076,
        121050108002024,
        121050108001045,
        121050108002003,
        121050108002019,
        121050108001083,
        121050108001077,
        121050108001082,
        121050108001051,
        121050108001072,
        121050108002032,
        121050107012002,
        121050108002028,
        121050108002027,
        121050108002030,
        121050108001078,
        121050108001052,
        121050107012004,
        121050108001046,
        121050108001071,
        121050108001048,
        121050108002029,
        121050108002037,
        121050108002045,
        121050108002039,
        121050108001054,
        121050108001080,
        121050108001068,
        121050108002006,
        121050108002036,
        121050108002025,
        121050108001079,
        121050107012003,
        121050108001053,
        121050108001070,
        121050108001069,
        121050108002002,
        121050108002013,
        121050108002026,
        121050108001081,
        121050108001092,
        121050108001091
    ],
    "zs:housing10":963,
    "zs:label":"Lake Hunter Heights",
    "zs:pop10":1885
},
  "geometry": {"coordinates":[-81.96548300000001,28.030282],"type":"Point"}
}