{
  "type": "Feature",
  "properties": {
    "gn:admin1_code":"MI",
    "gn:admin2_code":"107.0",
    "gn:admin3_code":"21240.0",
    "gn:asciiname":"Rustford",
    "gn:country_code":"US",
    "gn:dem":289,
    "gn:elevation":"288.0",
    "gn:feature_class":"P",
    "gn:feature_code":"PPL",
    "gn:name":"Rustford",
    "gn:population":0,
    "gn:timezone":"America/Detroit",
    "iso:country":"US",
    "wof:name":"Rustford",
    "wof:placetype":"locality"
},
  "geometry": {"coordinates":[-85.34281,43.51253],"type":"Point"}
}