{
  "type": "Feature",
  "properties": {
    "gn:admin1_code":"AK",
    "gn:admin2_code":"70.0",
    "gn:asciiname":"Tunravik",
    "gn:country_code":"US",
    "gn:dem":39,
    "gn:elevation":"38.0",
    "gn:feature_class":"P",
    "gn:feature_code":"PPL",
    "gn:name":"Tunravik",
    "gn:population":0,
    "gn:timezone":"America/Anchorage",
    "iso:country":"US",
    "name:eng_x_preferred":[
        "Tunravik"
    ],
    "name:und_x_variant":[
        "Turnavk",
        "Tunravk"
    ],
    "wof:name":"Tunravik",
    "wof:placetype":"locality"
},
  "geometry": {"coordinates":[-157.22528,59.48861],"type":"Point"}
}