{
  "type": "Feature",
  "properties": {
    "gn:admin1_code":"FL",
    "gn:admin2_code":"57",
    "gn:asciiname":"Cooks Cove",
    "gn:country_code":"US",
    "gn:dem":33,
    "gn:elevation":"26.0",
    "gn:feature_class":"P",
    "gn:feature_code":"PPL",
    "gn:name":"Cooks Cove",
    "gn:population":0,
    "gn:timezone":"America/New_York",
    "iso:country":"US",
    "wof:name":"Cooks Cove",
    "wof:placetype":"locality"
},
  "geometry": {"coordinates":[-82.1908,28.0806],"type":"Point"}
}