{
  "type": "Feature",
  "properties": {
    "gn:country":"US",
    "gn:fcode":"PPL",
    "gn:population":0,
    "iso:country":"US",
    "name:ara_x_preferred":[
        "\u0645\u0648\u0646\u062a\u064a\u0632\u0648\u0645\u0627"
    ],
    "name:deu_x_preferred":[
        "Montezuma"
    ],
    "name:eng_x_preferred":[
        "Montezuma"
    ],
    "name:eus_x_preferred":[
        "Montezuma"
    ],
    "name:fra_x_preferred":[
        "Montezuma"
    ],
    "name:hat_x_preferred":[
        "Montezuma"
    ],
    "name:hun_x_preferred":[
        "Montezuma"
    ],
    "name:ita_x_preferred":[
        "Montezuma"
    ],
    "name:pol_x_preferred":[
        "Montezuma"
    ],
    "name:spa_x_preferred":[
        "Montezuma"
    ],
    "name:und_x_variant":[
        "Tecarjikhado"
    ],
    "name:uzb_x_preferred":[
        "Montezuma"
    ],
    "name:zho_x_preferred":[
        "\u8499\u7279\u82cf\u9a6c"
    ],
    "qs_pg:aaroncc":"US",
    "qs_pg:gn_country":"US",
    "qs_pg:gn_fcode":"PPL",
    "qs_pg:gn_pop":0,
    "qs_pg:name":"Montezuma",
    "qs_pg:name_adm0":"United States",
    "qs_pg:name_adm1":"New York",
    "qs_pg:photos":470,
    "qs_pg:photos_1k":95,
    "qs_pg:photos_9k":2,
    "qs_pg:photos_9r":5,
    "qs_pg:photos_all":515,
    "qs_pg:photos_sr":7,
    "qs_pg:pop_sr":0,
    "qs_pg:qs_pg_placetype":"locality",
    "qs_pg:qs_pg_placetype_gp":"Town",
    "qs_pg:woe_adm0":23424977,
    "woe:adm0_id":23424977,
    "woe:name_adm0":"United States",
    "woe:name_adm1":"New York",
    "woe:placetype":"Town",
    "wof:name":"Montezuma",
    "wof:placetype":"locality"
},
  "geometry": {"coordinates":[-76.70328000000001,43.01006],"type":"Point"}
}