{
  "type": "Feature",
  "properties": {
    "iso:country":"US",
    "name:deu_x_preferred":[
        "Spragueville"
    ],
    "name:eng_x_preferred":[
        "Spragueville"
    ],
    "wd:wordcount":8,
    "wof:name":"Spragueville",
    "wof:placetype":"neighbourhood",
    "wof:population":696,
    "zs:area_m":42948547.612936,
    "zs:blockids":[
        230039520002070,
        230039519002064,
        230039521003025,
        230039521003008,
        230039520002072,
        230039520002079,
        230039520002064,
        230039520002095,
        230039520002017,
        230039521003009,
        230039520002073,
        230039520002080,
        230039520002067,
        230039520002044,
        230039520002089,
        230039521003026,
        230039520002065,
        230039520002081,
        230039520002052,
        230039520002069,
        230039520002091,
        230039520002063,
        230039520002057,
        230039520002056,
        230039520002054,
        230039520002082,
        230039520002058,
        230039520002046,
        230039520002055,
        230039520002053,
        230039520002090,
        230039521003007,
        230039520002060,
        230039520002037,
        230039520002068,
        230039520002074,
        230039520002036,
        230039520002062,
        230039520002066,
        230039520002061,
        230039519001034,
        230039520002045,
        230039520002059
    ],
    "zs:housing10":323,
    "zs:label":"Spragueville",
    "zs:pop10":696
},
  "geometry": {"coordinates":[-67.97413,46.628486],"type":"Point"}
}