{
  "type": "Feature",
  "properties": {
    "gn:admin1_code":"SC",
    "gn:admin2_code":"13.0",
    "gn:asciiname":"Scott",
    "gn:country_code":"US",
    "gn:dem":7,
    "gn:elevation":"3.0",
    "gn:feature_class":"P",
    "gn:feature_code":"PPL",
    "gn:name":"Scott",
    "gn:population":0,
    "gn:timezone":"America/New_York",
    "iso:country":"US",
    "name:ara_x_preferred":[
        "\u0633\u0643\u0648\u062a"
    ],
    "name:bel_x_preferred":[
        "\u0421\u043a\u043e\u0442"
    ],
    "name:bul_x_preferred":[
        "\u0421\u043a\u043e\u0442"
    ],
    "name:cat_x_preferred":[
        "Scott"
    ],
    "name:ceb_x_preferred":[
        "Scott"
    ],
    "name:ces_x_preferred":[
        "Scott"
    ],
    "name:deu_x_preferred":[
        "Scott"
    ],
    "name:fin_x_preferred":[
        "Scott"
    ],
    "name:fra_x_preferred":[
        "Scott"
    ],
    "name:heb_x_preferred":[
        "\u05e1\u05e7\u05d5\u05d8"
    ],
    "name:ita_x_preferred":[
        "Scott"
    ],
    "name:jpn_x_preferred":[
        "\u30b9\u30b3\u30c3\u30c8"
    ],
    "name:lav_x_preferred":[
        "Skots"
    ],
    "name:lit_x_preferred":[
        "Scott"
    ],
    "name:nld_x_preferred":[
        "Scott"
    ],
    "name:nor_x_preferred":[
        "Scott"
    ],
    "name:pol_x_preferred":[
        "Scott"
    ],
    "name:por_x_preferred":[
        "Scott"
    ],
    "name:rus_x_preferred":[
        "\u0421\u043a\u043e\u0442\u0442"
    ],
    "name:slv_x_preferred":[
        "Scott"
    ],
    "name:spa_x_preferred":[
        "Scott"
    ],
    "name:srp_x_preferred":[
        "\u0421\u043a\u043e\u0442"
    ],
    "name:swe_x_preferred":[
        "Scott"
    ],
    "name:ukr_x_preferred":[
        "\u0421\u043a\u043e\u0442\u0442"
    ],
    "name:vie_x_preferred":[
        "Scott"
    ],
    "name:vol_x_preferred":[
        "Scott"
    ],
    "name:zho_x_preferred":[
        "\u65af\u79d1\u7279"
    ],
    "wof:name":"Scott",
    "wof:placetype":"locality"
},
  "geometry": {"coordinates":[-80.62316,32.34659],"type":"Point"}
}