{
  "type": "Feature",
  "properties": {
    "gn:admin1_code":"WA",
    "gn:admin2_code":"39.0",
    "gn:asciiname":"Moona",
    "gn:country_code":"US",
    "gn:dem":80,
    "gn:elevation":"82.0",
    "gn:feature_class":"P",
    "gn:feature_code":"PPL",
    "gn:name":"Moona",
    "gn:population":0,
    "gn:timezone":"America/Los_Angeles",
    "iso:country":"US",
    "wof:name":"Moona",
    "wof:placetype":"locality"
},
  "geometry": {"coordinates":[-120.1056,45.78569],"type":"Point"}
}