{
  "type": "Feature",
  "properties": {
    "gn:country":"US",
    "gn:fcode":"PPL",
    "gn:population":0,
    "iso:country":"US",
    "name:deu_x_preferred":[
        "East Union"
    ],
    "name:eng_x_preferred":[
        "East Union"
    ],
    "name:pol_x_preferred":[
        "East Union"
    ],
    "name:und_x_variant":[
        "Crosskeys"
    ],
    "name:vol_x_preferred":[
        "East Union"
    ],
    "qs_pg:aaroncc":"US",
    "qs_pg:gn_country":"US",
    "qs_pg:gn_fcode":"PPL",
    "qs_pg:gn_pop":0,
    "qs_pg:name":"East Union",
    "qs_pg:name_adm0":"United States",
    "qs_pg:name_adm1":"Ohio",
    "qs_pg:photos":7,
    "qs_pg:photos_1k":1,
    "qs_pg:photos_9k":1,
    "qs_pg:photos_9r":1,
    "qs_pg:photos_all":7,
    "qs_pg:photos_sr":1,
    "qs_pg:pop_sr":0,
    "qs_pg:qs_pg_placetype":"neighbourhood",
    "qs_pg:qs_pg_placetype_gp":"Suburb",
    "qs_pg:woe_adm0":23424977,
    "wd:wordcount":45,
    "wof:name":"East Union",
    "wof:placetype":"neighbourhood",
    "wof:population":267,
    "zs:area_m":2471518.228628,
    "zs:blockids":[
        391690013002042,
        391690013001034,
        391690014002015
    ],
    "zs:housing10":98,
    "zs:label":"East Union",
    "zs:pop10":267
},
  "geometry": {"coordinates":[-81.831025,40.790385],"type":"Point"}
}