{
  "type": "Feature",
  "properties": {
    "gn:admin1_code":"GA",
    "gn:admin2_code":"237",
    "gn:asciiname":"Reids Crossroads",
    "gn:country_code":"US",
    "gn:dem":154,
    "gn:elevation":"151.0",
    "gn:feature_class":"P",
    "gn:feature_code":"PPL",
    "gn:name":"Reids Crossroads",
    "gn:population":0,
    "gn:timezone":"America/New_York",
    "iso:country":"US",
    "name:eng_x_preferred":[
        "Reids Crossroads"
    ],
    "name:und_x_variant":[
        "Reids Corner"
    ],
    "wof:name":"Reids Crossroads",
    "wof:placetype":"locality"
},
  "geometry": {"coordinates":[-83.42655000000001,33.4093],"type":"Point"}
}