{
  "type": "Feature",
  "properties": {
    "iso:country":"US",
    "name:eng_x_preferred":[
        "Longview Center"
    ],
    "wof:name":"Longview Center",
    "wof:placetype":"neighbourhood",
    "wof:population":4619,
    "zs:area_m":4299088.005878,
    "zs:blockids":[
        120210104171025,
        120210102123004,
        120210104171013,
        120210102123005,
        120210102122005,
        120210102122018,
        120210104171022,
        120210104171010,
        120210104171029,
        120210102123007,
        120210104171011,
        120210102122016,
        120210102122001,
        120210102122022,
        120210104172007,
        120210104172004,
        120210104172002,
        120210104171021,
        120210104171014,
        120210102123002,
        120210104171026,
        120210104171019,
        120210104171024,
        120210104171023,
        120210102122010,
        120210104171027,
        120210102123019,
        120210104172003,
        120210102123000,
        120210102122021,
        120210102121004,
        120210102122020,
        120210102122019,
        120210102122017,
        120210102123018,
        120210102123013,
        120210102123020,
        120210102121005,
        120210102122015,
        120210104171028,
        120210102123011,
        120210102122024,
        120210104171012,
        120210102122023,
        120210102123003,
        120210104171030
    ],
    "zs:housing10":2701,
    "zs:label":"Longview Center",
    "zs:pop10":4619
},
  "geometry": {"coordinates":[-81.768856,26.2334],"type":"Point"}
}