{
  "type": "Feature",
  "properties": {
    "gn:admin1_code":"OH",
    "gn:admin2_code":"11.0",
    "gn:admin3_code":"15448.0",
    "gn:asciiname":"Santa Fe",
    "gn:country_code":"US",
    "gn:dem":309,
    "gn:elevation":"308.0",
    "gn:feature_class":"P",
    "gn:feature_code":"PPL",
    "gn:name":"Santa Fe",
    "gn:population":0,
    "gn:timezone":"America/New_York",
    "iso:country":"US",
    "name:eng_x_preferred":[
        "Santa Fe"
    ],
    "name:fas_x_preferred":[
        "\u0633\u0627\u0646\u062a\u0627 \u0641\u06cc"
    ],
    "name:hun_x_preferred":[
        "Santa Fe"
    ],
    "name:und_x_variant":[
        "Santa Fee"
    ],
    "name:urd_x_preferred":[
        "\u0633\u0627\u0646\u062a\u0627 \u0641\u06d2"
    ],
    "wof:name":"Santa Fe",
    "wof:placetype":"locality"
},
  "geometry": {"coordinates":[-83.99411000000001,40.49144],"type":"Point"}
}