{
  "type": "Feature",
  "properties": {
    "gn:admin1_code":"VT",
    "gn:admin2_code":"11.0",
    "gn:admin3_code":"59125.0",
    "gn:asciiname":"Stevens Mills",
    "gn:country_code":"US",
    "gn:dem":154,
    "gn:elevation":"147.0",
    "gn:feature_class":"P",
    "gn:feature_code":"PPL",
    "gn:name":"Stevens Mills",
    "gn:population":0,
    "gn:timezone":"America/New_York",
    "iso:country":"US",
    "name:eng_x_preferred":[
        "Stevens Mills"
    ],
    "name:und_x_variant":[
        "Stevens Mill"
    ],
    "wof:name":"Stevens Mills",
    "wof:placetype":"locality"
},
  "geometry": {"coordinates":[-72.61400999999999,44.99532],"type":"Point"}
}