{
  "type": "Feature",
  "properties": {
    "gn:country":"US",
    "gn:fcode":"PPL",
    "gn:population":0,
    "iso:country":"US",
    "name:eng_x_preferred":[
        "Stowe of Amyclae"
    ],
    "qs_pg:aaroncc":"US",
    "qs_pg:gn_country":"US",
    "qs_pg:gn_fcode":"PPL",
    "qs_pg:gn_pop":0,
    "qs_pg:name":"Stowe of Amyclae",
    "qs_pg:name_adm0":"United States",
    "qs_pg:name_adm1":"Virginia",
    "qs_pg:photos":1,
    "qs_pg:photos_1k":1,
    "qs_pg:photos_9k":1,
    "qs_pg:photos_9r":1,
    "qs_pg:photos_all":1,
    "qs_pg:photos_sr":1,
    "qs_pg:pop_sr":0,
    "qs_pg:qs_pg_placetype":"neighbourhood",
    "qs_pg:qs_pg_placetype_gp":"Suburb",
    "qs_pg:woe_adm0":23424977,
    "wof:name":"Stowe of Amyclae",
    "wof:placetype":"neighbourhood",
    "wof:population":2180,
    "zs:area_m":4004610.749311,
    "zs:blockids":[
        511790102041007,
        511790102041031,
        511790102041033,
        511790102041000,
        511790102041004,
        511790102141011,
        511790102041030,
        511790102041032,
        511790102141007,
        511790102141013,
        511790102041002,
        511790102041001,
        511790102041003
    ],
    "zs:housing10":655,
    "zs:label":"Stowe of Amyclae",
    "zs:pop10":2180
},
  "geometry": {"coordinates":[-77.463301,38.45112],"type":"Point"}
}