{
  "type": "Feature",
  "properties": {
    "gn:country":"US",
    "gn:fcode":"PPL",
    "gn:population":0,
    "iso:country":"US",
    "name:eng_x_preferred":[
        "South Albany"
    ],
    "qs_pg:aaroncc":"US",
    "qs_pg:gn_country":"US",
    "qs_pg:gn_fcode":"PPL",
    "qs_pg:gn_pop":0,
    "qs_pg:name":"South Albany",
    "qs_pg:name_adm0":"United States",
    "qs_pg:name_adm1":"Vermont",
    "qs_pg:photos":1,
    "qs_pg:photos_1k":1,
    "qs_pg:photos_9k":1,
    "qs_pg:photos_9r":1,
    "qs_pg:photos_all":1,
    "qs_pg:photos_sr":1,
    "qs_pg:pop_sr":0,
    "qs_pg:qs_pg_placetype":"neighbourhood",
    "qs_pg:qs_pg_placetype_gp":"Suburb",
    "qs_pg:woe_adm0":23424977,
    "wof:name":"South Albany",
    "wof:placetype":"neighbourhood",
    "wof:population":128,
    "zs:area_m":13769991.363928,
    "zs:blockids":[
        500199517003042,
        500199517003046,
        500199517003033,
        500199520001029,
        500199517003003,
        500199517003036,
        500199517003041,
        500199517003040,
        500199517003044,
        500199520001027,
        500199517003037,
        500199520001028,
        500199517003039
    ],
    "zs:housing10":69,
    "zs:label":"South Albany",
    "zs:pop10":128
},
  "geometry": {"coordinates":[-72.28147199999999,44.73004],"type":"Point"}
}