{
  "type": "Feature",
  "properties": {
    "iso:country":"US",
    "name:azb_x_preferred":[
        "\u0628\u0631\u0642\u0648\u06cc\u0644"
    ],
    "name:eng_x_preferred":[
        "Braggville"
    ],
    "name:fas_x_preferred":[
        "\u0628\u0631\u06af\u0648\u06cc\u0644"
    ],
    "name:fra_x_preferred":[
        "Braggville"
    ],
    "qs:gn_local":0,
    "qs:local_max":179,
    "qs:local_sum":322,
    "qs:localhoods":4,
    "qs:name":"Braggville",
    "qs:name_adm0":"United States",
    "qs:name_adm1":"Massachusetts",
    "qs:name_adm2":"Middlesex",
    "qs:name_local":"Holliston",
    "qs:photo_max":3,
    "qs:photo_sum":9,
    "qs:placetype":"Suburb",
    "qs:quad_count":6,
    "qs:woe_adm0":23424977,
    "qs:woe_adm1":2347580,
    "qs:woe_adm2":12588708,
    "qs:woe_lau":0,
    "qs:woe_local":2423210,
    "qs:woe_ver":"7.10.0",
    "wd:wordcount":575,
    "wof:lang":[
        "eng"
    ],
    "wof:name":"Braggville",
    "wof:placetype":"neighbourhood",
    "wof:population":206,
    "zs:blockids":[
        250173872022009,
        250173872022007,
        250173872022006,
        250173872022005
    ],
    "zs:housing10":74,
    "zs:pop10":206
},
  "geometry": {"coordinates":[-71.474304,42.178106],"type":"Point"}
}