{
  "type": "Feature",
  "properties": {
    "gn:admin1_code":"TX",
    "gn:admin2_code":"243.0",
    "gn:asciiname":"Saltlick Mill",
    "gn:country_code":"US",
    "gn:dem":1169,
    "gn:elevation":"1168.0",
    "gn:feature_class":"P",
    "gn:feature_code":"PPL",
    "gn:name":"Saltlick Mill",
    "gn:population":0,
    "gn:timezone":"America/Chicago",
    "iso:country":"US",
    "wof:name":"Saltlick Mill",
    "wof:placetype":"locality"
},
  "geometry": {"coordinates":[-103.62823,30.74154],"type":"Point"}
}