{
  "type": "Feature",
  "properties": {
    "gn:admin1_code":"OH",
    "gn:admin2_code":"165.0",
    "gn:admin3_code":"82306.0",
    "gn:asciiname":"Crosswick",
    "gn:country_code":"US",
    "gn:dem":264,
    "gn:elevation":"264.0",
    "gn:feature_class":"P",
    "gn:feature_code":"PPL",
    "gn:name":"Crosswick",
    "gn:population":0,
    "gn:timezone":"America/New_York",
    "iso:country":"US",
    "name:eng_x_preferred":[
        "Crosswick"
    ],
    "name:und_x_variant":[
        "Crosswicks"
    ],
    "name:vol_x_preferred":[
        "Crosswick"
    ],
    "wof:name":"Crosswick",
    "wof:placetype":"locality"
},
  "geometry": {"coordinates":[-84.07881999999999,39.54395],"type":"Point"}
}