{
  "type": "Feature",
  "properties": {
    "iso:country":"US",
    "name:ceb_x_preferred":[
        "Rosedale"
    ],
    "name:deu_x_preferred":[
        "Rosedale"
    ],
    "name:eng_x_preferred":[
        "Rosedale"
    ],
    "name:fra_x_preferred":[
        "Rosedale"
    ],
    "name:ita_x_preferred":[
        "Rosedale"
    ],
    "name:kor_x_preferred":[
        "\ub85c\uc988\ub370\uc77c"
    ],
    "name:nld_x_preferred":[
        "Rosedale"
    ],
    "name:pol_x_preferred":[
        "Rosedale"
    ],
    "name:por_x_preferred":[
        "Rosedale"
    ],
    "name:spa_x_preferred":[
        "Rosedale"
    ],
    "name:srp_x_preferred":[
        "\u0420\u043e\u0443\u0437\u0434\u0435\u0458\u043b"
    ],
    "name:swe_x_preferred":[
        "Rosedale"
    ],
    "name:vol_x_preferred":[
        "Rosedale"
    ],
    "wof:name":"Rosedale",
    "wof:placetype":"neighbourhood",
    "zs:area_m":16691.250193,
    "zs:blockids":[
        121050103003033
    ],
    "zs:housing10":0,
    "zs:label":"Rosedale",
    "zs:pop10":0
},
  "geometry": {"coordinates":[-81.944294,28.043555],"type":"Point"}
}