{
  "type": "Feature",
  "properties": {
    "iso:country":"US",
    "name:cat_x_preferred":[
        "New Hope"
    ],
    "name:ceb_x_preferred":[
        "New Hope"
    ],
    "name:ces_x_preferred":[
        "New Hope"
    ],
    "name:deu_x_preferred":[
        "New Hope"
    ],
    "name:eng_x_preferred":[
        "New Hope"
    ],
    "name:fra_x_preferred":[
        "New Hope"
    ],
    "name:hbs_x_preferred":[
        "Nju Houp"
    ],
    "name:ita_x_preferred":[
        "New Hope"
    ],
    "name:jpn_x_preferred":[
        "\u30cb\u30e5\u30fc\u30db\u30fc\u30d7"
    ],
    "name:nld_x_preferred":[
        "New Hope"
    ],
    "name:pol_x_preferred":[
        "New Hope"
    ],
    "name:spa_x_preferred":[
        "New Hope"
    ],
    "name:srp_x_preferred":[
        "\u040a\u0443 \u0425\u043e\u0443\u043f"
    ],
    "name:swe_x_preferred":[
        "New Hope"
    ],
    "name:ukr_x_preferred":[
        "\u041d\u044c\u044e-\u0413\u043e\u0443\u043f"
    ],
    "name:vol_x_preferred":[
        "New Hope"
    ],
    "qs:gn_local":0,
    "qs:local_max":28,
    "qs:local_sum":28,
    "qs:localhoods":1,
    "qs:name":"New Hope",
    "qs:name_adm0":"United States",
    "qs:name_adm1":"Texas",
    "qs:name_adm2":"Dallas",
    "qs:name_local":"Sunnyvale",
    "qs:photo_max":16,
    "qs:photo_sum":28,
    "qs:placetype":"Suburb",
    "qs:quad_count":4,
    "qs:woe_adm0":23424977,
    "qs:woe_adm1":2347602,
    "qs:woe_adm2":12590063,
    "qs:woe_lau":0,
    "qs:woe_local":2502264,
    "qs:woe_ver":"7.10.0",
    "wof:lang":[
        "eng"
    ],
    "wof:name":"New Hope",
    "wof:placetype":"neighbourhood",
    "wof:population":2041,
    "zs:blockids":[
        481130181042012,
        481130181042034,
        481130181042037,
        481130181042035,
        481130178141007,
        481130178141002,
        481130181042055,
        481130181042059,
        481130181042042,
        481130181042013,
        481130181042057,
        481130181042036,
        481130181042024,
        481130178141009,
        481130181042045,
        481130181042014,
        481130178141000,
        481130181042039,
        481130181042058,
        481130181042033,
        481130181042061,
        481130181042053,
        481130181042038,
        481130181042017,
        481130181042046,
        481130181042054,
        481130181042044
    ],
    "zs:housing10":670,
    "zs:pop10":2041
},
  "geometry": {"coordinates":[-96.585323,32.809041],"type":"Point"}
}