{
  "type": "Feature",
  "properties": {
    "gn:admin1_code":"MS",
    "gn:admin2_code":"91.0",
    "gn:asciiname":"Emmanuel",
    "gn:country_code":"US",
    "gn:dem":69,
    "gn:elevation":"62.0",
    "gn:feature_class":"P",
    "gn:feature_code":"PPL",
    "gn:name":"Emmanuel",
    "gn:population":0,
    "gn:timezone":"America/Chicago",
    "iso:country":"US",
    "wof:name":"Emmanuel",
    "wof:placetype":"locality"
},
  "geometry": {"coordinates":[-89.82035999999999,31.30684],"type":"Point"}
}