{
  "type": "Feature",
  "properties": {
    "iso:country":"US",
    "name:eng_x_preferred":[
        "Whitney Lakes"
    ],
    "wof:name":"Whitney Lakes",
    "wof:placetype":"neighbourhood",
    "wof:population":713,
    "zs:area_m":702126.448162,
    "zs:blockids":[
        121030254141037,
        121030254141047,
        121030254141049,
        121030254141012,
        121030254141009,
        121030254141036,
        121030254141002,
        121030254141052,
        121030245071022,
        121030254141005,
        121030254141039,
        121030254141050,
        121030245071023,
        121030254141021,
        121030254141003,
        121030254141013,
        121030245071027,
        121030254141048,
        121030254141022,
        121030245071026,
        121030245071028,
        121030254141008,
        121030254141011,
        121030254141026,
        121030254141015,
        121030254141023,
        121030254141014,
        121030254141001,
        121030254141038,
        121030254141007,
        121030254141000,
        121030254141006,
        121030245071025
    ],
    "zs:housing10":629,
    "zs:label":"Whitney Lakes",
    "zs:pop10":713
},
  "geometry": {"coordinates":[-82.733692,27.925966],"type":"Point"}
}