{
  "type": "Feature",
  "properties": {
    "gn:admin1_code":"NY",
    "gn:admin2_code":"77.0",
    "gn:admin3_code":"55629.0",
    "gn:asciiname":"Otsdawa",
    "gn:country_code":"US",
    "gn:dem":435,
    "gn:elevation":"431.0",
    "gn:feature_class":"P",
    "gn:feature_code":"PPL",
    "gn:name":"Otsdawa",
    "gn:population":0,
    "gn:timezone":"America/New_York",
    "iso:country":"US",
    "wof:name":"Otsdawa",
    "wof:placetype":"locality"
},
  "geometry": {"coordinates":[-75.17433,42.4848],"type":"Point"}
}