{
  "type": "Feature",
  "properties": {
    "gn:admin1_code":"MO",
    "gn:admin2_code":"143.0",
    "gn:admin3_code":"52094.0",
    "gn:asciiname":"La Forge",
    "gn:country_code":"US",
    "gn:dem":92,
    "gn:elevation":"92.0",
    "gn:feature_class":"P",
    "gn:feature_code":"PPL",
    "gn:name":"La Forge",
    "gn:population":0,
    "gn:timezone":"America/Chicago",
    "iso:country":"US",
    "name:deu_x_preferred":[
        "La Forge"
    ],
    "name:fra_x_preferred":[
        "La Forge"
    ],
    "wof:name":"La Forge",
    "wof:placetype":"locality"
},
  "geometry": {"coordinates":[-89.52563000000001,36.67145],"type":"Point"}
}