{
  "type": "Feature",
  "properties": {
    "gn:admin1_code":"TN",
    "gn:admin2_code":"79",
    "gn:asciiname":"Osage",
    "gn:country_code":"US",
    "gn:dem":178,
    "gn:elevation":"177.0",
    "gn:feature_class":"P",
    "gn:feature_code":"PPL",
    "gn:name":"Osage",
    "gn:population":0,
    "gn:timezone":"America/Chicago",
    "iso:country":"US",
    "name:ara_x_preferred":[
        "\u0623\u0648\u0633\u0627\u062c"
    ],
    "name:ben_x_preferred":[
        "\u0993\u09b8\u09c7\u099c"
    ],
    "name:cat_x_preferred":[
        "Osage"
    ],
    "name:ceb_x_preferred":[
        "Osage"
    ],
    "name:deu_x_preferred":[
        "Osage"
    ],
    "name:ell_x_preferred":[
        "\u039f\u03c3\u03ac\u03b6"
    ],
    "name:fas_x_preferred":[
        "\u0627\u0648\u0633\u0627\u0698"
    ],
    "name:fra_x_preferred":[
        "Osage"
    ],
    "name:heb_x_preferred":[
        "\u05d0\u05d5\u05e1\u05d0\u05d2'"
    ],
    "name:hin_x_preferred":[
        "\u0913\u0938\u0947\u091c"
    ],
    "name:hun_x_preferred":[
        "Osage"
    ],
    "name:ind_x_preferred":[
        "Osage"
    ],
    "name:ita_x_preferred":[
        "Osage"
    ],
    "name:kor_x_preferred":[
        "\uc624\uc0ac\uc8fc"
    ],
    "name:nld_x_preferred":[
        "Osage"
    ],
    "name:pol_x_preferred":[
        "Osage"
    ],
    "name:por_x_preferred":[
        "Osage"
    ],
    "name:rus_x_preferred":[
        "\u041e\u0441\u0435\u0439\u0434\u0436"
    ],
    "name:srp_x_preferred":[
        "\u041e\u0441\u0435\u0458\u045f"
    ],
    "name:swe_x_preferred":[
        "Osage River"
    ],
    "name:tur_x_preferred":[
        "Osage"
    ],
    "name:ukr_x_preferred":[
        "\u041e\u0441\u0430\u0433\u0435"
    ],
    "name:urd_x_preferred":[
        "\u0627\u0648\u0633\u06cc\u062c"
    ],
    "name:vie_x_preferred":[
        "S\u00f4ng Osage"
    ],
    "name:vol_x_preferred":[
        "Osage"
    ],
    "wof:name":"Osage",
    "wof:placetype":"locality"
},
  "geometry": {"coordinates":[-88.41171,36.35589],"type":"Point"}
}