{
  "type": "Feature",
  "properties": {
    "gn:admin1_code":"TN",
    "gn:admin2_code":"79",
    "gn:asciiname":"Osage",
    "gn:country_code":"US",
    "gn:dem":178,
    "gn:elevation":"177.0",
    "gn:feature_class":"P",
    "gn:feature_code":"PPL",
    "gn:name":"Osage",
    "gn:population":0,
    "gn:timezone":"America/Chicago",
    "iso:country":"US",
    "name:cat_x_preferred":[
        "Osage"
    ],
    "name:ceb_x_preferred":[
        "Osage"
    ],
    "name:deu_x_preferred":[
        "Osage"
    ],
    "name:fra_x_preferred":[
        "Osage"
    ],
    "name:hun_x_preferred":[
        "Osage"
    ],
    "name:ita_x_preferred":[
        "Osage"
    ],
    "name:nld_x_preferred":[
        "Osage"
    ],
    "name:pol_x_preferred":[
        "Osage"
    ],
    "name:por_x_preferred":[
        "Osage"
    ],
    "name:rus_x_preferred":[
        "\u041e\u0441\u0435\u0439\u0434\u0436"
    ],
    "name:srp_x_preferred":[
        "\u041e\u0441\u0435\u0458\u045f"
    ],
    "name:vol_x_preferred":[
        "Osage"
    ],
    "wof:name":"Osage",
    "wof:placetype":"locality"
},
  "geometry": {"coordinates":[-88.41171,36.35589],"type":"Point"}
}