{
  "type": "Feature",
  "properties": {
    "gn:admin1_code":"SD",
    "gn:admin2_code":"79.0",
    "gn:admin3_code":"22780.0",
    "gn:asciiname":"Rustic Acres Colony",
    "gn:country_code":"US",
    "gn:dem":527,
    "gn:elevation":"528.0",
    "gn:feature_class":"P",
    "gn:feature_code":"PPL",
    "gn:name":"Rustic Acres Colony",
    "gn:population":0,
    "gn:timezone":"America/Chicago",
    "iso:country":"US",
    "wof:name":"Rustic Acres Colony",
    "wof:placetype":"locality"
},
  "geometry": {"coordinates":[-97.09084,43.87177],"type":"Point"}
}