{
  "type": "Feature",
  "properties": {
    "iso:country":"US",
    "name:arz_x_preferred":[
        "\u0627\u0631\u0643\u064a\u0628\u0627\u0644\u062f \u064a\u0644"
    ],
    "name:ast_x_preferred":[
        "Archibald Yell"
    ],
    "name:azb_x_preferred":[
        "\u0622\u0631\u0686\u06cc\u0628\u0627\u0644\u062f \u06cc\u0644"
    ],
    "name:cat_x_preferred":[
        "Archibald Yell"
    ],
    "name:ces_x_preferred":[
        "Archibald Yell"
    ],
    "name:dag_x_preferred":[
        "Archibald Yell"
    ],
    "name:dan_x_preferred":[
        "Archibald Yell"
    ],
    "name:deu_x_preferred":[
        "Archibald Yell"
    ],
    "name:eng_x_preferred":[
        "Archibald Yell"
    ],
    "name:fin_x_preferred":[
        "Archibald Yell"
    ],
    "name:fra_x_preferred":[
        "Archibald Yell"
    ],
    "name:gle_x_preferred":[
        "Archibald Yell"
    ],
    "name:hun_x_preferred":[
        "Archibald Yell"
    ],
    "name:ita_x_preferred":[
        "Archibald Yell"
    ],
    "name:jpn_x_preferred":[
        "\u30a2\u30fc\u30c1\u30dc\u30eb\u30c9\u30fb\u30a4\u30a7\u30eb"
    ],
    "name:jpn_x_variant":[
        "\u30a2\u30fc\u30c1\u30dc\u30eb\u30c9\u30fb\u30a4\u30a7\u30fc\u30eb"
    ],
    "name:ltz_x_preferred":[
        "Archibald Yell"
    ],
    "name:nds_x_preferred":[
        "Archibald Yell"
    ],
    "name:nld_x_preferred":[
        "Archibald Yell"
    ],
    "name:nno_x_preferred":[
        "Archibald Yell"
    ],
    "name:nob_x_preferred":[
        "Archibald Yell"
    ],
    "name:pap_x_preferred":[
        "Archibald Yell"
    ],
    "name:pol_x_preferred":[
        "Archibald Yell"
    ],
    "name:por_x_preferred":[
        "Archibald Yell"
    ],
    "name:slv_x_preferred":[
        "Archibald Yell"
    ],
    "name:spa_x_preferred":[
        "Archibald Yell"
    ],
    "name:sqi_x_preferred":[
        "Archibald Yell"
    ],
    "name:swe_x_preferred":[
        "Archibald Yell"
    ],
    "name:yor_x_preferred":[
        "Archibald Yell"
    ],
    "name:zho_x_preferred":[
        "\u963f\u5947\u535a\u5c14\u5fb7\u00b7\u8036\u723e"
    ],
    "wd:wordcount":861,
    "wof:name":"Archibald Yell",
    "wof:placetype":"neighbourhood",
    "wof:population":98,
    "zs:area_m":477808.785855,
    "zs:blockids":[
        51430111013002,
        51430111011026,
        51430111011027,
        51430111012023,
        51430111011028,
        51430111012022,
        51430111013003
    ],
    "zs:housing10":31,
    "zs:label":"Archibald Yell",
    "zs:pop10":98
},
  "geometry": {"coordinates":[-94.16309200000001,36.046412],"type":"Point"}
}