{
  "type": "Feature",
  "properties": {
    "iso:country":"US",
    "name:eng_x_preferred":[
        "Edison Beach House"
    ],
    "qs:gn_adm0_cc":"US",
    "qs:gn_local":4155996,
    "qs:gn_nam_loc":"Fort Myers Beach, Lee, Florida, US",
    "qs:gn_namadm1":"FL",
    "qs:local_max":1285,
    "qs:local_sum":4484,
    "qs:localhoods":12,
    "qs:name":"Edison Beach House",
    "qs:name_adm0":"United States",
    "qs:name_adm1":"Florida",
    "qs:name_adm2":"Lee",
    "qs:name_local":"Fort Myers Beach",
    "qs:photo_max":50,
    "qs:photo_sum":76,
    "qs:placetype":"Suburb",
    "qs:quad_count":3,
    "qs:woe_adm0":23424977,
    "qs:woe_adm1":2347568,
    "qs:woe_adm2":12587838,
    "qs:woe_lau":0,
    "qs:woe_local":2405875,
    "qs:woe_ver":"7.10.0",
    "wof:lang":[
        "eng"
    ],
    "wof:name":"Edison Beach House",
    "wof:placetype":"neighbourhood",
    "zs:blockids":[
        120710601021003
    ],
    "zs:housing10":0,
    "zs:pop10":0
},
  "geometry": {"coordinates":[-81.959874,26.454211],"type":"Point"}
}