{
  "type": "Feature",
  "properties": {
    "iso:country":"US",
    "name:eng_x_preferred":[
        "Haines Corner"
    ],
    "wof:name":"Haines Corner",
    "wof:placetype":"neighbourhood",
    "wof:population":266,
    "zs:area_m":145071.540797,
    "zs:blockids":[
        340210043101009
    ],
    "zs:housing10":165,
    "zs:label":"Haines Corner",
    "zs:pop10":266
},
  "geometry": {"coordinates":[-74.630223,40.219942],"type":"Point"}
}