{
  "type": "Feature",
  "properties": {
    "iso:country":"US",
    "name:eng_x_preferred":[
        "Hidden Cove Number 3"
    ],
    "wof:name":"Hidden Cove Number 3",
    "wof:placetype":"neighbourhood",
    "wof:population":164,
    "zs:area_m":147144.332931,
    "zs:blockids":[
        490351135143001,
        490351135143002
    ],
    "zs:housing10":66,
    "zs:label":"Hidden Cove Number 3",
    "zs:pop10":164
},
  "geometry": {"coordinates":[-111.91811300000001,40.671902],"type":"Point"}
}