{
  "type": "Feature",
  "properties": {
    "gn:admin1_code":"VA",
    "gn:admin2_code":"47",
    "gn:asciiname":"Whitestone Estates",
    "gn:country_code":"US",
    "gn:dem":151,
    "gn:elevation":"152.0",
    "gn:feature_class":"P",
    "gn:feature_code":"PPL",
    "gn:name":"Whitestone Estates",
    "gn:population":0,
    "gn:timezone":"America/New_York",
    "iso:country":"US",
    "wof:name":"Whitestone Estates",
    "wof:placetype":"locality"
},
  "geometry": {"coordinates":[-78.07778,38.42985],"type":"Point"}
}