{
  "type": "Feature",
  "properties": {
    "gn:admin1_code":"SD",
    "gn:admin2_code":"71.0",
    "gn:admin3_code":"59856.0",
    "gn:asciiname":"Long Valley",
    "gn:country_code":"US",
    "gn:dem":813,
    "gn:elevation":"813.0",
    "gn:feature_class":"P",
    "gn:feature_code":"PPL",
    "gn:name":"Long Valley",
    "gn:population":0,
    "gn:timezone":"America/Denver",
    "iso:country":"US",
    "name:eng_x_preferred":[
        "Long Valley"
    ],
    "name:und_x_variant":[
        "Longvalley"
    ],
    "wof:name":"Long Valley",
    "wof:placetype":"locality"
},
  "geometry": {"coordinates":[-101.49487000000001,43.46167],"type":"Point"}
}