{
  "type": "Feature",
  "properties": {
    "gn:admin1_code":"FL",
    "gn:admin2_code":"97.0",
    "gn:asciiname":"Saint Cloud Trailer Park",
    "gn:country_code":"US",
    "gn:dem":29,
    "gn:elevation":"23.0",
    "gn:feature_class":"P",
    "gn:feature_code":"PPL",
    "gn:name":"Saint Cloud Trailer Park",
    "gn:population":0,
    "gn:timezone":"America/New_York",
    "iso:country":"US",
    "wof:name":"Saint Cloud Trailer Park",
    "wof:placetype":"campus"
},
  "geometry": {"coordinates":[-81.27001,28.24651],"type":"Point"}
}