{
  "type": "Feature",
  "properties": {
    "gn:admin1_code":"OH",
    "gn:admin2_code":"153.0",
    "gn:asciiname":"Hillcrest Highlands",
    "gn:country_code":"US",
    "gn:dem":327,
    "gn:elevation":"326.0",
    "gn:feature_class":"P",
    "gn:feature_code":"PPL",
    "gn:name":"Hillcrest Highlands",
    "gn:population":0,
    "gn:timezone":"America/New_York",
    "iso:country":"US",
    "wof:name":"Hillcrest Highlands",
    "wof:placetype":"locality"
},
  "geometry": {"coordinates":[-81.50839999999999,40.9804],"type":"Point"}
}