{
  "type": "Feature",
  "properties": {
    "iso:country":"US",
    "name:eng_x_preferred":[
        "Morrills Corner"
    ],
    "name:eng_x_variant":[
        "Morrills Cor"
    ],
    "name:und_x_variant":[
        "Morrill's Corner"
    ],
    "qs:gn_adm0_cc":"US",
    "qs:gn_fcode":"PPL",
    "qs:gn_local":4975603,
    "qs:gn_nam_loc":"weeks mills",
    "qs:gn_namadm1":"ME",
    "qs:gn_name":"Morrills Corner",
    "qs:local_max":12027,
    "qs:local_sum":30761,
    "qs:localhoods":27,
    "qs:name":"Morrills Corner",
    "qs:name_adm0":"United States",
    "qs:name_adm1":"Maine",
    "qs:name_adm2":"Cumberland",
    "qs:name_local":"Portland",
    "qs:photo_max":75,
    "qs:photo_sum":92,
    "qs:placetype":"Suburb",
    "qs:quad_count":3,
    "qs:woe_adm0":23424977,
    "qs:woe_adm1":2347578,
    "qs:woe_adm2":12588662,
    "qs:woe_funk":"Parented by a neighborhood",
    "qs:woe_lau":0,
    "qs:woe_local":2475688,
    "qs:woe_ver":"7.10.0",
    "wof:lang":[
        "eng"
    ],
    "wof:name":"Morrills Corner",
    "wof:placetype":"neighbourhood"
},
  "geometry": {"coordinates":[-70.300605,43.687289],"type":"Point"}
}