{
  "type": "Feature",
  "properties": {
    "gn:admin1_code":"NC",
    "gn:admin2_code":"139",
    "gn:admin3_code":"92576.0",
    "gn:asciiname":"Amarest Manor Mobile Home Park",
    "gn:country_code":"US",
    "gn:dem":2,
    "gn:elevation":"2.0",
    "gn:feature_class":"P",
    "gn:feature_code":"PPL",
    "gn:name":"Amarest Manor Mobile Home Park",
    "gn:population":0,
    "gn:timezone":"America/New_York",
    "iso:country":"US",
    "wof:name":"Amarest Manor Mobile Home Park",
    "wof:placetype":"campus"
},
  "geometry": {"coordinates":[-76.22450000000001,36.333],"type":"Point"}
}