{
  "type": "Feature",
  "properties": {
    "gn:admin1_code":"MD",
    "gn:admin2_code":"21.0",
    "gn:asciiname":"Gallagher Estates",
    "gn:country_code":"US",
    "gn:dem":157,
    "gn:elevation":"161.0",
    "gn:feature_class":"P",
    "gn:feature_code":"PPL",
    "gn:name":"Gallagher Estates",
    "gn:population":0,
    "gn:timezone":"America/New_York",
    "iso:country":"US",
    "wof:name":"Gallagher Estates",
    "wof:placetype":"locality"
},
  "geometry": {"coordinates":[-77.19165,39.43149],"type":"Point"}
}