{
  "type": "Feature",
  "properties": {
    "gn:admin1_code":"MO",
    "gn:admin2_code":"123.0",
    "gn:admin3_code":"42212.0",
    "gn:asciiname":"Jewett",
    "gn:country_code":"US",
    "gn:dem":160,
    "gn:elevation":"159.0",
    "gn:feature_class":"P",
    "gn:feature_code":"PPL",
    "gn:name":"Jewett",
    "gn:population":0,
    "gn:timezone":"America/Chicago",
    "iso:country":"US",
    "name:cat_x_preferred":[
        "Jewett"
    ],
    "name:ceb_x_preferred":[
        "Jewett"
    ],
    "name:deu_x_preferred":[
        "Jewett"
    ],
    "name:ita_x_preferred":[
        "Jewett"
    ],
    "name:nld_x_preferred":[
        "Jewett"
    ],
    "name:pol_x_preferred":[
        "Jewett"
    ],
    "name:srp_x_preferred":[
        "\u040f\u0443\u0435\u0442"
    ],
    "name:ukr_x_preferred":[
        "\u0414\u0436\u044e\u0435\u0442\u0442"
    ],
    "name:vol_x_preferred":[
        "Jewett"
    ],
    "wof:name":"Jewett",
    "wof:placetype":"locality"
},
  "geometry": {"coordinates":[-90.50151,37.38033],"type":"Point"}
}