{
  "type": "Feature",
  "properties": {
    "gn:admin1_code":"CA",
    "gn:admin2_code":"7",
    "gn:asciiname":"East Biggs",
    "gn:country_code":"US",
    "gn:dem":35,
    "gn:elevation":"37.0",
    "gn:feature_class":"P",
    "gn:feature_code":"PPL",
    "gn:name":"East Biggs",
    "gn:population":0,
    "gn:timezone":"America/Los_Angeles",
    "iso:country":"US",
    "name:ara_x_preferred":[
        "\u0634\u0631\u0642 \u0628\u064a\u062c\u0632"
    ],
    "name:eng_x_preferred":[
        "East Biggs"
    ],
    "name:fas_x_preferred":[
        "\u0627\u06cc\u0633\u062a \u0628\u06cc\u06af\u0632"
    ],
    "name:und_x_variant":[
        "Rio Bonito"
    ],
    "name:zho_x_preferred":[
        "\u6771\u6bd4\u683c\u65af"
    ],
    "wof:name":"East Biggs",
    "wof:placetype":"locality"
},
  "geometry": {"coordinates":[-121.65385999999999,39.41517],"type":"Point"}
}