{
  "type": "Feature",
  "properties": {
    "gn:admin1_code":"GA",
    "gn:admin2_code":"151.0",
    "gn:asciiname":"Circle Creek",
    "gn:country_code":"US",
    "gn:dem":236,
    "gn:elevation":"225.0",
    "gn:feature_class":"P",
    "gn:feature_code":"PPL",
    "gn:name":"Circle Creek",
    "gn:population":0,
    "gn:timezone":"America/New_York",
    "iso:country":"US",
    "wof:name":"Circle Creek",
    "wof:placetype":"locality"
},
  "geometry": {"coordinates":[-84.19381,33.5665],"type":"Point"}
}