{
  "type": "Feature",
  "properties": {
    "gn:admin1_code":"MD",
    "gn:admin2_code":"5.0",
    "gn:asciiname":"Kings Court",
    "gn:country_code":"US",
    "gn:dem":25,
    "gn:elevation":"28.0",
    "gn:feature_class":"P",
    "gn:feature_code":"PPL",
    "gn:name":"Kings Court",
    "gn:population":0,
    "gn:timezone":"America/New_York",
    "iso:country":"US",
    "wof:name":"Kings Court",
    "wof:placetype":"locality"
},
  "geometry": {"coordinates":[-76.46468,39.35733],"type":"Point"}
}