{
  "type": "Feature",
  "properties": {
    "gn:country":"US",
    "gn:fcode":"PPL",
    "gn:population":263,
    "iso:country":"US",
    "name:bre_x_preferred":[
        "Argyle"
    ],
    "name:cat_x_preferred":[
        "Argyle"
    ],
    "name:ceb_x_preferred":[
        "Argyle"
    ],
    "name:ces_x_preferred":[
        "Argyle"
    ],
    "name:deu_x_preferred":[
        "Argyle"
    ],
    "name:fra_x_preferred":[
        "Argyle"
    ],
    "name:ita_x_preferred":[
        "Argyle"
    ],
    "name:jpn_x_preferred":[
        "\u30a2\u30fc\u30ac\u30a4\u30eb"
    ],
    "name:nld_x_preferred":[
        "Argyle"
    ],
    "name:pol_x_preferred":[
        "Argyle"
    ],
    "name:por_x_preferred":[
        "Argyle"
    ],
    "name:spa_x_preferred":[
        "Argyle"
    ],
    "name:srp_x_preferred":[
        "\u0410\u0440\u0433\u0430\u0458\u043b"
    ],
    "name:swe_x_preferred":[
        "Argyle"
    ],
    "name:vol_x_preferred":[
        "Argyle"
    ],
    "qs_pg:aaroncc":"US",
    "qs_pg:gn_country":"US",
    "qs_pg:gn_fcode":"PPL",
    "qs_pg:gn_pop":263,
    "qs_pg:name":"Argyle",
    "qs_pg:name_adm0":"United States",
    "qs_pg:name_adm1":"Maine",
    "qs_pg:photos_9k":1,
    "qs_pg:photos_9r":1,
    "qs_pg:photos_all":1,
    "qs_pg:photos_sr":0,
    "qs_pg:pop_sr":2,
    "qs_pg:qs_pg_placetype":"locality",
    "qs_pg:qs_pg_placetype_gp":"Town",
    "qs_pg:woe_adm0":23424977,
    "woe:adm0_id":23424977,
    "woe:name_adm0":"United States",
    "woe:name_adm1":"Maine",
    "woe:placetype":"Town",
    "wof:name":"Argyle",
    "wof:placetype":"locality",
    "wof:population":263
},
  "geometry": {"coordinates":[-68.67225000000001,45.05423],"type":"Point"}
}