{
  "type": "Feature",
  "properties": {
    "gn:admin1_code":"CO",
    "gn:admin2_code":"23.0",
    "gn:asciiname":"Russell",
    "gn:country_code":"US",
    "gn:dem":2566,
    "gn:elevation":"2569.0",
    "gn:feature_class":"P",
    "gn:feature_code":"PPL",
    "gn:name":"Russell",
    "gn:population":0,
    "gn:timezone":"America/Denver",
    "iso:country":"US",
    "name:bel_x_preferred":[
        "\u0420\u0430\u0441\u0435\u043b"
    ],
    "name:bul_x_preferred":[
        "\u0420\u044a\u0441\u0435\u043b"
    ],
    "name:cat_x_preferred":[
        "Russell"
    ],
    "name:ceb_x_preferred":[
        "Russell"
    ],
    "name:ces_x_preferred":[
        "Russell"
    ],
    "name:dan_x_preferred":[
        "Russell"
    ],
    "name:deu_x_preferred":[
        "Russell"
    ],
    "name:eng_x_preferred":[
        "Russell"
    ],
    "name:eus_x_preferred":[
        "Russell"
    ],
    "name:fas_x_preferred":[
        "\u0631\u0627\u0633\u0644"
    ],
    "name:fin_x_preferred":[
        "Russell"
    ],
    "name:fra_x_preferred":[
        "Russell"
    ],
    "name:heb_x_preferred":[
        "\u05e8\u05d0\u05e1\u05dc"
    ],
    "name:hun_x_preferred":[
        "Russell"
    ],
    "name:ita_x_preferred":[
        "Russell"
    ],
    "name:jpn_x_preferred":[
        "\u30e9\u30c3\u30bb\u30eb"
    ],
    "name:lav_x_preferred":[
        "Rasels"
    ],
    "name:nld_x_preferred":[
        "Russell"
    ],
    "name:nor_x_preferred":[
        "Russell"
    ],
    "name:pol_x_preferred":[
        "Russell"
    ],
    "name:por_x_preferred":[
        "Russell"
    ],
    "name:rus_x_preferred":[
        "\u0420\u0430\u0441\u0441\u0435\u043b\u043b"
    ],
    "name:slv_x_preferred":[
        "Russell"
    ],
    "name:spa_x_preferred":[
        "Russell"
    ],
    "name:srp_x_preferred":[
        "\u0420\u0430\u0441\u0435\u043b"
    ],
    "name:swe_x_preferred":[
        "Russell"
    ],
    "name:ukr_x_preferred":[
        "\u0420\u0430\u0441\u0441\u0435\u043b\u043b"
    ],
    "name:und_x_variant":[
        "Placer"
    ],
    "name:vie_x_preferred":[
        "Russell"
    ],
    "name:vol_x_preferred":[
        "Russell"
    ],
    "wof:name":"Russell",
    "wof:placetype":"locality"
},
  "geometry": {"coordinates":[-105.28778,37.55529],"type":"Point"}
}