{
  "type": "Feature",
  "properties": {
    "gn:admin1_code":"GA",
    "gn:admin2_code":"97.0",
    "gn:asciiname":"Creek Indian",
    "gn:country_code":"US",
    "gn:dem":253,
    "gn:elevation":"237.0",
    "gn:feature_class":"P",
    "gn:feature_code":"PPL",
    "gn:name":"Creek Indian",
    "gn:population":0,
    "gn:timezone":"America/New_York",
    "iso:country":"US",
    "wof:name":"Creek Indian",
    "wof:placetype":"locality"
},
  "geometry": {"coordinates":[-84.69438000000002,33.65844],"type":"Point"}
}