{
  "type": "Feature",
  "properties": {
    "gn:admin1_code":"AL",
    "gn:admin2_code":"33.0",
    "gn:asciiname":"Spring Valley",
    "gn:country_code":"US",
    "gn:dem":159,
    "gn:elevation":"156.0",
    "gn:feature_class":"P",
    "gn:feature_code":"PPL",
    "gn:name":"Spring Valley",
    "gn:population":0,
    "gn:timezone":"America/Chicago",
    "iso:country":"US",
    "name:fas_x_preferred":[
        "\u0627\u0633\u067e\u0631\u06cc\u0646\u06af \u0648\u0644\u06cc"
    ],
    "name:zho_x_preferred":[
        "\u65af\u666e\u6797\u74e6\u5229"
    ],
    "wof:name":"Spring Valley",
    "wof:placetype":"locality"
},
  "geometry": {"coordinates":[-87.61669999999999,34.65676],"type":"Point"}
}