{
  "type": "Feature",
  "properties": {
    "gn:admin1_code":"GA",
    "gn:admin2_code":"113.0",
    "gn:asciiname":"Morning Creek Estates",
    "gn:country_code":"US",
    "gn:dem":259,
    "gn:elevation":"251.0",
    "gn:feature_class":"P",
    "gn:feature_code":"PPL",
    "gn:name":"Morning Creek Estates",
    "gn:population":0,
    "gn:timezone":"America/New_York",
    "iso:country":"US",
    "wof:name":"Morning Creek Estates",
    "wof:placetype":"locality"
},
  "geometry": {"coordinates":[-84.45048,33.50956],"type":"Point"}
}