{
  "type": "Feature",
  "properties": {
    "gn:admin1_code":"MA",
    "gn:admin2_code":"15.0",
    "gn:admin3_code":"4825.0",
    "gn:asciiname":"Highland Glen Estates",
    "gn:country_code":"US",
    "gn:dem":169,
    "gn:elevation":"166.0",
    "gn:feature_class":"P",
    "gn:feature_code":"PPL",
    "gn:name":"Highland Glen Estates",
    "gn:population":0,
    "gn:timezone":"America/New_York",
    "iso:country":"US",
    "wof:name":"Highland Glen Estates",
    "wof:placetype":"locality"
},
  "geometry": {"coordinates":[-72.41230999999998,42.28398],"type":"Point"}
}