{
  "type": "Feature",
  "properties": {
    "iso:country":"US",
    "name:deu_x_preferred":[
        "Bratcher"
    ],
    "name:eng_x_preferred":[
        "Bratcher"
    ],
    "name:ind_x_preferred":[
        "Bratcher"
    ],
    "name:nld_x_preferred":[
        "Bratcher"
    ],
    "name:spa_x_preferred":[
        "Bratcher"
    ],
    "wd:wordcount":27,
    "wof:name":"Bratcher",
    "wof:placetype":"neighbourhood",
    "wof:population":734,
    "zs:area_m":577867.492516,
    "zs:blockids":[
        484530018582064,
        484530018582019,
        484530018582012,
        484530018582006,
        484530018584031,
        484530018582020,
        484530018582018,
        484530018582009,
        484530018582005,
        484530018582004,
        484530018582021,
        484530018582007,
        484530018582010
    ],
    "zs:housing10":215,
    "zs:label":"Bratcher",
    "zs:pop10":734
},
  "geometry": {"coordinates":[-97.578626,30.46172],"type":"Point"}
}