{
  "type": "Feature",
  "properties": {
    "gn:admin1_code":"AR",
    "gn:admin2_code":"7.0",
    "gn:admin3_code":"93628.0",
    "gn:asciiname":"Cross Hollow",
    "gn:country_code":"US",
    "gn:dem":382,
    "gn:elevation":"372.0",
    "gn:feature_class":"P",
    "gn:feature_code":"PPL",
    "gn:name":"Cross Hollow",
    "gn:population":0,
    "gn:timezone":"America/Chicago",
    "iso:country":"US",
    "name:eng_x_preferred":[
        "Cross Hollow"
    ],
    "name:und_x_variant":[
        "Cross Hollows Station",
        "Limedale",
        "Stony Point",
        "Cross Hollows"
    ],
    "wof:name":"Cross Hollow",
    "wof:placetype":"locality"
},
  "geometry": {"coordinates":[-94.11326,36.27841],"type":"Point"}
}