{
  "type": "Feature",
  "properties": {
    "gn:admin1_code":"TN",
    "gn:admin2_code":"145.0",
    "gn:asciiname":"Riverbend Estates",
    "gn:country_code":"US",
    "gn:dem":255,
    "gn:elevation":"245.0",
    "gn:feature_class":"P",
    "gn:feature_code":"PPL",
    "gn:name":"Riverbend Estates",
    "gn:population":0,
    "gn:timezone":"America/New_York",
    "iso:country":"US",
    "wof:name":"Riverbend Estates",
    "wof:placetype":"locality"
},
  "geometry": {"coordinates":[-84.46104,35.88619],"type":"Point"}
}