{
  "type": "Feature",
  "properties": {
    "gn:country":"US",
    "gn:fcode":"ADMD",
    "gn:population":0,
    "iso:country":"US",
    "name:ara_x_preferred":[
        "\u0647\u0648\u0631\u064a\u0643\u0648\u0646"
    ],
    "name:che_x_preferred":[
        "\u0413\u043e\u0440\u0438\u043a\u043e\u043d"
    ],
    "name:deu_x_preferred":[
        "Horicon"
    ],
    "name:eng_x_preferred":[
        "Horicon"
    ],
    "name:eus_x_preferred":[
        "Horicon"
    ],
    "name:fra_x_preferred":[
        "Horicon"
    ],
    "name:hat_x_preferred":[
        "Horicon"
    ],
    "name:hun_x_preferred":[
        "Horicon"
    ],
    "name:pol_x_preferred":[
        "Horicon"
    ],
    "name:spa_x_preferred":[
        "Horicon"
    ],
    "name:swe_x_preferred":[
        "Horicon"
    ],
    "name:tat_x_preferred":[
        "\u0413\u043e\u0440\u0438\u043a\u043e\u043d"
    ],
    "name:ukr_x_preferred":[
        "\u0413\u043e\u0440\u0456\u043a\u043e\u043d"
    ],
    "name:uzb_x_preferred":[
        "Horicon"
    ],
    "qs_pg:aaroncc":"US",
    "qs_pg:gn_country":"US",
    "qs_pg:gn_fcode":"ADMD",
    "qs_pg:gn_pop":0,
    "qs_pg:name":"Horicon",
    "qs_pg:name_adm0":"United States",
    "qs_pg:name_adm1":"New York",
    "qs_pg:photos":6,
    "qs_pg:photos_1k":1,
    "qs_pg:photos_9k":1,
    "qs_pg:photos_9r":3,
    "qs_pg:photos_all":85,
    "qs_pg:photos_sr":1,
    "qs_pg:pop_sr":0,
    "qs_pg:qs_pg_placetype":"locality",
    "qs_pg:qs_pg_placetype_gp":"Town",
    "qs_pg:woe_adm0":23424977,
    "woe:adm0_id":23424977,
    "woe:name_adm0":"United States",
    "woe:name_adm1":"New York",
    "woe:placetype":"Town",
    "wof:coterminous":[
        404523287
    ],
    "wof:name":"Horicon",
    "wof:placetype":"locality",
    "wof:population":1365,
    "wof:statistical_gore":1
},
  "geometry": {"coordinates":[-73.71124,43.7034],"type":"Point"}
}