{
  "type": "Feature",
  "properties": {
    "gn:admin1_code":"AL",
    "gn:admin2_code":"127",
    "gn:asciiname":"Bradleytown",
    "gn:country_code":"US",
    "gn:dem":131,
    "gn:elevation":"127.0",
    "gn:feature_class":"P",
    "gn:feature_code":"PPL",
    "gn:name":"Bradleytown",
    "gn:population":0,
    "gn:timezone":"America/Chicago",
    "iso:country":"US",
    "wof:name":"Bradleytown",
    "wof:placetype":"locality"
},
  "geometry": {"coordinates":[-87.24916999999998,33.70011],"type":"Point"}
}