{
  "type": "Feature",
  "properties": {
    "gn:admin1_code":"WY",
    "gn:admin2_code":"33.0",
    "gn:asciiname":"Leiter",
    "gn:country_code":"US",
    "gn:dem":1149,
    "gn:elevation":"1152.0",
    "gn:feature_class":"P",
    "gn:feature_code":"PPL",
    "gn:name":"Leiter",
    "gn:population":0,
    "gn:timezone":"America/Denver",
    "iso:country":"US",
    "wof:name":"Leiter",
    "wof:placetype":"locality"
},
  "geometry": {"coordinates":[-106.2692,44.71804],"type":"Point"}
}