{
  "type": "Feature",
  "properties": {
    "gn:admin1_code":"OH",
    "gn:admin2_code":"41.0",
    "gn:admin3_code":"58618.0",
    "gn:asciiname":"Walnut Woods",
    "gn:country_code":"US",
    "gn:dem":277,
    "gn:elevation":"269.0",
    "gn:feature_class":"P",
    "gn:feature_code":"PPL",
    "gn:name":"Walnut Woods",
    "gn:population":0,
    "gn:timezone":"America/New_York",
    "iso:country":"US",
    "wof:name":"Walnut Woods",
    "wof:placetype":"locality"
},
  "geometry": {"coordinates":[-82.94580999999999,40.18383],"type":"Point"}
}