{
  "type": "Feature",
  "properties": {
    "gn:admin1_code":"GA",
    "gn:admin2_code":"155",
    "gn:asciiname":"Riverbend",
    "gn:country_code":"US",
    "gn:dem":104,
    "gn:elevation":"99.0",
    "gn:feature_class":"P",
    "gn:feature_code":"PPL",
    "gn:name":"Riverbend",
    "gn:population":0,
    "gn:timezone":"America/New_York",
    "iso:country":"US",
    "name:ceb_x_preferred":[
        "Riverbend"
    ],
    "name:fra_x_preferred":[
        "Riverbend"
    ],
    "name:ita_x_preferred":[
        "Riverbend"
    ],
    "name:nld_x_preferred":[
        "Riverbend"
    ],
    "name:pol_x_preferred":[
        "Riverbend"
    ],
    "name:por_x_preferred":[
        "Riverbend"
    ],
    "name:srp_x_preferred":[
        "\u0420\u0438\u0432\u0435\u0440\u0431\u0435\u043d\u0434"
    ],
    "name:vol_x_preferred":[
        "Riverbend"
    ],
    "wof:name":"Riverbend",
    "wof:placetype":"locality"
},
  "geometry": {"coordinates":[-83.26321,31.49075],"type":"Point"}
}