{
  "type": "Feature",
  "properties": {
    "gn:admin1_code":"SC",
    "gn:admin2_code":"41.0",
    "gn:asciiname":"Perrot",
    "gn:country_code":"US",
    "gn:dem":21,
    "gn:elevation":"26.0",
    "gn:feature_class":"P",
    "gn:feature_code":"PPL",
    "gn:name":"Perrot",
    "gn:population":0,
    "gn:timezone":"America/New_York",
    "iso:country":"US",
    "name:deu_x_preferred":[
        "Perrot"
    ],
    "name:fra_x_preferred":[
        "Perrot"
    ],
    "name:heb_x_preferred":[
        "\u05e4\u05e8\u05d5"
    ],
    "name:ita_x_preferred":[
        "Perrot"
    ],
    "wof:name":"Perrot",
    "wof:placetype":"locality"
},
  "geometry": {"coordinates":[-79.59895,34.03433],"type":"Point"}
}