{
  "type": "Feature",
  "properties": {
    "gn:admin1_code":"IN",
    "gn:admin2_code":"113.0",
    "gn:admin3_code":"71756.0",
    "gn:asciiname":"Indian Village",
    "gn:country_code":"US",
    "gn:dem":271,
    "gn:elevation":"270.0",
    "gn:feature_class":"P",
    "gn:feature_code":"PPL",
    "gn:name":"Indian Village",
    "gn:population":0,
    "gn:timezone":"America/Indiana/Indianapolis",
    "iso:country":"US",
    "name:deu_x_preferred":[
        "Indian Village"
    ],
    "name:eng_x_preferred":[
        "Indian Village"
    ],
    "name:fra_x_preferred":[
        "Indian Village"
    ],
    "name:pol_x_preferred":[
        "Indian Village"
    ],
    "name:und_x_variant":[
        "Alcinda"
    ],
    "name:vol_x_preferred":[
        "Indian Village"
    ],
    "wof:name":"Indian Village",
    "wof:placetype":"locality"
},
  "geometry": {"coordinates":[-85.63943,41.36588],"type":"Point"}
}