{
  "type": "Feature",
  "properties": {
    "gn:admin1_code":"MI",
    "gn:admin2_code":"21.0",
    "gn:admin3_code":"7820.0",
    "gn:asciiname":"Fairland",
    "gn:country_code":"US",
    "gn:dem":237,
    "gn:elevation":"239.0",
    "gn:feature_class":"P",
    "gn:feature_code":"PPL",
    "gn:name":"Fairland",
    "gn:population":0,
    "gn:timezone":"America/Detroit",
    "iso:country":"US",
    "name:bar_x_preferred":[
        "Fairland"
    ],
    "name:ceb_x_preferred":[
        "Fairland"
    ],
    "name:deu_x_preferred":[
        "Fairland"
    ],
    "name:ita_x_preferred":[
        "Fairland"
    ],
    "name:nld_x_preferred":[
        "Fairland"
    ],
    "name:pol_x_preferred":[
        "Fairland"
    ],
    "name:por_x_preferred":[
        "Fairland"
    ],
    "name:rus_x_preferred":[
        "\u0424\u044d\u0440\u043b\u0435\u043d\u0434"
    ],
    "name:ukr_x_preferred":[
        "\u0424\u0435\u0439\u0440\u043b\u0435\u043d\u0434"
    ],
    "name:vol_x_preferred":[
        "Fairland"
    ],
    "wof:name":"Fairland",
    "wof:placetype":"locality"
},
  "geometry": {"coordinates":[-86.28224,41.89921],"type":"Point"}
}