{
  "type": "Feature",
  "properties": {
    "iso:country":"US",
    "name:eng_x_preferred":[
        "South Juanita"
    ],
    "qs:gn_adm0_cc":"US",
    "qs:gn_local":5799841,
    "qs:gn_nam_loc":"Kirkland, King, Washington, US",
    "qs:gn_namadm1":"WA",
    "qs:local_max":4528,
    "qs:local_sum":21278,
    "qs:localhoods":19,
    "qs:name":"South Juanita",
    "qs:name_adm0":"United States",
    "qs:name_adm1":"Washington",
    "qs:name_adm2":"King",
    "qs:name_local":"Kirkland",
    "qs:photo_max":4459,
    "qs:photo_sum":4528,
    "qs:placetype":"Suburb",
    "qs:quad_count":8,
    "qs:woe_adm0":23424977,
    "qs:woe_adm1":2347606,
    "qs:woe_adm2":12590456,
    "qs:woe_lau":0,
    "qs:woe_local":2433074,
    "qs:woe_ver":"7.10.0",
    "wof:lang":[
        "eng"
    ],
    "wof:name":"South Juanita",
    "wof:placetype":"neighbourhood",
    "wof:population":1358,
    "zs:blockids":[
        530330224001017,
        530330224001003,
        530330224001020,
        530330224001019,
        530330224001014,
        530330224001015,
        530330224001018,
        530330224001004,
        530330224001002,
        530330224002002,
        530330224001001,
        530330224001021,
        530330224001000,
        530330220061004,
        530330224001012,
        530330224001013,
        530330224001007,
        530330224001016
    ],
    "zs:housing10":732,
    "zs:pop10":1358
},
  "geometry": {"coordinates":[-122.19954,47.704734],"type":"Point"}
}