{
  "type": "Feature",
  "properties": {
    "gn:admin1_code":"KY",
    "gn:admin2_code":"141",
    "gn:asciiname":"Gasper",
    "gn:country_code":"US",
    "gn:dem":217,
    "gn:elevation":"215.0",
    "gn:feature_class":"P",
    "gn:feature_code":"PPL",
    "gn:name":"Gasper",
    "gn:population":0,
    "gn:timezone":"America/Chicago",
    "iso:country":"US",
    "name:eng_x_preferred":[
        "Gasper"
    ],
    "name:und_x_variant":[
        "Bucksville"
    ],
    "wof:name":"Gasper",
    "wof:placetype":"locality"
},
  "geometry": {"coordinates":[-86.74194,36.95004],"type":"Point"}
}