{
  "type": "Feature",
  "properties": {
    "gn:admin1_code":"TX",
    "gn:admin2_code":"61.0",
    "gn:asciiname":"Santa Elena Colonia",
    "gn:country_code":"US",
    "gn:dem":16,
    "gn:elevation":"9.0",
    "gn:feature_class":"P",
    "gn:feature_code":"PPL",
    "gn:name":"Santa Elena Colonia",
    "gn:population":0,
    "gn:timezone":"America/Chicago",
    "iso:country":"US",
    "wof:name":"Santa Elena Colonia",
    "wof:placetype":"locality"
},
  "geometry": {"coordinates":[-97.63221,26.2473],"type":"Point"}
}