{
  "type": "Feature",
  "properties": {
    "iso:country":"US",
    "name:ceb_x_preferred":[
        "Bellagio"
    ],
    "name:eng_x_preferred":[
        "Bellagio"
    ],
    "name:ita_x_preferred":[
        "Bellagio"
    ],
    "name:lav_x_preferred":[
        "Bellagio"
    ],
    "name:nld_x_preferred":[
        "Bellagio"
    ],
    "name:swe_x_preferred":[
        "Bellagio"
    ],
    "name:tha_x_preferred":[
        "Bellagio"
    ],
    "name:tur_x_preferred":[
        "Bellagio"
    ],
    "wof:name":"Bellagio",
    "wof:placetype":"neighbourhood",
    "wof:population":182,
    "zs:area_m":75156.724509,
    "zs:blockids":[
        60590320392001,
        60590320392002
    ],
    "zs:housing10":56,
    "zs:label":"Bellagio",
    "zs:pop10":182
},
  "geometry": {"coordinates":[-117.64294,33.579833],"type":"Point"}
}