{
  "type": "Feature",
  "properties": {
    "gn:admin1_code":"VA",
    "gn:admin2_code":"710",
    "gn:asciiname":"Wayside Manor",
    "gn:country_code":"US",
    "gn:dem":4,
    "gn:elevation":"4.0",
    "gn:feature_class":"P",
    "gn:feature_code":"PPL",
    "gn:name":"Wayside Manor",
    "gn:population":0,
    "gn:timezone":"America/New_York",
    "iso:country":"US",
    "wof:name":"Wayside Manor",
    "wof:placetype":"locality"
},
  "geometry": {"coordinates":[-76.20076999999998,36.83987],"type":"Point"}
}