{
  "type": "Feature",
  "properties": {
    "gn:admin1_code":"GA",
    "gn:admin2_code":"255",
    "gn:asciiname":"Rio",
    "gn:country_code":"US",
    "gn:dem":242,
    "gn:elevation":"241.0",
    "gn:feature_class":"P",
    "gn:feature_code":"PPL",
    "gn:name":"Rio",
    "gn:population":0,
    "gn:timezone":"America/New_York",
    "iso:country":"US",
    "name:ara_x_preferred":[
        "\u0631\u064a\u0648"
    ],
    "name:bre_x_preferred":[
        "Rio"
    ],
    "name:bul_x_preferred":[
        "\u0420\u0438\u043e"
    ],
    "name:cat_x_preferred":[
        "Rio"
    ],
    "name:ceb_x_preferred":[
        "Rio"
    ],
    "name:ces_x_preferred":[
        "Rio"
    ],
    "name:dan_x_preferred":[
        "Rio"
    ],
    "name:deu_x_preferred":[
        "Rio"
    ],
    "name:epo_x_preferred":[
        "Rio"
    ],
    "name:fas_x_preferred":[
        "\u0631\u06cc\u0648"
    ],
    "name:fin_x_preferred":[
        "Rio"
    ],
    "name:fra_x_preferred":[
        "Rio"
    ],
    "name:glg_x_preferred":[
        "R\u00edo"
    ],
    "name:heb_x_preferred":[
        "\u05e8\u05d9\u05d5"
    ],
    "name:hun_x_preferred":[
        "Rio"
    ],
    "name:ind_x_preferred":[
        "Rio"
    ],
    "name:lav_x_preferred":[
        "Rio"
    ],
    "name:msa_x_preferred":[
        "Rio"
    ],
    "name:nld_x_preferred":[
        "Rio"
    ],
    "name:pms_x_preferred":[
        "Rio"
    ],
    "name:pol_x_preferred":[
        "Rio"
    ],
    "name:por_x_preferred":[
        "Rio"
    ],
    "name:rus_x_preferred":[
        "Rio"
    ],
    "name:sco_x_preferred":[
        "Rio"
    ],
    "name:spa_x_preferred":[
        "R\u00edo"
    ],
    "name:srp_x_preferred":[
        "\u0420\u0438\u043e"
    ],
    "name:swe_x_preferred":[
        "Rio"
    ],
    "name:tam_x_preferred":[
        "\u0bb0\u0bbf\u0baf\u0bcb"
    ],
    "name:vol_x_preferred":[
        "Rio"
    ],
    "name:zho_x_preferred":[
        "Rio"
    ],
    "wof:name":"Rio",
    "wof:placetype":"locality"
},
  "geometry": {"coordinates":[-84.38186999999998,33.28012],"type":"Point"}
}