{
  "type": "Feature",
  "properties": {
    "gn:admin1_code":"OH",
    "gn:admin2_code":"45",
    "gn:admin3_code":"66684.0",
    "gn:asciiname":"Oakthorpe",
    "gn:country_code":"US",
    "gn:dem":277,
    "gn:elevation":"278.0",
    "gn:feature_class":"P",
    "gn:feature_code":"PPL",
    "gn:name":"Oakthorpe",
    "gn:population":0,
    "gn:timezone":"America/New_York",
    "iso:country":"US",
    "name:cym_x_preferred":[
        "Oakthorpe"
    ],
    "name:eng_x_preferred":[
        "Oakthorpe"
    ],
    "name:pol_x_preferred":[
        "Oakthorpe"
    ],
    "name:spa_x_preferred":[
        "Oakthorpe"
    ],
    "name:swe_x_preferred":[
        "Oakthorpe"
    ],
    "name:und_x_variant":[
        "Oakthorp"
    ],
    "wof:name":"Oakthorpe",
    "wof:placetype":"locality"
},
  "geometry": {"coordinates":[-82.43599,39.80562000000001],"type":"Point"}
}