{
  "type": "Feature",
  "properties": {
    "gn:admin1_code":"VA",
    "gn:admin2_code":"99",
    "gn:asciiname":"Tetotum",
    "gn:country_code":"US",
    "gn:dem":50,
    "gn:elevation":"50.0",
    "gn:feature_class":"P",
    "gn:feature_code":"PPL",
    "gn:name":"Tetotum",
    "gn:population":0,
    "gn:timezone":"America/New_York",
    "iso:country":"US",
    "name:eng_x_preferred":[
        "Tetotum"
    ],
    "name:und_x_variant":[
        "Round Hill"
    ],
    "wof:name":"Tetotum",
    "wof:placetype":"locality"
},
  "geometry": {"coordinates":[-77.04525,38.27596],"type":"Point"}
}