{
  "type": "Feature",
  "properties": {
    "gn:admin1_code":"WV",
    "gn:admin2_code":"25",
    "gn:asciiname":"Blaker Mills",
    "gn:country_code":"US",
    "gn:dem":515,
    "gn:elevation":"514.0",
    "gn:feature_class":"P",
    "gn:feature_code":"PPL",
    "gn:name":"Blaker Mills",
    "gn:population":0,
    "gn:timezone":"America/New_York",
    "iso:country":"US",
    "name:eng_x_preferred":[
        "Blaker Mills"
    ],
    "name:fas_x_preferred":[
        "\u0628\u0644\u06a9\u0631 \u0645\u06cc\u0644\u0632"
    ],
    "name:und_x_variant":[
        "Blakers Mill",
        "Lewis Mill",
        "Red Mill",
        "Blaker Mill"
    ],
    "wof:name":"Blaker Mills",
    "wof:placetype":"locality"
},
  "geometry": {"coordinates":[-80.6073,37.76179000000001],"type":"Point"}
}