{
  "type": "Feature",
  "properties": {
    "gn:country":"US",
    "gn:fcode":"PPL",
    "gn:population":0,
    "iso:country":"US",
    "name:ara_x_preferred":[
        "\u0641\u064a\u0630\u0631 \u0641\u0648\u0644\u0632"
    ],
    "name:azb_x_preferred":[
        "\u0641\u062f\u0631\u0641\u0627\u0644\u0632"
    ],
    "name:eng_x_preferred":[
        "Feather Falls"
    ],
    "name:fas_x_preferred":[
        "\u0641\u062f\u0631\u0641\u0627\u0644\u0632"
    ],
    "name:fra_x_preferred":[
        "Feather Falls"
    ],
    "name:tur_x_preferred":[
        "Feather Falls"
    ],
    "name:und_x_variant":[
        "Mooretown"
    ],
    "name:vol_x_preferred":[
        "Feather Falls"
    ],
    "name:zho_x_preferred":[
        "\u5f17\u745f\u798f\u723e\u65af"
    ],
    "qs_pg:aaroncc":"US",
    "qs_pg:gn_country":"US",
    "qs_pg:gn_fcode":"PPL",
    "qs_pg:gn_pop":0,
    "qs_pg:name":"Feather Falls",
    "qs_pg:name_adm0":"United States",
    "qs_pg:name_adm1":"California",
    "qs_pg:photos":64,
    "qs_pg:photos_1k":13,
    "qs_pg:photos_9k":1,
    "qs_pg:photos_9r":2,
    "qs_pg:photos_all":64,
    "qs_pg:photos_sr":2,
    "qs_pg:pop_sr":5,
    "qs_pg:qs_pg_placetype":"locality",
    "qs_pg:qs_pg_placetype_gp":"Town",
    "qs_pg:woe_adm0":23424977,
    "woe:adm0_id":23424977,
    "woe:name_adm0":"United States",
    "woe:name_adm1":"California",
    "woe:placetype":"Town",
    "wof:name":"Feather Falls",
    "wof:placetype":"locality"
},
  "geometry": {"coordinates":[-121.25635,39.59322],"type":"Point"}
}