{
  "type": "Feature",
  "properties": {
    "iso:country":"US",
    "name:eng_x_preferred":[
        "Grandview Center"
    ],
    "wd:wordcount":876,
    "wof:name":"Grandview Center",
    "wof:placetype":"neighbourhood",
    "wof:population":4145,
    "zs:area_m":1744181.00653,
    "zs:blockids":[
        80010092061008,
        80010091031023,
        80010092071002,
        80010092071003,
        80010092071016,
        80010092061021,
        80010091042044,
        80010091042001,
        80010091041017,
        80010092071011,
        80010091031035,
        80010092061009,
        80010091031024,
        80010091041002,
        80010092071006,
        80010092071007,
        80010091031034,
        80010091031033,
        80010091041008,
        80010091041005,
        80010091041003,
        80010092071001,
        80010092061000,
        80010092071009,
        80010091041009,
        80010091041012,
        80010091041004,
        80010091041006,
        80010092061029,
        80010091042000,
        80010092071005,
        80010091041013,
        80010091041014,
        80010091041011,
        80010091041007,
        80010091041015,
        80010092071012,
        80010092071004,
        80010091031036,
        80010091041010,
        80010091041018,
        80010091041016,
        80010085331025,
        80010092061020,
        80010092061028,
        80010091031032,
        80010092071015,
        80010092071008,
        80010092061014,
        80010092061012,
        80010092071010,
        80010092071000,
        80010091031031,
        80010091041024,
        80010091041030
    ],
    "zs:housing10":1405,
    "zs:label":"Grandview Center",
    "zs:pop10":4145
},
  "geometry": {"coordinates":[-104.939027,39.873879],"type":"Point"}
}