{
  "type": "Feature",
  "properties": {
    "gn:admin1_code":"SD",
    "gn:admin2_code":"13.0",
    "gn:admin3_code":"47420.0",
    "gn:asciiname":"Deevaan Villa Development",
    "gn:country_code":"US",
    "gn:dem":393,
    "gn:elevation":"395.0",
    "gn:feature_class":"P",
    "gn:feature_code":"PPL",
    "gn:name":"Deevaan Villa Development",
    "gn:population":0,
    "gn:timezone":"America/Chicago",
    "iso:country":"US",
    "wof:name":"Deevaan Villa Development",
    "wof:placetype":"locality"
},
  "geometry": {"coordinates":[-98.45759,45.50498],"type":"Point"}
}