{
  "type": "Feature",
  "properties": {
    "iso:country":"US",
    "name:eng_x_preferred":[
        "Neighborhood H"
    ],
    "qs:gn_adm0_cc":"US",
    "qs:gn_local":5388564,
    "qs:gn_nam_loc":"Rohnert Park, Sonoma, California, US",
    "qs:gn_namadm1":"CA",
    "qs:local_max":1145,
    "qs:local_sum":2704,
    "qs:localhoods":9,
    "qs:name":"Neighborhood H",
    "qs:name_adm0":"United States",
    "qs:name_adm1":"California",
    "qs:name_adm2":"Sonoma",
    "qs:name_local":"Rohnert Park",
    "qs:photo_max":18,
    "qs:photo_sum":24,
    "qs:placetype":"Suburb",
    "qs:quad_count":6,
    "qs:woe_adm0":23424977,
    "qs:woe_adm1":2347563,
    "qs:woe_adm2":12587718,
    "qs:woe_lau":0,
    "qs:woe_local":2483970,
    "qs:woe_ver":"7.10.0",
    "wof:lang":[
        "eng"
    ],
    "wof:name":"Neighborhood H",
    "wof:placetype":"neighbourhood",
    "wof:population":3944,
    "zs:blockids":[
        60971513082005,
        60971513073005,
        60971513074004,
        60971513074001,
        60971513073008,
        60971513072017,
        60971513071009,
        60971513074006,
        60971514024021,
        60971513074002,
        60971513074000,
        60971513074014,
        60971513082006,
        60971513073007,
        60971514024018,
        60971513073011,
        60971513082004,
        60971513074013,
        60971513072018,
        60971514024017,
        60971513071001,
        60971513074009,
        60971513071008,
        60971513074012,
        60971513071005,
        60971513072000,
        60971513074008,
        60971513071010,
        60971514024020,
        60971513085000,
        60971513071004,
        60971513073010,
        60971513074015,
        60971513074003,
        60971513072004,
        60971513074010,
        60971513074005,
        60971513073009,
        60971513072001,
        60971513074011
    ],
    "zs:housing10":1535,
    "zs:pop10":3944
},
  "geometry": {"coordinates":[-122.69354,38.361737],"type":"Point"}
}