{
  "type": "Feature",
  "properties": {
    "gn:admin1_code":"MD",
    "gn:admin2_code":"3.0",
    "gn:asciiname":"College Manor",
    "gn:country_code":"US",
    "gn:dem":19,
    "gn:elevation":"20.0",
    "gn:feature_class":"P",
    "gn:feature_code":"PPL",
    "gn:name":"College Manor",
    "gn:population":0,
    "gn:timezone":"America/New_York",
    "iso:country":"US",
    "wof:name":"College Manor",
    "wof:placetype":"locality"
},
  "geometry": {"coordinates":[-76.50385,39.04761],"type":"Point"}
}