{
  "type": "Feature",
  "properties": {
    "gn:admin1_code":"WV",
    "gn:admin2_code":"19",
    "gn:asciiname":"Coalfield",
    "gn:country_code":"US",
    "gn:dem":333,
    "gn:elevation":"305.0",
    "gn:feature_class":"P",
    "gn:feature_code":"PPL",
    "gn:name":"Coalfield",
    "gn:population":0,
    "gn:timezone":"America/New_York",
    "iso:country":"US",
    "name:eng_x_preferred":[
        "Coalfield"
    ],
    "name:und_x_variant":[
        "Krebs"
    ],
    "wof:name":"Coalfield",
    "wof:placetype":"locality"
},
  "geometry": {"coordinates":[-81.35039,38.00455],"type":"Point"}
}