{
  "type": "Feature",
  "properties": {
    "gn:admin1_code":"FL",
    "gn:admin2_code":"43.0",
    "gn:asciiname":"Sarasota Colony",
    "gn:country_code":"US",
    "gn:dem":9,
    "gn:elevation":"5.0",
    "gn:feature_class":"P",
    "gn:feature_code":"PPL",
    "gn:name":"Sarasota Colony",
    "gn:population":0,
    "gn:timezone":"America/New_York",
    "iso:country":"US",
    "wof:name":"Sarasota Colony",
    "wof:placetype":"locality"
},
  "geometry": {"coordinates":[-81.05423,27.00533],"type":"Point"}
}