{
  "type": "Feature",
  "properties": {
    "iso:country":"US",
    "name:eng_x_preferred":[
        "Crossroads Colorado West"
    ],
    "wof:name":"Crossroads Colorado West",
    "wof:placetype":"neighbourhood",
    "wof:population":2359,
    "zs:area_m":3688834.931645,
    "zs:blockids":[
        80770010013026,
        80770010013004,
        80770016002038,
        80770010011001,
        80770010021015,
        80770016002065,
        80770016002072,
        80770010021011,
        80770010011020,
        80770010013015,
        80770010011013,
        80770010011000,
        80770016002076,
        80770010013023,
        80770010013014,
        80770010021001,
        80770010011004,
        80770010013005,
        80770010012004,
        80770010012003,
        80770010021009,
        80770010011007,
        80770010011016,
        80770010011005,
        80770010012013,
        80770016002068,
        80770010013003,
        80770010021000,
        80770010013029,
        80770010011003,
        80770010012005,
        80770010013025,
        80770010021010,
        80770016002034,
        80770010011010,
        80770016002066,
        80770016002075,
        80770016002077,
        80770010011018,
        80770010011024,
        80770010013031,
        80770010011026,
        80770010013020,
        80770010011006,
        80770010021014,
        80770010011002,
        80770016002071,
        80770016002070,
        80770010011008,
        80770010011023,
        80770010013044,
        80770010013045,
        80770010011011,
        80770010011015,
        80770010013016,
        80770010011017,
        80770010013046,
        80770016002095,
        80770010012000,
        80770016002091,
        80770010011025,
        80770016002069,
        80770010011009,
        80770010011012,
        80770010013019,
        80770010011019,
        80770010013018,
        80770010011022,
        80770016002067,
        80770010013027,
        80770010013030,
        80770016002042,
        80770010021002,
        80770016002090,
        80770010011021,
        80770010013021,
        80770010013022,
        80770010011014
    ],
    "zs:housing10":1116,
    "zs:label":"Crossroads Colorado West",
    "zs:pop10":2359
},
  "geometry": {"coordinates":[-108.546178,39.111418],"type":"Point"}
}