{
  "type": "Feature",
  "properties": {
    "gn:admin1_code":"MD",
    "gn:admin2_code":"21.0",
    "gn:asciiname":"Gibralter Acres",
    "gn:country_code":"US",
    "gn:dem":135,
    "gn:elevation":"131.0",
    "gn:feature_class":"P",
    "gn:feature_code":"PPL",
    "gn:name":"Gibralter Acres",
    "gn:population":0,
    "gn:timezone":"America/New_York",
    "iso:country":"US",
    "wof:name":"Gibralter Acres",
    "wof:placetype":"locality"
},
  "geometry": {"coordinates":[-77.33136999999998,39.30344],"type":"Point"}
}