{
  "type": "Feature",
  "properties": {
    "gn:admin1_code":"VA",
    "gn:admin2_code":"155",
    "gn:asciiname":"Tinytown",
    "gn:country_code":"US",
    "gn:dem":644,
    "gn:elevation":"640.0",
    "gn:feature_class":"P",
    "gn:feature_code":"PPL",
    "gn:name":"Tinytown",
    "gn:population":0,
    "gn:timezone":"America/New_York",
    "iso:country":"US",
    "wof:name":"Tinytown",
    "wof:placetype":"locality"
},
  "geometry": {"coordinates":[-80.69646,36.98207],"type":"Point"}
}