{
  "type": "Feature",
  "properties": {
    "iso:country":"US",
    "name:cat_x_preferred":[
        "Elmwood"
    ],
    "name:ceb_x_preferred":[
        "Elmwood"
    ],
    "name:deu_x_preferred":[
        "Elmwood"
    ],
    "name:eng_x_preferred":[
        "Elmwood"
    ],
    "name:ita_x_preferred":[
        "Elmwood"
    ],
    "name:nld_x_preferred":[
        "Elmwood"
    ],
    "name:pol_x_preferred":[
        "Elmwood"
    ],
    "name:por_x_preferred":[
        "Elmwood"
    ],
    "name:srp_x_preferred":[
        "\u0415\u043b\u043c\u0432\u0443\u0434"
    ],
    "name:ukr_x_preferred":[
        "\u0415\u043b\u043c\u0432\u0443\u0434"
    ],
    "name:vol_x_preferred":[
        "Elmwood"
    ],
    "wd:wordcount":334,
    "wof:name":"Elmwood",
    "wof:placetype":"neighbourhood",
    "wof:population":209,
    "zs:area_m":20694570.911626,
    "zs:blockids":[
        330130415002082,
        330130415002073,
        330130415002075,
        330130415002085,
        330130415002070,
        330130415002088,
        330130415002089,
        330130415002055,
        330130415002086
    ],
    "zs:housing10":115,
    "zs:label":"Elmwood",
    "zs:pop10":209
},
  "geometry": {"coordinates":[-71.852782,43.47586],"type":"Point"}
}