{
  "type": "Feature",
  "properties": {
    "gn:country":"US",
    "gn:fcode":"PPL",
    "gn:population":0,
    "iso:country":"US",
    "name:cat_x_preferred":[
        "Russellville"
    ],
    "name:ceb_x_preferred":[
        "Russellville"
    ],
    "name:deu_x_preferred":[
        "Russellville"
    ],
    "name:eng_x_preferred":[
        "Russellville"
    ],
    "name:fra_x_preferred":[
        "Russellville"
    ],
    "name:ita_x_preferred":[
        "Russellville"
    ],
    "name:kor_x_preferred":[
        "\ub7ec\uc140\ube4c"
    ],
    "name:nld_x_preferred":[
        "Russellville"
    ],
    "name:pol_x_preferred":[
        "Russellville"
    ],
    "name:por_x_preferred":[
        "Russellville"
    ],
    "name:rus_x_preferred":[
        "\u0420\u0430\u0441\u0441\u0435\u043b\u043b\u0432\u0438\u043b\u043b"
    ],
    "name:srp_x_preferred":[
        "\u0420\u0430\u0441\u0435\u043b\u0432\u0438\u043b"
    ],
    "name:swe_x_preferred":[
        "Russellville"
    ],
    "name:und_x_variant":[
        "Russelville"
    ],
    "name:vol_x_preferred":[
        "Russellville"
    ],
    "qs_pg:aaroncc":"US",
    "qs_pg:gn_country":"US",
    "qs_pg:gn_fcode":"PPL",
    "qs_pg:gn_pop":0,
    "qs_pg:name":"Russellville",
    "qs_pg:name_adm0":"United States",
    "qs_pg:name_adm1":"Michigan",
    "qs_pg:photos":828,
    "qs_pg:photos_1k":168,
    "qs_pg:photos_9k":4,
    "qs_pg:photos_9r":6,
    "qs_pg:photos_all":828,
    "qs_pg:photos_sr":9,
    "qs_pg:pop_sr":0,
    "qs_pg:qs_pg_placetype":"locality",
    "qs_pg:qs_pg_placetype_gp":"Town",
    "qs_pg:woe_adm0":23424977,
    "woe:adm0_id":23424977,
    "woe:name_adm0":"United States",
    "woe:name_adm1":"Michigan",
    "woe:placetype":"Town",
    "wof:name":"Russellville",
    "wof:placetype":"locality"
},
  "geometry": {"coordinates":[-83.55829,43.09169],"type":"Point"}
}