{
  "type": "Feature",
  "properties": {
    "iso:country":"US",
    "name:eng_x_preferred":[
        "Tara Place"
    ],
    "name:eng_x_variant":[
        "Tara Pl"
    ],
    "qs:gn_adm0_cc":"US",
    "qs:gn_fcode":"PPLX",
    "qs:gn_local":4315588,
    "qs:gn_nam_loc":"Baton Rouge, East Baton Rouge Parish, Louisiana, US",
    "qs:gn_namadm1":"LA",
    "qs:gn_name":"Tara Place",
    "qs:local_max":4803,
    "qs:local_sum":39503,
    "qs:localhoods":84,
    "qs:name":"Tara Place",
    "qs:name_adm0":"United States",
    "qs:name_adm1":"Louisiana",
    "qs:name_adm2":"East Baton Rouge Parish",
    "qs:name_local":"Baton Rouge",
    "qs:photo_max":251,
    "qs:photo_sum":511,
    "qs:placetype":"Suburb",
    "qs:quad_count":11,
    "qs:woe_adm0":23424977,
    "qs:woe_adm1":2347577,
    "qs:woe_adm2":12588612,
    "qs:woe_lau":0,
    "qs:woe_local":2359991,
    "qs:woe_ver":"7.10.0",
    "wof:lang":[
        "eng"
    ],
    "wof:name":"Tara Place",
    "wof:placetype":"neighbourhood",
    "wof:population":1822,
    "zs:blockids":[
        220330020002013,
        220330037013012,
        220330037013006,
        220330020001019,
        220330020001006,
        220330037013014,
        220330020001038,
        220330020002009,
        220330020001013,
        220330037012015,
        220330037012022,
        220330037012011,
        220330037013003,
        220330037013001,
        220330020001031,
        220330020001015,
        220330020001034,
        220330020001011,
        220330020001012,
        220330020001032,
        220330037013013,
        220330020001009,
        220330037013000,
        220330020001025,
        220330020001017,
        220330020001008,
        220330037013005,
        220330020001037,
        220330020002010,
        220330037013002,
        220330020001010,
        220330037012019,
        220330037012021,
        220330037012018,
        220330020001033,
        220330037012023,
        220330037013008,
        220330020001020,
        220330037014012,
        220330020001018,
        220330037014004,
        220330037013007,
        220330020002015,
        220330020001023,
        220330020001016,
        220330037013004,
        220330020001030,
        220330037013015,
        220330037013009,
        220330020001035,
        220330020002012,
        220330037012016,
        220330037013011,
        220330037013010,
        220330020002011,
        220330020001036
    ],
    "zs:housing10":755,
    "zs:pop10":1822
},
  "geometry": {"coordinates":[-91.092069,30.44362],"type":"Point"}
}