{
  "type": "Feature",
  "properties": {
    "gn:admin1_code":"GA",
    "gn:admin2_code":"135.0",
    "gn:asciiname":"Indian Crossing",
    "gn:country_code":"US",
    "gn:dem":305,
    "gn:elevation":"305.0",
    "gn:feature_class":"P",
    "gn:feature_code":"PPL",
    "gn:name":"Indian Crossing",
    "gn:population":0,
    "gn:timezone":"America/New_York",
    "iso:country":"US",
    "wof:name":"Indian Crossing",
    "wof:placetype":"locality"
},
  "geometry": {"coordinates":[-84.17797,33.93482],"type":"Point"}
}