{
  "type": "Feature",
  "properties": {
    "gn:admin1_code":"IN",
    "gn:admin2_code":"31.0",
    "gn:admin3_code":"67536.0",
    "gn:asciiname":"Rossburg",
    "gn:country_code":"US",
    "gn:dem":282,
    "gn:elevation":"284.0",
    "gn:feature_class":"P",
    "gn:feature_code":"PPL",
    "gn:name":"Rossburg",
    "gn:population":0,
    "gn:timezone":"America/Indiana/Indianapolis",
    "iso:country":"US",
    "name:eng_x_preferred":[
        "Rossburg"
    ],
    "name:und_x_variant":[
        "Rossburgh",
        "Rossville"
    ],
    "wof:name":"Rossburg",
    "wof:placetype":"locality"
},
  "geometry": {"coordinates":[-85.32608,39.32588],"type":"Point"}
}