{
  "type": "Feature",
  "properties": {
    "iso:country":"US",
    "name:eng_x_preferred":[
        "Oxbridge Neighborhood Association"
    ],
    "wof:name":"Oxbridge Neighborhood Association",
    "wof:placetype":"neighbourhood",
    "wof:population":1053,
    "zs:area_m":663460.781517,
    "zs:blockids":[
        261614003003005,
        261614053001008,
        261614053001002,
        261614053005025,
        261614053005021,
        261614053005008,
        261614053005026,
        261614053005033,
        261614053001005,
        261614053001003,
        261614053005022,
        261614053001004,
        261614053005020,
        261614053001012,
        261614053005018,
        261614053005056,
        261614053001007,
        261614053005032,
        261614053005011,
        261614053005010,
        261614053005019,
        261614053005057,
        261614053001006,
        261614053005005
    ],
    "zs:housing10":286,
    "zs:label":"Oxbridge Neighborhood Association",
    "zs:pop10":1053
},
  "geometry": {"coordinates":[-83.718343,42.273338],"type":"Point"}
}