{
  "type": "Feature",
  "properties": {
    "gn:admin1_code":"TN",
    "gn:admin2_code":"13",
    "gn:asciiname":"Ilford",
    "gn:country_code":"US",
    "gn:dem":373,
    "gn:elevation":"367.0",
    "gn:feature_class":"P",
    "gn:feature_code":"PPL",
    "gn:name":"Ilford",
    "gn:population":0,
    "gn:timezone":"America/New_York",
    "iso:country":"US",
    "name:azb_x_preferred":[
        "\u0627\u06cc\u0644\u0641\u0648\u0631\u062f"
    ],
    "name:cym_x_preferred":[
        "Ilford"
    ],
    "name:fas_x_preferred":[
        "\u0627\u06cc\u0644\u0641\u0648\u0631\u062f"
    ],
    "name:fra_x_preferred":[
        "Ilford"
    ],
    "name:fry_x_preferred":[
        "Ilford"
    ],
    "name:gle_x_preferred":[
        "Ilford"
    ],
    "name:hin_x_preferred":[
        "\u0907\u0932\u092b\u093c\u0930\u094d\u0921"
    ],
    "name:ita_x_preferred":[
        "Ilford"
    ],
    "name:jpn_x_preferred":[
        "\u30a4\u30eb\u30d5\u30a9\u30fc\u30c9"
    ],
    "name:kor_x_preferred":[
        "\uc77c\ud37c\ub4dc"
    ],
    "name:nld_x_preferred":[
        "Ilford"
    ],
    "name:nno_x_preferred":[
        "Ilford"
    ],
    "name:nor_x_preferred":[
        "Ilford"
    ],
    "name:pol_x_preferred":[
        "Ilford"
    ],
    "name:rus_x_preferred":[
        "\u0418\u043b\u0444\u043e\u0440\u0434"
    ],
    "name:spa_x_preferred":[
        "Ilford"
    ],
    "name:ukr_x_preferred":[
        "\u0406\u043b\u0444\u043e\u0440\u0434"
    ],
    "name:vie_x_preferred":[
        "Ilford"
    ],
    "name:yid_x_preferred":[
        "\u05d0\u05d9\u05dc\u05e4\u05d0\u05e8\u05d3"
    ],
    "name:zho_x_preferred":[
        "\u4f0a\u723e\u798f\u5fb7"
    ],
    "wof:name":"Ilford",
    "wof:placetype":"locality"
},
  "geometry": {"coordinates":[-84.06326,36.49591],"type":"Point"}
}