{
  "type": "Feature",
  "properties": {
    "iso:country":"US",
    "name:eng_x_preferred":[
        "Waukegan Harbor"
    ],
    "name:eng_x_variant":[
        "Waukegan Harbor Light"
    ],
    "name:rus_x_preferred":[
        "\u0423\u043e\u043a\u0438\u0433\u0430\u043d-\u0425\u0430\u0440\u0431\u043e\u0440-\u041b\u0430\u0439\u0442"
    ],
    "qs:gn_adm0_cc":"US",
    "qs:gn_local":4915734,
    "qs:gn_nam_loc":"Waukegan, Lake, Illinois, US",
    "qs:gn_namadm1":"IL",
    "qs:local_max":2774,
    "qs:local_sum":3710,
    "qs:localhoods":7,
    "qs:name":"Waukegan Harbor",
    "qs:name_adm0":"United States",
    "qs:name_adm1":"Illinois",
    "qs:name_adm2":"Lake",
    "qs:name_local":"Waukegan",
    "qs:photo_max":283,
    "qs:photo_sum":352,
    "qs:placetype":"Suburb",
    "qs:quad_count":9,
    "qs:woe_adm0":23424977,
    "qs:woe_adm1":2347572,
    "qs:woe_adm2":12588127,
    "qs:woe_lau":0,
    "qs:woe_local":2515434,
    "qs:woe_ver":"7.10.0",
    "wd:wordcount":158,
    "wof:lang":[
        "eng"
    ],
    "wof:name":"Waukegan Harbor",
    "wof:placetype":"neighbourhood",
    "wof:population":3,
    "zs:blockids":[
        170978622002006,
        170978622002005,
        170978622002007,
        170978622002004,
        170978622002008
    ],
    "zs:housing10":1,
    "zs:pop10":3
},
  "geometry": {"coordinates":[-87.815141,42.363339],"type":"Point"}
}