{
  "type": "Feature",
  "properties": {
    "iso:country":"US",
    "name:eng_x_preferred":[
        "Hautala Corner"
    ],
    "wof:name":"Hautala Corner",
    "wof:placetype":"neighbourhood",
    "wof:population":629,
    "zs:area_m":103420385.739398,
    "zs:blockids":[
        260539507001072,
        260539507003008,
        260539507003013,
        260539507002002,
        260539507001111,
        260539507001105,
        260539507003017,
        260539507003004,
        260539507003007,
        260539507003018,
        260539507001200,
        260539507003019,
        260539507003003,
        260539507003006,
        260539507003005,
        260539507003012,
        260539507001122,
        260539507003011,
        260539507001108,
        260539507001103,
        260539507001102,
        260539507001094,
        260539507001199,
        260539507001183,
        260539507003015,
        260539507002000,
        260539507001198,
        260539507001106,
        260539507001101,
        260539507002003,
        260539507002001,
        260539507003009,
        260539507001197,
        260539507001071,
        260539507001104
    ],
    "zs:housing10":367,
    "zs:label":"Hautala Corner",
    "zs:pop10":629
},
  "geometry": {"coordinates":[-90.13501100000001,46.571876],"type":"Point"}
}