{
  "type": "Feature",
  "properties": {
    "gn:admin1_code":"GA",
    "gn:admin2_code":"255.0",
    "gn:asciiname":"Blantons Mill",
    "gn:country_code":"US",
    "gn:dem":231,
    "gn:elevation":"225.0",
    "gn:feature_class":"P",
    "gn:feature_code":"PPL",
    "gn:name":"Blantons Mill",
    "gn:population":0,
    "gn:timezone":"America/New_York",
    "iso:country":"US",
    "wof:name":"Blantons Mill",
    "wof:placetype":"locality"
},
  "geometry": {"coordinates":[-84.43437,33.22068],"type":"Point"}
}