{
  "type": "Feature",
  "properties": {
    "gn:admin1_code":"NM",
    "gn:admin2_code":"39.0",
    "gn:asciiname":"La Junta",
    "gn:country_code":"US",
    "gn:dem":1786,
    "gn:elevation":"1788.0",
    "gn:feature_class":"P",
    "gn:feature_code":"PPL",
    "gn:name":"La Junta",
    "gn:population":0,
    "gn:timezone":"America/Denver",
    "iso:country":"US",
    "wof:name":"La Junta",
    "wof:placetype":"locality"
},
  "geometry": {"coordinates":[-105.91696,36.21141],"type":"Point"}
}