{
  "type": "Feature",
  "properties": {
    "gn:admin1_code":"NY",
    "gn:admin2_code":"93.0",
    "gn:admin3_code":"59861.0",
    "gn:asciiname":"Kelleys",
    "gn:country_code":"US",
    "gn:dem":150,
    "gn:elevation":"153.0",
    "gn:feature_class":"P",
    "gn:feature_code":"PPL",
    "gn:name":"Kelleys",
    "gn:population":0,
    "gn:timezone":"America/New_York",
    "iso:country":"US",
    "wof:name":"Kelleys",
    "wof:placetype":"locality"
},
  "geometry": {"coordinates":[-74.06789999999999,42.77952],"type":"Point"}
}