{
  "type": "Feature",
  "properties": {
    "gn:admin1_code":"IL",
    "gn:admin2_code":"3",
    "gn:asciiname":"Cairo Junction",
    "gn:country_code":"US",
    "gn:dem":93,
    "gn:elevation":"93.0",
    "gn:feature_class":"P",
    "gn:feature_code":"PPL",
    "gn:name":"Cairo Junction",
    "gn:population":0,
    "gn:timezone":"America/Chicago",
    "iso:country":"US",
    "wof:name":"Cairo Junction",
    "wof:placetype":"locality"
},
  "geometry": {"coordinates":[-89.19174,37.04088],"type":"Point"}
}