{
  "type": "Feature",
  "properties": {
    "gn:admin1_code":"WV",
    "gn:admin2_code":"39.0",
    "gn:asciiname":"Riverlake",
    "gn:country_code":"US",
    "gn:dem":184,
    "gn:elevation":"184.0",
    "gn:feature_class":"P",
    "gn:feature_code":"PPL",
    "gn:name":"Riverlake",
    "gn:population":0,
    "gn:timezone":"America/New_York",
    "iso:country":"US",
    "name:eng_x_preferred":[
        "Riverlake"
    ],
    "name:und_x_variant":[
        "Riverlake Estates"
    ],
    "wof:name":"Riverlake",
    "wof:placetype":"locality"
},
  "geometry": {"coordinates":[-81.85096,38.36759],"type":"Point"}
}