{
  "type": "Feature",
  "properties": {
    "gn:admin1_code":"FL",
    "gn:admin2_code":"3.0",
    "gn:asciiname":"Sapp",
    "gn:country_code":"US",
    "gn:dem":47,
    "gn:elevation":"42.0",
    "gn:feature_class":"P",
    "gn:feature_code":"PPL",
    "gn:name":"Sapp",
    "gn:population":0,
    "gn:timezone":"America/New_York",
    "iso:country":"US",
    "name:deu_x_preferred":[
        "Sapp"
    ],
    "name:fra_x_preferred":[
        "Sapp"
    ],
    "wof:name":"Sapp",
    "wof:placetype":"locality"
},
  "geometry": {"coordinates":[-82.18567,30.14746],"type":"Point"}
}