{
  "type": "Feature",
  "properties": {
    "iso:country":"US",
    "name:eng_x_preferred":[
        "Livonia North"
    ],
    "wof:name":"Livonia North",
    "wof:placetype":"neighbourhood",
    "wof:population":2125,
    "zs:area_m":2052537.595316,
    "zs:blockids":[
        261635574002004,
        261635573002000,
        261635574002008,
        261635574002003,
        261635568002015,
        261635573002002,
        261635567002011,
        261635573002003,
        261635573001003,
        261635568002012,
        261635574002024,
        261635574002007,
        261635568002013,
        261635568002016,
        261635573002001,
        261635568002009,
        261635573002010,
        261635574002006,
        261635574002001,
        261635574002005,
        261635568002011,
        261635574002002,
        261635567002010,
        261635573002004,
        261635573002009,
        261635573002008,
        261635573002006,
        261635573002007,
        261635574002000
    ],
    "zs:housing10":873,
    "zs:label":"Livonia North",
    "zs:pop10":2125
},
  "geometry": {"coordinates":[-83.371047,42.409489],"type":"Point"}
}