{
  "type": "Feature",
  "properties": {
    "gn:admin1_code":"VA",
    "gn:admin2_code":"730.0",
    "gn:asciiname":"Battlefield Park",
    "gn:country_code":"US",
    "gn:dem":53,
    "gn:elevation":"46.0",
    "gn:feature_class":"P",
    "gn:feature_code":"PPL",
    "gn:name":"Battlefield Park",
    "gn:population":0,
    "gn:timezone":"America/New_York",
    "iso:country":"US",
    "wof:name":"Battlefield Park",
    "wof:placetype":"locality"
},
  "geometry": {"coordinates":[-77.38248,37.19182],"type":"Point"}
}