{
  "type": "Feature",
  "properties": {
    "gn:admin1_code":"MT",
    "gn:admin2_code":"35.0",
    "gn:asciiname":"Glacier Colony",
    "gn:country_code":"US",
    "gn:dem":1249,
    "gn:elevation":"1256.0",
    "gn:feature_class":"P",
    "gn:feature_code":"PPL",
    "gn:name":"Glacier Colony",
    "gn:population":0,
    "gn:timezone":"America/Denver",
    "iso:country":"US",
    "wof:name":"Glacier Colony",
    "wof:placetype":"locality"
},
  "geometry": {"coordinates":[-112.21894,48.83277],"type":"Point"}
}