{
  "type": "Feature",
  "properties": {
    "gn:admin1_code":"GA",
    "gn:admin2_code":"223.0",
    "gn:asciiname":"Hasford Estates",
    "gn:country_code":"US",
    "gn:dem":311,
    "gn:elevation":"287.0",
    "gn:feature_class":"P",
    "gn:feature_code":"PPL",
    "gn:name":"Hasford Estates",
    "gn:population":0,
    "gn:timezone":"America/New_York",
    "iso:country":"US",
    "wof:name":"Hasford Estates",
    "wof:placetype":"locality"
},
  "geometry": {"coordinates":[-84.79271999999997,33.99038],"type":"Point"}
}