{
  "type": "Feature",
  "properties": {
    "iso:country":"US",
    "name:eng_x_preferred":[
        "Tam O' Shanter"
    ],
    "qs:gn_adm0_cc":"US",
    "qs:gn_local":5786882,
    "qs:gn_nam_loc":"Bellevue, King, Washington, US",
    "qs:gn_namadm1":"WA",
    "qs:local_max":5360,
    "qs:local_sum":48946,
    "qs:localhoods":55,
    "qs:name":"Tam O' Shanter",
    "qs:name_adm0":"United States",
    "qs:name_adm1":"Washington",
    "qs:name_adm2":"King",
    "qs:name_local":"Bellevue",
    "qs:photo_max":70,
    "qs:photo_sum":306,
    "qs:placetype":"Suburb",
    "qs:quad_count":18,
    "qs:woe_adm0":23424977,
    "qs:woe_adm1":2347606,
    "qs:woe_adm2":12590456,
    "qs:woe_lau":0,
    "qs:woe_local":2362031,
    "qs:woe_ver":"7.10.0",
    "wd:wordcount":94,
    "wof:name":"Tam O' Shanter",
    "wof:placetype":"neighbourhood",
    "wof:population":4686,
    "zs:blockids":[
        530330229025015,
        530330229024015,
        530330229021014,
        530330229025005,
        530330230004020,
        530330230004018,
        530330229022003,
        530330229025006,
        530330229025004,
        530330229022002,
        530330229024011,
        530330229024012,
        530330229025011,
        530330229022007,
        530330229022013,
        530330230001007,
        530330230004017,
        530330230004001,
        530330229021011,
        530330229022006,
        530330229022014,
        530330230001002,
        530330229022016,
        530330229025012,
        530330230004005,
        530330230001000,
        530330229022015,
        530330229025013,
        530330229025000,
        530330229022012,
        530330229022009,
        530330230004021,
        530330230001011,
        530330230001003,
        530330230001012,
        530330229025014,
        530330229021010,
        530330230004003,
        530330229025002,
        530330230001009,
        530330230004000,
        530330230004015,
        530330322033006,
        530330229025009,
        530330229024014,
        530330230004007,
        530330229021015,
        530330230004019,
        530330230004016,
        530330230004004,
        530330229024013,
        530330229025001,
        530330229025008,
        530330230001017,
        530330229022008,
        530330230001004,
        530330230001008,
        530330230001006,
        530330230001001,
        530330229022011,
        530330229022005,
        530330230004002,
        530330229025010,
        530330229025003,
        530330230004006,
        530330229021012,
        530330229025007,
        530330229022010,
        530330229021013,
        530330230001018,
        530330229022001
    ],
    "zs:housing10":1743,
    "zs:pop10":4686
},
  "geometry": {"coordinates":[-122.100829,47.622952],"type":"Point"}
}