{
  "type": "Feature",
  "properties": {
    "gn:admin1_code":"MO",
    "gn:admin2_code":"171.0",
    "gn:admin3_code":"61580.0",
    "gn:asciiname":"Elko",
    "gn:country_code":"US",
    "gn:dem":284,
    "gn:elevation":"283.0",
    "gn:feature_class":"P",
    "gn:feature_code":"PPL",
    "gn:name":"Elko",
    "gn:population":0,
    "gn:timezone":"America/Chicago",
    "iso:country":"US",
    "name:ben_x_preferred":[
        "\u098f\u09b2\u0995\u09cb"
    ],
    "name:ceb_x_preferred":[
        "Elko"
    ],
    "name:ces_x_preferred":[
        "Elko"
    ],
    "name:deu_x_preferred":[
        "Elko"
    ],
    "name:ell_x_preferred":[
        "\u0388\u03bb\u03ba\u03bf"
    ],
    "name:eng_x_preferred":[
        "Elko"
    ],
    "name:fra_x_preferred":[
        "Elko"
    ],
    "name:ido_x_preferred":[
        "Elko"
    ],
    "name:ind_x_preferred":[
        "Elko"
    ],
    "name:ita_x_preferred":[
        "Elko"
    ],
    "name:nld_x_preferred":[
        "Elko"
    ],
    "name:pol_x_preferred":[
        "Elko"
    ],
    "name:por_x_preferred":[
        "Elko"
    ],
    "name:rus_x_preferred":[
        "\u042d\u043b\u043a\u043e"
    ],
    "name:spa_x_preferred":[
        "Elko"
    ],
    "name:srp_x_preferred":[
        "\u0415\u043b\u043a\u043e"
    ],
    "name:swe_x_preferred":[
        "Elko"
    ],
    "name:ukr_x_preferred":[
        "\u0415\u043b\u043a\u043e"
    ],
    "name:und_x_variant":[
        "Garfield Springs"
    ],
    "name:vol_x_preferred":[
        "Elko"
    ],
    "wof:name":"Elko",
    "wof:placetype":"locality"
},
  "geometry": {"coordinates":[-92.86492,40.41502],"type":"Point"}
}