{
  "type": "Feature",
  "properties": {
    "gn:admin1_code":"PA",
    "gn:admin2_code":"21.0",
    "gn:admin3_code":"63608.0",
    "gn:asciiname":"Van Ormer",
    "gn:country_code":"US",
    "gn:dem":439,
    "gn:elevation":"436.0",
    "gn:feature_class":"P",
    "gn:feature_code":"PPL",
    "gn:name":"Van Ormer",
    "gn:population":0,
    "gn:timezone":"America/New_York",
    "iso:country":"US",
    "wof:name":"Van Ormer",
    "wof:placetype":"locality"
},
  "geometry": {"coordinates":[-78.49252,40.6734],"type":"Point"}
}