{
  "type": "Feature",
  "properties": {
    "iso:country":"US",
    "name:eng_x_preferred":[
        "Withrow Woods"
    ],
    "qs:gn_adm0_cc":"US",
    "qs:gn_local":4148986,
    "qs:gn_nam_loc":"Brooksville, Hernando, Florida, US",
    "qs:gn_namadm1":"FL",
    "qs:local_max":450,
    "qs:local_sum":822,
    "qs:localhoods":10,
    "qs:name":"Withrow Woods",
    "qs:name_adm0":"United States",
    "qs:name_adm1":"Florida",
    "qs:name_adm2":"Hernando",
    "qs:name_local":"Brooksville",
    "qs:photo_max":19,
    "qs:photo_sum":38,
    "qs:placetype":"Suburb",
    "qs:quad_count":3,
    "qs:woe_adm0":23424977,
    "qs:woe_adm1":2347568,
    "qs:woe_adm2":12587829,
    "qs:woe_lau":0,
    "qs:woe_local":2370136,
    "qs:woe_ver":"7.10.0",
    "wof:lang":[
        "eng"
    ],
    "wof:name":"Withrow Woods",
    "wof:placetype":"neighbourhood",
    "wof:population":212,
    "zs:blockids":[
        120530402021004,
        120530402011056,
        120530402011039,
        120530402011037,
        120530402011036
    ],
    "zs:housing10":101,
    "zs:pop10":212
},
  "geometry": {"coordinates":[-82.293814,28.595946],"type":"Point"}
}