{
  "type": "Feature",
  "properties": {
    "iso:country":"US",
    "name:eng_x_preferred":[
        "Greater Sunset/Brooks Neighborhood Association"
    ],
    "wof:name":"Greater Sunset/Brooks Neighborhood Association",
    "wof:placetype":"neighbourhood",
    "wof:population":468,
    "zs:area_m":554451.817597,
    "zs:blockids":[
        261614032002005,
        261614032002004,
        261614032001023,
        261614032001022,
        261614032002006,
        261614032001026,
        261614032002000,
        261614032001025,
        261614032002001,
        261614032002003
    ],
    "zs:housing10":211,
    "zs:label":"Greater Sunset/Brooks Neighborhood Association",
    "zs:pop10":468
},
  "geometry": {"coordinates":[-83.760847,42.29598],"type":"Point"}
}