{
  "type": "Feature",
  "properties": {
    "iso:country":"US",
    "name:eng_x_preferred":[
        "Gilbert Corners"
    ],
    "name:eng_x_variant":[
        "Gilbert Cors"
    ],
    "qs:gn_adm0_cc":"US",
    "qs:gn_local":4845871,
    "qs:gn_nam_loc":"wilton",
    "qs:gn_namadm1":"CT",
    "qs:local_max":213,
    "qs:local_sum":465,
    "qs:localhoods":4,
    "qs:name":"Gilbert Corners",
    "qs:name_adm0":"United States",
    "qs:name_adm1":"Connecticut",
    "qs:name_adm2":"Fairfield",
    "qs:name_local":"Wilton",
    "qs:photo_max":58,
    "qs:photo_sum":213,
    "qs:placetype":"Suburb",
    "qs:quad_count":16,
    "qs:woe_adm0":23424977,
    "qs:woe_adm1":2347565,
    "qs:woe_adm2":12587791,
    "qs:woe_lau":0,
    "qs:woe_local":2521596,
    "qs:woe_ver":"7.10.0",
    "wof:lang":[
        "eng"
    ],
    "wof:name":"Gilbert Corners",
    "wof:placetype":"neighbourhood",
    "wof:population":3068,
    "zs:blockids":[
        90010451011006,
        90010452002007,
        90010452002020,
        90010451011002,
        90010451011031,
        90010451011027,
        90010451011022,
        90010452002006,
        90010452002003,
        90010451011007,
        90010451011003,
        90010451011020,
        90010451011028,
        90010453002000,
        90010453001005,
        90010451011025,
        90010451011010,
        90010452002014,
        90010354002001,
        90010451011026,
        90010451011032,
        90010453001003,
        90010451011009,
        90010451011004,
        90010451011023,
        90010451011015,
        90010354001019,
        90010354002000,
        90010452002018,
        90010451011021,
        90010451011029,
        90010451023032,
        90010451011005,
        90010452002019,
        90010451011030,
        90010451011008,
        90010452001018,
        90010452002015,
        90010354001009,
        90010451011014,
        90010354002002,
        90010451011013,
        90010453001004,
        90010451011024
    ],
    "zs:housing10":1256,
    "zs:pop10":3068
},
  "geometry": {"coordinates":[-73.440212,41.189869],"type":"Point"}
}