{
  "type": "Feature",
  "properties": {
    "iso:country":"US",
    "name:eng_x_preferred":[
        "Boulder Tech Center"
    ],
    "wof:name":"Boulder Tech Center",
    "wof:placetype":"neighbourhood",
    "wof:population":62,
    "zs:area_m":2664796.044164,
    "zs:blockids":[
        80130127012049,
        80130132051037,
        80130127012054,
        80130127012068,
        80130127012061,
        80130132051033,
        80130132051035,
        80130132131070,
        80130132051036,
        80130127012067,
        80130127012057,
        80130132131071,
        80130127012060,
        80130127012055,
        80130127012062,
        80130132051031,
        80130132051032,
        80130127012053,
        80130132051029,
        80130132051030,
        80130132051034
    ],
    "zs:housing10":27,
    "zs:label":"Boulder Tech Center",
    "zs:pop10":62
},
  "geometry": {"coordinates":[-105.181877,40.088455],"type":"Point"}
}