{
  "type": "Feature",
  "properties": {
    "gn:admin1_code":"MD",
    "gn:admin2_code":"31.0",
    "gn:asciiname":"Estates at Rivers Edge",
    "gn:country_code":"US",
    "gn:dem":96,
    "gn:elevation":"98.0",
    "gn:feature_class":"P",
    "gn:feature_code":"PPL",
    "gn:name":"Estates at Rivers Edge",
    "gn:population":0,
    "gn:timezone":"America/New_York",
    "iso:country":"US",
    "wof:name":"Estates at Rivers Edge",
    "wof:placetype":"locality"
},
  "geometry": {"coordinates":[-77.2822,39.05622],"type":"Point"}
}