{
  "type": "Feature",
  "properties": {
    "gn:admin1_code":"TX",
    "gn:admin2_code":"61.0",
    "gn:asciiname":"Cavazos",
    "gn:country_code":"US",
    "gn:dem":15,
    "gn:elevation":"14.0",
    "gn:feature_class":"P",
    "gn:feature_code":"PPL",
    "gn:name":"Cavazos",
    "gn:population":0,
    "gn:timezone":"America/Chicago",
    "iso:country":"US",
    "wof:name":"Cavazos",
    "wof:placetype":"locality"
},
  "geometry": {"coordinates":[-97.60777,26.01869],"type":"Point"}
}