{
  "type": "Feature",
  "properties": {
    "gn:admin1_code":"TX",
    "gn:admin2_code":"505",
    "gn:asciiname":"Falcon Lake",
    "gn:country_code":"US",
    "gn:dem":112,
    "gn:elevation":"111.0",
    "gn:feature_class":"P",
    "gn:feature_code":"PPL",
    "gn:name":"Falcon Lake",
    "gn:population":0,
    "gn:timezone":"America/Chicago",
    "iso:country":"US",
    "name:ara_x_preferred":[
        "\u0628\u062d\u064a\u0631\u0629 \u0641\u0627\u0644\u0643\u0648\u0646"
    ],
    "name:ben_x_preferred":[
        "\u09ab\u09cd\u09af\u09be\u09b2\u0995\u09a8 \u09b2\u09c7\u0995"
    ],
    "name:ceb_x_preferred":[
        "Falcon Lake"
    ],
    "name:deu_x_preferred":[
        "Falcon Lake"
    ],
    "name:ell_x_preferred":[
        "\u039b\u03af\u03bc\u03bd\u03b7 \u03a6\u03ac\u03bb\u03ba\u03bf\u03bd"
    ],
    "name:fas_x_preferred":[
        "\u062f\u0631\u06cc\u0627\u0686\u0647 \u0641\u0627\u0644\u06a9\u0648\u0646"
    ],
    "name:heb_x_preferred":[
        "\u05d0\u05d2\u05dd \u05e4\u05dc\u05e7\u05d5\u05df"
    ],
    "name:hin_x_preferred":[
        "\u095e\u093e\u0932\u094d\u0915\u0928 \u091d\u0940\u0932"
    ],
    "name:hun_x_preferred":[
        "Falcon-t\u00f3"
    ],
    "name:ind_x_preferred":[
        "Danau Falcon"
    ],
    "name:ita_x_preferred":[
        "Lago Falcon"
    ],
    "name:kor_x_preferred":[
        "\ud314\ucf58 \ub808\uc774\ud06c"
    ],
    "name:nld_x_preferred":[
        "Falcon Lake"
    ],
    "name:pol_x_preferred":[
        "Jezioro Falcon"
    ],
    "name:por_x_preferred":[
        "Lago Falcon"
    ],
    "name:rus_x_preferred":[
        "\u0432\u043e\u0434\u043e\u0445\u0440\u0430\u043d\u0438\u043b\u0438\u0449\u0435 \u0424\u0430\u043b\u043a\u043e\u043d-\u041b\u0435\u0439\u043a"
    ],
    "name:swe_x_preferred":[
        "Falcon Lake"
    ],
    "name:tur_x_preferred":[
        "Falcon G\u00f6l\u00fc"
    ],
    "name:ukr_x_preferred":[
        "\u043e\u0437\u0435\u0440\u043e \u0424\u0430\u043b\u044c\u043a\u043e\u043d"
    ],
    "name:urd_x_preferred":[
        "\u0641\u06cc\u0644\u06a9\u0646 \u062c\u06be\u06cc\u0644"
    ],
    "name:vie_x_preferred":[
        "H\u1ed3 Falcon"
    ],
    "name:zho_cn_x_preferred":[
        "\u730e\u9e70\u6e56"
    ],
    "name:zho_tw_x_preferred":[
        "\u6cd5\u723e\u5eb7\u6e56"
    ],
    "wof:name":"Falcon Lake",
    "wof:placetype":"locality"
},
  "geometry": {"coordinates":[-99.25559,26.87171],"type":"Point"}
}