{
  "type": "Feature",
  "properties": {
    "gn:admin1_code":"TX",
    "gn:admin2_code":"505",
    "gn:asciiname":"Falcon Lake",
    "gn:country_code":"US",
    "gn:dem":112,
    "gn:elevation":"111.0",
    "gn:feature_class":"P",
    "gn:feature_code":"PPL",
    "gn:name":"Falcon Lake",
    "gn:population":0,
    "gn:timezone":"America/Chicago",
    "iso:country":"US",
    "name:ceb_x_preferred":[
        "Falcon Lake"
    ],
    "name:deu_x_preferred":[
        "Falcon Lake"
    ],
    "name:swe_x_preferred":[
        "Falcon Lake"
    ],
    "wof:name":"Falcon Lake",
    "wof:placetype":"locality"
},
  "geometry": {"coordinates":[-99.25559,26.87171],"type":"Point"}
}