{
  "type": "Feature",
  "properties": {
    "gn:admin1_code":"TX",
    "gn:admin2_code":"451.0",
    "gn:asciiname":"Sixmile Crossing",
    "gn:country_code":"US",
    "gn:dem":538,
    "gn:elevation":"534.0",
    "gn:feature_class":"P",
    "gn:feature_code":"PPL",
    "gn:name":"Sixmile Crossing",
    "gn:population":0,
    "gn:timezone":"America/Chicago",
    "iso:country":"US",
    "wof:name":"Sixmile Crossing",
    "wof:placetype":"locality"
},
  "geometry": {"coordinates":[-100.34175999999999,31.46905],"type":"Point"}
}