{
  "type": "Feature",
  "properties": {
    "gn:admin1_code":"IN",
    "gn:admin2_code":"171.0",
    "gn:admin3_code":"51264.0",
    "gn:asciiname":"Foster",
    "gn:country_code":"US",
    "gn:dem":195,
    "gn:elevation":"193.0",
    "gn:feature_class":"P",
    "gn:feature_code":"PPL",
    "gn:name":"Foster",
    "gn:population":0,
    "gn:timezone":"America/Indiana/Indianapolis",
    "iso:country":"US",
    "name:azb_x_preferred":[
        "\u0641\u0627\u0633\u062a\u0631"
    ],
    "name:fas_x_preferred":[
        "\u0641\u0627\u0633\u062a\u0631"
    ],
    "name:fra_x_preferred":[
        "Foster"
    ],
    "name:spa_x_preferred":[
        "Foster"
    ],
    "name:vol_x_preferred":[
        "Foster"
    ],
    "wof:name":"Foster",
    "wof:placetype":"locality"
},
  "geometry": {"coordinates":[-87.4714,40.1467],"type":"Point"}
}