{
  "type": "Feature",
  "properties": {
    "gn:admin1_code":"KY",
    "gn:admin2_code":"153",
    "gn:asciiname":"Gullett",
    "gn:country_code":"US",
    "gn:dem":261,
    "gn:elevation":"260.0",
    "gn:feature_class":"P",
    "gn:feature_code":"PPL",
    "gn:name":"Gullett",
    "gn:population":0,
    "gn:timezone":"America/New_York",
    "iso:country":"US",
    "wof:name":"Gullett",
    "wof:placetype":"locality"
},
  "geometry": {"coordinates":[-83.12684,37.73731],"type":"Point"}
}