{
  "type": "Feature",
  "properties": {
    "gn:admin1_code":"MN",
    "gn:admin2_code":"153.0",
    "gn:admin3_code":"6022.0",
    "gn:asciiname":"Spaulding",
    "gn:country_code":"US",
    "gn:dem":399,
    "gn:elevation":"396.0",
    "gn:feature_class":"P",
    "gn:feature_code":"PPL",
    "gn:name":"Spaulding",
    "gn:population":0,
    "gn:timezone":"America/Chicago",
    "iso:country":"US",
    "name:ceb_x_preferred":[
        "Spaulding"
    ],
    "name:deu_x_preferred":[
        "Spaulding"
    ],
    "name:ita_x_preferred":[
        "Spaulding"
    ],
    "name:nld_x_preferred":[
        "Spaulding"
    ],
    "name:pol_x_preferred":[
        "Spaulding"
    ],
    "name:vol_x_preferred":[
        "Spaulding"
    ],
    "wof:name":"Spaulding",
    "wof:placetype":"locality"
},
  "geometry": {"coordinates":[-94.8528,45.77608],"type":"Point"}
}