{
  "type": "Feature",
  "properties": {
    "iso:country":"US",
    "name:eng_x_preferred":[
        "Oakcrest"
    ],
    "wof:name":"Oakcrest",
    "wof:placetype":"neighbourhood",
    "wof:population":587,
    "zs:area_m":450557.980329,
    "zs:blockids":[
        490111264051003,
        490111264051000,
        490111268023029,
        490111264051016,
        490111264041002
    ],
    "zs:housing10":171,
    "zs:label":"Oakcrest",
    "zs:pop10":587
},
  "geometry": {"coordinates":[-111.86964,40.852136],"type":"Point"}
}