{
  "type": "Feature",
  "properties": {
    "iso:country":"US",
    "name:eng_x_preferred":[
        "Mountain Laurel"
    ],
    "wd:wordcount":53,
    "wof:name":"Mountain Laurel",
    "wof:placetype":"neighbourhood",
    "wof:population":322,
    "zs:area_m":254669.825597,
    "zs:blockids":[
        370250425031006,
        370250425031009,
        370250425031005
    ],
    "zs:housing10":97,
    "zs:label":"Mountain Laurel",
    "zs:pop10":322
},
  "geometry": {"coordinates":[-80.65092300000001,35.408491],"type":"Point"}
}