{
  "type": "Feature",
  "properties": {
    "gn:country":"US",
    "gn:fcode":"PPL",
    "gn:population":399,
    "iso:country":"US",
    "name:azb_x_preferred":[
        "\u0631\u0648\u06a9\u0633\u0628\u0648\u0631\u06cc"
    ],
    "name:cat_x_preferred":[
        "Roxbury"
    ],
    "name:ceb_x_preferred":[
        "Roxbury"
    ],
    "name:che_x_preferred":[
        "\u0420\u043e\u043a\u0441\u0431\u0435\u0440\u0438"
    ],
    "name:cym_x_preferred":[
        "Roxbury"
    ],
    "name:deu_x_preferred":[
        "Roxbury"
    ],
    "name:eng_x_preferred":[
        "Roxbury"
    ],
    "name:eus_x_preferred":[
        "Roxbury"
    ],
    "name:fas_x_preferred":[
        "\u0631\u0627\u06a9\u0633\u0628\u0631\u06cc\u060c \u0645\u06cc\u0646"
    ],
    "name:fas_x_variant":[
        "\u0631\u0627\u06a9\u0633\u0628\u0631\u06cc"
    ],
    "name:fra_x_preferred":[
        "Roxbury"
    ],
    "name:hat_x_preferred":[
        "Roxbury"
    ],
    "name:hun_x_preferred":[
        "Roxbury"
    ],
    "name:ita_x_preferred":[
        "Roxbury"
    ],
    "name:jpn_x_preferred":[
        "\u30ed\u30af\u30b9\u30d9\u30ea\u30fc"
    ],
    "name:kaz_x_preferred":[
        "\u0420\u043e\u043a\u0441\u0431\u044e\u0440\u0438"
    ],
    "name:kir_x_preferred":[
        "\u0420\u043e\u043a\u0441\u0431\u044e\u0440\u0438"
    ],
    "name:nld_x_preferred":[
        "Roxbury"
    ],
    "name:pol_x_preferred":[
        "Roxbury"
    ],
    "name:spa_x_preferred":[
        "Roxbury"
    ],
    "name:tat_x_preferred":[
        "\u0420\u043e\u043a\u0441\u0431\u0435\u0440\u0438"
    ],
    "name:tur_x_preferred":[
        "Roxbury"
    ],
    "name:ukr_x_preferred":[
        "\u0420\u043e\u043a\u0441\u0431\u0435\u0440\u0456"
    ],
    "name:vol_x_preferred":[
        "Roxbury"
    ],
    "qs_pg:aaroncc":"US",
    "qs_pg:gn_country":"US",
    "qs_pg:gn_fcode":"PPL",
    "qs_pg:gn_pop":399,
    "qs_pg:name":"Roxbury",
    "qs_pg:name_adm0":"United States",
    "qs_pg:name_adm1":"Maine",
    "qs_pg:photos_9k":1,
    "qs_pg:photos_9r":1,
    "qs_pg:photos_all":1,
    "qs_pg:photos_sr":0,
    "qs_pg:pop_sr":2,
    "qs_pg:qs_pg_placetype":"locality",
    "qs_pg:qs_pg_placetype_gp":"Town",
    "qs_pg:woe_adm0":23424977,
    "woe:adm0_id":23424977,
    "woe:name_adm0":"United States",
    "woe:name_adm1":"Maine",
    "woe:placetype":"Town",
    "wof:coterminous":[
        404475023
    ],
    "wof:name":"Roxbury",
    "wof:placetype":"locality",
    "wof:population":399,
    "wof:statistical_gore":1
},
  "geometry": {"coordinates":[-70.5934,44.66978],"type":"Point"}
}