{
  "type": "Feature",
  "properties": {
    "gn:admin1_code":"TN",
    "gn:admin2_code":"63",
    "gn:asciiname":"Gaby Hills",
    "gn:country_code":"US",
    "gn:dem":380,
    "gn:elevation":"383.0",
    "gn:feature_class":"P",
    "gn:feature_code":"PPL",
    "gn:name":"Gaby Hills",
    "gn:population":0,
    "gn:timezone":"America/New_York",
    "iso:country":"US",
    "wof:name":"Gaby Hills",
    "wof:placetype":"locality"
},
  "geometry": {"coordinates":[-83.29878000000002,36.25037],"type":"Point"}
}