{
  "type": "Feature",
  "properties": {
    "gn:admin1_code":"OH",
    "gn:admin2_code":"143.0",
    "gn:admin3_code":"16308.0",
    "gn:asciiname":"Mobile Home Estates",
    "gn:country_code":"US",
    "gn:dem":200,
    "gn:elevation":"201.0",
    "gn:feature_class":"P",
    "gn:feature_code":"PPL",
    "gn:name":"Mobile Home Estates",
    "gn:population":0,
    "gn:timezone":"America/New_York",
    "iso:country":"US",
    "wof:name":"Mobile Home Estates",
    "wof:placetype":"campus"
},
  "geometry": {"coordinates":[-82.97889000000001,41.31306],"type":"Point"}
}