{
  "type": "Feature",
  "properties": {
    "gn:admin1_code":"FL",
    "gn:admin2_code":"131.0",
    "gn:asciiname":"Steele Church",
    "gn:country_code":"US",
    "gn:dem":47,
    "gn:elevation":"46.0",
    "gn:feature_class":"P",
    "gn:feature_code":"PPL",
    "gn:name":"Steele Church",
    "gn:population":0,
    "gn:timezone":"America/Chicago",
    "iso:country":"US",
    "wof:name":"Steele Church",
    "wof:placetype":"locality"
},
  "geometry": {"coordinates":[-86.14744,30.64852],"type":"Point"}
}