{
  "type": "Feature",
  "properties": {
    "gn:country":"US",
    "gn:fcode":"PPL",
    "gn:population":0,
    "iso:country":"US",
    "name:eng_x_preferred":[
        "Medinah"
    ],
    "name:fas_x_preferred":[
        "\u0645\u062f\u06cc\u0646\u0627\u0647"
    ],
    "name:fra_x_preferred":[
        "Medinah"
    ],
    "name:nld_x_preferred":[
        "Medinah"
    ],
    "name:nob_x_preferred":[
        "Medinah"
    ],
    "name:pol_x_preferred":[
        "Vevay"
    ],
    "name:und_x_variant":[
        "Meacham"
    ],
    "name:urd_x_preferred":[
        "\u0645\u062f\u06cc\u0646\u06c1\u060c \u0627\u0644\u06cc\u0646\u0648\u0627\u0626\u06d2"
    ],
    "name:urd_x_variant":[
        "\u0645\u062f\u06cc\u0646\u06c1"
    ],
    "name:vol_x_preferred":[
        "Medinah"
    ],
    "name:zho_x_preferred":[
        "\u6885\u8fea\u7d0d"
    ],
    "qs_pg:aaroncc":"US",
    "qs_pg:gn_country":"US",
    "qs_pg:gn_fcode":"PPL",
    "qs_pg:gn_pop":0,
    "qs_pg:name":"Medinah",
    "qs_pg:name_adm0":"United States",
    "qs_pg:name_adm1":"Illinois",
    "qs_pg:photos":1614,
    "qs_pg:photos_1k":327,
    "qs_pg:photos_9k":7,
    "qs_pg:photos_9r":8,
    "qs_pg:photos_all":1614,
    "qs_pg:photos_sr":13,
    "qs_pg:pop_sr":7,
    "qs_pg:qs_pg_placetype":"locality",
    "qs_pg:qs_pg_placetype_gp":"Town",
    "qs_pg:woe_adm0":23424977,
    "woe:adm0_id":23424977,
    "woe:name_adm0":"United States",
    "woe:name_adm1":"Illinois",
    "woe:placetype":"Town",
    "wof:name":"Medinah",
    "wof:placetype":"locality"
},
  "geometry": {"coordinates":[-88.05118,41.98142],"type":"Point"}
}