{
  "type": "Feature",
  "properties": {
    "gn:admin1_code":"TX",
    "gn:admin2_code":"83.0",
    "gn:asciiname":"San Angelo Junction",
    "gn:country_code":"US",
    "gn:dem":521,
    "gn:elevation":"517.0",
    "gn:feature_class":"P",
    "gn:feature_code":"PPL",
    "gn:name":"San Angelo Junction",
    "gn:population":0,
    "gn:timezone":"America/Chicago",
    "iso:country":"US",
    "name:eng_x_preferred":[
        "San Angelo Junction"
    ],
    "name:und_x_variant":[
        "Coleman Junction"
    ],
    "wof:name":"San Angelo Junction",
    "wof:placetype":"locality"
},
  "geometry": {"coordinates":[-99.36784,31.77626],"type":"Point"}
}