{
  "type": "Feature",
  "properties": {
    "gn:admin1_code":"OK",
    "gn:admin2_code":"117",
    "gn:asciiname":"Leroy",
    "gn:country_code":"US",
    "gn:dem":254,
    "gn:elevation":"251.0",
    "gn:feature_class":"P",
    "gn:feature_code":"PPL",
    "gn:name":"Leroy",
    "gn:population":0,
    "gn:timezone":"America/Chicago",
    "iso:country":"US",
    "name:cat_x_preferred":[
        "Leroy"
    ],
    "name:ceb_x_preferred":[
        "Leroy"
    ],
    "name:deu_x_preferred":[
        "Leroy"
    ],
    "name:fra_x_preferred":[
        "Leroy"
    ],
    "name:ita_x_preferred":[
        "Leroy"
    ],
    "name:nld_x_preferred":[
        "Leroy"
    ],
    "name:pol_x_preferred":[
        "Leroy"
    ],
    "name:por_x_preferred":[
        "Leroy"
    ],
    "name:ron_x_preferred":[
        "Leroy"
    ],
    "name:srp_x_preferred":[
        "\u041b\u0438\u0440\u043e\u0458"
    ],
    "name:swe_x_preferred":[
        "Leroy"
    ],
    "name:ukr_x_preferred":[
        "\u041b\u0435\u0440\u043e\u0439"
    ],
    "wof:name":"Leroy",
    "wof:placetype":"locality"
},
  "geometry": {"coordinates":[-96.25696000000001,36.21036],"type":"Point"}
}