{
  "type": "Feature",
  "properties": {
    "gn:admin1_code":"MI",
    "gn:admin2_code":"73.0",
    "gn:admin3_code":"15580.0",
    "gn:asciiname":"Alembic",
    "gn:country_code":"US",
    "gn:dem":225,
    "gn:elevation":"226.0",
    "gn:feature_class":"P",
    "gn:feature_code":"PPL",
    "gn:name":"Alembic",
    "gn:population":0,
    "gn:timezone":"America/Detroit",
    "iso:country":"US",
    "name:ara_x_preferred":[
        "\u0625\u0646\u0628\u064a\u0642"
    ],
    "name:bel_x_preferred":[
        "\u0410\u043b\u0430\u043c\u0431\u0456\u043a"
    ],
    "name:cat_x_preferred":[
        "Alamb\u00ed"
    ],
    "name:ces_x_preferred":[
        "Alembik"
    ],
    "name:chv_x_preferred":[
        "\u0410\u043b\u0430\u043c\u0431\u0438\u043a"
    ],
    "name:deu_x_preferred":[
        "Alembik"
    ],
    "name:epo_x_preferred":[
        "Alambiko"
    ],
    "name:fas_x_preferred":[
        "\u0627\u0646\u0628\u06cc\u0642"
    ],
    "name:fra_x_preferred":[
        "Alambic"
    ],
    "name:glg_x_preferred":[
        "Alambique"
    ],
    "name:ido_x_preferred":[
        "Alambiko"
    ],
    "name:ind_x_preferred":[
        "Alembik"
    ],
    "name:ita_x_preferred":[
        "Alambicco"
    ],
    "name:jpn_x_preferred":[
        "\u30a2\u30e9\u30f3\u30d3\u30c3\u30af"
    ],
    "name:lat_x_preferred":[
        "Alembicus"
    ],
    "name:nld_x_preferred":[
        "Alambiek"
    ],
    "name:oci_x_preferred":[
        "Alambic"
    ],
    "name:pol_x_preferred":[
        "Alembik"
    ],
    "name:por_x_preferred":[
        "Alambique"
    ],
    "name:ron_x_preferred":[
        "Alambic"
    ],
    "name:rus_x_preferred":[
        "\u0410\u043b\u0430\u043c\u0431\u0438\u043a"
    ],
    "name:scn_x_preferred":[
        "Allammiccu"
    ],
    "name:spa_x_preferred":[
        "Alambique"
    ],
    "name:srp_x_preferred":[
        "\u0410\u043b\u0435\u043c\u0431\u0438\u043a"
    ],
    "name:tgk_x_preferred":[
        "\u0410\u043d\u0431\u0438\u049b"
    ],
    "name:tur_x_preferred":[
        "\u0130mbik"
    ],
    "name:ukr_x_preferred":[
        "\u0410\u043b\u0430\u043c\u0431\u0456\u043a"
    ],
    "wof:name":"Alembic",
    "wof:placetype":"locality"
},
  "geometry": {"coordinates":[-84.66834,43.59753],"type":"Point"}
}