{
  "type": "Feature",
  "properties": {
    "iso:country":"US",
    "name:urd_x_preferred":[
        "\u0628\u0631\u0648\u0645\u0644\u06cc \u0645\u0627\u0624\u0646\u0679\u06cc\u0646"
    ],
    "qs_pg:aaroncc":"US",
    "qs_pg:name":"Bromley Mountain",
    "qs_pg:name_adm0":"United States",
    "qs_pg:name_adm1":"Vermont",
    "qs_pg:photos":297,
    "qs_pg:photos_1k":60,
    "qs_pg:photos_9k":1,
    "qs_pg:photos_9r":4,
    "qs_pg:photos_all":297,
    "qs_pg:photos_sr":5,
    "qs_pg:pop_sr":0,
    "qs_pg:qs_pg_placetype":"locality",
    "qs_pg:qs_pg_placetype_gp":"Town",
    "qs_pg:woe_adm0":23424977,
    "woe:adm0_id":23424977,
    "woe:name_adm0":"United States",
    "woe:name_adm1":"Vermont",
    "woe:placetype":"Town",
    "wof:name":"Bromley Mountain",
    "wof:placetype":"locality"
},
  "geometry": {"coordinates":[-72.938039,43.214684],"type":"Point"}
}