{
  "type": "Feature",
  "properties": {
    "gn:admin1_code":"TX",
    "gn:admin2_code":"99",
    "gn:asciiname":"Levita",
    "gn:country_code":"US",
    "gn:dem":283,
    "gn:elevation":"280.0",
    "gn:feature_class":"P",
    "gn:feature_code":"PPL",
    "gn:name":"Levita",
    "gn:population":0,
    "gn:timezone":"America/Chicago",
    "iso:country":"US",
    "name:deu_x_preferred":[
        "Levita"
    ],
    "name:eng_x_preferred":[
        "Levita"
    ],
    "name:slk_x_preferred":[
        "Levita"
    ],
    "name:spa_x_preferred":[
        "Levita"
    ],
    "name:und_x_variant":[
        "Simpsonville"
    ],
    "wof:name":"Levita",
    "wof:placetype":"locality"
},
  "geometry": {"coordinates":[-97.88808,31.51488],"type":"Point"}
}