{
  "type": "Feature",
  "properties": {
    "gn:admin1_code":"VA",
    "gn:admin2_code":"75",
    "gn:asciiname":"Deerfield",
    "gn:country_code":"US",
    "gn:dem":80,
    "gn:elevation":"77.0",
    "gn:feature_class":"P",
    "gn:feature_code":"PPL",
    "gn:name":"Deerfield",
    "gn:population":0,
    "gn:timezone":"America/New_York",
    "iso:country":"US",
    "name:cat_x_preferred":[
        "Deerfield"
    ],
    "name:ceb_x_preferred":[
        "Deerfield"
    ],
    "name:deu_x_preferred":[
        "Deerfield"
    ],
    "name:fas_x_preferred":[
        "\u062f\u06cc\u0631\u0641\u06cc\u0644\u062f"
    ],
    "name:fra_x_preferred":[
        "Deerfield"
    ],
    "name:ita_x_preferred":[
        "Deerfield"
    ],
    "name:kor_x_preferred":[
        "\ub514\uc5b4\ud544\ub4dc"
    ],
    "name:nld_x_preferred":[
        "Deerfield"
    ],
    "name:pol_x_preferred":[
        "Deerfield"
    ],
    "name:por_x_preferred":[
        "Deerfield"
    ],
    "name:rus_x_preferred":[
        "\u0414\u0438\u0440\u0444\u0438\u043b\u0434"
    ],
    "name:spa_x_preferred":[
        "Deerfield"
    ],
    "name:srp_x_preferred":[
        "\u0414\u0438\u0440\u0444\u0438\u043b\u0434"
    ],
    "name:swe_x_preferred":[
        "Deerfield"
    ],
    "name:ukr_x_preferred":[
        "\u0414\u0456\u0435\u0440\u0444\u0456\u043b\u0434"
    ],
    "name:vol_x_preferred":[
        "Deerfield"
    ],
    "wof:name":"Deerfield",
    "wof:placetype":"locality"
},
  "geometry": {"coordinates":[-77.82694000000002,37.66959],"type":"Point"}
}