{
  "type": "Feature",
  "properties": {
    "gn:admin1_code":"VA",
    "gn:admin2_code":"27",
    "gn:asciiname":"Kelsa",
    "gn:country_code":"US",
    "gn:dem":295,
    "gn:elevation":"286.0",
    "gn:feature_class":"P",
    "gn:feature_code":"PPL",
    "gn:name":"Kelsa",
    "gn:population":0,
    "gn:timezone":"America/New_York",
    "iso:country":"US",
    "name:eng_x_preferred":[
        "Kelsa"
    ],
    "name:und_x_variant":[
        "Kelsea"
    ],
    "wof:name":"Kelsa",
    "wof:placetype":"locality"
},
  "geometry": {"coordinates":[-82.06874000000001,37.44066],"type":"Point"}
}