{
  "type": "Feature",
  "properties": {
    "gn:admin1_code":"FL",
    "gn:admin2_code":"45.0",
    "gn:asciiname":"Lake Grove",
    "gn:country_code":"US",
    "gn:dem":13,
    "gn:elevation":"6.0",
    "gn:feature_class":"P",
    "gn:feature_code":"PPL",
    "gn:name":"Lake Grove",
    "gn:population":0,
    "gn:timezone":"America/Chicago",
    "iso:country":"US",
    "name:pol_x_preferred":[
        "Lake Grove"
    ],
    "wof:name":"Lake Grove",
    "wof:placetype":"locality"
},
  "geometry": {"coordinates":[-85.17519,30.11881],"type":"Point"}
}