{
  "type": "Feature",
  "properties": {
    "gn:admin1_code":"KY",
    "gn:admin2_code":"13",
    "gn:asciiname":"Cary",
    "gn:country_code":"US",
    "gn:dem":336,
    "gn:elevation":"312.0",
    "gn:feature_class":"P",
    "gn:feature_code":"PPL",
    "gn:name":"Cary",
    "gn:population":0,
    "gn:timezone":"America/New_York",
    "iso:country":"US",
    "name:cat_x_preferred":[
        "Cary"
    ],
    "name:ceb_x_preferred":[
        "Cary"
    ],
    "name:deu_x_preferred":[
        "Cary"
    ],
    "name:eng_x_preferred":[
        "Cary"
    ],
    "name:fra_x_preferred":[
        "Cary"
    ],
    "name:ita_x_preferred":[
        "Cary"
    ],
    "name:nld_x_preferred":[
        "Cary"
    ],
    "name:pol_x_preferred":[
        "Cary"
    ],
    "name:por_x_preferred":[
        "Cary"
    ],
    "name:rus_x_preferred":[
        "\u041a\u044d\u0440\u0438"
    ],
    "name:sco_x_preferred":[
        "Cary"
    ],
    "name:spa_x_preferred":[
        "Cary"
    ],
    "name:swe_x_preferred":[
        "Cary"
    ],
    "name:und_x_variant":[
        "Poordo"
    ],
    "name:vol_x_preferred":[
        "Cary"
    ],
    "wof:name":"Cary",
    "wof:placetype":"locality"
},
  "geometry": {"coordinates":[-83.66436,36.7937],"type":"Point"}
}