{
  "type": "Feature",
  "properties": {
    "gn:admin1_code":"FL",
    "gn:admin2_code":"1.0",
    "gn:asciiname":"Newnansville",
    "gn:country_code":"US",
    "gn:dem":39,
    "gn:elevation":"43.0",
    "gn:feature_class":"P",
    "gn:feature_code":"PPL",
    "gn:name":"Newnansville",
    "gn:population":0,
    "gn:timezone":"America/New_York",
    "iso:country":"US",
    "wof:name":"Newnansville",
    "wof:placetype":"locality"
},
  "geometry": {"coordinates":[-82.47678000000001,29.80858],"type":"Point"}
}