{
  "type": "Feature",
  "properties": {
    "gn:admin1_code":"WA",
    "gn:admin2_code":"33.0",
    "gn:asciiname":"Junction",
    "gn:country_code":"US",
    "gn:dem":237,
    "gn:elevation":"227.0",
    "gn:feature_class":"P",
    "gn:feature_code":"PPL",
    "gn:name":"Junction",
    "gn:population":0,
    "gn:timezone":"America/Los_Angeles",
    "iso:country":"US",
    "name:cat_x_preferred":[
        "Junction"
    ],
    "name:ceb_x_preferred":[
        "Junction"
    ],
    "name:deu_x_preferred":[
        "Junction"
    ],
    "name:fra_x_preferred":[
        "Jonction"
    ],
    "name:ita_x_preferred":[
        "Junction"
    ],
    "name:jpn_x_preferred":[
        "\u30b8\u30e3\u30f3\u30af\u30b7\u30e7\u30f3"
    ],
    "name:nld_x_preferred":[
        "Junction"
    ],
    "name:pol_x_preferred":[
        "Junction"
    ],
    "name:por_x_preferred":[
        "Junction"
    ],
    "name:rus_x_preferred":[
        "\u0414\u0436\u0430\u043d\u043a\u0448\u0435\u043d"
    ],
    "name:sna_x_preferred":[
        "Masanga"
    ],
    "name:spa_x_preferred":[
        "Junction"
    ],
    "name:srp_x_preferred":[
        "\u040f\u0430\u043d\u043a\u0448\u043e\u043d"
    ],
    "name:swe_x_preferred":[
        "Junction"
    ],
    "name:ukr_x_preferred":[
        "\u0414\u0436\u0430\u043d\u043a\u0448\u0435\u043d"
    ],
    "name:vol_x_preferred":[
        "Junction"
    ],
    "wof:name":"Junction",
    "wof:placetype":"locality"
},
  "geometry": {"coordinates":[-121.80234,47.61371],"type":"Point"}
}