{
  "type": "Feature",
  "properties": {
    "gn:admin1_code":"OK",
    "gn:admin2_code":"141",
    "gn:asciiname":"Burt",
    "gn:country_code":"US",
    "gn:dem":418,
    "gn:elevation":"413.0",
    "gn:feature_class":"P",
    "gn:feature_code":"PPL",
    "gn:name":"Burt",
    "gn:population":0,
    "gn:timezone":"America/Chicago",
    "iso:country":"US",
    "name:fas_x_preferred":[
        "\u0628\u0631\u062a"
    ],
    "wof:name":"Burt",
    "wof:placetype":"locality"
},
  "geometry": {"coordinates":[-99.08091,34.45036],"type":"Point"}
}