{
  "type": "Feature",
  "properties": {
    "gn:admin1_code":"KY",
    "gn:admin2_code":"87",
    "gn:asciiname":"Black Gnat",
    "gn:country_code":"US",
    "gn:dem":254,
    "gn:elevation":"258.0",
    "gn:feature_class":"P",
    "gn:feature_code":"PPL",
    "gn:name":"Black Gnat",
    "gn:population":0,
    "gn:timezone":"America/Chicago",
    "iso:country":"US",
    "wof:name":"Black Gnat",
    "wof:placetype":"locality"
},
  "geometry": {"coordinates":[-85.43635,37.30423],"type":"Point"}
}