{
  "type": "Feature",
  "properties": {
    "gn:admin1_code":"SC",
    "gn:admin2_code":"13.0",
    "gn:asciiname":"Chisolms",
    "gn:country_code":"US",
    "gn:dem":7,
    "gn:elevation":"2.0",
    "gn:feature_class":"P",
    "gn:feature_code":"PPL",
    "gn:name":"Chisolms",
    "gn:population":0,
    "gn:timezone":"America/New_York",
    "iso:country":"US",
    "name:eng_x_preferred":[
        "Chisolms"
    ],
    "name:und_x_variant":[
        "Chisholm"
    ],
    "wof:name":"Chisolms",
    "wof:placetype":"locality"
},
  "geometry": {"coordinates":[-80.67316,32.57574],"type":"Point"}
}