{
  "type": "Feature",
  "properties": {
    "gn:country":"US",
    "gn:fcode":"PPL",
    "gn:population":0,
    "iso:country":"US",
    "name:azb_x_preferred":[
        "\u0647\u06cc\u0644\u0633 \u0641\u0644\u0627\u062a"
    ],
    "name:eng_x_preferred":[
        "Hills Flat"
    ],
    "name:fas_x_preferred":[
        "\u0647\u06cc\u0644\u0632 \u0641\u0644\u062a"
    ],
    "name:fra_x_preferred":[
        "Hills Flat"
    ],
    "name:tur_x_preferred":[
        "Hills Flat"
    ],
    "name:zho_x_preferred":[
        "\u5e0c\u723e\u65af\u5f17\u62c9\u7279"
    ],
    "qs_pg:aaroncc":"US",
    "qs_pg:gn_country":"US",
    "qs_pg:gn_fcode":"PPL",
    "qs_pg:gn_pop":0,
    "qs_pg:name":"Hills Flat",
    "qs_pg:name_adm0":"United States",
    "qs_pg:name_adm1":"California",
    "qs_pg:photos":46,
    "qs_pg:photos_1k":9,
    "qs_pg:photos_9k":1,
    "qs_pg:photos_9r":2,
    "qs_pg:photos_all":46,
    "qs_pg:photos_sr":2,
    "qs_pg:pop_sr":0,
    "qs_pg:qs_pg_placetype":"locality",
    "qs_pg:qs_pg_placetype_gp":"Town",
    "qs_pg:woe_adm0":23424977,
    "woe:adm0_id":23424977,
    "woe:name_adm0":"United States",
    "woe:name_adm1":"California",
    "woe:placetype":"Town",
    "wof:name":"Hills Flat",
    "wof:placetype":"locality"
},
  "geometry": {"coordinates":[-121.05328,39.22406],"type":"Point"}
}