{
  "type": "Feature",
  "properties": {
    "iso:country":"US",
    "name:bul_x_preferred":[
        "\u0411\u0440\u0435\u0439\u043c\u0430\u0440"
    ],
    "name:ceb_x_preferred":[
        "Braemar"
    ],
    "name:cym_x_preferred":[
        "Braemar"
    ],
    "name:deu_x_preferred":[
        "Braemar"
    ],
    "name:eng_x_preferred":[
        "Braemar"
    ],
    "name:eus_x_preferred":[
        "Braemar"
    ],
    "name:fas_x_preferred":[
        "\u0628\u0631\u0627\u0626\u0645\u0627\u0631"
    ],
    "name:fra_x_preferred":[
        "Braemar"
    ],
    "name:gla_x_preferred":[
        "Br\u00e0igh Mh\u00e0rr"
    ],
    "name:gle_x_preferred":[
        "Baile Chaisteil"
    ],
    "name:ind_x_preferred":[
        "Braemar"
    ],
    "name:ita_x_preferred":[
        "Braemar"
    ],
    "name:nld_x_preferred":[
        "Braemar"
    ],
    "name:nno_x_preferred":[
        "Braemar"
    ],
    "name:nor_x_preferred":[
        "Braemar"
    ],
    "name:pol_x_preferred":[
        "Braemar"
    ],
    "name:sco_x_preferred":[
        "Braemar"
    ],
    "name:spa_x_preferred":[
        "Braemar"
    ],
    "name:swe_x_preferred":[
        "Braemar"
    ],
    "wd:wordcount":1596,
    "wof:name":"Braemar",
    "wof:placetype":"neighbourhood",
    "wof:population":12,
    "zs:area_m":1302061.153634,
    "zs:blockids":[
        240253024002001,
        240253024002050,
        240253024002051,
        240253024002000
    ],
    "zs:housing10":5,
    "zs:label":"Braemar",
    "zs:pop10":12
},
  "geometry": {"coordinates":[-76.186588,39.477326],"type":"Point"}
}