{
  "type": "Feature",
  "properties": {
    "iso:country":"US",
    "wof:name":"Freeman Estate",
    "wof:placetype":"neighbourhood"
},
  "geometry": {"coordinates":[-83.69123571679656,42.2413438755062],"type":"Point"}
}