{
  "type": "Feature",
  "properties": {
    "gn:admin1_code":"AZ",
    "gn:admin2_code":"13.0",
    "gn:asciiname":"Pony Acres Mobile Home Park",
    "gn:country_code":"US",
    "gn:dem":362,
    "gn:elevation":"361.0",
    "gn:feature_class":"P",
    "gn:feature_code":"PPL",
    "gn:name":"Pony Acres Mobile Home Park",
    "gn:population":0,
    "gn:timezone":"America/Phoenix",
    "iso:country":"US",
    "wof:name":"Pony Acres Mobile Home Park",
    "wof:placetype":"campus"
},
  "geometry": {"coordinates":[-111.90598,33.41338],"type":"Point"}
}