{
  "type": "Feature",
  "properties": {
    "iso:country":"US",
    "name:eng_x_preferred":[
        "Hawks Ridge"
    ],
    "wof:name":"Hawks Ridge",
    "wof:placetype":"neighbourhood",
    "wof:population":495,
    "zs:area_m":8036090.802998,
    "zs:blockids":[
        130570905011028,
        130570905011014,
        130570905011008,
        130570905011011,
        130570905011033,
        130570905011015,
        130570905011030,
        130570905011012,
        130570905011027,
        130570905011031,
        130570905011016
    ],
    "zs:housing10":202,
    "zs:label":"Hawks Ridge",
    "zs:pop10":495
},
  "geometry": {"coordinates":[-84.273318,34.260699],"type":"Point"}
}