{
  "type": "Feature",
  "properties": {
    "gn:admin1_code":"IA",
    "gn:admin2_code":"55.0",
    "gn:admin3_code":"93132.0",
    "gn:asciiname":"Rockville",
    "gn:country_code":"US",
    "gn:dem":288,
    "gn:elevation":"282.0",
    "gn:feature_class":"P",
    "gn:feature_code":"PPL",
    "gn:name":"Rockville",
    "gn:population":0,
    "gn:timezone":"America/Chicago",
    "iso:country":"US",
    "wof:name":"Rockville",
    "wof:placetype":"locality"
},
  "geometry": {"coordinates":[-91.14208000000001,42.41861],"type":"Point"}
}