{
  "type": "Feature",
  "properties": {
    "gn:admin1_code":"MI",
    "gn:admin2_code":"91.0",
    "gn:admin3_code":"27020.0",
    "gn:asciiname":"Ridgeville",
    "gn:country_code":"US",
    "gn:dem":223,
    "gn:elevation":"223.0",
    "gn:feature_class":"P",
    "gn:feature_code":"PPL",
    "gn:name":"Ridgeville",
    "gn:population":0,
    "gn:timezone":"America/Detroit",
    "iso:country":"US",
    "name:ceb_x_preferred":[
        "Ridgeville"
    ],
    "name:deu_x_preferred":[
        "Ridgeville"
    ],
    "name:fra_x_preferred":[
        "Ridgeville"
    ],
    "name:ind_x_preferred":[
        "Ridgeville"
    ],
    "name:ita_x_preferred":[
        "Ridgeville"
    ],
    "name:nld_x_preferred":[
        "Ridgeville"
    ],
    "name:pol_x_preferred":[
        "Ridgeville"
    ],
    "name:srp_x_preferred":[
        "\u0420\u0438\u045f\u0432\u0438\u043b"
    ],
    "name:ukr_x_preferred":[
        "\u0420\u0438\u0434\u0436\u0432\u0456\u043b\u043b"
    ],
    "name:vol_x_preferred":[
        "Ridgeville"
    ],
    "wof:name":"Ridgeville",
    "wof:placetype":"locality"
},
  "geometry": {"coordinates":[-84.02161,41.75727],"type":"Point"}
}