{
  "type": "Feature",
  "properties": {
    "iso:country":"US",
    "name:eng_x_preferred":[
        "College Hills"
    ],
    "wof:name":"College Hills",
    "wof:placetype":"neighbourhood",
    "wof:population":348,
    "zs:area_m":384976.444767,
    "zs:blockids":[
        470930070002003
    ],
    "zs:housing10":115,
    "zs:label":"College Hills",
    "zs:pop10":348
},
  "geometry": {"coordinates":[-83.946538,35.971265],"type":"Point"}
}