{
  "type": "Feature",
  "properties": {
    "gn:admin1_code":"MD",
    "gn:admin2_code":"019",
    "gn:asciiname":"Wesley",
    "gn:country_code":"US",
    "gn:dem":2,
    "gn:elevation":"1.0",
    "gn:feature_class":"P",
    "gn:feature_code":"PPL",
    "gn:name":"Wesley",
    "gn:population":0,
    "gn:timezone":"America/New_York",
    "iso:country":"US",
    "name:deu_x_preferred":[
        "Wesley"
    ],
    "name:fin_x_preferred":[
        "Wesley"
    ],
    "wof:name":"Wesley",
    "wof:placetype":"locality"
},
  "geometry": {"coordinates":[-76.08327,38.34707],"type":"Point"}
}