{
  "type": "Feature",
  "properties": {
    "gn:admin1_code":"MD",
    "gn:admin2_code":"3.0",
    "gn:asciiname":"Little John",
    "gn:country_code":"US",
    "gn:dem":22,
    "gn:elevation":"24.0",
    "gn:feature_class":"P",
    "gn:feature_code":"PPL",
    "gn:name":"Little John",
    "gn:population":0,
    "gn:timezone":"America/New_York",
    "iso:country":"US",
    "name:deu_x_preferred":[
        "Little John"
    ],
    "name:fin_x_preferred":[
        "Pikku John"
    ],
    "name:fra_x_preferred":[
        "Petit Jean"
    ],
    "name:heb_x_preferred":[
        "\u05d2'\u05d5\u05df \u05d4\u05e7\u05d8\u05df"
    ],
    "name:hye_x_preferred":[
        "\u0553\u0578\u0584\u0580\u056b\u056f \u054b\u0578\u0576"
    ],
    "name:ita_x_preferred":[
        "Little John"
    ],
    "name:nld_x_preferred":[
        "Kleine Jan"
    ],
    "name:pol_x_preferred":[
        "Ma\u0142y John"
    ],
    "name:rus_x_preferred":[
        "\u041c\u0430\u043b\u0435\u043d\u044c\u043a\u0438\u0439 \u0414\u0436\u043e\u043d"
    ],
    "name:spa_x_preferred":[
        "Little John"
    ],
    "name:swe_x_preferred":[
        "Lille John"
    ],
    "name:tgl_x_preferred":[
        "Little John"
    ],
    "name:tur_x_preferred":[
        "K\u00fc\u00e7\u00fck John"
    ],
    "wof:name":"Little John",
    "wof:placetype":"locality"
},
  "geometry": {"coordinates":[-76.53635,39.02594000000001],"type":"Point"}
}