{
  "type": "Feature",
  "properties": {
    "gn:admin1_code":"LA",
    "gn:admin2_code":"11.0",
    "gn:asciiname":"Kernan",
    "gn:country_code":"US",
    "gn:dem":25,
    "gn:elevation":"20.0",
    "gn:feature_class":"P",
    "gn:feature_code":"PPL",
    "gn:name":"Kernan",
    "gn:population":0,
    "gn:timezone":"America/Chicago",
    "iso:country":"US",
    "name:deu_x_preferred":[
        "Kernan"
    ],
    "name:eng_x_preferred":[
        "Kernan"
    ],
    "name:und_x_variant":[
        "Bear"
    ],
    "wof:name":"Kernan",
    "wof:placetype":"locality"
},
  "geometry": {"coordinates":[-93.26237999999999,30.50714],"type":"Point"}
}