{
  "type": "Feature",
  "properties": {
    "gn:admin1_code":"MD",
    "gn:admin2_code":"19.0",
    "gn:asciiname":"Thompson",
    "gn:country_code":"US",
    "gn:dem":4,
    "gn:elevation":"4.0",
    "gn:feature_class":"P",
    "gn:feature_code":"PPL",
    "gn:name":"Thompson",
    "gn:population":0,
    "gn:timezone":"America/New_York",
    "iso:country":"US",
    "name:bel_x_preferred":[
        "\u0422\u043e\u043c\u043f\u0441\u0430\u043d"
    ],
    "name:bul_x_preferred":[
        "\u0422\u043e\u043c\u043f\u0441\u044a\u043d"
    ],
    "name:cat_x_preferred":[
        "Thompson"
    ],
    "name:ceb_x_preferred":[
        "Thompson"
    ],
    "name:ces_x_preferred":[
        "Thompson"
    ],
    "name:deu_x_preferred":[
        "Thompson"
    ],
    "name:fin_x_preferred":[
        "Thompson"
    ],
    "name:fra_x_preferred":[
        "Thompson"
    ],
    "name:heb_x_preferred":[
        "\u05ea\u05d5\u05de\u05e4\u05e1\u05d5\u05df"
    ],
    "name:hrv_x_preferred":[
        "Thompson"
    ],
    "name:ita_x_preferred":[
        "Thompson"
    ],
    "name:jpn_x_preferred":[
        "\u30c8\u30f3\u30d7\u30bd\u30f3"
    ],
    "name:kor_x_preferred":[
        "\ud1b0\uc2a8"
    ],
    "name:kor_x_variant":[
        "\ud1b0\ud504\uc2a8"
    ],
    "name:lav_x_preferred":[
        "Tompsons"
    ],
    "name:nld_x_preferred":[
        "Thompson"
    ],
    "name:nor_x_preferred":[
        "Thompson"
    ],
    "name:pol_x_preferred":[
        "Thompson"
    ],
    "name:por_x_preferred":[
        "Thompson"
    ],
    "name:ron_x_preferred":[
        "Thompson"
    ],
    "name:rus_x_preferred":[
        "\u0422\u043e\u043c\u043f\u0441\u043e\u043d"
    ],
    "name:slv_x_preferred":[
        "Thompson"
    ],
    "name:spa_x_preferred":[
        "Thompson"
    ],
    "name:srp_x_preferred":[
        "\u0422\u043e\u043c\u043f\u0441\u043e\u043d"
    ],
    "name:swe_x_preferred":[
        "Thompson"
    ],
    "name:tur_x_preferred":[
        "Thompson"
    ],
    "name:ukr_x_preferred":[
        "\u0422\u043e\u043c\u043f\u0441\u043e\u043d"
    ],
    "name:urd_x_preferred":[
        "\u062a\u06be\u0627\u0645\u067e\u0633\u0646"
    ],
    "name:vie_x_preferred":[
        "S\u00f4ng Thompson"
    ],
    "name:vie_x_variant":[
        "Thompson"
    ],
    "name:vol_x_preferred":[
        "Thompson"
    ],
    "name:zho_x_preferred":[
        "\u6c64\u666e\u68ee"
    ],
    "wof:name":"Thompson",
    "wof:placetype":"locality"
},
  "geometry": {"coordinates":[-76.03077,38.53595],"type":"Point"}
}