{
  "type": "Feature",
  "properties": {
    "gn:admin1_code":"VA",
    "gn:admin2_code":"67",
    "gn:asciiname":"Waidsboro",
    "gn:country_code":"US",
    "gn:dem":390,
    "gn:elevation":"391.0",
    "gn:feature_class":"P",
    "gn:feature_code":"PPL",
    "gn:name":"Waidsboro",
    "gn:population":0,
    "gn:timezone":"America/New_York",
    "iso:country":"US",
    "name:eng_x_preferred":[
        "Waidsboro"
    ],
    "name:und_x_variant":[
        "Lanahan"
    ],
    "wof:name":"Waidsboro",
    "wof:placetype":"locality"
},
  "geometry": {"coordinates":[-79.95976,36.94875],"type":"Point"}
}