{
  "type": "Feature",
  "properties": {
    "gn:admin1_code":"AL",
    "gn:admin2_code":"79.0",
    "gn:asciiname":"Youngtown",
    "gn:country_code":"US",
    "gn:dem":208,
    "gn:elevation":"205.0",
    "gn:feature_class":"P",
    "gn:feature_code":"PPL",
    "gn:name":"Youngtown",
    "gn:population":0,
    "gn:timezone":"America/Chicago",
    "iso:country":"US",
    "name:eng_x_preferred":[
        "Youngtown"
    ],
    "name:fas_x_preferred":[
        "\u06cc\u0627\u0646\u06af\u0633\u062a\u0627\u0648\u0646"
    ],
    "name:und_x_variant":[
        "Young Town",
        "Youngs Store"
    ],
    "name:zho_x_preferred":[
        "\u694a\u683c\u6566"
    ],
    "wof:name":"Youngtown",
    "wof:placetype":"locality"
},
  "geometry": {"coordinates":[-87.39085,34.41676],"type":"Point"}
}