{
  "type": "Feature",
  "properties": {
    "gn:country":"US",
    "gn:fcode":"PPL",
    "gn:population":0,
    "iso:country":"US",
    "name:ara_x_preferred":[
        "\u062a\u064a\u0646\u0645\u0648\u062b"
    ],
    "name:cat_x_preferred":[
        "Tinmouth"
    ],
    "name:deu_x_preferred":[
        "Tinmouth"
    ],
    "name:eng_x_preferred":[
        "Tinmouth"
    ],
    "name:eus_x_preferred":[
        "Tinmouth"
    ],
    "name:fra_x_preferred":[
        "Tinmouth"
    ],
    "name:hat_x_preferred":[
        "Tinmouth"
    ],
    "name:hun_x_preferred":[
        "Tinmouth"
    ],
    "name:ita_x_preferred":[
        "Tinmouth"
    ],
    "name:pol_x_preferred":[
        "Tinmouth"
    ],
    "name:spa_x_preferred":[
        "Tinmouth"
    ],
    "name:swe_x_preferred":[
        "Tinmouth"
    ],
    "name:uzb_x_preferred":[
        "Tinmouth"
    ],
    "name:vol_x_preferred":[
        "Tinmouth"
    ],
    "qs_pg:aaroncc":"US",
    "qs_pg:gn_country":"US",
    "qs_pg:gn_fcode":"PPL",
    "qs_pg:gn_pop":0,
    "qs_pg:name":"Tinmouth",
    "qs_pg:name_adm0":"United States",
    "qs_pg:name_adm1":"Vermont",
    "qs_pg:photos":47,
    "qs_pg:photos_1k":10,
    "qs_pg:photos_9k":1,
    "qs_pg:photos_9r":2,
    "qs_pg:photos_all":49,
    "qs_pg:photos_sr":2,
    "qs_pg:pop_sr":0,
    "qs_pg:qs_pg_placetype":"locality",
    "qs_pg:qs_pg_placetype_gp":"Town",
    "qs_pg:woe_adm0":23424977,
    "woe:adm0_id":23424977,
    "woe:name_adm0":"United States",
    "woe:name_adm1":"Vermont",
    "woe:placetype":"Town",
    "wof:name":"Tinmouth",
    "wof:placetype":"locality"
},
  "geometry": {"coordinates":[-73.04955,43.44868],"type":"Point"}
}