{
  "type": "Feature",
  "properties": {
    "gn:admin1_code":"OH",
    "gn:admin2_code":"167",
    "gn:admin3_code":"55356.0",
    "gn:asciiname":"Yankeeburg",
    "gn:country_code":"US",
    "gn:dem":228,
    "gn:elevation":"218.0",
    "gn:feature_class":"P",
    "gn:feature_code":"PPL",
    "gn:name":"Yankeeburg",
    "gn:population":0,
    "gn:timezone":"America/New_York",
    "iso:country":"US",
    "name:eng_x_preferred":[
        "Yankeeburg"
    ],
    "name:und_x_variant":[
        "Yankeeburgh"
    ],
    "wof:name":"Yankeeburg",
    "wof:placetype":"locality"
},
  "geometry": {"coordinates":[-81.34317,39.38035],"type":"Point"}
}