{
  "type": "Feature",
  "properties": {
    "gn:elevation":186,
    "iso:country":"US",
    "name:deu_x_preferred":[
        "Kleeblatt"
    ],
    "name:eng_x_preferred":[
        "Cloverleaf"
    ],
    "name:srp_x_preferred":[
        "\u041a\u043b\u043e\u0432\u0435\u0440\u043b\u0438\u0444"
    ],
    "qs:gn_adm0_cc":"US",
    "qs:gn_fcode":"PPLX",
    "qs:gn_local":4830796,
    "qs:gn_nam_loc":"auburn",
    "qs:gn_namadm1":"AL",
    "qs:gn_name":"Cloverleaf",
    "qs:local_max":2313,
    "qs:local_sum":8751,
    "qs:localhoods":21,
    "qs:name":"Cloverleaf",
    "qs:name_adm0":"United States",
    "qs:name_adm1":"Alabama",
    "qs:name_adm2":"Lee",
    "qs:name_local":"Auburn",
    "qs:photo_max":23,
    "qs:photo_sum":48,
    "qs:placetype":"Suburb",
    "qs:quad_count":4,
    "qs:woe_adm0":23424977,
    "qs:woe_adm1":2347559,
    "qs:woe_adm2":12587527,
    "qs:woe_lau":0,
    "qs:woe_local":2357287,
    "qs:woe_ver":"7.10.0",
    "wd:wordcount":142,
    "wof:lang":[
        "eng"
    ],
    "wof:name":"Cloverleaf",
    "wof:placetype":"neighbourhood",
    "wof:population":1319,
    "zs:blockids":[
        10810404003009,
        10810404002028,
        10810404003002,
        10810404003001,
        10810404003006,
        10810404003003,
        10810404003014,
        10810404003027,
        10810404003000,
        10810405002066,
        10810404003004,
        10810407002025,
        10810407001017,
        10810404003024,
        10810404003025,
        10810404002026,
        10810404003012,
        10810404003029,
        10810404002027,
        10810404002022,
        10810404003026,
        10810404003005,
        10810404003008,
        10810403002010,
        10810404003011,
        10810404002029,
        10810404003007,
        10810404003023,
        10810404003013,
        10810405002071,
        10810405001001,
        10810405001000,
        10810404003030,
        10810404002021,
        10810404002014,
        10810404003028,
        10810405002068,
        10810405001004
    ],
    "zs:housing10":614,
    "zs:pop10":1319
},
  "geometry": {"coordinates":[-85.47528,32.584733],"type":"Point"}
}