{
  "type": "Feature",
  "properties": {
    "gn:admin1_code":"NE",
    "gn:admin2_code":"41.0",
    "gn:admin3_code":"29365.0",
    "gn:asciiname":"Buckeye",
    "gn:country_code":"US",
    "gn:dem":744,
    "gn:elevation":"741.0",
    "gn:feature_class":"P",
    "gn:feature_code":"PPL",
    "gn:name":"Buckeye",
    "gn:population":0,
    "gn:timezone":"America/Chicago",
    "iso:country":"US",
    "name:ceb_x_preferred":[
        "Buckeye"
    ],
    "name:deu_x_preferred":[
        "Buckeye"
    ],
    "name:fra_x_preferred":[
        "Buckeye"
    ],
    "name:hye_x_preferred":[
        "\u0532\u0561\u056f\u0561\u0575"
    ],
    "name:ita_x_preferred":[
        "Buckeye"
    ],
    "name:nld_x_preferred":[
        "Buckeye"
    ],
    "name:pol_x_preferred":[
        "Buckeye"
    ],
    "name:por_x_preferred":[
        "Buckeye"
    ],
    "name:rus_x_preferred":[
        "\u0411\u0430\u043a\u0430\u0439"
    ],
    "name:srp_x_preferred":[
        "\u0411\u0430\u043a\u0430\u0458"
    ],
    "name:ukr_x_preferred":[
        "\u0411\u0430\u043a\u0430\u0439"
    ],
    "name:urd_x_preferred":[
        "\u0628\u06a9\u0622\u0626\u06cc"
    ],
    "name:vol_x_preferred":[
        "Buckeye"
    ],
    "wof:name":"Buckeye",
    "wof:placetype":"locality"
},
  "geometry": {"coordinates":[-99.56844,41.19056],"type":"Point"}
}