{
  "type": "Feature",
  "properties": {
    "gn:admin1_code":"PA",
    "gn:admin2_code":"23.0",
    "gn:admin3_code":"70336.0",
    "gn:asciiname":"Lockwood",
    "gn:country_code":"US",
    "gn:dem":328,
    "gn:elevation":"326.0",
    "gn:feature_class":"P",
    "gn:feature_code":"PPL",
    "gn:name":"Lockwood",
    "gn:population":0,
    "gn:timezone":"America/New_York",
    "iso:country":"US",
    "name:ceb_x_preferred":[
        "Lockwood"
    ],
    "name:deu_x_preferred":[
        "Lockwood"
    ],
    "name:fra_x_preferred":[
        "Lockwood"
    ],
    "name:ita_x_preferred":[
        "Lockwood"
    ],
    "name:jpn_x_preferred":[
        "\u30ed\u30c3\u30af\u30a6\u30c3\u30c9"
    ],
    "name:nds_x_preferred":[
        "Lockwood"
    ],
    "name:nld_x_preferred":[
        "Lockwood"
    ],
    "name:pol_x_preferred":[
        "Lockwood"
    ],
    "name:por_x_preferred":[
        "Lockwood"
    ],
    "name:rus_x_preferred":[
        "\u041b\u043e\u043a\u0432\u0443\u0434"
    ],
    "name:srp_x_preferred":[
        "\u041b\u043e\u043a\u0432\u0443\u0434"
    ],
    "name:swe_x_preferred":[
        "Lockwood"
    ],
    "name:ukr_x_preferred":[
        "\u041b\u043e\u043a\u0432\u0443\u0434"
    ],
    "name:vol_x_preferred":[
        "Lockwood"
    ],
    "wof:name":"Lockwood",
    "wof:placetype":"locality"
},
  "geometry": {"coordinates":[-78.27418,41.52895],"type":"Point"}
}