{
  "type": "Feature",
  "properties": {
    "gn:admin1_code":"MD",
    "gn:admin2_code":"43.0",
    "gn:asciiname":"Flickersville",
    "gn:country_code":"US",
    "gn:dem":246,
    "gn:elevation":"244.0",
    "gn:feature_class":"P",
    "gn:feature_code":"PPL",
    "gn:name":"Flickersville",
    "gn:population":0,
    "gn:timezone":"America/New_York",
    "iso:country":"US",
    "wof:name":"Flickersville",
    "wof:placetype":"locality"
},
  "geometry": {"coordinates":[-77.70220999999999,39.45038],"type":"Point"}
}