{
  "type": "Feature",
  "properties": {
    "gn:admin1_code":"MO",
    "gn:admin2_code":"123.0",
    "gn:admin3_code":"11962.0",
    "gn:asciiname":"Higdon",
    "gn:country_code":"US",
    "gn:dem":261,
    "gn:elevation":"256.0",
    "gn:feature_class":"P",
    "gn:feature_code":"PPL",
    "gn:name":"Higdon",
    "gn:population":0,
    "gn:timezone":"America/Chicago",
    "iso:country":"US",
    "wof:name":"Higdon",
    "wof:placetype":"locality"
},
  "geometry": {"coordinates":[-90.16789,37.59283],"type":"Point"}
}