{
  "type": "Feature",
  "properties": {
    "gn:admin1_code":"TX",
    "gn:admin2_code":"167.0",
    "gn:asciiname":"Frenchmans Creek",
    "gn:country_code":"US",
    "gn:dem":16,
    "gn:elevation":"6.0",
    "gn:feature_class":"P",
    "gn:feature_code":"PPL",
    "gn:name":"Frenchmans Creek",
    "gn:population":0,
    "gn:timezone":"America/Chicago",
    "iso:country":"US",
    "wof:name":"Frenchmans Creek",
    "wof:placetype":"locality"
},
  "geometry": {"coordinates":[-95.1722,29.5074],"type":"Point"}
}