{
  "type": "Feature",
  "properties": {
    "iso:country":"US",
    "name:eng_x_preferred":[
        "Fort Richardson Military Reservation"
    ],
    "name:eng_x_variant":[
        "Ft Richardson Military Reservation",
        "Ft. Richardson Military Reservation"
    ],
    "qs:gn_adm0_cc":"US",
    "qs:gn_local":5879400,
    "qs:local_max":8197,
    "qs:local_sum":33853,
    "qs:localhoods":34,
    "qs:name":"Fort Richardson Military Reservation",
    "qs:name_adm0":"United States",
    "qs:name_adm1":"Alaska",
    "qs:name_adm2":"Municipality of Anchorage",
    "qs:name_local":"Anchorage",
    "qs:photo_max":104,
    "qs:photo_sum":306,
    "qs:placetype":"Suburb",
    "qs:quad_count":32,
    "qs:woe_adm0":23424977,
    "qs:woe_adm1":2347560,
    "qs:woe_adm2":12587556,
    "qs:woe_lau":0,
    "qs:woe_local":2354490,
    "qs:woe_ver":"7.10.0",
    "wof:name":"Fort Richardson Military Reservation",
    "wof:placetype":"neighbourhood",
    "wof:population":3294,
    "zs:blockids":[
        20200007021006,
        20200007022008,
        20200003001063,
        20200004001071,
        20200003001146,
        20200003001097,
        20200003001150,
        20200003001147,
        20200003001164,
        20200004001082,
        20200007021005,
        20200007022001,
        20200004001084,
        20200004001085,
        20200007022007,
        20200003001096
    ],
    "zs:housing10":1019,
    "zs:pop10":3294
},
  "geometry": {"coordinates":[-149.72699,61.242926],"type":"Point"}
}