{
  "type": "Feature",
  "properties": {
    "iso:country":"US",
    "name:deu_x_preferred":[
        "Flughafen Chignik Lagoon"
    ],
    "name:eng_x_preferred":[
        "Chignik Lagoon Airport"
    ],
    "name:eng_x_variant":[
        "KCL"
    ],
    "name:fas_x_preferred":[
        "\u0641\u0631\u0648\u062f\u06af\u0627\u0647 \u0686\u06cc\u0627\u06af\u0646\u06cc\u06a9 \u0644\u06af\u0648\u0646"
    ],
    "name:rus_x_preferred":[
        "\u0427\u0438\u0433\u043d\u0438\u043a-\u041b\u0430\u0433\u0443\u043d"
    ],
    "name:tgk_x_preferred":[
        "\u0424\u0443\u0440\u0443\u0434\u0433\u043e\u04b3\u0438 \u0447\u0438\u043e\u0433\u043d\u0438\u043a \u043b\u0433\u0443\u043d"
    ],
    "oa:elevation_ft":"25",
    "oa:type":"small_airport",
    "wd:wordcount":304,
    "woe:hierarchy":{
        "country_id":23424977,
        "county_id":12587567,
        "planet_id":1,
        "state_id":2347560
    },
    "wof:name":"Chignik Lagoon Airport",
    "wof:placetype":"campus"
},
  "geometry": {"coordinates":[-158.53599600000001,56.311199],"type":"Point"}
}