{
  "type": "Feature",
  "properties": {
    "gn:admin1_code":"MS",
    "gn:admin2_code":"47.0",
    "gn:asciiname":"Pine Haven Mobile Home Village",
    "gn:country_code":"US",
    "gn:dem":28,
    "gn:elevation":"24.0",
    "gn:feature_class":"P",
    "gn:feature_code":"PPL",
    "gn:name":"Pine Haven Mobile Home Village",
    "gn:population":0,
    "gn:timezone":"America/Chicago",
    "iso:country":"US",
    "wof:name":"Pine Haven Mobile Home Village",
    "wof:placetype":"campus"
},
  "geometry": {"coordinates":[-88.98253000000003,30.49011],"type":"Point"}
}