{
  "type": "Feature",
  "properties": {
    "gn:elevation":1,
    "iso:country":"US",
    "name:eng_x_preferred":[
        "Laurel Harbor"
    ],
    "name:eng_x_variant":[
        "Laurel Hbr"
    ],
    "qs:gn_adm0_cc":"US",
    "qs:gn_fcode":"PPL",
    "qs:gn_local":4502562,
    "qs:gn_nam_loc":"Lacey, Ocean, New Jersey, US",
    "qs:gn_namadm1":"NJ",
    "qs:gn_name":"Laurel Harbor",
    "qs:local_max":339,
    "qs:local_sum":740,
    "qs:localhoods":9,
    "qs:name":"Laurel Harbor",
    "qs:name_adm0":"United States",
    "qs:name_adm1":"New Jersey",
    "qs:name_adm2":"Ocean",
    "qs:name_local":"Lacey",
    "qs:photo_max":2,
    "qs:photo_sum":3,
    "qs:placetype":"Suburb",
    "qs:quad_count":2,
    "qs:woe_adm0":23424977,
    "qs:woe_adm1":2347589,
    "qs:woe_adm2":12589272,
    "qs:woe_funk":"Grouping neighborhood",
    "qs:woe_lau":0,
    "qs:woe_local":2434414,
    "qs:woe_ver":"7.10.0",
    "wof:lang":[
        "eng"
    ],
    "wof:name":"Laurel Harbor",
    "wof:placetype":"neighbourhood"
},
  "geometry": {"coordinates":[-74.145813,39.857046],"type":"Point"}
}