{
  "type": "Feature",
  "properties": {
    "gn:admin1_code":"NY",
    "gn:admin2_code":"45.0",
    "gn:admin3_code":"42015.0",
    "gn:asciiname":"Sanfords Four Corners",
    "gn:country_code":"US",
    "gn:dem":149,
    "gn:elevation":"150.0",
    "gn:feature_class":"P",
    "gn:feature_code":"PPL",
    "gn:name":"Sanfords Four Corners",
    "gn:population":0,
    "gn:timezone":"America/New_York",
    "iso:country":"US",
    "name:und_x_variant":[
        "Sanford's Corners",
        "Sanfords Four Corners"
    ],
    "wof:name":"Sanfords Four Corners",
    "wof:placetype":"locality"
},
  "geometry": {"coordinates":[-75.83499999999999,44.03111],"type":"Point"}
}