{
  "type": "Feature",
  "properties": {
    "gn:elevation":226,
    "iso:country":"US",
    "name:eng_x_preferred":[
        "Milford Terrace"
    ],
    "name:eng_x_variant":[
        "Milford Ter"
    ],
    "qs:gn_adm0_cc":"US",
    "qs:gn_fcode":"PPLX",
    "qs:gn_local":4489985,
    "qs:gn_nam_loc":"Salisbury, Rowan, North Carolina, US",
    "qs:gn_namadm1":"NC",
    "qs:gn_name":"Milford Terrace",
    "qs:local_max":640,
    "qs:local_sum":845,
    "qs:localhoods":6,
    "qs:name":"Milford Terrace",
    "qs:name_adm0":"United States",
    "qs:name_adm1":"North Carolina",
    "qs:name_adm2":"Rowan",
    "qs:name_local":"Salisbury",
    "qs:photo_max":6,
    "qs:photo_sum":15,
    "qs:placetype":"Suburb",
    "qs:quad_count":5,
    "qs:woe_adm0":23424977,
    "qs:woe_adm1":2347592,
    "qs:woe_adm2":12589453,
    "qs:woe_lau":0,
    "qs:woe_local":2487492,
    "qs:woe_ver":"7.10.0",
    "wof:lang":[
        "eng"
    ],
    "wof:name":"Milford Terrace",
    "wof:placetype":"neighbourhood",
    "wof:population":3437,
    "zs:blockids":[
        371590513034009,
        371590512021015,
        371590513031008,
        371590512021018,
        371590512021024,
        371590512021019,
        371590512021010,
        371590513034012,
        371590513034008,
        371590512021000,
        371590513034016,
        371590513034022,
        371590513034019,
        371590513031005,
        371590512021002,
        371590513034005,
        371590512021014,
        371590512021020,
        371590513034013,
        371590512021017,
        371590513034006,
        371590513034015,
        371590512021012,
        371590513034024,
        371590512021016,
        371590512021025,
        371590512021003,
        371590513032034,
        371590512021033,
        371590513032035,
        371590513033015,
        371590513034017,
        371590512021013,
        371590512021007,
        371590512021021,
        371590513035000,
        371590513034020,
        371590513032036,
        371590512021011,
        371590513034018,
        371590513034000,
        371590513034004,
        371590513034023,
        371590513034021,
        371590513031009,
        371590513034011,
        371590512021022,
        371590513034014,
        371590513034010,
        371590513034007,
        371590512021008,
        371590513034001,
        371590513034025,
        371590512021034
    ],
    "zs:housing10":1541,
    "zs:pop10":3437
},
  "geometry": {"coordinates":[-80.51422100000001,35.690765],"type":"Point"}
}