{
  "type": "Feature",
  "properties": {
    "gn:admin1_code":"WV",
    "gn:admin2_code":"15",
    "gn:asciiname":"Harrison",
    "gn:country_code":"US",
    "gn:dem":330,
    "gn:elevation":"328.0",
    "gn:feature_class":"P",
    "gn:feature_code":"PPL",
    "gn:name":"Harrison",
    "gn:population":0,
    "gn:timezone":"America/New_York",
    "iso:country":"US",
    "name:bel_x_preferred":[
        "\u0413\u0430\u0440\u044b\u0441\u0430\u043d"
    ],
    "name:cat_x_preferred":[
        "Harrison"
    ],
    "name:ceb_x_preferred":[
        "Harrison"
    ],
    "name:ces_x_preferred":[
        "Harrison"
    ],
    "name:deu_x_preferred":[
        "Harrison"
    ],
    "name:eng_x_preferred":[
        "Harrison"
    ],
    "name:fas_x_preferred":[
        "\u0647\u0631\u06cc\u0633\u0648\u0646"
    ],
    "name:fin_x_preferred":[
        "Harrison"
    ],
    "name:fra_x_preferred":[
        "Harrison"
    ],
    "name:heb_x_preferred":[
        "\u05d4\u05e8\u05d9\u05e1\u05d5\u05df"
    ],
    "name:ita_x_preferred":[
        "Harrison"
    ],
    "name:jpn_x_preferred":[
        "\u30cf\u30ea\u30bd\u30f3"
    ],
    "name:kor_x_preferred":[
        "\ud574\ub9ac\uc2a8"
    ],
    "name:lav_x_preferred":[
        "Herisons"
    ],
    "name:lit_x_preferred":[
        "Harrison"
    ],
    "name:nds_x_preferred":[
        "Harrison"
    ],
    "name:nld_x_preferred":[
        "Harrison"
    ],
    "name:pol_x_preferred":[
        "Harrison"
    ],
    "name:por_x_preferred":[
        "Harrison"
    ],
    "name:ron_x_preferred":[
        "Harrison"
    ],
    "name:rus_x_preferred":[
        "\u0425\u0430\u0440\u0440\u0438\u0441\u043e\u043d"
    ],
    "name:spa_x_preferred":[
        "Harrison"
    ],
    "name:srp_x_preferred":[
        "\u0425\u0430\u0440\u0438\u0441\u043e\u043d"
    ],
    "name:swa_x_preferred":[
        "Harrison"
    ],
    "name:swe_x_preferred":[
        "Harrison"
    ],
    "name:ukr_x_preferred":[
        "\u0413\u0430\u0440\u0440\u0456\u0441\u043e\u043d"
    ],
    "name:und_x_variant":[
        "Flat Fork",
        "New Flat Creek"
    ],
    "name:vol_x_preferred":[
        "Harrison"
    ],
    "wof:name":"Harrison",
    "wof:placetype":"locality"
},
  "geometry": {"coordinates":[-80.95344,38.51288],"type":"Point"}
}