{
  "type": "Feature",
  "properties": {
    "gn:admin1_code":"TX",
    "gn:admin2_code":"347",
    "gn:asciiname":"Lacyville",
    "gn:country_code":"US",
    "gn:dem":77,
    "gn:elevation":"72.0",
    "gn:feature_class":"P",
    "gn:feature_code":"PPL",
    "gn:name":"Lacyville",
    "gn:population":0,
    "gn:timezone":"America/Chicago",
    "iso:country":"US",
    "wof:name":"Lacyville",
    "wof:placetype":"locality"
},
  "geometry": {"coordinates":[-94.60715,31.50518],"type":"Point"}
}