{
  "type": "Feature",
  "properties": {
    "gn:admin1_code":"UT",
    "gn:admin2_code":"35.0",
    "gn:asciiname":"Oakdale",
    "gn:country_code":"US",
    "gn:dem":1347,
    "gn:elevation":"1339.0",
    "gn:feature_class":"P",
    "gn:feature_code":"PPL",
    "gn:name":"Oakdale",
    "gn:population":0,
    "gn:timezone":"America/Denver",
    "iso:country":"US",
    "name:cat_x_preferred":[
        "Oakdale"
    ],
    "name:ceb_x_preferred":[
        "Oakdale"
    ],
    "name:cym_x_preferred":[
        "Oakdale"
    ],
    "name:deu_x_preferred":[
        "Oakdale"
    ],
    "name:fra_x_preferred":[
        "Oakdale"
    ],
    "name:ita_x_preferred":[
        "Oakdale"
    ],
    "name:nld_x_preferred":[
        "Oakdale"
    ],
    "name:pol_x_preferred":[
        "Oakdale"
    ],
    "name:por_x_preferred":[
        "Oakdale"
    ],
    "name:spa_x_preferred":[
        "Oakdale"
    ],
    "name:srp_x_preferred":[
        "\u041e\u0443\u043a\u0434\u0435\u0458\u043b"
    ],
    "name:swe_x_preferred":[
        "Oakdale"
    ],
    "name:vol_x_preferred":[
        "Oakdale"
    ],
    "wof:name":"Oakdale",
    "wof:placetype":"locality"
},
  "geometry": {"coordinates":[-111.84104000000001,40.64661],"type":"Point"}
}