{
  "type": "Feature",
  "properties": {
    "gn:elevation":184,
    "iso:country":"US",
    "name:eng_x_preferred":[
        "Vermilion Heights"
    ],
    "name:eng_x_variant":[
        "Vermilion Hts"
    ],
    "qs:gn_adm0_cc":"US",
    "qs:gn_fcode":"PPL",
    "qs:gn_local":4889426,
    "qs:gn_nam_loc":"Danville, Vermilion, Illinois, US",
    "qs:gn_namadm1":"IL",
    "qs:gn_name":"Vermilion Heights",
    "qs:local_max":569,
    "qs:local_sum":574,
    "qs:localhoods":2,
    "qs:name":"Vermilion Heights",
    "qs:name_adm0":"United States",
    "qs:name_adm1":"Illinois",
    "qs:name_adm2":"Vermilion",
    "qs:name_local":"Danville",
    "qs:photo_max":4,
    "qs:photo_sum":5,
    "qs:placetype":"Suburb",
    "qs:quad_count":2,
    "qs:woe_adm0":23424977,
    "qs:woe_adm1":2347572,
    "qs:woe_adm2":12588169,
    "qs:woe_funk":"Grouping neighborhood",
    "qs:woe_lau":0,
    "qs:woe_local":2389336,
    "qs:woe_ver":"7.10.0",
    "wof:lang":[
        "eng"
    ],
    "wof:name":"Vermilion Heights",
    "wof:placetype":"neighbourhood"
},
  "geometry": {"coordinates":[-87.652771,40.12639],"type":"Point"}
}