{
  "type": "Feature",
  "properties": {
    "iso:country":"US",
    "name:ara_x_preferred":[
        "\u0648\u0633\u0637 \u0627\u0644\u0628\u0644\u062f"
    ],
    "name:arz_x_preferred":[
        "\u0648\u0633\u0637 \u0627\u0644\u0628\u0644\u062f"
    ],
    "name:ast_x_preferred":[
        "Distritu financieru"
    ],
    "name:ben_x_preferred":[
        "\u09b6\u09b9\u09b0\u09c7\u09b0 \u0995\u09c7\u09a8\u09cd\u09a6\u09cd\u09b0\u09b8\u09cd\u09a5\u09b2"
    ],
    "name:bul_x_preferred":[
        "\u0426\u0435\u043d\u0442\u044a\u0440"
    ],
    "name:ces_x_preferred":[
        "Downtown"
    ],
    "name:deu_x_preferred":[
        "Downtown"
    ],
    "name:eng_x_preferred":[
        "Downtown"
    ],
    "name:eng_x_variant":[
        "downtown"
    ],
    "name:epo_x_preferred":[
        "urbocentro"
    ],
    "name:fas_x_preferred":[
        "\u0647\u0633\u062a\u0647 \u0634\u0647\u0631"
    ],
    "name:fra_x_preferred":[
        "centre-ville"
    ],
    "name:hun_x_preferred":[
        "belv\u00e1ros"
    ],
    "name:jpn_x_preferred":[
        "\u30c0\u30a6\u30f3\u30bf\u30a6\u30f3"
    ],
    "name:kor_x_preferred":[
        "\ub3c4\uc2ec"
    ],
    "name:nld_x_preferred":[
        "downtown"
    ],
    "name:pol_x_preferred":[
        "centrum miasta"
    ],
    "name:por_x_preferred":[
        "centro"
    ],
    "name:ron_x_preferred":[
        "Centru civic"
    ],
    "name:rus_x_preferred":[
        "\u0434\u0430\u0443\u043d\u0442\u0430\u0443\u043d"
    ],
    "name:sco_x_preferred":[
        "Downtown"
    ],
    "name:spa_x_preferred":[
        "downtown"
    ],
    "name:swe_x_preferred":[
        "Downtown"
    ],
    "name:ukr_x_preferred":[
        "\u0434\u0430\u0443\u043d\u0442\u0430\u0443\u043d"
    ],
    "name:wuu_x_preferred":[
        "\u4e0b\u57ce"
    ],
    "name:yue_x_preferred":[
        "\u4e0b\u57ce"
    ],
    "name:zho_x_preferred":[
        "\u4e0b\u57ce"
    ],
    "wd:wordcount":1123,
    "wof:name":"Downtown",
    "wof:placetype":"neighbourhood",
    "wof:population":2208,
    "zs:area_m":595489.460939,
    "zs:blockids":[
        250173363007002,
        250173363007005,
        250173362004014,
        250173363007010,
        250173363006001,
        250173363006002,
        250173362004011,
        250173363003007,
        250173363007004,
        250173363007009,
        250173362004004,
        250173363007006,
        250173363004003,
        250173363007011,
        250173364021006,
        250173363007007,
        250173364011000,
        250173363007003,
        250173363007000,
        250173363003008,
        250173363004002,
        250173363006008,
        250173363003009,
        250173362004010,
        250173363007001,
        250173362004012,
        250173364021013,
        250173363003010,
        250173363006007,
        250173363007008,
        250173362004005,
        250173362004009,
        250173363006003,
        250173363006005
    ],
    "zs:housing10":985,
    "zs:label":"Downtown",
    "zs:pop10":2208
},
  "geometry": {"coordinates":[-71.060757,42.455097],"type":"Point"}
}