{
  "type": "Feature",
  "properties": {
    "gn:admin1_code":"KY",
    "gn:admin2_code":"65.0",
    "gn:asciiname":"Lower White Oak",
    "gn:country_code":"US",
    "gn:dem":214,
    "gn:elevation":"213.0",
    "gn:feature_class":"P",
    "gn:feature_code":"PPL",
    "gn:name":"Lower White Oak",
    "gn:population":0,
    "gn:timezone":"America/New_York",
    "iso:country":"US",
    "wof:name":"Lower White Oak",
    "wof:placetype":"locality"
},
  "geometry": {"coordinates":[-83.96471,37.73298],"type":"Point"}
}