{
  "type": "Feature",
  "properties": {
    "gn:admin1_code":"MT",
    "gn:admin2_code":"77.0",
    "gn:asciiname":"Dutton",
    "gn:country_code":"US",
    "gn:dem":1289,
    "gn:elevation":"1286.0",
    "gn:feature_class":"P",
    "gn:feature_code":"PPL",
    "gn:name":"Dutton",
    "gn:population":0,
    "gn:timezone":"America/Denver",
    "iso:country":"US",
    "name:ceb_x_preferred":[
        "Dutton"
    ],
    "name:deu_x_preferred":[
        "Dutton"
    ],
    "name:fra_x_preferred":[
        "Dutton"
    ],
    "name:ita_x_preferred":[
        "Dutton"
    ],
    "name:nld_x_preferred":[
        "Dutton"
    ],
    "name:pol_x_preferred":[
        "Dutton"
    ],
    "name:por_x_preferred":[
        "Dutton"
    ],
    "name:rus_x_preferred":[
        "\u0414\u0430\u0442\u0442\u043e\u043d"
    ],
    "name:spa_x_preferred":[
        "Dutton"
    ],
    "name:srp_x_preferred":[
        "\u0414\u0430\u0442\u043e\u043d"
    ],
    "name:swe_x_preferred":[
        "Dutton"
    ],
    "name:vol_x_preferred":[
        "Dutton"
    ],
    "wof:name":"Dutton",
    "wof:placetype":"locality"
},
  "geometry": {"coordinates":[-112.94727,46.60299000000001],"type":"Point"}
}