{
  "type": "Feature",
  "properties": {
    "gn:admin1_code":"OH",
    "gn:admin2_code":"133",
    "gn:admin3_code":"65606.0",
    "gn:asciiname":"Pine Gate Village",
    "gn:country_code":"US",
    "gn:dem":325,
    "gn:elevation":"326.0",
    "gn:feature_class":"P",
    "gn:feature_code":"PPL",
    "gn:name":"Pine Gate Village",
    "gn:population":0,
    "gn:timezone":"America/New_York",
    "iso:country":"US",
    "wof:name":"Pine Gate Village",
    "wof:placetype":"locality"
},
  "geometry": {"coordinates":[-81.26167,41.16944],"type":"Point"}
}