{
  "type": "Feature",
  "properties": {
    "gn:admin1_code":"LA",
    "gn:admin2_code":"45.0",
    "gn:asciiname":"Oliva Mobile Home Park",
    "gn:country_code":"US",
    "gn:dem":9,
    "gn:elevation":"7.0",
    "gn:feature_class":"P",
    "gn:feature_code":"PPL",
    "gn:name":"Oliva Mobile Home Park",
    "gn:population":0,
    "gn:timezone":"America/Chicago",
    "iso:country":"US",
    "wof:name":"Oliva Mobile Home Park",
    "wof:placetype":"campus"
},
  "geometry": {"coordinates":[-91.92749999999999,30.03993],"type":"Point"}
}