{
  "type": "Feature",
  "properties": {
    "gn:admin1_code":"AR",
    "gn:admin2_code":"29.0",
    "gn:admin3_code":"93492.0",
    "gn:asciiname":"Mount Olive",
    "gn:country_code":"US",
    "gn:dem":118,
    "gn:elevation":"117.0",
    "gn:feature_class":"P",
    "gn:feature_code":"PPL",
    "gn:name":"Mount Olive",
    "gn:population":0,
    "gn:timezone":"America/Chicago",
    "iso:country":"US",
    "name:ceb_x_preferred":[
        "Mount Olive"
    ],
    "name:deu_x_preferred":[
        "Mount Olive"
    ],
    "name:fra_x_preferred":[
        "Mount Olive"
    ],
    "name:hun_x_preferred":[
        "Mount Olive"
    ],
    "name:ita_x_preferred":[
        "Mount Olive"
    ],
    "name:nds_x_preferred":[
        "Mount Olive"
    ],
    "name:nld_x_preferred":[
        "Mount Olive"
    ],
    "name:pol_x_preferred":[
        "Mount Olive"
    ],
    "name:por_x_preferred":[
        "Mount Olive"
    ],
    "name:spa_x_preferred":[
        "Mount Olive"
    ],
    "name:srp_x_preferred":[
        "\u041c\u0430\u0443\u043d\u0442 \u041e\u043b\u0438\u0432"
    ],
    "name:swe_x_preferred":[
        "Mount Olive"
    ],
    "name:ukr_x_preferred":[
        "\u041c\u0430\u0443\u043d\u0442-\u041e\u043b\u0456\u0432"
    ],
    "name:vol_x_preferred":[
        "Mount Olive"
    ],
    "wof:name":"Mount Olive",
    "wof:placetype":"locality"
},
  "geometry": {"coordinates":[-92.55516,35.19675],"type":"Point"}
}