{
  "type": "Feature",
  "properties": {
    "gn:admin1_code":"AL",
    "gn:admin2_code":"9",
    "gn:asciiname":"Graystone",
    "gn:country_code":"US",
    "gn:dem":235,
    "gn:elevation":"234.0",
    "gn:feature_class":"P",
    "gn:feature_code":"PPL",
    "gn:name":"Graystone",
    "gn:population":0,
    "gn:timezone":"America/Chicago",
    "iso:country":"US",
    "wof:name":"Graystone",
    "wof:placetype":"locality"
},
  "geometry": {"coordinates":[-86.50832,33.92621],"type":"Point"}
}