{
  "type": "Feature",
  "properties": {
    "iso:country":"US",
    "name:eng_x_preferred":[
        "Lower Greenville"
    ],
    "name:fra_x_preferred":[
        "Lower Greenville"
    ],
    "name:jpn_x_preferred":[
        "\u30ed\u30a6\u30ef\u30fc\u30fb\u30b0\u30ea\u30fc\u30f3\u30f4\u30a3\u30eb"
    ],
    "name:nld_x_preferred":[
        "Lower Greenville"
    ],
    "wd:wordcount":481,
    "wof:name":"Lower Greenville",
    "wof:placetype":"neighbourhood",
    "wof:population":3607,
    "zs:area_m":675559.478134,
    "zs:blockids":[
        481130009004004,
        481130010022023,
        481130010022002,
        481130010022011,
        481130009002006,
        481130010011008,
        481130010021008,
        481130010022013,
        481130010021011,
        481130009002000,
        481130009003003,
        481130010022004,
        481130009001008,
        481130010021012,
        481130009003002,
        481130010021002,
        481130010021010,
        481130010021009,
        481130009004000,
        481130009003001,
        481130010022014,
        481130009003000,
        481130010022005,
        481130010021005,
        481130010022003,
        481130010022012,
        481130009004005
    ],
    "zs:housing10":1904,
    "zs:label":"Lower Greenville",
    "zs:pop10":3607
},
  "geometry": {"coordinates":[-96.777795,32.814982],"type":"Point"}
}