{
  "type": "Feature",
  "properties": {
    "gn:admin1_code":"OR",
    "gn:admin2_code":"33.0",
    "gn:asciiname":"Placer",
    "gn:country_code":"US",
    "gn:dem":439,
    "gn:elevation":"438.0",
    "gn:feature_class":"P",
    "gn:feature_code":"PPL",
    "gn:name":"Placer",
    "gn:population":0,
    "gn:timezone":"America/Los_Angeles",
    "iso:country":"US",
    "wof:name":"Placer",
    "wof:placetype":"locality"
},
  "geometry": {"coordinates":[-123.31534000000001,42.63206],"type":"Point"}
}