{
  "type": "Feature",
  "properties": {
    "gn:admin1_code":"NY",
    "gn:admin2_code":"31.0",
    "gn:admin3_code":"64529.0",
    "gn:asciiname":"Pine Ridge Mobile Home Park",
    "gn:country_code":"US",
    "gn:dem":486,
    "gn:elevation":"485.0",
    "gn:feature_class":"P",
    "gn:feature_code":"PPL",
    "gn:name":"Pine Ridge Mobile Home Park",
    "gn:population":0,
    "gn:timezone":"America/New_York",
    "iso:country":"US",
    "wof:name":"Pine Ridge Mobile Home Park",
    "wof:placetype":"campus"
},
  "geometry": {"coordinates":[-74.08892,44.40574],"type":"Point"}
}