{
  "type": "Feature",
  "properties": {
    "gn:admin1_code":"AL",
    "gn:admin2_code":"55",
    "gn:asciiname":"East Gadsden",
    "gn:country_code":"US",
    "gn:dem":174,
    "gn:elevation":"174.0",
    "gn:feature_class":"P",
    "gn:feature_code":"PPL",
    "gn:name":"East Gadsden",
    "gn:population":0,
    "gn:timezone":"America/Chicago",
    "iso:country":"US",
    "wof:name":"East Gadsden",
    "wof:placetype":"locality"
},
  "geometry": {"coordinates":[-85.96858,34.0026],"type":"Point"}
}