{
  "type": "Feature",
  "properties": {
    "iso:country":"US",
    "name:ceb_x_preferred":[
        "Jenne"
    ],
    "name:deu_x_preferred":[
        "Jenne"
    ],
    "name:sco_x_preferred":[
        "Jenne"
    ],
    "name:swe_x_preferred":[
        "Jenne"
    ],
    "qs_pg:aaroncc":"US",
    "qs_pg:name":"Jenne",
    "qs_pg:name_adm0":"United States",
    "qs_pg:name_adm1":"Oregon",
    "qs_pg:photos":26,
    "qs_pg:photos_1k":5,
    "qs_pg:photos_9k":1,
    "qs_pg:photos_9r":2,
    "qs_pg:photos_all":26,
    "qs_pg:photos_sr":2,
    "qs_pg:pop_sr":0,
    "qs_pg:qs_pg_placetype":"locality",
    "qs_pg:qs_pg_placetype_gp":"Town",
    "qs_pg:woe_adm0":23424977,
    "woe:adm0_id":23424977,
    "woe:name_adm0":"United States",
    "woe:name_adm1":"Oregon",
    "woe:placetype":"Town",
    "wof:name":"Jenne",
    "wof:placetype":"locality"
},
  "geometry": {"coordinates":[-122.501335,45.4900875],"type":"Point"}
}