{
  "type": "Feature",
  "properties": {
    "gn:admin1_code":"MS",
    "gn:admin2_code":"51.0",
    "gn:asciiname":"Castalian Springs",
    "gn:country_code":"US",
    "gn:dem":96,
    "gn:elevation":"91.0",
    "gn:feature_class":"P",
    "gn:feature_code":"PPL",
    "gn:name":"Castalian Springs",
    "gn:population":0,
    "gn:timezone":"America/Chicago",
    "iso:country":"US",
    "wof:name":"Castalian Springs",
    "wof:placetype":"locality"
},
  "geometry": {"coordinates":[-89.90425,33.07291],"type":"Point"}
}