{
  "type": "Feature",
  "properties": {
    "gn:country":"US",
    "gn:fcode":"PPL",
    "gn:population":0,
    "iso:country":"US",
    "name:ara_x_preferred":[
        "\u0641\u064a\u0633\u062a\u0627"
    ],
    "name:bul_x_preferred":[
        "\u0412\u0438\u0441\u0442\u0430"
    ],
    "name:ceb_x_preferred":[
        "Vista"
    ],
    "name:ces_x_preferred":[
        "Vista"
    ],
    "name:deu_x_preferred":[
        "Vista"
    ],
    "name:eng_x_preferred":[
        "Vista"
    ],
    "name:fas_x_preferred":[
        "\u0648\u06cc\u0633\u062a\u0627"
    ],
    "name:fin_x_preferred":[
        "Vista"
    ],
    "name:fra_x_preferred":[
        "Vista"
    ],
    "name:hun_x_preferred":[
        "Vista"
    ],
    "name:ita_x_preferred":[
        "Vista"
    ],
    "name:jpn_x_preferred":[
        "\u30d3\u30b9\u30bf"
    ],
    "name:kor_x_preferred":[
        "\ube44\uc2a4\ud0c0"
    ],
    "name:lav_x_preferred":[
        "Vista"
    ],
    "name:nld_x_preferred":[
        "Vista"
    ],
    "name:nor_x_preferred":[
        "Vista"
    ],
    "name:pol_x_preferred":[
        "Vista"
    ],
    "name:por_x_preferred":[
        "Vista"
    ],
    "name:rus_x_preferred":[
        "Vista"
    ],
    "name:slk_x_preferred":[
        "Vista"
    ],
    "name:spa_x_preferred":[
        "Vista"
    ],
    "name:srp_x_preferred":[
        "\u0412\u0438\u0441\u0442\u0430"
    ],
    "name:swa_x_preferred":[
        "Vista"
    ],
    "name:swe_x_preferred":[
        "Vista"
    ],
    "name:tur_x_preferred":[
        "Vista"
    ],
    "name:ukr_x_preferred":[
        "Vista"
    ],
    "name:und_x_variant":[
        "Vista Station"
    ],
    "name:vie_x_preferred":[
        "Vista"
    ],
    "name:zho_x_preferred":[
        "Vista"
    ],
    "qs_pg:aaroncc":"US",
    "qs_pg:gn_country":"US",
    "qs_pg:gn_fcode":"PPL",
    "qs_pg:gn_pop":0,
    "qs_pg:name":"Vista",
    "qs_pg:name_adm0":"United States",
    "qs_pg:name_adm1":"Utah",
    "qs_pg:photos":41,
    "qs_pg:photos_1k":8,
    "qs_pg:photos_9k":1,
    "qs_pg:photos_9r":2,
    "qs_pg:photos_all":41,
    "qs_pg:photos_sr":2,
    "qs_pg:pop_sr":0,
    "qs_pg:qs_pg_placetype":"locality",
    "qs_pg:qs_pg_placetype_gp":"Town",
    "qs_pg:woe_adm0":23424977,
    "woe:adm0_id":23424977,
    "woe:name_adm0":"United States",
    "woe:name_adm1":"Utah",
    "woe:placetype":"Town",
    "wof:name":"Vista",
    "wof:placetype":"locality"
},
  "geometry": {"coordinates":[-109.67735,38.96386],"type":"Point"}
}