{
  "type": "Feature",
  "properties": {
    "gn:admin1_code":"MO",
    "gn:admin2_code":"111.0",
    "gn:admin3_code":"60950.0",
    "gn:asciiname":"Williamstown",
    "gn:country_code":"US",
    "gn:dem":224,
    "gn:elevation":"220.0",
    "gn:feature_class":"P",
    "gn:feature_code":"PPL",
    "gn:name":"Williamstown",
    "gn:population":0,
    "gn:timezone":"America/Chicago",
    "iso:country":"US",
    "name:vol_x_preferred":[
        "Williamstown"
    ],
    "wof:name":"Williamstown",
    "wof:placetype":"locality"
},
  "geometry": {"coordinates":[-91.79711,40.24088],"type":"Point"}
}