{
  "type": "Feature",
  "properties": {
    "gn:admin1_code":"NC",
    "gn:admin2_code":"51",
    "gn:admin3_code":"92724.0",
    "gn:asciiname":"Ardulusa",
    "gn:country_code":"US",
    "gn:dem":34,
    "gn:elevation":"28.0",
    "gn:feature_class":"P",
    "gn:feature_code":"PPL",
    "gn:name":"Ardulusa",
    "gn:population":0,
    "gn:timezone":"America/New_York",
    "iso:country":"US",
    "wof:name":"Ardulusa",
    "wof:placetype":"locality"
},
  "geometry": {"coordinates":[-78.91696999999998,34.96294],"type":"Point"}
}