{
  "type": "Feature",
  "properties": {
    "gn:admin1_code":"IL",
    "gn:admin2_code":"37.0",
    "gn:admin3_code":"40078.0",
    "gn:asciiname":"Colvin Park",
    "gn:country_code":"US",
    "gn:dem":258,
    "gn:elevation":"259.0",
    "gn:feature_class":"P",
    "gn:feature_code":"PPL",
    "gn:name":"Colvin Park",
    "gn:population":0,
    "gn:timezone":"America/Chicago",
    "iso:country":"US",
    "name:eng_x_preferred":[
        "Colvin Park"
    ],
    "name:und_x_variant":[
        "Colvinpark"
    ],
    "wof:name":"Colvin Park",
    "wof:placetype":"locality"
},
  "geometry": {"coordinates":[-88.78343000000002,42.13808],"type":"Point"}
}