{
  "type": "Feature",
  "properties": {
    "gn:admin1_code":"WV",
    "gn:admin2_code":"39",
    "gn:asciiname":"Donwood",
    "gn:country_code":"US",
    "gn:dem":238,
    "gn:elevation":"225.0",
    "gn:feature_class":"P",
    "gn:feature_code":"PPL",
    "gn:name":"Donwood",
    "gn:population":0,
    "gn:timezone":"America/New_York",
    "iso:country":"US",
    "wof:name":"Donwood",
    "wof:placetype":"locality"
},
  "geometry": {"coordinates":[-81.33206,38.16233],"type":"Point"}
}