{
  "type": "Feature",
  "properties": {
    "gn:admin1_code":"FL",
    "gn:admin2_code":"63.0",
    "gn:asciiname":"Steele City",
    "gn:country_code":"US",
    "gn:dem":43,
    "gn:elevation":"41.0",
    "gn:feature_class":"P",
    "gn:feature_code":"PPL",
    "gn:name":"Steele City",
    "gn:population":0,
    "gn:timezone":"America/Chicago",
    "iso:country":"US",
    "wof:name":"Steele City",
    "wof:placetype":"locality"
},
  "geometry": {"coordinates":[-85.38771,30.72436],"type":"Point"}
}