{
  "type": "Feature",
  "properties": {
    "gn:admin1_code":"NY",
    "gn:admin2_code":"13.0",
    "gn:admin3_code":"52155.0",
    "gn:asciiname":"Ashville",
    "gn:country_code":"US",
    "gn:dem":419,
    "gn:elevation":"414.0",
    "gn:feature_class":"P",
    "gn:feature_code":"PPL",
    "gn:name":"Ashville",
    "gn:population":0,
    "gn:timezone":"America/New_York",
    "iso:country":"US",
    "name:azb_x_preferred":[
        "\u0627\u0634\u0648\u06cc\u0644"
    ],
    "name:fas_x_preferred":[
        "\u0627\u0634\u0648\u06cc\u0644"
    ],
    "name:spa_x_preferred":[
        "Ashville"
    ],
    "wof:name":"Ashville",
    "wof:placetype":"locality"
},
  "geometry": {"coordinates":[-79.37560000000001,42.09645],"type":"Point"}
}