{
  "type": "Feature",
  "properties": {
    "gn:admin1_code":"SC",
    "gn:admin2_code":"15.0",
    "gn:asciiname":"Judge Town",
    "gn:country_code":"US",
    "gn:dem":28,
    "gn:elevation":"24.0",
    "gn:feature_class":"P",
    "gn:feature_code":"PPL",
    "gn:name":"Judge Town",
    "gn:population":0,
    "gn:timezone":"America/New_York",
    "iso:country":"US",
    "wof:name":"Judge Town",
    "wof:placetype":"locality"
},
  "geometry": {"coordinates":[-80.01925,33.43210999999999],"type":"Point"}
}