{
  "type": "Feature",
  "properties": {
    "gn:admin1_code":"WA",
    "gn:admin2_code":"53.0",
    "gn:asciiname":"Bayview",
    "gn:country_code":"US",
    "gn:dem":44,
    "gn:elevation":"41.0",
    "gn:feature_class":"P",
    "gn:feature_code":"PPL",
    "gn:name":"Bayview",
    "gn:population":0,
    "gn:timezone":"America/Los_Angeles",
    "iso:country":"US",
    "name:eng_x_preferred":[
        "Bayview"
    ],
    "name:und_x_variant":[
        "Bay View"
    ],
    "wof:name":"Bayview",
    "wof:placetype":"locality"
},
  "geometry": {"coordinates":[-122.60568000000001,47.27954],"type":"Point"}
}