{
  "type": "Feature",
  "properties": {
    "gn:admin1_code":"FL",
    "gn:admin2_code":"127.0",
    "gn:asciiname":"The Oaks Mobile Home Park",
    "gn:country_code":"US",
    "gn:dem":36,
    "gn:elevation":"27.0",
    "gn:feature_class":"P",
    "gn:feature_code":"PPL",
    "gn:name":"The Oaks Mobile Home Park",
    "gn:population":0,
    "gn:timezone":"America/New_York",
    "iso:country":"US",
    "wof:name":"The Oaks Mobile Home Park",
    "wof:placetype":"campus"
},
  "geometry": {"coordinates":[-81.27072,29.02283],"type":"Point"}
}