{
  "type": "Feature",
  "properties": {
    "iso:country":"US",
    "name:eng_x_preferred":[
        "Park View"
    ],
    "wd:wordcount":103,
    "wof:name":"Park View",
    "wof:placetype":"neighbourhood",
    "wof:population":524,
    "zs:area_m":2329228.92086,
    "zs:blockids":[
        121050117041029,
        121050118343046,
        121050117041038,
        121050118343037,
        121050118343024,
        121050118343062,
        121050118343042,
        121050118343023,
        121050118343036,
        121050118343125,
        121050118343009,
        121050118343011,
        121050117041020,
        121050118343029,
        121050118343030,
        121050118343126,
        121050118343025,
        121050118343044,
        121050117041023,
        121050118343122,
        121050118343048,
        121050117041034,
        121050117041032,
        121050117041033,
        121050117041030,
        121050118343034,
        121050118343014,
        121050118343028,
        121050118343128,
        121050118343022,
        121050118343045,
        121050118343018,
        121050117041021,
        121050117041035,
        121050118343032,
        121050118343041,
        121050118343026,
        121050118343016,
        121050118343017,
        121050118343033,
        121050118343035,
        121050117041037,
        121050118343038,
        121050118343013,
        121050118343056,
        121050118343027,
        121050118343049,
        121050118343040,
        121050117041019,
        121050117041031,
        121050118343039,
        121050118343031,
        121050118343043,
        121050118343050
    ],
    "zs:housing10":274,
    "zs:label":"Park View",
    "zs:pop10":524
},
  "geometry": {"coordinates":[-81.90645499999999,27.996474],"type":"Point"}
}