{
  "type": "Feature",
  "properties": {
    "gn:admin1_code":"VA",
    "gn:admin2_code":"770",
    "gn:asciiname":"Cox Estates",
    "gn:country_code":"US",
    "gn:dem":300,
    "gn:elevation":"301.0",
    "gn:feature_class":"P",
    "gn:feature_code":"PPL",
    "gn:name":"Cox Estates",
    "gn:population":0,
    "gn:timezone":"America/New_York",
    "iso:country":"US",
    "wof:name":"Cox Estates",
    "wof:placetype":"locality"
},
  "geometry": {"coordinates":[-80.00171,37.26375],"type":"Point"}
}