{
  "type": "Feature",
  "properties": {
    "gn:admin1_code":"CA",
    "gn:admin2_code":"109.0",
    "gn:asciiname":"Crystal Falls",
    "gn:country_code":"US",
    "gn:dem":848,
    "gn:elevation":"840.0",
    "gn:feature_class":"P",
    "gn:feature_code":"PPL",
    "gn:name":"Crystal Falls",
    "gn:population":0,
    "gn:timezone":"America/Los_Angeles",
    "iso:country":"US",
    "name:deu_x_preferred":[
        "Crystal Falls"
    ],
    "name:pol_x_preferred":[
        "Crystal Falls"
    ],
    "wof:name":"Crystal Falls",
    "wof:placetype":"locality"
},
  "geometry": {"coordinates":[-120.27186,38.0202],"type":"Point"}
}