{
  "type": "Feature",
  "properties": {
    "gn:admin1_code":"KS",
    "gn:admin2_code":"9.0",
    "gn:admin3_code":"66725.0",
    "gn:asciiname":"Kanbrick",
    "gn:country_code":"US",
    "gn:dem":562,
    "gn:elevation":"553.0",
    "gn:feature_class":"P",
    "gn:feature_code":"PPL",
    "gn:name":"Kanbrick",
    "gn:population":0,
    "gn:timezone":"America/Chicago",
    "iso:country":"US",
    "wof:name":"Kanbrick",
    "wof:placetype":"locality"
},
  "geometry": {"coordinates":[-98.77731,38.47279],"type":"Point"}
}