{
  "type": "Feature",
  "properties": {
    "gn:admin1_code":"CO",
    "gn:admin2_code":"71",
    "gn:asciiname":"Vigil",
    "gn:country_code":"US",
    "gn:dem":2238,
    "gn:elevation":"2245.0",
    "gn:feature_class":"P",
    "gn:feature_code":"PPL",
    "gn:name":"Vigil",
    "gn:population":0,
    "gn:timezone":"America/Denver",
    "iso:country":"US",
    "name:ara_x_preferred":[
        "\u0633\u0647\u0631"
    ],
    "name:ces_x_preferred":[
        "Vigilie"
    ],
    "name:fra_x_preferred":[
        "Veill\u00e9e"
    ],
    "name:ido_x_preferred":[
        "Vigilio"
    ],
    "name:ind_x_preferred":[
        "Ibadat malam"
    ],
    "name:ita_x_preferred":[
        "Vigilia"
    ],
    "name:jpn_x_preferred":[
        "\u30d3\u30b8\u30ea\u30a2"
    ],
    "name:lat_x_preferred":[
        "Pervigilium"
    ],
    "name:nld_x_preferred":[
        "Vooravond"
    ],
    "name:pol_x_preferred":[
        "Wigilia"
    ],
    "name:rus_x_preferred":[
        "\u0412\u0438\u0433\u0438\u043b\u0438\u044f"
    ],
    "name:swa_x_preferred":[
        "Kesha"
    ],
    "name:tam_x_preferred":[
        "\u0ba4\u0bbf\u0bb0\u0bc1\u0bb5\u0bbf\u0bb4\u0bbf\u0baa\u0bcd\u0baa\u0bc1"
    ],
    "name:ukr_x_preferred":[
        "\u041d\u0456\u0447\u043d\u0435 \u0447\u0443\u0432\u0430\u043d\u043d\u044f"
    ],
    "wof:name":"Vigil",
    "wof:placetype":"locality"
},
  "geometry": {"coordinates":[-104.94167,37.16113],"type":"Point"}
}