{
  "type": "Feature",
  "properties": {
    "gn:admin1_code":"TX",
    "gn:admin2_code":"379",
    "gn:asciiname":"Hooker Ridge",
    "gn:country_code":"US",
    "gn:dem":149,
    "gn:elevation":"144.0",
    "gn:feature_class":"P",
    "gn:feature_code":"PPL",
    "gn:name":"Hooker Ridge",
    "gn:population":0,
    "gn:timezone":"America/Chicago",
    "iso:country":"US",
    "wof:name":"Hooker Ridge",
    "wof:placetype":"locality"
},
  "geometry": {"coordinates":[-95.96552,32.91457],"type":"Point"}
}