{
  "type": "Feature",
  "properties": {
    "iso:country":"US",
    "name:eng_x_preferred":[
        "Fountainbrook"
    ],
    "wof:name":"Fountainbrook",
    "wof:placetype":"neighbourhood",
    "wof:population":614,
    "zs:area_m":234864.958057,
    "zs:blockids":[
        120950188003004,
        120950188003009,
        120950188003007,
        120950188003006,
        120950188003005,
        120950188004045,
        120950189006017,
        120950188003012,
        120950127013039,
        120950188003002,
        120950188004046
    ],
    "zs:housing10":548,
    "zs:label":"Fountainbrook",
    "zs:pop10":614
},
  "geometry": {"coordinates":[-81.379527,28.558016],"type":"Point"}
}