{
  "type": "Feature",
  "properties": {
    "gn:admin1_code":"NC",
    "gn:admin2_code":"53",
    "gn:admin3_code":"91188.0",
    "gn:asciiname":"Hemsath Mobile Home Park",
    "gn:country_code":"US",
    "gn:dem":4,
    "gn:elevation":"3.0",
    "gn:feature_class":"P",
    "gn:feature_code":"PPL",
    "gn:name":"Hemsath Mobile Home Park",
    "gn:population":0,
    "gn:timezone":"America/New_York",
    "iso:country":"US",
    "wof:name":"Hemsath Mobile Home Park",
    "wof:placetype":"campus"
},
  "geometry": {"coordinates":[-75.9242,36.506],"type":"Point"}
}