{
  "type": "Feature",
  "properties": {
    "gn:admin1_code":"CA",
    "gn:admin2_code":"65",
    "gn:asciiname":"Mesaville",
    "gn:country_code":"US",
    "gn:dem":127,
    "gn:elevation":"128.0",
    "gn:feature_class":"P",
    "gn:feature_code":"PPL",
    "gn:name":"Mesaville",
    "gn:population":0,
    "gn:timezone":"America/Los_Angeles",
    "iso:country":"US",
    "wof:name":"Mesaville",
    "wof:placetype":"locality"
},
  "geometry": {"coordinates":[-114.64995999999999,33.69419],"type":"Point"}
}