{
  "type": "Feature",
  "properties": {
    "iso:country":"US",
    "name:fra_x_preferred":[
        "Burpee"
    ],
    "qs_pg:aaroncc":"US",
    "qs_pg:name":"Burpee",
    "qs_pg:name_adm0":"United States",
    "qs_pg:name_adm1":"Oregon",
    "qs_pg:photos":17,
    "qs_pg:photos_1k":3,
    "qs_pg:photos_9k":1,
    "qs_pg:photos_9r":1,
    "qs_pg:photos_all":17,
    "qs_pg:photos_sr":1,
    "qs_pg:pop_sr":0,
    "qs_pg:qs_pg_placetype":"locality",
    "qs_pg:qs_pg_placetype_gp":"Town",
    "qs_pg:woe_adm0":23424977,
    "woe:adm0_id":23424977,
    "woe:name_adm0":"United States",
    "woe:name_adm1":"Oregon",
    "woe:placetype":"Town",
    "wof:name":"Burpee",
    "wof:placetype":"locality"
},
  "geometry": {"coordinates":[-123.902424,44.603939],"type":"Point"}
}