{
  "type": "Feature",
  "properties": {
    "gn:admin1_code":"KY",
    "gn:admin2_code":"31",
    "gn:asciiname":"Jetson",
    "gn:country_code":"US",
    "gn:dem":192,
    "gn:elevation":"192.0",
    "gn:feature_class":"P",
    "gn:feature_code":"PPL",
    "gn:name":"Jetson",
    "gn:population":0,
    "gn:timezone":"America/Chicago",
    "iso:country":"US",
    "wof:name":"Jetson",
    "wof:placetype":"locality"
},
  "geometry": {"coordinates":[-86.53193,37.24921],"type":"Point"}
}