{
  "type": "Feature",
  "properties": {
    "gn:admin1_code":"NC",
    "gn:admin2_code":"157",
    "gn:admin3_code":"92772.0",
    "gn:asciiname":"Hickory Grove",
    "gn:country_code":"US",
    "gn:dem":192,
    "gn:elevation":"186.0",
    "gn:feature_class":"P",
    "gn:feature_code":"PPL",
    "gn:name":"Hickory Grove",
    "gn:population":0,
    "gn:timezone":"America/New_York",
    "iso:country":"US",
    "name:ceb_x_preferred":[
        "Hickory Grove"
    ],
    "name:deu_x_preferred":[
        "Hickory Grove"
    ],
    "name:ita_x_preferred":[
        "Hickory Grove"
    ],
    "name:pol_x_preferred":[
        "Hickory Grove"
    ],
    "wof:name":"Hickory Grove",
    "wof:placetype":"locality"
},
  "geometry": {"coordinates":[-79.53836,36.51875],"type":"Point"}
}