{
  "type": "Feature",
  "properties": {
    "iso:country":"US",
    "name:eng_x_preferred":[
        "Glade/Westover"
    ],
    "qs:gn_adm0_cc":"US",
    "qs:gn_local":4747845,
    "qs:gn_nam_loc":"Blacksburg, Montgomery, Virginia, US",
    "qs:gn_namadm1":"VA",
    "qs:local_max":5389,
    "qs:local_sum":19335,
    "qs:localhoods":26,
    "qs:name":"Glade/Westover",
    "qs:name_adm0":"United States",
    "qs:name_adm1":"Virginia",
    "qs:name_adm2":"Montgomery",
    "qs:name_local":"Blacksburg",
    "qs:photo_max":44,
    "qs:photo_sum":44,
    "qs:placetype":"Suburb",
    "qs:quad_count":1,
    "qs:woe_adm0":23424977,
    "qs:woe_adm1":2347605,
    "qs:woe_adm2":12590387,
    "qs:woe_lau":0,
    "qs:woe_local":2365044,
    "qs:woe_ver":"7.10.0",
    "wof:lang":[
        "eng"
    ],
    "wof:name":"Glade/Westover",
    "wof:placetype":"neighbourhood",
    "wof:population":506,
    "zs:blockids":[
        511210203002025,
        511210203002026,
        511210203002024,
        511210203002031,
        511210203002029,
        511210203002039,
        511210203002028,
        511210203002030,
        511210203002027,
        511210203002040
    ],
    "zs:housing10":203,
    "zs:pop10":506
},
  "geometry": {"coordinates":[-80.451508,37.233608],"type":"Point"}
}