{
  "type": "Feature",
  "properties": {
    "gn:admin1_code":"CT",
    "gn:admin2_code":"1.0",
    "gn:admin3_code":"33620.0",
    "gn:asciiname":"North Mianus",
    "gn:country_code":"US",
    "gn:dem":57,
    "gn:elevation":"45.0",
    "gn:feature_class":"P",
    "gn:feature_code":"PPL",
    "gn:name":"North Mianus",
    "gn:population":0,
    "gn:timezone":"America/New_York",
    "iso:country":"US",
    "wof:name":"North Mianus",
    "wof:placetype":"locality"
},
  "geometry": {"coordinates":[-73.59206999999998,41.06676],"type":"Point"}
}