{
  "type": "Feature",
  "properties": {
    "gn:admin1_code":"MO",
    "gn:admin2_code":"229.0",
    "gn:admin3_code":"75634.0",
    "gn:asciiname":"Latham Mill",
    "gn:country_code":"US",
    "gn:dem":338,
    "gn:elevation":"337.0",
    "gn:feature_class":"P",
    "gn:feature_code":"PPL",
    "gn:name":"Latham Mill",
    "gn:population":0,
    "gn:timezone":"America/Chicago",
    "iso:country":"US",
    "wof:name":"Latham Mill",
    "wof:placetype":"locality"
},
  "geometry": {"coordinates":[-92.38905,37.28505],"type":"Point"}
}