{
  "type": "Feature",
  "properties": {
    "gn:country":"US",
    "gn:fcode":"PPL",
    "gn:population":0,
    "iso:country":"US",
    "name:azb_x_preferred":[
        "\u0648\u0631\u0645\u0632"
    ],
    "name:eng_x_preferred":[
        "Worms"
    ],
    "name:fas_x_preferred":[
        "\u0648\u0631\u0645\u0632"
    ],
    "name:hat_x_preferred":[
        "Worms"
    ],
    "qs_pg:aaroncc":"US",
    "qs_pg:gn_country":"US",
    "qs_pg:gn_fcode":"PPL",
    "qs_pg:gn_pop":0,
    "qs_pg:name":"Worms",
    "qs_pg:name_adm0":"United States",
    "qs_pg:name_adm1":"Nebraska",
    "qs_pg:photos":8,
    "qs_pg:photos_1k":2,
    "qs_pg:photos_9k":1,
    "qs_pg:photos_9r":1,
    "qs_pg:photos_all":8,
    "qs_pg:photos_sr":1,
    "qs_pg:pop_sr":0,
    "qs_pg:qs_pg_placetype":"locality",
    "qs_pg:qs_pg_placetype_gp":"Town",
    "qs_pg:woe_adm0":23424977,
    "woe:adm0_id":23424977,
    "woe:name_adm0":"United States",
    "woe:name_adm1":"Nebraska",
    "woe:placetype":"Town",
    "wof:name":"Worms",
    "wof:placetype":"locality"
},
  "geometry": {"coordinates":[-98.26895,41.09723],"type":"Point"}
}