{
  "type": "Feature",
  "properties": {
    "gn:elevation":524,
    "iso:country":"US",
    "name:eng_x_preferred":[
        "Garland Acres"
    ],
    "qs:gn_adm0_cc":"US",
    "qs:gn_fcode":"PPLX",
    "qs:gn_local":4633419,
    "qs:gn_nam_loc":"Johnson City, Washington, Tennessee, US",
    "qs:gn_namadm1":"TN",
    "qs:gn_name":"Garland Acres",
    "qs:local_max":1154,
    "qs:local_sum":3859,
    "qs:localhoods":24,
    "qs:name":"Garland Acres",
    "qs:name_adm0":"United States",
    "qs:name_adm1":"Tennessee",
    "qs:name_adm2":"Washington",
    "qs:name_local":"Johnson City",
    "qs:photo_max":28,
    "qs:photo_sum":51,
    "qs:placetype":"Suburb",
    "qs:quad_count":5,
    "qs:woe_adm0":23424977,
    "qs:woe_adm1":2347601,
    "qs:woe_adm2":12590001,
    "qs:woe_lau":0,
    "qs:woe_local":2429523,
    "qs:woe_ver":"7.10.0",
    "wof:lang":[
        "eng"
    ],
    "wof:name":"Garland Acres",
    "wof:placetype":"neighbourhood",
    "wof:population":2153,
    "zs:blockids":[
        471790609005016,
        471790609005017,
        471790609005008,
        471790609005021,
        471790606003012,
        471790606002040,
        471790609005020,
        471790606003018,
        471790609005014,
        471790606002033,
        471790606003027,
        471790606002022,
        471790606002018,
        471790606002031,
        471790606002030,
        471790606002035,
        471790609005013,
        471790606003029,
        471790606002034,
        471790606003025,
        471790606003033,
        471790606002021,
        471790606003013,
        471790606002041,
        471790609005007,
        471790609005015,
        471790609005006,
        471790609005019,
        471790606002026,
        471790606002038,
        471790606002016,
        471790606002019,
        471790609005018,
        471790606003031,
        471790606003028,
        471790606002029,
        471790606002036,
        471790606002025,
        471790606002039,
        471790606002017,
        471790606002010,
        471790606002028,
        471790606002027,
        471790606002037,
        471790606002032,
        471790606003024,
        471790606003017,
        471790606003030,
        471790606002015,
        471790606003026,
        471790606002020
    ],
    "zs:housing10":977,
    "zs:pop10":2153
},
  "geometry": {"coordinates":[-82.332351,36.293902],"type":"Point"}
}