{
  "type": "Feature",
  "properties": {
    "iso:country":"US",
    "name:eng_x_preferred":[
        "Dodge Tavern"
    ],
    "wof:name":"Dodge Tavern",
    "wof:placetype":"neighbourhood",
    "wof:population":24,
    "zs:area_m":219188.104921,
    "zs:blockids":[
        330059702002009,
        330059702002006,
        330059702002007,
        330059702002008
    ],
    "zs:housing10":9,
    "zs:label":"Dodge Tavern",
    "zs:pop10":24
},
  "geometry": {"coordinates":[-72.40219,43.111881],"type":"Point"}
}