{
  "type": "Feature",
  "properties": {
    "gn:admin1_code":"GA",
    "gn:admin2_code":"139.0",
    "gn:asciiname":"Clarks Bridge Place",
    "gn:country_code":"US",
    "gn:dem":377,
    "gn:elevation":"374.0",
    "gn:feature_class":"P",
    "gn:feature_code":"PPL",
    "gn:name":"Clarks Bridge Place",
    "gn:population":0,
    "gn:timezone":"America/New_York",
    "iso:country":"US",
    "wof:name":"Clarks Bridge Place",
    "wof:placetype":"locality"
},
  "geometry": {"coordinates":[-83.78268,34.38038],"type":"Point"}
}