{
  "type": "Feature",
  "properties": {
    "iso:country":"US",
    "name:eng_x_preferred":[
        "Woodsdale"
    ],
    "wof:name":"Woodsdale",
    "wof:placetype":"neighbourhood",
    "wof:population":1350,
    "zs:area_m":2467753.10925,
    "zs:blockids":[
        540690015003031,
        540690015003038,
        540690015003037,
        540690003001002,
        540690015003021,
        540690015001028,
        540690015003002,
        540690015001019,
        540690015001015,
        540690015001023,
        540690015003010,
        540690015003023,
        540690015003011,
        540690015003040,
        540690003002003,
        540690003001001,
        540690015001020,
        540690015001029,
        540690015003013,
        540690015001021,
        540690015001035,
        540690003002030,
        540690015003008,
        540690015003012,
        540690003002002,
        540690015003041,
        540690015001033,
        540690003001012,
        540690015001026,
        540690015003018,
        540690015003022,
        540690015003020,
        540690015002016,
        540690015003003,
        540690015001013,
        540690015001018,
        540690015001014,
        540690003002000,
        540690015001024,
        540690015003030,
        540690003001003,
        540690015002017,
        540690003002004,
        540690015001034,
        540690015001022,
        540690015003042,
        540690015003029,
        540690015003028,
        540690015001027,
        540690015003019,
        540690003001011,
        540690003002001,
        540690015003009,
        540690015001025,
        540690003002005
    ],
    "zs:housing10":586,
    "zs:label":"Woodsdale",
    "zs:pop10":1350
},
  "geometry": {"coordinates":[-80.697847,40.086215],"type":"Point"}
}