{
  "type": "Feature",
  "properties": {
    "iso:country":"US",
    "name:eng_x_preferred":[
        "Parkmeadow"
    ],
    "wof:name":"Parkmeadow",
    "wof:placetype":"neighbourhood",
    "wof:population":2054,
    "zs:area_m":1327834.012629,
    "zs:blockids":[
        371830534082000,
        371830534081019,
        371830534081020,
        371830536031065,
        371830534081004,
        371830534081017,
        371830534081003,
        371830534081016,
        371830534081014,
        371830534081005,
        371830534081009,
        371830534081010
    ],
    "zs:housing10":624,
    "zs:label":"Parkmeadow",
    "zs:pop10":2054
},
  "geometry": {"coordinates":[-78.860101,35.784213],"type":"Point"}
}