{
  "type": "Feature",
  "properties": {
    "iso:country":"US",
    "name:eng_x_preferred":[
        "Windermere Centre"
    ],
    "wof:name":"Windermere Centre",
    "wof:placetype":"neighbourhood",
    "wof:population":59,
    "zs:area_m":78294.217459,
    "zs:blockids":[
        484530018403028
    ],
    "zs:housing10":20,
    "zs:label":"Windermere Centre",
    "zs:pop10":59
},
  "geometry": {"coordinates":[-97.64823800000001,30.441393],"type":"Point"}
}