{
  "type": "Feature",
  "properties": {
    "iso:country":"US",
    "name:deu_x_preferred":[
        "Old Salem"
    ],
    "name:jpn_x_preferred":[
        "\u30aa\u30fc\u30eb\u30c9\u30fb\u30bb\u30fc\u30e9\u30e0"
    ],
    "name:rus_x_preferred":[
        "\u0421\u0442\u0430\u0440\u044b\u0439 \u0421\u0430\u043b\u0435\u043c"
    ],
    "qs_pg:aaroncc":"US",
    "qs_pg:name":"Old Salem",
    "qs_pg:name_adm0":"United States",
    "qs_pg:name_adm1":"Texas",
    "qs_pg:photos":193,
    "qs_pg:photos_1k":39,
    "qs_pg:photos_9k":1,
    "qs_pg:photos_9r":4,
    "qs_pg:photos_all":193,
    "qs_pg:photos_sr":4,
    "qs_pg:pop_sr":0,
    "qs_pg:qs_pg_placetype":"locality",
    "qs_pg:qs_pg_placetype_gp":"Town",
    "qs_pg:woe_adm0":23424977,
    "woe:adm0_id":23424977,
    "woe:name_adm0":"United States",
    "woe:name_adm1":"Texas",
    "woe:placetype":"Town",
    "wof:name":"Old Salem",
    "wof:placetype":"locality"
},
  "geometry": {"coordinates":[-93.77624900000001,30.578177],"type":"Point"}
}