{
  "type": "Feature",
  "properties": {
    "gn:admin1_code":"AR",
    "gn:admin2_code":"77.0",
    "gn:admin3_code":"93600.0",
    "gn:asciiname":"Holub Crossing",
    "gn:country_code":"US",
    "gn:dem":62,
    "gn:elevation":"63.0",
    "gn:feature_class":"P",
    "gn:feature_code":"PPL",
    "gn:name":"Holub Crossing",
    "gn:population":0,
    "gn:timezone":"America/Chicago",
    "iso:country":"US",
    "name:eng_x_preferred":[
        "Holub Crossing"
    ],
    "name:und_x_variant":[
        "Holders Corners",
        "Holub",
        "Holub Holders Corners"
    ],
    "wof:name":"Holub Crossing",
    "wof:placetype":"locality"
},
  "geometry": {"coordinates":[-90.90817,34.84787],"type":"Point"}
}