{
  "type": "Feature",
  "properties": {
    "gn:admin1_code":"WA",
    "gn:admin2_code":"27.0",
    "gn:asciiname":"Rustemeyer Mobile Home Park",
    "gn:country_code":"US",
    "gn:dem":25,
    "gn:elevation":"27.0",
    "gn:feature_class":"P",
    "gn:feature_code":"PPL",
    "gn:name":"Rustemeyer Mobile Home Park",
    "gn:population":0,
    "gn:timezone":"America/Los_Angeles",
    "iso:country":"US",
    "wof:name":"Rustemeyer Mobile Home Park",
    "wof:placetype":"campus"
},
  "geometry": {"coordinates":[-123.98396,46.91323],"type":"Point"}
}