{
  "type": "Feature",
  "properties": {
    "gn:admin1_code":"PA",
    "gn:admin2_code":"15.0",
    "gn:admin3_code":"57176.0",
    "gn:asciiname":"Zion Heights",
    "gn:country_code":"US",
    "gn:dem":427,
    "gn:elevation":"415.0",
    "gn:feature_class":"P",
    "gn:feature_code":"PPL",
    "gn:name":"Zion Heights",
    "gn:population":0,
    "gn:timezone":"America/New_York",
    "iso:country":"US",
    "wof:name":"Zion Heights",
    "wof:placetype":"locality"
},
  "geometry": {"coordinates":[-76.24799,41.84646],"type":"Point"}
}