{
  "type": "Feature",
  "properties": {
    "gn:admin1_code":"VA",
    "gn:admin2_code":"51",
    "gn:asciiname":"Smith Corners",
    "gn:country_code":"US",
    "gn:dem":726,
    "gn:elevation":"735.0",
    "gn:feature_class":"P",
    "gn:feature_code":"PPL",
    "gn:name":"Smith Corners",
    "gn:population":0,
    "gn:timezone":"America/New_York",
    "iso:country":"US",
    "wof:name":"Smith Corners",
    "wof:placetype":"locality"
},
  "geometry": {"coordinates":[-82.38404,37.05899],"type":"Point"}
}