{
  "type": "Feature",
  "properties": {
    "gn:admin1_code":"VT",
    "gn:admin2_code":"5.0",
    "gn:admin3_code":"17125.0",
    "gn:asciiname":"Greenbank Hollow",
    "gn:country_code":"US",
    "gn:dem":343,
    "gn:elevation":"352.0",
    "gn:feature_class":"P",
    "gn:feature_code":"PPL",
    "gn:name":"Greenbank Hollow",
    "gn:population":0,
    "gn:timezone":"America/New_York",
    "iso:country":"US",
    "name:eng_x_preferred":[
        "Greenbank Hollow"
    ],
    "name:und_x_variant":[
        "South Danville",
        "Greenbanks",
        "Greenbank Village"
    ],
    "wof:name":"Greenbank Hollow",
    "wof:placetype":"locality"
},
  "geometry": {"coordinates":[-72.12120999999998,44.37728],"type":"Point"}
}