{
  "type": "Feature",
  "properties": {
    "gn:admin1_code":"VA",
    "gn:admin2_code":"1",
    "gn:asciiname":"Tunnels Mill",
    "gn:country_code":"US",
    "gn:dem":6,
    "gn:elevation":"2.0",
    "gn:feature_class":"P",
    "gn:feature_code":"PPL",
    "gn:name":"Tunnels Mill",
    "gn:population":0,
    "gn:timezone":"America/New_York",
    "iso:country":"US",
    "wof:name":"Tunnels Mill",
    "wof:placetype":"locality"
},
  "geometry": {"coordinates":[-75.58076,37.96651],"type":"Point"}
}