{
  "type": "Feature",
  "properties": {
    "gn:admin1_code":"OH",
    "gn:admin2_code":"99.0",
    "gn:admin3_code":"3198.0",
    "gn:asciiname":"Fountain Square",
    "gn:country_code":"US",
    "gn:dem":329,
    "gn:feature_class":"P",
    "gn:feature_code":"PPL",
    "gn:name":"Fountain Square",
    "gn:population":0,
    "gn:timezone":"America/New_York",
    "iso:country":"US",
    "wof:name":"Fountain Square",
    "wof:placetype":"locality"
},
  "geometry": {"coordinates":[-80.72518000000002,41.08495],"type":"Point"}
}