{
  "type": "Feature",
  "properties": {
    "gn:admin1_code":"AR",
    "gn:admin2_code":"85.0",
    "gn:admin3_code":"94131.0",
    "gn:asciiname":"Windwood Circle",
    "gn:country_code":"US",
    "gn:dem":103,
    "gn:elevation":"94.0",
    "gn:feature_class":"P",
    "gn:feature_code":"PPL",
    "gn:name":"Windwood Circle",
    "gn:population":0,
    "gn:timezone":"America/Chicago",
    "iso:country":"US",
    "wof:name":"Windwood Circle",
    "wof:placetype":"locality"
},
  "geometry": {"coordinates":[-91.99625,34.93259],"type":"Point"}
}