{
  "type": "Feature",
  "properties": {
    "gn:country":"US",
    "gn:fcode":"PPL",
    "gn:population":0,
    "iso:country":"US",
    "name:azb_x_preferred":[
        "\u0641\u0631\u0646\u0686 \u06a9\u0631\u06cc\u06a9"
    ],
    "name:eng_x_preferred":[
        "French Creek"
    ],
    "name:fas_x_preferred":[
        "\u0641\u0631\u0646\u0686 \u06a9\u0631\u06cc\u06a9"
    ],
    "name:fra_x_preferred":[
        "French Creek"
    ],
    "name:und_x_variant":[
        "Frenchcreek"
    ],
    "name:vol_x_preferred":[
        "French Creek"
    ],
    "qs_pg:aaroncc":"US",
    "qs_pg:gn_country":"US",
    "qs_pg:gn_fcode":"PPL",
    "qs_pg:gn_pop":0,
    "qs_pg:name":"French Creek",
    "qs_pg:name_adm0":"United States",
    "qs_pg:name_adm1":"West Virginia",
    "qs_pg:photos":142,
    "qs_pg:photos_1k":29,
    "qs_pg:photos_9k":1,
    "qs_pg:photos_9r":3,
    "qs_pg:photos_all":142,
    "qs_pg:photos_sr":3,
    "qs_pg:pop_sr":0,
    "qs_pg:qs_pg_placetype":"locality",
    "qs_pg:qs_pg_placetype_gp":"Town",
    "qs_pg:woe_adm0":23424977,
    "woe:adm0_id":23424977,
    "woe:name_adm0":"United States",
    "woe:name_adm1":"West Virginia",
    "woe:placetype":"Town",
    "wof:name":"French Creek",
    "wof:placetype":"locality"
},
  "geometry": {"coordinates":[-80.29731,38.88566],"type":"Point"}
}