{
  "type": "Feature",
  "properties": {
    "gn:admin1_code":"KY",
    "gn:admin2_code":"85",
    "gn:asciiname":"Tousey",
    "gn:country_code":"US",
    "gn:dem":137,
    "gn:elevation":"136.0",
    "gn:feature_class":"P",
    "gn:feature_code":"PPL",
    "gn:name":"Tousey",
    "gn:population":0,
    "gn:timezone":"America/Chicago",
    "iso:country":"US",
    "wof:name":"Tousey",
    "wof:placetype":"locality"
},
  "geometry": {"coordinates":[-86.54776,37.5145],"type":"Point"}
}