{
  "type": "Feature",
  "properties": {
    "gn:admin1_code":"TX",
    "gn:admin2_code":"115.0",
    "gn:asciiname":"Pride",
    "gn:country_code":"US",
    "gn:dem":945,
    "gn:elevation":"944.0",
    "gn:feature_class":"P",
    "gn:feature_code":"PPL",
    "gn:name":"Pride",
    "gn:population":0,
    "gn:timezone":"America/Chicago",
    "iso:country":"US",
    "name:ara_x_preferred":[
        "\u0641\u062e\u0631"
    ],
    "name:bre_x_preferred":[
        "Ourgouilh"
    ],
    "name:cat_x_preferred":[
        "Orgull"
    ],
    "name:deu_x_preferred":[
        "Stolz"
    ],
    "name:epo_x_preferred":[
        "Orgojlo"
    ],
    "name:fra_x_preferred":[
        "Orgueil"
    ],
    "name:heb_x_preferred":[
        "\u05d2\u05d0\u05d5\u05d5\u05d4"
    ],
    "name:ita_x_preferred":[
        "Orgoglio"
    ],
    "name:kan_x_preferred":[
        "\u0c85\u0cad\u0cbf\u0cae\u0cbe\u0ca8"
    ],
    "name:nld_x_preferred":[
        "Trots"
    ],
    "name:por_x_preferred":[
        "Orgulho"
    ],
    "name:sco_x_preferred":[
        "Pride"
    ],
    "wof:name":"Pride",
    "wof:placetype":"locality"
},
  "geometry": {"coordinates":[-102.07767,32.93732],"type":"Point"}
}