{
  "type": "Feature",
  "properties": {
    "gn:admin1_code":"FL",
    "gn:admin2_code":"43.0",
    "gn:asciiname":"Lakeport",
    "gn:country_code":"US",
    "gn:dem":12,
    "gn:elevation":"5.0",
    "gn:feature_class":"P",
    "gn:feature_code":"PPL",
    "gn:name":"Lakeport",
    "gn:population":0,
    "gn:timezone":"America/New_York",
    "iso:country":"US",
    "name:zho_x_preferred":[
        "\u840a\u514b\u6ce2\u7279"
    ],
    "wof:name":"Lakeport",
    "wof:placetype":"locality"
},
  "geometry": {"coordinates":[-81.12729,26.97644],"type":"Point"}
}