{
  "type": "Feature",
  "properties": {
    "gn:admin1_code":"ME",
    "gn:admin2_code":"9.0",
    "gn:admin3_code":"86655.0",
    "gn:asciiname":"Summer Harbor",
    "gn:country_code":"US",
    "gn:dem":31,
    "gn:elevation":"27.0",
    "gn:feature_class":"P",
    "gn:feature_code":"PPL",
    "gn:name":"Summer Harbor",
    "gn:population":0,
    "gn:timezone":"America/New_York",
    "iso:country":"US",
    "name:eng_x_preferred":[
        "Summer Harbor"
    ],
    "name:und_x_variant":[
        "Myrickville"
    ],
    "wof:name":"Summer Harbor",
    "wof:placetype":"locality"
},
  "geometry": {"coordinates":[-68.10584,44.41564],"type":"Point"}
}