{
  "type": "Feature",
  "properties": {
    "iso:country":"US",
    "name:eng_x_preferred":[
        "Copperhill"
    ],
    "qs:gn_adm0_cc":"US",
    "qs:gn_local":5405288,
    "qs:gn_nam_loc":"Valencia, Los Angeles, California, US",
    "qs:gn_namadm1":"CA",
    "qs:local_max":1805,
    "qs:local_sum":7254,
    "qs:localhoods":16,
    "qs:name":"Copperhill",
    "qs:name_adm0":"United States",
    "qs:name_adm1":"California",
    "qs:name_adm2":"Los Angeles",
    "qs:name_local":"Valencia",
    "qs:photo_max":415,
    "qs:photo_sum":1078,
    "qs:placetype":"Suburb",
    "qs:quad_count":35,
    "qs:woe_adm0":23424977,
    "qs:woe_adm1":2347563,
    "qs:woe_adm2":12587688,
    "qs:woe_lau":0,
    "qs:woe_local":2510684,
    "qs:woe_ver":"7.10.0",
    "wof:name":"Copperhill",
    "wof:placetype":"neighbourhood",
    "wof:population":4604,
    "zs:blockids":[
        60379200111069,
        60379201071017,
        60379201021003,
        60379201021012,
        60379201071009,
        60379201021004,
        60379201021008,
        60379201071003,
        60379201021009,
        60379201071011,
        60379201071012,
        60379201071001,
        60379201071008,
        60379201021010,
        60379201071069,
        60379201071000,
        60379201071070,
        60379201071015,
        60379201021007,
        60379201071004,
        60379201071016,
        60379201071010,
        60379201081008,
        60379201021011,
        60379201071071,
        60379201071002,
        60379201081028,
        60379201071013,
        60379202001030,
        60379201021017,
        60379201071007
    ],
    "zs:housing10":1468,
    "zs:pop10":4604
},
  "geometry": {"coordinates":[-118.55626599999999,34.469496],"type":"Point"}
}