{
  "type": "Feature",
  "properties": {
    "gn:admin1_code":"TX",
    "gn:admin2_code":"61",
    "gn:asciiname":"Monica",
    "gn:country_code":"US",
    "gn:dem":13,
    "gn:elevation":"7.0",
    "gn:feature_class":"P",
    "gn:feature_code":"PPL",
    "gn:name":"Monica",
    "gn:population":0,
    "gn:timezone":"America/Chicago",
    "iso:country":"US",
    "name:bre_x_preferred":[
        "Monica"
    ],
    "name:deu_x_preferred":[
        "Monica"
    ],
    "name:fas_x_preferred":[
        "\u0645\u0648\u0646\u06cc\u06a9\u0627"
    ],
    "name:fra_x_preferred":[
        "Monica"
    ],
    "name:ita_x_preferred":[
        "Monica"
    ],
    "name:lat_x_preferred":[
        "Monica"
    ],
    "name:nld_x_preferred":[
        "Monica"
    ],
    "name:por_x_preferred":[
        "Monica"
    ],
    "wof:name":"Monica",
    "wof:placetype":"locality"
},
  "geometry": {"coordinates":[-97.24609,25.96425],"type":"Point"}
}