{
  "type": "Feature",
  "properties": {
    "gn:admin1_code":"PA",
    "gn:admin2_code":"29",
    "gn:admin3_code":"84104.0",
    "gn:asciiname":"Land Grant Farms",
    "gn:country_code":"US",
    "gn:dem":93,
    "gn:elevation":"93.0",
    "gn:feature_class":"P",
    "gn:feature_code":"PPL",
    "gn:name":"Land Grant Farms",
    "gn:population":0,
    "gn:timezone":"America/New_York",
    "iso:country":"US",
    "wof:name":"Land Grant Farms",
    "wof:placetype":"locality"
},
  "geometry": {"coordinates":[-75.52630000000001,39.9444],"type":"Point"}
}