{
  "type": "Feature",
  "properties": {
    "gn:elevation":271,
    "iso:country":"US",
    "name:bel_x_preferred":[
        "\u041f\u0430\u0440\u043a\u0435\u0440"
    ],
    "name:ceb_x_preferred":[
        "Parker"
    ],
    "name:ces_x_preferred":[
        "Parker"
    ],
    "name:deu_x_preferred":[
        "Parker"
    ],
    "name:eng_x_preferred":[
        "Parker"
    ],
    "name:fas_x_preferred":[
        "\u067e\u0627\u0631\u06a9\u0631"
    ],
    "name:fin_x_preferred":[
        "Parker"
    ],
    "name:fra_x_preferred":[
        "Parker"
    ],
    "name:heb_x_preferred":[
        "\u05e4\u05d0\u05e8\u05e7\u05e8"
    ],
    "name:hun_x_preferred":[
        "Parker"
    ],
    "name:ita_x_preferred":[
        "Parker"
    ],
    "name:jpn_x_preferred":[
        "\u30d1\u30fc\u30ab\u30fc"
    ],
    "name:lav_x_preferred":[
        "P\u0101rkers"
    ],
    "name:lit_x_preferred":[
        "Parker"
    ],
    "name:nld_x_preferred":[
        "Parker"
    ],
    "name:nor_x_preferred":[
        "Parker"
    ],
    "name:pol_x_preferred":[
        "Parker"
    ],
    "name:por_x_preferred":[
        "Parker"
    ],
    "name:rus_x_preferred":[
        "\u041f\u0430\u0440\u043a\u0435\u0440"
    ],
    "name:spa_x_preferred":[
        "Parker"
    ],
    "name:srp_x_preferred":[
        "\u041f\u0430\u0440\u043a\u0435\u0440"
    ],
    "name:swe_x_preferred":[
        "Parker"
    ],
    "name:ukr_x_preferred":[
        "\u041f\u0430\u0440\u043a\u0435\u0440"
    ],
    "name:und_x_variant":[
        "Unionville"
    ],
    "name:urd_x_preferred":[
        "\u067e\u0627\u0631\u06a9\u0631"
    ],
    "name:vie_x_preferred":[
        "Parker"
    ],
    "name:vol_x_preferred":[
        "Parker"
    ],
    "qs:gn_adm0_cc":"US",
    "qs:gn_fcode":"PPL",
    "qs:gn_local":5106124,
    "qs:gn_nam_loc":"Washington Twp, Morris, New Jersey, US",
    "qs:gn_namadm1":"NJ",
    "qs:gn_name":"Parker",
    "qs:local_max":308,
    "qs:local_sum":614,
    "qs:localhoods":7,
    "qs:name":"Parker",
    "qs:name_adm0":"United States",
    "qs:name_adm1":"New Jersey",
    "qs:name_adm2":"Morris",
    "qs:name_local":"Washington Twp",
    "qs:photo_max":1,
    "qs:photo_sum":2,
    "qs:placetype":"Suburb",
    "qs:quad_count":2,
    "qs:woe_adm0":23424977,
    "qs:woe_adm1":2347589,
    "qs:woe_adm2":12589271,
    "qs:woe_lau":0,
    "qs:woe_local":55864856,
    "qs:woe_ver":"7.10.0",
    "wof:lang":[
        "eng"
    ],
    "wof:name":"Parker",
    "wof:placetype":"neighbourhood",
    "wof:population":277,
    "zs:blockids":[
        340270462983013,
        340270462982017,
        340270462983005,
        340270462983003,
        340270462983004,
        340270462982008
    ],
    "zs:housing10":93,
    "zs:pop10":277
},
  "geometry": {"coordinates":[-74.76196299999999,40.76182],"type":"Point"}
}