{
  "type": "Feature",
  "properties": {
    "gn:admin1_code":"IL",
    "gn:admin2_code":"151",
    "gn:asciiname":"New Liberty",
    "gn:country_code":"US",
    "gn:dem":108,
    "gn:elevation":"104.0",
    "gn:feature_class":"P",
    "gn:feature_code":"PPL",
    "gn:name":"New Liberty",
    "gn:population":0,
    "gn:timezone":"America/Chicago",
    "iso:country":"US",
    "name:fas_x_preferred":[
        "\u0646\u06cc\u0648 \u0644\u06cc\u0628\u0631\u062a\u06cc"
    ],
    "name:urd_x_preferred":[
        "\u0646\u06cc\u0648 \u0644\u0628\u0631\u0679\u06cc"
    ],
    "wof:name":"New Liberty",
    "wof:placetype":"locality"
},
  "geometry": {"coordinates":[-88.44781999999999,37.122],"type":"Point"}
}