{
  "type": "Feature",
  "properties": {
    "gn:admin1_code":"MO",
    "gn:admin2_code":"181.0",
    "gn:admin3_code":"37448.0",
    "gn:asciiname":"Paterson Ford",
    "gn:country_code":"US",
    "gn:dem":126,
    "gn:elevation":"119.0",
    "gn:feature_class":"P",
    "gn:feature_code":"PPL",
    "gn:name":"Paterson Ford",
    "gn:population":0,
    "gn:timezone":"America/Chicago",
    "iso:country":"US",
    "wof:name":"Paterson Ford",
    "wof:placetype":"locality"
},
  "geometry": {"coordinates":[-90.73345,36.73339],"type":"Point"}
}