{
  "type": "Feature",
  "properties": {
    "gn:admin1_code":"OK",
    "gn:admin2_code":"41.0",
    "gn:asciiname":"Row",
    "gn:country_code":"US",
    "gn:dem":354,
    "gn:elevation":"351.0",
    "gn:feature_class":"P",
    "gn:feature_code":"PPL",
    "gn:name":"Row",
    "gn:population":0,
    "gn:timezone":"America/Chicago",
    "iso:country":"US",
    "name:ceb_x_preferred":[
        "Row"
    ],
    "name:deu_x_preferred":[
        "Row"
    ],
    "name:sna_x_preferred":[
        "Muzera"
    ],
    "name:swe_x_preferred":[
        "Row"
    ],
    "wof:name":"Row",
    "wof:placetype":"locality"
},
  "geometry": {"coordinates":[-94.6905,36.27869000000001],"type":"Point"}
}