{
  "type": "Feature",
  "properties": {
    "gn:admin1_code":"OK",
    "gn:admin2_code":"35",
    "gn:asciiname":"Cocklebur Flat",
    "gn:country_code":"US",
    "gn:dem":247,
    "gn:elevation":"245.0",
    "gn:feature_class":"P",
    "gn:feature_code":"PPL",
    "gn:name":"Cocklebur Flat",
    "gn:population":0,
    "gn:timezone":"America/Chicago",
    "iso:country":"US",
    "wof:name":"Cocklebur Flat",
    "wof:placetype":"locality"
},
  "geometry": {"coordinates":[-95.19775,36.83008],"type":"Point"}
}