{
  "type": "Feature",
  "properties": {
    "gn:admin1_code":"VT",
    "gn:admin2_code":"25.0",
    "gn:admin3_code":"7900.0",
    "gn:asciiname":"White River Junction VA Medical Center",
    "gn:country_code":"US",
    "gn:dem":128,
    "gn:feature_class":"P",
    "gn:feature_code":"PPL",
    "gn:name":"White River Junction VA Medical Center",
    "gn:population":0,
    "gn:timezone":"America/New_York",
    "iso:country":"US",
    "wof:name":"White River Junction VA Medical Center",
    "wof:placetype":"locality"
},
  "geometry": {"coordinates":[-72.56786,42.83049000000001],"type":"Point"}
}