{
  "type": "Feature",
  "properties": {
    "gn:admin1_code":"AR",
    "gn:admin2_code":"143.0",
    "gn:admin3_code":"90957.0",
    "gn:asciiname":"Woolsey",
    "gn:country_code":"US",
    "gn:dem":425,
    "gn:elevation":"415.0",
    "gn:feature_class":"P",
    "gn:feature_code":"PPL",
    "gn:name":"Woolsey",
    "gn:population":0,
    "gn:timezone":"America/Chicago",
    "iso:country":"US",
    "name:eng_x_preferred":[
        "Woolsey"
    ],
    "name:fas_x_preferred":[
        "\u0648\u0648\u0644\u0633\u06cc"
    ],
    "name:und_x_variant":[
        "Woolseys"
    ],
    "name:zho_x_preferred":[
        "\u4f0d\u723e\u897f"
    ],
    "wof:name":"Woolsey",
    "wof:placetype":"locality"
},
  "geometry": {"coordinates":[-94.16853999999999,35.88536],"type":"Point"}
}