{
  "type": "Feature",
  "properties": {
    "gn:admin1_code":"WV",
    "gn:admin2_code":"61",
    "gn:asciiname":"Laurel Point",
    "gn:country_code":"US",
    "gn:dem":301,
    "gn:elevation":"301.0",
    "gn:feature_class":"P",
    "gn:feature_code":"PPL",
    "gn:name":"Laurel Point",
    "gn:population":0,
    "gn:timezone":"America/New_York",
    "iso:country":"US",
    "wof:name":"Laurel Point",
    "wof:placetype":"locality"
},
  "geometry": {"coordinates":[-80.00811999999998,39.61925],"type":"Point"}
}