{
  "type": "Feature",
  "properties": {
    "gn:admin1_code":"WV",
    "gn:admin2_code":"33",
    "gn:asciiname":"Dawmont",
    "gn:country_code":"US",
    "gn:dem":319,
    "gn:elevation":"317.0",
    "gn:feature_class":"P",
    "gn:feature_code":"PPL",
    "gn:name":"Dawmont",
    "gn:population":0,
    "gn:timezone":"America/New_York",
    "iso:country":"US",
    "name:eng_x_preferred":[
        "Dawmont"
    ],
    "name:und_x_variant":[
        "Dawson"
    ],
    "wof:name":"Dawmont",
    "wof:placetype":"locality"
},
  "geometry": {"coordinates":[-80.34231,39.31759],"type":"Point"}
}