{
  "type": "Feature",
  "properties": {
    "iso:country":"US",
    "name:eng_x_preferred":[
        "Fonmeadow"
    ],
    "wof:name":"Fonmeadow",
    "wof:placetype":"neighbourhood",
    "wof:population":3409,
    "zs:area_m":691117.035514,
    "zs:blockids":[
        482014236004003,
        482014223011000,
        482014222003003,
        482014223011003,
        482014236004002,
        482014234011012,
        482014236004005,
        482014223011005,
        482014234011013,
        482014223011008,
        482014222003002,
        482014222003001,
        482014222003006,
        482014222003005,
        482014222003000,
        482014223011004,
        482014223011006,
        482014223011009,
        482014222003007,
        482014222003009,
        482014222001030,
        482014222003008,
        482014236004012,
        482014223011007,
        482014222003004,
        482014223011001,
        482014223011002,
        482014223013001,
        482014236004000,
        482014236004001
    ],
    "zs:housing10":1864,
    "zs:label":"Fonmeadow",
    "zs:pop10":3409
},
  "geometry": {"coordinates":[-95.50762899999999,29.644063],"type":"Point"}
}