{
  "type": "Feature",
  "properties": {
    "iso:country":"US",
    "name:eng_x_preferred":[
        "Hathaway Home Tracts"
    ],
    "wof:name":"Hathaway Home Tracts",
    "wof:placetype":"neighbourhood",
    "wof:population":436,
    "zs:area_m":552067.116256,
    "zs:blockids":[
        530110405081034,
        530110405092056,
        530110405081035,
        530110405092003,
        530110405081028,
        530110405081009,
        530110405092058,
        530110405081011,
        530110405092000,
        530110405092027,
        530110405092001,
        530110405081023,
        530110405092026,
        530110405081018,
        530110405081022,
        530110405081013,
        530110405092057,
        530110405081033,
        530110405092002,
        530110405081012
    ],
    "zs:housing10":190,
    "zs:label":"Hathaway Home Tracts",
    "zs:pop10":436
},
  "geometry": {"coordinates":[-122.343564,45.582064],"type":"Point"}
}