{
  "type": "Feature",
  "properties": {
    "gn:admin1_code":"TX",
    "gn:admin2_code":"427.0",
    "gn:asciiname":"West Alto Bonito Colonia",
    "gn:country_code":"US",
    "gn:dem":53,
    "gn:elevation":"50.0",
    "gn:feature_class":"P",
    "gn:feature_code":"PPL",
    "gn:name":"West Alto Bonito Colonia",
    "gn:population":696,
    "gn:timezone":"America/Chicago",
    "iso:country":"US",
    "name:eng_x_preferred":[
        "West Alto Bonito Colonia"
    ],
    "name:und_x_variant":[
        "Alto Bonito",
        "Alto Bonito Heights Number 5 Colonia"
    ],
    "wof:name":"West Alto Bonito Colonia",
    "wof:placetype":"locality",
    "wof:population":696
},
  "geometry": {"coordinates":[-98.66336,26.31424],"type":"Point"}
}