{
  "type": "Feature",
  "properties": {
    "gn:admin1_code":"ID",
    "gn:admin2_code":"17.0",
    "gn:asciiname":"Denton",
    "gn:country_code":"US",
    "gn:dem":644,
    "gn:elevation":"643.0",
    "gn:feature_class":"P",
    "gn:feature_code":"PPL",
    "gn:name":"Denton",
    "gn:population":0,
    "gn:timezone":"America/Los_Angeles",
    "iso:country":"US",
    "name:ara_x_preferred":[
        "\u062f\u0646\u062a\u0648\u0646"
    ],
    "name:bul_x_preferred":[
        "\u0414\u0435\u043d\u0442\u044a\u043d"
    ],
    "name:cat_x_preferred":[
        "Denton"
    ],
    "name:ceb_x_preferred":[
        "Denton"
    ],
    "name:ces_x_preferred":[
        "Denton"
    ],
    "name:deu_x_preferred":[
        "Denton"
    ],
    "name:eng_x_preferred":[
        "Denton"
    ],
    "name:est_x_preferred":[
        "Denton"
    ],
    "name:fas_x_preferred":[
        "\u062f\u0646\u062a\u0648\u0646"
    ],
    "name:fin_x_preferred":[
        "Denton"
    ],
    "name:fra_x_preferred":[
        "Denton"
    ],
    "name:ita_x_preferred":[
        "Denton"
    ],
    "name:jpn_x_preferred":[
        "\u30c7\u30f3\u30c8\u30f3"
    ],
    "name:nld_x_preferred":[
        "Denton"
    ],
    "name:pol_x_preferred":[
        "Denton"
    ],
    "name:por_x_preferred":[
        "Denton"
    ],
    "name:rus_x_preferred":[
        "\u0414\u0435\u043d\u0442\u043e\u043d"
    ],
    "name:srp_x_preferred":[
        "\u0414\u0435\u043d\u0442\u043e\u043d"
    ],
    "name:swe_x_preferred":[
        "Denton"
    ],
    "name:ukr_x_preferred":[
        "\u0414\u0435\u043d\u0442\u043e\u043d"
    ],
    "name:und_x_variant":[
        "Thornton"
    ],
    "name:vol_x_preferred":[
        "Denton"
    ],
    "wof:name":"Denton",
    "wof:placetype":"locality"
},
  "geometry": {"coordinates":[-116.24823000000001,48.20271],"type":"Point"}
}