{
  "type": "Feature",
  "properties": {
    "gn:admin1_code":"NC",
    "gn:admin2_code":"85",
    "gn:admin3_code":"90416.0",
    "gn:asciiname":"Duncan",
    "gn:country_code":"US",
    "gn:dem":139,
    "gn:elevation":"143.0",
    "gn:feature_class":"P",
    "gn:feature_code":"PPL",
    "gn:name":"Duncan",
    "gn:population":0,
    "gn:timezone":"America/New_York",
    "iso:country":"US",
    "name:spa_x_preferred":[
        "Duncan"
    ],
    "wof:name":"Duncan",
    "wof:placetype":"locality"
},
  "geometry": {"coordinates":[-78.87196,35.56266],"type":"Point"}
}