{
  "type": "Feature",
  "properties": {
    "gn:admin1_code":"MS",
    "gn:admin2_code":"63.0",
    "gn:asciiname":"McBride",
    "gn:country_code":"US",
    "gn:dem":112,
    "gn:elevation":"106.0",
    "gn:feature_class":"P",
    "gn:feature_code":"PPL",
    "gn:name":"McBride",
    "gn:population":0,
    "gn:timezone":"America/Chicago",
    "iso:country":"US",
    "wof:name":"McBride",
    "wof:placetype":"locality"
},
  "geometry": {"coordinates":[-90.78232,31.76572],"type":"Point"}
}