{
  "type": "Feature",
  "properties": {
    "gn:admin1_code":"TN",
    "gn:admin2_code":"13.0",
    "gn:asciiname":"Westbourne",
    "gn:country_code":"US",
    "gn:dem":436,
    "gn:elevation":"421.0",
    "gn:feature_class":"P",
    "gn:feature_code":"PPL",
    "gn:name":"Westbourne",
    "gn:population":0,
    "gn:timezone":"America/New_York",
    "iso:country":"US",
    "wof:name":"Westbourne",
    "wof:placetype":"locality"
},
  "geometry": {"coordinates":[-84.02937,36.49369],"type":"Point"}
}