{
  "type": "Feature",
  "properties": {
    "gn:admin1_code":"WI",
    "gn:admin2_code":"111.0",
    "gn:admin3_code":"76050.0",
    "gn:asciiname":"Oak Ridge Estates",
    "gn:country_code":"US",
    "gn:dem":219,
    "gn:elevation":"219.0",
    "gn:feature_class":"P",
    "gn:feature_code":"PPL",
    "gn:name":"Oak Ridge Estates",
    "gn:population":0,
    "gn:timezone":"America/Chicago",
    "iso:country":"US",
    "wof:name":"Oak Ridge Estates",
    "wof:placetype":"locality"
},
  "geometry": {"coordinates":[-90.08194,43.17028],"type":"Point"}
}