{
  "type": "Feature",
  "properties": {
    "gn:admin1_code":"IL",
    "gn:admin2_code":"93.0",
    "gn:admin3_code":"56900.0",
    "gn:asciiname":"Springbrook At Farmington Lakes",
    "gn:country_code":"US",
    "gn:dem":202,
    "gn:elevation":"202.0",
    "gn:feature_class":"P",
    "gn:feature_code":"PPL",
    "gn:name":"Springbrook At Farmington Lakes",
    "gn:population":0,
    "gn:timezone":"America/Chicago",
    "iso:country":"US",
    "wof:name":"Springbrook At Farmington Lakes",
    "wof:placetype":"locality"
},
  "geometry": {"coordinates":[-88.30747,41.7097],"type":"Point"}
}