{
  "type": "Feature",
  "properties": {
    "gn:admin1_code":"PA",
    "gn:admin2_code":"123.0",
    "gn:admin3_code":"69992.0",
    "gn:asciiname":"Donaldson",
    "gn:country_code":"US",
    "gn:dem":414,
    "gn:elevation":"406.0",
    "gn:feature_class":"P",
    "gn:feature_code":"PPL",
    "gn:name":"Donaldson",
    "gn:population":0,
    "gn:timezone":"America/New_York",
    "iso:country":"US",
    "name:ces_x_preferred":[
        "Donaldson"
    ],
    "name:eng_x_preferred":[
        "Donaldson"
    ],
    "name:und_x_variant":[
        "Donaldsons"
    ],
    "wof:name":"Donaldson",
    "wof:placetype":"locality"
},
  "geometry": {"coordinates":[-79.01309000000001,41.65895],"type":"Point"}
}