{
  "type": "Feature",
  "properties": {
    "iso:country":"US",
    "name:eng_x_preferred":[
        "Lake Eldora"
    ],
    "qs:gn_adm0_cc":"US",
    "qs:gn_local":5432410,
    "qs:gn_nam_loc":"Nederland, Boulder, Colorado, US",
    "qs:gn_namadm1":"CO",
    "qs:local_max":243,
    "qs:local_sum":559,
    "qs:localhoods":5,
    "qs:name":"Lake Eldora",
    "qs:name_adm0":"United States",
    "qs:name_adm1":"Colorado",
    "qs:name_adm2":"Boulder",
    "qs:name_local":"Nederland",
    "qs:photo_max":20,
    "qs:photo_sum":116,
    "qs:placetype":"Suburb",
    "qs:quad_count":19,
    "qs:woe_adm0":23424977,
    "qs:woe_adm1":2347564,
    "qs:woe_adm2":12587734,
    "qs:woe_lau":0,
    "qs:woe_local":2457505,
    "qs:woe_ver":"7.10.0",
    "wof:lang":[
        "eng"
    ],
    "wof:name":"Lake Eldora",
    "wof:placetype":"neighbourhood",
    "wof:population":46,
    "zs:blockids":[
        80470138002033,
        80470138002019,
        80470138002196,
        80470138002200,
        80470138002046,
        80470138002197,
        80470138002049,
        80470138002042,
        80470138002065,
        80470138002047,
        80470138002202,
        80470138002225,
        80470138002067,
        80470138002211,
        80470138002191,
        80470138002021,
        80470138002030,
        80470138002023,
        80470138002041,
        80470138002194,
        80470138002031,
        80470138002186,
        80470138002181,
        80470138002184,
        80470138002199,
        80470138002205,
        80470138002189,
        80470138002227,
        80470138002018,
        80470138002055,
        80470138002216,
        80470138002187,
        80470138002054,
        80470138002027,
        80470138002264,
        80470138002044,
        80470138002035,
        80470138002073,
        80470138002022,
        80470138002029,
        80470138002051,
        80470138002190,
        80470138002052,
        80470138002277,
        80470138002020,
        80470138002188,
        80470138002053,
        80470138002034,
        80470138002228,
        80470138002043,
        80470138002040,
        80470138002193,
        80470138002075,
        80470138002185,
        80470138002210,
        80470138002024,
        80470138002179,
        80470138002025,
        80470138002045,
        80470138002048,
        80470138002280,
        80470138002026,
        80470138002050,
        80470138002178,
        80470138002207,
        80470138002180,
        80470138002074,
        80470138002273,
        80470138002017,
        80470138002192,
        80470138002195,
        80470138002206,
        80470138002203,
        80470138002032,
        80470138002204
    ],
    "zs:housing10":110,
    "zs:pop10":46
},
  "geometry": {"coordinates":[-105.584279,39.934774],"type":"Point"}
}