{
  "type": "Feature",
  "properties": {
    "gn:admin1_code":"ND",
    "gn:admin2_code":"77.0",
    "gn:admin3_code":"25340.0",
    "gn:asciiname":"Blackmer",
    "gn:country_code":"US",
    "gn:dem":294,
    "gn:elevation":"297.0",
    "gn:feature_class":"P",
    "gn:feature_code":"PPL",
    "gn:name":"Blackmer",
    "gn:population":0,
    "gn:timezone":"America/Chicago",
    "iso:country":"US",
    "name:eng_x_preferred":[
        "Blackmer"
    ],
    "name:und_x_variant":[
        "Blockmer Elevator"
    ],
    "wof:name":"Blackmer",
    "wof:placetype":"locality"
},
  "geometry": {"coordinates":[-96.60063,45.97885],"type":"Point"}
}