{
  "type": "Feature",
  "properties": {
    "gn:admin1_code":"VA",
    "gn:admin2_code":"57",
    "gn:asciiname":"Farmers Fork",
    "gn:country_code":"US",
    "gn:dem":59,
    "gn:elevation":"59.0",
    "gn:feature_class":"P",
    "gn:feature_code":"PPL",
    "gn:name":"Farmers Fork",
    "gn:population":0,
    "gn:timezone":"America/New_York",
    "iso:country":"US",
    "name:eng_x_preferred":[
        "Farmers Fork"
    ],
    "name:und_x_variant":[
        "Pedro",
        "Pedros"
    ],
    "wof:name":"Farmers Fork",
    "wof:placetype":"locality"
},
  "geometry": {"coordinates":[-77.10609000000002,38.06124000000001],"type":"Point"}
}