{
  "type": "Feature",
  "properties": {
    "gn:elevation":18,
    "iso:country":"US",
    "name:eng_x_preferred":[
        "Town Hall Corner"
    ],
    "name:eng_x_variant":[
        "Town Hall Cor"
    ],
    "qs:gn_adm0_cc":"US",
    "qs:gn_fcode":"PPL",
    "qs:gn_local":5087122,
    "qs:gn_nam_loc":"Hampton Falls, Rockingham, New Hampshire, US",
    "qs:gn_namadm1":"NH",
    "qs:gn_name":"Town Hall Corner",
    "qs:local_max":157,
    "qs:local_sum":259,
    "qs:localhoods":3,
    "qs:name":"Town Hall Corner",
    "qs:name_adm0":"United States",
    "qs:name_adm1":"New Hampshire",
    "qs:name_adm2":"Rockingham",
    "qs:name_local":"Hampton Falls",
    "qs:photo_max":27,
    "qs:photo_sum":62,
    "qs:placetype":"Suburb",
    "qs:quad_count":12,
    "qs:woe_adm0":23424977,
    "qs:woe_adm1":2347588,
    "qs:woe_adm2":12589255,
    "qs:woe_lau":0,
    "qs:woe_local":2416865,
    "qs:woe_ver":"7.10.0",
    "wof:lang":[
        "eng"
    ],
    "wof:name":"Town Hall Corner",
    "wof:placetype":"neighbourhood",
    "wof:population":668,
    "zs:blockids":[
        330150640001043,
        330150640001047,
        330150640001040,
        330150640001021,
        330150640001031,
        330150640001048,
        330150640001035,
        330150640001024,
        330150640001034,
        330150640001046,
        330150640001028,
        330150640001032,
        330150640001039,
        330150640001033,
        330150640001030,
        330150640001037,
        330150640001041,
        330150640001025,
        330150640001036,
        330150640001038,
        330150640001026,
        330150640001049
    ],
    "zs:housing10":275,
    "zs:pop10":668
},
  "geometry": {"coordinates":[-70.86571600000001,42.92341],"type":"Point"}
}