{
  "type": "Feature",
  "properties": {
    "gn:country":"US",
    "gn:fcode":"PPL",
    "gn:population":0,
    "iso:country":"US",
    "name:eng_x_preferred":[
        "Greenwood"
    ],
    "name:fas_x_preferred":[
        "\u06af\u0631\u06cc\u0646\u0648\u0648\u062f"
    ],
    "name:fra_x_preferred":[
        "Greenwood"
    ],
    "name:spa_x_preferred":[
        "Greenwood"
    ],
    "name:tur_x_preferred":[
        "Greenwood"
    ],
    "name:und_x_variant":[
        "Louisville"
    ],
    "name:zho_x_preferred":[
        "\u683c\u6797\u4f0d\u5fb7"
    ],
    "qs_pg:aaroncc":"US",
    "qs_pg:gn_country":"US",
    "qs_pg:gn_fcode":"PPL",
    "qs_pg:gn_pop":0,
    "qs_pg:name":"Greenwood",
    "qs_pg:name_adm0":"United States",
    "qs_pg:name_adm1":"California",
    "qs_pg:photos":54,
    "qs_pg:photos_1k":11,
    "qs_pg:photos_9k":1,
    "qs_pg:photos_9r":3,
    "qs_pg:photos_all":99,
    "qs_pg:photos_sr":2,
    "qs_pg:pop_sr":0,
    "qs_pg:qs_pg_placetype":"locality",
    "qs_pg:qs_pg_placetype_gp":"Town",
    "qs_pg:woe_adm0":23424977,
    "woe:adm0_id":23424977,
    "woe:name_adm0":"United States",
    "woe:name_adm1":"California",
    "woe:placetype":"Town",
    "wof:name":"Greenwood",
    "wof:placetype":"locality"
},
  "geometry": {"coordinates":[-120.91271999999999,38.89657],"type":"Point"}
}