{
  "type": "Feature",
  "properties": {
    "gn:admin1_code":"NM",
    "gn:admin2_code":"35",
    "gn:asciiname":"Blazers Mill",
    "gn:country_code":"US",
    "gn:dem":1967,
    "gn:elevation":"1965.0",
    "gn:feature_class":"P",
    "gn:feature_code":"PPL",
    "gn:name":"Blazers Mill",
    "gn:population":0,
    "gn:timezone":"America/Denver",
    "iso:country":"US",
    "wof:name":"Blazers Mill",
    "wof:placetype":"locality"
},
  "geometry": {"coordinates":[-105.78749000000001,33.15647],"type":"Point"}
}