{
  "type": "Feature",
  "properties": {
    "iso:country":"US",
    "name:eng_x_preferred":[
        "Hidden Ridge"
    ],
    "wof:name":"Hidden Ridge",
    "wof:placetype":"neighbourhood",
    "wof:population":516,
    "zs:area_m":832502.043836,
    "zs:blockids":[
        10730129111009,
        10730129113024,
        10730129111012,
        10730129111008,
        10730129111011
    ],
    "zs:housing10":173,
    "zs:label":"Hidden Ridge",
    "zs:pop10":516
},
  "geometry": {"coordinates":[-86.760835,33.434022],"type":"Point"}
}