{
  "type": "Feature",
  "properties": {
    "gn:admin1_code":"WI",
    "gn:admin2_code":"61.0",
    "gn:admin3_code":"44425.0",
    "gn:asciiname":"Euren",
    "gn:country_code":"US",
    "gn:dem":230,
    "gn:elevation":"229.0",
    "gn:feature_class":"P",
    "gn:feature_code":"PPL",
    "gn:name":"Euren",
    "gn:population":0,
    "gn:timezone":"America/Chicago",
    "iso:country":"US",
    "wof:name":"Euren",
    "wof:placetype":"locality"
},
  "geometry": {"coordinates":[-87.60231,44.61833],"type":"Point"}
}