{
  "type": "Feature",
  "properties": {
    "gn:admin1_code":"MD",
    "gn:admin2_code":"29.0",
    "gn:asciiname":"Harmony Corner",
    "gn:country_code":"US",
    "gn:dem":25,
    "gn:elevation":"23.0",
    "gn:feature_class":"P",
    "gn:feature_code":"PPL",
    "gn:name":"Harmony Corner",
    "gn:population":0,
    "gn:timezone":"America/New_York",
    "iso:country":"US",
    "name:eng_x_preferred":[
        "Harmony Corner"
    ],
    "name:und_x_variant":[
        "Harmony"
    ],
    "wof:name":"Harmony Corner",
    "wof:placetype":"locality"
},
  "geometry": {"coordinates":[-75.97689,39.32011],"type":"Point"}
}