{
  "type": "Feature",
  "properties": {
    "iso:country":"US",
    "name:ceb_x_preferred":[
        "North Hills"
    ],
    "name:deu_x_preferred":[
        "North Hills"
    ],
    "name:ita_x_preferred":[
        "North Hills"
    ],
    "name:nld_x_preferred":[
        "North Hills"
    ],
    "name:pol_x_preferred":[
        "North Hills"
    ],
    "name:srp_x_preferred":[
        "\u041d\u043e\u0440\u0442 \u0425\u0438\u043b\u0441"
    ],
    "name:vol_x_preferred":[
        "North Hills"
    ],
    "qs_pg:aaroncc":"US",
    "qs_pg:name":"North Hills",
    "qs_pg:name_adm0":"United States",
    "qs_pg:name_adm1":"North Carolina",
    "qs_pg:photos":10,
    "qs_pg:photos_1k":2,
    "qs_pg:photos_9k":1,
    "qs_pg:photos_9r":1,
    "qs_pg:photos_all":10,
    "qs_pg:photos_sr":1,
    "qs_pg:pop_sr":0,
    "qs_pg:qs_pg_placetype":"neighbourhood",
    "qs_pg:qs_pg_placetype_gp":"Suburb",
    "qs_pg:woe_adm0":23424977,
    "woe:adm0_id":23424977,
    "woe:name_adm0":"United States",
    "woe:name_adm1":"North Carolina",
    "woe:placetype":"Suburb",
    "wof:name":"North Hills",
    "wof:placetype":"neighbourhood"
},
  "geometry": {"coordinates":[-79.453811,35.732718],"type":"Point"}
}