{
  "type": "Feature",
  "properties": {
    "gn:country":"US",
    "gn:fcode":"PPL",
    "gn:population":0,
    "iso:country":"US",
    "name:eng_x_preferred":[
        "Dry Top"
    ],
    "qs_pg:aaroncc":"US",
    "qs_pg:gn_country":"US",
    "qs_pg:gn_fcode":"PPL",
    "qs_pg:gn_pop":0,
    "qs_pg:name":"Dry Top",
    "qs_pg:name_adm0":"United States",
    "qs_pg:name_adm1":"Pennsylvania",
    "qs_pg:photos":2,
    "qs_pg:photos_1k":1,
    "qs_pg:photos_9k":1,
    "qs_pg:photos_9r":1,
    "qs_pg:photos_all":2,
    "qs_pg:photos_sr":1,
    "qs_pg:pop_sr":0,
    "qs_pg:qs_pg_placetype":"neighbourhood",
    "qs_pg:qs_pg_placetype_gp":"Suburb",
    "qs_pg:woe_adm0":23424977,
    "wof:name":"Dry Top",
    "wof:placetype":"neighbourhood",
    "wof:population":956,
    "zs:area_m":15273373.440826,
    "zs:blockids":[
        420270106001058,
        420270106003013,
        420270106002055,
        420270106002049,
        420270106003074,
        420270106001060,
        420270106003063,
        420270106001067,
        420270106001065,
        420270106003012,
        420270106002052,
        420270106003073,
        420270106003011,
        420270106003024,
        420270106003065,
        420270106003069,
        420270106001066,
        420270106003070,
        420270106003071,
        420270106001059,
        420270106001063,
        420270106003062,
        420270106003064,
        420270106003014,
        420270106001056,
        420270106003072,
        420270106002053,
        420270106001064,
        420270106003061,
        420270106003060
    ],
    "zs:housing10":392,
    "zs:label":"Dry Top",
    "zs:pop10":956
},
  "geometry": {"coordinates":[-77.803867,40.959728],"type":"Point"}
}