{
  "type": "Feature",
  "properties": {
    "gn:admin1_code":"PA",
    "gn:admin2_code":"55.0",
    "gn:admin3_code":"71912.0",
    "gn:asciiname":"Pinola",
    "gn:country_code":"US",
    "gn:dem":185,
    "gn:elevation":"182.0",
    "gn:feature_class":"P",
    "gn:feature_code":"PPL",
    "gn:name":"Pinola",
    "gn:population":0,
    "gn:timezone":"America/New_York",
    "iso:country":"US",
    "name:deu_x_preferred":[
        "Pinola"
    ],
    "wof:name":"Pinola",
    "wof:placetype":"locality"
},
  "geometry": {"coordinates":[-77.59166,40.03759],"type":"Point"}
}