{
  "type": "Feature",
  "properties": {
    "gn:country":"US",
    "gn:fcode":"PPL",
    "gn:population":0,
    "iso:country":"US",
    "name:che_x_preferred":[
        "\u041f\u0430\u043b\u0442\u043d\u0438"
    ],
    "name:deu_x_preferred":[
        "Pulteney"
    ],
    "name:eng_x_preferred":[
        "Pulteney"
    ],
    "name:eus_x_preferred":[
        "Pulteney"
    ],
    "name:fra_x_preferred":[
        "Pulteney"
    ],
    "name:hat_x_preferred":[
        "Pulteney"
    ],
    "name:hun_x_preferred":[
        "Pulteney"
    ],
    "name:pol_x_preferred":[
        "Pulteney"
    ],
    "name:spa_x_preferred":[
        "Pulteney"
    ],
    "name:tat_x_preferred":[
        "\u041f\u0430\u043b\u0442\u043d\u0438"
    ],
    "name:tur_x_preferred":[
        "Pulteney"
    ],
    "name:ukr_x_preferred":[
        "\u041f\u0430\u043b\u0442\u043d\u0456"
    ],
    "name:und_x_variant":[
        "Harmonyville"
    ],
    "name:uzb_x_preferred":[
        "Pulteney"
    ],
    "qs_pg:aaroncc":"US",
    "qs_pg:gn_country":"US",
    "qs_pg:gn_fcode":"PPL",
    "qs_pg:gn_pop":0,
    "qs_pg:name":"Pulteney",
    "qs_pg:name_adm0":"United States",
    "qs_pg:name_adm1":"New York",
    "qs_pg:photos":230,
    "qs_pg:photos_1k":47,
    "qs_pg:photos_9k":2,
    "qs_pg:photos_9r":5,
    "qs_pg:photos_all":551,
    "qs_pg:photos_sr":4,
    "qs_pg:pop_sr":0,
    "qs_pg:qs_pg_placetype":"locality",
    "qs_pg:qs_pg_placetype_gp":"Town",
    "qs_pg:woe_adm0":23424977,
    "woe:adm0_id":23424977,
    "woe:name_adm0":"United States",
    "woe:name_adm1":"New York",
    "woe:placetype":"Town",
    "wof:name":"Pulteney",
    "wof:placetype":"locality"
},
  "geometry": {"coordinates":[-77.16719999999999,42.52507],"type":"Point"}
}