{
  "type": "Feature",
  "properties": {
    "gn:admin1_code":"KY",
    "gn:admin2_code":"193",
    "gn:asciiname":"Dow",
    "gn:country_code":"US",
    "gn:dem":308,
    "gn:elevation":"312.0",
    "gn:feature_class":"P",
    "gn:feature_code":"PPL",
    "gn:name":"Dow",
    "gn:population":0,
    "gn:timezone":"America/New_York",
    "iso:country":"US",
    "wof:name":"Dow",
    "wof:placetype":"locality"
},
  "geometry": {"coordinates":[-83.16295,37.15704],"type":"Point"}
}