{
  "type": "Feature",
  "properties": {
    "gn:admin1_code":"TX",
    "gn:admin2_code":"309.0",
    "gn:asciiname":"Asa",
    "gn:country_code":"US",
    "gn:dem":120,
    "gn:elevation":"119.0",
    "gn:feature_class":"P",
    "gn:feature_code":"PPL",
    "gn:name":"Asa",
    "gn:population":0,
    "gn:timezone":"America/Chicago",
    "iso:country":"US",
    "name:cat_x_preferred":[
        "Asa"
    ],
    "name:ceb_x_preferred":[
        "Asa"
    ],
    "name:fin_x_preferred":[
        "Asa"
    ],
    "name:heb_x_preferred":[
        "\u05d0\u05e1\u05d0"
    ],
    "name:jpn_x_preferred":[
        "\u30a2\u30b5"
    ],
    "name:lmo_x_preferred":[
        "As\u00e0"
    ],
    "name:nld_x_preferred":[
        "Asa"
    ],
    "name:pol_x_preferred":[
        "Asa"
    ],
    "name:por_x_preferred":[
        "Asa"
    ],
    "name:spa_x_preferred":[
        "Asa"
    ],
    "name:swe_x_preferred":[
        "Asa"
    ],
    "wof:name":"Asa",
    "wof:placetype":"locality"
},
  "geometry": {"coordinates":[-97.05416,31.41434000000001],"type":"Point"}
}