{
  "type": "Feature",
  "properties": {
    "gn:admin1_code":"MI",
    "gn:admin2_code":"123.0",
    "gn:admin3_code":"80680.0",
    "gn:asciiname":"Walgamor Corners",
    "gn:country_code":"US",
    "gn:dem":248,
    "gn:elevation":"241.0",
    "gn:feature_class":"P",
    "gn:feature_code":"PPL",
    "gn:name":"Walgamor Corners",
    "gn:population":0,
    "gn:timezone":"America/Detroit",
    "iso:country":"US",
    "name:eng_x_preferred":[
        "Walgamor Corners"
    ],
    "name:und_x_variant":[
        "Walgamott Corners"
    ],
    "wof:name":"Walgamor Corners",
    "wof:placetype":"locality"
},
  "geometry": {"coordinates":[-85.94923,43.74196],"type":"Point"}
}