{
  "type": "Feature",
  "properties": {
    "gn:admin1_code":"MD",
    "gn:admin2_code":"43.0",
    "gn:asciiname":"Jefferson Heights",
    "gn:country_code":"US",
    "gn:dem":169,
    "gn:elevation":"170.0",
    "gn:feature_class":"P",
    "gn:feature_code":"PPL",
    "gn:name":"Jefferson Heights",
    "gn:population":0,
    "gn:timezone":"America/New_York",
    "iso:country":"US",
    "wof:name":"Jefferson Heights",
    "wof:placetype":"locality"
},
  "geometry": {"coordinates":[-77.67694,39.64399],"type":"Point"}
}