{
  "type": "Feature",
  "properties": {
    "gn:admin1_code":"IL",
    "gn:admin2_code":"23.0",
    "gn:admin3_code":"18680.0",
    "gn:asciiname":"Snyder",
    "gn:country_code":"US",
    "gn:dem":164,
    "gn:elevation":"161.0",
    "gn:feature_class":"P",
    "gn:feature_code":"PPL",
    "gn:name":"Snyder",
    "gn:population":0,
    "gn:timezone":"America/Chicago",
    "iso:country":"US",
    "wof:name":"Snyder",
    "wof:placetype":"locality"
},
  "geometry": {"coordinates":[-87.66753,39.28254],"type":"Point"}
}