{
  "type": "Feature",
  "properties": {
    "iso:country":"US",
    "name:eng_x_preferred":[
        "Pinnacle"
    ],
    "qs:gn_adm0_cc":"US",
    "qs:gn_local":5786882,
    "qs:gn_nam_loc":"Bellevue, King, Washington, US",
    "qs:gn_namadm1":"WA",
    "qs:local_max":5360,
    "qs:local_sum":48946,
    "qs:localhoods":55,
    "qs:name":"Pinnacle",
    "qs:name_adm0":"United States",
    "qs:name_adm1":"Washington",
    "qs:name_adm2":"King",
    "qs:name_local":"Bellevue",
    "qs:photo_max":27,
    "qs:photo_sum":198,
    "qs:placetype":"Suburb",
    "qs:quad_count":27,
    "qs:woe_adm0":23424977,
    "qs:woe_adm1":2347606,
    "qs:woe_adm2":12590456,
    "qs:woe_lau":0,
    "qs:woe_local":2362031,
    "qs:woe_ver":"7.10.0",
    "wof:lang":[
        "eng"
    ],
    "wof:name":"The Pinnacle",
    "wof:placetype":"neighbourhood",
    "wof:population":2324,
    "zs:blockids":[
        530330250061019,
        530330250061001,
        530330250063020,
        530330250063014,
        530330250063027,
        530330250063012,
        530330250061013,
        530330250035007,
        530330250034006,
        530330250061021,
        530330250061017,
        530330250035009,
        530330250061012,
        530330250063016,
        530330250061018,
        530330250035008,
        530330250061000,
        530330250061002,
        530330250061005,
        530330250061007,
        530330250061006,
        530330250061016,
        530330250061011,
        530330250034007,
        530330250063026,
        530330250063018,
        530330250061015,
        530330250063017,
        530330250061004,
        530330250063015,
        530330250034011,
        530330250061010,
        530330250061003,
        530330250061009,
        530330250063013,
        530330250061014,
        530330250061008,
        530330250034008,
        530330250061022,
        530330250063019
    ],
    "zs:housing10":869,
    "zs:pop10":2324
},
  "geometry": {"coordinates":[-122.113225,47.542575],"type":"Point"}
}