{
  "type": "Feature",
  "properties": {
    "gn:admin1_code":"TX",
    "gn:admin2_code":"5",
    "gn:asciiname":"Dunagan",
    "gn:country_code":"US",
    "gn:dem":97,
    "gn:elevation":"93.0",
    "gn:feature_class":"P",
    "gn:feature_code":"PPL",
    "gn:name":"Dunagan",
    "gn:population":0,
    "gn:timezone":"America/Chicago",
    "iso:country":"US",
    "wof:name":"Dunagan",
    "wof:placetype":"locality"
},
  "geometry": {"coordinates":[-94.61521,31.34657],"type":"Point"}
}