{
  "type": "Feature",
  "properties": {
    "iso:country":"US",
    "name:eng_x_preferred":[
        "Knoll Crest"
    ],
    "wof:name":"Knoll Crest",
    "wof:placetype":"neighbourhood",
    "wof:population":1983,
    "zs:area_m":1480065.324037,
    "zs:blockids":[
        171430029002020,
        171430023001014,
        171430028002022,
        171430029002010,
        171430023001020,
        171430023002007,
        171430023002004,
        171430023001003,
        171430028002023,
        171430023001015,
        171430029002019,
        171430023002005,
        171430023001008,
        171430023001013,
        171430023001010,
        171430023001004,
        171430029003022,
        171430029002013,
        171430023002008,
        171430029002012,
        171430023001022,
        171430029002021,
        171430023002000,
        171430023001018,
        171430023001006,
        171430023002001,
        171430029002004,
        171430023001016,
        171430023001021,
        171430023001007,
        171430023001017,
        171430023001011,
        171430023002006,
        171430023001005,
        171430029002018,
        171430023002002,
        171430023001012,
        171430023002003,
        171430029002011
    ],
    "zs:housing10":1081,
    "zs:label":"Knoll Crest",
    "zs:pop10":1983
},
  "geometry": {"coordinates":[-89.606746,40.739447],"type":"Point"}
}