{
  "type": "Feature",
  "properties": {
    "gn:admin1_code":"GA",
    "gn:admin2_code":"77",
    "gn:asciiname":"Pine Hills",
    "gn:country_code":"US",
    "gn:dem":279,
    "gn:elevation":"275.0",
    "gn:feature_class":"P",
    "gn:feature_code":"PPL",
    "gn:name":"Pine Hills",
    "gn:population":0,
    "gn:timezone":"America/New_York",
    "iso:country":"US",
    "name:ceb_x_preferred":[
        "Pine Hills"
    ],
    "name:deu_x_preferred":[
        "Pine Hills"
    ],
    "name:ita_x_preferred":[
        "Pine Hills"
    ],
    "name:nld_x_preferred":[
        "Pine Hills"
    ],
    "name:pol_x_preferred":[
        "Pine Hills"
    ],
    "name:srp_x_preferred":[
        "\u041f\u0430\u0458\u043d \u0425\u0438\u043b\u0441"
    ],
    "name:swe_x_preferred":[
        "Pine Hills"
    ],
    "name:vol_x_preferred":[
        "Pine Hills"
    ],
    "wof:name":"Pine Hills",
    "wof:placetype":"locality"
},
  "geometry": {"coordinates":[-84.83466,33.36095],"type":"Point"}
}