{
  "type": "Feature",
  "properties": {
    "gn:country":"US",
    "gn:fcode":"PPLX",
    "gn:population":0,
    "iso:country":"US",
    "name:eng_x_preferred":[
        "Beech Park Acres"
    ],
    "name:eng_x_variant":[
        "Beech Fork Lake"
    ],
    "name:fra_x_preferred":[
        "Beech Fork Lake"
    ],
    "qs_pg:aaroncc":"US",
    "qs_pg:gn_country":"US",
    "qs_pg:gn_fcode":"PPLX",
    "qs_pg:gn_pop":0,
    "qs_pg:name":"Beech Park Acres",
    "qs_pg:name_adm0":"United States",
    "qs_pg:name_adm1":"West Virginia",
    "qs_pg:photos":1352,
    "qs_pg:photos_1k":274,
    "qs_pg:photos_9k":6,
    "qs_pg:photos_9r":7,
    "qs_pg:photos_all":1352,
    "qs_pg:photos_sr":12,
    "qs_pg:pop_sr":0,
    "qs_pg:qs_pg_placetype":"neighbourhood",
    "qs_pg:qs_pg_placetype_gp":"Suburb",
    "qs_pg:woe_adm0":23424977,
    "woe:adm0_id":23424977,
    "woe:name_adm0":"United States",
    "woe:name_adm1":"West Virginia",
    "woe:placetype":"Suburb",
    "wof:name":"Beech Park Acres",
    "wof:placetype":"neighbourhood",
    "wof:population":2775
},
  "geometry": {"coordinates":[-81.80013,38.37315],"type":"Point"}
}