{
  "type": "Feature",
  "properties": {
    "gn:admin1_code":"FL",
    "gn:admin2_code":"57",
    "gn:asciiname":"Seabron",
    "gn:country_code":"US",
    "gn:dem":25,
    "gn:elevation":"18.0",
    "gn:feature_class":"P",
    "gn:feature_code":"PPL",
    "gn:name":"Seabron",
    "gn:population":0,
    "gn:timezone":"America/New_York",
    "iso:country":"US",
    "wof:name":"Seabron",
    "wof:placetype":"locality"
},
  "geometry": {"coordinates":[-82.4481,28.0078],"type":"Point"}
}