{
  "type": "Feature",
  "properties": {
    "gn:admin1_code":"CA",
    "gn:admin2_code":"71",
    "gn:asciiname":"High Country",
    "gn:country_code":"US",
    "gn:dem":1112,
    "gn:elevation":"1108.0",
    "gn:feature_class":"P",
    "gn:feature_code":"PPL",
    "gn:name":"High Country",
    "gn:population":0,
    "gn:timezone":"America/Los_Angeles",
    "iso:country":"US",
    "wof:name":"High Country",
    "wof:placetype":"locality"
},
  "geometry": {"coordinates":[-117.38144,34.405],"type":"Point"}
}