{
  "type": "Feature",
  "properties": {
    "iso:country":"US",
    "name:eng_x_preferred":[
        "Fairview Road"
    ],
    "wof:name":"Fairview Road",
    "wof:placetype":"neighbourhood",
    "wof:population":39,
    "zs:area_m":87715.300749,
    "zs:blockids":[
        371830534163005
    ],
    "zs:housing10":18,
    "zs:label":"Fairview Road",
    "zs:pop10":39
},
  "geometry": {"coordinates":[-78.857839,35.734221],"type":"Point"}
}