{
  "type": "Feature",
  "properties": {
    "gn:admin1_code":"GA",
    "gn:admin2_code":"1",
    "gn:asciiname":"Shady Acres",
    "gn:country_code":"US",
    "gn:dem":69,
    "gn:elevation":"60.0",
    "gn:feature_class":"P",
    "gn:feature_code":"PPL",
    "gn:name":"Shady Acres",
    "gn:population":0,
    "gn:timezone":"America/New_York",
    "iso:country":"US",
    "wof:name":"Shady Acres",
    "wof:placetype":"locality"
},
  "geometry": {"coordinates":[-82.36513000000002,31.75853],"type":"Point"}
}