{
  "type": "Feature",
  "properties": {
    "gn:elevation":183,
    "iso:country":"US",
    "name:eng_x_preferred":[
        "Rolling Acres"
    ],
    "qs:gn_adm0_cc":"US",
    "qs:gn_fcode":"PPLX",
    "qs:gn_local":4628735,
    "qs:gn_nam_loc":"hendersonville",
    "qs:gn_namadm1":"TN",
    "qs:gn_name":"Rolling Acres",
    "qs:local_max":573,
    "qs:local_sum":2800,
    "qs:localhoods":15,
    "qs:name":"Rolling Acres",
    "qs:name_adm0":"United States",
    "qs:name_adm1":"Tennessee",
    "qs:name_adm2":"Sumner",
    "qs:name_local":"Hendersonville",
    "qs:photo_max":4,
    "qs:photo_sum":7,
    "qs:placetype":"Suburb",
    "qs:quad_count":2,
    "qs:woe_adm0":23424977,
    "qs:woe_adm1":2347601,
    "qs:woe_adm2":12589994,
    "qs:woe_lau":0,
    "qs:woe_local":2419982,
    "qs:woe_ver":"7.10.0",
    "wof:name":"Rolling Acres",
    "wof:placetype":"neighbourhood",
    "wof:population":1820,
    "zs:blockids":[
        471650211052020,
        471650211053005,
        471650211053006,
        471650211052014,
        471650211052015,
        471650211053001,
        471650211053003,
        471650211053004,
        471650211053007,
        471650211052021,
        471650211053000
    ],
    "zs:housing10":727,
    "zs:pop10":1820
},
  "geometry": {"coordinates":[-86.62994399999999,36.31544],"type":"Point"}
}