{
  "type": "Feature",
  "properties": {
    "iso:country":"US",
    "name:eng_x_preferred":[
        "Circle Ville"
    ],
    "name:eng_x_variant":[
        "Circle Vl"
    ],
    "qs:gn_adm0_cc":"US",
    "qs:gn_fcode":"PPL",
    "qs:gn_local":5189467,
    "qs:gn_nam_loc":"Ferguson, Centre, Pennsylvania, US",
    "qs:gn_namadm1":"PA",
    "qs:gn_name":"Circle Ville",
    "qs:local_max":3630,
    "qs:local_sum":7016,
    "qs:localhoods":7,
    "qs:name":"Circle Ville",
    "qs:name_adm0":"United States",
    "qs:name_adm1":"Pennsylvania",
    "qs:name_adm2":"Centre",
    "qs:name_local":"Ferguson",
    "qs:photo_max":7,
    "qs:photo_sum":19,
    "qs:placetype":"Suburb",
    "qs:quad_count":8,
    "qs:woe_adm0":23424977,
    "qs:woe_adm1":2347597,
    "qs:woe_adm2":12589741,
    "qs:woe_lau":0,
    "qs:woe_local":28745481,
    "qs:woe_ver":"7.10.0",
    "wof:lang":[
        "eng"
    ],
    "wof:name":"Circle Ville",
    "wof:placetype":"neighbourhood",
    "wof:population":3232,
    "zs:blockids":[
        420270119022000,
        420270119022012,
        420270115023013,
        420270115022013,
        420270119022064,
        420270115023023,
        420270119022006,
        420270115022014,
        420270119022002,
        420270119022017,
        420270115023016,
        420270119022010,
        420270115023012,
        420270115022016,
        420270115022007,
        420270119022003,
        420270119022070,
        420270115023015,
        420270119022013,
        420270115022015,
        420270115022012,
        420270119022065,
        420270115022011,
        420270115023014,
        420270119022007,
        420270115022017,
        420270119022001,
        420270119022066,
        420270119022005,
        420270119022060,
        420270119022014,
        420270119022059,
        420270119022015,
        420270115023017,
        420270119022008,
        420270115022008,
        420270119022004
    ],
    "zs:housing10":1362,
    "zs:pop10":3232
},
  "geometry": {"coordinates":[-77.90593200000001,40.788093],"type":"Point"}
}