{
  "type": "Feature",
  "properties": {
    "gn:admin1_code":"WV",
    "gn:admin2_code":"7",
    "gn:asciiname":"Holly",
    "gn:country_code":"US",
    "gn:dem":290,
    "gn:elevation":"284.0",
    "gn:feature_class":"P",
    "gn:feature_code":"PPL",
    "gn:name":"Holly",
    "gn:population":0,
    "gn:timezone":"America/New_York",
    "iso:country":"US",
    "name:afr_x_preferred":[
        "Hulsboom"
    ],
    "name:ara_x_preferred":[
        "\u0628\u0647\u0634\u064a\u0629"
    ],
    "name:aze_x_preferred":[
        "Pirkal"
    ],
    "name:bul_x_preferred":[
        "\u0414\u0436\u0435\u043b"
    ],
    "name:cat_x_preferred":[
        "Ilex"
    ],
    "name:ceb_x_preferred":[
        "Ilex"
    ],
    "name:ces_x_preferred":[
        "Cesm\u00edna"
    ],
    "name:dan_x_preferred":[
        "Kristtorn"
    ],
    "name:deu_x_preferred":[
        "Stechpalmen"
    ],
    "name:ell_x_preferred":[
        "\u038a\u03bb\u03b7\u03be"
    ],
    "name:eng_x_preferred":[
        "Holly"
    ],
    "name:epo_x_preferred":[
        "Ilekso"
    ],
    "name:est_x_preferred":[
        "Iileks"
    ],
    "name:eus_x_preferred":[
        "Ilex"
    ],
    "name:fas_x_preferred":[
        "\u062e\u0627\u0633"
    ],
    "name:fra_x_preferred":[
        "Ilex"
    ],
    "name:gla_x_preferred":[
        "Cuileann"
    ],
    "name:gle_x_preferred":[
        "Cuileann"
    ],
    "name:glg_x_preferred":[
        "Ilex"
    ],
    "name:heb_x_preferred":[
        "\u05e6\u05d9\u05e0\u05d9\u05ea"
    ],
    "name:hin_x_preferred":[
        "\u0936\u0942\u0932\u092a\u0930\u094d\u0923\u0940"
    ],
    "name:hrv_x_preferred":[
        "Bo\u017eikovina"
    ],
    "name:hun_x_preferred":[
        "Magyal"
    ],
    "name:hye_x_preferred":[
        "\u054d\u0572\u0578\u0581\u056b"
    ],
    "name:ind_x_preferred":[
        "Aquifoliaceae"
    ],
    "name:ita_x_preferred":[
        "Ilex"
    ],
    "name:kat_x_preferred":[
        "\u10d1\u10d0\u10eb\u10d2\u10d8"
    ],
    "name:kor_x_preferred":[
        "\uac10\ud0d5\ub098\ubb34\uc18d"
    ],
    "name:kur_x_preferred":[
        "Hol"
    ],
    "name:lat_x_preferred":[
        "Ilex"
    ],
    "name:lit_x_preferred":[
        "Bugienis"
    ],
    "name:mal_x_preferred":[
        "\u0d05\u0d15\u0d4d\u0d35\u0d3f\u0d2b\u0d4b\u0d33\u0d3f\u0d2f\u0d47\u0d38\u0d3f"
    ],
    "name:mya_x_preferred":[
        "\u101f\u1031\u102c\u103a\u101c\u102e\u1015\u1004\u103a"
    ],
    "name:nav_x_preferred":[
        "Didz\u00e9\u0142ch\u00ed\u00ed\u02bc"
    ],
    "name:nld_x_preferred":[
        "Ilex"
    ],
    "name:nor_x_preferred":[
        "Kristtornslekten"
    ],
    "name:oss_x_preferred":[
        "\u0426\u0445\u044a\u043e\u0440\u0438"
    ],
    "name:pol_x_preferred":[
        "Ostrokrzew"
    ],
    "name:por_x_preferred":[
        "Ilex"
    ],
    "name:que_x_preferred":[
        "Wayusa"
    ],
    "name:rus_x_preferred":[
        "\u041f\u0430\u0434\u0443\u0431"
    ],
    "name:spa_x_preferred":[
        "Ilex"
    ],
    "name:swe_x_preferred":[
        "J\u00e4rnekssl\u00e4ktet"
    ],
    "name:tgl_x_preferred":[
        "Asebo"
    ],
    "name:ukr_x_preferred":[
        "\u041f\u0430\u0434\u0443\u0431"
    ],
    "name:und_x_variant":[
        "Holly River",
        "Forks of Holly"
    ],
    "name:vie_x_preferred":[
        "Chi B\u00f9i"
    ],
    "name:war_x_preferred":[
        "Ilex"
    ],
    "wof:name":"Holly",
    "wof:placetype":"locality"
},
  "geometry": {"coordinates":[-80.54786999999997,38.67038],"type":"Point"}
}