{
  "type": "Feature",
  "properties": {
    "gn:admin1_code":"NY",
    "gn:admin2_code":"67.0",
    "gn:admin3_code":"24878.0",
    "gn:asciiname":"Apulia Station",
    "gn:country_code":"US",
    "gn:dem":382,
    "gn:elevation":"379.0",
    "gn:feature_class":"P",
    "gn:feature_code":"PPL",
    "gn:name":"Apulia Station",
    "gn:population":0,
    "gn:timezone":"America/New_York",
    "iso:country":"US",
    "wof:name":"Apulia Station",
    "wof:placetype":"locality"
},
  "geometry": {"coordinates":[-76.07241999999999,42.81868],"type":"Point"}
}