{
  "type": "Feature",
  "properties": {
    "gn:admin1_code":"TX",
    "gn:admin2_code":"217",
    "gn:asciiname":"Irene",
    "gn:country_code":"US",
    "gn:dem":162,
    "gn:elevation":"159.0",
    "gn:feature_class":"P",
    "gn:feature_code":"PPL",
    "gn:name":"Irene",
    "gn:population":0,
    "gn:timezone":"America/Chicago",
    "iso:country":"US",
    "wof:name":"Irene",
    "wof:placetype":"locality"
},
  "geometry": {"coordinates":[-96.87139000000001,31.9921],"type":"Point"}
}