{
  "type": "Feature",
  "properties": {
    "gn:admin1_code":"WA",
    "gn:admin2_code":"73.0",
    "gn:asciiname":"Bel Air Village Trailer Court",
    "gn:country_code":"US",
    "gn:dem":16,
    "gn:elevation":"17.0",
    "gn:feature_class":"P",
    "gn:feature_code":"PPL",
    "gn:name":"Bel Air Village Trailer Court",
    "gn:population":0,
    "gn:timezone":"America/Los_Angeles",
    "iso:country":"US",
    "wof:name":"Bel Air Village Trailer Court",
    "wof:placetype":"locality"
},
  "geometry": {"coordinates":[-122.73017,48.97826],"type":"Point"}
}