{
  "type": "Feature",
  "properties": {
    "gn:gn_country":"US",
    "gn:gn_fcode":"PPL",
    "gn:gn_pop":0,
    "iso:country":"US",
    "name:eng_x_preferred":[
        "El Morro"
    ],
    "name:fra_x_preferred":[
        "El Morro"
    ],
    "name:jpn_x_preferred":[
        "\u30a8\u30eb\u30fb\u30e2\u30ed"
    ],
    "qs_pg:aaroncc":"US",
    "qs_pg:gn_country":"US",
    "qs_pg:gn_fcode":"PPL",
    "qs_pg:gn_pop":0,
    "qs_pg:name":"El Morro",
    "qs_pg:name_adm0":"United States",
    "qs_pg:name_adm1":"New Mexico",
    "qs_pg:photos":851,
    "qs_pg:photos_1k":172,
    "qs_pg:photos_9k":4,
    "qs_pg:photos_9r":6,
    "qs_pg:photos_all":851,
    "qs_pg:photos_sr":10,
    "qs_pg:pop_sr":0,
    "qs_pg:qs_pg_placetype":"locality",
    "qs_pg:qs_pg_placetype_gp":"Town",
    "qs_pg:woe_adm0":23424977,
    "woe:adm0_id":23424977,
    "woe:name_adm0":"United States",
    "woe:name_adm1":"New Mexico",
    "woe:placetype":"Town",
    "wof:name":"El Morro",
    "wof:placetype":"locality"
},
  "geometry": {"coordinates":[-108.32035,35.04448],"type":"Point"}
}