{
  "type": "Feature",
  "properties": {
    "gn:admin1_code":"PA",
    "gn:admin2_code":"15.0",
    "gn:admin3_code":"15376.0",
    "gn:asciiname":"Sopertown",
    "gn:country_code":"US",
    "gn:dem":440,
    "gn:elevation":"440.0",
    "gn:feature_class":"P",
    "gn:feature_code":"PPL",
    "gn:name":"Sopertown",
    "gn:population":0,
    "gn:timezone":"America/New_York",
    "iso:country":"US",
    "name:eng_x_preferred":[
        "Sopertown"
    ],
    "name:und_x_variant":[
        "Soper Hollow"
    ],
    "wof:name":"Sopertown",
    "wof:placetype":"locality"
},
  "geometry": {"coordinates":[-76.90441,41.87563],"type":"Point"}
}