{
  "type": "Feature",
  "properties": {
    "iso:country":"US",
    "name:eng_x_preferred":[
        "Noble Nela"
    ],
    "qs:gn_adm0_cc":"US",
    "qs:gn_local":4833320,
    "qs:gn_nam_loc":"Cleveland Heights, Cuyahoga, Ohio, US",
    "qs:gn_namadm1":"OH",
    "qs:local_max":236,
    "qs:local_sum":541,
    "qs:localhoods":5,
    "qs:name":"Noble Nela",
    "qs:name_adm0":"United States",
    "qs:name_adm1":"Ohio",
    "qs:name_adm2":"Cuyahoga",
    "qs:name_local":"Cleveland Heights",
    "qs:photo_max":174,
    "qs:photo_sum":236,
    "qs:placetype":"Suburb",
    "qs:quad_count":10,
    "qs:woe_adm0":23424977,
    "qs:woe_adm1":2347594,
    "qs:woe_adm2":12589544,
    "qs:woe_lau":0,
    "qs:woe_local":2381503,
    "qs:woe_ver":"7.10.0",
    "wof:lang":[
        "eng"
    ],
    "wof:name":"Noble Nela",
    "wof:placetype":"neighbourhood",
    "wof:population":3626,
    "zs:blockids":[
        390351851012010,
        390351405002002,
        390351851012007,
        390351851012004,
        390351851011005,
        390351405002004,
        390351851011013,
        390351405001001,
        390351405001000,
        390351851012008,
        390351851012001,
        390351405002000,
        390351851012011,
        390351851012000,
        390351401001006,
        390351851012006,
        390351405002003,
        390351405002006,
        390351851012012,
        390351401001005,
        390351401001008,
        390351851012009,
        390351851012005,
        390351851012002,
        390351405002001,
        390351405002007,
        390351401001012,
        390351405001007,
        390351401001002,
        390351851011012,
        390351405002005,
        390351851012003,
        390351401001007,
        390351851012013,
        390351405001002,
        390351851011004,
        390351851011008
    ],
    "zs:housing10":1546,
    "zs:pop10":3626
},
  "geometry": {"coordinates":[-81.55814599999999,41.537922],"type":"Point"}
}