{
  "type": "Feature",
  "properties": {
    "gn:admin1_code":"PA",
    "gn:admin2_code":"55.0",
    "gn:admin3_code":"63200.0",
    "gn:asciiname":"Tomstown",
    "gn:country_code":"US",
    "gn:dem":232,
    "gn:elevation":"235.0",
    "gn:feature_class":"P",
    "gn:feature_code":"PPL",
    "gn:name":"Tomstown",
    "gn:population":0,
    "gn:timezone":"America/New_York",
    "iso:country":"US",
    "name:eng_x_preferred":[
        "Tomstown"
    ],
    "name:und_x_variant":[
        "Toms Town"
    ],
    "wof:name":"Tomstown",
    "wof:placetype":"locality"
},
  "geometry": {"coordinates":[-77.56166,39.79287],"type":"Point"}
}