{
  "type": "Feature",
  "properties": {
    "gn:country":"US",
    "gn:fcode":"PPL",
    "gn:population":0,
    "iso:country":"US",
    "name:ben_x_preferred":[
        "\u0993\u0995 \u09b0\u09bf\u099c"
    ],
    "name:cat_x_preferred":[
        "Oak Ridge"
    ],
    "name:ceb_x_preferred":[
        "Oak Ridge"
    ],
    "name:deu_x_preferred":[
        "Oak Ridge"
    ],
    "name:ell_x_preferred":[
        "\u038c\u03bf\u03c5\u03ba \u03a1\u03b9\u03c4\u03bd\u03c4\u03b6"
    ],
    "name:eus_x_preferred":[
        "Oak Ridge"
    ],
    "name:fra_x_preferred":[
        "Oak Ridge"
    ],
    "name:hin_x_preferred":[
        "\u0913\u0915 \u0930\u093f\u091c"
    ],
    "name:hun_x_preferred":[
        "Oak Ridge"
    ],
    "name:ita_x_preferred":[
        "Oak Ridge"
    ],
    "name:nld_x_preferred":[
        "Oak Ridge"
    ],
    "name:nor_x_preferred":[
        "Oak Ridge"
    ],
    "name:pol_x_preferred":[
        "Oak Ridge"
    ],
    "name:por_x_preferred":[
        "Oak Ridge"
    ],
    "name:rus_x_preferred":[
        "\u041e\u043a-\u0420\u0438\u0434\u0436"
    ],
    "name:spa_x_preferred":[
        "Oak Ridge"
    ],
    "name:srp_x_preferred":[
        "\u041e\u0443\u043a \u0420\u0438\u045f"
    ],
    "name:swe_x_preferred":[
        "Oak Ridge"
    ],
    "name:ukr_x_preferred":[
        "\u041e\u0443\u043a-\u0420\u0438\u0434\u0436"
    ],
    "name:urd_x_preferred":[
        "\u0627\u0648\u06a9 \u0631\u06cc\u062c"
    ],
    "name:vie_x_preferred":[
        "Oak Ridge"
    ],
    "name:vol_x_preferred":[
        "Oak Ridge"
    ],
    "qs_pg:aaroncc":"US",
    "qs_pg:gn_country":"US",
    "qs_pg:gn_fcode":"PPL",
    "qs_pg:gn_pop":0,
    "qs_pg:name":"Oak Ridge",
    "qs_pg:name_adm0":"United States",
    "qs_pg:name_adm1":"Alabama",
    "qs_pg:photos":8,
    "qs_pg:photos_1k":2,
    "qs_pg:photos_9k":1,
    "qs_pg:photos_9r":1,
    "qs_pg:photos_all":8,
    "qs_pg:photos_sr":1,
    "qs_pg:pop_sr":0,
    "qs_pg:qs_pg_placetype":"neighbourhood",
    "qs_pg:qs_pg_placetype_gp":"Suburb",
    "qs_pg:woe_adm0":23424977,
    "woe:adm0_id":23424977,
    "woe:name_adm0":"United States",
    "woe:name_adm1":"Alabama",
    "woe:placetype":"Suburb",
    "wof:name":"Oak Ridge",
    "wof:placetype":"neighbourhood"
},
  "geometry": {"coordinates":[-86.27942,33.60094],"type":"Point"}
}