{
  "type": "Feature",
  "properties": {
    "gn:admin1_code":"AL",
    "gn:admin2_code":"77.0",
    "gn:asciiname":"Wilson",
    "gn:country_code":"US",
    "gn:dem":218,
    "gn:elevation":"217.0",
    "gn:feature_class":"P",
    "gn:feature_code":"PPL",
    "gn:name":"Wilson",
    "gn:population":0,
    "gn:timezone":"America/Chicago",
    "iso:country":"US",
    "name:ara_x_preferred":[
        "\u0648\u064a\u0644\u0633\u0648\u0646"
    ],
    "name:bel_x_preferred":[
        "\u0412\u0456\u043b\u044c\u0441\u0430\u043d"
    ],
    "name:bul_x_preferred":[
        "\u0423\u0438\u043b\u0441\u044a\u043d"
    ],
    "name:cat_x_preferred":[
        "Wilson"
    ],
    "name:ceb_x_preferred":[
        "Wilson"
    ],
    "name:ces_x_preferred":[
        "Wilson"
    ],
    "name:deu_x_preferred":[
        "Wilson"
    ],
    "name:epo_x_preferred":[
        "Wilson"
    ],
    "name:fas_x_preferred":[
        "\u0648\u06cc\u0644\u0633\u0648\u0646"
    ],
    "name:fin_x_preferred":[
        "Wilson"
    ],
    "name:fra_x_preferred":[
        "Wilson"
    ],
    "name:heb_x_preferred":[
        "\u05d5\u05d9\u05dc\u05e1\u05d5\u05df"
    ],
    "name:hun_x_preferred":[
        "Wilson"
    ],
    "name:ita_x_preferred":[
        "Wilson"
    ],
    "name:jpn_x_preferred":[
        "\u30a6\u30a3\u30eb\u30bd\u30f3"
    ],
    "name:lav_x_preferred":[
        "Vilsons"
    ],
    "name:lit_x_preferred":[
        "Wilson"
    ],
    "name:nld_x_preferred":[
        "Wilson"
    ],
    "name:pol_x_preferred":[
        "Wilson"
    ],
    "name:por_x_preferred":[
        "Wilson"
    ],
    "name:ron_x_preferred":[
        "Wilson"
    ],
    "name:rus_x_preferred":[
        "\u0423\u0438\u043b\u0441\u043e\u043d"
    ],
    "name:slv_x_preferred":[
        "Wilson"
    ],
    "name:spa_x_preferred":[
        "Wilson"
    ],
    "name:srp_x_preferred":[
        "\u0412\u0438\u043b\u0441\u043e\u043d"
    ],
    "name:swe_x_preferred":[
        "Wilson"
    ],
    "name:tur_x_preferred":[
        "Wilson"
    ],
    "name:ukr_x_preferred":[
        "\u0412\u0456\u043b\u0441\u043e\u043d"
    ],
    "name:urd_x_preferred":[
        "\u0648\u0644\u0633\u0646"
    ],
    "name:vie_x_preferred":[
        "Wilson"
    ],
    "name:vol_x_preferred":[
        "Wilson"
    ],
    "name:yid_x_preferred":[
        "\u05d5\u05d5\u05d9\u05dc\u05e1\u05d0\u05df"
    ],
    "name:zho_x_preferred":[
        "\u5a01\u723e\u905c"
    ],
    "wof:name":"Wilson",
    "wof:placetype":"locality"
},
  "geometry": {"coordinates":[-87.66946999999998,34.92703],"type":"Point"}
}