{
  "type": "Feature",
  "properties": {
    "gn:admin1_code":"IL",
    "gn:admin2_code":"43.0",
    "gn:admin3_code":"20604.0",
    "gn:asciiname":"Fullersburg",
    "gn:country_code":"US",
    "gn:dem":204,
    "gn:elevation":"202.0",
    "gn:feature_class":"P",
    "gn:feature_code":"PPL",
    "gn:name":"Fullersburg",
    "gn:population":0,
    "gn:timezone":"America/Chicago",
    "iso:country":"US",
    "wof:name":"Fullersburg",
    "wof:placetype":"locality"
},
  "geometry": {"coordinates":[-87.91839,41.81809000000001],"type":"Point"}
}