{
  "type": "Feature",
  "properties": {
    "gn:admin1_code":"AL",
    "gn:admin2_code":"97",
    "gn:asciiname":"Mertz",
    "gn:country_code":"US",
    "gn:dem":12,
    "gn:elevation":"7.0",
    "gn:feature_class":"P",
    "gn:feature_code":"PPL",
    "gn:name":"Mertz",
    "gn:population":0,
    "gn:timezone":"America/Chicago",
    "iso:country":"US",
    "name:eng_x_preferred":[
        "Mertz"
    ],
    "name:und_x_variant":[
        "Mertz Station"
    ],
    "wof:name":"Mertz",
    "wof:placetype":"locality"
},
  "geometry": {"coordinates":[-88.08833,30.66269],"type":"Point"}
}