{
  "type": "Feature",
  "properties": {
    "iso:country":"US",
    "wof:name":"Grier Heights",
    "wof:placetype":"neighbourhood"
},
  "geometry": {"coordinates":[-80.8034764557957,35.19679787450405],"type":"Point"}
}