{
  "type": "Feature",
  "properties": {
    "gn:country":"US",
    "gn:fcode":"PPL",
    "gn:population":0,
    "iso:country":"US",
    "name:eng_x_preferred":[
        "Southside"
    ],
    "name:fra_x_preferred":[
        "Southside"
    ],
    "name:jpn_x_preferred":[
        "\u30b5\u30a6\u30b9\u30b5\u30a4\u30c9"
    ],
    "name:und_x_variant":[
        "South Side"
    ],
    "qs_pg:aaroncc":"US",
    "qs_pg:gn_country":"US",
    "qs_pg:gn_fcode":"PPL",
    "qs_pg:gn_pop":0,
    "qs_pg:name":"Southside",
    "qs_pg:name_adm0":"United States",
    "qs_pg:name_adm1":"Tennessee",
    "qs_pg:photos":5,
    "qs_pg:photos_1k":1,
    "qs_pg:photos_9k":1,
    "qs_pg:photos_9r":1,
    "qs_pg:photos_all":5,
    "qs_pg:photos_sr":1,
    "qs_pg:pop_sr":0,
    "qs_pg:qs_pg_placetype":"locality",
    "qs_pg:qs_pg_placetype_gp":"Town",
    "qs_pg:woe_adm0":23424977,
    "woe:adm0_id":23424977,
    "woe:name_adm0":"United States",
    "woe:name_adm1":"Tennessee",
    "woe:placetype":"Town",
    "wof:name":"Southside",
    "wof:placetype":"locality"
},
  "geometry": {"coordinates":[-87.29555999999999,36.37144],"type":"Point"}
}