{
  "type": "Feature",
  "properties": {
    "gn:admin1_code":"TX",
    "gn:admin2_code":"249.0",
    "gn:asciiname":"Water City Estates Colonia",
    "gn:country_code":"US",
    "gn:dem":46,
    "gn:elevation":"43.0",
    "gn:feature_class":"P",
    "gn:feature_code":"PPL",
    "gn:name":"Water City Estates Colonia",
    "gn:population":0,
    "gn:timezone":"America/Chicago",
    "iso:country":"US",
    "wof:name":"Water City Estates Colonia",
    "wof:placetype":"locality"
},
  "geometry": {"coordinates":[-97.95028000000001,27.7703],"type":"Point"}
}