{
  "type": "Feature",
  "properties": {
    "gn:admin1_code":"TX",
    "gn:admin2_code":"469.0",
    "gn:asciiname":"Carr",
    "gn:country_code":"US",
    "gn:dem":17,
    "gn:elevation":"14.0",
    "gn:feature_class":"P",
    "gn:feature_code":"PPL",
    "gn:name":"Carr",
    "gn:population":0,
    "gn:timezone":"America/Chicago",
    "iso:country":"US",
    "name:deu_x_preferred":[
        "Carr"
    ],
    "name:fin_x_preferred":[
        "Carr"
    ],
    "name:fra_x_preferred":[
        "Carr"
    ],
    "name:heb_x_preferred":[
        "\u05e7\u05d0\u05e8"
    ],
    "name:ita_x_preferred":[
        "Carr"
    ],
    "name:nds_x_preferred":[
        "Carr"
    ],
    "name:pol_x_preferred":[
        "Carr"
    ],
    "name:spa_x_preferred":[
        "Carr"
    ],
    "name:swe_x_preferred":[
        "Carr"
    ],
    "name:ukr_x_preferred":[
        "\u041a\u0430\u0440\u0440"
    ],
    "wof:name":"Carr",
    "wof:placetype":"locality"
},
  "geometry": {"coordinates":[-96.75498,28.73583],"type":"Point"}
}