{
  "type": "Feature",
  "properties": {
    "gn:admin1_code":"MN",
    "gn:admin2_code":"145.0",
    "gn:admin3_code":"56896.0",
    "gn:asciiname":"Riverview Park",
    "gn:country_code":"US",
    "gn:dem":318,
    "gn:elevation":"319.0",
    "gn:feature_class":"P",
    "gn:feature_code":"PPL",
    "gn:name":"Riverview Park",
    "gn:population":0,
    "gn:timezone":"America/Chicago",
    "iso:country":"US",
    "name:ceb_x_preferred":[
        "Riverview Park"
    ],
    "name:deu_x_preferred":[
        "Riverview Park"
    ],
    "name:swe_x_preferred":[
        "Riverview Park"
    ],
    "wof:name":"Riverview Park",
    "wof:placetype":"locality"
},
  "geometry": {"coordinates":[-94.23056,45.56389],"type":"Point"}
}