{
  "type": "Feature",
  "properties": {
    "gn:elevation":67,
    "iso:country":"US",
    "name:eng_x_preferred":[
        "North Bellingham"
    ],
    "name:eng_x_variant":[
        "N Bellingham"
    ],
    "qs:gn_adm0_cc":"US",
    "qs:gn_fcode":"PPL",
    "qs:gn_local":4930266,
    "qs:gn_nam_loc":"bellingham",
    "qs:gn_namadm1":"MA",
    "qs:gn_name":"North Bellingham",
    "qs:local_max":59,
    "qs:local_sum":165,
    "qs:localhoods":5,
    "qs:name":"North Bellingham",
    "qs:name_adm0":"United States",
    "qs:name_adm1":"Massachusetts",
    "qs:name_adm2":"Norfolk",
    "qs:name_local":"Bellingham",
    "qs:photo_max":18,
    "qs:photo_sum":59,
    "qs:placetype":"Suburb",
    "qs:quad_count":13,
    "qs:woe_adm0":23424977,
    "qs:woe_adm1":2347580,
    "qs:woe_adm2":12588710,
    "qs:woe_lau":0,
    "qs:woe_local":2362062,
    "qs:woe_ver":"7.10.0",
    "wof:lang":[
        "eng"
    ],
    "wof:name":"North Bellingham",
    "wof:placetype":"neighbourhood",
    "wof:population":1373,
    "zs:blockids":[
        250214431012001,
        250214431013035,
        250214431013029,
        250214431012010,
        250214431014030,
        250214431011002,
        250214431013027,
        250214431013025,
        250214431012011,
        250214431013031,
        250214431013030,
        250214431013020,
        250214431013045,
        250214431013046,
        250214431013009,
        250214431013028,
        250214431012003,
        250214431012000,
        250214431013038,
        250214431013036,
        250214431013007,
        250214431013008,
        250214421033018,
        250214431013033,
        250214431013013,
        250214431014028,
        250214431013043,
        250214431013026,
        250214431013018,
        250214431013042,
        250214431013032,
        250214431013010,
        250214431013039,
        250214431013024,
        250214421033019,
        250214431014029,
        250214431013034,
        250214431013011,
        250214431013041,
        250214431013023,
        250214431013044
    ],
    "zs:housing10":497,
    "zs:pop10":1373
},
  "geometry": {"coordinates":[-71.461083,42.117667],"type":"Point"}
}