{
  "type": "Feature",
  "properties": {
    "gn:admin1_code":"CO",
    "gn:admin2_code":"35.0",
    "gn:asciiname":"Kistler Park",
    "gn:country_code":"US",
    "gn:dem":1750,
    "gn:elevation":"1749.0",
    "gn:feature_class":"P",
    "gn:feature_code":"PPL",
    "gn:name":"Kistler Park",
    "gn:population":0,
    "gn:timezone":"America/Denver",
    "iso:country":"US",
    "wof:name":"Kistler Park",
    "wof:placetype":"locality"
},
  "geometry": {"coordinates":[-104.98050000000001,39.5417],"type":"Point"}
}