{
  "type": "Feature",
  "properties": {
    "gn:admin1_code":"OH",
    "gn:admin2_code":"115.0",
    "gn:admin3_code":"36092.0",
    "gn:asciiname":"Bishopville",
    "gn:country_code":"US",
    "gn:dem":250,
    "gn:elevation":"250.0",
    "gn:feature_class":"P",
    "gn:feature_code":"PPL",
    "gn:name":"Bishopville",
    "gn:population":0,
    "gn:timezone":"America/New_York",
    "iso:country":"US",
    "wof:name":"Bishopville",
    "wof:placetype":"locality"
},
  "geometry": {"coordinates":[-82.04903,39.51313],"type":"Point"}
}