{
  "type": "Feature",
  "properties": {
    "gn:admin1_code":"VA",
    "gn:admin2_code":"5",
    "gn:asciiname":"Crows",
    "gn:country_code":"US",
    "gn:dem":502,
    "gn:elevation":"499.0",
    "gn:feature_class":"P",
    "gn:feature_code":"PPL",
    "gn:name":"Crows",
    "gn:population":0,
    "gn:timezone":"America/New_York",
    "iso:country":"US",
    "name:eng_x_preferred":[
        "Crows"
    ],
    "name:und_x_variant":[
        "Crow's"
    ],
    "wof:name":"Crows",
    "wof:placetype":"locality"
},
  "geometry": {"coordinates":[-80.20255999999998,37.71957],"type":"Point"}
}