{
  "type": "Feature",
  "properties": {
    "gn:country":"US",
    "gn:fcode":"PPL",
    "gn:population":0,
    "iso:country":"US",
    "name:eng_x_preferred":[
        "Beatty"
    ],
    "name:fas_x_preferred":[
        "\u0628\u06cc\u062a\u06cc"
    ],
    "name:ukr_x_preferred":[
        "\u0411\u0456\u0442\u0456"
    ],
    "qs_pg:aaroncc":"US",
    "qs_pg:gn_country":"US",
    "qs_pg:gn_fcode":"PPL",
    "qs_pg:gn_pop":0,
    "qs_pg:name":"Beatty",
    "qs_pg:name_adm0":"United States",
    "qs_pg:name_adm1":"Pennsylvania",
    "qs_pg:photos":2,
    "qs_pg:photos_1k":1,
    "qs_pg:photos_9k":1,
    "qs_pg:photos_9r":1,
    "qs_pg:photos_all":2,
    "qs_pg:photos_sr":1,
    "qs_pg:pop_sr":0,
    "qs_pg:qs_pg_placetype":"neighbourhood",
    "qs_pg:qs_pg_placetype_gp":"Suburb",
    "qs_pg:woe_adm0":23424977,
    "wd:wordcount":706,
    "wof:name":"Beatty",
    "wof:placetype":"neighbourhood",
    "wof:population":823,
    "zs:area_m":5743238.600778,
    "zs:blockids":[
        421298074023058,
        421298074024046,
        421298074024047,
        421298072004010,
        421298074024044,
        421298074024037,
        421298074023045,
        421298074024045,
        421298074024048,
        421298074024049,
        421298074024050
    ],
    "zs:housing10":280,
    "zs:label":"Beatty",
    "zs:pop10":823
},
  "geometry": {"coordinates":[-79.44217500000001,40.295339],"type":"Point"}
}