{
  "type": "Feature",
  "properties": {
    "gn:admin1_code":"TX",
    "gn:admin2_code":"225",
    "gn:asciiname":"Fog Town",
    "gn:country_code":"US",
    "gn:dem":91,
    "gn:elevation":"85.0",
    "gn:feature_class":"P",
    "gn:feature_code":"PPL",
    "gn:name":"Fog Town",
    "gn:population":0,
    "gn:timezone":"America/Chicago",
    "iso:country":"US",
    "wof:name":"Fog Town",
    "wof:placetype":"locality"
},
  "geometry": {"coordinates":[-95.13077,31.33518],"type":"Point"}
}