{
  "type": "Feature",
  "properties": {
    "iso:country":"US",
    "name:eng_x_preferred":[
        "Timbercrest"
    ],
    "wof:name":"Timbercrest",
    "wof:placetype":"neighbourhood",
    "wof:population":157,
    "zs:area_m":2088337.292241,
    "zs:blockids":[
        371350112042026,
        371350112042027,
        371350112041036,
        371350112042024
    ],
    "zs:housing10":70,
    "zs:label":"Timbercrest",
    "zs:pop10":157
},
  "geometry": {"coordinates":[-79.011977,35.972495],"type":"Point"}
}