{
  "type": "Feature",
  "properties": {
    "gn:admin1_code":"NC",
    "gn:admin2_code":"49",
    "gn:admin3_code":"93460.0",
    "gn:asciiname":"Craven Corner",
    "gn:country_code":"US",
    "gn:dem":3,
    "gn:elevation":"3.0",
    "gn:feature_class":"P",
    "gn:feature_code":"PPL",
    "gn:name":"Craven Corner",
    "gn:population":0,
    "gn:timezone":"America/New_York",
    "iso:country":"US",
    "wof:name":"Craven Corner",
    "wof:placetype":"locality"
},
  "geometry": {"coordinates":[-76.74993000000001,34.86683],"type":"Point"}
}