{
  "type": "Feature",
  "properties": {
    "iso:country":"US",
    "name:eng_x_preferred":[
        "North Black Row"
    ],
    "wof:name":"North Black Row",
    "wof:placetype":"neighbourhood",
    "wof:population":143,
    "zs:area_m":49525.820219,
    "zs:blockids":[
        300310007014030,
        300310007014034,
        300310007014031,
        300310007014028,
        300310007014029,
        300310007014021,
        300310007014042
    ],
    "zs:housing10":59,
    "zs:label":"North Black Row",
    "zs:pop10":143
},
  "geometry": {"coordinates":[-111.036556,45.681677],"type":"Point"}
}