{
  "type": "Feature",
  "properties": {
    "iso:country":"US",
    "name:eng_x_preferred":[
        "Haven Heights"
    ],
    "name:eng_x_variant":[
        "Haven Hts"
    ],
    "qs:gn_adm0_cc":"US",
    "qs:gn_local":4791259,
    "qs:gn_nam_loc":"Virginia Beach, Virginia Beach, Virginia, US",
    "qs:gn_namadm1":"VA",
    "qs:local_max":5828,
    "qs:local_sum":35994,
    "qs:localhoods":70,
    "qs:name":"Haven Heights",
    "qs:name_adm0":"United States",
    "qs:name_adm1":"Virginia",
    "qs:name_adm2":"Virginia Beach City",
    "qs:name_local":"Virginia Beach",
    "qs:photo_max":16,
    "qs:photo_sum":16,
    "qs:placetype":"Suburb",
    "qs:quad_count":1,
    "qs:woe_adm0":23424977,
    "qs:woe_adm1":2347605,
    "qs:woe_adm2":12590430,
    "qs:woe_lau":0,
    "qs:woe_local":2512636,
    "qs:woe_ver":"7.10.0",
    "wof:name":"Haven Heights",
    "wof:placetype":"neighbourhood",
    "wof:population":2383,
    "zs:blockids":[
        518100460021029,
        518100462061003,
        518100462063001,
        518100462061001,
        518100460021032,
        518100460021021,
        518100462063006,
        518100460021024,
        518100462061007,
        518100460021017,
        518100462063005,
        518100460021025,
        518100462061006,
        518100460021016,
        518100460021018,
        518100460021019,
        518100462061002,
        518100462061010,
        518100462063002,
        518100460021013,
        518100460022004,
        518100462063004,
        518100460021030,
        518100462061008,
        518100460021014,
        518100462063000,
        518100460021020,
        518100462061009,
        518100462061014
    ],
    "zs:housing10":926,
    "zs:pop10":2383
},
  "geometry": {"coordinates":[-76.177654,36.812582],"type":"Point"}
}