{
  "type": "Feature",
  "properties": {
    "iso:country":"US",
    "name:arz_x_preferred":[
        "\u0645\u0637\u0627\u0631 \u0645\u0642\u0627\u0637\u0639\u0647 \u0648\u0627\u064a\u0643\u0631\u0648\u0633 \u0648\u064a\u0631"
    ],
    "name:ceb_x_preferred":[
        "Waycross-Ware County Airport"
    ],
    "name:eng_x_preferred":[
        "Waycross Ware County Airport"
    ],
    "name:eng_x_variant":[
        "AYS",
        "KAYS",
        "Waycross-Ware County Airport"
    ],
    "name:fas_x_preferred":[
        "\u0641\u0631\u0648\u062f\u06af\u0627\u0647 \u0634\u0647\u0631\u0633\u062a\u0627\u0646 \u0648\u06cc\u06a9\u0631\u0627\u0633-\u0648\u06cc\u0631"
    ],
    "name:fas_x_variant":[
        "\u0641\u0631\u0648\u062f\u06af\u0627\u0647 \u0648\u06cc\u06a9\u0631\u0627\u0633-\u0648\u06cc\u0631 \u06a9\u0627\u0646\u062a\u06cc"
    ],
    "name:jpn_x_preferred":[
        "\u30a6\u30a7\u30a4\u30af\u30ed\u30b9\uff1d\u30a6\u30a7\u30a2\u90e1\u7a7a\u6e2f"
    ],
    "name:ron_x_preferred":[
        "Aeroportul Waycross-Ware County"
    ],
    "name:tgk_x_preferred":[
        "\u0424\u0443\u0440\u0443\u0434\u0433\u043e\u04b3\u0438 \u0432\u0438\u043a\u0440\u043e\u0441-\u0432\u0438\u0440 \u043a\u043e\u043d"
    ],
    "name:zho_x_preferred":[
        "\u97cb\u514b\u7f85\u65af-\u97cb\u723e\u7e23\u6a5f\u5834"
    ],
    "oa:elevation_ft":"142",
    "oa:type":"small_airport",
    "wd:wordcount":1551,
    "woe:hierarchy":{
        "country_id":23424977,
        "county_id":12588017,
        "planet_id":1,
        "state_id":2347569
    },
    "wof:name":"Waycross Ware County Airport",
    "wof:placetype":"campus"
},
  "geometry": {"coordinates":[-82.3955,31.2491],"type":"Point"}
}