{
  "type": "Feature",
  "properties": {
    "gn:admin1_code":"GA",
    "gn:admin2_code":"121.0",
    "gn:asciiname":"Morning Creek Estates",
    "gn:country_code":"US",
    "gn:dem":296,
    "gn:elevation":"288.0",
    "gn:feature_class":"P",
    "gn:feature_code":"PPL",
    "gn:name":"Morning Creek Estates",
    "gn:population":0,
    "gn:timezone":"America/New_York",
    "iso:country":"US",
    "wof:name":"Morning Creek Estates",
    "wof:placetype":"locality"
},
  "geometry": {"coordinates":[-84.51104000000002,33.60233],"type":"Point"}
}