{
  "type": "Feature",
  "properties": {
    "gn:admin1_code":"AL",
    "gn:admin2_code":"3.0",
    "gn:asciiname":"Autumn Park Mobile Home Park",
    "gn:country_code":"US",
    "gn:dem":33,
    "gn:elevation":"30.0",
    "gn:feature_class":"P",
    "gn:feature_code":"PPL",
    "gn:name":"Autumn Park Mobile Home Park",
    "gn:population":0,
    "gn:timezone":"America/Chicago",
    "iso:country":"US",
    "wof:name":"Autumn Park Mobile Home Park",
    "wof:placetype":"campus"
},
  "geometry": {"coordinates":[-87.88404,30.51005],"type":"Point"}
}