{
  "type": "Feature",
  "properties": {
    "gn:admin1_code":"FL",
    "gn:admin2_code":"119.0",
    "gn:asciiname":"Wahoo",
    "gn:country_code":"US",
    "gn:dem":29,
    "gn:elevation":"15.0",
    "gn:feature_class":"P",
    "gn:feature_code":"PPL",
    "gn:name":"Wahoo",
    "gn:population":0,
    "gn:timezone":"America/New_York",
    "iso:country":"US",
    "name:swe_x_preferred":[
        "Wahoo"
    ],
    "name:zho_x_preferred":[
        "\u74e6\u80e1"
    ],
    "wof:name":"Wahoo",
    "wof:placetype":"locality"
},
  "geometry": {"coordinates":[-82.19564,28.69055],"type":"Point"}
}