{
  "type": "Feature",
  "properties": {
    "gn:country":"US",
    "gn:fcode":"PPL",
    "gn:population":0,
    "iso:country":"US",
    "name:azb_x_preferred":[
        "\u0633\u0645\u0648\u0631\u0627"
    ],
    "name:cym_x_preferred":[
        "Semora"
    ],
    "name:eng_x_preferred":[
        "Semora"
    ],
    "name:fas_x_preferred":[
        "\u0633\u0645\u0648\u0631\u0627"
    ],
    "name:fra_x_preferred":[
        "Semora"
    ],
    "name:spa_x_preferred":[
        "Semora"
    ],
    "name:und_x_variant":[
        "Campbells Crossroads"
    ],
    "name:vol_x_preferred":[
        "Semora"
    ],
    "qs_pg:aaroncc":"US",
    "qs_pg:gn_country":"US",
    "qs_pg:gn_fcode":"PPL",
    "qs_pg:gn_pop":0,
    "qs_pg:name":"Semora",
    "qs_pg:name_adm0":"United States",
    "qs_pg:name_adm1":"North Carolina",
    "qs_pg:photos":111,
    "qs_pg:photos_1k":22,
    "qs_pg:photos_9k":1,
    "qs_pg:photos_9r":3,
    "qs_pg:photos_all":111,
    "qs_pg:photos_sr":3,
    "qs_pg:pop_sr":0,
    "qs_pg:qs_pg_placetype":"locality",
    "qs_pg:qs_pg_placetype_gp":"Town",
    "qs_pg:woe_adm0":23424977,
    "woe:adm0_id":23424977,
    "woe:name_adm0":"United States",
    "woe:name_adm1":"North Carolina",
    "woe:placetype":"Town",
    "wof:name":"Semora",
    "wof:placetype":"locality"
},
  "geometry": {"coordinates":[-79.1489,36.49847],"type":"Point"}
}