{
  "type": "Feature",
  "properties": {
    "gn:elevation":742,
    "gn:population":2776,
    "iso:country":"US",
    "name:ceb_x_preferred":[
        "Fairchild Air Force Base"
    ],
    "name:ces_x_preferred":[
        "Fairchildova leteck\u00e1 z\u00e1kladna"
    ],
    "name:deu_x_preferred":[
        "Fairchild Air Force Base"
    ],
    "name:eng_x_preferred":[
        "Fairchild Air Force Base"
    ],
    "name:eng_x_variant":[
        "SKA",
        "KSKA"
    ],
    "name:fas_x_preferred":[
        "\u067e\u0627\u06cc\u06af\u0627\u0647 \u0646\u06cc\u0631\u0648\u06cc \u0647\u0648\u0627\u06cc\u06cc \u0641\u06cc\u0631\u0686\u0627\u06cc\u0644\u062f"
    ],
    "name:fra_x_preferred":[
        "Fairchild Air Force Base"
    ],
    "name:hun_x_preferred":[
        "Fairchild l\u00e9git\u00e1maszpont"
    ],
    "name:ita_x_preferred":[
        "Fairchild Air Force Base"
    ],
    "name:jpn_x_preferred":[
        "\u30d5\u30a7\u30a2\u30c1\u30e3\u30a4\u30eb\u30c9\u7a7a\u8ecd\u57fa\u5730"
    ],
    "name:nan_x_preferred":[
        "Fairchild AFB"
    ],
    "name:nav_x_preferred":[
        "Naakigo Hadahiil\u00ediniidi sil\u00e1o\u0142tsoo\u00ed bichid\u00ed naat\u02bca\u02bc\u00ed \u0144dinib\u012f\u012fh\u00edgi"
    ],
    "name:nld_x_preferred":[
        "Fairchild Air Force Base"
    ],
    "name:nob_x_preferred":[
        "Fairchild Air Force Base"
    ],
    "name:por_x_preferred":[
        "Fairchild Air Force Base"
    ],
    "name:spa_x_preferred":[
        "Base de la Fuerza A\u00e9rea Fairchild"
    ],
    "name:srp_x_preferred":[
        "\u0412\u0430\u0437\u0434\u0443\u0445\u043e\u043f\u043b\u043e\u0432\u043d\u0430 \u0431\u0430\u0437\u0430 \u0424\u0435\u0440\u0447\u0430\u0458\u043b\u0434"
    ],
    "name:tgk_x_preferred":[
        "\u041f\u043e\u0439\u0433\u043e\u04b3\u0438 \u043d\u0435\u0440\u04ef\u0435 \u04b3\u0430\u0432\u043e \u0444\u0438\u0440\u0447\u043e\u0438\u043b\u0434"
    ],
    "name:und_x_variant":[
        "Fairchild Air Force Base CDP"
    ],
    "name:uzb_x_preferred":[
        "Fairchild AFB"
    ],
    "oa:elevation_ft":"2461",
    "oa:type":"large_airport",
    "wd:wordcount":4470,
    "woe:hierarchy":{
        "country_id":23424977,
        "county_id":12590471,
        "planet_id":1,
        "state_id":2347606
    },
    "wof:name":"Fairchild Air Force Base",
    "wof:placetype":"campus",
    "wof:population":2776
},
  "geometry": {"coordinates":[-117.655998,47.615101],"type":"Point"}
}