{
  "type": "Feature",
  "properties": {
    "iso:country":"US",
    "name:eng_x_preferred":[
        "North Side Fargo Builder's Residential Historic Di"
    ],
    "wof:name":"North Side Fargo Builder's Residential Historic Di",
    "wof:placetype":"neighbourhood",
    "wof:population":2090,
    "zs:area_m":1009096.607609,
    "zs:blockids":[
        380170004003000,
        380170004002002,
        380170004002032,
        380170001002022,
        380170001002025,
        380170004004006,
        380170001002021,
        380170001002024,
        380170004004005,
        380170004002009,
        380170004002025,
        380170004002028,
        380170004002027,
        380170004001011,
        380170004002001,
        380170001002023,
        380170004004003,
        380170004002004,
        380170004001012,
        380170001002020,
        380170004004007,
        380170004004011,
        380170001002029,
        380170001002019,
        380170004002005,
        380170004002003,
        380170004002008,
        380170004004015,
        380170004004009,
        380170004004004,
        380170004004002,
        380170001002027,
        380170004002010,
        380170004002012,
        380170004004000,
        380170004002000,
        380170004004001,
        380170004002030,
        380170001002026,
        380170004002011,
        380170004002026,
        380170004002031,
        380170004004014,
        380170004004008,
        380170004004012,
        380170004002007,
        380170004002029,
        380170004004013,
        380170001002028,
        380170001002018
    ],
    "zs:housing10":943,
    "zs:label":"North Side Fargo Builder's Residential Historic Di",
    "zs:pop10":2090
},
  "geometry": {"coordinates":[-96.784808,46.894855],"type":"Point"}
}