{
  "type": "Feature",
  "properties": {
    "gn:admin1_code":"IN",
    "gn:admin2_code":"65.0",
    "gn:admin3_code":"43308.0",
    "gn:asciiname":"Corwin",
    "gn:country_code":"US",
    "gn:dem":335,
    "gn:elevation":"336.0",
    "gn:feature_class":"P",
    "gn:feature_code":"PPL",
    "gn:name":"Corwin",
    "gn:population":0,
    "gn:timezone":"America/Indiana/Indianapolis",
    "iso:country":"US",
    "wof:name":"Corwin",
    "wof:placetype":"locality"
},
  "geometry": {"coordinates":[-85.29913000000001,39.88838],"type":"Point"}
}