{
  "type": "Feature",
  "properties": {
    "gn:admin1_code":"FL",
    "gn:admin2_code":"21.0",
    "gn:asciiname":"Vanderbilt Beach Estates",
    "gn:country_code":"US",
    "gn:dem":5,
    "gn:elevation":"0.0",
    "gn:feature_class":"P",
    "gn:feature_code":"PPL",
    "gn:name":"Vanderbilt Beach Estates",
    "gn:population":0,
    "gn:timezone":"America/New_York",
    "iso:country":"US",
    "name:ara_x_preferred":[
        "\u0641\u0627\u0646\u062f\u0631\u0628\u064a\u0644\u062a \u0628\u064a\u062a\u0634 \u0625\u0633\u062a\u064a\u062a\u0633"
    ],
    "name:eng_x_preferred":[
        "Vanderbilt Beach Estates"
    ],
    "name:fas_x_preferred":[
        "\u0633\u0627\u062d\u0644 \u0648\u0646\u062f\u0631\u0628\u06cc\u0644\u062a \u0627\u0633\u062a\u062a\u0633"
    ],
    "name:und_x_variant":[
        "Vanderbilt Beach"
    ],
    "wof:name":"Vanderbilt Beach Estates",
    "wof:placetype":"locality"
},
  "geometry": {"coordinates":[-81.82398000000001,26.26342],"type":"Point"}
}