{
  "type": "Feature",
  "properties": {
    "iso:country":"US",
    "name:bre_x_preferred":[
        "Antrim"
    ],
    "name:ceb_x_preferred":[
        "Antrim"
    ],
    "name:ces_x_preferred":[
        "Antrim"
    ],
    "name:deu_x_preferred":[
        "Antrim"
    ],
    "name:eng_x_preferred":[
        "Antrim"
    ],
    "name:fin_x_preferred":[
        "Antrim"
    ],
    "name:fra_x_preferred":[
        "Antrim"
    ],
    "name:ita_x_preferred":[
        "Antrim"
    ],
    "name:nld_x_preferred":[
        "Antrim"
    ],
    "name:pol_x_preferred":[
        "Antrim"
    ],
    "name:por_x_preferred":[
        "Antrim"
    ],
    "name:rus_x_preferred":[
        "\u0410\u043d\u0442\u0440\u0438\u043c"
    ],
    "name:slk_x_preferred":[
        "Antrim"
    ],
    "name:srp_x_preferred":[
        "\u0410\u043d\u0442\u0440\u0438\u043c"
    ],
    "name:swe_x_preferred":[
        "Antrim"
    ],
    "name:ukr_x_preferred":[
        "\u0410\u043d\u0442\u0440\u0456\u043c"
    ],
    "wof:name":"Antrim",
    "wof:placetype":"neighbourhood",
    "wof:population":20,
    "zs:area_m":74378.097221,
    "zs:blockids":[
        360870119022012,
        360870119022013
    ],
    "zs:housing10":6,
    "zs:label":"Antrim",
    "zs:pop10":20
},
  "geometry": {"coordinates":[-74.144064,41.121814],"type":"Point"}
}