{
  "type": "Feature",
  "properties": {
    "iso:country":"US",
    "name:ara_x_preferred":[
        "\u0623\u0646\u062a\u0631\u064a\u0645 "
    ],
    "name:ben_x_preferred":[
        "\u0986\u09a8\u09cd\u099f\u09cd\u09b0\u09bf\u09ae"
    ],
    "name:bre_x_preferred":[
        "Antrim"
    ],
    "name:ceb_x_preferred":[
        "Antrim"
    ],
    "name:ces_x_preferred":[
        "Antrim"
    ],
    "name:deu_x_preferred":[
        "Antrim"
    ],
    "name:ell_x_preferred":[
        "\u0391\u03bd\u03c4\u03c1\u03af\u03bc"
    ],
    "name:eng_x_preferred":[
        "Antrim"
    ],
    "name:fas_x_preferred":[
        "\u0622\u0646\u062a\u0631\u06cc\u0645"
    ],
    "name:fin_x_preferred":[
        "Antrim"
    ],
    "name:fra_x_preferred":[
        "Antrim"
    ],
    "name:heb_x_preferred":[
        "\u05d0\u05e0\u05d8\u05e8\u05d9\u05dd"
    ],
    "name:hin_x_preferred":[
        "\u090f\u0902\u091f\u094d\u0930\u093f\u092e"
    ],
    "name:hun_x_preferred":[
        "Antrim"
    ],
    "name:ind_x_preferred":[
        "Antrim"
    ],
    "name:ita_x_preferred":[
        "Antrim"
    ],
    "name:nld_x_preferred":[
        "Antrim"
    ],
    "name:pol_x_preferred":[
        "Antrim"
    ],
    "name:por_x_preferred":[
        "Antrim"
    ],
    "name:rus_x_preferred":[
        "\u0410\u043d\u0442\u0440\u0438\u043c"
    ],
    "name:slk_x_preferred":[
        "Antrim"
    ],
    "name:spa_x_preferred":[
        "Antrim"
    ],
    "name:srp_x_preferred":[
        "\u0410\u043d\u0442\u0440\u0438\u043c"
    ],
    "name:swe_x_preferred":[
        "Antrim"
    ],
    "name:tur_x_preferred":[
        "Antrim"
    ],
    "name:ukr_x_preferred":[
        "\u0410\u043d\u0442\u0440\u0456\u043c"
    ],
    "name:urd_x_preferred":[
        "\u0627\u06cc\u0646\u0679\u0631\u0645"
    ],
    "name:vie_x_preferred":[
        "Antrim"
    ],
    "wof:name":"Antrim",
    "wof:placetype":"neighbourhood",
    "wof:population":20,
    "zs:area_m":74378.097221,
    "zs:blockids":[
        360870119022012,
        360870119022013
    ],
    "zs:housing10":6,
    "zs:label":"Antrim",
    "zs:pop10":20
},
  "geometry": {"coordinates":[-74.144064,41.121814],"type":"Point"}
}