{
  "type": "Feature",
  "properties": {
    "gn:country":"US",
    "gn:fcode":"PPL",
    "gn:population":0,
    "iso:country":"US",
    "name:ben_x_preferred":[
        "\u0993\u09df\u09c7\u09b8\u09cd\u099f \u09ac\u09c7\u09a8\u09cd\u09a1"
    ],
    "name:ceb_x_preferred":[
        "West Bend"
    ],
    "name:deu_x_preferred":[
        "West Bend"
    ],
    "name:ell_x_preferred":[
        "\u0393\u03bf\u03c5\u03ad\u03c3\u03c4 \u039c\u03c0\u03b5\u03bd\u03c4"
    ],
    "name:fas_x_preferred":[
        "\u0648\u0633\u062a \u0628\u0646\u062f"
    ],
    "name:fra_x_preferred":[
        "West Bend"
    ],
    "name:heb_x_preferred":[
        "\u05d5\u05d5\u05e1\u05d8 \u05d1\u05e0\u05d3"
    ],
    "name:hin_x_preferred":[
        "\u0935\u0947\u0938\u094d\u091f \u092c\u0947\u0902\u0921"
    ],
    "name:ind_x_preferred":[
        "West Bend"
    ],
    "name:ita_x_preferred":[
        "West Bend"
    ],
    "name:kor_x_preferred":[
        "\uc6e8\uc2a4\ud2b8 \ubca4\ub4dc"
    ],
    "name:nld_x_preferred":[
        "West Bend"
    ],
    "name:pol_x_preferred":[
        "West Bend"
    ],
    "name:por_x_preferred":[
        "West Bend"
    ],
    "name:srp_x_preferred":[
        "\u0412\u0435\u0441\u0442 \u0411\u0435\u043d\u0434"
    ],
    "name:swe_x_preferred":[
        "West Bend"
    ],
    "name:ukr_x_preferred":[
        "\u0412\u0435\u0441\u0442-\u0411\u0435\u043d\u0434"
    ],
    "name:vol_x_preferred":[
        "West Bend"
    ],
    "qs_pg:aaroncc":"US",
    "qs_pg:gn_country":"US",
    "qs_pg:gn_fcode":"PPL",
    "qs_pg:gn_pop":0,
    "qs_pg:name":"West Bend",
    "qs_pg:name_adm0":"United States",
    "qs_pg:name_adm1":"North Carolina",
    "qs_pg:photos":114,
    "qs_pg:photos_1k":23,
    "qs_pg:photos_9k":1,
    "qs_pg:photos_9r":3,
    "qs_pg:photos_all":114,
    "qs_pg:photos_sr":3,
    "qs_pg:pop_sr":0,
    "qs_pg:qs_pg_placetype":"locality",
    "qs_pg:qs_pg_placetype_gp":"Town",
    "qs_pg:woe_adm0":23424977,
    "woe:adm0_id":23424977,
    "woe:name_adm0":"United States",
    "woe:name_adm1":"North Carolina",
    "woe:placetype":"Town",
    "wof:name":"West Bend",
    "wof:placetype":"locality"
},
  "geometry": {"coordinates":[-80.48867,36.09514],"type":"Point"}
}