{
  "type": "Feature",
  "properties": {
    "gn:admin1_code":"ME",
    "gn:admin2_code":"3.0",
    "gn:admin3_code":"1710.0",
    "gn:asciiname":"Sheridan",
    "gn:country_code":"US",
    "gn:dem":158,
    "gn:elevation":"165.0",
    "gn:feature_class":"P",
    "gn:feature_code":"PPL",
    "gn:name":"Sheridan",
    "gn:population":0,
    "gn:timezone":"America/New_York",
    "iso:country":"US",
    "name:bul_x_preferred":[
        "\u0428\u0435\u0440\u0438\u0434\u0430\u043d"
    ],
    "name:cat_x_preferred":[
        "Sheridan"
    ],
    "name:ceb_x_preferred":[
        "Sheridan"
    ],
    "name:ces_x_preferred":[
        "Sheridan"
    ],
    "name:dan_x_preferred":[
        "Sheridan"
    ],
    "name:deu_x_preferred":[
        "Sheridan"
    ],
    "name:eng_x_preferred":[
        "Sheridan"
    ],
    "name:fas_x_preferred":[
        "\u0634\u0631\u06cc\u062f\u0627\u0646"
    ],
    "name:fin_x_preferred":[
        "Sheridan"
    ],
    "name:fra_x_preferred":[
        "Sheridan"
    ],
    "name:heb_x_preferred":[
        "\u05e9\u05e8\u05d9\u05d3\u05df"
    ],
    "name:ita_x_preferred":[
        "Sheridan"
    ],
    "name:jpn_x_preferred":[
        "\u30b7\u30a7\u30ea\u30c0\u30f3"
    ],
    "name:kor_x_preferred":[
        "\uc170\ub9ac\ub4e0"
    ],
    "name:nld_x_preferred":[
        "Sheridan"
    ],
    "name:pol_x_preferred":[
        "Sheridan"
    ],
    "name:por_x_preferred":[
        "Sheridan"
    ],
    "name:rus_x_preferred":[
        "\u0428\u0435\u0440\u0438\u0434\u0430\u043d"
    ],
    "name:srp_x_preferred":[
        "\u0428\u0435\u0440\u0438\u0434\u0430\u043d"
    ],
    "name:swe_x_preferred":[
        "Sheridan"
    ],
    "name:ukr_x_preferred":[
        "\u0428\u0435\u0440\u0456\u0434\u0430\u043d"
    ],
    "name:und_x_variant":[
        "Sheriden"
    ],
    "name:vol_x_preferred":[
        "Sheridan"
    ],
    "wof:name":"Sheridan",
    "wof:placetype":"locality"
},
  "geometry": {"coordinates":[-68.40504,46.65726],"type":"Point"}
}