{
  "type": "Feature",
  "properties": {
    "gn:admin1_code":"OH",
    "gn:admin2_code":"59",
    "gn:admin3_code":"11003.0",
    "gn:asciiname":"Jackson Special",
    "gn:country_code":"US",
    "gn:dem":244,
    "gn:elevation":"243.0",
    "gn:feature_class":"P",
    "gn:feature_code":"PPL",
    "gn:name":"Jackson Special",
    "gn:population":0,
    "gn:timezone":"America/New_York",
    "iso:country":"US",
    "name:eng_x_preferred":[
        "Jackson Special"
    ],
    "name:und_x_variant":[
        "Nicholson",
        "Nicholsons"
    ],
    "wof:name":"Jackson Special",
    "wof:placetype":"locality"
},
  "geometry": {"coordinates":[-81.57346,39.99341],"type":"Point"}
}