{
  "type": "Feature",
  "properties": {
    "gn:admin1_code":"MD",
    "gn:admin2_code":"31.0",
    "gn:asciiname":"Bradley Hills",
    "gn:country_code":"US",
    "gn:dem":98,
    "gn:elevation":"97.0",
    "gn:feature_class":"P",
    "gn:feature_code":"PPL",
    "gn:name":"Bradley Hills",
    "gn:population":0,
    "gn:timezone":"America/New_York",
    "iso:country":"US",
    "wof:name":"Bradley Hills",
    "wof:placetype":"locality"
},
  "geometry": {"coordinates":[-77.10776,38.97983],"type":"Point"}
}