{
  "type": "Feature",
  "properties": {
    "gn:admin1_code":"TX",
    "gn:admin2_code":"215",
    "gn:asciiname":"Francis Addition Colonia",
    "gn:country_code":"US",
    "gn:dem":46,
    "gn:elevation":"36.0",
    "gn:feature_class":"P",
    "gn:feature_code":"PPL",
    "gn:name":"Francis Addition Colonia",
    "gn:population":0,
    "gn:timezone":"America/Chicago",
    "iso:country":"US",
    "wof:name":"Francis Addition Colonia",
    "wof:placetype":"locality"
},
  "geometry": {"coordinates":[-98.21639999999999,26.19535],"type":"Point"}
}