{
  "type": "Feature",
  "properties": {
    "gn:admin1_code":"WV",
    "gn:admin2_code":"33.0",
    "gn:asciiname":"Wilsonburg",
    "gn:country_code":"US",
    "gn:dem":299,
    "gn:elevation":"301.0",
    "gn:feature_class":"P",
    "gn:feature_code":"PPL",
    "gn:name":"Wilsonburg",
    "gn:population":0,
    "gn:timezone":"America/New_York",
    "iso:country":"US",
    "name:eng_x_preferred":[
        "Wilsonburg"
    ],
    "name:fas_x_preferred":[
        "\u0648\u06cc\u0644\u0633\u0648\u0646\u0628\u0631\u06af"
    ],
    "name:und_x_variant":[
        "Wilsonburgh"
    ],
    "wof:name":"Wilsonburg",
    "wof:placetype":"locality"
},
  "geometry": {"coordinates":[-80.39619999999999,39.29259],"type":"Point"}
}