{
  "type": "Feature",
  "properties": {
    "gn:admin1_code":"SD",
    "gn:admin2_code":"81.0",
    "gn:admin3_code":"45600.0",
    "gn:asciiname":"Tinton",
    "gn:country_code":"US",
    "gn:dem":1817,
    "gn:elevation":"1817.0",
    "gn:feature_class":"P",
    "gn:feature_code":"PPL",
    "gn:name":"Tinton",
    "gn:population":0,
    "gn:timezone":"America/Denver",
    "iso:country":"US",
    "name:eng_x_preferred":[
        "Tinton"
    ],
    "name:und_x_variant":[
        "Negro Hills"
    ],
    "wof:name":"Tinton",
    "wof:placetype":"locality"
},
  "geometry": {"coordinates":[-104.04854,44.38054],"type":"Point"}
}