{
  "type": "Feature",
  "properties": {
    "gn:admin1_code":"VA",
    "gn:admin2_code":"161",
    "gn:asciiname":"Pine Acres",
    "gn:country_code":"US",
    "gn:dem":377,
    "gn:elevation":"367.0",
    "gn:feature_class":"P",
    "gn:feature_code":"PPL",
    "gn:name":"Pine Acres",
    "gn:population":0,
    "gn:timezone":"America/New_York",
    "iso:country":"US",
    "wof:name":"Pine Acres",
    "wof:placetype":"locality"
},
  "geometry": {"coordinates":[-80.01393,37.21041],"type":"Point"}
}