{
  "type": "Feature",
  "properties": {
    "gn:admin1_code":"TX",
    "gn:admin2_code":"501.0",
    "gn:asciiname":"Allred",
    "gn:country_code":"US",
    "gn:dem":1106,
    "gn:elevation":"1108.0",
    "gn:feature_class":"P",
    "gn:feature_code":"PPL",
    "gn:name":"Allred",
    "gn:population":0,
    "gn:timezone":"America/Chicago",
    "iso:country":"US",
    "wof:name":"Allred",
    "wof:placetype":"locality"
},
  "geometry": {"coordinates":[-102.88799,32.98621],"type":"Point"}
}