{
  "type": "Feature",
  "properties": {
    "iso:country":"US",
    "wof:name":"Georgetown East",
    "wof:placetype":"neighbourhood"
},
  "geometry": {"coordinates":[-76.24360969034549,36.80550324251304],"type":"Point"}
}