{
  "type": "Feature",
  "properties": {
    "gn:admin1_code":"IN",
    "gn:admin2_code":"119.0",
    "gn:admin3_code":"46998.0",
    "gn:asciiname":"Denmark",
    "gn:country_code":"US",
    "gn:dem":168,
    "gn:elevation":"167.0",
    "gn:feature_class":"P",
    "gn:feature_code":"PPL",
    "gn:name":"Denmark",
    "gn:population":0,
    "gn:timezone":"America/Indiana/Indianapolis",
    "iso:country":"US",
    "name:fas_x_preferred":[
        "\u062f\u0627\u0646\u0645\u0627\u0631\u06a9"
    ],
    "name:urd_x_preferred":[
        "\u0688\u0646\u0645\u0627\u0631\u06a9"
    ],
    "wof:name":"Denmark",
    "wof:placetype":"locality"
},
  "geometry": {"coordinates":[-87.02584,39.26976],"type":"Point"}
}