{
  "type": "Feature",
  "properties": {
    "gn:elevation":1604,
    "iso:country":"US",
    "name:ceb_x_preferred":[
        "Glendo State Park"
    ],
    "name:deu_x_preferred":[
        "Glendo State Park"
    ],
    "name:eng_x_preferred":[
        "Mckay Landing"
    ],
    "name:eng_x_variant":[
        "Mckay Lndg"
    ],
    "name:unk_x_variant":[
        "Mckay Landing"
    ],
    "qs:gn_fcode":"PPL",
    "qs:gn_local":0,
    "qs:gn_namadm1":"CO",
    "qs:gn_name":"McKay Landing",
    "qs:local_max":2502,
    "qs:local_sum":10799,
    "qs:localhoods":32,
    "qs:name":"Mckay Landing",
    "qs:name_adm0":"United States",
    "qs:name_adm1":"Colorado",
    "qs:name_adm2":"Broomfield",
    "qs:name_local":"Broomfield",
    "qs:photo_max":3,
    "qs:photo_sum":7,
    "qs:placetype":"Suburb",
    "qs:quad_count":3,
    "qs:woe_adm0":23424977,
    "qs:woe_adm1":2347564,
    "qs:woe_adm2":26343011,
    "qs:woe_lau":0,
    "qs:woe_local":2370243,
    "qs:woe_ver":"7.10.0",
    "wof:lang":[
        "eng"
    ],
    "wof:name":"Mckay Landing",
    "wof:placetype":"neighbourhood",
    "wof:population":1682,
    "zs:blockids":[
        80140313002032,
        80140310003048,
        80140310002000,
        80140310003043,
        80140310001001,
        80140310003009,
        80140310003018,
        80140310003036,
        80140310003035,
        80140310003000,
        80140310001016,
        80140310003038,
        80140310003037,
        80140310003042,
        80140310003016,
        80140310003006,
        80140310003046,
        80140310003017,
        80140310002029,
        80140310003011,
        80140310003030,
        80140310003047,
        80140310003034,
        80140313002031,
        80140313002030,
        80140310001017,
        80140310003007,
        80140310003008,
        80140310003040,
        80140310003044,
        80140310001000,
        80140310003005,
        80140310003015,
        80140310003032,
        80140310003039,
        80140310003041,
        80140310003031,
        80140310003033,
        80140310002027,
        80140310003010,
        80140310001018,
        80140310002030,
        80140310002028
    ],
    "zs:housing10":651,
    "zs:pop10":1682
},
  "geometry": {"coordinates":[-105.024981,39.950956],"type":"Point"}
}