{
  "type": "Feature",
  "properties": {
    "gn:admin1_code":"OK",
    "gn:admin2_code":"123",
    "gn:asciiname":"Coil",
    "gn:country_code":"US",
    "gn:dem":211,
    "gn:elevation":"207.0",
    "gn:feature_class":"P",
    "gn:feature_code":"PPL",
    "gn:name":"Coil",
    "gn:population":0,
    "gn:timezone":"America/Chicago",
    "iso:country":"US",
    "name:ben_x_preferred":[
        "\u0995\u09af\u09bc\u09c7\u09b2"
    ],
    "name:deu_x_preferred":[
        "Coil"
    ],
    "name:heb_x_preferred":[
        "\u05e7\u05d5\u05d9\u05dc"
    ],
    "name:jpn_x_preferred":[
        "\u30b3\u30a4\u30eb"
    ],
    "name:kor_x_preferred":[
        "\ucf54\uc77c"
    ],
    "name:por_x_preferred":[
        "Coil"
    ],
    "wof:name":"Coil",
    "wof:placetype":"locality"
},
  "geometry": {"coordinates":[-96.52973,34.65815],"type":"Point"}
}