{
  "type": "Feature",
  "properties": {
    "iso:country":"US",
    "name:eng_x_preferred":[
        "Loma Vista"
    ],
    "name:eng_x_variant":[
        "Loma Vis"
    ],
    "qs:gn_fcode":"PPL",
    "qs:gn_local":0,
    "qs:gn_nam_loc":"Kansas City, Wyandotte, Kansas, US",
    "qs:gn_namadm1":"KS",
    "qs:gn_name":"Loma Vista",
    "qs:local_max":4300,
    "qs:local_sum":10961,
    "qs:localhoods":23,
    "qs:name":"Loma Vista",
    "qs:name_adm0":"United States",
    "qs:name_adm1":"Kansas",
    "qs:name_adm2":"Wyandotte",
    "qs:name_local":"Kansas City",
    "qs:photo_max":72,
    "qs:photo_sum":115,
    "qs:placetype":"Suburb",
    "qs:quad_count":14,
    "qs:woe_adm0":23424977,
    "qs:woe_adm1":2347575,
    "qs:woe_adm2":12588475,
    "qs:woe_lau":0,
    "qs:woe_local":2430632,
    "qs:woe_ver":"7.10.0",
    "wof:lang":[
        "eng"
    ],
    "wof:name":"Loma Vista",
    "wof:placetype":"neighbourhood",
    "wof:population":692,
    "zs:blockids":[
        202090446011011,
        202090446011045,
        202090448042039,
        202090446011016,
        202090446011019,
        202090446011004,
        202090446011043,
        202090446011035,
        202090446011018,
        202090448042038,
        202090446011051,
        202090448042011,
        202090446011020,
        202090446011054,
        202090446011014,
        202090446011044,
        202090446011053,
        202090446011015,
        202090446011059,
        202090446011050,
        202090446011037,
        202090446011041,
        202090446011039,
        202090446011060,
        202090446011049,
        202090446011021,
        202090446011024,
        202090446011042,
        202090446011047,
        202090446011040,
        202090446011023,
        202090446011055,
        202090446011048,
        202090446011036,
        202090446011056,
        202090448042009,
        202090446011038,
        202090446011052,
        202090446011046,
        202090446011017,
        202090446011013,
        202090446011058,
        202090446011012
    ],
    "zs:housing10":256,
    "zs:pop10":692
},
  "geometry": {"coordinates":[-94.782988,39.159687],"type":"Point"}
}