{
  "type": "Feature",
  "properties": {
    "gn:admin1_code":"MD",
    "gn:admin2_code":"3.0",
    "gn:asciiname":"Altoona Beach",
    "gn:country_code":"US",
    "gn:dem":20,
    "gn:elevation":"14.0",
    "gn:feature_class":"P",
    "gn:feature_code":"PPL",
    "gn:name":"Altoona Beach",
    "gn:population":0,
    "gn:timezone":"America/New_York",
    "iso:country":"US",
    "wof:name":"Altoona Beach",
    "wof:placetype":"locality"
},
  "geometry": {"coordinates":[-76.54024,39.15928],"type":"Point"}
}