{
  "type": "Feature",
  "properties": {
    "iso:country":"US",
    "name:ceb_x_preferred":[
        "Hampton Ridge"
    ],
    "name:deu_x_preferred":[
        "Hampton Ridge"
    ],
    "name:eng_x_preferred":[
        "Hampton Ridge"
    ],
    "name:swe_x_preferred":[
        "Hampton Ridge"
    ],
    "name:zho_x_preferred":[
        "\u6f22\u666e\u9813\u5dba"
    ],
    "wd:wordcount":117,
    "wof:name":"Hampton Ridge",
    "wof:placetype":"neighbourhood",
    "wof:population":646,
    "zs:area_m":660474.927331,
    "zs:blockids":[
        450790116043030,
        450790116042046,
        450790116042018,
        450790116042037,
        450790116042026,
        450790116043026,
        450790116042035,
        450790116043027,
        450790116043029,
        450790116043028,
        450790116042036,
        450790116043025,
        450790116043032,
        450790116042025,
        450790116043031
    ],
    "zs:housing10":281,
    "zs:label":"Hampton Ridge",
    "zs:pop10":646
},
  "geometry": {"coordinates":[-80.965417,33.969975],"type":"Point"}
}