{
  "type": "Feature",
  "properties": {
    "gn:admin1_code":"PA",
    "gn:admin2_code":"109.0",
    "gn:admin3_code":"82464.0",
    "gn:asciiname":"Lowell",
    "gn:country_code":"US",
    "gn:dem":198,
    "gn:elevation":"196.0",
    "gn:feature_class":"P",
    "gn:feature_code":"PPL",
    "gn:name":"Lowell",
    "gn:population":0,
    "gn:timezone":"America/New_York",
    "iso:country":"US",
    "name:bre_x_preferred":[
        "Lowell"
    ],
    "name:cat_x_preferred":[
        "Lowell"
    ],
    "name:ceb_x_preferred":[
        "Lowell"
    ],
    "name:ces_x_preferred":[
        "Lowell"
    ],
    "name:deu_x_preferred":[
        "Lowell"
    ],
    "name:est_x_preferred":[
        "Lowell"
    ],
    "name:fas_x_preferred":[
        "\u0644\u0648\u0648\u0644"
    ],
    "name:fin_x_preferred":[
        "Lowell"
    ],
    "name:fra_x_preferred":[
        "Lowell"
    ],
    "name:heb_x_preferred":[
        "\u05dc\u05d5\u05d5\u05dc"
    ],
    "name:ita_x_preferred":[
        "Lowell"
    ],
    "name:jpn_x_preferred":[
        "\u30ed\u30fc\u30a6\u30a7\u30eb"
    ],
    "name:nds_x_preferred":[
        "Lowell"
    ],
    "name:nld_x_preferred":[
        "Lowell"
    ],
    "name:pol_x_preferred":[
        "Lowell"
    ],
    "name:por_x_preferred":[
        "Lowell"
    ],
    "name:rus_x_preferred":[
        "\u041b\u043e\u0443\u044d\u043b\u043b"
    ],
    "name:spa_x_preferred":[
        "Lowell"
    ],
    "name:srp_x_preferred":[
        "\u041b\u043e\u0443\u0435\u043b"
    ],
    "name:swe_x_preferred":[
        "Lowell"
    ],
    "name:vie_x_preferred":[
        "Lowell"
    ],
    "name:vol_x_preferred":[
        "Lowell"
    ],
    "name:zho_x_preferred":[
        "\u6d1b\u5384\u5c14"
    ],
    "wof:name":"Lowell",
    "wof:placetype":"locality"
},
  "geometry": {"coordinates":[-77.29581999999998,40.73008],"type":"Point"}
}