{
  "type": "Feature",
  "properties": {
    "iso:country":"US",
    "name:ceb_x_preferred":[
        "Sandy Ridge"
    ],
    "name:deu_x_preferred":[
        "Sandy Ridge"
    ],
    "name:eng_x_preferred":[
        "Sandy Ridge"
    ],
    "name:pol_x_preferred":[
        "Sandy Ridge"
    ],
    "name:swe_x_preferred":[
        "Sandy Ridge"
    ],
    "wd:wordcount":42,
    "wof:name":"Sandy Ridge",
    "wof:placetype":"neighbourhood",
    "wof:population":866,
    "zs:area_m":1683052.623819,
    "zs:blockids":[
        120690309131002,
        120690309131006,
        120690309131013,
        120690309131014,
        120690302033046,
        120690302033049,
        120690309131017,
        120690309131019,
        120690309131008,
        120690302032066,
        120690309131007,
        120690302033047,
        120690309144001,
        120690309131012,
        120690309131009,
        120690309131020,
        120690302033070,
        120690309144007,
        120690309144002,
        120690302033073,
        120690309131018,
        120690309131001,
        120690309131000,
        120690309144006,
        120690302033069,
        120690302033072,
        120690309131016,
        120690309131004,
        120690302033071,
        120690309131005,
        120690309131015,
        120690309144008
    ],
    "zs:housing10":587,
    "zs:label":"Sandy Ridge",
    "zs:pop10":866
},
  "geometry": {"coordinates":[-81.643432,28.822822],"type":"Point"}
}