{
  "type": "Feature",
  "properties": {
    "iso:country":"US",
    "name:eng_x_preferred":[
        "Crabtree Woods"
    ],
    "wof:name":"Crabtree Woods",
    "wof:placetype":"neighbourhood",
    "wof:population":417,
    "zs:area_m":572741.395749,
    "zs:blockids":[
        371830525043005,
        371830525043019,
        371830525043004,
        371830525043031
    ],
    "zs:housing10":281,
    "zs:label":"Crabtree Woods",
    "zs:pop10":417
},
  "geometry": {"coordinates":[-78.690189,35.834962],"type":"Point"}
}