{
  "type": "Feature",
  "properties": {
    "iso:country":"US",
    "name:eng_x_preferred":[
        "Fitzgerald Crossing"
    ],
    "name:eng_x_variant":[
        "Fitzgerald Xing"
    ],
    "qs:gn_local":0,
    "qs:local_max":259,
    "qs:local_sum":259,
    "qs:localhoods":1,
    "qs:name":"Fitzgerald Crossing",
    "qs:name_adm0":"United States",
    "qs:name_adm1":"Arkansas",
    "qs:name_adm2":"Cross",
    "qs:name_local":"Wynne",
    "qs:photo_max":165,
    "qs:photo_sum":259,
    "qs:placetype":"Suburb",
    "qs:quad_count":11,
    "qs:woe_adm0":23424977,
    "qs:woe_adm1":2347562,
    "qs:woe_adm2":12587613,
    "qs:woe_lau":0,
    "qs:woe_local":2524338,
    "qs:woe_ver":"7.10.0",
    "wof:name":"Fitzgerald Crossing",
    "wof:placetype":"neighbourhood",
    "wof:population":444,
    "zs:blockids":[
        50379506001026,
        50379506003019,
        50379506001027,
        50379506003015,
        50379506003017,
        50379506001041,
        50379506003011,
        50379506001010,
        50379506001016,
        50379506001006,
        50379505001074,
        50379506001062,
        50379506001058,
        50379506003042
    ],
    "zs:housing10":169,
    "zs:pop10":444
},
  "geometry": {"coordinates":[-90.782201,35.220551],"type":"Point"}
}