{
  "type": "Feature",
  "properties": {
    "iso:country":"US",
    "name:eng_x_preferred":[
        "Fairfiled"
    ],
    "wof:name":"Fairfiled",
    "wof:placetype":"neighbourhood",
    "wof:population":333,
    "zs:area_m":5878363.341012,
    "zs:blockids":[
        420710145022016,
        420710145022025,
        420710145023012,
        420710145023010,
        420710145022022,
        420710145023014,
        420710145022023,
        420710145023013,
        420710145023011
    ],
    "zs:housing10":93,
    "zs:label":"Fairfiled",
    "zs:pop10":333
},
  "geometry": {"coordinates":[-76.230811,39.788553],"type":"Point"}
}