{
  "type": "Feature",
  "properties": {
    "gn:admin1_code":"MI",
    "gn:admin2_code":"163.0",
    "gn:admin3_code":"77360.0",
    "gn:asciiname":"Martinsville",
    "gn:country_code":"US",
    "gn:dem":201,
    "gn:elevation":"198.0",
    "gn:feature_class":"P",
    "gn:feature_code":"PPL",
    "gn:name":"Martinsville",
    "gn:population":0,
    "gn:timezone":"America/Detroit",
    "iso:country":"US",
    "name:ara_x_preferred":[
        "\u0645\u0627\u0631\u062a\u064a\u0646\u0633\u0641\u064a\u0644"
    ],
    "name:cat_x_preferred":[
        "Martinsville"
    ],
    "name:ceb_x_preferred":[
        "Martinsville"
    ],
    "name:deu_x_preferred":[
        "Martinsville"
    ],
    "name:fra_x_preferred":[
        "Martinsville"
    ],
    "name:ita_x_preferred":[
        "Martinsville"
    ],
    "name:nld_x_preferred":[
        "Martinsville"
    ],
    "name:pol_x_preferred":[
        "Martinsville"
    ],
    "name:rus_x_preferred":[
        "\u041c\u0430\u0440\u0442\u0438\u043d\u0441\u0432\u0438\u043b\u043b"
    ],
    "name:srp_x_preferred":[
        "\u041c\u0430\u0440\u0442\u0438\u043d\u0441\u0432\u0438\u043b"
    ],
    "name:swe_x_preferred":[
        "Martinsville"
    ],
    "name:ukr_x_preferred":[
        "\u041c\u0430\u0440\u0442\u0456\u043d\u0441\u0432\u0456\u043b\u043b"
    ],
    "name:vol_x_preferred":[
        "Martinsville"
    ],
    "wof:name":"Martinsville",
    "wof:placetype":"locality"
},
  "geometry": {"coordinates":[-83.46049000000002,42.14476],"type":"Point"}
}