{
  "type": "Feature",
  "properties": {
    "gn:admin1_code":"MD",
    "gn:admin2_code":"41.0",
    "gn:asciiname":"Holly Oaks",
    "gn:country_code":"US",
    "gn:dem":20,
    "gn:elevation":"19.0",
    "gn:feature_class":"P",
    "gn:feature_code":"PPL",
    "gn:name":"Holly Oaks",
    "gn:population":0,
    "gn:timezone":"America/New_York",
    "iso:country":"US",
    "wof:name":"Holly Oaks",
    "wof:placetype":"locality"
},
  "geometry": {"coordinates":[-76.05716,38.71956],"type":"Point"}
}