{
  "type": "Feature",
  "properties": {
    "gn:admin1_code":"KY",
    "gn:admin2_code":"177.0",
    "gn:asciiname":"Weir",
    "gn:country_code":"US",
    "gn:dem":192,
    "gn:elevation":"192.0",
    "gn:feature_class":"P",
    "gn:feature_code":"PPL",
    "gn:name":"Weir",
    "gn:population":0,
    "gn:timezone":"America/Chicago",
    "iso:country":"US",
    "wof:name":"Weir",
    "wof:placetype":"locality"
},
  "geometry": {"coordinates":[-87.21250000000001,37.1231],"type":"Point"}
}