{
  "type": "Feature",
  "properties": {
    "gn:admin1_code":"MS",
    "gn:admin2_code":"141",
    "gn:asciiname":"Sandy Creek Subdivision",
    "gn:country_code":"US",
    "gn:dem":151,
    "gn:elevation":"139.0",
    "gn:feature_class":"P",
    "gn:feature_code":"PPL",
    "gn:name":"Sandy Creek Subdivision",
    "gn:population":0,
    "gn:timezone":"America/Chicago",
    "iso:country":"US",
    "wof:name":"Sandy Creek Subdivision",
    "wof:placetype":"locality"
},
  "geometry": {"coordinates":[-88.25726,34.99231],"type":"Point"}
}