{
  "type": "Feature",
  "properties": {
    "gn:admin1_code":"GA",
    "gn:admin2_code":"63.0",
    "gn:asciiname":"Lake Tara",
    "gn:country_code":"US",
    "gn:dem":286,
    "gn:elevation":"283.0",
    "gn:feature_class":"P",
    "gn:feature_code":"PPL",
    "gn:name":"Lake Tara",
    "gn:population":0,
    "gn:timezone":"America/New_York",
    "iso:country":"US",
    "wof:name":"Lake Tara",
    "wof:placetype":"locality"
},
  "geometry": {"coordinates":[-84.34992,33.54178],"type":"Point"}
}