{
  "type": "Feature",
  "properties": {
    "gn:elevation":155,
    "iso:country":"US",
    "name:eng_x_preferred":[
        "Colony West"
    ],
    "qs:gn_adm0_cc":"US",
    "qs:gn_fcode":"PPLX",
    "qs:gn_local":4119403,
    "qs:gn_nam_loc":"Little Rock, Pulaski, Arkansas, US",
    "qs:gn_namadm1":"AR",
    "qs:gn_name":"Colony West",
    "qs:local_max":10871,
    "qs:local_sum":36947,
    "qs:localhoods":46,
    "qs:name":"Colony West",
    "qs:name_adm0":"United States",
    "qs:name_adm1":"Arkansas",
    "qs:name_adm2":"Pulaski",
    "qs:name_local":"Little Rock",
    "qs:photo_max":37,
    "qs:photo_sum":150,
    "qs:placetype":"Suburb",
    "qs:quad_count":17,
    "qs:woe_adm0":23424977,
    "qs:woe_adm1":2347562,
    "qs:woe_adm2":12587654,
    "qs:woe_lau":0,
    "qs:woe_local":2440351,
    "qs:woe_ver":"7.10.0",
    "wof:lang":[
        "eng"
    ],
    "wof:name":"Colony West",
    "wof:placetype":"neighbourhood",
    "wof:population":5822,
    "zs:blockids":[
        51190022042005,
        51190022044010,
        51190022042004,
        51190022043004,
        51190022043001,
        51190022045006,
        51190022045004,
        51190022034014,
        51190022034015,
        51190022044004,
        51190021042010,
        51190022034001,
        51190022045015,
        51190022034006,
        51190022045005,
        51190022041012,
        51190022041025,
        51190022043000,
        51190022041031,
        51190022045000,
        51190022044009,
        51190022044011,
        51190022034013,
        51190022032002,
        51190022045013,
        51190049002013,
        51190022044008,
        51190022042000,
        51190022032000,
        51190022045018,
        51190022041008,
        51190022041013,
        51190022042003,
        51190022032003,
        51190022042002,
        51190022044013,
        51190022044007,
        51190022034000,
        51190022043005,
        51190021042011,
        51190022042001,
        51190022041014,
        51190022041033,
        51190022045021,
        51190022041030,
        51190022041034,
        51190022034012,
        51190022034005,
        51190022044006,
        51190022041029,
        51190022041028,
        51190022044005,
        51190022034003,
        51190021042004,
        51190022044003,
        51190022045019,
        51190022045001,
        51190022034002,
        51190022045020,
        51190022045014,
        51190022045017,
        51190022044017,
        51190022045016,
        51190022041032
    ],
    "zs:housing10":2992,
    "zs:pop10":5822
},
  "geometry": {"coordinates":[-92.384496,34.776887],"type":"Point"}
}