{
  "type": "Feature",
  "properties": {
    "iso:country":"US",
    "name:eng_x_preferred":[
        "Beautiful Downtown Orchards"
    ],
    "name:unk_x_variant":[
        "Beautiful Downtown Orchards"
    ],
    "qs:gn_adm0_cc":"US",
    "qs:gn_local":5814616,
    "qs:gn_nam_loc":"Vancouver, Clark, Washington, US",
    "qs:gn_namadm1":"WA",
    "qs:local_max":2037,
    "qs:local_sum":14855,
    "qs:localhoods":74,
    "qs:name":"Beautiful Downtown Orchards",
    "qs:name_adm0":"United States",
    "qs:name_adm1":"Washington",
    "qs:name_adm2":"Clark",
    "qs:name_local":"Vancouver",
    "qs:photo_max":19,
    "qs:photo_sum":68,
    "qs:placetype":"Suburb",
    "qs:quad_count":8,
    "qs:woe_adm0":23424977,
    "qs:woe_adm1":2347606,
    "qs:woe_adm2":12590445,
    "qs:woe_lau":0,
    "qs:woe_local":2511258,
    "qs:woe_ver":"7.10.0",
    "wof:lang":[
        "eng"
    ],
    "wof:name":"Beautiful Downtown Orchards",
    "wof:placetype":"neighbourhood",
    "wof:population":1989,
    "zs:blockids":[
        530110413131013,
        530110413131015,
        530110411042002,
        530110411042007,
        530110413131020,
        530110413131010,
        530110413131009,
        530110413131002,
        530110411042013,
        530110411042015,
        530110411042001,
        530110411042012,
        530110413131007,
        530110413131006,
        530110411042014,
        530110413131005,
        530110407033007,
        530110411042016,
        530110407033008,
        530110413131014,
        530110413131012,
        530110413131004,
        530110413121003,
        530110413131011,
        530110413131019,
        530110413131003,
        530110407034006,
        530110411042017,
        530110413131016,
        530110411042004,
        530110413131021,
        530110407033006
    ],
    "zs:housing10":703,
    "zs:pop10":1989
},
  "geometry": {"coordinates":[-122.56407299999999,45.662299],"type":"Point"}
}