{
  "type": "Feature",
  "properties": {
    "gn:admin1_code":"NY",
    "gn:admin2_code":"3.0",
    "gn:admin3_code":"12243.0",
    "gn:asciiname":"Oramel",
    "gn:country_code":"US",
    "gn:dem":384,
    "gn:elevation":"379.0",
    "gn:feature_class":"P",
    "gn:feature_code":"PPL",
    "gn:name":"Oramel",
    "gn:population":0,
    "gn:timezone":"America/New_York",
    "iso:country":"US",
    "wof:name":"Oramel",
    "wof:placetype":"locality"
},
  "geometry": {"coordinates":[-78.13556,42.36618],"type":"Point"}
}