{
  "type": "Feature",
  "properties": {
    "gn:admin1_code":"WV",
    "gn:admin2_code":"45.0",
    "gn:asciiname":"Phico",
    "gn:country_code":"US",
    "gn:dem":204,
    "gn:elevation":"202.0",
    "gn:feature_class":"P",
    "gn:feature_code":"PPL",
    "gn:name":"Phico",
    "gn:population":0,
    "gn:timezone":"America/New_York",
    "iso:country":"US",
    "wof:name":"Phico",
    "wof:placetype":"locality"
},
  "geometry": {"coordinates":[-82.01402,37.95066],"type":"Point"}
}