{
  "type": "Feature",
  "properties": {
    "iso:country":"US",
    "name:eng_x_preferred":[
        "Westmont Terrace"
    ],
    "wof:name":"Westmont Terrace",
    "wof:placetype":"neighbourhood",
    "wof:population":46,
    "zs:area_m":48892.002298,
    "zs:blockids":[
        120570068022024,
        120570068014000
    ],
    "zs:housing10":26,
    "zs:label":"Westmont Terrace",
    "zs:pop10":46
},
  "geometry": {"coordinates":[-82.49422800000001,27.887643],"type":"Point"}
}