{
  "type": "Feature",
  "properties": {
    "gn:admin1_code":"KY",
    "gn:admin2_code":"209",
    "gn:asciiname":"Turkey Foot",
    "gn:country_code":"US",
    "gn:dem":260,
    "gn:elevation":"256.0",
    "gn:feature_class":"P",
    "gn:feature_code":"PPL",
    "gn:name":"Turkey Foot",
    "gn:population":0,
    "gn:timezone":"America/New_York",
    "iso:country":"US",
    "wof:name":"Turkey Foot",
    "wof:placetype":"locality"
},
  "geometry": {"coordinates":[-84.51105,38.33841],"type":"Point"}
}