{
  "type": "Feature",
  "properties": {
    "gn:admin1_code":"TX",
    "gn:admin2_code":"203.0",
    "gn:asciiname":"South Shore",
    "gn:country_code":"US",
    "gn:dem":62,
    "gn:elevation":"52.0",
    "gn:feature_class":"P",
    "gn:feature_code":"PPL",
    "gn:name":"South Shore",
    "gn:population":0,
    "gn:timezone":"America/Chicago",
    "iso:country":"US",
    "name:ceb_x_preferred":[
        "South Shore"
    ],
    "name:deu_x_preferred":[
        "South Shore"
    ],
    "name:fra_x_preferred":[
        "South Shore"
    ],
    "name:ita_x_preferred":[
        "South Shore"
    ],
    "name:nld_x_preferred":[
        "South Shore"
    ],
    "name:pol_x_preferred":[
        "South Shore"
    ],
    "name:por_x_preferred":[
        "South Shore"
    ],
    "name:srp_x_preferred":[
        "\u0421\u0430\u0443\u0442 \u0428\u043e\u0440"
    ],
    "name:swe_x_preferred":[
        "South Shore"
    ],
    "name:urd_x_preferred":[
        "\u0633\u0627\u0648\u062a\u06be \u0634\u0648\u0631"
    ],
    "name:vol_x_preferred":[
        "South Shore"
    ],
    "wof:name":"South Shore",
    "wof:placetype":"locality"
},
  "geometry": {"coordinates":[-94.08296,32.67015],"type":"Point"}
}