{
  "type": "Feature",
  "properties": {
    "gn:admin1_code":"OH",
    "gn:admin2_code":"167",
    "gn:admin3_code":"47642.0",
    "gn:asciiname":"Sandhill",
    "gn:country_code":"US",
    "gn:dem":219,
    "gn:elevation":"220.0",
    "gn:feature_class":"P",
    "gn:feature_code":"PPL",
    "gn:name":"Sandhill",
    "gn:population":0,
    "gn:timezone":"America/New_York",
    "iso:country":"US",
    "name:eng_x_preferred":[
        "Sandhill"
    ],
    "name:und_x_variant":[
        "Sand Hill"
    ],
    "wof:name":"Sandhill",
    "wof:placetype":"locality"
},
  "geometry": {"coordinates":[-81.38762,39.37896],"type":"Point"}
}