{
  "type": "Feature",
  "properties": {
    "gn:gn_country":"US",
    "gn:gn_fcode":"PPLX",
    "gn:gn_pop":0,
    "iso:country":"US",
    "name:ceb_x_preferred":[
        "Meadowbrook"
    ],
    "name:deu_x_preferred":[
        "Meadowbrook"
    ],
    "name:ita_x_preferred":[
        "Meadowbrook"
    ],
    "name:pol_x_preferred":[
        "Meadowbrook"
    ],
    "name:por_x_preferred":[
        "Meadowbrook"
    ],
    "name:srp_x_preferred":[
        "\u041c\u0435\u0434\u043e\u0443\u0431\u0440\u0443\u043a"
    ],
    "name:ukr_x_preferred":[
        "\u041c\u0456\u0434\u043e\u0432\u0431\u0440\u0443\u043a"
    ],
    "qs_pg:aaroncc":"US",
    "qs_pg:gn_country":"US",
    "qs_pg:gn_fcode":"PPLX",
    "qs_pg:gn_pop":0,
    "qs_pg:name":"Meadowbrook",
    "qs_pg:name_adm0":"United States",
    "qs_pg:name_adm1":"North Carolina",
    "qs_pg:photos":3,
    "qs_pg:photos_1k":1,
    "qs_pg:photos_9k":1,
    "qs_pg:photos_9r":1,
    "qs_pg:photos_all":3,
    "qs_pg:photos_sr":1,
    "qs_pg:pop_sr":0,
    "qs_pg:qs_pg_placetype":"neighbourhood",
    "qs_pg:qs_pg_placetype_gp":"Suburb",
    "qs_pg:woe_adm0":23424977,
    "woe:adm0_id":23424977,
    "woe:name_adm0":"United States",
    "woe:name_adm1":"North Carolina",
    "woe:placetype":"Suburb",
    "wof:name":"Meadowbrook",
    "wof:placetype":"neighbourhood"
},
  "geometry": {"coordinates":[-80.49562,35.69208],"type":"Point"}
}