{
  "type": "Feature",
  "properties": {
    "gn:admin1_code":"NM",
    "gn:admin2_code":"55.0",
    "gn:asciiname":"Twining",
    "gn:country_code":"US",
    "gn:dem":2876,
    "gn:elevation":"2874.0",
    "gn:feature_class":"P",
    "gn:feature_code":"PPL",
    "gn:name":"Twining",
    "gn:population":0,
    "gn:timezone":"America/Denver",
    "iso:country":"US",
    "name:deu_x_preferred":[
        "Twining"
    ],
    "name:jpn_x_preferred":[
        "\u30c8\u30ef\u30a4\u30cb\u30f3\u30b0"
    ],
    "wof:name":"Twining",
    "wof:placetype":"locality"
},
  "geometry": {"coordinates":[-105.45028000000001,36.59475],"type":"Point"}
}