{
  "type": "Feature",
  "properties": {
    "gn:country":"US",
    "gn:fcode":"PPL",
    "gn:population":110,
    "iso:country":"US",
    "name:ara_x_preferred":[
        "\u063a\u0631\u0627\u0633 \u0631\u0627\u0646\u062c"
    ],
    "name:arz_x_preferred":[
        "\u062c\u0631\u0627\u0633 \u0631\u0627\u0646\u062c"
    ],
    "name:azb_x_preferred":[
        "\u0642\u0631\u0627\u0633 \u0631\u0627\u0646\u062c"
    ],
    "name:cat_x_preferred":[
        "Grass Range"
    ],
    "name:ceb_x_preferred":[
        "Grass Range"
    ],
    "name:che_x_preferred":[
        "\u0413\u0440\u0430\u0441\u0441-\u0420\u0435\u0439\u043d\u0434\u0436"
    ],
    "name:deu_x_preferred":[
        "Grass Range"
    ],
    "name:eng_x_preferred":[
        "Grass Range"
    ],
    "name:eus_x_preferred":[
        "Grass Range"
    ],
    "name:fas_x_preferred":[
        "\u06af\u0631\u0633 \u0631\u06cc\u0646\u062c\u060c \u0645\u0648\u0646\u062a\u0627\u0646\u0627"
    ],
    "name:fas_x_variant":[
        "\u06af\u0631\u0633 \u0631\u06cc\u0646\u062c"
    ],
    "name:fra_x_preferred":[
        "Grass Range"
    ],
    "name:hat_x_preferred":[
        "Grass Range"
    ],
    "name:hun_x_preferred":[
        "Grass Range"
    ],
    "name:ita_x_preferred":[
        "Grass Range"
    ],
    "name:kaz_x_preferred":[
        "\u0413\u0440\u0430\u0441\u0441 \u0420\u0435\u0439\u043d\u0434\u0436"
    ],
    "name:kir_x_preferred":[
        "\u0413\u0440\u0430\u0441\u0441 \u0420\u0435\u0439\u043d\u0434\u0436"
    ],
    "name:lld_x_preferred":[
        "Grass Range"
    ],
    "name:nan_x_preferred":[
        "Grass Range"
    ],
    "name:nld_x_preferred":[
        "Grass Range"
    ],
    "name:pol_x_preferred":[
        "Grass Range"
    ],
    "name:por_x_preferred":[
        "Grass Range"
    ],
    "name:spa_x_preferred":[
        "Grass Range"
    ],
    "name:srp_x_preferred":[
        "\u0413\u0440\u0430\u0441 \u0420\u0435\u0458\u043d\u045f"
    ],
    "name:tat_x_preferred":[
        "\u0413\u0440\u0430\u0441\u0441-\u0420\u0435\u0439\u043d\u0434\u0436"
    ],
    "name:ukr_x_preferred":[
        "\u0413\u0440\u0430\u0441\u0441-\u0420\u0435\u0439\u043d\u0434\u0436"
    ],
    "name:uzb_x_preferred":[
        "Grass Range"
    ],
    "name:vol_x_preferred":[
        "Grass Range"
    ],
    "name:war_x_preferred":[
        "Grass Range"
    ],
    "name:zho_x_preferred":[
        "\u683c\u62c9\u65af\u5170\u6cbb"
    ],
    "qs_pg:aaroncc":"US",
    "qs_pg:gn_country":"US",
    "qs_pg:gn_fcode":"PPL",
    "qs_pg:gn_pop":110,
    "qs_pg:name":"Grassrange",
    "qs_pg:name_adm0":"United States",
    "qs_pg:name_adm1":"Montana",
    "qs_pg:photos":75,
    "qs_pg:photos_1k":15,
    "qs_pg:photos_9k":1,
    "qs_pg:photos_9r":2,
    "qs_pg:photos_all":75,
    "qs_pg:photos_sr":2,
    "qs_pg:pop_sr":1,
    "qs_pg:qs_pg_placetype":"locality",
    "qs_pg:qs_pg_placetype_gp":"Town",
    "qs_pg:woe_adm0":23424977,
    "woe:adm0_id":23424977,
    "woe:name_adm0":"United States",
    "woe:name_adm1":"Montana",
    "woe:placetype":"Town",
    "wof:name":"Grassrange",
    "wof:placetype":"locality",
    "wof:population":110
},
  "geometry": {"coordinates":[-108.80459,47.02608],"type":"Point"}
}