{
  "type": "Feature",
  "properties": {
    "gn:admin1_code":"FL",
    "gn:admin2_code":"71.0",
    "gn:asciiname":"Poinciana Estates",
    "gn:country_code":"US",
    "gn:dem":10,
    "gn:elevation":"3.0",
    "gn:feature_class":"P",
    "gn:feature_code":"PPL",
    "gn:name":"Poinciana Estates",
    "gn:population":0,
    "gn:timezone":"America/New_York",
    "iso:country":"US",
    "wof:name":"Poinciana Estates",
    "wof:placetype":"locality"
},
  "geometry": {"coordinates":[-81.85111999999999,26.70169000000001],"type":"Point"}
}