{
  "type": "Feature",
  "properties": {
    "gn:admin1_code":"CO",
    "gn:admin2_code":"69.0",
    "gn:asciiname":"Glen Comfort",
    "gn:country_code":"US",
    "gn:dem":2199,
    "gn:elevation":"2189.0",
    "gn:feature_class":"P",
    "gn:feature_code":"PPL",
    "gn:name":"Glen Comfort",
    "gn:population":0,
    "gn:timezone":"America/Denver",
    "iso:country":"US",
    "wof:name":"Glen Comfort",
    "wof:placetype":"locality"
},
  "geometry": {"coordinates":[-105.44027,40.39359],"type":"Point"}
}