{
  "type": "Feature",
  "properties": {
    "gn:admin1_code":"WV",
    "gn:admin2_code":"37",
    "gn:asciiname":"Aldridge",
    "gn:country_code":"US",
    "gn:dem":171,
    "gn:elevation":"168.0",
    "gn:feature_class":"P",
    "gn:feature_code":"PPL",
    "gn:name":"Aldridge",
    "gn:population":0,
    "gn:timezone":"America/New_York",
    "iso:country":"US",
    "name:ceb_x_preferred":[
        "Aldridge"
    ],
    "name:eng_x_preferred":[
        "Aldridge"
    ],
    "name:gle_x_preferred":[
        "Aldridge"
    ],
    "name:ita_x_preferred":[
        "Aldridge"
    ],
    "name:lit_x_preferred":[
        "Oldrid\u017eas"
    ],
    "name:nld_x_preferred":[
        "Aldridge"
    ],
    "name:nno_x_preferred":[
        "Aldridge"
    ],
    "name:pol_x_preferred":[
        "Aldridge"
    ],
    "name:ron_x_preferred":[
        "Aldridge"
    ],
    "name:spa_x_preferred":[
        "Aldridge"
    ],
    "name:swe_x_preferred":[
        "Aldridge"
    ],
    "name:und_x_variant":[
        "Aldridges",
        "Camerons Depot"
    ],
    "name:zho_x_preferred":[
        "\u5967\u723e\u5fb7\u91cc\u5947"
    ],
    "wof:name":"Aldridge",
    "wof:placetype":"locality"
},
  "geometry": {"coordinates":[-77.9225,39.30121],"type":"Point"}
}