{
  "type": "Feature",
  "properties": {
    "gn:admin1_code":"NY",
    "gn:admin2_code":"73.0",
    "gn:admin3_code":"12496.0",
    "gn:asciiname":"Toms Landing",
    "gn:country_code":"US",
    "gn:dem":93,
    "gn:elevation":"79.0",
    "gn:feature_class":"P",
    "gn:feature_code":"PPL",
    "gn:name":"Toms Landing",
    "gn:population":0,
    "gn:timezone":"America/New_York",
    "iso:country":"US",
    "wof:name":"Toms Landing",
    "wof:placetype":"locality"
},
  "geometry": {"coordinates":[-78.22363,43.34089],"type":"Point"}
}