{
  "type": "Feature",
  "properties": {
    "gn:admin1_code":"PA",
    "gn:admin2_code":"5.0",
    "gn:admin3_code":"46632.0",
    "gn:asciiname":"Mahoning Furnace",
    "gn:country_code":"US",
    "gn:dem":280,
    "gn:elevation":"268.0",
    "gn:feature_class":"P",
    "gn:feature_code":"PPL",
    "gn:name":"Mahoning Furnace",
    "gn:population":0,
    "gn:timezone":"America/New_York",
    "iso:country":"US",
    "wof:name":"Mahoning Furnace",
    "wof:placetype":"locality"
},
  "geometry": {"coordinates":[-79.36421,40.9459],"type":"Point"}
}