{
  "type": "Feature",
  "properties": {
    "iso:country":"US",
    "name:eng_x_preferred":[
        "Imperial Forest"
    ],
    "wof:name":"Imperial Forest",
    "wof:placetype":"neighbourhood",
    "wof:population":2242,
    "zs:area_m":2823966.930397,
    "zs:blockids":[
        10730144041087,
        10730144041089,
        10730144041081,
        10730144041063,
        10730107063040,
        10730144041076,
        10730144052049,
        10730144041086,
        10730144041088,
        10730144041066,
        10730144041077,
        10730144041082,
        10730144041085,
        10730144051004,
        10730144051000,
        10730144041080,
        10730144041083,
        10730144052009,
        10730107063038,
        10730144052048,
        10730144052010,
        10730144051003,
        10730144052008,
        10730144041078,
        10730144041084,
        10730144051001,
        10730144041067,
        10730144051002,
        10730144041068,
        10730144041079
    ],
    "zs:housing10":921,
    "zs:label":"Imperial Forest",
    "zs:pop10":2242
},
  "geometry": {"coordinates":[-86.834693,33.429481],"type":"Point"}
}