{
  "type": "Feature",
  "properties": {
    "gn:admin1_code":"OR",
    "gn:admin2_code":"25.0",
    "gn:asciiname":"Modesto",
    "gn:country_code":"US",
    "gn:dem":1390,
    "gn:feature_class":"P",
    "gn:feature_code":"PPL",
    "gn:name":"Modesto",
    "gn:population":0,
    "gn:timezone":"America/Los_Angeles",
    "iso:country":"US",
    "wof:name":"Modesto",
    "wof:placetype":"locality"
},
  "geometry": {"coordinates":[-118.80135,42.04765],"type":"Point"}
}