{
  "type": "Feature",
  "properties": {
    "gn:admin1_code":"WI",
    "gn:admin2_code":"3.0",
    "gn:admin3_code":"50700.0",
    "gn:asciiname":"Tannery Town",
    "gn:country_code":"US",
    "gn:dem":377,
    "gn:elevation":"380.0",
    "gn:feature_class":"P",
    "gn:feature_code":"PPL",
    "gn:name":"Tannery Town",
    "gn:population":0,
    "gn:timezone":"America/Chicago",
    "iso:country":"US",
    "wof:name":"Tannery Town",
    "wof:placetype":"locality"
},
  "geometry": {"coordinates":[-90.65379,46.31912],"type":"Point"}
}