{
  "type": "Feature",
  "properties": {
    "gn:admin1_code":"VT",
    "gn:admin2_code":"1.0",
    "gn:admin3_code":"29575.0",
    "gn:asciiname":"Lower Granville",
    "gn:country_code":"US",
    "gn:dem":293,
    "gn:elevation":"294.0",
    "gn:feature_class":"P",
    "gn:feature_code":"PPL",
    "gn:name":"Lower Granville",
    "gn:population":0,
    "gn:timezone":"America/New_York",
    "iso:country":"US",
    "name:eng_x_preferred":[
        "Lower Granville"
    ],
    "name:und_x_variant":[
        "Granville Center"
    ],
    "wof:name":"Lower Granville",
    "wof:placetype":"locality"
},
  "geometry": {"coordinates":[-72.84289,43.9684],"type":"Point"}
}