{
  "type": "Feature",
  "properties": {
    "gn:admin1_code":"PA",
    "gn:admin2_code":"91",
    "gn:admin3_code":"86496.0",
    "gn:asciiname":"Abruzzi Estates",
    "gn:country_code":"US",
    "gn:dem":133,
    "gn:elevation":"133.0",
    "gn:feature_class":"P",
    "gn:feature_code":"PPL",
    "gn:name":"Abruzzi Estates",
    "gn:population":0,
    "gn:timezone":"America/New_York",
    "iso:country":"US",
    "wof:name":"Abruzzi Estates",
    "wof:placetype":"locality"
},
  "geometry": {"coordinates":[-75.38809999999999,40.165],"type":"Point"}
}