{
  "type": "Feature",
  "properties": {
    "gn:admin1_code":"NY",
    "gn:admin2_code":"63",
    "gn:admin3_code":"59267.0",
    "gn:asciiname":"Tryonville",
    "gn:country_code":"US",
    "gn:dem":93,
    "gn:elevation":"91.0",
    "gn:feature_class":"P",
    "gn:feature_code":"PPL",
    "gn:name":"Tryonville",
    "gn:population":0,
    "gn:timezone":"America/New_York",
    "iso:country":"US",
    "wof:name":"Tryonville",
    "wof:placetype":"locality"
},
  "geometry": {"coordinates":[-78.95333000000002,43.26333],"type":"Point"}
}