{
  "type": "Feature",
  "properties": {
    "gn:elevation":25,
    "iso:country":"US",
    "name:eng_x_preferred":[
        "Point of Woods"
    ],
    "qs:gn_adm0_cc":"US",
    "qs:gn_fcode":"PPL",
    "qs:gn_local":4501198,
    "qs:gn_nam_loc":"cherry hill",
    "qs:gn_namadm1":"NJ",
    "qs:gn_name":"Point of Woods",
    "qs:local_max":395,
    "qs:local_sum":1706,
    "qs:localhoods":14,
    "qs:name":"Point of Woods",
    "qs:name_adm0":"United States",
    "qs:name_adm1":"New Jersey",
    "qs:name_adm2":"Camden",
    "qs:name_local":"Cherry Hill",
    "qs:photo_max":19,
    "qs:photo_sum":58,
    "qs:placetype":"Suburb",
    "qs:quad_count":10,
    "qs:woe_adm0":23424977,
    "qs:woe_adm1":2347589,
    "qs:woe_adm2":12589261,
    "qs:woe_lau":0,
    "qs:woe_local":2379079,
    "qs:woe_ver":"7.10.0",
    "wd:wordcount":905,
    "wof:lang":[
        "eng"
    ],
    "wof:name":"Point of Woods",
    "wof:placetype":"neighbourhood",
    "wof:population":1032,
    "zs:blockids":[
        340057040042006,
        340057029061082,
        340057040051003,
        340057040051006,
        340057029061084,
        340057029061083,
        340057029061085,
        340057040051000,
        340057040051008,
        340057029061073,
        340057029061076,
        340057040051002,
        340057040051004,
        340057040051001
    ],
    "zs:housing10":501,
    "zs:pop10":1032
},
  "geometry": {"coordinates":[-74.948914,39.918302],"type":"Point"}
}