{
  "type": "Feature",
  "properties": {
    "gn:admin1_code":"MT",
    "gn:admin2_code":"43.0",
    "gn:asciiname":"Clasoil",
    "gn:country_code":"US",
    "gn:dem":1256,
    "gn:elevation":"1259.0",
    "gn:feature_class":"P",
    "gn:feature_code":"PPL",
    "gn:name":"Clasoil",
    "gn:population":0,
    "gn:timezone":"America/Denver",
    "iso:country":"US",
    "wof:name":"Clasoil",
    "wof:placetype":"locality"
},
  "geometry": {"coordinates":[-111.79358999999999,46.56299],"type":"Point"}
}