{
  "type": "Feature",
  "properties": {
    "iso:country":"US",
    "name:dan_x_preferred":[
        "Trongisv\u00e1gur"
    ],
    "name:deu_x_preferred":[
        "Trongisv\u00e1gur"
    ],
    "name:eng_x_preferred":[
        "Summertimes Plantation"
    ],
    "name:epo_x_preferred":[
        "Trongisv\u00e1gur"
    ],
    "name:fao_x_preferred":[
        "Trongisv\u00e1gur"
    ],
    "name:glv_x_preferred":[
        "Trongisv\u00e1gur"
    ],
    "name:hun_x_preferred":[
        "Trongisv\u00e1gur"
    ],
    "name:kal_x_preferred":[
        "Trongisv\u00e1gur"
    ],
    "name:lit_x_preferred":[
        "Trongisvaguras"
    ],
    "name:nld_x_preferred":[
        "Trongisv\u00e1gur"
    ],
    "name:nor_x_preferred":[
        "Trongisv\u00e1gur"
    ],
    "wof:name":"Summertimes Plantation",
    "wof:placetype":"neighbourhood",
    "zs:area_m":9745778.860412,
    "zs:blockids":[
        121050147022032,
        121050147022044
    ],
    "zs:housing10":0,
    "zs:label":"Summertimes Plantation",
    "zs:pop10":0
},
  "geometry": {"coordinates":[-81.829932,27.963152],"type":"Point"}
}