{
  "type": "Feature",
  "properties": {
    "iso:country":"US",
    "name:eng_x_preferred":[
        "Signal Hills"
    ],
    "wd:wordcount":33,
    "wof:name":"Signal Hills",
    "wof:placetype":"neighbourhood",
    "zs:area_m":73503.836917,
    "zs:blockids":[
        470650109021051,
        470650109021043
    ],
    "zs:housing10":0,
    "zs:label":"Signal Hills",
    "zs:pop10":0
},
  "geometry": {"coordinates":[-85.328603,35.097458],"type":"Point"}
}