{
  "type": "Feature",
  "properties": {
    "gn:admin1_code":"VA",
    "gn:admin2_code":"187",
    "gn:asciiname":"Dungadin Heights",
    "gn:country_code":"US",
    "gn:dem":226,
    "gn:elevation":"224.0",
    "gn:feature_class":"P",
    "gn:feature_code":"PPL",
    "gn:name":"Dungadin Heights",
    "gn:population":0,
    "gn:timezone":"America/New_York",
    "iso:country":"US",
    "wof:name":"Dungadin Heights",
    "wof:placetype":"locality"
},
  "geometry": {"coordinates":[-78.23028000000002,38.88817],"type":"Point"}
}