{
  "type": "Feature",
  "properties": {
    "gn:admin1_code":"CT",
    "gn:admin2_code":"15.0",
    "gn:admin3_code":"88190.0",
    "gn:asciiname":"Woodstock Valley",
    "gn:country_code":"US",
    "gn:dem":183,
    "gn:elevation":"182.0",
    "gn:feature_class":"P",
    "gn:feature_code":"PPL",
    "gn:name":"Woodstock Valley",
    "gn:population":0,
    "gn:timezone":"America/New_York",
    "iso:country":"US",
    "wof:name":"Woodstock Valley",
    "wof:placetype":"locality"
},
  "geometry": {"coordinates":[-72.07174000000001,41.94093],"type":"Point"}
}