{
  "type": "Feature",
  "properties": {
    "gn:admin1_code":"AR",
    "gn:admin2_code":"31.0",
    "gn:admin3_code":"92004.0",
    "gn:asciiname":"Herman",
    "gn:country_code":"US",
    "gn:dem":92,
    "gn:elevation":"92.0",
    "gn:feature_class":"P",
    "gn:feature_code":"PPL",
    "gn:name":"Herman",
    "gn:population":0,
    "gn:timezone":"America/Chicago",
    "iso:country":"US",
    "name:ara_x_preferred":[
        "\u0647\u064a\u0631\u0645\u0627\u0646"
    ],
    "name:ceb_x_preferred":[
        "Herman"
    ],
    "name:deu_x_preferred":[
        "Herman"
    ],
    "name:est_x_preferred":[
        "Herman"
    ],
    "name:fra_x_preferred":[
        "Herman"
    ],
    "name:heb_x_preferred":[
        "\u05d4\u05e8\u05de\u05df"
    ],
    "name:hsb_x_preferred":[
        "Herman"
    ],
    "name:ita_x_preferred":[
        "Herman"
    ],
    "name:jpn_x_preferred":[
        "\u30cf\u30fc\u30de\u30f3"
    ],
    "name:lav_x_preferred":[
        "Hermanis"
    ],
    "name:nld_x_preferred":[
        "Herman"
    ],
    "name:nor_x_preferred":[
        "Herman"
    ],
    "name:pol_x_preferred":[
        "Herman"
    ],
    "name:por_x_preferred":[
        "Herman"
    ],
    "name:rus_x_preferred":[
        "\u0425\u0435\u0440\u043c\u0430\u043d"
    ],
    "name:slv_x_preferred":[
        "Herman"
    ],
    "name:spa_x_preferred":[
        "Herman"
    ],
    "name:srp_x_preferred":[
        "\u0425\u0435\u0440\u043c\u0430\u043d"
    ],
    "name:swe_x_preferred":[
        "Herman"
    ],
    "name:vls_x_preferred":[
        "Herman"
    ],
    "name:vol_x_preferred":[
        "Herman"
    ],
    "name:zho_x_preferred":[
        "\u8d6b\u5c14\u66fc"
    ],
    "wof:name":"Herman",
    "wof:placetype":"locality"
},
  "geometry": {"coordinates":[-90.8015,35.85369],"type":"Point"}
}