{
  "type": "Feature",
  "properties": {
    "gn:admin1_code":"NY",
    "gn:admin2_code":"83.0",
    "gn:admin3_code":"65013.0",
    "gn:asciiname":"West Sand Lake",
    "gn:country_code":"US",
    "gn:dem":161,
    "gn:elevation":"160.0",
    "gn:feature_class":"P",
    "gn:feature_code":"PPL",
    "gn:name":"West Sand Lake",
    "gn:population":2660,
    "gn:timezone":"America/New_York",
    "iso:country":"US",
    "name:azb_x_preferred":[
        "\u0648\u0633\u062a \u0627\u0633\u062a\u0646\u062f \u0644\u06cc\u06a9"
    ],
    "name:cat_x_preferred":[
        "West Sand Lake"
    ],
    "name:ceb_x_preferred":[
        "West Sand Lake"
    ],
    "name:eng_x_preferred":[
        "West Sand Lake"
    ],
    "name:fas_x_preferred":[
        "\u0648\u0633\u062a \u0627\u0633\u062a\u0646\u062f \u0644\u06cc\u06a9"
    ],
    "name:mlg_x_preferred":[
        "West Sand Lake"
    ],
    "name:pol_x_preferred":[
        "West Sand Lake"
    ],
    "name:spa_x_preferred":[
        "West Sand Lake"
    ],
    "name:srp_x_preferred":[
        "\u0412\u0435\u0441\u0442 \u0421\u0435\u043d\u0434 \u041b\u0435\u0458\u043a"
    ],
    "name:und_x_variant":[
        "Ulinesville",
        "West Sandlake"
    ],
    "name:vol_x_preferred":[
        "West Sand Lake"
    ],
    "wof:name":"West Sand Lake",
    "wof:placetype":"locality",
    "wof:population":2660
},
  "geometry": {"coordinates":[-73.60873000000002,42.64341],"type":"Point"}
}