{
  "type": "Feature",
  "properties": {
    "gn:admin1_code":"PA",
    "gn:admin2_code":"121.0",
    "gn:admin3_code":"27832.0",
    "gn:asciiname":"Mapledale",
    "gn:country_code":"US",
    "gn:dem":450,
    "gn:elevation":"448.0",
    "gn:feature_class":"P",
    "gn:feature_code":"PPL",
    "gn:name":"Mapledale",
    "gn:population":0,
    "gn:timezone":"America/New_York",
    "iso:country":"US",
    "wof:name":"Mapledale",
    "wof:placetype":"locality"
},
  "geometry": {"coordinates":[-79.86089,41.38422],"type":"Point"}
}