{
  "type": "Feature",
  "properties": {
    "gn:gn_country":"US",
    "gn:gn_fcode":"PPL",
    "gn:gn_pop":0,
    "iso:country":"US",
    "name:cat_x_preferred":[
        "Manuelito"
    ],
    "name:deu_x_preferred":[
        "Manuelito"
    ],
    "name:eng_x_preferred":[
        "Manuelito"
    ],
    "name:fra_x_preferred":[
        "Manuelito"
    ],
    "name:glg_x_preferred":[
        "Manuelito"
    ],
    "name:ita_x_preferred":[
        "Manuelito"
    ],
    "name:pol_x_preferred":[
        "Manuelito"
    ],
    "name:por_x_preferred":[
        "Manuelito"
    ],
    "name:spa_x_preferred":[
        "Manuelito"
    ],
    "name:tur_x_preferred":[
        "Manuelito"
    ],
    "name:unk_x_variant":[
        "Cooks Ranch"
    ],
    "qs_pg:aaroncc":"US",
    "qs_pg:gn_country":"US",
    "qs_pg:gn_fcode":"PPL",
    "qs_pg:gn_pop":0,
    "qs_pg:name":"Manuelito",
    "qs_pg:name_adm0":"United States",
    "qs_pg:name_adm1":"New Mexico",
    "qs_pg:photos":127,
    "qs_pg:photos_1k":26,
    "qs_pg:photos_9k":1,
    "qs_pg:photos_9r":3,
    "qs_pg:photos_all":127,
    "qs_pg:photos_sr":3,
    "qs_pg:pop_sr":5,
    "qs_pg:qs_pg_placetype":"locality",
    "qs_pg:qs_pg_placetype_gp":"Town",
    "qs_pg:woe_adm0":23424977,
    "woe:adm0_id":23424977,
    "woe:name_adm0":"United States",
    "woe:name_adm1":"New Mexico",
    "woe:placetype":"Town",
    "wof:name":"Manuelito",
    "wof:placetype":"locality"
},
  "geometry": {"coordinates":[-108.99397999999999,35.42197],"type":"Point"}
}