{
  "type": "Feature",
  "properties": {
    "gn:admin1_code":"NC",
    "gn:admin2_code":"115.0",
    "gn:asciiname":"Luck",
    "gn:country_code":"US",
    "gn:dem":797,
    "gn:elevation":"780.0",
    "gn:feature_class":"P",
    "gn:feature_code":"PPL",
    "gn:name":"Luck",
    "gn:population":0,
    "gn:timezone":"America/New_York",
    "iso:country":"US",
    "wof:name":"Luck",
    "wof:placetype":"locality"
},
  "geometry": {"coordinates":[-82.86624999999999,35.73594],"type":"Point"}
}