{
  "type": "Feature",
  "properties": {
    "gn:country":"US",
    "gn:fcode":"PPL",
    "gn:population":0,
    "iso:country":"US",
    "name:eng_x_preferred":[
        "Stanton"
    ],
    "name:fra_x_preferred":[
        "Stanton"
    ],
    "name:jpn_x_preferred":[
        "\u30b9\u30bf\u30f3\u30c8\u30f3"
    ],
    "qs_pg:aaroncc":"US",
    "qs_pg:gn_country":"US",
    "qs_pg:gn_fcode":"PPL",
    "qs_pg:gn_pop":0,
    "qs_pg:name":"Stanton",
    "qs_pg:name_adm0":"United States",
    "qs_pg:name_adm1":"Mississippi",
    "qs_pg:photos":242,
    "qs_pg:photos_1k":49,
    "qs_pg:photos_9k":1,
    "qs_pg:photos_9r":4,
    "qs_pg:photos_all":242,
    "qs_pg:photos_sr":4,
    "qs_pg:pop_sr":5,
    "qs_pg:qs_pg_placetype":"locality",
    "qs_pg:qs_pg_placetype_gp":"Town",
    "qs_pg:woe_adm0":23424977,
    "woe:adm0_id":23424977,
    "woe:name_adm0":"United States",
    "woe:name_adm1":"Mississippi",
    "woe:placetype":"Town",
    "wof:name":"Stanton",
    "wof:placetype":"locality"
},
  "geometry": {"coordinates":[-91.24039,31.616],"type":"Point"}
}