{
  "type": "Feature",
  "properties": {
    "iso:country":"US",
    "name:eng_x_preferred":[
        "Knauertown"
    ],
    "name:fra_x_preferred":[
        "Knauertown"
    ],
    "qs:gn_adm0_cc":"US",
    "qs:gn_fcode":"PPL",
    "qs:gn_local":5218046,
    "qs:gn_nam_loc":"warwick",
    "qs:gn_namadm1":"PA",
    "qs:gn_name":"Knauertown",
    "qs:local_max":365,
    "qs:local_sum":525,
    "qs:localhoods":3,
    "qs:name":"Knauertown",
    "qs:name_adm0":"United States",
    "qs:name_adm1":"Pennsylvania",
    "qs:name_adm2":"Chester",
    "qs:name_local":"Warwick",
    "qs:photo_max":30,
    "qs:photo_sum":144,
    "qs:placetype":"Suburb",
    "qs:quad_count":11,
    "qs:woe_adm0":23424977,
    "qs:woe_adm1":2347597,
    "qs:woe_adm2":12589742,
    "qs:woe_lau":0,
    "qs:woe_local":2514526,
    "qs:woe_ver":"7.10.0",
    "wd:wordcount":88,
    "wof:lang":[
        "eng"
    ],
    "wof:name":"Knauertown",
    "wof:placetype":"neighbourhood",
    "wof:population":701,
    "zs:blockids":[
        420293016001032,
        420293016001094,
        420293016001058,
        420293016001066,
        420293016001090,
        420293016001059,
        420293016001052,
        420293016001030,
        420293016001093,
        420293016001048,
        420293016001049,
        420293016001060,
        420293016001028,
        420293016001029,
        420293016001034,
        420293016001033,
        420293016001047
    ],
    "zs:housing10":303,
    "zs:pop10":701
},
  "geometry": {"coordinates":[-75.73181200000001,40.177301],"type":"Point"}
}