{
  "type": "Feature",
  "properties": {
    "gn:admin1_code":"PA",
    "gn:admin2_code":"17.0",
    "gn:admin3_code":"21760.0",
    "gn:asciiname":"Smoketown",
    "gn:country_code":"US",
    "gn:dem":184,
    "gn:elevation":"176.0",
    "gn:feature_class":"P",
    "gn:feature_code":"PPL",
    "gn:name":"Smoketown",
    "gn:population":0,
    "gn:timezone":"America/New_York",
    "iso:country":"US",
    "wof:name":"Smoketown",
    "wof:placetype":"locality"
},
  "geometry": {"coordinates":[-75.32795,40.39844],"type":"Point"}
}