{
  "type": "Feature",
  "properties": {
    "gn:admin1_code":"MD",
    "gn:admin2_code":"3.0",
    "gn:asciiname":"Saint Stephens Estates",
    "gn:country_code":"US",
    "gn:dem":45,
    "gn:elevation":"47.0",
    "gn:feature_class":"P",
    "gn:feature_code":"PPL",
    "gn:name":"Saint Stephens Estates",
    "gn:population":0,
    "gn:timezone":"America/New_York",
    "iso:country":"US",
    "wof:name":"Saint Stephens Estates",
    "wof:placetype":"locality"
},
  "geometry": {"coordinates":[-76.66524,39.03983],"type":"Point"}
}