{
  "type": "Feature",
  "properties": {
    "gn:admin1_code":"MD",
    "gn:admin2_code":"25.0",
    "gn:asciiname":"Fairway",
    "gn:country_code":"US",
    "gn:dem":94,
    "gn:elevation":"96.0",
    "gn:feature_class":"P",
    "gn:feature_code":"PPL",
    "gn:name":"Fairway",
    "gn:population":0,
    "gn:timezone":"America/New_York",
    "iso:country":"US",
    "name:ceb_x_preferred":[
        "Fairway"
    ],
    "name:deu_x_preferred":[
        "Fairway"
    ],
    "name:fra_x_preferred":[
        "Fairway"
    ],
    "name:ita_x_preferred":[
        "Fairway"
    ],
    "name:jpn_x_preferred":[
        "\u30d5\u30a7\u30a2\u30a6\u30a7\u30a4"
    ],
    "name:nld_x_preferred":[
        "Fairway"
    ],
    "wof:name":"Fairway",
    "wof:placetype":"locality"
},
  "geometry": {"coordinates":[-76.29411999999998,39.51122],"type":"Point"}
}