{
  "type": "Feature",
  "properties": {
    "iso:country":"US",
    "name:ara_x_preferred":[
        "\u0627\u0644\u0623\u0631\u0627\u0636\u064a \u0627\u0644\u062e\u0634\u0628\u064a\u0629"
    ],
    "name:bel_x_preferred":[
        "\u0420\u044d\u0434\u043a\u0430\u043b\u0435\u0441\u0441\u0435"
    ],
    "name:ben_x_preferred":[
        "\u0995\u09be\u09b7\u09cd\u09a0\u09ad\u09c2\u09ae\u09bf"
    ],
    "name:eng_x_preferred":[
        "Woodland"
    ],
    "name:epo_x_preferred":[
        "Duonarbaro"
    ],
    "name:fas_x_preferred":[
        "\u0628\u06cc\u0634\u0647\u200c\u0632\u0627\u0631"
    ],
    "name:fra_x_preferred":[
        "For\u00eat claire"
    ],
    "name:gle_x_preferred":[
        "Coillearnach"
    ],
    "name:ita_x_preferred":[
        "Bosco"
    ],
    "name:kat_x_preferred":[
        "\u10db\u10d4\u10e9\u10ee\u10d4\u10e0\u10d8 \u10e2\u10e7\u10d4"
    ],
    "name:lmo_x_preferred":[
        "Busch"
    ],
    "name:nor_x_preferred":[
        "Mark"
    ],
    "name:por_x_preferred":[
        "Bosque"
    ],
    "name:rus_x_preferred":[
        "\u0420\u0435\u0434\u043a\u043e\u043b\u0435\u0441\u044c\u0435"
    ],
    "name:scn_x_preferred":[
        "Voscu"
    ],
    "name:tam_x_preferred":[
        "\u0bae\u0bb0\u0b95\u0bcd\u0b95\u0bbe\u0b9f\u0bc1"
    ],
    "name:ukr_x_preferred":[
        "\u0420\u0456\u0434\u043a\u043e\u043b\u0456\u0441\u0441\u044f"
    ],
    "name:vie_x_preferred":[
        "R\u1eebng th\u01b0a"
    ],
    "wof:name":"Woodland",
    "wof:placetype":"neighbourhood",
    "wof:population":2117,
    "zs:area_m":1928901.507742,
    "zs:blockids":[
        170438414011026,
        170438414011017,
        170438414014007,
        170438414013032,
        170438414011023,
        170438414011024,
        170438414011021,
        170438414011022,
        170438414011070,
        170438414014000,
        170438414012017,
        170438414012060,
        170438414011016,
        170438414011028,
        170438414011025,
        170438414011036,
        170438414011019,
        170438414011020,
        170438414011071,
        170438414011018,
        170438414011012,
        170438414011034,
        170438414011032,
        170438414012056,
        170438414014008,
        170438414012059,
        170438414011010,
        170438414011027,
        170438414012016,
        170438414011008,
        170438414014009,
        170438414011011,
        170438415031017,
        170438414011015,
        170438414011037,
        170438414014011,
        170438414013033,
        170438414012015,
        170438414011033,
        170438414014010,
        170438414012061,
        170438414014001,
        170438414012063,
        170438414012062,
        170438415032000,
        170438414011035,
        170438414011031,
        170438414012055,
        170438414011007,
        170438414012054
    ],
    "zs:housing10":621,
    "zs:label":"Woodland",
    "zs:pop10":2117
},
  "geometry": {"coordinates":[-88.188616,41.873075],"type":"Point"}
}