{
  "type": "Feature",
  "properties": {
    "gn:admin1_code":"IN",
    "gn:admin2_code":"93.0",
    "gn:admin3_code":"59040.0",
    "gn:asciiname":"Red Hill",
    "gn:country_code":"US",
    "gn:dem":236,
    "gn:elevation":"231.0",
    "gn:feature_class":"P",
    "gn:feature_code":"PPL",
    "gn:name":"Red Hill",
    "gn:population":0,
    "gn:timezone":"America/Indiana/Indianapolis",
    "iso:country":"US",
    "name:ceb_x_preferred":[
        "Red Hill"
    ],
    "name:deu_x_preferred":[
        "Red Hill"
    ],
    "name:fra_x_preferred":[
        "Red Hill"
    ],
    "name:ita_x_preferred":[
        "Red Hill"
    ],
    "name:mlg_x_preferred":[
        "Red Hill"
    ],
    "name:nld_x_preferred":[
        "Red Hill"
    ],
    "name:pol_x_preferred":[
        "Red Hill"
    ],
    "name:srp_x_preferred":[
        "\u0420\u0435\u0434 \u0425\u0438\u043b"
    ],
    "name:swe_x_preferred":[
        "Red Hill"
    ],
    "name:ukr_x_preferred":[
        "\u0420\u0435\u0434-\u0413\u0456\u043b\u043b"
    ],
    "name:vol_x_preferred":[
        "Red Hill"
    ],
    "wof:name":"Red Hill",
    "wof:placetype":"locality"
},
  "geometry": {"coordinates":[-86.59777,38.93338],"type":"Point"}
}