{
  "type": "Feature",
  "properties": {
    "iso:country":"US",
    "name:eng_x_preferred":[
        "Morrellville"
    ],
    "wof:name":"Morrellville",
    "wof:placetype":"neighbourhood",
    "wof:population":2653,
    "zs:area_m":4931808.127947,
    "zs:blockids":[
        420210114002005,
        420210114003028,
        420210113003019,
        420210113004015,
        420210113004017,
        420210113003022,
        420210113004025,
        420210114003008,
        420210114002002,
        420210114002004,
        420210114003024,
        420210114002007,
        420210113004024,
        420210114002019,
        420210113003000,
        420210114002003,
        420210114002015,
        420210114002000,
        420210113003005,
        420210113003021,
        420210113003007,
        420210114002009,
        420210114002018,
        420210114002001,
        420210113004016,
        420210114003022,
        420210114002011,
        420210114003023,
        420210114003025,
        420210114002017,
        420210113003020,
        420210113003002,
        420210114002008,
        420210114003027,
        420210113003001,
        420210114003026,
        420210114002016,
        420210114002020,
        420210113004020,
        420210113003006,
        420210113003003,
        420210113003004,
        420210114002014,
        420210114002013,
        420210113004026,
        420210114002010,
        420210114003007,
        420210114002006,
        420210113004014,
        420210113004010,
        420210114002012
    ],
    "zs:housing10":1318,
    "zs:label":"Morrellville",
    "zs:pop10":2653
},
  "geometry": {"coordinates":[-78.961326,40.325797],"type":"Point"}
}