{
  "type": "Feature",
  "properties": {
    "gn:admin1_code":"AL",
    "gn:admin2_code":"23",
    "gn:asciiname":"Oakchia",
    "gn:country_code":"US",
    "gn:dem":39,
    "gn:elevation":"32.0",
    "gn:feature_class":"P",
    "gn:feature_code":"PPL",
    "gn:name":"Oakchia",
    "gn:population":0,
    "gn:timezone":"America/Chicago",
    "iso:country":"US",
    "name:eng_x_preferred":[
        "Oakchia"
    ],
    "name:und_x_variant":[
        "Hook-choie",
        "Okchai",
        "West Okchai",
        "Occhoy",
        "West Oakchia",
        "Oke-choy-atte"
    ],
    "wof:name":"Oakchia",
    "wof:placetype":"locality"
},
  "geometry": {"coordinates":[-88.01057,32.29848],"type":"Point"}
}