{
  "type": "Feature",
  "properties": {
    "gn:admin1_code":"KY",
    "gn:admin2_code":"79",
    "gn:asciiname":"Nina",
    "gn:country_code":"US",
    "gn:dem":296,
    "gn:elevation":"301.0",
    "gn:feature_class":"P",
    "gn:feature_code":"PPL",
    "gn:name":"Nina",
    "gn:population":0,
    "gn:timezone":"America/New_York",
    "iso:country":"US",
    "name:cat_x_preferred":[
        "Nina"
    ],
    "name:ceb_x_preferred":[
        "Nina"
    ],
    "name:deu_x_preferred":[
        "Nina"
    ],
    "name:fas_x_preferred":[
        "\u0646\u06cc\u0646\u0627"
    ],
    "name:fin_x_preferred":[
        "Nina"
    ],
    "name:fra_x_preferred":[
        "Nina"
    ],
    "name:hun_x_preferred":[
        "Nina"
    ],
    "name:ita_x_preferred":[
        "Nina"
    ],
    "name:jpn_x_preferred":[
        "\u30cb\u30fc\u30ca"
    ],
    "name:nld_x_preferred":[
        "Nina"
    ],
    "name:nor_x_preferred":[
        "Nina"
    ],
    "name:por_x_preferred":[
        "Nina"
    ],
    "name:rus_x_preferred":[
        "\u041d\u0438\u043d\u0430"
    ],
    "name:spa_x_preferred":[
        "Nina"
    ],
    "name:srp_x_preferred":[
        "\u041d\u0438\u043d\u0430"
    ],
    "name:swe_x_preferred":[
        "Nina"
    ],
    "name:ukr_x_preferred":[
        "\u041d\u0456\u043d\u0430"
    ],
    "wof:name":"Nina",
    "wof:placetype":"locality"
},
  "geometry": {"coordinates":[-84.46633,37.66397],"type":"Point"}
}