{
  "type": "Feature",
  "properties": {
    "gn:admin1_code":"OR",
    "gn:admin2_code":"45",
    "gn:asciiname":"Ironside",
    "gn:country_code":"US",
    "gn:dem":1150,
    "gn:elevation":"1153.0",
    "gn:feature_class":"P",
    "gn:feature_code":"PPL",
    "gn:name":"Ironside",
    "gn:population":0,
    "gn:timezone":"America/Boise",
    "iso:country":"US",
    "name:fas_x_preferred":[
        "\u0622\u06cc\u0631\u0648\u0646\u0633\u0627\u06cc\u062f"
    ],
    "name:hat_x_preferred":[
        "Ironside"
    ],
    "wof:name":"Ironside",
    "wof:placetype":"locality"
},
  "geometry": {"coordinates":[-117.94465,44.32433],"type":"Point"}
}