{
  "type": "Feature",
  "properties": {
    "gn:admin1_code":"AR",
    "gn:admin2_code":"149.0",
    "gn:admin3_code":"92613.0",
    "gn:asciiname":"Gum Tree",
    "gn:country_code":"US",
    "gn:dem":244,
    "gn:elevation":"233.0",
    "gn:feature_class":"P",
    "gn:feature_code":"PPL",
    "gn:name":"Gum Tree",
    "gn:population":0,
    "gn:timezone":"America/Chicago",
    "iso:country":"US",
    "name:zho_x_preferred":[
        "\u683c\u59c6\u7279\u91cc"
    ],
    "wof:name":"Gum Tree",
    "wof:placetype":"locality"
},
  "geometry": {"coordinates":[-93.45296,35.18675],"type":"Point"}
}