{
  "type": "Feature",
  "properties": {
    "gn:admin1_code":"MD",
    "gn:admin2_code":"31.0",
    "gn:asciiname":"Fox Hills Green",
    "gn:country_code":"US",
    "gn:dem":116,
    "gn:elevation":"113.0",
    "gn:feature_class":"P",
    "gn:feature_code":"PPL",
    "gn:name":"Fox Hills Green",
    "gn:population":0,
    "gn:timezone":"America/New_York",
    "iso:country":"US",
    "wof:name":"Fox Hills Green",
    "wof:placetype":"locality"
},
  "geometry": {"coordinates":[-77.26220000000001,39.10011],"type":"Point"}
}