{
  "type": "Feature",
  "properties": {
    "gn:admin1_code":"GA",
    "gn:admin2_code":"63.0",
    "gn:asciiname":"Lake Spivey Estates",
    "gn:country_code":"US",
    "gn:dem":263,
    "gn:elevation":"260.0",
    "gn:feature_class":"P",
    "gn:feature_code":"PPL",
    "gn:name":"Lake Spivey Estates",
    "gn:population":0,
    "gn:timezone":"America/New_York",
    "iso:country":"US",
    "wof:name":"Lake Spivey Estates",
    "wof:placetype":"locality"
},
  "geometry": {"coordinates":[-84.30159,33.5115],"type":"Point"}
}