{
  "type": "Feature",
  "properties": {
    "gn:country":"US",
    "gn:fcode":"ADMD",
    "gn:population":0,
    "iso:country":"US",
    "name:cym_x_preferred":[
        "Scrubgrass Township"
    ],
    "name:deu_x_preferred":[
        "Scrubgrass Township"
    ],
    "name:eng_x_preferred":[
        "Scrubgrass Township"
    ],
    "name:spa_x_preferred":[
        "Municipio de Scrubgrass"
    ],
    "name:ukr_x_preferred":[
        "\u0421\u043a\u0440\u0430\u0431\u0433\u0440\u0430\u0441\u0441 \u0422\u0430\u0443\u043d\u0448\u0438\u043f"
    ],
    "name:vie_x_preferred":[
        "Scrubgrass"
    ],
    "name:vie_x_variant":[
        "X\u00e3 Scrubgrass"
    ],
    "qs_pg:aaroncc":"US",
    "qs_pg:gn_country":"US",
    "qs_pg:gn_fcode":"ADMD",
    "qs_pg:gn_pop":0,
    "qs_pg:name":"Scrubgrass",
    "qs_pg:name_adm0":"United States",
    "qs_pg:name_adm1":"Pennsylvania",
    "qs_pg:photos":17,
    "qs_pg:photos_1k":3,
    "qs_pg:photos_9k":1,
    "qs_pg:photos_9r":2,
    "qs_pg:photos_all":55,
    "qs_pg:photos_sr":1,
    "qs_pg:pop_sr":0,
    "qs_pg:qs_pg_placetype":"locality",
    "qs_pg:qs_pg_placetype_gp":"Town",
    "qs_pg:woe_adm0":23424977,
    "woe:adm0_id":23424977,
    "woe:name_adm0":"United States",
    "woe:name_adm1":"Pennsylvania",
    "woe:placetype":"Town",
    "wof:coterminous":[
        404487607
    ],
    "wof:name":"Scrubgrass",
    "wof:placetype":"locality",
    "wof:statistical_gore":1
},
  "geometry": {"coordinates":[-79.79977,41.26673],"type":"Point"}
}