{
  "type": "Feature",
  "properties": {
    "gn:country":"US",
    "gn:fcode":"PPL",
    "gn:population":0,
    "iso:country":"US",
    "name:eng_x_preferred":[
        "Enterprise"
    ],
    "name:fas_x_preferred":[
        "\u0627\u0646\u062a\u0631\u067e\u0631\u0627\u06cc\u0632"
    ],
    "name:fra_x_preferred":[
        "Enterprise"
    ],
    "name:heb_x_preferred":[
        "\u05d0\u05e0\u05d8\u05e8\u05e4\u05e8\u05d9\u05d9\u05e1"
    ],
    "name:hun_x_preferred":[
        "Enterprise"
    ],
    "name:jpn_x_preferred":[
        "\u30a8\u30f3\u30bf\u30fc\u30d7\u30e9\u30a4\u30ba"
    ],
    "name:zho_x_preferred":[
        "\u6069\u7279\u666e\u8cf4\u65af"
    ],
    "qs_pg:aaroncc":"US",
    "qs_pg:gn_country":"US",
    "qs_pg:gn_fcode":"PPL",
    "qs_pg:gn_pop":0,
    "qs_pg:name":"Enterprise",
    "qs_pg:name_adm0":"United States",
    "qs_pg:name_adm1":"California",
    "qs_pg:photos":107,
    "qs_pg:photos_1k":22,
    "qs_pg:photos_9k":1,
    "qs_pg:photos_9r":3,
    "qs_pg:photos_all":107,
    "qs_pg:photos_sr":3,
    "qs_pg:pop_sr":0,
    "qs_pg:qs_pg_placetype":"locality",
    "qs_pg:qs_pg_placetype_gp":"Town",
    "qs_pg:woe_adm0":23424977,
    "woe:adm0_id":23424977,
    "woe:name_adm0":"United States",
    "woe:name_adm1":"California",
    "woe:placetype":"Town",
    "wof:name":"Enterprise",
    "wof:placetype":"locality"
},
  "geometry": {"coordinates":[-120.84716,38.54018],"type":"Point"}
}