{
  "type": "Feature",
  "properties": {
    "iso:country":"US",
    "name:eng_x_preferred":[
        "Woodward Heights"
    ],
    "name:nld_x_preferred":[
        "Woodward Heights"
    ],
    "wd:wordcount":369,
    "wof:name":"Woodward Heights",
    "wof:placetype":"neighbourhood",
    "wof:population":447,
    "zs:area_m":341758.835505,
    "zs:blockids":[
        210670001022015,
        210670009001001,
        210670009001000,
        210670001022013,
        210670009001010,
        210670009001011,
        210670009001008,
        210670009001036,
        210670001022010,
        210670009001003,
        210670001022014,
        210670001022012,
        210670010001040,
        210670001022011,
        210670009001009
    ],
    "zs:housing10":274,
    "zs:label":"Woodward Heights",
    "zs:pop10":447
},
  "geometry": {"coordinates":[-84.507724,38.049732],"type":"Point"}
}