{
  "type": "Feature",
  "properties": {
    "gn:admin1_code":"CA",
    "gn:admin2_code":"107.0",
    "gn:asciiname":"Cotton Center",
    "gn:country_code":"US",
    "gn:dem":116,
    "gn:elevation":"115.0",
    "gn:feature_class":"P",
    "gn:feature_code":"PPL",
    "gn:name":"Cotton Center",
    "gn:population":0,
    "gn:timezone":"America/Los_Angeles",
    "iso:country":"US",
    "wof:name":"Cotton Center",
    "wof:placetype":"locality"
},
  "geometry": {"coordinates":[-119.14288000000001,36.06606],"type":"Point"}
}