{
  "type": "Feature",
  "properties": {
    "gn:country":"US",
    "gn:fcode":"PPL",
    "gn:population":0,
    "iso:country":"US",
    "name:deu_x_preferred":[
        "Cottageville"
    ],
    "name:eng_x_preferred":[
        "Cottageville"
    ],
    "name:und_x_variant":[
        "Michener"
    ],
    "qs_pg:aaroncc":"US",
    "qs_pg:gn_country":"US",
    "qs_pg:gn_fcode":"PPL",
    "qs_pg:gn_pop":0,
    "qs_pg:name":"Cottageville",
    "qs_pg:name_adm0":"United States",
    "qs_pg:name_adm1":"Pennsylvania",
    "qs_pg:photos":10,
    "qs_pg:photos_1k":2,
    "qs_pg:photos_9k":1,
    "qs_pg:photos_9r":1,
    "qs_pg:photos_all":10,
    "qs_pg:photos_sr":1,
    "qs_pg:pop_sr":0,
    "qs_pg:qs_pg_placetype":"neighbourhood",
    "qs_pg:qs_pg_placetype_gp":"Suburb",
    "qs_pg:woe_adm0":23424977,
    "wd:wordcount":13,
    "wof:name":"Cottageville",
    "wof:placetype":"neighbourhood",
    "wof:population":1974,
    "zs:area_m":14467165.095394,
    "zs:blockids":[
        420171042011065,
        420171042032002,
        420171042032018,
        420171042032007,
        420171042011050,
        420171042032001,
        420171042011049,
        420171042011057,
        420171042011056,
        420171042011058,
        420171042031000,
        420171042032015,
        420171042032006,
        420171042011054,
        420171042011040,
        420171042011039,
        420171042011046,
        420171042011059,
        420171042032003,
        420171042011048,
        420171042032005,
        420171042032004,
        420171042011047,
        420171042011045,
        420171042011053
    ],
    "zs:housing10":663,
    "zs:label":"Cottageville",
    "zs:pop10":1974
},
  "geometry": {"coordinates":[-75.10821,40.389295],"type":"Point"}
}