{
  "type": "Feature",
  "properties": {
    "gn:admin1_code":"NC",
    "gn:admin2_code":"9.0",
    "gn:admin3_code":"91652.0",
    "gn:asciiname":"Orion",
    "gn:country_code":"US",
    "gn:dem":855,
    "gn:elevation":"853.0",
    "gn:feature_class":"P",
    "gn:feature_code":"PPL",
    "gn:name":"Orion",
    "gn:population":0,
    "gn:timezone":"America/New_York",
    "iso:country":"US",
    "name:ara_x_preferred":[
        "\u0623\u0648\u0631\u064a\u0648\u0646"
    ],
    "name:ast_x_preferred":[
        "Ori\u00f3n"
    ],
    "name:bel_x_preferred":[
        "\u0410\u0440\u044b\u0451\u043d"
    ],
    "name:bre_x_preferred":[
        "Orion"
    ],
    "name:cat_x_preferred":[
        "Orion"
    ],
    "name:ceb_x_preferred":[
        "Orion"
    ],
    "name:ces_x_preferred":[
        "Orion"
    ],
    "name:cym_x_preferred":[
        "Orion"
    ],
    "name:dan_x_preferred":[
        "Orion"
    ],
    "name:deu_x_preferred":[
        "Orion"
    ],
    "name:ell_x_preferred":[
        "\u03a9\u03c1\u03af\u03c9\u03bd"
    ],
    "name:est_x_preferred":[
        "Orion"
    ],
    "name:eus_x_preferred":[
        "Orion"
    ],
    "name:fas_x_preferred":[
        "\u0634\u06a9\u0627\u0631\u0686\u06cc"
    ],
    "name:fin_x_preferred":[
        "Orion"
    ],
    "name:fra_x_preferred":[
        "Orion"
    ],
    "name:heb_x_preferred":[
        "\u05d0\u05d5\u05e8\u05d9\u05d5\u05df"
    ],
    "name:hrv_x_preferred":[
        "Orion"
    ],
    "name:hun_x_preferred":[
        "Orion"
    ],
    "name:hye_x_preferred":[
        "\u0555\u0580\u056b\u0578\u0576"
    ],
    "name:ind_x_preferred":[
        "Orion"
    ],
    "name:ita_x_preferred":[
        "Orion"
    ],
    "name:jpn_x_preferred":[
        "\u30aa\u30ea\u30aa\u30f3"
    ],
    "name:kat_x_preferred":[
        "\u10dd\u10e0\u10d8\u10dd\u10dc\u10d8"
    ],
    "name:kor_x_preferred":[
        "\uc624\ub9ac\uc628"
    ],
    "name:lat_x_preferred":[
        "Orion"
    ],
    "name:lav_x_preferred":[
        "Orion"
    ],
    "name:lit_x_preferred":[
        "Orionas"
    ],
    "name:ltz_x_preferred":[
        "Orion"
    ],
    "name:mkd_x_preferred":[
        "\u041e\u0440\u0438\u043e\u043d"
    ],
    "name:msa_x_preferred":[
        "Orion"
    ],
    "name:nds_x_preferred":[
        "Orion"
    ],
    "name:nld_x_preferred":[
        "Orion"
    ],
    "name:nno_x_preferred":[
        "Orion"
    ],
    "name:nor_x_preferred":[
        "Orion"
    ],
    "name:pol_x_preferred":[
        "Orion"
    ],
    "name:por_x_preferred":[
        "Orion"
    ],
    "name:ron_x_preferred":[
        "Orion"
    ],
    "name:rus_x_preferred":[
        "Orion"
    ],
    "name:slk_x_preferred":[
        "Orion"
    ],
    "name:slv_x_preferred":[
        "Orion"
    ],
    "name:spa_x_preferred":[
        "Ori\u00f3n"
    ],
    "name:swe_x_preferred":[
        "Orion"
    ],
    "name:tur_x_preferred":[
        "Orion"
    ],
    "name:ukr_x_preferred":[
        "\u041e\u0440\u0456\u043e\u043d"
    ],
    "name:urd_x_preferred":[
        "\u0627\u0648\u0631\u06cc\u0646"
    ],
    "name:vie_x_preferred":[
        "Orion"
    ],
    "name:war_x_preferred":[
        "Orion"
    ],
    "wof:name":"Orion",
    "wof:placetype":"locality"
},
  "geometry": {"coordinates":[-81.42093,36.39763],"type":"Point"}
}