{
  "type": "Feature",
  "properties": {
    "iso:country":"US",
    "qs_pg:aaroncc":"US",
    "qs_pg:name":"Silver Springs",
    "qs_pg:name_adm0":"United States",
    "qs_pg:name_adm1":"Colorado",
    "qs_pg:photos":186,
    "qs_pg:photos_1k":38,
    "qs_pg:photos_9k":1,
    "qs_pg:photos_9r":4,
    "qs_pg:photos_all":186,
    "qs_pg:photos_sr":4,
    "qs_pg:pop_sr":0,
    "qs_pg:qs_pg_placetype":"neighbourhood",
    "qs_pg:qs_pg_placetype_gp":"Suburb",
    "qs_pg:woe_adm0":23424977,
    "woe:adm0_id":23424977,
    "woe:name_adm0":"United States",
    "woe:name_adm1":"Colorado",
    "woe:placetype":"Suburb",
    "wof:name":"Silver Springs",
    "wof:placetype":"neighbourhood"
},
  "geometry": {"coordinates":[-105.279021,40.015739],"type":"Point"}
}