{
  "type": "Feature",
  "properties": {
    "gn:admin1_code":"IN",
    "gn:admin2_code":"149.0",
    "gn:admin3_code":"54504.0",
    "gn:asciiname":"Winona",
    "gn:country_code":"US",
    "gn:dem":226,
    "gn:elevation":"221.0",
    "gn:feature_class":"P",
    "gn:feature_code":"PPL",
    "gn:name":"Winona",
    "gn:population":0,
    "gn:timezone":"America/Indiana/Knox",
    "iso:country":"US",
    "name:ben_x_preferred":[
        "\u0989\u0987\u09a8\u09cb\u09b0\u09be"
    ],
    "name:ceb_x_preferred":[
        "Winona"
    ],
    "name:ces_x_preferred":[
        "Winona"
    ],
    "name:deu_x_preferred":[
        "Winona"
    ],
    "name:ell_x_preferred":[
        "\u0393\u03bf\u03c5\u03af\u03bd\u03bf\u03b3\u03bf\u03c5\u03b1"
    ],
    "name:fin_x_preferred":[
        "Winona"
    ],
    "name:fra_x_preferred":[
        "Winona"
    ],
    "name:hin_x_preferred":[
        "\u0935\u093f\u0928\u094b\u0928\u093e"
    ],
    "name:ind_x_preferred":[
        "Winona"
    ],
    "name:ita_x_preferred":[
        "Winona"
    ],
    "name:jpn_x_preferred":[
        "\u30a6\u30a3\u30ce\u30ca"
    ],
    "name:kor_x_preferred":[
        "\uc704\ub178\ub098"
    ],
    "name:nld_x_preferred":[
        "Winona"
    ],
    "name:pol_x_preferred":[
        "Winona"
    ],
    "name:por_x_preferred":[
        "Winona"
    ],
    "name:rus_x_preferred":[
        "\u0423\u0438\u043d\u043e\u043d\u0430"
    ],
    "name:spa_x_preferred":[
        "Winona"
    ],
    "name:srp_x_preferred":[
        "\u0412\u0430\u0458\u043d\u043e\u043d\u0430"
    ],
    "name:swe_x_preferred":[
        "Winona"
    ],
    "name:vol_x_preferred":[
        "Winona"
    ],
    "wof:name":"Winona",
    "wof:placetype":"locality"
},
  "geometry": {"coordinates":[-86.56946000000001,41.23615],"type":"Point"}
}