{
  "type": "Feature",
  "properties": {
    "gn:admin1_code":"IL",
    "gn:admin2_code":"49",
    "gn:admin3_code":"79254.0",
    "gn:asciiname":"Heartville",
    "gn:country_code":"US",
    "gn:dem":174,
    "gn:elevation":"171.0",
    "gn:feature_class":"P",
    "gn:feature_code":"PPL",
    "gn:name":"Heartville",
    "gn:population":0,
    "gn:timezone":"America/Chicago",
    "iso:country":"US",
    "wof:name":"Heartville",
    "wof:placetype":"locality"
},
  "geometry": {"coordinates":[-88.54338,39.0506],"type":"Point"}
}