{
  "type": "Feature",
  "properties": {
    "gn:admin1_code":"TX",
    "gn:admin2_code":"427.0",
    "gn:asciiname":"Anacua Colonia",
    "gn:country_code":"US",
    "gn:dem":57,
    "gn:elevation":"54.0",
    "gn:feature_class":"P",
    "gn:feature_code":"PPL",
    "gn:name":"Anacua Colonia",
    "gn:population":0,
    "gn:timezone":"America/Chicago",
    "iso:country":"US",
    "wof:name":"Anacua Colonia",
    "wof:placetype":"locality"
},
  "geometry": {"coordinates":[-98.92031,26.38645],"type":"Point"}
}