{
  "type": "Feature",
  "properties": {
    "gn:admin1_code":"ID",
    "gn:admin2_code":"61.0",
    "gn:asciiname":"Mohler",
    "gn:country_code":"US",
    "gn:dem":983,
    "gn:elevation":"987.0",
    "gn:feature_class":"P",
    "gn:feature_code":"PPL",
    "gn:name":"Mohler",
    "gn:population":0,
    "gn:timezone":"America/Los_Angeles",
    "iso:country":"US",
    "wof:name":"Mohler",
    "wof:placetype":"locality"
},
  "geometry": {"coordinates":[-116.34625,46.28961],"type":"Point"}
}