{
  "type": "Feature",
  "properties": {
    "gn:admin1_code":"VA",
    "gn:admin2_code":"710",
    "gn:asciiname":"Casterton Trailer Park",
    "gn:country_code":"US",
    "gn:dem":6,
    "gn:elevation":"4.0",
    "gn:feature_class":"P",
    "gn:feature_code":"PPL",
    "gn:name":"Casterton Trailer Park",
    "gn:population":0,
    "gn:timezone":"America/New_York",
    "iso:country":"US",
    "wof:name":"Casterton Trailer Park",
    "wof:placetype":"campus"
},
  "geometry": {"coordinates":[-76.25780999999998,36.91629],"type":"Point"}
}