{
  "type": "Feature",
  "properties": {
    "gn:admin1_code":"WI",
    "gn:admin2_code":"95.0",
    "gn:admin3_code":"4500.0",
    "gn:asciiname":"Lykens",
    "gn:country_code":"US",
    "gn:dem":328,
    "gn:elevation":"332.0",
    "gn:feature_class":"P",
    "gn:feature_code":"PPL",
    "gn:name":"Lykens",
    "gn:population":0,
    "gn:timezone":"America/Chicago",
    "iso:country":"US",
    "wof:name":"Lykens",
    "wof:placetype":"locality"
},
  "geometry": {"coordinates":[-92.46908999999999,45.4244],"type":"Point"}
}