{
  "type": "Feature",
  "properties": {
    "iso:country":"US",
    "name:eng_x_preferred":[
        "Salmen"
    ],
    "wof:name":"Salmen",
    "wof:placetype":"neighbourhood",
    "wof:population":406,
    "zs:area_m":369538.196672,
    "zs:blockids":[
        221030411042006,
        221030411042016,
        221030408012003
    ],
    "zs:housing10":172,
    "zs:label":"Salmen",
    "zs:pop10":406
},
  "geometry": {"coordinates":[-89.78952099999999,30.258149],"type":"Point"}
}