{
  "type": "Feature",
  "properties": {
    "gn:admin1_code":"TX",
    "gn:admin2_code":"47.0",
    "gn:asciiname":"Cantu Addition Number 2 Colonia",
    "gn:country_code":"US",
    "gn:dem":38,
    "gn:elevation":"34.0",
    "gn:feature_class":"P",
    "gn:feature_code":"PPL",
    "gn:name":"Cantu Addition Number 2 Colonia",
    "gn:population":0,
    "gn:timezone":"America/Chicago",
    "iso:country":"US",
    "wof:name":"Cantu Addition Number 2 Colonia",
    "wof:placetype":"locality"
},
  "geometry": {"coordinates":[-98.15528,27.20227],"type":"Point"}
}