{
  "type": "Feature",
  "properties": {
    "gn:admin1_code":"ME",
    "gn:admin2_code":"3.0",
    "gn:admin3_code":"25755.0",
    "gn:asciiname":"Fort Kent Mills",
    "gn:country_code":"US",
    "gn:dem":193,
    "gn:elevation":"190.0",
    "gn:feature_class":"P",
    "gn:feature_code":"PPL",
    "gn:name":"Fort Kent Mills",
    "gn:population":0,
    "gn:timezone":"America/New_York",
    "iso:country":"US",
    "wof:name":"Fort Kent Mills",
    "wof:placetype":"locality"
},
  "geometry": {"coordinates":[-68.58394,47.23893],"type":"Point"}
}