{
  "type": "Feature",
  "properties": {
    "gn:admin1_code":"SC",
    "gn:admin2_code":"59.0",
    "gn:asciiname":"Black Gate",
    "gn:country_code":"US",
    "gn:dem":154,
    "gn:elevation":"143.0",
    "gn:feature_class":"P",
    "gn:feature_code":"PPL",
    "gn:name":"Black Gate",
    "gn:population":0,
    "gn:timezone":"America/New_York",
    "iso:country":"US",
    "wof:name":"Black Gate",
    "wof:placetype":"locality"
},
  "geometry": {"coordinates":[-81.98595,34.25068],"type":"Point"}
}