{
  "type": "Feature",
  "properties": {
    "gn:admin1_code":"TX",
    "gn:admin2_code":"201.0",
    "gn:asciiname":"Blue Bell Place",
    "gn:country_code":"US",
    "gn:dem":27,
    "gn:elevation":"26.0",
    "gn:feature_class":"P",
    "gn:feature_code":"PPL",
    "gn:name":"Blue Bell Place",
    "gn:population":0,
    "gn:timezone":"America/Chicago",
    "iso:country":"US",
    "wof:name":"Blue Bell Place",
    "wof:placetype":"locality"
},
  "geometry": {"coordinates":[-95.4102,29.9063],"type":"Point"}
}