{
  "type": "Feature",
  "properties": {
    "gn:elevation":1330,
    "iso:country":"US",
    "name:eng_x_preferred":[
        "Eggli Meadows"
    ],
    "name:eng_x_variant":[
        "Eggli Mdws"
    ],
    "qs:gn_adm0_cc":"US",
    "qs:gn_fcode":"PPLX",
    "qs:gn_local":5784549,
    "qs:gn_nam_loc":"West Jordan, Salt Lake, Utah, US",
    "qs:gn_namadm1":"UT",
    "qs:gn_name":"Eggli Meadows",
    "qs:local_max":726,
    "qs:local_sum":2346,
    "qs:localhoods":9,
    "qs:name":"Eggli Meadows",
    "qs:name_adm0":"United States",
    "qs:name_adm1":"Utah",
    "qs:name_adm2":"Salt Lake",
    "qs:name_local":"West Jordan",
    "qs:photo_max":103,
    "qs:photo_sum":199,
    "qs:placetype":"Suburb",
    "qs:quad_count":11,
    "qs:woe_adm0":23424977,
    "qs:woe_adm1":2347603,
    "qs:woe_adm2":12590278,
    "qs:woe_lau":0,
    "qs:woe_local":2517245,
    "qs:woe_ver":"7.10.0",
    "wof:name":"Eggli Meadows",
    "wof:placetype":"neighbourhood",
    "wof:population":4166,
    "zs:blockids":[
        490351129202011,
        490351129171017,
        490351142001043,
        490351129202012,
        490351129202007,
        490351129171001,
        490351129182008,
        490351129182021,
        490351129202001,
        490351129182004,
        490351142002004,
        490351129202009,
        490351129171005,
        490351129171006,
        490351129171004,
        490351129171014,
        490351129133011,
        490351129182014,
        490351129202002,
        490351129133006,
        490351129182017,
        490351129182011,
        490351129171002,
        490351129202006,
        490351129171016,
        490351142002016,
        490351129171003,
        490351129202005,
        490351129171013,
        490351129202013,
        490351129202004,
        490351129182007,
        490351129182009,
        490351129133005,
        490351129182005,
        490351129182006,
        490351129171012,
        490351129182015,
        490351129133012,
        490351129202000,
        490351129071015,
        490351142002005,
        490351129182012,
        490351129202008,
        490351129182013,
        490351129182022,
        490351129182019,
        490351129182010,
        490351129182020,
        490351129202003,
        490351129182002,
        490351129182001,
        490351129182000,
        490351129171000,
        490351129182003,
        490351129202010,
        490351129182018,
        490351129182016
    ],
    "zs:housing10":1311,
    "zs:pop10":4166
},
  "geometry": {"coordinates":[-111.943873,40.604351],"type":"Point"}
}