{
  "type": "Feature",
  "properties": {
    "gn:admin1_code":"TN",
    "gn:admin2_code":"119",
    "gn:asciiname":"Natco",
    "gn:country_code":"US",
    "gn:dem":183,
    "gn:elevation":"183.0",
    "gn:feature_class":"P",
    "gn:feature_code":"PPL",
    "gn:name":"Natco",
    "gn:population":0,
    "gn:timezone":"America/Chicago",
    "iso:country":"US",
    "wof:name":"Natco",
    "wof:placetype":"locality"
},
  "geometry": {"coordinates":[-87.05417,35.64229],"type":"Point"}
}