{
  "type": "Feature",
  "properties": {
    "iso:country":"US",
    "name:ces_x_preferred":[
        "Dorsey"
    ],
    "name:deu_x_preferred":[
        "Dorsey"
    ],
    "name:fra_x_preferred":[
        "Dorsey"
    ],
    "name:glg_x_preferred":[
        "Dorsey"
    ],
    "name:heb_x_preferred":[
        "\u05d3\u05d5\u05e8\u05e1\u05d9"
    ],
    "name:ita_x_preferred":[
        "Dorsey"
    ],
    "name:rus_x_preferred":[
        "\u0414\u043e\u0440\u0441\u0438"
    ],
    "qs_pg:aaroncc":"US",
    "qs_pg:name":"Dorsey",
    "qs_pg:name_adm0":"United States",
    "qs_pg:name_adm1":"Colorado",
    "qs_pg:photos":21,
    "qs_pg:photos_1k":4,
    "qs_pg:photos_9k":1,
    "qs_pg:photos_9r":1,
    "qs_pg:photos_all":21,
    "qs_pg:photos_sr":1,
    "qs_pg:pop_sr":0,
    "qs_pg:qs_pg_placetype":"locality",
    "qs_pg:qs_pg_placetype_gp":"Town",
    "qs_pg:woe_adm0":23424977,
    "woe:adm0_id":23424977,
    "woe:name_adm0":"United States",
    "woe:name_adm1":"Colorado",
    "woe:placetype":"Town",
    "wof:name":"Dorsey",
    "wof:placetype":"locality"
},
  "geometry": {"coordinates":[-102.61344800000001,40.916908],"type":"Point"}
}