{
  "type": "Feature",
  "properties": {
    "gn:elevation":11,
    "iso:country":"US",
    "name:eng_x_preferred":[
        "Holiday City"
    ],
    "name:eng_x_variant":[
        "Holiday Cty"
    ],
    "qs:gn_adm0_cc":"US",
    "qs:gn_fcode":"PPL",
    "qs:gn_local":4504476,
    "qs:gn_nam_loc":"Toms River, Ocean, New Jersey, US",
    "qs:gn_namadm1":"NJ",
    "qs:gn_name":"Holiday City",
    "qs:local_max":626,
    "qs:local_sum":2479,
    "qs:localhoods":17,
    "qs:name":"Holiday City",
    "qs:name_adm0":"United States",
    "qs:name_adm1":"New Jersey",
    "qs:name_adm2":"Ocean",
    "qs:name_local":"Toms River",
    "qs:photo_max":4,
    "qs:photo_sum":10,
    "qs:placetype":"Suburb",
    "qs:quad_count":6,
    "qs:woe_adm0":23424977,
    "qs:woe_adm1":2347589,
    "qs:woe_adm2":12589272,
    "qs:woe_lau":0,
    "qs:woe_local":2507064,
    "qs:woe_ver":"7.10.0",
    "wof:lang":[
        "eng"
    ],
    "wof:name":"Holiday City",
    "wof:placetype":"neighbourhood",
    "wof:population":3395,
    "zs:blockids":[
        340297222001013,
        340297223002012,
        340297227013023,
        340297223001021,
        340297223002030,
        340297223001016,
        340297223002026,
        340297223002017,
        340297227013034,
        340297227013032,
        340297222001014,
        340297227013005,
        340297227013017,
        340297222003002,
        340297223002023,
        340297223001014,
        340297227013011,
        340297223002018,
        340297227013006,
        340297221003014,
        340297227013014,
        340297223002032,
        340297222001012,
        340297222001004,
        340297223002025,
        340297223002024,
        340297223002010,
        340297223002021,
        340297227013033,
        340297227013012,
        340297223002020,
        340297223001019,
        340297223002013,
        340297223002022,
        340297223002014,
        340297223002015,
        340297227013001,
        340297221003023,
        340297223001018,
        340297223001015,
        340297227013019,
        340297227013020,
        340297227013013,
        340297223001020,
        340297227013009,
        340297223002027,
        340297223002009,
        340297227013008,
        340297227013016,
        340297221003024,
        340297227013004,
        340297223002019,
        340297227013015,
        340297227012006,
        340297227013007,
        340297223002011,
        340297227013002,
        340297223002005,
        340297227013010,
        340297223001012,
        340297223002016
    ],
    "zs:housing10":1191,
    "zs:pop10":3395
},
  "geometry": {"coordinates":[-74.16925000000001,40.020042],"type":"Point"}
}