{
  "type": "Feature",
  "properties": {
    "gn:admin1_code":"FL",
    "gn:admin2_code":"71.0",
    "gn:asciiname":"Alta Vista Park Mobille Home Park",
    "gn:country_code":"US",
    "gn:dem":7,
    "gn:elevation":"4.0",
    "gn:feature_class":"P",
    "gn:feature_code":"PPL",
    "gn:name":"Alta Vista Park Mobille Home Park",
    "gn:population":0,
    "gn:timezone":"America/New_York",
    "iso:country":"US",
    "wof:name":"Alta Vista Park Mobille Home Park",
    "wof:placetype":"locality"
},
  "geometry": {"coordinates":[-81.80880000000001,26.6773],"type":"Point"}
}