{
  "type": "Feature",
  "properties": {
    "gn:admin1_code":"AL",
    "gn:admin2_code":"105.0",
    "gn:asciiname":"Rabbityard",
    "gn:country_code":"US",
    "gn:dem":85,
    "gn:elevation":"83.0",
    "gn:feature_class":"P",
    "gn:feature_code":"PPL",
    "gn:name":"Rabbityard",
    "gn:population":0,
    "gn:timezone":"America/Chicago",
    "iso:country":"US",
    "wof:name":"Rabbityard",
    "wof:placetype":"locality"
},
  "geometry": {"coordinates":[-87.52084000000001,32.4543],"type":"Point"}
}