{
  "type": "Feature",
  "properties": {
    "iso:country":"US",
    "qs_pg:aaroncc":"US",
    "qs_pg:name":"Clayworks",
    "qs_pg:name_adm0":"United States",
    "qs_pg:name_adm1":"Iowa",
    "qs_pg:photos":20,
    "qs_pg:photos_1k":4,
    "qs_pg:photos_9k":1,
    "qs_pg:photos_9r":1,
    "qs_pg:photos_all":20,
    "qs_pg:photos_sr":1,
    "qs_pg:pop_sr":0,
    "qs_pg:qs_pg_placetype":"locality",
    "qs_pg:qs_pg_placetype_gp":"Town",
    "qs_pg:woe_adm0":23424977,
    "woe:adm0_id":23424977,
    "woe:name_adm0":"United States",
    "woe:name_adm1":"Iowa",
    "woe:placetype":"Town",
    "wof:name":"Clayworks",
    "wof:placetype":"locality"
},
  "geometry": {"coordinates":[-94.186477,42.50349],"type":"Point"}
}