{
  "type": "Feature",
  "properties": {
    "gn:admin1_code":"IN",
    "gn:admin2_code":"15.0",
    "gn:admin3_code":"10540.0",
    "gn:asciiname":"Sharon",
    "gn:country_code":"US",
    "gn:dem":235,
    "gn:elevation":"232.0",
    "gn:feature_class":"P",
    "gn:feature_code":"PPL",
    "gn:name":"Sharon",
    "gn:population":0,
    "gn:timezone":"America/Indiana/Indianapolis",
    "iso:country":"US",
    "wof:name":"Sharon",
    "wof:placetype":"locality"
},
  "geometry": {"coordinates":[-86.39139,40.55365],"type":"Point"}
}