{
  "type": "Feature",
  "properties": {
    "gn:admin1_code":"NY",
    "gn:admin2_code":"77.0",
    "gn:admin3_code":"79972.0",
    "gn:asciiname":"Westville",
    "gn:country_code":"US",
    "gn:dem":372,
    "gn:elevation":"374.0",
    "gn:feature_class":"P",
    "gn:feature_code":"PPL",
    "gn:name":"Westville",
    "gn:population":0,
    "gn:timezone":"America/New_York",
    "iso:country":"US",
    "name:ceb_x_preferred":[
        "Westville"
    ],
    "name:deu_x_preferred":[
        "Westville"
    ],
    "name:fra_x_preferred":[
        "Westville"
    ],
    "name:ita_x_preferred":[
        "Westville"
    ],
    "name:nld_x_preferred":[
        "Westville"
    ],
    "name:pol_x_preferred":[
        "Westville"
    ],
    "name:por_x_preferred":[
        "Westville"
    ],
    "name:rus_x_preferred":[
        "\u0423\u044d\u0441\u0442\u0432\u0438\u043b\u043b"
    ],
    "name:srp_x_preferred":[
        "\u0412\u0435\u0441\u0442\u0432\u0438\u043b"
    ],
    "name:swe_x_preferred":[
        "Westville"
    ],
    "name:vol_x_preferred":[
        "Westville"
    ],
    "wof:name":"Westville",
    "wof:placetype":"locality"
},
  "geometry": {"coordinates":[-74.88043,42.6273],"type":"Point"}
}