{
  "type": "Feature",
  "properties": {
    "gn:admin1_code":"ID",
    "gn:admin2_code":"19.0",
    "gn:asciiname":"Bone",
    "gn:country_code":"US",
    "gn:dem":1846,
    "gn:elevation":"1851.0",
    "gn:feature_class":"P",
    "gn:feature_code":"PPL",
    "gn:name":"Bone",
    "gn:population":0,
    "gn:timezone":"America/Boise",
    "iso:country":"US",
    "name:azb_x_preferred":[
        "\u0628\u0648\u0646"
    ],
    "name:fas_x_preferred":[
        "\u0628\u0648\u0646"
    ],
    "wof:name":"Bone",
    "wof:placetype":"locality"
},
  "geometry": {"coordinates":[-111.79524000000001,43.31242],"type":"Point"}
}