{
  "type": "Feature",
  "properties": {
    "gn:admin1_code":"LA",
    "gn:admin2_code":"15.0",
    "gn:asciiname":"Dogwood Acres",
    "gn:country_code":"US",
    "gn:dem":77,
    "gn:elevation":"63.0",
    "gn:feature_class":"P",
    "gn:feature_code":"PPL",
    "gn:name":"Dogwood Acres",
    "gn:population":0,
    "gn:timezone":"America/Chicago",
    "iso:country":"US",
    "wof:name":"Dogwood Acres",
    "wof:placetype":"locality"
},
  "geometry": {"coordinates":[-93.60518,32.57459],"type":"Point"}
}