{
  "type": "Feature",
  "properties": {
    "gn:country":"US",
    "gn:fcode":"PPL",
    "gn:population":0,
    "iso:country":"US",
    "name:deu_x_preferred":[
        "Shivers"
    ],
    "name:fin_x_preferred":[
        "Shivers"
    ],
    "name:fra_x_preferred":[
        "Shiver"
    ],
    "name:ita_x_preferred":[
        "Shivers"
    ],
    "name:nld_x_preferred":[
        "Shivers"
    ],
    "qs_pg:aaroncc":"US",
    "qs_pg:gn_country":"US",
    "qs_pg:gn_fcode":"PPL",
    "qs_pg:gn_pop":0,
    "qs_pg:name":"Shivers",
    "qs_pg:name_adm0":"United States",
    "qs_pg:name_adm1":"Mississippi",
    "qs_pg:photos_9k":1,
    "qs_pg:photos_9r":1,
    "qs_pg:photos_all":1,
    "qs_pg:photos_sr":0,
    "qs_pg:pop_sr":5,
    "qs_pg:qs_pg_placetype":"locality",
    "qs_pg:qs_pg_placetype_gp":"Town",
    "qs_pg:woe_adm0":23424977,
    "woe:adm0_id":23424977,
    "woe:name_adm0":"United States",
    "woe:name_adm1":"Mississippi",
    "woe:placetype":"Town",
    "wof:name":"Shivers",
    "wof:placetype":"locality"
},
  "geometry": {"coordinates":[-89.98757999999999,31.79655],"type":"Point"}
}