{
  "type": "Feature",
  "properties": {
    "gn:elevation":32,
    "iso:country":"US",
    "name:eng_x_preferred":[
        "Fort Clinton"
    ],
    "name:eng_x_variant":[
        "Ft Clinton"
    ],
    "name:ind_x_preferred":[
        "Benteng Clinton"
    ],
    "name:jpn_x_preferred":[
        "\u30d5\u30a9\u30fc\u30c8\u30fb\u30af\u30ea\u30f3\u30c8\u30f3"
    ],
    "qs:gn_adm0_cc":"US",
    "qs:gn_fcode":"PPL",
    "qs:gn_local":5117685,
    "qs:gn_nam_loc":"Fort Montgomery, Orange, New York, US",
    "qs:gn_namadm1":"NY",
    "qs:gn_name":"Fort Clinton",
    "qs:local_max":2550,
    "qs:local_sum":2550,
    "qs:localhoods":1,
    "qs:name":"Fort Clinton",
    "qs:name_adm0":"United States",
    "qs:name_adm1":"New York",
    "qs:name_adm2":"Orange",
    "qs:name_local":"Fort Montgomery",
    "qs:photo_max":195,
    "qs:photo_sum":2550,
    "qs:placetype":"Suburb",
    "qs:quad_count":75,
    "qs:woe_adm0":23424977,
    "qs:woe_adm1":2347591,
    "qs:woe_adm2":12589347,
    "qs:woe_lau":0,
    "qs:woe_local":2405854,
    "qs:woe_ver":"7.10.0",
    "wd:wordcount":366,
    "wof:lang":[
        "eng"
    ],
    "wof:name":"Fort Clinton",
    "wof:placetype":"neighbourhood",
    "zs:blockids":[
        361190147011032,
        361190147011040,
        361190147011030,
        361190147011034,
        361190147011035,
        361190147011029,
        361190147011038,
        361190147011031,
        361190147011039,
        361190147011033
    ],
    "zs:housing10":0,
    "zs:pop10":0
},
  "geometry": {"coordinates":[-73.990315,41.31737],"type":"Point"}
}