{
  "type": "Feature",
  "properties": {
    "gn:admin1_code":"MO",
    "gn:admin2_code":"189.0",
    "gn:admin3_code":"69284.0",
    "gn:asciiname":"Shoveltown",
    "gn:country_code":"US",
    "gn:dem":168,
    "gn:elevation":"168.0",
    "gn:feature_class":"P",
    "gn:feature_code":"PPL",
    "gn:name":"Shoveltown",
    "gn:population":0,
    "gn:timezone":"America/Chicago",
    "iso:country":"US",
    "wof:name":"Shoveltown",
    "wof:placetype":"locality"
},
  "geometry": {"coordinates":[-90.28067,38.81561],"type":"Point"}
}