{
  "type": "Feature",
  "properties": {
    "iso:country":"US",
    "name:eng_x_preferred":[
        "Goyan Heights"
    ],
    "wof:name":"Goyan Heights",
    "wof:placetype":"neighbourhood",
    "wof:population":98,
    "zs:area_m":401578.825145,
    "zs:blockids":[
        60170312001063,
        60170312001064,
        60170312001065
    ],
    "zs:housing10":37,
    "zs:label":"Goyan Heights",
    "zs:pop10":98
},
  "geometry": {"coordinates":[-120.784888,38.718695],"type":"Point"}
}