{
  "type": "Feature",
  "properties": {
    "gn:admin1_code":"MN",
    "gn:admin2_code":"9.0",
    "gn:asciiname":"Sherwood Manor",
    "gn:country_code":"US",
    "gn:dem":317,
    "gn:elevation":"317.0",
    "gn:feature_class":"P",
    "gn:feature_code":"PPL",
    "gn:name":"Sherwood Manor",
    "gn:population":0,
    "gn:timezone":"America/Chicago",
    "iso:country":"US",
    "wof:name":"Sherwood Manor",
    "wof:placetype":"locality"
},
  "geometry": {"coordinates":[-94.13778000000001,45.56139],"type":"Point"}
}