{
  "type": "Feature",
  "properties": {
    "gn:admin1_code":"MD",
    "gn:admin2_code":"21.0",
    "gn:asciiname":"Hines Woods",
    "gn:country_code":"US",
    "gn:dem":147,
    "gn:elevation":"143.0",
    "gn:feature_class":"P",
    "gn:feature_code":"PPL",
    "gn:name":"Hines Woods",
    "gn:population":0,
    "gn:timezone":"America/New_York",
    "iso:country":"US",
    "wof:name":"Hines Woods",
    "wof:placetype":"locality"
},
  "geometry": {"coordinates":[-77.35637,39.38121],"type":"Point"}
}