{
  "type": "Feature",
  "properties": {
    "gn:admin1_code":"NC",
    "gn:admin2_code":"133.0",
    "gn:admin3_code":"91632.0",
    "gn:asciiname":"Oakhurst River Estates",
    "gn:country_code":"US",
    "gn:dem":8,
    "gn:elevation":"4.0",
    "gn:feature_class":"P",
    "gn:feature_code":"PPL",
    "gn:name":"Oakhurst River Estates",
    "gn:population":0,
    "gn:timezone":"America/New_York",
    "iso:country":"US",
    "wof:name":"Oakhurst River Estates",
    "wof:placetype":"locality"
},
  "geometry": {"coordinates":[-77.47135,34.76183],"type":"Point"}
}