{
  "type": "Feature",
  "properties": {
    "iso:country":"US",
    "name:afr_x_preferred":[
        "Marble Hall"
    ],
    "name:deu_x_preferred":[
        "Marble Hall"
    ],
    "name:eng_x_preferred":[
        "Marble Hall"
    ],
    "name:est_x_preferred":[
        "Marble Hall"
    ],
    "name:nso_x_preferred":[
        "Marble Hall"
    ],
    "name:ron_x_preferred":[
        "Marble Hall"
    ],
    "name:rus_x_preferred":[
        "\u041c\u0430\u0440\u0431\u043b-\u0425\u043e\u043b"
    ],
    "name:zho_x_preferred":[
        "\u99ac\u723e\u5e03\u970d\u723e"
    ],
    "wof:name":"Marble Hall",
    "wof:placetype":"neighbourhood",
    "wof:population":185,
    "zs:area_m":149272.895787,
    "zs:blockids":[
        420912031042006,
        420912031042005,
        420912031043022
    ],
    "zs:housing10":72,
    "zs:label":"Marble Hall",
    "zs:pop10":185
},
  "geometry": {"coordinates":[-75.247799,40.086125],"type":"Point"}
}