{
  "type": "Feature",
  "properties": {
    "gn:admin1_code":"MD",
    "gn:admin2_code":"33.0",
    "gn:asciiname":"Broadwater Estates",
    "gn:country_code":"US",
    "gn:dem":8,
    "gn:elevation":"12.0",
    "gn:feature_class":"P",
    "gn:feature_code":"PPL",
    "gn:name":"Broadwater Estates",
    "gn:population":0,
    "gn:timezone":"America/New_York",
    "iso:country":"US",
    "wof:name":"Broadwater Estates",
    "wof:placetype":"locality"
},
  "geometry": {"coordinates":[-77.01275,38.7415],"type":"Point"}
}