{
  "type": "Feature",
  "properties": {
    "gn:country":"US",
    "gn:fcode":"ADMD",
    "gn:population":0,
    "iso:country":"US",
    "name:cym_x_preferred":[
        "Ogle Township"
    ],
    "name:deu_x_preferred":[
        "Ogle Township"
    ],
    "name:eng_x_preferred":[
        "Ogle Township"
    ],
    "name:spa_x_preferred":[
        "Municipio de Ogle"
    ],
    "name:ukr_x_preferred":[
        "\u041e\u0433\u0435\u043b \u0422\u0430\u0443\u043d\u0448\u0438\u043f"
    ],
    "name:vie_x_preferred":[
        "Ogle"
    ],
    "name:vie_x_variant":[
        "X\u00e3 Ogle"
    ],
    "qs_pg:aaroncc":"US",
    "qs_pg:gn_country":"US",
    "qs_pg:gn_fcode":"ADMD",
    "qs_pg:gn_pop":0,
    "qs_pg:name":"Ogle Twp",
    "qs_pg:name_adm0":"United States",
    "qs_pg:name_adm1":"Pennsylvania",
    "qs_pg:photos":70,
    "qs_pg:photos_1k":14,
    "qs_pg:photos_9k":1,
    "qs_pg:photos_9r":3,
    "qs_pg:photos_all":89,
    "qs_pg:photos_sr":2,
    "qs_pg:pop_sr":0,
    "qs_pg:qs_pg_placetype":"locality",
    "qs_pg:qs_pg_placetype_gp":"Town",
    "qs_pg:woe_adm0":23424977,
    "woe:adm0_id":23424977,
    "woe:name_adm0":"United States",
    "woe:name_adm1":"Pennsylvania",
    "woe:placetype":"Town",
    "wof:name":"Ogle Twp",
    "wof:placetype":"locality"
},
  "geometry": {"coordinates":[-78.7253,40.20008],"type":"Point"}
}