{
  "type": "Feature",
  "properties": {
    "gn:admin1_code":"LA",
    "gn:admin2_code":"107.0",
    "gn:asciiname":"Yucatan Landing",
    "gn:country_code":"US",
    "gn:dem":31,
    "gn:elevation":"21.0",
    "gn:feature_class":"P",
    "gn:feature_code":"PPL",
    "gn:name":"Yucatan Landing",
    "gn:population":0,
    "gn:timezone":"America/Chicago",
    "iso:country":"US",
    "name:fas_x_preferred":[
        "\u06cc\u0648\u06a9\u0627\u062a\u0627\u0646 \u0644\u0646\u062f\u06cc\u0646\u06af"
    ],
    "name:urd_x_preferred":[
        "\u06cc\u0648\u06a9\u062a\u0627\u0646 \u0644\u06cc\u0646\u0688\u0646\u06af"
    ],
    "wof:name":"Yucatan Landing",
    "wof:placetype":"locality"
},
  "geometry": {"coordinates":[-91.154,32.07988],"type":"Point"}
}