{
  "type": "Feature",
  "properties": {
    "gn:admin1_code":"OK",
    "gn:admin2_code":"113",
    "gn:asciiname":"Boulanger Landing",
    "gn:country_code":"US",
    "gn:dem":238,
    "gn:elevation":"229.0",
    "gn:feature_class":"P",
    "gn:feature_code":"PPL",
    "gn:name":"Boulanger Landing",
    "gn:population":0,
    "gn:timezone":"America/Chicago",
    "iso:country":"US",
    "wof:name":"Boulanger Landing",
    "wof:placetype":"locality"
},
  "geometry": {"coordinates":[-96.20027,36.97006],"type":"Point"}
}