{
  "type": "Feature",
  "properties": {
    "iso:country":"US",
    "name:eng_x_preferred":[
        "North Augusta"
    ],
    "name:eng_x_variant":[
        "N Augusta"
    ],
    "qs:gn_adm0_cc":"US",
    "qs:gn_fcode":"PPL",
    "qs:gn_local":4957003,
    "qs:gn_nam_loc":"Augusta, Kennebec, Maine, US",
    "qs:gn_namadm1":"ME",
    "qs:gn_name":"North Augusta",
    "qs:local_max":370,
    "qs:local_sum":370,
    "qs:localhoods":1,
    "qs:name":"North Augusta",
    "qs:name_adm0":"United States",
    "qs:name_adm1":"Maine",
    "qs:name_adm2":"Kennebec",
    "qs:name_local":"Augusta",
    "qs:photo_max":368,
    "qs:photo_sum":370,
    "qs:placetype":"Suburb",
    "qs:quad_count":3,
    "qs:woe_adm0":23424977,
    "qs:woe_adm1":2347578,
    "qs:woe_adm2":12588665,
    "qs:woe_lau":0,
    "qs:woe_local":2357379,
    "qs:woe_ver":"7.10.0",
    "wof:lang":[
        "eng"
    ],
    "wof:name":"North Augusta",
    "wof:placetype":"neighbourhood",
    "wof:population":1463,
    "zs:blockids":[
        230110102001017,
        230110102001002,
        230110102001004,
        230110170002049,
        230110102001015,
        230110102001008,
        230110102004006,
        230110102001013,
        230110102001014,
        230110102001032,
        230110102001031,
        230110170002047,
        230110102001007,
        230110102004008,
        230110170002054,
        230110170002045,
        230110102001027,
        230110102001021,
        230110170002052,
        230110102001006,
        230110102001001,
        230110102001020,
        230110102001029,
        230110102001025,
        230110102001010,
        230110102001028,
        230110102001030,
        230110102001022,
        230110102001023,
        230110170002046,
        230110170002053
    ],
    "zs:housing10":650,
    "zs:pop10":1463
},
  "geometry": {"coordinates":[-69.79472,44.371972],"type":"Point"}
}