{
  "type": "Feature",
  "properties": {
    "gn:admin1_code":"WV",
    "gn:admin2_code":"107",
    "gn:asciiname":"Bonnivale",
    "gn:country_code":"US",
    "gn:dem":191,
    "gn:elevation":"190.0",
    "gn:feature_class":"P",
    "gn:feature_code":"PPL",
    "gn:name":"Bonnivale",
    "gn:population":0,
    "gn:timezone":"America/New_York",
    "iso:country":"US",
    "name:eng_x_preferred":[
        "Bonnivale"
    ],
    "name:und_x_variant":[
        "Bonneyville"
    ],
    "wof:name":"Bonnivale",
    "wof:placetype":"locality"
},
  "geometry": {"coordinates":[-81.50539999999999,39.17424000000001],"type":"Point"}
}