{
  "type": "Feature",
  "properties": {
    "gn:admin1_code":"NE",
    "gn:admin2_code":"45.0",
    "gn:asciiname":"J and L Trailer Court",
    "gn:country_code":"US",
    "gn:dem":1006,
    "gn:elevation":"1012.0",
    "gn:feature_class":"P",
    "gn:feature_code":"PPL",
    "gn:name":"J and L Trailer Court",
    "gn:population":0,
    "gn:timezone":"America/Denver",
    "iso:country":"US",
    "wof:name":"J and L Trailer Court",
    "wof:placetype":"locality"
},
  "geometry": {"coordinates":[-103.06990999999999,42.82942],"type":"Point"}
}