{
  "type": "Feature",
  "properties": {
    "gn:admin1_code":"WY",
    "gn:admin2_code":"7.0",
    "gn:asciiname":"McFadden",
    "gn:country_code":"US",
    "gn:dem":2213,
    "gn:elevation":"2215.0",
    "gn:feature_class":"P",
    "gn:feature_code":"PPL",
    "gn:name":"McFadden",
    "gn:population":0,
    "gn:timezone":"America/Denver",
    "iso:country":"US",
    "name:ces_x_preferred":[
        "McFadden"
    ],
    "name:deu_x_preferred":[
        "McFadden"
    ],
    "name:eng_x_preferred":[
        "McFadden"
    ],
    "name:fra_x_preferred":[
        "McFadden"
    ],
    "name:heb_x_preferred":[
        "\u05de\u05e7\u05e4\u05d0\u05d3\u05df"
    ],
    "name:ita_x_preferred":[
        "McFadden"
    ],
    "name:jpn_x_preferred":[
        "\u30de\u30af\u30d5\u30a1\u30c7\u30f3"
    ],
    "name:nds_x_preferred":[
        "McFadden"
    ],
    "name:rus_x_preferred":[
        "\u041c\u0430\u043a\u0444\u0430\u0434\u0434\u0435\u043d"
    ],
    "name:und_x_variant":[
        "Ohio City"
    ],
    "wof:name":"McFadden",
    "wof:placetype":"locality"
},
  "geometry": {"coordinates":[-106.13057000000001,41.65441],"type":"Point"}
}