{
  "type": "Feature",
  "properties": {
    "gn:admin1_code":"MT",
    "gn:admin2_code":"29.0",
    "gn:asciiname":"Jessup",
    "gn:country_code":"US",
    "gn:dem":914,
    "gn:elevation":"912.0",
    "gn:feature_class":"P",
    "gn:feature_code":"PPL",
    "gn:name":"Jessup",
    "gn:population":0,
    "gn:timezone":"America/Denver",
    "iso:country":"US",
    "name:ceb_x_preferred":[
        "Jessup"
    ],
    "name:deu_x_preferred":[
        "Jessup"
    ],
    "name:fra_x_preferred":[
        "Jessup"
    ],
    "name:ita_x_preferred":[
        "Jessup"
    ],
    "name:nds_x_preferred":[
        "Jessup"
    ],
    "name:nld_x_preferred":[
        "Jessup"
    ],
    "name:pol_x_preferred":[
        "Jessup"
    ],
    "name:por_x_preferred":[
        "Jessup"
    ],
    "name:spa_x_preferred":[
        "Jessup"
    ],
    "name:srp_x_preferred":[
        "\u040f\u0435\u0441\u0430\u043f"
    ],
    "name:ukr_x_preferred":[
        "\u0414\u0436\u0435\u0441\u0441\u0430\u043f"
    ],
    "name:vol_x_preferred":[
        "Jessup"
    ],
    "wof:name":"Jessup",
    "wof:placetype":"locality"
},
  "geometry": {"coordinates":[-114.12818,48.21107],"type":"Point"}
}