{
  "type": "Feature",
  "properties": {
    "gn:admin1_code":"PA",
    "gn:admin2_code":"83.0",
    "gn:admin3_code":"57312.0",
    "gn:asciiname":"Prentisvale",
    "gn:country_code":"US",
    "gn:dem":456,
    "gn:elevation":"453.0",
    "gn:feature_class":"P",
    "gn:feature_code":"PPL",
    "gn:name":"Prentisvale",
    "gn:population":0,
    "gn:timezone":"America/New_York",
    "iso:country":"US",
    "name:eng_x_preferred":[
        "Prentisvale"
    ],
    "name:und_x_variant":[
        "Prentiss Vale",
        "Prenticeville"
    ],
    "wof:name":"Prentisvale",
    "wof:placetype":"locality"
},
  "geometry": {"coordinates":[-78.43890999999998,41.9334],"type":"Point"}
}