{
  "type": "Feature",
  "properties": {
    "gn:admin1_code":"MI",
    "gn:admin2_code":"109.0",
    "gn:admin3_code":"40600.0",
    "gn:asciiname":"Johnson Landing",
    "gn:country_code":"US",
    "gn:dem":181,
    "gn:elevation":"176.0",
    "gn:feature_class":"P",
    "gn:feature_code":"PPL",
    "gn:name":"Johnson Landing",
    "gn:population":0,
    "gn:timezone":"America/Detroit",
    "iso:country":"US",
    "name:eng_x_preferred":[
        "Johnson Landing"
    ],
    "name:und_x_variant":[
        "Johnsons Landing"
    ],
    "wof:name":"Johnson Landing",
    "wof:placetype":"locality"
},
  "geometry": {"coordinates":[-87.46566999999997,45.27331],"type":"Point"}
}