{
  "type": "Feature",
  "properties": {
    "gn:admin1_code":"GA",
    "gn:admin2_code":"159.0",
    "gn:asciiname":"Goolsby",
    "gn:country_code":"US",
    "gn:dem":191,
    "gn:elevation":"189.0",
    "gn:feature_class":"P",
    "gn:feature_code":"PPL",
    "gn:name":"Goolsby",
    "gn:population":0,
    "gn:timezone":"America/New_York",
    "iso:country":"US",
    "wof:name":"Goolsby",
    "wof:placetype":"locality"
},
  "geometry": {"coordinates":[-83.62378000000002,33.23540999999999],"type":"Point"}
}