{
  "type": "Feature",
  "properties": {
    "gn:admin1_code":"KY",
    "gn:admin2_code":"135",
    "gn:asciiname":"Carrs",
    "gn:country_code":"US",
    "gn:dem":163,
    "gn:elevation":"164.0",
    "gn:feature_class":"P",
    "gn:feature_code":"PPL",
    "gn:name":"Carrs",
    "gn:population":0,
    "gn:timezone":"America/New_York",
    "iso:country":"US",
    "name:nds_x_preferred":[
        "Carrs"
    ],
    "wof:name":"Carrs",
    "wof:placetype":"locality"
},
  "geometry": {"coordinates":[-83.41934999999999,38.65757],"type":"Point"}
}