{
  "type": "Feature",
  "properties": {
    "gn:admin1_code":"OH",
    "gn:admin2_code":"017",
    "gn:admin3_code":"43050.0",
    "gn:asciiname":"Taylor Village",
    "gn:country_code":"US",
    "gn:dem":261,
    "gn:elevation":"261.0",
    "gn:feature_class":"P",
    "gn:feature_code":"PPL",
    "gn:name":"Taylor Village",
    "gn:population":0,
    "gn:timezone":"America/New_York",
    "iso:country":"US",
    "wof:name":"Taylor Village",
    "wof:placetype":"locality"
},
  "geometry": {"coordinates":[-84.36861,39.38889],"type":"Point"}
}