{
  "type": "Feature",
  "properties": {
    "iso:country":"US",
    "name:eng_x_preferred":[
        "Kalua Ahupua`a"
    ],
    "qs:gn_adm0_cc":"US",
    "qs:gn_local":5856111,
    "qs:gn_nam_loc":"Honoka'a, Hawaii, Hawaii, US",
    "qs:gn_namadm1":"HI",
    "qs:local_max":101,
    "qs:local_sum":275,
    "qs:localhoods":4,
    "qs:name":"Kalua Ahupua`a",
    "qs:name_adm0":"United States",
    "qs:name_adm1":"Hawaii",
    "qs:name_adm2":"Hawaii",
    "qs:name_local":"Honokaa",
    "qs:photo_max":68,
    "qs:photo_sum":95,
    "qs:placetype":"Suburb",
    "qs:quad_count":8,
    "qs:woe_adm0":23424977,
    "qs:woe_adm1":2347570,
    "qs:woe_adm2":12588029,
    "qs:woe_lau":0,
    "qs:woe_local":2423936,
    "qs:woe_ver":"7.10.0",
    "wof:lang":[
        "eng"
    ],
    "wof:name":"Kalua Ahupua`a",
    "wof:placetype":"neighbourhood",
    "wof:population":634,
    "zs:blockids":[
        150010220002063,
        150010219023007,
        150010219021228,
        150010219023010,
        150010220001029,
        150010219023022,
        150010219023011,
        150010219023012,
        150010220002062,
        150010219021254,
        150010219021251,
        150010219023008,
        150010219023020,
        150010220001030,
        150010220002019,
        150010219021220,
        150010219021252,
        150010219021231,
        150010219023009,
        150010219021230,
        150010220002061,
        150010219023021,
        150010219021229,
        150010220002065,
        150010219023024,
        150010219023023,
        150010219021253,
        150010219021250,
        150010220002064
    ],
    "zs:housing10":214,
    "zs:pop10":634
},
  "geometry": {"coordinates":[-155.460623,20.072415],"type":"Point"}
}