{
  "type": "Feature",
  "properties": {
    "gn:admin1_code":"SC",
    "gn:admin2_code":"9.0",
    "gn:asciiname":"Hughes",
    "gn:country_code":"US",
    "gn:dem":47,
    "gn:elevation":"47.0",
    "gn:feature_class":"P",
    "gn:feature_code":"PPL",
    "gn:name":"Hughes",
    "gn:population":0,
    "gn:timezone":"America/New_York",
    "iso:country":"US",
    "name:ara_x_preferred":[
        "\u0647\u064a\u0648\u0632"
    ],
    "name:bel_x_preferred":[
        "\u0425\u2019\u044e\u0437"
    ],
    "name:bre_x_preferred":[
        "Hughes"
    ],
    "name:cat_x_preferred":[
        "Hughes"
    ],
    "name:ceb_x_preferred":[
        "Hughes"
    ],
    "name:ces_x_preferred":[
        "Hughes"
    ],
    "name:deu_x_preferred":[
        "Hughes"
    ],
    "name:fin_x_preferred":[
        "Hughes"
    ],
    "name:fra_x_preferred":[
        "Hughes"
    ],
    "name:heb_x_preferred":[
        "\u05d4\u05d9\u05d5\u05d0\u05e1"
    ],
    "name:heb_x_variant":[
        "\u05d9\u05d5\u05d6"
    ],
    "name:hin_x_preferred":[
        "\u0939\u094d\u092f\u0942\u091c\u093c"
    ],
    "name:hun_x_preferred":[
        "Hughes"
    ],
    "name:ind_x_preferred":[
        "Hughes"
    ],
    "name:ita_x_preferred":[
        "Hughes"
    ],
    "name:jpn_x_preferred":[
        "\u30d2\u30e5\u30fc\u30ba"
    ],
    "name:kor_x_preferred":[
        "\ud734\uc988"
    ],
    "name:nld_x_preferred":[
        "Hughes"
    ],
    "name:pol_x_preferred":[
        "Hughes"
    ],
    "name:por_x_preferred":[
        "Hughes"
    ],
    "name:rus_x_preferred":[
        "\u0425\u044c\u044e\u0437"
    ],
    "name:slv_x_preferred":[
        "Hughes"
    ],
    "name:srp_x_preferred":[
        "\u0425\u0458\u0443\u0437"
    ],
    "name:swe_x_preferred":[
        "Hughes"
    ],
    "name:tur_x_preferred":[
        "Hughes"
    ],
    "name:ukr_x_preferred":[
        "\u0413'\u044e\u0437"
    ],
    "name:urd_x_preferred":[
        "\u06c1\u06cc\u0648\u0633"
    ],
    "name:vie_x_preferred":[
        "Hughes"
    ],
    "wof:name":"Hughes",
    "wof:placetype":"locality"
},
  "geometry": {"coordinates":[-81.01621,33.13655],"type":"Point"}
}