{
  "type": "Feature",
  "properties": {
    "gn:elevation":159,
    "iso:country":"US",
    "name:deu_x_preferred":[
        "The Maples"
    ],
    "name:eng_x_preferred":[
        "The Maples"
    ],
    "qs:gn_adm0_cc":"US",
    "qs:gn_fcode":"PPLX",
    "qs:gn_local":4628735,
    "qs:gn_nam_loc":"hendersonville",
    "qs:gn_namadm1":"TN",
    "qs:gn_name":"The Maples",
    "qs:local_max":573,
    "qs:local_sum":2800,
    "qs:localhoods":15,
    "qs:name":"The Maples",
    "qs:name_adm0":"United States",
    "qs:name_adm1":"Tennessee",
    "qs:name_adm2":"Sumner",
    "qs:name_local":"Hendersonville",
    "qs:photo_max":294,
    "qs:photo_sum":507,
    "qs:placetype":"Suburb",
    "qs:quad_count":15,
    "qs:woe_adm0":23424977,
    "qs:woe_adm1":2347601,
    "qs:woe_adm2":12589994,
    "qs:woe_lau":0,
    "qs:woe_local":2419982,
    "qs:woe_ver":"7.10.0",
    "wd:wordcount":68,
    "wof:name":"The Maples",
    "wof:placetype":"neighbourhood",
    "wof:population":5280,
    "zs:blockids":[
        471650212042017,
        471650212043030,
        471650212043011,
        471650212052049,
        471650212042006,
        471650212052044,
        471650212043014,
        471650212042022,
        471650212043019,
        471650212042002,
        471650212043032,
        471650212043024,
        471650212042013,
        471650212043000,
        471650212043009,
        471650212011003,
        471650212043031,
        471650212043010,
        471650212043018,
        471650212043007,
        471650212043020,
        471650212052048,
        471650212052036,
        471650212052014,
        471650212042016,
        471650212042000,
        471650212052042,
        471650212042021,
        471650212052026,
        471650212042024,
        471650212052046,
        471650212043026,
        471650212043003,
        471650212043008,
        471650212043004,
        471650212043017,
        471650212042001,
        471650212041020,
        471650212052022,
        471650212042007,
        471650212052016,
        471650212043021,
        471650212042005,
        471650212042014,
        471650212042018,
        471650212042012,
        471650212042008,
        471650212042025,
        471650212043027,
        471650212043012,
        471650212043033,
        471650212043001,
        471650212042009,
        471650212042015,
        471650212043002,
        471650212042020,
        471650212042010,
        471650212052023,
        471650212043023,
        471650212011000,
        471650212043013,
        471650212042011,
        471650212052051,
        471650212043029,
        471650212043015,
        471650212042019,
        471650212052034,
        471650212042004,
        471650212043025,
        471650212043016,
        471650212052043,
        471650212052050,
        471650212042023,
        471650212042003,
        471650212043028,
        471650212043005,
        471650212043006
    ],
    "zs:housing10":2233,
    "zs:pop10":5280
},
  "geometry": {"coordinates":[-86.583068,36.307566],"type":"Point"}
}