{
  "type": "Feature",
  "properties": {
    "gn:admin1_code":"PA",
    "gn:admin2_code":"33.0",
    "gn:admin3_code":"29224.0",
    "gn:asciiname":"Surveyor",
    "gn:country_code":"US",
    "gn:dem":331,
    "gn:elevation":"329.0",
    "gn:feature_class":"P",
    "gn:feature_code":"PPL",
    "gn:name":"Surveyor",
    "gn:population":0,
    "gn:timezone":"America/New_York",
    "iso:country":"US",
    "wof:name":"Surveyor",
    "wof:placetype":"locality"
},
  "geometry": {"coordinates":[-78.32557,41.07395],"type":"Point"}
}