{
  "type": "Feature",
  "properties": {
    "gn:admin1_code":"WI",
    "gn:admin2_code":"115.0",
    "gn:admin3_code":"34025.0",
    "gn:asciiname":"Lyndhurst",
    "gn:country_code":"US",
    "gn:dem":291,
    "gn:elevation":"290.0",
    "gn:feature_class":"P",
    "gn:feature_code":"PPL",
    "gn:name":"Lyndhurst",
    "gn:population":0,
    "gn:timezone":"America/Chicago",
    "iso:country":"US",
    "name:fas_x_preferred":[
        "\u0644\u06cc\u0646\u062f\u0647\u0631\u0633\u062a"
    ],
    "name:fra_x_preferred":[
        "Lyndhurst"
    ],
    "wof:name":"Lyndhurst",
    "wof:placetype":"locality"
},
  "geometry": {"coordinates":[-88.81260999999998,44.84192],"type":"Point"}
}