{
  "type": "Feature",
  "properties": {
    "gn:admin1_code":"FL",
    "gn:admin2_code":"57",
    "gn:asciiname":"Lake Marie Mobile Estates",
    "gn:country_code":"US",
    "gn:dem":17,
    "gn:elevation":"9.0",
    "gn:feature_class":"P",
    "gn:feature_code":"PPL",
    "gn:name":"Lake Marie Mobile Estates",
    "gn:population":0,
    "gn:timezone":"America/New_York",
    "iso:country":"US",
    "wof:name":"Lake Marie Mobile Estates",
    "wof:placetype":"locality"
},
  "geometry": {"coordinates":[-82.32080000000001,27.9956],"type":"Point"}
}