{
  "type": "Feature",
  "properties": {
    "gn:admin1_code":"FL",
    "gn:admin2_code":"127.0",
    "gn:asciiname":"Cow Creek",
    "gn:country_code":"US",
    "gn:dem":10,
    "gn:elevation":"6.0",
    "gn:feature_class":"P",
    "gn:feature_code":"PPL",
    "gn:name":"Cow Creek",
    "gn:population":0,
    "gn:timezone":"America/New_York",
    "iso:country":"US",
    "name:zho_x_preferred":[
        "\u8003\u514b\u91cc\u514b"
    ],
    "wof:name":"Cow Creek",
    "wof:placetype":"locality"
},
  "geometry": {"coordinates":[-81.02755999999999,28.83749000000001],"type":"Point"}
}