{
  "type": "Feature",
  "properties": {
    "gn:admin1_code":"FL",
    "gn:admin2_code":"57",
    "gn:asciiname":"McGrady Estates",
    "gn:country_code":"US",
    "gn:dem":36,
    "gn:elevation":"32.0",
    "gn:feature_class":"P",
    "gn:feature_code":"PPL",
    "gn:name":"McGrady Estates",
    "gn:population":0,
    "gn:timezone":"America/New_York",
    "iso:country":"US",
    "wof:name":"McGrady Estates",
    "wof:placetype":"locality"
},
  "geometry": {"coordinates":[-82.27679999999999,27.7605],"type":"Point"}
}