{
  "type": "Feature",
  "properties": {
    "gn:admin1_code":"TX",
    "gn:admin2_code":"61.0",
    "gn:asciiname":"Angel Haven Colonia",
    "gn:country_code":"US",
    "gn:dem":12,
    "gn:elevation":"8.0",
    "gn:feature_class":"P",
    "gn:feature_code":"PPL",
    "gn:name":"Angel Haven Colonia",
    "gn:population":0,
    "gn:timezone":"America/Chicago",
    "iso:country":"US",
    "wof:name":"Angel Haven Colonia",
    "wof:placetype":"locality"
},
  "geometry": {"coordinates":[-97.43026,25.8673],"type":"Point"}
}