{
  "type": "Feature",
  "properties": {
    "iso:country":"US",
    "name:deu_x_preferred":[
        "Freedmen's town"
    ],
    "name:eng_x_preferred":[
        "Freedman's Town"
    ],
    "name:eng_x_variant":[
        "Freedmen's town",
        "freedmen's town"
    ],
    "wd:wordcount":156,
    "wof:name":"Freedman's Town",
    "wof:placetype":"neighbourhood",
    "wof:population":1808,
    "zs:area_m":632905.828238,
    "zs:blockids":[
        481130022001021,
        481130016001031,
        481130016001045,
        481130016002038,
        481130016002042,
        481130016001016,
        481130016001008,
        481130016001027,
        481130022001002,
        481130016001006,
        481130016001013,
        481130016002029,
        481130016001028,
        481130016001047,
        481130022001022,
        481130016002039,
        481130016001009,
        481130016001014,
        481130016001030,
        481130016001032,
        481130022001018,
        481130022001039,
        481130022001019,
        481130016001017,
        481130016001004,
        481130016001034,
        481130016001011,
        481130022001038,
        481130022001003,
        481130016001046,
        481130016001012,
        481130022001035,
        481130016001010,
        481130016001029,
        481130016001033,
        481130016001003,
        481130016001005,
        481130016001015,
        481130016002041,
        481130016001007,
        481130016001035,
        481130022001034
    ],
    "zs:housing10":1256,
    "zs:label":"Freedman's Town",
    "zs:pop10":1808
},
  "geometry": {"coordinates":[-96.788068,32.794915],"type":"Point"}
}