{
  "type": "Feature",
  "properties": {
    "gn:admin1_code":"KY",
    "gn:admin2_code":"17",
    "gn:asciiname":"Bunker Hill",
    "gn:country_code":"US",
    "gn:dem":304,
    "gn:elevation":"303.0",
    "gn:feature_class":"P",
    "gn:feature_code":"PPL",
    "gn:name":"Bunker Hill",
    "gn:population":0,
    "gn:timezone":"America/New_York",
    "iso:country":"US",
    "name:ceb_x_preferred":[
        "Bunker Hill"
    ],
    "name:deu_x_preferred":[
        "Bunker Hill"
    ],
    "name:fra_x_preferred":[
        "Bunker Hill"
    ],
    "name:hun_x_preferred":[
        "Bunker Hill"
    ],
    "name:ita_x_preferred":[
        "Bunker Hill"
    ],
    "name:jpn_x_preferred":[
        "\u30d0\u30f3\u30ab\u30fc\u30fb\u30d2\u30eb"
    ],
    "name:nld_x_preferred":[
        "Bunker Hill"
    ],
    "name:pol_x_preferred":[
        "Bunker Hill"
    ],
    "name:por_x_preferred":[
        "Bunker Hill"
    ],
    "name:srp_x_preferred":[
        "\u0411\u0430\u043d\u043a\u0435\u0440 \u0425\u0438\u043b"
    ],
    "name:swe_x_preferred":[
        "Bunker Hill"
    ],
    "name:ukr_x_preferred":[
        "\u0411\u0430\u043d\u043a\u0435\u0440-\u0413\u0456\u043b\u043b"
    ],
    "name:vol_x_preferred":[
        "Bunker Hill"
    ],
    "name:zho_x_preferred":[
        "\u90a6\u514b\u5c71"
    ],
    "wof:name":"Bunker Hill",
    "wof:placetype":"locality"
},
  "geometry": {"coordinates":[-84.01298,38.16397],"type":"Point"}
}