{
  "type": "Feature",
  "properties": {
    "iso:country":"US",
    "name:ceb_x_preferred":[
        "Black Canyon"
    ],
    "name:eng_x_preferred":[
        "Black Canyon"
    ],
    "name:fra_x_preferred":[
        "Black Canyon"
    ],
    "name:swe_x_preferred":[
        "Black Canyon"
    ],
    "wd:wordcount":114,
    "wof:name":"Black Canyon",
    "wof:placetype":"neighbourhood",
    "wof:population":1472,
    "zs:area_m":3334448.677158,
    "zs:blockids":[
        60411101002010,
        60411101001022,
        60411101001005,
        60411101001001,
        60411101002002,
        60411101002008,
        60411101001003,
        60411101002001,
        60411101002009,
        60411101002000,
        60411101001006,
        60411101002007,
        60411101002011,
        60411101002003,
        60411101001004,
        60411101001012,
        60411101001002,
        60411101001007
    ],
    "zs:housing10":388,
    "zs:label":"Black Canyon",
    "zs:pop10":1472
},
  "geometry": {"coordinates":[-122.506304,37.986231],"type":"Point"}
}