{
  "type": "Feature",
  "properties": {
    "gn:admin1_code":"OH",
    "gn:admin2_code":"173.0",
    "gn:admin3_code":"62162.0",
    "gn:asciiname":"Starbright Addition",
    "gn:country_code":"US",
    "gn:dem":190,
    "gn:elevation":"190.0",
    "gn:feature_class":"P",
    "gn:feature_code":"PPL",
    "gn:name":"Starbright Addition",
    "gn:population":0,
    "gn:timezone":"America/New_York",
    "iso:country":"US",
    "wof:name":"Starbright Addition",
    "wof:placetype":"locality"
},
  "geometry": {"coordinates":[-83.53493,41.567],"type":"Point"}
}