{
  "type": "Feature",
  "properties": {
    "iso:country":"US",
    "name:eng_x_preferred":[
        "Northeast Yonkers"
    ],
    "qs:gn_adm0_cc":"US",
    "qs:gn_local":5145215,
    "qs:gn_nam_loc":"Yonkers, Westchester, New York, US",
    "qs:gn_namadm1":"NY",
    "qs:local_max":978,
    "qs:local_sum":3911,
    "qs:localhoods":16,
    "qs:name":"Northeast Yonkers",
    "qs:name_adm0":"United States",
    "qs:name_adm1":"New York",
    "qs:name_adm2":"Westchester",
    "qs:name_local":"Yonkers",
    "qs:photo_max":63,
    "qs:photo_sum":87,
    "qs:placetype":"Suburb",
    "qs:quad_count":11,
    "qs:woe_adm0":23424977,
    "qs:woe_adm1":2347591,
    "qs:woe_adm2":12589371,
    "qs:woe_funk":"Grouping neighborhood",
    "qs:woe_lau":0,
    "qs:woe_local":2524811,
    "qs:woe_ver":"7.10.0",
    "wof:lang":[
        "eng"
    ],
    "wof:name":"Northeast Yonkers",
    "wof:placetype":"neighbourhood",
    "wof:population":3435,
    "zs:blockids":[
        361190022011017,
        361190022012016,
        361190020004004,
        361190020005016,
        361190020004005,
        361190022011007,
        361190022011009,
        361190022011022,
        361190020003004,
        361190022011005,
        361190022011004,
        361190022011011,
        361190021041012,
        361190021041016,
        361190020005026,
        361190022011018,
        361190022011023,
        361190022011024,
        361190021042039,
        361190022011012,
        361190022011013,
        361190021044000,
        361190020004006,
        361190022011019,
        361190022012020,
        361190022011021,
        361190020004010,
        361190020003003,
        361190022011027,
        361190022011016,
        361190020004000,
        361190021044001,
        361190022012006,
        361190022012007,
        361190021042029,
        361190021044002,
        361190022011026,
        361190020004001,
        361190021042031,
        361190021042036,
        361190022011006,
        361190020005028,
        361190020005027,
        361190022011008,
        361190020004011,
        361190020005023,
        361190020004003,
        361190020005024,
        361190022012012,
        361190020004002,
        361190020005025,
        361190021044003,
        361190020004009,
        361190022011025,
        361190022011010,
        361190022011020,
        361190020003005,
        361190021042030,
        361190021042040
    ],
    "zs:housing10":1399,
    "zs:pop10":3435
},
  "geometry": {"coordinates":[-73.823616,40.99263],"type":"Point"}
}