{
  "type": "Feature",
  "properties": {
    "gn:admin1_code":"MN",
    "gn:admin2_code":"61.0",
    "gn:admin3_code":"25118.0",
    "gn:asciiname":"Huhn Addition Mobile Home Court",
    "gn:country_code":"US",
    "gn:dem":400,
    "gn:elevation":"398.0",
    "gn:feature_class":"P",
    "gn:feature_code":"PPL",
    "gn:name":"Huhn Addition Mobile Home Court",
    "gn:population":0,
    "gn:timezone":"America/Chicago",
    "iso:country":"US",
    "wof:name":"Huhn Addition Mobile Home Court",
    "wof:placetype":"campus"
},
  "geometry": {"coordinates":[-93.51222,47.23944],"type":"Point"}
}