{
  "type": "Feature",
  "properties": {
    "gn:admin1_code":"MD",
    "gn:admin2_code":"15.0",
    "gn:asciiname":"Principio",
    "gn:country_code":"US",
    "gn:dem":93,
    "gn:elevation":"93.0",
    "gn:feature_class":"P",
    "gn:feature_code":"PPL",
    "gn:name":"Principio",
    "gn:population":0,
    "gn:timezone":"America/New_York",
    "iso:country":"US",
    "wof:name":"Principio",
    "wof:placetype":"locality"
},
  "geometry": {"coordinates":[-76.038,39.65067],"type":"Point"}
}