{
  "type": "Feature",
  "properties": {
    "gn:admin1_code":"AR",
    "gn:admin2_code":"69.0",
    "gn:admin3_code":"90399.0",
    "gn:asciiname":"Wright",
    "gn:country_code":"US",
    "gn:dem":68,
    "gn:elevation":"67.0",
    "gn:feature_class":"P",
    "gn:feature_code":"PPL",
    "gn:name":"Wright",
    "gn:population":0,
    "gn:timezone":"America/Chicago",
    "iso:country":"US",
    "name:eng_x_preferred":[
        "Wright"
    ],
    "name:fas_x_preferred":[
        "\u0631\u0627\u06cc\u062a"
    ],
    "name:hat_x_preferred":[
        "Wright"
    ],
    "name:und_x_variant":[
        "Greer"
    ],
    "name:zho_x_preferred":[
        "\u8cf4\u7279"
    ],
    "wof:name":"Wright",
    "wof:placetype":"locality"
},
  "geometry": {"coordinates":[-92.06625,34.4351],"type":"Point"}
}