{
  "type": "Feature",
  "properties": {
    "gn:admin1_code":"MS",
    "gn:admin2_code":"57.0",
    "gn:asciiname":"Dorsey",
    "gn:country_code":"US",
    "gn:dem":120,
    "gn:elevation":"116.0",
    "gn:feature_class":"P",
    "gn:feature_code":"PPL",
    "gn:name":"Dorsey",
    "gn:population":0,
    "gn:timezone":"America/Chicago",
    "iso:country":"US",
    "wof:name":"Dorsey",
    "wof:placetype":"locality"
},
  "geometry": {"coordinates":[-88.50976999999997,34.25205],"type":"Point"}
}