{
  "type": "Feature",
  "properties": {
    "gn:admin1_code":"TX",
    "gn:admin2_code":"87.0",
    "gn:asciiname":"New Loco",
    "gn:country_code":"US",
    "gn:dem":570,
    "gn:elevation":"568.0",
    "gn:feature_class":"P",
    "gn:feature_code":"PPL",
    "gn:name":"New Loco",
    "gn:population":0,
    "gn:timezone":"America/Chicago",
    "iso:country":"US",
    "wof:name":"New Loco",
    "wof:placetype":"locality"
},
  "geometry": {"coordinates":[-100.20623000000001,34.74839],"type":"Point"}
}