{
  "type": "Feature",
  "properties": {
    "gn:elevation":5,
    "iso:country":"US",
    "name:eng_x_preferred":[
        "Hartford-Brainard Airport"
    ],
    "name:eng_x_variant":[
        "HFD",
        "KHFD"
    ],
    "name:fas_x_preferred":[
        "\u0641\u0631\u0648\u062f\u06af\u0627\u0647 \u0647\u0627\u0631\u062a\u0641\u0631\u062f-\u0628\u0631\u0627\u06cc\u0646\u0627\u0631\u062f"
    ],
    "name:tgk_x_preferred":[
        "\u0424\u0443\u0440\u0443\u0434\u0433\u043e\u04b3\u0438 \u04b3\u043e\u0440\u0442\u0444\u0440\u0434-\u0431\u0440\u043e\u0438\u043d\u043e\u0440\u0434"
    ],
    "name:und_x_variant":[
        "Brainard Airport"
    ],
    "wd:wordcount":270,
    "woe:hierarchy":{
        "country_id":23424977,
        "county_id":12587792,
        "planet_id":1,
        "state_id":2347565,
        "suburb_id":55859595
    },
    "wof:name":"Hartford-Brainard Airport",
    "wof:placetype":"campus"
},
  "geometry": {"coordinates":[-72.64958,41.74119],"type":"Point"}
}