{
  "type": "Feature",
  "properties": {
    "gn:admin1_code":"NY",
    "gn:admin2_code":"19.0",
    "gn:admin3_code":"1583.0",
    "gn:asciiname":"Alder Bend",
    "gn:country_code":"US",
    "gn:dem":299,
    "gn:elevation":"300.0",
    "gn:feature_class":"P",
    "gn:feature_code":"PPL",
    "gn:name":"Alder Bend",
    "gn:population":0,
    "gn:timezone":"America/New_York",
    "iso:country":"US",
    "wof:name":"Alder Bend",
    "wof:placetype":"locality"
},
  "geometry": {"coordinates":[-73.72098000000003,44.84809],"type":"Point"}
}