{
  "type": "Feature",
  "properties": {
    "gn:admin1_code":"MD",
    "gn:admin2_code":"13.0",
    "gn:asciiname":"Forest Oaks",
    "gn:country_code":"US",
    "gn:dem":165,
    "gn:elevation":"165.0",
    "gn:feature_class":"P",
    "gn:feature_code":"PPL",
    "gn:name":"Forest Oaks",
    "gn:population":0,
    "gn:timezone":"America/New_York",
    "iso:country":"US",
    "wof:name":"Forest Oaks",
    "wof:placetype":"locality"
},
  "geometry": {"coordinates":[-76.91664,39.40344],"type":"Point"}
}