{
  "type": "Feature",
  "properties": {
    "gn:admin1_code":"ID",
    "gn:admin2_code":"13.0",
    "gn:asciiname":"DeWoff",
    "gn:country_code":"US",
    "gn:dem":1308,
    "gn:elevation":"1309.0",
    "gn:feature_class":"P",
    "gn:feature_code":"PPL",
    "gn:name":"DeWoff",
    "gn:population":0,
    "gn:timezone":"America/Boise",
    "iso:country":"US",
    "wof:name":"DeWoff",
    "wof:placetype":"locality"
},
  "geometry": {"coordinates":[-113.26056,42.70658],"type":"Point"}
}