{
  "type": "Feature",
  "properties": {
    "gn:admin1_code":"MS",
    "gn:admin2_code":"123.0",
    "gn:asciiname":"Branch",
    "gn:country_code":"US",
    "gn:dem":127,
    "gn:elevation":"125.0",
    "gn:feature_class":"P",
    "gn:feature_code":"PPL",
    "gn:name":"Branch",
    "gn:population":0,
    "gn:timezone":"America/Chicago",
    "iso:country":"US",
    "name:ara_x_preferred":[
        "\u063a\u0635\u0646"
    ],
    "name:arg_x_preferred":[
        "Rama"
    ],
    "name:bel_x_preferred":[
        "\u0413\u0430\u043b\u0456\u043d\u0430"
    ],
    "name:cat_x_preferred":[
        "Branca"
    ],
    "name:ces_x_preferred":[
        "V\u011btev"
    ],
    "name:dan_x_preferred":[
        "Gren"
    ],
    "name:deu_x_preferred":[
        "Ast"
    ],
    "name:eng_x_preferred":[
        "Branch"
    ],
    "name:epo_x_preferred":[
        "Bran\u0109o"
    ],
    "name:est_x_preferred":[
        "Oks"
    ],
    "name:eus_x_preferred":[
        "Adar"
    ],
    "name:fas_x_preferred":[
        "\u0634\u0627\u062e\u0647"
    ],
    "name:fin_x_preferred":[
        "Oksa"
    ],
    "name:fra_x_preferred":[
        "Branche"
    ],
    "name:fry_x_preferred":[
        "T\u00fbke"
    ],
    "name:gle_x_preferred":[
        "Craobh"
    ],
    "name:glg_x_preferred":[
        "P\u00f3la"
    ],
    "name:hat_x_preferred":[
        "Branch"
    ],
    "name:heb_x_preferred":[
        "\u05e2\u05e0\u05e3"
    ],
    "name:hin_x_preferred":[
        "\u0936\u093e\u0916\u093e"
    ],
    "name:ido_x_preferred":[
        "Brancho"
    ],
    "name:ina_x_preferred":[
        "Ramo"
    ],
    "name:ita_x_preferred":[
        "Ramo"
    ],
    "name:jpn_x_preferred":[
        "\u5206\u679d"
    ],
    "name:kaz_x_preferred":[
        "\u0411\u04b1\u0442\u0430\u049b"
    ],
    "name:kor_x_preferred":[
        "\uac00\uc9c0"
    ],
    "name:lat_x_preferred":[
        "Ramus"
    ],
    "name:lit_x_preferred":[
        "\u0160aka"
    ],
    "name:lmo_x_preferred":[
        "Ram"
    ],
    "name:mal_x_preferred":[
        "\u0d36\u0d3e\u0d16"
    ],
    "name:mzn_x_preferred":[
        "\u0686\u0644\u0647"
    ],
    "name:nap_x_preferred":[
        "Rame"
    ],
    "name:nld_x_preferred":[
        "Tak"
    ],
    "name:nno_x_preferred":[
        "Grein"
    ],
    "name:nrm_x_preferred":[
        "Braunque"
    ],
    "name:oss_x_preferred":[
        "\u041a\u044a\u0430\u043b\u0438\u0443"
    ],
    "name:pol_x_preferred":[
        "Ga\u0142\u0105\u017a"
    ],
    "name:por_x_preferred":[
        "Ramo"
    ],
    "name:que_x_preferred":[
        "K'allma"
    ],
    "name:rus_x_preferred":[
        "\u0412\u0435\u0442\u0432\u044c"
    ],
    "name:sah_x_preferred":[
        "\u0421\u0430\u043b\u0430\u0430"
    ],
    "name:sco_x_preferred":[
        "Brainch"
    ],
    "name:slk_x_preferred":[
        "Kon\u00e1r"
    ],
    "name:som_x_preferred":[
        "Laan"
    ],
    "name:spa_x_preferred":[
        "Rama"
    ],
    "name:swe_x_preferred":[
        "Gren"
    ],
    "name:tel_x_preferred":[
        "\u0c15\u0c4a\u0c2e\u0c4d\u0c2e"
    ],
    "name:tgk_x_preferred":[
        "\u041d\u0430\u0432\u0434\u0430"
    ],
    "name:ukr_x_preferred":[
        "\u0413\u0456\u043b\u043a\u0430"
    ],
    "name:und_x_variant":[
        "Groveton"
    ],
    "wof:name":"Branch",
    "wof:placetype":"locality"
},
  "geometry": {"coordinates":[-89.71146,32.43042],"type":"Point"}
}