{
  "type": "Feature",
  "properties": {
    "gn:country":"US",
    "gn:fcode":"PPL",
    "gn:population":1320,
    "iso:country":"US",
    "name:ceb_x_preferred":[
        "Mountain Village"
    ],
    "name:fra_x_preferred":[
        "Mountain Village"
    ],
    "name:ita_x_preferred":[
        "Mountain Village"
    ],
    "name:nld_x_preferred":[
        "Mountain Village"
    ],
    "name:pol_x_preferred":[
        "Mountain Village"
    ],
    "name:por_x_preferred":[
        "Mountain Village"
    ],
    "name:spa_x_preferred":[
        "Mountain Village"
    ],
    "name:srp_x_preferred":[
        "\u041c\u0430\u0443\u043d\u0442\u0438\u043d \u0412\u0438\u043b\u0438\u045f"
    ],
    "name:ukr_x_preferred":[
        "\u041c\u0430\u0443\u043d\u0442\u0435\u043d-\u0412\u0456\u043b\u043b\u0435\u0434\u0436"
    ],
    "qs_pg:aaroncc":"US",
    "qs_pg:gn_country":"US",
    "qs_pg:gn_fcode":"PPL",
    "qs_pg:gn_pop":1320,
    "qs_pg:name":"Mountain Village",
    "qs_pg:name_adm0":"United States",
    "qs_pg:name_adm1":"Colorado",
    "qs_pg:photos":127,
    "qs_pg:photos_1k":26,
    "qs_pg:photos_9k":1,
    "qs_pg:photos_9r":3,
    "qs_pg:photos_all":127,
    "qs_pg:photos_sr":3,
    "qs_pg:pop_sr":3,
    "qs_pg:qs_pg_placetype":"neighbourhood",
    "qs_pg:qs_pg_placetype_gp":"Suburb",
    "qs_pg:woe_adm0":23424977,
    "woe:adm0_id":23424977,
    "woe:name_adm0":"United States",
    "woe:name_adm1":"Colorado",
    "woe:placetype":"Suburb",
    "wof:name":"Mountain Village",
    "wof:placetype":"neighbourhood",
    "wof:population":1320
},
  "geometry": {"coordinates":[-107.85645,37.93138],"type":"Point"}
}