{
  "type": "Feature",
  "properties": {
    "gn:country":"US",
    "gn:fcode":"PPL",
    "gn:population":1320,
    "iso:country":"US",
    "name:ben_x_preferred":[
        "\u09ae\u09be\u0989\u09a8\u09cd\u099f\u09c7\u09a8 \u09ad\u09bf\u09b2\u09c7\u099c"
    ],
    "name:ceb_x_preferred":[
        "Mountain Village"
    ],
    "name:ell_x_preferred":[
        "\u039c\u03ac\u03bf\u03c5\u03bd\u03c4\u03b5\u03bd \u0392\u03af\u03bb\u03b1\u03c4\u03b6"
    ],
    "name:fra_x_preferred":[
        "Mountain Village"
    ],
    "name:heb_x_preferred":[
        "\u05de\u05d0\u05d5\u05e0\u05d8\u05d9\u05d9\u05df \u05d5\u05d5\u05d9\u05dc\u05d2'"
    ],
    "name:hin_x_preferred":[
        "\u092e\u093e\u0909\u0902\u091f\u0947\u0928 \u0935\u093f\u0932\u0947\u091c"
    ],
    "name:hun_x_preferred":[
        "Mountain Village"
    ],
    "name:ind_x_preferred":[
        "Mountain Village"
    ],
    "name:ita_x_preferred":[
        "Mountain Village"
    ],
    "name:jpn_x_preferred":[
        "\u30de\u30a6\u30f3\u30c6\u30f3\u30d3\u30ec\u30c3\u30b8"
    ],
    "name:kor_x_preferred":[
        "\ub9c8\uc6b4\ud2f4 \ube4c\ub9ac\uc9c0"
    ],
    "name:nld_x_preferred":[
        "Mountain Village"
    ],
    "name:pol_x_preferred":[
        "Mountain Village"
    ],
    "name:por_x_preferred":[
        "Mountain Village"
    ],
    "name:spa_x_preferred":[
        "Mountain Village"
    ],
    "name:srp_x_preferred":[
        "\u041c\u0430\u0443\u043d\u0442\u0438\u043d \u0412\u0438\u043b\u0438\u045f"
    ],
    "name:swe_x_preferred":[
        "Mountain Village"
    ],
    "name:tur_x_preferred":[
        "Mountain Village"
    ],
    "name:ukr_x_preferred":[
        "\u041c\u0430\u0443\u043d\u0442\u0435\u043d-\u0412\u0456\u043b\u043b\u0435\u0434\u0436"
    ],
    "name:urd_x_preferred":[
        "\u0645\u0627\u0624\u0646\u0679\u06cc\u0646 \u0648\u0644\u06cc\u062c"
    ],
    "name:vie_x_preferred":[
        "Mountain Village"
    ],
    "qs_pg:aaroncc":"US",
    "qs_pg:gn_country":"US",
    "qs_pg:gn_fcode":"PPL",
    "qs_pg:gn_pop":1320,
    "qs_pg:name":"Mountain Village",
    "qs_pg:name_adm0":"United States",
    "qs_pg:name_adm1":"Colorado",
    "qs_pg:photos":127,
    "qs_pg:photos_1k":26,
    "qs_pg:photos_9k":1,
    "qs_pg:photos_9r":3,
    "qs_pg:photos_all":127,
    "qs_pg:photos_sr":3,
    "qs_pg:pop_sr":3,
    "qs_pg:qs_pg_placetype":"neighbourhood",
    "qs_pg:qs_pg_placetype_gp":"Suburb",
    "qs_pg:woe_adm0":23424977,
    "woe:adm0_id":23424977,
    "woe:name_adm0":"United States",
    "woe:name_adm1":"Colorado",
    "woe:placetype":"Suburb",
    "wof:name":"Mountain Village",
    "wof:placetype":"neighbourhood",
    "wof:population":1320
},
  "geometry": {"coordinates":[-107.85645,37.93138],"type":"Point"}
}