{
  "type": "Feature",
  "properties": {
    "gn:admin1_code":"NC",
    "gn:admin2_code":"133",
    "gn:admin3_code":"93160.0",
    "gn:asciiname":"Fulcher Landing",
    "gn:country_code":"US",
    "gn:dem":1,
    "gn:elevation":"1.0",
    "gn:feature_class":"P",
    "gn:feature_code":"PPL",
    "gn:name":"Fulcher Landing",
    "gn:population":0,
    "gn:timezone":"America/New_York",
    "iso:country":"US",
    "name:eng_x_preferred":[
        "Fulcher Landing"
    ],
    "name:und_x_variant":[
        "Fulchers Landing"
    ],
    "wof:name":"Fulcher Landing",
    "wof:placetype":"locality"
},
  "geometry": {"coordinates":[-77.38274,34.56544],"type":"Point"}
}