{
  "type": "Feature",
  "properties": {
    "gn:admin1_code":"LA",
    "gn:admin2_code":"111.0",
    "gn:asciiname":"Randolph",
    "gn:country_code":"US",
    "gn:dem":46,
    "gn:elevation":"39.0",
    "gn:feature_class":"P",
    "gn:feature_code":"PPL",
    "gn:name":"Randolph",
    "gn:population":0,
    "gn:timezone":"America/Chicago",
    "iso:country":"US",
    "name:ara_x_preferred":[
        "\u0631\u0627\u0646\u062f\u0648\u0644\u0641"
    ],
    "name:cat_x_preferred":[
        "Randolph"
    ],
    "name:ceb_x_preferred":[
        "Randolph"
    ],
    "name:ces_x_preferred":[
        "Randolph"
    ],
    "name:deu_x_preferred":[
        "Randolph"
    ],
    "name:fra_x_preferred":[
        "Randolph"
    ],
    "name:heb_x_preferred":[
        "\u05e8\u05e0\u05d3\u05d5\u05dc\u05e3"
    ],
    "name:ita_x_preferred":[
        "Randolph"
    ],
    "name:jpn_x_preferred":[
        "\u30e9\u30f3\u30c9\u30eb\u30d5"
    ],
    "name:kor_x_preferred":[
        "\ub79c\ub3cc\ud504"
    ],
    "name:nld_x_preferred":[
        "Randolph"
    ],
    "name:pol_x_preferred":[
        "Randolph"
    ],
    "name:por_x_preferred":[
        "Randolph"
    ],
    "name:rus_x_preferred":[
        "\u0420\u044d\u043d\u0434\u043e\u043b\u044c\u0444"
    ],
    "name:spa_x_preferred":[
        "Randolph"
    ],
    "name:srp_x_preferred":[
        "\u0420\u0430\u043d\u0434\u043e\u043b\u0444"
    ],
    "name:swe_x_preferred":[
        "Randolph"
    ],
    "name:ukr_x_preferred":[
        "\u0420\u0435\u043d\u0434\u043e\u043b\u0444"
    ],
    "name:urd_x_preferred":[
        "\u0631\u06cc\u0646\u0688\u0648\u0644\u0641"
    ],
    "name:vol_x_preferred":[
        "Randolph"
    ],
    "wof:name":"Randolph",
    "wof:placetype":"locality"
},
  "geometry": {"coordinates":[-92.69043000000001,32.98653],"type":"Point"}
}