{
  "type": "Feature",
  "properties": {
    "gn:admin1_code":"PA",
    "gn:admin2_code":"45",
    "gn:admin3_code":"54224.0",
    "gn:asciiname":"Springton Pointe",
    "gn:country_code":"US",
    "gn:dem":97,
    "gn:elevation":"92.0",
    "gn:feature_class":"P",
    "gn:feature_code":"PPL",
    "gn:name":"Springton Pointe",
    "gn:population":0,
    "gn:timezone":"America/New_York",
    "iso:country":"US",
    "wof:name":"Springton Pointe",
    "wof:placetype":"locality"
},
  "geometry": {"coordinates":[-75.4135,39.9634],"type":"Point"}
}