{
  "type": "Feature",
  "properties": {
    "gn:admin1_code":"MD",
    "gn:admin2_code":"21.0",
    "gn:asciiname":"Sidmar",
    "gn:country_code":"US",
    "gn:dem":154,
    "gn:elevation":"158.0",
    "gn:feature_class":"P",
    "gn:feature_code":"PPL",
    "gn:name":"Sidmar",
    "gn:population":0,
    "gn:timezone":"America/New_York",
    "iso:country":"US",
    "wof:name":"Sidmar",
    "wof:placetype":"locality"
},
  "geometry": {"coordinates":[-77.26304,39.55343],"type":"Point"}
}