{
  "type": "Feature",
  "properties": {
    "iso:country":"US",
    "name:eng_x_preferred":[
        "Beacon Groves"
    ],
    "wof:name":"Beacon Groves",
    "wof:placetype":"neighbourhood",
    "wof:population":4185,
    "zs:area_m":3023052.132662,
    "zs:blockids":[
        121030273161008,
        121030272063005,
        121030272063002,
        121030272063031,
        121030272063004,
        121030272062011,
        121030273152000,
        121030273152006,
        121030272063035,
        121030272063032,
        121030272063033,
        121030272062021,
        121030272062024,
        121030272072000,
        121030273161005,
        121030273161009,
        121030272063018,
        121030272063001,
        121030272063003,
        121030272062018,
        121030272062016,
        121030272062012,
        121030272072002,
        121030272062027,
        121030272062003,
        121030272062028,
        121030272063029,
        121030272063006,
        121030272062020,
        121030272063009,
        121030272063000,
        121030272063010,
        121030272063036,
        121030272063028,
        121030272063015,
        121030272063007,
        121030272062015,
        121030273152001,
        121030272062014,
        121030272072001,
        121030272062026,
        121030273161006,
        121030273161007,
        121030272063034,
        121030272063011,
        121030272062025,
        121030272071003,
        121030272062008,
        121030272062017,
        121030272062006,
        121030272062029,
        121030272062013,
        121030273152011,
        121030272071004,
        121030272063014,
        121030272062001,
        121030272062023,
        121030272062022,
        121030272063030,
        121030272062019
    ],
    "zs:housing10":2276,
    "zs:label":"Beacon Groves",
    "zs:pop10":4185
},
  "geometry": {"coordinates":[-82.744462,28.084116],"type":"Point"}
}