{
  "type": "Feature",
  "properties": {
    "gn:country":"US",
    "gn:fcode":"PPL",
    "gn:population":0,
    "iso:country":"US",
    "name:ara_x_preferred":[
        "\u0633\u0648\u0628\u064a\u0631\u064a\u0648\u0631"
    ],
    "name:ben_x_preferred":[
        "\u09b8\u09c1\u09aa\u09bf\u09b0\u09bf\u09df\u09b0"
    ],
    "name:cat_x_preferred":[
        "Superior"
    ],
    "name:ceb_x_preferred":[
        "Superior"
    ],
    "name:ces_x_preferred":[
        "Superior"
    ],
    "name:dan_x_preferred":[
        "Superior"
    ],
    "name:deu_x_preferred":[
        "Superior"
    ],
    "name:ell_x_preferred":[
        "\u03a3\u03bf\u03c5\u03c0\u03ad\u03c1\u03b9\u03bf\u03c1"
    ],
    "name:eng_x_preferred":[
        "Superior"
    ],
    "name:fas_x_preferred":[
        "\u0633\u0648\u067e\u0631\u06cc\u0648\u0631"
    ],
    "name:fin_x_preferred":[
        "Superior"
    ],
    "name:fra_x_preferred":[
        "Superior"
    ],
    "name:hin_x_preferred":[
        "\u0938\u0941\u092a\u0940\u0930\u093f\u092f\u0930"
    ],
    "name:hun_x_preferred":[
        "Superior"
    ],
    "name:ind_x_preferred":[
        "Superior"
    ],
    "name:ita_x_preferred":[
        "Superior"
    ],
    "name:jpn_x_preferred":[
        "Superior"
    ],
    "name:lat_x_preferred":[
        "Superior"
    ],
    "name:nld_x_preferred":[
        "Superior"
    ],
    "name:pol_x_preferred":[
        "Superior"
    ],
    "name:por_x_preferred":[
        "Superior"
    ],
    "name:rus_x_preferred":[
        "\u0421\u044c\u044e\u043f\u0438\u0440\u0438\u043e\u0440"
    ],
    "name:spa_x_preferred":[
        "Superior"
    ],
    "name:srp_x_preferred":[
        "\u0421\u0443\u043f\u0438\u0440\u0438\u043e\u0440"
    ],
    "name:swe_x_preferred":[
        "Superior"
    ],
    "name:tha_x_preferred":[
        "\u0e2d\u0e18\u0e34\u0e01\u0e32\u0e23"
    ],
    "name:ukr_x_preferred":[
        "\u0421\u0443\u043f\u0435\u0440\u0456\u043e\u0440"
    ],
    "name:vol_x_preferred":[
        "Superior"
    ],
    "qs_pg:aaroncc":"US",
    "qs_pg:gn_country":"US",
    "qs_pg:gn_fcode":"PPL",
    "qs_pg:gn_pop":0,
    "qs_pg:name":"Superior",
    "qs_pg:name_adm0":"United States",
    "qs_pg:name_adm1":"Michigan",
    "qs_pg:photos":1814,
    "qs_pg:photos_1k":368,
    "qs_pg:photos_9k":8,
    "qs_pg:photos_9r":9,
    "qs_pg:photos_all":1831,
    "qs_pg:photos_sr":14,
    "qs_pg:pop_sr":0,
    "qs_pg:qs_pg_placetype":"locality",
    "qs_pg:qs_pg_placetype_gp":"Town",
    "qs_pg:woe_adm0":23424977,
    "woe:adm0_id":23424977,
    "woe:name_adm0":"United States",
    "woe:name_adm1":"Michigan",
    "woe:placetype":"Town",
    "wof:coterminous":[
        404508521
    ],
    "wof:name":"Superior",
    "wof:placetype":"locality",
    "wof:statistical_gore":1
},
  "geometry": {"coordinates":[-83.63772,42.26309],"type":"Point"}
}