{
  "type": "Feature",
  "properties": {
    "gn:admin1_code":"WV",
    "gn:admin2_code":"99",
    "gn:asciiname":"Armilda",
    "gn:country_code":"US",
    "gn:dem":191,
    "gn:elevation":"191.0",
    "gn:feature_class":"P",
    "gn:feature_code":"PPL",
    "gn:name":"Armilda",
    "gn:population":0,
    "gn:timezone":"America/New_York",
    "iso:country":"US",
    "name:vol_x_preferred":[
        "Armilda"
    ],
    "wof:name":"Armilda",
    "wof:placetype":"locality"
},
  "geometry": {"coordinates":[-82.40154,38.1837],"type":"Point"}
}