{
  "type": "Feature",
  "properties": {
    "gn:admin1_code":"MO",
    "gn:admin2_code":"65.0",
    "gn:admin3_code":"72808.0",
    "gn:asciiname":"Smoky Hollow",
    "gn:country_code":"US",
    "gn:dem":388,
    "gn:elevation":"385.0",
    "gn:feature_class":"P",
    "gn:feature_code":"PPL",
    "gn:name":"Smoky Hollow",
    "gn:population":0,
    "gn:timezone":"America/Chicago",
    "iso:country":"US",
    "wof:name":"Smoky Hollow",
    "wof:placetype":"locality"
},
  "geometry": {"coordinates":[-91.69293,37.62227],"type":"Point"}
}