{
  "type": "Feature",
  "properties": {
    "gn:country":"US",
    "gn:fcode":"PPLX",
    "gn:population":0,
    "iso:country":"US",
    "name:eng_x_preferred":[
        "Duggar Farms"
    ],
    "qs_pg:aaroncc":"US",
    "qs_pg:gn_country":"US",
    "qs_pg:gn_fcode":"PPLX",
    "qs_pg:gn_pop":0,
    "qs_pg:name":"Duggar Farms",
    "qs_pg:name_adm0":"United States",
    "qs_pg:name_adm1":"Alabama",
    "qs_pg:photos":41,
    "qs_pg:photos_1k":8,
    "qs_pg:photos_9k":1,
    "qs_pg:photos_9r":2,
    "qs_pg:photos_all":41,
    "qs_pg:photos_sr":2,
    "qs_pg:pop_sr":0,
    "qs_pg:qs_pg_placetype":"neighbourhood",
    "qs_pg:qs_pg_placetype_gp":"Suburb",
    "qs_pg:woe_adm0":23424977,
    "wof:name":"Duggar Farms",
    "wof:placetype":"neighbourhood",
    "wof:population":191,
    "zs:area_m":3290200.640921,
    "zs:blockids":[
        10810406043047,
        10810406043005,
        10810406043042,
        10810406043019,
        10810406043006,
        10810406043020,
        10810406043008,
        10810406043018,
        10810406043010,
        10810406043021,
        10810406043023,
        10810406043041
    ],
    "zs:housing10":105,
    "zs:label":"Duggar Farms",
    "zs:pop10":191
},
  "geometry": {"coordinates":[-85.51872299999999,32.563938],"type":"Point"}
}