{
  "type": "Feature",
  "properties": {
    "gn:admin1_code":"FL",
    "gn:admin2_code":"57",
    "gn:asciiname":"The Arbors",
    "gn:country_code":"US",
    "gn:dem":24,
    "gn:elevation":"14.0",
    "gn:feature_class":"P",
    "gn:feature_code":"PPL",
    "gn:name":"The Arbors",
    "gn:population":0,
    "gn:timezone":"America/New_York",
    "iso:country":"US",
    "name:tur_x_preferred":[
        "The Arbors"
    ],
    "wof:name":"The Arbors",
    "wof:placetype":"locality"
},
  "geometry": {"coordinates":[-82.3857,28.052],"type":"Point"}
}