{
  "type": "Feature",
  "properties": {
    "gn:admin1_code":"MD",
    "gn:admin2_code":"25.0",
    "gn:asciiname":"Osborne",
    "gn:country_code":"US",
    "gn:dem":24,
    "gn:elevation":"21.0",
    "gn:feature_class":"P",
    "gn:feature_code":"PPL",
    "gn:name":"Osborne",
    "gn:population":0,
    "gn:timezone":"America/New_York",
    "iso:country":"US",
    "name:cat_x_preferred":[
        "Osborne"
    ],
    "name:ceb_x_preferred":[
        "Osborne"
    ],
    "name:ces_x_preferred":[
        "Osborne"
    ],
    "name:deu_x_preferred":[
        "Osborne"
    ],
    "name:fra_x_preferred":[
        "Osborne"
    ],
    "name:ita_x_preferred":[
        "Osborne"
    ],
    "name:jpn_x_preferred":[
        "\u30aa\u30ba\u30dc\u30fc\u30f3"
    ],
    "name:nld_x_preferred":[
        "Osborne"
    ],
    "name:nor_x_preferred":[
        "Osborne"
    ],
    "name:pol_x_preferred":[
        "Osborne"
    ],
    "name:spa_x_preferred":[
        "Osborne"
    ],
    "name:srp_x_preferred":[
        "\u041e\u0437\u0431\u043e\u0440\u043d"
    ],
    "name:swe_x_preferred":[
        "Osborne"
    ],
    "name:vol_x_preferred":[
        "Osborne"
    ],
    "wof:name":"Osborne",
    "wof:placetype":"locality"
},
  "geometry": {"coordinates":[-76.11717,39.53678],"type":"Point"}
}