{
  "type": "Feature",
  "properties": {
    "iso:country":"US",
    "name:eng_x_preferred":[
        "Bellvue"
    ],
    "wof:name":"Bellvue",
    "wof:placetype":"neighbourhood",
    "wof:population":1534,
    "zs:area_m":973333.046279,
    "zs:blockids":[
        370250411001016,
        370250424023017,
        370250424023015,
        370250424023018,
        370250424023021,
        370250424023016,
        370250424023019,
        370250424023014,
        370250424023020,
        370250424023012
    ],
    "zs:housing10":682,
    "zs:label":"Bellvue",
    "zs:pop10":1534
},
  "geometry": {"coordinates":[-80.631635,35.437094],"type":"Point"}
}