{
  "type": "Feature",
  "properties": {
    "iso:country":"US",
    "name:eng_x_preferred":[
        "Central Trust"
    ],
    "qs_pg:aaroncc":"US",
    "qs_pg:name":"Central Trust",
    "qs_pg:name_adm0":"United States",
    "qs_pg:name_adm1":"South Carolina",
    "qs_pg:photos":9,
    "qs_pg:photos_1k":2,
    "qs_pg:photos_9k":1,
    "qs_pg:photos_9r":1,
    "qs_pg:photos_all":9,
    "qs_pg:photos_sr":1,
    "qs_pg:pop_sr":0,
    "qs_pg:qs_pg_placetype":"neighbourhood",
    "qs_pg:qs_pg_placetype_gp":"Suburb",
    "qs_pg:woe_adm0":23424977,
    "wof:name":"Central Trust",
    "wof:placetype":"neighbourhood",
    "wof:population":266,
    "zs:area_m":8108628.581745,
    "zs:blockids":[
        450479707023019,
        450479707024012,
        450479707023001,
        450479707023012,
        450479707023011,
        450479707024010,
        450479707023000,
        450479707023010,
        450479707024055,
        450479707023018,
        450479707024052,
        450479707024053,
        450479707024056,
        450479707024043,
        450479707024011
    ],
    "zs:housing10":124,
    "zs:label":"Central Trust",
    "zs:pop10":266
},
  "geometry": {"coordinates":[-81.996544,34.159747],"type":"Point"}
}