{
  "type": "Feature",
  "properties": {
    "gn:country":"US",
    "gn:fcode":"PPL",
    "gn:population":16724,
    "iso:country":"US",
    "name:cat_x_preferred":[
        "Auburn"
    ],
    "name:ceb_x_preferred":[
        "Auburn"
    ],
    "name:ces_x_preferred":[
        "Auburn"
    ],
    "name:dan_x_preferred":[
        "Auburn"
    ],
    "name:deu_x_preferred":[
        "Auburn"
    ],
    "name:eng_x_preferred":[
        "Auburn"
    ],
    "name:est_x_preferred":[
        "Auburn"
    ],
    "name:fas_x_preferred":[
        "\u0627\u0648\u0628\u0631\u0646\u060c \u0645\u0627\u0633\u0627\u0686\u0648\u0633\u062a"
    ],
    "name:fas_x_variant":[
        "\u0627\u0648\u0628\u0631\u0646"
    ],
    "name:fin_x_preferred":[
        "Auburn"
    ],
    "name:fra_x_preferred":[
        "Auburn"
    ],
    "name:glg_x_preferred":[
        "Auburn"
    ],
    "name:hun_x_preferred":[
        "Auburn"
    ],
    "name:ita_x_preferred":[
        "Auburn"
    ],
    "name:jpn_x_preferred":[
        "\u30aa\u30fc\u30d0\u30fc\u30f3"
    ],
    "name:kaz_x_preferred":[
        "\u0410\u0443\u0431\u0443\u0440\u043d"
    ],
    "name:kir_x_preferred":[
        "\u0410\u0443\u0431\u0443\u0440\u043d"
    ],
    "name:kor_x_preferred":[
        "\uc624\ubc88"
    ],
    "name:mlg_x_preferred":[
        "Auburn"
    ],
    "name:nld_x_preferred":[
        "Auburn"
    ],
    "name:nor_x_preferred":[
        "Auburn"
    ],
    "name:pol_x_preferred":[
        "Auburn"
    ],
    "name:por_x_preferred":[
        "Auburn"
    ],
    "name:rus_x_preferred":[
        "\u041e\u0431\u0435\u0440\u043d"
    ],
    "name:slk_x_preferred":[
        "Auburn"
    ],
    "name:spa_x_preferred":[
        "Auburn"
    ],
    "name:srp_x_preferred":[
        "\u041e\u0431\u0435\u0440\u043d"
    ],
    "name:swa_x_preferred":[
        "Auburn"
    ],
    "name:swe_x_preferred":[
        "Auburn"
    ],
    "name:ukr_x_preferred":[
        "\u041e\u0431\u0435\u0440\u043d"
    ],
    "name:und_x_variant":[
        "Auburn Centre"
    ],
    "name:urd_x_preferred":[
        "\u0622\u0628\u0631\u0646\u060c \u0645\u06cc\u0633\u0627\u0686\u0648\u0633\u0679\u0633"
    ],
    "name:urd_x_variant":[
        "\u0622\u0628\u0631\u0646"
    ],
    "name:vol_x_preferred":[
        "Auburn"
    ],
    "qs_pg:aaroncc":"US",
    "qs_pg:gn_country":"US",
    "qs_pg:gn_fcode":"PPL",
    "qs_pg:gn_pop":16724,
    "qs_pg:name":"Auburn",
    "qs_pg:name_adm0":"United States",
    "qs_pg:name_adm1":"Massachusetts",
    "qs_pg:photos":160,
    "qs_pg:photos_1k":32,
    "qs_pg:photos_9k":4,
    "qs_pg:photos_9r":6,
    "qs_pg:photos_all":809,
    "qs_pg:photos_sr":4,
    "qs_pg:pop_sr":6,
    "qs_pg:qs_pg_placetype":"locality",
    "qs_pg:qs_pg_placetype_gp":"Town",
    "qs_pg:woe_adm0":23424977,
    "woe:adm0_id":23424977,
    "woe:name_adm0":"United States",
    "woe:name_adm1":"Massachusetts",
    "woe:placetype":"Town",
    "wof:coterminous":[
        404476529
    ],
    "wof:name":"Auburn",
    "wof:placetype":"locality",
    "wof:population":16724,
    "wof:statistical_gore":1
},
  "geometry": {"coordinates":[-71.83562999999999,42.19454],"type":"Point"}
}