{
  "type": "Feature",
  "properties": {
    "gn:admin1_code":"OH",
    "gn:admin2_code":"81.0",
    "gn:admin3_code":"74122.0",
    "gn:asciiname":"The Eastern",
    "gn:country_code":"US",
    "gn:dem":290,
    "gn:elevation":"292.0",
    "gn:feature_class":"P",
    "gn:feature_code":"PPL",
    "gn:name":"The Eastern",
    "gn:population":0,
    "gn:timezone":"America/New_York",
    "iso:country":"US",
    "name:eng_x_preferred":[
        "The Eastern"
    ],
    "name:und_x_variant":[
        "Eastern"
    ],
    "wof:name":"The Eastern",
    "wof:placetype":"locality"
},
  "geometry": {"coordinates":[-80.89591999999998,40.49701],"type":"Point"}
}