{
  "type": "Feature",
  "properties": {
    "gn:admin1_code":"MD",
    "gn:admin2_code":"5.0",
    "gn:asciiname":"Foreston Ridge Estates",
    "gn:country_code":"US",
    "gn:dem":208,
    "gn:elevation":"209.0",
    "gn:feature_class":"P",
    "gn:feature_code":"PPL",
    "gn:name":"Foreston Ridge Estates",
    "gn:population":0,
    "gn:timezone":"America/New_York",
    "iso:country":"US",
    "wof:name":"Foreston Ridge Estates",
    "wof:placetype":"locality"
},
  "geometry": {"coordinates":[-76.77025,39.62844000000001],"type":"Point"}
}