{
  "type": "Feature",
  "properties": {
    "iso:country":"US",
    "name:eng_x_preferred":[
        "Downtown Rahway"
    ],
    "qs:gn_adm0_cc":"US",
    "qs:gn_local":5103055,
    "qs:gn_nam_loc":"Rahway, Union, New Jersey, US",
    "qs:gn_namadm1":"NJ",
    "qs:local_max":504,
    "qs:local_sum":531,
    "qs:localhoods":2,
    "qs:name":"Downtown Rahway",
    "qs:name_adm0":"United States",
    "qs:name_adm1":"New Jersey",
    "qs:name_adm2":"Union",
    "qs:name_local":"Rahway",
    "qs:photo_max":133,
    "qs:photo_sum":504,
    "qs:placetype":"Suburb",
    "qs:quad_count":33,
    "qs:woe_adm0":23424977,
    "qs:woe_adm1":2347589,
    "qs:woe_adm2":12589277,
    "qs:woe_lau":0,
    "qs:woe_local":2478173,
    "qs:woe_ver":"7.10.0",
    "wof:lang":[
        "eng"
    ],
    "wof:name":"Downtown Rahway",
    "wof:placetype":"neighbourhood",
    "wof:population":23,
    "zs:blockids":[
        340230090001003,
        340230090001002,
        340230090001005,
        340230090001001,
        340230090001004
    ],
    "zs:housing10":7,
    "zs:pop10":23
},
  "geometry": {"coordinates":[-74.273094,40.608384],"type":"Point"}
}