{
  "type": "Feature",
  "properties": {
    "gn:admin1_code":"NC",
    "gn:admin2_code":"61",
    "gn:admin3_code":"90020.0",
    "gn:asciiname":"Kornegay",
    "gn:country_code":"US",
    "gn:dem":26,
    "gn:elevation":"23.0",
    "gn:feature_class":"P",
    "gn:feature_code":"PPL",
    "gn:name":"Kornegay",
    "gn:population":0,
    "gn:timezone":"America/New_York",
    "iso:country":"US",
    "wof:name":"Kornegay",
    "wof:placetype":"locality"
},
  "geometry": {"coordinates":[-77.82554,35.05794],"type":"Point"}
}