{
  "type": "Feature",
  "properties": {
    "gn:country":"US",
    "gn:fcode":"PPL",
    "gn:population":0,
    "iso:country":"US",
    "name:deu_x_preferred":[
        "Sundale"
    ],
    "name:eng_x_preferred":[
        "Sundale"
    ],
    "name:und_x_variant":[
        "Head Quarters"
    ],
    "qs_pg:aaroncc":"US",
    "qs_pg:gn_country":"US",
    "qs_pg:gn_fcode":"PPL",
    "qs_pg:gn_pop":0,
    "qs_pg:name":"Sundale",
    "qs_pg:name_adm0":"United States",
    "qs_pg:name_adm1":"Pennsylvania",
    "qs_pg:photos":15,
    "qs_pg:photos_1k":3,
    "qs_pg:photos_9k":1,
    "qs_pg:photos_9r":1,
    "qs_pg:photos_all":15,
    "qs_pg:photos_sr":1,
    "qs_pg:pop_sr":0,
    "qs_pg:qs_pg_placetype":"neighbourhood",
    "qs_pg:qs_pg_placetype_gp":"Suburb",
    "qs_pg:woe_adm0":23424977,
    "wd:wordcount":8,
    "wof:name":"Sundale",
    "wof:placetype":"neighbourhood",
    "wof:population":600,
    "zs:area_m":12682476.683371,
    "zs:blockids":[
        420171037002052,
        420171037002057,
        420171039003002,
        420171039001060,
        420171039003023,
        420171039003013,
        420171039003021,
        420171037002051,
        420171039003007,
        420171039003009,
        420171037002050,
        420171037002054,
        420171037002062,
        420171039003012,
        420171037002063,
        420171039003004,
        420171037002053,
        420171039003000,
        420171039003005,
        420171039003001,
        420171039003006,
        420171039003008,
        420171039003016,
        420171039003003,
        420171037002045,
        420171039003024
    ],
    "zs:housing10":282,
    "zs:label":"Sundale",
    "zs:pop10":600
},
  "geometry": {"coordinates":[-75.126554,40.503508],"type":"Point"}
}