{
  "type": "Feature",
  "properties": {
    "iso:country":"US",
    "name:ara_x_preferred":[
        "\u0645\u0637\u0627\u0631 \u0644\u0627\u0646\u062a\u0634\u0648 \u062a\u0634\u0648\u0646\u063a \u062a\u0634\u0648\u0627\u0646"
    ],
    "name:ceb_x_preferred":[
        "Lanzhou Zhongchuan Airport"
    ],
    "name:ces_x_preferred":[
        "Mezin\u00e1rodn\u00ed leti\u0161t\u011b Lan-\u010dou \u010cung-\u010dchuan"
    ],
    "name:cym_x_preferred":[
        "Maes Awyr Rhyngwladol Lanzhou Zhongchuan"
    ],
    "name:eng_x_preferred":[
        "Wright Army Air Field"
    ],
    "name:eng_x_variant":[
        "LHW",
        "KLHW",
        "Lanzhou Zhongchuan International Airport"
    ],
    "name:eus_x_preferred":[
        "Lanzhou Zhongchuan aireportua"
    ],
    "name:fas_x_preferred":[
        "\u0641\u0631\u0648\u062f\u06af\u0627\u0647 \u0644\u0627\u0646\u062c\u0648 \u0698\u0646\u06af\u0686\u0648\u0627\u0646"
    ],
    "name:fra_x_preferred":[
        "a\u00e9roport de Lanzhou Zhongchuan"
    ],
    "name:ind_x_preferred":[
        "Bandar Udara Internasional Zhongchuan Lanzhou"
    ],
    "name:jpn_x_preferred":[
        "\u862d\u5dde\u4e2d\u5ddd\u7a7a\u6e2f"
    ],
    "name:msa_x_preferred":[
        "Lapangan Terbang Zhongchuan"
    ],
    "name:nld_x_preferred":[
        "Lanzhou Zhongchuan International Airport"
    ],
    "name:pol_x_preferred":[
        "Port lotniczy Lanzhou-Zhongchuan"
    ],
    "name:ron_x_preferred":[
        "Aeroportul Lanzhou Zhongchuan"
    ],
    "name:swe_x_preferred":[
        "Lanzhou Zhongchuan Airport"
    ],
    "name:tgk_x_preferred":[
        "\u0424\u0443\u0440\u0443\u0434\u0433\u043e\u04b3\u0438 \u043b\u043e\u043d\u04b7\u0443 \u0436\u043d\u0433\u0447\u0443\u043e\u043d"
    ],
    "name:vie_x_preferred":[
        "S\u00e2n bay Trung Xuy\u00ean Lan Ch\u00e2u"
    ],
    "name:zho_x_preferred":[
        "\u5170\u5dde\u4e2d\u5ddd\u673a\u573a"
    ],
    "oa:elevation_ft":"6388",
    "oa:type":"medium_airport",
    "woe:hierarchy":{
        "country_id":23424977,
        "county_id":12587958,
        "planet_id":1,
        "state_id":2347569
    },
    "wof:name":"Wright Army Air Field",
    "wof:placetype":"campus"
},
  "geometry": {"coordinates":[103.620003,36.515202],"type":"Point"}
}