{
  "type": "Feature",
  "properties": {
    "gn:country":"US",
    "gn:fcode":"PPL",
    "gn:population":0,
    "iso:country":"US",
    "name:azb_x_preferred":[
        "\u0622\u0642\u0648\u0633\u062a\u0627"
    ],
    "name:eng_x_preferred":[
        "Augusta"
    ],
    "name:fas_x_preferred":[
        "\u0622\u06af\u0648\u0633\u062a\u0627"
    ],
    "name:fra_x_preferred":[
        "Augusta"
    ],
    "name:rus_x_preferred":[
        "\u041e\u0433\u0430\u0441\u0442\u0430"
    ],
    "name:urd_x_preferred":[
        "\u0622\u06af\u0633\u0679\u0627\u060c \u0646\u06cc\u0648 \u062c\u0631\u0633\u06cc"
    ],
    "name:urd_x_variant":[
        "\u0622\u06af\u0633\u0679\u0627"
    ],
    "name:vol_x_preferred":[
        "Augusta"
    ],
    "qs_pg:aaroncc":"US",
    "qs_pg:gn_country":"US",
    "qs_pg:gn_fcode":"PPL",
    "qs_pg:gn_pop":0,
    "qs_pg:name":"Augusta",
    "qs_pg:name_adm0":"United States",
    "qs_pg:name_adm1":"New Jersey",
    "qs_pg:photos":457,
    "qs_pg:photos_1k":93,
    "qs_pg:photos_9k":2,
    "qs_pg:photos_9r":5,
    "qs_pg:photos_all":457,
    "qs_pg:photos_sr":7,
    "qs_pg:pop_sr":5,
    "qs_pg:qs_pg_placetype":"locality",
    "qs_pg:qs_pg_placetype_gp":"Town",
    "qs_pg:woe_adm0":23424977,
    "woe:adm0_id":23424977,
    "woe:name_adm0":"United States",
    "woe:name_adm1":"New Jersey",
    "woe:placetype":"Town",
    "wof:name":"Augusta",
    "wof:placetype":"locality"
},
  "geometry": {"coordinates":[-74.72821999999999,41.12899],"type":"Point"}
}