{
  "type": "Feature",
  "properties": {
    "iso:country":"US",
    "name:eng_x_preferred":[
        "Creekmont"
    ],
    "wof:name":"Creekmont",
    "wof:placetype":"neighbourhood",
    "wof:population":989,
    "zs:area_m":5088776.651951,
    "zs:blockids":[
        481576745021086,
        481576745011102,
        481576745021089,
        481576745021046,
        481576745011101,
        481576745021272,
        481576745011053,
        481576745021082,
        481576745011047,
        481576745011120,
        481576745011114,
        481576745021275,
        481576745011051,
        481576745011110,
        481576745011121,
        481576745011112,
        481576745021281,
        481576708003047,
        481576745021083,
        481576745021006,
        481576745021088,
        481576745021087,
        481576745021007,
        481576745021085,
        481576745011111,
        481576745011119,
        481576745021084,
        481576745021040,
        481576745011122,
        481576745011048,
        481576745011049
    ],
    "zs:housing10":398,
    "zs:label":"Creekmont",
    "zs:pop10":989
},
  "geometry": {"coordinates":[-95.50117899999999,29.518955],"type":"Point"}
}