{
  "type": "Feature",
  "properties": {
    "gn:admin1_code":"NH",
    "gn:admin2_code":"11.0",
    "gn:admin3_code":"85220.0",
    "gn:asciiname":"West Wilton",
    "gn:country_code":"US",
    "gn:dem":205,
    "gn:elevation":"196.0",
    "gn:feature_class":"P",
    "gn:feature_code":"PPL",
    "gn:name":"West Wilton",
    "gn:population":0,
    "gn:timezone":"America/New_York",
    "iso:country":"US",
    "wof:name":"West Wilton",
    "wof:placetype":"locality"
},
  "geometry": {"coordinates":[-71.80591,42.83036],"type":"Point"}
}