{
  "type": "Feature",
  "properties": {
    "gn:admin1_code":"SC",
    "gn:admin2_code":"45.0",
    "gn:asciiname":"Carolina Heights",
    "gn:country_code":"US",
    "gn:dem":285,
    "gn:elevation":"275.0",
    "gn:feature_class":"P",
    "gn:feature_code":"PPL",
    "gn:name":"Carolina Heights",
    "gn:population":0,
    "gn:timezone":"America/New_York",
    "iso:country":"US",
    "wof:name":"Carolina Heights",
    "wof:placetype":"locality"
},
  "geometry": {"coordinates":[-82.45345999999998,34.81123],"type":"Point"}
}