{
  "type": "Feature",
  "properties": {
    "gn:admin1_code":"OH",
    "gn:admin2_code":"107.0",
    "gn:admin3_code":"38724.0",
    "gn:asciiname":"Northwood",
    "gn:country_code":"US",
    "gn:dem":270,
    "gn:elevation":"267.0",
    "gn:feature_class":"P",
    "gn:feature_code":"PPL",
    "gn:name":"Northwood",
    "gn:population":0,
    "gn:timezone":"America/New_York",
    "iso:country":"US",
    "name:bar_x_preferred":[
        "Northwood"
    ],
    "name:cat_x_preferred":[
        "Northwood"
    ],
    "name:ceb_x_preferred":[
        "Northwood"
    ],
    "name:deu_x_preferred":[
        "Northwood"
    ],
    "name:fin_x_preferred":[
        "Northwood"
    ],
    "name:fra_x_preferred":[
        "Northwood"
    ],
    "name:hun_x_preferred":[
        "Northwood"
    ],
    "name:ita_x_preferred":[
        "Northwood"
    ],
    "name:jpn_x_preferred":[
        "\u30ce\u30fc\u30b9\u30a6\u30c3\u30c9"
    ],
    "name:kor_x_preferred":[
        "\ub178\uc2a4\uc6b0\ub4dc"
    ],
    "name:nld_x_preferred":[
        "Northwood"
    ],
    "name:pol_x_preferred":[
        "Northwood"
    ],
    "name:por_x_preferred":[
        "Northwood"
    ],
    "name:rus_x_preferred":[
        "\u041d\u043e\u0440\u0442\u0432\u0443\u0434"
    ],
    "name:srp_x_preferred":[
        "\u041d\u043e\u0440\u0442\u0432\u0443\u0434"
    ],
    "name:swe_x_preferred":[
        "Northwood"
    ],
    "name:vol_x_preferred":[
        "Northwood"
    ],
    "wof:name":"Northwood",
    "wof:placetype":"locality"
},
  "geometry": {"coordinates":[-84.48300999999999,40.54727000000001],"type":"Point"}
}