{
  "type": "Feature",
  "properties": {
    "gn:country":"US",
    "gn:fcode":"PPL",
    "gn:population":0,
    "iso:country":"US",
    "name:azb_x_preferred":[
        "\u0645\u0648\u0631\u0645\u0648\u0646 \u0644\u0626\u06cc\u06a9"
    ],
    "name:eng_x_preferred":[
        "Mormon Lake"
    ],
    "name:fas_x_preferred":[
        "\u0645\u0648\u0631\u0645\u0648\u0646 \u0644\u06cc\u06a9"
    ],
    "name:fra_x_preferred":[
        "Mormon Lake"
    ],
    "name:gle_x_preferred":[
        "Mormon Lake"
    ],
    "name:lld_x_preferred":[
        "Mormon Lake"
    ],
    "name:nav_x_preferred":[
        "Be\u02bcek\u02bcid H\u00f3teel\u00ed"
    ],
    "name:por_x_preferred":[
        "Mormon Lake"
    ],
    "name:tur_x_preferred":[
        "Mormon Lake"
    ],
    "name:und_x_variant":[
        "Lakeview"
    ],
    "name:zho_x_preferred":[
        "\u6469\u9580\u6e56"
    ],
    "qs_pg:aaroncc":"US",
    "qs_pg:gn_country":"US",
    "qs_pg:gn_fcode":"PPL",
    "qs_pg:gn_pop":0,
    "qs_pg:name":"Mormon Lake",
    "qs_pg:name_adm0":"United States",
    "qs_pg:name_adm1":"Arizona",
    "qs_pg:photos":321,
    "qs_pg:photos_1k":65,
    "qs_pg:photos_9k":1,
    "qs_pg:photos_9r":5,
    "qs_pg:photos_all":321,
    "qs_pg:photos_sr":5,
    "qs_pg:pop_sr":5,
    "qs_pg:qs_pg_placetype":"locality",
    "qs_pg:qs_pg_placetype_gp":"Town",
    "qs_pg:woe_adm0":23424977,
    "woe:adm0_id":23424977,
    "woe:name_adm0":"United States",
    "woe:name_adm1":"Arizona",
    "woe:placetype":"Town",
    "wof:name":"Mormon Lake",
    "wof:placetype":"locality"
},
  "geometry": {"coordinates":[-111.46321,34.90835],"type":"Point"}
}