{
  "type": "Feature",
  "properties": {
    "gn:admin1_code":"TX",
    "gn:admin2_code":"427",
    "gn:asciiname":"Hillside Terrace Colonia",
    "gn:country_code":"US",
    "gn:dem":57,
    "gn:elevation":"56.0",
    "gn:feature_class":"P",
    "gn:feature_code":"PPL",
    "gn:name":"Hillside Terrace Colonia",
    "gn:population":0,
    "gn:timezone":"America/Chicago",
    "iso:country":"US",
    "wof:name":"Hillside Terrace Colonia",
    "wof:placetype":"locality"
},
  "geometry": {"coordinates":[-98.98031,26.41229],"type":"Point"}
}