{
  "type": "Feature",
  "properties": {
    "iso:country":"US",
    "name:eng_x_preferred":[
        "Stonecreek East"
    ],
    "wof:name":"Stonecreek East",
    "wof:placetype":"neighbourhood",
    "wof:population":308,
    "zs:area_m":655293.320719,
    "zs:blockids":[
        530110402033017,
        530110402033018,
        530110402014033,
        530110402033033,
        530110402033034
    ],
    "zs:housing10":90,
    "zs:label":"Stonecreek East",
    "zs:pop10":308
},
  "geometry": {"coordinates":[-122.652951,45.862839],"type":"Point"}
}