{
  "type": "Feature",
  "properties": {
    "gn:admin1_code":"VA",
    "gn:admin2_code":"770.0",
    "gn:asciiname":"Airlee Court",
    "gn:country_code":"US",
    "gn:dem":336,
    "gn:elevation":"336.0",
    "gn:feature_class":"P",
    "gn:feature_code":"PPL",
    "gn:name":"Airlee Court",
    "gn:population":0,
    "gn:timezone":"America/New_York",
    "iso:country":"US",
    "wof:name":"Airlee Court",
    "wof:placetype":"locality"
},
  "geometry": {"coordinates":[-79.95393,37.31847],"type":"Point"}
}