{
  "type": "Feature",
  "properties": {
    "gn:admin1_code":"WV",
    "gn:admin2_code":"17",
    "gn:asciiname":"Middle Point",
    "gn:country_code":"US",
    "gn:dem":372,
    "gn:elevation":"369.0",
    "gn:feature_class":"P",
    "gn:feature_code":"PPL",
    "gn:name":"Middle Point",
    "gn:population":0,
    "gn:timezone":"America/New_York",
    "iso:country":"US",
    "wof:name":"Middle Point",
    "wof:placetype":"locality"
},
  "geometry": {"coordinates":[-80.74677,39.20592],"type":"Point"}
}