{
  "type": "Feature",
  "properties": {
    "gn:admin1_code":"IL",
    "gn:admin2_code":"83",
    "gn:admin3_code":"65689.0",
    "gn:asciiname":"Nutwood",
    "gn:country_code":"US",
    "gn:dem":142,
    "gn:elevation":"137.0",
    "gn:feature_class":"P",
    "gn:feature_code":"PPL",
    "gn:name":"Nutwood",
    "gn:population":0,
    "gn:timezone":"America/Chicago",
    "iso:country":"US",
    "wof:name":"Nutwood",
    "wof:placetype":"locality"
},
  "geometry": {"coordinates":[-90.55595,39.08477],"type":"Point"}
}