{
  "type": "Feature",
  "properties": {
    "gn:admin1_code":"PA",
    "gn:admin2_code":"17",
    "gn:admin3_code":"53304.0",
    "gn:asciiname":"Little Farm Trace Park",
    "gn:country_code":"US",
    "gn:dem":133,
    "gn:elevation":"135.0",
    "gn:feature_class":"P",
    "gn:feature_code":"PPL",
    "gn:name":"Little Farm Trace Park",
    "gn:population":0,
    "gn:timezone":"America/New_York",
    "iso:country":"US",
    "wof:name":"Little Farm Trace Park",
    "wof:placetype":"locality"
},
  "geometry": {"coordinates":[-75.2178,40.2673],"type":"Point"}
}