{
  "type": "Feature",
  "properties": {
    "gn:admin1_code":"KY",
    "gn:admin2_code":"115",
    "gn:asciiname":"Asa",
    "gn:country_code":"US",
    "gn:dem":237,
    "gn:elevation":"220.0",
    "gn:feature_class":"P",
    "gn:feature_code":"PPL",
    "gn:name":"Asa",
    "gn:population":0,
    "gn:timezone":"America/New_York",
    "iso:country":"US",
    "name:azb_x_preferred":[
        "\u0622\u0633\u0627"
    ],
    "name:fas_x_preferred":[
        "\u0622\u0633\u0627"
    ],
    "name:spa_x_preferred":[
        "Asa"
    ],
    "wof:name":"Asa",
    "wof:placetype":"locality"
},
  "geometry": {"coordinates":[-82.90405,37.76787],"type":"Point"}
}