{
  "type": "Feature",
  "properties": {
    "gn:admin1_code":"TN",
    "gn:admin2_code":"31.0",
    "gn:asciiname":"Bryan Mill",
    "gn:country_code":"US",
    "gn:dem":314,
    "gn:elevation":"307.0",
    "gn:feature_class":"P",
    "gn:feature_code":"PPL",
    "gn:name":"Bryan Mill",
    "gn:population":0,
    "gn:timezone":"America/Chicago",
    "iso:country":"US",
    "wof:name":"Bryan Mill",
    "wof:placetype":"locality"
},
  "geometry": {"coordinates":[-85.93776,35.56646],"type":"Point"}
}