{
  "type": "Feature",
  "properties": {
    "iso:country":"US",
    "name:eng_x_preferred":[
        "Downtown Villa Park"
    ],
    "wof:name":"Downtown Villa Park",
    "wof:placetype":"neighbourhood",
    "wof:population":153,
    "zs:area_m":40055.294799,
    "zs:blockids":[
        170438431003002
    ],
    "zs:housing10":70,
    "zs:label":"Downtown Villa Park",
    "zs:pop10":153
},
  "geometry": {"coordinates":[-87.976713,41.895423],"type":"Point"}
}