{
  "type": "Feature",
  "properties": {
    "gn:admin1_code":"SC",
    "gn:admin2_code":"91.0",
    "gn:asciiname":"Timber Ridge",
    "gn:country_code":"US",
    "gn:dem":190,
    "gn:elevation":"183.0",
    "gn:feature_class":"P",
    "gn:feature_code":"PPL",
    "gn:name":"Timber Ridge",
    "gn:population":0,
    "gn:timezone":"America/New_York",
    "iso:country":"US",
    "name:ceb_x_preferred":[
        "Timber Ridge"
    ],
    "wof:name":"Timber Ridge",
    "wof:placetype":"locality"
},
  "geometry": {"coordinates":[-81.06924000000002,35.10848],"type":"Point"}
}