{
  "type": "Feature",
  "properties": {
    "gn:admin1_code":"AL",
    "gn:admin2_code":"89",
    "gn:asciiname":"Greenwycke Village",
    "gn:country_code":"US",
    "gn:dem":207,
    "gn:elevation":"208.0",
    "gn:feature_class":"P",
    "gn:feature_code":"PPL",
    "gn:name":"Greenwycke Village",
    "gn:population":0,
    "gn:timezone":"America/Chicago",
    "iso:country":"US",
    "wof:name":"Greenwycke Village",
    "wof:placetype":"locality"
},
  "geometry": {"coordinates":[-86.55055,34.70342],"type":"Point"}
}