{
  "type": "Feature",
  "properties": {
    "iso:country":"US",
    "name:eng_x_preferred":[
        "Ferrellton"
    ],
    "qs:gn_adm0_cc":"US",
    "qs:gn_fcode":"PPL",
    "qs:gn_local":5195375,
    "qs:gn_nam_loc":"jenners",
    "qs:gn_namadm1":"PA",
    "qs:gn_name":"Ferrellton",
    "qs:local_max":110,
    "qs:local_sum":143,
    "qs:localhoods":5,
    "qs:name":"Ferrellton",
    "qs:name_adm0":"United States",
    "qs:name_adm1":"Pennsylvania",
    "qs:name_adm2":"Somerset",
    "qs:name_local":"Jenners",
    "qs:photo_max":10,
    "qs:photo_sum":10,
    "qs:placetype":"Suburb",
    "qs:quad_count":1,
    "qs:woe_adm0":23424977,
    "qs:woe_adm1":2347597,
    "qs:woe_adm2":12589783,
    "qs:woe_funk":"Grouping neighborhood",
    "qs:woe_lau":0,
    "qs:woe_local":2429025,
    "qs:woe_ver":"7.10.0",
    "wof:lang":[
        "eng"
    ],
    "wof:name":"Ferrellton",
    "wof:placetype":"neighbourhood",
    "wof:population":586,
    "zs:blockids":[
        421110206004023,
        421110206004012,
        421110206004017,
        421110206004013,
        421110206004033,
        421110206004016,
        421110206004005,
        421110206004021,
        421110206004014,
        421110206004019,
        421110206004018,
        421110206004011,
        421110206004015,
        421110206004022
    ],
    "zs:housing10":263,
    "zs:pop10":586
},
  "geometry": {"coordinates":[-79.04388400000001,40.147388],"type":"Point"}
}