{
  "type": "Feature",
  "properties": {
    "gn:admin1_code":"LA",
    "gn:admin2_code":"73.0",
    "gn:asciiname":"Old Ten",
    "gn:country_code":"US",
    "gn:dem":21,
    "gn:elevation":"24.0",
    "gn:feature_class":"P",
    "gn:feature_code":"PPL",
    "gn:name":"Old Ten",
    "gn:population":0,
    "gn:timezone":"America/Chicago",
    "iso:country":"US",
    "wof:name":"Old Ten",
    "wof:placetype":"locality"
},
  "geometry": {"coordinates":[-92.13625,32.52042],"type":"Point"}
}