{
  "type": "Feature",
  "properties": {
    "gn:admin1_code":"TN",
    "gn:admin2_code":"19",
    "gn:asciiname":"Green Pine",
    "gn:country_code":"US",
    "gn:dem":575,
    "gn:elevation":"576.0",
    "gn:feature_class":"P",
    "gn:feature_code":"PPL",
    "gn:name":"Green Pine",
    "gn:population":0,
    "gn:timezone":"America/New_York",
    "iso:country":"US",
    "wof:name":"Green Pine",
    "wof:placetype":"locality"
},
  "geometry": {"coordinates":[-82.27736,36.26983],"type":"Point"}
}