{
  "type": "Feature",
  "properties": {
    "gn:admin1_code":"WA",
    "gn:admin2_code":"53.0",
    "gn:asciiname":"Ardenia Gale Mobile Home Park",
    "gn:country_code":"US",
    "gn:dem":6,
    "gn:elevation":"10.0",
    "gn:feature_class":"P",
    "gn:feature_code":"PPL",
    "gn:name":"Ardenia Gale Mobile Home Park",
    "gn:population":0,
    "gn:timezone":"America/Los_Angeles",
    "iso:country":"US",
    "wof:name":"Ardenia Gale Mobile Home Park",
    "wof:placetype":"campus"
},
  "geometry": {"coordinates":[-122.33601000000002,47.21297],"type":"Point"}
}