{
  "type": "Feature",
  "properties": {
    "gn:admin1_code":"SC",
    "gn:admin2_code":"9.0",
    "gn:asciiname":"Bufords Bridge",
    "gn:country_code":"US",
    "gn:dem":41,
    "gn:elevation":"30.0",
    "gn:feature_class":"P",
    "gn:feature_code":"PPL",
    "gn:name":"Bufords Bridge",
    "gn:population":0,
    "gn:timezone":"America/New_York",
    "iso:country":"US",
    "name:eng_x_preferred":[
        "Bufords Bridge"
    ],
    "name:und_x_variant":[
        "The Crossroads",
        "Buford's Bridge",
        "Beauforts Bridge"
    ],
    "wof:name":"Bufords Bridge",
    "wof:placetype":"locality"
},
  "geometry": {"coordinates":[-81.18371999999999,33.1146],"type":"Point"}
}