{
  "type": "Feature",
  "properties": {
    "gn:admin1_code":"AL",
    "gn:admin2_code":"95",
    "gn:asciiname":"High Point",
    "gn:country_code":"US",
    "gn:dem":311,
    "gn:elevation":"312.0",
    "gn:feature_class":"P",
    "gn:feature_code":"PPL",
    "gn:name":"High Point",
    "gn:population":0,
    "gn:timezone":"America/Chicago",
    "iso:country":"US",
    "name:cat_x_preferred":[
        "High Point"
    ],
    "name:ceb_x_preferred":[
        "High Point"
    ],
    "name:deu_x_preferred":[
        "High Point"
    ],
    "name:fra_x_preferred":[
        "High Point"
    ],
    "name:ita_x_preferred":[
        "High Point"
    ],
    "name:nld_x_preferred":[
        "High Point"
    ],
    "name:pol_x_preferred":[
        "High Point"
    ],
    "name:rus_x_preferred":[
        "\u0425\u0430\u0439-\u041f\u043e\u0439\u043d\u0442"
    ],
    "name:srp_x_preferred":[
        "\u0425\u0430\u0458 \u041f\u043e\u0458\u043d\u0442"
    ],
    "name:swe_x_preferred":[
        "High Point"
    ],
    "name:ukr_x_preferred":[
        "\u0413\u0430\u0439-\u041f\u043e\u0439\u043d\u0442"
    ],
    "name:vol_x_preferred":[
        "High Point"
    ],
    "wof:name":"High Point",
    "wof:placetype":"locality"
},
  "geometry": {"coordinates":[-86.27859000000002,34.24232],"type":"Point"}
}