{
  "type": "Feature",
  "properties": {
    "gn:gn_country":"US",
    "gn:gn_fcode":"PPL",
    "gn:gn_pop":0,
    "iso:country":"US",
    "name:als_x_preferred":[
        "Osco"
    ],
    "name:cat_x_preferred":[
        "Osco"
    ],
    "name:ceb_x_preferred":[
        "Osco"
    ],
    "name:deu_x_preferred":[
        "Osco"
    ],
    "name:fra_x_preferred":[
        "Osco"
    ],
    "name:ita_x_preferred":[
        "Osco"
    ],
    "name:lmo_x_preferred":[
        "Vosch"
    ],
    "name:nld_x_preferred":[
        "Osco"
    ],
    "name:nno_x_preferred":[
        "Osco"
    ],
    "name:por_x_preferred":[
        "Osco"
    ],
    "name:roh_x_preferred":[
        "Osco"
    ],
    "name:spa_x_preferred":[
        "Osco"
    ],
    "name:sqi_x_preferred":[
        "Osco"
    ],
    "name:vol_x_preferred":[
        "Osco"
    ],
    "name:war_x_preferred":[
        "Osco"
    ],
    "qs_pg:aaroncc":"US",
    "qs_pg:gn_country":"US",
    "qs_pg:gn_fcode":"PPL",
    "qs_pg:gn_pop":0,
    "qs_pg:name":"Osco",
    "qs_pg:name_adm0":"United States",
    "qs_pg:name_adm1":"Alabama",
    "qs_pg:photos":2,
    "qs_pg:photos_1k":1,
    "qs_pg:photos_9k":1,
    "qs_pg:photos_9r":1,
    "qs_pg:photos_all":2,
    "qs_pg:photos_sr":1,
    "qs_pg:pop_sr":0,
    "qs_pg:qs_pg_placetype":"neighbourhood",
    "qs_pg:qs_pg_placetype_gp":"Suburb",
    "qs_pg:woe_adm0":23424977,
    "woe:adm0_id":23424977,
    "woe:name_adm0":"United States",
    "woe:name_adm1":"Alabama",
    "woe:placetype":"Suburb",
    "wof:name":"Osco",
    "wof:placetype":"neighbourhood"
},
  "geometry": {"coordinates":[-85.23577,31.87711],"type":"Point"}
}