{
  "type": "Feature",
  "properties": {
    "gn:admin1_code":"SD",
    "gn:admin2_code":"47.0",
    "gn:admin3_code":"59955.0",
    "gn:asciiname":"Marietta",
    "gn:country_code":"US",
    "gn:dem":1065,
    "gn:elevation":"1065.0",
    "gn:feature_class":"P",
    "gn:feature_code":"PPL",
    "gn:name":"Marietta",
    "gn:population":0,
    "gn:timezone":"America/Denver",
    "iso:country":"US",
    "name:cat_x_preferred":[
        "Marietta"
    ],
    "name:ceb_x_preferred":[
        "Marietta"
    ],
    "name:deu_x_preferred":[
        "Marietta"
    ],
    "name:fin_x_preferred":[
        "Marietta"
    ],
    "name:fra_x_preferred":[
        "Marietta"
    ],
    "name:hun_x_preferred":[
        "Marietta"
    ],
    "name:ita_x_preferred":[
        "Marietta"
    ],
    "name:jpn_x_preferred":[
        "\u30de\u30ea\u30a8\u30c3\u30bf"
    ],
    "name:kor_x_preferred":[
        "\ub9e4\ub9ac\uc5d0\ud0c0"
    ],
    "name:nld_x_preferred":[
        "Marietta"
    ],
    "name:pol_x_preferred":[
        "Marietta"
    ],
    "name:por_x_preferred":[
        "Marietta"
    ],
    "name:rus_x_preferred":[
        "\u041c\u0430\u0440\u0438\u0435\u0442\u0442\u0430"
    ],
    "name:spa_x_preferred":[
        "Marietta"
    ],
    "name:srp_x_preferred":[
        "\u041c\u0430\u0440\u0438\u0458\u0435\u0442\u0430"
    ],
    "name:swe_x_preferred":[
        "Marietta"
    ],
    "name:tur_x_preferred":[
        "Marietta"
    ],
    "name:ukr_x_preferred":[
        "\u041c\u0430\u0440\u0456\u0435\u0442\u0442\u0430"
    ],
    "name:vol_x_preferred":[
        "Marietta"
    ],
    "wof:name":"Marietta",
    "wof:placetype":"locality"
},
  "geometry": {"coordinates":[-103.91937,43.39192],"type":"Point"}
}