{
  "type": "Feature",
  "properties": {
    "gn:country":"US",
    "gn:fcode":"PPL",
    "gn:population":0,
    "iso:country":"US",
    "name:eng_x_preferred":[
        "Crystal Bay"
    ],
    "name:fra_x_preferred":[
        "Crystal Bay"
    ],
    "name:nld_x_preferred":[
        "Crystal Bay"
    ],
    "qs_pg:aaroncc":"US",
    "qs_pg:gn_country":"US",
    "qs_pg:gn_fcode":"PPL",
    "qs_pg:gn_pop":0,
    "qs_pg:name":"Crystal Bay",
    "qs_pg:name_adm0":"United States",
    "qs_pg:name_adm1":"Minnesota",
    "qs_pg:photos":501,
    "qs_pg:photos_1k":102,
    "qs_pg:photos_9k":2,
    "qs_pg:photos_9r":5,
    "qs_pg:photos_all":501,
    "qs_pg:photos_sr":7,
    "qs_pg:pop_sr":0,
    "qs_pg:qs_pg_placetype":"locality",
    "qs_pg:qs_pg_placetype_gp":"Town",
    "qs_pg:woe_adm0":23424977,
    "woe:adm0_id":23424977,
    "woe:name_adm0":"United States",
    "woe:name_adm1":"Minnesota",
    "woe:placetype":"Town",
    "wof:name":"Crystal Bay",
    "wof:placetype":"locality"
},
  "geometry": {"coordinates":[-93.57635000000001,44.95302],"type":"Point"}
}