{
  "type": "Feature",
  "properties": {
    "iso:country":"US",
    "name:eng_x_preferred":[
        "South Overland Park"
    ],
    "qs:gn_adm0_cc":"US",
    "qs:gn_fcode":"PPL",
    "qs:gn_local":4276873,
    "qs:gn_nam_loc":"Overland Park, Johnson, Kansas, US",
    "qs:gn_namadm1":"KS",
    "qs:gn_name":"Overland Park",
    "qs:local_max":1231,
    "qs:local_sum":10500,
    "qs:localhoods":24,
    "qs:name":"South Overland Park",
    "qs:name_adm0":"United States",
    "qs:name_adm1":"Kansas",
    "qs:name_adm2":"Johnson",
    "qs:name_local":"Overland Park",
    "qs:photo_max":9,
    "qs:photo_sum":27,
    "qs:placetype":"Suburb",
    "qs:quad_count":6,
    "qs:woe_adm0":23424977,
    "qs:woe_adm1":2347575,
    "qs:woe_adm2":12588416,
    "qs:woe_funk":"Grouping neighborhood",
    "qs:woe_lau":0,
    "qs:woe_local":2466942,
    "qs:woe_ver":"7.10.0",
    "wof:lang":[
        "eng"
    ],
    "wof:name":"South Overland Park",
    "wof:placetype":"neighbourhood",
    "wof:population":237,
    "zs:blockids":[
        200910518041018,
        200910518041017
    ],
    "zs:housing10":81,
    "zs:pop10":237
},
  "geometry": {"coordinates":[-94.680339,38.954132],"type":"Point"}
}