{
  "type": "Feature",
  "properties": {
    "gn:country":"US",
    "gn:fcode":"PPL",
    "gn:population":0,
    "iso:country":"US",
    "qs_pg:aaroncc":"US",
    "qs_pg:gn_country":"US",
    "qs_pg:gn_fcode":"PPL",
    "qs_pg:gn_pop":0,
    "qs_pg:name":"Ancient Oak North",
    "qs_pg:name_adm0":"United States",
    "qs_pg:name_adm1":"Maryland",
    "qs_pg:photos":69,
    "qs_pg:photos_1k":14,
    "qs_pg:photos_9k":1,
    "qs_pg:photos_9r":2,
    "qs_pg:photos_all":69,
    "qs_pg:photos_sr":2,
    "qs_pg:pop_sr":0,
    "qs_pg:qs_pg_placetype":"locality",
    "qs_pg:qs_pg_placetype_gp":"Town",
    "qs_pg:woe_adm0":23424977,
    "woe:adm0_id":23424977,
    "woe:name_adm0":"United States",
    "woe:name_adm1":"Maryland",
    "woe:placetype":"Town",
    "wof:name":"Ancient Oak North",
    "wof:placetype":"locality"
},
  "geometry": {"coordinates":[-77.27221,39.12289],"type":"Point"}
}