{
  "type": "Feature",
  "properties": {
    "gn:admin1_code":"TN",
    "gn:admin2_code":"59",
    "gn:asciiname":"Harrison Hills",
    "gn:country_code":"US",
    "gn:dem":473,
    "gn:elevation":"467.0",
    "gn:feature_class":"P",
    "gn:feature_code":"PPL",
    "gn:name":"Harrison Hills",
    "gn:population":0,
    "gn:timezone":"America/New_York",
    "iso:country":"US",
    "wof:name":"Harrison Hills",
    "wof:placetype":"locality"
},
  "geometry": {"coordinates":[-82.79571,36.16288],"type":"Point"}
}