{
  "type": "Feature",
  "properties": {
    "gn:elevation":378,
    "iso:country":"US",
    "name:eng_x_preferred":[
        "Phoenix Mills"
    ],
    "name:eng_x_variant":[
        "Phoenix Mls"
    ],
    "qs:gn_adm0_cc":"US",
    "qs:gn_fcode":"PPL",
    "qs:gn_local":5126833,
    "qs:gn_nam_loc":"Middlefield, Otsego, New York, US",
    "qs:gn_namadm1":"NY",
    "qs:gn_name":"Phoenix Mills",
    "qs:local_max":3467,
    "qs:local_sum":3518,
    "qs:localhoods":4,
    "qs:name":"Phoenix Mills",
    "qs:name_adm0":"United States",
    "qs:name_adm1":"New York",
    "qs:name_adm2":"Otsego",
    "qs:name_local":"Middlefield",
    "qs:photo_max":10,
    "qs:photo_sum":32,
    "qs:placetype":"Suburb",
    "qs:quad_count":9,
    "qs:woe_adm0":23424977,
    "qs:woe_adm1":2347591,
    "qs:woe_adm2":12589350,
    "qs:woe_lau":0,
    "qs:woe_local":2450312,
    "qs:woe_ver":"7.10.0",
    "wof:lang":[
        "eng"
    ],
    "wof:name":"Phoenix Mills",
    "wof:placetype":"neighbourhood",
    "wof:population":383,
    "zs:blockids":[
        360775901004097,
        360775901004098,
        360775902022040,
        360775901004066,
        360775901004101,
        360775901004095,
        360775901004049,
        360775901004102,
        360775902022031,
        360775901004043,
        360775901004047,
        360775901004114,
        360775901004096,
        360775901004100,
        360775901004045,
        360775901004046,
        360775901004113
    ],
    "zs:housing10":152,
    "zs:pop10":383
},
  "geometry": {"coordinates":[-74.944782,42.660978],"type":"Point"}
}