{
  "type": "Feature",
  "properties": {
    "gn:admin1_code":"AZ",
    "gn:admin2_code":"7.0",
    "gn:asciiname":"Ponderosa Glen Mobile Home Park",
    "gn:country_code":"US",
    "gn:dem":1421,
    "gn:elevation":"1425.0",
    "gn:feature_class":"P",
    "gn:feature_code":"PPL",
    "gn:name":"Ponderosa Glen Mobile Home Park",
    "gn:population":0,
    "gn:timezone":"America/Phoenix",
    "iso:country":"US",
    "wof:name":"Ponderosa Glen Mobile Home Park",
    "wof:placetype":"campus"
},
  "geometry": {"coordinates":[-111.25946999999999,34.25866],"type":"Point"}
}