{
  "type": "Feature",
  "properties": {
    "gn:admin1_code":"FL",
    "gn:admin2_code":"19.0",
    "gn:asciiname":"Leno",
    "gn:country_code":"US",
    "gn:dem":12,
    "gn:elevation":"4.0",
    "gn:feature_class":"P",
    "gn:feature_code":"PPL",
    "gn:name":"Leno",
    "gn:population":0,
    "gn:timezone":"America/New_York",
    "iso:country":"US",
    "wof:name":"Leno",
    "wof:placetype":"locality"
},
  "geometry": {"coordinates":[-81.64064,29.88969],"type":"Point"}
}