{
  "type": "Feature",
  "properties": {
    "gn:admin1_code":"MO",
    "gn:admin2_code":"65.0",
    "gn:admin3_code":"55118.0",
    "gn:asciiname":"Howes Mill",
    "gn:country_code":"US",
    "gn:dem":427,
    "gn:elevation":"420.0",
    "gn:feature_class":"P",
    "gn:feature_code":"PPL",
    "gn:name":"Howes Mill",
    "gn:population":0,
    "gn:timezone":"America/Chicago",
    "iso:country":"US",
    "wof:name":"Howes Mill",
    "wof:placetype":"locality"
},
  "geometry": {"coordinates":[-91.29179999999999,37.61782],"type":"Point"}
}