{
  "type": "Feature",
  "properties": {
    "gn:admin1_code":"FL",
    "gn:admin2_code":"125.0",
    "gn:asciiname":"Browns Still",
    "gn:country_code":"US",
    "gn:dem":42,
    "gn:elevation":"45.0",
    "gn:feature_class":"P",
    "gn:feature_code":"PPL",
    "gn:name":"Browns Still",
    "gn:population":0,
    "gn:timezone":"America/New_York",
    "iso:country":"US",
    "wof:name":"Browns Still",
    "wof:placetype":"locality"
},
  "geometry": {"coordinates":[-82.49066999999999,29.98441],"type":"Point"}
}