{
  "type": "Feature",
  "properties": {
    "gn:admin1_code":"MD",
    "gn:admin2_code":"5.0",
    "gn:asciiname":"York Ridge",
    "gn:country_code":"US",
    "gn:dem":138,
    "gn:elevation":"128.0",
    "gn:feature_class":"P",
    "gn:feature_code":"PPL",
    "gn:name":"York Ridge",
    "gn:population":0,
    "gn:timezone":"America/New_York",
    "iso:country":"US",
    "wof:name":"York Ridge",
    "wof:placetype":"locality"
},
  "geometry": {"coordinates":[-76.63996999999998,39.41122],"type":"Point"}
}