{
  "type": "Feature",
  "properties": {
    "iso:country":"US",
    "name:eng_x_preferred":[
        "Mill Creek Falls"
    ],
    "wof:name":"Mill Creek Falls",
    "wof:placetype":"neighbourhood",
    "wof:population":2307,
    "zs:area_m":947870.088235,
    "zs:blockids":[
        420171004011006,
        420171004012009,
        420171004011026,
        420171004011022,
        420171004011020,
        420171004011023,
        420171004012010,
        420171004011008,
        420171004011012,
        420171004011024,
        420171004012019,
        420171004011007,
        420171004011009,
        420171004011010,
        420171004011027,
        420171004011016,
        420171004012008,
        420171004011011,
        420171004011017,
        420171004011018,
        420171004011021,
        420171008113008,
        420171004011019,
        420171004011005,
        420171004011025,
        420171004011015
    ],
    "zs:housing10":1136,
    "zs:label":"Mill Creek Falls",
    "zs:pop10":2307
},
  "geometry": {"coordinates":[-74.87473799999999,40.12968],"type":"Point"}
}