{
  "type": "Feature",
  "properties": {
    "gn:admin1_code":"ME",
    "gn:admin2_code":"25.0",
    "gn:admin3_code":"67238.0",
    "gn:asciiname":"Seboomook",
    "gn:country_code":"US",
    "gn:dem":319,
    "gn:elevation":"317.0",
    "gn:feature_class":"P",
    "gn:feature_code":"PPL",
    "gn:name":"Seboomook",
    "gn:population":0,
    "gn:timezone":"America/New_York",
    "iso:country":"US",
    "wof:name":"Seboomook",
    "wof:placetype":"locality"
},
  "geometry": {"coordinates":[-69.72506,45.8806],"type":"Point"}
}