{
  "type": "Feature",
  "properties": {
    "gn:country":"US",
    "gn:fcode":"PPL",
    "gn:population":0,
    "iso:country":"US",
    "name:azb_x_preferred":[
        "\u0627\u0644\u0633\u06cc"
    ],
    "name:eng_x_preferred":[
        "Elsie"
    ],
    "name:fas_x_preferred":[
        "\u0627\u0644\u0633\u06cc"
    ],
    "name:fra_x_preferred":[
        "Elsie"
    ],
    "name:hat_x_preferred":[
        "Elsie"
    ],
    "name:hun_x_preferred":[
        "Elsie"
    ],
    "name:jpn_x_preferred":[
        "\u30a8\u30eb\u30b7\u30fc"
    ],
    "qs_pg:aaroncc":"US",
    "qs_pg:gn_country":"US",
    "qs_pg:gn_fcode":"PPL",
    "qs_pg:gn_pop":0,
    "qs_pg:name":"Elsie",
    "qs_pg:name_adm0":"United States",
    "qs_pg:name_adm1":"Oregon",
    "qs_pg:photos":408,
    "qs_pg:photos_1k":83,
    "qs_pg:photos_9k":2,
    "qs_pg:photos_9r":5,
    "qs_pg:photos_all":408,
    "qs_pg:photos_sr":6,
    "qs_pg:pop_sr":5,
    "qs_pg:qs_pg_placetype":"locality",
    "qs_pg:qs_pg_placetype_gp":"Town",
    "qs_pg:woe_adm0":23424977,
    "woe:adm0_id":23424977,
    "woe:name_adm0":"United States",
    "woe:name_adm1":"Oregon",
    "woe:placetype":"Town",
    "wof:name":"Elsie",
    "wof:placetype":"locality"
},
  "geometry": {"coordinates":[-123.59484999999999,45.86567],"type":"Point"}
}