{
  "type": "Feature",
  "properties": {
    "iso:country":"US",
    "name:eng_x_preferred":[
        "Biscayne North"
    ],
    "qs:gn_adm0_cc":"US",
    "qs:gn_local":4166233,
    "qs:gn_nam_loc":"North Miami Beach, Miami-Dade, Florida, US",
    "qs:gn_namadm1":"FL",
    "qs:local_max":568,
    "qs:local_sum":792,
    "qs:localhoods":2,
    "qs:name":"Biscayne North",
    "qs:name_adm0":"United States",
    "qs:name_adm1":"Florida",
    "qs:name_adm2":"Miami-Dade",
    "qs:name_local":"North Miami Beach",
    "qs:photo_max":134,
    "qs:photo_sum":568,
    "qs:placetype":"Suburb",
    "qs:quad_count":15,
    "qs:woe_adm0":23424977,
    "qs:woe_adm1":2347568,
    "qs:woe_adm2":12587815,
    "qs:woe_lau":0,
    "qs:woe_local":2461331,
    "qs:woe_ver":"7.10.0",
    "wof:lang":[
        "eng"
    ],
    "wof:name":"Biscayne North",
    "wof:placetype":"neighbourhood",
    "wof:population":4105,
    "zs:blockids":[
        120860001281001,
        120860002061012,
        120860001091014,
        120860001321009,
        120860001281013,
        120860002061000,
        120860001281003,
        120860002122000,
        120860002122007,
        120860002122006,
        120860002122011,
        120860002143011,
        120860002111029,
        120860002061016,
        120860001281015,
        120860002143010,
        120860002121000,
        120860001281020,
        120860002121001,
        120860002122010,
        120860002112019,
        120860001281031,
        120860001281022,
        120860002061001,
        120860001281009,
        120860002122004,
        120860001281008,
        120860001321008,
        120860002112015,
        120860001281029,
        120860001281007,
        120860002123010,
        120860001091018,
        120860001281023,
        120860002122001,
        120860002122009,
        120860001281004,
        120860002061002,
        120860002122002,
        120860002122005,
        120860002061013,
        120860002061014,
        120860001281019,
        120860002122008,
        120860001281014,
        120860002122012,
        120860001091020,
        120860001281021,
        120860001281018,
        120860001281005,
        120860002112020,
        120860002061021,
        120860002111030,
        120860002122003,
        120860001281006,
        120860001281002,
        120860002143009,
        120860001281030,
        120860001091019,
        120860002121002,
        120860001281017
    ],
    "zs:housing10":1830,
    "zs:pop10":4105
},
  "geometry": {"coordinates":[-80.15394999999999,25.929726],"type":"Point"}
}