{
  "type": "Feature",
  "properties": {
    "gn:country":"US",
    "gn:fcode":"PPL",
    "gn:population":28637,
    "iso:country":"US",
    "qs_pg:aaroncc":"US",
    "qs_pg:gn_country":"US",
    "qs_pg:gn_fcode":"PPL",
    "qs_pg:gn_pop":28637,
    "qs_pg:name":"Socorro Mission Number 1 Colonia",
    "qs_pg:photos_9r":0,
    "qs_pg:photos_sr":0,
    "qs_pg:pop_sr":7,
    "qs_pg:qs_pg_placetype":"locality",
    "wof:name":"Socorro Mission Number 1 Colonia",
    "wof:placetype":"locality",
    "wof:population":28637
},
  "geometry": {"coordinates":[-106.29053999999999,31.63622],"type":"Point"}
}