{
  "type": "Feature",
  "properties": {
    "iso:country":"US",
    "name:eng_x_preferred":[
        "Lake View Terrace"
    ],
    "wd:wordcount":1379,
    "wof:name":"Lake View Terrace",
    "wof:placetype":"neighbourhood",
    "wof:population":688,
    "zs:area_m":818223.399991,
    "zs:blockids":[
        530110410033011,
        530110410033015,
        530110421002005,
        530110420002011,
        530110420002016,
        530110421002004,
        530110410051000,
        530110421002006,
        530110410033013,
        530110420002015,
        530110410033012,
        530110410033014,
        530110421002007,
        530110420002005,
        530110420002012,
        530110420002013,
        530110420002014,
        530110410033010,
        530110420002004,
        530110410052080
    ],
    "zs:housing10":269,
    "zs:label":"Lake View Terrace",
    "zs:pop10":688
},
  "geometry": {"coordinates":[-122.686271,45.653314],"type":"Point"}
}