{
  "type": "Feature",
  "properties": {
    "gn:admin1_code":"NM",
    "gn:admin2_code":"1",
    "gn:asciiname":"Barr",
    "gn:country_code":"US",
    "gn:dem":1499,
    "gn:elevation":"1500.0",
    "gn:feature_class":"P",
    "gn:feature_code":"PPL",
    "gn:name":"Barr",
    "gn:population":0,
    "gn:timezone":"America/Denver",
    "iso:country":"US",
    "name:ceb_x_preferred":[
        "Barr"
    ],
    "name:ces_x_preferred":[
        "Barr"
    ],
    "name:deu_x_preferred":[
        "Barr"
    ],
    "name:epo_x_preferred":[
        "Barr"
    ],
    "name:fra_x_preferred":[
        "Barr"
    ],
    "name:nds_x_preferred":[
        "Barr"
    ],
    "name:pol_x_preferred":[
        "Barr"
    ],
    "name:por_x_preferred":[
        "Barr"
    ],
    "name:rus_x_preferred":[
        "\u0411\u0430\u0440\u0440"
    ],
    "name:spa_x_preferred":[
        "Barr"
    ],
    "name:swe_x_preferred":[
        "Barr"
    ],
    "name:ukr_x_preferred":[
        "\u0411\u0430\u0440\u0440"
    ],
    "wof:name":"Barr",
    "wof:placetype":"locality"
},
  "geometry": {"coordinates":[-106.66752,34.97755],"type":"Point"}
}