{
  "type": "Feature",
  "properties": {
    "gn:admin1_code":"SC",
    "gn:admin2_code":"65.0",
    "gn:asciiname":"Hickory Knob Subdivision",
    "gn:country_code":"US",
    "gn:dem":112,
    "gn:elevation":"106.0",
    "gn:feature_class":"P",
    "gn:feature_code":"PPL",
    "gn:name":"Hickory Knob Subdivision",
    "gn:population":0,
    "gn:timezone":"America/New_York",
    "iso:country":"US",
    "wof:name":"Hickory Knob Subdivision",
    "wof:placetype":"locality"
},
  "geometry": {"coordinates":[-82.43401999999998,33.8929],"type":"Point"}
}