{
  "type": "Feature",
  "properties": {
    "gn:elevation":170,
    "iso:country":"US",
    "name:eng_x_preferred":[
        "Alphano"
    ],
    "qs:gn_adm0_cc":"US",
    "qs:gn_fcode":"PPL",
    "qs:gn_local":5095115,
    "qs:gn_nam_loc":"Allamuchy, Warren, New Jersey, US",
    "qs:gn_namadm1":"NJ",
    "qs:gn_name":"Alphano",
    "qs:local_max":51,
    "qs:local_sum":127,
    "qs:localhoods":5,
    "qs:name":"Alphano",
    "qs:name_adm0":"United States",
    "qs:name_adm1":"New Jersey",
    "qs:name_adm2":"Warren",
    "qs:name_local":"Allamuchy",
    "qs:photo_max":19,
    "qs:photo_sum":20,
    "qs:placetype":"Suburb",
    "qs:quad_count":2,
    "qs:woe_adm0":23424977,
    "qs:woe_adm1":2347589,
    "qs:woe_adm2":12589278,
    "qs:woe_lau":0,
    "qs:woe_local":2353207,
    "qs:woe_ver":"7.10.0",
    "wof:lang":[
        "eng"
    ],
    "wof:name":"Alphano",
    "wof:placetype":"neighbourhood",
    "wof:population":3079,
    "zs:blockids":[
        340410313021051,
        340410313021049,
        340410313023009,
        340410313021136,
        340410313021149,
        340410313022013,
        340410313021155,
        340410313021134,
        340410313021141,
        340410313021028,
        340410313021065,
        340410313011018,
        340410313022018,
        340410313021135,
        340410313021063,
        340410313021153,
        340410313023010,
        340410313023018,
        340410313021053,
        340410313021142,
        340410313021050,
        340410313022015,
        340410313021132,
        340410313023007,
        340410313021044,
        340410313022016,
        340410313021046,
        340410313023006,
        340410313021048,
        340410313021052,
        340410313021147,
        340410313023016,
        340410313023012,
        340410313021154,
        340410313021152,
        340410313022014,
        340410313023005,
        340410313021146,
        340410313011015,
        340410313021140,
        340410313022017,
        340410313021047,
        340410313011014,
        340410313021156,
        340410313023011,
        340410313012000,
        340410313021139,
        340410313021045,
        340410313023020,
        340410313011019,
        340410313021043,
        340410313023017,
        340410313022020,
        340410313021064,
        340410313021148,
        340410313021066,
        340410313023008,
        340410313021019,
        340410313023015,
        340410313022019,
        340410313023013,
        340410313021137,
        340410313021138,
        340410313021150,
        340410313023014,
        340410313023019
    ],
    "zs:housing10":1465,
    "zs:pop10":3079
},
  "geometry": {"coordinates":[-74.852875,40.903339],"type":"Point"}
}