{
  "type": "Feature",
  "properties": {
    "gn:admin1_code":"TX",
    "gn:admin2_code":"373.0",
    "gn:asciiname":"Oak Shade",
    "gn:country_code":"US",
    "gn:dem":55,
    "gn:elevation":"48.0",
    "gn:feature_class":"P",
    "gn:feature_code":"PPL",
    "gn:name":"Oak Shade",
    "gn:population":0,
    "gn:timezone":"America/Chicago",
    "iso:country":"US",
    "wof:name":"Oak Shade",
    "wof:placetype":"locality"
},
  "geometry": {"coordinates":[-94.57853,30.53437000000001],"type":"Point"}
}