{
  "type": "Feature",
  "properties": {
    "gn:admin1_code":"NY",
    "gn:admin2_code":"3.0",
    "gn:admin3_code":"64166.0",
    "gn:asciiname":"Hillcrest",
    "gn:country_code":"US",
    "gn:dem":477,
    "gn:elevation":"473.0",
    "gn:feature_class":"P",
    "gn:feature_code":"PPL",
    "gn:name":"Hillcrest",
    "gn:population":0,
    "gn:timezone":"America/New_York",
    "iso:country":"US",
    "name:bar_x_preferred":[
        "Hillcrest"
    ],
    "name:cat_x_preferred":[
        "Hillcrest"
    ],
    "name:ceb_x_preferred":[
        "Hillcrest"
    ],
    "name:deu_x_preferred":[
        "Hillcrest"
    ],
    "name:ita_x_preferred":[
        "Hillcrest"
    ],
    "name:nld_x_preferred":[
        "Hillcrest"
    ],
    "name:pol_x_preferred":[
        "Hillcrest"
    ],
    "name:por_x_preferred":[
        "Hillcrest"
    ],
    "name:srp_x_preferred":[
        "\u0425\u0438\u043b\u043a\u0440\u0435\u0441\u0442"
    ],
    "name:ukr_x_preferred":[
        "\u0413\u0456\u043b\u043b\u043a\u0440\u0435\u0441\u0442"
    ],
    "name:vol_x_preferred":[
        "Hillcrest"
    ],
    "wof:name":"Hillcrest",
    "wof:placetype":"locality"
},
  "geometry": {"coordinates":[-78.20529000000001,42.37923],"type":"Point"}
}