{
  "type": "Feature",
  "properties": {
    "gn:admin1_code":"OH",
    "gn:admin2_code":"61",
    "gn:admin3_code":"1672.0",
    "gn:asciiname":"Rolling Knolls Estate",
    "gn:country_code":"US",
    "gn:dem":253,
    "gn:elevation":"247.0",
    "gn:feature_class":"P",
    "gn:feature_code":"PPL",
    "gn:name":"Rolling Knolls Estate",
    "gn:population":0,
    "gn:timezone":"America/New_York",
    "iso:country":"US",
    "wof:name":"Rolling Knolls Estate",
    "wof:placetype":"locality"
},
  "geometry": {"coordinates":[-84.42215999999998,39.20756],"type":"Point"}
}