{
  "type": "Feature",
  "properties": {
    "gn:country":"US",
    "gn:fcode":"PPL",
    "gn:population":0,
    "iso:country":"US",
    "name:eng_x_preferred":[
        "Arrowhead Springs"
    ],
    "name:fra_x_preferred":[
        "Arrowhead Springs"
    ],
    "name:nld_x_preferred":[
        "Arrowhead Springs"
    ],
    "name:spa_x_preferred":[
        "Arrowhead Springs"
    ],
    "name:und_x_variant":[
        "Arrow Head Springs"
    ],
    "qs_pg:aaroncc":"US",
    "qs_pg:gn_country":"US",
    "qs_pg:gn_fcode":"PPL",
    "qs_pg:gn_pop":0,
    "qs_pg:name":"Arrowhead Springs",
    "qs_pg:name_adm0":"United States",
    "qs_pg:name_adm1":"California",
    "qs_pg:photos":39,
    "qs_pg:photos_1k":8,
    "qs_pg:photos_9k":1,
    "qs_pg:photos_9r":2,
    "qs_pg:photos_all":39,
    "qs_pg:photos_sr":2,
    "qs_pg:pop_sr":0,
    "qs_pg:qs_pg_placetype":"locality",
    "qs_pg:qs_pg_placetype_gp":"Town",
    "qs_pg:woe_adm0":23424977,
    "woe:adm0_id":23424977,
    "woe:name_adm0":"United States",
    "woe:name_adm1":"California",
    "woe:placetype":"Town",
    "wof:name":"Arrowhead Springs",
    "wof:placetype":"locality"
},
  "geometry": {"coordinates":[-117.26170999999999,34.18668],"type":"Point"}
}