{
  "type": "Feature",
  "properties": {
    "gn:admin1_code":"NM",
    "gn:admin2_code":"51.0",
    "gn:asciiname":"Jornada",
    "gn:country_code":"US",
    "gn:dem":1444,
    "gn:elevation":"1445.0",
    "gn:feature_class":"P",
    "gn:feature_code":"PPL",
    "gn:name":"Jornada",
    "gn:population":0,
    "gn:timezone":"America/Denver",
    "iso:country":"US",
    "name:cat_x_preferred":[
        "Jornada"
    ],
    "name:deu_x_preferred":[
        "Jornada"
    ],
    "name:por_x_preferred":[
        "Jornada"
    ],
    "name:spa_x_preferred":[
        "Jornada"
    ],
    "wof:name":"Jornada",
    "wof:placetype":"locality"
},
  "geometry": {"coordinates":[-107.03391000000001,33.12313],"type":"Point"}
}