{
  "type": "Feature",
  "properties": {
    "gn:admin1_code":"VA",
    "gn:admin2_code":"550",
    "gn:asciiname":"Edgewood",
    "gn:country_code":"US",
    "gn:dem":7,
    "gn:elevation":"4.0",
    "gn:feature_class":"P",
    "gn:feature_code":"PPL",
    "gn:name":"Edgewood",
    "gn:population":0,
    "gn:timezone":"America/New_York",
    "iso:country":"US",
    "name:cat_x_preferred":[
        "Edgewood"
    ],
    "name:ceb_x_preferred":[
        "Edgewood"
    ],
    "name:deu_x_preferred":[
        "Edgewood"
    ],
    "name:fas_x_preferred":[
        "\u0627\u062c\u0648\u0648\u062f"
    ],
    "name:fra_x_preferred":[
        "Edgewood"
    ],
    "name:ita_x_preferred":[
        "Edgewood"
    ],
    "name:kor_x_preferred":[
        "\uc5d0\uc9c0\uc6b0\ub4dc"
    ],
    "name:nld_x_preferred":[
        "Edgewood"
    ],
    "name:pol_x_preferred":[
        "Edgewood"
    ],
    "name:por_x_preferred":[
        "Edgewood"
    ],
    "name:spa_x_preferred":[
        "Edgewood"
    ],
    "name:srp_x_preferred":[
        "\u0415\u045f\u0432\u0443\u0434"
    ],
    "name:swe_x_preferred":[
        "Edgewood"
    ],
    "name:ukr_x_preferred":[
        "\u0415\u0434\u0436\u0432\u0443\u0434"
    ],
    "name:urd_x_preferred":[
        "\u0627\u06cc\u062c\u0648\u0648\u0688"
    ],
    "name:vol_x_preferred":[
        "Edgewood"
    ],
    "wof:name":"Edgewood",
    "wof:placetype":"locality"
},
  "geometry": {"coordinates":[-76.23272,36.73682],"type":"Point"}
}