{
  "type": "Feature",
  "properties": {
    "gn:admin1_code":"MO",
    "gn:admin2_code":"41.0",
    "gn:admin3_code":"65486.0",
    "gn:asciiname":"Newhall",
    "gn:country_code":"US",
    "gn:dem":256,
    "gn:elevation":"249.0",
    "gn:feature_class":"P",
    "gn:feature_code":"PPL",
    "gn:name":"Newhall",
    "gn:population":0,
    "gn:timezone":"America/Chicago",
    "iso:country":"US",
    "name:ceb_x_preferred":[
        "Newhall"
    ],
    "name:deu_x_preferred":[
        "Newhall"
    ],
    "name:fas_x_preferred":[
        "\u0646\u06cc\u0648\u0647\u0627\u0644"
    ],
    "name:fra_x_preferred":[
        "Newhall"
    ],
    "name:ita_x_preferred":[
        "Newhall"
    ],
    "name:nld_x_preferred":[
        "Newhall"
    ],
    "name:pol_x_preferred":[
        "Newhall"
    ],
    "name:swe_x_preferred":[
        "Newhall"
    ],
    "wof:name":"Newhall",
    "wof:placetype":"locality"
},
  "geometry": {"coordinates":[-93.03214,39.57725],"type":"Point"}
}