{
  "type": "Feature",
  "properties": {
    "gn:admin1_code":"OH",
    "gn:admin2_code":"23.0",
    "gn:admin3_code":"31703.0",
    "gn:asciiname":"Cortsville",
    "gn:country_code":"US",
    "gn:dem":345,
    "gn:elevation":"344.0",
    "gn:feature_class":"P",
    "gn:feature_code":"PPL",
    "gn:name":"Cortsville",
    "gn:population":0,
    "gn:timezone":"America/New_York",
    "iso:country":"US",
    "name:eng_x_preferred":[
        "Cortsville"
    ],
    "name:und_x_variant":[
        "Selma",
        "Courtsville"
    ],
    "wof:name":"Cortsville",
    "wof:placetype":"locality"
},
  "geometry": {"coordinates":[-83.72104,39.79645],"type":"Point"}
}