{
  "type": "Feature",
  "properties": {
    "gn:admin1_code":"NV",
    "gn:admin2_code":"1.0",
    "gn:asciiname":"Parran",
    "gn:country_code":"US",
    "gn:dem":1186,
    "gn:elevation":"1184.0",
    "gn:feature_class":"P",
    "gn:feature_code":"PPL",
    "gn:name":"Parran",
    "gn:population":0,
    "gn:timezone":"America/Los_Angeles",
    "iso:country":"US",
    "name:eng_x_preferred":[
        "Parran"
    ],
    "name:und_x_variant":[
        "Paran"
    ],
    "wof:name":"Parran",
    "wof:placetype":"locality"
},
  "geometry": {"coordinates":[-118.77321000000001,39.8013],"type":"Point"}
}