{
  "type": "Feature",
  "properties": {
    "gn:admin1_code":"LA",
    "gn:admin2_code":"127.0",
    "gn:asciiname":"Bethlehem",
    "gn:country_code":"US",
    "gn:dem":58,
    "gn:elevation":"53.0",
    "gn:feature_class":"P",
    "gn:feature_code":"PPL",
    "gn:name":"Bethlehem",
    "gn:population":0,
    "gn:timezone":"America/Chicago",
    "iso:country":"US",
    "wof:name":"Bethlehem",
    "wof:placetype":"locality"
},
  "geometry": {"coordinates":[-92.77349,32.00544],"type":"Point"}
}