{
  "type": "Feature",
  "properties": {
    "iso:country":"US",
    "name:eng_x_preferred":[
        "North Blendon"
    ],
    "name:eng_x_variant":[
        "N Blendon"
    ],
    "qs:gn_adm0_cc":"US",
    "qs:gn_fcode":"PPL",
    "qs:gn_local":4984029,
    "qs:gn_nam_loc":"Allendale, Ottawa, Michigan, US",
    "qs:gn_namadm1":"MI",
    "qs:gn_name":"North Blendon",
    "qs:local_max":159,
    "qs:local_sum":203,
    "qs:localhoods":2,
    "qs:name":"North Blendon",
    "qs:name_adm0":"United States",
    "qs:name_adm1":"Michigan",
    "qs:name_adm2":"Ottawa",
    "qs:name_local":"Allendale",
    "qs:photo_max":30,
    "qs:photo_sum":44,
    "qs:placetype":"Suburb",
    "qs:quad_count":4,
    "qs:woe_adm0":23424977,
    "qs:woe_adm1":2347581,
    "qs:woe_adm2":12588783,
    "qs:woe_lau":0,
    "qs:woe_local":2353321,
    "qs:woe_ver":"7.10.0",
    "wof:lang":[
        "eng"
    ],
    "wof:name":"North Blendon",
    "wof:placetype":"neighbourhood"
},
  "geometry": {"coordinates":[-85.95066300000001,42.964372],"type":"Point"}
}