{
  "type": "Feature",
  "properties": {
    "gn:admin1_code":"MD",
    "gn:admin2_code":"13.0",
    "gn:asciiname":"Ridgemont",
    "gn:country_code":"US",
    "gn:dem":200,
    "gn:elevation":"205.0",
    "gn:feature_class":"P",
    "gn:feature_code":"PPL",
    "gn:name":"Ridgemont",
    "gn:population":0,
    "gn:timezone":"America/New_York",
    "iso:country":"US",
    "wof:name":"Ridgemont",
    "wof:placetype":"locality"
},
  "geometry": {"coordinates":[-76.91275999999998,39.51399],"type":"Point"}
}