{
  "type": "Feature",
  "properties": {
    "gn:admin1_code":"MI",
    "gn:admin2_code":"147.0",
    "gn:admin3_code":"65840.0",
    "gn:asciiname":"Fenner's Mobile Village",
    "gn:country_code":"US",
    "gn:dem":194,
    "gn:elevation":"191.0",
    "gn:feature_class":"P",
    "gn:feature_code":"PPL",
    "gn:name":"Fenner's Mobile Village",
    "gn:population":0,
    "gn:timezone":"America/Detroit",
    "iso:country":"US",
    "wof:name":"Fenner's Mobile Village",
    "wof:placetype":"locality"
},
  "geometry": {"coordinates":[-82.49167,42.98139000000001],"type":"Point"}
}