{
  "type": "Feature",
  "properties": {
    "gn:admin1_code":"VA",
    "gn:admin2_code":"175",
    "gn:asciiname":"Burdette",
    "gn:country_code":"US",
    "gn:dem":10,
    "gn:elevation":"8.0",
    "gn:feature_class":"P",
    "gn:feature_code":"PPL",
    "gn:name":"Burdette",
    "gn:population":0,
    "gn:timezone":"America/New_York",
    "iso:country":"US",
    "name:deu_x_preferred":[
        "Burdette"
    ],
    "name:eng_x_preferred":[
        "Burdette"
    ],
    "name:nld_x_preferred":[
        "Burdette"
    ],
    "name:pol_x_preferred":[
        "Burdette"
    ],
    "name:por_x_preferred":[
        "Burdette"
    ],
    "name:rus_x_preferred":[
        "\u0411\u0435\u0440\u0434\u0435\u0442\u0442"
    ],
    "name:und_x_variant":[
        "Burdett"
    ],
    "wof:name":"Burdette",
    "wof:placetype":"locality"
},
  "geometry": {"coordinates":[-76.89829,36.76848],"type":"Point"}
}