{
  "type": "Feature",
  "properties": {
    "iso:country":"US",
    "name:ceb_x_preferred":[
        "Glenbrook"
    ],
    "name:deu_x_preferred":[
        "Glenbrook"
    ],
    "name:eng_x_preferred":[
        "Glenbrook"
    ],
    "name:swe_x_preferred":[
        "Glenbrook"
    ],
    "wd:wordcount":105,
    "wof:name":"Glenbrook",
    "wof:placetype":"neighbourhood",
    "wof:population":1568,
    "zs:area_m":1341921.547321,
    "zs:blockids":[
        120690313114026,
        120690313112043,
        120690313114101,
        120690313113058,
        120690313112042,
        120690313112041,
        120690313112038,
        120690313114112,
        120690313114039,
        120690313114041,
        120690313114131,
        120690313114035,
        120690313114136,
        120690313114046,
        120690313112040,
        120690313112039,
        120690313113060,
        120690313114116,
        120690313114120,
        120690313114040,
        120690313113071,
        120690313114150,
        120690313114079,
        120690313114102,
        120690313114091,
        120690313114122,
        120690313114159,
        120690313113056,
        120690313114083,
        120690313113043,
        120690313114062,
        120690313114138
    ],
    "zs:housing10":849,
    "zs:label":"Glenbrook",
    "zs:pop10":1568
},
  "geometry": {"coordinates":[-81.68167200000001,28.371384],"type":"Point"}
}