{
  "type": "Feature",
  "properties": {
    "gn:admin1_code":"ND",
    "gn:admin2_code":"17.0",
    "gn:admin3_code":"24660.0",
    "gn:asciiname":"Mason",
    "gn:country_code":"US",
    "gn:dem":318,
    "gn:elevation":"320.0",
    "gn:feature_class":"P",
    "gn:feature_code":"PPL",
    "gn:name":"Mason",
    "gn:population":0,
    "gn:timezone":"America/Chicago",
    "iso:country":"US",
    "name:bul_x_preferred":[
        "\u041c\u0435\u0439\u0441\u044a\u043d"
    ],
    "name:cat_x_preferred":[
        "Mason"
    ],
    "name:ceb_x_preferred":[
        "Mason"
    ],
    "name:ces_x_preferred":[
        "Mason"
    ],
    "name:deu_x_preferred":[
        "Mason"
    ],
    "name:eng_x_preferred":[
        "Mason"
    ],
    "name:fra_x_preferred":[
        "Mason"
    ],
    "name:heb_x_preferred":[
        "\u05de\u05d9\u05d9\u05e1\u05d5\u05df"
    ],
    "name:ita_x_preferred":[
        "Mason"
    ],
    "name:jpn_x_preferred":[
        "\u30e1\u30a4\u30bd\u30f3"
    ],
    "name:kor_x_preferred":[
        "\uba54\uc774\uc2a8"
    ],
    "name:lav_x_preferred":[
        "Meisons"
    ],
    "name:mkd_x_preferred":[
        "\u041c\u0430\u0441\u043e\u043d"
    ],
    "name:nld_x_preferred":[
        "Mason"
    ],
    "name:pol_x_preferred":[
        "Mason"
    ],
    "name:por_x_preferred":[
        "Mason"
    ],
    "name:rus_x_preferred":[
        "\u041c\u0435\u0439\u0441\u043e\u043d"
    ],
    "name:slv_x_preferred":[
        "Mason"
    ],
    "name:spa_x_preferred":[
        "Mason"
    ],
    "name:srn_x_preferred":[
        "Mason"
    ],
    "name:srp_x_preferred":[
        "\u041c\u0435\u0458\u0441\u043e\u043d"
    ],
    "name:swe_x_preferred":[
        "Mason"
    ],
    "name:ukr_x_preferred":[
        "\u041c\u0435\u0439\u0441\u043e\u043d"
    ],
    "name:und_x_variant":[
        "Oatland"
    ],
    "name:urd_x_preferred":[
        "\u0645\u06cc\u0633\u0646"
    ],
    "name:vol_x_preferred":[
        "Mason"
    ],
    "wof:name":"Mason",
    "wof:placetype":"locality"
},
  "geometry": {"coordinates":[-97.32898,47.07359],"type":"Point"}
}