{
  "type": "Feature",
  "properties": {
    "gn:admin1_code":"AR",
    "gn:admin2_code":"65.0",
    "gn:admin3_code":"90513.0",
    "gn:asciiname":"Dolph",
    "gn:country_code":"US",
    "gn:dem":272,
    "gn:elevation":"269.0",
    "gn:feature_class":"P",
    "gn:feature_code":"PPL",
    "gn:name":"Dolph",
    "gn:population":0,
    "gn:timezone":"America/Chicago",
    "iso:country":"US",
    "name:fas_x_preferred":[
        "\u062f\u0644\u0641"
    ],
    "name:zho_x_preferred":[
        "\u591a\u723e\u592b"
    ],
    "wof:name":"Dolph",
    "wof:placetype":"locality"
},
  "geometry": {"coordinates":[-92.11265,36.2284],"type":"Point"}
}