{
  "type": "Feature",
  "properties": {
    "gn:country":"US",
    "gn:fcode":"PPL",
    "gn:population":0,
    "iso:country":"US",
    "name:eng_x_preferred":[
        "Cox Town"
    ],
    "name:und_x_variant":[
        "Coxtown"
    ],
    "qs_pg:aaroncc":"US",
    "qs_pg:gn_country":"US",
    "qs_pg:gn_fcode":"PPL",
    "qs_pg:gn_pop":0,
    "qs_pg:name":"Cox Town",
    "qs_pg:name_adm0":"United States",
    "qs_pg:name_adm1":"West Virginia",
    "qs_pg:photos":40,
    "qs_pg:photos_1k":8,
    "qs_pg:photos_9k":1,
    "qs_pg:photos_9r":2,
    "qs_pg:photos_all":40,
    "qs_pg:photos_sr":2,
    "qs_pg:pop_sr":0,
    "qs_pg:qs_pg_placetype":"neighbourhood",
    "qs_pg:qs_pg_placetype_gp":"Suburb",
    "qs_pg:woe_adm0":23424977,
    "wd:wordcount":24,
    "wof:name":"Cox Town",
    "wof:placetype":"neighbourhood",
    "wof:population":178,
    "zs:area_m":4148766.907461,
    "zs:blockids":[
        540419674002061,
        540419674002160,
        540419674002066,
        540419676002061,
        540419674002163,
        540419676002065,
        540419674002176,
        540419674002170,
        540419674002162,
        540419674002161,
        540419674002062,
        540419674002055,
        540419674002172,
        540419676002059,
        540419674002164,
        540419674002065
    ],
    "zs:housing10":89,
    "zs:label":"Cox Town",
    "zs:pop10":178
},
  "geometry": {"coordinates":[-80.465445,39.020947],"type":"Point"}
}