{
  "type": "Feature",
  "properties": {
    "gn:country":"US",
    "gn:fcode":"PPL",
    "gn:population":0,
    "iso:country":"US",
    "name:cat_x_preferred":[
        "Allentown"
    ],
    "name:ceb_x_preferred":[
        "Allentown"
    ],
    "name:ces_x_preferred":[
        "Allentown"
    ],
    "name:deu_x_preferred":[
        "Allentown"
    ],
    "name:epo_x_preferred":[
        "Allentown"
    ],
    "name:fra_x_preferred":[
        "Allentown"
    ],
    "name:ita_x_preferred":[
        "Allentown"
    ],
    "name:jpn_x_preferred":[
        "\u30a2\u30ec\u30f3\u30bf\u30a6\u30f3"
    ],
    "name:nld_x_preferred":[
        "Allentown"
    ],
    "name:pol_x_preferred":[
        "Allentown"
    ],
    "name:por_x_preferred":[
        "Allentown"
    ],
    "name:rus_x_preferred":[
        "\u0410\u043b\u043b\u0435\u043d\u0442\u0430\u0443\u043d"
    ],
    "name:spa_x_preferred":[
        "Allentown"
    ],
    "name:srp_x_preferred":[
        "\u0410\u043b\u0435\u043d\u0442\u0430\u0443\u043d"
    ],
    "name:swe_x_preferred":[
        "Allentown"
    ],
    "name:ukr_x_preferred":[
        "\u0410\u043b\u043b\u0435\u043d\u0442\u0430\u0443\u043d"
    ],
    "name:urd_x_preferred":[
        "\u0627\u06cc\u0644\u0646 \u0679\u0627\u0624\u0646"
    ],
    "name:vol_x_preferred":[
        "Allentown"
    ],
    "name:zho_x_preferred":[
        "\u963f\u4f26\u6566"
    ],
    "qs_pg:aaroncc":"US",
    "qs_pg:gn_country":"US",
    "qs_pg:gn_fcode":"PPL",
    "qs_pg:gn_pop":0,
    "qs_pg:name":"Allentown",
    "qs_pg:name_adm0":"United States",
    "qs_pg:name_adm1":"New York",
    "qs_pg:photos_9k":1,
    "qs_pg:photos_9r":2,
    "qs_pg:photos_all":66,
    "qs_pg:photos_sr":0,
    "qs_pg:pop_sr":0,
    "qs_pg:qs_pg_placetype":"locality",
    "qs_pg:qs_pg_placetype_gp":"Town",
    "qs_pg:woe_adm0":23424977,
    "woe:adm0_id":23424977,
    "woe:name_adm0":"United States",
    "woe:name_adm1":"New York",
    "woe:placetype":"Town",
    "wof:name":"Allentown",
    "wof:placetype":"locality"
},
  "geometry": {"coordinates":[-78.06444999999999,42.08368],"type":"Point"}
}