{
  "type": "Feature",
  "properties": {
    "gn:admin1_code":"MO",
    "gn:admin2_code":"155.0",
    "gn:admin3_code":"16012.0",
    "gn:asciiname":"Ingram Ridge",
    "gn:country_code":"US",
    "gn:dem":82,
    "gn:elevation":"81.0",
    "gn:feature_class":"P",
    "gn:feature_code":"PPL",
    "gn:name":"Ingram Ridge",
    "gn:population":0,
    "gn:timezone":"America/Chicago",
    "iso:country":"US",
    "wof:name":"Ingram Ridge",
    "wof:placetype":"locality"
},
  "geometry": {"coordinates":[-89.79092,36.29173],"type":"Point"}
}