{
  "type": "Feature",
  "properties": {
    "gn:admin1_code":"ID",
    "gn:admin2_code":"85",
    "gn:asciiname":"Stibnite",
    "gn:country_code":"US",
    "gn:dem":2019,
    "gn:elevation":"2020.0",
    "gn:feature_class":"P",
    "gn:feature_code":"PPL",
    "gn:name":"Stibnite",
    "gn:population":0,
    "gn:timezone":"America/Boise",
    "iso:country":"US",
    "name:aze_x_preferred":[
        "Antimonit"
    ],
    "name:bel_x_preferred":[
        "\u0410\u043d\u0442\u044b\u043c\u0430\u043d\u0456\u0442"
    ],
    "name:bul_x_preferred":[
        "\u0410\u043d\u0442\u0438\u043c\u043e\u043d\u0438\u0442"
    ],
    "name:cat_x_preferred":[
        "Estibina"
    ],
    "name:ces_x_preferred":[
        "Antimonit"
    ],
    "name:deu_x_preferred":[
        "Stibnit"
    ],
    "name:div_x_preferred":[
        "\u078e\u07a6\u078d\u07a6\u078b\u07aa\u0782\u07b0"
    ],
    "name:ell_x_preferred":[
        "\u0391\u03bd\u03c4\u03b9\u03bc\u03bf\u03bd\u03af\u03c4\u03b7\u03c2"
    ],
    "name:eus_x_preferred":[
        "Estibina"
    ],
    "name:fas_x_preferred":[
        "\u0627\u0633\u062a\u06cc\u0628\u06cc\u0646"
    ],
    "name:fin_x_preferred":[
        "Antimonihohde"
    ],
    "name:fra_x_preferred":[
        "Stibine"
    ],
    "name:gle_x_preferred":[
        "Stibn\u00edt"
    ],
    "name:hrv_x_preferred":[
        "Antimonit"
    ],
    "name:hun_x_preferred":[
        "Antimonit"
    ],
    "name:hye_x_preferred":[
        "\u0531\u0576\u057f\u056b\u0574\u0578\u0576\u056b\u057f"
    ],
    "name:ita_x_preferred":[
        "Stibnite"
    ],
    "name:jpn_x_preferred":[
        "\u8f1d\u5b89\u9271"
    ],
    "name:kaz_x_preferred":[
        "\u0410\u043d\u0442\u0438\u043c\u043e\u043d\u0438\u0442"
    ],
    "name:kir_x_preferred":[
        "\u0410\u043d\u0442\u0438\u043c\u043e\u043d\u0438\u0442"
    ],
    "name:lit_x_preferred":[
        "Antimonitas"
    ],
    "name:nds_x_preferred":[
        "Stibnit"
    ],
    "name:nld_x_preferred":[
        "Stibniet"
    ],
    "name:nno_x_preferred":[
        "Stibnitt"
    ],
    "name:nor_x_preferred":[
        "Stibnitt"
    ],
    "name:pol_x_preferred":[
        "Antymonit"
    ],
    "name:por_x_preferred":[
        "Estibina"
    ],
    "name:ron_x_preferred":[
        "Stibnit"
    ],
    "name:rus_x_preferred":[
        "\u0410\u043d\u0442\u0438\u043c\u043e\u043d\u0438\u0442"
    ],
    "name:slk_x_preferred":[
        "Antimonit"
    ],
    "name:slv_x_preferred":[
        "Antimonit"
    ],
    "name:spa_x_preferred":[
        "Estibina"
    ],
    "name:srp_x_preferred":[
        "\u0410\u043d\u0442\u0438\u043c\u043e\u043d\u0438\u0442"
    ],
    "name:swe_x_preferred":[
        "Spetsglans"
    ],
    "name:tgk_x_preferred":[
        "\u0410\u043d\u0442\u0438\u043c\u043e\u043d\u0438\u0442"
    ],
    "name:tha_x_preferred":[
        "\u0e2a\u0e15\u0e34\u0e1a\u0e44\u0e19\u0e17\u0e4c"
    ],
    "name:ukr_x_preferred":[
        "\u0410\u043d\u0442\u0438\u043c\u043e\u043d\u0456\u0442"
    ],
    "name:uzb_x_preferred":[
        "Antimonit"
    ],
    "name:vie_x_preferred":[
        "Stibnite"
    ],
    "name:zho_x_preferred":[
        "\u8f89\u9511\u77ff"
    ],
    "wof:name":"Stibnite",
    "wof:placetype":"locality"
},
  "geometry": {"coordinates":[-115.33928,44.89824],"type":"Point"}
}