{
  "type": "Feature",
  "properties": {
    "gn:admin1_code":"IA",
    "gn:admin2_code":"61.0",
    "gn:admin3_code":"90798.0",
    "gn:asciiname":"Cottage Hill",
    "gn:country_code":"US",
    "gn:dem":344,
    "gn:elevation":"348.0",
    "gn:feature_class":"P",
    "gn:feature_code":"PPL",
    "gn:name":"Cottage Hill",
    "gn:population":0,
    "gn:timezone":"America/Chicago",
    "iso:country":"US",
    "name:ceb_x_preferred":[
        "Cottage Hill"
    ],
    "name:deu_x_preferred":[
        "Cottage Hill"
    ],
    "wof:name":"Cottage Hill",
    "wof:placetype":"locality"
},
  "geometry": {"coordinates":[-90.91374,42.58528],"type":"Point"}
}