{
  "type": "Feature",
  "properties": {
    "gn:country":"US",
    "gn:fcode":"PPL",
    "gn:population":0,
    "iso:country":"US",
    "name:cat_x_preferred":[
        "Waterville"
    ],
    "name:ceb_x_preferred":[
        "Waterville"
    ],
    "name:deu_x_preferred":[
        "Waterville"
    ],
    "name:eng_x_preferred":[
        "Waterville"
    ],
    "name:fin_x_preferred":[
        "Waterville"
    ],
    "name:fra_x_preferred":[
        "Waterville"
    ],
    "name:ita_x_preferred":[
        "Waterville"
    ],
    "name:jpn_x_preferred":[
        "\u30a6\u30a9\u30fc\u30bf\u30fc\u30d3\u30eb"
    ],
    "name:kor_x_preferred":[
        "\uc6cc\ud130\ube4c"
    ],
    "name:nld_x_preferred":[
        "Waterville"
    ],
    "name:pol_x_preferred":[
        "Waterville"
    ],
    "name:por_x_preferred":[
        "Waterville"
    ],
    "name:rus_x_preferred":[
        "\u0423\u043e\u0442\u0435\u0440\u0432\u0438\u043b\u043b"
    ],
    "name:spa_x_preferred":[
        "Waterville"
    ],
    "name:srp_x_preferred":[
        "\u0412\u043e\u0442\u0435\u0440\u0432\u0438\u043b"
    ],
    "name:swe_x_preferred":[
        "Waterville"
    ],
    "name:und_x_variant":[
        "Walterville"
    ],
    "name:vol_x_preferred":[
        "Waterville"
    ],
    "qs_pg:aaroncc":"US",
    "qs_pg:gn_country":"US",
    "qs_pg:gn_fcode":"PPL",
    "qs_pg:gn_pop":0,
    "qs_pg:name":"Waterville",
    "qs_pg:name_adm0":"United States",
    "qs_pg:name_adm1":"Pennsylvania",
    "qs_pg:photos_9k":1,
    "qs_pg:photos_9r":1,
    "qs_pg:photos_all":13,
    "qs_pg:photos_sr":0,
    "qs_pg:pop_sr":0,
    "qs_pg:qs_pg_placetype":"locality",
    "qs_pg:qs_pg_placetype_gp":"Town",
    "qs_pg:woe_adm0":23424977,
    "woe:adm0_id":23424977,
    "woe:name_adm0":"United States",
    "woe:name_adm1":"Pennsylvania",
    "woe:placetype":"Town",
    "wof:name":"Waterville",
    "wof:placetype":"locality"
},
  "geometry": {"coordinates":[-77.36136,41.30979],"type":"Point"}
}