{
  "type": "Feature",
  "properties": {
    "iso:country":"US",
    "name:ceb_x_preferred":[
        "Jefferson County"
    ],
    "name:ces_x_preferred":[
        "Jefferson County"
    ],
    "name:cym_x_preferred":[
        "Swydd Jefferson"
    ],
    "name:dan_x_preferred":[
        "Jefferson County"
    ],
    "name:deu_x_preferred":[
        "Jefferson County"
    ],
    "name:est_x_preferred":[
        "Jeffersoni maakond"
    ],
    "name:eus_x_preferred":[
        "Jefferson konderria"
    ],
    "name:fas_x_preferred":[
        "\u0634\u0647\u0631\u0633\u062a\u0627\u0646 \u062c\u0641\u0631\u0633\u0648\u0646"
    ],
    "name:fin_x_preferred":[
        "Jeffersonin piirikunta"
    ],
    "name:heb_x_preferred":[
        "\u05de\u05d7\u05d5\u05d6 \u05d2'\u05e4\u05e8\u05e1\u05d5\u05df"
    ],
    "name:hun_x_preferred":[
        "Jefferson megye"
    ],
    "name:hye_x_preferred":[
        "\u054b\u0565\u0586\u0565\u0580\u057d\u0578\u0576 \u0577\u0580\u057b\u0561\u0576"
    ],
    "name:jpn_x_preferred":[
        "\u30b8\u30a7\u30d5\u30a1\u30fc\u30bd\u30f3\u90e1"
    ],
    "name:kor_x_preferred":[
        "\uc81c\ud37c\uc2a8 \uad70"
    ],
    "name:mkd_x_preferred":[
        "\u040f\u0435\u0444\u0435\u0440\u0441\u043e\u043d"
    ],
    "name:nds_x_preferred":[
        "Jefferson County"
    ],
    "name:nld_x_preferred":[
        "Jefferson County"
    ],
    "name:pol_x_preferred":[
        "Hrabstwo Jefferson"
    ],
    "name:ron_x_preferred":[
        "Comitatul Jefferson"
    ],
    "name:rus_x_preferred":[
        "\u0414\u0436\u0435\u0444\u0444\u0435\u0440\u0441\u043e\u043d"
    ],
    "name:swe_x_preferred":[
        "Jefferson County"
    ],
    "name:ukr_x_preferred":[
        "\u0414\u0436\u0435\u0444\u0444\u0435\u0440\u0441\u043e\u043d"
    ],
    "name:urd_x_preferred":[
        "\u062c\u06cc\u0641\u0631\u0633\u0646 \u06a9\u0627\u0624\u0646\u0679\u06cc"
    ],
    "name:vie_x_preferred":[
        "Qu\u1eadn Jefferson"
    ],
    "name:zho_x_preferred":[
        "\u5091\u4f5b\u905c\u7e23"
    ],
    "qs_pg:aaroncc":"US",
    "qs_pg:name":"Jefferson County",
    "qs_pg:name_adm0":"United States",
    "qs_pg:name_adm1":"Colorado",
    "qs_pg:photos":76,
    "qs_pg:photos_1k":15,
    "qs_pg:photos_9k":1,
    "qs_pg:photos_9r":3,
    "qs_pg:photos_all":76,
    "qs_pg:photos_sr":3,
    "qs_pg:pop_sr":0,
    "qs_pg:qs_pg_placetype":"locality",
    "qs_pg:qs_pg_placetype_gp":"Town",
    "qs_pg:woe_adm0":23424977,
    "woe:adm0_id":23424977,
    "woe:name_adm0":"United States",
    "woe:name_adm1":"Colorado",
    "woe:placetype":"Town",
    "wof:name":"Jefferson County",
    "wof:placetype":"locality"
},
  "geometry": {"coordinates":[-105.27279799999999,39.6355185],"type":"Point"}
}