{
  "type": "Feature",
  "properties": {
    "gn:country":"US",
    "gn:fcode":"PPL",
    "gn:population":0,
    "iso:country":"US",
    "name:ara_x_preferred":[
        "\u0631\u0627\u0648\u0628"
    ],
    "name:ben_x_preferred":[
        "\u09b0\u09cb\u0989\u09ac"
    ],
    "name:ell_x_preferred":[
        "\u03a1\u03b1\u03bf\u03cd\u03bc\u03c0"
    ],
    "name:eng_x_preferred":[
        "Raub"
    ],
    "name:fas_x_preferred":[
        "\u0631\u0627\u0648\u0628"
    ],
    "name:fra_x_preferred":[
        "Raub"
    ],
    "name:heb_x_preferred":[
        "\u05e8\u05d0\u05d5\u05d1"
    ],
    "name:hin_x_preferred":[
        "\u0930\u093e\u0909\u092c"
    ],
    "name:hun_x_preferred":[
        "Raub"
    ],
    "name:jpn_x_preferred":[
        "\u30e9\u30a6\u30d6"
    ],
    "name:kor_x_preferred":[
        "\ub77c\uc6b0\ube0c"
    ],
    "name:rus_x_preferred":[
        "\u0420\u0430\u0443\u0431"
    ],
    "name:tur_x_preferred":[
        "Raub"
    ],
    "name:ukr_x_preferred":[
        "\u0420\u0430\u0443\u0431"
    ],
    "name:urd_x_preferred":[
        "\u0631\u0627\u0624\u0628"
    ],
    "name:vol_x_preferred":[
        "Raub"
    ],
    "qs_pg:aaroncc":"US",
    "qs_pg:gn_country":"US",
    "qs_pg:gn_fcode":"PPL",
    "qs_pg:gn_pop":0,
    "qs_pg:name":"Raub",
    "qs_pg:name_adm0":"United States",
    "qs_pg:name_adm1":"Indiana",
    "qs_pg:photos":71,
    "qs_pg:photos_1k":14,
    "qs_pg:photos_9k":1,
    "qs_pg:photos_9r":2,
    "qs_pg:photos_all":71,
    "qs_pg:photos_sr":2,
    "qs_pg:pop_sr":0,
    "qs_pg:qs_pg_placetype":"locality",
    "qs_pg:qs_pg_placetype_gp":"Town",
    "qs_pg:woe_adm0":23424977,
    "woe:adm0_id":23424977,
    "woe:name_adm0":"United States",
    "woe:name_adm1":"Indiana",
    "woe:placetype":"Town",
    "wof:name":"Raub",
    "wof:placetype":"locality"
},
  "geometry": {"coordinates":[-87.49169000000001,40.73004],"type":"Point"}
}