{
  "type": "Feature",
  "properties": {
    "gn:admin1_code":"TX",
    "gn:admin2_code":"427",
    "gn:asciiname":"La Escondida Colonia",
    "gn:country_code":"US",
    "gn:dem":56,
    "gn:elevation":"54.0",
    "gn:feature_class":"P",
    "gn:feature_code":"PPL",
    "gn:name":"La Escondida Colonia",
    "gn:population":0,
    "gn:timezone":"America/Chicago",
    "iso:country":"US",
    "wof:name":"La Escondida Colonia",
    "wof:placetype":"locality"
},
  "geometry": {"coordinates":[-98.87419,26.37923],"type":"Point"}
}