{
  "type": "Feature",
  "properties": {
    "iso:country":"US",
    "name:eng_x_preferred":[
        "Ellett/Jennelle"
    ],
    "wof:name":"Ellett/Jennelle",
    "wof:placetype":"neighbourhood",
    "wof:population":21,
    "zs:area_m":1326307.532808,
    "zs:blockids":[
        511210207004068,
        511210207004061,
        511210207004049,
        511210207004054,
        511210207004046,
        511210207004071,
        511210207004052,
        511210207004125
    ],
    "zs:housing10":8,
    "zs:label":"Ellett/Jennelle",
    "zs:pop10":21
},
  "geometry": {"coordinates":[-80.39156,37.19087],"type":"Point"}
}