{
  "type": "Feature",
  "properties": {
    "gn:country":"US",
    "gn:fcode":"PPL",
    "gn:population":4799,
    "iso:country":"US",
    "name:ara_x_preferred":[
        "\u0643\u0627\u0631\u0644\u064a\u0644\u0633"
    ],
    "name:arz_x_preferred":[
        "\u0643\u0627\u0631\u0644\u064a\u0644\u0633"
    ],
    "name:azb_x_preferred":[
        "\u06a9\u0627\u0631\u0644\u06cc\u0633\u0644"
    ],
    "name:cat_x_preferred":[
        "Carlisle"
    ],
    "name:ceb_x_preferred":[
        "Carlisle"
    ],
    "name:che_x_preferred":[
        "\u041a\u0430\u0440\u043b\u0430\u0439\u043b"
    ],
    "name:cym_x_preferred":[
        "Carlisle"
    ],
    "name:deu_x_preferred":[
        "Carlisle"
    ],
    "name:eng_x_preferred":[
        "Carlisle"
    ],
    "name:eus_x_preferred":[
        "Carlisle"
    ],
    "name:fas_x_preferred":[
        "\u06a9\u0627\u0631\u0644\u0627\u06cc\u0644\u060c \u0645\u0627\u0633\u0627\u0686\u0648\u0633\u062a"
    ],
    "name:fas_x_variant":[
        "\u06a9\u0627\u0631\u0644\u0627\u06cc\u0644"
    ],
    "name:fra_x_preferred":[
        "Carlisle"
    ],
    "name:hat_x_preferred":[
        "Carlisle"
    ],
    "name:hun_x_preferred":[
        "Carlisle"
    ],
    "name:ita_x_preferred":[
        "Carlisle"
    ],
    "name:jpn_x_preferred":[
        "\u30ab\u30fc\u30e9\u30a4\u30eb"
    ],
    "name:kaz_x_preferred":[
        "\u041a\u0430\u0440\u043b\u0438\u0441\u043b"
    ],
    "name:kir_x_preferred":[
        "\u041a\u0430\u0440\u043b\u0438\u0441\u043b"
    ],
    "name:nld_x_preferred":[
        "Carlisle"
    ],
    "name:pol_x_preferred":[
        "Carlisle"
    ],
    "name:por_x_preferred":[
        "Carlisle"
    ],
    "name:spa_x_preferred":[
        "Carlisle"
    ],
    "name:swa_x_preferred":[
        "Carlisle"
    ],
    "name:tat_x_preferred":[
        "\u041a\u0430\u0440\u043b\u0430\u0439\u043b"
    ],
    "name:tur_x_preferred":[
        "Carlisle"
    ],
    "name:ukr_x_preferred":[
        "\u041a\u0430\u0440\u043b\u0430\u0439\u043b"
    ],
    "name:und_x_variant":[
        "Carlisle Centre"
    ],
    "name:urd_x_preferred":[
        "\u06a9\u0627\u0631\u0644\u0627\u0626\u0644\u060c \u0645\u06cc\u0633\u0627\u0686\u0648\u0633\u0679\u0633"
    ],
    "name:urd_x_variant":[
        "\u06a9\u0627\u0631\u0644\u0627\u0626\u0644"
    ],
    "name:vol_x_preferred":[
        "Carlisle"
    ],
    "name:zho_x_preferred":[
        "\u5361\u840a\u723e"
    ],
    "qs_pg:aaroncc":"US",
    "qs_pg:gn_country":"US",
    "qs_pg:gn_fcode":"PPL",
    "qs_pg:gn_pop":4799,
    "qs_pg:name":"Carlisle",
    "qs_pg:name_adm0":"United States",
    "qs_pg:name_adm1":"Massachusetts",
    "qs_pg:photos":1701,
    "qs_pg:photos_1k":345,
    "qs_pg:photos_9k":8,
    "qs_pg:photos_9r":8,
    "qs_pg:photos_all":1701,
    "qs_pg:photos_sr":14,
    "qs_pg:pop_sr":4,
    "qs_pg:qs_pg_placetype":"locality",
    "qs_pg:qs_pg_placetype_gp":"Town",
    "qs_pg:woe_adm0":23424977,
    "woe:adm0_id":23424977,
    "woe:name_adm0":"United States",
    "woe:name_adm1":"Massachusetts",
    "woe:placetype":"Town",
    "wof:name":"Carlisle",
    "wof:placetype":"locality",
    "wof:population":4799
},
  "geometry": {"coordinates":[-71.34950000000001,42.52926],"type":"Point"}
}