{
  "type": "Feature",
  "properties": {
    "gn:admin1_code":"OR",
    "gn:admin2_code":"11.0",
    "gn:asciiname":"Riverton",
    "gn:country_code":"US",
    "gn:dem":11,
    "gn:elevation":"7.0",
    "gn:feature_class":"P",
    "gn:feature_code":"PPL",
    "gn:name":"Riverton",
    "gn:population":0,
    "gn:timezone":"America/Los_Angeles",
    "iso:country":"US",
    "name:fas_x_preferred":[
        "\u0631\u06cc\u0648\u0631\u062a\u0648\u0646"
    ],
    "name:hat_x_preferred":[
        "Riverton"
    ],
    "name:heb_x_preferred":[
        "\u05e8\u05d9\u05d1\u05e8\u05d8\u05d5\u05df"
    ],
    "wof:name":"Riverton",
    "wof:placetype":"locality"
},
  "geometry": {"coordinates":[-124.27455999999999,43.15733],"type":"Point"}
}