{
  "type": "Feature",
  "properties": {
    "gn:admin1_code":"IN",
    "gn:admin2_code":"147.0",
    "gn:admin3_code":"56160.0",
    "gn:asciiname":"Rock Hill",
    "gn:country_code":"US",
    "gn:dem":121,
    "gn:elevation":"118.0",
    "gn:feature_class":"P",
    "gn:feature_code":"PPL",
    "gn:name":"Rock Hill",
    "gn:population":0,
    "gn:timezone":"America/Chicago",
    "iso:country":"US",
    "name:cat_x_preferred":[
        "Rock Hill"
    ],
    "name:ceb_x_preferred":[
        "Rock Hill"
    ],
    "name:deu_x_preferred":[
        "Rock Hill"
    ],
    "name:fra_x_preferred":[
        "Rock Hill"
    ],
    "name:ita_x_preferred":[
        "Rock Hill"
    ],
    "name:nld_x_preferred":[
        "Rock Hill"
    ],
    "name:pol_x_preferred":[
        "Rock Hill"
    ],
    "name:por_x_preferred":[
        "Rock Hill"
    ],
    "name:spa_x_preferred":[
        "Rock Hill"
    ],
    "name:srp_x_preferred":[
        "\u0420\u043e\u043a \u0425\u0438\u043b"
    ],
    "name:swe_x_preferred":[
        "Rock Hill"
    ],
    "name:vol_x_preferred":[
        "Rock Hill"
    ],
    "wof:name":"Rock Hill",
    "wof:placetype":"locality"
},
  "geometry": {"coordinates":[-87.04000000000001,37.94505],"type":"Point"}
}