{
  "type": "Feature",
  "properties": {
    "gn:admin1_code":"LA",
    "gn:admin2_code":"25.0",
    "gn:asciiname":"Archie",
    "gn:country_code":"US",
    "gn:dem":21,
    "gn:elevation":"17.0",
    "gn:feature_class":"P",
    "gn:feature_code":"PPL",
    "gn:name":"Archie",
    "gn:population":0,
    "gn:timezone":"America/Chicago",
    "iso:country":"US",
    "wof:name":"Archie",
    "wof:placetype":"locality"
},
  "geometry": {"coordinates":[-91.96735,31.5799],"type":"Point"}
}