{
  "type": "Feature",
  "properties": {
    "gn:gn_country":"US",
    "gn:gn_fcode":"PPL",
    "gn:gn_pop":0,
    "iso:country":"US",
    "name:eng_x_preferred":[
        "Rippon"
    ],
    "name:fra_x_preferred":[
        "Rippon"
    ],
    "name:mlg_x_preferred":[
        "Rippon"
    ],
    "name:unk_x_variant":[
        "Ripon"
    ],
    "name:vol_x_preferred":[
        "Rippon"
    ],
    "qs_pg:aaroncc":"US",
    "qs_pg:gn_country":"US",
    "qs_pg:gn_fcode":"PPL",
    "qs_pg:gn_pop":0,
    "qs_pg:name":"Rippon",
    "qs_pg:name_adm0":"United States",
    "qs_pg:name_adm1":"West Virginia",
    "qs_pg:photos":356,
    "qs_pg:photos_1k":72,
    "qs_pg:photos_9k":2,
    "qs_pg:photos_9r":5,
    "qs_pg:photos_all":356,
    "qs_pg:photos_sr":6,
    "qs_pg:pop_sr":5,
    "qs_pg:qs_pg_placetype":"locality",
    "qs_pg:qs_pg_placetype_gp":"Town",
    "qs_pg:woe_adm0":23424977,
    "woe:adm0_id":23424977,
    "woe:name_adm0":"United States",
    "woe:name_adm1":"West Virginia",
    "woe:placetype":"Town",
    "wof:name":"Rippon",
    "wof:placetype":"locality"
},
  "geometry": {"coordinates":[-77.90527,39.21844],"type":"Point"}
}