{
  "type": "Feature",
  "properties": {
    "gn:admin1_code":"MS",
    "gn:admin2_code":"135.0",
    "gn:asciiname":"Paynes",
    "gn:country_code":"US",
    "gn:dem":52,
    "gn:elevation":"54.0",
    "gn:feature_class":"P",
    "gn:feature_code":"PPL",
    "gn:name":"Paynes",
    "gn:population":0,
    "gn:timezone":"America/Chicago",
    "iso:country":"US",
    "name:eng_x_preferred":[
        "Paynes"
    ],
    "name:und_x_variant":[
        "Pages on Sculmore"
    ],
    "wof:name":"Paynes",
    "wof:placetype":"locality"
},
  "geometry": {"coordinates":[-90.06953,33.92095],"type":"Point"}
}