{
  "type": "Feature",
  "properties": {
    "gn:admin1_code":"MO",
    "gn:admin2_code":"41.0",
    "gn:admin3_code":"13204.0",
    "gn:asciiname":"Lewis Mill",
    "gn:country_code":"US",
    "gn:dem":202,
    "gn:elevation":"200.0",
    "gn:feature_class":"P",
    "gn:feature_code":"PPL",
    "gn:name":"Lewis Mill",
    "gn:population":0,
    "gn:timezone":"America/Chicago",
    "iso:country":"US",
    "wof:name":"Lewis Mill",
    "wof:placetype":"locality"
},
  "geometry": {"coordinates":[-92.85296,39.25753],"type":"Point"}
}