{
  "type": "Feature",
  "properties": {
    "gn:admin1_code":"MO",
    "gn:admin2_code":"95.0",
    "gn:admin3_code":"77506.0",
    "gn:asciiname":"Truman Corners",
    "gn:country_code":"US",
    "gn:dem":312,
    "gn:elevation":"304.0",
    "gn:feature_class":"P",
    "gn:feature_code":"PPL",
    "gn:name":"Truman Corners",
    "gn:population":0,
    "gn:timezone":"America/Chicago",
    "iso:country":"US",
    "wof:name":"Truman Corners",
    "wof:placetype":"locality"
},
  "geometry": {"coordinates":[-94.51967999999999,38.90806],"type":"Point"}
}