{
  "type": "Feature",
  "properties": {
    "gn:admin1_code":"MS",
    "gn:admin2_code":"29",
    "gn:asciiname":"Stronghope",
    "gn:country_code":"US",
    "gn:dem":101,
    "gn:elevation":"97.0",
    "gn:feature_class":"P",
    "gn:feature_code":"PPL",
    "gn:name":"Stronghope",
    "gn:population":0,
    "gn:timezone":"America/Chicago",
    "iso:country":"US",
    "name:eng_x_preferred":[
        "Stronghope"
    ],
    "name:und_x_variant":[
        "Strong Hope"
    ],
    "wof:name":"Stronghope",
    "wof:placetype":"locality"
},
  "geometry": {"coordinates":[-90.26342,31.74405],"type":"Point"}
}