{
  "type": "Feature",
  "properties": {
    "gn:country":"US",
    "gn:fcode":"PPL",
    "gn:population":0,
    "iso:country":"US",
    "name:cym_x_preferred":[
        "Leroy Township"
    ],
    "name:deu_x_preferred":[
        "Leroy"
    ],
    "name:eng_x_preferred":[
        "Leroy"
    ],
    "name:eng_x_variant":[
        "Leroy Township"
    ],
    "name:fra_x_preferred":[
        "Leroy Township"
    ],
    "name:ita_x_preferred":[
        "Leroy"
    ],
    "name:jpn_x_preferred":[
        "\u30ea\u30ed\u30a4\u90e1\u533a"
    ],
    "name:nld_x_preferred":[
        "Leroy Township"
    ],
    "name:spa_x_preferred":[
        "Municipio de Leroy"
    ],
    "name:ukr_x_preferred":[
        "\u041b\u0435\u0440\u043e\u0439 \u0422\u0430\u0443\u043d\u0448\u0438\u043f"
    ],
    "name:und_x_variant":[
        "LeRoy"
    ],
    "name:vie_x_preferred":[
        "Leroy"
    ],
    "name:vie_x_variant":[
        "X\u00e3 Leroy"
    ],
    "name:zho_x_preferred":[
        "\u52d2\u7f85\u4f0a"
    ],
    "qs_pg:aaroncc":"US",
    "qs_pg:gn_country":"US",
    "qs_pg:gn_fcode":"PPL",
    "qs_pg:gn_pop":0,
    "qs_pg:name":"Leroy",
    "qs_pg:name_adm0":"United States",
    "qs_pg:name_adm1":"Pennsylvania",
    "qs_pg:photos":28,
    "qs_pg:photos_1k":6,
    "qs_pg:photos_9k":1,
    "qs_pg:photos_9r":2,
    "qs_pg:photos_all":28,
    "qs_pg:photos_sr":2,
    "qs_pg:pop_sr":5,
    "qs_pg:qs_pg_placetype":"locality",
    "qs_pg:qs_pg_placetype_gp":"Town",
    "qs_pg:woe_adm0":23424977,
    "woe:adm0_id":23424977,
    "woe:name_adm0":"United States",
    "woe:name_adm1":"Pennsylvania",
    "woe:placetype":"Town",
    "wof:coterminous":[
        404482723
    ],
    "wof:name":"Leroy",
    "wof:placetype":"locality",
    "wof:statistical_gore":1
},
  "geometry": {"coordinates":[-76.70717999999999,41.67591],"type":"Point"}
}