{
  "type": "Feature",
  "properties": {
    "iso:country":"US",
    "name:eng_x_preferred":[
        "Bluemont Hill"
    ],
    "name:eng_x_variant":[
        "Bluemont Hl"
    ],
    "qs:gn_adm0_cc":"US",
    "qs:gn_fcode":"PPL",
    "qs:gn_local":4274994,
    "qs:gn_namadm1":"KS",
    "qs:gn_name":"Bluemont Hill",
    "qs:local_max":1709,
    "qs:local_sum":1709,
    "qs:localhoods":1,
    "qs:name":"Bluemont Hill",
    "qs:name_adm0":"United States",
    "qs:name_adm1":"Kansas",
    "qs:name_adm2":"Riley",
    "qs:name_local":"Manhattan",
    "qs:photo_max":177,
    "qs:photo_sum":1709,
    "qs:placetype":"Suburb",
    "qs:quad_count":71,
    "qs:woe_adm0":23424977,
    "qs:woe_adm1":2347575,
    "qs:woe_adm2":12588451,
    "qs:woe_lau":0,
    "qs:woe_local":2444768,
    "qs:woe_ver":"7.10.0",
    "wof:lang":[
        "eng"
    ],
    "wof:name":"Bluemont Hill",
    "wof:placetype":"neighbourhood",
    "wof:population":3,
    "zs:blockids":[
        201490001004226,
        201490001004187,
        201490001004225,
        201490001004089,
        201490001004184,
        201490001004143,
        201490001004164,
        201490001004209,
        201490001004218,
        201490001004088,
        201490001004103,
        201490001004173,
        201490001004154,
        201490001004135,
        201490001004161,
        201490001004125
    ],
    "zs:housing10":3,
    "zs:pop10":3
},
  "geometry": {"coordinates":[-96.569999,39.189429],"type":"Point"}
}