{
  "type": "Feature",
  "properties": {
    "gn:admin1_code":"LA",
    "gn:admin2_code":"45.0",
    "gn:asciiname":"Derouen",
    "gn:country_code":"US",
    "gn:dem":6,
    "gn:elevation":"2.0",
    "gn:feature_class":"P",
    "gn:feature_code":"PPL",
    "gn:name":"Derouen",
    "gn:population":0,
    "gn:timezone":"America/Chicago",
    "iso:country":"US",
    "wof:name":"Derouen",
    "wof:placetype":"locality"
},
  "geometry": {"coordinates":[-91.90873000000001,29.96687],"type":"Point"}
}