{
  "type": "Feature",
  "properties": {
    "gn:elevation":181,
    "iso:country":"US",
    "name:deu_x_preferred":[
        "Oakton"
    ],
    "name:eng_x_preferred":[
        "Oakton"
    ],
    "name:nds_x_preferred":[
        "Oakton"
    ],
    "qs:gn_adm0_cc":"US",
    "qs:gn_fcode":"PPL",
    "qs:gn_local":4891382,
    "qs:gn_nam_loc":"Evanston, Cook, Illinois, US",
    "qs:gn_namadm1":"IL",
    "qs:gn_name":"Oakton",
    "qs:local_max":7299,
    "qs:local_sum":20615,
    "qs:localhoods":12,
    "qs:name":"Oakton",
    "qs:name_adm0":"United States",
    "qs:name_adm1":"Illinois",
    "qs:name_adm2":"Cook",
    "qs:name_local":"Evanston",
    "qs:photo_max":72,
    "qs:photo_sum":659,
    "qs:placetype":"Suburb",
    "qs:quad_count":29,
    "qs:woe_adm0":23424977,
    "qs:woe_adm1":2347572,
    "qs:woe_adm2":12588093,
    "qs:woe_funk":"Parented by a neighborhood",
    "qs:woe_lau":0,
    "qs:woe_local":2400737,
    "qs:woe_ver":"7.10.0",
    "wd:wordcount":24,
    "wof:lang":[
        "eng"
    ],
    "wof:name":"Oakton",
    "wof:placetype":"neighbourhood",
    "wof:population":6825,
    "zs:blockids":[
        170310101002012,
        170318101002008,
        170310101001001,
        170318101002012,
        170318100002015,
        170318100002012,
        170310101002008,
        170310101002007,
        170318100002007,
        170318100003007,
        170318100003001,
        170318100002006,
        170318100002014,
        170318100003008,
        170318102001001,
        170318102004000,
        170318100003019,
        170310102021000,
        170318100003013,
        170318100003012,
        170318101002000,
        170318101003002,
        170318100002000,
        170318102001005,
        170318102001006,
        170310101001002,
        170310101002000,
        170318100003000,
        170318100003018,
        170318100003011,
        170318102004004,
        170318100003010,
        170318100003014,
        170318102001004,
        170310101003001,
        170318100002009,
        170310101002009,
        170318100002008,
        170318101003017,
        170318102001002,
        170318100003017,
        170310101003002,
        170318101003006,
        170318100002010,
        170318101003016,
        170318102001000,
        170318101003014,
        170318100003009,
        170318102004005,
        170318102001003,
        170310101002003,
        170310101002001,
        170318100002005,
        170318101002009,
        170318101003001,
        170310101002004,
        170318101003005,
        170318101003000,
        170318100002016,
        170310101002002,
        170310101002005,
        170310101002011,
        170318101002013,
        170318100002001,
        170318101003015,
        170318100002011,
        170318100002013,
        170310101002006
    ],
    "zs:housing10":3583,
    "zs:pop10":6825
},
  "geometry": {"coordinates":[-87.66949099999999,42.024849],"type":"Point"}
}