{
  "type": "Feature",
  "properties": {
    "gn:admin1_code":"VT",
    "gn:admin2_code":"17.0",
    "gn:admin3_code":"25675.0",
    "gn:asciiname":"Ely",
    "gn:country_code":"US",
    "gn:dem":136,
    "gn:elevation":"131.0",
    "gn:feature_class":"P",
    "gn:feature_code":"PPL",
    "gn:name":"Ely",
    "gn:population":0,
    "gn:timezone":"America/New_York",
    "iso:country":"US",
    "name:ben_x_preferred":[
        "\u098f\u09b2\u09bf"
    ],
    "name:cat_x_preferred":[
        "Ely"
    ],
    "name:ceb_x_preferred":[
        "Ely"
    ],
    "name:deu_x_preferred":[
        "Ely"
    ],
    "name:ell_x_preferred":[
        "\u0388\u03bb\u03b9"
    ],
    "name:eng_x_preferred":[
        "Ely"
    ],
    "name:fin_x_preferred":[
        "Ely"
    ],
    "name:fra_x_preferred":[
        "Ely"
    ],
    "name:hin_x_preferred":[
        "\u090f\u0932\u0940"
    ],
    "name:hun_x_preferred":[
        "Ely"
    ],
    "name:ind_x_preferred":[
        "Ely"
    ],
    "name:nld_x_preferred":[
        "Ely"
    ],
    "name:pol_x_preferred":[
        "Ely"
    ],
    "name:por_x_preferred":[
        "Ely"
    ],
    "name:ron_x_preferred":[
        "Ely"
    ],
    "name:rus_x_preferred":[
        "\u0418\u043b\u0438"
    ],
    "name:spa_x_preferred":[
        "Ely"
    ],
    "name:srp_x_preferred":[
        "\u0418\u043b\u0438"
    ],
    "name:swe_x_preferred":[
        "Ely"
    ],
    "name:ukr_x_preferred":[
        "\u0415\u043b\u0456"
    ],
    "name:und_x_variant":[
        "Ely Depot",
        "Wares Crossing",
        "Ely Station",
        "South Fairlee"
    ],
    "name:urd_x_preferred":[
        "\u0627\u06cc\u0644\u06cc"
    ],
    "name:vol_x_preferred":[
        "Ely"
    ],
    "wof:name":"Ely",
    "wof:placetype":"locality"
},
  "geometry": {"coordinates":[-72.17648,43.87646],"type":"Point"}
}