{
  "type": "Feature",
  "properties": {
    "gn:admin1_code":"PA",
    "gn:admin2_code":"107.0",
    "gn:admin3_code":"46584.0",
    "gn:asciiname":"Maple Hill",
    "gn:country_code":"US",
    "gn:dem":398,
    "gn:elevation":"393.0",
    "gn:feature_class":"P",
    "gn:feature_code":"PPL",
    "gn:name":"Maple Hill",
    "gn:population":0,
    "gn:timezone":"America/New_York",
    "iso:country":"US",
    "name:ceb_x_preferred":[
        "Maple Hill"
    ],
    "name:deu_x_preferred":[
        "Maple Hill"
    ],
    "name:fra_x_preferred":[
        "Maple Hill"
    ],
    "name:pol_x_preferred":[
        "Maple Hill"
    ],
    "wof:name":"Maple Hill",
    "wof:placetype":"locality"
},
  "geometry": {"coordinates":[-76.17744,40.81398],"type":"Point"}
}