{
  "type": "Feature",
  "properties": {
    "gn:admin1_code":"MD",
    "gn:admin2_code":"35.0",
    "gn:asciiname":"Blair Woods",
    "gn:country_code":"US",
    "gn:dem":4,
    "gn:elevation":"5.0",
    "gn:feature_class":"P",
    "gn:feature_code":"PPL",
    "gn:name":"Blair Woods",
    "gn:population":0,
    "gn:timezone":"America/New_York",
    "iso:country":"US",
    "wof:name":"Blair Woods",
    "wof:placetype":"locality"
},
  "geometry": {"coordinates":[-76.17328000000001,38.92095],"type":"Point"}
}