{
  "type": "Feature",
  "properties": {
    "iso:country":"US",
    "name:eng_x_preferred":[
        "Aldenville"
    ],
    "wof:name":"Aldenville",
    "wof:placetype":"neighbourhood",
    "wof:population":370,
    "zs:area_m":28563816.286658,
    "zs:blockids":[
        421279602003032,
        421279604001087,
        421279603001025,
        421279602003045,
        421279604001084,
        421279602003069,
        421279602003071,
        421279603001001,
        421279603001002,
        421279602003058,
        421279604001080,
        421279603001020,
        421279602003031,
        421279603001016,
        421279603001014,
        421279602003059,
        421279604001089,
        421279602003046,
        421279603001013,
        421279602003047,
        421279603001026,
        421279603001003,
        421279604001079,
        421279603001017,
        421279604001088,
        421279603001027,
        421279604001086,
        421279604001081,
        421279602003060,
        421279603001036,
        421279603001028,
        421279604001085,
        421279604001132,
        421279604001082,
        421279602003044,
        421279604001083,
        421279603001022
    ],
    "zs:housing10":286,
    "zs:label":"Aldenville",
    "zs:pop10":370
},
  "geometry": {"coordinates":[-75.34535,41.659705],"type":"Point"}
}