{
  "type": "Feature",
  "properties": {
    "gn:admin1_code":"PA",
    "gn:admin2_code":"91",
    "gn:admin3_code":"79256.0",
    "gn:asciiname":"Renninger Tract",
    "gn:country_code":"US",
    "gn:dem":53,
    "gn:elevation":"53.0",
    "gn:feature_class":"P",
    "gn:feature_code":"PPL",
    "gn:name":"Renninger Tract",
    "gn:population":0,
    "gn:timezone":"America/New_York",
    "iso:country":"US",
    "wof:name":"Renninger Tract",
    "wof:placetype":"locality"
},
  "geometry": {"coordinates":[-75.5284,40.1735],"type":"Point"}
}