{
  "type": "Feature",
  "properties": {
    "gn:admin1_code":"LA",
    "gn:admin2_code":"75.0",
    "gn:asciiname":"Ironton",
    "gn:country_code":"US",
    "gn:dem":2,
    "gn:elevation":"1.0",
    "gn:feature_class":"P",
    "gn:feature_code":"PPL",
    "gn:name":"Ironton",
    "gn:population":0,
    "gn:timezone":"America/Chicago",
    "iso:country":"US",
    "name:cat_x_preferred":[
        "Ironton"
    ],
    "name:ceb_x_preferred":[
        "Ironton"
    ],
    "name:deu_x_preferred":[
        "Ironton"
    ],
    "name:fra_x_preferred":[
        "Ironton"
    ],
    "name:ita_x_preferred":[
        "Ironton"
    ],
    "name:nld_x_preferred":[
        "Ironton"
    ],
    "name:pol_x_preferred":[
        "Ironton"
    ],
    "name:por_x_preferred":[
        "Ironton"
    ],
    "name:rus_x_preferred":[
        "\u0410\u0439\u0440\u043e\u043d\u0442\u043e\u043d"
    ],
    "name:srp_x_preferred":[
        "\u0410\u0458\u0440\u043e\u043d\u0442\u043e\u043d"
    ],
    "name:swe_x_preferred":[
        "Ironton"
    ],
    "name:vol_x_preferred":[
        "Ironton"
    ],
    "name:zho_x_preferred":[
        "\u827e\u6602\u987f"
    ],
    "wof:name":"Ironton",
    "wof:placetype":"locality"
},
  "geometry": {"coordinates":[-89.96146,29.64882],"type":"Point"}
}