{
  "type": "Feature",
  "properties": {
    "iso:country":"US",
    "name:eng_x_preferred":[
        "Southridge"
    ],
    "qs:gn_adm0_cc":"US",
    "qs:gn_local":4772354,
    "qs:gn_nam_loc":"McLean, Fairfax, Virginia, US",
    "qs:gn_namadm1":"VA",
    "qs:local_max":3237,
    "qs:local_sum":9380,
    "qs:localhoods":16,
    "qs:name":"Southridge",
    "qs:name_adm0":"United States",
    "qs:name_adm1":"Virginia",
    "qs:name_adm2":"Fairfax",
    "qs:name_local":"Mclean",
    "qs:photo_max":62,
    "qs:photo_sum":90,
    "qs:placetype":"Suburb",
    "qs:quad_count":7,
    "qs:woe_adm0":23424977,
    "qs:woe_adm1":2347605,
    "qs:woe_adm2":12590343,
    "qs:woe_lau":0,
    "qs:woe_local":2448240,
    "qs:woe_ver":"7.10.0",
    "wd:wordcount":90,
    "wof:name":"Southridge",
    "wof:placetype":"neighbourhood",
    "wof:population":957,
    "zs:blockids":[
        510594709004003,
        510594708002009,
        510594708002017,
        510594711005015,
        510594708002026,
        510594708002023,
        510594708002018,
        510594708002024,
        510594708002019,
        510594711005018,
        510594708002010,
        510594708002025,
        510594708002016,
        510594711005017,
        510594711005019,
        510594711005016,
        510594708002014,
        510594709004005
    ],
    "zs:housing10":356,
    "zs:pop10":957
},
  "geometry": {"coordinates":[-77.181237,38.913574],"type":"Point"}
}