{
  "type": "Feature",
  "properties": {
    "gn:admin1_code":"OH",
    "gn:admin2_code":"81.0",
    "gn:admin3_code":"70086.0",
    "gn:asciiname":"Cream City",
    "gn:country_code":"US",
    "gn:dem":213,
    "gn:elevation":"213.0",
    "gn:feature_class":"P",
    "gn:feature_code":"PPL",
    "gn:name":"Cream City",
    "gn:population":0,
    "gn:timezone":"America/New_York",
    "iso:country":"US",
    "wof:name":"Cream City",
    "wof:placetype":"locality"
},
  "geometry": {"coordinates":[-80.71786,40.56451],"type":"Point"}
}