{
  "type": "Feature",
  "properties": {
    "iso:country":"US",
    "name:deu_x_preferred":[
        "Briarwood"
    ],
    "name:eng_x_preferred":[
        "Briarwood"
    ],
    "name:ita_x_preferred":[
        "Briarwood"
    ],
    "name:kor_x_preferred":[
        "\ube0c\ub77c\uc774\uc5b4\uc6b0\ub4dc"
    ],
    "name:nld_x_preferred":[
        "Briarwood"
    ],
    "name:pol_x_preferred":[
        "Briarwood"
    ],
    "name:por_x_preferred":[
        "Briarwood"
    ],
    "name:srp_x_preferred":[
        "\u0411\u0440\u0430\u0458\u0435\u0440\u0432\u0443\u0434"
    ],
    "name:swe_x_preferred":[
        "Briarwood"
    ],
    "name:ukr_x_preferred":[
        "\u0411\u0440\u0430\u0435\u0440\u0432\u0443\u0434"
    ],
    "name:vol_x_preferred":[
        "Briarwood"
    ],
    "wd:wordcount":89,
    "wof:name":"Briarwood",
    "wof:placetype":"neighbourhood",
    "wof:population":73,
    "zs:area_m":302713.326642,
    "zs:blockids":[
        280819506012007
    ],
    "zs:housing10":43,
    "zs:label":"Briarwood",
    "zs:pop10":73
},
  "geometry": {"coordinates":[-88.72918900000001,34.274853],"type":"Point"}
}