{
  "type": "Feature",
  "properties": {
    "gn:country":"US",
    "gn:fcode":"PPL",
    "gn:population":0,
    "iso:country":"US",
    "name:che_x_preferred":[
        "\u0420\u0435\u043d\u0441\u0441\u0435\u043b\u0438\u0435\u0440\u0432\u0438\u043b\u043b"
    ],
    "name:deu_x_preferred":[
        "Rensselaerville"
    ],
    "name:eng_x_preferred":[
        "Rensselaerville"
    ],
    "name:fra_x_preferred":[
        "Rensselaerville"
    ],
    "name:hat_x_preferred":[
        "Rensselaerville"
    ],
    "name:hun_x_preferred":[
        "Rensselaerville"
    ],
    "name:ita_x_preferred":[
        "Rensselaerville"
    ],
    "name:pol_x_preferred":[
        "Rensselaerville"
    ],
    "name:rus_x_preferred":[
        "\u0420\u0435\u043d\u0441\u0441\u0435\u043b\u0435\u0440\u0432\u0438\u043b\u043b"
    ],
    "name:spa_x_preferred":[
        "Rensselaerville"
    ],
    "name:tat_x_preferred":[
        "\u0420\u0435\u043d\u0441\u0441\u0435\u043b\u0438\u0435\u0440\u0432\u0438\u043b\u043b"
    ],
    "name:ukr_x_preferred":[
        "\u0420\u0435\u043d\u0441\u0441\u0435\u043b\u0456\u0435\u0440\u0432\u0456\u043b\u043b"
    ],
    "name:zho_x_preferred":[
        "\u4f26\u65af\u52d2\u7ef4\u5c14"
    ],
    "qs_pg:aaroncc":"US",
    "qs_pg:gn_country":"US",
    "qs_pg:gn_fcode":"PPL",
    "qs_pg:gn_pop":0,
    "qs_pg:name":"Rensselaerville",
    "qs_pg:name_adm0":"United States",
    "qs_pg:name_adm1":"New York",
    "qs_pg:photos":319,
    "qs_pg:photos_1k":65,
    "qs_pg:photos_9k":2,
    "qs_pg:photos_9r":5,
    "qs_pg:photos_all":377,
    "qs_pg:photos_sr":5,
    "qs_pg:pop_sr":0,
    "qs_pg:qs_pg_placetype":"locality",
    "qs_pg:qs_pg_placetype_gp":"Town",
    "qs_pg:woe_adm0":23424977,
    "woe:adm0_id":23424977,
    "woe:name_adm0":"United States",
    "woe:name_adm1":"New York",
    "woe:placetype":"Town",
    "wof:name":"Rensselaerville",
    "wof:placetype":"locality",
    "wof:statistical_gore":1
},
  "geometry": {"coordinates":[-74.13791000000001,42.51619],"type":"Point"}
}