{
  "type": "Feature",
  "properties": {
    "gn:admin1_code":"WA",
    "gn:admin2_code":"33.0",
    "gn:asciiname":"Horseshoe Acres Mobile Home Park",
    "gn:country_code":"US",
    "gn:dem":13,
    "gn:elevation":"10.0",
    "gn:feature_class":"P",
    "gn:feature_code":"PPL",
    "gn:name":"Horseshoe Acres Mobile Home Park",
    "gn:population":0,
    "gn:timezone":"America/Los_Angeles",
    "iso:country":"US",
    "wof:name":"Horseshoe Acres Mobile Home Park",
    "wof:placetype":"campus"
},
  "geometry": {"coordinates":[-122.22579,47.36509],"type":"Point"}
}