{
  "type": "Feature",
  "properties": {
    "gn:admin1_code":"TX",
    "gn:admin2_code":"141.0",
    "gn:asciiname":"Ponderosa Mobile Home Colonia",
    "gn:country_code":"US",
    "gn:dem":1146,
    "gn:elevation":"1149.0",
    "gn:feature_class":"P",
    "gn:feature_code":"PPL",
    "gn:name":"Ponderosa Mobile Home Colonia",
    "gn:population":0,
    "gn:timezone":"America/Denver",
    "iso:country":"US",
    "name:eng_x_preferred":[
        "Ponderosa Mobile Home Colonia"
    ],
    "name:und_x_variant":[
        "Ponderosa Mobile Home Subdivision Colonia"
    ],
    "wof:name":"Ponderosa Mobile Home Colonia",
    "wof:placetype":"campus"
},
  "geometry": {"coordinates":[-106.61444,31.9251],"type":"Point"}
}