{
  "type": "Feature",
  "properties": {
    "iso:country":"US",
    "name:deu_x_preferred":[
        "Harmony Ranch"
    ],
    "name:eng_x_preferred":[
        "Harmony Ranch"
    ],
    "name:fin_x_preferred":[
        "Harmony Ranch"
    ],
    "name:fra_x_preferred":[
        "Harmony Ranch"
    ],
    "name:nld_x_preferred":[
        "Harmony Ranch"
    ],
    "name:spa_x_preferred":[
        "Harmony Ranch"
    ],
    "wd:wordcount":208,
    "wof:name":"Harmony Ranch",
    "wof:placetype":"neighbourhood",
    "wof:population":2,
    "zs:area_m":8556028.913744,
    "zs:blockids":[
        81070005004098
    ],
    "zs:housing10":1,
    "zs:label":"Harmony Ranch",
    "zs:pop10":2
},
  "geometry": {"coordinates":[-106.926327,40.444326],"type":"Point"}
}