{
  "type": "Feature",
  "properties": {
    "gn:admin1_code":"WI",
    "gn:admin2_code":"115.0",
    "gn:admin3_code":"48900.0",
    "gn:asciiname":"Frazer Corners",
    "gn:country_code":"US",
    "gn:dem":289,
    "gn:elevation":"290.0",
    "gn:feature_class":"P",
    "gn:feature_code":"PPL",
    "gn:name":"Frazer Corners",
    "gn:population":0,
    "gn:timezone":"America/Chicago",
    "iso:country":"US",
    "wof:name":"Frazer Corners",
    "wof:placetype":"locality"
},
  "geometry": {"coordinates":[-88.36232,44.67444],"type":"Point"}
}