{
  "type": "Feature",
  "properties": {
    "gn:admin1_code":"VA",
    "gn:admin2_code":"3",
    "gn:asciiname":"Laurel Hills",
    "gn:country_code":"US",
    "gn:dem":225,
    "gn:elevation":"219.0",
    "gn:feature_class":"P",
    "gn:feature_code":"PPL",
    "gn:name":"Laurel Hills",
    "gn:population":0,
    "gn:timezone":"America/New_York",
    "iso:country":"US",
    "wof:name":"Laurel Hills",
    "wof:placetype":"locality"
},
  "geometry": {"coordinates":[-78.70113000000001,38.07736],"type":"Point"}
}