{
  "type": "Feature",
  "properties": {
    "gn:admin1_code":"FL",
    "gn:admin2_code":"19.0",
    "gn:asciiname":"Brewers Landing",
    "gn:country_code":"US",
    "gn:dem":17,
    "gn:elevation":"1.0",
    "gn:feature_class":"P",
    "gn:feature_code":"PPL",
    "gn:name":"Brewers Landing",
    "gn:population":0,
    "gn:timezone":"America/New_York",
    "iso:country":"US",
    "wof:name":"Brewers Landing",
    "wof:placetype":"locality"
},
  "geometry": {"coordinates":[-81.62064000000002,29.8733],"type":"Point"}
}