{
  "type": "Feature",
  "properties": {
    "gn:admin1_code":"UT",
    "gn:admin2_code":"35.0",
    "gn:asciiname":"Ponderosa Estates",
    "gn:country_code":"US",
    "gn:dem":1375,
    "gn:elevation":"1373.0",
    "gn:feature_class":"P",
    "gn:feature_code":"PPL",
    "gn:name":"Ponderosa Estates",
    "gn:population":0,
    "gn:timezone":"America/Denver",
    "iso:country":"US",
    "wof:name":"Ponderosa Estates",
    "wof:placetype":"locality"
},
  "geometry": {"coordinates":[-111.86271000000001,40.61217],"type":"Point"}
}