{
  "type": "Feature",
  "properties": {
    "iso:country":"US",
    "name:ceb_x_preferred":[
        "Marina Bay"
    ],
    "name:eng_x_preferred":[
        "Marina Bay"
    ],
    "name:fra_x_preferred":[
        "Marina Bay"
    ],
    "name:nld_x_preferred":[
        "Marina Bay"
    ],
    "name:swe_x_preferred":[
        "Marina Bay"
    ],
    "name:zho_x_preferred":[
        "\u6ff1\u6d77\u7063"
    ],
    "qs:gn_adm0_cc":"US",
    "qs:gn_local":5387428,
    "qs:gn_nam_loc":"richmond",
    "qs:gn_namadm1":"CA",
    "qs:local_max":7168,
    "qs:local_sum":20495,
    "qs:localhoods":19,
    "qs:name":"Marina Bay",
    "qs:name_adm0":"United States",
    "qs:name_adm1":"California",
    "qs:name_adm2":"Contra Costa",
    "qs:name_local":"Richmond",
    "qs:photo_max":3246,
    "qs:photo_sum":7168,
    "qs:placetype":"Suburb",
    "qs:quad_count":45,
    "qs:woe_adm0":23424977,
    "qs:woe_adm1":2347563,
    "qs:woe_adm2":12587676,
    "qs:woe_lau":0,
    "qs:woe_local":2480904,
    "qs:woe_ver":"7.10.0",
    "wd:wordcount":36,
    "wof:lang":[
        "eng"
    ],
    "wof:name":"Marina Bay",
    "wof:placetype":"neighbourhood",
    "wof:population":3148,
    "zs:blockids":[
        60133800003003,
        60133800003021,
        60133800001010,
        60133800001011,
        60133800003024,
        60133800001022,
        60133800001023,
        60133800003025,
        60133800001013,
        60133800001032,
        60133800001035,
        60133800001037,
        60133800001046,
        60133800001012,
        60133800003022,
        60133780002072,
        60133800001028,
        60133800001031,
        60133800001006,
        60133800001044,
        60133800001042,
        60133800001005,
        60133800001008,
        60133800001026,
        60133800001034,
        60133800001019,
        60133800003020,
        60133800001002,
        60133800001015,
        60133800001007,
        60133800001025,
        60133800001047,
        60133800001003,
        60133800001020,
        60133800001021,
        60133800001040,
        60133800001045,
        60133800001016,
        60133800001036,
        60133800001039,
        60133800001029,
        60133800001041,
        60133800001018,
        60133800001027,
        60133800001030,
        60133800001014,
        60133800001038,
        60133800001024,
        60133800001017,
        60133800001004,
        60133800001033,
        60133800001043,
        60133800001009,
        60133800003023,
        60133800003005
    ],
    "zs:housing10":1911,
    "zs:pop10":3148
},
  "geometry": {"coordinates":[-122.34675300000001,37.917455],"type":"Point"}
}