{
  "type": "Feature",
  "properties": {
    "gn:admin1_code":"VA",
    "gn:admin2_code":"175",
    "gn:asciiname":"Hunterdale",
    "gn:country_code":"US",
    "gn:dem":29,
    "gn:elevation":"27.0",
    "gn:feature_class":"P",
    "gn:feature_code":"PPL",
    "gn:name":"Hunterdale",
    "gn:population":0,
    "gn:timezone":"America/New_York",
    "iso:country":"US",
    "wof:name":"Hunterdale",
    "wof:placetype":"locality"
},
  "geometry": {"coordinates":[-76.96106999999998,36.70154],"type":"Point"}
}