{
  "type": "Feature",
  "properties": {
    "iso:country":"US",
    "name:eng_x_preferred":[
        "Michigan Corners"
    ],
    "name:nld_x_preferred":[
        "Michigan Corners"
    ],
    "name:vol_x_preferred":[
        "Michigan Corners"
    ],
    "wd:wordcount":169,
    "wof:name":"Michigan Corners",
    "wof:placetype":"neighbourhood",
    "wof:population":4634,
    "zs:area_m":8042012.004186,
    "zs:blockids":[
        360710110004029,
        360710111021001,
        360710111023002,
        360710111022018,
        360710111021005,
        360710111011007,
        360710111011011,
        360710111022005,
        360710111023020,
        360710110003026,
        360710111023022,
        360710111023014,
        360710111023012,
        360710111021007,
        360710111021002,
        360710111023004,
        360710110003007,
        360710111011008,
        360710111011006,
        360710111023003,
        360710111011014,
        360710111023001,
        360710111023023,
        360710111021008,
        360710110003028,
        360710111023006,
        360710111023008,
        360710110005024,
        360710110005025,
        360710111021004,
        360710110003024,
        360710111011005,
        360710111011004,
        360710111011015,
        360710111023017,
        360710111023016,
        360710111022004,
        360710110003025,
        360710111023013,
        360710110005023,
        360710111021000,
        360710111011009,
        360710111023019,
        360710111011001,
        360710111011002,
        360710111011012,
        360710111011010,
        360710111022000,
        360710110004028,
        360710110005005,
        360710111021009,
        360710110003029,
        360710111011003,
        360710111023015,
        360710111023011,
        360710110005026,
        360710111023021,
        360710111021011,
        360710111011000,
        360710111011013,
        360710110003027,
        360710111023018,
        360710111021006,
        360710111021010,
        360710110004027,
        360710110005022,
        360710111022006,
        360710111023024,
        360710110005007,
        360710111021003,
        360710111022002,
        360710111023005,
        360710111023010,
        360710111023009,
        360710110005021,
        360710110005006,
        360710111023000,
        360710111011017,
        360710111022001,
        360710111023007,
        360710111022003
    ],
    "zs:housing10":1713,
    "zs:label":"Michigan Corners",
    "zs:pop10":4634
},
  "geometry": {"coordinates":[-74.35206100000001,41.480242],"type":"Point"}
}