{
  "type": "Feature",
  "properties": {
    "iso:country":"US",
    "name:eng_x_preferred":[
        "Mumbauersville"
    ],
    "wof:name":"Mumbauersville",
    "wof:placetype":"neighbourhood",
    "wof:population":111,
    "zs:area_m":880199.163161,
    "zs:blockids":[
        420171028012013
    ],
    "zs:housing10":38,
    "zs:label":"Mumbauersville",
    "zs:pop10":111
},
  "geometry": {"coordinates":[-75.437595,40.416356],"type":"Point"}
}