{
  "type": "Feature",
  "properties": {
    "gn:admin1_code":"PA",
    "gn:admin2_code":"129.0",
    "gn:admin3_code":"33792.0",
    "gn:asciiname":"Edna Number Two",
    "gn:country_code":"US",
    "gn:dem":323,
    "gn:elevation":"318.0",
    "gn:feature_class":"P",
    "gn:feature_code":"PPL",
    "gn:name":"Edna Number Two",
    "gn:population":0,
    "gn:timezone":"America/New_York",
    "iso:country":"US",
    "wof:name":"Edna Number Two",
    "wof:placetype":"locality"
},
  "geometry": {"coordinates":[-79.68865,40.29285],"type":"Point"}
}