{
  "type": "Feature",
  "properties": {
    "iso:country":"US",
    "name:cat_x_preferred":[
        "Woodlawn"
    ],
    "name:ceb_x_preferred":[
        "Woodlawn"
    ],
    "name:deu_x_preferred":[
        "Woodlawn"
    ],
    "name:eng_x_preferred":[
        "Woodlawn"
    ],
    "name:ind_x_preferred":[
        "Woodlawn"
    ],
    "name:ita_x_preferred":[
        "Woodlawn"
    ],
    "name:kor_x_preferred":[
        "\uc6b0\ub4e4\ub860"
    ],
    "name:nld_x_preferred":[
        "Woodlawn"
    ],
    "name:pol_x_preferred":[
        "Woodlawn"
    ],
    "name:por_x_preferred":[
        "Woodlawn"
    ],
    "name:rus_x_preferred":[
        "\u0412\u0443\u0434\u043b\u043e\u043d"
    ],
    "name:spa_x_preferred":[
        "Woodlawn"
    ],
    "name:srp_x_preferred":[
        "\u0412\u0443\u0434\u043b\u043e\u043d"
    ],
    "name:unk_x_variant":[
        "Woodlawn"
    ],
    "name:vol_x_preferred":[
        "Woodlawn"
    ],
    "qs:gn_adm0_cc":"US",
    "qs:gn_fcode":"PPLX",
    "qs:gn_local":4198972,
    "qs:gn_nam_loc":"Hampton, Henry, Georgia, US",
    "qs:gn_namadm1":"GA",
    "qs:gn_name":"Woodlawn",
    "qs:local_max":1968,
    "qs:local_sum":2208,
    "qs:localhoods":3,
    "qs:name":"Woodlawn",
    "qs:name_adm0":"United States",
    "qs:name_adm1":"Georgia",
    "qs:name_adm2":"Henry",
    "qs:name_local":"Hampton",
    "qs:photo_max":790,
    "qs:photo_sum":1968,
    "qs:placetype":"Suburb",
    "qs:quad_count":18,
    "qs:woe_adm0":23424977,
    "qs:woe_adm1":2347569,
    "qs:woe_adm2":12587944,
    "qs:woe_lau":0,
    "qs:woe_local":2416844,
    "qs:woe_ver":"7.10.0",
    "wof:lang":[
        "eng"
    ],
    "wof:name":"Woodlawn",
    "wof:placetype":"neighbourhood",
    "wof:population":666,
    "zs:blockids":[
        131510705012043,
        131510705012016,
        131510705012072,
        131510705012026,
        131510705012028,
        131510705012052,
        131510705012032,
        131510705012031,
        131510705011055,
        131510705012002,
        131510705012011,
        131510705012014,
        131510705012029
    ],
    "zs:housing10":345,
    "zs:pop10":666
},
  "geometry": {"coordinates":[-84.315613,33.384404],"type":"Point"}
}