{
  "type": "Feature",
  "properties": {
    "gn:admin1_code":"VA",
    "gn:admin2_code":"59",
    "gn:asciiname":"Jermantown",
    "gn:country_code":"US",
    "gn:dem":139,
    "gn:elevation":"140.0",
    "gn:feature_class":"P",
    "gn:feature_code":"PPL",
    "gn:name":"Jermantown",
    "gn:population":0,
    "gn:timezone":"America/New_York",
    "iso:country":"US",
    "name:fas_x_preferred":[
        "\u0698\u0631\u0645\u0646\u200c\u062a\u0627\u0648\u0646"
    ],
    "name:vol_x_preferred":[
        "Jermantown"
    ],
    "wof:name":"Jermantown",
    "wof:placetype":"locality"
},
  "geometry": {"coordinates":[-77.33221,38.85706],"type":"Point"}
}