{
  "type": "Feature",
  "properties": {
    "gn:admin1_code":"FL",
    "gn:admin2_code":"57",
    "gn:asciiname":"Rocky Ford",
    "gn:country_code":"US",
    "gn:dem":13,
    "gn:elevation":"1.0",
    "gn:feature_class":"P",
    "gn:feature_code":"PPL",
    "gn:name":"Rocky Ford",
    "gn:population":0,
    "gn:timezone":"America/New_York",
    "iso:country":"US",
    "name:cat_x_preferred":[
        "Rocky Ford"
    ],
    "name:ceb_x_preferred":[
        "Rocky Ford"
    ],
    "name:deu_x_preferred":[
        "Rocky Ford"
    ],
    "name:ita_x_preferred":[
        "Rocky Ford"
    ],
    "name:nld_x_preferred":[
        "Rocky Ford"
    ],
    "name:pol_x_preferred":[
        "Rocky Ford"
    ],
    "name:por_x_preferred":[
        "Rocky Ford"
    ],
    "name:srp_x_preferred":[
        "\u0420\u043e\u043a\u0438 \u0424\u043e\u0440\u0434"
    ],
    "name:vol_x_preferred":[
        "Rocky Ford"
    ],
    "wof:name":"Rocky Ford",
    "wof:placetype":"locality"
},
  "geometry": {"coordinates":[-82.58150000000001,28.0008],"type":"Point"}
}