{
  "type": "Feature",
  "properties": {
    "gn:admin1_code":"VT",
    "gn:admin2_code":"15.0",
    "gn:admin3_code":"4375.0",
    "gn:asciiname":"Belvidere Center",
    "gn:country_code":"US",
    "gn:dem":265,
    "gn:elevation":"263.0",
    "gn:feature_class":"P",
    "gn:feature_code":"PPL",
    "gn:name":"Belvidere Center",
    "gn:population":0,
    "gn:timezone":"America/New_York",
    "iso:country":"US",
    "wof:name":"Belvidere Center",
    "wof:placetype":"locality"
},
  "geometry": {"coordinates":[-72.69123,44.75005],"type":"Point"}
}