{
  "type": "Feature",
  "properties": {
    "iso:country":"US",
    "name:ara_x_preferred":[
        "\u0646\u0648\u0631\u062b \u0634\u0648\u0631"
    ],
    "name:ben_x_preferred":[
        "\u09a8\u09b0\u09cd\u09a5 \u09b6\u09cb\u09b0"
    ],
    "name:bul_x_preferred":[
        "\u041d\u043e\u0440\u0442 \u0448\u043e\u0440"
    ],
    "name:ceb_x_preferred":[
        "North Shore"
    ],
    "name:deu_x_preferred":[
        "North Shore"
    ],
    "name:eng_x_preferred":[
        "North Shore"
    ],
    "name:fas_x_preferred":[
        "\u0646\u0648\u0631\u062b \u0634\u0648\u0631"
    ],
    "name:fra_x_preferred":[
        "North Shore"
    ],
    "name:heb_x_preferred":[
        "\u05e0\u05d5\u05e8\u05ea' \u05e9\u05d5\u05e8"
    ],
    "name:hin_x_preferred":[
        "\u0928\u0949\u0930\u094d\u0925 \u0936\u094b\u0930"
    ],
    "name:hun_x_preferred":[
        "North Shore"
    ],
    "name:ita_x_preferred":[
        "North Shore"
    ],
    "name:jpn_x_preferred":[
        "\u30ce\u30fc\u30b9\u30b7\u30e7\u30a2"
    ],
    "name:kor_x_preferred":[
        "\ub178\uc2a4\uc1fc\uc5b4"
    ],
    "name:mlg_x_preferred":[
        "North Shore"
    ],
    "name:pol_x_preferred":[
        "North Shore"
    ],
    "name:por_x_preferred":[
        "North Shore"
    ],
    "name:slk_x_preferred":[
        "North Shore"
    ],
    "name:spa_x_preferred":[
        "North Shore"
    ],
    "name:srp_x_preferred":[
        "\u041d\u043e\u0440\u0442 \u0428\u043e\u0440"
    ],
    "name:swe_x_preferred":[
        "North Shore"
    ],
    "name:ukr_x_preferred":[
        "\u041d\u043e\u0440\u0442-\u0428\u043e\u0440"
    ],
    "name:urd_x_preferred":[
        "\u0646\u0627\u0631\u062a\u06be \u0634\u0648\u0631"
    ],
    "name:vie_x_preferred":[
        "North Shore"
    ],
    "name:vol_x_preferred":[
        "North Shore"
    ],
    "wof:name":"North Shore",
    "wof:placetype":"neighbourhood",
    "wof:population":606,
    "zs:area_m":1867715.111905,
    "zs:blockids":[
        371510303012058,
        371510303013013,
        371510303012055,
        371510303013014,
        371510303013010,
        371510303012062,
        371510303013009,
        371510303012061
    ],
    "zs:housing10":252,
    "zs:label":"North Shore",
    "zs:pop10":606
},
  "geometry": {"coordinates":[-79.802871,35.729408],"type":"Point"}
}