{
  "type": "Feature",
  "properties": {
    "gn:admin1_code":"NC",
    "gn:admin2_code":"67",
    "gn:admin3_code":"92062.0",
    "gn:asciiname":"Guthrie",
    "gn:country_code":"US",
    "gn:dem":281,
    "gn:elevation":"283.0",
    "gn:feature_class":"P",
    "gn:feature_code":"PPL",
    "gn:name":"Guthrie",
    "gn:population":0,
    "gn:timezone":"America/New_York",
    "iso:country":"US",
    "name:ceb_x_preferred":[
        "Guthrie"
    ],
    "name:deu_x_preferred":[
        "Guthrie"
    ],
    "name:fas_x_preferred":[
        "\u06af\u0627\u062a\u0631\u06cc"
    ],
    "name:fra_x_preferred":[
        "Guthrie"
    ],
    "name:ita_x_preferred":[
        "Guthrie"
    ],
    "name:jpn_x_preferred":[
        "\u30ac\u30b9\u30ea\u30fc"
    ],
    "name:nds_x_preferred":[
        "Guthrie"
    ],
    "name:nld_x_preferred":[
        "Guthrie"
    ],
    "name:pol_x_preferred":[
        "Guthrie"
    ],
    "name:por_x_preferred":[
        "Guthrie"
    ],
    "name:rus_x_preferred":[
        "\u0413\u0430\u0442\u0440\u0438"
    ],
    "name:spa_x_preferred":[
        "Guthrie"
    ],
    "name:srp_x_preferred":[
        "\u0413\u0430\u0442\u0440\u0438"
    ],
    "name:swe_x_preferred":[
        "Guthrie"
    ],
    "name:tur_x_preferred":[
        "Guthrie"
    ],
    "name:ukr_x_preferred":[
        "\u0413\u0430\u0442\u0440\u0456"
    ],
    "name:vol_x_preferred":[
        "Guthrie"
    ],
    "wof:name":"Guthrie",
    "wof:placetype":"locality"
},
  "geometry": {"coordinates":[-80.15116,36.12153],"type":"Point"}
}