{
  "type": "Feature",
  "properties": {
    "iso:country":"US",
    "name:eng_x_preferred":[
        "Eastmont"
    ],
    "qs:gn_adm0_cc":"US",
    "qs:gn_local":4509884,
    "qs:gn_nam_loc":"Dayton, Montgomery, Ohio, US",
    "qs:gn_namadm1":"OH",
    "qs:local_max":11923,
    "qs:local_sum":38490,
    "qs:localhoods":42,
    "qs:name":"Eastmont",
    "qs:name_adm0":"United States",
    "qs:name_adm1":"Ohio",
    "qs:name_adm2":"Montgomery",
    "qs:name_local":"Dayton",
    "qs:photo_max":89,
    "qs:photo_sum":175,
    "qs:placetype":"Suburb",
    "qs:quad_count":14,
    "qs:woe_adm0":23424977,
    "qs:woe_adm1":2347594,
    "qs:woe_adm2":12589583,
    "qs:woe_lau":0,
    "qs:woe_local":2389876,
    "qs:woe_ver":"7.10.0",
    "wd:wordcount":16,
    "wof:lang":[
        "eng"
    ],
    "wof:name":"Eastmont",
    "wof:placetype":"neighbourhood",
    "wof:population":1810,
    "zs:blockids":[
        390572102002017,
        390572102005013,
        390572102005009,
        390572102002015,
        390572102002004,
        390572103002009,
        390572102002016,
        390572102002025,
        390572102005024,
        390572102002014,
        390572102002034,
        390572102002009,
        390572102005018,
        390572102002005,
        390572102002021,
        390572102002024,
        390572102002036,
        390572102005026,
        390572103002003,
        390572102002018,
        390572103002004,
        390572102005022,
        390572102002020,
        390572102005011,
        390572102002026,
        390572102002019,
        390572102002013,
        390572102005020,
        390572102005025,
        390572102005014,
        390572102005012,
        390572102005019,
        390572102002035,
        390572102002033,
        390572102002008,
        390572102002023,
        390572103002012,
        390572103002005,
        390572103002013,
        390572102005028,
        390572102002006,
        390572102002012,
        390572103002006,
        390572102002010,
        390572102002037,
        390572102005010,
        390572102005015,
        390572102005017,
        390572103002007,
        390572103002008,
        390572102005021,
        390572102002011,
        390572102005016,
        390572102002003
    ],
    "zs:housing10":649,
    "zs:pop10":1810
},
  "geometry": {"coordinates":[-84.110966,39.73411],"type":"Point"}
}