{
  "type": "Feature",
  "properties": {
    "gn:admin1_code":"UT",
    "gn:admin2_code":"21.0",
    "gn:asciiname":"Iron Mountain",
    "gn:country_code":"US",
    "gn:dem":1973,
    "gn:elevation":"1969.0",
    "gn:feature_class":"P",
    "gn:feature_code":"PPL",
    "gn:name":"Iron Mountain",
    "gn:population":0,
    "gn:timezone":"America/Denver",
    "iso:country":"US",
    "name:ceb_x_preferred":[
        "Iron Mountain"
    ],
    "name:fin_x_preferred":[
        "Iron Mountain"
    ],
    "name:spa_x_preferred":[
        "Iron Mountain"
    ],
    "name:swe_x_preferred":[
        "Iron Mountain"
    ],
    "name:vol_x_preferred":[
        "Iron Mountain"
    ],
    "wof:name":"Iron Mountain",
    "wof:placetype":"locality"
},
  "geometry": {"coordinates":[-113.39079,37.61748],"type":"Point"}
}