{
  "type": "Feature",
  "properties": {
    "gn:admin1_code":"UT",
    "gn:admin2_code":"21.0",
    "gn:asciiname":"Iron Mountain",
    "gn:country_code":"US",
    "gn:dem":1973,
    "gn:elevation":"1969.0",
    "gn:feature_class":"P",
    "gn:feature_code":"PPL",
    "gn:name":"Iron Mountain",
    "gn:population":0,
    "gn:timezone":"America/Denver",
    "iso:country":"US",
    "name:ben_x_preferred":[
        "\u0986\u09df\u09b0\u09a8 \u09ae\u09be\u0989\u09a8\u09cd\u099f\u09c7\u09a8"
    ],
    "name:ceb_x_preferred":[
        "Iron Mountain"
    ],
    "name:ell_x_preferred":[
        "\u0386\u03b9\u03c1\u03bf\u03bd \u039c\u03ac\u03bf\u03c5\u03bd\u03c4\u03b5\u03bd"
    ],
    "name:fin_x_preferred":[
        "Iron Mountain"
    ],
    "name:hin_x_preferred":[
        "\u0906\u092f\u0930\u0928 \u092e\u093e\u0909\u0902\u091f\u0947\u0928"
    ],
    "name:ind_x_preferred":[
        "Iron Mountain"
    ],
    "name:kor_x_preferred":[
        "\uc544\uc774\uc5b8 \ub9c8\uc6b4\ud2f4"
    ],
    "name:rus_x_preferred":[
        "\u0410\u0439\u0440\u043e\u043d-\u041c\u0430\u0443\u043d\u0442\u0438\u043d"
    ],
    "name:spa_x_preferred":[
        "Iron Mountain"
    ],
    "name:swe_x_preferred":[
        "Iron Mountain"
    ],
    "name:urd_x_preferred":[
        "\u0622\u0626\u0631\u0646 \u0645\u0627\u0624\u0646\u062a\u06cc\u0646"
    ],
    "name:vie_x_preferred":[
        "Iron Mountain"
    ],
    "name:vol_x_preferred":[
        "Iron Mountain"
    ],
    "wof:name":"Iron Mountain",
    "wof:placetype":"locality"
},
  "geometry": {"coordinates":[-113.39079,37.61748],"type":"Point"}
}