{
  "type": "Feature",
  "properties": {
    "gn:admin1_code":"NJ",
    "gn:admin2_code":"9.0",
    "gn:admin3_code":"41610.0",
    "gn:asciiname":"Erma Park",
    "gn:country_code":"US",
    "gn:dem":9,
    "gn:elevation":"6.0",
    "gn:feature_class":"P",
    "gn:feature_code":"PPL",
    "gn:name":"Erma Park",
    "gn:population":0,
    "gn:timezone":"America/New_York",
    "iso:country":"US",
    "wof:name":"Erma Park",
    "wof:placetype":"locality"
},
  "geometry": {"coordinates":[-74.8835,39.00595],"type":"Point"}
}