{
  "type": "Feature",
  "properties": {
    "gn:admin1_code":"PA",
    "gn:admin2_code":"107.0",
    "gn:admin3_code":"26944.0",
    "gn:asciiname":"Glen Carbon",
    "gn:country_code":"US",
    "gn:dem":351,
    "gn:elevation":"350.0",
    "gn:feature_class":"P",
    "gn:feature_code":"PPL",
    "gn:name":"Glen Carbon",
    "gn:population":0,
    "gn:timezone":"America/New_York",
    "iso:country":"US",
    "wof:name":"Glen Carbon",
    "wof:placetype":"locality"
},
  "geometry": {"coordinates":[-76.31106,40.71509],"type":"Point"}
}