{
  "type": "Feature",
  "properties": {
    "gn:country":"US",
    "gn:fcode":"ADMD",
    "gn:population":0,
    "iso:country":"US",
    "name:deu_x_preferred":[
        "Pleasant Run Township"
    ],
    "name:eng_x_preferred":[
        "Pleasant Run Township"
    ],
    "name:spa_x_preferred":[
        "Municipio de Pleasant Run"
    ],
    "name:urd_x_preferred":[
        "\u067e\u0644\u06cc\u0632\u06cc\u0646\u0679 \u0631\u0646 \u0679\u0627\u0624\u0646 \u0634\u067e"
    ],
    "name:vie_x_preferred":[
        "X\u00e3 Pleasant Run"
    ],
    "name:zho_x_preferred":[
        "\u666e\u840a\u68ee\u7279\u502b\u93ae\u5340"
    ],
    "qs_pg:aaroncc":"US",
    "qs_pg:gn_country":"US",
    "qs_pg:gn_fcode":"ADMD",
    "qs_pg:gn_pop":0,
    "qs_pg:name":"Pleasant Run",
    "qs_pg:name_adm0":"United States",
    "qs_pg:name_adm1":"Indiana",
    "qs_pg:photos":36,
    "qs_pg:photos_1k":7,
    "qs_pg:photos_9k":1,
    "qs_pg:photos_9r":2,
    "qs_pg:photos_all":36,
    "qs_pg:photos_sr":2,
    "qs_pg:pop_sr":0,
    "qs_pg:qs_pg_placetype":"locality",
    "qs_pg:qs_pg_placetype_gp":"Town",
    "qs_pg:woe_adm0":23424977,
    "woe:adm0_id":23424977,
    "woe:name_adm0":"United States",
    "woe:name_adm1":"Indiana",
    "woe:placetype":"Town",
    "wof:name":"Pleasant Run",
    "wof:placetype":"locality"
},
  "geometry": {"coordinates":[-86.36638000000001,38.942],"type":"Point"}
}