{
  "type": "Feature",
  "properties": {
    "gn:admin1_code":"MO",
    "gn:admin2_code":"71.0",
    "gn:admin3_code":"44714.0",
    "gn:asciiname":"Jaegers Shop",
    "gn:country_code":"US",
    "gn:dem":252,
    "gn:elevation":"249.0",
    "gn:feature_class":"P",
    "gn:feature_code":"PPL",
    "gn:name":"Jaegers Shop",
    "gn:population":0,
    "gn:timezone":"America/Chicago",
    "iso:country":"US",
    "name:eng_x_preferred":[
        "Jaegers Shop"
    ],
    "name:und_x_variant":[
        "Jaeger",
        "Cedar Fork",
        "Cedarfork"
    ],
    "wof:name":"Jaegers Shop",
    "wof:placetype":"locality"
},
  "geometry": {"coordinates":[-91.29931999999999,38.46116],"type":"Point"}
}