{
  "type": "Feature",
  "properties": {
    "iso:country":"US",
    "name:eng_x_preferred":[
        "Crystal Meadows"
    ],
    "wd:wordcount":233,
    "wof:name":"Crystal Meadows",
    "wof:placetype":"neighbourhood",
    "wof:population":49,
    "zs:area_m":11712327.762978,
    "zs:blockids":[
        80519639001043,
        80519639001011,
        80519639001005,
        80519639001342,
        80519639001025,
        80519639001262,
        80519639001018,
        80519639001026,
        80519639001261,
        80519639001010,
        80519639001028,
        80519639001199,
        80519639001024,
        80519639001340,
        80519639001343,
        80519639001201,
        80519639001027,
        80519639001023,
        80519639001038,
        80519639001017,
        80519639001200
    ],
    "zs:housing10":30,
    "zs:label":"Crystal Meadows",
    "zs:pop10":49
},
  "geometry": {"coordinates":[-107.271888,39.098049],"type":"Point"}
}