{
  "type": "Feature",
  "properties": {
    "gn:admin1_code":"MA",
    "gn:admin2_code":"23.0",
    "gn:admin3_code":"11665.0",
    "gn:asciiname":"South Meadow Village",
    "gn:country_code":"US",
    "gn:dem":45,
    "gn:elevation":"38.0",
    "gn:feature_class":"P",
    "gn:feature_code":"PPL",
    "gn:name":"South Meadow Village",
    "gn:population":0,
    "gn:timezone":"America/New_York",
    "iso:country":"US",
    "wof:name":"South Meadow Village",
    "wof:placetype":"locality"
},
  "geometry": {"coordinates":[-70.75086999999998,41.89399],"type":"Point"}
}