{
  "type": "Feature",
  "properties": {
    "gn:elevation":120,
    "iso:country":"US",
    "name:eng_x_preferred":[
        "Macdonald Woods"
    ],
    "qs:gn_adm0_cc":"US",
    "qs:gn_fcode":"PPLX",
    "qs:gn_local":4459467,
    "qs:gn_nam_loc":"Cary, Wake, North Carolina, US",
    "qs:gn_namadm1":"NC",
    "qs:gn_name":"MacDonald Woods",
    "qs:local_max":1353,
    "qs:local_sum":11778,
    "qs:localhoods":52,
    "qs:name":"Macdonald Woods",
    "qs:name_adm0":"United States",
    "qs:name_adm1":"North Carolina",
    "qs:name_adm2":"Wake",
    "qs:name_local":"Cary",
    "qs:photo_max":11,
    "qs:photo_sum":58,
    "qs:placetype":"Suburb",
    "qs:quad_count":9,
    "qs:woe_adm0":23424977,
    "qs:woe_adm1":2347592,
    "qs:woe_adm2":12589465,
    "qs:woe_lau":0,
    "qs:woe_local":2375810,
    "qs:woe_ver":"7.10.0",
    "wof:lang":[
        "eng"
    ],
    "wof:name":"Macdonald Woods",
    "wof:placetype":"neighbourhood",
    "wof:population":318,
    "zs:blockids":[
        371830535052010,
        371830535051007
    ],
    "zs:housing10":104,
    "zs:pop10":318
},
  "geometry": {"coordinates":[-78.76545,35.758354],"type":"Point"}
}