{
  "type": "Feature",
  "properties": {
    "iso:country":"US",
    "name:fra_x_preferred":[
        "Big Chief"
    ],
    "qs_pg:aaroncc":"US",
    "qs_pg:name":"Big Chief",
    "qs_pg:name_adm0":"United States",
    "qs_pg:name_adm1":"California",
    "qs_pg:photos":395,
    "qs_pg:photos_1k":80,
    "qs_pg:photos_9k":2,
    "qs_pg:photos_9r":5,
    "qs_pg:photos_all":395,
    "qs_pg:photos_sr":6,
    "qs_pg:pop_sr":0,
    "qs_pg:qs_pg_placetype":"locality",
    "qs_pg:qs_pg_placetype_gp":"Town",
    "qs_pg:woe_adm0":23424977,
    "woe:adm0_id":23424977,
    "woe:name_adm0":"United States",
    "woe:name_adm1":"California",
    "woe:placetype":"Town",
    "wof:name":"Big Chief",
    "wof:placetype":"locality"
},
  "geometry": {"coordinates":[-120.20658899999999,39.246341],"type":"Point"}
}