{
  "type": "Feature",
  "properties": {
    "gn:admin1_code":"LA",
    "gn:admin2_code":"41.0",
    "gn:asciiname":"Oakwood Landing",
    "gn:country_code":"US",
    "gn:dem":23,
    "gn:elevation":"17.0",
    "gn:feature_class":"P",
    "gn:feature_code":"PPL",
    "gn:name":"Oakwood Landing",
    "gn:population":0,
    "gn:timezone":"America/Chicago",
    "iso:country":"US",
    "wof:name":"Oakwood Landing",
    "wof:placetype":"locality"
},
  "geometry": {"coordinates":[-91.57483999999999,32.06071],"type":"Point"}
}