{
  "type": "Feature",
  "properties": {
    "iso:country":"US",
    "name:eng_x_preferred":[
        "Indian Creek Overlook"
    ],
    "wof:name":"Indian Creek Overlook",
    "wof:placetype":"neighbourhood",
    "wof:population":101,
    "zs:area_m":294794.014866,
    "zs:blockids":[
        371830529022002
    ],
    "zs:housing10":48,
    "zs:label":"Indian Creek Overlook",
    "zs:pop10":101
},
  "geometry": {"coordinates":[-78.61254599999999,35.64817],"type":"Point"}
}