{
  "type": "Feature",
  "properties": {
    "gn:admin1_code":"NY",
    "gn:admin2_code":"7",
    "gn:admin3_code":"44611.0",
    "gn:asciiname":"Twining Trailer Park",
    "gn:country_code":"US",
    "gn:dem":278,
    "gn:elevation":"277.0",
    "gn:feature_class":"P",
    "gn:feature_code":"PPL",
    "gn:name":"Twining Trailer Park",
    "gn:population":0,
    "gn:timezone":"America/New_York",
    "iso:country":"US",
    "wof:name":"Twining Trailer Park",
    "wof:placetype":"campus"
},
  "geometry": {"coordinates":[-76.065,42.17889],"type":"Point"}
}