{
  "type": "Feature",
  "properties": {
    "gn:admin1_code":"SC",
    "gn:admin2_code":"87.0",
    "gn:asciiname":"Carem",
    "gn:country_code":"US",
    "gn:dem":181,
    "gn:elevation":"177.0",
    "gn:feature_class":"P",
    "gn:feature_code":"PPL",
    "gn:name":"Carem",
    "gn:population":0,
    "gn:timezone":"America/New_York",
    "iso:country":"US",
    "name:eng_x_preferred":[
        "Carem"
    ],
    "name:und_x_variant":[
        "Hog Foot"
    ],
    "wof:name":"Carem",
    "wof:placetype":"locality"
},
  "geometry": {"coordinates":[-81.56788,34.69847],"type":"Point"}
}