{
  "type": "Feature",
  "properties": {
    "gn:admin1_code":"NY",
    "gn:admin2_code":"27.0",
    "gn:admin3_code":"51891.0",
    "gn:asciiname":"Whitehouse Crossing",
    "gn:country_code":"US",
    "gn:dem":233,
    "gn:elevation":"230.0",
    "gn:feature_class":"P",
    "gn:feature_code":"PPL",
    "gn:name":"Whitehouse Crossing",
    "gn:population":0,
    "gn:timezone":"America/New_York",
    "iso:country":"US",
    "wof:name":"Whitehouse Crossing",
    "wof:placetype":"locality"
},
  "geometry": {"coordinates":[-73.51984,42.02593],"type":"Point"}
}