{
  "type": "Feature",
  "properties": {
    "gn:admin1_code":"AL",
    "gn:admin2_code":"5",
    "gn:asciiname":"Gaino",
    "gn:country_code":"US",
    "gn:dem":156,
    "gn:elevation":"153.0",
    "gn:feature_class":"P",
    "gn:feature_code":"PPL",
    "gn:name":"Gaino",
    "gn:population":0,
    "gn:timezone":"America/Chicago",
    "iso:country":"US",
    "wof:name":"Gaino",
    "wof:placetype":"locality"
},
  "geometry": {"coordinates":[-85.3441,31.84127],"type":"Point"}
}