{
  "type": "Feature",
  "properties": {
    "gn:admin1_code":"GA",
    "gn:admin2_code":"133.0",
    "gn:asciiname":"Carey",
    "gn:country_code":"US",
    "gn:dem":150,
    "gn:elevation":"147.0",
    "gn:feature_class":"P",
    "gn:feature_code":"PPL",
    "gn:name":"Carey",
    "gn:population":0,
    "gn:timezone":"America/New_York",
    "iso:country":"US",
    "name:ceb_x_preferred":[
        "Carey"
    ],
    "name:deu_x_preferred":[
        "Carey"
    ],
    "name:eng_x_preferred":[
        "Carey"
    ],
    "name:fin_x_preferred":[
        "Carey"
    ],
    "name:fra_x_preferred":[
        "Carey"
    ],
    "name:ita_x_preferred":[
        "Carey"
    ],
    "name:lav_x_preferred":[
        "Carey"
    ],
    "name:nld_x_preferred":[
        "Carey"
    ],
    "name:pol_x_preferred":[
        "Carey"
    ],
    "name:por_x_preferred":[
        "Carey"
    ],
    "name:rus_x_preferred":[
        "\u041a\u044d\u0440\u0438"
    ],
    "name:spa_x_preferred":[
        "Carey"
    ],
    "name:ukr_x_preferred":[
        "\u041a\u0435\u0440\u0456"
    ],
    "name:und_x_variant":[
        "Litch"
    ],
    "name:vol_x_preferred":[
        "Carey"
    ],
    "wof:name":"Carey",
    "wof:placetype":"locality"
},
  "geometry": {"coordinates":[-83.26904999999999,33.54763],"type":"Point"}
}