{
  "type": "Feature",
  "properties": {
    "gn:admin1_code":"ND",
    "gn:admin2_code":"67.0",
    "gn:admin3_code":"700.0",
    "gn:asciiname":"Leyden",
    "gn:country_code":"US",
    "gn:dem":284,
    "gn:elevation":"288.0",
    "gn:feature_class":"P",
    "gn:feature_code":"PPL",
    "gn:name":"Leyden",
    "gn:population":0,
    "gn:timezone":"America/Chicago",
    "iso:country":"US",
    "wof:name":"Leyden",
    "wof:placetype":"locality"
},
  "geometry": {"coordinates":[-97.81092,48.87666],"type":"Point"}
}