{
  "type": "Feature",
  "properties": {
    "gn:admin1_code":"AR",
    "gn:admin2_code":"35.0",
    "gn:admin3_code":"92298.0",
    "gn:asciiname":"Beck",
    "gn:country_code":"US",
    "gn:dem":61,
    "gn:elevation":"62.0",
    "gn:feature_class":"P",
    "gn:feature_code":"PPL",
    "gn:name":"Beck",
    "gn:population":0,
    "gn:timezone":"America/Chicago",
    "iso:country":"US",
    "name:ara_x_preferred":[
        "\u0628\u064a\u0643"
    ],
    "name:azb_x_preferred":[
        "\u0628\u06a9 \u0647\u0627\u0646\u0633\u0646"
    ],
    "name:cat_x_preferred":[
        "Beck Hansen"
    ],
    "name:ces_x_preferred":[
        "Beck"
    ],
    "name:crh_x_preferred":[
        "Bek"
    ],
    "name:dan_x_preferred":[
        "Beck"
    ],
    "name:deu_x_preferred":[
        "Beck"
    ],
    "name:epo_x_preferred":[
        "Beck"
    ],
    "name:eus_x_preferred":[
        "Beck"
    ],
    "name:fas_x_preferred":[
        "\u0628\u06a9 \u0647\u0627\u0646\u0633\u0646"
    ],
    "name:fin_x_preferred":[
        "Beck"
    ],
    "name:fra_x_preferred":[
        "Beck Hansen"
    ],
    "name:glg_x_preferred":[
        "Beck"
    ],
    "name:hrv_x_preferred":[
        "Beck"
    ],
    "name:hun_x_preferred":[
        "Beck"
    ],
    "name:hye_x_preferred":[
        "\u0532\u0565\u0584 \u0540\u0565\u0576\u057d\u0565\u0576"
    ],
    "name:isl_x_preferred":[
        "Beck"
    ],
    "name:ita_x_preferred":[
        "Beck"
    ],
    "name:jpn_x_preferred":[
        "\u30d9\u30c3\u30af"
    ],
    "name:kat_x_preferred":[
        "\u10d1\u10d4\u10d9\u10d8"
    ],
    "name:mzn_x_preferred":[
        "\u0628\u06a9"
    ],
    "name:nld_x_preferred":[
        "Beck Hansen"
    ],
    "name:nno_x_preferred":[
        "Beck"
    ],
    "name:nor_x_preferred":[
        "Beck"
    ],
    "name:oci_x_preferred":[
        "Beck"
    ],
    "name:pol_x_preferred":[
        "Beck Hansen"
    ],
    "name:por_x_preferred":[
        "Beck Hansen"
    ],
    "name:ron_x_preferred":[
        "Beck"
    ],
    "name:rus_x_preferred":[
        "\u0411\u0435\u043a \u0425\u044d\u043d\u0441\u0435\u043d"
    ],
    "name:sco_x_preferred":[
        "Beck"
    ],
    "name:slk_x_preferred":[
        "Beck"
    ],
    "name:spa_x_preferred":[
        "Beck"
    ],
    "name:swe_x_preferred":[
        "Beck Hansen"
    ],
    "name:tha_x_preferred":[
        "\u0e40\u0e1a\u0e47\u0e01"
    ],
    "name:tur_x_preferred":[
        "Beck"
    ],
    "name:ukr_x_preferred":[
        "\u0411\u0435\u043a \u0413\u0430\u043d\u0441\u0435\u043d"
    ],
    "name:vie_x_preferred":[
        "Beck"
    ],
    "name:zho_x_preferred":[
        "\u8c9d\u514b"
    ],
    "wof:name":"Beck",
    "wof:placetype":"locality"
},
  "geometry": {"coordinates":[-90.39593000000001,34.9226],"type":"Point"}
}