{
  "type": "Feature",
  "properties": {
    "iso:country":"US",
    "name:ara_x_preferred":[
        "\u0628\u0644\u064a\u0632\u0627\u0646\u062a \u0641\u0627\u0644\u064a"
    ],
    "name:cat_x_preferred":[
        "Pleasant Valley"
    ],
    "name:ceb_x_preferred":[
        "Pleasant Valley"
    ],
    "name:deu_x_preferred":[
        "Pleasant Valley"
    ],
    "name:eng_x_preferred":[
        "Pleasant Valley"
    ],
    "name:fra_x_preferred":[
        "Pleasant Valley"
    ],
    "name:ita_x_preferred":[
        "Pleasant Valley"
    ],
    "name:nld_x_preferred":[
        "Pleasant Valley"
    ],
    "name:pol_x_preferred":[
        "Pleasant Valley"
    ],
    "name:por_x_preferred":[
        "Pleasant Valley"
    ],
    "name:spa_x_preferred":[
        "Pleasant Valley"
    ],
    "name:srp_x_preferred":[
        "\u041f\u043b\u0435\u0437\u0430\u043d\u0442 \u0412\u0430\u043b\u0438"
    ],
    "name:swe_x_preferred":[
        "Pleasant Valley"
    ],
    "name:vol_x_preferred":[
        "Pleasant Valley"
    ],
    "wof:name":"Pleasant Valley",
    "wof:placetype":"neighbourhood",
    "wof:population":3276,
    "zs:area_m":1980097.935298,
    "zs:blockids":[
        60411031001026,
        60411031002035,
        60411031003009,
        60411031002032,
        60411031002038,
        60411031002039,
        60411031003002,
        60411031003008,
        60411031001024,
        60411031003003,
        60411031004004,
        60411031004008,
        60411031002013,
        60411031002036,
        60411031003001,
        60411031004006,
        60411031004007,
        60411031002030,
        60411031003005,
        60411031004005,
        60411031003011,
        60411031004000,
        60411031004009,
        60411031002033,
        60411031002031,
        60411031003000,
        60411031004002,
        60411031004010,
        60411031004001,
        60411031002034,
        60411031004003,
        60411031001025,
        60411031003007,
        60411031002037
    ],
    "zs:housing10":1255,
    "zs:label":"Pleasant Valley",
    "zs:pop10":3276
},
  "geometry": {"coordinates":[-122.609331,38.106939],"type":"Point"}
}