{
  "type": "Feature",
  "properties": {
    "gn:admin1_code":"PA",
    "gn:admin2_code":"91",
    "gn:admin3_code":"84888.0",
    "gn:asciiname":"Center Square Green",
    "gn:country_code":"US",
    "gn:dem":83,
    "gn:elevation":"81.0",
    "gn:feature_class":"P",
    "gn:feature_code":"PPL",
    "gn:name":"Center Square Green",
    "gn:population":0,
    "gn:timezone":"America/New_York",
    "iso:country":"US",
    "wof:name":"Center Square Green",
    "wof:placetype":"locality"
},
  "geometry": {"coordinates":[-75.31189999999999,40.1569],"type":"Point"}
}