{
  "type": "Feature",
  "properties": {
    "iso:country":"US",
    "name:eng_x_preferred":[
        "Acadian Place"
    ],
    "wof:name":"Acadian Place",
    "wof:placetype":"neighbourhood",
    "zs:area_m":50971.09853,
    "zs:blockids":[
        220330039102030,
        220330039102032
    ],
    "zs:housing10":0,
    "zs:label":"Acadian Place",
    "zs:pop10":0
},
  "geometry": {"coordinates":[-91.06835700000001,30.416056],"type":"Point"}
}