{
  "type": "Feature",
  "properties": {
    "gn:admin1_code":"OH",
    "gn:admin2_code":"169",
    "gn:admin3_code":"4276.0",
    "gn:asciiname":"Smithville Trailer Park",
    "gn:country_code":"US",
    "gn:dem":330,
    "gn:elevation":"331.0",
    "gn:feature_class":"P",
    "gn:feature_code":"PPL",
    "gn:name":"Smithville Trailer Park",
    "gn:population":0,
    "gn:timezone":"America/New_York",
    "iso:country":"US",
    "wof:name":"Smithville Trailer Park",
    "wof:placetype":"campus"
},
  "geometry": {"coordinates":[-81.67860999999998,40.87333],"type":"Point"}
}