{
  "type": "Feature",
  "properties": {
    "gn:admin1_code":"FL",
    "gn:admin2_code":"57",
    "gn:asciiname":"Gandy Manor Estates",
    "gn:country_code":"US",
    "gn:dem":9,
    "gn:elevation":"3.0",
    "gn:feature_class":"P",
    "gn:feature_code":"PPL",
    "gn:name":"Gandy Manor Estates",
    "gn:population":0,
    "gn:timezone":"America/New_York",
    "iso:country":"US",
    "wof:name":"Gandy Manor Estates",
    "wof:placetype":"locality"
},
  "geometry": {"coordinates":[-82.5168,27.8808],"type":"Point"}
}