{
  "type": "Feature",
  "properties": {
    "gn:admin1_code":"TX",
    "gn:admin2_code":"201.0",
    "gn:asciiname":"Clear Lake",
    "gn:country_code":"US",
    "gn:dem":12,
    "gn:elevation":"7.0",
    "gn:feature_class":"P",
    "gn:feature_code":"PPL",
    "gn:name":"Clear Lake",
    "gn:population":0,
    "gn:timezone":"America/Chicago",
    "iso:country":"US",
    "name:cat_x_preferred":[
        "Clear Lake"
    ],
    "name:ceb_x_preferred":[
        "Clear Lake"
    ],
    "name:ces_x_preferred":[
        "Clear Lake"
    ],
    "name:deu_x_preferred":[
        "Clear Lake"
    ],
    "name:fra_x_preferred":[
        "Clear Lake"
    ],
    "name:ita_x_preferred":[
        "Clear Lake"
    ],
    "name:msa_x_preferred":[
        "Gunung Berapi Clear Lake"
    ],
    "name:nld_x_preferred":[
        "Clear Lake"
    ],
    "name:pol_x_preferred":[
        "Clear Lake"
    ],
    "name:por_x_preferred":[
        "Clear Lake"
    ],
    "name:spa_x_preferred":[
        "Clear Lake"
    ],
    "name:srp_x_preferred":[
        "\u041a\u043b\u0438\u0440 \u041b\u0435\u0458\u043a"
    ],
    "name:swe_x_preferred":[
        "Clear Lake"
    ],
    "name:vol_x_preferred":[
        "Clear Lake"
    ],
    "wof:name":"Clear Lake",
    "wof:placetype":"locality"
},
  "geometry": {"coordinates":[-95.1276,29.5534],"type":"Point"}
}