{
  "type": "Feature",
  "properties": {
    "iso:country":"US",
    "name:eng_x_preferred":[
        "Kahuku Ahupua`a"
    ],
    "wof:name":"Kahuku Ahupua`a",
    "wof:placetype":"neighbourhood",
    "wof:population":3,
    "zs:area_m":104204733.927651,
    "zs:blockids":[
        150010212023001
    ],
    "zs:housing10":2,
    "zs:label":"Kahuku Ahupua`a",
    "zs:pop10":3
},
  "geometry": {"coordinates":[-155.735062,19.013844],"type":"Point"}
}