{
  "type": "Feature",
  "properties": {
    "gn:admin1_code":"FL",
    "gn:admin2_code":"69.0",
    "gn:asciiname":"Woodlands at Church Lake Mobile Home Park",
    "gn:country_code":"US",
    "gn:dem":33,
    "gn:elevation":"27.0",
    "gn:feature_class":"P",
    "gn:feature_code":"PPL",
    "gn:name":"Woodlands at Church Lake Mobile Home Park",
    "gn:population":0,
    "gn:timezone":"America/New_York",
    "iso:country":"US",
    "wof:name":"Woodlands at Church Lake Mobile Home Park",
    "wof:placetype":"campus"
},
  "geometry": {"coordinates":[-81.83577,28.64576],"type":"Point"}
}