{
  "type": "Feature",
  "properties": {
    "iso:country":"US",
    "name:eng_x_preferred":[
        "Ashland Meadows"
    ],
    "wof:name":"Ashland Meadows",
    "wof:placetype":"neighbourhood",
    "wof:population":216,
    "zs:area_m":96728.472686,
    "zs:blockids":[
        191530102033061,
        191530102033060
    ],
    "zs:housing10":85,
    "zs:label":"Ashland Meadows",
    "zs:pop10":216
},
  "geometry": {"coordinates":[-93.61313,41.747803],"type":"Point"}
}