{
  "type": "Feature",
  "properties": {
    "iso:country":"US",
    "qs_pg:aaroncc":"US",
    "qs_pg:name":"Cooks Heiau",
    "qs_pg:name_adm0":"United States",
    "qs_pg:name_adm1":"Hawaii",
    "qs_pg:photos":78,
    "qs_pg:photos_1k":16,
    "qs_pg:photos_9k":1,
    "qs_pg:photos_9r":3,
    "qs_pg:photos_all":78,
    "qs_pg:photos_sr":3,
    "qs_pg:pop_sr":0,
    "qs_pg:qs_pg_placetype":"locality",
    "qs_pg:qs_pg_placetype_gp":"Town",
    "qs_pg:woe_adm0":23424977,
    "woe:adm0_id":23424977,
    "woe:name_adm0":"United States",
    "woe:name_adm1":"Hawaii",
    "woe:placetype":"Town",
    "wof:name":"Cooks Heiau",
    "wof:placetype":"locality"
},
  "geometry": {"coordinates":[-155.94543400000001,19.492485],"type":"Point"}
}