{
  "type": "Feature",
  "properties": {
    "gn:admin1_code":"WI",
    "gn:admin2_code":"135",
    "gn:admin3_code":"25400.0",
    "gn:asciiname":"Chain O' Lakes-King",
    "gn:country_code":"US",
    "gn:dem":282,
    "gn:elevation":"275.0",
    "gn:feature_class":"P",
    "gn:feature_code":"PPL",
    "gn:name":"Chain O' Lakes-King",
    "gn:population":0,
    "gn:timezone":"America/Chicago",
    "iso:country":"US",
    "name:azb_x_preferred":[
        "\u0686\u06cc\u0646 \u0627\u0648 \u0644\u06cc\u06a9\u0633-\u06a9\u06cc\u0646\u0642"
    ],
    "name:cat_x_preferred":[
        "Chain O' Lakes-King"
    ],
    "name:ceb_x_preferred":[
        "Chain O' Lakes-King"
    ],
    "name:fas_x_preferred":[
        "\u0686\u06cc\u0646 \u0627\u0648 \u0644\u06cc\u06a9\u0633-\u06a9\u06cc\u0646\u06af"
    ],
    "name:ita_x_preferred":[
        "Chain O'Lakes-King"
    ],
    "name:nld_x_preferred":[
        "Chain O' Lakes-King"
    ],
    "name:por_x_preferred":[
        "Chain O' Lakes-King"
    ],
    "name:ron_x_preferred":[
        "Chain O' Lakes-King"
    ],
    "name:srp_x_preferred":[
        "\u0427\u0435\u0458\u043d \u041e \u041b\u0435\u043a\u0441-\u041a\u0438\u043d\u0433"
    ],
    "name:und_x_variant":[
        "Chain O' Lakes-King CDP"
    ],
    "name:uzb_x_preferred":[
        "Chain O' Lakes-King"
    ],
    "name:vol_x_preferred":[
        "Chain O' Lakes-King"
    ],
    "wof:name":"Chain O' Lakes-King",
    "wof:placetype":"locality"
},
  "geometry": {"coordinates":[-89.16694,44.33073],"type":"Point"}
}