{
  "type": "Feature",
  "properties": {
    "gn:admin1_code":"GA",
    "gn:admin2_code":"287.0",
    "gn:asciiname":"Dakota",
    "gn:country_code":"US",
    "gn:dem":129,
    "gn:elevation":"123.0",
    "gn:feature_class":"P",
    "gn:feature_code":"PPL",
    "gn:name":"Dakota",
    "gn:population":0,
    "gn:timezone":"America/New_York",
    "iso:country":"US",
    "name:afr_x_preferred":[
        "Dakota"
    ],
    "name:bak_x_preferred":[
        "\u0414\u0430\u043a\u043e\u0442\u0430"
    ],
    "name:ceb_x_preferred":[
        "Dakota"
    ],
    "name:ces_x_preferred":[
        "Dakota"
    ],
    "name:deu_x_preferred":[
        "Dakota"
    ],
    "name:ell_x_preferred":[
        "\u039d\u03c4\u03b1\u03ba\u03cc\u03c4\u03b1"
    ],
    "name:eng_x_preferred":[
        "Dakota"
    ],
    "name:est_x_preferred":[
        "Dakota"
    ],
    "name:eus_x_preferred":[
        "Dakota"
    ],
    "name:fas_x_preferred":[
        "\u062f\u0627\u06a9\u0648\u062a\u0627"
    ],
    "name:fin_x_preferred":[
        "Dakota"
    ],
    "name:fra_x_preferred":[
        "Dakota"
    ],
    "name:fry_x_preferred":[
        "Dakota"
    ],
    "name:heb_x_preferred":[
        "\u05d3\u05e7\u05d5\u05d8\u05d4"
    ],
    "name:ita_x_preferred":[
        "Dakota"
    ],
    "name:jpn_x_preferred":[
        "\u30b5\u30a6\u30b9\u30c0\u30b3\u30bf"
    ],
    "name:kbp_x_preferred":[
        "Takota"
    ],
    "name:kor_x_preferred":[
        "\ub2e4\ucf54\ud0c0"
    ],
    "name:lav_x_preferred":[
        "Dakota"
    ],
    "name:nds_x_preferred":[
        "Dakota"
    ],
    "name:nld_x_preferred":[
        "Dakota"
    ],
    "name:nor_x_preferred":[
        "Dakota"
    ],
    "name:oci_x_preferred":[
        "Dakota"
    ],
    "name:oss_x_preferred":[
        "\u0414\u0430\u043a\u043e\u0442\u00e6"
    ],
    "name:pol_x_preferred":[
        "Dakota"
    ],
    "name:por_x_preferred":[
        "Dakota"
    ],
    "name:que_x_preferred":[
        "Dakota"
    ],
    "name:ron_x_preferred":[
        "Dakota"
    ],
    "name:rus_x_preferred":[
        "\u0414\u0430\u043a\u043e\u0442\u0430"
    ],
    "name:sco_x_preferred":[
        "Dakota"
    ],
    "name:slv_x_preferred":[
        "North Dakota"
    ],
    "name:spa_x_preferred":[
        "Dakota"
    ],
    "name:srp_x_preferred":[
        "\u0414\u0430\u043a\u043e\u0442\u0430"
    ],
    "name:swe_x_preferred":[
        "Dakota"
    ],
    "name:tur_x_preferred":[
        "Dakota"
    ],
    "name:ukr_x_preferred":[
        "\u0414\u0430\u043a\u043e\u0442\u0430"
    ],
    "name:und_x_variant":[
        "Ada",
        "Dakota Station"
    ],
    "name:urd_x_preferred":[
        "\u0688\u06a9\u0648\u0679\u0627"
    ],
    "name:vol_x_preferred":[
        "Dakota"
    ],
    "name:zho_x_preferred":[
        "\u9054\u79d1\u5854"
    ],
    "wof:name":"Dakota",
    "wof:placetype":"locality"
},
  "geometry": {"coordinates":[-83.69323,31.77601],"type":"Point"}
}