{
  "type": "Feature",
  "properties": {
    "gn:admin1_code":"LA",
    "gn:admin2_code":"101.0",
    "gn:asciiname":"Bodin",
    "gn:country_code":"US",
    "gn:dem":6,
    "gn:elevation":"2.0",
    "gn:feature_class":"P",
    "gn:feature_code":"PPL",
    "gn:name":"Bodin",
    "gn:population":0,
    "gn:timezone":"America/Chicago",
    "iso:country":"US",
    "name:nno_x_preferred":[
        "Bodin"
    ],
    "name:nor_x_preferred":[
        "Bodin"
    ],
    "name:rus_x_preferred":[
        "\u0411\u0443\u0434\u0438\u043d"
    ],
    "wof:name":"Bodin",
    "wof:placetype":"locality"
},
  "geometry": {"coordinates":[-91.61261,29.83798],"type":"Point"}
}