{
  "type": "Feature",
  "properties": {
    "gn:admin1_code":"FL",
    "gn:admin2_code":"47.0",
    "gn:asciiname":"Blue Springs",
    "gn:country_code":"US",
    "gn:dem":33,
    "gn:elevation":"24.0",
    "gn:feature_class":"P",
    "gn:feature_code":"PPL",
    "gn:name":"Blue Springs",
    "gn:population":0,
    "gn:timezone":"America/New_York",
    "iso:country":"US",
    "name:ara_x_preferred":[
        "\u0628\u0644\u0648 \u0633\u0628\u0631\u064a\u0646\u063a\u0632"
    ],
    "name:ceb_x_preferred":[
        "Blue Springs"
    ],
    "name:deu_x_preferred":[
        "Blue Springs"
    ],
    "name:ita_x_preferred":[
        "Blue Springs"
    ],
    "name:nld_x_preferred":[
        "Blue Springs"
    ],
    "name:pol_x_preferred":[
        "Blue Springs"
    ],
    "name:por_x_preferred":[
        "Blue Springs"
    ],
    "name:spa_x_preferred":[
        "Blue Springs"
    ],
    "name:srp_x_preferred":[
        "\u0411\u043b\u0443 \u0421\u043f\u0440\u0438\u043d\u0433\u0441"
    ],
    "name:swe_x_preferred":[
        "Blue Springs"
    ],
    "name:ukr_x_preferred":[
        "\u0411\u043b\u0443-\u0421\u043f\u0440\u0456\u043d\u0433\u0441"
    ],
    "name:urd_x_preferred":[
        "\u0628\u0644\u06cc\u0648 \u0633\u067e\u0631\u0646\u06af\u0632"
    ],
    "name:vol_x_preferred":[
        "Blue Springs"
    ],
    "wof:name":"Blue Springs",
    "wof:placetype":"locality"
},
  "geometry": {"coordinates":[-83.21986,30.4866],"type":"Point"}
}