{
  "type": "Feature",
  "properties": {
    "gn:admin1_code":"DE",
    "gn:admin2_code":"1.0",
    "gn:asciiname":"Colmar Manor",
    "gn:country_code":"US",
    "gn:dem":12,
    "gn:elevation":"14.0",
    "gn:feature_class":"P",
    "gn:feature_code":"PPL",
    "gn:name":"Colmar Manor",
    "gn:population":0,
    "gn:timezone":"America/New_York",
    "iso:country":"US",
    "wof:name":"Colmar Manor",
    "wof:placetype":"locality"
},
  "geometry": {"coordinates":[-75.60937,39.28344],"type":"Point"}
}