{
  "type": "Feature",
  "properties": {
    "gn:admin1_code":"CA",
    "gn:admin2_code":"113.0",
    "gn:asciiname":"Daisie",
    "gn:country_code":"US",
    "gn:dem":-1,
    "gn:elevation":"5.0",
    "gn:feature_class":"P",
    "gn:feature_code":"PPL",
    "gn:name":"Daisie",
    "gn:population":0,
    "gn:timezone":"America/Los_Angeles",
    "iso:country":"US",
    "name:zho_x_preferred":[
        "\u9edb\u897f"
    ],
    "wof:name":"Daisie",
    "wof:placetype":"locality"
},
  "geometry": {"coordinates":[-121.64384,38.31463],"type":"Point"}
}