{
  "type": "Feature",
  "properties": {
    "iso:country":"US",
    "name:eng_x_preferred":[
        "Hightower Lake"
    ],
    "wof:name":"Hightower Lake",
    "wof:placetype":"neighbourhood",
    "wof:population":135,
    "zs:area_m":3884740.008535,
    "zs:blockids":[
        130570905012020,
        130570905011004,
        130570905011005
    ],
    "zs:housing10":59,
    "zs:label":"Hightower Lake",
    "zs:pop10":135
},
  "geometry": {"coordinates":[-84.29098999999999,34.284368],"type":"Point"}
}