{
  "type": "Feature",
  "properties": {
    "iso:country":"US",
    "name:eng_x_preferred":[
        "El Cerrito Hills"
    ],
    "qs:gn_adm0_cc":"US",
    "qs:gn_local":5345623,
    "qs:gn_nam_loc":"El Cerrito, Contra Costa, California, US",
    "qs:gn_namadm1":"CA",
    "qs:local_max":1851,
    "qs:local_sum":3346,
    "qs:localhoods":3,
    "qs:name":"El Cerrito Hills",
    "qs:name_adm0":"United States",
    "qs:name_adm1":"California",
    "qs:name_adm2":"Contra Costa",
    "qs:name_local":"El Cerrito",
    "qs:photo_max":83,
    "qs:photo_sum":757,
    "qs:placetype":"Suburb",
    "qs:quad_count":49,
    "qs:woe_adm0":23424977,
    "qs:woe_adm1":2347563,
    "qs:woe_adm2":12587676,
    "qs:woe_lau":0,
    "qs:woe_local":2397751,
    "qs:woe_ver":"7.10.0",
    "wof:lang":[
        "eng"
    ],
    "wof:name":"El Cerrito Hills",
    "wof:placetype":"neighbourhood",
    "wof:population":4714,
    "zs:blockids":[
        60133851002001,
        60133901001008,
        60133851001009,
        60133920001004,
        60133910002005,
        60133870001001,
        60133851002003,
        60133901003001,
        60133851002008,
        60133851002014,
        60133910001003,
        60133902002011,
        60133851001026,
        60133901001002,
        60133870002000,
        60133901001005,
        60133851002010,
        60133902002000,
        60133851002013,
        60133610002046,
        60133851001010,
        60133901002002,
        60133901001007,
        60133901003007,
        60133851002016,
        60133851001007,
        60133851001024,
        60133851002007,
        60133851001023,
        60133901003000,
        60133901001004,
        60133851002017,
        60133910001002,
        60133851002011,
        60133901002003,
        60133901001003,
        60133901002000,
        60133910002006,
        60133910002003,
        60133870001014,
        60133870001013,
        60133851001016,
        60133901002004,
        60133910001004,
        60133851002009,
        60133851002015,
        60133851001030,
        60133851001015,
        60133851001011,
        60133851001025,
        60133851002005,
        60133851001021,
        60133851001012,
        60133851002000,
        60133851001013,
        60133851001018,
        60133901001006,
        60133851001029,
        60133910001000,
        60133851001027,
        60133851002012,
        60133910002001,
        60133910002004,
        60133920001003,
        60133870001000,
        60133851001017,
        60133851001019,
        60133851001020,
        60133851001022,
        60133851001014,
        60133920001002,
        60133851001008,
        60133902002007,
        60133851002002,
        60133901001000,
        60133901001001,
        60133851001028,
        60133901003006,
        60133851002004,
        60133851001003,
        60133901002001,
        60133851002006
    ],
    "zs:housing10":2051,
    "zs:pop10":4714
},
  "geometry": {"coordinates":[-122.290712,37.921774],"type":"Point"}
}