{
  "type": "Feature",
  "properties": {
    "gn:admin1_code":"MS",
    "gn:admin2_code":"149.0",
    "gn:asciiname":"Culkin",
    "gn:country_code":"US",
    "gn:dem":115,
    "gn:elevation":"111.0",
    "gn:feature_class":"P",
    "gn:feature_code":"PPL",
    "gn:name":"Culkin",
    "gn:population":0,
    "gn:timezone":"America/Chicago",
    "iso:country":"US",
    "name:ces_x_preferred":[
        "Culkin"
    ],
    "name:deu_x_preferred":[
        "Culkin"
    ],
    "name:fra_x_preferred":[
        "Culkin"
    ],
    "name:ita_x_preferred":[
        "Culkin"
    ],
    "name:jpn_x_preferred":[
        "\u30ab\u30eb\u30ad\u30f3"
    ],
    "name:nds_x_preferred":[
        "Culkin"
    ],
    "name:rus_x_preferred":[
        "\u041a\u0430\u043b\u043a\u0438\u043d"
    ],
    "name:ukr_x_preferred":[
        "\u041a\u0430\u043b\u043a\u0456\u043d"
    ],
    "wof:name":"Culkin",
    "wof:placetype":"locality"
},
  "geometry": {"coordinates":[-90.81816000000001,32.3682],"type":"Point"}
}