{
  "type": "Feature",
  "properties": {
    "iso:country":"US",
    "name:eng_x_preferred":[
        "River Neck"
    ],
    "name:eng_x_variant":[
        "River Nck"
    ],
    "qs:gn_adm0_cc":"US",
    "qs:gn_local":4461493,
    "qs:gn_nam_loc":"Columbia, Tyrrell, North Carolina, US",
    "qs:gn_namadm1":"NC",
    "qs:local_max":53,
    "qs:local_sum":53,
    "qs:localhoods":1,
    "qs:name":"River Neck",
    "qs:name_adm0":"United States",
    "qs:name_adm1":"North Carolina",
    "qs:name_adm2":"Tyrrell",
    "qs:name_local":"Columbia",
    "qs:photo_max":25,
    "qs:photo_sum":53,
    "qs:placetype":"Suburb",
    "qs:quad_count":8,
    "qs:woe_adm0":23424977,
    "qs:woe_adm1":2347592,
    "qs:woe_adm2":12589462,
    "qs:woe_lau":0,
    "qs:woe_local":2383555,
    "qs:woe_ver":"7.10.0",
    "wof:lang":[
        "eng"
    ],
    "wof:name":"River Neck",
    "wof:placetype":"neighbourhood",
    "wof:population":367,
    "zs:blockids":[
        371779601002048,
        371779601002036,
        371779601002053,
        371779601002064,
        371779601002052,
        371779601002063,
        371779601002047,
        371779601002069,
        371779601002068,
        371779601002038,
        371779601002041,
        371779601002001,
        371779601002044
    ],
    "zs:housing10":178,
    "zs:pop10":367
},
  "geometry": {"coordinates":[-76.251986,35.917319],"type":"Point"}
}