{
  "type": "Feature",
  "properties": {
    "gn:admin1_code":"IN",
    "gn:admin2_code":"31.0",
    "gn:admin3_code":"13042.0",
    "gn:asciiname":"Ewington",
    "gn:country_code":"US",
    "gn:dem":270,
    "gn:elevation":"270.0",
    "gn:feature_class":"P",
    "gn:feature_code":"PPL",
    "gn:name":"Ewington",
    "gn:population":0,
    "gn:timezone":"America/Indiana/Indianapolis",
    "iso:country":"US",
    "wof:name":"Ewington",
    "wof:placetype":"locality"
},
  "geometry": {"coordinates":[-85.56803000000002,39.32644000000001],"type":"Point"}
}