{
  "type": "Feature",
  "properties": {
    "gn:country":"US",
    "gn:fcode":"PPL",
    "gn:population":20199,
    "iso:country":"US",
    "name:ara_x_preferred":[
        "\u063a\u0644\u064a\u0646 \u0623\u0641\u0648\u0646"
    ],
    "name:arz_x_preferred":[
        "\u062c\u0644\u064a\u0646 \u0627\u0641\u0648\u0646"
    ],
    "name:ast_x_preferred":[
        "Glen Avon"
    ],
    "name:azb_x_preferred":[
        "\u0642\u0644\u0646 \u0627\u06cc\u0648\u0648\u0646"
    ],
    "name:cat_x_preferred":[
        "Glen Avon"
    ],
    "name:ceb_x_preferred":[
        "Glen Avon"
    ],
    "name:che_x_preferred":[
        "\u0413\u043b\u0435\u043d-\u0415\u0439\u0432\u043e\u043d"
    ],
    "name:deu_x_preferred":[
        "Glen Avon"
    ],
    "name:eng_x_preferred":[
        "Glen Avon"
    ],
    "name:fas_x_preferred":[
        "\u06af\u0644\u0646 \u0627\u06cc\u0648\u0648\u0646"
    ],
    "name:fra_x_preferred":[
        "Glen Avon"
    ],
    "name:gle_x_preferred":[
        "Glen Avon"
    ],
    "name:hrv_x_preferred":[
        "Glen Avon"
    ],
    "name:ita_x_preferred":[
        "Glen Avon"
    ],
    "name:lld_x_preferred":[
        "Glen Avon"
    ],
    "name:nan_x_preferred":[
        "Glen Avon"
    ],
    "name:new_x_preferred":[
        "\u0917\u094d\u0932\u0947\u0928 \u090f\u092d\u094b\u0928"
    ],
    "name:nld_x_preferred":[
        "Glen Avon"
    ],
    "name:nob_x_preferred":[
        "Glen Avon"
    ],
    "name:pol_x_preferred":[
        "Glen Avon"
    ],
    "name:por_x_preferred":[
        "Glen Avon"
    ],
    "name:spa_x_preferred":[
        "Glen Avon"
    ],
    "name:srp_x_preferred":[
        "\u0413\u043b\u0435\u043d \u0415\u0458\u0432\u043e\u043d"
    ],
    "name:swe_x_preferred":[
        "Glen Avon"
    ],
    "name:tat_x_preferred":[
        "\u0413\u043b\u0435\u043d-\u0415\u0439\u0432\u043e\u043d"
    ],
    "name:ukr_x_preferred":[
        "\u0413\u043b\u0435\u043d-\u0415\u0439\u0432\u043e\u043d"
    ],
    "name:und_x_variant":[
        "Glen Avon Heights"
    ],
    "name:vol_x_preferred":[
        "Glen Avon"
    ],
    "name:zho_x_preferred":[
        "\u683c\u502b\u963f\u65fa"
    ],
    "qs_pg:aaroncc":"US",
    "qs_pg:gn_country":"US",
    "qs_pg:gn_fcode":"PPL",
    "qs_pg:gn_pop":20199,
    "qs_pg:name":"Glen Avon",
    "qs_pg:name_adm0":"United States",
    "qs_pg:name_adm1":"California",
    "qs_pg:photos":18,
    "qs_pg:photos_1k":4,
    "qs_pg:photos_9k":1,
    "qs_pg:photos_9r":1,
    "qs_pg:photos_all":18,
    "qs_pg:photos_sr":1,
    "qs_pg:pop_sr":7,
    "qs_pg:qs_pg_placetype":"locality",
    "qs_pg:qs_pg_placetype_gp":"Town",
    "qs_pg:woe_adm0":23424977,
    "woe:adm0_id":23424977,
    "woe:name_adm0":"United States",
    "woe:name_adm1":"California",
    "woe:placetype":"Town",
    "wof:name":"Glen Avon",
    "wof:placetype":"locality",
    "wof:population":20199
},
  "geometry": {"coordinates":[-117.48477,34.01168],"type":"Point"}
}