{
  "type": "Feature",
  "properties": {
    "gn:admin1_code":"DE",
    "gn:admin2_code":"3.0",
    "gn:asciiname":"Mockingbird Hills",
    "gn:country_code":"US",
    "gn:dem":82,
    "gn:elevation":"78.0",
    "gn:feature_class":"P",
    "gn:feature_code":"PPL",
    "gn:name":"Mockingbird Hills",
    "gn:population":0,
    "gn:timezone":"America/New_York",
    "iso:country":"US",
    "name:zho_x_preferred":[
        "\u83ab\u91d1\u4f2f\u5fb7\u5e0c\u723e\u65af"
    ],
    "wof:name":"Mockingbird Hills",
    "wof:placetype":"locality"
},
  "geometry": {"coordinates":[-75.67743,39.76039],"type":"Point"}
}