{
  "type": "Feature",
  "properties": {
    "iso:country":"US",
    "name:eng_x_preferred":[
        "Oakwood Two"
    ],
    "wof:name":"Oakwood Two",
    "wof:placetype":"neighbourhood",
    "wof:population":140,
    "zs:area_m":310454.18456,
    "zs:blockids":[
        490351006003016,
        490351006002011
    ],
    "zs:housing10":31,
    "zs:label":"Oakwood Two",
    "zs:pop10":140
},
  "geometry": {"coordinates":[-111.923053,40.773694],"type":"Point"}
}