{
  "type": "Feature",
  "properties": {
    "gn:admin1_code":"MO",
    "gn:admin2_code":"143.0",
    "gn:admin3_code":"15832.0",
    "gn:asciiname":"Turner",
    "gn:country_code":"US",
    "gn:dem":84,
    "gn:elevation":"85.0",
    "gn:feature_class":"P",
    "gn:feature_code":"PPL",
    "gn:name":"Turner",
    "gn:population":0,
    "gn:timezone":"America/Chicago",
    "iso:country":"US",
    "name:bre_x_preferred":[
        "Turner"
    ],
    "name:cat_x_preferred":[
        "Turner"
    ],
    "name:ceb_x_preferred":[
        "Turner"
    ],
    "name:ces_x_preferred":[
        "Turner"
    ],
    "name:deu_x_preferred":[
        "Turner"
    ],
    "name:fas_x_preferred":[
        "\u062a\u0631\u0646\u0631"
    ],
    "name:fin_x_preferred":[
        "Turner"
    ],
    "name:fra_x_preferred":[
        "Turner"
    ],
    "name:heb_x_preferred":[
        "\u05d8\u05e8\u05e0\u05e8"
    ],
    "name:ita_x_preferred":[
        "Turner"
    ],
    "name:jpn_x_preferred":[
        "\u30bf\u30fc\u30ca\u30fc"
    ],
    "name:lav_x_preferred":[
        "Turner"
    ],
    "name:nld_x_preferred":[
        "Turner"
    ],
    "name:nor_x_preferred":[
        "Turner"
    ],
    "name:pol_x_preferred":[
        "Turner"
    ],
    "name:por_x_preferred":[
        "Turner"
    ],
    "name:rus_x_preferred":[
        "\u0422\u0451\u0440\u043d\u0435\u0440"
    ],
    "name:spa_x_preferred":[
        "Turner"
    ],
    "name:srp_x_preferred":[
        "\u0422\u0435\u0440\u043d\u0435\u0440"
    ],
    "name:swe_x_preferred":[
        "Turner"
    ],
    "name:ukr_x_preferred":[
        "\u0422\u0435\u0440\u043d\u0435\u0440"
    ],
    "name:urd_x_preferred":[
        "\u0679\u0631\u0646\u0631"
    ],
    "name:vie_x_preferred":[
        "Turner"
    ],
    "name:vol_x_preferred":[
        "Turner"
    ],
    "wof:name":"Turner",
    "wof:placetype":"locality"
},
  "geometry": {"coordinates":[-89.91259000000002,36.58784],"type":"Point"}
}