{
  "type": "Feature",
  "properties": {
    "iso:country":"US",
    "name:eng_x_preferred":[
        "Watrous Heights"
    ],
    "wof:name":"Watrous Heights",
    "wof:placetype":"neighbourhood",
    "wof:population":159,
    "zs:area_m":98528.472368,
    "zs:blockids":[
        191530045013002,
        191530045022002,
        191530045013012,
        191530045022000,
        191530045013003
    ],
    "zs:housing10":85,
    "zs:label":"Watrous Heights",
    "zs:pop10":159
},
  "geometry": {"coordinates":[-93.62459800000001,41.546838],"type":"Point"}
}