{
  "type": "Feature",
  "properties": {
    "gn:admin1_code":"MN",
    "gn:admin2_code":"49.0",
    "gn:admin3_code":"67990.0",
    "gn:asciiname":"Hader",
    "gn:country_code":"US",
    "gn:dem":355,
    "gn:elevation":"360.0",
    "gn:feature_class":"P",
    "gn:feature_code":"PPL",
    "gn:name":"Hader",
    "gn:population":0,
    "gn:timezone":"America/Chicago",
    "iso:country":"US",
    "wof:name":"Hader",
    "wof:placetype":"locality"
},
  "geometry": {"coordinates":[-92.80103,44.36552],"type":"Point"}
}