{
  "type": "Feature",
  "properties": {
    "gn:elevation":28,
    "iso:country":"US",
    "name:eng_x_preferred":[
        "Ashley Heights"
    ],
    "name:eng_x_variant":[
        "Ashley Hts"
    ],
    "qs:gn_fcode":"PPL",
    "qs:gn_local":0,
    "qs:gn_namadm1":"MA",
    "qs:gn_name":"Ashley Heights",
    "qs:local_max":97,
    "qs:local_sum":165,
    "qs:localhoods":2,
    "qs:name":"Ashley Heights",
    "qs:name_adm0":"United States",
    "qs:name_adm1":"Massachusetts",
    "qs:name_adm2":"Bristol",
    "qs:name_local":"Freetown",
    "qs:photo_max":61,
    "qs:photo_sum":68,
    "qs:placetype":"Suburb",
    "qs:quad_count":3,
    "qs:woe_adm0":23424977,
    "qs:woe_adm1":2347580,
    "qs:woe_adm2":12588702,
    "qs:woe_lau":0,
    "qs:woe_local":23417598,
    "qs:woe_ver":"7.10.0",
    "wof:lang":[
        "eng"
    ],
    "wof:name":"Ashley Heights",
    "wof:placetype":"neighbourhood",
    "zs:blockids":[
        250235411002025,
        250235411002040,
        250235411002080,
        250235411002026,
        250235411002024,
        250235411002079,
        250235401021061,
        250235401021062
    ],
    "zs:housing10":0,
    "zs:pop10":0
},
  "geometry": {"coordinates":[-70.92715,41.787169],"type":"Point"}
}