{
  "type": "Feature",
  "properties": {
    "iso:country":"US",
    "name:eng_x_preferred":[
        "Mount Calvary"
    ],
    "wof:name":"Mount Calvary",
    "wof:placetype":"neighbourhood",
    "wof:population":38,
    "zs:area_m":9016412.770816,
    "zs:blockids":[
        130879707001091,
        130879707002125
    ],
    "zs:housing10":27,
    "zs:label":"Mount Calvary",
    "zs:pop10":38
},
  "geometry": {"coordinates":[-84.63414299999999,30.714068],"type":"Point"}
}