{
  "type": "Feature",
  "properties": {
    "gn:admin1_code":"OK",
    "gn:admin2_code":"55",
    "gn:asciiname":"Bloomington",
    "gn:country_code":"US",
    "gn:dem":514,
    "gn:elevation":"512.0",
    "gn:feature_class":"P",
    "gn:feature_code":"PPL",
    "gn:name":"Bloomington",
    "gn:population":0,
    "gn:timezone":"America/Chicago",
    "iso:country":"US",
    "name:bel_x_preferred":[
        "\u0411\u043b\u0443\u043c\u0456\u043d\u0433\u0442\u0430\u043d"
    ],
    "name:bul_x_preferred":[
        "\u0411\u043b\u0443\u043c\u0438\u043d\u0433\u0442\u044a\u043d"
    ],
    "name:cat_x_preferred":[
        "Bloomington"
    ],
    "name:ceb_x_preferred":[
        "Bloomington"
    ],
    "name:ces_x_preferred":[
        "Bloomington"
    ],
    "name:dan_x_preferred":[
        "Bloomington"
    ],
    "name:deu_x_preferred":[
        "Bloomington"
    ],
    "name:est_x_preferred":[
        "Bloomington"
    ],
    "name:fas_x_preferred":[
        "\u0628\u0644\u0648\u0645\u06cc\u0646\u06af\u062a\u0648\u0646"
    ],
    "name:fin_x_preferred":[
        "Bloomington"
    ],
    "name:fra_x_preferred":[
        "Bloomington"
    ],
    "name:hun_x_preferred":[
        "Bloomington"
    ],
    "name:ido_x_preferred":[
        "Bloomington"
    ],
    "name:ina_x_preferred":[
        "Bloomington"
    ],
    "name:ind_x_preferred":[
        "Bloomington"
    ],
    "name:ita_x_preferred":[
        "Bloomington"
    ],
    "name:jpn_x_preferred":[
        "\u30d6\u30eb\u30fc\u30df\u30f3\u30c8\u30f3"
    ],
    "name:kor_x_preferred":[
        "\ube14\ub8e8\ubc0d\ud134"
    ],
    "name:lav_x_preferred":[
        "Bl\u016bmingtona"
    ],
    "name:nld_x_preferred":[
        "Bloomington"
    ],
    "name:pol_x_preferred":[
        "Bloomington"
    ],
    "name:por_x_preferred":[
        "Bloomington"
    ],
    "name:rus_x_preferred":[
        "\u0411\u043b\u0443\u043c\u0438\u043d\u0433\u0442\u043e\u043d"
    ],
    "name:slk_x_preferred":[
        "Bloomington"
    ],
    "name:spa_x_preferred":[
        "Bloomington"
    ],
    "name:srp_x_preferred":[
        "\u0411\u043b\u0443\u043c\u0438\u043d\u0433\u0442\u043e\u043d"
    ],
    "name:swe_x_preferred":[
        "Bloomington"
    ],
    "name:tur_x_preferred":[
        "Bloomington"
    ],
    "name:ukr_x_preferred":[
        "\u0411\u043b\u0443\u043c\u0456\u043d\u0433\u0442\u043e\u043d"
    ],
    "name:urd_x_preferred":[
        "\u0628\u0644\u0648\u0645\u0646\u06af\u0679\u0646"
    ],
    "name:vie_x_preferred":[
        "Bloomington"
    ],
    "name:vol_x_preferred":[
        "Bloomington"
    ],
    "wof:name":"Bloomington",
    "wof:placetype":"locality"
},
  "geometry": {"coordinates":[-99.63093000000001,35.00172],"type":"Point"}
}