{
  "type": "Feature",
  "properties": {
    "gn:admin1_code":"MS",
    "gn:admin2_code":"71",
    "gn:asciiname":"Union Hall",
    "gn:country_code":"US",
    "gn:dem":131,
    "gn:elevation":"134.0",
    "gn:feature_class":"P",
    "gn:feature_code":"PPL",
    "gn:name":"Union Hall",
    "gn:population":0,
    "gn:timezone":"America/Chicago",
    "iso:country":"US",
    "name:deu_x_preferred":[
        "Union Hall"
    ],
    "name:ita_x_preferred":[
        "Union Hall"
    ],
    "wof:name":"Union Hall",
    "wof:placetype":"locality"
},
  "geometry": {"coordinates":[-89.54286,34.22455],"type":"Point"}
}