{
  "type": "Feature",
  "properties": {
    "gn:admin1_code":"OH",
    "gn:admin2_code":"41.0",
    "gn:admin3_code":"58618.0",
    "gn:asciiname":"Abbey Knoll",
    "gn:country_code":"US",
    "gn:dem":283,
    "gn:elevation":"285.0",
    "gn:feature_class":"P",
    "gn:feature_code":"PPL",
    "gn:name":"Abbey Knoll",
    "gn:population":0,
    "gn:timezone":"America/New_York",
    "iso:country":"US",
    "wof:name":"Abbey Knoll",
    "wof:placetype":"locality"
},
  "geometry": {"coordinates":[-82.98741,40.17841],"type":"Point"}
}