{
  "type": "Feature",
  "properties": {
    "gn:admin1_code":"MD",
    "gn:admin2_code":"13.0",
    "gn:asciiname":"Grafton Manor",
    "gn:country_code":"US",
    "gn:dem":206,
    "gn:elevation":"211.0",
    "gn:feature_class":"P",
    "gn:feature_code":"PPL",
    "gn:name":"Grafton Manor",
    "gn:population":0,
    "gn:timezone":"America/New_York",
    "iso:country":"US",
    "name:swe_x_preferred":[
        "Grafton Manor"
    ],
    "wof:name":"Grafton Manor",
    "wof:placetype":"locality"
},
  "geometry": {"coordinates":[-76.94386999999998,39.51121],"type":"Point"}
}