{
  "type": "Feature",
  "properties": {
    "gn:admin1_code":"KS",
    "gn:admin2_code":"57.0",
    "gn:admin3_code":"21450.0",
    "gn:asciiname":"Green Acres Trailer Park",
    "gn:country_code":"US",
    "gn:dem":756,
    "gn:elevation":"749.0",
    "gn:feature_class":"P",
    "gn:feature_code":"PPL",
    "gn:name":"Green Acres Trailer Park",
    "gn:population":0,
    "gn:timezone":"America/Chicago",
    "iso:country":"US",
    "wof:name":"Green Acres Trailer Park",
    "wof:placetype":"campus"
},
  "geometry": {"coordinates":[-99.97264,37.72918],"type":"Point"}
}