{
  "type": "Feature",
  "properties": {
    "iso:country":"US",
    "name:eng_x_preferred":[
        "West Central"
    ],
    "wd:wordcount":23,
    "wof:name":"West Central",
    "wof:placetype":"neighbourhood",
    "wof:population":3243,
    "zs:area_m":1275364.025847,
    "zs:blockids":[
        171430022002002,
        171430022001017,
        171430022001018,
        171430022002007,
        171430022002016,
        171430023002019,
        171430022005010,
        171430023002023,
        171430022003006,
        171430022003001,
        171430021003008,
        171430022005012,
        171430022005005,
        171430022003005,
        171430022003008,
        171430021003007,
        171430023003023,
        171430022002018,
        171430022002014,
        171430021002002,
        171430022002001,
        171430023003018,
        171430022002004,
        171430023002024,
        171430022002015,
        171430022005007,
        171430022003007,
        171430022003000,
        171430022002013,
        171430022002003,
        171430021003001,
        171430022002005,
        171430023003024,
        171430023003022,
        171430022002017,
        171430021003000,
        171430023003020,
        171430022002012,
        171430022005008,
        171430022003002,
        171430022002011,
        171430022005009,
        171430022005011,
        171430022001015,
        171430022001016,
        171430023003021,
        171430022002008
    ],
    "zs:housing10":1353,
    "zs:label":"West Central",
    "zs:pop10":3243
},
  "geometry": {"coordinates":[-89.60613600000001,40.721545],"type":"Point"}
}