{
  "type": "Feature",
  "properties": {
    "gn:admin1_code":"MD",
    "gn:admin2_code":"31.0",
    "gn:asciiname":"Mills Farm",
    "gn:country_code":"US",
    "gn:dem":108,
    "gn:elevation":"110.0",
    "gn:feature_class":"P",
    "gn:feature_code":"PPL",
    "gn:name":"Mills Farm",
    "gn:population":0,
    "gn:timezone":"America/New_York",
    "iso:country":"US",
    "wof:name":"Mills Farm",
    "wof:placetype":"locality"
},
  "geometry": {"coordinates":[-77.25554,39.09705],"type":"Point"}
}