{
  "type": "Feature",
  "properties": {
    "gn:admin1_code":"IL",
    "gn:admin2_code":"135.0",
    "gn:asciiname":"White Oak",
    "gn:country_code":"US",
    "gn:dem":185,
    "gn:elevation":"185.0",
    "gn:feature_class":"P",
    "gn:feature_code":"PPL",
    "gn:name":"White Oak",
    "gn:population":0,
    "gn:timezone":"America/Chicago",
    "iso:country":"US",
    "wof:name":"White Oak",
    "wof:placetype":"locality"
},
  "geometry": {"coordinates":[-89.57120999999999,39.50977],"type":"Point"}
}