{
  "type": "Feature",
  "properties": {
    "gn:admin1_code":"AK",
    "gn:admin2_code":"290.0",
    "gn:asciiname":"Deacons Landing",
    "gn:country_code":"US",
    "gn:dem":84,
    "gn:elevation":"84.0",
    "gn:feature_class":"P",
    "gn:feature_code":"PPL",
    "gn:name":"Deacons Landing",
    "gn:population":0,
    "gn:timezone":"America/Anchorage",
    "iso:country":"US",
    "name:eng_x_preferred":[
        "Deacons Landing"
    ],
    "name:und_x_variant":[
        "Deacon's Landing"
    ],
    "wof:name":"Deacons Landing",
    "wof:placetype":"locality"
},
  "geometry": {"coordinates":[-156.02028000000001,62.46917],"type":"Point"}
}