{
  "type": "Feature",
  "properties": {
    "gn:admin1_code":"LA",
    "gn:admin2_code":"33.0",
    "gn:asciiname":"Elliot Acres",
    "gn:country_code":"US",
    "gn:dem":14,
    "gn:elevation":"7.0",
    "gn:feature_class":"P",
    "gn:feature_code":"PPL",
    "gn:name":"Elliot Acres",
    "gn:population":0,
    "gn:timezone":"America/Chicago",
    "iso:country":"US",
    "wof:name":"Elliot Acres",
    "wof:placetype":"locality"
},
  "geometry": {"coordinates":[-90.99038,30.36325],"type":"Point"}
}