{
  "type": "Feature",
  "properties": {
    "gn:admin1_code":"VA",
    "gn:admin2_code":"59",
    "gn:asciiname":"Westwood Park",
    "gn:country_code":"US",
    "gn:dem":136,
    "gn:elevation":"130.0",
    "gn:feature_class":"P",
    "gn:feature_code":"PPL",
    "gn:name":"Westwood Park",
    "gn:population":0,
    "gn:timezone":"America/New_York",
    "iso:country":"US",
    "wof:name":"Westwood Park",
    "wof:placetype":"locality"
},
  "geometry": {"coordinates":[-77.20026,38.88428],"type":"Point"}
}