{
  "type": "Feature",
  "properties": {
    "gn:gn_country":"US",
    "gn:gn_fcode":"PPLX",
    "gn:gn_pop":0,
    "iso:country":"US",
    "name:ceb_x_preferred":[
        "Thomas Hill"
    ],
    "name:deu_x_preferred":[
        "Thomas Hill"
    ],
    "name:fra_x_preferred":[
        "Tom Hill"
    ],
    "name:fry_x_preferred":[
        "Thomas Hill"
    ],
    "name:ita_x_preferred":[
        "Thomas Hill"
    ],
    "name:nld_x_preferred":[
        "Thomas Hill"
    ],
    "name:pol_x_preferred":[
        "Thomas Hill"
    ],
    "qs_pg:aaroncc":"US",
    "qs_pg:gn_country":"US",
    "qs_pg:gn_fcode":"PPLX",
    "qs_pg:gn_pop":0,
    "qs_pg:name":"Thomas Hill",
    "qs_pg:name_adm0":"United States",
    "qs_pg:name_adm1":"Alabama",
    "qs_pg:photos":10,
    "qs_pg:photos_1k":2,
    "qs_pg:photos_9k":1,
    "qs_pg:photos_9r":1,
    "qs_pg:photos_all":10,
    "qs_pg:photos_sr":1,
    "qs_pg:pop_sr":0,
    "qs_pg:qs_pg_placetype":"neighbourhood",
    "qs_pg:qs_pg_placetype_gp":"Suburb",
    "qs_pg:woe_adm0":23424977,
    "woe:adm0_id":23424977,
    "woe:name_adm0":"United States",
    "woe:name_adm1":"Alabama",
    "woe:placetype":"Suburb",
    "wof:name":"Thomas Hill",
    "wof:placetype":"neighbourhood"
},
  "geometry": {"coordinates":[-86.27746999999999,33.184],"type":"Point"}
}