{
  "type": "Feature",
  "properties": {
    "gn:admin1_code":"OH",
    "gn:admin2_code":"161.0",
    "gn:admin3_code":"81676.0",
    "gn:asciiname":"Ulm's Mobile Home Court II",
    "gn:country_code":"US",
    "gn:dem":235,
    "gn:elevation":"235.0",
    "gn:feature_class":"P",
    "gn:feature_code":"PPL",
    "gn:name":"Ulm's Mobile Home Court II",
    "gn:population":0,
    "gn:timezone":"America/New_York",
    "iso:country":"US",
    "wof:name":"Ulm's Mobile Home Court II",
    "wof:placetype":"campus"
},
  "geometry": {"coordinates":[-84.34166999999999,40.83278],"type":"Point"}
}