{
  "type": "Feature",
  "properties": {
    "gn:elevation":216,
    "iso:country":"US",
    "name:bul_x_preferred":[
        "\u0411\u0440\u0435\u043d\u0442\u0443\u0434"
    ],
    "name:cat_x_preferred":[
        "Brentwood"
    ],
    "name:ceb_x_preferred":[
        "Brentwood"
    ],
    "name:cym_x_preferred":[
        "Brentwood"
    ],
    "name:deu_x_preferred":[
        "Brentwood"
    ],
    "name:eng_x_preferred":[
        "Brentwood"
    ],
    "name:fra_x_preferred":[
        "Brentwood"
    ],
    "name:ita_x_preferred":[
        "Brentwood"
    ],
    "name:kor_x_preferred":[
        "\ube0c\ub80c\ud2b8\uc6b0\ub4dc"
    ],
    "name:nld_x_preferred":[
        "Brentwood"
    ],
    "name:nor_x_preferred":[
        "Brentwood"
    ],
    "name:pol_x_preferred":[
        "Brentwood"
    ],
    "name:por_x_preferred":[
        "Brentwood"
    ],
    "name:rus_x_preferred":[
        "\u0411\u0440\u0435\u043d\u0442\u0432\u0443\u0434"
    ],
    "name:spa_x_preferred":[
        "Brentwood"
    ],
    "name:srp_x_preferred":[
        "\u0411\u0440\u0435\u043d\u0442\u0432\u0443\u0434"
    ],
    "name:swe_x_preferred":[
        "Brentwood"
    ],
    "name:ukr_x_preferred":[
        "\u0411\u0440\u0435\u043d\u0442\u0432\u0443\u0434"
    ],
    "name:urd_x_preferred":[
        "\u0628\u0631\u06cc\u0646\u0679\u0648\u0648\u0688"
    ],
    "name:vol_x_preferred":[
        "Brentwood"
    ],
    "qs:gn_adm0_cc":"US",
    "qs:gn_fcode":"PPLX",
    "qs:gn_local":4068590,
    "qs:gn_nam_loc":"Huntsville, Madison, Alabama, US",
    "qs:gn_namadm1":"AL",
    "qs:gn_name":"Brentwood",
    "qs:local_max":7422,
    "qs:local_sum":26447,
    "qs:localhoods":60,
    "qs:name":"Brentwood",
    "qs:name_adm0":"United States",
    "qs:name_adm1":"Alabama",
    "qs:name_adm2":"Madison",
    "qs:name_local":"Huntsville",
    "qs:photo_max":573,
    "qs:photo_sum":1255,
    "qs:placetype":"Suburb",
    "qs:quad_count":23,
    "qs:woe_adm0":23424977,
    "qs:woe_adm1":2347559,
    "qs:woe_adm2":12587531,
    "qs:woe_lau":0,
    "qs:woe_local":2426010,
    "qs:woe_ver":"7.10.0",
    "wof:lang":[
        "eng"
    ],
    "wof:name":"Brentwood",
    "wof:placetype":"neighbourhood"
},
  "geometry": {"coordinates":[-86.730709,34.701448],"type":"Point"}
}