{
  "type": "Feature",
  "properties": {
    "iso:country":"US",
    "name:eng_x_preferred":[
        "Wech Corners"
    ],
    "wof:name":"Wech Corners",
    "wof:placetype":"neighbourhood",
    "wof:population":1797,
    "zs:area_m":7850649.022322,
    "zs:blockids":[
        420792155021018,
        420792155021051,
        420792155021001,
        420792155011032,
        420792155011035,
        420792155011049,
        420792155021049,
        420792155032006,
        420792155032001,
        420792155021006,
        420792155021017,
        420792155021002,
        420792155021004,
        420792155021007,
        420792155032008,
        420792155021015,
        420792155021008,
        420792155032005,
        420792155011033,
        420792155021016,
        420792155021050,
        420792155021048,
        420792155021003,
        420792155021000,
        420792155032002,
        420792155032009,
        420792155032003,
        420792155021034,
        420792155021012,
        420792155021005,
        420792155032004,
        420792155032007,
        420792155021033
    ],
    "zs:housing10":670,
    "zs:label":"Wech Corners",
    "zs:pop10":1797
},
  "geometry": {"coordinates":[-75.904211,41.151375],"type":"Point"}
}