{
  "type": "Feature",
  "properties": {
    "gn:admin1_code":"ND",
    "gn:admin2_code":"21.0",
    "gn:admin3_code":"42340.0",
    "gn:asciiname":"Maple River Colony",
    "gn:country_code":"US",
    "gn:dem":433,
    "gn:elevation":"433.0",
    "gn:feature_class":"P",
    "gn:feature_code":"PPL",
    "gn:name":"Maple River Colony",
    "gn:population":0,
    "gn:timezone":"America/Chicago",
    "iso:country":"US",
    "wof:name":"Maple River Colony",
    "wof:placetype":"locality"
},
  "geometry": {"coordinates":[-98.4405,46.07272],"type":"Point"}
}