{
  "type": "Feature",
  "properties": {
    "gn:admin1_code":"IN",
    "gn:admin2_code":"125.0",
    "gn:admin3_code":"80936.0",
    "gn:asciiname":"Alford",
    "gn:country_code":"US",
    "gn:dem":157,
    "gn:elevation":"158.0",
    "gn:feature_class":"P",
    "gn:feature_code":"PPL",
    "gn:name":"Alford",
    "gn:population":0,
    "gn:timezone":"America/Indiana/Petersburg",
    "iso:country":"US",
    "name:eng_x_preferred":[
        "Alford"
    ],
    "name:und_x_variant":[
        "Alfords"
    ],
    "wof:name":"Alford",
    "wof:placetype":"locality"
},
  "geometry": {"coordinates":[-87.24279,38.49144],"type":"Point"}
}