{
  "type": "Feature",
  "properties": {
    "gn:admin1_code":"SC",
    "gn:admin2_code":"51.0",
    "gn:asciiname":"Oakey Bay",
    "gn:country_code":"US",
    "gn:dem":6,
    "gn:elevation":"10.0",
    "gn:feature_class":"P",
    "gn:feature_code":"PPL",
    "gn:name":"Oakey Bay",
    "gn:population":0,
    "gn:timezone":"America/New_York",
    "iso:country":"US",
    "wof:name":"Oakey Bay",
    "wof:placetype":"locality"
},
  "geometry": {"coordinates":[-79.1331,33.84378],"type":"Point"}
}