{
  "type": "Feature",
  "properties": {
    "iso:country":"US",
    "name:eng_x_preferred":[
        "Huntington Ridge"
    ],
    "name:eng_x_variant":[
        "Huntington Rdg"
    ],
    "qs:gn_adm0_cc":"US",
    "qs:gn_local":4900080,
    "qs:gn_nam_loc":"Lisle, DuPage, Illinois, US",
    "qs:gn_namadm1":"IL",
    "qs:local_max":5310,
    "qs:local_sum":7766,
    "qs:localhoods":5,
    "qs:name":"Huntington Ridge",
    "qs:name_adm0":"United States",
    "qs:name_adm1":"Illinois",
    "qs:name_adm2":"Dupage",
    "qs:name_local":"Lisle",
    "qs:photo_max":11,
    "qs:photo_sum":15,
    "qs:placetype":"Suburb",
    "qs:quad_count":5,
    "qs:woe_adm0":23424977,
    "qs:woe_adm1":2347572,
    "qs:woe_adm2":12588099,
    "qs:woe_funk":"Parented by a neighborhood",
    "qs:woe_lau":0,
    "qs:woe_local":2440013,
    "qs:woe_ver":"7.10.0",
    "wof:lang":[
        "eng"
    ],
    "wof:name":"Huntington Ridge",
    "wof:placetype":"neighbourhood",
    "wof:population":5056,
    "zs:blockids":[
        170438463042028,
        170438463044019,
        170438463042009,
        170438463133020,
        170438463042011,
        170438463131037,
        170438463042015,
        170438463041004,
        170438463041006,
        170438463042027,
        170438463044025,
        170438463133017,
        170438463045009,
        170438463132015,
        170438463045003,
        170438463044022,
        170438463045005,
        170438463045010,
        170438463044024,
        170438463133027,
        170438463133026,
        170438463044023,
        170438463131019,
        170438463042013,
        170438463132001,
        170438463045000,
        170438463045006,
        170438462022007,
        170438463133022,
        170438463044012,
        170438462022013,
        170438463132013,
        170438463133018,
        170438463044021,
        170438463133025,
        170438463132018,
        170438463044009,
        170438462022006,
        170438463044027,
        170438463041003,
        170438463045001,
        170438463042012,
        170438463042014,
        170438463041000,
        170438463044010,
        170438463133007,
        170438463133024,
        170438463132014,
        170438463132016,
        170438463133019,
        170438463044015,
        170438463044017,
        170438463045004,
        170438463045002,
        170438463041005,
        170438463042010,
        170438463041008,
        170438463132019,
        170438463133021,
        170438463133023,
        170438463044020,
        170438463133015,
        170438462022014,
        170438462022011,
        170438463044018,
        170438463041001,
        170438463041002,
        170438463131039
    ],
    "zs:housing10":1740,
    "zs:pop10":5056
},
  "geometry": {"coordinates":[-88.091492,41.756971],"type":"Point"}
}