{
  "type": "Feature",
  "properties": {
    "iso:country":"US",
    "name:eng_x_preferred":[
        "Blanchardville"
    ],
    "wof:name":"Blanchardville",
    "wof:placetype":"neighbourhood",
    "wof:population":712,
    "zs:area_m":2879904.940418,
    "zs:blockids":[
        250138101001041,
        250138101001051,
        250138101001044,
        250138101001039,
        250138101001042,
        250138101001045,
        250138101001046,
        250138101001043,
        250138101001047,
        250138101001053,
        250138101001055,
        250138101001040
    ],
    "zs:housing10":248,
    "zs:label":"Blanchardville",
    "zs:pop10":712
},
  "geometry": {"coordinates":[-72.289598,42.152521],"type":"Point"}
}