{
  "type": "Feature",
  "properties": {
    "iso:country":"US",
    "name:eng_x_preferred":[
        "Central Hialeah"
    ],
    "wof:name":"Central Hialeah",
    "wof:placetype":"neighbourhood",
    "wof:population":3294,
    "zs:area_m":778621.826447,
    "zs:blockids":[
        120860007084002,
        120860093112007,
        120860093112029,
        120860093112020,
        120860007084016,
        120860007071005,
        120860093112028,
        120860093112023,
        120860007084014,
        120860007084015,
        120860007084017,
        120860093112016,
        120860093112025,
        120860007084001,
        120860007071000,
        120860007071004,
        120860007071008,
        120860093112022,
        120860007071007,
        120860093114015,
        120860007071001,
        120860007071006,
        120860093112019,
        120860093112024,
        120860007084000,
        120860007071009,
        120860093112017,
        120860093112010,
        120860093112015,
        120860093112018,
        120860093112021,
        120860093112027
    ],
    "zs:housing10":1136,
    "zs:label":"Central Hialeah",
    "zs:pop10":3294
},
  "geometry": {"coordinates":[-80.301304,25.870034],"type":"Point"}
}