{
  "type": "Feature",
  "properties": {
    "gn:admin1_code":"MD",
    "gn:admin2_code":"17.0",
    "gn:asciiname":"Pomfret Estates",
    "gn:country_code":"US",
    "gn:dem":58,
    "gn:elevation":"58.0",
    "gn:feature_class":"P",
    "gn:feature_code":"PPL",
    "gn:name":"Pomfret Estates",
    "gn:population":0,
    "gn:timezone":"America/New_York",
    "iso:country":"US",
    "wof:name":"Pomfret Estates",
    "wof:placetype":"locality"
},
  "geometry": {"coordinates":[-77.03303000000002,38.57512],"type":"Point"}
}