{
  "type": "Feature",
  "properties": {
    "gn:admin1_code":"PA",
    "gn:admin2_code":"63.0",
    "gn:admin3_code":"11120.0",
    "gn:asciiname":"Enterprise",
    "gn:country_code":"US",
    "gn:dem":412,
    "gn:elevation":"399.0",
    "gn:feature_class":"P",
    "gn:feature_code":"PPL",
    "gn:name":"Enterprise",
    "gn:population":0,
    "gn:timezone":"America/New_York",
    "iso:country":"US",
    "name:bul_x_preferred":[
        "\u0415\u043d\u0442\u044a\u0440\u043f\u0440\u0430\u0439\u0437"
    ],
    "name:cat_x_preferred":[
        "Enterprise"
    ],
    "name:ceb_x_preferred":[
        "Enterprise"
    ],
    "name:ces_x_preferred":[
        "Enterprise"
    ],
    "name:dan_x_preferred":[
        "Enterprise"
    ],
    "name:deu_x_preferred":[
        "Enterprise"
    ],
    "name:est_x_preferred":[
        "Enterprise"
    ],
    "name:fas_x_preferred":[
        "\u0633\u0627\u0632\u0645\u0627\u0646\u06cc"
    ],
    "name:fin_x_preferred":[
        "Enterprise"
    ],
    "name:fra_x_preferred":[
        "Enterprise"
    ],
    "name:heb_x_preferred":[
        "\u05d0\u05e0\u05d8\u05e8\u05e4\u05e8\u05d9\u05d9\u05e1"
    ],
    "name:heb_x_variant":[
        "\u05d0\u05e0\u05d8\u05e8\u05e4\u05e8\u05d9\u05d9\u05d6"
    ],
    "name:hrv_x_preferred":[
        "Enterprise"
    ],
    "name:hun_x_preferred":[
        "Enterprise"
    ],
    "name:ind_x_preferred":[
        "Enterprise"
    ],
    "name:ita_x_preferred":[
        "Enterprise"
    ],
    "name:jpn_x_preferred":[
        "\u30a8\u30f3\u30bf\u30fc\u30d7\u30e9\u30a4\u30ba"
    ],
    "name:kaz_x_preferred":[
        "\u041c\u0435\u043a\u0435\u043c\u0435"
    ],
    "name:kor_x_preferred":[
        "\uc5d4\ud130\ud504\ub77c\uc774\uc988"
    ],
    "name:nld_x_preferred":[
        "Enterprise"
    ],
    "name:nor_x_preferred":[
        "Enterprise"
    ],
    "name:pol_x_preferred":[
        "Enterprise"
    ],
    "name:por_x_preferred":[
        "Enterprise"
    ],
    "name:rus_x_preferred":[
        "\u042d\u043d\u0442\u0435\u0440\u043f\u0440\u0430\u0439\u0437"
    ],
    "name:slk_x_preferred":[
        "Enterprise"
    ],
    "name:slv_x_preferred":[
        "Enterprise"
    ],
    "name:spa_x_preferred":[
        "Enterprise"
    ],
    "name:sqi_x_preferred":[
        "Nd\u00ebrmarrje"
    ],
    "name:srp_x_preferred":[
        "\u0415\u043d\u0442\u0435\u0440\u043f\u0440\u0430\u0458\u0437"
    ],
    "name:swe_x_preferred":[
        "Enterprise"
    ],
    "name:ukr_x_preferred":[
        "\u0415\u043d\u0442\u0435\u0440\u043f\u0440\u0430\u0439\u0437"
    ],
    "name:vol_x_preferred":[
        "Enterprise"
    ],
    "name:zho_x_preferred":[
        "Enterprise"
    ],
    "wof:name":"Enterprise",
    "wof:placetype":"locality"
},
  "geometry": {"coordinates":[-78.96364,40.8284],"type":"Point"}
}