{
  "type": "Feature",
  "properties": {
    "iso:country":"US",
    "name:eng_x_preferred":[
        "Prosperity Acres"
    ],
    "wof:name":"Prosperity Acres",
    "wof:placetype":"neighbourhood",
    "wof:population":345,
    "zs:area_m":14678312.051995,
    "zs:blockids":[
        480410001021049,
        480410020023001,
        480410020023008
    ],
    "zs:housing10":130,
    "zs:label":"Prosperity Acres",
    "zs:pop10":345
},
  "geometry": {"coordinates":[-96.23568899999999,30.642894],"type":"Point"}
}