{
  "type": "Feature",
  "properties": {
    "gn:admin1_code":"FL",
    "gn:admin2_code":"127.0",
    "gn:asciiname":"Country Village Mobile Home Park",
    "gn:country_code":"US",
    "gn:dem":22,
    "gn:elevation":"15.0",
    "gn:feature_class":"P",
    "gn:feature_code":"PPL",
    "gn:name":"Country Village Mobile Home Park",
    "gn:population":0,
    "gn:timezone":"America/New_York",
    "iso:country":"US",
    "wof:name":"Country Village Mobile Home Park",
    "wof:placetype":"campus"
},
  "geometry": {"coordinates":[-81.2701,28.93827000000001],"type":"Point"}
}