{
  "type": "Feature",
  "properties": {
    "gn:admin1_code":"IN",
    "gn:admin2_code":"3.0",
    "gn:admin3_code":"298.0",
    "gn:asciiname":"Fairfax",
    "gn:country_code":"US",
    "gn:dem":240,
    "gn:elevation":"238.0",
    "gn:feature_class":"P",
    "gn:feature_code":"PPL",
    "gn:name":"Fairfax",
    "gn:population":0,
    "gn:timezone":"America/Indiana/Indianapolis",
    "iso:country":"US",
    "name:cat_x_preferred":[
        "Fairfax"
    ],
    "name:ceb_x_preferred":[
        "Fairfax"
    ],
    "name:deu_x_preferred":[
        "Fairfax"
    ],
    "name:fin_x_preferred":[
        "Fairfax"
    ],
    "name:fra_x_preferred":[
        "Fairfax"
    ],
    "name:hun_x_preferred":[
        "Fairfax"
    ],
    "name:ido_x_preferred":[
        "Fairfax"
    ],
    "name:ita_x_preferred":[
        "Fairfax"
    ],
    "name:kor_x_preferred":[
        "\ud398\uc5b4\ud329\uc2a4"
    ],
    "name:nld_x_preferred":[
        "Fairfax"
    ],
    "name:pol_x_preferred":[
        "Fairfax"
    ],
    "name:por_x_preferred":[
        "Fairfax"
    ],
    "name:rus_x_preferred":[
        "\u0424\u044d\u0440\u0444\u0430\u043a\u0441"
    ],
    "name:spa_x_preferred":[
        "Fairfax"
    ],
    "name:srp_x_preferred":[
        "\u0424\u0435\u0440\u0444\u0430\u043a\u0441"
    ],
    "name:swe_x_preferred":[
        "Fairfax"
    ],
    "name:ukr_x_preferred":[
        "\u0424\u0435\u0439\u0440\u0444\u0430\u043a\u0441"
    ],
    "name:vol_x_preferred":[
        "Fairfax"
    ],
    "wof:name":"Fairfax",
    "wof:placetype":"locality"
},
  "geometry": {"coordinates":[-85.0883,41.04199000000001],"type":"Point"}
}