{
  "type": "Feature",
  "properties": {
    "gn:admin1_code":"NM",
    "gn:admin2_code":"47",
    "gn:asciiname":"Douthit Place",
    "gn:country_code":"US",
    "gn:dem":2102,
    "gn:elevation":"2103.0",
    "gn:feature_class":"P",
    "gn:feature_code":"PPL",
    "gn:name":"Douthit Place",
    "gn:population":0,
    "gn:timezone":"America/Denver",
    "iso:country":"US",
    "wof:name":"Douthit Place",
    "wof:placetype":"locality"
},
  "geometry": {"coordinates":[-105.65835,35.26393],"type":"Point"}
}