{
  "type": "Feature",
  "properties": {
    "gn:admin1_code":"NC",
    "gn:admin2_code":"169",
    "gn:admin3_code":"92028.0",
    "gn:asciiname":"Brook Cove",
    "gn:country_code":"US",
    "gn:dem":200,
    "gn:elevation":"202.0",
    "gn:feature_class":"P",
    "gn:feature_code":"PPL",
    "gn:name":"Brook Cove",
    "gn:population":0,
    "gn:timezone":"America/New_York",
    "iso:country":"US",
    "wof:name":"Brook Cove",
    "wof:placetype":"locality"
},
  "geometry": {"coordinates":[-80.18949000000001,36.28653],"type":"Point"}
}