{
  "type": "Feature",
  "properties": {
    "gn:admin1_code":"AL",
    "gn:admin2_code":"15.0",
    "gn:asciiname":"Allsop",
    "gn:country_code":"US",
    "gn:dem":206,
    "gn:elevation":"205.0",
    "gn:feature_class":"P",
    "gn:feature_code":"PPL",
    "gn:name":"Allsop",
    "gn:population":0,
    "gn:timezone":"America/Chicago",
    "iso:country":"US",
    "name:eng_x_preferred":[
        "Allsop"
    ],
    "name:und_x_variant":[
        "Allsup"
    ],
    "wof:name":"Allsop",
    "wof:placetype":"locality"
},
  "geometry": {"coordinates":[-85.71635000000001,33.94121],"type":"Point"}
}