{
  "type": "Feature",
  "properties": {
    "gn:admin1_code":"MD",
    "gn:admin2_code":"13.0",
    "gn:asciiname":"Daniel",
    "gn:country_code":"US",
    "gn:dem":234,
    "gn:elevation":"237.0",
    "gn:feature_class":"P",
    "gn:feature_code":"PPL",
    "gn:name":"Daniel",
    "gn:population":0,
    "gn:timezone":"America/New_York",
    "iso:country":"US",
    "name:ara_x_preferred":[
        "\u062f\u0627\u0646\u064a\u064a\u0644"
    ],
    "name:aze_x_preferred":[
        "Daniel"
    ],
    "name:bre_x_preferred":[
        "Daniel"
    ],
    "name:ces_x_preferred":[
        "Daniel"
    ],
    "name:dan_x_preferred":[
        "Daniel"
    ],
    "name:deu_x_preferred":[
        "Daniel"
    ],
    "name:eng_x_preferred":[
        "Daniel"
    ],
    "name:epo_x_preferred":[
        "Danielo"
    ],
    "name:est_x_preferred":[
        "Daniel"
    ],
    "name:fin_x_preferred":[
        "Daniel"
    ],
    "name:fra_x_preferred":[
        "Daniel"
    ],
    "name:hye_x_preferred":[
        "\u0534\u0561\u0576\u056b\u0565\u056c"
    ],
    "name:isl_x_preferred":[
        "Daniel"
    ],
    "name:kat_x_preferred":[
        "\u10d3\u10d0\u10dc\u10d8\u10d4\u10da\u10d8"
    ],
    "name:lat_x_preferred":[
        "Daniel"
    ],
    "name:nld_x_preferred":[
        "Daniel"
    ],
    "name:nno_x_preferred":[
        "Daniel"
    ],
    "name:nor_x_preferred":[
        "Daniel"
    ],
    "name:pol_x_preferred":[
        "Daniel"
    ],
    "name:ron_x_preferred":[
        "Daniel"
    ],
    "name:rus_x_preferred":[
        "\u0414\u0430\u043d\u0438\u0435\u043b"
    ],
    "name:sin_x_preferred":[
        "\u0daf\u0dcf\u0db1\u0dd2\u0dba\u0dd9\u0dbd\u0dca"
    ],
    "name:slk_x_preferred":[
        "Daniel"
    ],
    "name:slv_x_preferred":[
        "Daniel"
    ],
    "name:spa_x_preferred":[
        "Daniel"
    ],
    "name:swe_x_preferred":[
        "Daniel"
    ],
    "name:ukr_x_preferred":[
        "\u0414\u0430\u043d\u0456\u0435\u043b"
    ],
    "name:und_x_variant":[
        "Defiance",
        "Dog Town",
        "Braddock Manor"
    ],
    "name:zho_x_preferred":[
        "\u4e39\u5c3c\u5c14"
    ],
    "wof:name":"Daniel",
    "wof:placetype":"locality"
},
  "geometry": {"coordinates":[-77.05359,39.4351],"type":"Point"}
}