{
  "type": "Feature",
  "properties": {
    "gn:admin1_code":"MO",
    "gn:admin2_code":"127.0",
    "gn:admin3_code":"77074.0",
    "gn:asciiname":"Sharpsburg",
    "gn:country_code":"US",
    "gn:dem":208,
    "gn:elevation":"209.0",
    "gn:feature_class":"P",
    "gn:feature_code":"PPL",
    "gn:name":"Sharpsburg",
    "gn:population":0,
    "gn:timezone":"America/Chicago",
    "iso:country":"US",
    "name:cat_x_preferred":[
        "Sharpsburg"
    ],
    "name:ceb_x_preferred":[
        "Sharpsburg"
    ],
    "name:deu_x_preferred":[
        "Sharpsburg"
    ],
    "name:fra_x_preferred":[
        "Sharpsburg"
    ],
    "name:ita_x_preferred":[
        "Sharpsburg"
    ],
    "name:nld_x_preferred":[
        "Sharpsburg"
    ],
    "name:pol_x_preferred":[
        "Sharpsburg"
    ],
    "name:srp_x_preferred":[
        "\u0428\u0430\u0440\u043f\u0441\u0431\u0443\u0440\u0433"
    ],
    "name:tur_x_preferred":[
        "Sharpsburg"
    ],
    "name:vol_x_preferred":[
        "Sharpsburg"
    ],
    "wof:name":"Sharpsburg",
    "wof:placetype":"locality"
},
  "geometry": {"coordinates":[-91.76237999999999,39.68699],"type":"Point"}
}