{
  "type": "Feature",
  "properties": {
    "gn:elevation":6,
    "iso:country":"US",
    "name:eng_x_preferred":[
        "Chadwick Beach"
    ],
    "name:eng_x_variant":[
        "Chadwick Bch"
    ],
    "qs:gn_adm0_cc":"US",
    "qs:gn_fcode":"PPL",
    "qs:gn_local":4504476,
    "qs:gn_nam_loc":"Toms River, Ocean, New Jersey, US",
    "qs:gn_namadm1":"NJ",
    "qs:gn_name":"Chadwick Beach",
    "qs:local_max":626,
    "qs:local_sum":2479,
    "qs:localhoods":17,
    "qs:name":"Chadwick Beach",
    "qs:name_adm0":"United States",
    "qs:name_adm1":"New Jersey",
    "qs:name_adm2":"Ocean",
    "qs:name_local":"Toms River",
    "qs:photo_max":195,
    "qs:photo_sum":626,
    "qs:placetype":"Suburb",
    "qs:quad_count":18,
    "qs:woe_adm0":23424977,
    "qs:woe_adm1":2347589,
    "qs:woe_adm2":12589272,
    "qs:woe_lau":0,
    "qs:woe_local":2507064,
    "qs:woe_ver":"7.10.0",
    "wof:lang":[
        "eng"
    ],
    "wof:name":"Chadwick Beach",
    "wof:placetype":"neighbourhood",
    "wof:population":701,
    "zs:blockids":[
        340297225003056,
        340297270011010,
        340297270011042,
        340297270011001,
        340297225003046,
        340297270011031,
        340297270011008,
        340297270011045,
        340297270011059,
        340297270011032,
        340297270011023,
        340297225003085,
        340297225003050,
        340297270011047,
        340297225003052,
        340297270011028,
        340297225003058,
        340297270011058,
        340297270011016,
        340297225003055,
        340297225003049,
        340297225003044,
        340297225003041,
        340297225003084,
        340297270011044,
        340297225003086,
        340297225003057,
        340297270011051,
        340297270011038,
        340297270011040,
        340297270011050,
        340297270011037,
        340297270011007,
        340297270011026,
        340297270011054,
        340297225003083,
        340297225003045,
        340297270011049,
        340297270011002,
        340297270011035,
        340297225003047,
        340297270011046,
        340297225003054,
        340297225003053,
        340297225003059,
        340297270011017,
        340297225003042,
        340297225003043,
        340297225003051,
        340297270011003,
        340297270011033,
        340297270011039,
        340297270011052,
        340297270011018,
        340297270011014,
        340297270011057,
        340297270011048,
        340297270011030,
        340297270011000,
        340297270011036,
        340297270011029,
        340297225003048,
        340297270011056,
        340297270011053,
        340297270011013,
        340297270011041,
        340297270011009,
        340297270011034,
        340297270011065,
        340297270011022,
        340297270011043,
        340297270011060,
        340297270011019,
        340297270011055
    ],
    "zs:housing10":1722,
    "zs:pop10":701
},
  "geometry": {"coordinates":[-74.066378,39.978041],"type":"Point"}
}