{
  "type": "Feature",
  "properties": {
    "iso:country":"US",
    "wof:name":"Indianola Forest",
    "wof:placetype":"neighbourhood"
},
  "geometry": {"coordinates":[-83.00579581551631,40.00551644808069],"type":"Point"}
}