{
  "type": "Feature",
  "properties": {
    "gn:country":"US",
    "gn:fcode":"PPLX",
    "gn:population":0,
    "iso:country":"US",
    "name:ara_x_preferred":[
        "\u062a\u0648\u0645\u0627\u0633 \u0648\u0648\u062f\u0633"
    ],
    "name:ces_x_preferred":[
        "Thomas Woods"
    ],
    "name:fas_x_preferred":[
        "\u062a\u0627\u0645\u0633 \u0648\u0648\u062f\u0632"
    ],
    "name:fra_x_preferred":[
        "Thomas Woods"
    ],
    "name:ita_x_preferred":[
        "Thomas Woods"
    ],
    "name:pol_x_preferred":[
        "Thomas Woods"
    ],
    "name:por_x_preferred":[
        "Thomas Woods"
    ],
    "name:spa_x_preferred":[
        "Thomas Woods"
    ],
    "name:swe_x_preferred":[
        "Thomas Woods"
    ],
    "name:zho_x_preferred":[
        "\u6258\u9a6c\u65af\u00b7\u4f0d\u5179"
    ],
    "qs_pg:aaroncc":"US",
    "qs_pg:gn_country":"US",
    "qs_pg:gn_fcode":"PPLX",
    "qs_pg:gn_pop":0,
    "qs_pg:name":"Thomas Woods",
    "qs_pg:name_adm0":"United States",
    "qs_pg:name_adm1":"North Carolina",
    "qs_pg:photos":2886,
    "qs_pg:photos_1k":585,
    "qs_pg:photos_9k":13,
    "qs_pg:photos_9r":11,
    "qs_pg:photos_all":2886,
    "qs_pg:photos_sr":19,
    "qs_pg:pop_sr":0,
    "qs_pg:qs_pg_placetype":"neighbourhood",
    "qs_pg:qs_pg_placetype_gp":"Suburb",
    "qs_pg:woe_adm0":23424977,
    "woe:adm0_id":23424977,
    "woe:name_adm0":"United States",
    "woe:name_adm1":"North Carolina",
    "woe:placetype":"Suburb",
    "wof:name":"Thomas Woods",
    "wof:placetype":"neighbourhood"
},
  "geometry": {"coordinates":[-82.67485000000001,35.25067],"type":"Point"}
}