{
  "type": "Feature",
  "properties": {
    "gn:admin1_code":"AL",
    "gn:admin2_code":"7",
    "gn:asciiname":"Lucille",
    "gn:country_code":"US",
    "gn:dem":148,
    "gn:elevation":"143.0",
    "gn:feature_class":"P",
    "gn:feature_code":"PPL",
    "gn:name":"Lucille",
    "gn:population":0,
    "gn:timezone":"America/Chicago",
    "iso:country":"US",
    "name:cat_x_preferred":[
        "Lucille"
    ],
    "name:fra_x_preferred":[
        "Lucille"
    ],
    "name:ita_x_preferred":[
        "Lucille"
    ],
    "name:jpn_x_preferred":[
        "\u30eb\u30b7\u30fc\u30eb"
    ],
    "name:rus_x_preferred":[
        "\u041b\u044e\u0441\u0438\u043b\u044c"
    ],
    "wof:name":"Lucille",
    "wof:placetype":"locality"
},
  "geometry": {"coordinates":[-87.14749999999999,33.08845],"type":"Point"}
}