{
  "type": "Feature",
  "properties": {
    "iso:country":"US",
    "name:eng_x_preferred":[
        "Williamsburgh"
    ],
    "wd:wordcount":80,
    "wof:name":"Williamsburgh",
    "wof:placetype":"neighbourhood",
    "wof:population":2266,
    "zs:area_m":1606623.598608,
    "zs:blockids":[
        490351147001052,
        490351147002013,
        490351003081000,
        490351003082006,
        490351003082005,
        490351147001049,
        490351147001054,
        490351147002010,
        490351147001067,
        490351147001048,
        490351147001066,
        490351147002000,
        490351147002012,
        490351147002015,
        490351147002014,
        490351147002011,
        490351147001051,
        490351147001050,
        490351147002009,
        490351147002005,
        490351147002016
    ],
    "zs:housing10":840,
    "zs:label":"Williamsburgh",
    "zs:pop10":2266
},
  "geometry": {"coordinates":[-111.935401,40.801845],"type":"Point"}
}