{
  "type": "Feature",
  "properties": {
    "gn:admin1_code":"MA",
    "gn:admin2_code":"27.0",
    "gn:admin3_code":"53225.0",
    "gn:asciiname":"Goulding Village",
    "gn:country_code":"US",
    "gn:dem":334,
    "gn:elevation":"329.0",
    "gn:feature_class":"P",
    "gn:feature_code":"PPL",
    "gn:name":"Goulding Village",
    "gn:population":0,
    "gn:timezone":"America/New_York",
    "iso:country":"US",
    "name:eng_x_preferred":[
        "Goulding Village"
    ],
    "name:und_x_variant":[
        "East Phillipston"
    ],
    "wof:name":"Goulding Village",
    "wof:placetype":"locality"
},
  "geometry": {"coordinates":[-72.10980000000001,42.54176],"type":"Point"}
}