{
  "type": "Feature",
  "properties": {
    "iso:country":"US",
    "name:eng_x_preferred":[
        "Pelican's Nest"
    ],
    "wof:name":"Pelican's Nest",
    "wof:placetype":"neighbourhood",
    "wof:population":521,
    "zs:area_m":1245394.380609,
    "zs:blockids":[
        120710503142052,
        120710503051001,
        120710503142048,
        120710503143033,
        120710503143031,
        120710503142037,
        120710503142034,
        120710503142035,
        120710503142036,
        120710503142039,
        120710503142038,
        120710503051002,
        120710503142033,
        120710503051095,
        120710503143032,
        120710503142041,
        120710503142049,
        120710503051096,
        120710503142040,
        120710503051008
    ],
    "zs:housing10":481,
    "zs:label":"Pelican's Nest",
    "zs:pop10":521
},
  "geometry": {"coordinates":[-81.829052,26.377429],"type":"Point"}
}