{
  "type": "Feature",
  "properties": {
    "gn:admin1_code":"KY",
    "gn:admin2_code":"63",
    "gn:asciiname":"Sarah",
    "gn:country_code":"US",
    "gn:dem":239,
    "gn:elevation":"232.0",
    "gn:feature_class":"P",
    "gn:feature_code":"PPL",
    "gn:name":"Sarah",
    "gn:population":0,
    "gn:timezone":"America/New_York",
    "iso:country":"US",
    "wof:name":"Sarah",
    "wof:placetype":"locality"
},
  "geometry": {"coordinates":[-82.96044000000001,38.06203],"type":"Point"}
}