{
  "type": "Feature",
  "properties": {
    "gn:admin1_code":"IA",
    "gn:admin2_code":"167.0",
    "gn:admin3_code":"94653.0",
    "gn:asciiname":"Westbrook Village",
    "gn:country_code":"US",
    "gn:dem":434,
    "gn:elevation":"435.0",
    "gn:feature_class":"P",
    "gn:feature_code":"PPL",
    "gn:name":"Westbrook Village",
    "gn:population":0,
    "gn:timezone":"America/Chicago",
    "iso:country":"US",
    "wof:name":"Westbrook Village",
    "wof:placetype":"locality"
},
  "geometry": {"coordinates":[-96.18501999999999,43.08332],"type":"Point"}
}