{
  "type": "Feature",
  "properties": {
    "gn:admin1_code":"MD",
    "gn:admin2_code":"15.0",
    "gn:asciiname":"Chesapeake Cove",
    "gn:country_code":"US",
    "gn:dem":24,
    "gn:elevation":"19.0",
    "gn:feature_class":"P",
    "gn:feature_code":"PPL",
    "gn:name":"Chesapeake Cove",
    "gn:population":0,
    "gn:timezone":"America/New_York",
    "iso:country":"US",
    "wof:name":"Chesapeake Cove",
    "wof:placetype":"locality"
},
  "geometry": {"coordinates":[-75.85883000000003,39.5765],"type":"Point"}
}