{
  "type": "Feature",
  "properties": {
    "gn:admin1_code":"SC",
    "gn:admin2_code":"41.0",
    "gn:asciiname":"Quinby Forest",
    "gn:country_code":"US",
    "gn:dem":45,
    "gn:elevation":"39.0",
    "gn:feature_class":"P",
    "gn:feature_code":"PPL",
    "gn:name":"Quinby Forest",
    "gn:population":0,
    "gn:timezone":"America/New_York",
    "iso:country":"US",
    "wof:name":"Quinby Forest",
    "wof:placetype":"locality"
},
  "geometry": {"coordinates":[-79.72951,34.22682],"type":"Point"}
}