{
  "type": "Feature",
  "properties": {
    "gn:admin1_code":"OH",
    "gn:admin2_code":"87",
    "gn:admin3_code":"81396.0",
    "gn:asciiname":"Olive Furnace",
    "gn:country_code":"US",
    "gn:dem":208,
    "gn:elevation":"206.0",
    "gn:feature_class":"P",
    "gn:feature_code":"PPL",
    "gn:name":"Olive Furnace",
    "gn:population":0,
    "gn:timezone":"America/New_York",
    "iso:country":"US",
    "name:eng_x_preferred":[
        "Olive Furnace"
    ],
    "name:und_x_variant":[
        "Olive"
    ],
    "wof:name":"Olive Furnace",
    "wof:placetype":"locality"
},
  "geometry": {"coordinates":[-82.62989,38.76174],"type":"Point"}
}