{
  "type": "Feature",
  "properties": {
    "gn:admin1_code":"IN",
    "gn:admin2_code":"057",
    "gn:admin3_code":"17488.0",
    "gn:asciiname":"Forest Ridge",
    "gn:country_code":"US",
    "gn:dem":251,
    "gn:elevation":"250.0",
    "gn:feature_class":"P",
    "gn:feature_code":"PPL",
    "gn:name":"Forest Ridge",
    "gn:population":0,
    "gn:timezone":"America/Indiana/Indianapolis",
    "iso:country":"US",
    "wof:name":"Forest Ridge",
    "wof:placetype":"locality"
},
  "geometry": {"coordinates":[-86.00305999999998,39.94028],"type":"Point"}
}