{
  "type": "Feature",
  "properties": {
    "iso:country":"US",
    "name:eng_x_preferred":[
        "North Monroeville"
    ],
    "wof:name":"North Monroeville",
    "wof:placetype":"neighbourhood",
    "wof:population":306,
    "zs:area_m":20726816.379806,
    "zs:blockids":[
        390430418002077,
        390430418002075,
        390430418003024,
        390430418002071,
        390430418002074,
        390430418003023,
        390430418003033,
        390430418002073,
        390430418002042,
        390430418002079,
        390430418003018,
        390430418003037,
        390430418002070,
        390430418002078,
        390430418001068,
        390430418003031,
        390430418002043,
        390430418003039,
        390430418003019,
        390430418001061,
        390430418002082,
        390430418003017,
        390430418003016,
        390430418003034,
        390430418003035,
        390430418002085,
        390430418003036,
        390430418002047,
        390430418002069,
        390430418002083,
        390430418002072,
        390430418003032
    ],
    "zs:housing10":125,
    "zs:label":"North Monroeville",
    "zs:pop10":306
},
  "geometry": {"coordinates":[-82.746931,41.320283],"type":"Point"}
}