{
  "type": "Feature",
  "properties": {
    "gn:elevation":136,
    "iso:country":"US",
    "name:arz_x_preferred":[
        "\u0645\u0637\u0627\u0631 \u0645\u0648\u0644\u0648\u0643\u0627\u0649"
    ],
    "name:ceb_x_preferred":[
        "Molokai Airport"
    ],
    "name:deu_x_preferred":[
        "Molokai Airport"
    ],
    "name:eng_x_preferred":[
        "Molokai Airport"
    ],
    "name:eng_x_variant":[
        "MKK",
        "PHMK"
    ],
    "name:fas_x_preferred":[
        "\u0641\u0631\u0648\u062f\u06af\u0627\u0647 \u0645\u0648\u0644\u0648\u06a9\u0627\u06cc"
    ],
    "name:fra_x_preferred":[
        "A\u00e9roport de Molokai"
    ],
    "name:fra_x_variant":[
        "Molokai Airport"
    ],
    "name:haw_x_preferred":[
        "Moloka\u2018i Airport"
    ],
    "name:ita_x_preferred":[
        "Aeroporto di Molokai"
    ],
    "name:jpn_x_preferred":[
        "\u30e2\u30ed\u30ab\u30a4\u7a7a\u6e2f"
    ],
    "name:nld_x_preferred":[
        "Molokai Airport"
    ],
    "name:ron_x_preferred":[
        "Aeroportul Molokai"
    ],
    "name:spa_x_preferred":[
        "Aeroport de Molokai"
    ],
    "name:tgk_x_preferred":[
        "\u0424\u0443\u0440\u0443\u0434\u0433\u043e\u04b3\u0438 \u043c\u0443\u043b\u0443\u043a"
    ],
    "name:urd_x_preferred":[
        "\u0645\u0648\u0644\u0648\u06a9\u0627\u0626\u06cc \u06c1\u0648\u0627\u0626\u06cc \u0627\u0688\u0627"
    ],
    "oa:elevation_ft":"454",
    "oa:type":"medium_airport",
    "wd:wordcount":666,
    "woe:hierarchy":{
        "country_id":23424977,
        "county_id":12588033,
        "planet_id":1,
        "state_id":2347570
    },
    "wof:name":"Molokai Airport",
    "wof:placetype":"campus"
},
  "geometry": {"coordinates":[-157.09599299999999,21.152901],"type":"Point"}
}