{
  "type": "Feature",
  "properties": {
    "gn:admin1_code":"TX",
    "gn:admin2_code":"5.0",
    "gn:asciiname":"Parker Point",
    "gn:country_code":"US",
    "gn:dem":74,
    "gn:elevation":"61.0",
    "gn:feature_class":"P",
    "gn:feature_code":"PPL",
    "gn:name":"Parker Point",
    "gn:population":0,
    "gn:timezone":"America/Chicago",
    "iso:country":"US",
    "wof:name":"Parker Point",
    "wof:placetype":"locality"
},
  "geometry": {"coordinates":[-94.21603,31.09825],"type":"Point"}
}