{
  "type": "Feature",
  "properties": {
    "iso:country":"US",
    "name:ceb_x_preferred":[
        "West Hills"
    ],
    "name:deu_x_preferred":[
        "West Hills"
    ],
    "name:eng_x_preferred":[
        "West Hills"
    ],
    "name:kor_x_preferred":[
        "\uc6e8\uc2a4\ud2b8\ud790\uc2a4"
    ],
    "name:nld_x_preferred":[
        "West Hills"
    ],
    "name:pol_x_preferred":[
        "West Hills"
    ],
    "name:rus_x_preferred":[
        "\u0423\u044d\u0441\u0442-\u0425\u0438\u043b\u043b\u0437"
    ],
    "name:srp_x_preferred":[
        "\u0412\u0435\u0441\u0442 \u0425\u0438\u043b\u0441"
    ],
    "name:vol_x_preferred":[
        "West Hills"
    ],
    "wd:wordcount":82,
    "wof:name":"West Hills",
    "wof:placetype":"neighbourhood",
    "wof:population":3175,
    "zs:area_m":989783.285337,
    "zs:blockids":[
        490351135271003,
        490351138032028,
        490351138032008,
        490351138032003,
        490351138032002,
        490351135262010,
        490351138032012,
        490351138032033,
        490351138032010,
        490351138032009,
        490351135262012,
        490351135262013,
        490351138032014,
        490351138032029,
        490351135271006,
        490351138032001,
        490351138032007,
        490351138032031,
        490351138032013,
        490351135271001,
        490351135271000,
        490351138032018,
        490351135271005,
        490351138032015,
        490351135271004,
        490351135262011,
        490351138032017,
        490351138032016,
        490351138032030,
        490351138032011
    ],
    "zs:housing10":806,
    "zs:label":"West Hills",
    "zs:pop10":3175
},
  "geometry": {"coordinates":[-112.022183,40.646265],"type":"Point"}
}