{
  "type": "Feature",
  "properties": {
    "iso:country":"US",
    "name:eng_x_preferred":[
        "Randolphville"
    ],
    "wof:name":"Randolphville",
    "wof:placetype":"neighbourhood",
    "wof:population":4076,
    "zs:area_m":4359758.313455,
    "zs:blockids":[
        340230006061032,
        340230006031042,
        340230006031043,
        340230006031001,
        340230006061023,
        340230006061027,
        340230006031040,
        340230006031041,
        340230006031003,
        340230006031000,
        340230006031006,
        340230006063023,
        340230006031039,
        340230006063024,
        340230088003005,
        340230006063001,
        340230006031010,
        340230006031013,
        340230006063005,
        340230006031002,
        340230006032043,
        340230006032042,
        340230006031011,
        340230006032050,
        340230006063025,
        340230006061007,
        340230006031015,
        340230088003003,
        340230006063010,
        340230006063004,
        340230006031046,
        340230006031025,
        340230088003011,
        340230006031012,
        340230006031037,
        340230006061026,
        340230006031007,
        340230006031033,
        340230088003004,
        340230006061031,
        340230088003002,
        340230006061033,
        340230006031045,
        340230006061008,
        340230006061006,
        340230006031038,
        340230006031005,
        340230006031016,
        340230006031004,
        340230006031035,
        340230006061034,
        340230006061024,
        340230006061025,
        340230006063003,
        340230088003001,
        340230006031036,
        340230006061030,
        340230006063011,
        340230006031014,
        340230006031008,
        340230006061035,
        340230006032039,
        340230006031009,
        340230006031044,
        340230006031034,
        340230006063002
    ],
    "zs:housing10":1330,
    "zs:label":"Randolphville",
    "zs:pop10":4076
},
  "geometry": {"coordinates":[-74.449382,40.54512],"type":"Point"}
}