{
  "type": "Feature",
  "properties": {
    "gn:admin1_code":"MD",
    "gn:admin2_code":"13.0",
    "gn:asciiname":"Fleming Way Estates",
    "gn:country_code":"US",
    "gn:dem":224,
    "gn:elevation":"236.0",
    "gn:feature_class":"P",
    "gn:feature_code":"PPL",
    "gn:name":"Fleming Way Estates",
    "gn:population":0,
    "gn:timezone":"America/New_York",
    "iso:country":"US",
    "wof:name":"Fleming Way Estates",
    "wof:placetype":"locality"
},
  "geometry": {"coordinates":[-77.08525999999998,39.42982],"type":"Point"}
}