{
  "type": "Feature",
  "properties": {
    "gn:admin1_code":"TX",
    "gn:admin2_code":"215.0",
    "gn:asciiname":"Agua Dulce Colonia",
    "gn:country_code":"US",
    "gn:dem":28,
    "gn:elevation":"22.0",
    "gn:feature_class":"P",
    "gn:feature_code":"PPL",
    "gn:name":"Agua Dulce Colonia",
    "gn:population":0,
    "gn:timezone":"America/Chicago",
    "iso:country":"US",
    "wof:name":"Agua Dulce Colonia",
    "wof:placetype":"locality"
},
  "geometry": {"coordinates":[-97.96528000000001,26.12924],"type":"Point"}
}