{
  "type": "Feature",
  "properties": {
    "gn:admin1_code":"PA",
    "gn:admin2_code":"43.0",
    "gn:admin3_code":"75672.0",
    "gn:asciiname":"Chestnut Hill",
    "gn:country_code":"US",
    "gn:dem":179,
    "gn:elevation":"176.0",
    "gn:feature_class":"P",
    "gn:feature_code":"PPL",
    "gn:name":"Chestnut Hill",
    "gn:population":0,
    "gn:timezone":"America/New_York",
    "iso:country":"US",
    "name:ceb_x_preferred":[
        "Chestnut Hill"
    ],
    "name:deu_x_preferred":[
        "Chestnut Hill"
    ],
    "name:fra_x_preferred":[
        "Chestnut Hill"
    ],
    "name:ita_x_preferred":[
        "Chestnut Hill"
    ],
    "name:nld_x_preferred":[
        "Chestnut Hill"
    ],
    "wof:name":"Chestnut Hill",
    "wof:placetype":"locality"
},
  "geometry": {"coordinates":[-76.78386,40.25092],"type":"Point"}
}