{
  "type": "Feature",
  "properties": {
    "gn:admin1_code":"NC",
    "gn:admin2_code":"127",
    "gn:admin3_code":"91100.0",
    "gn:asciiname":"Gold Valley Crossroads",
    "gn:country_code":"US",
    "gn:dem":85,
    "gn:elevation":"83.0",
    "gn:feature_class":"P",
    "gn:feature_code":"PPL",
    "gn:name":"Gold Valley Crossroads",
    "gn:population":0,
    "gn:timezone":"America/New_York",
    "iso:country":"US",
    "name:eng_x_preferred":[
        "Gold Valley Crossroads"
    ],
    "name:und_x_variant":[
        "Gold Valley Cross Roads"
    ],
    "wof:name":"Gold Valley Crossroads",
    "wof:placetype":"locality"
},
  "geometry": {"coordinates":[-78.16804999999999,35.8996],"type":"Point"}
}