{
  "type": "Feature",
  "properties": {
    "gn:admin1_code":"AL",
    "gn:admin2_code":"51.0",
    "gn:asciiname":"Tuskugu",
    "gn:country_code":"US",
    "gn:dem":59,
    "gn:elevation":"50.0",
    "gn:feature_class":"P",
    "gn:feature_code":"PPL",
    "gn:name":"Tuskugu",
    "gn:population":0,
    "gn:timezone":"America/Chicago",
    "iso:country":"US",
    "name:eng_x_preferred":[
        "Tuskugu"
    ],
    "name:und_x_variant":[
        "Tus-ke-gee",
        "Tooses",
        "Jascag",
        "Tasquiqui",
        "Jaskigis",
        "Takiki",
        "Taskegee",
        "Tuskeegies",
        "Tuskeegee",
        "Touzas",
        "Jasquijis",
        "Joskage",
        "Tae-keo-ge",
        "Tuskegees",
        "Les Taskaque",
        "Tastekis",
        "Jascage",
        "Tuskiki",
        "Tiscugas",
        "Taskigi",
        "Tasquilki",
        "Taskikis",
        "Tuskeego",
        "Tuskogee",
        "Jaskegis"
    ],
    "wof:name":"Tuskugu",
    "wof:placetype":"locality"
},
  "geometry": {"coordinates":[-86.25414000000001,32.5043],"type":"Point"}
}