{
  "type": "Feature",
  "properties": {
    "gn:admin1_code":"MI",
    "gn:admin2_code":"141.0",
    "gn:admin3_code":"66020.0",
    "gn:asciiname":"Orchard",
    "gn:country_code":"US",
    "gn:dem":248,
    "gn:elevation":"252.0",
    "gn:feature_class":"P",
    "gn:feature_code":"PPL",
    "gn:name":"Orchard",
    "gn:population":0,
    "gn:timezone":"America/Detroit",
    "iso:country":"US",
    "name:ara_x_preferred":[
        "\u0628\u0633\u062a\u0627\u0646"
    ],
    "name:arg_x_preferred":[
        "Huerta"
    ],
    "name:ast_x_preferred":[
        "G\u00fcertu frutal"
    ],
    "name:bel_x_preferred":[
        "\u041f\u043b\u0430\u0434\u043e\u0432\u044b \u0441\u0430\u0434"
    ],
    "name:bjn_x_preferred":[
        "Kabun"
    ],
    "name:bul_x_preferred":[
        "\u041e\u0432\u043e\u0449\u043d\u0430 \u0433\u0440\u0430\u0434\u0438\u043d\u0430"
    ],
    "name:ces_x_preferred":[
        "Sad"
    ],
    "name:deu_x_preferred":[
        "Streuobstwiese"
    ],
    "name:diq_x_preferred":[
        "Bostan"
    ],
    "name:epo_x_preferred":[
        "Frukto\u011dardeno"
    ],
    "name:fas_x_preferred":[
        "\u0628\u0627\u063a \u0645\u06cc\u0648\u0647"
    ],
    "name:fin_x_preferred":[
        "Hedelm\u00e4nviljely"
    ],
    "name:fra_x_preferred":[
        "Verger"
    ],
    "name:fry_x_preferred":[
        "H\u00f4f"
    ],
    "name:gla_x_preferred":[
        "Ubhal-ghort"
    ],
    "name:heb_x_preferred":[
        "\u05e4\u05e8\u05d3\u05e1"
    ],
    "name:hin_x_preferred":[
        "\u092b\u0932\u094b\u0926\u094d\u092f\u093e\u0928"
    ],
    "name:hrv_x_preferred":[
        "Vo\u0107njak"
    ],
    "name:ind_x_preferred":[
        "Kebun"
    ],
    "name:ita_x_preferred":[
        "Frutteto"
    ],
    "name:jpn_x_preferred":[
        "\u679c\u6a39\u5712"
    ],
    "name:kor_x_preferred":[
        "\uacfc\uc218\uc6d0"
    ],
    "name:lat_x_preferred":[
        "Arbustum"
    ],
    "name:lim_x_preferred":[
        "B\u00f3ngerd"
    ],
    "name:ltz_x_preferred":[
        "Bongert"
    ],
    "name:mal_x_preferred":[
        "\u0d2b\u0d32 \u0d35\u0d43\u0d15\u0d4d\u0d37\u0d24\u0d4d\u0d24\u0d4b\u0d2a\u0d4d\u0d2a\u0d4d"
    ],
    "name:mkd_x_preferred":[
        "\u041e\u0432\u043e\u0448\u0442\u0430\u0440\u043d\u0438\u043a"
    ],
    "name:msa_x_preferred":[
        "Dusun"
    ],
    "name:nld_x_preferred":[
        "Boomgaard"
    ],
    "name:nno_x_preferred":[
        "Fruktdyrking"
    ],
    "name:pdc_x_preferred":[
        "Baamgaarde"
    ],
    "name:pol_x_preferred":[
        "Sad"
    ],
    "name:por_x_preferred":[
        "Pomar"
    ],
    "name:que_x_preferred":[
        "Mallki-mallki"
    ],
    "name:ron_x_preferred":[
        "Livad\u0103"
    ],
    "name:rus_x_preferred":[
        "\u041f\u043b\u043e\u0434\u043e\u0432\u044b\u0439 \u0441\u0430\u0434"
    ],
    "name:sco_x_preferred":[
        "Orchart"
    ],
    "name:slk_x_preferred":[
        "Sad"
    ],
    "name:slv_x_preferred":[
        "Sadovnjak"
    ],
    "name:spa_x_preferred":[
        "Huerto frutal"
    ],
    "name:srp_x_preferred":[
        "\u0412\u043e\u045b\u045a\u0430\u043a"
    ],
    "name:swe_x_preferred":[
        "Fruktodling"
    ],
    "name:tur_x_preferred":[
        "Bostan"
    ],
    "name:ukr_x_preferred":[
        "\u0424\u0440\u0443\u043a\u0442\u043e\u0432\u0438\u0439 \u0441\u0430\u0434"
    ],
    "name:vec_x_preferred":[
        "Fruter"
    ],
    "wof:name":"Orchard",
    "wof:placetype":"locality"
},
  "geometry": {"coordinates":[-83.73013,45.291],"type":"Point"}
}