{
  "type": "Feature",
  "properties": {
    "gn:admin1_code":"AR",
    "gn:admin2_code":"9.0",
    "gn:admin3_code":"90507.0",
    "gn:asciiname":"Capps",
    "gn:country_code":"US",
    "gn:dem":442,
    "gn:elevation":"439.0",
    "gn:feature_class":"P",
    "gn:feature_code":"PPL",
    "gn:name":"Capps",
    "gn:population":0,
    "gn:timezone":"America/Chicago",
    "iso:country":"US",
    "name:azb_x_preferred":[
        "\u06a9\u067e\u0633"
    ],
    "name:fas_x_preferred":[
        "\u06a9\u067e\u0633"
    ],
    "name:ita_x_preferred":[
        "Capps"
    ],
    "name:zho_x_preferred":[
        "\u5361\u666e\u65af"
    ],
    "wof:name":"Capps",
    "wof:placetype":"locality"
},
  "geometry": {"coordinates":[-93.18935,36.23563],"type":"Point"}
}