{
  "type": "Feature",
  "properties": {
    "gn:admin1_code":"MS",
    "gn:admin2_code":"23",
    "gn:asciiname":"Wautubbee",
    "gn:country_code":"US",
    "gn:dem":122,
    "gn:elevation":"115.0",
    "gn:feature_class":"P",
    "gn:feature_code":"PPL",
    "gn:name":"Wautubbee",
    "gn:population":0,
    "gn:timezone":"America/Chicago",
    "iso:country":"US",
    "name:eng_x_preferred":[
        "Wautubbee"
    ],
    "name:und_x_variant":[
        "Hells Valley"
    ],
    "wof:name":"Wautubbee",
    "wof:placetype":"locality"
},
  "geometry": {"coordinates":[-88.85838000000003,32.11626],"type":"Point"}
}