{
  "type": "Feature",
  "properties": {
    "gn:admin1_code":"CO",
    "gn:admin2_code":"69.0",
    "gn:asciiname":"Old Roach",
    "gn:country_code":"US",
    "gn:dem":2868,
    "gn:elevation":"2859.0",
    "gn:feature_class":"P",
    "gn:feature_code":"PPL",
    "gn:name":"Old Roach",
    "gn:population":0,
    "gn:timezone":"America/Denver",
    "iso:country":"US",
    "wof:name":"Old Roach",
    "wof:placetype":"locality"
},
  "geometry": {"coordinates":[-106.11724,40.92442],"type":"Point"}
}