{
  "type": "Feature",
  "properties": {
    "gn:admin1_code":"NV",
    "gn:admin2_code":"23.0",
    "gn:asciiname":"Lodi Tanks",
    "gn:country_code":"US",
    "gn:dem":1526,
    "gn:elevation":"1523.0",
    "gn:feature_class":"P",
    "gn:feature_code":"PPL",
    "gn:name":"Lodi Tanks",
    "gn:population":0,
    "gn:timezone":"America/Los_Angeles",
    "iso:country":"US",
    "wof:name":"Lodi Tanks",
    "wof:placetype":"locality"
},
  "geometry": {"coordinates":[-117.834,38.98715],"type":"Point"}
}