{
  "type": "Feature",
  "properties": {
    "gn:elevation":184,
    "iso:country":"US",
    "name:eng_x_preferred":[
        "Mountain Creek"
    ],
    "name:eng_x_variant":[
        "Mountain Crk"
    ],
    "qs:gn_adm0_cc":"US",
    "qs:gn_fcode":"PPL",
    "qs:gn_local":4612862,
    "qs:gn_nam_loc":"Chattanooga, Hamilton, Tennessee, US",
    "qs:gn_namadm1":"AL",
    "qs:gn_name":"Mountain Acres",
    "qs:local_max":13653,
    "qs:local_sum":34620,
    "qs:localhoods":63,
    "qs:name":"Mountain Creek",
    "qs:name_adm0":"United States",
    "qs:name_adm1":"Tennessee",
    "qs:name_adm2":"Hamilton",
    "qs:name_local":"Chattanooga",
    "qs:photo_max":148,
    "qs:photo_sum":216,
    "qs:placetype":"Suburb",
    "qs:quad_count":10,
    "qs:woe_adm0":23424977,
    "qs:woe_adm1":2347601,
    "qs:woe_adm2":12589944,
    "qs:woe_funk":"Grouping neighborhood",
    "qs:woe_lau":0,
    "qs:woe_local":2378695,
    "qs:woe_ver":"7.10.0",
    "wof:lang":[
        "eng"
    ],
    "wof:name":"Mountain Creek",
    "wof:placetype":"neighbourhood",
    "wof:population":1051,
    "zs:blockids":[
        470650121001016,
        470650109021027,
        470650109034010,
        470650109021044,
        470650109021048,
        470650109021033,
        470650109034017,
        470650109021040,
        470650109021050,
        470650109021054,
        470650109021036,
        470650109021055,
        470650109011012,
        470650109021039,
        470650121001005,
        470650121001011,
        470650109021042,
        470650109034018,
        470650109011022,
        470650121001010,
        470650109011033,
        470650109021032,
        470650109021046,
        470650109011034,
        470650121001015,
        470650109021053,
        470650109034008,
        470650109011021,
        470650109011031,
        470650109021047,
        470650109011070,
        470650109011032,
        470650121001013,
        470650109021041,
        470650109021052,
        470650109034009,
        470650109011023,
        470650109011013,
        470650109021034,
        470650109021045
    ],
    "zs:housing10":546,
    "zs:pop10":1051
},
  "geometry": {"coordinates":[-85.334458,35.086638],"type":"Point"}
}