{
  "type": "Feature",
  "properties": {
    "gn:admin1_code":"OH",
    "gn:admin2_code":"153",
    "gn:admin3_code":"74130.0",
    "gn:asciiname":"Bear's Mobile Home Park",
    "gn:country_code":"US",
    "gn:dem":328,
    "gn:elevation":"329.0",
    "gn:feature_class":"P",
    "gn:feature_code":"PPL",
    "gn:name":"Bear's Mobile Home Park",
    "gn:population":0,
    "gn:timezone":"America/New_York",
    "iso:country":"US",
    "wof:name":"Bear's Mobile Home Park",
    "wof:placetype":"campus"
},
  "geometry": {"coordinates":[-81.42971999999997,41.03528],"type":"Point"}
}