{
  "type": "Feature",
  "properties": {
    "gn:elevation":107,
    "iso:country":"US",
    "name:eng_x_preferred":[
        "Camp Green Eyrie"
    ],
    "qs:gn_adm0_cc":"US",
    "qs:gn_fcode":"PPL",
    "qs:gn_local":4938957,
    "qs:gn_nam_loc":"Harvard, Worcester, Massachusetts, US",
    "qs:gn_namadm1":"MA",
    "qs:gn_name":"Camp Green Eyrie",
    "qs:local_max":515,
    "qs:local_sum":941,
    "qs:localhoods":2,
    "qs:name":"Camp Green Eyrie",
    "qs:name_adm0":"United States",
    "qs:name_adm1":"Massachusetts",
    "qs:name_adm2":"Worcester",
    "qs:name_local":"Harvard",
    "qs:photo_max":102,
    "qs:photo_sum":426,
    "qs:placetype":"Suburb",
    "qs:quad_count":28,
    "qs:woe_adm0":23424977,
    "qs:woe_adm1":2347580,
    "qs:woe_adm2":12588713,
    "qs:woe_lau":0,
    "qs:woe_local":2418410,
    "qs:woe_ver":"7.10.0",
    "wof:lang":[
        "eng"
    ],
    "wof:name":"Camp Green Eyrie",
    "wof:placetype":"neighbourhood"
},
  "geometry": {"coordinates":[-71.58605300000001,42.501034],"type":"Point"}
}