{
  "type": "Feature",
  "properties": {
    "gn:country":"US",
    "gn:fcode":"PPL",
    "gn:population":302,
    "iso:country":"US",
    "name:ara_x_preferred":[
        "\u0625\u0644\u0628\u0631\u062a\u0627"
    ],
    "name:azb_x_preferred":[
        "\u0627\u0644\u0628\u0631\u062a\u0627"
    ],
    "name:cat_x_preferred":[
        "Elberta"
    ],
    "name:ceb_x_preferred":[
        "Elberta"
    ],
    "name:che_x_preferred":[
        "\u0415\u043b\u0431\u0435\u0440\u0442\u0430"
    ],
    "name:deu_x_preferred":[
        "Elberta"
    ],
    "name:eng_x_preferred":[
        "Mount Nebo"
    ],
    "name:eng_x_variant":[
        "Elberta"
    ],
    "name:eus_x_preferred":[
        "Elberta"
    ],
    "name:fas_x_preferred":[
        "\u0627\u0644\u0628\u0631\u062a\u0627"
    ],
    "name:fra_x_preferred":[
        "Elberta"
    ],
    "name:gle_x_preferred":[
        "Elberta"
    ],
    "name:ita_x_preferred":[
        "Elberta"
    ],
    "name:lld_x_preferred":[
        "Elberta"
    ],
    "name:nan_x_preferred":[
        "Elberta"
    ],
    "name:nld_x_preferred":[
        "Elberta"
    ],
    "name:pol_x_preferred":[
        "Elberta"
    ],
    "name:por_x_preferred":[
        "Elberta"
    ],
    "name:spa_x_preferred":[
        "Elberta"
    ],
    "name:srp_x_preferred":[
        "\u0415\u043b\u0431\u0435\u0440\u0442\u0430"
    ],
    "name:tat_x_preferred":[
        "\u0415\u043b\u0431\u0435\u0440\u0442\u0430"
    ],
    "name:ukr_x_preferred":[
        "\u0415\u043b\u0431\u0435\u0440\u0442\u0430"
    ],
    "name:vol_x_preferred":[
        "Elberta"
    ],
    "name:zho_x_preferred":[
        "\u57c3\u723e\u4f2f\u5854"
    ],
    "qs_pg:aaroncc":"US",
    "qs_pg:gn_country":"US",
    "qs_pg:gn_fcode":"PPL",
    "qs_pg:gn_pop":302,
    "qs_pg:name":"Mount Nebo",
    "qs_pg:photos_9r":0,
    "qs_pg:photos_sr":0,
    "qs_pg:pop_sr":2,
    "qs_pg:qs_pg_placetype":"locality",
    "wof:name":"Mount Nebo",
    "wof:placetype":"locality",
    "wof:population":302
},
  "geometry": {"coordinates":[-111.95632999999999,39.95273],"type":"Point"}
}