{
  "type": "Feature",
  "properties": {
    "gn:gn_country":"US",
    "gn:gn_fcode":"PPL",
    "gn:gn_pop":302,
    "gn:population":302,
    "iso:country":"US",
    "name:cat_x_preferred":[
        "Elberta"
    ],
    "name:deu_x_preferred":[
        "Elberta"
    ],
    "name:eng_x_preferred":[
        "Mount Nebo"
    ],
    "name:fra_x_preferred":[
        "Elberta"
    ],
    "name:ita_x_preferred":[
        "Elberta"
    ],
    "name:nld_x_preferred":[
        "Elberta"
    ],
    "name:por_x_preferred":[
        "Elberta"
    ],
    "name:spa_x_preferred":[
        "Elberta"
    ],
    "name:srp_x_preferred":[
        "\u0415\u043b\u0431\u0435\u0440\u0442\u0430"
    ],
    "name:unk_x_variant":[
        "Elberta"
    ],
    "name:vol_x_preferred":[
        "Elberta"
    ],
    "qs_pg:aaroncc":"US",
    "qs_pg:gn_country":"US",
    "qs_pg:gn_fcode":"PPL",
    "qs_pg:gn_pop":302,
    "qs_pg:name":"Mount Nebo",
    "qs_pg:photos_9r":0,
    "qs_pg:photos_sr":0,
    "qs_pg:pop_sr":2,
    "qs_pg:qs_pg_placetype":"locality",
    "wof:name":"Mount Nebo",
    "wof:placetype":"locality",
    "wof:population":302
},
  "geometry": {"coordinates":[-111.95632999999999,39.95273],"type":"Point"}
}