{
  "type": "Feature",
  "properties": {
    "gn:admin1_code":"TX",
    "gn:admin2_code":"215.0",
    "gn:asciiname":"Bar Number 3 Colonia",
    "gn:country_code":"US",
    "gn:dem":23,
    "gn:elevation":"20.0",
    "gn:feature_class":"P",
    "gn:feature_code":"PPL",
    "gn:name":"Bar Number 3 Colonia",
    "gn:population":0,
    "gn:timezone":"America/Chicago",
    "iso:country":"US",
    "wof:name":"Bar Number 3 Colonia",
    "wof:placetype":"locality"
},
  "geometry": {"coordinates":[-97.97722,26.3184],"type":"Point"}
}