{
  "type": "Feature",
  "properties": {
    "gn:admin1_code":"OR",
    "gn:admin2_code":"35",
    "gn:asciiname":"Falcon Heights",
    "gn:country_code":"US",
    "gn:dem":1347,
    "gn:elevation":"1346.0",
    "gn:feature_class":"P",
    "gn:feature_code":"PPL",
    "gn:name":"Falcon Heights",
    "gn:population":0,
    "gn:timezone":"America/Los_Angeles",
    "iso:country":"US",
    "name:ceb_x_preferred":[
        "Falcon Heights"
    ],
    "name:deu_x_preferred":[
        "Falcon Heights"
    ],
    "name:ido_x_preferred":[
        "Falcon Heights"
    ],
    "name:ita_x_preferred":[
        "Falcon Heights"
    ],
    "name:nld_x_preferred":[
        "Falcon Heights"
    ],
    "name:por_x_preferred":[
        "Falcon Heights"
    ],
    "name:srp_x_preferred":[
        "\u0424\u0430\u043b\u043a\u043e\u043d \u0425\u0430\u0458\u0442\u0441"
    ],
    "name:vol_x_preferred":[
        "Falcon Heights"
    ],
    "wof:name":"Falcon Heights",
    "wof:placetype":"locality"
},
  "geometry": {"coordinates":[-121.75667,42.13737],"type":"Point"}
}