{
  "type": "Feature",
  "properties": {
    "iso:country":"US",
    "name:eng_x_preferred":[
        "Smoketree"
    ],
    "wd:wordcount":62,
    "wof:name":"Smoketree",
    "wof:placetype":"neighbourhood",
    "wof:population":1968,
    "zs:area_m":2476056.141202,
    "zs:blockids":[
        371830540171040,
        371830540162001,
        371830540162020,
        371830540151005,
        371830540143027,
        371830540151004,
        371830540143015,
        371830540171049,
        371830540143035,
        371830540143006,
        371830540143007,
        371830540171041,
        371830540143028,
        371830540162023,
        371830540171055,
        371830540143034,
        371830540143037,
        371830540143036,
        371830540162002,
        371830540171044,
        371830540143000,
        371830540171048,
        371830540171043,
        371830540171052,
        371830540143013,
        371830540171047,
        371830540143008,
        371830540143010,
        371830540143026,
        371830540143011,
        371830540171042,
        371830540143033,
        371830540143012,
        371830540143014,
        371830540143004,
        371830540143022,
        371830540143023,
        371830540171039,
        371830540171054,
        371830540162021,
        371830540162025,
        371830540162022,
        371830540143001,
        371830540143003,
        371830540143024,
        371830540151002,
        371830540143017,
        371830540143016,
        371830540162024,
        371830540143002,
        371830540171000,
        371830540171001,
        371830540143009,
        371830540143025,
        371830540171046,
        371830540171053
    ],
    "zs:housing10":770,
    "zs:label":"Smoketree",
    "zs:pop10":1968
},
  "geometry": {"coordinates":[-78.56549200000001,35.879545],"type":"Point"}
}