{
  "type": "Feature",
  "properties": {
    "gn:admin1_code":"VA",
    "gn:admin2_code":"11.0",
    "gn:asciiname":"Bent Creek",
    "gn:country_code":"US",
    "gn:dem":136,
    "gn:elevation":"127.0",
    "gn:feature_class":"P",
    "gn:feature_code":"PPL",
    "gn:name":"Bent Creek",
    "gn:population":0,
    "gn:timezone":"America/New_York",
    "iso:country":"US",
    "name:eng_x_preferred":[
        "Bent Creek"
    ],
    "name:und_x_variant":[
        "Bentcreek",
        "Duguidsville"
    ],
    "wof:name":"Bent Creek",
    "wof:placetype":"locality"
},
  "geometry": {"coordinates":[-78.82696,37.53487],"type":"Point"}
}