{
  "type": "Feature",
  "properties": {
    "iso:country":"US",
    "name:eng_x_preferred":[
        "Carver Park"
    ],
    "wof:name":"Carver Park",
    "wof:placetype":"neighbourhood",
    "wof:population":420,
    "zs:area_m":1022757.283154,
    "zs:blockids":[
        120690305032000,
        120690305041015,
        120690305044047,
        120690305032001,
        120690305041018,
        120690305032005,
        120690305041020,
        120690305041014,
        120690305032004,
        120690305031002,
        120690305041022,
        120690305044036,
        120690305041016,
        120690305041019,
        120690305041032
    ],
    "zs:housing10":166,
    "zs:label":"Carver Park",
    "zs:pop10":420
},
  "geometry": {"coordinates":[-81.90209,28.821539],"type":"Point"}
}