{
  "type": "Feature",
  "properties": {
    "iso:country":"US",
    "name:eng_x_preferred":[
        "Meshanticut"
    ],
    "name:fra_x_preferred":[
        "Meshanticut"
    ],
    "name:und_x_variant":[
        "Meshantacuck"
    ],
    "wof:name":"Meshanticut",
    "wof:placetype":"neighbourhood",
    "wof:population":2194,
    "zs:area_m":1237953.861812,
    "zs:blockids":[
        440070145022033,
        440070143004007,
        440070143004031,
        440070143004001,
        440070145022010,
        440070144001003,
        440070143004024,
        440070143004029,
        440070144001021,
        440070143004002,
        440070145022028,
        440070145022025,
        440070143004015,
        440070143004011,
        440070143004020,
        440070143004022,
        440070145022011,
        440070144001010,
        440070144001004,
        440070145022021,
        440070145022034,
        440070144001009,
        440070143004008,
        440070143004019,
        440070143004025,
        440070143004028,
        440070143004012,
        440070144001006,
        440070145022002,
        440070145022023,
        440070143004014,
        440070143004010,
        440070143004003,
        440070143004005,
        440070143004006,
        440070143004004,
        440070143004026,
        440070144001007,
        440070144001005,
        440070144001022,
        440070145021023,
        440070145022012,
        440070143004021,
        440070144001008,
        440070143004016,
        440070143004009,
        440070143004017,
        440070144001023,
        440070145022014,
        440070143004027,
        440070145022015,
        440070143003018,
        440070143004000,
        440070143004013,
        440070143004023
    ],
    "zs:housing10":1080,
    "zs:label":"Meshanticut",
    "zs:pop10":2194
},
  "geometry": {"coordinates":[-71.469042,41.769327],"type":"Point"}
}