{
  "type": "Feature",
  "properties": {
    "iso:country":"US",
    "name:eng_x_preferred":[
        "Ironworkers Addition To South Chicago"
    ],
    "wof:name":"Ironworkers Addition To South Chicago",
    "wof:placetype":"neighbourhood",
    "zs:blockids":[
        170315101002017,
        170315101002015,
        180890202001009,
        180890202001012,
        180890202001008,
        180890202001001,
        180890202001007,
        180890202001003,
        180890202001006,
        180890202001002
    ],
    "zs:housing10":0,
    "zs:label":"Ironworkers Addition To South Chicago",
    "zs:pop10":0
},
  "geometry": {"coordinates":[-87.513678,41.703631],"type":"Point"}
}