{
  "type": "Feature",
  "properties": {
    "gn:country":"US",
    "gn:fcode":"PPL",
    "gn:population":0,
    "iso:country":"US",
    "name:bul_x_preferred":[
        "\u0423\u0438\u043b\u044f\u043c\u0441\u0431\u044a\u0440\u0433"
    ],
    "name:cat_x_preferred":[
        "Williamsburg"
    ],
    "name:ceb_x_preferred":[
        "Williamsburg"
    ],
    "name:dan_x_preferred":[
        "Williamsburg"
    ],
    "name:deu_x_preferred":[
        "Williamsburg"
    ],
    "name:fin_x_preferred":[
        "Williamsburg"
    ],
    "name:fra_x_preferred":[
        "Williamsburg"
    ],
    "name:heb_x_preferred":[
        "\u05d5\u05d9\u05dc\u05d9\u05d0\u05de\u05e1\u05d1\u05d5\u05e8\u05d2"
    ],
    "name:ido_x_preferred":[
        "Williamsburg"
    ],
    "name:ita_x_preferred":[
        "Williamsburg"
    ],
    "name:jpn_x_preferred":[
        "\u30a6\u30a3\u30ea\u30a2\u30e0\u30ba\u30d0\u30fc\u30b0"
    ],
    "name:kor_x_preferred":[
        "\uc70c\ub9ac\uc5c4\uc2a4\ubc84\uadf8"
    ],
    "name:nld_x_preferred":[
        "Williamsburg"
    ],
    "name:nno_x_preferred":[
        "Williamsburg"
    ],
    "name:pol_x_preferred":[
        "Williamsburg"
    ],
    "name:por_x_preferred":[
        "Williamsburg"
    ],
    "name:rus_x_preferred":[
        "\u0423\u0438\u043b\u044c\u044f\u043c\u0441\u0431\u0435\u0440\u0433"
    ],
    "name:spa_x_preferred":[
        "Williamsburg"
    ],
    "name:srp_x_preferred":[
        "\u0412\u0438\u043b\u0438\u0458\u0430\u043c\u0441\u0431\u0443\u0440\u0433"
    ],
    "name:swe_x_preferred":[
        "Williamsburg"
    ],
    "name:urd_x_preferred":[
        "\u0648\u06cc\u0644\u0645\u0632\u0628\u0631\u06af"
    ],
    "name:vol_x_preferred":[
        "Williamsburg"
    ],
    "name:zho_x_preferred":[
        "\u5a01\u5ec9\u65af\u5821"
    ],
    "qs_pg:aaroncc":"US",
    "qs_pg:gn_country":"US",
    "qs_pg:gn_fcode":"PPL",
    "qs_pg:gn_pop":0,
    "qs_pg:name":"Williamsburg",
    "qs_pg:name_adm0":"United States",
    "qs_pg:name_adm1":"Michigan",
    "qs_pg:photos":207,
    "qs_pg:photos_1k":42,
    "qs_pg:photos_9k":1,
    "qs_pg:photos_9r":4,
    "qs_pg:photos_all":207,
    "qs_pg:photos_sr":4,
    "qs_pg:pop_sr":5,
    "qs_pg:qs_pg_placetype":"locality",
    "qs_pg:qs_pg_placetype_gp":"Town",
    "qs_pg:woe_adm0":23424977,
    "woe:adm0_id":23424977,
    "woe:name_adm0":"United States",
    "woe:name_adm1":"Michigan",
    "woe:placetype":"Town",
    "wof:name":"Williamsburg",
    "wof:placetype":"locality"
},
  "geometry": {"coordinates":[-85.40396,44.77361],"type":"Point"}
}