{
  "type": "Feature",
  "properties": {
    "gn:admin1_code":"MD",
    "gn:admin2_code":"13.0",
    "gn:asciiname":"Dales Delight",
    "gn:country_code":"US",
    "gn:dem":234,
    "gn:elevation":"229.0",
    "gn:feature_class":"P",
    "gn:feature_code":"PPL",
    "gn:name":"Dales Delight",
    "gn:population":0,
    "gn:timezone":"America/New_York",
    "iso:country":"US",
    "wof:name":"Dales Delight",
    "wof:placetype":"locality"
},
  "geometry": {"coordinates":[-77.12359000000002,39.37983],"type":"Point"}
}