{
  "type": "Feature",
  "properties": {
    "gn:country":"US",
    "gn:fcode":"PPL",
    "gn:population":0,
    "iso:country":"US",
    "name:eng_x_preferred":[
        "Cranesville"
    ],
    "name:fra_x_preferred":[
        "Cranesville"
    ],
    "name:spa_x_preferred":[
        "Cranesville"
    ],
    "qs_pg:aaroncc":"US",
    "qs_pg:gn_country":"US",
    "qs_pg:gn_fcode":"PPL",
    "qs_pg:gn_pop":0,
    "qs_pg:name":"Cranesville",
    "qs_pg:name_adm0":"United States",
    "qs_pg:name_adm1":"West Virginia",
    "qs_pg:photos":125,
    "qs_pg:photos_1k":25,
    "qs_pg:photos_9k":1,
    "qs_pg:photos_9r":3,
    "qs_pg:photos_all":125,
    "qs_pg:photos_sr":3,
    "qs_pg:pop_sr":0,
    "qs_pg:qs_pg_placetype":"locality",
    "qs_pg:qs_pg_placetype_gp":"Town",
    "qs_pg:woe_adm0":23424977,
    "woe:adm0_id":23424977,
    "woe:name_adm0":"United States",
    "woe:name_adm1":"West Virginia",
    "woe:placetype":"Town",
    "wof:name":"Cranesville",
    "wof:placetype":"locality"
},
  "geometry": {"coordinates":[-79.49477,39.55314],"type":"Point"}
}