{
  "type": "Feature",
  "properties": {
    "iso:country":"US",
    "name:eng_x_preferred":[
        "South Green"
    ],
    "wof:name":"South Green",
    "wof:placetype":"neighbourhood",
    "wof:population":35,
    "zs:area_m":525219.439364,
    "zs:blockids":[
        120570133071006,
        120570133071005
    ],
    "zs:housing10":29,
    "zs:label":"South Green",
    "zs:pop10":35
},
  "geometry": {"coordinates":[-82.305132,27.930879],"type":"Point"}
}