{
  "type": "Feature",
  "properties": {
    "gn:admin1_code":"TN",
    "gn:admin2_code":"125",
    "gn:asciiname":"Fredonia",
    "gn:country_code":"US",
    "gn:dem":197,
    "gn:elevation":"198.0",
    "gn:feature_class":"P",
    "gn:feature_code":"PPL",
    "gn:name":"Fredonia",
    "gn:population":0,
    "gn:timezone":"America/Chicago",
    "iso:country":"US",
    "name:ceb_x_preferred":[
        "Fredonia"
    ],
    "name:deu_x_preferred":[
        "Fredonia"
    ],
    "name:fas_x_preferred":[
        "\u0641\u0631\u062f\u0648\u0646\u06cc\u0627"
    ],
    "name:fra_x_preferred":[
        "Fredonia"
    ],
    "name:ita_x_preferred":[
        "Fredonia"
    ],
    "name:nld_x_preferred":[
        "Fredonia"
    ],
    "name:pol_x_preferred":[
        "Fredonia"
    ],
    "name:por_x_preferred":[
        "Fredonia"
    ],
    "name:spa_x_preferred":[
        "Fredonia"
    ],
    "name:srp_x_preferred":[
        "\u0424\u0440\u0438\u0434\u043e\u043d\u0438\u0458\u0430"
    ],
    "name:swe_x_preferred":[
        "Fredonia"
    ],
    "name:ukr_x_preferred":[
        "\u0424\u0440\u0435\u0434\u043e\u043d\u0456\u044f"
    ],
    "name:vie_x_preferred":[
        "Fredonia"
    ],
    "name:vol_x_preferred":[
        "Fredonia"
    ],
    "wof:name":"Fredonia",
    "wof:placetype":"locality"
},
  "geometry": {"coordinates":[-87.21862,36.43977],"type":"Point"}
}