{
  "type": "Feature",
  "properties": {
    "gn:admin1_code":"IL",
    "gn:admin2_code":"183.0",
    "gn:admin3_code":"48775.0",
    "gn:asciiname":"Ellis",
    "gn:country_code":"US",
    "gn:dem":233,
    "gn:elevation":"230.0",
    "gn:feature_class":"P",
    "gn:feature_code":"PPL",
    "gn:name":"Ellis",
    "gn:population":0,
    "gn:timezone":"America/Chicago",
    "iso:country":"US",
    "name:ces_x_preferred":[
        "Ellis"
    ],
    "name:deu_x_preferred":[
        "Ellis"
    ],
    "wof:name":"Ellis",
    "wof:placetype":"locality"
},
  "geometry": {"coordinates":[-87.88503,40.35531],"type":"Point"}
}