{
  "type": "Feature",
  "properties": {
    "gn:admin1_code":"MO",
    "gn:admin2_code":"95.0",
    "gn:admin3_code":"8686.0",
    "gn:asciiname":"Union Point",
    "gn:country_code":"US",
    "gn:dem":291,
    "gn:elevation":"290.0",
    "gn:feature_class":"P",
    "gn:feature_code":"PPL",
    "gn:name":"Union Point",
    "gn:population":0,
    "gn:timezone":"America/Chicago",
    "iso:country":"US",
    "wof:name":"Union Point",
    "wof:placetype":"locality"
},
  "geometry": {"coordinates":[-94.46606,38.95056],"type":"Point"}
}