{
  "type": "Feature",
  "properties": {
    "gn:admin1_code":"FL",
    "gn:admin2_code":"83.0",
    "gn:asciiname":"Fairfield Village of Ocala Mobile Home Park",
    "gn:country_code":"US",
    "gn:dem":27,
    "gn:elevation":"27.0",
    "gn:feature_class":"P",
    "gn:feature_code":"PPL",
    "gn:name":"Fairfield Village of Ocala Mobile Home Park",
    "gn:population":0,
    "gn:timezone":"America/New_York",
    "iso:country":"US",
    "wof:name":"Fairfield Village of Ocala Mobile Home Park",
    "wof:placetype":"campus"
},
  "geometry": {"coordinates":[-82.2162,29.1293],"type":"Point"}
}