{
  "type": "Feature",
  "properties": {
    "gn:admin1_code":"FL",
    "gn:admin2_code":"127.0",
    "gn:asciiname":"Alamana",
    "gn:country_code":"US",
    "gn:dem":16,
    "gn:elevation":"10.0",
    "gn:feature_class":"P",
    "gn:feature_code":"PPL",
    "gn:name":"Alamana",
    "gn:population":0,
    "gn:timezone":"America/New_York",
    "iso:country":"US",
    "name:fas_x_preferred":[
        "\u0627\u0644\u0627\u0645\u0627\u0646\u0627"
    ],
    "name:zho_x_preferred":[
        "\u963f\u62c9\u99ac\u7d0d"
    ],
    "wof:name":"Alamana",
    "wof:placetype":"locality"
},
  "geometry": {"coordinates":[-81.10256,28.94304],"type":"Point"}
}