{
  "type": "Feature",
  "properties": {
    "gn:country":"US",
    "gn:fcode":"PPL",
    "gn:population":0,
    "iso:country":"US",
    "name:cat_x_preferred":[
        "Wheatland"
    ],
    "name:ceb_x_preferred":[
        "Wheatland"
    ],
    "name:deu_x_preferred":[
        "Wheatland"
    ],
    "name:fra_x_preferred":[
        "Wheatland"
    ],
    "name:ita_x_preferred":[
        "Wheatland"
    ],
    "name:nld_x_preferred":[
        "Wheatland"
    ],
    "name:pol_x_preferred":[
        "Wheatland"
    ],
    "name:por_x_preferred":[
        "Wheatland"
    ],
    "name:rus_x_preferred":[
        "\u0423\u0438\u0442\u043b\u0435\u043d\u0434"
    ],
    "name:srp_x_preferred":[
        "\u0412\u0438\u0442\u043b\u0430\u043d\u0434"
    ],
    "name:swe_x_preferred":[
        "Wheatland"
    ],
    "name:urd_x_preferred":[
        "\u0648\u06cc\u0679\u0644\u06cc\u0646\u0688"
    ],
    "name:vol_x_preferred":[
        "Wheatland"
    ],
    "qs_pg:aaroncc":"US",
    "qs_pg:gn_country":"US",
    "qs_pg:gn_fcode":"PPL",
    "qs_pg:gn_pop":0,
    "qs_pg:name":"Wheatland",
    "qs_pg:name_adm0":"United States",
    "qs_pg:name_adm1":"Virginia",
    "qs_pg:photos":294,
    "qs_pg:photos_1k":60,
    "qs_pg:photos_9k":1,
    "qs_pg:photos_9r":4,
    "qs_pg:photos_all":294,
    "qs_pg:photos_sr":5,
    "qs_pg:pop_sr":0,
    "qs_pg:qs_pg_placetype":"locality",
    "qs_pg:qs_pg_placetype_gp":"Town",
    "qs_pg:woe_adm0":23424977,
    "woe:adm0_id":23424977,
    "woe:name_adm0":"United States",
    "woe:name_adm1":"Virginia",
    "woe:placetype":"Town",
    "wof:name":"Wheatland",
    "wof:placetype":"locality"
},
  "geometry": {"coordinates":[-77.67555,39.19094],"type":"Point"}
}