{
  "type": "Feature",
  "properties": {
    "iso:country":"US",
    "name:eng_x_preferred":[
        "Panhandle Annex"
    ],
    "name:eng_x_variant":[
        "Panhandle Anx"
    ],
    "qs:gn_adm0_cc":"US",
    "qs:gn_local":5387428,
    "qs:gn_nam_loc":"richmond",
    "qs:gn_namadm1":"CA",
    "qs:local_max":7168,
    "qs:local_sum":20495,
    "qs:localhoods":19,
    "qs:name":"Panhandle Annex",
    "qs:name_adm0":"United States",
    "qs:name_adm1":"California",
    "qs:name_adm2":"Contra Costa",
    "qs:name_local":"Richmond",
    "qs:photo_max":287,
    "qs:photo_sum":799,
    "qs:placetype":"Suburb",
    "qs:quad_count":20,
    "qs:woe_adm0":23424977,
    "qs:woe_adm1":2347563,
    "qs:woe_adm2":12587676,
    "qs:woe_lau":0,
    "qs:woe_local":2480904,
    "qs:woe_ver":"7.10.0",
    "wof:name":"Panhandle Annex",
    "wof:placetype":"neighbourhood",
    "zs:blockids":[
        60133800002051,
        60133800002049,
        60133800002061,
        60133800002057,
        60133800002052,
        60133800002054,
        60133800002048,
        60133800002056,
        60133800002058,
        60133800002053,
        60133800002055
    ],
    "zs:housing10":0,
    "zs:pop10":0
},
  "geometry": {"coordinates":[-122.320148,37.914129],"type":"Point"}
}