{
  "type": "Feature",
  "properties": {
    "gn:admin1_code":"TX",
    "gn:admin2_code":"77.0",
    "gn:asciiname":"Shannon",
    "gn:country_code":"US",
    "gn:dem":321,
    "gn:elevation":"316.0",
    "gn:feature_class":"P",
    "gn:feature_code":"PPL",
    "gn:name":"Shannon",
    "gn:population":0,
    "gn:timezone":"America/Chicago",
    "iso:country":"US",
    "name:vol_x_preferred":[
        "Shannon"
    ],
    "wof:name":"Shannon",
    "wof:placetype":"locality"
},
  "geometry": {"coordinates":[-98.25894,33.474],"type":"Point"}
}