{
  "type": "Feature",
  "properties": {
    "gn:admin1_code":"TX",
    "gn:admin2_code":"77.0",
    "gn:asciiname":"Shannon",
    "gn:country_code":"US",
    "gn:dem":321,
    "gn:elevation":"316.0",
    "gn:feature_class":"P",
    "gn:feature_code":"PPL",
    "gn:name":"Shannon",
    "gn:population":0,
    "gn:timezone":"America/Chicago",
    "iso:country":"US",
    "name:ben_x_preferred":[
        "\u09b6\u09cd\u09af\u09be\u09a8\u09a8"
    ],
    "name:ell_x_preferred":[
        "\u03a3\u03ac\u03bd\u03bf\u03bd"
    ],
    "name:hin_x_preferred":[
        "\u0936\u0947\u0928\u0928"
    ],
    "name:ukr_x_preferred":[
        "\u0428\u0430\u043d\u043d\u043e\u043d"
    ],
    "name:vie_x_preferred":[
        "S\u00f4ng Shannon"
    ],
    "name:vol_x_preferred":[
        "Shannon"
    ],
    "wof:name":"Shannon",
    "wof:placetype":"locality"
},
  "geometry": {"coordinates":[-98.25894,33.474],"type":"Point"}
}