{
  "type": "Feature",
  "properties": {
    "gn:admin1_code":"AL",
    "gn:admin2_code":"121",
    "gn:asciiname":"Overbrook",
    "gn:country_code":"US",
    "gn:dem":260,
    "gn:elevation":"240.0",
    "gn:feature_class":"P",
    "gn:feature_code":"PPL",
    "gn:name":"Overbrook",
    "gn:population":0,
    "gn:timezone":"America/Chicago",
    "iso:country":"US",
    "name:deu_x_preferred":[
        "Overbrook"
    ],
    "name:ita_x_preferred":[
        "Overbrook"
    ],
    "name:rus_x_preferred":[
        "\u041e\u0432\u0435\u0440\u0431\u0440\u0443\u043a"
    ],
    "wof:name":"Overbrook",
    "wof:placetype":"locality"
},
  "geometry": {"coordinates":[-86.19830999999998,33.12178],"type":"Point"}
}