{
  "type": "Feature",
  "properties": {
    "gn:admin1_code":"MO",
    "gn:admin2_code":"207.0",
    "gn:admin3_code":"11980.0",
    "gn:asciiname":"Aquilla",
    "gn:country_code":"US",
    "gn:dem":113,
    "gn:elevation":"110.0",
    "gn:feature_class":"P",
    "gn:feature_code":"PPL",
    "gn:name":"Aquilla",
    "gn:population":0,
    "gn:timezone":"America/Chicago",
    "iso:country":"US",
    "name:ceb_x_preferred":[
        "Aquilla"
    ],
    "name:deu_x_preferred":[
        "Aquilla"
    ],
    "name:ita_x_preferred":[
        "Aquilla"
    ],
    "name:nld_x_preferred":[
        "Aquilla"
    ],
    "name:pol_x_preferred":[
        "Aquilla"
    ],
    "name:srp_x_preferred":[
        "\u0410\u043a\u0432\u0438\u043b\u0430"
    ],
    "name:ukr_x_preferred":[
        "\u0410\u043a\u0432\u0456\u043b\u043b\u0430"
    ],
    "wof:name":"Aquilla",
    "wof:placetype":"locality"
},
  "geometry": {"coordinates":[-89.91481,36.947],"type":"Point"}
}