{
  "type": "Feature",
  "properties": {
    "gn:admin1_code":"ME",
    "gn:admin2_code":"19.0",
    "gn:admin3_code":"27190.0",
    "gn:asciiname":"Twin Brook",
    "gn:country_code":"US",
    "gn:dem":79,
    "gn:elevation":"75.0",
    "gn:feature_class":"P",
    "gn:feature_code":"PPL",
    "gn:name":"Twin Brook",
    "gn:population":0,
    "gn:timezone":"America/New_York",
    "iso:country":"US",
    "wof:name":"Twin Brook",
    "wof:placetype":"locality"
},
  "geometry": {"coordinates":[-69.1056,45.02562],"type":"Point"}
}