{
  "type": "Feature",
  "properties": {
    "gn:admin1_code":"IA",
    "gn:admin2_code":"181.0",
    "gn:admin3_code":"93624.0",
    "gn:asciiname":"Ford",
    "gn:country_code":"US",
    "gn:dem":230,
    "gn:elevation":"232.0",
    "gn:feature_class":"P",
    "gn:feature_code":"PPL",
    "gn:name":"Ford",
    "gn:population":0,
    "gn:timezone":"America/Chicago",
    "iso:country":"US",
    "wof:name":"Ford",
    "wof:placetype":"locality"
},
  "geometry": {"coordinates":[-93.38854000000001,41.48499],"type":"Point"}
}