{
  "type": "Feature",
  "properties": {
    "iso:country":"US",
    "name:deu_x_preferred":[
        "Argonne"
    ],
    "name:fra_x_preferred":[
        "Argonne"
    ],
    "name:ltz_x_preferred":[
        "Argonne"
    ],
    "name:ukr_x_preferred":[
        "\u0410\u0440\u0433\u043e\u043d\u043d"
    ],
    "qs_pg:aaroncc":"US",
    "qs_pg:name":"Argonne",
    "qs_pg:name_adm0":"United States",
    "qs_pg:name_adm1":"Illinois",
    "qs_pg:photos":361,
    "qs_pg:photos_1k":73,
    "qs_pg:photos_9k":2,
    "qs_pg:photos_9r":5,
    "qs_pg:photos_all":361,
    "qs_pg:photos_sr":6,
    "qs_pg:pop_sr":0,
    "qs_pg:qs_pg_placetype":"locality",
    "qs_pg:qs_pg_placetype_gp":"Town",
    "qs_pg:woe_adm0":23424977,
    "woe:adm0_id":23424977,
    "woe:name_adm0":"United States",
    "woe:name_adm1":"Illinois",
    "woe:placetype":"Town",
    "wof:name":"Argonne",
    "wof:placetype":"locality"
},
  "geometry": {"coordinates":[-88.007462,41.7059],"type":"Point"}
}