{
  "type": "Feature",
  "properties": {
    "gn:country":"US",
    "gn:fcode":"PPL",
    "gn:population":0,
    "iso:country":"US",
    "name:ara_x_preferred":[
        "\u0645\u0627\u0631\u062a\u064a\u0646\u0633\u0641\u064a\u0644"
    ],
    "name:cat_x_preferred":[
        "Martinsville"
    ],
    "name:ceb_x_preferred":[
        "Martinsville"
    ],
    "name:deu_x_preferred":[
        "Martinsville"
    ],
    "name:fra_x_preferred":[
        "Martinsville"
    ],
    "name:ita_x_preferred":[
        "Martinsville"
    ],
    "name:nld_x_preferred":[
        "Martinsville"
    ],
    "name:pol_x_preferred":[
        "Martinsville"
    ],
    "name:rus_x_preferred":[
        "\u041c\u0430\u0440\u0442\u0438\u043d\u0441\u0432\u0438\u043b\u043b"
    ],
    "name:srp_x_preferred":[
        "\u041c\u0430\u0440\u0442\u0438\u043d\u0441\u0432\u0438\u043b"
    ],
    "name:swe_x_preferred":[
        "Martinsville"
    ],
    "name:ukr_x_preferred":[
        "\u041c\u0430\u0440\u0442\u0456\u043d\u0441\u0432\u0456\u043b\u043b"
    ],
    "name:vol_x_preferred":[
        "Martinsville"
    ],
    "qs_pg:aaroncc":"US",
    "qs_pg:gn_country":"US",
    "qs_pg:gn_fcode":"PPL",
    "qs_pg:gn_pop":0,
    "qs_pg:name":"Martinsville",
    "qs_pg:name_adm0":"United States",
    "qs_pg:name_adm1":"Wisconsin",
    "qs_pg:photos":2,
    "qs_pg:photos_1k":1,
    "qs_pg:photos_9k":1,
    "qs_pg:photos_9r":1,
    "qs_pg:photos_all":2,
    "qs_pg:photos_sr":1,
    "qs_pg:pop_sr":5,
    "qs_pg:qs_pg_placetype":"neighbourhood",
    "qs_pg:qs_pg_placetype_gp":"Suburb",
    "qs_pg:woe_adm0":23424977,
    "woe:adm0_id":23424977,
    "woe:name_adm0":"United States",
    "woe:name_adm1":"Wisconsin",
    "woe:placetype":"Suburb",
    "wof:name":"Martinsville",
    "wof:placetype":"neighbourhood"
},
  "geometry": {"coordinates":[-89.59012,43.18027],"type":"Point"}
}