{
  "type": "Feature",
  "properties": {
    "gn:admin1_code":"WI",
    "gn:admin2_code":"39.0",
    "gn:admin3_code":"49650.0",
    "gn:asciiname":"Calvary",
    "gn:country_code":"US",
    "gn:dem":287,
    "gn:elevation":"288.0",
    "gn:feature_class":"P",
    "gn:feature_code":"PPL",
    "gn:name":"Calvary",
    "gn:population":0,
    "gn:timezone":"America/Chicago",
    "iso:country":"US",
    "wof:name":"Calvary",
    "wof:placetype":"locality"
},
  "geometry": {"coordinates":[-88.24399,43.84666],"type":"Point"}
}