{
  "type": "Feature",
  "properties": {
    "gn:admin1_code":"MD",
    "gn:admin2_code":"47.0",
    "gn:asciiname":"Louis Heights",
    "gn:country_code":"US",
    "gn:dem":7,
    "gn:elevation":"5.0",
    "gn:feature_class":"P",
    "gn:feature_code":"PPL",
    "gn:name":"Louis Heights",
    "gn:population":0,
    "gn:timezone":"America/New_York",
    "iso:country":"US",
    "wof:name":"Louis Heights",
    "wof:placetype":"locality"
},
  "geometry": {"coordinates":[-75.16574,38.42706],"type":"Point"}
}