{
  "type": "Feature",
  "properties": {
    "gn:country":"US",
    "gn:fcode":"PPL",
    "gn:population":0,
    "iso:country":"US",
    "name:deu_x_preferred":[
        "Enos"
    ],
    "name:fra_x_preferred":[
        "Enos"
    ],
    "name:heb_x_preferred":[
        "\u05d0\u05e0\u05d5\u05e9"
    ],
    "name:hun_x_preferred":[
        "\u00c9nos"
    ],
    "name:ind_x_preferred":[
        "Enos"
    ],
    "name:ita_x_preferred":[
        "Enos"
    ],
    "name:nld_x_preferred":[
        "Enos"
    ],
    "name:pol_x_preferred":[
        "Enos"
    ],
    "name:spa_x_preferred":[
        "En\u00f3s"
    ],
    "qs_pg:aaroncc":"US",
    "qs_pg:gn_country":"US",
    "qs_pg:gn_fcode":"PPL",
    "qs_pg:gn_pop":0,
    "qs_pg:name":"Enos",
    "qs_pg:name_adm0":"United States",
    "qs_pg:name_adm1":"South Carolina",
    "qs_pg:photos":166,
    "qs_pg:photos_1k":34,
    "qs_pg:photos_9k":1,
    "qs_pg:photos_9r":4,
    "qs_pg:photos_all":166,
    "qs_pg:photos_sr":4,
    "qs_pg:pop_sr":0,
    "qs_pg:qs_pg_placetype":"locality",
    "qs_pg:qs_pg_placetype_gp":"Town",
    "qs_pg:woe_adm0":23424977,
    "woe:adm0_id":23424977,
    "woe:name_adm0":"United States",
    "woe:name_adm1":"South Carolina",
    "woe:placetype":"Town",
    "wof:name":"Enos",
    "wof:placetype":"locality"
},
  "geometry": {"coordinates":[-81.0462,33.79738],"type":"Point"}
}