{
  "type": "Feature",
  "properties": {
    "gn:admin1_code":"ND",
    "gn:admin2_code":"45.0",
    "gn:admin3_code":"30420.0",
    "gn:asciiname":"Benson Corner",
    "gn:country_code":"US",
    "gn:dem":440,
    "gn:elevation":"441.0",
    "gn:feature_class":"P",
    "gn:feature_code":"PPL",
    "gn:name":"Benson Corner",
    "gn:population":0,
    "gn:timezone":"America/Chicago",
    "iso:country":"US",
    "name:eng_x_preferred":[
        "Benson Corner"
    ],
    "name:und_x_variant":[
        "Benson Corners",
        "Benson"
    ],
    "wof:name":"Benson Corner",
    "wof:placetype":"locality"
},
  "geometry": {"coordinates":[-98.20149000000001,46.48581],"type":"Point"}
}