{
  "type": "Feature",
  "properties": {
    "gn:admin1_code":"MD",
    "gn:admin2_code":"9.0",
    "gn:asciiname":"Carriage Hills",
    "gn:country_code":"US",
    "gn:dem":45,
    "gn:elevation":"42.0",
    "gn:feature_class":"P",
    "gn:feature_code":"PPL",
    "gn:name":"Carriage Hills",
    "gn:population":0,
    "gn:timezone":"America/New_York",
    "iso:country":"US",
    "wof:name":"Carriage Hills",
    "wof:placetype":"locality"
},
  "geometry": {"coordinates":[-76.61357,38.63568],"type":"Point"}
}