{
  "type": "Feature",
  "properties": {
    "gn:admin1_code":"GA",
    "gn:admin2_code":"113.0",
    "gn:asciiname":"Marion",
    "gn:country_code":"US",
    "gn:dem":289,
    "gn:elevation":"278.0",
    "gn:feature_class":"P",
    "gn:feature_code":"PPL",
    "gn:name":"Marion",
    "gn:population":0,
    "gn:timezone":"America/New_York",
    "iso:country":"US",
    "name:ben_x_preferred":[
        "\u09ae\u09cd\u09af\u09be\u09b0\u09bf\u09df\u09a8"
    ],
    "name:bre_x_preferred":[
        "Marion"
    ],
    "name:cat_x_preferred":[
        "Marion"
    ],
    "name:ceb_x_preferred":[
        "Marion"
    ],
    "name:ces_x_preferred":[
        "Marion"
    ],
    "name:deu_x_preferred":[
        "Marion"
    ],
    "name:ell_x_preferred":[
        "\u039c\u03ac\u03c1\u03b9\u03bf\u03bd"
    ],
    "name:fas_x_preferred":[
        "\u0645\u0627\u0631\u06cc\u0648\u0646"
    ],
    "name:fin_x_preferred":[
        "Marion"
    ],
    "name:fra_x_preferred":[
        "Marion"
    ],
    "name:hun_x_preferred":[
        "Marion"
    ],
    "name:ind_x_preferred":[
        "Marion"
    ],
    "name:ita_x_preferred":[
        "Marion"
    ],
    "name:jpn_x_preferred":[
        "\u30de\u30ea\u30aa\u30f3"
    ],
    "name:kor_x_preferred":[
        "\ub9e4\ub9ac\uc5b8"
    ],
    "name:nld_x_preferred":[
        "Marion"
    ],
    "name:nor_x_preferred":[
        "Marion"
    ],
    "name:pol_x_preferred":[
        "Marion"
    ],
    "name:por_x_preferred":[
        "Marion"
    ],
    "name:ron_x_preferred":[
        "Marion"
    ],
    "name:rus_x_preferred":[
        "\u041c\u0430\u0440\u0438\u043e\u043d"
    ],
    "name:spa_x_preferred":[
        "Marion"
    ],
    "name:srp_x_preferred":[
        "\u041c\u0430\u0440\u0438\u043e\u043d"
    ],
    "name:swe_x_preferred":[
        "Marion"
    ],
    "name:ukr_x_preferred":[
        "\u041c\u0430\u0440\u0456\u043e\u043d"
    ],
    "name:urd_x_preferred":[
        "\u0645\u0627\u0631\u06cc\u0648\u0646"
    ],
    "name:vie_x_preferred":[
        "Marion"
    ],
    "name:vol_x_preferred":[
        "Marion"
    ],
    "name:war_x_preferred":[
        "Marion"
    ],
    "name:zho_x_preferred":[
        "\u9a6c\u91cc\u6602"
    ],
    "wof:name":"Marion",
    "wof:placetype":"locality"
},
  "geometry": {"coordinates":[-84.44548,33.42456],"type":"Point"}
}