{
  "type": "Feature",
  "properties": {
    "gn:admin1_code":"CA",
    "gn:admin2_code":"27",
    "gn:asciiname":"Harrisburg",
    "gn:country_code":"US",
    "gn:dem":1517,
    "gn:elevation":"1520.0",
    "gn:feature_class":"P",
    "gn:feature_code":"PPL",
    "gn:name":"Harrisburg",
    "gn:population":0,
    "gn:timezone":"America/Los_Angeles",
    "iso:country":"US",
    "name:eng_x_preferred":[
        "Harrisburg"
    ],
    "name:und_x_variant":[
        "Harrisberry"
    ],
    "wof:name":"Harrisburg",
    "wof:placetype":"locality"
},
  "geometry": {"coordinates":[-117.11145,36.36384],"type":"Point"}
}