{
  "type": "Feature",
  "properties": {
    "gn:admin1_code":"TX",
    "gn:admin2_code":"257.0",
    "gn:asciiname":"Ables Springs",
    "gn:country_code":"US",
    "gn:dem":166,
    "gn:elevation":"158.0",
    "gn:feature_class":"P",
    "gn:feature_code":"PPL",
    "gn:name":"Ables Springs",
    "gn:population":0,
    "gn:timezone":"America/Chicago",
    "iso:country":"US",
    "name:deu_x_preferred":[
        "Ables Springs"
    ],
    "name:por_x_preferred":[
        "Ables Springs"
    ],
    "wof:name":"Ables Springs",
    "wof:placetype":"locality"
},
  "geometry": {"coordinates":[-96.12108000000001,32.81485],"type":"Point"}
}