{
  "type": "Feature",
  "properties": {
    "gn:admin1_code":"IL",
    "gn:admin2_code":"3.0",
    "gn:asciiname":"Unity",
    "gn:country_code":"US",
    "gn:dem":102,
    "gn:elevation":"102.0",
    "gn:feature_class":"P",
    "gn:feature_code":"PPL",
    "gn:name":"Unity",
    "gn:population":0,
    "gn:timezone":"America/Chicago",
    "iso:country":"US",
    "name:eng_x_preferred":[
        "Unity"
    ],
    "name:fas_x_preferred":[
        "\u06cc\u0648\u0646\u06cc\u062a\u06cc"
    ],
    "name:hun_x_preferred":[
        "Unity"
    ],
    "name:und_x_variant":[
        "Hodges Park Station"
    ],
    "wof:name":"Unity",
    "wof:placetype":"locality"
},
  "geometry": {"coordinates":[-89.27285999999999,37.14977],"type":"Point"}
}