{
  "type": "Feature",
  "properties": {
    "iso:country":"US",
    "name:eng_x_preferred":[
        "Nela Park"
    ],
    "wd:wordcount":239,
    "wof:name":"Nela Park",
    "wof:placetype":"neighbourhood",
    "wof:population":65,
    "zs:area_m":66124.908834,
    "zs:blockids":[
        390351179003002
    ],
    "zs:housing10":37,
    "zs:label":"Nela Park",
    "zs:pop10":65
},
  "geometry": {"coordinates":[-81.562473,41.550775],"type":"Point"}
}