{
  "type": "Feature",
  "properties": {
    "gn:admin1_code":"OH",
    "gn:admin2_code":"165",
    "gn:admin3_code":"33474.0",
    "gn:asciiname":"Hicks",
    "gn:country_code":"US",
    "gn:dem":237,
    "gn:elevation":"235.0",
    "gn:feature_class":"P",
    "gn:feature_code":"PPL",
    "gn:name":"Hicks",
    "gn:population":0,
    "gn:timezone":"America/New_York",
    "iso:country":"US",
    "name:ces_x_preferred":[
        "Hicks"
    ],
    "name:deu_x_preferred":[
        "Hicks"
    ],
    "name:eng_x_preferred":[
        "Hicks"
    ],
    "name:fin_x_preferred":[
        "Hicks"
    ],
    "name:fra_x_preferred":[
        "Hicks"
    ],
    "name:heb_x_preferred":[
        "\u05d4\u05d9\u05e7\u05e1"
    ],
    "name:ita_x_preferred":[
        "Hicks"
    ],
    "name:jpn_x_preferred":[
        "\u30d2\u30c3\u30af\u30b9"
    ],
    "name:nds_x_preferred":[
        "Hicks"
    ],
    "name:por_x_preferred":[
        "Hicks"
    ],
    "name:rus_x_preferred":[
        "\u0425\u0438\u043a\u0441"
    ],
    "name:ukr_x_preferred":[
        "\u0413\u0456\u043a\u0441"
    ],
    "name:und_x_variant":[
        "Hick Station"
    ],
    "wof:name":"Hicks",
    "wof:placetype":"locality"
},
  "geometry": {"coordinates":[-84.05604,39.35839],"type":"Point"}
}