{
  "type": "Feature",
  "properties": {
    "gn:admin1_code":"MS",
    "gn:admin2_code":"113.0",
    "gn:asciiname":"Pitts",
    "gn:country_code":"US",
    "gn:dem":112,
    "gn:elevation":"109.0",
    "gn:feature_class":"P",
    "gn:feature_code":"PPL",
    "gn:name":"Pitts",
    "gn:population":0,
    "gn:timezone":"America/Chicago",
    "iso:country":"US",
    "name:deu_x_preferred":[
        "Pitts"
    ],
    "name:fra_x_preferred":[
        "Pitts"
    ],
    "name:por_x_preferred":[
        "Pitts"
    ],
    "wof:name":"Pitts",
    "wof:placetype":"locality"
},
  "geometry": {"coordinates":[-90.4126,31.18907],"type":"Point"}
}