{
  "type": "Feature",
  "properties": {
    "iso:country":"US",
    "name:eng_x_preferred":[
        "Bull's Head"
    ],
    "wof:name":"Bull's Head",
    "wof:placetype":"neighbourhood"
},
  "geometry": {"coordinates":[-77.63700730776468,43.14987931766456],"type":"Point"}
}