{
  "type": "Feature",
  "properties": {
    "gn:admin1_code":"NC",
    "gn:admin2_code":"147.0",
    "gn:admin3_code":"94072.0",
    "gn:asciiname":"Planters Walk",
    "gn:country_code":"US",
    "gn:dem":22,
    "gn:elevation":"21.0",
    "gn:feature_class":"P",
    "gn:feature_code":"PPL",
    "gn:name":"Planters Walk",
    "gn:population":0,
    "gn:timezone":"America/New_York",
    "iso:country":"US",
    "wof:name":"Planters Walk",
    "wof:placetype":"locality"
},
  "geometry": {"coordinates":[-77.34191,35.57599000000001],"type":"Point"}
}