{
  "type": "Feature",
  "properties": {
    "gn:country":"US",
    "gn:fcode":"PPL",
    "gn:population":0,
    "iso:country":"US",
    "name:azb_x_preferred":[
        "\u0648\u0627\u0631\u0646\u0631 \u0627\u0633\u067e\u0631\u06cc\u0646\u0642\u0632"
    ],
    "name:eng_x_preferred":[
        "Warner Springs"
    ],
    "name:fas_x_preferred":[
        "\u0648\u0627\u0631\u0646\u0631 \u0627\u0633\u067e\u0631\u06cc\u0646\u06af\u0632"
    ],
    "name:fra_x_preferred":[
        "Warner Springs"
    ],
    "name:nld_x_preferred":[
        "Warner Springs"
    ],
    "name:spa_x_preferred":[
        "Warner Springs"
    ],
    "name:tur_x_preferred":[
        "Warner Springs"
    ],
    "name:zho_x_preferred":[
        "\u83ef\u7d0d\u6cc9"
    ],
    "qs_pg:aaroncc":"US",
    "qs_pg:gn_country":"US",
    "qs_pg:gn_fcode":"PPL",
    "qs_pg:gn_pop":0,
    "qs_pg:name":"Warner Springs",
    "qs_pg:name_adm0":"United States",
    "qs_pg:name_adm1":"California",
    "qs_pg:photos":933,
    "qs_pg:photos_1k":189,
    "qs_pg:photos_9k":4,
    "qs_pg:photos_9r":6,
    "qs_pg:photos_all":933,
    "qs_pg:photos_sr":10,
    "qs_pg:pop_sr":5,
    "qs_pg:qs_pg_placetype":"locality",
    "qs_pg:qs_pg_placetype_gp":"Town",
    "qs_pg:woe_adm0":23424977,
    "woe:adm0_id":23424977,
    "woe:name_adm0":"United States",
    "woe:name_adm1":"California",
    "woe:placetype":"Town",
    "wof:name":"Warner Springs",
    "wof:placetype":"locality"
},
  "geometry": {"coordinates":[-116.63363,33.28226],"type":"Point"}
}