{
  "type": "Feature",
  "properties": {
    "gn:admin1_code":"MO",
    "gn:admin2_code":"181.0",
    "gn:admin3_code":"30448.0",
    "gn:asciiname":"Current View",
    "gn:country_code":"US",
    "gn:dem":104,
    "gn:elevation":"102.0",
    "gn:feature_class":"P",
    "gn:feature_code":"PPL",
    "gn:name":"Current View",
    "gn:population":0,
    "gn:timezone":"America/Chicago",
    "iso:country":"US",
    "name:eng_x_preferred":[
        "Current View"
    ],
    "name:und_x_variant":[
        "Currentview"
    ],
    "wof:name":"Current View",
    "wof:placetype":"locality"
},
  "geometry": {"coordinates":[-90.77818000000001,36.49895],"type":"Point"}
}