{
  "type": "Feature",
  "properties": {
    "gn:admin1_code":"FL",
    "gn:admin2_code":"95.0",
    "gn:asciiname":"Oak Tree Park",
    "gn:country_code":"US",
    "gn:dem":44,
    "gn:elevation":"33.0",
    "gn:feature_class":"P",
    "gn:feature_code":"PPL",
    "gn:name":"Oak Tree Park",
    "gn:population":0,
    "gn:timezone":"America/New_York",
    "iso:country":"US",
    "wof:name":"Oak Tree Park",
    "wof:placetype":"locality"
},
  "geometry": {"coordinates":[-81.55887,28.75395],"type":"Point"}
}