{
  "type": "Feature",
  "properties": {
    "gn:admin1_code":"NC",
    "gn:admin2_code":"159",
    "gn:admin3_code":"91840.0",
    "gn:asciiname":"Correll Park",
    "gn:country_code":"US",
    "gn:dem":254,
    "gn:elevation":"253.0",
    "gn:feature_class":"P",
    "gn:feature_code":"PPL",
    "gn:name":"Correll Park",
    "gn:population":0,
    "gn:timezone":"America/New_York",
    "iso:country":"US",
    "wof:name":"Correll Park",
    "wof:placetype":"locality"
},
  "geometry": {"coordinates":[-80.49923000000003,35.60264],"type":"Point"}
}