{
  "type": "Feature",
  "properties": {
    "gn:admin1_code":"OH",
    "gn:admin2_code":"49.0",
    "gn:admin3_code":"37772.0",
    "gn:asciiname":"Meadow Grove",
    "gn:country_code":"US",
    "gn:dem":245,
    "gn:elevation":"245.0",
    "gn:feature_class":"P",
    "gn:feature_code":"PPL",
    "gn:name":"Meadow Grove",
    "gn:population":0,
    "gn:timezone":"America/New_York",
    "iso:country":"US",
    "wof:name":"Meadow Grove",
    "wof:placetype":"locality"
},
  "geometry": {"coordinates":[-83.06824,39.8507],"type":"Point"}
}