{
  "type": "Feature",
  "properties": {
    "iso:country":"US",
    "name:eng_x_preferred":[
        "Echo Hills"
    ],
    "name:eng_x_variant":[
        "Echo Hls"
    ],
    "qs:gn_adm0_cc":"US",
    "qs:gn_local":4453066,
    "qs:gn_nam_loc":"Asheville, Buncombe, North Carolina, US",
    "qs:gn_namadm1":"NC",
    "qs:local_max":10696,
    "qs:local_sum":28334,
    "qs:localhoods":33,
    "qs:name":"Echo Hills",
    "qs:name_adm0":"United States",
    "qs:name_adm1":"North Carolina",
    "qs:name_adm2":"Buncombe",
    "qs:name_local":"Asheville",
    "qs:photo_max":2,
    "qs:photo_sum":2,
    "qs:placetype":"Suburb",
    "qs:quad_count":1,
    "qs:woe_adm0":23424977,
    "qs:woe_adm1":2347592,
    "qs:woe_adm2":12589384,
    "qs:woe_lau":0,
    "qs:woe_local":2356566,
    "qs:woe_ver":"7.10.0",
    "wof:lang":[
        "eng"
    ],
    "wof:name":"Echo Hills",
    "wof:placetype":"neighbourhood",
    "wof:population":1238,
    "zs:blockids":[
        370210013002015,
        370210013002016,
        370210012002002,
        370210012001005,
        370210012001014,
        370210013001000,
        370210012001017,
        370210012001022,
        370210013002003,
        370210012002010,
        370210013002018,
        370210012001015,
        370210012001006,
        370210013002001,
        370210012001004,
        370210012002008,
        370210014005018,
        370210013002002,
        370210013002038,
        370210012002001,
        370210012001011,
        370210012001012,
        370210012003000,
        370210013002014,
        370210012001001,
        370210012001016,
        370210012001007,
        370210012002003,
        370210012001020,
        370210013002017,
        370210012002006,
        370210012002004,
        370210013002039,
        370210013002013,
        370210012001003,
        370210012002000,
        370210014005027,
        370210013002000,
        370210012001021
    ],
    "zs:housing10":589,
    "zs:pop10":1238
},
  "geometry": {"coordinates":[-82.608948,35.583618],"type":"Point"}
}