{
  "type": "Feature",
  "properties": {
    "gn:admin1_code":"FL",
    "gn:admin2_code":"103.0",
    "gn:asciiname":"Lakewood Estates",
    "gn:country_code":"US",
    "gn:dem":14,
    "gn:elevation":"6.0",
    "gn:feature_class":"P",
    "gn:feature_code":"PPL",
    "gn:name":"Lakewood Estates",
    "gn:population":0,
    "gn:timezone":"America/New_York",
    "iso:country":"US",
    "wof:name":"Lakewood Estates",
    "wof:placetype":"locality"
},
  "geometry": {"coordinates":[-82.66731999999998,27.72781],"type":"Point"}
}