{
  "type": "Feature",
  "properties": {
    "gn:admin1_code":"GA",
    "gn:admin2_code":"223.0",
    "gn:asciiname":"Cross Road Farms",
    "gn:country_code":"US",
    "gn:dem":307,
    "gn:elevation":"306.0",
    "gn:feature_class":"P",
    "gn:feature_code":"PPL",
    "gn:name":"Cross Road Farms",
    "gn:population":0,
    "gn:timezone":"America/New_York",
    "iso:country":"US",
    "wof:name":"Cross Road Farms",
    "wof:placetype":"locality"
},
  "geometry": {"coordinates":[-84.7666,34.01538],"type":"Point"}
}