{
  "type": "Feature",
  "properties": {
    "gn:admin1_code":"AZ",
    "gn:admin2_code":"13.0",
    "gn:asciiname":"Gladden",
    "gn:country_code":"US",
    "gn:dem":669,
    "gn:elevation":"671.0",
    "gn:feature_class":"P",
    "gn:feature_code":"PPL",
    "gn:name":"Gladden",
    "gn:population":0,
    "gn:timezone":"America/Phoenix",
    "iso:country":"US",
    "name:deu_x_preferred":[
        "Gladden"
    ],
    "wof:name":"Gladden",
    "wof:placetype":"locality"
},
  "geometry": {"coordinates":[-113.29935999999999,33.90253],"type":"Point"}
}