{
  "type": "Feature",
  "properties": {
    "iso:country":"US",
    "name:bre_x_preferred":[
        "Hermitage"
    ],
    "name:ceb_x_preferred":[
        "Hermitage"
    ],
    "name:deu_x_preferred":[
        "Hermitage"
    ],
    "name:eng_x_preferred":[
        "Hermitage"
    ],
    "name:fra_x_preferred":[
        "Hermitage"
    ],
    "name:ita_x_preferred":[
        "Hermitage"
    ],
    "name:jpn_x_preferred":[
        "\u30a8\u30eb\u30df\u30bf\u30fc\u30b8\u30e5"
    ],
    "name:lim_x_preferred":[
        "Hermitage"
    ],
    "name:nds_x_preferred":[
        "Hermitage"
    ],
    "name:nld_x_preferred":[
        "Hermitage"
    ],
    "name:pol_x_preferred":[
        "Hermitage"
    ],
    "name:por_x_preferred":[
        "Hermitage"
    ],
    "name:rus_x_preferred":[
        "\u042d\u0440\u043c\u0438\u0442\u0430\u0436"
    ],
    "name:srp_x_preferred":[
        "\u0425\u0435\u0440\u043c\u0438\u0442\u0438\u045f"
    ],
    "name:swe_x_preferred":[
        "Hermitage"
    ],
    "name:tat_x_preferred":[
        "\u042d\u0440\u043c\u0438\u0442\u0430\u0436"
    ],
    "name:ukr_x_preferred":[
        "\u0415\u0440\u043c\u0456\u0442\u0430\u0436"
    ],
    "name:vol_x_preferred":[
        "Hermitage"
    ],
    "wof:name":"Hermitage",
    "wof:placetype":"neighbourhood",
    "wof:population":797,
    "zs:area_m":1245805.663018,
    "zs:blockids":[
        370510020012002,
        370510020012017,
        370510020012014,
        370510020012013,
        370510020012015,
        370510020012006,
        370510020012012,
        370510020012005,
        370510020012016,
        370510020012003
    ],
    "zs:housing10":372,
    "zs:label":"Hermitage",
    "zs:pop10":797
},
  "geometry": {"coordinates":[-78.975269,35.068284],"type":"Point"}
}