{
  "type": "Feature",
  "properties": {
    "gn:admin1_code":"AZ",
    "gn:admin2_code":"13.0",
    "gn:asciiname":"Pecan Grove Trailer Park",
    "gn:country_code":"US",
    "gn:dem":335,
    "gn:elevation":"339.0",
    "gn:feature_class":"P",
    "gn:feature_code":"PPL",
    "gn:name":"Pecan Grove Trailer Park",
    "gn:population":0,
    "gn:timezone":"America/Phoenix",
    "iso:country":"US",
    "wof:name":"Pecan Grove Trailer Park",
    "wof:placetype":"campus"
},
  "geometry": {"coordinates":[-112.11654,33.48782],"type":"Point"}
}