{
  "type": "Feature",
  "properties": {
    "gn:admin1_code":"PA",
    "gn:admin2_code":"77.0",
    "gn:admin3_code":"79104.0",
    "gn:asciiname":"Haines",
    "gn:country_code":"US",
    "gn:dem":135,
    "gn:elevation":"133.0",
    "gn:feature_class":"P",
    "gn:feature_code":"PPL",
    "gn:name":"Haines",
    "gn:population":0,
    "gn:timezone":"America/New_York",
    "iso:country":"US",
    "name:ceb_x_preferred":[
        "Haines"
    ],
    "name:deu_x_preferred":[
        "Haines"
    ],
    "name:fin_x_preferred":[
        "Haines"
    ],
    "name:fra_x_preferred":[
        "Haines"
    ],
    "name:hun_x_preferred":[
        "Haines"
    ],
    "name:ita_x_preferred":[
        "Haines"
    ],
    "name:nds_x_preferred":[
        "Haines"
    ],
    "name:nld_x_preferred":[
        "Haines"
    ],
    "name:pol_x_preferred":[
        "Haines"
    ],
    "name:por_x_preferred":[
        "Haines"
    ],
    "name:spa_x_preferred":[
        "Haines"
    ],
    "name:srp_x_preferred":[
        "\u0425\u0430\u0458\u043d\u0441"
    ],
    "name:vol_x_preferred":[
        "Haines"
    ],
    "wof:name":"Haines",
    "wof:placetype":"locality"
},
  "geometry": {"coordinates":[-75.61658,40.57065],"type":"Point"}
}