{
  "type": "Feature",
  "properties": {
    "gn:admin1_code":"KY",
    "gn:admin2_code":"31",
    "gn:asciiname":"Neafus",
    "gn:country_code":"US",
    "gn:dem":194,
    "gn:elevation":"191.0",
    "gn:feature_class":"P",
    "gn:feature_code":"PPL",
    "gn:name":"Neafus",
    "gn:population":0,
    "gn:timezone":"America/Chicago",
    "iso:country":"US",
    "wof:name":"Neafus",
    "wof:placetype":"locality"
},
  "geometry": {"coordinates":[-86.61193,37.39505],"type":"Point"}
}