{
  "type": "Feature",
  "properties": {
    "gn:admin1_code":"DE",
    "gn:admin2_code":"3.0",
    "gn:asciiname":"Carpenter",
    "gn:country_code":"US",
    "gn:dem":48,
    "gn:elevation":"48.0",
    "gn:feature_class":"P",
    "gn:feature_code":"PPL",
    "gn:name":"Carpenter",
    "gn:population":0,
    "gn:timezone":"America/New_York",
    "iso:country":"US",
    "name:zho_x_preferred":[
        "\u5361\u5f6d\u7279"
    ],
    "wof:name":"Carpenter",
    "wof:placetype":"locality"
},
  "geometry": {"coordinates":[-75.46436,39.81845],"type":"Point"}
}