{
  "type": "Feature",
  "properties": {
    "gn:admin1_code":"MI",
    "gn:admin2_code":"31.0",
    "gn:admin3_code":"40820.0",
    "gn:asciiname":"Mullett Lake",
    "gn:country_code":"US",
    "gn:dem":181,
    "gn:elevation":"183.0",
    "gn:feature_class":"P",
    "gn:feature_code":"PPL",
    "gn:name":"Mullett Lake",
    "gn:population":0,
    "gn:timezone":"America/Detroit",
    "iso:country":"US",
    "name:ceb_x_preferred":[
        "Mullett Lake"
    ],
    "name:eng_x_preferred":[
        "Mullett Lake"
    ],
    "name:und_x_variant":[
        "Mullett",
        "Mullet Lake"
    ],
    "wof:name":"Mullett Lake",
    "wof:placetype":"locality"
},
  "geometry": {"coordinates":[-84.52559000000002,45.56196],"type":"Point"}
}