{
  "type": "Feature",
  "properties": {
    "gn:admin1_code":"TN",
    "gn:admin2_code":"91.0",
    "gn:asciiname":"Shingletown",
    "gn:country_code":"US",
    "gn:dem":781,
    "gn:elevation":"778.0",
    "gn:feature_class":"P",
    "gn:feature_code":"PPL",
    "gn:name":"Shingletown",
    "gn:population":0,
    "gn:timezone":"America/New_York",
    "iso:country":"US",
    "name:eng_x_preferred":[
        "Shingletown"
    ],
    "name:und_x_variant":[
        "Shingleton"
    ],
    "wof:name":"Shingletown",
    "wof:placetype":"locality"
},
  "geometry": {"coordinates":[-81.78789,36.5504],"type":"Point"}
}