{
  "type": "Feature",
  "properties": {
    "gn:admin1_code":"GA",
    "gn:admin2_code":"135.0",
    "gn:asciiname":"Edgemoor",
    "gn:country_code":"US",
    "gn:dem":304,
    "gn:elevation":"300.0",
    "gn:feature_class":"P",
    "gn:feature_code":"PPL",
    "gn:name":"Edgemoor",
    "gn:population":0,
    "gn:timezone":"America/New_York",
    "iso:country":"US",
    "wof:name":"Edgemoor",
    "wof:placetype":"locality"
},
  "geometry": {"coordinates":[-84.18964,33.94455],"type":"Point"}
}