{
  "type": "Feature",
  "properties": {
    "gn:gn_country":"US",
    "gn:gn_fcode":"PPL",
    "gn:gn_pop":0,
    "iso:country":"US",
    "name:eng_x_preferred":[
        "Dungeness"
    ],
    "name:spa_x_preferred":[
        "Dungeness"
    ],
    "name:zho_x_preferred":[
        "\u9127\u5091\u5167\u65af"
    ],
    "qs_pg:aaroncc":"US",
    "qs_pg:gn_country":"US",
    "qs_pg:gn_fcode":"PPL",
    "qs_pg:gn_pop":0,
    "qs_pg:name":"Dungeness",
    "qs_pg:name_adm0":"United States",
    "qs_pg:name_adm1":"Georgia",
    "qs_pg:photos":1737,
    "qs_pg:photos_1k":352,
    "qs_pg:photos_9k":8,
    "qs_pg:photos_9r":8,
    "qs_pg:photos_all":1737,
    "qs_pg:photos_sr":14,
    "qs_pg:pop_sr":0,
    "qs_pg:qs_pg_placetype":"locality",
    "qs_pg:qs_pg_placetype_gp":"Town",
    "qs_pg:woe_adm0":23424977,
    "woe:adm0_id":23424977,
    "woe:name_adm0":"United States",
    "woe:name_adm1":"Georgia",
    "woe:placetype":"Town",
    "wof:name":"Dungeness",
    "wof:placetype":"locality"
},
  "geometry": {"coordinates":[-81.46732,30.74829],"type":"Point"}
}