{
  "type": "Feature",
  "properties": {
    "gn:admin1_code":"GA",
    "gn:admin2_code":"77",
    "gn:asciiname":"Smokey Acres",
    "gn:country_code":"US",
    "gn:dem":281,
    "gn:elevation":"275.0",
    "gn:feature_class":"P",
    "gn:feature_code":"PPL",
    "gn:name":"Smokey Acres",
    "gn:population":0,
    "gn:timezone":"America/New_York",
    "iso:country":"US",
    "wof:name":"Smokey Acres",
    "wof:placetype":"locality"
},
  "geometry": {"coordinates":[-84.82465999999999,33.35845],"type":"Point"}
}