{
  "type": "Feature",
  "properties": {
    "iso:country":"US",
    "name:eng_x_preferred":[
        "Citrus Pointe"
    ],
    "wof:name":"Citrus Pointe",
    "wof:placetype":"neighbourhood",
    "wof:population":1176,
    "zs:area_m":1540462.951622,
    "zs:blockids":[
        120570114121009,
        120570114121011,
        120570114121013,
        120570114121010,
        120570114121008,
        120570114121012
    ],
    "zs:housing10":531,
    "zs:label":"Citrus Pointe",
    "zs:pop10":1176
},
  "geometry": {"coordinates":[-82.57583,28.071708],"type":"Point"}
}