{
  "type": "Feature",
  "properties": {
    "gn:admin1_code":"VT",
    "gn:admin2_code":"9.0",
    "gn:admin3_code":"42475.0",
    "gn:asciiname":"Stevens",
    "gn:country_code":"US",
    "gn:dem":270,
    "gn:elevation":"270.0",
    "gn:feature_class":"P",
    "gn:feature_code":"PPL",
    "gn:name":"Stevens",
    "gn:population":0,
    "gn:timezone":"America/New_York",
    "iso:country":"US",
    "name:cat_x_preferred":[
        "Stevens"
    ],
    "name:ceb_x_preferred":[
        "Stevens"
    ],
    "name:ces_x_preferred":[
        "Stevens"
    ],
    "name:deu_x_preferred":[
        "Stevens"
    ],
    "name:fas_x_preferred":[
        "\u0627\u0633\u062a\u06cc\u0648\u0646\u0632"
    ],
    "name:fra_x_preferred":[
        "Stevens"
    ],
    "name:heb_x_preferred":[
        "\u05e1\u05d8\u05d9\u05d1\u05e0\u05e1"
    ],
    "name:ita_x_preferred":[
        "Stevens"
    ],
    "name:jpn_x_preferred":[
        "\u30b9\u30c6\u30a3\u30fc\u30f4\u30f3\u30b9"
    ],
    "name:nld_x_preferred":[
        "Stevens"
    ],
    "name:pol_x_preferred":[
        "Stevens"
    ],
    "name:rus_x_preferred":[
        "\u0421\u0442\u0435\u0432\u0435\u043d\u0441"
    ],
    "name:slv_x_preferred":[
        "Stevens"
    ],
    "name:spa_x_preferred":[
        "Stevens"
    ],
    "name:swe_x_preferred":[
        "Stevens"
    ],
    "wof:name":"Stevens",
    "wof:placetype":"locality"
},
  "geometry": {"coordinates":[-71.56064000000001,44.59811],"type":"Point"}
}