{
  "type": "Feature",
  "properties": {
    "gn:elevation":79,
    "iso:country":"US",
    "name:eng_x_preferred":[
        "Talcose"
    ],
    "qs:gn_adm0_cc":"US",
    "qs:gn_fcode":"PPL",
    "qs:gn_local":4557670,
    "qs:gn_nam_loc":"East Bradford, Chester, Pennsylvania, US",
    "qs:gn_namadm1":"PA",
    "qs:gn_name":"Talcose",
    "qs:local_max":110,
    "qs:local_sum":288,
    "qs:localhoods":6,
    "qs:name":"Talcose",
    "qs:name_adm0":"United States",
    "qs:name_adm1":"Pennsylvania",
    "qs:name_adm2":"Chester",
    "qs:name_local":"East Bradford",
    "qs:photo_max":4,
    "qs:photo_sum":13,
    "qs:placetype":"Suburb",
    "qs:quad_count":7,
    "qs:woe_adm0":23424977,
    "qs:woe_adm1":2347597,
    "qs:woe_adm2":12589742,
    "qs:woe_lau":0,
    "qs:woe_local":28745201,
    "qs:woe_ver":"7.10.0",
    "wof:lang":[
        "eng"
    ],
    "wof:name":"Talcose",
    "wof:placetype":"neighbourhood",
    "wof:population":666,
    "zs:blockids":[
        420293039021029,
        420293039021003,
        420293039021004,
        420293040002050,
        420293039021008,
        420293039021009,
        420293039021011,
        420293040002027,
        420293039021032,
        420293039021010,
        420293039021002,
        420293039021007
    ],
    "zs:housing10":224,
    "zs:pop10":666
},
  "geometry": {"coordinates":[-75.665983,39.999366],"type":"Point"}
}