{
  "type": "Feature",
  "properties": {
    "gn:admin1_code":"MD",
    "gn:admin2_code":"21.0",
    "gn:asciiname":"Tarson Manor",
    "gn:country_code":"US",
    "gn:dem":207,
    "gn:elevation":"205.0",
    "gn:feature_class":"P",
    "gn:feature_code":"PPL",
    "gn:name":"Tarson Manor",
    "gn:population":0,
    "gn:timezone":"America/New_York",
    "iso:country":"US",
    "wof:name":"Tarson Manor",
    "wof:placetype":"locality"
},
  "geometry": {"coordinates":[-77.11887,39.48066],"type":"Point"}
}