{
  "type": "Feature",
  "properties": {
    "iso:country":"US",
    "name:ceb_x_preferred":[
        "Belmar"
    ],
    "name:deu_x_preferred":[
        "Belmar"
    ],
    "name:eng_x_preferred":[
        "Belmar"
    ],
    "name:hbs_x_preferred":[
        "Belmar"
    ],
    "name:spa_x_preferred":[
        "Belmar"
    ],
    "name:srp_x_preferred":[
        "\u0411\u0435\u043b\u043c\u0430\u0440"
    ],
    "name:ukr_x_preferred":[
        "\u0411\u0435\u043b\u043c\u0430\u0440"
    ],
    "wof:name":"Belmar",
    "wof:placetype":"neighbourhood",
    "wof:population":688,
    "zs:area_m":10616675.930236,
    "zs:blockids":[
        421212002002028,
        421212002003023,
        421212002003019,
        421212002003059,
        421212002003022,
        421212002003014,
        421212002003012,
        421212002003013,
        421212002003020,
        421212002003021
    ],
    "zs:housing10":304,
    "zs:label":"Belmar",
    "zs:pop10":688
},
  "geometry": {"coordinates":[-79.857423,41.358578],"type":"Point"}
}