{
  "type": "Feature",
  "properties": {
    "gn:admin1_code":"IA",
    "gn:admin2_code":"77.0",
    "gn:admin3_code":"90147.0",
    "gn:asciiname":"North Branch",
    "gn:country_code":"US",
    "gn:dem":430,
    "gn:elevation":"428.0",
    "gn:feature_class":"P",
    "gn:feature_code":"PPL",
    "gn:name":"North Branch",
    "gn:population":0,
    "gn:timezone":"America/Chicago",
    "iso:country":"US",
    "name:ceb_x_preferred":[
        "North Branch"
    ],
    "name:deu_x_preferred":[
        "North Branch"
    ],
    "name:ita_x_preferred":[
        "North Branch"
    ],
    "name:nld_x_preferred":[
        "North Branch"
    ],
    "name:pol_x_preferred":[
        "North Branch"
    ],
    "name:por_x_preferred":[
        "North Branch"
    ],
    "name:rus_x_preferred":[
        "\u041d\u043e\u0440\u0442-\u0411\u0440\u0430\u043d\u0447"
    ],
    "name:srp_x_preferred":[
        "\u041d\u043e\u0440\u0442 \u0411\u0440\u0430\u043d\u0447"
    ],
    "name:swe_x_preferred":[
        "North Branch"
    ],
    "name:vol_x_preferred":[
        "North Branch"
    ],
    "wof:name":"North Branch",
    "wof:placetype":"locality"
},
  "geometry": {"coordinates":[-94.71526,41.64582],"type":"Point"}
}