{
  "type": "Feature",
  "properties": {
    "gn:admin1_code":"KY",
    "gn:admin2_code":"221",
    "gn:asciiname":"Trigg Furnace",
    "gn:country_code":"US",
    "gn:dem":119,
    "gn:elevation":"117.0",
    "gn:feature_class":"P",
    "gn:feature_code":"PPL",
    "gn:name":"Trigg Furnace",
    "gn:population":0,
    "gn:timezone":"America/Chicago",
    "iso:country":"US",
    "wof:name":"Trigg Furnace",
    "wof:placetype":"locality"
},
  "geometry": {"coordinates":[-87.93613000000001,36.89005],"type":"Point"}
}