{
  "type": "Feature",
  "properties": {
    "gn:admin1_code":"OK",
    "gn:admin2_code":"145.0",
    "gn:asciiname":"Toppers",
    "gn:country_code":"US",
    "gn:dem":191,
    "gn:elevation":"185.0",
    "gn:feature_class":"P",
    "gn:feature_code":"PPL",
    "gn:name":"Toppers",
    "gn:population":0,
    "gn:timezone":"America/Chicago",
    "iso:country":"US",
    "wof:name":"Toppers",
    "wof:placetype":"locality"
},
  "geometry": {"coordinates":[-95.30969,35.97065999999999],"type":"Point"}
}