{
  "type": "Feature",
  "properties": {
    "gn:admin1_code":"SC",
    "gn:admin2_code":"15.0",
    "gn:asciiname":"Witherbee",
    "gn:country_code":"US",
    "gn:dem":17,
    "gn:elevation":"16.0",
    "gn:feature_class":"P",
    "gn:feature_code":"PPL",
    "gn:name":"Witherbee",
    "gn:population":0,
    "gn:timezone":"America/New_York",
    "iso:country":"US",
    "wof:name":"Witherbee",
    "wof:placetype":"locality"
},
  "geometry": {"coordinates":[-79.82980000000001,33.16184000000001],"type":"Point"}
}