{
  "type": "Feature",
  "properties": {
    "gn:elevation":383,
    "iso:country":"US",
    "name:eng_x_preferred":[
        "Saddlehorn Ranch"
    ],
    "name:eng_x_variant":[
        "Saddlehorn Rnch"
    ],
    "qs:gn_adm0_cc":"US",
    "qs:gn_fcode":"PPL",
    "qs:gn_local":5295985,
    "qs:gn_namadm1":"AZ",
    "qs:gn_name":"Saddlehorn Ranch",
    "qs:local_max":4074,
    "qs:local_sum":9653,
    "qs:localhoods":40,
    "qs:name":"Saddlehorn Ranch",
    "qs:name_adm0":"United States",
    "qs:name_adm1":"Arizona",
    "qs:name_adm2":"Maricopa",
    "qs:name_local":"Glendale",
    "qs:photo_max":18,
    "qs:photo_sum":46,
    "qs:placetype":"Suburb",
    "qs:quad_count":6,
    "qs:woe_adm0":23424977,
    "qs:woe_adm1":2347561,
    "qs:woe_adm2":12587587,
    "qs:woe_lau":0,
    "qs:woe_local":2411084,
    "qs:woe_ver":"7.10.0",
    "wof:name":"Saddlehorn Ranch",
    "wof:placetype":"neighbourhood",
    "wof:population":1783,
    "zs:blockids":[
        40136179002012,
        40131042153003,
        40136180003007,
        40131042153005,
        40136179002010,
        40136180003010,
        40131042155003,
        40131042153004,
        40131042153001,
        40136180003004,
        40136180003003,
        40131042153006,
        40131042155000,
        40131042153008,
        40131042153007,
        40131042153002,
        40131042153000,
        40131042141001,
        40131042142025,
        40136179002019,
        40136179002014,
        40131042153009,
        40131042155009,
        40131042155001,
        40131042153010,
        40136180003008,
        40136179002015,
        40136179002013,
        40136180003009,
        40131042142007,
        40136179002011,
        40131042155002,
        40131042142026,
        40136180003011
    ],
    "zs:housing10":657,
    "zs:pop10":1783
},
  "geometry": {"coordinates":[-112.188346,33.638072],"type":"Point"}
}