{
  "type": "Feature",
  "properties": {
    "gn:admin1_code":"MD",
    "gn:admin2_code":"37.0",
    "gn:asciiname":"Laceys Venture",
    "gn:country_code":"US",
    "gn:dem":34,
    "gn:elevation":"32.0",
    "gn:feature_class":"P",
    "gn:feature_code":"PPL",
    "gn:name":"Laceys Venture",
    "gn:population":0,
    "gn:timezone":"America/New_York",
    "iso:country":"US",
    "wof:name":"Laceys Venture",
    "wof:placetype":"locality"
},
  "geometry": {"coordinates":[-76.56468000000002,38.28263],"type":"Point"}
}