{
  "type": "Feature",
  "properties": {
    "gn:admin1_code":"KS",
    "gn:admin2_code":"101",
    "gn:admin3_code":"79725.0",
    "gn:asciiname":"Shields",
    "gn:country_code":"US",
    "gn:dem":855,
    "gn:elevation":"848.0",
    "gn:feature_class":"P",
    "gn:feature_code":"PPL",
    "gn:name":"Shields",
    "gn:population":0,
    "gn:timezone":"America/Chicago",
    "iso:country":"US",
    "wof:name":"Shields",
    "wof:placetype":"locality"
},
  "geometry": {"coordinates":[-100.44513999999999,38.61557],"type":"Point"}
}