{
  "type": "Feature",
  "properties": {
    "gn:country":"US",
    "gn:fcode":"PPL",
    "gn:population":0,
    "iso:country":"US",
    "name:ara_x_preferred":[
        "\u0643\u0631\u064a\u0633\u062a\u0627\u0644 \u0633\u0628\u0631\u064a\u0646\u062c"
    ],
    "name:eng_x_preferred":[
        "Crystal Springs"
    ],
    "name:fra_x_preferred":[
        "Crystal Springs"
    ],
    "name:ita_x_preferred":[
        "Crystal Springs"
    ],
    "name:jpn_x_preferred":[
        "\u30af\u30ea\u30b9\u30bf\u30eb\u30b9\u30d7\u30ea\u30f3\u30b0\u30b9"
    ],
    "name:nav_x_preferred":[
        "T\u00f3 Ni\u0142ts\u02bc\u00edl\u00ed H\u00e1\u00e1l\u012f\u0301"
    ],
    "name:nld_x_preferred":[
        "Crystal Springs"
    ],
    "name:por_x_preferred":[
        "Crystal Springs"
    ],
    "name:und_x_variant":[
        "Crystal Spring"
    ],
    "name:vie_x_preferred":[
        "Crystal Springs"
    ],
    "qs_pg:aaroncc":"US",
    "qs_pg:gn_country":"US",
    "qs_pg:gn_fcode":"PPL",
    "qs_pg:gn_pop":0,
    "qs_pg:name":"Crystal Springs",
    "qs_pg:name_adm0":"United States",
    "qs_pg:name_adm1":"Nevada",
    "qs_pg:photos":128,
    "qs_pg:photos_1k":26,
    "qs_pg:photos_9k":1,
    "qs_pg:photos_9r":3,
    "qs_pg:photos_all":128,
    "qs_pg:photos_sr":3,
    "qs_pg:pop_sr":0,
    "qs_pg:qs_pg_placetype":"locality",
    "qs_pg:qs_pg_placetype_gp":"Town",
    "qs_pg:woe_adm0":23424977,
    "woe:adm0_id":23424977,
    "woe:name_adm0":"United States",
    "woe:name_adm1":"Nevada",
    "woe:placetype":"Town",
    "wof:name":"Crystal Springs",
    "wof:placetype":"locality"
},
  "geometry": {"coordinates":[-115.23390999999999,37.53163],"type":"Point"}
}