{
  "type": "Feature",
  "properties": {
    "gn:admin1_code":"MT",
    "gn:admin2_code":"95.0",
    "gn:asciiname":"Beehive",
    "gn:country_code":"US",
    "gn:dem":1412,
    "gn:elevation":"1411.0",
    "gn:feature_class":"P",
    "gn:feature_code":"PPL",
    "gn:name":"Beehive",
    "gn:population":0,
    "gn:timezone":"America/Denver",
    "iso:country":"US",
    "name:fas_x_preferred":[
        "\u0628\u06cc\u0647\u0627\u06cc\u0648"
    ],
    "wof:name":"Beehive",
    "wof:placetype":"locality"
},
  "geometry": {"coordinates":[-109.72073,45.47911],"type":"Point"}
}