{
  "type": "Feature",
  "properties": {
    "gn:admin1_code":"MD",
    "gn:admin2_code":"9.0",
    "gn:asciiname":"Bowen Country",
    "gn:country_code":"US",
    "gn:dem":26,
    "gn:elevation":"29.0",
    "gn:feature_class":"P",
    "gn:feature_code":"PPL",
    "gn:name":"Bowen Country",
    "gn:population":0,
    "gn:timezone":"America/New_York",
    "iso:country":"US",
    "wof:name":"Bowen Country",
    "wof:placetype":"locality"
},
  "geometry": {"coordinates":[-76.61745999999999,38.5854],"type":"Point"}
}