{
  "type": "Feature",
  "properties": {
    "gn:admin1_code":"AR",
    "gn:admin2_code":"135.0",
    "gn:admin3_code":"90282.0",
    "gn:asciiname":"Calamine",
    "gn:country_code":"US",
    "gn:dem":98,
    "gn:elevation":"97.0",
    "gn:feature_class":"P",
    "gn:feature_code":"PPL",
    "gn:name":"Calamine",
    "gn:population":0,
    "gn:timezone":"America/Chicago",
    "iso:country":"US",
    "name:fas_x_preferred":[
        "\u06a9\u0627\u0644\u0627\u0645\u06cc\u0646"
    ],
    "name:zho_x_preferred":[
        "\u5361\u62c9\u9081\u6069"
    ],
    "wof:name":"Calamine",
    "wof:placetype":"locality"
},
  "geometry": {"coordinates":[-91.39901999999999,36.01146],"type":"Point"}
}