{
  "type": "Feature",
  "properties": {
    "iso:country":"US",
    "name:eng_x_preferred":[
        "Liberty Centre"
    ],
    "wof:name":"Liberty Centre",
    "wof:placetype":"neighbourhood",
    "wof:population":2733,
    "zs:area_m":2136074.812636,
    "zs:blockids":[
        191030103013119,
        191030103013093,
        191030103013088,
        191030103013133,
        191030103013084,
        191030103013077,
        191030103013120,
        191030103013087,
        191030103013125,
        191030103013062,
        191030103013073,
        191030103013097,
        191030103013063,
        191030103013112,
        191030103013076,
        191030103013132,
        191030103013115,
        191030103013074,
        191030103013123,
        191030103013071,
        191030103013124,
        191030103013134,
        191030103013069,
        191030103013057,
        191030103013095,
        191030103013064,
        191030103013121,
        191030103013091,
        191030103013075,
        191030103013081,
        191030103013086,
        191030103013050,
        191030103013068,
        191030103013128,
        191030103013085,
        191030103013118,
        191030103013117,
        191030103013122,
        191030103013078,
        191030103013072,
        191030103013067,
        191030103013113,
        191030103013096,
        191030103013114,
        191030103013138,
        191030103013116,
        191030103013080,
        191030103013127
    ],
    "zs:housing10":1159,
    "zs:label":"Liberty Centre",
    "zs:pop10":2733
},
  "geometry": {"coordinates":[-91.61269299999999,41.746991],"type":"Point"}
}