{
  "type": "Feature",
  "properties": {
    "gn:admin1_code":"PA",
    "gn:admin2_code":"89.0",
    "gn:admin3_code":"61728.0",
    "gn:asciiname":"Ski Haven Lake Estates",
    "gn:country_code":"US",
    "gn:dem":362,
    "gn:elevation":"357.0",
    "gn:feature_class":"P",
    "gn:feature_code":"PPL",
    "gn:name":"Ski Haven Lake Estates",
    "gn:population":0,
    "gn:timezone":"America/New_York",
    "iso:country":"US",
    "wof:name":"Ski Haven Lake Estates",
    "wof:placetype":"locality"
},
  "geometry": {"coordinates":[-75.30741,41.09342],"type":"Point"}
}