{
  "type": "Feature",
  "properties": {
    "gn:admin1_code":"OH",
    "gn:admin2_code":"73",
    "gn:admin3_code":"80780.0",
    "gn:asciiname":"Coalgate",
    "gn:country_code":"US",
    "gn:dem":247,
    "gn:elevation":"225.0",
    "gn:feature_class":"P",
    "gn:feature_code":"PPL",
    "gn:name":"Coalgate",
    "gn:population":0,
    "gn:timezone":"America/New_York",
    "iso:country":"US",
    "name:deu_x_preferred":[
        "Coalgate"
    ],
    "name:eng_x_preferred":[
        "Coalgate"
    ],
    "name:swe_x_preferred":[
        "Coalgate"
    ],
    "name:und_x_variant":[
        "Colgate",
        "Coal Gate"
    ],
    "wof:name":"Coalgate",
    "wof:placetype":"locality"
},
  "geometry": {"coordinates":[-82.18486999999998,39.53701],"type":"Point"}
}