{
  "type": "Feature",
  "properties": {
    "gn:admin1_code":"MD",
    "gn:admin2_code":"21.0",
    "gn:asciiname":"Titus Estates",
    "gn:country_code":"US",
    "gn:dem":96,
    "gn:elevation":"95.0",
    "gn:feature_class":"P",
    "gn:feature_code":"PPL",
    "gn:name":"Titus Estates",
    "gn:population":0,
    "gn:timezone":"America/New_York",
    "iso:country":"US",
    "wof:name":"Titus Estates",
    "wof:placetype":"locality"
},
  "geometry": {"coordinates":[-77.49276,39.27566],"type":"Point"}
}