{
  "type": "Feature",
  "properties": {
    "gn:gn_country":"US",
    "gn:gn_fcode":"PPL",
    "gn:gn_pop":0,
    "iso:country":"US",
    "name:ceb_x_preferred":[
        "Seal Cove"
    ],
    "name:nld_x_preferred":[
        "Seal Cove"
    ],
    "name:swe_x_preferred":[
        "Seal Cove"
    ],
    "qs_pg:aaroncc":"US",
    "qs_pg:gn_country":"US",
    "qs_pg:gn_fcode":"PPL",
    "qs_pg:gn_pop":0,
    "qs_pg:name":"Seal Cove",
    "qs_pg:name_adm0":"United States",
    "qs_pg:name_adm1":"California",
    "qs_pg:photos":627,
    "qs_pg:photos_1k":127,
    "qs_pg:photos_9k":3,
    "qs_pg:photos_9r":5,
    "qs_pg:photos_all":627,
    "qs_pg:photos_sr":8,
    "qs_pg:pop_sr":0,
    "qs_pg:qs_pg_placetype":"locality",
    "qs_pg:qs_pg_placetype_gp":"Town",
    "qs_pg:woe_adm0":23424977,
    "woe:adm0_id":23424977,
    "woe:name_adm0":"United States",
    "woe:name_adm1":"California",
    "woe:placetype":"Town",
    "wof:name":"Seal Cove",
    "wof:placetype":"locality"
},
  "geometry": {"coordinates":[-122.51276,37.51911],"type":"Point"}
}