{
  "type": "Feature",
  "properties": {
    "gn:admin1_code":"CA",
    "gn:admin2_code":"29.0",
    "gn:asciiname":"Spellacy",
    "gn:country_code":"US",
    "gn:dem":519,
    "gn:elevation":"511.0",
    "gn:feature_class":"P",
    "gn:feature_code":"PPL",
    "gn:name":"Spellacy",
    "gn:population":0,
    "gn:timezone":"America/Los_Angeles",
    "iso:country":"US",
    "name:azb_x_preferred":[
        "\u0627\u0633\u067e\u0644\u0633\u06cc"
    ],
    "name:fas_x_preferred":[
        "\u0627\u0633\u067e\u0644\u0633\u06cc"
    ],
    "name:pol_x_preferred":[
        "Spellacy"
    ],
    "name:zho_x_preferred":[
        "\u65af\u4f69\u62c9\u897f"
    ],
    "wof:name":"Spellacy",
    "wof:placetype":"locality"
},
  "geometry": {"coordinates":[-119.47150999999999,35.11302],"type":"Point"}
}