{
  "type": "Feature",
  "properties": {
    "iso:country":"US",
    "name:bar_x_preferred":[
        "Avondale"
    ],
    "name:ceb_x_preferred":[
        "Avondale"
    ],
    "name:deu_x_preferred":[
        "Avondale"
    ],
    "name:eng_x_preferred":[
        "Avondale"
    ],
    "name:fra_x_preferred":[
        "Avondale"
    ],
    "name:ita_x_preferred":[
        "Avondale"
    ],
    "name:nld_x_preferred":[
        "Avondale"
    ],
    "name:pol_x_preferred":[
        "Avondale"
    ],
    "name:por_x_preferred":[
        "Avondale"
    ],
    "name:ron_x_preferred":[
        "Avondale"
    ],
    "name:rus_x_preferred":[
        "\u042d\u0439\u0432\u043e\u043d\u0434\u0435\u0439\u043b"
    ],
    "name:spa_x_preferred":[
        "Avondale"
    ],
    "name:srp_x_preferred":[
        "\u0410\u0432\u043e\u043d\u0434\u0435\u0458\u043b"
    ],
    "name:swe_x_preferred":[
        "Avondale"
    ],
    "name:ukr_x_preferred":[
        "\u0415\u0439\u0432\u043e\u043d\u0435\u0439\u043b"
    ],
    "name:urd_x_preferred":[
        "\u0627\u06cc\u0648\u0646\u0688\u06cc\u0644"
    ],
    "name:vol_x_preferred":[
        "Avondale"
    ],
    "wof:name":"Avondale",
    "wof:placetype":"neighbourhood",
    "wof:population":326,
    "zs:area_m":2148760.156228,
    "zs:blockids":[
        471650212032012,
        471650212031016
    ],
    "zs:housing10":124,
    "zs:label":"Avondale",
    "zs:pop10":326
},
  "geometry": {"coordinates":[-86.52230299999999,36.336827],"type":"Point"}
}