{
  "type": "Feature",
  "properties": {
    "gn:admin1_code":"MI",
    "gn:admin2_code":"55.0",
    "gn:admin3_code":"49240.0",
    "gn:asciiname":"Cedar Run",
    "gn:country_code":"US",
    "gn:dem":243,
    "gn:elevation":"238.0",
    "gn:feature_class":"P",
    "gn:feature_code":"PPL",
    "gn:name":"Cedar Run",
    "gn:population":0,
    "gn:timezone":"America/Detroit",
    "iso:country":"US",
    "name:ceb_x_preferred":[
        "Cedar Run"
    ],
    "name:deu_x_preferred":[
        "Cedar Run"
    ],
    "wof:name":"Cedar Run",
    "wof:placetype":"locality"
},
  "geometry": {"coordinates":[-85.81369000000002,44.76278],"type":"Point"}
}