{
  "type": "Feature",
  "properties": {
    "gn:admin1_code":"TN",
    "gn:admin2_code":"59.0",
    "gn:asciiname":"Wedgewood Hills",
    "gn:country_code":"US",
    "gn:dem":514,
    "gn:elevation":"508.0",
    "gn:feature_class":"P",
    "gn:feature_code":"PPL",
    "gn:name":"Wedgewood Hills",
    "gn:population":0,
    "gn:timezone":"America/New_York",
    "iso:country":"US",
    "wof:name":"Wedgewood Hills",
    "wof:placetype":"locality"
},
  "geometry": {"coordinates":[-82.79793000000002,36.19232],"type":"Point"}
}