{
  "type": "Feature",
  "properties": {
    "gn:admin1_code":"TX",
    "gn:admin2_code":"215.0",
    "gn:asciiname":"Siesta Village Number 2 Colonia",
    "gn:country_code":"US",
    "gn:dem":26,
    "gn:elevation":"20.0",
    "gn:feature_class":"P",
    "gn:feature_code":"PPL",
    "gn:name":"Siesta Village Number 2 Colonia",
    "gn:population":0,
    "gn:timezone":"America/Chicago",
    "iso:country":"US",
    "wof:name":"Siesta Village Number 2 Colonia",
    "wof:placetype":"locality"
},
  "geometry": {"coordinates":[-97.96222,26.13424],"type":"Point"}
}