{
  "type": "Feature",
  "properties": {
    "gn:admin1_code":"VA",
    "gn:admin2_code":"3",
    "gn:asciiname":"Farmington",
    "gn:country_code":"US",
    "gn:dem":178,
    "gn:elevation":"183.0",
    "gn:feature_class":"P",
    "gn:feature_code":"PPL",
    "gn:name":"Farmington",
    "gn:population":0,
    "gn:timezone":"America/New_York",
    "iso:country":"US",
    "name:azb_x_preferred":[
        "\u0641\u0627\u0631\u0645\u06cc\u0646\u0642\u062a\u0648\u0646"
    ],
    "name:fas_x_preferred":[
        "\u0641\u0627\u0631\u0645\u06cc\u0646\u06af\u062a\u0648\u0646"
    ],
    "name:hun_x_preferred":[
        "Farmington"
    ],
    "name:urd_x_preferred":[
        "\u0641\u0627\u0631\u0645\u0646\u06af\u0679\u0646"
    ],
    "wof:name":"Farmington",
    "wof:placetype":"locality"
},
  "geometry": {"coordinates":[-78.54418,38.05125],"type":"Point"}
}