{
  "type": "Feature",
  "properties": {
    "gn:admin1_code":"MO",
    "gn:admin2_code":"89.0",
    "gn:admin3_code":"49232.0",
    "gn:asciiname":"Sebree",
    "gn:country_code":"US",
    "gn:dem":218,
    "gn:elevation":"215.0",
    "gn:feature_class":"P",
    "gn:feature_code":"PPL",
    "gn:name":"Sebree",
    "gn:population":0,
    "gn:timezone":"America/Chicago",
    "iso:country":"US",
    "wof:name":"Sebree",
    "wof:placetype":"locality"
},
  "geometry": {"coordinates":[-92.53100999999999,39.12698],"type":"Point"}
}