{
  "type": "Feature",
  "properties": {
    "gn:admin1_code":"NC",
    "gn:admin2_code":"99.0",
    "gn:admin3_code":"92856.0",
    "gn:asciiname":"Pumpkintown",
    "gn:country_code":"US",
    "gn:dem":855,
    "gn:elevation":"854.0",
    "gn:feature_class":"P",
    "gn:feature_code":"PPL",
    "gn:name":"Pumpkintown",
    "gn:population":0,
    "gn:timezone":"America/New_York",
    "iso:country":"US",
    "name:deu_x_preferred":[
        "Pumpkintown"
    ],
    "wof:name":"Pumpkintown",
    "wof:placetype":"locality"
},
  "geometry": {"coordinates":[-83.28209,35.25399],"type":"Point"}
}