{
  "type": "Feature",
  "properties": {
    "gn:admin1_code":"TN",
    "gn:admin2_code":"39",
    "gn:asciiname":"Lick Skillet",
    "gn:country_code":"US",
    "gn:dem":164,
    "gn:elevation":"161.0",
    "gn:feature_class":"P",
    "gn:feature_code":"PPL",
    "gn:name":"Lick Skillet",
    "gn:population":0,
    "gn:timezone":"America/Chicago",
    "iso:country":"US",
    "wof:name":"Lick Skillet",
    "wof:placetype":"locality"
},
  "geometry": {"coordinates":[-88.20586999999998,35.49063],"type":"Point"}
}