{
  "type": "Feature",
  "properties": {
    "gn:country":"US",
    "gn:fcode":"PPL",
    "gn:population":0,
    "iso:country":"US",
    "name:cat_x_preferred":[
        "Twin Lakes"
    ],
    "name:ceb_x_preferred":[
        "Twin Lakes"
    ],
    "name:deu_x_preferred":[
        "Twin Lakes"
    ],
    "name:ita_x_preferred":[
        "Twin Lakes"
    ],
    "name:nld_x_preferred":[
        "Twin Lakes"
    ],
    "name:pol_x_preferred":[
        "Twin Lakes"
    ],
    "name:por_x_preferred":[
        "Twin Lakes"
    ],
    "name:rus_x_preferred":[
        "\u0422\u0443\u0438\u043d-\u041b\u0435\u0439\u043a\u0441"
    ],
    "name:spa_x_preferred":[
        "Twin Lakes"
    ],
    "name:srp_x_preferred":[
        "\u0422\u0432\u0438\u043d \u041b\u0435\u0458\u043a\u0441"
    ],
    "name:swe_x_preferred":[
        "Twin Lakes"
    ],
    "name:vol_x_preferred":[
        "Twin Lakes"
    ],
    "qs_pg:aaroncc":"US",
    "qs_pg:gn_country":"US",
    "qs_pg:gn_fcode":"PPL",
    "qs_pg:gn_pop":0,
    "qs_pg:name":"Twin Lakes",
    "qs_pg:name_adm0":"United States",
    "qs_pg:name_adm1":"Pennsylvania",
    "qs_pg:photos":20,
    "qs_pg:photos_1k":4,
    "qs_pg:photos_9k":1,
    "qs_pg:photos_9r":1,
    "qs_pg:photos_all":20,
    "qs_pg:photos_sr":1,
    "qs_pg:pop_sr":0,
    "qs_pg:qs_pg_placetype":"locality",
    "qs_pg:qs_pg_placetype_gp":"Town",
    "qs_pg:woe_adm0":23424977,
    "woe:adm0_id":23424977,
    "woe:name_adm0":"United States",
    "woe:name_adm1":"Pennsylvania",
    "woe:placetype":"Town",
    "wof:name":"Twin Lakes",
    "wof:placetype":"locality"
},
  "geometry": {"coordinates":[-76.81135999999999,40.27592],"type":"Point"}
}