{
  "type": "Feature",
  "properties": {
    "gn:admin1_code":"VA",
    "gn:admin2_code":"117",
    "gn:asciiname":"Perfect Point",
    "gn:country_code":"US",
    "gn:dem":106,
    "gn:elevation":"102.0",
    "gn:feature_class":"P",
    "gn:feature_code":"PPL",
    "gn:name":"Perfect Point",
    "gn:population":0,
    "gn:timezone":"America/New_York",
    "iso:country":"US",
    "wof:name":"Perfect Point",
    "wof:placetype":"locality"
},
  "geometry": {"coordinates":[-78.56639,36.63486],"type":"Point"}
}