{
  "type": "Feature",
  "properties": {
    "gn:admin1_code":"IA",
    "gn:admin2_code":"43.0",
    "gn:admin3_code":"92214.0",
    "gn:asciiname":"Snefs",
    "gn:country_code":"US",
    "gn:dem":262,
    "gn:elevation":"259.0",
    "gn:feature_class":"P",
    "gn:feature_code":"PPL",
    "gn:name":"Snefs",
    "gn:population":0,
    "gn:timezone":"America/Chicago",
    "iso:country":"US",
    "wof:name":"Snefs",
    "wof:placetype":"locality"
},
  "geometry": {"coordinates":[-91.14096000000001,42.74082],"type":"Point"}
}