{
  "type": "Feature",
  "properties": {
    "gn:admin1_code":"KS",
    "gn:admin2_code":"169.0",
    "gn:admin3_code":"66075.0",
    "gn:asciiname":"Salemsborg",
    "gn:country_code":"US",
    "gn:dem":409,
    "gn:elevation":"405.0",
    "gn:feature_class":"P",
    "gn:feature_code":"PPL",
    "gn:name":"Salemsborg",
    "gn:population":0,
    "gn:timezone":"America/Chicago",
    "iso:country":"US",
    "name:eng_x_preferred":[
        "Salemsborg"
    ],
    "name:und_x_variant":[
        "Salemburg",
        "Salemsburg",
        "Salemsburgh"
    ],
    "wof:name":"Salemsborg",
    "wof:placetype":"locality"
},
  "geometry": {"coordinates":[-97.68615,38.69528],"type":"Point"}
}