{
  "type": "Feature",
  "properties": {
    "gn:admin1_code":"FL",
    "gn:admin2_code":"49.0",
    "gn:asciiname":"Griffins Corner",
    "gn:country_code":"US",
    "gn:dem":36,
    "gn:elevation":"32.0",
    "gn:feature_class":"P",
    "gn:feature_code":"PPL",
    "gn:name":"Griffins Corner",
    "gn:population":0,
    "gn:timezone":"America/New_York",
    "iso:country":"US",
    "wof:name":"Griffins Corner",
    "wof:placetype":"locality"
},
  "geometry": {"coordinates":[-81.73090999999999,27.53976],"type":"Point"}
}