{
  "type": "Feature",
  "properties": {
    "gn:admin1_code":"GA",
    "gn:admin2_code":"195",
    "gn:asciiname":"Velpoe",
    "gn:country_code":"US",
    "gn:dem":240,
    "gn:elevation":"242.0",
    "gn:feature_class":"P",
    "gn:feature_code":"PPL",
    "gn:name":"Velpoe",
    "gn:population":0,
    "gn:timezone":"America/New_York",
    "iso:country":"US",
    "wof:name":"Velpoe",
    "wof:placetype":"locality"
},
  "geometry": {"coordinates":[-83.23404000000002,34.17678],"type":"Point"}
}