{
  "type": "Feature",
  "properties": {
    "gn:admin1_code":"AL",
    "gn:admin2_code":"119",
    "gn:asciiname":"Lilita",
    "gn:country_code":"US",
    "gn:dem":43,
    "gn:elevation":"34.0",
    "gn:feature_class":"P",
    "gn:feature_code":"PPL",
    "gn:name":"Lilita",
    "gn:population":0,
    "gn:timezone":"America/Chicago",
    "iso:country":"US",
    "name:eng_x_preferred":[
        "Lilita"
    ],
    "name:und_x_variant":[
        "Lillita",
        "Lee Station"
    ],
    "wof:name":"Lilita",
    "wof:placetype":"locality"
},
  "geometry": {"coordinates":[-88.12836,32.48375],"type":"Point"}
}