{
  "type": "Feature",
  "properties": {
    "gn:admin1_code":"GA",
    "gn:admin2_code":"45",
    "gn:asciiname":"South Gate",
    "gn:country_code":"US",
    "gn:dem":350,
    "gn:elevation":"341.0",
    "gn:feature_class":"P",
    "gn:feature_code":"PPL",
    "gn:name":"South Gate",
    "gn:population":0,
    "gn:timezone":"America/New_York",
    "iso:country":"US",
    "wof:name":"South Gate",
    "wof:placetype":"locality"
},
  "geometry": {"coordinates":[-85.06078000000002,33.54344],"type":"Point"}
}