{
  "type": "Feature",
  "properties": {
    "gn:admin1_code":"PA",
    "gn:admin2_code":"41.0",
    "gn:admin3_code":"58824.0",
    "gn:asciiname":"Cobblesville",
    "gn:country_code":"US",
    "gn:dem":216,
    "gn:elevation":"214.0",
    "gn:feature_class":"P",
    "gn:feature_code":"PPL",
    "gn:name":"Cobblesville",
    "gn:population":0,
    "gn:timezone":"America/New_York",
    "iso:country":"US",
    "name:eng_x_preferred":[
        "Cobblesville"
    ],
    "name:und_x_variant":[
        "Cobblerville"
    ],
    "wof:name":"Cobblesville",
    "wof:placetype":"locality"
},
  "geometry": {"coordinates":[-77.33221,40.08537000000001],"type":"Point"}
}