{
  "type": "Feature",
  "properties": {
    "gn:admin1_code":"NM",
    "gn:admin2_code":"57",
    "gn:asciiname":"Los Chavez",
    "gn:country_code":"US",
    "gn:dem":2107,
    "gn:elevation":"2107.0",
    "gn:feature_class":"P",
    "gn:feature_code":"PPL",
    "gn:name":"Los Chavez",
    "gn:population":0,
    "gn:timezone":"America/Denver",
    "iso:country":"US",
    "wof:name":"Los Chavez",
    "wof:placetype":"locality"
},
  "geometry": {"coordinates":[-106.34,34.61194],"type":"Point"}
}