{
  "type": "Feature",
  "properties": {
    "gn:country":"US",
    "gn:fcode":"PPL",
    "gn:population":0,
    "iso:country":"US",
    "name:bul_x_preferred":[
        "\u041c\u0430\u043a"
    ],
    "name:cat_x_preferred":[
        "Mac"
    ],
    "name:ceb_x_preferred":[
        "Mac"
    ],
    "name:ces_x_preferred":[
        "Mac"
    ],
    "name:dan_x_preferred":[
        "Mac"
    ],
    "name:est_x_preferred":[
        "Mac"
    ],
    "name:fra_x_preferred":[
        "Mac"
    ],
    "name:hun_x_preferred":[
        "Mac"
    ],
    "name:ind_x_preferred":[
        "Mac"
    ],
    "name:ita_x_preferred":[
        "Mac"
    ],
    "name:jpn_x_preferred":[
        "\u30de\u30c3\u30af"
    ],
    "name:nld_x_preferred":[
        "Mac"
    ],
    "name:nno_x_preferred":[
        "Mac"
    ],
    "name:nor_x_preferred":[
        "Mac"
    ],
    "name:rus_x_preferred":[
        "Mac"
    ],
    "name:slv_x_preferred":[
        "Mac"
    ],
    "name:spa_x_preferred":[
        "Mac"
    ],
    "name:swe_x_preferred":[
        "Mac"
    ],
    "name:tha_x_preferred":[
        "\u0e41\u0e21\u0e04"
    ],
    "qs_pg:aaroncc":"US",
    "qs_pg:gn_country":"US",
    "qs_pg:gn_fcode":"PPL",
    "qs_pg:gn_pop":0,
    "qs_pg:name":"Mac",
    "qs_pg:name_adm0":"United States",
    "qs_pg:name_adm1":"Kentucky",
    "qs_pg:photos_9k":1,
    "qs_pg:photos_9r":1,
    "qs_pg:photos_all":1,
    "qs_pg:photos_sr":0,
    "qs_pg:pop_sr":0,
    "qs_pg:qs_pg_placetype":"locality",
    "qs_pg:qs_pg_placetype_gp":"Town",
    "qs_pg:woe_adm0":23424977,
    "woe:adm0_id":23424977,
    "woe:name_adm0":"United States",
    "woe:name_adm1":"Kentucky",
    "woe:placetype":"Town",
    "wof:name":"Mac",
    "wof:placetype":"locality"
},
  "geometry": {"coordinates":[-85.51052,37.40006],"type":"Point"}
}