{
  "type": "Feature",
  "properties": {
    "gn:admin1_code":"PA",
    "gn:admin2_code":"71.0",
    "gn:admin3_code":"20032.0",
    "gn:asciiname":"Buck",
    "gn:country_code":"US",
    "gn:dem":215,
    "gn:elevation":"216.0",
    "gn:feature_class":"P",
    "gn:feature_code":"PPL",
    "gn:name":"Buck",
    "gn:population":0,
    "gn:timezone":"America/New_York",
    "iso:country":"US",
    "wof:name":"Buck",
    "wof:placetype":"locality"
},
  "geometry": {"coordinates":[-76.22884999999999,39.8726],"type":"Point"}
}