{
  "type": "Feature",
  "properties": {
    "gn:admin1_code":"SC",
    "gn:admin2_code":"25.0",
    "gn:asciiname":"Five Forks",
    "gn:country_code":"US",
    "gn:dem":210,
    "gn:elevation":"208.0",
    "gn:feature_class":"P",
    "gn:feature_code":"PPL",
    "gn:name":"Five Forks",
    "gn:population":0,
    "gn:timezone":"America/New_York",
    "iso:country":"US",
    "name:deu_x_preferred":[
        "Five Forks"
    ],
    "wof:name":"Five Forks",
    "wof:placetype":"locality"
},
  "geometry": {"coordinates":[-80.45312,34.74182],"type":"Point"}
}