{
  "type": "Feature",
  "properties": {
    "gn:gn_country":"US",
    "gn:gn_fcode":"PPL",
    "gn:gn_pop":0,
    "iso:country":"US",
    "name:eng_x_preferred":[
        "Fourche Junction"
    ],
    "name:fas_x_preferred":[
        "\u0641\u0648\u0631\u0634 \u062c\u0627\u0646\u06a9\u0634\u0646"
    ],
    "name:zho_x_preferred":[
        "\u5bcc\u4ec0\u7ae0\u514b\u7533"
    ],
    "qs_pg:aaroncc":"US",
    "qs_pg:gn_country":"US",
    "qs_pg:gn_fcode":"PPL",
    "qs_pg:gn_pop":0,
    "qs_pg:name":"Fourche Junction",
    "qs_pg:name_adm0":"United States",
    "qs_pg:name_adm1":"Arkansas",
    "qs_pg:photos":53,
    "qs_pg:photos_1k":11,
    "qs_pg:photos_9k":1,
    "qs_pg:photos_9r":2,
    "qs_pg:photos_all":53,
    "qs_pg:photos_sr":2,
    "qs_pg:pop_sr":0,
    "qs_pg:qs_pg_placetype":"locality",
    "qs_pg:qs_pg_placetype_gp":"Town",
    "qs_pg:woe_adm0":23424977,
    "woe:adm0_id":23424977,
    "woe:name_adm0":"United States",
    "woe:name_adm1":"Arkansas",
    "woe:placetype":"Town",
    "wof:name":"Fourche Junction",
    "wof:placetype":"locality"
},
  "geometry": {"coordinates":[-93.15712000000001,34.95648],"type":"Point"}
}