{
  "type": "Feature",
  "properties": {
    "gn:admin1_code":"OH",
    "gn:admin2_code":"45",
    "gn:admin3_code":"5956.0",
    "gn:asciiname":"Pleasant Hill",
    "gn:country_code":"US",
    "gn:dem":314,
    "gn:elevation":"312.0",
    "gn:feature_class":"P",
    "gn:feature_code":"PPL",
    "gn:name":"Pleasant Hill",
    "gn:population":0,
    "gn:timezone":"America/New_York",
    "iso:country":"US",
    "name:cat_x_preferred":[
        "Pleasant Hill"
    ],
    "name:ceb_x_preferred":[
        "Pleasant Hill"
    ],
    "name:deu_x_preferred":[
        "Pleasant Hill"
    ],
    "name:fra_x_preferred":[
        "Pleasant Hill"
    ],
    "name:ind_x_preferred":[
        "Pleasant Hill"
    ],
    "name:ita_x_preferred":[
        "Pleasant Hill"
    ],
    "name:nld_x_preferred":[
        "Pleasant Hill"
    ],
    "name:pol_x_preferred":[
        "Pleasant Hill"
    ],
    "name:por_x_preferred":[
        "Pleasant Hill"
    ],
    "name:spa_x_preferred":[
        "Pleasant Hill"
    ],
    "name:srp_x_preferred":[
        "\u041f\u043b\u0435\u0437\u0430\u043d\u0442 \u0425\u0438\u043b"
    ],
    "name:swe_x_preferred":[
        "Pleasant Hill"
    ],
    "name:urd_x_preferred":[
        "\u067e\u0644\u06cc\u0632\u06cc\u0646\u0679 \u06c1\u0644"
    ],
    "name:vol_x_preferred":[
        "Pleasant Hill"
    ],
    "wof:name":"Pleasant Hill",
    "wof:placetype":"locality"
},
  "geometry": {"coordinates":[-82.50794,39.67145],"type":"Point"}
}