{
  "type": "Feature",
  "properties": {
    "gn:admin1_code":"PA",
    "gn:admin2_code":"29.0",
    "gn:admin3_code":"54936.0",
    "gn:asciiname":"Schades Corner",
    "gn:country_code":"US",
    "gn:dem":86,
    "gn:elevation":"83.0",
    "gn:feature_class":"P",
    "gn:feature_code":"PPL",
    "gn:name":"Schades Corner",
    "gn:population":0,
    "gn:timezone":"America/New_York",
    "iso:country":"US",
    "wof:name":"Schades Corner",
    "wof:placetype":"locality"
},
  "geometry": {"coordinates":[-75.66686,40.22982],"type":"Point"}
}