{
  "type": "Feature",
  "properties": {
    "iso:country":"US",
    "name:cat_x_preferred":[
        "Pownal"
    ],
    "name:deu_x_preferred":[
        "Pownal"
    ],
    "name:eng_x_preferred":[
        "Pownal"
    ],
    "name:eus_x_preferred":[
        "Pownal"
    ],
    "name:fra_x_preferred":[
        "Pownal"
    ],
    "name:hat_x_preferred":[
        "Pownal"
    ],
    "name:hun_x_preferred":[
        "Pownal"
    ],
    "name:ita_x_preferred":[
        "Pownal"
    ],
    "name:kaz_x_preferred":[
        "\u041f\u043e\u0443\u043d\u0430\u043b"
    ],
    "name:kir_x_preferred":[
        "\u041f\u043e\u0443\u043d\u0430\u043b"
    ],
    "name:nld_x_preferred":[
        "Pownal"
    ],
    "name:pol_x_preferred":[
        "Pownal"
    ],
    "name:spa_x_preferred":[
        "Pownal"
    ],
    "name:vol_x_preferred":[
        "Pownal"
    ],
    "qs_pg:aaroncc":"US",
    "qs_pg:name":"Pownal",
    "qs_pg:name_adm0":"United States",
    "qs_pg:name_adm1":"Maine",
    "qs_pg:photos":425,
    "qs_pg:photos_1k":86,
    "qs_pg:photos_9k":2,
    "qs_pg:photos_9r":5,
    "qs_pg:photos_all":426,
    "qs_pg:photos_sr":6,
    "qs_pg:pop_sr":0,
    "qs_pg:qs_pg_placetype":"locality",
    "qs_pg:qs_pg_placetype_gp":"Town",
    "qs_pg:woe_adm0":23424977,
    "woe:adm0_id":23424977,
    "woe:name_adm0":"United States",
    "woe:name_adm1":"Maine",
    "woe:placetype":"Town",
    "wof:name":"Pownal",
    "wof:placetype":"locality"
},
  "geometry": {"coordinates":[-70.181179,43.9005],"type":"Point"}
}