{
  "type": "Feature",
  "properties": {
    "iso:country":"US",
    "name:eng_x_preferred":[
        "Glendale North"
    ],
    "qs:gn_adm0_cc":"US",
    "qs:gn_local":5352423,
    "qs:gn_nam_loc":"Glendale, Los Angeles, California, US",
    "qs:gn_namadm1":"CA",
    "qs:local_max":8963,
    "qs:local_sum":34005,
    "qs:localhoods":36,
    "qs:name":"Glendale North",
    "qs:name_adm0":"United States",
    "qs:name_adm1":"California",
    "qs:name_adm2":"Los Angeles",
    "qs:name_local":"Glendale",
    "qs:photo_max":335,
    "qs:photo_sum":1664,
    "qs:placetype":"Suburb",
    "qs:quad_count":50,
    "qs:woe_adm0":23424977,
    "qs:woe_adm1":2347563,
    "qs:woe_adm2":12587688,
    "qs:woe_lau":0,
    "qs:woe_local":2411080,
    "qs:woe_ver":"7.10.0",
    "wof:lang":[
        "eng"
    ],
    "wof:name":"Glendale North",
    "wof:placetype":"neighbourhood",
    "wof:population":6207,
    "zs:blockids":[
        60373018013000,
        60373019001022,
        60373019001015,
        60373012041009,
        60373011006001,
        60373011005003,
        60373012031003,
        60373012031002,
        60373012041010,
        60373018013004,
        60373018012000,
        60373018013007,
        60373019001016,
        60373019001001,
        60373011005002,
        60373019001025,
        60373019001012,
        60373019001013,
        60373011006009,
        60373019001007,
        60373019001027,
        60373019001017,
        60373011006014,
        60373011006012,
        60373011006005,
        60373011004006,
        60373011004002,
        60373019004002,
        60373019001020,
        60373018013013,
        60373018013003,
        60373012042000,
        60373011004001,
        60373019004000,
        60373019004007,
        60373011006016,
        60373019001006,
        60373011006003,
        60373019001002,
        60373019001004,
        60373011006010,
        60373019001021,
        60373019001011,
        60373011005001,
        60373019001008,
        60373011006007,
        60373019001029,
        60373012041000,
        60373019001009,
        60373019001005,
        60373011006011,
        60373019004003,
        60373012041008,
        60373011006002,
        60373019001014,
        60373018013008,
        60373018012006,
        60373019001018,
        60373019001003,
        60373011005004,
        60373019004001,
        60373011006008,
        60373011004004,
        60373011004005,
        60373019001019,
        60373011006013,
        60373019001028,
        60373011006015,
        60373011006004,
        60373011006006,
        60373011004007,
        60373019001023,
        60373019001024
    ],
    "zs:housing10":3039,
    "zs:pop10":6207
},
  "geometry": {"coordinates":[-118.25783300000001,34.170928],"type":"Point"}
}