{
  "type": "Feature",
  "properties": {
    "gn:country":"US",
    "gn:fcode":"PPL",
    "gn:population":0,
    "iso:country":"US",
    "name:eng_x_preferred":[
        "Kramer"
    ],
    "name:fas_x_preferred":[
        "\u06a9\u0631\u0627\u0645\u0631"
    ],
    "name:fra_x_preferred":[
        "Kramer"
    ],
    "qs_pg:aaroncc":"US",
    "qs_pg:gn_country":"US",
    "qs_pg:gn_fcode":"PPL",
    "qs_pg:gn_pop":0,
    "qs_pg:name":"Kramer",
    "qs_pg:name_adm0":"United States",
    "qs_pg:name_adm1":"Nebraska",
    "qs_pg:photos_9k":1,
    "qs_pg:photos_9r":1,
    "qs_pg:photos_all":2,
    "qs_pg:photos_sr":0,
    "qs_pg:pop_sr":5,
    "qs_pg:qs_pg_placetype":"locality",
    "qs_pg:qs_pg_placetype_gp":"Town",
    "qs_pg:woe_adm0":23424977,
    "woe:adm0_id":23424977,
    "woe:name_adm0":"United States",
    "woe:name_adm1":"Nebraska",
    "woe:placetype":"Town",
    "wof:name":"Kramer",
    "wof:placetype":"locality"
},
  "geometry": {"coordinates":[-96.8753,40.58834],"type":"Point"}
}