{
  "type": "Feature",
  "properties": {
    "gn:admin1_code":"ID",
    "gn:admin2_code":"35.0",
    "gn:asciiname":"Cow Creek",
    "gn:country_code":"US",
    "gn:dem":765,
    "gn:elevation":"756.0",
    "gn:feature_class":"P",
    "gn:feature_code":"PPL",
    "gn:name":"Cow Creek",
    "gn:population":0,
    "gn:timezone":"America/Los_Angeles",
    "iso:country":"US",
    "name:ceb_x_preferred":[
        "Cow Creek"
    ],
    "name:deu_x_preferred":[
        "Cow Creek"
    ],
    "name:nds_x_preferred":[
        "Cow Creek"
    ],
    "name:swe_x_preferred":[
        "Cow Creek"
    ],
    "wof:name":"Cow Creek",
    "wof:placetype":"locality"
},
  "geometry": {"coordinates":[-115.93292,46.49574000000001],"type":"Point"}
}