{
  "type": "Feature",
  "properties": {
    "gn:admin1_code":"TN",
    "gn:admin2_code":"5.0",
    "gn:asciiname":"Birdsong Creek Subdivision",
    "gn:country_code":"US",
    "gn:dem":127,
    "gn:elevation":"125.0",
    "gn:feature_class":"P",
    "gn:feature_code":"PPL",
    "gn:name":"Birdsong Creek Subdivision",
    "gn:population":0,
    "gn:timezone":"America/Chicago",
    "iso:country":"US",
    "wof:name":"Birdsong Creek Subdivision",
    "wof:placetype":"locality"
},
  "geometry": {"coordinates":[-88.04448000000002,35.98755999999999],"type":"Point"}
}