{
  "type": "Feature",
  "properties": {
    "gn:admin1_code":"GA",
    "gn:admin2_code":"135",
    "gn:asciiname":"Summit Chase",
    "gn:country_code":"US",
    "gn:dem":291,
    "gn:elevation":"290.0",
    "gn:feature_class":"P",
    "gn:feature_code":"PPL",
    "gn:name":"Summit Chase",
    "gn:population":0,
    "gn:timezone":"America/New_York",
    "iso:country":"US",
    "wof:name":"Summit Chase",
    "wof:placetype":"locality"
},
  "geometry": {"coordinates":[-83.96935000000001,33.85705],"type":"Point"}
}