{
  "type": "Feature",
  "properties": {
    "gn:admin1_code":"AK",
    "gn:admin2_code":"240.0",
    "gn:asciiname":"Charlieskin Village",
    "gn:country_code":"US",
    "gn:dem":515,
    "gn:elevation":"516.0",
    "gn:feature_class":"P",
    "gn:feature_code":"PPL",
    "gn:name":"Charlieskin Village",
    "gn:population":0,
    "gn:timezone":"America/Anchorage",
    "iso:country":"US",
    "name:fas_x_preferred":[
        "\u0686\u0627\u0631\u0644\u06cc \u0627\u0633\u06a9\u06cc\u0646 \u0648\u06cc\u0631\u062c\u06cc\u0646\u06cc\u0627"
    ],
    "name:zho_x_preferred":[
        "\u67e5\u7406\u65af\u91d1\u6751"
    ],
    "wof:name":"Charlieskin Village",
    "wof:placetype":"locality"
},
  "geometry": {"coordinates":[-141.81999999999999,62.97056],"type":"Point"}
}