{
  "type": "Feature",
  "properties": {
    "gn:admin1_code":"OH",
    "gn:admin2_code":"89",
    "gn:admin3_code":"78400.0",
    "gn:asciiname":"Pinecrest Estates",
    "gn:country_code":"US",
    "gn:dem":290,
    "gn:elevation":"295.0",
    "gn:feature_class":"P",
    "gn:feature_code":"PPL",
    "gn:name":"Pinecrest Estates",
    "gn:population":0,
    "gn:timezone":"America/New_York",
    "iso:country":"US",
    "wof:name":"Pinecrest Estates",
    "wof:placetype":"locality"
},
  "geometry": {"coordinates":[-82.52460000000001,39.98201],"type":"Point"}
}