{
  "type": "Feature",
  "properties": {
    "gn:admin1_code":"WA",
    "gn:admin2_code":"25.0",
    "gn:asciiname":"Wheeler",
    "gn:country_code":"US",
    "gn:dem":390,
    "gn:elevation":"392.0",
    "gn:feature_class":"P",
    "gn:feature_code":"PPL",
    "gn:name":"Wheeler",
    "gn:population":0,
    "gn:timezone":"America/Los_Angeles",
    "iso:country":"US",
    "name:cat_x_preferred":[
        "Wheeler"
    ],
    "name:ceb_x_preferred":[
        "Wheeler"
    ],
    "name:ces_x_preferred":[
        "Wheeler"
    ],
    "name:deu_x_preferred":[
        "Wheeler"
    ],
    "name:fin_x_preferred":[
        "Wheeler"
    ],
    "name:fra_x_preferred":[
        "Wheeler"
    ],
    "name:heb_x_preferred":[
        "\u05d5\u05d9\u05dc\u05e8"
    ],
    "name:hun_x_preferred":[
        "Wheeler"
    ],
    "name:ita_x_preferred":[
        "Wheeler"
    ],
    "name:nld_x_preferred":[
        "Wheeler"
    ],
    "name:pol_x_preferred":[
        "Wheeler"
    ],
    "name:por_x_preferred":[
        "Wheeler"
    ],
    "name:rus_x_preferred":[
        "\u0423\u0438\u043b\u0435\u0440"
    ],
    "name:srp_x_preferred":[
        "\u0412\u0438\u043b\u0435\u0440"
    ],
    "name:swe_x_preferred":[
        "Wheeler"
    ],
    "name:ukr_x_preferred":[
        "\u0412\u0456\u043b\u0435\u0440"
    ],
    "name:vol_x_preferred":[
        "Wheeler"
    ],
    "wof:name":"Wheeler",
    "wof:placetype":"locality"
},
  "geometry": {"coordinates":[-119.17196,47.1307],"type":"Point"}
}