{
  "type": "Feature",
  "properties": {
    "iso:country":"US",
    "name:por_x_preferred":[
        "Whitehill"
    ],
    "qs_pg:aaroncc":"US",
    "qs_pg:name":"Whitehill",
    "qs_pg:name_adm0":"United States",
    "qs_pg:name_adm1":"Oregon",
    "qs_pg:photos":161,
    "qs_pg:photos_1k":33,
    "qs_pg:photos_9k":1,
    "qs_pg:photos_9r":4,
    "qs_pg:photos_all":161,
    "qs_pg:photos_sr":4,
    "qs_pg:pop_sr":0,
    "qs_pg:qs_pg_placetype":"locality",
    "qs_pg:qs_pg_placetype_gp":"Town",
    "qs_pg:woe_adm0":23424977,
    "woe:adm0_id":23424977,
    "woe:name_adm0":"United States",
    "woe:name_adm1":"Oregon",
    "woe:placetype":"Town",
    "wof:name":"Whitehill",
    "wof:placetype":"locality"
},
  "geometry": {"coordinates":[-120.70634099999999,42.725444],"type":"Point"}
}