{
  "type": "Feature",
  "properties": {
    "gn:country":"US",
    "gn:fcode":"PPL",
    "gn:population":0,
    "iso:country":"US",
    "name:bre_x_preferred":[
        "Burton"
    ],
    "name:cat_x_preferred":[
        "Burton"
    ],
    "name:ceb_x_preferred":[
        "Burton"
    ],
    "name:ces_x_preferred":[
        "Burton"
    ],
    "name:cor_x_preferred":[
        "Burton"
    ],
    "name:cym_x_preferred":[
        "Burton"
    ],
    "name:deu_x_preferred":[
        "Burton"
    ],
    "name:fas_x_preferred":[
        "\u0628\u0631\u062a\u0648\u0646"
    ],
    "name:fin_x_preferred":[
        "Burton"
    ],
    "name:fra_x_preferred":[
        "Burton"
    ],
    "name:gla_x_preferred":[
        "Burton"
    ],
    "name:heb_x_preferred":[
        "\u05d1\u05e8\u05d8\u05d5\u05df"
    ],
    "name:ita_x_preferred":[
        "Burton"
    ],
    "name:lit_x_preferred":[
        "Burton"
    ],
    "name:nld_x_preferred":[
        "Burton"
    ],
    "name:pol_x_preferred":[
        "Burton"
    ],
    "name:por_x_preferred":[
        "Burton"
    ],
    "name:rus_x_preferred":[
        "\u0411\u0451\u0440\u0442\u043e\u043d"
    ],
    "name:swe_x_preferred":[
        "Burton"
    ],
    "name:ukr_x_preferred":[
        "\u0411\u0435\u0440\u0442\u043e\u043d"
    ],
    "name:vol_x_preferred":[
        "Burton"
    ],
    "qs_pg:aaroncc":"US",
    "qs_pg:gn_country":"US",
    "qs_pg:gn_fcode":"PPL",
    "qs_pg:gn_pop":0,
    "qs_pg:name":"Burton",
    "qs_pg:name_adm0":"United States",
    "qs_pg:name_adm1":"North Carolina",
    "qs_pg:photos":21,
    "qs_pg:photos_1k":4,
    "qs_pg:photos_9k":1,
    "qs_pg:photos_9r":1,
    "qs_pg:photos_all":21,
    "qs_pg:photos_sr":1,
    "qs_pg:pop_sr":0,
    "qs_pg:qs_pg_placetype":"locality",
    "qs_pg:qs_pg_placetype_gp":"Town",
    "qs_pg:woe_adm0":23424977,
    "woe:adm0_id":23424977,
    "woe:name_adm0":"United States",
    "woe:name_adm1":"North Carolina",
    "woe:placetype":"Town",
    "wof:name":"Burton",
    "wof:placetype":"locality"
},
  "geometry": {"coordinates":[-78.8189,36.04042],"type":"Point"}
}