{
  "type": "Feature",
  "properties": {
    "iso:country":"US",
    "name:eng_x_preferred":[
        "Walnut Ridge Creek"
    ],
    "wof:name":"Walnut Ridge Creek",
    "wof:placetype":"neighbourhood",
    "wof:population":132,
    "zs:area_m":61215.881582,
    "zs:blockids":[
        191530112062017,
        191530112062031,
        191530112062030
    ],
    "zs:housing10":45,
    "zs:label":"Walnut Ridge Creek",
    "zs:pop10":132
},
  "geometry": {"coordinates":[-93.764004,41.602235],"type":"Point"}
}