{
  "type": "Feature",
  "properties": {
    "gn:admin1_code":"KS",
    "gn:admin2_code":"19.0",
    "gn:admin3_code":"30275.0",
    "gn:asciiname":"Osro",
    "gn:country_code":"US",
    "gn:dem":266,
    "gn:elevation":"267.0",
    "gn:feature_class":"P",
    "gn:feature_code":"PPL",
    "gn:name":"Osro",
    "gn:population":0,
    "gn:timezone":"America/Chicago",
    "iso:country":"US",
    "wof:name":"Osro",
    "wof:placetype":"locality"
},
  "geometry": {"coordinates":[-96.43612,37.06587],"type":"Point"}
}