{
  "type": "Feature",
  "properties": {
    "gn:admin1_code":"AR",
    "gn:admin2_code":"85.0",
    "gn:admin3_code":"92283.0",
    "gn:asciiname":"Sisemore",
    "gn:country_code":"US",
    "gn:dem":73,
    "gn:elevation":"70.0",
    "gn:feature_class":"P",
    "gn:feature_code":"PPL",
    "gn:name":"Sisemore",
    "gn:population":0,
    "gn:timezone":"America/Chicago",
    "iso:country":"US",
    "wof:name":"Sisemore",
    "wof:placetype":"locality"
},
  "geometry": {"coordinates":[-91.85153,34.7837],"type":"Point"}
}