{
  "type": "Feature",
  "properties": {
    "gn:admin1_code":"NC",
    "gn:admin2_code":"53",
    "gn:admin3_code":"92176.0",
    "gn:asciiname":"Middlewoods Mobile Home Park",
    "gn:country_code":"US",
    "gn:dem":6,
    "gn:elevation":"5.0",
    "gn:feature_class":"P",
    "gn:feature_code":"PPL",
    "gn:name":"Middlewoods Mobile Home Park",
    "gn:population":0,
    "gn:timezone":"America/New_York",
    "iso:country":"US",
    "wof:name":"Middlewoods Mobile Home Park",
    "wof:placetype":"campus"
},
  "geometry": {"coordinates":[-76.2366,36.5494],"type":"Point"}
}