{
  "type": "Feature",
  "properties": {
    "gn:admin1_code":"AR",
    "gn:admin2_code":"19.0",
    "gn:admin3_code":"90591.0",
    "gn:asciiname":"Vaden",
    "gn:country_code":"US",
    "gn:dem":64,
    "gn:elevation":"62.0",
    "gn:feature_class":"P",
    "gn:feature_code":"PPL",
    "gn:name":"Vaden",
    "gn:population":0,
    "gn:timezone":"America/Chicago",
    "iso:country":"US",
    "wof:name":"Vaden",
    "wof:placetype":"locality"
},
  "geometry": {"coordinates":[-92.93711,33.87205],"type":"Point"}
}