{
  "type": "Feature",
  "properties": {
    "gn:admin1_code":"GA",
    "gn:admin2_code":"223",
    "gn:asciiname":"Roxana",
    "gn:country_code":"US",
    "gn:dem":295,
    "gn:elevation":"292.0",
    "gn:feature_class":"P",
    "gn:feature_code":"PPL",
    "gn:name":"Roxana",
    "gn:population":0,
    "gn:timezone":"America/New_York",
    "iso:country":"US",
    "name:ara_x_preferred":[
        "\u0631\u0648\u0643\u0633\u0627\u0646\u0627"
    ],
    "name:aze_x_preferred":[
        "Roksana"
    ],
    "name:bel_x_preferred":[
        "\u0420\u0430\u043a\u0441\u0430\u043d\u0430"
    ],
    "name:bos_x_preferred":[
        "Roksana"
    ],
    "name:bre_x_preferred":[
        "Roxana"
    ],
    "name:bul_x_preferred":[
        "\u0420\u043e\u043a\u0441\u0430\u043d\u0430"
    ],
    "name:cat_x_preferred":[
        "Roxana"
    ],
    "name:ces_x_preferred":[
        "Roxana"
    ],
    "name:chv_x_preferred":[
        "\u0420\u043e\u0445\u0448\u0430\u043d\u0430\u043a"
    ],
    "name:cym_x_preferred":[
        "Roxana"
    ],
    "name:dan_x_preferred":[
        "Roxana"
    ],
    "name:deu_x_preferred":[
        "Roxane"
    ],
    "name:ell_x_preferred":[
        "\u03a1\u03c9\u03be\u03ac\u03bd\u03b7"
    ],
    "name:epo_x_preferred":[
        "Roksano"
    ],
    "name:eus_x_preferred":[
        "Roxana"
    ],
    "name:fas_x_preferred":[
        "\u0631\u0648\u0634\u0646\u06a9"
    ],
    "name:fin_x_preferred":[
        "Roksane"
    ],
    "name:fra_x_preferred":[
        "Roxane"
    ],
    "name:heb_x_preferred":[
        "\u05e8\u05d5\u05e7\u05e1\u05e0\u05d4"
    ],
    "name:hin_x_preferred":[
        "\u0930\u0941\u0916\u0938\u093e\u0928\u093e"
    ],
    "name:hun_x_preferred":[
        "Rh\u00f3xan\u00e9"
    ],
    "name:hye_x_preferred":[
        "\u054c\u0578\u0584\u057d\u0561\u0576\u0561"
    ],
    "name:ind_x_preferred":[
        "Roxana"
    ],
    "name:ita_x_preferred":[
        "Rossane"
    ],
    "name:jpn_x_preferred":[
        "\u30ed\u30af\u30b5\u30cd"
    ],
    "name:kaz_x_preferred":[
        "\u0420\u0430\u0443\u0448\u0430\u043d"
    ],
    "name:kor_x_preferred":[
        "\ub85d\uc0ac\ub124"
    ],
    "name:lit_x_preferred":[
        "Roksana"
    ],
    "name:mar_x_preferred":[
        "\u0930\u094b\u0915\u094d\u0938\u093e\u0928\u093e"
    ],
    "name:mkd_x_preferred":[
        "\u0420\u043e\u043a\u0441\u0430\u043d\u0430"
    ],
    "name:nep_x_preferred":[
        "\u0930\u094b\u0915\u094d\u0938\u093e\u0928\u093e"
    ],
    "name:nor_x_preferred":[
        "Roxana"
    ],
    "name:pol_x_preferred":[
        "Roksana"
    ],
    "name:por_x_preferred":[
        "Roxana"
    ],
    "name:ron_x_preferred":[
        "Roxana"
    ],
    "name:rus_x_preferred":[
        "\u0420\u043e\u043a\u0441\u0430\u043d\u0430"
    ],
    "name:sco_x_preferred":[
        "Roxana"
    ],
    "name:spa_x_preferred":[
        "Roxana"
    ],
    "name:srp_x_preferred":[
        "\u0420\u043e\u043a\u0441\u0430\u043d\u0430"
    ],
    "name:swe_x_preferred":[
        "Roxana"
    ],
    "name:ukr_x_preferred":[
        "\u0420\u043e\u043a\u0441\u0430\u043d\u0430"
    ],
    "name:urd_x_preferred":[
        "\u0631\u062e\u0633\u0627\u0646\u06c1"
    ],
    "name:uzb_x_preferred":[
        "Roxshanak"
    ],
    "name:vie_x_preferred":[
        "Roxana"
    ],
    "name:zho_x_preferred":[
        "\u7f57\u514b\u73ca\u5a1c"
    ],
    "wof:name":"Roxana",
    "wof:placetype":"locality"
},
  "geometry": {"coordinates":[-84.76272,33.99927],"type":"Point"}
}