{
  "type": "Feature",
  "properties": {
    "gn:admin1_code":"OH",
    "gn:admin2_code":"159.0",
    "gn:admin3_code":"59864.0",
    "gn:asciiname":"Countryside Mobile Home Park",
    "gn:country_code":"US",
    "gn:dem":303,
    "gn:elevation":"304.0",
    "gn:feature_class":"P",
    "gn:feature_code":"PPL",
    "gn:name":"Countryside Mobile Home Park",
    "gn:population":0,
    "gn:timezone":"America/New_York",
    "iso:country":"US",
    "wof:name":"Countryside Mobile Home Park",
    "wof:placetype":"campus"
},
  "geometry": {"coordinates":[-83.35899999999999,40.231],"type":"Point"}
}