{
  "type": "Feature",
  "properties": {
    "gn:elevation":14,
    "iso:country":"US",
    "name:cat_x_preferred":[
        "Oakdale"
    ],
    "name:ceb_x_preferred":[
        "Oakdale"
    ],
    "name:cym_x_preferred":[
        "Oakdale"
    ],
    "name:deu_x_preferred":[
        "Oakdale"
    ],
    "name:eng_x_preferred":[
        "Oakdale"
    ],
    "name:fra_x_preferred":[
        "Oakdale"
    ],
    "name:ita_x_preferred":[
        "Oakdale"
    ],
    "name:nld_x_preferred":[
        "Oakdale"
    ],
    "name:pol_x_preferred":[
        "Oakdale"
    ],
    "name:por_x_preferred":[
        "Oakdale"
    ],
    "name:spa_x_preferred":[
        "Oakdale"
    ],
    "name:srp_x_preferred":[
        "\u041e\u0443\u043a\u0434\u0435\u0458\u043b"
    ],
    "name:swe_x_preferred":[
        "Oakdale"
    ],
    "name:vol_x_preferred":[
        "Oakdale"
    ],
    "qs:gn_adm0_cc":"US",
    "qs:gn_fcode":"PPL",
    "qs:gn_local":4161438,
    "qs:gn_nam_loc":"Lakeland, Polk, Florida, US",
    "qs:gn_namadm1":"FL",
    "qs:gn_name":"Oakdale",
    "qs:local_max":3081,
    "qs:local_sum":7667,
    "qs:localhoods":24,
    "qs:name":"Oakdale",
    "qs:name_adm0":"United States",
    "qs:name_adm1":"Florida",
    "qs:name_adm2":"Polk",
    "qs:name_local":"Lakeland",
    "qs:photo_max":25,
    "qs:photo_sum":59,
    "qs:placetype":"Suburb",
    "qs:quad_count":6,
    "qs:woe_adm0":23424977,
    "qs:woe_adm1":2347568,
    "qs:woe_adm2":12587855,
    "qs:woe_lau":0,
    "qs:woe_local":2435325,
    "qs:woe_ver":"7.10.0",
    "wof:name":"Oakdale",
    "wof:placetype":"neighbourhood",
    "wof:population":1524,
    "zs:blockids":[
        121050107013011,
        121050105022032,
        121050105022036,
        121050105022028,
        121050106012004,
        121050105022035,
        121050106012005,
        121050107013016,
        121050107013013,
        121050105022013,
        121050107013007,
        121050106012007,
        121050106012003,
        121050107011018,
        121050107013008,
        121050107013012,
        121050105022038,
        121050105022044,
        121050105022029,
        121050107013001,
        121050107013018,
        121050105022042,
        121050105022034,
        121050105022033,
        121050105022031,
        121050105022030,
        121050105022037,
        121050107013003,
        121050107013010,
        121050107013015,
        121050107013002,
        121050105022043,
        121050105022012
    ],
    "zs:housing10":794,
    "zs:pop10":1524
},
  "geometry": {"coordinates":[-81.956745,28.013917],"type":"Point"}
}