{
  "type": "Feature",
  "properties": {
    "gn:admin1_code":"MO",
    "gn:admin2_code":"55.0",
    "gn:admin3_code":"55100.0",
    "gn:asciiname":"Czar",
    "gn:country_code":"US",
    "gn:dem":360,
    "gn:elevation":"353.0",
    "gn:feature_class":"P",
    "gn:feature_code":"PPL",
    "gn:name":"Czar",
    "gn:population":0,
    "gn:timezone":"America/Chicago",
    "iso:country":"US",
    "wof:name":"Czar",
    "wof:placetype":"locality"
},
  "geometry": {"coordinates":[-91.11847,37.7531],"type":"Point"}
}