{
  "type": "Feature",
  "properties": {
    "iso:country":"US",
    "name:eng_x_preferred":[
        "East Polk"
    ],
    "wof:name":"East Polk",
    "wof:placetype":"neighbourhood",
    "wof:population":6,
    "zs:area_m":1386406.687827,
    "zs:blockids":[
        191530107021039
    ],
    "zs:housing10":3,
    "zs:label":"East Polk",
    "zs:pop10":6
},
  "geometry": {"coordinates":[-93.34266599999999,41.560536],"type":"Point"}
}