{
  "type": "Feature",
  "properties": {
    "gn:admin1_code":"GA",
    "gn:admin2_code":"67",
    "gn:asciiname":"The Village Mobile Home Park",
    "gn:country_code":"US",
    "gn:dem":258,
    "gn:elevation":"255.0",
    "gn:feature_class":"P",
    "gn:feature_code":"PPL",
    "gn:name":"The Village Mobile Home Park",
    "gn:population":0,
    "gn:timezone":"America/New_York",
    "iso:country":"US",
    "wof:name":"The Village Mobile Home Park",
    "wof:placetype":"campus"
},
  "geometry": {"coordinates":[-84.57938,33.75566],"type":"Point"}
}