{
  "type": "Feature",
  "properties": {
    "iso:country":"US",
    "name:eng_x_preferred":[
        "Maplewood Forest"
    ],
    "wof:name":"Maplewood Forest",
    "wof:placetype":"neighbourhood",
    "wof:population":694,
    "zs:area_m":1631560.589479,
    "zs:blockids":[
        371830521021023,
        371830520023002,
        371830521021017,
        371830520023003,
        371830521021042,
        371830521021009,
        371830521021024,
        371830520023004,
        371830521021011,
        371830521021020,
        371830521021043,
        371830521021025
    ],
    "zs:housing10":243,
    "zs:label":"Maplewood Forest",
    "zs:pop10":694
},
  "geometry": {"coordinates":[-78.598381,35.751526],"type":"Point"}
}