{
  "type": "Feature",
  "properties": {
    "gn:admin1_code":"PA",
    "gn:admin2_code":"101.0",
    "gn:admin3_code":"60000.0",
    "gn:asciiname":"Shawmont",
    "gn:country_code":"US",
    "gn:dem":114,
    "gn:elevation":"110.0",
    "gn:feature_class":"P",
    "gn:feature_code":"PPL",
    "gn:name":"Shawmont",
    "gn:population":0,
    "gn:timezone":"America/New_York",
    "iso:country":"US",
    "name:eng_x_preferred":[
        "Shawmont"
    ],
    "name:und_x_variant":[
        "Roxboro"
    ],
    "wof:name":"Shawmont",
    "wof:placetype":"locality"
},
  "geometry": {"coordinates":[-75.23600999999999,40.05289000000001],"type":"Point"}
}