{
  "type": "Feature",
  "properties": {
    "gn:admin1_code":"PA",
    "gn:admin2_code":"133.0",
    "gn:admin3_code":"15656.0",
    "gn:asciiname":"Andersontown",
    "gn:country_code":"US",
    "gn:dem":169,
    "gn:elevation":"162.0",
    "gn:feature_class":"P",
    "gn:feature_code":"PPL",
    "gn:name":"Andersontown",
    "gn:population":0,
    "gn:timezone":"America/New_York",
    "iso:country":"US",
    "wof:name":"Andersontown",
    "wof:placetype":"locality"
},
  "geometry": {"coordinates":[-76.8283,40.07926],"type":"Point"}
}