{
  "type": "Feature",
  "properties": {
    "gn:country":"US",
    "gn:fcode":"PPL",
    "gn:population":0,
    "iso:country":"US",
    "name:azb_x_preferred":[
        "\u0645\u06cc\u062f\u0644\u0646\u062f"
    ],
    "name:eng_x_preferred":[
        "Midland"
    ],
    "name:fas_x_preferred":[
        "\u0645\u06cc\u062f\u0644\u0646\u062f"
    ],
    "name:fra_x_preferred":[
        "Midland"
    ],
    "name:hat_x_preferred":[
        "Midland"
    ],
    "name:vol_x_preferred":[
        "Midland"
    ],
    "name:zho_x_preferred":[
        "\u7c73\u5170\u5fb7\u9547"
    ],
    "qs_pg:aaroncc":"US",
    "qs_pg:gn_country":"US",
    "qs_pg:gn_fcode":"PPL",
    "qs_pg:gn_pop":0,
    "qs_pg:name":"Midland",
    "qs_pg:name_adm0":"United States",
    "qs_pg:name_adm1":"Oregon",
    "qs_pg:photos":43,
    "qs_pg:photos_1k":9,
    "qs_pg:photos_9k":1,
    "qs_pg:photos_9r":2,
    "qs_pg:photos_all":43,
    "qs_pg:photos_sr":2,
    "qs_pg:pop_sr":5,
    "qs_pg:qs_pg_placetype":"locality",
    "qs_pg:qs_pg_placetype_gp":"Town",
    "qs_pg:woe_adm0":23424977,
    "woe:adm0_id":23424977,
    "woe:name_adm0":"United States",
    "woe:name_adm1":"Oregon",
    "woe:placetype":"Town",
    "wof:name":"Midland",
    "wof:placetype":"locality"
},
  "geometry": {"coordinates":[-121.82028,42.1307],"type":"Point"}
}