{
  "type": "Feature",
  "properties": {
    "gn:admin1_code":"PA",
    "gn:admin2_code":"107.0",
    "gn:admin3_code":"79120.0",
    "gn:asciiname":"Hepler",
    "gn:country_code":"US",
    "gn:dem":272,
    "gn:elevation":"275.0",
    "gn:feature_class":"P",
    "gn:feature_code":"PPL",
    "gn:name":"Hepler",
    "gn:population":0,
    "gn:timezone":"America/New_York",
    "iso:country":"US",
    "wof:name":"Hepler",
    "wof:placetype":"locality"
},
  "geometry": {"coordinates":[-76.57746,40.69175],"type":"Point"}
}