{
  "type": "Feature",
  "properties": {
    "iso:country":"US",
    "name:cat_x_preferred":[
        "Newbury"
    ],
    "name:ceb_x_preferred":[
        "Newbury"
    ],
    "name:deu_x_preferred":[
        "Newbury"
    ],
    "name:fas_x_preferred":[
        "\u0646\u06cc\u0648\u0628\u0631\u06cc"
    ],
    "name:fra_x_preferred":[
        "Newbury"
    ],
    "name:ita_x_preferred":[
        "Newbury"
    ],
    "name:pol_x_preferred":[
        "Newbury"
    ],
    "name:por_x_preferred":[
        "Newbury"
    ],
    "name:spa_x_preferred":[
        "Newbury"
    ],
    "name:swe_x_preferred":[
        "Newbury"
    ],
    "name:vol_x_preferred":[
        "Newbury"
    ],
    "qs_pg:aaroncc":"US",
    "qs_pg:name":"Newbury",
    "qs_pg:name_adm0":"United States",
    "qs_pg:name_adm1":"Ohio",
    "qs_pg:photos":1,
    "qs_pg:photos_1k":1,
    "qs_pg:photos_9k":1,
    "qs_pg:photos_9r":1,
    "qs_pg:photos_all":1,
    "qs_pg:photos_sr":1,
    "qs_pg:pop_sr":0,
    "qs_pg:qs_pg_placetype":"locality",
    "qs_pg:qs_pg_placetype_gp":"Town",
    "qs_pg:woe_adm0":23424977,
    "woe:adm0_id":23424977,
    "woe:name_adm0":"United States",
    "woe:name_adm1":"Ohio",
    "woe:placetype":"Town",
    "wof:name":"Newbury",
    "wof:placetype":"locality"
},
  "geometry": {"coordinates":[-81.407999,41.455914],"type":"Point"}
}