{
  "type": "Feature",
  "properties": {
    "gn:admin1_code":"MD",
    "gn:admin2_code":"35.0",
    "gn:asciiname":"Beach Harbor Mobile Home Park",
    "gn:country_code":"US",
    "gn:dem":4,
    "gn:elevation":"2.0",
    "gn:feature_class":"P",
    "gn:feature_code":"PPL",
    "gn:name":"Beach Harbor Mobile Home Park",
    "gn:population":0,
    "gn:timezone":"America/New_York",
    "iso:country":"US",
    "wof:name":"Beach Harbor Mobile Home Park",
    "wof:placetype":"campus"
},
  "geometry": {"coordinates":[-76.21550999999999,38.96567],"type":"Point"}
}