{
  "type": "Feature",
  "properties": {
    "gn:admin1_code":"TN",
    "gn:admin2_code":"77",
    "gn:asciiname":"Hinson Springs",
    "gn:country_code":"US",
    "gn:dem":129,
    "gn:elevation":"134.0",
    "gn:feature_class":"P",
    "gn:feature_code":"PPL",
    "gn:name":"Hinson Springs",
    "gn:population":0,
    "gn:timezone":"America/Chicago",
    "iso:country":"US",
    "name:eng_x_preferred":[
        "Hinson Springs"
    ],
    "name:und_x_variant":[
        "Hinson Spring",
        "Hinsonsprings"
    ],
    "wof:name":"Hinson Springs",
    "wof:placetype":"locality"
},
  "geometry": {"coordinates":[-88.42449000000001,35.62785],"type":"Point"}
}