{
  "type": "Feature",
  "properties": {
    "gn:admin1_code":"TX",
    "gn:admin2_code":"201.0",
    "gn:asciiname":"Parkway Villages",
    "gn:country_code":"US",
    "gn:dem":31,
    "gn:elevation":"26.0",
    "gn:feature_class":"P",
    "gn:feature_code":"PPL",
    "gn:name":"Parkway Villages",
    "gn:population":0,
    "gn:timezone":"America/Chicago",
    "iso:country":"US",
    "wof:name":"Parkway Villages",
    "wof:placetype":"locality"
},
  "geometry": {"coordinates":[-95.6268,29.7626],"type":"Point"}
}