{
  "type": "Feature",
  "properties": {
    "gn:admin1_code":"IN",
    "gn:admin2_code":"53.0",
    "gn:admin3_code":"78479.0",
    "gn:asciiname":"Farrville",
    "gn:country_code":"US",
    "gn:dem":256,
    "gn:elevation":"258.0",
    "gn:feature_class":"P",
    "gn:feature_code":"PPL",
    "gn:name":"Farrville",
    "gn:population":0,
    "gn:timezone":"America/Indiana/Indianapolis",
    "iso:country":"US",
    "name:fas_x_preferred":[
        "\u0641\u0627\u0631\u0648\u06cc\u0644"
    ],
    "wof:name":"Farrville",
    "wof:placetype":"locality"
},
  "geometry": {"coordinates":[-85.46635999999999,40.58115],"type":"Point"}
}