{
  "type": "Feature",
  "properties": {
    "gn:admin1_code":"KY",
    "gn:admin2_code":"109",
    "gn:asciiname":"Egypt",
    "gn:country_code":"US",
    "gn:dem":348,
    "gn:elevation":"346.0",
    "gn:feature_class":"P",
    "gn:feature_code":"PPL",
    "gn:name":"Egypt",
    "gn:population":0,
    "gn:timezone":"America/New_York",
    "iso:country":"US",
    "wof:name":"Egypt",
    "wof:placetype":"locality"
},
  "geometry": {"coordinates":[-83.89604,37.31314],"type":"Point"}
}