{
  "type": "Feature",
  "properties": {
    "gn:admin1_code":"OH",
    "gn:admin2_code":"71.0",
    "gn:admin3_code":"43190.0",
    "gn:asciiname":"Blair Modern Trailer Court",
    "gn:country_code":"US",
    "gn:dem":324,
    "gn:elevation":"322.0",
    "gn:feature_class":"P",
    "gn:feature_code":"PPL",
    "gn:name":"Blair Modern Trailer Court",
    "gn:population":0,
    "gn:timezone":"America/New_York",
    "iso:country":"US",
    "wof:name":"Blair Modern Trailer Court",
    "wof:placetype":"locality"
},
  "geometry": {"coordinates":[-83.60611,39.19722],"type":"Point"}
}