{
  "type": "Feature",
  "properties": {
    "gn:admin1_code":"AL",
    "gn:admin2_code":"103",
    "gn:asciiname":"Briscoe",
    "gn:country_code":"US",
    "gn:dem":356,
    "gn:elevation":"349.0",
    "gn:feature_class":"P",
    "gn:feature_code":"PPL",
    "gn:name":"Briscoe",
    "gn:population":0,
    "gn:timezone":"America/Chicago",
    "iso:country":"US",
    "name:deu_x_preferred":[
        "Briscoe"
    ],
    "name:fra_x_preferred":[
        "Briscoe"
    ],
    "name:jpn_x_preferred":[
        "\u30d6\u30ea\u30b9\u30b3\u30fc"
    ],
    "name:rus_x_preferred":[
        "\u0411\u0440\u0438\u0441\u043a\u043e"
    ],
    "wof:name":"Briscoe",
    "wof:placetype":"locality"
},
  "geometry": {"coordinates":[-86.5886,34.45787],"type":"Point"}
}