{
  "type": "Feature",
  "properties": {
    "gn:admin1_code":"MO",
    "gn:admin2_code":"109.0",
    "gn:admin3_code":"42806.0",
    "gn:asciiname":"Stinson",
    "gn:country_code":"US",
    "gn:dem":346,
    "gn:elevation":"345.0",
    "gn:feature_class":"P",
    "gn:feature_code":"PPL",
    "gn:name":"Stinson",
    "gn:population":0,
    "gn:timezone":"America/Chicago",
    "iso:country":"US",
    "name:deu_x_preferred":[
        "Stinson"
    ],
    "name:eng_x_preferred":[
        "Stinson"
    ],
    "name:fra_x_preferred":[
        "Stinson"
    ],
    "name:nds_x_preferred":[
        "Stinson"
    ],
    "name:und_x_variant":[
        "Stinton"
    ],
    "wof:name":"Stinson",
    "wof:placetype":"locality"
},
  "geometry": {"coordinates":[-93.75243,37.24644],"type":"Point"}
}