{
  "type": "Feature",
  "properties": {
    "gn:admin1_code":"GA",
    "gn:admin2_code":"217.0",
    "gn:asciiname":"Millers Glen",
    "gn:country_code":"US",
    "gn:dem":256,
    "gn:elevation":"247.0",
    "gn:feature_class":"P",
    "gn:feature_code":"PPL",
    "gn:name":"Millers Glen",
    "gn:population":0,
    "gn:timezone":"America/New_York",
    "iso:country":"US",
    "wof:name":"Millers Glen",
    "wof:placetype":"locality"
},
  "geometry": {"coordinates":[-83.96519000000001,33.56845],"type":"Point"}
}