{
  "type": "Feature",
  "properties": {
    "gn:admin1_code":"NM",
    "gn:admin2_code":"49.0",
    "gn:asciiname":"Seton Village",
    "gn:country_code":"US",
    "gn:dem":2131,
    "gn:elevation":"2132.0",
    "gn:feature_class":"P",
    "gn:feature_code":"PPL",
    "gn:name":"Seton Village",
    "gn:population":0,
    "gn:timezone":"America/Denver",
    "iso:country":"US",
    "name:fas_x_preferred":[
        "\u0633\u06cc\u062a\u0648\u0646 \u0648\u06cc\u0644\u06cc\u062c"
    ],
    "wof:name":"Seton Village",
    "wof:placetype":"locality"
},
  "geometry": {"coordinates":[-105.93252,35.5992],"type":"Point"}
}