{
  "type": "Feature",
  "properties": {
    "gn:admin1_code":"MD",
    "gn:admin2_code":"27.0",
    "gn:asciiname":"Glenmont",
    "gn:country_code":"US",
    "gn:dem":135,
    "gn:elevation":"130.0",
    "gn:feature_class":"P",
    "gn:feature_code":"PPL",
    "gn:name":"Glenmont",
    "gn:population":0,
    "gn:timezone":"America/New_York",
    "iso:country":"US",
    "name:ceb_x_preferred":[
        "Glenmont"
    ],
    "name:deu_x_preferred":[
        "Glenmont"
    ],
    "name:ita_x_preferred":[
        "Glenmont"
    ],
    "name:nld_x_preferred":[
        "Glenmont"
    ],
    "name:pol_x_preferred":[
        "Glenmont"
    ],
    "name:por_x_preferred":[
        "Glenmont"
    ],
    "name:srp_x_preferred":[
        "\u0413\u043b\u0435\u043d\u043c\u043e\u043d\u0442"
    ],
    "wof:name":"Glenmont",
    "wof:placetype":"locality"
},
  "geometry": {"coordinates":[-76.82635999999999,39.22538],"type":"Point"}
}