{
  "type": "Feature",
  "properties": {
    "gn:country":"US",
    "gn:fcode":"PPL",
    "gn:population":0,
    "iso:country":"US",
    "name:cat_x_preferred":[
        "Bernards Township"
    ],
    "name:cym_x_preferred":[
        "Bernards Township"
    ],
    "name:deu_x_preferred":[
        "Bernards Township"
    ],
    "name:eng_x_preferred":[
        "Bernards Township"
    ],
    "name:eng_x_variant":[
        "Township of Bernards"
    ],
    "name:epo_x_preferred":[
        "Bernards"
    ],
    "name:fas_x_preferred":[
        "\u0628\u0631\u0646\u0627\u0631\u062f\u0632\u060c \u0646\u06cc\u0648\u062c\u0631\u0633\u06cc"
    ],
    "name:fas_x_variant":[
        "\u0628\u0631\u0646\u0627\u0631\u062f\u0632"
    ],
    "name:fra_x_preferred":[
        "township de Bernards"
    ],
    "name:hat_x_preferred":[
        "Bernards"
    ],
    "name:jpn_x_preferred":[
        "\u30d0\u30fc\u30ca\u30fc\u30ba\u30fb\u30bf\u30a6\u30f3\u30b7\u30c3\u30d7"
    ],
    "name:kaz_x_preferred":[
        "\u0411\u044d\u0440\u043d\u0430\u0440\u0434\u0441 \u0422\u0430\u0443\u043d\u0448\u0438\u043f"
    ],
    "name:kir_x_preferred":[
        "\u0411\u044d\u0440\u043d\u0430\u0440\u0434\u0441 \u0422\u0430\u0443\u043d\u0448\u0438\u043f"
    ],
    "name:rus_x_preferred":[
        "\u0442\u0430\u0443\u043d\u0448\u0438\u043f \u0411\u0435\u0440\u043d\u0430\u0440\u0434\u0441"
    ],
    "name:rus_x_variant":[
        "\u0411\u0435\u0440\u043d\u0430\u0440\u0434\u0441"
    ],
    "name:spa_x_preferred":[
        "Municipio de Bernards"
    ],
    "name:ukr_x_preferred":[
        "\u0411\u0435\u0440\u043d\u0430\u0440\u0434\u0441 \u0422\u0430\u0443\u043d\u0448\u0438\u043f"
    ],
    "name:und_x_variant":[
        "Bernard Township"
    ],
    "name:zho_x_preferred":[
        "\u4f2f\u7eb3\u5fb7"
    ],
    "qs_pg:aaroncc":"US",
    "qs_pg:gn_country":"US",
    "qs_pg:gn_fcode":"PPL",
    "qs_pg:gn_pop":0,
    "qs_pg:name":"Bernards",
    "qs_pg:name_adm0":"United States",
    "qs_pg:name_adm1":"New Jersey",
    "qs_pg:photos":58,
    "qs_pg:photos_1k":12,
    "qs_pg:photos_9k":2,
    "qs_pg:photos_9r":5,
    "qs_pg:photos_all":409,
    "qs_pg:photos_sr":2,
    "qs_pg:pop_sr":0,
    "qs_pg:qs_pg_placetype":"locality",
    "qs_pg:qs_pg_placetype_gp":"Town",
    "qs_pg:woe_adm0":23424977,
    "woe:adm0_id":23424977,
    "woe:name_adm0":"United States",
    "woe:name_adm1":"New Jersey",
    "woe:placetype":"Town",
    "wof:coterminous":[
        404477911
    ],
    "wof:name":"Bernards",
    "wof:placetype":"locality",
    "wof:statistical_gore":1
},
  "geometry": {"coordinates":[-74.5746,40.68343],"type":"Point"}
}