{
  "type": "Feature",
  "properties": {
    "gn:admin1_code":"TN",
    "gn:admin2_code":"13.0",
    "gn:asciiname":"Stinking Creek",
    "gn:country_code":"US",
    "gn:dem":373,
    "gn:elevation":"373.0",
    "gn:feature_class":"P",
    "gn:feature_code":"PPL",
    "gn:name":"Stinking Creek",
    "gn:population":0,
    "gn:timezone":"America/New_York",
    "iso:country":"US",
    "wof:name":"Stinking Creek",
    "wof:placetype":"locality"
},
  "geometry": {"coordinates":[-84.14104,36.50675],"type":"Point"}
}