{
  "type": "Feature",
  "properties": {
    "gn:admin1_code":"NY",
    "gn:admin2_code":"61.0",
    "gn:asciiname":"Taino Towers",
    "gn:country_code":"US",
    "gn:dem":13,
    "gn:elevation":"3.0",
    "gn:feature_class":"P",
    "gn:feature_code":"PPL",
    "gn:name":"Taino Towers",
    "gn:population":0,
    "gn:timezone":"America/New_York",
    "iso:country":"US",
    "wof:name":"Taino Towers",
    "wof:placetype":"locality"
},
  "geometry": {"coordinates":[-73.93361,40.80083],"type":"Point"}
}