{
  "type": "Feature",
  "properties": {
    "gn:admin1_code":"LA",
    "gn:admin2_code":"53.0",
    "gn:asciiname":"Paradise Mobile Home Park",
    "gn:country_code":"US",
    "gn:dem":10,
    "gn:elevation":"8.0",
    "gn:feature_class":"P",
    "gn:feature_code":"PPL",
    "gn:name":"Paradise Mobile Home Park",
    "gn:population":0,
    "gn:timezone":"America/Chicago",
    "iso:country":"US",
    "wof:name":"Paradise Mobile Home Park",
    "wof:placetype":"campus"
},
  "geometry": {"coordinates":[-92.66204999999999,30.21057],"type":"Point"}
}