{
  "type": "Feature",
  "properties": {
    "iso:country":"US",
    "name:eng_x_preferred":[
        "Windsor Forest"
    ],
    "name:eng_x_variant":[
        "Windsor Frst"
    ],
    "qs:gn_adm0_cc":"US",
    "qs:gn_fcode":"PPL",
    "qs:gn_local":4221552,
    "qs:gn_namadm1":"GA",
    "qs:gn_name":"Windsor Forest",
    "qs:local_max":19077,
    "qs:local_sum":44761,
    "qs:localhoods":36,
    "qs:name":"Windsor Forest",
    "qs:name_adm0":"United States",
    "qs:name_adm1":"Georgia",
    "qs:name_adm2":"Chatham",
    "qs:name_local":"Savannah",
    "qs:photo_max":15,
    "qs:photo_sum":37,
    "qs:placetype":"Suburb",
    "qs:quad_count":8,
    "qs:woe_adm0":23424977,
    "qs:woe_adm1":2347569,
    "qs:woe_adm2":12587894,
    "qs:woe_lau":0,
    "qs:woe_local":2489314,
    "qs:woe_ver":"7.10.0",
    "wof:name":"Windsor Forest",
    "wof:placetype":"neighbourhood"
},
  "geometry": {"coordinates":[-81.15169400000001,31.970266],"type":"Point"}
}