{
  "type": "Feature",
  "properties": {
    "iso:country":"US",
    "name:ara_x_preferred":[
        "\u063a\u0644\u0648\u0643\u0633\u062a\u064a\u0631"
    ],
    "name:arz_x_preferred":[
        "\u062c\u0644\u0648\u0643\u0633\u062a\u064a\u0631"
    ],
    "name:cat_x_preferred":[
        "Glocester"
    ],
    "name:che_x_preferred":[
        "\u0413\u043b\u043e\u0441\u0442\u0435\u0440"
    ],
    "name:cym_x_preferred":[
        "Glocester"
    ],
    "name:deu_x_preferred":[
        "Glocester"
    ],
    "name:eng_x_preferred":[
        "Glocester"
    ],
    "name:eus_x_preferred":[
        "Glocester"
    ],
    "name:fra_x_preferred":[
        "Glocester"
    ],
    "name:gle_x_preferred":[
        "Glocester"
    ],
    "name:hat_x_preferred":[
        "Glocester"
    ],
    "name:hun_x_preferred":[
        "Glocester"
    ],
    "name:ita_x_preferred":[
        "Glocester"
    ],
    "name:jpn_x_preferred":[
        "\u30b0\u30ed\u30b9\u30bf\u30fc"
    ],
    "name:nld_x_preferred":[
        "Glocester"
    ],
    "name:pol_x_preferred":[
        "Glocester"
    ],
    "name:por_x_preferred":[
        "Glocester"
    ],
    "name:spa_x_preferred":[
        "Glocester"
    ],
    "name:swe_x_preferred":[
        "Glocester"
    ],
    "name:tat_x_preferred":[
        "\u0413\u043b\u043e\u0441\u0442\u0435\u0440"
    ],
    "name:tur_x_preferred":[
        "Glocester"
    ],
    "name:ukr_x_preferred":[
        "\u0413\u043b\u043e\u0441\u0442\u0435\u0440"
    ],
    "name:urd_x_preferred":[
        "\u06af\u0644\u0627\u0633\u0679\u0631\u060c \u0631\u0648\u0688 \u0622\u0626\u0644\u06cc\u0646\u0688"
    ],
    "name:urd_x_variant":[
        "\u06af\u0644\u0627\u0633\u0679\u0631"
    ],
    "name:vol_x_preferred":[
        "Glocester"
    ],
    "name:war_x_preferred":[
        "Glocester"
    ],
    "name:zho_x_preferred":[
        "\u544a\u7f85\u58eb\u6253"
    ],
    "qs_pg:aaroncc":"US",
    "qs_pg:name":"Glocester",
    "qs_pg:name_adm0":"United States",
    "qs_pg:name_adm1":"Rhode Island",
    "qs_pg:photos":93,
    "qs_pg:photos_1k":19,
    "qs_pg:photos_9k":1,
    "qs_pg:photos_9r":4,
    "qs_pg:photos_all":215,
    "qs_pg:photos_sr":3,
    "qs_pg:pop_sr":0,
    "qs_pg:qs_pg_placetype":"locality",
    "qs_pg:qs_pg_placetype_gp":"Town",
    "qs_pg:woe_adm0":23424977,
    "woe:adm0_id":23424977,
    "woe:name_adm0":"United States",
    "woe:name_adm1":"Rhode Island",
    "woe:placetype":"Town",
    "wof:name":"Glocester",
    "wof:placetype":"locality",
    "wof:statistical_gore":1
},
  "geometry": {"coordinates":[-71.720634,41.876718],"type":"Point"}
}