{
  "type": "Feature",
  "properties": {
    "gn:admin1_code":"KY",
    "gn:admin2_code":"195",
    "gn:asciiname":"Boldman",
    "gn:country_code":"US",
    "gn:dem":203,
    "gn:elevation":"200.0",
    "gn:feature_class":"P",
    "gn:feature_code":"PPL",
    "gn:name":"Boldman",
    "gn:population":0,
    "gn:timezone":"America/New_York",
    "iso:country":"US",
    "wof:name":"Boldman",
    "wof:placetype":"locality"
},
  "geometry": {"coordinates":[-82.6221,37.52871],"type":"Point"}
}