{
  "type": "Feature",
  "properties": {
    "iso:country":"US",
    "wof:name":"North Slope",
    "wof:placetype":"neighbourhood"
},
  "geometry": {"coordinates":[-122.46278397193225,47.26154940928757],"type":"Point"}
}