{
  "type": "Feature",
  "properties": {
    "gn:admin1_code":"NM",
    "gn:admin2_code":"39",
    "gn:asciiname":"Gallegos",
    "gn:country_code":"US",
    "gn:dem":1897,
    "gn:elevation":"1896.0",
    "gn:feature_class":"P",
    "gn:feature_code":"PPL",
    "gn:name":"Gallegos",
    "gn:population":0,
    "gn:timezone":"America/Denver",
    "iso:country":"US",
    "name:ceb_x_preferred":[
        "Gallegos"
    ],
    "name:deu_x_preferred":[
        "Gallegos"
    ],
    "name:eng_x_preferred":[
        "Gallegos"
    ],
    "name:fra_x_preferred":[
        "Gallegos"
    ],
    "name:glg_x_preferred":[
        "Gallegos"
    ],
    "name:nds_x_preferred":[
        "Gallegos"
    ],
    "name:rus_x_preferred":[
        "\u0413\u0430\u043b\u044c\u0435\u0433\u043e\u0441"
    ],
    "name:slk_x_preferred":[
        "Gallegos"
    ],
    "name:spa_x_preferred":[
        "Gallegos"
    ],
    "name:swe_x_preferred":[
        "Gallegos"
    ],
    "name:ukr_x_preferred":[
        "\u0413\u0430\u043b\u044c\u0435\u0433\u043e\u0441"
    ],
    "name:ukr_x_variant":[
        "\u0413\u0430\u043b\u044c\u0454\u0433\u043e\u0441"
    ],
    "name:und_x_variant":[
        "Los Gallegos"
    ],
    "name:urd_x_preferred":[
        "\u06af\u06cc\u0644\u06cc\u06af\u0648\u0633"
    ],
    "name:vie_x_preferred":[
        "S\u00f4ng Gallegos"
    ],
    "name:zho_cn_x_preferred":[
        "\u52a0\u5229\u897f\u4e9a\u6cb3"
    ],
    "name:zho_tw_x_preferred":[
        "\u52a0\u5217\u6208\u65af\u6cb3"
    ],
    "wof:name":"Gallegos",
    "wof:placetype":"locality"
},
  "geometry": {"coordinates":[-106.05058,36.28863],"type":"Point"}
}