{
  "type": "Feature",
  "properties": {
    "gn:admin1_code":"VA",
    "gn:admin2_code":"179.0",
    "gn:asciiname":"Stratford Place",
    "gn:country_code":"US",
    "gn:dem":62,
    "gn:elevation":"50.0",
    "gn:feature_class":"P",
    "gn:feature_code":"PPL",
    "gn:name":"Stratford Place",
    "gn:population":0,
    "gn:timezone":"America/New_York",
    "iso:country":"US",
    "wof:name":"Stratford Place",
    "wof:placetype":"locality"
},
  "geometry": {"coordinates":[-77.4205,38.3258],"type":"Point"}
}