{
  "type": "Feature",
  "properties": {
    "iso:country":"US",
    "name:eng_x_preferred":[
        "Fairhills"
    ],
    "wof:name":"Fairhills",
    "wof:placetype":"neighbourhood",
    "wof:population":256,
    "zs:area_m":376965.538422,
    "zs:blockids":[
        470650006001000,
        470650006001004,
        470650006001001
    ],
    "zs:housing10":160,
    "zs:label":"Fairhills",
    "zs:pop10":256
},
  "geometry": {"coordinates":[-85.303444,35.073089],"type":"Point"}
}