{
  "type": "Feature",
  "properties": {
    "gn:admin1_code":"MD",
    "gn:admin2_code":"3.0",
    "gn:asciiname":"Champion Forest",
    "gn:country_code":"US",
    "gn:dem":73,
    "gn:elevation":"73.0",
    "gn:feature_class":"P",
    "gn:feature_code":"PPL",
    "gn:name":"Champion Forest",
    "gn:population":0,
    "gn:timezone":"America/New_York",
    "iso:country":"US",
    "wof:name":"Champion Forest",
    "wof:placetype":"locality"
},
  "geometry": {"coordinates":[-76.76108000000001,39.14733],"type":"Point"}
}