{
  "type": "Feature",
  "properties": {
    "iso:country":"US",
    "name:eng_x_preferred":[
        "Garretts Run"
    ],
    "qs:gn_fcode":"PPL",
    "qs:gn_local":0,
    "qs:gn_namadm1":"PA",
    "qs:gn_name":"Garretts Run",
    "qs:local_max":11,
    "qs:local_sum":11,
    "qs:localhoods":1,
    "qs:name":"Garretts Run",
    "qs:name_adm0":"United States",
    "qs:name_adm1":"Pennsylvania",
    "qs:name_adm2":"Armstrong",
    "qs:name_local":"Manor",
    "qs:photo_max":5,
    "qs:photo_sum":11,
    "qs:placetype":"Suburb",
    "qs:quad_count":5,
    "qs:woe_adm0":23424977,
    "qs:woe_adm1":2347597,
    "qs:woe_adm2":12589730,
    "qs:woe_lau":0,
    "qs:woe_local":28744913,
    "qs:woe_ver":"7.10.0",
    "wof:lang":[
        "eng"
    ],
    "wof:name":"Garretts Run",
    "wof:placetype":"neighbourhood",
    "wof:population":289,
    "zs:blockids":[
        420059512003010,
        420059512004006,
        420059512003012,
        420059512003015,
        420059512003014,
        420059512004000,
        420059512003016,
        420059512004001,
        420059512003008,
        420059512003018,
        420059512003009,
        420059512003011
    ],
    "zs:housing10":118,
    "zs:pop10":289
},
  "geometry": {"coordinates":[-79.533776,40.795475],"type":"Point"}
}