{
  "type": "Feature",
  "properties": {
    "iso:country":"US",
    "name:eng_x_preferred":[
        "Shops at the Forum"
    ],
    "wof:name":"Shops at the Forum",
    "wof:placetype":"neighbourhood",
    "wof:population":225,
    "zs:area_m":381596.660446,
    "zs:blockids":[
        50070205031029,
        50070206031001,
        50070206031000,
        50070205031025
    ],
    "zs:housing10":120,
    "zs:label":"Shops at the Forum",
    "zs:pop10":225
},
  "geometry": {"coordinates":[-94.192431,36.335587],"type":"Point"}
}