{
  "type": "Feature",
  "properties": {
    "gn:admin1_code":"OR",
    "gn:admin2_code":"45",
    "gn:asciiname":"Danner",
    "gn:country_code":"US",
    "gn:dem":1293,
    "gn:elevation":"1290.0",
    "gn:feature_class":"P",
    "gn:feature_code":"PPL",
    "gn:name":"Danner",
    "gn:population":0,
    "gn:timezone":"America/Boise",
    "iso:country":"US",
    "name:azb_x_preferred":[
        "\u062f\u0646\u0631"
    ],
    "name:fas_x_preferred":[
        "\u062f\u0646\u0631"
    ],
    "name:fra_x_preferred":[
        "Danner"
    ],
    "name:hat_x_preferred":[
        "Danner"
    ],
    "wof:name":"Danner",
    "wof:placetype":"locality"
},
  "geometry": {"coordinates":[-117.34014999999999,42.94432000000001],"type":"Point"}
}