{
  "type": "Feature",
  "properties": {
    "gn:admin1_code":"MO",
    "gn:admin2_code":"41.0",
    "gn:admin3_code":"13204.0",
    "gn:asciiname":"Aholt",
    "gn:country_code":"US",
    "gn:dem":188,
    "gn:elevation":"189.0",
    "gn:feature_class":"P",
    "gn:feature_code":"PPL",
    "gn:name":"Aholt",
    "gn:population":0,
    "gn:timezone":"America/Chicago",
    "iso:country":"US",
    "wof:name":"Aholt",
    "wof:placetype":"locality"
},
  "geometry": {"coordinates":[-92.90491,39.26447],"type":"Point"}
}