{
  "type": "Feature",
  "properties": {
    "gn:admin1_code":"LA",
    "gn:admin2_code":"59.0",
    "gn:asciiname":"Searcy",
    "gn:country_code":"US",
    "gn:dem":38,
    "gn:elevation":"31.0",
    "gn:feature_class":"P",
    "gn:feature_code":"PPL",
    "gn:name":"Searcy",
    "gn:population":0,
    "gn:timezone":"America/Chicago",
    "iso:country":"US",
    "name:deu_x_preferred":[
        "Searcy"
    ],
    "name:fra_x_preferred":[
        "Searcy"
    ],
    "name:pol_x_preferred":[
        "Searcy"
    ],
    "name:srp_x_preferred":[
        "\u0421\u0435\u0440\u0441\u0438"
    ],
    "wof:name":"Searcy",
    "wof:placetype":"locality"
},
  "geometry": {"coordinates":[-92.22819,31.70517000000001],"type":"Point"}
}