{
  "type": "Feature",
  "properties": {
    "gn:admin1_code":"IL",
    "gn:admin2_code":"197",
    "gn:admin3_code":"60300.0",
    "gn:asciiname":"Fond du Lac",
    "gn:country_code":"US",
    "gn:dem":188,
    "gn:elevation":"187.0",
    "gn:feature_class":"P",
    "gn:feature_code":"PPL",
    "gn:name":"Fond du Lac",
    "gn:population":0,
    "gn:timezone":"America/Chicago",
    "iso:country":"US",
    "name:ceb_x_preferred":[
        "Fond du Lac"
    ],
    "name:nld_x_preferred":[
        "Fond du Lac"
    ],
    "name:pol_x_preferred":[
        "Fond du Lac"
    ],
    "name:rus_x_preferred":[
        "\u0424\u043e\u043d-\u0434\u044e-\u041b\u0430\u043a"
    ],
    "name:srp_x_preferred":[
        "\u0424\u043e\u043d\u0434 \u0434\u0443 \u041b\u0430\u043a"
    ],
    "name:swe_x_preferred":[
        "Fond du Lac"
    ],
    "name:ukr_x_preferred":[
        "\u0424\u043e\u043d-\u0434\u044e-\u041b\u0430\u043a"
    ],
    "wof:name":"Fond du Lac",
    "wof:placetype":"locality"
},
  "geometry": {"coordinates":[-88.22083000000001,41.56806],"type":"Point"}
}