{
  "type": "Feature",
  "properties": {
    "gn:admin1_code":"SC",
    "gn:admin2_code":"33.0",
    "gn:asciiname":"Carmichael Crossroads",
    "gn:country_code":"US",
    "gn:dem":25,
    "gn:elevation":"30.0",
    "gn:feature_class":"P",
    "gn:feature_code":"PPL",
    "gn:name":"Carmichael Crossroads",
    "gn:population":0,
    "gn:timezone":"America/New_York",
    "iso:country":"US",
    "wof:name":"Carmichael Crossroads",
    "wof:placetype":"locality"
},
  "geometry": {"coordinates":[-79.27449,34.34044],"type":"Point"}
}