{
  "type": "Feature",
  "properties": {
    "gn:admin1_code":"SC",
    "gn:admin2_code":"39.0",
    "gn:asciiname":"Parr",
    "gn:country_code":"US",
    "gn:dem":110,
    "gn:elevation":"105.0",
    "gn:feature_class":"P",
    "gn:feature_code":"PPL",
    "gn:name":"Parr",
    "gn:population":0,
    "gn:timezone":"America/New_York",
    "iso:country":"US",
    "name:cat_x_preferred":[
        "Parr"
    ],
    "name:deu_x_preferred":[
        "Parr"
    ],
    "name:eng_x_preferred":[
        "Parr"
    ],
    "name:fin_x_preferred":[
        "Parr"
    ],
    "name:fra_x_preferred":[
        "Parr"
    ],
    "name:ita_x_preferred":[
        "Parr"
    ],
    "name:nld_x_preferred":[
        "Parr"
    ],
    "name:pol_x_preferred":[
        "Parr"
    ],
    "name:rus_x_preferred":[
        "\u041f\u0430\u0440\u0440"
    ],
    "name:und_x_variant":[
        "Parrs Bluff"
    ],
    "wof:name":"Parr",
    "wof:placetype":"locality"
},
  "geometry": {"coordinates":[-81.3326,34.26598],"type":"Point"}
}