{
  "type": "Feature",
  "properties": {
    "gn:admin1_code":"FL",
    "gn:admin2_code":"9.0",
    "gn:asciiname":"Angel City",
    "gn:country_code":"US",
    "gn:dem":5,
    "gn:elevation":"0.0",
    "gn:feature_class":"P",
    "gn:feature_code":"PPL",
    "gn:name":"Angel City",
    "gn:population":0,
    "gn:timezone":"America/New_York",
    "iso:country":"US",
    "wof:name":"Angel City",
    "wof:placetype":"locality"
},
  "geometry": {"coordinates":[-80.66060999999998,28.34445],"type":"Point"}
}