{
  "type": "Feature",
  "properties": {
    "gn:admin1_code":"IL",
    "gn:admin2_code":"43.0",
    "gn:admin3_code":"83947.0",
    "gn:asciiname":"Mammoth Springs",
    "gn:country_code":"US",
    "gn:dem":202,
    "gn:elevation":"201.0",
    "gn:feature_class":"P",
    "gn:feature_code":"PPL",
    "gn:name":"Mammoth Springs",
    "gn:population":0,
    "gn:timezone":"America/Chicago",
    "iso:country":"US",
    "wof:name":"Mammoth Springs",
    "wof:placetype":"locality"
},
  "geometry": {"coordinates":[-87.94895,41.85447],"type":"Point"}
}