{
  "type": "Feature",
  "properties": {
    "gn:admin1_code":"MI",
    "gn:admin2_code":"73.0",
    "gn:admin3_code":"47660.0",
    "gn:asciiname":"Strickland",
    "gn:country_code":"US",
    "gn:dem":260,
    "gn:elevation":"263.0",
    "gn:feature_class":"P",
    "gn:feature_code":"PPL",
    "gn:name":"Strickland",
    "gn:population":0,
    "gn:timezone":"America/Detroit",
    "iso:country":"US",
    "name:cat_x_preferred":[
        "Strickland"
    ],
    "name:deu_x_preferred":[
        "Strickland"
    ],
    "name:fra_x_preferred":[
        "Strickland"
    ],
    "name:heb_x_preferred":[
        "\u05e1\u05d8\u05e8\u05d9\u05e7\u05dc\u05e0\u05d3"
    ],
    "name:ita_x_preferred":[
        "Strickland"
    ],
    "name:nds_x_preferred":[
        "Strickland"
    ],
    "name:pol_x_preferred":[
        "Strickland"
    ],
    "name:rus_x_preferred":[
        "\u0421\u0442\u0440\u0438\u043a\u043b\u0435\u043d\u0434"
    ],
    "name:swe_x_preferred":[
        "Strickland"
    ],
    "name:ukr_x_preferred":[
        "\u0421\u0442\u0440\u0456\u043a\u043b\u0435\u043d\u0434"
    ],
    "wof:name":"Strickland",
    "wof:placetype":"locality"
},
  "geometry": {"coordinates":[-84.83529,43.49503],"type":"Point"}
}