{
  "type": "Feature",
  "properties": {
    "gn:admin1_code":"CO",
    "gn:admin2_code":"23.0",
    "gn:asciiname":"Mesita",
    "gn:country_code":"US",
    "gn:dem":2340,
    "gn:elevation":"2339.0",
    "gn:feature_class":"P",
    "gn:feature_code":"PPL",
    "gn:name":"Mesita",
    "gn:population":0,
    "gn:timezone":"America/Denver",
    "iso:country":"US",
    "name:eng_x_preferred":[
        "Mesita"
    ],
    "name:fas_x_preferred":[
        "\u0645\u0633\u06cc\u062a\u0627"
    ],
    "name:und_x_variant":[
        "Hamburg"
    ],
    "name:vol_x_preferred":[
        "Mesita"
    ],
    "name:zho_x_preferred":[
        "\u6885\u897f\u5854"
    ],
    "wof:name":"Mesita",
    "wof:placetype":"locality"
},
  "geometry": {"coordinates":[-105.60196000000001,37.09835],"type":"Point"}
}