{
  "type": "Feature",
  "properties": {
    "gn:elevation":123,
    "iso:country":"US",
    "name:eng_x_preferred":[
        "North Belle Sherman"
    ],
    "qs:gn_adm0_cc":"US",
    "qs:gn_fcode":"PPL",
    "qs:gn_local":5122432,
    "qs:gn_nam_loc":"Ithaca, Tompkins, New York, US",
    "qs:gn_namadm1":"NY",
    "qs:gn_name":"North Belle Isle",
    "qs:local_max":6849,
    "qs:local_sum":28362,
    "qs:localhoods":22,
    "qs:name":"North Belle Sherman",
    "qs:name_adm0":"United States",
    "qs:name_adm1":"New York",
    "qs:name_adm2":"Tompkins",
    "qs:name_local":"Ithaca",
    "qs:photo_max":81,
    "qs:photo_sum":81,
    "qs:placetype":"Suburb",
    "qs:quad_count":1,
    "qs:woe_adm0":23424977,
    "qs:woe_adm1":2347591,
    "qs:woe_adm2":12589366,
    "qs:woe_funk":"Grouping neighborhood",
    "qs:woe_lau":0,
    "qs:woe_local":2427936,
    "qs:woe_ver":"7.10.0",
    "wof:lang":[
        "eng"
    ],
    "wof:name":"North Belle Sherman",
    "wof:placetype":"neighbourhood",
    "wof:population":1062,
    "zs:blockids":[
        361090013004004,
        361090013005010,
        361090013005015,
        361090003001074,
        361090013002002,
        361090013002003,
        361090013005000,
        361090013005001,
        361090013005012,
        361090013005014,
        361090003001068,
        361090013005003,
        361090013005011,
        361090013005002,
        361090013002015,
        361090013002014,
        361090013002004,
        361090013002013,
        361090013005013,
        361090013002018,
        361090013004001,
        361090013004002,
        361090013002000,
        361090003001077,
        361090013005009,
        361090013002016,
        361090013005008
    ],
    "zs:housing10":522,
    "zs:pop10":1062
},
  "geometry": {"coordinates":[-76.47995,42.442715],"type":"Point"}
}