{
  "type": "Feature",
  "properties": {
    "iso:country":"US",
    "name:eng_x_preferred":[
        "Hidden View"
    ],
    "qs:gn_adm0_cc":"US",
    "qs:gn_local":5814616,
    "qs:gn_nam_loc":"Vancouver, Clark, Washington, US",
    "qs:gn_namadm1":"WA",
    "qs:local_max":2037,
    "qs:local_sum":14855,
    "qs:localhoods":74,
    "qs:name":"Hidden View",
    "qs:name_adm0":"United States",
    "qs:name_adm1":"Washington",
    "qs:name_adm2":"Clark",
    "qs:name_local":"Vancouver",
    "qs:photo_max":16,
    "qs:photo_sum":81,
    "qs:placetype":"Suburb",
    "qs:quad_count":16,
    "qs:woe_adm0":23424977,
    "qs:woe_adm1":2347606,
    "qs:woe_adm2":12590445,
    "qs:woe_lau":0,
    "qs:woe_local":2511258,
    "qs:woe_ver":"7.10.0",
    "wof:name":"Hidden View",
    "wof:placetype":"neighbourhood",
    "wof:population":1398,
    "zs:blockids":[
        530110421002036,
        530110421002044,
        530110423001003,
        530110421002028,
        530110421002029,
        530110421002009,
        530110421002012,
        530110421002010,
        530110421002030,
        530110421002035,
        530110421002033,
        530110423001004,
        530110421002017,
        530110423001002,
        530110421002038,
        530110421002037,
        530110421002008,
        530110421002040,
        530110421002034,
        530110421002018,
        530110423001001,
        530110421002039,
        530110421002011
    ],
    "zs:housing10":570,
    "zs:pop10":1398
},
  "geometry": {"coordinates":[-122.68011,45.637831],"type":"Point"}
}