{
  "type": "Feature",
  "properties": {
    "iso:country":"US",
    "name:deu_x_preferred":[
        "West Side"
    ],
    "name:eng_x_preferred":[
        "West Side"
    ],
    "name:fra_x_preferred":[
        "West Side"
    ],
    "name:ita_x_preferred":[
        "West Side"
    ],
    "name:jpn_x_preferred":[
        "\u30a6\u30a8\u30b9\u30c8\u30fb\u30b5\u30a4\u30c9"
    ],
    "name:kor_x_preferred":[
        "\uc6e8\uc2a4\ud2b8\uc0ac\uc774\ub4dc"
    ],
    "name:nld_x_preferred":[
        "West Side"
    ],
    "name:sco_x_preferred":[
        "West Side"
    ],
    "wof:name":"West Side",
    "wof:placetype":"neighbourhood",
    "wof:population":675,
    "zs:area_m":281236.203732,
    "zs:blockids":[
        371830524072006,
        371830524061002,
        371830524072007
    ],
    "zs:housing10":321,
    "zs:label":"West Side",
    "zs:pop10":675
},
  "geometry": {"coordinates":[-78.717507,35.783078],"type":"Point"}
}