{
  "type": "Feature",
  "properties": {
    "iso:country":"US",
    "name:eng_x_preferred":[
        "Footedale"
    ],
    "wof:name":"Footedale",
    "wof:placetype":"neighbourhood",
    "wof:population":500,
    "zs:area_m":6900566.704878,
    "zs:blockids":[
        420512629003032,
        420512629003026,
        420512629003031,
        420512629003029,
        420512629003024,
        420512629003020,
        420512629003055,
        420512629003027,
        420512629003021,
        420512629003033,
        420512629003022,
        420512629003041,
        420512629003048,
        420512629003025,
        420512629003030,
        420512629003039,
        420512629003049,
        420512629003028,
        420512629003040,
        420512629003023
    ],
    "zs:housing10":202,
    "zs:label":"Footedale",
    "zs:pop10":500
},
  "geometry": {"coordinates":[-79.830304,39.90495],"type":"Point"}
}