{
  "type": "Feature",
  "properties": {
    "iso:country":"US",
    "name:eng_x_preferred":[
        "Silver Fork"
    ],
    "wof:name":"Silver Fork",
    "wof:placetype":"neighbourhood",
    "wof:population":44,
    "zs:area_m":29514888.417012,
    "zs:blockids":[
        60170319001177,
        60170319001100,
        60170319001176,
        60170306034492,
        60170306034499,
        60170319001179,
        60170319001183,
        60170306034502,
        60170319001178,
        60170319001093,
        60170306034110,
        60170306034485,
        60170319001105,
        60170319001095,
        60170319001107,
        60170319001175,
        60170306034501,
        60170319001164,
        60170319001087,
        60170319001094,
        60170319001163,
        60170319001099,
        60170319001106,
        60170306034498,
        60170306034500,
        60170319001096,
        60170319001181,
        60170319001185,
        60170319001104,
        60170319001081,
        60170306034468,
        60170319001083,
        60170319001097,
        60170319001084,
        60170319001085,
        60170319001108,
        60170306034469,
        60170306034487,
        60170319001098,
        60170319001090
    ],
    "zs:housing10":125,
    "zs:label":"Silver Fork",
    "zs:pop10":44
},
  "geometry": {"coordinates":[-120.339057,38.748122],"type":"Point"}
}