{
  "type": "Feature",
  "properties": {
    "gn:admin1_code":"NY",
    "gn:admin2_code":"45.0",
    "gn:admin3_code":"210.0",
    "gn:asciiname":"Thomas Settlement",
    "gn:country_code":"US",
    "gn:dem":162,
    "gn:elevation":"162.0",
    "gn:feature_class":"P",
    "gn:feature_code":"PPL",
    "gn:name":"Thomas Settlement",
    "gn:population":0,
    "gn:timezone":"America/New_York",
    "iso:country":"US",
    "wof:name":"Thomas Settlement",
    "wof:placetype":"locality"
},
  "geometry": {"coordinates":[-76.07465000000001,43.81395],"type":"Point"}
}