{
  "type": "Feature",
  "properties": {
    "gn:admin1_code":"SD",
    "gn:admin2_code":"105.0",
    "gn:admin3_code":"17260.0",
    "gn:asciiname":"Date",
    "gn:country_code":"US",
    "gn:dem":831,
    "gn:elevation":"833.0",
    "gn:feature_class":"P",
    "gn:feature_code":"PPL",
    "gn:name":"Date",
    "gn:population":0,
    "gn:timezone":"America/Denver",
    "iso:country":"US",
    "name:ara_x_preferred":[
        "\u062a\u0627\u0631\u064a\u062e"
    ],
    "name:ceb_x_preferred":[
        "Date"
    ],
    "name:deu_x_preferred":[
        "Date"
    ],
    "name:fin_x_preferred":[
        "Date"
    ],
    "name:fra_x_preferred":[
        "Date"
    ],
    "name:heb_x_preferred":[
        "\u05d3\u05d9\u05d9\u05d8"
    ],
    "name:ita_x_preferred":[
        "Date"
    ],
    "name:jpn_x_preferred":[
        "\u30c7\u30a4\u30c8"
    ],
    "name:kor_x_preferred":[
        "\ub370\uc774\ud2b8"
    ],
    "name:nld_x_preferred":[
        "Date"
    ],
    "name:pol_x_preferred":[
        "Date"
    ],
    "name:ron_x_preferred":[
        "Date"
    ],
    "name:rus_x_preferred":[
        "\u0414\u0430\u0442\u0430"
    ],
    "name:sqi_x_preferred":[
        "Data"
    ],
    "name:swe_x_preferred":[
        "Date"
    ],
    "name:tgl_x_preferred":[
        "Date"
    ],
    "wof:name":"Date",
    "wof:placetype":"locality"
},
  "geometry": {"coordinates":[-102.67961,45.36721],"type":"Point"}
}