{
  "type": "Feature",
  "properties": {
    "gn:admin1_code":"KY",
    "gn:admin2_code":"101",
    "gn:asciiname":"Carlinburg",
    "gn:country_code":"US",
    "gn:dem":114,
    "gn:elevation":"116.0",
    "gn:feature_class":"P",
    "gn:feature_code":"PPL",
    "gn:name":"Carlinburg",
    "gn:population":0,
    "gn:timezone":"America/Chicago",
    "iso:country":"US",
    "wof:name":"Carlinburg",
    "wof:placetype":"locality"
},
  "geometry": {"coordinates":[-87.32334,37.88338],"type":"Point"}
}