{
  "type": "Feature",
  "properties": {
    "gn:admin1_code":"UT",
    "gn:admin2_code":"35.0",
    "gn:asciiname":"University Village",
    "gn:country_code":"US",
    "gn:dem":1444,
    "gn:elevation":"1442.0",
    "gn:feature_class":"P",
    "gn:feature_code":"PPL",
    "gn:name":"University Village",
    "gn:population":0,
    "gn:timezone":"America/Denver",
    "iso:country":"US",
    "wof:name":"University Village",
    "wof:placetype":"locality"
},
  "geometry": {"coordinates":[-111.83466,40.75272],"type":"Point"}
}