{
  "type": "Feature",
  "properties": {
    "gn:admin1_code":"MN",
    "gn:admin2_code":"137",
    "gn:admin3_code":"28790.0",
    "gn:asciiname":"Birch Lane Mobile Home Park",
    "gn:country_code":"US",
    "gn:dem":450,
    "gn:elevation":"449.0",
    "gn:feature_class":"P",
    "gn:feature_code":"PPL",
    "gn:name":"Birch Lane Mobile Home Park",
    "gn:population":0,
    "gn:timezone":"America/Chicago",
    "iso:country":"US",
    "wof:name":"Birch Lane Mobile Home Park",
    "wof:placetype":"campus"
},
  "geometry": {"coordinates":[-92.93222,47.39944000000001],"type":"Point"}
}