{
  "type": "Feature",
  "properties": {
    "gn:admin1_code":"IN",
    "gn:admin2_code":"45.0",
    "gn:admin3_code":"78452.0",
    "gn:asciiname":"Hunter Corner",
    "gn:country_code":"US",
    "gn:dem":204,
    "gn:elevation":"202.0",
    "gn:feature_class":"P",
    "gn:feature_code":"PPL",
    "gn:name":"Hunter Corner",
    "gn:population":0,
    "gn:timezone":"America/Indiana/Indianapolis",
    "iso:country":"US",
    "wof:name":"Hunter Corner",
    "wof:placetype":"locality"
},
  "geometry": {"coordinates":[-87.24306999999997,40.17143],"type":"Point"}
}