{
  "type": "Feature",
  "properties": {
    "gn:country":"US",
    "gn:fcode":"PPL",
    "gn:population":927,
    "iso:country":"US",
    "name:cat_x_preferred":[
        "Princeton"
    ],
    "name:ceb_x_preferred":[
        "Princeton"
    ],
    "name:che_x_preferred":[
        "\u041f\u0440\u0438\u043d\u0441\u0442\u043e\u043d"
    ],
    "name:cym_x_preferred":[
        "Princeton"
    ],
    "name:deu_x_preferred":[
        "Princeton"
    ],
    "name:eng_x_preferred":[
        "Princeton"
    ],
    "name:eus_x_preferred":[
        "Princeton"
    ],
    "name:fra_x_preferred":[
        "Princeton"
    ],
    "name:hat_x_preferred":[
        "Princeton"
    ],
    "name:hun_x_preferred":[
        "Princeton"
    ],
    "name:ita_x_preferred":[
        "Princeton"
    ],
    "name:jpn_x_preferred":[
        "\u30d7\u30ea\u30f3\u30b9\u30c8\u30f3"
    ],
    "name:kaz_x_preferred":[
        "\u041f\u0440\u0438\u0441\u0442\u043e\u043d"
    ],
    "name:kir_x_preferred":[
        "\u041f\u0440\u0438\u0441\u0442\u043e\u043d"
    ],
    "name:nld_x_preferred":[
        "Princeton"
    ],
    "name:pol_x_preferred":[
        "Princeton"
    ],
    "name:rus_x_preferred":[
        "\u041f\u0440\u0438\u043d\u0441\u0442\u043e\u043d"
    ],
    "name:spa_x_preferred":[
        "Princeton"
    ],
    "name:spa_x_variant":[
        "North Annville"
    ],
    "name:swe_x_preferred":[
        "Princeton"
    ],
    "name:tat_x_preferred":[
        "\u041f\u0440\u0438\u043d\u0441\u0442\u043e\u043d"
    ],
    "name:tur_x_preferred":[
        "Princeton"
    ],
    "name:ukr_x_preferred":[
        "\u041f\u0440\u0438\u043d\u0441\u0442\u043e\u043d"
    ],
    "name:und_x_variant":[
        "Memada-Kamioguk"
    ],
    "name:urd_x_preferred":[
        "\u067e\u0631\u0646\u0633\u0679\u0646\u060c \u0645\u06cc\u0646\u06d2"
    ],
    "name:urd_x_variant":[
        "\u067e\u0631\u0646\u0633\u0679\u0646"
    ],
    "name:vol_x_preferred":[
        "Princeton"
    ],
    "qs_pg:aaroncc":"US",
    "qs_pg:gn_country":"US",
    "qs_pg:gn_fcode":"PPL",
    "qs_pg:gn_pop":927,
    "qs_pg:name":"Princeton",
    "qs_pg:name_adm0":"United States",
    "qs_pg:name_adm1":"Maine",
    "qs_pg:photos":50,
    "qs_pg:photos_1k":10,
    "qs_pg:photos_9k":1,
    "qs_pg:photos_9r":3,
    "qs_pg:photos_all":81,
    "qs_pg:photos_sr":2,
    "qs_pg:pop_sr":2,
    "qs_pg:qs_pg_placetype":"locality",
    "qs_pg:qs_pg_placetype_gp":"Town",
    "qs_pg:woe_adm0":23424977,
    "woe:adm0_id":23424977,
    "woe:name_adm0":"United States",
    "woe:name_adm1":"Maine",
    "woe:placetype":"Town",
    "wof:name":"Princeton",
    "wof:placetype":"locality",
    "wof:population":927
},
  "geometry": {"coordinates":[-67.57222,45.22341],"type":"Point"}
}