{
  "type": "Feature",
  "properties": {
    "gn:admin1_code":"MO",
    "gn:admin2_code":"217.0",
    "gn:admin3_code":"19972.0",
    "gn:asciiname":"Bellamy",
    "gn:country_code":"US",
    "gn:dem":295,
    "gn:elevation":"291.0",
    "gn:feature_class":"P",
    "gn:feature_code":"PPL",
    "gn:name":"Bellamy",
    "gn:population":0,
    "gn:timezone":"America/Chicago",
    "iso:country":"US",
    "name:ast_x_preferred":[
        "Bellamy"
    ],
    "name:bre_x_preferred":[
        "Bellamy"
    ],
    "name:cat_x_preferred":[
        "Bellamy"
    ],
    "name:ces_x_preferred":[
        "Bellamy"
    ],
    "name:deu_x_preferred":[
        "Bellamy"
    ],
    "name:eng_x_preferred":[
        "Bellamy"
    ],
    "name:fra_x_preferred":[
        "Bellamy"
    ],
    "name:heb_x_preferred":[
        "\u05d1\u05dc\u05d0\u05de\u05d9"
    ],
    "name:ita_x_preferred":[
        "Bellamy"
    ],
    "name:jpn_x_preferred":[
        "\u30d9\u30e9\u30df\u30fc"
    ],
    "name:kor_x_preferred":[
        "\ubca8\ub7ec\ubbf8"
    ],
    "name:nld_x_preferred":[
        "Bellamy"
    ],
    "name:pol_x_preferred":[
        "Bellamy"
    ],
    "name:por_x_preferred":[
        "Bellamy"
    ],
    "name:rus_x_preferred":[
        "\u0411\u0435\u043b\u043b\u0430\u043c\u0438"
    ],
    "name:spa_x_preferred":[
        "Bellamy"
    ],
    "name:ukr_x_preferred":[
        "\u0411\u0435\u043b\u043b\u0430\u043c\u0456"
    ],
    "name:und_x_variant":[
        "Bellamy City"
    ],
    "name:zho_x_preferred":[
        "\u8c9d\u62c9\u7c73"
    ],
    "wof:name":"Bellamy",
    "wof:placetype":"locality"
},
  "geometry": {"coordinates":[-94.18049999999999,37.68504],"type":"Point"}
}