{
  "type": "Feature",
  "properties": {
    "gn:admin1_code":"MS",
    "gn:admin2_code":"47.0",
    "gn:asciiname":"Homestead Mobile Home Park",
    "gn:country_code":"US",
    "gn:dem":36,
    "gn:elevation":"34.0",
    "gn:feature_class":"P",
    "gn:feature_code":"PPL",
    "gn:name":"Homestead Mobile Home Park",
    "gn:population":0,
    "gn:timezone":"America/Chicago",
    "iso:country":"US",
    "wof:name":"Homestead Mobile Home Park",
    "wof:placetype":"campus"
},
  "geometry": {"coordinates":[-89.15756,30.509],"type":"Point"}
}