{
  "type": "Feature",
  "properties": {
    "gn:admin1_code":"MO",
    "gn:admin2_code":"133.0",
    "gn:admin3_code":"36278.0",
    "gn:asciiname":"Dorena",
    "gn:country_code":"US",
    "gn:dem":92,
    "gn:elevation":"91.0",
    "gn:feature_class":"P",
    "gn:feature_code":"PPL",
    "gn:name":"Dorena",
    "gn:population":0,
    "gn:timezone":"America/Chicago",
    "iso:country":"US",
    "name:deu_x_preferred":[
        "Dorena"
    ],
    "name:vol_x_preferred":[
        "Dorena"
    ],
    "wof:name":"Dorena",
    "wof:placetype":"locality"
},
  "geometry": {"coordinates":[-89.23729,36.61617],"type":"Point"}
}