{
  "type": "Feature",
  "properties": {
    "iso:country":"US",
    "name:eng_x_preferred":[
        "Tree Top"
    ],
    "wof:name":"Tree Top",
    "wof:placetype":"neighbourhood",
    "zs:area_m":160624.129314,
    "zs:blockids":[
        370250423001001
    ],
    "zs:housing10":0,
    "zs:label":"Tree Top",
    "zs:pop10":0
},
  "geometry": {"coordinates":[-80.582712,35.432066],"type":"Point"}
}