{
  "type": "Feature",
  "properties": {
    "iso:country":"US",
    "wof:name":"East Pinson Valley",
    "wof:placetype":"neighbourhood"
},
  "geometry": {"coordinates":[-86.72862437775412,33.62286439149713],"type":"Point"}
}