{
  "type": "Feature",
  "properties": {
    "gn:admin1_code":"VA",
    "gn:admin2_code":"29",
    "gn:asciiname":"New Mount Vinco",
    "gn:country_code":"US",
    "gn:dem":157,
    "gn:elevation":"156.0",
    "gn:feature_class":"P",
    "gn:feature_code":"PPL",
    "gn:name":"New Mount Vinco",
    "gn:population":0,
    "gn:timezone":"America/New_York",
    "iso:country":"US",
    "wof:name":"New Mount Vinco",
    "wof:placetype":"locality"
},
  "geometry": {"coordinates":[-78.60111999999999,37.58653],"type":"Point"}
}