{
  "type": "Feature",
  "properties": {
    "gn:admin1_code":"NC",
    "gn:admin2_code":"193.0",
    "gn:admin3_code":"93024.0",
    "gn:asciiname":"Somers Crossroads",
    "gn:country_code":"US",
    "gn:dem":334,
    "gn:elevation":"333.0",
    "gn:feature_class":"P",
    "gn:feature_code":"PPL",
    "gn:name":"Somers Crossroads",
    "gn:population":0,
    "gn:timezone":"America/New_York",
    "iso:country":"US",
    "wof:name":"Somers Crossroads",
    "wof:placetype":"locality"
},
  "geometry": {"coordinates":[-80.89646,36.08347],"type":"Point"}
}