{
  "type": "Feature",
  "properties": {
    "gn:admin1_code":"MI",
    "gn:admin2_code":"61.0",
    "gn:admin3_code":"76200.0",
    "gn:asciiname":"Beacon Hill",
    "gn:country_code":"US",
    "gn:dem":230,
    "gn:elevation":"229.0",
    "gn:feature_class":"P",
    "gn:feature_code":"PPL",
    "gn:name":"Beacon Hill",
    "gn:population":0,
    "gn:timezone":"America/Detroit",
    "iso:country":"US",
    "name:ceb_x_preferred":[
        "Beacon Hill"
    ],
    "name:deu_x_preferred":[
        "Beacon Hill"
    ],
    "name:fra_x_preferred":[
        "Beacon Hill"
    ],
    "name:ita_x_preferred":[
        "Beacon Hill"
    ],
    "name:kor_x_preferred":[
        "\ube44\ucee8\ud790"
    ],
    "name:rus_x_preferred":[
        "\u0411\u0438\u043a\u043e\u043d-\u0425\u0438\u043b\u043b"
    ],
    "name:swe_x_preferred":[
        "Beacon Hill"
    ],
    "wof:name":"Beacon Hill",
    "wof:placetype":"locality"
},
  "geometry": {"coordinates":[-88.80679000000001,47.13909],"type":"Point"}
}