{
  "type": "Feature",
  "properties": {
    "gn:admin1_code":"TN",
    "gn:admin2_code":"17",
    "gn:asciiname":"Howley",
    "gn:country_code":"US",
    "gn:dem":182,
    "gn:elevation":"178.0",
    "gn:feature_class":"P",
    "gn:feature_code":"PPL",
    "gn:name":"Howley",
    "gn:population":0,
    "gn:timezone":"America/Chicago",
    "iso:country":"US",
    "name:ceb_x_preferred":[
        "Howley"
    ],
    "name:deu_x_preferred":[
        "Howley"
    ],
    "name:swe_x_preferred":[
        "Howley"
    ],
    "wof:name":"Howley",
    "wof:placetype":"locality"
},
  "geometry": {"coordinates":[-88.53922,35.88451],"type":"Point"}
}