{
  "type": "Feature",
  "properties": {
    "iso:country":"US",
    "name:eng_x_preferred":[
        "Claiborne Tract"
    ],
    "wof:name":"Claiborne Tract",
    "wof:placetype":"neighbourhood",
    "wof:population":388,
    "zs:area_m":181661.693942,
    "zs:blockids":[
        60610208062008,
        60610208061026,
        60610208062007,
        60610208061027,
        60610208061024
    ],
    "zs:housing10":175,
    "zs:label":"Claiborne Tract",
    "zs:pop10":388
},
  "geometry": {"coordinates":[-121.28067900000001,38.743804],"type":"Point"}
}