{
  "type": "Feature",
  "properties": {
    "gn:admin1_code":"IL",
    "gn:admin2_code":"105.0",
    "gn:admin3_code":"57056.0",
    "gn:asciiname":"Swygert",
    "gn:country_code":"US",
    "gn:dem":225,
    "gn:elevation":"223.0",
    "gn:feature_class":"P",
    "gn:feature_code":"PPL",
    "gn:name":"Swygert",
    "gn:population":0,
    "gn:timezone":"America/Chicago",
    "iso:country":"US",
    "wof:name":"Swygert",
    "wof:placetype":"locality"
},
  "geometry": {"coordinates":[-88.5295,40.9117],"type":"Point"}
}