{
  "type": "Feature",
  "properties": {
    "iso:country":"US",
    "wof:name":"South Inglewood",
    "wof:placetype":"neighbourhood"
},
  "geometry": {"coordinates":[-86.73258173510008,36.1997717397435],"type":"Point"}
}