{
  "type": "Feature",
  "properties": {
    "gn:admin1_code":"TN",
    "gn:admin2_code":"97.0",
    "gn:asciiname":"Porter Gap",
    "gn:country_code":"US",
    "gn:dem":113,
    "gn:elevation":"110.0",
    "gn:feature_class":"P",
    "gn:feature_code":"PPL",
    "gn:name":"Porter Gap",
    "gn:population":0,
    "gn:timezone":"America/Chicago",
    "iso:country":"US",
    "wof:name":"Porter Gap",
    "wof:placetype":"locality"
},
  "geometry": {"coordinates":[-89.4973,35.91535],"type":"Point"}
}