{
  "type": "Feature",
  "properties": {
    "gn:admin1_code":"TN",
    "gn:admin2_code":"129",
    "gn:asciiname":"Glades",
    "gn:country_code":"US",
    "gn:dem":479,
    "gn:elevation":"479.0",
    "gn:feature_class":"P",
    "gn:feature_code":"PPL",
    "gn:name":"Glades",
    "gn:population":0,
    "gn:timezone":"America/New_York",
    "iso:country":"US",
    "name:deu_x_preferred":[
        "Glades"
    ],
    "wof:name":"Glades",
    "wof:placetype":"locality"
},
  "geometry": {"coordinates":[-84.78995,36.24257],"type":"Point"}
}