{
  "type": "Feature",
  "properties": {
    "iso:country":"US",
    "name:eng_x_preferred":[
        "Cloverhill"
    ],
    "wof:name":"Cloverhill",
    "wof:placetype":"neighbourhood",
    "wof:population":1113,
    "zs:blockids":[
        340350537031005,
        340350537031022,
        340350537031008,
        340190113042013,
        340190113042018,
        340190113042012,
        340190117001000,
        340190113042017,
        340190113042014,
        340190117001012,
        340190113042016,
        340190113042009,
        340190113042011,
        340190113042010,
        340190113042015
    ],
    "zs:housing10":401,
    "zs:label":"Cloverhill",
    "zs:pop10":1113
},
  "geometry": {"coordinates":[-74.774545,40.492762],"type":"Point"}
}