{
  "type": "Feature",
  "properties": {
    "gn:admin1_code":"MD",
    "gn:admin2_code":"25.0",
    "gn:asciiname":"Cherrywood Estates",
    "gn:country_code":"US",
    "gn:dem":106,
    "gn:elevation":"85.0",
    "gn:feature_class":"P",
    "gn:feature_code":"PPL",
    "gn:name":"Cherrywood Estates",
    "gn:population":0,
    "gn:timezone":"America/New_York",
    "iso:country":"US",
    "wof:name":"Cherrywood Estates",
    "wof:placetype":"locality"
},
  "geometry": {"coordinates":[-76.39024000000001,39.63149],"type":"Point"}
}