{
  "type": "Feature",
  "properties": {
    "gn:admin1_code":"TX",
    "gn:admin2_code":"309.0",
    "gn:asciiname":"Tokio",
    "gn:country_code":"US",
    "gn:dem":173,
    "gn:elevation":"174.0",
    "gn:feature_class":"P",
    "gn:feature_code":"PPL",
    "gn:name":"Tokio",
    "gn:population":0,
    "gn:timezone":"America/Chicago",
    "iso:country":"US",
    "name:deu_x_preferred":[
        "Tokio"
    ],
    "name:ita_x_preferred":[
        "Tokio"
    ],
    "name:jpn_x_preferred":[
        "\u30c8\u30ad\u30aa"
    ],
    "name:nds_x_preferred":[
        "Tokio"
    ],
    "name:rus_x_preferred":[
        "Tokio"
    ],
    "name:spa_x_preferred":[
        "Tokio"
    ],
    "name:srp_x_preferred":[
        "\u0422\u043e\u043a\u0438\u043e"
    ],
    "wof:name":"Tokio",
    "wof:placetype":"locality"
},
  "geometry": {"coordinates":[-97.15584,31.7585],"type":"Point"}
}