{
  "type": "Feature",
  "properties": {
    "gn:admin1_code":"NJ",
    "gn:admin2_code":"39.0",
    "gn:admin3_code":"74480.0",
    "gn:asciiname":"Unionburg",
    "gn:country_code":"US",
    "gn:dem":36,
    "gn:elevation":"33.0",
    "gn:feature_class":"P",
    "gn:feature_code":"PPL",
    "gn:name":"Unionburg",
    "gn:population":0,
    "gn:timezone":"America/New_York",
    "iso:country":"US",
    "wof:name":"Unionburg",
    "wof:placetype":"locality"
},
  "geometry": {"coordinates":[-74.28126,40.70538],"type":"Point"}
}