{
  "type": "Feature",
  "properties": {
    "gn:admin1_code":"MS",
    "gn:admin2_code":"5",
    "gn:asciiname":"White Cap",
    "gn:country_code":"US",
    "gn:dem":134,
    "gn:elevation":"128.0",
    "gn:feature_class":"P",
    "gn:feature_code":"PPL",
    "gn:name":"White Cap",
    "gn:population":0,
    "gn:timezone":"America/Chicago",
    "iso:country":"US",
    "wof:name":"White Cap",
    "wof:placetype":"locality"
},
  "geometry": {"coordinates":[-90.97454999999999,31.21545],"type":"Point"}
}