{
  "type": "Feature",
  "properties": {
    "gn:admin1_code":"MI",
    "gn:admin2_code":"63.0",
    "gn:admin3_code":"27120.0",
    "gn:asciiname":"Weale",
    "gn:country_code":"US",
    "gn:dem":179,
    "gn:elevation":"178.0",
    "gn:feature_class":"P",
    "gn:feature_code":"PPL",
    "gn:name":"Weale",
    "gn:population":0,
    "gn:timezone":"America/Detroit",
    "iso:country":"US",
    "name:deu_x_preferred":[
        "Weale"
    ],
    "wof:name":"Weale",
    "wof:placetype":"locality"
},
  "geometry": {"coordinates":[-83.39718000000001,43.81196],"type":"Point"}
}