{
  "type": "Feature",
  "properties": {
    "gn:country":"US",
    "gn:fcode":"PPL",
    "gn:population":0,
    "iso:country":"US",
    "name:azb_x_preferred":[
        "\u0641\u0648\u0646\u06cc\u06a9\u0633"
    ],
    "name:eng_x_preferred":[
        "Phoenix"
    ],
    "name:fas_x_preferred":[
        "\u0641\u06cc\u0646\u06cc\u06a9\u0633"
    ],
    "name:fra_x_preferred":[
        "Phoenix"
    ],
    "name:urd_x_preferred":[
        "\u0641\u06cc\u0646\u06a9\u0633\u060c \u0645\u0634\u06cc \u06af\u0646"
    ],
    "name:urd_x_variant":[
        "\u0641\u06cc\u0646\u06a9\u0633"
    ],
    "qs_pg:aaroncc":"US",
    "qs_pg:gn_country":"US",
    "qs_pg:gn_fcode":"PPL",
    "qs_pg:gn_pop":0,
    "qs_pg:name":"Phoenix",
    "qs_pg:name_adm0":"United States",
    "qs_pg:name_adm1":"Michigan",
    "qs_pg:photos":61,
    "qs_pg:photos_1k":12,
    "qs_pg:photos_9k":1,
    "qs_pg:photos_9r":2,
    "qs_pg:photos_all":61,
    "qs_pg:photos_sr":2,
    "qs_pg:pop_sr":0,
    "qs_pg:qs_pg_placetype":"locality",
    "qs_pg:qs_pg_placetype_gp":"Town",
    "qs_pg:woe_adm0":23424977,
    "woe:adm0_id":23424977,
    "woe:name_adm0":"United States",
    "woe:name_adm1":"Michigan",
    "woe:placetype":"Town",
    "wof:name":"Phoenix",
    "wof:placetype":"locality"
},
  "geometry": {"coordinates":[-88.27761,47.38881],"type":"Point"}
}