{
  "type": "Feature",
  "properties": {
    "iso:country":"US",
    "name:eng_x_preferred":[
        "Thompson Cluster"
    ],
    "wof:name":"Thompson Cluster",
    "wof:placetype":"neighbourhood",
    "wof:population":417,
    "zs:area_m":6665490.638593,
    "zs:blockids":[
        530110404031006,
        530110404031008,
        530110404031021,
        530110404031010
    ],
    "zs:housing10":169,
    "zs:label":"Thompson Cluster",
    "zs:pop10":417
},
  "geometry": {"coordinates":[-122.642376,45.817703],"type":"Point"}
}