{
  "type": "Feature",
  "properties": {
    "gn:admin1_code":"GA",
    "gn:admin2_code":"269.0",
    "gn:asciiname":"Goldson",
    "gn:country_code":"US",
    "gn:dem":204,
    "gn:elevation":"204.0",
    "gn:feature_class":"P",
    "gn:feature_code":"PPL",
    "gn:name":"Goldson",
    "gn:population":0,
    "gn:timezone":"America/New_York",
    "iso:country":"US",
    "wof:name":"Goldson",
    "wof:placetype":"locality"
},
  "geometry": {"coordinates":[-84.25879999999999,32.56098],"type":"Point"}
}