{
  "type": "Feature",
  "properties": {
    "gn:admin1_code":"IA",
    "gn:admin2_code":"103.0",
    "gn:admin3_code":"90240.0",
    "gn:asciiname":"Twin View Heights",
    "gn:country_code":"US",
    "gn:dem":243,
    "gn:elevation":"243.0",
    "gn:feature_class":"P",
    "gn:feature_code":"PPL",
    "gn:name":"Twin View Heights",
    "gn:population":0,
    "gn:timezone":"America/Chicago",
    "iso:country":"US",
    "wof:name":"Twin View Heights",
    "wof:placetype":"locality"
},
  "geometry": {"coordinates":[-91.57323,41.81057],"type":"Point"}
}