{
  "type": "Feature",
  "properties": {
    "gn:admin1_code":"VA",
    "gn:admin2_code":"185",
    "gn:asciiname":"Mount Gate",
    "gn:country_code":"US",
    "gn:dem":820,
    "gn:elevation":"813.0",
    "gn:feature_class":"P",
    "gn:feature_code":"PPL",
    "gn:name":"Mount Gate",
    "gn:population":0,
    "gn:timezone":"America/New_York",
    "iso:country":"US",
    "wof:name":"Mount Gate",
    "wof:placetype":"locality"
},
  "geometry": {"coordinates":[-81.53067,37.05845],"type":"Point"}
}