{
  "type": "Feature",
  "properties": {
    "gn:admin1_code":"WV",
    "gn:admin2_code":"39.0",
    "gn:asciiname":"Riverdale Acres",
    "gn:country_code":"US",
    "gn:dem":196,
    "gn:elevation":"188.0",
    "gn:feature_class":"P",
    "gn:feature_code":"PPL",
    "gn:name":"Riverdale Acres",
    "gn:population":0,
    "gn:timezone":"America/New_York",
    "iso:country":"US",
    "wof:name":"Riverdale Acres",
    "wof:placetype":"locality"
},
  "geometry": {"coordinates":[-81.80901999999998,38.3937],"type":"Point"}
}