{
  "type": "Feature",
  "properties": {
    "gn:admin1_code":"VA",
    "gn:admin2_code":"111",
    "gn:asciiname":"Wilburn",
    "gn:country_code":"US",
    "gn:dem":121,
    "gn:elevation":"121.0",
    "gn:feature_class":"P",
    "gn:feature_code":"PPL",
    "gn:name":"Wilburn",
    "gn:population":0,
    "gn:timezone":"America/New_York",
    "iso:country":"US",
    "wof:name":"Wilburn",
    "wof:placetype":"locality"
},
  "geometry": {"coordinates":[-78.27139,36.84987],"type":"Point"}
}