{
  "type": "Feature",
  "properties": {
    "gn:admin1_code":"WI",
    "gn:admin2_code":"51.0",
    "gn:admin3_code":"61825.0",
    "gn:asciiname":"Hoyt",
    "gn:country_code":"US",
    "gn:dem":479,
    "gn:elevation":"480.0",
    "gn:feature_class":"P",
    "gn:feature_code":"PPL",
    "gn:name":"Hoyt",
    "gn:population":0,
    "gn:timezone":"America/Chicago",
    "iso:country":"US",
    "wof:name":"Hoyt",
    "wof:placetype":"locality"
},
  "geometry": {"coordinates":[-90.29962,46.4105],"type":"Point"}
}