{
  "type": "Feature",
  "properties": {
    "iso:country":"US",
    "name:ceb_x_preferred":[
        "Parkside"
    ],
    "name:deu_x_preferred":[
        "Parkside"
    ],
    "name:eng_x_preferred":[
        "Parkside"
    ],
    "name:swe_x_preferred":[
        "Parkside"
    ],
    "qs:gn_adm0_cc":"US",
    "qs:gn_local":4471641,
    "qs:gn_nam_loc":"Holly Springs, Wake, North Carolina, US",
    "qs:gn_namadm1":"NC",
    "qs:local_max":275,
    "qs:local_sum":574,
    "qs:localhoods":6,
    "qs:name":"Parkside",
    "qs:name_adm0":"United States",
    "qs:name_adm1":"North Carolina",
    "qs:name_adm2":"Wake",
    "qs:name_local":"Holly Springs",
    "qs:photo_max":21,
    "qs:photo_sum":39,
    "qs:placetype":"Suburb",
    "qs:quad_count":6,
    "qs:woe_adm0":23424977,
    "qs:woe_adm1":2347592,
    "qs:woe_adm2":12589465,
    "qs:woe_lau":0,
    "qs:woe_local":2423381,
    "qs:woe_ver":"7.10.0",
    "wof:name":"Parkside",
    "wof:placetype":"neighbourhood",
    "wof:population":1853,
    "zs:blockids":[
        371830532051010,
        371830532041045,
        371830532061004,
        371830532061040,
        371830532041041,
        371830532061016,
        371830532061007,
        371830532041036,
        371830532041046,
        371830532041039,
        371830532041038,
        371830532061022,
        371830532051024,
        371830532061006,
        371830532041044,
        371830532051022,
        371830532051020,
        371830532041042,
        371830532041040,
        371830532061009,
        371830532061020,
        371830532061001,
        371830532061017,
        371830532041034,
        371830532061010,
        371830532061019,
        371830532061029,
        371830532061011,
        371830532051009,
        371830532051052,
        371830532061024,
        371830532061002,
        371830532061013,
        371830532061005,
        371830532061000,
        371830532061014,
        371830532041037,
        371830532061003,
        371830532051029,
        371830532051025,
        371830532041035,
        371830532061021,
        371830532041043,
        371830532051028,
        371830532061008,
        371830532051026,
        371830532051021,
        371830532061015,
        371830532051023,
        371830532072051,
        371830532061018
    ],
    "zs:housing10":812,
    "zs:pop10":1853
},
  "geometry": {"coordinates":[-78.83204499999999,35.638016],"type":"Point"}
}