{
  "type": "Feature",
  "properties": {
    "gn:gn_country":"US",
    "gn:gn_fcode":"PPL",
    "gn:gn_pop":0,
    "iso:country":"US",
    "name:ara_x_preferred":[
        "\u063a\u0644\u064a\u0646\u0648\u0648\u062f"
    ],
    "name:bar_x_preferred":[
        "Glenwood"
    ],
    "name:ceb_x_preferred":[
        "Glenwood"
    ],
    "name:deu_x_preferred":[
        "Glenwood"
    ],
    "name:fas_x_preferred":[
        "\u06af\u0644\u0646\u0648\u0648\u062f"
    ],
    "name:fin_x_preferred":[
        "Glenwood"
    ],
    "name:fra_x_preferred":[
        "Glenwood"
    ],
    "name:hrv_x_preferred":[
        "Glenwood"
    ],
    "name:ita_x_preferred":[
        "Glenwood"
    ],
    "name:kor_x_preferred":[
        "\uae00\ub80c\uc6b0\ub4dc"
    ],
    "name:nld_x_preferred":[
        "Glenwood"
    ],
    "name:pol_x_preferred":[
        "Glenwood"
    ],
    "name:por_x_preferred":[
        "Glenwood"
    ],
    "name:rus_x_preferred":[
        "\u0413\u043b\u0435\u043d\u0432\u0443\u0434"
    ],
    "name:spa_x_preferred":[
        "Glenwood"
    ],
    "name:srp_x_preferred":[
        "\u0413\u043b\u0435\u043d\u0432\u0443\u0434"
    ],
    "name:swe_x_preferred":[
        "Glenwood"
    ],
    "name:ukr_x_preferred":[
        "\u0413\u043b\u0435\u043d\u0432\u0443\u0434"
    ],
    "name:vol_x_preferred":[
        "Glenwood"
    ],
    "qs_pg:aaroncc":"US",
    "qs_pg:gn_country":"US",
    "qs_pg:gn_fcode":"PPL",
    "qs_pg:gn_pop":0,
    "qs_pg:name":"Glenwood",
    "qs_pg:name_adm0":"United States",
    "qs_pg:name_adm1":"Maryland",
    "qs_pg:photos":167,
    "qs_pg:photos_1k":34,
    "qs_pg:photos_9k":1,
    "qs_pg:photos_9r":4,
    "qs_pg:photos_all":167,
    "qs_pg:photos_sr":4,
    "qs_pg:pop_sr":0,
    "qs_pg:qs_pg_placetype":"locality",
    "qs_pg:qs_pg_placetype_gp":"Town",
    "qs_pg:woe_adm0":23424977,
    "woe:adm0_id":23424977,
    "woe:name_adm0":"United States",
    "woe:name_adm1":"Maryland",
    "woe:placetype":"Town",
    "wof:name":"Glenwood",
    "wof:placetype":"locality"
},
  "geometry": {"coordinates":[-77.02803,39.2876],"type":"Point"}
}