{
  "type": "Feature",
  "properties": {
    "gn:admin1_code":"AZ",
    "gn:admin2_code":"5.0",
    "gn:asciiname":"Old Leupp",
    "gn:country_code":"US",
    "gn:dem":1434,
    "gn:elevation":"1433.0",
    "gn:feature_class":"P",
    "gn:feature_code":"PPL",
    "gn:name":"Old Leupp",
    "gn:population":0,
    "gn:timezone":"America/Denver",
    "iso:country":"US",
    "wof:name":"Old Leupp",
    "wof:placetype":"locality"
},
  "geometry": {"coordinates":[-110.96514000000001,35.2839],"type":"Point"}
}