{
  "type": "Feature",
  "properties": {
    "gn:admin1_code":"PA",
    "gn:admin2_code":"49.0",
    "gn:admin3_code":"31008.0",
    "gn:asciiname":"Little Hope",
    "gn:country_code":"US",
    "gn:dem":426,
    "gn:elevation":"425.0",
    "gn:feature_class":"P",
    "gn:feature_code":"PPL",
    "gn:name":"Little Hope",
    "gn:population":0,
    "gn:timezone":"America/New_York",
    "iso:country":"US",
    "name:deu_x_preferred":[
        "Little Hope"
    ],
    "name:eng_x_preferred":[
        "Little Hope"
    ],
    "name:und_x_variant":[
        "Greenfield"
    ],
    "wof:name":"Little Hope",
    "wof:placetype":"locality"
},
  "geometry": {"coordinates":[-79.81894,42.09894],"type":"Point"}
}