{
  "type": "Feature",
  "properties": {
    "iso:country":"US",
    "name:ceb_x_preferred":[
        "Pine Valley"
    ],
    "name:deu_x_preferred":[
        "Pine Valley"
    ],
    "name:eng_x_preferred":[
        "Pine Valley"
    ],
    "name:ita_x_preferred":[
        "Pine Valley"
    ],
    "name:nld_x_preferred":[
        "Pine Valley"
    ],
    "name:pol_x_preferred":[
        "Pine Valley"
    ],
    "name:por_x_preferred":[
        "Pine Valley"
    ],
    "name:srp_x_preferred":[
        "\u041f\u0430\u0458\u043d \u0412\u0430\u043b\u0438"
    ],
    "name:swe_x_preferred":[
        "Pine Valley"
    ],
    "name:vol_x_preferred":[
        "Pine Valley"
    ],
    "wd:wordcount":120,
    "wof:name":"Pine Valley",
    "wof:placetype":"neighbourhood",
    "wof:population":110,
    "zs:area_m":10607023.381513,
    "zs:blockids":[
        421239703004032,
        421239703004039,
        421239703005003,
        421239703004038,
        421239703004040,
        421239703005000,
        421239703005007,
        421239703005008,
        421239703005002,
        421239703005009,
        421239703005001
    ],
    "zs:housing10":42,
    "zs:label":"Pine Valley",
    "zs:pop10":110
},
  "geometry": {"coordinates":[-79.523208,41.936527],"type":"Point"}
}