{
  "type": "Feature",
  "properties": {
    "iso:country":"US",
    "name:eng_x_preferred":[
        "Saw Mill Valley"
    ],
    "wof:name":"Saw Mill Valley",
    "wof:placetype":"neighbourhood",
    "wof:population":654,
    "zs:area_m":130426.43755,
    "zs:blockids":[
        420912005071002,
        420912005071006
    ],
    "zs:housing10":362,
    "zs:label":"Saw Mill Valley",
    "zs:pop10":654
},
  "geometry": {"coordinates":[-75.150667,40.182884],"type":"Point"}
}