{
  "type": "Feature",
  "properties": {
    "gn:admin1_code":"LA",
    "gn:admin2_code":"17.0",
    "gn:asciiname":"Alpha Mobile Home Park",
    "gn:country_code":"US",
    "gn:dem":52,
    "gn:elevation":"50.0",
    "gn:feature_class":"P",
    "gn:feature_code":"PPL",
    "gn:name":"Alpha Mobile Home Park",
    "gn:population":0,
    "gn:timezone":"America/Chicago",
    "iso:country":"US",
    "wof:name":"Alpha Mobile Home Park",
    "wof:placetype":"campus"
},
  "geometry": {"coordinates":[-93.76573999999999,32.3896],"type":"Point"}
}