{
  "type": "Feature",
  "properties": {
    "gn:admin1_code":"CO",
    "gn:admin2_code":"85",
    "gn:asciiname":"West Vancorum",
    "gn:country_code":"US",
    "gn:dem":1650,
    "gn:elevation":"1647.0",
    "gn:feature_class":"P",
    "gn:feature_code":"PPL",
    "gn:name":"West Vancorum",
    "gn:population":0,
    "gn:timezone":"America/Denver",
    "iso:country":"US",
    "wof:name":"West Vancorum",
    "wof:placetype":"locality"
},
  "geometry": {"coordinates":[-108.60065,38.22777],"type":"Point"}
}