{
  "type": "Feature",
  "properties": {
    "gn:admin1_code":"NY",
    "gn:admin2_code":"65.0",
    "gn:admin3_code":"41762.0",
    "gn:asciiname":"Lake Delta",
    "gn:country_code":"US",
    "gn:dem":181,
    "gn:elevation":"181.0",
    "gn:feature_class":"P",
    "gn:feature_code":"PPL",
    "gn:name":"Lake Delta",
    "gn:population":0,
    "gn:timezone":"America/New_York",
    "iso:country":"US",
    "wof:name":"Lake Delta",
    "wof:placetype":"locality"
},
  "geometry": {"coordinates":[-75.47211999999998,43.29313],"type":"Point"}
}