{
  "type": "Feature",
  "properties": {
    "gn:country":"US",
    "gn:fcode":"PPL",
    "gn:population":0,
    "iso:country":"US",
    "name:cat_x_preferred":[
        "Glen Ridge"
    ],
    "name:ceb_x_preferred":[
        "Glen Ridge"
    ],
    "name:deu_x_preferred":[
        "Glen Ridge"
    ],
    "name:fra_x_preferred":[
        "Glen Ridge"
    ],
    "name:hun_x_preferred":[
        "Glen Ridge"
    ],
    "name:ita_x_preferred":[
        "Glen Ridge"
    ],
    "name:nld_x_preferred":[
        "Glen Ridge"
    ],
    "name:pol_x_preferred":[
        "Glen Ridge"
    ],
    "name:por_x_preferred":[
        "Glen Ridge"
    ],
    "name:srp_x_preferred":[
        "\u0413\u043b\u0435\u043d \u0420\u0438\u045f"
    ],
    "name:ukr_x_preferred":[
        "\u0413\u043b\u0435\u043d-\u0420\u0438\u0434\u0436"
    ],
    "name:vol_x_preferred":[
        "Glen Ridge"
    ],
    "qs_pg:aaroncc":"US",
    "qs_pg:gn_country":"US",
    "qs_pg:gn_fcode":"PPL",
    "qs_pg:gn_pop":0,
    "qs_pg:name":"Glen Ridge",
    "qs_pg:name_adm0":"United States",
    "qs_pg:name_adm1":"Maryland",
    "qs_pg:photos":90,
    "qs_pg:photos_1k":18,
    "qs_pg:photos_9k":1,
    "qs_pg:photos_9r":3,
    "qs_pg:photos_all":90,
    "qs_pg:photos_sr":3,
    "qs_pg:pop_sr":0,
    "qs_pg:qs_pg_placetype":"locality",
    "qs_pg:qs_pg_placetype_gp":"Town",
    "qs_pg:woe_adm0":23424977,
    "woe:adm0_id":23424977,
    "woe:name_adm0":"United States",
    "woe:name_adm1":"Maryland",
    "woe:placetype":"Town",
    "wof:name":"Glen Ridge",
    "wof:placetype":"locality"
},
  "geometry": {"coordinates":[-76.61636,39.18983],"type":"Point"}
}