{
  "type": "Feature",
  "properties": {
    "gn:elevation":180,
    "iso:country":"US",
    "name:eng_x_preferred":[
        "Canada Mills"
    ],
    "name:eng_x_variant":[
        "Canada Mls"
    ],
    "qs:gn_adm0_cc":"US",
    "qs:gn_fcode":"PPL",
    "qs:gn_local":4939647,
    "qs:gn_nam_loc":"holden",
    "qs:gn_namadm1":"MA",
    "qs:gn_name":"Canada Mills",
    "qs:local_max":238,
    "qs:local_sum":464,
    "qs:localhoods":4,
    "qs:name":"Canada Mills",
    "qs:name_adm0":"United States",
    "qs:name_adm1":"Massachusetts",
    "qs:name_adm2":"Worcester",
    "qs:name_local":"Holden",
    "qs:photo_max":188,
    "qs:photo_sum":204,
    "qs:placetype":"Suburb",
    "qs:quad_count":8,
    "qs:woe_adm0":23424977,
    "qs:woe_adm1":2347580,
    "qs:woe_adm2":12588713,
    "qs:woe_lau":0,
    "qs:woe_local":2422929,
    "qs:woe_ver":"7.10.0",
    "wof:lang":[
        "eng"
    ],
    "wof:name":"Canada Mills",
    "wof:placetype":"neighbourhood",
    "wof:population":49,
    "zs:blockids":[
        250277284003045,
        250277284003038,
        250277284003041,
        250277284003032,
        250277284003033,
        250277284003044
    ],
    "zs:housing10":20,
    "zs:pop10":49
},
  "geometry": {"coordinates":[-71.837622,42.38544],"type":"Point"}
}