{
  "type": "Feature",
  "properties": {
    "gn:admin1_code":"MI",
    "gn:admin2_code":"131.0",
    "gn:admin3_code":"9460.0",
    "gn:asciiname":"Rousseau",
    "gn:country_code":"US",
    "gn:dem":334,
    "gn:elevation":"338.0",
    "gn:feature_class":"P",
    "gn:feature_code":"PPL",
    "gn:name":"Rousseau",
    "gn:population":0,
    "gn:timezone":"America/Detroit",
    "iso:country":"US",
    "name:eng_x_preferred":[
        "Rousseau"
    ],
    "name:und_x_variant":[
        "Rosseau"
    ],
    "wof:name":"Rousseau",
    "wof:placetype":"locality"
},
  "geometry": {"coordinates":[-88.96986,46.70938],"type":"Point"}
}