{
  "type": "Feature",
  "properties": {
    "gn:admin1_code":"MT",
    "gn:admin2_code":"49.0",
    "gn:asciiname":"Old Weiss and French Place",
    "gn:country_code":"US",
    "gn:dem":1115,
    "gn:elevation":"1122.0",
    "gn:feature_class":"P",
    "gn:feature_code":"PPL",
    "gn:name":"Old Weiss and French Place",
    "gn:population":0,
    "gn:timezone":"America/Denver",
    "iso:country":"US",
    "wof:name":"Old Weiss and French Place",
    "wof:placetype":"locality"
},
  "geometry": {"coordinates":[-111.92444,46.80688],"type":"Point"}
}