{
  "type": "Feature",
  "properties": {
    "gn:admin1_code":"FL",
    "gn:admin2_code":"105.0",
    "gn:asciiname":"Imperial Manor Mobile Home Terrace",
    "gn:country_code":"US",
    "gn:dem":45,
    "gn:elevation":"42.0",
    "gn:feature_class":"P",
    "gn:feature_code":"PPL",
    "gn:name":"Imperial Manor Mobile Home Terrace",
    "gn:population":0,
    "gn:timezone":"America/New_York",
    "iso:country":"US",
    "wof:name":"Imperial Manor Mobile Home Terrace",
    "wof:placetype":"campus"
},
  "geometry": {"coordinates":[-81.99679999999999,28.0428],"type":"Point"}
}