{
  "type": "Feature",
  "properties": {
    "gn:admin1_code":"AZ",
    "gn:admin2_code":"13.0",
    "gn:asciiname":"Big Palm Trailer Park",
    "gn:country_code":"US",
    "gn:dem":361,
    "gn:elevation":"362.0",
    "gn:feature_class":"P",
    "gn:feature_code":"PPL",
    "gn:name":"Big Palm Trailer Park",
    "gn:population":0,
    "gn:timezone":"America/Phoenix",
    "iso:country":"US",
    "wof:name":"Big Palm Trailer Park",
    "wof:placetype":"campus"
},
  "geometry": {"coordinates":[-111.97987000000001,33.46254],"type":"Point"}
}