{
  "type": "Feature",
  "properties": {
    "gn:admin1_code":"VT",
    "gn:admin2_code":"5.0",
    "gn:admin3_code":"54400.0",
    "gn:asciiname":"Green Bay",
    "gn:country_code":"US",
    "gn:dem":482,
    "gn:elevation":"474.0",
    "gn:feature_class":"P",
    "gn:feature_code":"PPL",
    "gn:name":"Green Bay",
    "gn:population":0,
    "gn:timezone":"America/New_York",
    "iso:country":"US",
    "name:ceb_x_preferred":[
        "Green Bay"
    ],
    "name:ces_x_preferred":[
        "Green Bay"
    ],
    "name:deu_x_preferred":[
        "Green Bay"
    ],
    "name:ind_x_preferred":[
        "Green Bay"
    ],
    "name:ita_x_preferred":[
        "Green Bay"
    ],
    "name:nld_x_preferred":[
        "Green Bay"
    ],
    "name:nor_x_preferred":[
        "Green Bay"
    ],
    "name:pol_x_preferred":[
        "Green Bay"
    ],
    "name:por_x_preferred":[
        "Green Bay"
    ],
    "name:ron_x_preferred":[
        "Green Bay"
    ],
    "name:swe_x_preferred":[
        "Green Bay"
    ],
    "name:ukr_x_preferred":[
        "\u0413\u0440\u0456\u043d-\u0411\u0435\u0439"
    ],
    "wof:name":"Green Bay",
    "wof:placetype":"locality"
},
  "geometry": {"coordinates":[-72.20232,44.30478],"type":"Point"}
}