{
  "type": "Feature",
  "properties": {
    "gn:elevation":67,
    "iso:country":"US",
    "name:eng_x_preferred":[
        "Snake Hill"
    ],
    "name:eng_x_variant":[
        "Snake Hl"
    ],
    "qs:gn_adm0_cc":"US",
    "qs:gn_fcode":"PPL",
    "qs:gn_local":5139732,
    "qs:gn_nam_loc":"Stillwater, Saratoga, New York, US",
    "qs:gn_namadm1":"NY",
    "qs:gn_name":"Snake Hill",
    "qs:local_max":22,
    "qs:local_sum":22,
    "qs:localhoods":1,
    "qs:name":"Snake Hill",
    "qs:name_adm0":"United States",
    "qs:name_adm1":"New York",
    "qs:name_adm2":"Saratoga",
    "qs:name_local":"Stillwater",
    "qs:photo_max":8,
    "qs:photo_sum":22,
    "qs:placetype":"Suburb",
    "qs:quad_count":6,
    "qs:woe_adm0":23424977,
    "qs:woe_adm1":2347591,
    "qs:woe_adm2":12589356,
    "qs:woe_lau":0,
    "qs:woe_local":2499949,
    "qs:woe_ver":"7.10.0",
    "wd:wordcount":1845,
    "wof:lang":[
        "eng"
    ],
    "wof:name":"Snake Hill",
    "wof:placetype":"neighbourhood",
    "wof:population":1921,
    "zs:blockids":[
        360910619033020,
        360910620002038,
        360910619033000,
        360910619033005,
        360910620003009,
        360910620003010,
        360910620002042,
        360910619014038,
        360910619033025,
        360910619033021,
        360910620002036,
        360910619032013,
        360910620003008,
        360910620002032,
        360910620002021,
        360910620002037,
        360910619033027,
        360910619014049,
        360910619014042,
        360910620002040,
        360910620003049,
        360910620003006,
        360910620002039,
        360910619014039,
        360910619014047,
        360910619032006,
        360910619033003,
        360910620003004,
        360910620003003,
        360910619033023,
        360910619032016,
        360910619014051,
        360910619014040,
        360910619014052,
        360910619014041,
        360910619014043,
        360910620003002,
        360910620003007,
        360910619014035,
        360910619033019,
        360910619033018,
        360910620002029,
        360910620003005,
        360910620003001,
        360910619014036
    ],
    "zs:housing10":901,
    "zs:pop10":1921
},
  "geometry": {"coordinates":[-73.74523000000001,42.994056],"type":"Point"}
}