{
  "type": "Feature",
  "properties": {
    "gn:admin1_code":"AR",
    "gn:admin2_code":"55.0",
    "gn:admin3_code":"91389.0",
    "gn:asciiname":"Halliday",
    "gn:country_code":"US",
    "gn:dem":84,
    "gn:elevation":"84.0",
    "gn:feature_class":"P",
    "gn:feature_code":"PPL",
    "gn:name":"Halliday",
    "gn:population":0,
    "gn:timezone":"America/Chicago",
    "iso:country":"US",
    "wof:name":"Halliday",
    "wof:placetype":"locality"
},
  "geometry": {"coordinates":[-90.43427,36.12146],"type":"Point"}
}