{
  "type": "Feature",
  "properties": {
    "gn:elevation":165,
    "iso:country":"US",
    "name:eng_x_preferred":[
        "Long Bridge"
    ],
    "name:eng_x_variant":[
        "Long Brg"
    ],
    "qs:gn_adm0_cc":"US",
    "qs:gn_fcode":"PPL",
    "qs:gn_local":5095115,
    "qs:gn_nam_loc":"Allamuchy, Warren, New Jersey, US",
    "qs:gn_namadm1":"NJ",
    "qs:gn_name":"Long Bridge",
    "qs:local_max":51,
    "qs:local_sum":127,
    "qs:localhoods":5,
    "qs:name":"Long Bridge",
    "qs:name_adm0":"United States",
    "qs:name_adm1":"New Jersey",
    "qs:name_adm2":"Warren",
    "qs:name_local":"Allamuchy",
    "qs:photo_max":6,
    "qs:photo_sum":9,
    "qs:placetype":"Suburb",
    "qs:quad_count":2,
    "qs:woe_adm0":23424977,
    "qs:woe_adm1":2347589,
    "qs:woe_adm2":12589278,
    "qs:woe_lau":0,
    "qs:woe_local":2353207,
    "qs:woe_ver":"7.10.0",
    "wd:wordcount":100,
    "wof:lang":[
        "eng"
    ],
    "wof:name":"Long Bridge",
    "wof:placetype":"neighbourhood",
    "wof:population":647,
    "zs:blockids":[
        340410313022023,
        340410313022011,
        340410313022010,
        340410313022002,
        340410313022000,
        340410313022005,
        340410313022009,
        340410313022022,
        340410313022006,
        340410313022008,
        340410313021067
    ],
    "zs:housing10":367,
    "zs:pop10":647
},
  "geometry": {"coordinates":[-74.828796,40.92389],"type":"Point"}
}