{
  "type": "Feature",
  "properties": {
    "gn:admin1_code":"MI",
    "gn:admin2_code":"147.0",
    "gn:admin3_code":"89000.0",
    "gn:asciiname":"North Hill Mobile Home Village",
    "gn:country_code":"US",
    "gn:dem":252,
    "gn:elevation":"251.0",
    "gn:feature_class":"P",
    "gn:feature_code":"PPL",
    "gn:name":"North Hill Mobile Home Village",
    "gn:population":0,
    "gn:timezone":"America/Detroit",
    "iso:country":"US",
    "wof:name":"North Hill Mobile Home Village",
    "wof:placetype":"campus"
},
  "geometry": {"coordinates":[-82.79861,43.13694],"type":"Point"}
}