{
  "type": "Feature",
  "properties": {
    "gn:country":"US",
    "gn:fcode":"PPL",
    "gn:population":0,
    "iso:country":"US",
    "name:afr_x_preferred":[
        "Avalon"
    ],
    "name:ara_x_preferred":[
        "\u0623\u0641\u0627\u0644\u0648\u0646"
    ],
    "name:bel_x_preferred":[
        "\u0410\u0432\u0430\u043b\u043e\u043d"
    ],
    "name:bre_x_preferred":[
        "Enez Avalon"
    ],
    "name:bul_x_preferred":[
        "\u0410\u0432\u0430\u043b\u043e\u043d"
    ],
    "name:cat_x_preferred":[
        "Avalon"
    ],
    "name:ces_x_preferred":[
        "Avalon"
    ],
    "name:cym_x_preferred":[
        "Ynys Afallon"
    ],
    "name:dan_x_preferred":[
        "Avalon"
    ],
    "name:deu_x_preferred":[
        "Avalon"
    ],
    "name:ell_x_preferred":[
        "\u0386\u03b2\u03b1\u03bb\u03bf\u03bd"
    ],
    "name:epo_x_preferred":[
        "Avalon"
    ],
    "name:fas_x_preferred":[
        "\u0622\u0648\u0627\u0644\u0648\u0646"
    ],
    "name:fin_x_preferred":[
        "Avalon"
    ],
    "name:fra_x_preferred":[
        "Avalon"
    ],
    "name:glg_x_preferred":[
        "Avalon"
    ],
    "name:heb_x_preferred":[
        "\u05d0\u05d1\u05dc\u05d5\u05df"
    ],
    "name:ita_x_preferred":[
        "Avalon"
    ],
    "name:jpn_x_preferred":[
        "\u30a2\u30f4\u30a1\u30ed\u30f3"
    ],
    "name:kat_x_preferred":[
        "\u10d0\u10d5\u10d0\u10da\u10dd\u10dc\u10d8"
    ],
    "name:kor_x_preferred":[
        "\uc544\ubc1c\ub860"
    ],
    "name:lat_x_preferred":[
        "Avallonia"
    ],
    "name:nld_x_preferred":[
        "Avalon"
    ],
    "name:nor_x_preferred":[
        "Avalon"
    ],
    "name:pol_x_preferred":[
        "Avalon"
    ],
    "name:por_x_preferred":[
        "Avalon"
    ],
    "name:ron_x_preferred":[
        "Avalon"
    ],
    "name:rus_x_preferred":[
        "\u0410\u0432\u0430\u043b\u043e\u043d"
    ],
    "name:spa_x_preferred":[
        "\u00c1valon"
    ],
    "name:srp_x_preferred":[
        "Avalon"
    ],
    "name:swe_x_preferred":[
        "Avalon"
    ],
    "name:tha_x_preferred":[
        "\u0e41\u0e2d\u0e27\u0e32\u0e25\u0e2d\u0e19"
    ],
    "name:tur_x_preferred":[
        "Avalon"
    ],
    "name:ukr_x_preferred":[
        "\u0410\u0432\u0430\u043b\u043e\u043d"
    ],
    "name:zho_x_preferred":[
        "\u963f\u74e6\u9686"
    ],
    "qs_pg:aaroncc":"US",
    "qs_pg:gn_country":"US",
    "qs_pg:gn_fcode":"PPL",
    "qs_pg:gn_pop":0,
    "qs_pg:name":"Avalon",
    "qs_pg:name_adm0":"United States",
    "qs_pg:name_adm1":"Nevada",
    "qs_pg:photos":78,
    "qs_pg:photos_1k":16,
    "qs_pg:photos_9k":1,
    "qs_pg:photos_9r":3,
    "qs_pg:photos_all":78,
    "qs_pg:photos_sr":3,
    "qs_pg:pop_sr":0,
    "qs_pg:qs_pg_placetype":"locality",
    "qs_pg:qs_pg_placetype_gp":"Town",
    "qs_pg:woe_adm0":23424977,
    "woe:adm0_id":23424977,
    "woe:name_adm0":"United States",
    "woe:name_adm1":"Nevada",
    "woe:placetype":"Town",
    "wof:name":"Avalon",
    "wof:placetype":"locality"
},
  "geometry": {"coordinates":[-118.75624999999999,38.76297],"type":"Point"}
}