{
  "type": "Feature",
  "properties": {
    "gn:admin1_code":"KY",
    "gn:admin2_code":"95",
    "gn:asciiname":"Rio Vista",
    "gn:country_code":"US",
    "gn:dem":354,
    "gn:elevation":"356.0",
    "gn:feature_class":"P",
    "gn:feature_code":"PPL",
    "gn:name":"Rio Vista",
    "gn:population":0,
    "gn:timezone":"America/New_York",
    "iso:country":"US",
    "name:ceb_x_preferred":[
        "Rio Vista"
    ],
    "name:deu_x_preferred":[
        "Rio Vista"
    ],
    "name:eng_x_preferred":[
        "Rio Vista"
    ],
    "name:fra_x_preferred":[
        "Rio Vista"
    ],
    "name:ita_x_preferred":[
        "Rio Vista"
    ],
    "name:nds_x_preferred":[
        "Rio Vista"
    ],
    "name:nld_x_preferred":[
        "Rio Vista"
    ],
    "name:pol_x_preferred":[
        "Rio Vista"
    ],
    "name:por_x_preferred":[
        "Rio Vista"
    ],
    "name:srp_x_preferred":[
        "\u0420\u0438\u043e \u0412\u0438\u0441\u0442\u0430"
    ],
    "name:und_x_variant":[
        "Emerling Station"
    ],
    "wof:name":"Rio Vista",
    "wof:placetype":"locality"
},
  "geometry": {"coordinates":[-83.35935000000001,36.84398],"type":"Point"}
}