{
  "type": "Feature",
  "properties": {
    "gn:admin1_code":"IN",
    "gn:admin2_code":"097",
    "gn:admin3_code":"25504.0",
    "gn:asciiname":"Hickory Knoll Mobile Home Park",
    "gn:country_code":"US",
    "gn:dem":262,
    "gn:elevation":"261.0",
    "gn:feature_class":"P",
    "gn:feature_code":"PPL",
    "gn:name":"Hickory Knoll Mobile Home Park",
    "gn:population":0,
    "gn:timezone":"America/Indiana/Indianapolis",
    "iso:country":"US",
    "wof:name":"Hickory Knoll Mobile Home Park",
    "wof:placetype":"campus"
},
  "geometry": {"coordinates":[-86.05110999999999,39.70611],"type":"Point"}
}