{
  "type": "Feature",
  "properties": {
    "iso:country":"US",
    "name:eng_x_preferred":[
        "Downtown Valparaiso"
    ],
    "qs:gn_local":0,
    "qs:local_max":1310,
    "qs:local_sum":1789,
    "qs:localhoods":7,
    "qs:name":"Downtown Valparaiso",
    "qs:name_adm0":"United States",
    "qs:name_adm1":"Indiana",
    "qs:name_adm2":"Porter",
    "qs:name_local":"Valparaiso",
    "qs:photo_max":199,
    "qs:photo_sum":377,
    "qs:placetype":"Suburb",
    "qs:quad_count":18,
    "qs:woe_adm0":23424977,
    "qs:woe_adm1":2347573,
    "qs:woe_adm2":12588243,
    "qs:woe_lau":0,
    "qs:woe_local":2511078,
    "qs:woe_ver":"7.10.0",
    "wof:lang":[
        "eng"
    ],
    "wof:name":"Downtown Valparaiso",
    "wof:placetype":"neighbourhood",
    "wof:population":1463,
    "zs:blockids":[
        181270508002042,
        181270509001023,
        181270508002036,
        181270509002009,
        181270509002033,
        181270509001062,
        181270509001061,
        181270509001060,
        181270509001020,
        181270509001009,
        181270509001008,
        181270508002043,
        181270509002003,
        181270509001063,
        181270509001018,
        181270509002004,
        181270509001007,
        181270509001024,
        181270508002054,
        181270509001017,
        181270508002053,
        181270508002041,
        181270509002006,
        181270508002052,
        181270508002059,
        181270509001055,
        181270509002018,
        181270509002039,
        181270509001012,
        181270508002040,
        181270509001065,
        181270509002010,
        181270509002015,
        181270508002035,
        181270508001046,
        181270508002055,
        181270509001011,
        181270509001010,
        181270509001059,
        181270508002058,
        181270509002005,
        181270508001047,
        181270508002056,
        181270509001057,
        181270508002050,
        181270509002017,
        181270508002057,
        181270509001019,
        181270509002016,
        181270509001058,
        181270509001021,
        181270509001022,
        181270508002051,
        181270509001006,
        181270509001056
    ],
    "zs:housing10":792,
    "zs:pop10":1463
},
  "geometry": {"coordinates":[-87.06035300000001,41.466322],"type":"Point"}
}