{
  "type": "Feature",
  "properties": {
    "gn:admin1_code":"FL",
    "gn:admin2_code":"11.0",
    "gn:asciiname":"Colony Mobile Home Park",
    "gn:country_code":"US",
    "gn:dem":7,
    "gn:elevation":"1.0",
    "gn:feature_class":"P",
    "gn:feature_code":"PPL",
    "gn:name":"Colony Mobile Home Park",
    "gn:population":0,
    "gn:timezone":"America/New_York",
    "iso:country":"US",
    "wof:name":"Colony Mobile Home Park",
    "wof:placetype":"campus"
},
  "geometry": {"coordinates":[-80.166,26.0309],"type":"Point"}
}