{
  "type": "Feature",
  "properties": {
    "gn:admin1_code":"MI",
    "gn:admin2_code":"103.0",
    "gn:admin3_code":"14540.0",
    "gn:asciiname":"Beacon",
    "gn:country_code":"US",
    "gn:dem":525,
    "gn:elevation":"527.0",
    "gn:feature_class":"P",
    "gn:feature_code":"PPL",
    "gn:name":"Beacon",
    "gn:population":0,
    "gn:timezone":"America/Detroit",
    "iso:country":"US",
    "name:ara_x_preferred":[
        "\u0645\u0631\u0634\u062f \u0644\u0627\u0633\u0644\u0643\u064a"
    ],
    "name:cat_x_preferred":[
        "Balisa"
    ],
    "name:est_x_preferred":[
        "Tulepaak"
    ],
    "name:eus_x_preferred":[
        "Baliza"
    ],
    "name:fra_x_preferred":[
        "Balise"
    ],
    "name:hin_x_preferred":[
        "\u0927\u094d\u092f\u093e\u0928\u093e\u0915\u0930\u094d\u0937\u0915 \u092c\u0924\u094d\u0924\u0940"
    ],
    "name:hye_x_preferred":[
        "\u053d\u0578\u0582\u0569\u0561\u0576\u0577\u0561\u0576"
    ],
    "name:ind_x_preferred":[
        "Sinyal pandu"
    ],
    "name:isl_x_preferred":[
        "Vegviti"
    ],
    "name:nld_x_preferred":[
        "Baken"
    ],
    "name:spa_x_preferred":[
        "Baliza"
    ],
    "wof:name":"Beacon",
    "wof:placetype":"locality"
},
  "geometry": {"coordinates":[-87.98569000000001,46.51021],"type":"Point"}
}