{
  "type": "Feature",
  "properties": {
    "iso:country":"US",
    "name:ceb_x_preferred":[
        "Lincoln Heights"
    ],
    "name:deu_x_preferred":[
        "Lincoln Heights"
    ],
    "name:eng_x_preferred":[
        "Lincoln Heights"
    ],
    "qs_pg:aaroncc":"US",
    "qs_pg:name":"Lincoln Heights",
    "qs_pg:name_adm0":"United States",
    "qs_pg:name_adm1":"North Carolina",
    "qs_pg:photos":3,
    "qs_pg:photos_1k":1,
    "qs_pg:photos_9k":1,
    "qs_pg:photos_9r":1,
    "qs_pg:photos_all":3,
    "qs_pg:photos_sr":1,
    "qs_pg:pop_sr":0,
    "qs_pg:qs_pg_placetype":"neighbourhood",
    "qs_pg:qs_pg_placetype_gp":"Suburb",
    "qs_pg:woe_adm0":23424977,
    "woe:adm0_id":23424977,
    "woe:name_adm0":"United States",
    "woe:name_adm1":"North Carolina",
    "woe:placetype":"Suburb",
    "wof:name":"Lincoln Heights",
    "wof:placetype":"neighbourhood",
    "wof:population":24
},
  "geometry": {"coordinates":[-77.917407,35.729791],"type":"Point"}
}