{
  "type": "Feature",
  "properties": {
    "gn:admin1_code":"TX",
    "gn:admin2_code":"427",
    "gn:asciiname":"Mikes Colonia",
    "gn:country_code":"US",
    "gn:dem":65,
    "gn:elevation":"64.0",
    "gn:feature_class":"P",
    "gn:feature_code":"PPL",
    "gn:name":"Mikes Colonia",
    "gn:population":0,
    "gn:timezone":"America/Chicago",
    "iso:country":"US",
    "wof:name":"Mikes Colonia",
    "wof:placetype":"locality"
},
  "geometry": {"coordinates":[-98.63336,26.31535],"type":"Point"}
}