{
  "type": "Feature",
  "properties": {
    "gn:elevation":188,
    "iso:country":"US",
    "name:eng_x_preferred":[
        "Scotland Acres"
    ],
    "qs:gn_adm0_cc":"US",
    "qs:gn_fcode":"PPLX",
    "qs:gn_local":4644312,
    "qs:gn_nam_loc":"Murfreesboro, Rutherford, Tennessee, US",
    "qs:gn_namadm1":"TN",
    "qs:gn_name":"Scotland Acres",
    "qs:local_max":1182,
    "qs:local_sum":4977,
    "qs:localhoods":13,
    "qs:name":"Scotland Acres",
    "qs:name_adm0":"United States",
    "qs:name_adm1":"Tennessee",
    "qs:name_adm2":"Rutherford",
    "qs:name_local":"Murfreesboro",
    "qs:photo_max":100,
    "qs:photo_sum":371,
    "qs:placetype":"Suburb",
    "qs:quad_count":19,
    "qs:woe_adm0":23424977,
    "qs:woe_adm1":2347601,
    "qs:woe_adm2":12589986,
    "qs:woe_lau":0,
    "qs:woe_local":2456416,
    "qs:woe_ver":"7.10.0",
    "wof:lang":[
        "eng"
    ],
    "wof:name":"Scotland Acres",
    "wof:placetype":"neighbourhood",
    "wof:population":8454,
    "zs:blockids":[
        471490416001008,
        471490416001009,
        471490414031003,
        471490416001010,
        471490414031008,
        471490414032027,
        471490414032025,
        471490414031016,
        471490414024006,
        471490416001011,
        471490416001018,
        471490414031005,
        471490414031012,
        471490414031010,
        471490414024008,
        471490414024005,
        471490416001006,
        471490416001012,
        471490414024001,
        471490414022012,
        471490416001005,
        471490416001016,
        471490416001017,
        471490414031006,
        471490414031017,
        471490414024002,
        471490416001007,
        471490416004001,
        471490414031011,
        471490414031015,
        471490416004002,
        471490414031009,
        471490414023000,
        471490416001000,
        471490414032038,
        471490414024004,
        471490414024007,
        471490414031013,
        471490414024003,
        471490415001003,
        471490416001001,
        471490414031002,
        471490414031014,
        471490414032031,
        471490414022001,
        471490414031007,
        471490414024000,
        471490416001013
    ],
    "zs:housing10":4361,
    "zs:pop10":8454
},
  "geometry": {"coordinates":[-86.368692,35.857711],"type":"Point"}
}