{
  "type": "Feature",
  "properties": {
    "gn:admin1_code":"TX",
    "gn:admin2_code":"455",
    "gn:asciiname":"Crecy",
    "gn:country_code":"US",
    "gn:dem":114,
    "gn:elevation":"110.0",
    "gn:feature_class":"P",
    "gn:feature_code":"PPL",
    "gn:name":"Crecy",
    "gn:population":0,
    "gn:timezone":"America/Chicago",
    "iso:country":"US",
    "wof:name":"Crecy",
    "wof:placetype":"locality"
},
  "geometry": {"coordinates":[-95.05521,31.2013],"type":"Point"}
}