{
  "type": "Feature",
  "properties": {
    "gn:admin1_code":"VA",
    "gn:admin2_code":"770",
    "gn:asciiname":"Rockydale",
    "gn:country_code":"US",
    "gn:dem":317,
    "gn:elevation":"324.0",
    "gn:feature_class":"P",
    "gn:feature_code":"PPL",
    "gn:name":"Rockydale",
    "gn:population":0,
    "gn:timezone":"America/New_York",
    "iso:country":"US",
    "wof:name":"Rockydale",
    "wof:placetype":"locality"
},
  "geometry": {"coordinates":[-79.92643000000002,37.31264],"type":"Point"}
}