{
  "type": "Feature",
  "properties": {
    "gn:admin1_code":"DE",
    "gn:admin2_code":"1",
    "gn:asciiname":"Cedar Chase",
    "gn:country_code":"US",
    "gn:dem":14,
    "gn:elevation":"12.0",
    "gn:feature_class":"P",
    "gn:feature_code":"PPL",
    "gn:name":"Cedar Chase",
    "gn:population":0,
    "gn:timezone":"America/New_York",
    "iso:country":"US",
    "wof:name":"Cedar Chase",
    "wof:placetype":"locality"
},
  "geometry": {"coordinates":[-75.5527,39.1951],"type":"Point"}
}