{
  "type": "Feature",
  "properties": {
    "gn:admin1_code":"CA",
    "gn:admin2_code":"61.0",
    "gn:asciiname":"Whitney",
    "gn:country_code":"US",
    "gn:dem":37,
    "gn:elevation":"40.0",
    "gn:feature_class":"P",
    "gn:feature_code":"PPL",
    "gn:name":"Whitney",
    "gn:population":0,
    "gn:timezone":"America/Los_Angeles",
    "iso:country":"US",
    "name:zho_x_preferred":[
        "\u60e0\u7279\u5c3c"
    ],
    "wof:name":"Whitney",
    "wof:placetype":"locality"
},
  "geometry": {"coordinates":[-121.3069,38.83351],"type":"Point"}
}