{
  "type": "Feature",
  "properties": {
    "gn:admin1_code":"MD",
    "gn:admin2_code":"15.0",
    "gn:asciiname":"Rock Springs",
    "gn:country_code":"US",
    "gn:dem":157,
    "gn:elevation":"155.0",
    "gn:feature_class":"P",
    "gn:feature_code":"PPL",
    "gn:name":"Rock Springs",
    "gn:population":0,
    "gn:timezone":"America/New_York",
    "iso:country":"US",
    "name:cat_x_preferred":[
        "Rock Springs"
    ],
    "name:ceb_x_preferred":[
        "Rock Springs"
    ],
    "name:dan_x_preferred":[
        "Rock Springs"
    ],
    "name:deu_x_preferred":[
        "Rock Springs"
    ],
    "name:eng_x_preferred":[
        "Rock Springs"
    ],
    "name:fra_x_preferred":[
        "Rock Springs"
    ],
    "name:ita_x_preferred":[
        "Rock Springs"
    ],
    "name:jpn_x_preferred":[
        "\u30ed\u30c3\u30af\u30b9\u30d7\u30ea\u30f3\u30b0\u30b9"
    ],
    "name:nld_x_preferred":[
        "Rock Springs"
    ],
    "name:pol_x_preferred":[
        "Rock Springs"
    ],
    "name:por_x_preferred":[
        "Rock Springs"
    ],
    "name:rus_x_preferred":[
        "\u0420\u043e\u043a-\u0421\u043f\u0440\u0438\u043d\u0433\u0441"
    ],
    "name:spa_x_preferred":[
        "Rock Springs"
    ],
    "name:srp_x_preferred":[
        "\u0420\u043e\u043a \u0421\u043f\u0440\u0438\u043d\u0433\u0441"
    ],
    "name:swe_x_preferred":[
        "Rock Springs"
    ],
    "name:und_x_variant":[
        "Rocksprings",
        "Rock Spring"
    ],
    "name:vol_x_preferred":[
        "Rock Springs"
    ],
    "name:zho_x_preferred":[
        "\u77f3\u6cc9\u57ce"
    ],
    "wof:name":"Rock Springs",
    "wof:placetype":"locality"
},
  "geometry": {"coordinates":[-76.15855999999999,39.71511],"type":"Point"}
}