{
  "type": "Feature",
  "properties": {
    "gn:admin1_code":"IN",
    "gn:admin2_code":"75.0",
    "gn:admin3_code":"38034.0",
    "gn:asciiname":"Powers",
    "gn:country_code":"US",
    "gn:dem":303,
    "gn:elevation":"303.0",
    "gn:feature_class":"P",
    "gn:feature_code":"PPL",
    "gn:name":"Powers",
    "gn:population":0,
    "gn:timezone":"America/Indiana/Indianapolis",
    "iso:country":"US",
    "name:fas_x_preferred":[
        "\u067e\u0627\u0648\u0631\u0632"
    ],
    "wof:name":"Powers",
    "wof:placetype":"locality"
},
  "geometry": {"coordinates":[-85.09246999999998,40.32199],"type":"Point"}
}