{
  "type": "Feature",
  "properties": {
    "iso:country":"US",
    "name:eng_x_preferred":[
        "Charter Oaks"
    ],
    "wd:wordcount":779,
    "wof:name":"Charter Oaks",
    "wof:placetype":"neighbourhood",
    "wof:population":3269,
    "zs:area_m":5073600.241193,
    "zs:blockids":[
        370250423002009,
        370250424012019,
        370250423001003,
        370250424012028,
        370250423002020,
        370250424012033,
        370250424012071,
        370250423002016,
        370250423002000,
        370250424012031,
        370250423001017,
        370250423001011,
        370250423002005,
        370250423002014,
        370250423002006,
        370250424012035,
        370250424012013,
        370250423001005,
        370250424012039,
        370250423001002,
        370250423001019,
        370250423002024,
        370250423002013,
        370250423002010,
        370250424012027,
        370250424012026,
        370250424012010,
        370250424012011,
        370250424012004,
        370250424012076,
        370250424012052,
        370250423001015,
        370250423001012,
        370250423002026,
        370250423002015,
        370250423002008,
        370250423002011,
        370250424012018,
        370250424012029,
        370250424012037,
        370250424012012,
        370250424012015,
        370250423002001,
        370250423001020,
        370250419021007,
        370250423002027,
        370250424012014,
        370250424012032,
        370250419021014,
        370250423002022,
        370250423002028,
        370250423002017,
        370250424012034,
        370250423001009,
        370250424012053,
        370250424012016,
        370250424012036,
        370250423001000,
        370250424012073,
        370250423001016,
        370250423002025,
        370250423002003,
        370250424012040,
        370250424012038,
        370250424012021,
        370250424012030,
        370250423002023,
        370250423002018,
        370250424012017,
        370250423001004,
        370250423001008,
        370250423001006,
        370250423001007,
        370250423002021,
        370250423002019,
        370250423001010,
        370250423002012,
        370250423002007,
        370250423002004,
        370250423002002
    ],
    "zs:housing10":1403,
    "zs:label":"Charter Oaks",
    "zs:pop10":3269
},
  "geometry": {"coordinates":[-80.57551599999999,35.43697],"type":"Point"}
}