{
  "type": "Feature",
  "properties": {
    "gn:admin1_code":"SC",
    "gn:admin2_code":"3.0",
    "gn:asciiname":"Talatha",
    "gn:country_code":"US",
    "gn:dem":128,
    "gn:elevation":"124.0",
    "gn:feature_class":"P",
    "gn:feature_code":"PPL",
    "gn:name":"Talatha",
    "gn:population":0,
    "gn:timezone":"America/New_York",
    "iso:country":"US",
    "wof:name":"Talatha",
    "wof:placetype":"locality"
},
  "geometry": {"coordinates":[-81.70455,33.39514],"type":"Point"}
}