{
  "type": "Feature",
  "properties": {
    "gn:admin1_code":"TX",
    "gn:admin2_code":"131",
    "gn:asciiname":"Cruz Calle",
    "gn:country_code":"US",
    "gn:dem":79,
    "gn:elevation":"76.0",
    "gn:feature_class":"P",
    "gn:feature_code":"PPL",
    "gn:name":"Cruz Calle",
    "gn:population":0,
    "gn:timezone":"America/Chicago",
    "iso:country":"US",
    "wof:name":"Cruz Calle",
    "wof:placetype":"locality"
},
  "geometry": {"coordinates":[-98.27056,27.38698],"type":"Point"}
}