{
  "type": "Feature",
  "properties": {
    "gn:admin1_code":"GA",
    "gn:admin2_code":"119",
    "gn:asciiname":"Whitworth",
    "gn:country_code":"US",
    "gn:dem":258,
    "gn:elevation":"256.0",
    "gn:feature_class":"P",
    "gn:feature_code":"PPL",
    "gn:name":"Whitworth",
    "gn:population":0,
    "gn:timezone":"America/New_York",
    "iso:country":"US",
    "name:ceb_x_preferred":[
        "Whitworth"
    ],
    "name:deu_x_preferred":[
        "Whitworth"
    ],
    "name:fra_x_preferred":[
        "Whitworth"
    ],
    "name:ita_x_preferred":[
        "Whitworth"
    ],
    "name:jpn_x_preferred":[
        "\u30db\u30a4\u30c3\u30c8\u30ef\u30fc\u30b9"
    ],
    "name:nld_x_preferred":[
        "Whitworth"
    ],
    "name:pol_x_preferred":[
        "Whitworth"
    ],
    "name:rus_x_preferred":[
        "\u0423\u0438\u0442\u0432\u043e\u0440\u0442"
    ],
    "name:swe_x_preferred":[
        "Whitworth"
    ],
    "name:vol_x_preferred":[
        "Whitworth"
    ],
    "wof:name":"Whitworth",
    "wof:placetype":"locality"
},
  "geometry": {"coordinates":[-83.09487,34.48399000000001],"type":"Point"}
}