{
  "type": "Feature",
  "properties": {
    "iso:country":"US",
    "name:eng_x_preferred":[
        "Sierra Center"
    ],
    "wof:name":"Sierra Center",
    "wof:placetype":"neighbourhood",
    "zs:area_m":33235.513738,
    "zs:blockids":[
        60610208061018
    ],
    "zs:housing10":0,
    "zs:label":"Sierra Center",
    "zs:pop10":0
},
  "geometry": {"coordinates":[-121.27115999999999,38.744775],"type":"Point"}
}