{
  "type": "Feature",
  "properties": {
    "gn:admin1_code":"DE",
    "gn:admin2_code":"5.0",
    "gn:asciiname":"Herring Creek Estates",
    "gn:country_code":"US",
    "gn:dem":6,
    "gn:elevation":"5.0",
    "gn:feature_class":"P",
    "gn:feature_code":"PPL",
    "gn:name":"Herring Creek Estates",
    "gn:population":0,
    "gn:timezone":"America/New_York",
    "iso:country":"US",
    "wof:name":"Herring Creek Estates",
    "wof:placetype":"locality"
},
  "geometry": {"coordinates":[-75.18574,38.66233],"type":"Point"}
}