{
  "type": "Feature",
  "properties": {
    "gn:admin1_code":"VA",
    "gn:admin2_code":"83",
    "gn:asciiname":"High Rock",
    "gn:country_code":"US",
    "gn:dem":182,
    "gn:elevation":"185.0",
    "gn:feature_class":"P",
    "gn:feature_code":"PPL",
    "gn:name":"High Rock",
    "gn:population":0,
    "gn:timezone":"America/New_York",
    "iso:country":"US",
    "name:ceb_x_preferred":[
        "High Rock"
    ],
    "name:fas_x_preferred":[
        "\u0647\u0627\u06cc \u0631\u0627\u06a9"
    ],
    "name:fra_x_preferred":[
        "High Rock"
    ],
    "name:por_x_preferred":[
        "High Rock"
    ],
    "name:ron_x_preferred":[
        "High Rock"
    ],
    "name:swe_x_preferred":[
        "High Rock"
    ],
    "wof:name":"High Rock",
    "wof:placetype":"locality"
},
  "geometry": {"coordinates":[-79.09696,36.77958],"type":"Point"}
}