{
  "type": "Feature",
  "properties": {
    "iso:country":"US",
    "name:eng_x_preferred":[
        "Hollars Hill"
    ],
    "wof:name":"Hollars Hill",
    "wof:placetype":"neighbourhood",
    "wof:population":1324,
    "zs:area_m":6782674.267068,
    "zs:blockids":[
        420792170012208,
        420792170012209,
        420792170012207,
        420792170011013,
        420792179004019,
        420792179001001,
        420792179004017,
        420792179004045,
        420792170011002,
        420792179004048,
        420792179004054,
        420792170011042,
        420792170012117,
        420792170011034,
        420792179001013,
        420792170011012,
        420792179001006,
        420792170012123,
        420792170011007,
        420792170012118,
        420792170011044,
        420792179004018,
        420792179004047,
        420792170011008,
        420792170012113,
        420792170011040,
        420792170011045,
        420792170011014,
        420792170011039,
        420792170012116,
        420792170012121,
        420792170011019,
        420792170011001,
        420792170011011,
        420792170011004,
        420792170011005,
        420792179004016,
        420792170011031,
        420792179001011,
        420792170012120,
        420792170011006,
        420792170011009,
        420792170011041,
        420792170011010,
        420792170012124,
        420792170011024,
        420792170011033,
        420792170012115,
        420792170011022,
        420792170011032,
        420792170011043,
        420792170012119,
        420792170011023,
        420792179004046,
        420792179004063,
        420792170011018,
        420792179001012,
        420792179004020,
        420792179004044,
        420792170011030,
        420792179001003,
        420792170012122
    ],
    "zs:housing10":611,
    "zs:label":"Hollars Hill",
    "zs:pop10":1324
},
  "geometry": {"coordinates":[-76.012494,40.955962],"type":"Point"}
}