{
  "type": "Feature",
  "properties": {
    "gn:admin1_code":"TX",
    "gn:admin2_code":"411",
    "gn:asciiname":"McMillan",
    "gn:country_code":"US",
    "gn:dem":369,
    "gn:elevation":"368.0",
    "gn:feature_class":"P",
    "gn:feature_code":"PPL",
    "gn:name":"McMillan",
    "gn:population":0,
    "gn:timezone":"America/Chicago",
    "iso:country":"US",
    "name:bel_x_preferred":[
        "\u041c\u0430\u043a-\u041c\u0456\u043b\u0430\u043d"
    ],
    "name:deu_x_preferred":[
        "McMillan"
    ],
    "name:epo_x_preferred":[
        "McMillan"
    ],
    "name:fin_x_preferred":[
        "McMillan"
    ],
    "name:heb_x_preferred":[
        "\u05de\u05e7\u05de\u05d9\u05dc\u05df"
    ],
    "name:ita_x_preferred":[
        "McMillan"
    ],
    "name:jpn_x_preferred":[
        "\u30de\u30af\u30df\u30e9\u30f3"
    ],
    "name:kor_x_preferred":[
        "\ub9e5\ubc00\ub7f0"
    ],
    "name:pol_x_preferred":[
        "McMillan"
    ],
    "name:por_x_preferred":[
        "McMillan"
    ],
    "name:rus_x_preferred":[
        "\u041c\u0430\u043a\u043c\u0438\u043b\u043b\u0430\u043d"
    ],
    "name:srp_x_preferred":[
        "\u041c\u0430\u043a\u043c\u0438\u043b\u0430\u043d"
    ],
    "name:ukr_x_preferred":[
        "\u041c\u0430\u043a\u043c\u0456\u043b\u043b\u0430\u043d"
    ],
    "name:zho_x_preferred":[
        "\u9ea5\u7f8e\u502b"
    ],
    "wof:name":"McMillan",
    "wof:placetype":"locality"
},
  "geometry": {"coordinates":[-98.65199,31.31961],"type":"Point"}
}