{
  "type": "Feature",
  "properties": {
    "gn:elevation":2,
    "iso:country":"US",
    "name:eng_x_preferred":[
        "Fort Elfsborg"
    ],
    "name:eng_x_variant":[
        "Ft Elfsborg",
        "Fort Nya Elfsborg"
    ],
    "name:swe_x_preferred":[
        "Fort Nya Elfsborg"
    ],
    "name:und_x_variant":[
        "Wootsessungsing"
    ],
    "qs:gn_fcode":"PPL",
    "qs:gn_local":0,
    "qs:gn_namadm1":"NJ",
    "qs:gn_name":"Fort Elfsborg",
    "qs:local_max":91,
    "qs:local_sum":189,
    "qs:localhoods":3,
    "qs:name":"Fort Elfsborg",
    "qs:name_adm0":"United States",
    "qs:name_adm1":"New Jersey",
    "qs:name_adm2":"Salem",
    "qs:name_local":"Elsinboro",
    "qs:photo_max":5,
    "qs:photo_sum":8,
    "qs:placetype":"Suburb",
    "qs:quad_count":3,
    "qs:woe_adm0":23424977,
    "qs:woe_adm1":2347589,
    "qs:woe_adm2":12589274,
    "qs:woe_lau":0,
    "qs:woe_local":28745540,
    "qs:woe_ver":"7.10.0",
    "wd:wordcount":768,
    "wof:lang":[
        "eng"
    ],
    "wof:name":"Fort Elfsborg",
    "wof:placetype":"neighbourhood",
    "wof:population":352,
    "zs:blockids":[
        340330222021042,
        340330222021034,
        340330222021051,
        340330222021038,
        340330222021039,
        340330222021031,
        340330222021028,
        340330222011036,
        340330222021050,
        340330222021047,
        340330222021041,
        340330222011032,
        340330222021063,
        340330222011008,
        340330222021027,
        340330222021046,
        340330222011118,
        340330222021052,
        340330222011030,
        340330222021043,
        340330222021048,
        340330222021036,
        340330222021029,
        340330222021045,
        340330222011007,
        340330222021035,
        340330222021068,
        340330222021044,
        340330222021049,
        340330222021069,
        340330222011057,
        340330222021030,
        340330222021037,
        340330222021040,
        340330222021033,
        340330222021062,
        340330222021067,
        340330222021064,
        340330222021032
    ],
    "zs:housing10":183,
    "zs:pop10":352
},
  "geometry": {"coordinates":[-75.524826,39.548],"type":"Point"}
}