{
  "type": "Feature",
  "properties": {
    "gn:admin1_code":"AL",
    "gn:admin2_code":"13",
    "gn:asciiname":"Garland",
    "gn:country_code":"US",
    "gn:dem":68,
    "gn:elevation":"64.0",
    "gn:feature_class":"P",
    "gn:feature_code":"PPL",
    "gn:name":"Garland",
    "gn:population":0,
    "gn:timezone":"America/Chicago",
    "iso:country":"US",
    "name:ara_x_preferred":[
        "\u0625\u0643\u0644\u064a\u0644 \u0632\u0647\u0648\u0631"
    ],
    "name:ces_x_preferred":[
        "Girlanda"
    ],
    "name:dan_x_preferred":[
        "Guirlande"
    ],
    "name:deu_x_preferred":[
        "Girlande"
    ],
    "name:epo_x_preferred":[
        "Girlando"
    ],
    "name:eus_x_preferred":[
        "Girlanda"
    ],
    "name:fra_x_preferred":[
        "Guirlande"
    ],
    "name:glg_x_preferred":[
        "Grilanda"
    ],
    "name:hin_x_preferred":[
        "\u092e\u093e\u0932\u093e"
    ],
    "name:hrv_x_preferred":[
        "Girlanda"
    ],
    "name:hye_x_preferred":[
        "\u053e\u0561\u0572\u056f\u0561\u0577\u0572\u0569\u0561"
    ],
    "name:ido_x_preferred":[
        "Girlando"
    ],
    "name:kan_x_preferred":[
        "\u0cb9\u0cbe\u0cb0"
    ],
    "name:kir_x_preferred":[
        "\u0413\u0438\u0440\u043b\u044f\u043d\u0434\u0430"
    ],
    "name:mal_x_preferred":[
        "\u0d2a\u0d42\u0d2e\u0d3e\u0d32"
    ],
    "name:nep_x_preferred":[
        "\u092e\u093e\u0932\u093e"
    ],
    "name:nld_x_preferred":[
        "Slinger"
    ],
    "name:nno_x_preferred":[
        "Girlander"
    ],
    "name:nor_x_preferred":[
        "Girlander"
    ],
    "name:pol_x_preferred":[
        "Girlanda"
    ],
    "name:por_x_preferred":[
        "Guirlanda"
    ],
    "name:rus_x_preferred":[
        "\u0413\u0438\u0440\u043b\u044f\u043d\u0434\u0430"
    ],
    "name:spa_x_preferred":[
        "Guirnalda"
    ],
    "name:ukr_x_preferred":[
        "\u0413\u0456\u0440\u043b\u044f\u043d\u0434\u0430"
    ],
    "wof:name":"Garland",
    "wof:placetype":"locality"
},
  "geometry": {"coordinates":[-86.82330999999998,31.55655],"type":"Point"}
}