{
  "type": "Feature",
  "properties": {
    "gn:admin1_code":"TX",
    "gn:admin2_code":"1.0",
    "gn:asciiname":"Ward",
    "gn:country_code":"US",
    "gn:dem":112,
    "gn:elevation":"110.0",
    "gn:feature_class":"P",
    "gn:feature_code":"PPL",
    "gn:name":"Ward",
    "gn:population":0,
    "gn:timezone":"America/Chicago",
    "iso:country":"US",
    "name:cat_x_preferred":[
        "Ward"
    ],
    "name:ceb_x_preferred":[
        "Ward"
    ],
    "name:ces_x_preferred":[
        "Ward"
    ],
    "name:deu_x_preferred":[
        "Ward"
    ],
    "name:fin_x_preferred":[
        "Ward"
    ],
    "name:fra_x_preferred":[
        "Ward"
    ],
    "name:ita_x_preferred":[
        "Ward"
    ],
    "name:jpn_x_preferred":[
        "\u30a6\u30a9\u30fc\u30c9"
    ],
    "name:nld_x_preferred":[
        "Ward"
    ],
    "name:pol_x_preferred":[
        "Ward"
    ],
    "name:por_x_preferred":[
        "Ward"
    ],
    "name:rus_x_preferred":[
        "\u0423\u043e\u0440\u0434"
    ],
    "name:slk_x_preferred":[
        "Ward"
    ],
    "name:swe_x_preferred":[
        "Ward"
    ],
    "name:urd_x_preferred":[
        "\u0648\u0627\u0631\u0688"
    ],
    "name:vol_x_preferred":[
        "Ward"
    ],
    "wof:name":"Ward",
    "wof:placetype":"locality"
},
  "geometry": {"coordinates":[-95.80468,31.90711],"type":"Point"}
}