{
  "type": "Feature",
  "properties": {
    "gn:admin1_code":"IL",
    "gn:admin2_code":"167",
    "gn:admin3_code":"83310.0",
    "gn:asciiname":"Coleman",
    "gn:country_code":"US",
    "gn:dem":183,
    "gn:elevation":"183.0",
    "gn:feature_class":"P",
    "gn:feature_code":"PPL",
    "gn:name":"Coleman",
    "gn:population":0,
    "gn:timezone":"America/Chicago",
    "iso:country":"US",
    "name:cat_x_preferred":[
        "Coleman"
    ],
    "name:ceb_x_preferred":[
        "Coleman"
    ],
    "name:ces_x_preferred":[
        "Coleman"
    ],
    "name:deu_x_preferred":[
        "Coleman"
    ],
    "name:fas_x_preferred":[
        "\u06a9\u0644\u0645\u0646"
    ],
    "name:fin_x_preferred":[
        "Coleman"
    ],
    "name:fra_x_preferred":[
        "Coleman"
    ],
    "name:heb_x_preferred":[
        "\u05e7\u05d5\u05dc\u05de\u05df"
    ],
    "name:ita_x_preferred":[
        "Coleman"
    ],
    "name:jpn_x_preferred":[
        "\u30b3\u30fc\u30eb\u30de\u30f3"
    ],
    "name:lav_x_preferred":[
        "Kolmens"
    ],
    "name:nld_x_preferred":[
        "Coleman"
    ],
    "name:pol_x_preferred":[
        "Coleman"
    ],
    "name:por_x_preferred":[
        "Coleman"
    ],
    "name:rus_x_preferred":[
        "\u041a\u043e\u0443\u043b\u043c\u0430\u043d"
    ],
    "name:spa_x_preferred":[
        "Coleman"
    ],
    "name:srp_x_preferred":[
        "\u041a\u043e\u043b\u043c\u0430\u043d"
    ],
    "name:swe_x_preferred":[
        "Coleman"
    ],
    "name:ukr_x_preferred":[
        "\u041a\u043e\u0443\u043b\u043c\u0435\u043d"
    ],
    "name:vol_x_preferred":[
        "Coleman"
    ],
    "wof:name":"Coleman",
    "wof:placetype":"locality"
},
  "geometry": {"coordinates":[-89.68621,39.76116],"type":"Point"}
}