{
  "type": "Feature",
  "properties": {
    "gn:country":"US",
    "gn:fcode":"PPL",
    "gn:population":0,
    "iso:country":"US",
    "name:deu_x_preferred":[
        "Pender"
    ],
    "name:eng_x_preferred":[
        "Pender"
    ],
    "name:fra_x_preferred":[
        "Pender"
    ],
    "name:pol_x_preferred":[
        "Pender"
    ],
    "name:por_x_preferred":[
        "Pender"
    ],
    "name:rus_x_preferred":[
        "\u041f\u0435\u043d\u0434\u0435\u0440"
    ],
    "name:srp_x_preferred":[
        "\u041f\u0435\u043d\u0434\u0435\u0440"
    ],
    "name:swe_x_preferred":[
        "Pender"
    ],
    "name:und_x_variant":[
        "Ox Hill"
    ],
    "qs_pg:aaroncc":"US",
    "qs_pg:gn_country":"US",
    "qs_pg:gn_fcode":"PPL",
    "qs_pg:gn_pop":0,
    "qs_pg:name":"Pender",
    "qs_pg:name_adm0":"United States",
    "qs_pg:name_adm1":"Virginia",
    "qs_pg:photos":275,
    "qs_pg:photos_1k":56,
    "qs_pg:photos_9k":1,
    "qs_pg:photos_9r":4,
    "qs_pg:photos_all":275,
    "qs_pg:photos_sr":5,
    "qs_pg:pop_sr":5,
    "qs_pg:qs_pg_placetype":"locality",
    "qs_pg:qs_pg_placetype_gp":"Town",
    "qs_pg:woe_adm0":23424977,
    "woe:adm0_id":23424977,
    "woe:name_adm0":"United States",
    "woe:name_adm1":"Virginia",
    "woe:placetype":"Town",
    "wof:name":"Pender",
    "wof:placetype":"locality"
},
  "geometry": {"coordinates":[-77.36888,38.87067],"type":"Point"}
}