{
  "type": "Feature",
  "properties": {
    "gn:admin1_code":"MO",
    "gn:admin2_code":"119.0",
    "gn:admin3_code":"59600.0",
    "gn:asciiname":"Saratoga",
    "gn:country_code":"US",
    "gn:dem":313,
    "gn:elevation":"311.0",
    "gn:feature_class":"P",
    "gn:feature_code":"PPL",
    "gn:name":"Saratoga",
    "gn:population":0,
    "gn:timezone":"America/Chicago",
    "iso:country":"US",
    "name:bul_x_preferred":[
        "\u0421\u0430\u0440\u0430\u0442\u043e\u0433\u0430"
    ],
    "name:cat_x_preferred":[
        "Saratoga"
    ],
    "name:ceb_x_preferred":[
        "Saratoga"
    ],
    "name:deu_x_preferred":[
        "Saratoga"
    ],
    "name:eng_x_preferred":[
        "Saratoga"
    ],
    "name:fin_x_preferred":[
        "Saratoga"
    ],
    "name:fra_x_preferred":[
        "Saratoga"
    ],
    "name:ita_x_preferred":[
        "Saratoga"
    ],
    "name:jpn_x_preferred":[
        "\u30b5\u30e9\u30c8\u30ac"
    ],
    "name:kor_x_preferred":[
        "\uc0c8\ub7ec\ud1a0\uac00"
    ],
    "name:nld_x_preferred":[
        "Saratoga"
    ],
    "name:pol_x_preferred":[
        "Saratoga"
    ],
    "name:por_x_preferred":[
        "Saratoga"
    ],
    "name:ron_x_preferred":[
        "Saratoga"
    ],
    "name:rus_x_preferred":[
        "\u0421\u0430\u0440\u0430\u0442\u043e\u0433\u0430"
    ],
    "name:spa_x_preferred":[
        "Saratoga"
    ],
    "name:srp_x_preferred":[
        "\u0421\u0430\u0440\u0430\u0442\u043e\u0433\u0430"
    ],
    "name:swe_x_preferred":[
        "Saratoga"
    ],
    "name:ukr_x_preferred":[
        "\u0421\u0430\u0440\u0430\u0442\u043e\u0433\u0430"
    ],
    "name:und_x_variant":[
        "Saratoga Springs"
    ],
    "name:vol_x_preferred":[
        "Saratoga"
    ],
    "name:zho_x_preferred":[
        "\u8428\u62c9\u6258\u52a0"
    ],
    "wof:name":"Saratoga",
    "wof:placetype":"locality"
},
  "geometry": {"coordinates":[-94.55661000000001,36.54146],"type":"Point"}
}