{
  "type": "Feature",
  "properties": {
    "iso:country":"US",
    "name:eng_x_preferred":[
        "Rail Road Heights"
    ],
    "wof:name":"Rail Road Heights",
    "wof:placetype":"neighbourhood",
    "wof:population":2490,
    "zs:area_m":27221310.214761,
    "zs:blockids":[
        121050124071020,
        121050124071027,
        121050123061004,
        121050124071024,
        121050123061014,
        121050123051048,
        121050123051042,
        121050124071043,
        121050123051045,
        121050124071040,
        121050116051000,
        121050123051031,
        121050124071012,
        121050123051003,
        121050116051007,
        121050123061001,
        121050124071007,
        121050123051033,
        121050123061003,
        121050123051037,
        121050123051013,
        121050124071082,
        121050124071030,
        121050123051020,
        121050123051023,
        121050123051017,
        121050123051018,
        121050123051043,
        121050124071038,
        121050116051091,
        121050116051010,
        121050123051014,
        121050123051000,
        121050124071083,
        121050123051034,
        121050116051005,
        121050116051003,
        121050124071037,
        121050123051021,
        121050123051025,
        121050123051052,
        121050116051008,
        121050124071026,
        121050123051032,
        121050123051022,
        121050123051038,
        121050123051006,
        121050124071036,
        121050123051047,
        121050123051016,
        121050124071032,
        121050124071023,
        121050123061002,
        121050124071029,
        121050124071013,
        121050124071004,
        121050123051055,
        121050123051019,
        121050123051024,
        121050123051041,
        121050116051001,
        121050124071019,
        121050124071041,
        121050123051005,
        121050124071014,
        121050123051039,
        121050123051007,
        121050123051012,
        121050123051035,
        121050116051002,
        121050123051015,
        121050123051050,
        121050124071039,
        121050124071016,
        121050116051009,
        121050124071042,
        121050123051044,
        121050123051036,
        121050123051049,
        121050123051051,
        121050116051082,
        121050124071031,
        121050123051011,
        121050124071025,
        121050116051027,
        121050124071017,
        121050123051009,
        121050123051010,
        121050123051040,
        121050116051004,
        121050123051046,
        121050124071015,
        121050116051030
    ],
    "zs:housing10":1064,
    "zs:label":"Rail Road Heights",
    "zs:pop10":2490
},
  "geometry": {"coordinates":[-81.847092,28.312051],"type":"Point"}
}