{
  "type": "Feature",
  "properties": {
    "gn:admin1_code":"OK",
    "gn:admin2_code":"13.0",
    "gn:asciiname":"Pirtle",
    "gn:country_code":"US",
    "gn:dem":183,
    "gn:elevation":"179.0",
    "gn:feature_class":"P",
    "gn:feature_code":"PPL",
    "gn:name":"Pirtle",
    "gn:population":0,
    "gn:timezone":"America/Chicago",
    "iso:country":"US",
    "wof:name":"Pirtle",
    "wof:placetype":"locality"
},
  "geometry": {"coordinates":[-96.26777,33.98899],"type":"Point"}
}