{
  "type": "Feature",
  "properties": {
    "gn:admin1_code":"FL",
    "gn:admin2_code":"105.0",
    "gn:asciiname":"Santa Fe Mobile Home Park",
    "gn:country_code":"US",
    "gn:dem":43,
    "gn:elevation":"42.0",
    "gn:feature_class":"P",
    "gn:feature_code":"PPL",
    "gn:name":"Santa Fe Mobile Home Park",
    "gn:population":0,
    "gn:timezone":"America/New_York",
    "iso:country":"US",
    "wof:name":"Santa Fe Mobile Home Park",
    "wof:placetype":"campus"
},
  "geometry": {"coordinates":[-81.74160999999999,27.95841],"type":"Point"}
}