{
  "type": "Feature",
  "properties": {
    "gn:admin1_code":"MD",
    "gn:admin2_code":"25.0",
    "gn:asciiname":"Clear Spring Estates",
    "gn:country_code":"US",
    "gn:dem":172,
    "gn:elevation":"182.0",
    "gn:feature_class":"P",
    "gn:feature_code":"PPL",
    "gn:name":"Clear Spring Estates",
    "gn:population":0,
    "gn:timezone":"America/New_York",
    "iso:country":"US",
    "wof:name":"Clear Spring Estates",
    "wof:placetype":"locality"
},
  "geometry": {"coordinates":[-76.46552,39.57344000000001],"type":"Point"}
}