{
  "type": "Feature",
  "properties": {
    "gn:admin1_code":"AL",
    "gn:admin2_code":"73",
    "gn:asciiname":"Northgate Trailer Park",
    "gn:country_code":"US",
    "gn:dem":195,
    "gn:elevation":"199.0",
    "gn:feature_class":"P",
    "gn:feature_code":"PPL",
    "gn:name":"Northgate Trailer Park",
    "gn:population":0,
    "gn:timezone":"America/Chicago",
    "iso:country":"US",
    "wof:name":"Northgate Trailer Park",
    "wof:placetype":"campus"
},
  "geometry": {"coordinates":[-86.6811,33.7201],"type":"Point"}
}