{
  "type": "Feature",
  "properties": {
    "gn:admin1_code":"MD",
    "gn:admin2_code":"13.0",
    "gn:asciiname":"Lakeview",
    "gn:country_code":"US",
    "gn:dem":185,
    "gn:elevation":"183.0",
    "gn:feature_class":"P",
    "gn:feature_code":"PPL",
    "gn:name":"Lakeview",
    "gn:population":0,
    "gn:timezone":"America/New_York",
    "iso:country":"US",
    "name:cat_x_preferred":[
        "Lakeview"
    ],
    "name:ceb_x_preferred":[
        "Lakeview"
    ],
    "name:deu_x_preferred":[
        "Lakeview"
    ],
    "name:fas_x_preferred":[
        "\u0644\u06cc\u06a9\u0648\u06cc\u0648"
    ],
    "name:fra_x_preferred":[
        "Lakeview"
    ],
    "name:hun_x_preferred":[
        "Lakeview"
    ],
    "name:ita_x_preferred":[
        "Lakeview"
    ],
    "name:nld_x_preferred":[
        "Lakeview"
    ],
    "name:pol_x_preferred":[
        "Lakeview"
    ],
    "name:por_x_preferred":[
        "Lakeview"
    ],
    "name:rus_x_preferred":[
        "\u041b\u0435\u0439\u043a\u0432\u044c\u044e"
    ],
    "name:spa_x_preferred":[
        "Lakeview"
    ],
    "name:srp_x_preferred":[
        "\u041b\u0435\u0458\u043a\u0432\u0458\u0443"
    ],
    "name:swe_x_preferred":[
        "Lakeview"
    ],
    "name:ukr_x_preferred":[
        "\u041b\u0435\u0439\u043a\u0432'\u044e"
    ],
    "name:vol_x_preferred":[
        "Lakeview"
    ],
    "wof:name":"Lakeview",
    "wof:placetype":"locality"
},
  "geometry": {"coordinates":[-76.90998,39.41344],"type":"Point"}
}