{
  "type": "Feature",
  "properties": {
    "gn:admin1_code":"GA",
    "gn:admin2_code":"63.0",
    "gn:asciiname":"Hyde Park Mobile Home Park",
    "gn:country_code":"US",
    "gn:dem":275,
    "gn:elevation":"274.0",
    "gn:feature_class":"P",
    "gn:feature_code":"PPL",
    "gn:name":"Hyde Park Mobile Home Park",
    "gn:population":0,
    "gn:timezone":"America/New_York",
    "iso:country":"US",
    "wof:name":"Hyde Park Mobile Home Park",
    "wof:placetype":"campus"
},
  "geometry": {"coordinates":[-84.31881,33.63455],"type":"Point"}
}