{
  "type": "Feature",
  "properties": {
    "iso:country":"US",
    "name:eng_x_preferred":[
        "Wales Center"
    ],
    "wof:name":"Wales Center",
    "wof:placetype":"neighbourhood",
    "wof:population":392,
    "zs:area_m":13699898.240861,
    "zs:blockids":[
        230010465004046,
        230010465004036,
        230010465004033,
        230010465004044
    ],
    "zs:housing10":165,
    "zs:label":"Wales Center",
    "zs:pop10":392
},
  "geometry": {"coordinates":[-70.070857,44.14776],"type":"Point"}
}