{
  "type": "Feature",
  "properties": {
    "gn:country":"US",
    "gn:fcode":"PPL",
    "gn:population":0,
    "iso:country":"US",
    "name:deu_x_preferred":[
        "Brownstone"
    ],
    "name:fra_x_preferred":[
        "Brownstone"
    ],
    "name:ind_x_preferred":[
        "Batu cokelat"
    ],
    "qs_pg:aaroncc":"US",
    "qs_pg:gn_country":"US",
    "qs_pg:gn_fcode":"PPL",
    "qs_pg:gn_pop":0,
    "qs_pg:name":"Brownstone",
    "qs_pg:name_adm0":"United States",
    "qs_pg:name_adm1":"Kansas",
    "qs_pg:photos":3,
    "qs_pg:photos_1k":1,
    "qs_pg:photos_9k":1,
    "qs_pg:photos_9r":1,
    "qs_pg:photos_all":3,
    "qs_pg:photos_sr":1,
    "qs_pg:pop_sr":0,
    "qs_pg:qs_pg_placetype":"locality",
    "qs_pg:qs_pg_placetype_gp":"Town",
    "qs_pg:woe_adm0":23424977,
    "woe:adm0_id":23424977,
    "woe:name_adm0":"United States",
    "woe:name_adm1":"Kansas",
    "woe:placetype":"Town",
    "wof:name":"Brownstone",
    "wof:placetype":"locality"
},
  "geometry": {"coordinates":[-95.19414,37.33284],"type":"Point"}
}