{
  "type": "Feature",
  "properties": {
    "iso:country":"US",
    "name:eng_x_preferred":[
        "Bordeaux Village 3"
    ],
    "wof:name":"Bordeaux Village 3",
    "wof:placetype":"neighbourhood",
    "zs:area_m":60606.009826,
    "zs:blockids":[
        121030244121012
    ],
    "zs:housing10":0,
    "zs:label":"Bordeaux Village 3",
    "zs:pop10":0
},
  "geometry": {"coordinates":[-82.666628,27.892589],"type":"Point"}
}