{
  "type": "Feature",
  "properties": {
    "gn:admin1_code":"UT",
    "gn:admin2_code":"11.0",
    "gn:asciiname":"The Oaks at Mutton Hollow",
    "gn:country_code":"US",
    "gn:dem":1440,
    "gn:elevation":"1436.0",
    "gn:feature_class":"P",
    "gn:feature_code":"PPL",
    "gn:name":"The Oaks at Mutton Hollow",
    "gn:population":0,
    "gn:timezone":"America/Denver",
    "iso:country":"US",
    "wof:name":"The Oaks at Mutton Hollow",
    "wof:placetype":"locality"
},
  "geometry": {"coordinates":[-111.91827000000001,41.05967],"type":"Point"}
}