{
  "type": "Feature",
  "properties": {
    "gn:admin1_code":"MN",
    "gn:admin2_code":"47.0",
    "gn:admin3_code":"54088.0",
    "gn:asciiname":"South Hollandale",
    "gn:country_code":"US",
    "gn:dem":362,
    "gn:elevation":"366.0",
    "gn:feature_class":"P",
    "gn:feature_code":"PPL",
    "gn:name":"South Hollandale",
    "gn:population":0,
    "gn:timezone":"America/Chicago",
    "iso:country":"US",
    "wof:name":"South Hollandale",
    "wof:placetype":"locality"
},
  "geometry": {"coordinates":[-93.18965,43.72079],"type":"Point"}
}