{
  "type": "Feature",
  "properties": {
    "gn:admin1_code":"IL",
    "gn:admin2_code":"115",
    "gn:admin3_code":"6769.0",
    "gn:asciiname":"Blackland",
    "gn:country_code":"US",
    "gn:dem":188,
    "gn:elevation":"188.0",
    "gn:feature_class":"P",
    "gn:feature_code":"PPL",
    "gn:name":"Blackland",
    "gn:population":0,
    "gn:timezone":"America/Chicago",
    "iso:country":"US",
    "wof:name":"Blackland",
    "wof:placetype":"locality"
},
  "geometry": {"coordinates":[-89.10396999999998,39.76143],"type":"Point"}
}