{
  "type": "Feature",
  "properties": {
    "gn:admin1_code":"HI",
    "gn:admin2_code":"1.0",
    "gn:asciiname":"Laniakea",
    "gn:country_code":"US",
    "gn:dem":14,
    "gn:elevation":"9.0",
    "gn:feature_class":"P",
    "gn:feature_code":"PPL",
    "gn:name":"Lani\u0101kea",
    "gn:population":0,
    "gn:timezone":"Pacific/Honolulu",
    "iso:country":"US",
    "name:dan_x_preferred":[
        "Laniakea"
    ],
    "name:eng_x_preferred":[
        "Lani\u0101kea"
    ],
    "name:pol_x_preferred":[
        "Laniakea"
    ],
    "wof:name":"Laniakea",
    "wof:placetype":"locality"
},
  "geometry": {"coordinates":[-155.99006,19.63564],"type":"Point"}
}