{
  "type": "Feature",
  "properties": {
    "iso:country":"US",
    "name:eng_x_preferred":[
        "Tannery"
    ],
    "qs:gn_adm0_cc":"US",
    "qs:gn_local":4815286,
    "qs:gn_nam_loc":"Moorefield, Hardy, West Virginia, US",
    "qs:gn_namadm1":"WV",
    "qs:local_max":49,
    "qs:local_sum":49,
    "qs:localhoods":1,
    "qs:name":"Tannery",
    "qs:name_adm0":"United States",
    "qs:name_adm1":"West Virginia",
    "qs:name_adm2":"Hardy",
    "qs:name_local":"Moorefield",
    "qs:photo_max":30,
    "qs:photo_sum":49,
    "qs:placetype":"Suburb",
    "qs:quad_count":8,
    "qs:woe_adm0":23424977,
    "qs:woe_adm1":2347607,
    "qs:woe_adm2":12590494,
    "qs:woe_lau":0,
    "qs:woe_local":2453744,
    "qs:woe_ver":"7.10.0",
    "wof:lang":[
        "eng"
    ],
    "wof:name":"Tannery",
    "wof:placetype":"neighbourhood",
    "wof:population":747,
    "zs:blockids":[
        540319702001036,
        540319702001044,
        540319703002035,
        540319702001045,
        540319703002027,
        540319702001062,
        540319702003036,
        540319703002060,
        540319702001049,
        540319702001074,
        540319702003037,
        540319702003039,
        540319702003031,
        540319702003018,
        540319702001061,
        540319702001068,
        540319702003001,
        540319702001053,
        540319702003085,
        540319702001056,
        540319702001066,
        540319702003035,
        540319702003051,
        540319702003044,
        540319703002034,
        540319702003069,
        540319702001060,
        540319702001055,
        540319703002072
    ],
    "zs:housing10":361,
    "zs:pop10":747
},
  "geometry": {"coordinates":[-78.96709199999999,39.061979],"type":"Point"}
}