{
  "type": "Feature",
  "properties": {
    "gn:admin1_code":"VA",
    "gn:admin2_code":"83",
    "gn:asciiname":"Catawba",
    "gn:country_code":"US",
    "gn:dem":178,
    "gn:elevation":"177.0",
    "gn:feature_class":"P",
    "gn:feature_code":"PPL",
    "gn:name":"Catawba",
    "gn:population":0,
    "gn:timezone":"America/New_York",
    "iso:country":"US",
    "name:ara_x_preferred":[
        "\u0643\u0627\u062a\u0627\u0648\u0628\u0627"
    ],
    "name:ceb_x_preferred":[
        "Catawba"
    ],
    "name:deu_x_preferred":[
        "Catawba"
    ],
    "name:fra_x_preferred":[
        "Catawba"
    ],
    "name:fry_x_preferred":[
        "Catawba"
    ],
    "name:ita_x_preferred":[
        "Catawba"
    ],
    "name:mal_x_preferred":[
        "\u0d15\u0d31\u0d4d\u0d31\u0d4c\u0d2c"
    ],
    "name:nld_x_preferred":[
        "Catawba"
    ],
    "name:pol_x_preferred":[
        "Catawba"
    ],
    "name:rus_x_preferred":[
        "\u041a\u0430\u0442\u043e\u0431\u0430"
    ],
    "name:srp_x_preferred":[
        "\u041a\u0430\u0442\u043e\u0431\u0430"
    ],
    "name:ukr_x_preferred":[
        "\u041a\u0435\u0442\u0443\u0431\u0430"
    ],
    "name:vol_x_preferred":[
        "Catawba"
    ],
    "wof:name":"Catawba",
    "wof:placetype":"locality"
},
  "geometry": {"coordinates":[-78.95029,36.92236],"type":"Point"}
}