{
  "type": "Feature",
  "properties": {
    "gn:admin1_code":"SD",
    "gn:admin2_code":"81.0",
    "gn:admin3_code":"59870.0",
    "gn:asciiname":"Blacktail",
    "gn:country_code":"US",
    "gn:dem":1462,
    "gn:elevation":"1456.0",
    "gn:feature_class":"P",
    "gn:feature_code":"PPL",
    "gn:name":"Blacktail",
    "gn:population":0,
    "gn:timezone":"America/Denver",
    "iso:country":"US",
    "name:eng_x_preferred":[
        "Blacktail"
    ],
    "name:und_x_variant":[
        "Black Tail"
    ],
    "wof:name":"Blacktail",
    "wof:placetype":"locality"
},
  "geometry": {"coordinates":[-103.7602,44.36998],"type":"Point"}
}