{
  "type": "Feature",
  "properties": {
    "gn:elevation":10,
    "iso:country":"US",
    "name:eng_x_preferred":[
        "Beach Bluff"
    ],
    "name:eng_x_variant":[
        "Beach Blf"
    ],
    "qs:gn_adm0_cc":"US",
    "qs:gn_fcode":"PPL",
    "qs:gn_local":4943097,
    "qs:gn_nam_loc":"marblehead",
    "qs:gn_namadm1":"MA",
    "qs:gn_name":"Beach Bluff",
    "qs:local_max":2153,
    "qs:local_sum":3161,
    "qs:localhoods":5,
    "qs:name":"Beach Bluff",
    "qs:name_adm0":"United States",
    "qs:name_adm1":"Massachusetts",
    "qs:name_adm2":"Essex",
    "qs:name_local":"Marblehead",
    "qs:photo_max":81,
    "qs:photo_sum":212,
    "qs:placetype":"Suburb",
    "qs:quad_count":14,
    "qs:woe_adm0":23424977,
    "qs:woe_adm1":2347580,
    "qs:woe_adm2":12588704,
    "qs:woe_funk":"Parented by a neighborhood",
    "qs:woe_lau":0,
    "qs:woe_local":2445485,
    "qs:woe_ver":"7.10.0",
    "wof:lang":[
        "eng"
    ],
    "wof:name":"Beach Bluff",
    "wof:placetype":"neighbourhood",
    "wof:population":2509,
    "zs:blockids":[
        250092031007011,
        250092031006009,
        250092022001012,
        250092022003006,
        250092022003022,
        250092022003024,
        250092022001000,
        250092031005012,
        250092022003018,
        250092031005013,
        250092022001002,
        250092022001008,
        250092022003020,
        250092031006012,
        250092022001010,
        250092022003023,
        250092022003003,
        250092031003008,
        250092022003010,
        250092022003014,
        250092031007014,
        250092031006011,
        250092031006004,
        250092031006010,
        250092022001018,
        250092022001016,
        250092022003025,
        250092022003011,
        250092022003009,
        250092022001011,
        250092022001009,
        250092031007013,
        250092022001017,
        250092031006002,
        250092031006003,
        250092022003015,
        250092022003012,
        250092022003013,
        250092031006005,
        250092022003021,
        250092031006001,
        250092031003014,
        250092031006008,
        250092031003018,
        250092031006000,
        250092022003005,
        250092022003002,
        250092022003001,
        250092031007006,
        250092031007015,
        250092022001006,
        250092022001003,
        250092022001007,
        250092031003013,
        250092022003004,
        250092022003007,
        250092031007008,
        250092022003017,
        250092022001020,
        250092022003016,
        250092022003008,
        250092022003000,
        250092031003017
    ],
    "zs:housing10":954,
    "zs:pop10":2509
},
  "geometry": {"coordinates":[-70.87974,42.478588],"type":"Point"}
}