{
  "type": "Feature",
  "properties": {
    "gn:admin1_code":"GA",
    "gn:admin2_code":"59",
    "gn:asciiname":"Tallassee Estates",
    "gn:country_code":"US",
    "gn:dem":245,
    "gn:elevation":"238.0",
    "gn:feature_class":"P",
    "gn:feature_code":"PPL",
    "gn:name":"Tallassee Estates",
    "gn:population":0,
    "gn:timezone":"America/New_York",
    "iso:country":"US",
    "wof:name":"Tallassee Estates",
    "wof:placetype":"locality"
},
  "geometry": {"coordinates":[-83.47627,33.98761],"type":"Point"}
}