{
  "type": "Feature",
  "properties": {
    "iso:country":"US",
    "name:eng_x_preferred":[
        "Edgewood Acres"
    ],
    "wof:name":"Edgewood Acres",
    "wof:placetype":"neighbourhood",
    "zs:area_m":1580393.75115,
    "zs:blockids":[
        470090104002120,
        470090104002095,
        470090104002068,
        470090104002098,
        470090104002066,
        470090104002146,
        470090104002097,
        470090104002096,
        470090109001008
    ],
    "zs:housing10":2,
    "zs:label":"Edgewood Acres",
    "zs:pop10":0
},
  "geometry": {"coordinates":[-83.933094,35.802474],"type":"Point"}
}