{
  "type": "Feature",
  "properties": {
    "gn:admin1_code":"CA",
    "gn:admin2_code":"51",
    "gn:asciiname":"Lundy",
    "gn:country_code":"US",
    "gn:dem":2398,
    "gn:elevation":"2395.0",
    "gn:feature_class":"P",
    "gn:feature_code":"PPL",
    "gn:name":"Lundy",
    "gn:population":0,
    "gn:timezone":"America/Los_Angeles",
    "iso:country":"US",
    "name:azb_x_preferred":[
        "\u0644\u0627\u0646\u062f\u06cc"
    ],
    "name:eng_x_preferred":[
        "Lundy"
    ],
    "name:fas_x_preferred":[
        "\u0644\u0627\u0646\u062f\u06cc"
    ],
    "name:ita_x_preferred":[
        "Lundy"
    ],
    "name:spa_x_preferred":[
        "Lundy"
    ],
    "name:und_x_variant":[
        "Mill Creek"
    ],
    "wof:name":"Lundy",
    "wof:placetype":"locality"
},
  "geometry": {"coordinates":[-119.24154,38.02742],"type":"Point"}
}