{
  "type": "Feature",
  "properties": {
    "gn:admin1_code":"AR",
    "gn:admin2_code":"129.0",
    "gn:admin3_code":"93351.0",
    "gn:asciiname":"Booster",
    "gn:country_code":"US",
    "gn:dem":511,
    "gn:elevation":"510.0",
    "gn:feature_class":"P",
    "gn:feature_code":"PPL",
    "gn:name":"Booster",
    "gn:population":0,
    "gn:timezone":"America/Chicago",
    "iso:country":"US",
    "name:deu_x_preferred":[
        "Booster"
    ],
    "name:fra_x_preferred":[
        "Booster"
    ],
    "name:ita_x_preferred":[
        "Booster"
    ],
    "name:jpn_x_preferred":[
        "\u30d6\u30fc\u30b9\u30bf\u30fc"
    ],
    "name:kor_x_preferred":[
        "\ubd80\uc2a4\ud130"
    ],
    "name:ltz_x_preferred":[
        "Booster"
    ],
    "name:rus_x_preferred":[
        "\u0411\u0443\u0441\u0442\u0435\u0440"
    ],
    "wof:name":"Booster",
    "wof:placetype":"locality"
},
  "geometry": {"coordinates":[-92.66016,35.74952000000001],"type":"Point"}
}