{
  "type": "Feature",
  "properties": {
    "gn:admin1_code":"KS",
    "gn:admin2_code":"37.0",
    "gn:admin3_code":"40575.0",
    "gn:asciiname":"Gross",
    "gn:country_code":"US",
    "gn:dem":274,
    "gn:elevation":"269.0",
    "gn:feature_class":"P",
    "gn:feature_code":"PPL",
    "gn:name":"Gross",
    "gn:population":0,
    "gn:timezone":"America/Chicago",
    "iso:country":"US",
    "name:azb_x_preferred":[
        "\u0642\u0631\u0627\u0633"
    ],
    "name:fas_x_preferred":[
        "\u06af\u0631\u0627\u0633"
    ],
    "name:zho_x_preferred":[
        "\u683c\u7f85\u65af"
    ],
    "wof:name":"Gross",
    "wof:placetype":"locality"
},
  "geometry": {"coordinates":[-94.64968,37.60088],"type":"Point"}
}