{
  "type": "Feature",
  "properties": {
    "gn:elevation":139,
    "iso:country":"US",
    "name:ceb_x_preferred":[
        "Red Lion"
    ],
    "name:deu_x_preferred":[
        "Red Lion"
    ],
    "name:eng_x_preferred":[
        "Red Lion"
    ],
    "name:vol_x_preferred":[
        "Red Lion"
    ],
    "qs:gn_adm0_cc":"US",
    "qs:gn_fcode":"PPL",
    "qs:gn_local":4557703,
    "qs:gn_nam_loc":"East Marlborough, Chester, Pennsylvania, US",
    "qs:gn_namadm1":"PA",
    "qs:gn_name":"Red Lion",
    "qs:local_max":28909,
    "qs:local_sum":34837,
    "qs:localhoods":3,
    "qs:name":"Red Lion",
    "qs:name_adm0":"United States",
    "qs:name_adm1":"Pennsylvania",
    "qs:name_adm2":"Chester",
    "qs:name_local":"East Marlborough",
    "qs:photo_max":1332,
    "qs:photo_sum":5865,
    "qs:placetype":"Suburb",
    "qs:quad_count":31,
    "qs:woe_adm0":23424977,
    "qs:woe_adm1":2347597,
    "qs:woe_adm2":12589742,
    "qs:woe_lau":0,
    "qs:woe_local":28745610,
    "qs:woe_ver":"7.10.0",
    "wd:wordcount":298,
    "wof:lang":[
        "eng"
    ],
    "wof:name":"Red Lion",
    "wof:placetype":"neighbourhood",
    "wof:population":17,
    "zs:blockids":[
        420293035011012
    ],
    "zs:housing10":5,
    "zs:pop10":17
},
  "geometry": {"coordinates":[-75.678428,39.872906],"type":"Point"}
}