{
  "type": "Feature",
  "properties": {
    "gn:admin1_code":"MO",
    "gn:admin2_code":"55.0",
    "gn:admin3_code":"16930.0",
    "gn:asciiname":"Berryman",
    "gn:country_code":"US",
    "gn:dem":237,
    "gn:elevation":"232.0",
    "gn:feature_class":"P",
    "gn:feature_code":"PPL",
    "gn:name":"Berryman",
    "gn:population":0,
    "gn:timezone":"America/Chicago",
    "iso:country":"US",
    "name:ara_x_preferred":[
        "\u0628\u064a\u0631\u064a\u0645\u0627\u0646"
    ],
    "name:ron_x_preferred":[
        "Berryman"
    ],
    "name:vol_x_preferred":[
        "Berryman"
    ],
    "wof:name":"Berryman",
    "wof:placetype":"locality"
},
  "geometry": {"coordinates":[-91.09644,37.91882],"type":"Point"}
}