{
  "type": "Feature",
  "properties": {
    "gn:admin1_code":"MA",
    "gn:admin2_code":"9.0",
    "gn:admin3_code":"37490.0",
    "gn:asciiname":"Lynn Community Based Outpatient Clinic (CBOC)",
    "gn:country_code":"US",
    "gn:dem":17,
    "gn:feature_class":"P",
    "gn:feature_code":"PPL",
    "gn:name":"Lynn Community Based Outpatient Clinic (CBOC)",
    "gn:population":0,
    "gn:timezone":"America/New_York",
    "iso:country":"US",
    "wof:name":"Lynn Community Based Outpatient Clinic (CBOC)",
    "wof:placetype":"locality"
},
  "geometry": {"coordinates":[-70.96004000000001,42.4705],"type":"Point"}
}