{
  "type": "Feature",
  "properties": {
    "iso:country":"US",
    "name:eng_x_preferred":[
        "North Gorham"
    ],
    "name:eng_x_variant":[
        "N Gorham"
    ],
    "name:und_x_variant":[
        "Great Falls"
    ],
    "qs:gn_adm0_cc":"US",
    "qs:gn_fcode":"PPL",
    "qs:gn_local":4965481,
    "qs:gn_nam_loc":"gorham",
    "qs:gn_namadm1":"ME",
    "qs:gn_name":"North Gorham",
    "qs:local_max":54,
    "qs:local_sum":130,
    "qs:localhoods":6,
    "qs:name":"North Gorham",
    "qs:name_adm0":"United States",
    "qs:name_adm1":"Maine",
    "qs:name_adm2":"Cumberland",
    "qs:name_local":"Gorham",
    "qs:photo_max":18,
    "qs:photo_sum":24,
    "qs:placetype":"Suburb",
    "qs:quad_count":4,
    "qs:woe_adm0":23424977,
    "qs:woe_adm1":2347578,
    "qs:woe_adm2":12588662,
    "qs:woe_lau":0,
    "qs:woe_local":2412335,
    "qs:woe_ver":"7.10.0",
    "wof:lang":[
        "eng"
    ],
    "wof:name":"North Gorham",
    "wof:placetype":"neighbourhood",
    "wof:population":1466,
    "zs:blockids":[
        230050041002007,
        230050041002005,
        230050041003002,
        230050170021036,
        230050041002003,
        230050041002012,
        230050041002009,
        230050048016038,
        230050048033006,
        230050041002056,
        230050041002011,
        230050041003001,
        230050048016035,
        230050041002002,
        230050041002001,
        230050048033007,
        230050041002013,
        230050170021042,
        230050048016036,
        230050041002004,
        230050041003005,
        230050170021035,
        230050041003003,
        230050041002006,
        230050170021041,
        230050048033004,
        230050170021038,
        230050170021039,
        230050041003008,
        230050170021028,
        230050048033005,
        230050170021040,
        230050041002008,
        230050048033010,
        230050041003004,
        230050041002010,
        230050170021043,
        230050048033009,
        230050041003000,
        230050170021037
    ],
    "zs:housing10":595,
    "zs:pop10":1466
},
  "geometry": {"coordinates":[-70.45921300000001,43.797365],"type":"Point"}
}