{
  "type": "Feature",
  "properties": {
    "gn:admin1_code":"MD",
    "gn:admin2_code":"31.0",
    "gn:asciiname":"Brooke Grove",
    "gn:country_code":"US",
    "gn:dem":177,
    "gn:elevation":"177.0",
    "gn:feature_class":"P",
    "gn:feature_code":"PPL",
    "gn:name":"Brooke Grove",
    "gn:population":0,
    "gn:timezone":"America/New_York",
    "iso:country":"US",
    "wof:name":"Brooke Grove",
    "wof:placetype":"locality"
},
  "geometry": {"coordinates":[-77.14081,39.19955],"type":"Point"}
}