{
  "type": "Feature",
  "properties": {
    "gn:elevation":65,
    "iso:country":"US",
    "name:eng_x_preferred":[
        "Floydville"
    ],
    "qs:gn_adm0_cc":"US",
    "qs:gn_fcode":"PPL",
    "qs:gn_local":4833343,
    "qs:gn_nam_loc":"east granby",
    "qs:gn_namadm1":"CT",
    "qs:gn_name":"Floydville",
    "qs:local_max":36,
    "qs:local_sum":36,
    "qs:localhoods":1,
    "qs:name":"Floydville",
    "qs:name_adm0":"United States",
    "qs:name_adm1":"Connecticut",
    "qs:name_adm2":"Hartford",
    "qs:name_local":"East Granby",
    "qs:photo_max":13,
    "qs:photo_sum":36,
    "qs:placetype":"Suburb",
    "qs:quad_count":4,
    "qs:woe_adm0":23424977,
    "qs:woe_adm1":2347565,
    "qs:woe_adm2":12587792,
    "qs:woe_lau":0,
    "qs:woe_local":2395633,
    "qs:woe_ver":"7.10.0",
    "wof:lang":[
        "eng"
    ],
    "wof:name":"Floydville",
    "wof:placetype":"neighbourhood",
    "wof:population":2720,
    "zs:blockids":[
        90034701002008,
        90034701002014,
        90034701002027,
        90034701002005,
        90034681023006,
        90034701002017,
        90034701002021,
        90034681023018,
        90034681023022,
        90034681023015,
        90034701001022,
        90034681023000,
        90034701002010,
        90034681023024,
        90034681022013,
        90034681023003,
        90034701002033,
        90034681023007,
        90034701002040,
        90034662012004,
        90034701002006,
        90034701002037,
        90034701004019,
        90034681023017,
        90034701002012,
        90034701002011,
        90034681023012,
        90034701002025,
        90034701001010,
        90034701001011,
        90034681023020,
        90034681023023,
        90034681023016,
        90034701002039,
        90034701002032,
        90034701004027,
        90034701002016,
        90034701002019,
        90034701004020,
        90034701002036,
        90034701002004,
        90034681023021,
        90034701002029,
        90034681023019,
        90034701002038,
        90034701002003,
        90034701001024,
        90034701002000,
        90034681023014,
        90034701002009,
        90034681023002,
        90034701002018,
        90034662012003,
        90034701002041,
        90034662012005,
        90034681022002,
        90034701002001,
        90034701002023,
        90034701002002,
        90034681022001,
        90034701002022,
        90034701001023,
        90034701004017,
        90034701002035,
        90034701004018,
        90034701002024,
        90034701002007,
        90034701002013,
        90034681023011,
        90034701004021,
        90034662012002,
        90034662012001,
        90034701002031,
        90034662012007,
        90034701002015,
        90034701002020,
        90034701002026,
        90034681022012
    ],
    "zs:housing10":1124,
    "zs:pop10":2720
},
  "geometry": {"coordinates":[-72.779083,41.934863],"type":"Point"}
}