{
  "type": "Feature",
  "properties": {
    "gn:elevation":144,
    "iso:country":"US",
    "name:ast_x_preferred":[
        "Air City"
    ],
    "name:eng_x_preferred":[
        "Air City"
    ],
    "name:eng_x_variant":[
        "Air Cty"
    ],
    "name:ind_x_preferred":[
        "Air City"
    ],
    "name:ita_x_preferred":[
        "Air City"
    ],
    "name:jpn_x_preferred":[
        "\u30a8\u30a2\u30fb\u30b7\u30c6\u30a3"
    ],
    "name:kor_x_preferred":[
        "\uc5d0\uc5b4\uc2dc\ud2f0"
    ],
    "name:msa_x_preferred":[
        "Air City"
    ],
    "name:nld_x_preferred":[
        "Air City"
    ],
    "name:por_x_preferred":[
        "Air City"
    ],
    "name:tgl_x_preferred":[
        "Air City"
    ],
    "name:zho_x_preferred":[
        "\u7a7a\u6e2f\u57ce\u5e02"
    ],
    "qs:gn_adm0_cc":"US",
    "qs:gn_fcode":"PPL",
    "qs:gn_local":5134295,
    "qs:gn_nam_loc":"Rome, Oneida, New York, US",
    "qs:gn_namadm1":"NY",
    "qs:gn_name":"Air City",
    "qs:local_max":224,
    "qs:local_sum":635,
    "qs:localhoods":5,
    "qs:name":"Air City",
    "qs:name_adm0":"United States",
    "qs:name_adm1":"New York",
    "qs:name_adm2":"Oneida",
    "qs:name_local":"Rome",
    "qs:photo_max":201,
    "qs:photo_sum":207,
    "qs:placetype":"Suburb",
    "qs:quad_count":6,
    "qs:woe_adm0":23424977,
    "qs:woe_adm1":2347591,
    "qs:woe_adm2":12589344,
    "qs:woe_lau":0,
    "qs:woe_local":2484260,
    "qs:woe_ver":"7.10.0",
    "wd:wordcount":759,
    "wof:lang":[
        "eng"
    ],
    "wof:name":"Air City",
    "wof:placetype":"neighbourhood"
},
  "geometry": {"coordinates":[-75.414244,43.212088],"type":"Point"}
}