{
  "type": "Feature",
  "properties": {
    "gn:country":"US",
    "gn:fcode":"PPL",
    "gn:population":0,
    "iso:country":"US",
    "name:eng_x_preferred":[
        "Concan"
    ],
    "name:fas_x_preferred":[
        "\u06a9\u0627\u0646\u06a9\u0646\u060c \u062a\u06af\u0632\u0627\u0633"
    ],
    "name:fas_x_variant":[
        "\u06a9\u0627\u0646\u06a9\u0646"
    ],
    "name:fra_x_preferred":[
        "Concan"
    ],
    "name:und_x_variant":[
        "Con Can"
    ],
    "qs_pg:aaroncc":"US",
    "qs_pg:gn_country":"US",
    "qs_pg:gn_fcode":"PPL",
    "qs_pg:gn_pop":0,
    "qs_pg:name":"Concan",
    "qs_pg:name_adm0":"United States",
    "qs_pg:name_adm1":"Texas",
    "qs_pg:photos":328,
    "qs_pg:photos_1k":66,
    "qs_pg:photos_9k":1,
    "qs_pg:photos_9r":5,
    "qs_pg:photos_all":328,
    "qs_pg:photos_sr":5,
    "qs_pg:pop_sr":5,
    "qs_pg:qs_pg_placetype":"locality",
    "qs_pg:qs_pg_placetype_gp":"Town",
    "qs_pg:woe_adm0":23424977,
    "woe:adm0_id":23424977,
    "woe:name_adm0":"United States",
    "woe:name_adm1":"Texas",
    "woe:placetype":"Town",
    "wof:name":"Concan",
    "wof:placetype":"locality"
},
  "geometry": {"coordinates":[-99.71254999999999,29.49523],"type":"Point"}
}