{
  "type": "Feature",
  "properties": {
    "gn:admin1_code":"SC",
    "gn:admin2_code":"89.0",
    "gn:asciiname":"Baker Crossroads",
    "gn:country_code":"US",
    "gn:dem":28,
    "gn:elevation":"26.0",
    "gn:feature_class":"P",
    "gn:feature_code":"PPL",
    "gn:name":"Baker Crossroads",
    "gn:population":0,
    "gn:timezone":"America/New_York",
    "iso:country":"US",
    "wof:name":"Baker Crossroads",
    "wof:placetype":"locality"
},
  "geometry": {"coordinates":[-79.85785,33.80877],"type":"Point"}
}