{
  "type": "Feature",
  "properties": {
    "gn:admin1_code":"NC",
    "gn:admin2_code":"69.0",
    "gn:admin3_code":"91438.0",
    "gn:asciiname":"Rocky Ford",
    "gn:country_code":"US",
    "gn:dem":119,
    "gn:elevation":"121.0",
    "gn:feature_class":"P",
    "gn:feature_code":"PPL",
    "gn:name":"Rocky Ford",
    "gn:population":0,
    "gn:timezone":"America/New_York",
    "iso:country":"US",
    "wof:name":"Rocky Ford",
    "wof:placetype":"locality"
},
  "geometry": {"coordinates":[-78.34333000000002,36.19987],"type":"Point"}
}