{
  "type": "Feature",
  "properties": {
    "gn:admin1_code":"OH",
    "gn:admin2_code":"85.0",
    "gn:admin3_code":"61896.0",
    "gn:asciiname":"Camp Roosevelt",
    "gn:country_code":"US",
    "gn:dem":189,
    "gn:elevation":"182.0",
    "gn:feature_class":"P",
    "gn:feature_code":"PPL",
    "gn:name":"Camp Roosevelt",
    "gn:population":0,
    "gn:timezone":"America/New_York",
    "iso:country":"US",
    "name:eng_x_preferred":[
        "Camp Roosevelt"
    ],
    "name:und_x_variant":[
        "Perry Park"
    ],
    "wof:name":"Camp Roosevelt",
    "wof:placetype":"locality"
},
  "geometry": {"coordinates":[-81.16731999999998,41.79144],"type":"Point"}
}