{
  "type": "Feature",
  "properties": {
    "gn:admin1_code":"MI",
    "gn:admin2_code":"109.0",
    "gn:admin3_code":"53040.0",
    "gn:asciiname":"Carbondale",
    "gn:country_code":"US",
    "gn:dem":199,
    "gn:elevation":"202.0",
    "gn:feature_class":"P",
    "gn:feature_code":"PPL",
    "gn:name":"Carbondale",
    "gn:population":0,
    "gn:timezone":"America/Menominee",
    "iso:country":"US",
    "name:ell_x_preferred":[
        "\u039a\u03ac\u03c1\u03bc\u03c0\u03bf\u03bd\u03c4\u03b5\u03ca\u03bb"
    ],
    "name:hin_x_preferred":[
        "\u0915\u093e\u0930\u094d\u092c\u0928\u0921\u0947\u0932"
    ],
    "name:ind_x_preferred":[
        "Carbondale"
    ],
    "wof:name":"Carbondale",
    "wof:placetype":"locality"
},
  "geometry": {"coordinates":[-87.61593999999999,45.27831],"type":"Point"}
}