{
  "type": "Feature",
  "properties": {
    "gn:admin1_code":"MI",
    "gn:admin2_code":"109.0",
    "gn:admin3_code":"53040.0",
    "gn:asciiname":"Carbondale",
    "gn:country_code":"US",
    "gn:dem":199,
    "gn:elevation":"202.0",
    "gn:feature_class":"P",
    "gn:feature_code":"PPL",
    "gn:name":"Carbondale",
    "gn:population":0,
    "gn:timezone":"America/Menominee",
    "iso:country":"US",
    "wof:name":"Carbondale",
    "wof:placetype":"locality"
},
  "geometry": {"coordinates":[-87.61594000000002,45.27831],"type":"Point"}
}