{
  "type": "Feature",
  "properties": {
    "gn:country":"US",
    "gn:fcode":"PPL",
    "gn:population":0,
    "iso:country":"US",
    "name:azb_x_preferred":[
        "\u0633\u06cc\u0644\u0648\u0631 \u0644\u0626\u06cc\u06a9"
    ],
    "name:deu_x_preferred":[
        "Silver Lake"
    ],
    "name:eng_x_preferred":[
        "Silver Lake"
    ],
    "name:fra_x_preferred":[
        "Silver Lake"
    ],
    "name:hun_x_preferred":[
        "Silver Lake"
    ],
    "name:nld_x_preferred":[
        "Silver Lake"
    ],
    "qs_pg:aaroncc":"US",
    "qs_pg:gn_country":"US",
    "qs_pg:gn_fcode":"PPL",
    "qs_pg:gn_pop":0,
    "qs_pg:name":"Silverlake",
    "qs_pg:name_adm0":"United States",
    "qs_pg:name_adm1":"Washington",
    "qs_pg:photos":524,
    "qs_pg:photos_1k":106,
    "qs_pg:photos_9k":2,
    "qs_pg:photos_9r":5,
    "qs_pg:photos_all":524,
    "qs_pg:photos_sr":7,
    "qs_pg:pop_sr":5,
    "qs_pg:qs_pg_placetype":"locality",
    "qs_pg:qs_pg_placetype_gp":"Town",
    "qs_pg:woe_adm0":23424977,
    "woe:adm0_id":23424977,
    "woe:name_adm0":"United States",
    "woe:name_adm1":"Washington",
    "woe:placetype":"Town",
    "wof:name":"Silverlake",
    "wof:placetype":"locality"
},
  "geometry": {"coordinates":[-122.81067,46.29733],"type":"Point"}
}