{
  "type": "Feature",
  "properties": {
    "iso:country":"US",
    "name:eng_x_preferred":[
        "Holders"
    ],
    "wof:name":"Holders",
    "wof:placetype":"neighbourhood",
    "wof:population":5,
    "zs:area_m":602828.021518,
    "zs:blockids":[
        131570102002084,
        131570107021071,
        131570102002077
    ],
    "zs:housing10":3,
    "zs:label":"Holders",
    "zs:pop10":5
},
  "geometry": {"coordinates":[-83.63878800000001,34.156175],"type":"Point"}
}