{
  "type": "Feature",
  "properties": {
    "gn:admin1_code":"MS",
    "gn:admin2_code":"163.0",
    "gn:asciiname":"Evans",
    "gn:country_code":"US",
    "gn:dem":99,
    "gn:elevation":"98.0",
    "gn:feature_class":"P",
    "gn:feature_code":"PPL",
    "gn:name":"Evans",
    "gn:population":0,
    "gn:timezone":"America/Chicago",
    "iso:country":"US",
    "name:bel_x_preferred":[
        "\u042d\u0432\u0430\u043d\u0441"
    ],
    "name:bre_x_preferred":[
        "Evans"
    ],
    "name:ceb_x_preferred":[
        "Evans"
    ],
    "name:ces_x_preferred":[
        "Evans"
    ],
    "name:deu_x_preferred":[
        "Evans"
    ],
    "name:fin_x_preferred":[
        "Evans"
    ],
    "name:fra_x_preferred":[
        "Evans"
    ],
    "name:heb_x_preferred":[
        "\u05d0\u05d5\u05d5\u05e0\u05e1"
    ],
    "name:ita_x_preferred":[
        "Evans"
    ],
    "name:jpn_x_preferred":[
        "\u30a8\u30f4\u30a1\u30f3\u30ba"
    ],
    "name:kor_x_preferred":[
        "\uc5d0\ubc88\uc2a4"
    ],
    "name:lav_x_preferred":[
        "Evanss"
    ],
    "name:nld_x_preferred":[
        "Evans"
    ],
    "name:pol_x_preferred":[
        "Evans"
    ],
    "name:por_x_preferred":[
        "Evans"
    ],
    "name:slv_x_preferred":[
        "Evans"
    ],
    "name:srp_x_preferred":[
        "\u0415\u0432\u0430\u043d\u0441"
    ],
    "name:swe_x_preferred":[
        "Evans"
    ],
    "name:vie_x_preferred":[
        "Evans"
    ],
    "name:vol_x_preferred":[
        "Evans"
    ],
    "wof:name":"Evans",
    "wof:placetype":"locality"
},
  "geometry": {"coordinates":[-90.17480999999999,32.85319],"type":"Point"}
}