{
  "type": "Feature",
  "properties": {
    "gn:admin1_code":"MS",
    "gn:admin2_code":"129",
    "gn:asciiname":"Zion Hill",
    "gn:country_code":"US",
    "gn:dem":143,
    "gn:elevation":"141.0",
    "gn:feature_class":"P",
    "gn:feature_code":"PPL",
    "gn:name":"Zion Hill",
    "gn:population":0,
    "gn:timezone":"America/Chicago",
    "iso:country":"US",
    "wof:name":"Zion Hill",
    "wof:placetype":"locality"
},
  "geometry": {"coordinates":[-89.56674,31.83794],"type":"Point"}
}