{
  "type": "Feature",
  "properties": {
    "gn:country":"US",
    "gn:fcode":"PPL",
    "gn:population":0,
    "iso:country":"US",
    "name:eng_x_preferred":[
        "Villa Grande"
    ],
    "name:fra_x_preferred":[
        "Villa Grande"
    ],
    "name:tur_x_preferred":[
        "Villa Grande"
    ],
    "name:und_x_variant":[
        "Grandville"
    ],
    "name:zho_x_preferred":[
        "\u7dad\u62c9\u683c\u862d\u5fb7"
    ],
    "qs_pg:aaroncc":"US",
    "qs_pg:gn_country":"US",
    "qs_pg:gn_fcode":"PPL",
    "qs_pg:gn_pop":0,
    "qs_pg:name":"Villa Grande",
    "qs_pg:name_adm0":"United States",
    "qs_pg:name_adm1":"California",
    "qs_pg:photos":211,
    "qs_pg:photos_1k":43,
    "qs_pg:photos_9k":1,
    "qs_pg:photos_9r":4,
    "qs_pg:photos_all":211,
    "qs_pg:photos_sr":4,
    "qs_pg:pop_sr":0,
    "qs_pg:qs_pg_placetype":"locality",
    "qs_pg:qs_pg_placetype_gp":"Town",
    "qs_pg:woe_adm0":23424977,
    "woe:adm0_id":23424977,
    "woe:name_adm0":"United States",
    "woe:name_adm1":"California",
    "woe:placetype":"Town",
    "wof:name":"Villa Grande",
    "wof:placetype":"locality"
},
  "geometry": {"coordinates":[-123.02556,38.47297],"type":"Point"}
}