{
  "type": "Feature",
  "properties": {
    "gn:gn_country":"US",
    "gn:gn_fcode":"PPLX",
    "gn:gn_pop":0,
    "iso:country":"US",
    "name:ceb_x_preferred":[
        "Cottonwood"
    ],
    "name:deu_x_preferred":[
        "Cottonwood"
    ],
    "name:ewe_x_preferred":[
        "Cottonwood"
    ],
    "name:fra_x_preferred":[
        "Cottonwood"
    ],
    "name:isl_x_preferred":[
        "Cottonwood"
    ],
    "name:ita_x_preferred":[
        "Cottonwood"
    ],
    "name:nld_x_preferred":[
        "Cottonwood"
    ],
    "name:pol_x_preferred":[
        "Cottonwood"
    ],
    "name:por_x_preferred":[
        "Cottonwood"
    ],
    "name:rus_x_preferred":[
        "\u041a\u043e\u0442\u0442\u043e\u043d\u0432\u0443\u0434"
    ],
    "name:spa_x_preferred":[
        "Cottonwood"
    ],
    "name:srp_x_preferred":[
        "\u041a\u043e\u0442\u043e\u043d\u0432\u0443\u0434"
    ],
    "name:swe_x_preferred":[
        "Cottonwood"
    ],
    "name:ukr_x_preferred":[
        "\u041a\u043e\u0442\u0442\u043e\u043d\u0432\u0443\u0434"
    ],
    "name:vol_x_preferred":[
        "Cottonwood"
    ],
    "qs_pg:aaroncc":"US",
    "qs_pg:gn_country":"US",
    "qs_pg:gn_fcode":"PPLX",
    "qs_pg:gn_pop":0,
    "qs_pg:name":"Cottonwood",
    "qs_pg:name_adm0":"United States",
    "qs_pg:name_adm1":"Alabama",
    "qs_pg:photos":4,
    "qs_pg:photos_1k":1,
    "qs_pg:photos_9k":1,
    "qs_pg:photos_9r":1,
    "qs_pg:photos_all":4,
    "qs_pg:photos_sr":1,
    "qs_pg:pop_sr":0,
    "qs_pg:qs_pg_placetype":"neighbourhood",
    "qs_pg:qs_pg_placetype_gp":"Suburb",
    "qs_pg:woe_adm0":23424977,
    "woe:adm0_id":23424977,
    "woe:name_adm0":"United States",
    "woe:name_adm1":"Alabama",
    "woe:placetype":"Suburb",
    "wof:name":"Cottonwood",
    "wof:placetype":"neighbourhood"
},
  "geometry": {"coordinates":[-86.92639,34.78537],"type":"Point"}
}