{
  "type": "Feature",
  "properties": {
    "gn:admin1_code":"MD",
    "gn:admin2_code":"27.0",
    "gn:asciiname":"Sylvan Hill",
    "gn:country_code":"US",
    "gn:dem":130,
    "gn:elevation":"138.0",
    "gn:feature_class":"P",
    "gn:feature_code":"PPL",
    "gn:name":"Sylvan Hill",
    "gn:population":0,
    "gn:timezone":"America/New_York",
    "iso:country":"US",
    "wof:name":"Sylvan Hill",
    "wof:placetype":"locality"
},
  "geometry": {"coordinates":[-76.79386,39.29011],"type":"Point"}
}