{
  "type": "Feature",
  "properties": {
    "gn:admin1_code":"GA",
    "gn:admin2_code":"199",
    "gn:asciiname":"Routons Crossroads",
    "gn:country_code":"US",
    "gn:dem":281,
    "gn:elevation":"281.0",
    "gn:feature_class":"P",
    "gn:feature_code":"PPL",
    "gn:name":"Routons Crossroads",
    "gn:population":0,
    "gn:timezone":"America/New_York",
    "iso:country":"US",
    "wof:name":"Routons Crossroads",
    "wof:placetype":"locality"
},
  "geometry": {"coordinates":[-84.63243,32.89346],"type":"Point"}
}