{
  "type": "Feature",
  "properties": {
    "gn:admin1_code":"NV",
    "gn:admin2_code":"7.0",
    "gn:asciiname":"Brennen Ranch",
    "gn:country_code":"US",
    "gn:dem":1814,
    "gn:elevation":"1811.0",
    "gn:feature_class":"P",
    "gn:feature_code":"PPL",
    "gn:name":"Brennen Ranch",
    "gn:population":0,
    "gn:timezone":"America/Los_Angeles",
    "iso:country":"US",
    "name:eng_x_preferred":[
        "Brennen Ranch"
    ],
    "name:und_x_variant":[
        "Blaine"
    ],
    "wof:name":"Brennen Ranch",
    "wof:placetype":"locality"
},
  "geometry": {"coordinates":[-115.54812,40.66798],"type":"Point"}
}