{
  "type": "Feature",
  "properties": {
    "gn:admin1_code":"NY",
    "gn:admin2_code":"55.0",
    "gn:admin3_code":"46558.0",
    "gn:asciiname":"Ford Corner",
    "gn:country_code":"US",
    "gn:dem":188,
    "gn:elevation":"187.0",
    "gn:feature_class":"P",
    "gn:feature_code":"PPL",
    "gn:name":"Ford Corner",
    "gn:population":0,
    "gn:timezone":"America/New_York",
    "iso:country":"US",
    "wof:name":"Ford Corner",
    "wof:placetype":"locality"
},
  "geometry": {"coordinates":[-77.52722,42.97534],"type":"Point"}
}