{
  "type": "Feature",
  "properties": {
    "gn:admin1_code":"WI",
    "gn:admin2_code":"29.0",
    "gn:admin3_code":"43925.0",
    "gn:asciiname":"Northport",
    "gn:country_code":"US",
    "gn:dem":190,
    "gn:elevation":"181.0",
    "gn:feature_class":"P",
    "gn:feature_code":"PPL",
    "gn:name":"Northport",
    "gn:population":0,
    "gn:timezone":"America/Chicago",
    "iso:country":"US",
    "name:fas_x_preferred":[
        "\u0646\u0648\u0631\u062a \u067e\u0648\u0631\u062a"
    ],
    "name:vol_x_preferred":[
        "Northport"
    ],
    "wof:name":"Northport",
    "wof:placetype":"locality"
},
  "geometry": {"coordinates":[-86.98012,45.29193],"type":"Point"}
}