{
  "type": "Feature",
  "properties": {
    "gn:admin1_code":"VA",
    "gn:admin2_code":"95",
    "gn:asciiname":"Williamsburg West",
    "gn:country_code":"US",
    "gn:dem":24,
    "gn:elevation":"24.0",
    "gn:feature_class":"P",
    "gn:feature_code":"PPL",
    "gn:name":"Williamsburg West",
    "gn:population":0,
    "gn:timezone":"America/New_York",
    "iso:country":"US",
    "wof:name":"Williamsburg West",
    "wof:placetype":"locality"
},
  "geometry": {"coordinates":[-76.75468000000002,37.29987],"type":"Point"}
}