{
  "type": "Feature",
  "properties": {
    "gn:admin1_code":"CO",
    "gn:admin2_code":"45.0",
    "gn:asciiname":"Kiggin",
    "gn:country_code":"US",
    "gn:dem":1879,
    "gn:elevation":"1867.0",
    "gn:feature_class":"P",
    "gn:feature_code":"PPL",
    "gn:name":"Kiggin",
    "gn:population":0,
    "gn:timezone":"America/Denver",
    "iso:country":"US",
    "wof:name":"Kiggin",
    "wof:placetype":"locality"
},
  "geometry": {"coordinates":[-107.23950000000001,39.42637],"type":"Point"}
}