{
  "type": "Feature",
  "properties": {
    "gn:admin1_code":"UT",
    "gn:admin2_code":"35.0",
    "gn:asciiname":"Park Ridge Estates",
    "gn:country_code":"US",
    "gn:dem":1396,
    "gn:elevation":"1397.0",
    "gn:feature_class":"P",
    "gn:feature_code":"PPL",
    "gn:name":"Park Ridge Estates",
    "gn:population":0,
    "gn:timezone":"America/Denver",
    "iso:country":"US",
    "wof:name":"Park Ridge Estates",
    "wof:placetype":"locality"
},
  "geometry": {"coordinates":[-111.83466,40.61967],"type":"Point"}
}