{
  "type": "Feature",
  "properties": {
    "gn:admin1_code":"MD",
    "gn:admin2_code":"25.0",
    "gn:asciiname":"Shawsville Acres",
    "gn:country_code":"US",
    "gn:dem":196,
    "gn:elevation":"201.0",
    "gn:feature_class":"P",
    "gn:feature_code":"PPL",
    "gn:name":"Shawsville Acres",
    "gn:population":0,
    "gn:timezone":"America/New_York",
    "iso:country":"US",
    "wof:name":"Shawsville Acres",
    "wof:placetype":"locality"
},
  "geometry": {"coordinates":[-76.55190999999998,39.63149],"type":"Point"}
}