{
  "type": "Feature",
  "properties": {
    "gn:admin1_code":"LA",
    "gn:admin2_code":"13.0",
    "gn:asciiname":"Woodardville",
    "gn:country_code":"US",
    "gn:dem":77,
    "gn:elevation":"73.0",
    "gn:feature_class":"P",
    "gn:feature_code":"PPL",
    "gn:name":"Woodardville",
    "gn:population":0,
    "gn:timezone":"America/Chicago",
    "iso:country":"US",
    "wof:name":"Woodardville",
    "wof:placetype":"locality"
},
  "geometry": {"coordinates":[-93.28017,32.25988],"type":"Point"}
}