{
  "type": "Feature",
  "properties": {
    "gn:admin1_code":"OH",
    "gn:admin2_code":"51.0",
    "gn:admin3_code":"22442.0",
    "gn:asciiname":"Dover Glen",
    "gn:country_code":"US",
    "gn:dem":239,
    "gn:elevation":"239.0",
    "gn:feature_class":"P",
    "gn:feature_code":"PPL",
    "gn:name":"Dover Glen",
    "gn:population":0,
    "gn:timezone":"America/New_York",
    "iso:country":"US",
    "wof:name":"Dover Glen",
    "wof:placetype":"locality"
},
  "geometry": {"coordinates":[-84.15194,41.58917],"type":"Point"}
}