{
  "type": "Feature",
  "properties": {
    "gn:admin1_code":"VA",
    "gn:admin2_code":"700.0",
    "gn:asciiname":"Warwick Mobile Home Estates",
    "gn:country_code":"US",
    "gn:dem":10,
    "gn:elevation":"11.0",
    "gn:feature_class":"P",
    "gn:feature_code":"PPL",
    "gn:name":"Warwick Mobile Home Estates",
    "gn:population":0,
    "gn:timezone":"America/New_York",
    "iso:country":"US",
    "wof:name":"Warwick Mobile Home Estates",
    "wof:placetype":"campus"
},
  "geometry": {"coordinates":[-76.49528000000002,37.09889],"type":"Point"}
}