{
  "type": "Feature",
  "properties": {
    "gn:admin1_code":"KY",
    "gn:admin2_code":"177",
    "gn:asciiname":"Earles",
    "gn:country_code":"US",
    "gn:dem":151,
    "gn:elevation":"152.0",
    "gn:feature_class":"P",
    "gn:feature_code":"PPL",
    "gn:name":"Earles",
    "gn:population":0,
    "gn:timezone":"America/Chicago",
    "iso:country":"US",
    "wof:name":"Earles",
    "wof:placetype":"locality"
},
  "geometry": {"coordinates":[-87.31026999999997,37.30004],"type":"Point"}
}