{
  "type": "Feature",
  "properties": {
    "gn:admin1_code":"AZ",
    "gn:admin2_code":"19.0",
    "gn:asciiname":"Mesa Ridge Mobile Home Park",
    "gn:country_code":"US",
    "gn:dem":732,
    "gn:elevation":"733.0",
    "gn:feature_class":"P",
    "gn:feature_code":"PPL",
    "gn:name":"Mesa Ridge Mobile Home Park",
    "gn:population":0,
    "gn:timezone":"America/Phoenix",
    "iso:country":"US",
    "wof:name":"Mesa Ridge Mobile Home Park",
    "wof:placetype":"campus"
},
  "geometry": {"coordinates":[-110.99611000000002,32.1802],"type":"Point"}
}