{
  "type": "Feature",
  "properties": {
    "iso:country":"US",
    "name:eng_x_preferred":[
        "Fairwood Firs"
    ],
    "wof:name":"Fairwood Firs",
    "wof:placetype":"neighbourhood",
    "wof:population":3257,
    "zs:area_m":1758236.336059,
    "zs:blockids":[
        530330319092003,
        530330293043011,
        530330319092000,
        530330319091008,
        530330319082005,
        530330319091011,
        530330293043001,
        530330319091017,
        530330319091024,
        530330319092005,
        530330319091012,
        530330293043000,
        530330319082004,
        530330319091006,
        530330319092001,
        530330319091013,
        530330258043013,
        530330319092008,
        530330319082006,
        530330319092004,
        530330319091007,
        530330258043014,
        530330319092002,
        530330258043012,
        530330258043015,
        530330258043016,
        530330319083005,
        530330319082007
    ],
    "zs:housing10":1355,
    "zs:label":"Fairwood Firs",
    "zs:pop10":3257
},
  "geometry": {"coordinates":[-122.14933000000001,47.439209],"type":"Point"}
}