{
  "type": "Feature",
  "properties": {
    "gn:admin1_code":"MN",
    "gn:admin2_code":"49.0",
    "gn:admin3_code":"4816.0",
    "gn:asciiname":"Ryan",
    "gn:country_code":"US",
    "gn:dem":349,
    "gn:elevation":"353.0",
    "gn:feature_class":"P",
    "gn:feature_code":"PPL",
    "gn:name":"Ryan",
    "gn:population":0,
    "gn:timezone":"America/Chicago",
    "iso:country":"US",
    "wof:name":"Ryan",
    "wof:placetype":"locality"
},
  "geometry": {"coordinates":[-92.71547,44.42386],"type":"Point"}
}