{
  "type": "Feature",
  "properties": {
    "gn:elevation":24,
    "iso:country":"US",
    "name:eng_x_preferred":[
        "North Stelton"
    ],
    "name:eng_x_variant":[
        "N Stelton"
    ],
    "name:fra_x_preferred":[
        "North Stelton"
    ],
    "qs:gn_adm0_cc":"US",
    "qs:gn_fcode":"PPL",
    "qs:gn_local":5102713,
    "qs:gn_nam_loc":"Piscataway, Middlesex, New Jersey, US",
    "qs:gn_namadm1":"NJ",
    "qs:gn_name":"North Stelton",
    "qs:local_max":2836,
    "qs:local_sum":8197,
    "qs:localhoods":7,
    "qs:name":"North Stelton",
    "qs:name_adm0":"United States",
    "qs:name_adm1":"New Jersey",
    "qs:name_adm2":"Middlesex",
    "qs:name_local":"Piscataway",
    "qs:photo_max":665,
    "qs:photo_sum":1538,
    "qs:placetype":"Suburb",
    "qs:quad_count":12,
    "qs:woe_adm0":23424977,
    "qs:woe_adm1":2347589,
    "qs:woe_adm2":12589269,
    "qs:woe_funk":"Parented by a neighborhood",
    "qs:woe_lau":0,
    "qs:woe_local":2473091,
    "qs:woe_ver":"7.10.0",
    "wd:wordcount":43,
    "wof:lang":[
        "eng"
    ],
    "wof:name":"North Stelton",
    "wof:placetype":"neighbourhood",
    "wof:population":3043,
    "zs:blockids":[
        340230006063013,
        340230015062016,
        340230088001002,
        340230088001008,
        340230006063027,
        340230088001003,
        340230006063007,
        340230088001007,
        340230006063008,
        340230015062023,
        340230015062015,
        340230006063026,
        340230006063018,
        340230006063017,
        340230015062008,
        340230088001005,
        340230088001014,
        340230006063009,
        340230015062004,
        340230088001009,
        340230015062007,
        340230006063006,
        340230088001006,
        340230088001004,
        340230015062014,
        340230006063012,
        340230015062009,
        340230015062013,
        340230015062003,
        340230015062006,
        340230088001015
    ],
    "zs:housing10":305,
    "zs:pop10":3043
},
  "geometry": {"coordinates":[-74.434842,40.522532],"type":"Point"}
}