{
  "type": "Feature",
  "properties": {
    "gn:country":"US",
    "gn:fcode":"PPL",
    "gn:population":0,
    "iso:country":"US",
    "name:ceb_x_preferred":[
        "Summersville"
    ],
    "name:deu_x_preferred":[
        "Summersville"
    ],
    "name:est_x_preferred":[
        "Summersville"
    ],
    "name:ita_x_preferred":[
        "Summersville"
    ],
    "name:nld_x_preferred":[
        "Summersville"
    ],
    "name:pol_x_preferred":[
        "Summersville"
    ],
    "name:por_x_preferred":[
        "Summersville"
    ],
    "name:rus_x_preferred":[
        "\u0421\u0430\u043c\u043c\u0435\u0440\u0441\u0432\u0438\u043b\u043b"
    ],
    "name:swe_x_preferred":[
        "Summersville"
    ],
    "name:vol_x_preferred":[
        "Summersville"
    ],
    "qs_pg:aaroncc":"US",
    "qs_pg:gn_country":"US",
    "qs_pg:gn_fcode":"PPL",
    "qs_pg:gn_pop":0,
    "qs_pg:name":"Summersville",
    "qs_pg:name_adm0":"United States",
    "qs_pg:name_adm1":"Tennessee",
    "qs_pg:photos":5,
    "qs_pg:photos_1k":1,
    "qs_pg:photos_9k":1,
    "qs_pg:photos_9r":1,
    "qs_pg:photos_all":5,
    "qs_pg:photos_sr":1,
    "qs_pg:pop_sr":0,
    "qs_pg:qs_pg_placetype":"locality",
    "qs_pg:qs_pg_placetype_gp":"Town",
    "qs_pg:woe_adm0":23424977,
    "woe:adm0_id":23424977,
    "woe:name_adm0":"United States",
    "woe:name_adm1":"Tennessee",
    "woe:placetype":"Town",
    "wof:name":"Summersville",
    "wof:placetype":"locality"
},
  "geometry": {"coordinates":[-82.5307,36.46482],"type":"Point"}
}