{
  "type": "Feature",
  "properties": {
    "gn:admin1_code":"AL",
    "gn:admin2_code":"9",
    "gn:asciiname":"Little Warrior",
    "gn:country_code":"US",
    "gn:dem":152,
    "gn:elevation":"144.0",
    "gn:feature_class":"P",
    "gn:feature_code":"PPL",
    "gn:name":"Little Warrior",
    "gn:population":0,
    "gn:timezone":"America/Chicago",
    "iso:country":"US",
    "name:fas_x_preferred":[
        "\u0644\u06cc\u062a\u0644 \u0648\u0627\u0631\u06cc\u0631"
    ],
    "name:zho_x_preferred":[
        "\u5229\u7279\u723e\u6c83\u91cc\u723e"
    ],
    "wof:name":"Little Warrior",
    "wof:placetype":"locality"
},
  "geometry": {"coordinates":[-86.59832,33.9076],"type":"Point"}
}