{
  "type": "Feature",
  "properties": {
    "gn:admin1_code":"MD",
    "gn:admin2_code":"9.0",
    "gn:asciiname":"Mutual Consent",
    "gn:country_code":"US",
    "gn:dem":42,
    "gn:elevation":"35.0",
    "gn:feature_class":"P",
    "gn:feature_code":"PPL",
    "gn:name":"Mutual Consent",
    "gn:population":0,
    "gn:timezone":"America/New_York",
    "iso:country":"US",
    "wof:name":"Mutual Consent",
    "wof:placetype":"locality"
},
  "geometry": {"coordinates":[-76.56050999999999,38.46235],"type":"Point"}
}