{
  "type": "Feature",
  "properties": {
    "gn:admin1_code":"AR",
    "gn:admin2_code":"79.0",
    "gn:admin3_code":"92262.0",
    "gn:asciiname":"Relfs Bluff",
    "gn:country_code":"US",
    "gn:dem":83,
    "gn:elevation":"79.0",
    "gn:feature_class":"P",
    "gn:feature_code":"PPL",
    "gn:name":"Relfs Bluff",
    "gn:population":0,
    "gn:timezone":"America/Chicago",
    "iso:country":"US",
    "name:eng_x_preferred":[
        "Relfs Bluff"
    ],
    "name:fas_x_preferred":[
        "\u0631\u0644\u0641\u0633 \u0628\u0644\u0627\u0641"
    ],
    "name:und_x_variant":[
        "Relfsbluff"
    ],
    "name:zho_x_preferred":[
        "\u96f7\u723e\u592b\u65af\u5e03\u62c9\u592b"
    ],
    "wof:name":"Relfs Bluff",
    "wof:placetype":"locality"
},
  "geometry": {"coordinates":[-91.84291,33.80122],"type":"Point"}
}