{
  "type": "Feature",
  "properties": {
    "gn:admin1_code":"NM",
    "gn:admin2_code":"39",
    "gn:asciiname":"Frijoles Spring",
    "gn:country_code":"US",
    "gn:dem":2149,
    "gn:elevation":"2138.0",
    "gn:feature_class":"P",
    "gn:feature_code":"PPL",
    "gn:name":"Frijoles Spring",
    "gn:population":0,
    "gn:timezone":"America/Denver",
    "iso:country":"US",
    "wof:name":"Frijoles Spring",
    "wof:placetype":"locality"
},
  "geometry": {"coordinates":[-106.37059000000001,36.16113],"type":"Point"}
}