{
  "type": "Feature",
  "properties": {
    "gn:admin1_code":"VA",
    "gn:admin2_code":"3",
    "gn:asciiname":"Gilbert",
    "gn:country_code":"US",
    "gn:dem":115,
    "gn:elevation":"114.0",
    "gn:feature_class":"P",
    "gn:feature_code":"PPL",
    "gn:name":"Gilbert",
    "gn:population":0,
    "gn:timezone":"America/New_York",
    "iso:country":"US",
    "wof:name":"Gilbert",
    "wof:placetype":"locality"
},
  "geometry": {"coordinates":[-78.37390000000001,38.14597],"type":"Point"}
}