{
  "type": "Feature",
  "properties": {
    "iso:country":"US",
    "name:eng_x_preferred":[
        "South Beaumont"
    ],
    "wof:name":"South Beaumont",
    "wof:placetype":"neighbourhood",
    "wof:population":847,
    "zs:area_m":819007.236344,
    "zs:blockids":[
        120970418002021,
        120970416003033,
        120970416005013,
        120970418002020,
        120970416003038,
        120970416005008,
        120970416003030,
        120970418002037,
        120970416003026,
        120970418003018,
        120970416003028,
        120970416003046,
        120970416003045,
        120970418002024,
        120970416003035,
        120970416003036,
        120970416005024,
        120970416005005,
        120970416005019,
        120970416005026,
        120970416005002,
        120970416004020,
        120970416003042,
        120970416005018,
        120970416003031,
        120970416005023,
        120970416005016,
        120970416005029,
        120970416003025,
        120970418002007,
        120970418003003,
        120970418002008,
        120970416003032,
        120970416005014,
        120970416003043,
        120970418003004,
        120970416003004,
        120970418002022,
        120970416005010,
        120970416003039,
        120970416005030,
        120970418003000,
        120970416003027,
        120970416005007,
        120970416004022,
        120970418003001,
        120970416003048,
        120970416005028,
        120970416005031,
        120970416005003,
        120970416005020,
        120970416005004,
        120970416003040,
        120970416004021,
        120970416004023,
        120970418003019,
        120970416003029,
        120970416005001,
        120970416003049,
        120970416003044,
        120970416005006,
        120970416005022,
        120970416005033,
        120970416003023,
        120970416005021,
        120970416005011,
        120970416004024,
        120970416005009,
        120970418002002,
        120970416003047,
        120970416005015,
        120970416003024,
        120970416003020,
        120970418002023,
        120970416003005,
        120970416005025,
        120970416005017,
        120970416005027,
        120970416005032,
        120970416003022,
        120970416003041,
        120970416003037,
        120970416005012,
        120970416005000
    ],
    "zs:housing10":420,
    "zs:label":"South Beaumont",
    "zs:pop10":847
},
  "geometry": {"coordinates":[-81.413541,28.291006],"type":"Point"}
}