{
  "type": "Feature",
  "properties": {
    "gn:admin1_code":"FL",
    "gn:admin2_code":"11.0",
    "gn:asciiname":"Sunshine Ranches",
    "gn:country_code":"US",
    "gn:dem":6,
    "gn:elevation":"1.0",
    "gn:feature_class":"P",
    "gn:feature_code":"PPL",
    "gn:name":"Sunshine Ranches",
    "gn:population":0,
    "gn:timezone":"America/New_York",
    "iso:country":"US",
    "name:azb_x_preferred":[
        "\u0633\u0627\u0646\u0634\u0627\u06cc\u0646 \u0631\u0627\u0646\u0686\u0633"
    ],
    "name:eus_x_preferred":[
        "Sunshine Ranches"
    ],
    "name:fas_x_preferred":[
        "\u0633\u0627\u0646\u0634\u0627\u06cc\u0646 \u0631\u0627\u0646\u0686\u0633"
    ],
    "name:new_x_preferred":[
        "\u0938\u0928\u0936\u093e\u0907\u0928 \u0930\u094d\u0930\u094d\u092f\u093e\u0928\u094d\u091a\u0947\u091c"
    ],
    "name:nld_x_preferred":[
        "Sunshine Ranches"
    ],
    "name:por_x_preferred":[
        "Sunshine Ranches"
    ],
    "name:uzb_x_preferred":[
        "Sunshine Ranches"
    ],
    "wof:name":"Sunshine Ranches",
    "wof:placetype":"locality"
},
  "geometry": {"coordinates":[-80.32921999999998,26.04398],"type":"Point"}
}