{
  "type": "Feature",
  "properties": {
    "gn:admin1_code":"MT",
    "gn:admin2_code":"29.0",
    "gn:asciiname":"Crystal Ford",
    "gn:country_code":"US",
    "gn:dem":1277,
    "gn:elevation":"1258.0",
    "gn:feature_class":"P",
    "gn:feature_code":"PPL",
    "gn:name":"Crystal Ford",
    "gn:population":0,
    "gn:timezone":"America/Denver",
    "iso:country":"US",
    "wof:name":"Crystal Ford",
    "wof:placetype":"locality"
},
  "geometry": {"coordinates":[-113.84873,48.60886],"type":"Point"}
}