{
  "type": "Feature",
  "properties": {
    "gn:admin1_code":"HI",
    "gn:admin2_code":"3.0",
    "gn:asciiname":"Renton Village",
    "gn:country_code":"US",
    "gn:dem":19,
    "gn:elevation":"14.0",
    "gn:feature_class":"P",
    "gn:feature_code":"PPL",
    "gn:name":"Renton Village",
    "gn:population":0,
    "gn:timezone":"Pacific/Honolulu",
    "iso:country":"US",
    "wof:name":"Renton Village",
    "wof:placetype":"locality"
},
  "geometry": {"coordinates":[-158.03587999999999,21.34215],"type":"Point"}
}