{
  "type": "Feature",
  "properties": {
    "gn:admin1_code":"TX",
    "gn:admin2_code":"225.0",
    "gn:asciiname":"San Pedro",
    "gn:country_code":"US",
    "gn:dem":123,
    "gn:elevation":"116.0",
    "gn:feature_class":"P",
    "gn:feature_code":"PPL",
    "gn:name":"San Pedro",
    "gn:population":733,
    "gn:timezone":"America/Chicago",
    "iso:country":"US",
    "name:arg_x_preferred":[
        "San Pedro"
    ],
    "name:ast_x_preferred":[
        "San Pedro"
    ],
    "name:bre_x_preferred":[
        "San Pedro"
    ],
    "name:cat_x_preferred":[
        "San Pedro"
    ],
    "name:ceb_x_preferred":[
        "San Pedro"
    ],
    "name:ces_x_preferred":[
        "San Pedro"
    ],
    "name:deu_x_preferred":[
        "San Pedro"
    ],
    "name:epo_x_preferred":[
        "San Pedro"
    ],
    "name:est_x_preferred":[
        "San Pedro"
    ],
    "name:fas_x_preferred":[
        "\u0633\u0646 \u067e\u062f\u0631\u0648"
    ],
    "name:fra_x_preferred":[
        "San Pedro"
    ],
    "name:glg_x_preferred":[
        "San Pedro"
    ],
    "name:heb_x_preferred":[
        "\u05e1\u05df \u05e4\u05d3\u05e8\u05d5"
    ],
    "name:hrv_x_preferred":[
        "San Pedro"
    ],
    "name:hye_x_preferred":[
        "\u054d\u0561\u0576 \u054a\u0565\u0564\u0580\u0578"
    ],
    "name:ilo_x_preferred":[
        "San Pedro"
    ],
    "name:ita_x_preferred":[
        "San Pedro"
    ],
    "name:jpn_x_preferred":[
        "\u30b5\u30f3\u30da\u30c9\u30ed"
    ],
    "name:kor_x_preferred":[
        "\uc0b0\ud398\ub4dc\ub85c"
    ],
    "name:lit_x_preferred":[
        "San Pedras"
    ],
    "name:nds_x_preferred":[
        "San Pedro"
    ],
    "name:nld_x_preferred":[
        "San Pedro"
    ],
    "name:nor_x_preferred":[
        "San Pedro"
    ],
    "name:pol_x_preferred":[
        "San Pedro"
    ],
    "name:por_x_preferred":[
        "San Pedro"
    ],
    "name:rus_x_preferred":[
        "\u043e\u0437\u0435\u0440\u043e \u0421\u0430\u043d-\u041f\u0435\u0434\u0440\u043e"
    ],
    "name:rus_x_variant":[
        "\u0421\u0430\u043d-\u041f\u0435\u0434\u0440\u043e"
    ],
    "name:sco_x_preferred":[
        "San Pedro"
    ],
    "name:slk_x_preferred":[
        "San Pedro"
    ],
    "name:spa_x_preferred":[
        "San Pedro"
    ],
    "name:srp_x_preferred":[
        "\u0421\u0430\u043d \u041f\u0435\u0434\u0440\u043e"
    ],
    "name:swe_x_preferred":[
        "R\u00edo San Pedro"
    ],
    "name:swe_x_variant":[
        "San Pedro"
    ],
    "name:tur_x_preferred":[
        "San Pedro"
    ],
    "name:ukr_x_preferred":[
        "\u0421\u0430\u043d-\u041f\u0435\u0434\u0440\u043e"
    ],
    "name:urd_x_preferred":[
        "\u0633\u0627\u0646 \u067e\u06cc\u0688\u0631\u0648"
    ],
    "name:vie_x_preferred":[
        "S\u00f4ng San Pedro"
    ],
    "name:war_x_preferred":[
        "San Pedro"
    ],
    "name:zho_cn_x_preferred":[
        "\u5723\u4f69\u5fb7\u7f57\u6cb3"
    ],
    "name:zho_tw_x_preferred":[
        "\u8056\u4f69\u5fb7\u7f85\u6cb3"
    ],
    "wof:name":"San Pedro",
    "wof:placetype":"locality",
    "wof:population":733
},
  "geometry": {"coordinates":[-95.37828,31.47629],"type":"Point"}
}