{
  "type": "Feature",
  "properties": {
    "gn:admin1_code":"MI",
    "gn:admin2_code":"149",
    "gn:admin3_code":"76980.0",
    "gn:asciiname":"Memory Lane Mobile Home Park",
    "gn:country_code":"US",
    "gn:dem":273,
    "gn:elevation":"272.0",
    "gn:feature_class":"P",
    "gn:feature_code":"PPL",
    "gn:name":"Memory Lane Mobile Home Park",
    "gn:population":0,
    "gn:timezone":"America/Detroit",
    "iso:country":"US",
    "wof:name":"Memory Lane Mobile Home Park",
    "wof:placetype":"campus"
},
  "geometry": {"coordinates":[-85.46556,41.79361],"type":"Point"}
}