{
  "type": "Feature",
  "properties": {
    "gn:admin1_code":"TX",
    "gn:admin2_code":"91.0",
    "gn:asciiname":"Westhaven",
    "gn:country_code":"US",
    "gn:dem":303,
    "gn:elevation":"300.0",
    "gn:feature_class":"P",
    "gn:feature_code":"PPL",
    "gn:name":"Westhaven",
    "gn:population":0,
    "gn:timezone":"America/Chicago",
    "iso:country":"US",
    "wof:name":"Westhaven",
    "wof:placetype":"locality"
},
  "geometry": {"coordinates":[-98.27779,29.86577],"type":"Point"}
}