{
  "type": "Feature",
  "properties": {
    "gn:admin1_code":"AL",
    "gn:admin2_code":"57",
    "gn:asciiname":"Bobo",
    "gn:country_code":"US",
    "gn:dem":158,
    "gn:elevation":"155.0",
    "gn:feature_class":"P",
    "gn:feature_code":"PPL",
    "gn:name":"Bobo",
    "gn:population":0,
    "gn:timezone":"America/Chicago",
    "iso:country":"US",
    "name:ceb_x_preferred":[
        "Bobo"
    ],
    "name:deu_x_preferred":[
        "Bobo"
    ],
    "name:fin_x_preferred":[
        "Bobo"
    ],
    "name:fra_x_preferred":[
        "Bobo"
    ],
    "name:hun_x_preferred":[
        "Bobo"
    ],
    "name:ita_x_preferred":[
        "Bobo"
    ],
    "name:nld_x_preferred":[
        "Bobo"
    ],
    "name:pol_x_preferred":[
        "Bobo"
    ],
    "name:por_x_preferred":[
        "Bobo"
    ],
    "name:rus_x_preferred":[
        "\u0411\u043e\u0431\u043e"
    ],
    "name:spa_x_preferred":[
        "Bobo"
    ],
    "name:zho_x_preferred":[
        "Bobo"
    ],
    "wof:name":"Bobo",
    "wof:placetype":"locality"
},
  "geometry": {"coordinates":[-87.82252,33.87733],"type":"Point"}
}