{
  "type": "Feature",
  "properties": {
    "gn:admin1_code":"WA",
    "gn:admin2_code":"67.0",
    "gn:asciiname":"Rignall",
    "gn:country_code":"US",
    "gn:dem":28,
    "gn:elevation":"30.0",
    "gn:feature_class":"P",
    "gn:feature_code":"PPL",
    "gn:name":"Rignall",
    "gn:population":0,
    "gn:timezone":"America/Los_Angeles",
    "iso:country":"US",
    "wof:name":"Rignall",
    "wof:placetype":"locality"
},
  "geometry": {"coordinates":[-122.92264,47.1651],"type":"Point"}
}