{
  "type": "Feature",
  "properties": {
    "gn:admin1_code":"PA",
    "gn:admin2_code":"133",
    "gn:admin3_code":"87056.0",
    "gn:asciiname":"Dallas Acres",
    "gn:country_code":"US",
    "gn:dem":231,
    "gn:elevation":"234.0",
    "gn:feature_class":"P",
    "gn:feature_code":"PPL",
    "gn:name":"Dallas Acres",
    "gn:population":0,
    "gn:timezone":"America/New_York",
    "iso:country":"US",
    "wof:name":"Dallas Acres",
    "wof:placetype":"locality"
},
  "geometry": {"coordinates":[-76.66190999999998,39.90177],"type":"Point"}
}