{
  "type": "Feature",
  "properties": {
    "gn:admin1_code":"TX",
    "gn:admin2_code":"193.0",
    "gn:asciiname":"Sunshine",
    "gn:country_code":"US",
    "gn:dem":395,
    "gn:elevation":"391.0",
    "gn:feature_class":"P",
    "gn:feature_code":"PPL",
    "gn:name":"Sunshine",
    "gn:population":0,
    "gn:timezone":"America/Chicago",
    "iso:country":"US",
    "wof:name":"Sunshine",
    "wof:placetype":"locality"
},
  "geometry": {"coordinates":[-98.14476000000001,31.86348],"type":"Point"}
}