{
  "type": "Feature",
  "properties": {
    "iso:country":"US",
    "name:eng_x_preferred":[
        "Western Pump Station"
    ],
    "wof:name":"Western Pump Station",
    "wof:placetype":"neighbourhood",
    "wof:population":20,
    "zs:area_m":361229.291636,
    "zs:blockids":[
        481210203032053,
        481210203032047,
        481210203032058,
        481210203032062
    ],
    "zs:housing10":4,
    "zs:label":"Western Pump Station",
    "zs:pop10":20
},
  "geometry": {"coordinates":[-97.19222499999999,33.084398],"type":"Point"}
}