{
  "type": "Feature",
  "properties": {
    "iso:country":"US",
    "name:eng_x_preferred":[
        "Granite Hill"
    ],
    "wof:name":"Granite Hill",
    "wof:placetype":"neighbourhood",
    "wof:population":1037,
    "zs:area_m":23016656.267599,
    "zs:blockids":[
        420010306001061,
        420010306003011,
        420010306001038,
        420010306003044,
        420010306003059,
        420010306003017,
        420010306001058,
        420010306003013,
        420010306001034,
        420010306003009,
        420010306003024,
        420010306003015,
        420010306001059,
        420010306001056,
        420010306002067,
        420010306001057,
        420010306001035,
        420010306002072,
        420010306003057,
        420010306001036,
        420010306001089,
        420010306003008,
        420010306003054,
        420010306003016,
        420010306001039,
        420010306001040,
        420010306001075,
        420010306003010,
        420010306001078,
        420010306001074,
        420010306001072,
        420010306001060,
        420010306001005,
        420010306001073,
        420010306002066,
        420010306001041,
        420010306001063,
        420010306002077,
        420010306001054,
        420010306002039,
        420010306002068,
        420010306002079,
        420010306001006,
        420010306001055,
        420010306001014,
        420010306001003,
        420010306002010,
        420010306002069,
        420010306002078,
        420010306001044,
        420010306001037,
        420010306001046,
        420010306001004,
        420010306002029,
        420010306003014,
        420010306001076,
        420010306001077,
        420010306002071,
        420010306001012,
        420010306001008,
        420010306001007,
        420010306001062,
        420010306001066,
        420010306003012,
        420010306001071,
        420010306002038,
        420010306001079,
        420010306001067,
        420010306001011,
        420010306001009,
        420010306001010,
        420010306002073,
        420010306002070
    ],
    "zs:housing10":414,
    "zs:label":"Granite Hill",
    "zs:pop10":1037
},
  "geometry": {"coordinates":[-77.177706,39.866953],"type":"Point"}
}