{
  "type": "Feature",
  "properties": {
    "gn:admin1_code":"AK",
    "gn:admin2_code":"122.0",
    "gn:asciiname":"Dahl",
    "gn:country_code":"US",
    "gn:dem":382,
    "gn:elevation":"383.0",
    "gn:feature_class":"P",
    "gn:feature_code":"PPL",
    "gn:name":"Dahl",
    "gn:population":0,
    "gn:timezone":"America/Anchorage",
    "iso:country":"US",
    "name:bel_x_preferred":[
        "\u0414\u0430\u043b\u044c"
    ],
    "name:ceb_x_preferred":[
        "Dahl"
    ],
    "name:ces_x_preferred":[
        "Dahl"
    ],
    "name:deu_x_preferred":[
        "Dahl"
    ],
    "name:fin_x_preferred":[
        "Dahl"
    ],
    "name:fra_x_preferred":[
        "Dahl"
    ],
    "name:ita_x_preferred":[
        "Dahl"
    ],
    "name:jpn_x_preferred":[
        "\u30c0\u30fc\u30eb"
    ],
    "name:kor_x_preferred":[
        "\ub2ec"
    ],
    "name:nld_x_preferred":[
        "Dahl"
    ],
    "name:nor_x_preferred":[
        "Dahl"
    ],
    "name:pol_x_preferred":[
        "Dahl"
    ],
    "name:rus_x_preferred":[
        "\u0414\u0430\u043b\u044c"
    ],
    "name:spa_x_preferred":[
        "Dahl"
    ],
    "name:swe_x_preferred":[
        "Dahl"
    ],
    "name:ukr_x_preferred":[
        "\u0414\u0430\u043b\u044c"
    ],
    "wof:name":"Dahl",
    "wof:placetype":"locality"
},
  "geometry": {"coordinates":[-149.47721999999999,60.66556],"type":"Point"}
}