{
  "type": "Feature",
  "properties": {
    "gn:admin1_code":"NC",
    "gn:admin2_code":"191",
    "gn:admin3_code":"91576.0",
    "gn:asciiname":"Gradys",
    "gn:country_code":"US",
    "gn:dem":41,
    "gn:elevation":"41.0",
    "gn:feature_class":"P",
    "gn:feature_code":"PPL",
    "gn:name":"Gradys",
    "gn:population":0,
    "gn:timezone":"America/New_York",
    "iso:country":"US",
    "wof:name":"Gradys",
    "wof:placetype":"locality"
},
  "geometry": {"coordinates":[-77.88526,35.16572],"type":"Point"}
}