{
  "type": "Feature",
  "properties": {
    "gn:admin1_code":"MD",
    "gn:admin2_code":"21.0",
    "gn:asciiname":"McDonald",
    "gn:country_code":"US",
    "gn:dem":215,
    "gn:elevation":"229.0",
    "gn:feature_class":"P",
    "gn:feature_code":"PPL",
    "gn:name":"McDonald",
    "gn:population":0,
    "gn:timezone":"America/New_York",
    "iso:country":"US",
    "wof:name":"McDonald",
    "wof:placetype":"locality"
},
  "geometry": {"coordinates":[-77.16415000000001,39.43344],"type":"Point"}
}