{
  "type": "Feature",
  "properties": {
    "gn:admin1_code":"NC",
    "gn:admin2_code":"21.0",
    "gn:admin3_code":"93180.0",
    "gn:asciiname":"Rattlesnake Lodge",
    "gn:country_code":"US",
    "gn:dem":1153,
    "gn:elevation":"1132.0",
    "gn:feature_class":"P",
    "gn:feature_code":"PPL",
    "gn:name":"Rattlesnake Lodge",
    "gn:population":0,
    "gn:timezone":"America/New_York",
    "iso:country":"US",
    "wof:name":"Rattlesnake Lodge",
    "wof:placetype":"locality"
},
  "geometry": {"coordinates":[-82.45568,35.66845],"type":"Point"}
}