{
  "type": "Feature",
  "properties": {
    "gn:admin1_code":"DE",
    "gn:admin2_code":"1",
    "gn:asciiname":"Reynard Crossing",
    "gn:country_code":"US",
    "gn:dem":20,
    "gn:elevation":"20.0",
    "gn:feature_class":"P",
    "gn:feature_code":"PPL",
    "gn:name":"Reynard Crossing",
    "gn:population":0,
    "gn:timezone":"America/New_York",
    "iso:country":"US",
    "wof:name":"Reynard Crossing",
    "wof:placetype":"locality"
},
  "geometry": {"coordinates":[-75.7406,39.2334],"type":"Point"}
}