{
  "type": "Feature",
  "properties": {
    "gn:elevation":260,
    "iso:country":"US",
    "name:eng_x_preferred":[
        "Taylorshire"
    ],
    "qs:gn_fcode":"PPL",
    "qs:gn_local":0,
    "qs:gn_namadm1":"NY",
    "qs:gn_name":"Taylorshire",
    "qs:local_max":730,
    "qs:local_sum":800,
    "qs:localhoods":2,
    "qs:name":"Taylorshire",
    "qs:name_adm0":"United States",
    "qs:name_adm1":"New York",
    "qs:name_adm2":"Erie",
    "qs:name_local":"Aurora",
    "qs:photo_max":439,
    "qs:photo_sum":730,
    "qs:placetype":"Suburb",
    "qs:quad_count":11,
    "qs:woe_adm0":23424977,
    "qs:woe_adm1":2347591,
    "qs:woe_adm2":12589326,
    "qs:woe_lau":0,
    "qs:woe_local":28744526,
    "qs:woe_ver":"7.10.0",
    "wof:lang":[
        "eng"
    ],
    "wof:name":"Taylorshire",
    "wof:placetype":"neighbourhood",
    "wof:population":1890,
    "zs:blockids":[
        360290138001005,
        360290138004015,
        360290138004016,
        360290138001001,
        360290138001042,
        360290138003016,
        360290138001004,
        360290138003023,
        360290138004006,
        360290138001002,
        360290138001053,
        360290138001018,
        360290138001003,
        360290138001015,
        360290138001009,
        360290138001000,
        360290138001017,
        360290138001014,
        360290138001016,
        360290138004005,
        360290138003024,
        360290138001041,
        360290138001008,
        360290138001043,
        360290138003050,
        360290138003049,
        360290138001013
    ],
    "zs:housing10":778,
    "zs:pop10":1890
},
  "geometry": {"coordinates":[-78.656953,42.746488],"type":"Point"}
}