{
  "type": "Feature",
  "properties": {
    "gn:admin1_code":"ND",
    "gn:admin2_code":"9.0",
    "gn:admin3_code":"86500.0",
    "gn:asciiname":"Omemee",
    "gn:country_code":"US",
    "gn:dem":459,
    "gn:elevation":"461.0",
    "gn:feature_class":"P",
    "gn:feature_code":"PPL",
    "gn:name":"Omemee",
    "gn:population":0,
    "gn:timezone":"America/Chicago",
    "iso:country":"US",
    "name:eng_x_preferred":[
        "Omemee"
    ],
    "name:und_x_variant":[
        "Omenee"
    ],
    "wof:name":"Omemee",
    "wof:placetype":"locality"
},
  "geometry": {"coordinates":[-100.35514000000001,48.70639],"type":"Point"}
}