{
  "type": "Feature",
  "properties": {
    "iso:country":"US",
    "name:eng_x_preferred":[
        "Log Barn Road"
    ],
    "wof:name":"Log Barn Road",
    "wof:placetype":"neighbourhood",
    "wof:population":485,
    "zs:area_m":19769960.354805,
    "zs:blockids":[
        370370208004039,
        370370208004033,
        370370208004047,
        370370208004044
    ],
    "zs:housing10":197,
    "zs:label":"Log Barn Road",
    "zs:pop10":485
},
  "geometry": {"coordinates":[-79.201193,35.676646],"type":"Point"}
}