{
  "type": "Feature",
  "properties": {
    "gn:admin1_code":"NC",
    "gn:admin2_code":"91",
    "gn:admin3_code":"91412.0",
    "gn:asciiname":"Lloyd Crossroads",
    "gn:country_code":"US",
    "gn:dem":24,
    "gn:elevation":"19.0",
    "gn:feature_class":"P",
    "gn:feature_code":"PPL",
    "gn:name":"Lloyd Crossroads",
    "gn:population":0,
    "gn:timezone":"America/New_York",
    "iso:country":"US",
    "wof:name":"Lloyd Crossroads",
    "wof:placetype":"locality"
},
  "geometry": {"coordinates":[-76.72523000000002,36.2796],"type":"Point"}
}