{
  "type": "Feature",
  "properties": {
    "gn:country":"US",
    "gn:fcode":"PPL",
    "gn:population":0,
    "iso:country":"US",
    "name:ara_x_preferred":[
        "\u0645\u064a \u0641\u064a\u0631"
    ],
    "name:bel_x_preferred":[
        "\u041c\u0435\u0439\u0444\u044d\u0440"
    ],
    "name:bul_x_preferred":[
        "\u041c\u0435\u0439\u0444\u0435\u044a\u0440"
    ],
    "name:cat_x_preferred":[
        "Mayfair"
    ],
    "name:ces_x_preferred":[
        "Mayfair"
    ],
    "name:cym_x_preferred":[
        "Mayfair"
    ],
    "name:dan_x_preferred":[
        "Mayfair"
    ],
    "name:deu_x_preferred":[
        "Mayfair"
    ],
    "name:ell_x_preferred":[
        "\u039c\u03ad\u03b9\u03c6\u03b5\u03c1"
    ],
    "name:epo_x_preferred":[
        "Mayfair"
    ],
    "name:fas_x_preferred":[
        "\u0645\u06cc\u200c\u0641\u0631"
    ],
    "name:fra_x_preferred":[
        "Mayfair"
    ],
    "name:gle_x_preferred":[
        "Mayfair"
    ],
    "name:heb_x_preferred":[
        "\u05de\u05d9\u05d9\u05e4\u05d9\u05d9\u05e8"
    ],
    "name:hin_x_preferred":[
        "\u092e\u0947\u092b\u093c\u0947\u092f\u0930"
    ],
    "name:ind_x_preferred":[
        "Mayfair"
    ],
    "name:isl_x_preferred":[
        "Mayfair"
    ],
    "name:ita_x_preferred":[
        "Mayfair"
    ],
    "name:jpn_x_preferred":[
        "\u30e1\u30a4\u30d5\u30a7\u30a2"
    ],
    "name:kab_x_preferred":[
        "Mayfair"
    ],
    "name:kor_x_preferred":[
        "\uba54\uc774\ud398\uc5b4"
    ],
    "name:lat_x_preferred":[
        "Mayfair"
    ],
    "name:msa_x_preferred":[
        "Mayfair"
    ],
    "name:nld_x_preferred":[
        "Mayfair"
    ],
    "name:nno_x_preferred":[
        "Mayfair"
    ],
    "name:nor_x_preferred":[
        "Mayfair"
    ],
    "name:pol_x_preferred":[
        "Mayfair"
    ],
    "name:por_x_preferred":[
        "Mayfair"
    ],
    "name:rus_x_preferred":[
        "\u041c\u0435\u0439\u0444\u044d\u0440"
    ],
    "name:spa_x_preferred":[
        "Mayfair"
    ],
    "name:swe_x_preferred":[
        "Mayfair"
    ],
    "name:ukr_x_preferred":[
        "\u041c\u0435\u0439\u0444\u0435\u0440"
    ],
    "name:urd_x_preferred":[
        "\u0645\u06d2 \u0641\u06cc\u0626\u0631"
    ],
    "name:zho_x_preferred":[
        "\u6885\u8d39\u5c14"
    ],
    "qs_pg:aaroncc":"US",
    "qs_pg:gn_country":"US",
    "qs_pg:gn_fcode":"PPL",
    "qs_pg:gn_pop":0,
    "qs_pg:name":"Mayfair",
    "qs_pg:name_adm0":"United States",
    "qs_pg:name_adm1":"Illinois",
    "qs_pg:photos":4,
    "qs_pg:photos_1k":1,
    "qs_pg:photos_9k":1,
    "qs_pg:photos_9r":1,
    "qs_pg:photos_all":4,
    "qs_pg:photos_sr":1,
    "qs_pg:pop_sr":0,
    "qs_pg:qs_pg_placetype":"locality",
    "qs_pg:qs_pg_placetype_gp":"Town",
    "qs_pg:woe_adm0":23424977,
    "woe:adm0_id":23424977,
    "woe:name_adm0":"United States",
    "woe:name_adm1":"Illinois",
    "woe:placetype":"Town",
    "wof:name":"Mayfair",
    "wof:placetype":"locality"
},
  "geometry": {"coordinates":[-89.40787,40.61504],"type":"Point"}
}