{
  "type": "Feature",
  "properties": {
    "gn:admin1_code":"AR",
    "gn:admin2_code":"87.0",
    "gn:admin3_code":"93759.0",
    "gn:asciiname":"Cannon Creek",
    "gn:country_code":"US",
    "gn:dem":448,
    "gn:elevation":"442.0",
    "gn:feature_class":"P",
    "gn:feature_code":"PPL",
    "gn:name":"Cannon Creek",
    "gn:population":0,
    "gn:timezone":"America/Chicago",
    "iso:country":"US",
    "wof:name":"Cannon Creek",
    "wof:placetype":"locality"
},
  "geometry": {"coordinates":[-93.9402,35.9048],"type":"Point"}
}