{
  "type": "Feature",
  "properties": {
    "gn:admin1_code":"GA",
    "gn:admin2_code":"165",
    "gn:asciiname":"Rogers",
    "gn:country_code":"US",
    "gn:dem":53,
    "gn:elevation":"48.0",
    "gn:feature_class":"P",
    "gn:feature_code":"PPL",
    "gn:name":"Rogers",
    "gn:population":0,
    "gn:timezone":"America/New_York",
    "iso:country":"US",
    "name:bel_x_preferred":[
        "\u0420\u043e\u0434\u0436\u044d\u0440\u0441"
    ],
    "name:cat_x_preferred":[
        "Rogers"
    ],
    "name:ceb_x_preferred":[
        "Rogers"
    ],
    "name:ces_x_preferred":[
        "Rogers"
    ],
    "name:deu_x_preferred":[
        "Rogers"
    ],
    "name:fra_x_preferred":[
        "Rogers"
    ],
    "name:heb_x_preferred":[
        "\u05e8\u05d5\u05d2'\u05e8\u05e1"
    ],
    "name:ita_x_preferred":[
        "Rogers"
    ],
    "name:jpn_x_preferred":[
        "\u30ed\u30b8\u30e3\u30fc\u30b9"
    ],
    "name:kor_x_preferred":[
        "\ub85c\uc800\uc2a4"
    ],
    "name:lav_x_preferred":[
        "Rogers"
    ],
    "name:nld_x_preferred":[
        "Rogers"
    ],
    "name:pol_x_preferred":[
        "Rogers"
    ],
    "name:por_x_preferred":[
        "Rogers"
    ],
    "name:rus_x_preferred":[
        "\u0420\u043e\u0434\u0436\u0435\u0440\u0441"
    ],
    "name:srp_x_preferred":[
        "\u0420\u043e\u045f\u0435\u0440\u0441"
    ],
    "name:swe_x_preferred":[
        "Rogers"
    ],
    "name:ukr_x_preferred":[
        "\u0420\u043e\u0434\u0436\u0435\u0440\u0441"
    ],
    "name:vol_x_preferred":[
        "Rogers"
    ],
    "name:zho_x_preferred":[
        "\u7f57\u6770\u65af"
    ],
    "wof:name":"Rogers",
    "wof:placetype":"locality"
},
  "geometry": {"coordinates":[-82.07373,32.81933],"type":"Point"}
}