{
  "type": "Feature",
  "properties": {
    "gn:admin1_code":"NY",
    "gn:admin2_code":"13.0",
    "gn:admin3_code":"2605.0",
    "gn:asciiname":"Black Corners",
    "gn:country_code":"US",
    "gn:dem":428,
    "gn:elevation":"428.0",
    "gn:feature_class":"P",
    "gn:feature_code":"PPL",
    "gn:name":"Black Corners",
    "gn:population":0,
    "gn:timezone":"America/New_York",
    "iso:country":"US",
    "wof:name":"Black Corners",
    "wof:placetype":"locality"
},
  "geometry": {"coordinates":[-79.1981,42.39423],"type":"Point"}
}