{
  "type": "Feature",
  "properties": {
    "gn:country":"US",
    "gn:fcode":"PPL",
    "gn:population":0,
    "iso:country":"US",
    "name:azb_x_preferred":[
        "\u06cc\u0648\u062f\u0631"
    ],
    "name:eng_x_preferred":[
        "Yoder"
    ],
    "name:fas_x_preferred":[
        "\u06cc\u0648\u062f\u0631"
    ],
    "name:fra_x_preferred":[
        "Yoder"
    ],
    "name:urd_x_preferred":[
        "\u06cc\u0648\u0688\u0631\u060c \u06a9\u0648\u0644\u0648\u0631\u0627\u0688\u0648"
    ],
    "name:urd_x_variant":[
        "\u06cc\u0648\u0688\u0631"
    ],
    "name:uzb_x_preferred":[
        "Yoder"
    ],
    "name:vol_x_preferred":[
        "Yoder"
    ],
    "name:zho_x_preferred":[
        "\u7d04\u5fb7\u723e"
    ],
    "qs_pg:aaroncc":"US",
    "qs_pg:gn_country":"US",
    "qs_pg:gn_fcode":"PPL",
    "qs_pg:gn_pop":0,
    "qs_pg:name":"Yoder",
    "qs_pg:name_adm0":"United States",
    "qs_pg:name_adm1":"Colorado",
    "qs_pg:photos":14,
    "qs_pg:photos_1k":3,
    "qs_pg:photos_9k":1,
    "qs_pg:photos_9r":1,
    "qs_pg:photos_all":14,
    "qs_pg:photos_sr":1,
    "qs_pg:pop_sr":5,
    "qs_pg:qs_pg_placetype":"locality",
    "qs_pg:qs_pg_placetype_gp":"Town",
    "qs_pg:woe_adm0":23424977,
    "woe:adm0_id":23424977,
    "woe:name_adm0":"United States",
    "woe:name_adm1":"Colorado",
    "woe:placetype":"Town",
    "wof:name":"Yoder",
    "wof:placetype":"locality"
},
  "geometry": {"coordinates":[-104.22190000000001,38.83944],"type":"Point"}
}