{
  "type": "Feature",
  "properties": {
    "iso:country":"US",
    "name:eng_x_preferred":[
        "Viewmont Circle"
    ],
    "wof:name":"Viewmont Circle",
    "wof:placetype":"neighbourhood",
    "wof:population":225,
    "zs:area_m":444824.248546,
    "zs:blockids":[
        490351110013007,
        490351110012006,
        490351108002020,
        490351110012005
    ],
    "zs:housing10":71,
    "zs:label":"Viewmont Circle",
    "zs:pop10":225
},
  "geometry": {"coordinates":[-111.822909,40.654363],"type":"Point"}
}