{
  "type": "Feature",
  "properties": {
    "iso:country":"US",
    "name:eng_x_preferred":[
        "Jane Terrace"
    ],
    "wof:name":"Jane Terrace",
    "wof:placetype":"neighbourhood",
    "wof:population":592,
    "zs:area_m":454020.984482,
    "zs:blockids":[
        120570116064006,
        120570116064001,
        120570116063009,
        120570116063004,
        120570116063008,
        120570116063006,
        120570116064005,
        120570116064002
    ],
    "zs:housing10":248,
    "zs:label":"Jane Terrace",
    "zs:pop10":592
},
  "geometry": {"coordinates":[-82.599129,28.007486],"type":"Point"}
}