{
  "type": "Feature",
  "properties": {
    "gn:country":"US",
    "gn:fcode":"PPL",
    "gn:population":0,
    "iso:country":"US",
    "name:eng_x_preferred":[
        "Camp Bird"
    ],
    "name:est_x_preferred":[
        "Camp Bird"
    ],
    "name:fra_x_preferred":[
        "Camp Bird"
    ],
    "name:nav_x_preferred":[
        "Ts\u00eddii \u0141\u00e1n\u00ed"
    ],
    "name:zho_x_preferred":[
        "\u9ce5\u71df"
    ],
    "qs_pg:aaroncc":"US",
    "qs_pg:gn_country":"US",
    "qs_pg:gn_fcode":"PPL",
    "qs_pg:gn_pop":0,
    "qs_pg:name":"Camp Bird",
    "qs_pg:name_adm0":"United States",
    "qs_pg:name_adm1":"Colorado",
    "qs_pg:photos":277,
    "qs_pg:photos_1k":56,
    "qs_pg:photos_9k":1,
    "qs_pg:photos_9r":4,
    "qs_pg:photos_all":277,
    "qs_pg:photos_sr":5,
    "qs_pg:pop_sr":5,
    "qs_pg:qs_pg_placetype":"locality",
    "qs_pg:qs_pg_placetype_gp":"Town",
    "qs_pg:woe_adm0":23424977,
    "woe:adm0_id":23424977,
    "woe:name_adm0":"United States",
    "woe:name_adm1":"Colorado",
    "woe:placetype":"Town",
    "wof:name":"Camp Bird",
    "wof:placetype":"locality"
},
  "geometry": {"coordinates":[-107.72645,37.97277],"type":"Point"}
}