{
  "type": "Feature",
  "properties": {
    "gn:admin1_code":"MN",
    "gn:admin2_code":"71.0",
    "gn:admin3_code":"61433.0",
    "gn:asciiname":"Lindford",
    "gn:country_code":"US",
    "gn:dem":346,
    "gn:elevation":"345.0",
    "gn:feature_class":"P",
    "gn:feature_code":"PPL",
    "gn:name":"Lindford",
    "gn:population":0,
    "gn:timezone":"America/Chicago",
    "iso:country":"US",
    "wof:name":"Lindford",
    "wof:placetype":"locality"
},
  "geometry": {"coordinates":[-93.78184,48.41078],"type":"Point"}
}