{
  "type": "Feature",
  "properties": {
    "gn:country":"US",
    "gn:fcode":"PPL",
    "gn:population":0,
    "iso:country":"US",
    "name:cat_x_preferred":[
        "Bagdad"
    ],
    "name:ceb_x_preferred":[
        "Bagdad"
    ],
    "name:deu_x_preferred":[
        "Bagdad"
    ],
    "name:fra_x_preferred":[
        "Bagdad"
    ],
    "name:hun_x_preferred":[
        "Bagdad"
    ],
    "name:nep_x_preferred":[
        "\u092c\u0917\u0926\u093e\u0926"
    ],
    "name:nld_x_preferred":[
        "Bagdad"
    ],
    "name:pol_x_preferred":[
        "Bagdad"
    ],
    "name:ron_x_preferred":[
        "Bagdad"
    ],
    "name:slv_x_preferred":[
        "Bagdad"
    ],
    "name:spa_x_preferred":[
        "Bagdad"
    ],
    "name:srp_x_preferred":[
        "\u0411\u0430\u0433\u0434\u0430\u0434"
    ],
    "name:swe_x_preferred":[
        "Bagdad"
    ],
    "name:vol_x_preferred":[
        "Bagdad"
    ],
    "qs_pg:aaroncc":"US",
    "qs_pg:gn_country":"US",
    "qs_pg:gn_fcode":"PPL",
    "qs_pg:gn_pop":0,
    "qs_pg:name":"Bagdad",
    "qs_pg:name_adm0":"United States",
    "qs_pg:name_adm1":"Pennsylvania",
    "qs_pg:photos":1,
    "qs_pg:photos_1k":1,
    "qs_pg:photos_9k":1,
    "qs_pg:photos_9r":1,
    "qs_pg:photos_all":1,
    "qs_pg:photos_sr":1,
    "qs_pg:pop_sr":0,
    "qs_pg:qs_pg_placetype":"neighbourhood",
    "qs_pg:qs_pg_placetype_gp":"Suburb",
    "qs_pg:woe_adm0":23424977,
    "woe:adm0_id":23424977,
    "woe:name_adm0":"United States",
    "woe:name_adm1":"Pennsylvania",
    "woe:placetype":"Suburb",
    "wof:name":"Bagdad",
    "wof:placetype":"neighbourhood"
},
  "geometry": {"coordinates":[-79.64421,40.65312],"type":"Point"}
}