{
  "type": "Feature",
  "properties": {
    "gn:admin1_code":"MT",
    "gn:admin2_code":"57.0",
    "gn:asciiname":"Jeffers",
    "gn:country_code":"US",
    "gn:dem":1505,
    "gn:elevation":"1502.0",
    "gn:feature_class":"P",
    "gn:feature_code":"PPL",
    "gn:name":"Jeffers",
    "gn:population":0,
    "gn:timezone":"America/Denver",
    "iso:country":"US",
    "wof:name":"Jeffers",
    "wof:placetype":"locality"
},
  "geometry": {"coordinates":[-111.70553,45.34882],"type":"Point"}
}