{
  "type": "Feature",
  "properties": {
    "gn:admin1_code":"LA",
    "gn:admin2_code":"63.0",
    "gn:asciiname":"Big D Mobile Home Park",
    "gn:country_code":"US",
    "gn:dem":18,
    "gn:elevation":"13.0",
    "gn:feature_class":"P",
    "gn:feature_code":"PPL",
    "gn:name":"Big D Mobile Home Park",
    "gn:population":0,
    "gn:timezone":"America/Chicago",
    "iso:country":"US",
    "wof:name":"Big D Mobile Home Park",
    "wof:placetype":"campus"
},
  "geometry": {"coordinates":[-90.87794,30.48768],"type":"Point"}
}