{
  "type": "Feature",
  "properties": {
    "gn:country":"US",
    "gn:fcode":"PPL",
    "gn:population":0,
    "iso:country":"US",
    "name:cat_x_preferred":[
        "Yola"
    ],
    "name:ceb_x_preferred":[
        "Yola"
    ],
    "name:deu_x_preferred":[
        "Yola"
    ],
    "name:fra_x_preferred":[
        "Yola"
    ],
    "name:heb_x_preferred":[
        "\u05d9\u05d5\u05dc\u05d4"
    ],
    "name:por_x_preferred":[
        "Yola"
    ],
    "name:rus_x_preferred":[
        "\u0419\u043e\u043b\u0430"
    ],
    "qs_pg:aaroncc":"US",
    "qs_pg:gn_country":"US",
    "qs_pg:gn_fcode":"PPL",
    "qs_pg:gn_pop":0,
    "qs_pg:name":"Yola",
    "qs_pg:name_adm0":"United States",
    "qs_pg:name_adm1":"Minnesota",
    "qs_pg:photos_9r":0,
    "qs_pg:photos_sr":0,
    "qs_pg:pop_sr":0,
    "qs_pg:qs_pg_placetype":"locality",
    "qs_pg:qs_pg_placetype_gp":"Town",
    "qs_pg:woe_adm0":23424977,
    "woe:adm0_id":23424977,
    "woe:name_adm0":"United States",
    "woe:name_adm1":"Minnesota",
    "woe:placetype":"Town",
    "wof:name":"Yola",
    "wof:placetype":"locality"
},
  "geometry": {"coordinates":[-95.01224000000001,47.23218],"type":"Point"}
}