{
  "type": "Feature",
  "properties": {
    "iso:country":"US",
    "name:cat_x_preferred":[
        "Deer Creek"
    ],
    "name:deu_x_preferred":[
        "Deer Creek"
    ],
    "name:ita_x_preferred":[
        "Deer Creek"
    ],
    "name:nld_x_preferred":[
        "Deer Creek"
    ],
    "name:pol_x_preferred":[
        "Deer Creek"
    ],
    "name:por_x_preferred":[
        "Deer Creek"
    ],
    "name:rus_x_preferred":[
        "\u0414\u0438\u0440-\u041a\u0440\u0438\u043a"
    ],
    "name:spa_x_preferred":[
        "Deer Creek"
    ],
    "name:srp_x_preferred":[
        "\u0414\u0438\u0440 \u041a\u0440\u0438\u043a"
    ],
    "name:swe_x_preferred":[
        "Deer Creek"
    ],
    "name:ukr_x_preferred":[
        "\u0414\u0456\u0435\u0440-\u041a\u0440\u0456\u043a"
    ],
    "name:vol_x_preferred":[
        "Deer Creek"
    ],
    "wof:name":"Deer Creek",
    "wof:placetype":"neighbourhood"
},
  "geometry": {"coordinates":[-93.56623305603644,41.74194154201744],"type":"Point"}
}