{
  "type": "Feature",
  "properties": {
    "gn:gn_country":"US",
    "gn:gn_fcode":"PPL",
    "gn:gn_pop":0,
    "iso:country":"US",
    "name:ceb_x_preferred":[
        "Colby"
    ],
    "name:deu_x_preferred":[
        "Colby"
    ],
    "name:eng_x_preferred":[
        "Colby"
    ],
    "name:fra_x_preferred":[
        "Colby"
    ],
    "name:ita_x_preferred":[
        "Colby"
    ],
    "name:jpn_x_preferred":[
        "\u30b3\u30eb\u30d3\u30fc"
    ],
    "name:nld_x_preferred":[
        "Colby"
    ],
    "name:pol_x_preferred":[
        "Colby"
    ],
    "name:rus_x_preferred":[
        "\u041a\u043e\u043b\u0431\u0438"
    ],
    "name:srp_x_preferred":[
        "\u041a\u043e\u043b\u0431\u0438"
    ],
    "name:swe_x_preferred":[
        "Colby"
    ],
    "name:ukr_x_preferred":[
        "\u041a\u043e\u043b\u0431\u0456"
    ],
    "name:unk_x_variant":[
        "Coal Bay"
    ],
    "name:urd_x_preferred":[
        "\u06a9\u0648\u0644\u0628\u06cc"
    ],
    "name:vol_x_preferred":[
        "Colby"
    ],
    "qs_pg:aaroncc":"US",
    "qs_pg:gn_country":"US",
    "qs_pg:gn_fcode":"PPL",
    "qs_pg:gn_pop":0,
    "qs_pg:name":"Colby",
    "qs_pg:name_adm0":"United States",
    "qs_pg:name_adm1":"Washington",
    "qs_pg:photos":44,
    "qs_pg:photos_1k":9,
    "qs_pg:photos_9k":1,
    "qs_pg:photos_9r":2,
    "qs_pg:photos_all":44,
    "qs_pg:photos_sr":2,
    "qs_pg:pop_sr":0,
    "qs_pg:qs_pg_placetype":"locality",
    "qs_pg:qs_pg_placetype_gp":"Town",
    "qs_pg:woe_adm0":23424977,
    "woe:adm0_id":23424977,
    "woe:name_adm0":"United States",
    "woe:name_adm1":"Washington",
    "woe:placetype":"Town",
    "wof:name":"Colby",
    "wof:placetype":"locality"
},
  "geometry": {"coordinates":[-122.54568999999999,47.5326],"type":"Point"}
}