{
  "type": "Feature",
  "properties": {
    "gn:admin1_code":"TN",
    "gn:admin2_code":"59",
    "gn:asciiname":"Lovelace",
    "gn:country_code":"US",
    "gn:dem":413,
    "gn:elevation":"414.0",
    "gn:feature_class":"P",
    "gn:feature_code":"PPL",
    "gn:name":"Lovelace",
    "gn:population":0,
    "gn:timezone":"America/New_York",
    "iso:country":"US",
    "name:heb_x_preferred":[
        "\u05dc\u05d0\u05d1\u05dc\u05d9\u05d9\u05e1"
    ],
    "wof:name":"Lovelace",
    "wof:placetype":"locality"
},
  "geometry": {"coordinates":[-82.65682,36.4076],"type":"Point"}
}