{
  "type": "Feature",
  "properties": {
    "gn:admin1_code":"MD",
    "gn:admin2_code":"3.0",
    "gn:asciiname":"Powhatan Village",
    "gn:country_code":"US",
    "gn:dem":25,
    "gn:elevation":"18.0",
    "gn:feature_class":"P",
    "gn:feature_code":"PPL",
    "gn:name":"Powhatan Village",
    "gn:population":0,
    "gn:timezone":"America/New_York",
    "iso:country":"US",
    "wof:name":"Powhatan Village",
    "wof:placetype":"locality"
},
  "geometry": {"coordinates":[-76.57219000000001,39.13344],"type":"Point"}
}