{
  "type": "Feature",
  "properties": {
    "gn:admin1_code":"VA",
    "gn:admin2_code":"185",
    "gn:asciiname":"Green Place",
    "gn:country_code":"US",
    "gn:dem":769,
    "gn:elevation":"766.0",
    "gn:feature_class":"P",
    "gn:feature_code":"PPL",
    "gn:name":"Green Place",
    "gn:population":0,
    "gn:timezone":"America/New_York",
    "iso:country":"US",
    "wof:name":"Green Place",
    "wof:placetype":"locality"
},
  "geometry": {"coordinates":[-81.74011999999998,37.01317],"type":"Point"}
}