{
  "type": "Feature",
  "properties": {
    "gn:admin1_code":"IN",
    "gn:admin2_code":"081",
    "gn:admin3_code":"83924.0",
    "gn:asciiname":"Pebble Run",
    "gn:country_code":"US",
    "gn:dem":209,
    "gn:elevation":"209.0",
    "gn:feature_class":"P",
    "gn:feature_code":"PPL",
    "gn:name":"Pebble Run",
    "gn:population":0,
    "gn:timezone":"America/Indiana/Indianapolis",
    "iso:country":"US",
    "wof:name":"Pebble Run",
    "wof:placetype":"locality"
},
  "geometry": {"coordinates":[-86.19972,39.62139000000001],"type":"Point"}
}