{
  "type": "Feature",
  "properties": {
    "gn:admin1_code":"MN",
    "gn:admin2_code":"077",
    "gn:admin3_code":"4024.0",
    "gn:asciiname":"Judy's East Side Trailer Park",
    "gn:country_code":"US",
    "gn:dem":330,
    "gn:elevation":"332.0",
    "gn:feature_class":"P",
    "gn:feature_code":"PPL",
    "gn:name":"Judy's East Side Trailer Park",
    "gn:population":0,
    "gn:timezone":"America/Chicago",
    "iso:country":"US",
    "wof:name":"Judy's East Side Trailer Park",
    "wof:placetype":"campus"
},
  "geometry": {"coordinates":[-94.57222,48.70833],"type":"Point"}
}