{
  "type": "Feature",
  "properties": {
    "gn:admin1_code":"AL",
    "gn:admin2_code":"131.0",
    "gn:asciiname":"Rehoboth",
    "gn:country_code":"US",
    "gn:dem":85,
    "gn:elevation":"83.0",
    "gn:feature_class":"P",
    "gn:feature_code":"PPL",
    "gn:name":"Rehoboth",
    "gn:population":0,
    "gn:timezone":"America/Chicago",
    "iso:country":"US",
    "name:cat_x_preferred":[
        "Rehoboth"
    ],
    "name:ceb_x_preferred":[
        "Rehoboth"
    ],
    "name:deu_x_preferred":[
        "Rehoboth"
    ],
    "name:eng_x_preferred":[
        "Rehoboth"
    ],
    "name:fra_x_preferred":[
        "Rehoboth"
    ],
    "name:ind_x_preferred":[
        "Rehoboth"
    ],
    "name:ind_x_variant":[
        "Rehobot"
    ],
    "name:ita_x_preferred":[
        "Rehoboth"
    ],
    "name:kor_x_preferred":[
        "\ub974\ud638\ubd07"
    ],
    "name:nld_x_preferred":[
        "Rehoboth"
    ],
    "name:por_x_preferred":[
        "Rehoboth"
    ],
    "name:und_x_variant":[
        "Rehobeth"
    ],
    "name:urd_x_preferred":[
        "\u0631\u06cc\u06c1\u0648\u0628\u0648\u062a\u06be"
    ],
    "name:vie_x_preferred":[
        "Rehoboth"
    ],
    "name:vol_x_preferred":[
        "Rehoboth"
    ],
    "wof:name":"Rehoboth",
    "wof:placetype":"locality"
},
  "geometry": {"coordinates":[-87.38137999999999,32.1957],"type":"Point"}
}