{
  "type": "Feature",
  "properties": {
    "gn:admin1_code":"WV",
    "gn:admin2_code":"77",
    "gn:asciiname":"Hopewell",
    "gn:country_code":"US",
    "gn:dem":528,
    "gn:elevation":"531.0",
    "gn:feature_class":"P",
    "gn:feature_code":"PPL",
    "gn:name":"Hopewell",
    "gn:population":0,
    "gn:timezone":"America/New_York",
    "iso:country":"US",
    "name:cat_x_preferred":[
        "Hopewell"
    ],
    "name:ceb_x_preferred":[
        "Hopewell"
    ],
    "name:deu_x_preferred":[
        "Hopewell"
    ],
    "name:fra_x_preferred":[
        "Hopewell"
    ],
    "name:ita_x_preferred":[
        "Hopewell"
    ],
    "name:jpn_x_preferred":[
        "\u30db\u30fc\u30d7\u30a6\u30a7\u30eb"
    ],
    "name:kor_x_preferred":[
        "\ud638\ud504\uc6f0"
    ],
    "name:nld_x_preferred":[
        "Hopewell"
    ],
    "name:pol_x_preferred":[
        "Hopewell"
    ],
    "name:por_x_preferred":[
        "Hopewell"
    ],
    "name:rus_x_preferred":[
        "\u0425\u043e\u0443\u043f\u0443\u044d\u043b\u043b"
    ],
    "name:srp_x_preferred":[
        "\u0425\u043e\u0443\u043f\u0432\u0435\u043b"
    ],
    "name:swe_x_preferred":[
        "Hopewell"
    ],
    "name:ukr_x_preferred":[
        "\u0413\u043e\u0443\u043f\u0432\u0435\u043b\u043b"
    ],
    "name:vol_x_preferred":[
        "Hopewell"
    ],
    "wof:name":"Hopewell",
    "wof:placetype":"locality"
},
  "geometry": {"coordinates":[-79.67477,39.66369],"type":"Point"}
}