{
  "type": "Feature",
  "properties": {
    "gn:admin1_code":"TN",
    "gn:admin2_code":"179",
    "gn:asciiname":"South Ridge Estates",
    "gn:country_code":"US",
    "gn:dem":551,
    "gn:elevation":"556.0",
    "gn:feature_class":"P",
    "gn:feature_code":"PPL",
    "gn:name":"South Ridge Estates",
    "gn:population":0,
    "gn:timezone":"America/New_York",
    "iso:country":"US",
    "wof:name":"South Ridge Estates",
    "wof:placetype":"locality"
},
  "geometry": {"coordinates":[-82.4075,36.29611],"type":"Point"}
}