{
  "type": "Feature",
  "properties": {
    "gn:admin1_code":"NY",
    "gn:admin2_code":"123.0",
    "gn:admin3_code":"47020.0",
    "gn:asciiname":"Williams Corner",
    "gn:country_code":"US",
    "gn:dem":336,
    "gn:elevation":"332.0",
    "gn:feature_class":"P",
    "gn:feature_code":"PPL",
    "gn:name":"Williams Corner",
    "gn:population":0,
    "gn:timezone":"America/New_York",
    "iso:country":"US",
    "wof:name":"Williams Corner",
    "wof:placetype":"locality"
},
  "geometry": {"coordinates":[-77.25331,42.71284],"type":"Point"}
}