{
  "type": "Feature",
  "properties": {
    "gn:country":"US",
    "gn:fcode":"PPLX",
    "gn:population":0,
    "iso:country":"US",
    "name:ceb_x_preferred":[
        "Hickory Creek"
    ],
    "name:deu_x_preferred":[
        "Hickory Creek"
    ],
    "name:eng_x_preferred":[
        "Hickory Creek"
    ],
    "name:swe_x_preferred":[
        "Hickory Creek"
    ],
    "qs_pg:aaroncc":"US",
    "qs_pg:gn_country":"US",
    "qs_pg:gn_fcode":"PPLX",
    "qs_pg:gn_pop":0,
    "qs_pg:name":"Hickory Creek",
    "qs_pg:name_adm0":"United States",
    "qs_pg:name_adm1":"Illinois",
    "qs_pg:photos":3,
    "qs_pg:photos_1k":1,
    "qs_pg:photos_9k":1,
    "qs_pg:photos_9r":1,
    "qs_pg:photos_all":3,
    "qs_pg:photos_sr":1,
    "qs_pg:pop_sr":0,
    "qs_pg:qs_pg_placetype":"neighbourhood",
    "qs_pg:qs_pg_placetype_gp":"Suburb",
    "qs_pg:woe_adm0":23424977,
    "woe:adm0_id":23424977,
    "woe:name_adm0":"United States",
    "woe:name_adm1":"Illinois",
    "woe:placetype":"Suburb",
    "wof:name":"Hickory Creek",
    "wof:placetype":"neighbourhood",
    "wof:population":362
},
  "geometry": {"coordinates":[-89.15844,42.22113],"type":"Point"}
}