{
  "type": "Feature",
  "properties": {
    "gn:admin1_code":"KY",
    "gn:admin2_code":"61",
    "gn:asciiname":"Rhoda",
    "gn:country_code":"US",
    "gn:dem":175,
    "gn:elevation":"173.0",
    "gn:feature_class":"P",
    "gn:feature_code":"PPL",
    "gn:name":"Rhoda",
    "gn:population":0,
    "gn:timezone":"America/Chicago",
    "iso:country":"US",
    "wof:name":"Rhoda",
    "wof:placetype":"locality"
},
  "geometry": {"coordinates":[-86.22525999999998,37.15588],"type":"Point"}
}