{
  "type": "Feature",
  "properties": {
    "iso:country":"US",
    "name:eng_x_preferred":[
        "Aspinwall Hill"
    ],
    "name:eng_x_variant":[
        "Aspinwall Hl"
    ],
    "qs:gn_adm0_cc":"US",
    "qs:gn_local":4931482,
    "qs:gn_nam_loc":"Brookline, Norfolk, Massachusetts, US",
    "qs:gn_namadm1":"MA",
    "qs:local_max":9122,
    "qs:local_sum":25761,
    "qs:localhoods":13,
    "qs:name":"Aspinwall Hill",
    "qs:name_adm0":"United States",
    "qs:name_adm1":"Massachusetts",
    "qs:name_adm2":"Norfolk",
    "qs:name_local":"Brookline",
    "qs:photo_max":88,
    "qs:photo_sum":317,
    "qs:placetype":"Suburb",
    "qs:quad_count":15,
    "qs:woe_adm0":23424977,
    "qs:woe_adm1":2347580,
    "qs:woe_adm2":12588710,
    "qs:woe_lau":0,
    "qs:woe_local":2369930,
    "qs:woe_ver":"7.10.0",
    "wof:lang":[
        "eng"
    ],
    "wof:name":"Aspinwall Hill",
    "wof:placetype":"neighbourhood",
    "wof:population":2401,
    "zs:blockids":[
        250214005003001,
        250214005003000,
        250214005002005,
        250214005001007,
        250214007003010,
        250214005002003,
        250214005001011,
        250214006002023,
        250214005002002,
        250214005003014,
        250214005003009,
        250214005003005,
        250214005003008,
        250214005002001,
        250214005002006,
        250214007003000,
        250214007003001,
        250214005003002,
        250214005003003,
        250214005003004,
        250214005003007,
        250214005002004,
        250214005003006
    ],
    "zs:housing10":997,
    "zs:pop10":2401
},
  "geometry": {"coordinates":[-71.13196600000001,42.335847],"type":"Point"}
}