{
  "type": "Feature",
  "properties": {
    "gn:admin1_code":"AR",
    "gn:admin2_code":"45.0",
    "gn:admin3_code":"94083.0",
    "gn:asciiname":"Gentry Corner",
    "gn:country_code":"US",
    "gn:dem":109,
    "gn:elevation":"110.0",
    "gn:feature_class":"P",
    "gn:feature_code":"PPL",
    "gn:name":"Gentry Corner",
    "gn:population":0,
    "gn:timezone":"America/Chicago",
    "iso:country":"US",
    "wof:name":"Gentry Corner",
    "wof:placetype":"locality"
},
  "geometry": {"coordinates":[-92.29098999999999,34.95759],"type":"Point"}
}