{
  "type": "Feature",
  "properties": {
    "gn:admin1_code":"CT",
    "gn:admin2_code":"7.0",
    "gn:admin3_code":"47360.0",
    "gn:asciiname":"Highland Estates",
    "gn:country_code":"US",
    "gn:dem":44,
    "gn:elevation":"40.0",
    "gn:feature_class":"P",
    "gn:feature_code":"PPL",
    "gn:name":"Highland Estates",
    "gn:population":0,
    "gn:timezone":"America/New_York",
    "iso:country":"US",
    "wof:name":"Highland Estates",
    "wof:placetype":"locality"
},
  "geometry": {"coordinates":[-72.70148,41.59454],"type":"Point"}
}