{
  "type": "Feature",
  "properties": {
    "gn:admin1_code":"IN",
    "gn:admin2_code":"93.0",
    "gn:admin3_code":"30258.0",
    "gn:asciiname":"Buddha",
    "gn:country_code":"US",
    "gn:dem":214,
    "gn:elevation":"213.0",
    "gn:feature_class":"P",
    "gn:feature_code":"PPL",
    "gn:name":"Buddha",
    "gn:population":0,
    "gn:timezone":"America/Indiana/Indianapolis",
    "iso:country":"US",
    "name:azb_x_preferred":[
        "\u0628\u0648\u062f\u0627"
    ],
    "name:eng_x_preferred":[
        "Buddha"
    ],
    "name:fas_x_preferred":[
        "\u0628\u0648\u062f\u0627"
    ],
    "name:und_x_variant":[
        "Flynns Cross Roads"
    ],
    "name:vol_x_preferred":[
        "Buddha"
    ],
    "wof:name":"Buddha",
    "wof:placetype":"locality"
},
  "geometry": {"coordinates":[-86.40666,38.792],"type":"Point"}
}