{
  "type": "Feature",
  "properties": {
    "gn:admin1_code":"WA",
    "gn:admin2_code":"63.0",
    "gn:asciiname":"Mock",
    "gn:country_code":"US",
    "gn:dem":703,
    "gn:elevation":"706.0",
    "gn:feature_class":"P",
    "gn:feature_code":"PPL",
    "gn:name":"Mock",
    "gn:population":0,
    "gn:timezone":"America/Los_Angeles",
    "iso:country":"US",
    "name:deu_x_preferred":[
        "Mock"
    ],
    "name:fra_x_preferred":[
        "Mock"
    ],
    "name:jpn_x_preferred":[
        "\u30e2\u30c3\u30af"
    ],
    "wof:name":"Mock",
    "wof:placetype":"locality"
},
  "geometry": {"coordinates":[-117.65021000000002,47.39711],"type":"Point"}
}