{
  "type": "Feature",
  "properties": {
    "gn:admin1_code":"NM",
    "gn:admin2_code":"39",
    "gn:asciiname":"Amargo",
    "gn:country_code":"US",
    "gn:dem":2137,
    "gn:elevation":"2136.0",
    "gn:feature_class":"P",
    "gn:feature_code":"PPL",
    "gn:name":"Amargo",
    "gn:population":0,
    "gn:timezone":"America/Denver",
    "iso:country":"US",
    "name:deu_x_preferred":[
        "Amargo"
    ],
    "name:spa_x_preferred":[
        "Amargo"
    ],
    "wof:name":"Amargo",
    "wof:placetype":"locality"
},
  "geometry": {"coordinates":[-106.8917,36.93779],"type":"Point"}
}