{
  "type": "Feature",
  "properties": {
    "iso:country":"US",
    "name:eng_x_preferred":[
        "Carolina Heights"
    ],
    "wof:name":"Carolina Heights",
    "wof:placetype":"neighbourhood",
    "wof:population":1032,
    "zs:area_m":1074308.521674,
    "zs:blockids":[
        371470007021017,
        371470007022030,
        371470007022026,
        371470005011011,
        371470007022028,
        371470007021018,
        371470007021019,
        371470007022029,
        371470007021015,
        371470007021012,
        371470007021005,
        371470007021014,
        371470007022027
    ],
    "zs:housing10":432,
    "zs:label":"Carolina Heights",
    "zs:pop10":1032
},
  "geometry": {"coordinates":[-77.38611,35.591712],"type":"Point"}
}