{
  "type": "Feature",
  "properties": {
    "gn:admin1_code":"IL",
    "gn:admin2_code":"127",
    "gn:asciiname":"Massac City",
    "gn:country_code":"US",
    "gn:dem":106,
    "gn:elevation":"103.0",
    "gn:feature_class":"P",
    "gn:feature_code":"PPL",
    "gn:name":"Massac City",
    "gn:population":0,
    "gn:timezone":"America/Chicago",
    "iso:country":"US",
    "name:eng_x_preferred":[
        "Massac City"
    ],
    "name:und_x_variant":[
        "Bellegarde",
        "Belgrade",
        "Massac Creek"
    ],
    "wof:name":"Massac City",
    "wof:placetype":"locality"
},
  "geometry": {"coordinates":[-88.71866,37.14367],"type":"Point"}
}