{
  "type": "Feature",
  "properties": {
    "gn:admin1_code":"IL",
    "gn:admin2_code":"197",
    "gn:admin3_code":"76212.0",
    "gn:asciiname":"Fairway Estates",
    "gn:country_code":"US",
    "gn:dem":187,
    "gn:elevation":"186.0",
    "gn:feature_class":"P",
    "gn:feature_code":"PPL",
    "gn:name":"Fairway Estates",
    "gn:population":0,
    "gn:timezone":"America/Chicago",
    "iso:country":"US",
    "wof:name":"Fairway Estates",
    "wof:placetype":"locality"
},
  "geometry": {"coordinates":[-88.14860999999998,41.51694000000001],"type":"Point"}
}