{
  "type": "Feature",
  "properties": {
    "gn:admin1_code":"KS",
    "gn:admin2_code":"55.0",
    "gn:admin3_code":"25325.0",
    "gn:asciiname":"East Garden Mobile Home Village",
    "gn:country_code":"US",
    "gn:dem":861,
    "gn:elevation":"859.0",
    "gn:feature_class":"P",
    "gn:feature_code":"PPL",
    "gn:name":"East Garden Mobile Home Village",
    "gn:population":0,
    "gn:timezone":"America/Chicago",
    "iso:country":"US",
    "wof:name":"East Garden Mobile Home Village",
    "wof:placetype":"campus"
},
  "geometry": {"coordinates":[-100.82553,37.96358],"type":"Point"}
}