{
  "type": "Feature",
  "properties": {
    "gn:admin1_code":"KS",
    "gn:admin2_code":"61",
    "gn:admin3_code":"43500.0",
    "gn:asciiname":"Wreford",
    "gn:country_code":"US",
    "gn:dem":347,
    "gn:elevation":"346.0",
    "gn:feature_class":"P",
    "gn:feature_code":"PPL",
    "gn:name":"Wreford",
    "gn:population":0,
    "gn:timezone":"America/Chicago",
    "iso:country":"US",
    "wof:name":"Wreford",
    "wof:placetype":"locality"
},
  "geometry": {"coordinates":[-96.84862,38.96167],"type":"Point"}
}