{
  "type": "Feature",
  "properties": {
    "gn:admin1_code":"FL",
    "gn:admin2_code":"127.0",
    "gn:asciiname":"Bayview Trailer Park",
    "gn:country_code":"US",
    "gn:dem":1,
    "gn:elevation":"1.0",
    "gn:feature_class":"P",
    "gn:feature_code":"PPL",
    "gn:name":"Bayview Trailer Park",
    "gn:population":0,
    "gn:timezone":"America/New_York",
    "iso:country":"US",
    "wof:name":"Bayview Trailer Park",
    "wof:placetype":"campus"
},
  "geometry": {"coordinates":[-80.961,29.0515],"type":"Point"}
}