{
  "type": "Feature",
  "properties": {
    "iso:country":"US",
    "name:eng_x_preferred":[
        "Bulls Head"
    ],
    "wof:name":"Bulls Head",
    "wof:placetype":"neighbourhood",
    "wof:population":24,
    "zs:area_m":2638588.047872,
    "zs:blockids":[
        360270300002000
    ],
    "zs:housing10":17,
    "zs:label":"Bulls Head",
    "zs:pop10":24
},
  "geometry": {"coordinates":[-73.78394299999999,41.914251],"type":"Point"}
}