{
  "type": "Feature",
  "properties": {
    "gn:admin1_code":"NC",
    "gn:admin2_code":"159.0",
    "gn:admin3_code":"92860.0",
    "gn:asciiname":"Pittsburg",
    "gn:country_code":"US",
    "gn:dem":261,
    "gn:elevation":"262.0",
    "gn:feature_class":"P",
    "gn:feature_code":"PPL",
    "gn:name":"Pittsburg",
    "gn:population":0,
    "gn:timezone":"America/New_York",
    "iso:country":"US",
    "name:rus_x_preferred":[
        "\u041f\u0438\u0442\u0441\u0431\u0443\u0440\u0433"
    ],
    "wof:name":"Pittsburg",
    "wof:placetype":"locality"
},
  "geometry": {"coordinates":[-80.70034,35.82514000000001],"type":"Point"}
}