{
  "type": "Feature",
  "properties": {
    "gn:country":"US",
    "gn:fcode":"PPL",
    "gn:population":0,
    "iso:country":"US",
    "name:azb_x_preferred":[
        "\u0628\u06cc\u0648\u0644\u0627"
    ],
    "name:bar_x_preferred":[
        "Beulah"
    ],
    "name:cym_x_preferred":[
        "Beulah"
    ],
    "name:deu_x_preferred":[
        "Beulah"
    ],
    "name:eng_x_preferred":[
        "Beulah"
    ],
    "name:fas_x_preferred":[
        "\u0628\u06cc\u0648\u0644\u0627"
    ],
    "name:fra_x_preferred":[
        "Beulah"
    ],
    "name:hat_x_preferred":[
        "Beulah"
    ],
    "name:jpn_x_preferred":[
        "\u30d3\u30e5\u30fc\u30e9\u30fc"
    ],
    "name:vol_x_preferred":[
        "Beulah"
    ],
    "name:zho_x_preferred":[
        "\u6bd4\u5c24\u62c9"
    ],
    "qs_pg:aaroncc":"US",
    "qs_pg:gn_country":"US",
    "qs_pg:gn_fcode":"PPL",
    "qs_pg:gn_pop":0,
    "qs_pg:name":"Beulah",
    "qs_pg:name_adm0":"United States",
    "qs_pg:name_adm1":"Alabama",
    "qs_pg:photos_9r":0,
    "qs_pg:photos_sr":0,
    "qs_pg:pop_sr":0,
    "qs_pg:qs_pg_placetype":"locality",
    "qs_pg:qs_pg_placetype_gp":"Town",
    "qs_pg:woe_adm0":23424977,
    "woe:adm0_id":23424977,
    "woe:name_adm0":"United States",
    "woe:name_adm1":"Alabama",
    "woe:placetype":"Town",
    "wof:name":"Beulah",
    "wof:placetype":"locality"
},
  "geometry": {"coordinates":[-85.18216,32.71124],"type":"Point"}
}