{
  "type": "Feature",
  "properties": {
    "gn:gn_country":"US",
    "gn:gn_fcode":"PPL",
    "gn:gn_pop":1612,
    "gn:population":1612,
    "iso:country":"US",
    "name:eng_x_preferred":[
        "Keokea"
    ],
    "name:fra_x_preferred":[
        "Keokea"
    ],
    "name:jpn_x_preferred":[
        "\u30b1\u30aa\u30b1\u30a2"
    ],
    "name:spa_x_preferred":[
        "Keokea"
    ],
    "name:srp_x_preferred":[
        "\u041a\u0435\u043e\u043a\u0435\u0430"
    ],
    "qs_pg:aaroncc":"US",
    "qs_pg:gn_country":"US",
    "qs_pg:gn_fcode":"PPL",
    "qs_pg:gn_pop":1612,
    "qs_pg:name":"K\u0113\u014dkea",
    "qs_pg:photos_9r":0,
    "qs_pg:photos_sr":0,
    "qs_pg:pop_sr":5,
    "qs_pg:qs_pg_placetype":"locality",
    "wof:name":"K\u0113\u014dkea",
    "wof:placetype":"locality",
    "wof:population":1612
},
  "geometry": {"coordinates":[-156.35833,20.70861],"type":"Point"}
}