{
  "type": "Feature",
  "properties": {
    "gn:country":"US",
    "gn:fcode":"PPL",
    "gn:population":1612,
    "iso:country":"US",
    "name:ceb_x_preferred":[
        "K\u0113\u014dkea"
    ],
    "name:che_x_preferred":[
        "\u041a\u0438\u043e\u043a\u0438\u0430"
    ],
    "name:eng_x_preferred":[
        "Keokea"
    ],
    "name:fra_x_preferred":[
        "Keokea"
    ],
    "name:gle_x_preferred":[
        "Keokea"
    ],
    "name:jpn_x_preferred":[
        "\u30b1\u30aa\u30b1\u30a2"
    ],
    "name:lld_x_preferred":[
        "Keokea"
    ],
    "name:nld_x_preferred":[
        "K\u0113\u014dkea"
    ],
    "name:pol_x_preferred":[
        "Keokea"
    ],
    "name:spa_x_preferred":[
        "Keokea"
    ],
    "name:srp_x_preferred":[
        "\u041a\u0435\u043e\u043a\u0435\u0430"
    ],
    "name:tat_x_preferred":[
        "\u041a\u0438\u043e\u043a\u0438\u0430"
    ],
    "name:ukr_x_preferred":[
        "\u041a\u0456\u043e\u043a\u0456\u0430"
    ],
    "name:zho_x_preferred":[
        "\u51f1\u5967\u57fa"
    ],
    "qs_pg:aaroncc":"US",
    "qs_pg:gn_country":"US",
    "qs_pg:gn_fcode":"PPL",
    "qs_pg:gn_pop":1612,
    "qs_pg:name":"K\u0113\u014dkea",
    "qs_pg:photos_9r":0,
    "qs_pg:photos_sr":0,
    "qs_pg:pop_sr":5,
    "qs_pg:qs_pg_placetype":"locality",
    "wof:name":"K\u0113\u014dkea",
    "wof:placetype":"locality",
    "wof:population":1612
},
  "geometry": {"coordinates":[-156.35833,20.70861],"type":"Point"}
}