{
  "type": "Feature",
  "properties": {
    "gn:admin1_code":"GA",
    "gn:admin2_code":"59.0",
    "gn:asciiname":"North Place",
    "gn:country_code":"US",
    "gn:dem":221,
    "gn:elevation":"214.0",
    "gn:feature_class":"P",
    "gn:feature_code":"PPL",
    "gn:name":"North Place",
    "gn:population":0,
    "gn:timezone":"America/New_York",
    "iso:country":"US",
    "wof:name":"North Place",
    "wof:placetype":"locality"
},
  "geometry": {"coordinates":[-83.3796,33.99928],"type":"Point"}
}