{
  "type": "Feature",
  "properties": {
    "gn:admin1_code":"GA",
    "gn:admin2_code":"139",
    "gn:asciiname":"Point View Landing",
    "gn:country_code":"US",
    "gn:dem":357,
    "gn:elevation":"355.0",
    "gn:feature_class":"P",
    "gn:feature_code":"PPL",
    "gn:name":"Point View Landing",
    "gn:population":0,
    "gn:timezone":"America/New_York",
    "iso:country":"US",
    "wof:name":"Point View Landing",
    "wof:placetype":"locality"
},
  "geometry": {"coordinates":[-83.88601,34.30982],"type":"Point"}
}