{
  "type": "Feature",
  "properties": {
    "gn:admin1_code":"CA",
    "gn:admin2_code":"17.0",
    "gn:asciiname":"Aukum",
    "gn:country_code":"US",
    "gn:dem":658,
    "gn:elevation":"657.0",
    "gn:feature_class":"P",
    "gn:feature_code":"PPL",
    "gn:name":"Aukum",
    "gn:population":0,
    "gn:timezone":"America/Los_Angeles",
    "iso:country":"US",
    "name:azb_x_preferred":[
        "\u0622\u06a9\u0627\u0645"
    ],
    "name:eng_x_preferred":[
        "Aukum"
    ],
    "name:eng_x_variant":[
        "Mt. Aukum",
        "Mount Aukum"
    ],
    "name:fas_x_preferred":[
        "\u0622\u06a9\u0627\u0645"
    ],
    "name:spa_x_preferred":[
        "Aukum"
    ],
    "name:und_x_variant":[
        "Aukum Fork"
    ],
    "name:zho_x_preferred":[
        "\u5967\u5eab\u59c6"
    ],
    "wof:name":"Aukum",
    "wof:placetype":"locality"
},
  "geometry": {"coordinates":[-120.7266,38.55713],"type":"Point"}
}