{
  "type": "Feature",
  "properties": {
    "gn:admin1_code":"HI",
    "gn:admin2_code":"1.0",
    "gn:asciiname":"Komohana Kai",
    "gn:country_code":"US",
    "gn:dem":70,
    "gn:elevation":"67.0",
    "gn:feature_class":"P",
    "gn:feature_code":"PPL",
    "gn:name":"Komohana Kai",
    "gn:population":0,
    "gn:timezone":"Pacific/Honolulu",
    "iso:country":"US",
    "wof:name":"Komohana Kai",
    "wof:placetype":"locality"
},
  "geometry": {"coordinates":[-155.96878999999996,19.61044],"type":"Point"}
}