{
  "type": "Feature",
  "properties": {
    "gn:admin1_code":"VA",
    "gn:admin2_code":"83",
    "gn:asciiname":"Hickory Grove",
    "gn:country_code":"US",
    "gn:dem":182,
    "gn:elevation":"180.0",
    "gn:feature_class":"P",
    "gn:feature_code":"PPL",
    "gn:name":"Hickory Grove",
    "gn:population":0,
    "gn:timezone":"America/New_York",
    "iso:country":"US",
    "name:ceb_x_preferred":[
        "Hickory Grove"
    ],
    "name:deu_x_preferred":[
        "Hickory Grove"
    ],
    "name:ita_x_preferred":[
        "Hickory Grove"
    ],
    "name:pol_x_preferred":[
        "Hickory Grove"
    ],
    "wof:name":"Hickory Grove",
    "wof:placetype":"locality"
},
  "geometry": {"coordinates":[-79.09613,36.92681],"type":"Point"}
}