{
  "type": "Feature",
  "properties": {
    "iso:country":"US",
    "name:eng_x_preferred":[
        "Stonegate"
    ],
    "qs:gn_adm0_cc":"US",
    "qs:gn_local":4943170,
    "qs:gn_nam_loc":"Marlborough, Middlesex, Massachusetts, US",
    "qs:gn_namadm1":"MA",
    "qs:local_max":897,
    "qs:local_sum":2573,
    "qs:localhoods":7,
    "qs:name":"Stonegate",
    "qs:name_adm0":"United States",
    "qs:name_adm1":"Massachusetts",
    "qs:name_adm2":"Middlesex",
    "qs:name_local":"Marlborough",
    "qs:photo_max":72,
    "qs:photo_sum":298,
    "qs:placetype":"Suburb",
    "qs:quad_count":25,
    "qs:woe_adm0":23424977,
    "qs:woe_adm1":2347580,
    "qs:woe_adm2":12588708,
    "qs:woe_lau":0,
    "qs:woe_local":2445915,
    "qs:woe_ver":"7.10.0",
    "wd:wordcount":55,
    "wof:lang":[
        "eng"
    ],
    "wof:name":"Stonegate",
    "wof:placetype":"neighbourhood",
    "wof:population":2441,
    "zs:blockids":[
        250173214001054,
        250173214002002,
        250173214001078,
        250173214002014,
        250173214002003,
        250173214002009,
        250173213004010,
        250173214002022,
        250173214002033,
        250173214002006,
        250173214002021,
        250173214002016,
        250173214002011,
        250173213003019,
        250173214002042,
        250173214002030,
        250173214002023,
        250173214001074,
        250173214002005,
        250173214002039,
        250173213004011,
        250173214002024,
        250173214002034,
        250173214001075,
        250173214002045,
        250173214002049,
        250173214002013,
        250173214002036,
        250173214002015,
        250173214002004,
        250173214002017,
        250173214001060,
        250173214001076,
        250173213004017,
        250173214002040,
        250173214002028,
        250173214002043,
        250173214002026,
        250173214002031,
        250173214001064,
        250173214001063,
        250173214002008,
        250173214002041,
        250173214002044,
        250173214002019,
        250173214002007,
        250173213004012,
        250173214002032,
        250173214002018,
        250173214002046,
        250173214002025,
        250173213003018,
        250173213004008,
        250173214001061,
        250173214002010,
        250173214002029,
        250173213004014,
        250173214002048,
        250173214002037,
        250173214001062,
        250173214002047,
        250173213004016,
        250173214002012,
        250173214002027,
        250173213004015,
        250173214002035,
        250173214002038,
        250173214001077,
        250173214001053
    ],
    "zs:housing10":1011,
    "zs:pop10":2441
},
  "geometry": {"coordinates":[-71.57727199999999,42.323181],"type":"Point"}
}