{
  "type": "Feature",
  "properties": {
    "gn:admin1_code":"LA",
    "gn:admin2_code":"47.0",
    "gn:asciiname":"Bruly La Croix",
    "gn:country_code":"US",
    "gn:dem":3,
    "gn:elevation":"3.0",
    "gn:feature_class":"P",
    "gn:feature_code":"PPL",
    "gn:name":"Bruly La Croix",
    "gn:population":0,
    "gn:timezone":"America/Chicago",
    "iso:country":"US",
    "name:eng_x_preferred":[
        "Bruly La Croix"
    ],
    "name:und_x_variant":[
        "Bruly Lacroix"
    ],
    "wof:name":"Bruly La Croix",
    "wof:placetype":"locality"
},
  "geometry": {"coordinates":[-91.19427,30.15075],"type":"Point"}
}