{
  "type": "Feature",
  "properties": {
    "iso:country":"US",
    "name:eng_x_preferred":[
        "Normandy Shores"
    ],
    "name:eng_x_variant":[
        "Normandy Shrs"
    ],
    "name:nld_x_preferred":[
        "Normandy Shores"
    ],
    "qs:gn_adm0_cc":"US",
    "qs:gn_fcode":"PPL",
    "qs:gn_local":4164143,
    "qs:gn_nam_loc":"Miami Beach, Miami-Dade, Florida, US",
    "qs:gn_namadm1":"FL",
    "qs:gn_name":"Normandy Shores",
    "qs:local_max":14938,
    "qs:local_sum":54620,
    "qs:localhoods":15,
    "qs:name":"Normandy Shores",
    "qs:name_adm0":"United States",
    "qs:name_adm1":"Florida",
    "qs:name_adm2":"Miami-Dade",
    "qs:name_local":"Miami Beach",
    "qs:photo_max":2,
    "qs:photo_sum":2,
    "qs:placetype":"Suburb",
    "qs:quad_count":1,
    "qs:woe_adm0":23424977,
    "qs:woe_adm1":2347568,
    "qs:woe_adm2":12587815,
    "qs:woe_lau":0,
    "qs:woe_local":2450080,
    "qs:woe_ver":"7.10.0",
    "wd:wordcount":125,
    "wof:lang":[
        "eng"
    ],
    "wof:name":"Normandy Shores",
    "wof:placetype":"neighbourhood",
    "wof:population":8494,
    "zs:blockids":[
        120860039161000,
        120860039181004,
        120860039181000,
        120860039173009,
        120860039161014,
        120860039173004,
        120860039161003,
        120860039173001,
        120860039161013,
        120860039161017,
        120860039161007,
        120860039161005,
        120860039181002,
        120860039181003,
        120860039171001,
        120860039173010,
        120860039173003,
        120860039182001,
        120860039182002,
        120860039182000,
        120860039161015,
        120860039182004,
        120860039161002,
        120860039181005,
        120860039181006,
        120860039173000,
        120860039173006,
        120860039173007,
        120860039161012,
        120860039121007,
        120860039181001,
        120860039171000,
        120860039161008,
        120860039161001,
        120860013011000,
        120860039173008,
        120860039173005,
        120860039173002,
        120860039172000,
        120860039161011,
        120860039182003,
        120860039161009,
        120860039161010
    ],
    "zs:housing10":5169,
    "zs:pop10":8494
},
  "geometry": {"coordinates":[-80.13988500000001,25.85943],"type":"Point"}
}