{
  "type": "Feature",
  "properties": {
    "gn:admin1_code":"TX",
    "gn:admin2_code":"61",
    "gn:asciiname":"El Nogal Colonia",
    "gn:country_code":"US",
    "gn:dem":18,
    "gn:elevation":"14.0",
    "gn:feature_class":"P",
    "gn:feature_code":"PPL",
    "gn:name":"El Nogal Colonia",
    "gn:population":0,
    "gn:timezone":"America/Chicago",
    "iso:country":"US",
    "name:eng_x_preferred":[
        "El Nogal Colonia"
    ],
    "name:und_x_variant":[
        "Santo Rosa Number 15 Colonia"
    ],
    "wof:name":"El Nogal Colonia",
    "wof:placetype":"locality"
},
  "geometry": {"coordinates":[-97.81527,26.25841],"type":"Point"}
}