{
  "type": "Feature",
  "properties": {
    "iso:country":"US",
    "name:eng_x_preferred":[
        "Juniper Heights"
    ],
    "wof:name":"Juniper Heights",
    "wof:placetype":"neighbourhood",
    "wof:population":315,
    "zs:area_m":27631166.779399,
    "zs:blockids":[
        80679404002079,
        80679404002096,
        80679404001045,
        80679404001230,
        80679404002098,
        80679404002080,
        80679404002078,
        80679404002099,
        80679404002077,
        80679404001049
    ],
    "zs:housing10":147,
    "zs:label":"Juniper Heights",
    "zs:pop10":315
},
  "geometry": {"coordinates":[-107.849356,37.139213],"type":"Point"}
}