{
  "type": "Feature",
  "properties": {
    "gn:admin1_code":"VA",
    "gn:admin2_code":"33.0",
    "gn:asciiname":"Bagdad",
    "gn:country_code":"US",
    "gn:dem":66,
    "gn:elevation":"68.0",
    "gn:feature_class":"P",
    "gn:feature_code":"PPL",
    "gn:name":"Bagdad",
    "gn:population":0,
    "gn:timezone":"America/New_York",
    "iso:country":"US",
    "name:azb_x_preferred":[
        "\u0628\u063a\u062f\u0627\u062f"
    ],
    "name:fas_x_preferred":[
        "\u0628\u063a\u062f\u0627\u062f"
    ],
    "name:mkd_x_preferred":[
        "\u0411\u0430\u0433\u0434\u0430\u0434"
    ],
    "wof:name":"Bagdad",
    "wof:placetype":"locality"
},
  "geometry": {"coordinates":[-77.42331,37.90542],"type":"Point"}
}