{
  "type": "Feature",
  "properties": {
    "gn:admin1_code":"ND",
    "gn:admin2_code":"55.0",
    "gn:admin3_code":"80670.0",
    "gn:asciiname":"Riverdale Junction",
    "gn:country_code":"US",
    "gn:dem":608,
    "gn:elevation":"610.0",
    "gn:feature_class":"P",
    "gn:feature_code":"PPL",
    "gn:name":"Riverdale Junction",
    "gn:population":0,
    "gn:timezone":"America/Chicago",
    "iso:country":"US",
    "wof:name":"Riverdale Junction",
    "wof:placetype":"locality"
},
  "geometry": {"coordinates":[-101.17515,47.49889],"type":"Point"}
}