{
  "type": "Feature",
  "properties": {
    "gn:admin1_code":"FL",
    "gn:admin2_code":"123.0",
    "gn:asciiname":"Secotan",
    "gn:country_code":"US",
    "gn:dem":20,
    "gn:elevation":"14.0",
    "gn:feature_class":"P",
    "gn:feature_code":"PPL",
    "gn:name":"Secotan",
    "gn:population":0,
    "gn:timezone":"America/New_York",
    "iso:country":"US",
    "name:deu_x_preferred":[
        "Secotan"
    ],
    "name:hrv_x_preferred":[
        "Secotan"
    ],
    "name:srp_x_preferred":[
        "\u0421\u0435\u043a\u043e\u0442\u0430\u043d"
    ],
    "wof:name":"Secotan",
    "wof:placetype":"locality"
},
  "geometry": {"coordinates":[-83.63432,30.17632],"type":"Point"}
}