{
  "type": "Feature",
  "properties": {
    "gn:country":"US",
    "gn:fcode":"PPL",
    "gn:population":0,
    "iso:country":"US",
    "name:ceb_x_preferred":[
        "Dee"
    ],
    "name:ces_x_preferred":[
        "Dee"
    ],
    "name:cym_x_preferred":[
        "Dee"
    ],
    "name:deu_x_preferred":[
        "Dee"
    ],
    "name:eng_x_preferred":[
        "Dee"
    ],
    "name:fin_x_preferred":[
        "Dee"
    ],
    "name:fra_x_preferred":[
        "Dee"
    ],
    "name:lmo_x_preferred":[
        "Dee"
    ],
    "name:nds_x_preferred":[
        "Dee"
    ],
    "name:nld_x_preferred":[
        "Dee"
    ],
    "name:nor_x_preferred":[
        "Dee"
    ],
    "name:pol_x_preferred":[
        "Dee"
    ],
    "name:por_x_preferred":[
        "Dee"
    ],
    "name:slk_x_preferred":[
        "Dee"
    ],
    "name:swe_x_preferred":[
        "Dee"
    ],
    "name:und_x_variant":[
        "Stewardson Furnace"
    ],
    "qs_pg:aaroncc":"US",
    "qs_pg:gn_country":"US",
    "qs_pg:gn_fcode":"PPL",
    "qs_pg:gn_pop":0,
    "qs_pg:name":"Dee",
    "qs_pg:name_adm0":"United States",
    "qs_pg:name_adm1":"Pennsylvania",
    "qs_pg:photos":1,
    "qs_pg:photos_1k":1,
    "qs_pg:photos_9k":1,
    "qs_pg:photos_9r":1,
    "qs_pg:photos_all":1,
    "qs_pg:photos_sr":1,
    "qs_pg:pop_sr":0,
    "qs_pg:qs_pg_placetype":"neighbourhood",
    "qs_pg:qs_pg_placetype_gp":"Suburb",
    "qs_pg:woe_adm0":23424977,
    "woe:adm0_id":23424977,
    "woe:name_adm0":"United States",
    "woe:name_adm1":"Pennsylvania",
    "woe:placetype":"Suburb",
    "wof:name":"Dee",
    "wof:placetype":"neighbourhood"
},
  "geometry": {"coordinates":[-79.44338,40.93506],"type":"Point"}
}