{
  "type": "Feature",
  "properties": {
    "gn:country":"US",
    "gn:fcode":"PPL",
    "gn:population":0,
    "iso:country":"US",
    "name:deu_x_preferred":[
        "Markle"
    ],
    "name:eng_x_preferred":[
        "Markle"
    ],
    "name:fra_x_preferred":[
        "Markle"
    ],
    "name:ita_x_preferred":[
        "Markle"
    ],
    "name:spa_x_preferred":[
        "Markle"
    ],
    "qs_pg:aaroncc":"US",
    "qs_pg:gn_country":"US",
    "qs_pg:gn_fcode":"PPL",
    "qs_pg:gn_pop":0,
    "qs_pg:name":"Markle",
    "qs_pg:name_adm0":"United States",
    "qs_pg:name_adm1":"Pennsylvania",
    "qs_pg:photos":158,
    "qs_pg:photos_1k":32,
    "qs_pg:photos_9k":1,
    "qs_pg:photos_9r":4,
    "qs_pg:photos_all":158,
    "qs_pg:photos_sr":4,
    "qs_pg:pop_sr":5,
    "qs_pg:qs_pg_placetype":"neighbourhood",
    "qs_pg:qs_pg_placetype_gp":"Suburb",
    "qs_pg:woe_adm0":23424977,
    "woe:adm0_id":23424977,
    "woe:name_adm0":"United States",
    "woe:name_adm1":"Pennsylvania",
    "woe:placetype":"Suburb",
    "wof:name":"Markle",
    "wof:placetype":"neighbourhood",
    "wof:population":5274
},
  "geometry": {"coordinates":[-79.64366,40.57257],"type":"Point"}
}