{
  "type": "Feature",
  "properties": {
    "iso:country":"US",
    "name:cat_x_preferred":[
        "Willow Creek"
    ],
    "name:deu_x_preferred":[
        "Willow Creek"
    ],
    "name:eng_x_preferred":[
        "Willow Creek"
    ],
    "name:ita_x_preferred":[
        "Willow Creek"
    ],
    "name:nld_x_preferred":[
        "Willow Creek"
    ],
    "name:nor_x_preferred":[
        "Willow Creek"
    ],
    "name:pol_x_preferred":[
        "Willow Creek"
    ],
    "name:por_x_preferred":[
        "Willow Creek"
    ],
    "name:srp_x_preferred":[
        "\u0412\u0438\u043b\u043e\u0443 \u041a\u0440\u0438\u043a"
    ],
    "name:swe_x_preferred":[
        "Willow Creek"
    ],
    "name:ukr_x_preferred":[
        "\u0412\u0456\u043b\u043b\u043e\u0443-\u041a\u0440\u0456\u043a"
    ],
    "name:vol_x_preferred":[
        "Willow Creek"
    ],
    "wof:name":"Willow Creek",
    "wof:placetype":"neighbourhood",
    "wof:population":138,
    "zs:area_m":89153.4143,
    "zs:blockids":[
        490351113062005,
        490351113041021
    ],
    "zs:housing10":44,
    "zs:label":"Willow Creek",
    "zs:pop10":138
},
  "geometry": {"coordinates":[-111.81641500000001,40.604161],"type":"Point"}
}