{
  "type": "Feature",
  "properties": {
    "gn:elevation":56,
    "iso:country":"US",
    "name:eng_x_preferred":[
        "Munroe Station"
    ],
    "name:eng_x_variant":[
        "Munroe Sta"
    ],
    "qs:gn_adm0_cc":"US",
    "qs:gn_fcode":"PPL",
    "qs:gn_local":4941935,
    "qs:gn_nam_loc":"Lexington, Middlesex, Massachusetts, US",
    "qs:gn_namadm1":"MA",
    "qs:gn_name":"Munroe Station",
    "qs:local_max":2709,
    "qs:local_sum":5252,
    "qs:localhoods":9,
    "qs:name":"Munroe Station",
    "qs:name_adm0":"United States",
    "qs:name_adm1":"Massachusetts",
    "qs:name_adm2":"Middlesex",
    "qs:name_local":"Lexington",
    "qs:photo_max":255,
    "qs:photo_sum":555,
    "qs:placetype":"Suburb",
    "qs:quad_count":18,
    "qs:woe_adm0":23424977,
    "qs:woe_adm1":2347580,
    "qs:woe_adm2":12588708,
    "qs:woe_funk":"Parented by a neighborhood",
    "qs:woe_lau":0,
    "qs:woe_local":2438840,
    "qs:woe_ver":"7.10.0",
    "wd:wordcount":84,
    "wof:lang":[
        "eng"
    ],
    "wof:name":"Munroe Station",
    "wof:placetype":"neighbourhood",
    "wof:population":2511,
    "zs:blockids":[
        250173585002006,
        250173584001024,
        250173587003035,
        250173584002016,
        250173585002010,
        250173584002017,
        250173584002023,
        250173584002027,
        250173584002006,
        250173584002007,
        250173585002003,
        250173584002028,
        250173584002021,
        250173584002011,
        250173585002002,
        250173584003017,
        250173584002020,
        250173585001022,
        250173584002025,
        250173584002019,
        250173584002030,
        250173585001021,
        250173585002004,
        250173584001029,
        250173584002013,
        250173584002015,
        250173584002026,
        250173584002004,
        250173584002000,
        250173584002014,
        250173584001027,
        250173584002012,
        250173585001020,
        250173584002005,
        250173584002022,
        250173584002009,
        250173584002003,
        250173585002013,
        250173584002010,
        250173584002008,
        250173585001018,
        250173584001028,
        250173585001019,
        250173584002029,
        250173585002011,
        250173584001021,
        250173584001026,
        250173584001030,
        250173584002031,
        250173584002002,
        250173584002001,
        250173585002005
    ],
    "zs:housing10":1002,
    "zs:pop10":2511
},
  "geometry": {"coordinates":[-71.214614,42.438049],"type":"Point"}
}