{
  "type": "Feature",
  "properties": {
    "gn:country":"US",
    "gn:fcode":"PPL",
    "gn:population":0,
    "iso:country":"US",
    "name:afr_x_preferred":[
        "Aberdeen"
    ],
    "name:azb_x_preferred":[
        "\u0622\u0628\u0631\u062f\u06cc\u0646"
    ],
    "name:ceb_x_preferred":[
        "Aberdeen"
    ],
    "name:deu_x_preferred":[
        "Aberdeen"
    ],
    "name:eng_x_preferred":[
        "Aberdeen"
    ],
    "name:eus_x_preferred":[
        "Aberdeen"
    ],
    "name:fas_x_preferred":[
        "\u0627\u0628\u0631\u062f\u06cc\u0646\u060c \u0641\u0644\u0648\u0631\u06cc\u062f\u0627"
    ],
    "name:fas_x_variant":[
        "\u0627\u0628\u0631\u062f\u06cc\u0646"
    ],
    "name:fra_x_preferred":[
        "Aberdeen"
    ],
    "name:gle_x_preferred":[
        "Aberdeen"
    ],
    "name:lld_x_preferred":[
        "Aberdeen"
    ],
    "name:urd_x_preferred":[
        "\u0627\u06cc\u0628\u0631\u0688\u06cc\u0646\u060c \u0641\u0644\u0648\u0631\u06cc\u0688\u0627"
    ],
    "name:urd_x_variant":[
        "\u0627\u06cc\u0628\u0631\u0688\u06cc\u0646"
    ],
    "name:zho_x_preferred":[
        "\u963f\u4f2f\u4e01"
    ],
    "qs_pg:aaroncc":"US",
    "qs_pg:gn_country":"US",
    "qs_pg:gn_fcode":"PPL",
    "qs_pg:gn_pop":0,
    "qs_pg:name":"Aberdeen",
    "qs_pg:name_adm0":"United States",
    "qs_pg:name_adm1":"Florida",
    "qs_pg:photos":802,
    "qs_pg:photos_1k":163,
    "qs_pg:photos_9k":4,
    "qs_pg:photos_9r":6,
    "qs_pg:photos_all":802,
    "qs_pg:photos_sr":9,
    "qs_pg:pop_sr":0,
    "qs_pg:qs_pg_placetype":"locality",
    "qs_pg:qs_pg_placetype_gp":"Town",
    "qs_pg:woe_adm0":23424977,
    "woe:adm0_id":23424977,
    "woe:name_adm0":"United States",
    "woe:name_adm1":"Florida",
    "woe:placetype":"Town",
    "wof:name":"Aberdeen",
    "wof:placetype":"locality"
},
  "geometry": {"coordinates":[-80.14866000000001,26.55063],"type":"Point"}
}