{
  "type": "Feature",
  "properties": {
    "gn:country":"US",
    "gn:fcode":"PPL",
    "gn:population":0,
    "iso:country":"US",
    "name:ara_x_preferred":[
        "\u0623\u0648\u062a\u0648"
    ],
    "name:arz_x_preferred":[
        "\u0627\u0648\u062a\u0648"
    ],
    "name:azb_x_preferred":[
        "\u0627\u0648\u062a\u0648"
    ],
    "name:cat_x_preferred":[
        "Otto"
    ],
    "name:che_x_preferred":[
        "\u041e\u0442\u0442\u043e"
    ],
    "name:cym_x_preferred":[
        "Otto"
    ],
    "name:deu_x_preferred":[
        "Otto"
    ],
    "name:eng_x_preferred":[
        "Otto"
    ],
    "name:eus_x_preferred":[
        "Otto"
    ],
    "name:fas_x_preferred":[
        "\u0622\u062a\u0648"
    ],
    "name:fra_x_preferred":[
        "Otto"
    ],
    "name:hat_x_preferred":[
        "Otto"
    ],
    "name:hun_x_preferred":[
        "Otto"
    ],
    "name:ita_x_preferred":[
        "Otto"
    ],
    "name:pol_x_preferred":[
        "Otto"
    ],
    "name:spa_x_preferred":[
        "Otto"
    ],
    "name:swe_x_preferred":[
        "Otto"
    ],
    "name:tat_x_preferred":[
        "\u041e\u0442\u0442\u043e"
    ],
    "name:tur_x_preferred":[
        "Otto"
    ],
    "name:ukr_x_preferred":[
        "\u041e\u0442\u0442\u043e"
    ],
    "name:uzb_x_preferred":[
        "Otto"
    ],
    "name:zho_x_preferred":[
        "\u5965\u6258"
    ],
    "qs_pg:aaroncc":"US",
    "qs_pg:gn_country":"US",
    "qs_pg:gn_fcode":"PPL",
    "qs_pg:gn_pop":0,
    "qs_pg:name":"Otto",
    "qs_pg:name_adm0":"United States",
    "qs_pg:name_adm1":"New York",
    "qs_pg:photos_9k":1,
    "qs_pg:photos_9r":2,
    "qs_pg:photos_all":26,
    "qs_pg:photos_sr":0,
    "qs_pg:pop_sr":0,
    "qs_pg:qs_pg_placetype":"locality",
    "qs_pg:qs_pg_placetype_gp":"Town",
    "qs_pg:woe_adm0":23424977,
    "woe:adm0_id":23424977,
    "woe:name_adm0":"United States",
    "woe:name_adm1":"New York",
    "woe:placetype":"Town",
    "wof:coterminous":[
        404521789
    ],
    "wof:name":"Otto",
    "wof:placetype":"locality",
    "wof:statistical_gore":1
},
  "geometry": {"coordinates":[-78.8317,42.35617],"type":"Point"}
}