{
  "type": "Feature",
  "properties": {
    "gn:country":"US",
    "gn:fcode":"PPL",
    "gn:population":96,
    "iso:country":"US",
    "name:eng_x_preferred":[
        "Wilburton Number Two"
    ],
    "qs_pg:aaroncc":"US",
    "qs_pg:gn_country":"US",
    "qs_pg:gn_fcode":"PPL",
    "qs_pg:gn_pop":96,
    "qs_pg:name":"Wilburton Number Two",
    "qs_pg:name_adm0":"United States",
    "qs_pg:name_adm1":"Pennsylvania",
    "qs_pg:photos":118,
    "qs_pg:photos_1k":24,
    "qs_pg:photos_9k":1,
    "qs_pg:photos_9r":3,
    "qs_pg:photos_all":118,
    "qs_pg:photos_sr":3,
    "qs_pg:pop_sr":1,
    "qs_pg:qs_pg_placetype":"neighbourhood",
    "qs_pg:qs_pg_placetype_gp":"Suburb",
    "qs_pg:woe_adm0":23424977,
    "wof:name":"Wilburton Number Two",
    "wof:placetype":"neighbourhood",
    "wof:population":268,
    "zs:area_m":19572578.615976,
    "zs:blockids":[
        420370515006005,
        420370515006135,
        420370515006031,
        420370515006006,
        420370515006023,
        420370515006030,
        420370515006017,
        420370515006081,
        420370515006024,
        420370515006022,
        420370515006028,
        420370515006025,
        420370515006021,
        420370515006026,
        420370515006004,
        420370515006117,
        420370515006032,
        420370515006082,
        420370515006027,
        420370515006016,
        420370515006029,
        420370515006033,
        420370515006020
    ],
    "zs:housing10":142,
    "zs:label":"Wilburton Number Two",
    "zs:pop10":268
},
  "geometry": {"coordinates":[-76.37624,40.831834],"type":"Point"}
}