{
  "type": "Feature",
  "properties": {
    "iso:country":"US",
    "name:eng_x_preferred":[
        "Emoryville"
    ],
    "wof:name":"Emoryville",
    "wof:placetype":"neighbourhood",
    "wof:population":447,
    "zs:area_m":172156.409733,
    "zs:blockids":[
        370630020262013,
        370630020262020,
        370630020262002,
        370630020262036,
        370630020262018,
        370630020262019,
        370630020262007,
        370630020262008
    ],
    "zs:housing10":266,
    "zs:label":"Emoryville",
    "zs:pop10":447
},
  "geometry": {"coordinates":[-78.88972200000001,35.942451],"type":"Point"}
}