{
  "type": "Feature",
  "properties": {
    "gn:admin1_code":"WV",
    "gn:admin2_code":"61.0",
    "gn:asciiname":"Ringgold",
    "gn:country_code":"US",
    "gn:dem":411,
    "gn:elevation":"410.0",
    "gn:feature_class":"P",
    "gn:feature_code":"PPL",
    "gn:name":"Ringgold",
    "gn:population":0,
    "gn:timezone":"America/New_York",
    "iso:country":"US",
    "name:eng_x_preferred":[
        "Ringgold"
    ],
    "name:und_x_variant":[
        "Ringold"
    ],
    "wof:name":"Ringgold",
    "wof:placetype":"locality"
},
  "geometry": {"coordinates":[-79.94311999999999,39.56342],"type":"Point"}
}