{
  "type": "Feature",
  "properties": {
    "gn:country":"US",
    "gn:fcode":"PPL",
    "gn:population":0,
    "iso:country":"US",
    "name:ben_x_preferred":[
        "\u09b2\u09be\u09ab\u09be\u09df\u09c7\u09a4\u09cd\u09a4\u09c7"
    ],
    "name:bre_x_preferred":[
        "Lafayette"
    ],
    "name:bul_x_preferred":[
        "\u041b\u0430\u0444\u0430\u0439\u0435\u0442"
    ],
    "name:cat_x_preferred":[
        "Lafayette"
    ],
    "name:ceb_x_preferred":[
        "Lafayette"
    ],
    "name:ces_x_preferred":[
        "Lafayette"
    ],
    "name:dan_x_preferred":[
        "Lafayette"
    ],
    "name:deu_x_preferred":[
        "Lafayette"
    ],
    "name:ell_x_preferred":[
        "\u039b\u03b1\u03c6\u03b1\u03b3\u03b9\u03ad\u03c4"
    ],
    "name:eng_x_preferred":[
        "Lafayette"
    ],
    "name:eus_x_preferred":[
        "Lafayette"
    ],
    "name:fas_x_preferred":[
        "\u0644\u0627\u0641\u0627\u06cc\u062a"
    ],
    "name:fin_x_preferred":[
        "Lafayette"
    ],
    "name:fra_x_preferred":[
        "Lafayette"
    ],
    "name:hun_x_preferred":[
        "Lafayette"
    ],
    "name:hye_x_preferred":[
        "\u053c\u0561\u0586\u0561\u0575\u0565\u057f \u0577\u0580\u057b\u0561\u0576"
    ],
    "name:ind_x_preferred":[
        "Lafayette"
    ],
    "name:ita_x_preferred":[
        "Lafayette"
    ],
    "name:jpn_x_preferred":[
        "\u30e9\u30d5\u30a1\u30a4\u30a8\u30c3\u30c8"
    ],
    "name:kor_x_preferred":[
        "\ub77c\ud30c\uc608\ud2b8"
    ],
    "name:ltz_x_preferred":[
        "Lafayette"
    ],
    "name:nld_x_preferred":[
        "Lafayette"
    ],
    "name:nor_x_preferred":[
        "Lafayette"
    ],
    "name:pol_x_preferred":[
        "Lafayette"
    ],
    "name:por_x_preferred":[
        "Lafayette"
    ],
    "name:rus_x_preferred":[
        "\u041b\u0430\u0444\u0430\u0439\u0435\u0442"
    ],
    "name:spa_x_preferred":[
        "Lafayette"
    ],
    "name:srp_x_preferred":[
        "\u041b\u0430\u0444\u0435\u0458\u0435\u0442"
    ],
    "name:swa_x_preferred":[
        "Lafayette"
    ],
    "name:swe_x_preferred":[
        "Lafayette"
    ],
    "name:ukr_x_preferred":[
        "\u041b\u0430\u0444\u0430\u0454\u0442\u0442"
    ],
    "name:und_x_variant":[
        "La Fayette"
    ],
    "name:vie_x_preferred":[
        "Lafayette"
    ],
    "name:vol_x_preferred":[
        "Lafayette"
    ],
    "name:zho_x_preferred":[
        "\u62c9\u6cd5\u8449"
    ],
    "qs_pg:aaroncc":"US",
    "qs_pg:gn_country":"US",
    "qs_pg:gn_fcode":"PPL",
    "qs_pg:gn_pop":0,
    "qs_pg:name":"Lafayette",
    "qs_pg:name_adm0":"United States",
    "qs_pg:name_adm1":"New Jersey",
    "qs_pg:photos":195,
    "qs_pg:photos_1k":40,
    "qs_pg:photos_9k":1,
    "qs_pg:photos_9r":5,
    "qs_pg:photos_all":301,
    "qs_pg:photos_sr":4,
    "qs_pg:pop_sr":5,
    "qs_pg:qs_pg_placetype":"locality",
    "qs_pg:qs_pg_placetype_gp":"Town",
    "qs_pg:woe_adm0":23424977,
    "woe:adm0_id":23424977,
    "woe:name_adm0":"United States",
    "woe:name_adm1":"New Jersey",
    "woe:placetype":"Town",
    "wof:name":"Lafayette",
    "wof:placetype":"locality"
},
  "geometry": {"coordinates":[-74.6885,41.09843],"type":"Point"}
}