{
  "type": "Feature",
  "properties": {
    "gn:admin1_code":"MS",
    "gn:admin2_code":"59",
    "gn:asciiname":"Vestry",
    "gn:country_code":"US",
    "gn:dem":21,
    "gn:elevation":"12.0",
    "gn:feature_class":"P",
    "gn:feature_code":"PPL",
    "gn:name":"Vestry",
    "gn:population":0,
    "gn:timezone":"America/Chicago",
    "iso:country":"US",
    "wof:name":"Vestry",
    "wof:placetype":"locality"
},
  "geometry": {"coordinates":[-88.77585999999999,30.72686],"type":"Point"}
}