{
  "type": "Feature",
  "properties": {
    "gn:admin1_code":"KS",
    "gn:admin2_code":"73",
    "gn:admin3_code":"3625.0",
    "gn:asciiname":"Utopia",
    "gn:country_code":"US",
    "gn:dem":344,
    "gn:elevation":"345.0",
    "gn:feature_class":"P",
    "gn:feature_code":"PPL",
    "gn:name":"Utopia",
    "gn:population":0,
    "gn:timezone":"America/Chicago",
    "iso:country":"US",
    "name:eng_x_preferred":[
        "Utopia"
    ],
    "name:und_x_variant":[
        "Utopia Station"
    ],
    "wof:name":"Utopia",
    "wof:placetype":"locality"
},
  "geometry": {"coordinates":[-96.22417,37.89781],"type":"Point"}
}