{
  "type": "Feature",
  "properties": {
    "gn:country":"US",
    "gn:fcode":"PPL",
    "gn:population":808,
    "iso:country":"US",
    "name:ara_x_preferred":[
        "\u0645\u0648\u0646\u0631\u0648\u064a"
    ],
    "name:arz_x_preferred":[
        "\u0645\u0648\u0646\u0631\u0648\u0649"
    ],
    "name:azb_x_preferred":[
        "\u0645\u0648\u0646\u0631\u0648"
    ],
    "name:ben_x_preferred":[
        "\u09ae\u09a8\u09b0\u09cb"
    ],
    "name:cat_x_preferred":[
        "Monroe"
    ],
    "name:ceb_x_preferred":[
        "Monroe"
    ],
    "name:che_x_preferred":[
        "\u041c\u043e\u043d\u0440\u043e"
    ],
    "name:cym_x_preferred":[
        "Monroe"
    ],
    "name:deu_x_preferred":[
        "Monroe"
    ],
    "name:ell_x_preferred":[
        "\u039c\u03bf\u03bd\u03c1\u03cc"
    ],
    "name:eng_x_preferred":[
        "Monroe"
    ],
    "name:eus_x_preferred":[
        "Monroe"
    ],
    "name:fas_x_preferred":[
        "\u0645\u0648\u0646\u0631\u0648"
    ],
    "name:fra_x_preferred":[
        "Monroe"
    ],
    "name:hat_x_preferred":[
        "Monroe"
    ],
    "name:hin_x_preferred":[
        "\u092e\u094b\u0928\u0930\u094b"
    ],
    "name:hun_x_preferred":[
        "Monroe"
    ],
    "name:ind_x_preferred":[
        "Monroe"
    ],
    "name:ita_x_preferred":[
        "Monroe"
    ],
    "name:kaz_x_preferred":[
        "\u041c\u043e\u043d\u0440\u043e\u0439"
    ],
    "name:kir_x_preferred":[
        "\u041c\u043e\u043d\u0440\u043e\u0439"
    ],
    "name:nld_x_preferred":[
        "Monroe"
    ],
    "name:pol_x_preferred":[
        "Monroe"
    ],
    "name:rus_x_preferred":[
        "\u041c\u043e\u043d\u0440\u043e"
    ],
    "name:spa_x_preferred":[
        "Monroe"
    ],
    "name:swe_x_preferred":[
        "Monroe"
    ],
    "name:tat_x_preferred":[
        "\u041c\u043e\u043d\u0440\u043e"
    ],
    "name:tur_x_preferred":[
        "Monroe"
    ],
    "name:ukr_x_preferred":[
        "\u041c\u043e\u043d\u0440\u043e"
    ],
    "name:urd_x_preferred":[
        "\u0645\u0648\u0646\u0631\u0648\u060c \u0646\u06cc\u0648 \u06c1\u06cc\u0645\u067e\u0634\u0627\u0626\u0631"
    ],
    "name:urd_x_variant":[
        "\u0645\u0648\u0646\u0631\u0648"
    ],
    "name:vie_x_preferred":[
        "Monroe"
    ],
    "name:vol_x_preferred":[
        "Monroe"
    ],
    "name:war_x_preferred":[
        "Monroe"
    ],
    "qs_pg:aaroncc":"US",
    "qs_pg:gn_country":"US",
    "qs_pg:gn_fcode":"PPL",
    "qs_pg:gn_pop":808,
    "qs_pg:name":"Monroe",
    "qs_pg:name_adm0":"United States",
    "qs_pg:name_adm1":"New Hampshire",
    "qs_pg:photos_9k":1,
    "qs_pg:photos_9r":1,
    "qs_pg:photos_all":1,
    "qs_pg:photos_sr":0,
    "qs_pg:pop_sr":2,
    "qs_pg:qs_pg_placetype":"locality",
    "qs_pg:qs_pg_placetype_gp":"Town",
    "qs_pg:woe_adm0":23424977,
    "woe:adm0_id":23424977,
    "woe:name_adm0":"United States",
    "woe:name_adm1":"New Hampshire",
    "woe:placetype":"Town",
    "wof:name":"Monroe",
    "wof:placetype":"locality",
    "wof:population":808
},
  "geometry": {"coordinates":[-72.05482000000001,44.26034],"type":"Point"}
}