{
  "type": "Feature",
  "properties": {
    "gn:admin1_code":"GA",
    "gn:admin2_code":"129.0",
    "gn:asciiname":"Nickelsville",
    "gn:country_code":"US",
    "gn:dem":214,
    "gn:elevation":"213.0",
    "gn:feature_class":"P",
    "gn:feature_code":"PPL",
    "gn:name":"Nickelsville",
    "gn:population":0,
    "gn:timezone":"America/New_York",
    "iso:country":"US",
    "name:eng_x_preferred":[
        "Nickelsville"
    ],
    "name:und_x_variant":[
        "Nicklesville",
        "Little Five Points",
        "Nickelville",
        "Nicholsville"
    ],
    "wof:name":"Nickelsville",
    "wof:placetype":"locality"
},
  "geometry": {"coordinates":[-84.86689,34.60175],"type":"Point"}
}