{
  "type": "Feature",
  "properties": {
    "gn:admin1_code":"PA",
    "gn:admin2_code":"15.0",
    "gn:admin3_code":"71312.0",
    "gn:asciiname":"Riggs",
    "gn:country_code":"US",
    "gn:dem":377,
    "gn:elevation":"378.0",
    "gn:feature_class":"P",
    "gn:feature_code":"PPL",
    "gn:name":"Riggs",
    "gn:population":0,
    "gn:timezone":"America/New_York",
    "iso:country":"US",
    "wof:name":"Riggs",
    "wof:placetype":"locality"
},
  "geometry": {"coordinates":[-76.57606,41.83813],"type":"Point"}
}