{
  "type": "Feature",
  "properties": {
    "gn:admin1_code":"LA",
    "gn:admin2_code":"47.0",
    "gn:asciiname":"Myrtle Grove",
    "gn:country_code":"US",
    "gn:dem":10,
    "gn:elevation":"7.0",
    "gn:feature_class":"P",
    "gn:feature_code":"PPL",
    "gn:name":"Myrtle Grove",
    "gn:population":0,
    "gn:timezone":"America/Chicago",
    "iso:country":"US",
    "name:ceb_x_preferred":[
        "Myrtle Grove"
    ],
    "name:deu_x_preferred":[
        "Myrtle Grove"
    ],
    "name:nld_x_preferred":[
        "Myrtle Grove"
    ],
    "name:pol_x_preferred":[
        "Myrtle Grove"
    ],
    "name:por_x_preferred":[
        "Myrtle Grove"
    ],
    "name:srp_x_preferred":[
        "\u041c\u0435\u0440\u0442\u043b \u0413\u0440\u043e\u0443\u0432"
    ],
    "name:ukr_x_preferred":[
        "\u041c\u0435\u0440\u0442\u0435\u043b-\u0413\u0440\u043e\u0443\u0432"
    ],
    "name:vol_x_preferred":[
        "Myrtle Grove"
    ],
    "wof:name":"Myrtle Grove",
    "wof:placetype":"locality"
},
  "geometry": {"coordinates":[-91.2465,30.29603],"type":"Point"}
}