{
  "type": "Feature",
  "properties": {
    "iso:country":"US",
    "name:eng_x_preferred":[
        "North Federal Heights"
    ],
    "wof:name":"North Federal Heights",
    "wof:placetype":"neighbourhood",
    "wof:population":9,
    "zs:area_m":19914.817298,
    "zs:blockids":[
        80010093191001
    ],
    "zs:housing10":8,
    "zs:label":"North Federal Heights",
    "zs:pop10":9
},
  "geometry": {"coordinates":[-105.023843,39.863039],"type":"Point"}
}