{
  "type": "Feature",
  "properties": {
    "iso:country":"US",
    "name:ceb_x_preferred":[
        "Lake View"
    ],
    "name:deu_x_preferred":[
        "Lake View"
    ],
    "name:eng_x_preferred":[
        "Lake View"
    ],
    "name:eng_x_variant":[
        "Lake Vw",
        "Lk View",
        "Lk Vw"
    ],
    "name:ita_x_preferred":[
        "Lake View"
    ],
    "name:nld_x_preferred":[
        "Lake View"
    ],
    "name:pol_x_preferred":[
        "Lake View"
    ],
    "name:por_x_preferred":[
        "Lake View"
    ],
    "name:spa_x_preferred":[
        "Lake View"
    ],
    "name:srp_x_preferred":[
        "\u041b\u0435\u0458\u043a \u0412\u0458\u0443"
    ],
    "name:ukr_x_preferred":[
        "\u041b\u0435\u0439\u043a-\u0412'\u044e"
    ],
    "name:vol_x_preferred":[
        "Lake View"
    ],
    "name:zho_x_preferred":[
        "\u62c9\u514b\u592b\u7531"
    ],
    "qs:gn_local":0,
    "qs:local_max":1310,
    "qs:local_sum":1789,
    "qs:localhoods":7,
    "qs:name":"Lake View",
    "qs:name_adm0":"United States",
    "qs:name_adm1":"Indiana",
    "qs:name_adm2":"Porter",
    "qs:name_local":"Valparaiso",
    "qs:photo_max":1,
    "qs:photo_sum":1,
    "qs:placetype":"Suburb",
    "qs:quad_count":1,
    "qs:woe_adm0":23424977,
    "qs:woe_adm1":2347573,
    "qs:woe_adm2":12588243,
    "qs:woe_lau":0,
    "qs:woe_local":2511078,
    "qs:woe_ver":"7.10.0",
    "wof:lang":[
        "eng"
    ],
    "wof:name":"Lake View",
    "wof:placetype":"neighbourhood"
},
  "geometry": {"coordinates":[-87.04193100000001,41.535309],"type":"Point"}
}