{
  "type": "Feature",
  "properties": {
    "gn:elevation":6,
    "iso:country":"US",
    "name:ceb_x_preferred":[
        "Bayview"
    ],
    "name:deu_x_preferred":[
        "Bayview"
    ],
    "name:eng_x_preferred":[
        "Bayview"
    ],
    "name:fra_x_preferred":[
        "Bayview"
    ],
    "name:ita_x_preferred":[
        "Bayview"
    ],
    "name:nld_x_preferred":[
        "Bayview"
    ],
    "name:pol_x_preferred":[
        "Bayview"
    ],
    "name:por_x_preferred":[
        "Bayview"
    ],
    "name:srp_x_preferred":[
        "\u0411\u0435\u0458\u0432\u0458\u0443"
    ],
    "name:swe_x_preferred":[
        "Bayview"
    ],
    "name:ukr_x_preferred":[
        "\u0411\u0435\u0439\u0432'\u044e"
    ],
    "qs:gn_adm0_cc":"US",
    "qs:gn_fcode":"PPL",
    "qs:gn_local":4838652,
    "qs:gn_nam_loc":"milford",
    "qs:gn_namadm1":"CT",
    "qs:gn_name":"Bayview",
    "qs:local_max":1732,
    "qs:local_sum":6661,
    "qs:localhoods":13,
    "qs:name":"Bayview",
    "qs:name_adm0":"United States",
    "qs:name_adm1":"Connecticut",
    "qs:name_adm2":"New Haven",
    "qs:name_local":"Milford",
    "qs:photo_max":86,
    "qs:photo_sum":313,
    "qs:placetype":"Suburb",
    "qs:quad_count":32,
    "qs:woe_adm0":23424977,
    "qs:woe_adm1":2347565,
    "qs:woe_adm2":12587795,
    "qs:woe_lau":0,
    "qs:woe_local":2450978,
    "qs:woe_ver":"7.10.0",
    "wof:lang":[
        "eng"
    ],
    "wof:name":"Bayview",
    "wof:placetype":"neighbourhood"
},
  "geometry": {"coordinates":[-73.03099,41.212659],"type":"Point"}
}