{
  "type": "Feature",
  "properties": {
    "gn:elevation":22,
    "iso:country":"US",
    "name:eng_x_preferred":[
        "Braddocks Mill"
    ],
    "name:eng_x_variant":[
        "Braddocks Ml"
    ],
    "name:fra_x_preferred":[
        "Braddocks Mill"
    ],
    "qs:gn_adm0_cc":"US",
    "qs:gn_fcode":"PPL",
    "qs:gn_local":4502984,
    "qs:gn_nam_loc":"medford",
    "qs:gn_namadm1":"NJ",
    "qs:gn_name":"Braddocks Mill",
    "qs:local_max":841,
    "qs:local_sum":1628,
    "qs:localhoods":9,
    "qs:name":"Braddocks Mill",
    "qs:name_adm0":"United States",
    "qs:name_adm1":"New Jersey",
    "qs:name_adm2":"Burlington",
    "qs:name_local":"Medford",
    "qs:photo_max":46,
    "qs:photo_sum":66,
    "qs:placetype":"Suburb",
    "qs:quad_count":8,
    "qs:woe_adm0":23424977,
    "qs:woe_adm1":2347589,
    "qs:woe_adm2":12589260,
    "qs:woe_lau":0,
    "qs:woe_local":2448924,
    "qs:woe_ver":"7.10.0",
    "wd:wordcount":37,
    "wof:lang":[
        "eng"
    ],
    "wof:name":"Braddocks Mill",
    "wof:placetype":"neighbourhood",
    "wof:population":1464,
    "zs:blockids":[
        340057038044046,
        340057038044027,
        340057040111005,
        340057038044061,
        340057038044069,
        340057038044073,
        340057038044040,
        340057038044042,
        340057038043022,
        340057038044043,
        340057038043023,
        340057038044062,
        340057038044038,
        340057038043017,
        340057038044032,
        340057038044049,
        340057038044068,
        340057038043016,
        340057038044041,
        340057038044048,
        340057038044047,
        340057038043018,
        340057038044033,
        340057040111009,
        340057040111006,
        340057038044076,
        340057038044059,
        340057038044060,
        340057038043024,
        340057038044055,
        340057038044065,
        340057038044054,
        340057040111007,
        340057038044044,
        340057038044058,
        340057038044050,
        340057038044064,
        340057038044045,
        340057038044075,
        340057038044029,
        340057038044030,
        340057038044066,
        340057038044072,
        340057038044074,
        340057038044051,
        340057038044039,
        340057038044079,
        340057038044063,
        340057040111002,
        340057038043020,
        340057038044026,
        340057040111008,
        340057038044067,
        340057038044070,
        340057038044071
    ],
    "zs:housing10":479,
    "zs:pop10":1464
},
  "geometry": {"coordinates":[-74.85738499999999,39.811317],"type":"Point"}
}