{
  "type": "Feature",
  "properties": {
    "gn:admin1_code":"WV",
    "gn:admin2_code":"97",
    "gn:asciiname":"Ellamore",
    "gn:country_code":"US",
    "gn:dem":578,
    "gn:elevation":"566.0",
    "gn:feature_class":"P",
    "gn:feature_code":"PPL",
    "gn:name":"Ellamore",
    "gn:population":0,
    "gn:timezone":"America/New_York",
    "iso:country":"US",
    "wof:name":"Ellamore",
    "wof:placetype":"locality"
},
  "geometry": {"coordinates":[-80.09036,38.92427],"type":"Point"}
}