{
  "type": "Feature",
  "properties": {
    "gn:admin1_code":"NM",
    "gn:admin2_code":"51",
    "gn:asciiname":"Grafton",
    "gn:country_code":"US",
    "gn:dem":2081,
    "gn:elevation":"2077.0",
    "gn:feature_class":"P",
    "gn:feature_code":"PPL",
    "gn:name":"Grafton",
    "gn:population":0,
    "gn:timezone":"America/Denver",
    "iso:country":"US",
    "name:ara_x_preferred":[
        "\u063a\u0631\u0627\u0641\u062a\u0648\u0646"
    ],
    "name:cat_x_preferred":[
        "Grafton"
    ],
    "name:ceb_x_preferred":[
        "Grafton"
    ],
    "name:cym_x_preferred":[
        "Grafton"
    ],
    "name:deu_x_preferred":[
        "Grafton"
    ],
    "name:fin_x_preferred":[
        "Grafton"
    ],
    "name:fra_x_preferred":[
        "Grafton"
    ],
    "name:heb_x_preferred":[
        "\u05d2\u05e8\u05e4\u05d8\u05d5\u05df"
    ],
    "name:hun_x_preferred":[
        "Grafton"
    ],
    "name:ita_x_preferred":[
        "Grafton"
    ],
    "name:jpn_x_preferred":[
        "\u30b0\u30e9\u30d5\u30c8\u30f3"
    ],
    "name:kor_x_preferred":[
        "\uadf8\ub798\ud504\ud134"
    ],
    "name:mlg_x_preferred":[
        "Grafton"
    ],
    "name:nld_x_preferred":[
        "Grafton"
    ],
    "name:pol_x_preferred":[
        "Grafton"
    ],
    "name:por_x_preferred":[
        "Grafton"
    ],
    "name:rus_x_preferred":[
        "\u0413\u0440\u0430\u0444\u0442\u043e\u043d"
    ],
    "name:slv_x_preferred":[
        "Grafton"
    ],
    "name:spa_x_preferred":[
        "Grafton"
    ],
    "name:srp_x_preferred":[
        "\u0413\u0440\u0430\u0444\u0442\u043e\u043d"
    ],
    "name:swe_x_preferred":[
        "Grafton"
    ],
    "name:ukr_x_preferred":[
        "\u0413\u0440\u0430\u0444\u0442\u043e\u043d"
    ],
    "name:vol_x_preferred":[
        "Grafton"
    ],
    "wof:name":"Grafton",
    "wof:placetype":"locality"
},
  "geometry": {"coordinates":[-107.74615,33.43062],"type":"Point"}
}