{
  "type": "Feature",
  "properties": {
    "gn:country":"US",
    "gn:fcode":"PPL",
    "gn:population":17328,
    "iso:country":"US",
    "name:cat_x_preferred":[
        "Plainville"
    ],
    "name:ceb_x_preferred":[
        "Plainville"
    ],
    "name:che_x_preferred":[
        "\u041f\u043b\u0435\u0439\u043d\u0432\u0438\u043b\u043b"
    ],
    "name:cym_x_preferred":[
        "Plainville"
    ],
    "name:deu_x_preferred":[
        "Plainville"
    ],
    "name:eng_x_preferred":[
        "Plainville"
    ],
    "name:eus_x_preferred":[
        "Plainville"
    ],
    "name:fin_x_preferred":[
        "Plainville"
    ],
    "name:fra_x_preferred":[
        "Plainville"
    ],
    "name:hat_x_preferred":[
        "Plainville"
    ],
    "name:hun_x_preferred":[
        "Plainville"
    ],
    "name:ita_x_preferred":[
        "Plainville"
    ],
    "name:kaz_x_preferred":[
        "\u041f\u043b\u044d\u0439\u043d\u0432\u0438\u043b\u043b"
    ],
    "name:kir_x_preferred":[
        "\u041f\u043b\u044d\u0439\u043d\u0432\u0438\u043b\u043b"
    ],
    "name:nld_x_preferred":[
        "Plainville"
    ],
    "name:pol_x_preferred":[
        "Plainville"
    ],
    "name:rus_x_preferred":[
        "\u041f\u043b\u0435\u0439\u043d\u0432\u0438\u043b\u043b\u044c"
    ],
    "name:spa_x_preferred":[
        "Plainville"
    ],
    "name:swe_x_preferred":[
        "Plainville"
    ],
    "name:szl_x_preferred":[
        "Plainville"
    ],
    "name:tat_x_preferred":[
        "\u041f\u043b\u0435\u0439\u043d\u0432\u0438\u043b\u043b"
    ],
    "name:tur_x_preferred":[
        "Plainville"
    ],
    "name:ukr_x_preferred":[
        "\u041f\u043b\u0435\u0439\u043d\u0432\u0456\u043b\u043b"
    ],
    "name:urd_x_preferred":[
        "\u067e\u0644\u06cc\u0646\u0648\u06cc\u0644\u060c \u06a9\u0646\u06cc\u06a9\u0679\u06cc\u06a9\u0679"
    ],
    "name:urd_x_variant":[
        "\u067e\u0644\u06cc\u0646\u0648\u06cc\u0644"
    ],
    "name:vol_x_preferred":[
        "Plainville"
    ],
    "name:zho_x_preferred":[
        "\u666e\u840a\u6069\u7dad\u723e"
    ],
    "qs_pg:aaroncc":"US",
    "qs_pg:gn_country":"US",
    "qs_pg:gn_fcode":"PPL",
    "qs_pg:gn_pop":17328,
    "qs_pg:name":"Plainville",
    "qs_pg:name_adm0":"United States",
    "qs_pg:name_adm1":"Connecticut",
    "qs_pg:photos":2795,
    "qs_pg:photos_1k":566,
    "qs_pg:photos_9k":12,
    "qs_pg:photos_9r":10,
    "qs_pg:photos_all":2795,
    "qs_pg:photos_sr":19,
    "qs_pg:pop_sr":6,
    "qs_pg:qs_pg_placetype":"locality",
    "qs_pg:qs_pg_placetype_gp":"Town",
    "qs_pg:woe_adm0":23424977,
    "woe:adm0_id":23424977,
    "woe:name_adm0":"United States",
    "woe:name_adm1":"Connecticut",
    "woe:placetype":"Town",
    "wof:coterminous":[
        404495993
    ],
    "wof:name":"Plainville",
    "wof:placetype":"locality",
    "wof:population":17328,
    "wof:statistical_gore":1
},
  "geometry": {"coordinates":[-72.85816,41.67454],"type":"Point"}
}