{
  "type": "Feature",
  "properties": {
    "gn:admin1_code":"MD",
    "gn:admin2_code":"27.0",
    "gn:asciiname":"Maple Trailer Park",
    "gn:country_code":"US",
    "gn:dem":62,
    "gn:elevation":"64.0",
    "gn:feature_class":"P",
    "gn:feature_code":"PPL",
    "gn:name":"Maple Trailer Park",
    "gn:population":0,
    "gn:timezone":"America/New_York",
    "iso:country":"US",
    "wof:name":"Maple Trailer Park",
    "wof:placetype":"campus"
},
  "geometry": {"coordinates":[-76.79303,39.16094],"type":"Point"}
}