{
  "type": "Feature",
  "properties": {
    "iso:country":"US",
    "name:eng_x_preferred":[
        "Westchase"
    ],
    "wd:wordcount":31,
    "wof:name":"Westchase",
    "wof:placetype":"neighbourhood",
    "wof:population":161,
    "zs:area_m":2421561.944883,
    "zs:blockids":[
        371830537241010,
        371830537241021,
        371830537241020,
        371830537241012,
        371830537241006,
        371830537241008,
        371830537241005
    ],
    "zs:housing10":80,
    "zs:label":"Westchase",
    "zs:pop10":161
},
  "geometry": {"coordinates":[-78.748789,35.897797],"type":"Point"}
}