{
  "type": "Feature",
  "properties": {
    "gn:admin1_code":"AL",
    "gn:admin2_code":"71.0",
    "gn:asciiname":"Bass",
    "gn:country_code":"US",
    "gn:dem":189,
    "gn:elevation":"189.0",
    "gn:feature_class":"P",
    "gn:feature_code":"PPL",
    "gn:name":"Bass",
    "gn:population":0,
    "gn:timezone":"America/Chicago",
    "iso:country":"US",
    "name:fas_x_preferred":[
        "\u0628\u06cc\u0633"
    ],
    "name:zho_x_preferred":[
        "\u5df4\u65af"
    ],
    "wof:name":"Bass",
    "wof:placetype":"locality"
},
  "geometry": {"coordinates":[-85.91303000000001,34.93203],"type":"Point"}
}