{
  "type": "Feature",
  "properties": {
    "iso:country":"US",
    "name:eng_x_preferred":[
        "Sienna Village Of Waters Lake"
    ],
    "qs:gn_adm0_cc":"US",
    "qs:gn_local":4711801,
    "qs:gn_nam_loc":"Missouri City, Fort Bend, Texas, US",
    "qs:gn_namadm1":"TX",
    "qs:local_max":693,
    "qs:local_sum":1548,
    "qs:localhoods":11,
    "qs:name":"Sienna Village Of Waters Lake",
    "qs:name_adm0":"United States",
    "qs:name_adm1":"Texas",
    "qs:name_adm2":"Fort Bend",
    "qs:name_local":"Missouri City",
    "qs:photo_max":1,
    "qs:photo_sum":1,
    "qs:placetype":"Suburb",
    "qs:quad_count":1,
    "qs:woe_adm0":23424977,
    "qs:woe_adm1":2347602,
    "qs:woe_adm2":12590085,
    "qs:woe_lau":0,
    "qs:woe_local":2452376,
    "qs:woe_ver":"7.10.0",
    "wof:lang":[
        "eng"
    ],
    "wof:name":"Sienna Village Of Waters Lake",
    "wof:placetype":"neighbourhood",
    "wof:population":4211,
    "zs:blockids":[
        481576745021137,
        481576745022044,
        481576745021117,
        481576745021121,
        481576745021145,
        481576745021135,
        481576745021131,
        481576745021143,
        481576745021123,
        481576745021126,
        481576745021128,
        481576745021168,
        481576745021136,
        481576745021113,
        481576745021115,
        481576745021116,
        481576745021130,
        481576745021141,
        481576745021144,
        481576745021133,
        481576745021138,
        481576745021122,
        481576745021140,
        481576745021118,
        481576745021142,
        481576745021112,
        481576745021120,
        481576745021132,
        481576745022046,
        481576745021114,
        481576745021111,
        481576745021125,
        481576745022045,
        481576745021139,
        481576745021271
    ],
    "zs:housing10":1234,
    "zs:pop10":4211
},
  "geometry": {"coordinates":[-95.534363,29.499378],"type":"Point"}
}