{
  "type": "Feature",
  "properties": {
    "gn:admin1_code":"FL",
    "gn:admin2_code":"57",
    "gn:asciiname":"Gamelou Estates",
    "gn:country_code":"US",
    "gn:dem":32,
    "gn:elevation":"27.0",
    "gn:feature_class":"P",
    "gn:feature_code":"PPL",
    "gn:name":"Gamelou Estates",
    "gn:population":0,
    "gn:timezone":"America/New_York",
    "iso:country":"US",
    "wof:name":"Gamelou Estates",
    "wof:placetype":"locality"
},
  "geometry": {"coordinates":[-82.1803,28.0752],"type":"Point"}
}