{
  "type": "Feature",
  "properties": {
    "gn:admin1_code":"MN",
    "gn:admin2_code":"147.0",
    "gn:admin3_code":"41840.0",
    "gn:asciiname":"Moland",
    "gn:country_code":"US",
    "gn:dem":381,
    "gn:elevation":"385.0",
    "gn:feature_class":"P",
    "gn:feature_code":"PPL",
    "gn:name":"Moland",
    "gn:population":0,
    "gn:timezone":"America/Chicago",
    "iso:country":"US",
    "name:deu_x_preferred":[
        "Moland"
    ],
    "name:fas_x_preferred":[
        "\u0645\u0648\u0644\u0646\u062f"
    ],
    "wof:name":"Moland",
    "wof:placetype":"locality"
},
  "geometry": {"coordinates":[-93.0616,44.19663],"type":"Point"}
}