{
  "type": "Feature",
  "properties": {
    "gn:admin1_code":"MD",
    "gn:admin2_code":"25.0",
    "gn:asciiname":"Riverside Village of Church Creek",
    "gn:country_code":"US",
    "gn:dem":23,
    "gn:elevation":"19.0",
    "gn:feature_class":"P",
    "gn:feature_code":"PPL",
    "gn:name":"Riverside Village of Church Creek",
    "gn:population":0,
    "gn:timezone":"America/New_York",
    "iso:country":"US",
    "wof:name":"Riverside Village of Church Creek",
    "wof:placetype":"locality"
},
  "geometry": {"coordinates":[-76.23523,39.47372],"type":"Point"}
}