{
  "type": "Feature",
  "properties": {
    "gn:admin1_code":"SC",
    "gn:admin2_code":"41.0",
    "gn:asciiname":"Ferndale",
    "gn:country_code":"US",
    "gn:dem":47,
    "gn:elevation":"44.0",
    "gn:feature_class":"P",
    "gn:feature_code":"PPL",
    "gn:name":"Ferndale",
    "gn:population":0,
    "gn:timezone":"America/New_York",
    "iso:country":"US",
    "name:ast_x_preferred":[
        "Ferndale"
    ],
    "name:cat_x_preferred":[
        "Ferndale"
    ],
    "name:ceb_x_preferred":[
        "Ferndale"
    ],
    "name:cor_x_preferred":[
        "Ferndale"
    ],
    "name:deu_x_preferred":[
        "Ferndale"
    ],
    "name:fra_x_preferred":[
        "Ferndale"
    ],
    "name:gla_x_preferred":[
        "Ferndale"
    ],
    "name:ita_x_preferred":[
        "Ferndale"
    ],
    "name:kor_x_preferred":[
        "\ud380\ub370\uc77c"
    ],
    "name:mlg_x_preferred":[
        "Ferndale"
    ],
    "name:nld_x_preferred":[
        "Ferndale"
    ],
    "name:pol_x_preferred":[
        "Ferndale"
    ],
    "name:por_x_preferred":[
        "Ferndale"
    ],
    "name:rus_x_preferred":[
        "\u0424\u0435\u0440\u043d\u0434\u0435\u0439\u043b"
    ],
    "name:spa_x_preferred":[
        "Ferndale"
    ],
    "name:srp_x_preferred":[
        "\u0424\u0435\u0440\u043d\u0434\u0435\u0458\u043b"
    ],
    "name:swe_x_preferred":[
        "Ferndale"
    ],
    "name:vol_x_preferred":[
        "Ferndale"
    ],
    "wof:name":"Ferndale",
    "wof:placetype":"locality"
},
  "geometry": {"coordinates":[-79.90368000000002,34.18988],"type":"Point"}
}