{
  "type": "Feature",
  "properties": {
    "gn:admin1_code":"KY",
    "gn:admin2_code":"111",
    "gn:asciiname":"Longview",
    "gn:country_code":"US",
    "gn:dem":171,
    "gn:elevation":"163.0",
    "gn:feature_class":"P",
    "gn:feature_code":"PPL",
    "gn:name":"Longview",
    "gn:population":0,
    "gn:timezone":"America/Kentucky/Louisville",
    "iso:country":"US",
    "name:ceb_x_preferred":[
        "Longview"
    ],
    "name:deu_x_preferred":[
        "Longview"
    ],
    "name:fra_x_preferred":[
        "Longview"
    ],
    "name:heb_x_preferred":[
        "\u05dc\u05d5\u05e0\u05d2\u05d5\u05d5\u05d9\u05d5"
    ],
    "name:hun_x_preferred":[
        "Longview"
    ],
    "name:ita_x_preferred":[
        "Longview"
    ],
    "name:nld_x_preferred":[
        "Longview"
    ],
    "name:pol_x_preferred":[
        "Longview"
    ],
    "name:por_x_preferred":[
        "Longview"
    ],
    "name:rus_x_preferred":[
        "\u041b\u043e\u043d\u0433\u0432\u044c\u044e"
    ],
    "name:spa_x_preferred":[
        "Longview"
    ],
    "name:srp_x_preferred":[
        "\u041b\u043e\u043d\u0433\u0432\u0458\u0443"
    ],
    "name:swe_x_preferred":[
        "Longview"
    ],
    "name:ukr_x_preferred":[
        "\u041b\u043e\u043d\u0433\u0432'\u044e"
    ],
    "name:urd_x_preferred":[
        "\u0644\u0648\u0646\u06af\u0648\u06cc\u0626\u0648"
    ],
    "name:vol_x_preferred":[
        "Longview"
    ],
    "wof:name":"Longview",
    "wof:placetype":"locality"
},
  "geometry": {"coordinates":[-85.65885,38.29924],"type":"Point"}
}