{
  "type": "Feature",
  "properties": {
    "iso:country":"US",
    "name:eng_x_preferred":[
        "Clearmeadows at Fishers Landing"
    ],
    "wof:name":"Clearmeadows at Fishers Landing",
    "wof:placetype":"neighbourhood",
    "wof:population":291,
    "zs:area_m":80144.205347,
    "zs:blockids":[
        530110413283027,
        530110413283017,
        530110413283028,
        530110413283029
    ],
    "zs:housing10":96,
    "zs:label":"Clearmeadows at Fishers Landing",
    "zs:pop10":291
},
  "geometry": {"coordinates":[-122.48215,45.605386],"type":"Point"}
}