{
  "type": "Feature",
  "properties": {
    "gn:admin1_code":"MN",
    "gn:admin2_code":"57.0",
    "gn:admin3_code":"63076.0",
    "gn:asciiname":"Horton",
    "gn:country_code":"US",
    "gn:dem":429,
    "gn:elevation":"431.0",
    "gn:feature_class":"P",
    "gn:feature_code":"PPL",
    "gn:name":"Horton",
    "gn:population":0,
    "gn:timezone":"America/Chicago",
    "iso:country":"US",
    "wof:name":"Horton",
    "wof:placetype":"locality"
},
  "geometry": {"coordinates":[-95.09725,46.81107],"type":"Point"}
}