{
  "type": "Feature",
  "properties": {
    "gn:admin1_code":"DE",
    "gn:admin2_code":"5.0",
    "gn:asciiname":"White Creek Manor",
    "gn:country_code":"US",
    "gn:dem":1,
    "gn:elevation":"3.0",
    "gn:feature_class":"P",
    "gn:feature_code":"PPL",
    "gn:name":"White Creek Manor",
    "gn:population":0,
    "gn:timezone":"America/New_York",
    "iso:country":"US",
    "wof:name":"White Creek Manor",
    "wof:placetype":"locality"
},
  "geometry": {"coordinates":[-75.10351999999997,38.55372],"type":"Point"}
}