{
  "type": "Feature",
  "properties": {
    "iso:country":"US",
    "name:eng_x_preferred":[
        "Greenwood Heights"
    ],
    "name:eng_x_variant":[
        "Greenwood Hts"
    ],
    "name:spa_x_preferred":[
        "Greenwood Heights"
    ],
    "qs:gn_adm0_cc":"US",
    "qs:gn_local":5185237,
    "qs:gn_nam_loc":"Connellsville, Fayette, Pennsylvania, US",
    "qs:gn_namadm1":"PA",
    "qs:local_max":239,
    "qs:local_sum":245,
    "qs:localhoods":2,
    "qs:name":"Greenwood Heights",
    "qs:name_adm0":"United States",
    "qs:name_adm1":"Pennsylvania",
    "qs:name_adm2":"Fayette",
    "qs:name_local":"Connellsville",
    "qs:photo_max":2,
    "qs:photo_sum":6,
    "qs:placetype":"Suburb",
    "qs:quad_count":4,
    "qs:woe_adm0":23424977,
    "qs:woe_adm1":2347597,
    "qs:woe_adm2":12589753,
    "qs:woe_lau":0,
    "qs:woe_local":2384225,
    "qs:woe_ver":"7.10.0",
    "wd:wordcount":473,
    "wof:lang":[
        "eng"
    ],
    "wof:name":"Greenwood Heights",
    "wof:placetype":"neighbourhood",
    "wof:population":1105,
    "zs:blockids":[
        420512607001037,
        420512607001042,
        420512607002016,
        420512607002041,
        420512607002029,
        420512607003065,
        420512607002032,
        420512607003069,
        420512607003066,
        420512607001043,
        420512607002053,
        420512607001039,
        420512607002033,
        420512607002030,
        420512607003067,
        420512607002010,
        420512607001049,
        420512607001038,
        420512607002031,
        420512607003064,
        420512607003068,
        420512607002004,
        420512607003070,
        420512607001035,
        420512607002048,
        420512607002040,
        420512607001047,
        420512626001000,
        420512607002039,
        420512607002017,
        420512607001036,
        420512607001001,
        420512607001041,
        420512607001062,
        420512607001046,
        420512607002018,
        420512607001048,
        420512607002052,
        420512607002007,
        420512607002009
    ],
    "zs:housing10":522,
    "zs:pop10":1105
},
  "geometry": {"coordinates":[-79.595032,40.006578],"type":"Point"}
}