{
  "type": "Feature",
  "properties": {
    "gn:admin1_code":"MI",
    "gn:admin2_code":"63.0",
    "gn:admin3_code":"17140.0",
    "gn:asciiname":"Popple",
    "gn:country_code":"US",
    "gn:dem":226,
    "gn:elevation":"226.0",
    "gn:feature_class":"P",
    "gn:feature_code":"PPL",
    "gn:name":"Popple",
    "gn:population":0,
    "gn:timezone":"America/Detroit",
    "iso:country":"US",
    "name:fra_x_preferred":[
        "Popple"
    ],
    "wof:name":"Popple",
    "wof:placetype":"locality"
},
  "geometry": {"coordinates":[-83.09605999999999,43.77113],"type":"Point"}
}