{
  "type": "Feature",
  "properties": {
    "gn:admin1_code":"OK",
    "gn:admin2_code":"153",
    "gn:asciiname":"Curtis",
    "gn:country_code":"US",
    "gn:dem":600,
    "gn:elevation":"591.0",
    "gn:feature_class":"P",
    "gn:feature_code":"PPL",
    "gn:name":"Curtis",
    "gn:population":0,
    "gn:timezone":"America/Chicago",
    "iso:country":"US",
    "name:bel_x_preferred":[
        "\u041a\u0451\u0440\u0446\u0456\u0441"
    ],
    "name:deu_x_preferred":[
        "Curtis"
    ],
    "name:ita_x_preferred":[
        "Curtis"
    ],
    "name:swe_x_preferred":[
        "Curtis"
    ],
    "wof:name":"Curtis",
    "wof:placetype":"locality"
},
  "geometry": {"coordinates":[-99.1426,36.4392],"type":"Point"}
}