{
  "type": "Feature",
  "properties": {
    "iso:country":"US",
    "name:eng_x_preferred":[
        "Papaikou Ahupua`a"
    ],
    "wof:name":"Papaikou Ahupua`a",
    "wof:placetype":"neighbourhood",
    "wof:population":16,
    "zs:area_m":123450131.645015,
    "zs:blockids":[
        150010221021320,
        150010221021324,
        150010201002189,
        150010221021376,
        150010221021321,
        150010201002001,
        150010201002198,
        150010221021006,
        150010221021516,
        150010221021381,
        150010201002002,
        150010221021316,
        150010221021000,
        150010201002000,
        150010221021009,
        150010221021490,
        150010221021322,
        150010221021383,
        150010201001297,
        150010201002196,
        150010221021005,
        150010221021377,
        150010221021385,
        150010221021315,
        150010221021507,
        150010221021374,
        150010201002017,
        150010221021311,
        150010221021317,
        150010221021312,
        150010202021032,
        150010201002197,
        150010221021375,
        150010221021314,
        150010221021382,
        150010221021380,
        150010221021319,
        150010221021313,
        150010201002185,
        150010221021305,
        150010221021007,
        150010221021010,
        150010221021378,
        150010221021008,
        150010201001018,
        150010221021384,
        150010221021003,
        150010221021318,
        150010201001312
    ],
    "zs:housing10":6,
    "zs:label":"Papaikou Ahupua`a",
    "zs:pop10":16
},
  "geometry": {"coordinates":[-155.23122699999999,19.792],"type":"Point"}
}