{
  "type": "Feature",
  "properties": {
    "iso:country":"US",
    "name:ceb_x_preferred":[
        "Lacamas Creek"
    ],
    "name:eng_x_preferred":[
        "Lacamas Shores"
    ],
    "name:eng_x_variant":[
        "Lacamas Creek"
    ],
    "name:vec_x_preferred":[
        "Lacamas"
    ],
    "name:zho_x_preferred":[
        "\u62c9\u5361\u99ac\u65af\u6eaa"
    ],
    "wd:wordcount":525,
    "wof:name":"Lacamas Shores",
    "wof:placetype":"neighbourhood",
    "wof:population":2,
    "zs:area_m":1505555.941298,
    "zs:blockids":[
        530110406051019,
        530110406051020,
        530110406081025
    ],
    "zs:housing10":1,
    "zs:label":"Lacamas Shores",
    "zs:pop10":2
},
  "geometry": {"coordinates":[-122.418105,45.612656],"type":"Point"}
}