{
  "type": "Feature",
  "properties": {
    "gn:elevation":199,
    "iso:country":"US",
    "name:eng_x_preferred":[
        "Chapel Manor"
    ],
    "name:eng_x_variant":[
        "Chapel Mnr"
    ],
    "qs:gn_fcode":"PPL",
    "qs:gn_local":0,
    "qs:gn_namadm1":"IN",
    "qs:gn_name":"Chapel Manor",
    "qs:local_max":260,
    "qs:local_sum":381,
    "qs:localhoods":5,
    "qs:name":"Chapel Manor",
    "qs:name_adm0":"United States",
    "qs:name_adm1":"Indiana",
    "qs:name_adm2":"Lake",
    "qs:name_local":"Merrillville",
    "qs:photo_max":6,
    "qs:photo_sum":9,
    "qs:placetype":"Suburb",
    "qs:quad_count":3,
    "qs:woe_adm0":23424977,
    "qs:woe_adm1":2347573,
    "qs:woe_adm2":12588225,
    "qs:woe_funk":"Parented by a neighborhood",
    "qs:woe_lau":0,
    "qs:woe_local":2449700,
    "qs:woe_ver":"7.10.0",
    "wd:wordcount":748,
    "wof:lang":[
        "eng"
    ],
    "wof:name":"Chapel Manor",
    "wof:placetype":"neighbourhood",
    "zs:blockids":[
        180890425031050,
        180890425031048
    ],
    "zs:housing10":0,
    "zs:pop10":0
},
  "geometry": {"coordinates":[-87.325745,41.486403],"type":"Point"}
}