{
  "type": "Feature",
  "properties": {
    "gn:country":"US",
    "gn:fcode":"PPL",
    "gn:population":0,
    "iso:country":"US",
    "name:azb_x_preferred":[
        "\u0622\u0646\u0627\u06a9\u0631"
    ],
    "name:eng_x_preferred":[
        "Anacker"
    ],
    "name:fas_x_preferred":[
        "\u0627\u0646\u0627\u06a9\u0631\u060c \u0648\u06cc\u0633\u06a9\u0627\u0646\u0633\u06cc\u0646"
    ],
    "name:fas_x_variant":[
        "\u0627\u0646\u0627\u06a9\u0631"
    ],
    "name:fra_x_preferred":[
        "Anacker"
    ],
    "qs_pg:aaroncc":"US",
    "qs_pg:gn_country":"US",
    "qs_pg:gn_fcode":"PPL",
    "qs_pg:gn_pop":0,
    "qs_pg:name":"Anacker",
    "qs_pg:name_adm0":"United States",
    "qs_pg:name_adm1":"Wisconsin",
    "qs_pg:photos":7,
    "qs_pg:photos_1k":1,
    "qs_pg:photos_9k":1,
    "qs_pg:photos_9r":1,
    "qs_pg:photos_all":7,
    "qs_pg:photos_sr":1,
    "qs_pg:pop_sr":0,
    "qs_pg:qs_pg_placetype":"locality",
    "qs_pg:qs_pg_placetype_gp":"Town",
    "qs_pg:woe_adm0":23424977,
    "woe:adm0_id":23424977,
    "woe:name_adm0":"United States",
    "woe:name_adm1":"Wisconsin",
    "woe:placetype":"Town",
    "wof:name":"Anacker",
    "wof:placetype":"locality"
},
  "geometry": {"coordinates":[-89.44373,43.62554],"type":"Point"}
}