{
  "type": "Feature",
  "properties": {
    "iso:country":"US",
    "name:eng_x_preferred":[
        "Lomita Hills"
    ],
    "qs:gn_adm0_cc":"US",
    "qs:gn_local":5373129,
    "qs:gn_nam_loc":"Millbrae, San Mateo, California, US",
    "qs:gn_namadm1":"CA",
    "qs:local_max":2146,
    "qs:local_sum":4965,
    "qs:localhoods":7,
    "qs:name":"Lomita Hills",
    "qs:name_adm0":"United States",
    "qs:name_adm1":"California",
    "qs:name_adm2":"San Mateo",
    "qs:name_local":"Millbrae",
    "qs:photo_max":111,
    "qs:photo_sum":351,
    "qs:placetype":"Suburb",
    "qs:quad_count":18,
    "qs:woe_adm0":23424977,
    "qs:woe_adm1":2347563,
    "qs:woe_adm2":12587710,
    "qs:woe_lau":0,
    "qs:woe_local":2451206,
    "qs:woe_ver":"7.10.0",
    "wof:lang":[
        "eng"
    ],
    "wof:name":"Lomita Hills",
    "wof:placetype":"neighbourhood",
    "wof:population":5126,
    "zs:blockids":[
        60816045003009,
        60816045001001,
        60816041012017,
        60816041012011,
        60816044001007,
        60816041012005,
        60816045002000,
        60816039002011,
        60816041012014,
        60816039003004,
        60816044001006,
        60816039004005,
        60816045003008,
        60816039003001,
        60816039003002,
        60816041012003,
        60816041012010,
        60816039004004,
        60816045002005,
        60816041012008,
        60816042003026,
        60816041012002,
        60816039003003,
        60816039002009,
        60816045001004,
        60816045001006,
        60816045001002,
        60816045001003,
        60816041012009,
        60816045001000,
        60816039002012,
        60816039002007,
        60816045002002,
        60816039002013,
        60816045001007,
        60816041012013,
        60816041012016,
        60816039004002,
        60816041012004,
        60816039002006,
        60816039002005,
        60816045002003,
        60816041012001,
        60816041012006,
        60816041012012,
        60816044001005,
        60816044001014,
        60816041012018,
        60816039003000,
        60816039002010,
        60816039002004,
        60816039002008,
        60816039003005,
        60816045002001,
        60816045001005,
        60816041012007
    ],
    "zs:housing10":1865,
    "zs:pop10":5126
},
  "geometry": {"coordinates":[-122.416875,37.613574],"type":"Point"}
}