{
  "type": "Feature",
  "properties": {
    "gn:admin1_code":"KY",
    "gn:admin2_code":"231.0",
    "gn:asciiname":"Wray Gap",
    "gn:country_code":"US",
    "gn:dem":353,
    "gn:elevation":"353.0",
    "gn:feature_class":"P",
    "gn:feature_code":"PPL",
    "gn:name":"Wray Gap",
    "gn:population":0,
    "gn:timezone":"America/Kentucky/Monticello",
    "iso:country":"US",
    "wof:name":"Wray Gap",
    "wof:placetype":"locality"
},
  "geometry": {"coordinates":[-84.85160999999999,36.78813],"type":"Point"}
}