{
  "type": "Feature",
  "properties": {
    "iso:country":"US",
    "name:eng_x_preferred":[
        "White Lake Hills"
    ],
    "wof:name":"White Lake Hills",
    "wof:placetype":"neighbourhood",
    "wof:population":3757,
    "zs:area_m":3814949.104194,
    "zs:blockids":[
        484391065072006,
        484391014013002,
        484391014013010,
        484391065072016,
        484391065072001,
        484391014013007,
        484391065071003,
        484391014012000,
        484391014012007,
        484391014013004,
        484391065072010,
        484391065071006,
        484391014012002,
        484391014012005,
        484391012011074,
        484391065071008,
        484391014012001,
        484391014014000,
        484391014013009,
        484391065072005,
        484391014013000,
        484391065072011,
        484391065072013,
        484391065071011,
        484391065072012,
        484391065072009,
        484391014012012,
        484391065071010,
        484391014013001,
        484391065071001,
        484391014012003,
        484391065071007,
        484391065072007,
        484391065072008,
        484391065071015,
        484391065072002,
        484391065071004,
        484391014013008,
        484391065071012,
        484391065072015,
        484391065071005,
        484391065071000,
        484391065071014,
        484391014014001,
        484391014013005,
        484391014013006,
        484391014013012,
        484391065071013,
        484391065151008,
        484391065072017,
        484391065072004,
        484391065071002,
        484391065071009,
        484391065022001,
        484391065022002,
        484391014012009,
        484391014013003,
        484391014013011,
        484391065072003,
        484391065072000,
        484391065072014,
        484391014012004,
        484391012011072,
        484391014012006,
        484391012011073
    ],
    "zs:housing10":1844,
    "zs:label":"White Lake Hills",
    "zs:pop10":3757
},
  "geometry": {"coordinates":[-97.249562,32.764942],"type":"Point"}
}