{
  "type": "Feature",
  "properties": {
    "gn:admin1_code":"NM",
    "gn:admin2_code":"57.0",
    "gn:asciiname":"Moorehead Place",
    "gn:country_code":"US",
    "gn:dem":1971,
    "gn:elevation":"1971.0",
    "gn:feature_class":"P",
    "gn:feature_code":"PPL",
    "gn:name":"Moorehead Place",
    "gn:population":0,
    "gn:timezone":"America/Denver",
    "iso:country":"US",
    "wof:name":"Moorehead Place",
    "wof:placetype":"locality"
},
  "geometry": {"coordinates":[-106.27141,34.63062],"type":"Point"}
}