{
  "type": "Feature",
  "properties": {
    "iso:country":"US",
    "name:eng_x_preferred":[
        "Holiday Hill"
    ],
    "wof:name":"Holiday Hill",
    "wof:placetype":"neighbourhood",
    "wof:population":4064,
    "zs:area_m":2908771.877929,
    "zs:blockids":[
        120310158014003,
        120310158011022,
        120310158011023,
        120310158014012,
        120310158011029,
        120310158011020,
        120310158014023,
        120310158014006,
        120310158014005,
        120310158014004,
        120310158014018,
        120310158014021,
        120310158022010,
        120310158012016,
        120310158012002,
        120310158011011,
        120310158014010,
        120310158014016,
        120310158011039,
        120310158014002,
        120310155011043,
        120310158014022,
        120310158012021,
        120310158014013,
        120310158011021,
        120310158014007,
        120310158014017,
        120310158014020,
        120310158012020,
        120310155011044,
        120310155011045,
        120310158012017,
        120310158012023,
        120310158011019,
        120310158011040,
        120310158011041,
        120310158011026,
        120310158011017,
        120310158012005,
        120310158012010,
        120310155011037,
        120310155011036,
        120310158011027,
        120310158011012,
        120310158014014,
        120310158011024,
        120310158014008,
        120310158014009,
        120310158014019,
        120310158011031,
        120310158012013,
        120310155011038,
        120310158012004,
        120310158012001,
        120310155011040,
        120310158012022,
        120310158011014,
        120310158014011,
        120310158011015,
        120310158014015,
        120310158011043,
        120310158012015,
        120310158012000,
        120310158012003,
        120310158011010,
        120310158022024,
        120310158012019,
        120310158011016,
        120310158011042,
        120310158011030,
        120310158012006,
        120310158012014,
        120310158011025,
        120310158014024,
        120310158012018
    ],
    "zs:housing10":1838,
    "zs:label":"Holiday Hill",
    "zs:pop10":4064
},
  "geometry": {"coordinates":[-81.58347999999999,30.307261],"type":"Point"}
}