{
  "type": "Feature",
  "properties": {
    "gn:admin1_code":"SC",
    "gn:admin2_code":"31.0",
    "gn:asciiname":"Wallace Crossroads",
    "gn:country_code":"US",
    "gn:dem":43,
    "gn:elevation":"47.0",
    "gn:feature_class":"P",
    "gn:feature_code":"PPL",
    "gn:name":"Wallace Crossroads",
    "gn:population":0,
    "gn:timezone":"America/New_York",
    "iso:country":"US",
    "wof:name":"Wallace Crossroads",
    "wof:placetype":"locality"
},
  "geometry": {"coordinates":[-79.91506,34.20238],"type":"Point"}
}