{
  "type": "Feature",
  "properties": {
    "gn:admin1_code":"VA",
    "gn:admin2_code":"195",
    "gn:asciiname":"Laurel Grove",
    "gn:country_code":"US",
    "gn:dem":738,
    "gn:elevation":"726.0",
    "gn:feature_class":"P",
    "gn:feature_code":"PPL",
    "gn:name":"Laurel Grove",
    "gn:population":0,
    "gn:timezone":"America/New_York",
    "iso:country":"US",
    "name:deu_x_preferred":[
        "Laurel Grove"
    ],
    "wof:name":"Laurel Grove",
    "wof:placetype":"locality"
},
  "geometry": {"coordinates":[-82.65266,36.97982],"type":"Point"}
}