{
  "type": "Feature",
  "properties": {
    "gn:admin1_code":"IL",
    "gn:admin2_code":"201.0",
    "gn:admin3_code":"65013.0",
    "gn:asciiname":"Gem Suburban Manufactured Housing Community",
    "gn:country_code":"US",
    "gn:dem":218,
    "gn:elevation":"215.0",
    "gn:feature_class":"P",
    "gn:feature_code":"PPL",
    "gn:name":"Gem Suburban Manufactured Housing Community",
    "gn:population":0,
    "gn:timezone":"America/Chicago",
    "iso:country":"US",
    "wof:name":"Gem Suburban Manufactured Housing Community",
    "wof:placetype":"locality"
},
  "geometry": {"coordinates":[-89.10417,42.21222],"type":"Point"}
}