{
  "type": "Feature",
  "properties": {
    "gn:admin1_code":"MO",
    "gn:admin2_code":"167.0",
    "gn:admin3_code":"68874.0",
    "gn:asciiname":"Goodson",
    "gn:country_code":"US",
    "gn:dem":330,
    "gn:elevation":"325.0",
    "gn:feature_class":"P",
    "gn:feature_code":"PPL",
    "gn:name":"Goodson",
    "gn:population":0,
    "gn:timezone":"America/Chicago",
    "iso:country":"US",
    "name:azb_x_preferred":[
        "\u0642\u0648\u0648\u062f\u0633\u0648\u0646"
    ],
    "name:fas_x_preferred":[
        "\u06af\u0648\u0648\u062f\u0633\u0648\u0646"
    ],
    "name:vol_x_preferred":[
        "Goodson"
    ],
    "wof:name":"Goodson",
    "wof:placetype":"locality"
},
  "geometry": {"coordinates":[-93.25158,37.70198],"type":"Point"}
}