{
  "type": "Feature",
  "properties": {
    "gn:admin1_code":"FL",
    "gn:admin2_code":"57",
    "gn:asciiname":"Twenty Second Street Heights",
    "gn:country_code":"US",
    "gn:dem":25,
    "gn:elevation":"17.0",
    "gn:feature_class":"P",
    "gn:feature_code":"PPL",
    "gn:name":"Twenty Second Street Heights",
    "gn:population":0,
    "gn:timezone":"America/New_York",
    "iso:country":"US",
    "wof:name":"Twenty Second Street Heights",
    "wof:placetype":"locality"
},
  "geometry": {"coordinates":[-82.4337,28.0047],"type":"Point"}
}