{
  "type": "Feature",
  "properties": {
    "gn:elevation":190,
    "iso:country":"US",
    "name:ceb_x_preferred":[
        "Long Hill"
    ],
    "name:deu_x_preferred":[
        "Long Hill"
    ],
    "name:eng_x_preferred":[
        "Long Hill"
    ],
    "name:eng_x_variant":[
        "Long Hl"
    ],
    "name:pol_x_preferred":[
        "Long Hill"
    ],
    "name:swe_x_preferred":[
        "Long Hill"
    ],
    "name:ukr_x_preferred":[
        "\u041b\u043e\u043d\u0433-\u0413\u0456\u043b\u043b"
    ],
    "name:und_x_variant":[
        "Hoyt Hill"
    ],
    "name:vol_x_preferred":[
        "Long Hill"
    ],
    "qs:gn_adm0_cc":"US",
    "qs:gn_fcode":"PPL",
    "qs:gn_local":4845193,
    "qs:gn_nam_loc":"waterbury",
    "qs:gn_namadm1":"CT",
    "qs:gn_name":"Long Hill",
    "qs:local_max":242,
    "qs:local_sum":1074,
    "qs:localhoods":8,
    "qs:name":"Long Hill",
    "qs:name_adm0":"United States",
    "qs:name_adm1":"Connecticut",
    "qs:name_adm2":"New Haven",
    "qs:name_local":"Waterbury",
    "qs:photo_max":33,
    "qs:photo_sum":100,
    "qs:placetype":"Suburb",
    "qs:quad_count":15,
    "qs:woe_adm0":23424977,
    "qs:woe_adm1":2347565,
    "qs:woe_adm2":12587795,
    "qs:woe_lau":0,
    "qs:woe_local":2515048,
    "qs:woe_ver":"7.10.0",
    "wd:wordcount":29,
    "wof:lang":[
        "eng"
    ],
    "wof:name":"Long Hill",
    "wof:placetype":"neighbourhood",
    "wof:population":4615,
    "zs:blockids":[
        90093511001001,
        90093511001000,
        90093511002007,
        90093511001011,
        90093611004023,
        90093611004007,
        90093611004008,
        90093511002016,
        90093611004022,
        90093511002003,
        90093511001012,
        90093511001014,
        90093511002009,
        90093511002001,
        90093511002015,
        90093611004006,
        90093526001003,
        90093511002002,
        90093511001010,
        90093526001001,
        90093611004020,
        90093511002010,
        90093513002000,
        90093511001002,
        90093611004005,
        90093611004010,
        90093611004009,
        90093612003024,
        90093511002008,
        90093511002014,
        90093511002006,
        90093511002011,
        90093513002001,
        90093611004018,
        90093511002004,
        90093511001003,
        90093513002002,
        90093511001004,
        90093511001013,
        90093526001000,
        90093511002013,
        90093526003000,
        90093511002000,
        90093612003025,
        90093511002005,
        90093511001015,
        90093612003030,
        90093611004024,
        90093611004019,
        90093511002012,
        90093526001006
    ],
    "zs:housing10":2304,
    "zs:pop10":4615
},
  "geometry": {"coordinates":[-73.004988,41.567817],"type":"Point"}
}