{
  "type": "Feature",
  "properties": {
    "gn:country":"US",
    "gn:fcode":"PPL",
    "gn:population":304,
    "iso:country":"US",
    "name:azb_x_preferred":[
        "\u0644\u0627\u062a\u0648\u0646\u06cc\u0627 \u0644\u06cc\u06a9\u0633"
    ],
    "name:cat_x_preferred":[
        "Latonia Lakes"
    ],
    "name:ceb_x_preferred":[
        "Latonia Lakes"
    ],
    "name:dan_x_preferred":[
        "Latonia Lakes"
    ],
    "name:deu_x_preferred":[
        "Latonia Lakes"
    ],
    "name:eng_x_preferred":[
        "Latonia Lakes"
    ],
    "name:fas_x_preferred":[
        "\u0644\u0627\u062a\u0648\u0646\u06cc\u0627 \u0644\u06cc\u06a9\u0633"
    ],
    "name:fra_x_preferred":[
        "Latonia Lakes"
    ],
    "name:gle_x_preferred":[
        "Latonia Lakes"
    ],
    "name:hat_x_preferred":[
        "Latonia Lakes"
    ],
    "name:ido_x_preferred":[
        "Latonia Lakes"
    ],
    "name:ita_x_preferred":[
        "Latonia Lakes"
    ],
    "name:nan_x_preferred":[
        "Latonia Lakes"
    ],
    "name:nld_x_preferred":[
        "Latonia Lakes"
    ],
    "name:pol_x_preferred":[
        "Latonia Lakes"
    ],
    "name:por_x_preferred":[
        "Latonia Lakes"
    ],
    "name:srp_x_preferred":[
        "\u041b\u0430\u0442\u043e\u043d\u0438\u0458\u0430 \u041b\u0435\u0458\u043a\u0441"
    ],
    "name:urd_x_preferred":[
        "\u0644\u0627\u062a\u0646\u06cc\u0627 \u0644\u06cc\u06a9\u0633\u060c \u06a9\u06cc\u0646\u0679\u0648\u06a9\u06cc"
    ],
    "name:urd_x_variant":[
        "\u0644\u0627\u062a\u0646\u06cc\u0627 \u0644\u06cc\u06a9\u0633"
    ],
    "name:vol_x_preferred":[
        "Latonia Lakes"
    ],
    "name:zho_x_preferred":[
        "\u62c9\u6258\u5c3c\u4e9e\u840a\u514b\u65af"
    ],
    "qs_pg:aaroncc":"US",
    "qs_pg:gn_country":"US",
    "qs_pg:gn_fcode":"PPL",
    "qs_pg:gn_pop":304,
    "qs_pg:name":"Latonia Lakes",
    "qs_pg:name_adm0":"United States",
    "qs_pg:name_adm1":"Kentucky",
    "qs_pg:photos":4,
    "qs_pg:photos_1k":1,
    "qs_pg:photos_9k":1,
    "qs_pg:photos_9r":1,
    "qs_pg:photos_all":4,
    "qs_pg:photos_sr":1,
    "qs_pg:pop_sr":5,
    "qs_pg:qs_pg_placetype":"locality",
    "qs_pg:qs_pg_placetype_gp":"Town",
    "qs_pg:woe_adm0":23424977,
    "woe:adm0_id":23424977,
    "woe:name_adm0":"United States",
    "woe:name_adm1":"Kentucky",
    "woe:placetype":"Town",
    "wof:name":"Latonia Lakes",
    "wof:placetype":"locality",
    "wof:population":304
},
  "geometry": {"coordinates":[-84.49772,38.96756],"type":"Point"}
}