{
  "type": "Feature",
  "properties": {
    "gn:admin1_code":"WA",
    "gn:admin2_code":"47.0",
    "gn:asciiname":"M Bar J Ranch Mobile Home Park",
    "gn:country_code":"US",
    "gn:dem":248,
    "gn:elevation":"249.0",
    "gn:feature_class":"P",
    "gn:feature_code":"PPL",
    "gn:name":"M Bar J Ranch Mobile Home Park",
    "gn:population":0,
    "gn:timezone":"America/Los_Angeles",
    "iso:country":"US",
    "wof:name":"M Bar J Ranch Mobile Home Park",
    "wof:placetype":"campus"
},
  "geometry": {"coordinates":[-119.65975,48.29991],"type":"Point"}
}