{
  "type": "Feature",
  "properties": {
    "gn:country":"US",
    "gn:fcode":"PPL",
    "gn:population":0,
    "iso:country":"US",
    "name:cat_x_preferred":[
        "Pelham"
    ],
    "name:ceb_x_preferred":[
        "Pelham"
    ],
    "name:deu_x_preferred":[
        "Pelham"
    ],
    "name:eng_x_preferred":[
        "Pelham"
    ],
    "name:fas_x_preferred":[
        "\u067e\u0644\u0647\u0627\u0645"
    ],
    "name:fra_x_preferred":[
        "Pelham"
    ],
    "name:ita_x_preferred":[
        "Pelham"
    ],
    "name:jpn_x_preferred":[
        "\u30da\u30e9\u30e0"
    ],
    "name:nld_x_preferred":[
        "Pelham"
    ],
    "name:pol_x_preferred":[
        "Pelham"
    ],
    "name:srp_x_preferred":[
        "\u041f\u0435\u043b\u0430\u043c"
    ],
    "name:swa_x_preferred":[
        "Pelham"
    ],
    "name:swe_x_preferred":[
        "Pelham"
    ],
    "name:und_x_variant":[
        "Lesters Factory"
    ],
    "name:vol_x_preferred":[
        "Pelham"
    ],
    "qs_pg:aaroncc":"US",
    "qs_pg:gn_country":"US",
    "qs_pg:gn_fcode":"PPL",
    "qs_pg:gn_pop":0,
    "qs_pg:name":"Pelham",
    "qs_pg:name_adm0":"United States",
    "qs_pg:name_adm1":"South Carolina",
    "qs_pg:photos":130,
    "qs_pg:photos_1k":26,
    "qs_pg:photos_9k":1,
    "qs_pg:photos_9r":3,
    "qs_pg:photos_all":130,
    "qs_pg:photos_sr":3,
    "qs_pg:pop_sr":0,
    "qs_pg:qs_pg_placetype":"locality",
    "qs_pg:qs_pg_placetype_gp":"Town",
    "qs_pg:woe_adm0":23424977,
    "woe:adm0_id":23424977,
    "woe:name_adm0":"United States",
    "woe:name_adm1":"South Carolina",
    "woe:placetype":"Town",
    "wof:name":"Pelham",
    "wof:placetype":"locality"
},
  "geometry": {"coordinates":[-82.224,34.85706],"type":"Point"}
}