{
  "type": "Feature",
  "properties": {
    "gn:admin1_code":"TX",
    "gn:admin2_code":"409",
    "gn:asciiname":"J G Gonzales Colonia",
    "gn:country_code":"US",
    "gn:dem":21,
    "gn:elevation":"15.0",
    "gn:feature_class":"P",
    "gn:feature_code":"PPL",
    "gn:name":"J G Gonzales Colonia",
    "gn:population":0,
    "gn:timezone":"America/Chicago",
    "iso:country":"US",
    "wof:name":"J G Gonzales Colonia",
    "wof:placetype":"locality"
},
  "geometry": {"coordinates":[-97.50637999999999,28.01918],"type":"Point"}
}