{
  "type": "Feature",
  "properties": {
    "gn:country":"US",
    "gn:fcode":"PPL",
    "gn:population":2,
    "iso:country":"US",
    "name:azb_x_preferred":[
        "\u0647\u0648\u0648 \u0645\u0648\u0628\u0627\u06cc\u0644 \u067e\u0627\u0631\u06a9"
    ],
    "name:dan_x_preferred":[
        "Hove Mobile Park"
    ],
    "name:deu_x_preferred":[
        "Hove Mobile Park"
    ],
    "name:eng_x_preferred":[
        "Hove Mobile Park"
    ],
    "name:fas_x_preferred":[
        "\u0647\u0648\u0648 \u0645\u0648\u0628\u0627\u06cc\u0644 \u067e\u0627\u0631\u06a9"
    ],
    "name:fra_x_preferred":[
        "Hove Mobile Park"
    ],
    "name:nan_x_preferred":[
        "Hove Mobile Park"
    ],
    "name:nld_x_preferred":[
        "Hove Mobile Park"
    ],
    "name:por_x_preferred":[
        "Hove Mobile Park"
    ],
    "name:srp_x_preferred":[
        "\u0425\u043e\u0443\u0432 \u041c\u043e\u0431\u0430\u0458\u043b \u041f\u0430\u0440\u043a"
    ],
    "qs_pg:aaroncc":"US",
    "qs_pg:gn_country":"US",
    "qs_pg:gn_fcode":"PPL",
    "qs_pg:gn_pop":2,
    "qs_pg:name":"Hove Mobile Park",
    "qs_pg:photos_9r":0,
    "qs_pg:photos_sr":0,
    "qs_pg:pop_sr":1,
    "qs_pg:qs_pg_placetype":"locality",
    "wof:name":"Hove Mobile Park",
    "wof:placetype":"locality",
    "wof:population":2
},
  "geometry": {"coordinates":[-98.23066,48.5825],"type":"Point"}
}