{
  "type": "Feature",
  "properties": {
    "gn:admin1_code":"TN",
    "gn:admin2_code":"187.0",
    "gn:asciiname":"Carnton Plantation",
    "gn:country_code":"US",
    "gn:dem":204,
    "gn:elevation":"200.0",
    "gn:feature_class":"P",
    "gn:feature_code":"PPL",
    "gn:name":"Carnton Plantation",
    "gn:population":0,
    "gn:timezone":"America/Chicago",
    "iso:country":"US",
    "wof:name":"Carnton Plantation",
    "wof:placetype":"locality"
},
  "geometry": {"coordinates":[-86.85833000000002,35.90312],"type":"Point"}
}