{
  "type": "Feature",
  "properties": {
    "gn:admin1_code":"VA",
    "gn:admin2_code":"63",
    "gn:asciiname":"Union",
    "gn:country_code":"US",
    "gn:dem":829,
    "gn:elevation":"833.0",
    "gn:feature_class":"P",
    "gn:feature_code":"PPL",
    "gn:name":"Union",
    "gn:population":0,
    "gn:timezone":"America/New_York",
    "iso:country":"US",
    "name:fas_x_preferred":[
        "\u06cc\u0648\u0646\u06cc\u0648\u0646"
    ],
    "name:urd_x_preferred":[
        "\u06cc\u0648\u0646\u06cc\u0646"
    ],
    "wof:name":"Union",
    "wof:placetype":"locality"
},
  "geometry": {"coordinates":[-80.44173000000001,36.81041],"type":"Point"}
}