{
  "type": "Feature",
  "properties": {
    "gn:admin1_code":"OK",
    "gn:admin2_code":"39",
    "gn:asciiname":"Cody",
    "gn:country_code":"US",
    "gn:dem":475,
    "gn:elevation":"470.0",
    "gn:feature_class":"P",
    "gn:feature_code":"PPL",
    "gn:name":"Cody",
    "gn:population":0,
    "gn:timezone":"America/Chicago",
    "iso:country":"US",
    "name:ceb_x_preferred":[
        "Cody"
    ],
    "name:dan_x_preferred":[
        "Cody"
    ],
    "name:deu_x_preferred":[
        "Cody"
    ],
    "name:est_x_preferred":[
        "Cody"
    ],
    "name:fas_x_preferred":[
        "\u06a9\u0648\u062f\u06cc"
    ],
    "name:fin_x_preferred":[
        "Cody"
    ],
    "name:fra_x_preferred":[
        "Cody"
    ],
    "name:ita_x_preferred":[
        "Cody"
    ],
    "name:jpn_x_preferred":[
        "\u30b3\u30fc\u30c7\u30a3\u30fc"
    ],
    "name:lat_x_preferred":[
        "Cody"
    ],
    "name:nld_x_preferred":[
        "Cody"
    ],
    "name:pol_x_preferred":[
        "Cody"
    ],
    "name:por_x_preferred":[
        "Cody"
    ],
    "name:rus_x_preferred":[
        "\u041a\u043e\u0434\u0438"
    ],
    "name:spa_x_preferred":[
        "Cody"
    ],
    "name:srp_x_preferred":[
        "\u041a\u043e\u0434\u0438"
    ],
    "name:swe_x_preferred":[
        "Cody"
    ],
    "name:ukr_x_preferred":[
        "\u041a\u043e\u0434\u0456"
    ],
    "name:vol_x_preferred":[
        "Cody"
    ],
    "wof:name":"Cody",
    "wof:placetype":"locality"
},
  "geometry": {"coordinates":[-98.69064,35.80532],"type":"Point"}
}