{
  "type": "Feature",
  "properties": {
    "gn:admin1_code":"TN",
    "gn:admin2_code":"11",
    "gn:asciiname":"Misty Ridge",
    "gn:country_code":"US",
    "gn:dem":255,
    "gn:elevation":"254.0",
    "gn:feature_class":"P",
    "gn:feature_code":"PPL",
    "gn:name":"Misty Ridge",
    "gn:population":0,
    "gn:timezone":"America/New_York",
    "iso:country":"US",
    "wof:name":"Misty Ridge",
    "wof:placetype":"locality"
},
  "geometry": {"coordinates":[-84.93328000000002,35.26313],"type":"Point"}
}