{
  "type": "Feature",
  "properties": {
    "gn:admin1_code":"KY",
    "gn:admin2_code":"227",
    "gn:asciiname":"Clark Landing",
    "gn:country_code":"US",
    "gn:dem":127,
    "gn:elevation":"122.0",
    "gn:feature_class":"P",
    "gn:feature_code":"PPL",
    "gn:name":"Clark Landing",
    "gn:population":0,
    "gn:timezone":"America/Chicago",
    "iso:country":"US",
    "wof:name":"Clark Landing",
    "wof:placetype":"locality"
},
  "geometry": {"coordinates":[-86.60221,37.13532],"type":"Point"}
}