{
  "type": "Feature",
  "properties": {
    "gn:admin1_code":"OR",
    "gn:admin2_code":"21.0",
    "gn:asciiname":"Mikkalo",
    "gn:country_code":"US",
    "gn:dem":450,
    "gn:elevation":"448.0",
    "gn:feature_class":"P",
    "gn:feature_code":"PPL",
    "gn:name":"Mikkalo",
    "gn:population":0,
    "gn:timezone":"America/Los_Angeles",
    "iso:country":"US",
    "name:hat_x_preferred":[
        "Mikkalo"
    ],
    "wof:name":"Mikkalo",
    "wof:placetype":"locality"
},
  "geometry": {"coordinates":[-120.23475999999999,45.47096],"type":"Point"}
}