{
  "type": "Feature",
  "properties": {
    "iso:country":"US",
    "name:cat_x_preferred":[
        "Willowbrook"
    ],
    "name:ceb_x_preferred":[
        "Willowbrook"
    ],
    "name:deu_x_preferred":[
        "Willowbrook"
    ],
    "name:eng_x_preferred":[
        "Willowbrook"
    ],
    "name:fra_x_preferred":[
        "Willowbrook"
    ],
    "name:ita_x_preferred":[
        "Willowbrook"
    ],
    "name:nld_x_preferred":[
        "Willowbrook"
    ],
    "name:pol_x_preferred":[
        "Willowbrook"
    ],
    "name:por_x_preferred":[
        "Willowbrook"
    ],
    "name:spa_x_preferred":[
        "Willowbrook"
    ],
    "name:srp_x_preferred":[
        "\u0412\u0438\u043b\u043e\u0443\u0431\u0440\u0443\u043a"
    ],
    "name:swe_x_preferred":[
        "Willowbrook"
    ],
    "name:vol_x_preferred":[
        "Willowbrook"
    ],
    "wof:name":"Willowbrook",
    "wof:placetype":"neighbourhood",
    "wof:population":739,
    "zs:area_m":3953633.594259,
    "zs:blockids":[
        371010410023019,
        371010410023016,
        371010410023014,
        371010410023018,
        371010410023017,
        371010410023015
    ],
    "zs:housing10":328,
    "zs:label":"Willowbrook",
    "zs:pop10":739
},
  "geometry": {"coordinates":[-78.484832,35.681471],"type":"Point"}
}