{
  "type": "Feature",
  "properties": {
    "gn:admin1_code":"AR",
    "gn:admin2_code":"87.0",
    "gn:admin3_code":"93144.0",
    "gn:asciiname":"Roxton",
    "gn:country_code":"US",
    "gn:dem":446,
    "gn:elevation":"445.0",
    "gn:feature_class":"P",
    "gn:feature_code":"PPL",
    "gn:name":"Roxton",
    "gn:population":0,
    "gn:timezone":"America/Chicago",
    "iso:country":"US",
    "name:ceb_x_preferred":[
        "Roxton"
    ],
    "name:ita_x_preferred":[
        "Roxton"
    ],
    "name:nld_x_preferred":[
        "Roxton"
    ],
    "name:por_x_preferred":[
        "Roxton"
    ],
    "name:spa_x_preferred":[
        "Roxton"
    ],
    "name:swe_x_preferred":[
        "Roxton"
    ],
    "wof:name":"Roxton",
    "wof:placetype":"locality"
},
  "geometry": {"coordinates":[-93.79825,36.03702],"type":"Point"}
}