{
  "type": "Feature",
  "properties": {
    "gn:admin1_code":"MD",
    "gn:admin2_code":"31.0",
    "gn:asciiname":"Avenel",
    "gn:country_code":"US",
    "gn:dem":139,
    "gn:elevation":"142.0",
    "gn:feature_class":"P",
    "gn:feature_code":"PPL",
    "gn:name":"Avenel",
    "gn:population":0,
    "gn:timezone":"America/New_York",
    "iso:country":"US",
    "name:ceb_x_preferred":[
        "Avenel"
    ],
    "name:fra_x_preferred":[
        "Avenel"
    ],
    "name:ita_x_preferred":[
        "Avenel"
    ],
    "name:pol_x_preferred":[
        "Avenel"
    ],
    "name:rus_x_preferred":[
        "\u0410\u0432\u0435\u043d\u0435\u043b\u044c"
    ],
    "name:swe_x_preferred":[
        "Avenel"
    ],
    "wof:name":"Avenel",
    "wof:placetype":"locality"
},
  "geometry": {"coordinates":[-77.08581,39.15677],"type":"Point"}
}