{
  "type": "Feature",
  "properties": {
    "gn:admin1_code":"MD",
    "gn:admin2_code":"19.0",
    "gn:asciiname":"Rocky Hook",
    "gn:country_code":"US",
    "gn:dem":2,
    "gn:elevation":"2.0",
    "gn:feature_class":"P",
    "gn:feature_code":"PPL",
    "gn:name":"Rocky Hook",
    "gn:population":0,
    "gn:timezone":"America/New_York",
    "iso:country":"US",
    "wof:name":"Rocky Hook",
    "wof:placetype":"locality"
},
  "geometry": {"coordinates":[-75.92744,38.48401],"type":"Point"}
}