{
  "type": "Feature",
  "properties": {
    "gn:admin1_code":"DE",
    "gn:admin2_code":"3.0",
    "gn:asciiname":"Limestone Gap",
    "gn:country_code":"US",
    "gn:dem":32,
    "gn:elevation":"31.0",
    "gn:feature_class":"P",
    "gn:feature_code":"PPL",
    "gn:name":"Limestone Gap",
    "gn:population":0,
    "gn:timezone":"America/New_York",
    "iso:country":"US",
    "wof:name":"Limestone Gap",
    "wof:placetype":"locality"
},
  "geometry": {"coordinates":[-75.65937,39.72789],"type":"Point"}
}