{
  "type": "Feature",
  "properties": {
    "iso:country":"US",
    "name:eng_x_preferred":[
        "Cardinal Hill"
    ],
    "wof:name":"Cardinal Hill",
    "wof:placetype":"neighbourhood",
    "wof:population":76,
    "zs:area_m":50470.654778,
    "zs:blockids":[
        210670026003002
    ],
    "zs:housing10":42,
    "zs:label":"Cardinal Hill",
    "zs:pop10":76
},
  "geometry": {"coordinates":[-84.541524,38.038682],"type":"Point"}
}