{
  "type": "Feature",
  "properties": {
    "gn:admin1_code":"NY",
    "gn:admin2_code":"93.0",
    "gn:admin3_code":"51264.0",
    "gn:asciiname":"Van Buren Park Homes",
    "gn:country_code":"US",
    "gn:dem":129,
    "gn:elevation":"126.0",
    "gn:feature_class":"P",
    "gn:feature_code":"PPL",
    "gn:name":"Van Buren Park Homes",
    "gn:population":0,
    "gn:timezone":"America/New_York",
    "iso:country":"US",
    "wof:name":"Van Buren Park Homes",
    "wof:placetype":"locality"
},
  "geometry": {"coordinates":[-73.899,42.8003],"type":"Point"}
}