{
  "type": "Feature",
  "properties": {
    "gn:admin1_code":"AL",
    "gn:admin2_code":"115",
    "gn:asciiname":"Glen City",
    "gn:country_code":"US",
    "gn:dem":182,
    "gn:elevation":"178.0",
    "gn:feature_class":"P",
    "gn:feature_code":"PPL",
    "gn:name":"Glen City",
    "gn:population":0,
    "gn:timezone":"America/Chicago",
    "iso:country":"US",
    "wof:name":"Glen City",
    "wof:placetype":"locality"
},
  "geometry": {"coordinates":[-86.28414000000002,33.5776],"type":"Point"}
}