{
  "type": "Feature",
  "properties": {
    "gn:admin1_code":"PA",
    "gn:admin2_code":"47.0",
    "gn:admin3_code":"5576.0",
    "gn:asciiname":"Grant",
    "gn:country_code":"US",
    "gn:dem":304,
    "gn:elevation":"298.0",
    "gn:feature_class":"P",
    "gn:feature_code":"PPL",
    "gn:name":"Grant",
    "gn:population":0,
    "gn:timezone":"America/New_York",
    "iso:country":"US",
    "name:bos_x_preferred":[
        "Grant"
    ],
    "name:ceb_x_preferred":[
        "Grant"
    ],
    "name:ces_x_preferred":[
        "Grant"
    ],
    "name:deu_x_preferred":[
        "Grant"
    ],
    "name:epo_x_preferred":[
        "Grant"
    ],
    "name:fin_x_preferred":[
        "Grant"
    ],
    "name:fra_x_preferred":[
        "Grant"
    ],
    "name:heb_x_preferred":[
        "\u05d2\u05e8\u05e0\u05d8"
    ],
    "name:ita_x_preferred":[
        "Grant"
    ],
    "name:jpn_x_preferred":[
        "\u30b0\u30e9\u30f3\u30c8"
    ],
    "name:kor_x_preferred":[
        "\uadf8\ub79c\ud2b8"
    ],
    "name:lit_x_preferred":[
        "Grant"
    ],
    "name:nld_x_preferred":[
        "Grant"
    ],
    "name:pol_x_preferred":[
        "Grant"
    ],
    "name:por_x_preferred":[
        "Grant"
    ],
    "name:ron_x_preferred":[
        "Grant"
    ],
    "name:slv_x_preferred":[
        "Grant"
    ],
    "name:spa_x_preferred":[
        "Grant"
    ],
    "name:swe_x_preferred":[
        "Grant"
    ],
    "name:tur_x_preferred":[
        "Grant"
    ],
    "name:ukr_x_preferred":[
        "\u0490\u0440\u0430\u043d\u0442"
    ],
    "name:vol_x_preferred":[
        "Grant"
    ],
    "name:zho_x_preferred":[
        "\u683c\u5170\u7279"
    ],
    "wof:name":"Grant",
    "wof:placetype":"locality"
},
  "geometry": {"coordinates":[-78.30807,41.33673],"type":"Point"}
}