{
  "type": "Feature",
  "properties": {
    "gn:elevation":171,
    "iso:country":"US",
    "name:deu_x_preferred":[
        "Dargin"
    ],
    "name:eng_x_preferred":[
        "Dargin"
    ],
    "qs:gn_adm0_cc":"US",
    "qs:gn_fcode":"PPL",
    "qs:gn_local":4053050,
    "qs:gn_nam_loc":"Calera, Shelby, Alabama, US",
    "qs:gn_namadm1":"AL",
    "qs:gn_name":"Dargin",
    "qs:local_max":184,
    "qs:local_sum":191,
    "qs:localhoods":2,
    "qs:name":"Dargin",
    "qs:name_adm0":"United States",
    "qs:name_adm1":"Alabama",
    "qs:name_adm2":"Shelby",
    "qs:name_local":"Calera",
    "qs:photo_max":6,
    "qs:photo_sum":7,
    "qs:placetype":"Suburb",
    "qs:quad_count":2,
    "qs:woe_adm0":23424977,
    "qs:woe_adm1":2347559,
    "qs:woe_adm2":12587544,
    "qs:woe_lau":0,
    "qs:woe_local":2373220,
    "qs:woe_ver":"7.10.0",
    "wd:wordcount":12,
    "wof:lang":[
        "eng"
    ],
    "wof:name":"Dargin",
    "wof:placetype":"neighbourhood",
    "wof:population":2334,
    "zs:blockids":[
        11170306091066,
        11170306091059,
        11170306091070,
        11170306091057,
        11170306091056,
        11170306091063,
        11170306091065,
        11170306091061
    ],
    "zs:housing10":1114,
    "zs:pop10":2334
},
  "geometry": {"coordinates":[-86.74844299999999,33.158906],"type":"Point"}
}