{
  "type": "Feature",
  "properties": {
    "gn:admin1_code":"ME",
    "gn:admin2_code":"29.0",
    "gn:admin3_code":"51375.0",
    "gn:asciiname":"Mattimo Place",
    "gn:country_code":"US",
    "gn:dem":24,
    "gn:elevation":"25.0",
    "gn:feature_class":"P",
    "gn:feature_code":"PPL",
    "gn:name":"Mattimo Place",
    "gn:population":0,
    "gn:timezone":"America/New_York",
    "iso:country":"US",
    "wof:name":"Mattimo Place",
    "wof:placetype":"locality"
},
  "geometry": {"coordinates":[-67.64027,44.82258],"type":"Point"}
}