{
  "type": "Feature",
  "properties": {
    "gn:admin1_code":"TN",
    "gn:admin2_code":"17",
    "gn:asciiname":"Hico",
    "gn:country_code":"US",
    "gn:dem":123,
    "gn:elevation":"118.0",
    "gn:feature_class":"P",
    "gn:feature_code":"PPL",
    "gn:name":"Hico",
    "gn:population":0,
    "gn:timezone":"America/Chicago",
    "iso:country":"US",
    "wof:name":"Hico",
    "wof:placetype":"locality"
},
  "geometry": {"coordinates":[-88.48950000000001,36.09117],"type":"Point"}
}