{
  "type": "Feature",
  "properties": {
    "gn:admin1_code":"AR",
    "gn:admin2_code":"107.0",
    "gn:admin3_code":"90849.0",
    "gn:asciiname":"Southland",
    "gn:country_code":"US",
    "gn:dem":92,
    "gn:elevation":"88.0",
    "gn:feature_class":"P",
    "gn:feature_code":"PPL",
    "gn:name":"Southland",
    "gn:population":0,
    "gn:timezone":"America/Chicago",
    "iso:country":"US",
    "name:cat_x_preferred":[
        "Southland"
    ],
    "name:deu_x_preferred":[
        "Southland"
    ],
    "name:fin_x_preferred":[
        "Southland"
    ],
    "name:fra_x_preferred":[
        "Southland"
    ],
    "name:hun_x_preferred":[
        "Southland"
    ],
    "name:jpn_x_preferred":[
        "\u30b5\u30a6\u30b9\u30e9\u30f3\u30c9"
    ],
    "name:kor_x_preferred":[
        "\uc0ac\uc6b0\uc2a4\ub79c\ub4dc"
    ],
    "name:nld_x_preferred":[
        "Southland"
    ],
    "name:rus_x_preferred":[
        "\u0421\u0430\u0443\u0442\u043b\u0435\u043d\u0434"
    ],
    "name:swe_x_preferred":[
        "Southland"
    ],
    "wof:name":"Southland",
    "wof:placetype":"locality"
},
  "geometry": {"coordinates":[-90.654,34.58538],"type":"Point"}
}