{
  "type": "Feature",
  "properties": {
    "gn:admin1_code":"TN",
    "gn:admin2_code":"25.0",
    "gn:asciiname":"Riley",
    "gn:country_code":"US",
    "gn:dem":368,
    "gn:elevation":"370.0",
    "gn:feature_class":"P",
    "gn:feature_code":"PPL",
    "gn:name":"Riley",
    "gn:population":0,
    "gn:timezone":"America/New_York",
    "iso:country":"US",
    "name:bul_x_preferred":[
        "\u0420\u0430\u0439\u043b\u0438"
    ],
    "name:ceb_x_preferred":[
        "Riley"
    ],
    "name:ces_x_preferred":[
        "Riley"
    ],
    "name:deu_x_preferred":[
        "Riley"
    ],
    "name:fra_x_preferred":[
        "Riley"
    ],
    "name:heb_x_preferred":[
        "\u05e8\u05d9\u05d9\u05dc\u05d9"
    ],
    "name:ita_x_preferred":[
        "Riley"
    ],
    "name:jpn_x_preferred":[
        "\u30e9\u30a4\u30ea\u30fc"
    ],
    "name:nld_x_preferred":[
        "Riley"
    ],
    "name:pol_x_preferred":[
        "Riley"
    ],
    "name:por_x_preferred":[
        "Riley"
    ],
    "name:rus_x_preferred":[
        "\u0420\u0430\u0439\u043b\u0438"
    ],
    "name:spa_x_preferred":[
        "Riley"
    ],
    "name:srp_x_preferred":[
        "\u0420\u0430\u0458\u043b\u0438"
    ],
    "name:swe_x_preferred":[
        "Riley"
    ],
    "name:ukr_x_preferred":[
        "\u0420\u0430\u0439\u043b\u0456"
    ],
    "name:vol_x_preferred":[
        "Riley"
    ],
    "wof:name":"Riley",
    "wof:placetype":"locality"
},
  "geometry": {"coordinates":[-83.43185,36.5412],"type":"Point"}
}