{
  "type": "Feature",
  "properties": {
    "gn:admin1_code":"IN",
    "gn:admin2_code":"179.0",
    "gn:admin3_code":"55422.0",
    "gn:asciiname":"Phenix",
    "gn:country_code":"US",
    "gn:dem":264,
    "gn:elevation":"266.0",
    "gn:feature_class":"P",
    "gn:feature_code":"PPL",
    "gn:name":"Phenix",
    "gn:population":0,
    "gn:timezone":"America/Indiana/Indianapolis",
    "iso:country":"US",
    "name:deu_x_preferred":[
        "Phenix"
    ],
    "name:ita_x_preferred":[
        "Phenix"
    ],
    "name:nld_x_preferred":[
        "Phenix"
    ],
    "name:pol_x_preferred":[
        "Phenix"
    ],
    "name:swe_x_preferred":[
        "Phenix"
    ],
    "wof:name":"Phenix",
    "wof:placetype":"locality"
},
  "geometry": {"coordinates":[-85.10719,40.58199000000001],"type":"Point"}
}