{
  "type": "Feature",
  "properties": {
    "gn:admin1_code":"VA",
    "gn:admin2_code":"133",
    "gn:asciiname":"Fairport",
    "gn:country_code":"US",
    "gn:dem":7,
    "gn:elevation":"3.0",
    "gn:feature_class":"P",
    "gn:feature_code":"PPL",
    "gn:name":"Fairport",
    "gn:population":0,
    "gn:timezone":"America/New_York",
    "iso:country":"US",
    "name:eng_x_preferred":[
        "Fairport"
    ],
    "name:und_x_variant":[
        "Timbs Wharf",
        "Fair Port",
        "Timbs"
    ],
    "wof:name":"Fairport",
    "wof:placetype":"locality"
},
  "geometry": {"coordinates":[-76.29021999999998,37.83346],"type":"Point"}
}