{
  "type": "Feature",
  "properties": {
    "iso:country":"US",
    "name:eng_x_preferred":[
        "Bellaire Junction"
    ],
    "wof:name":"Bellaire Junction",
    "wof:placetype":"neighbourhood",
    "wof:population":501,
    "zs:area_m":463824.045432,
    "zs:blockids":[
        482014126002000,
        482014118003017,
        482014117002000,
        482014118003020,
        482014118003006,
        482014118003009,
        482014118003007,
        482014118003003,
        482014117002003,
        482014126002001,
        482014118003024,
        482014117001005,
        482014118003025,
        482014118003005,
        482014118003008,
        482014117002002,
        482014118003004,
        482014118003023,
        482014118003019,
        482014117002001
    ],
    "zs:housing10":229,
    "zs:label":"Bellaire Junction",
    "zs:pop10":501
},
  "geometry": {"coordinates":[-95.446451,29.727854],"type":"Point"}
}