{
  "type": "Feature",
  "properties": {
    "iso:country":"US",
    "name:ceb_x_preferred":[
        "Clear Creek"
    ],
    "name:deu_x_preferred":[
        "Clear Creek"
    ],
    "name:eng_x_preferred":[
        "Clear Creek"
    ],
    "name:fra_x_preferred":[
        "Clear Creek"
    ],
    "name:ita_x_preferred":[
        "Clear Creek"
    ],
    "name:pol_x_preferred":[
        "Clear Creek"
    ],
    "name:srp_x_preferred":[
        "\u041a\u043b\u0438 \u041a\u0440\u0438\u043a"
    ],
    "name:swe_x_preferred":[
        "Clear Creek"
    ],
    "name:ukr_x_preferred":[
        "\u041a\u043b\u0456\u0440-\u041a\u0440\u0456\u043a"
    ],
    "wof:name":"Clear Creek",
    "wof:placetype":"neighbourhood",
    "wof:population":3374,
    "zs:area_m":27195748.340321,
    "zs:blockids":[
        120690313114021,
        120690313114134,
        120690313114074,
        120690313114087
    ],
    "zs:housing10":1917,
    "zs:label":"Clear Creek",
    "zs:pop10":3374
},
  "geometry": {"coordinates":[-81.672077,28.396664],"type":"Point"}
}