{
  "type": "Feature",
  "properties": {
    "gn:admin1_code":"PA",
    "gn:admin2_code":"89.0",
    "gn:admin3_code":"49080.0",
    "gn:asciiname":"Monroe Lake",
    "gn:country_code":"US",
    "gn:dem":312,
    "gn:elevation":"310.0",
    "gn:feature_class":"P",
    "gn:feature_code":"PPL",
    "gn:name":"Monroe Lake",
    "gn:population":0,
    "gn:timezone":"America/New_York",
    "iso:country":"US",
    "wof:name":"Monroe Lake",
    "wof:placetype":"locality"
},
  "geometry": {"coordinates":[-75.14073,41.11482],"type":"Point"}
}