{
  "type": "Feature",
  "properties": {
    "gn:country":"US",
    "gn:fcode":"PPL",
    "gn:population":0,
    "iso:country":"US",
    "name:azb_x_preferred":[
        "\u0632\u0627\u06cc\u0632\u06a9\u0633"
    ],
    "name:bel_x_preferred":[
        "\u0417\u0430\u0439\u0437\u0456\u043a\u0441"
    ],
    "name:deu_x_preferred":[
        "Zzyzx"
    ],
    "name:eng_x_preferred":[
        "Zzyzx"
    ],
    "name:est_x_preferred":[
        "Zzyzx"
    ],
    "name:fas_x_preferred":[
        "\u0632\u0627\u06cc\u0632\u06a9\u0633"
    ],
    "name:fra_x_preferred":[
        "Zzyzx"
    ],
    "name:hun_x_preferred":[
        "Zzyzx"
    ],
    "name:ita_x_preferred":[
        "Zzyzx"
    ],
    "name:jpn_x_preferred":[
        "\u30b8\u30fc\u30b8\u30c3\u30af\u30b9"
    ],
    "name:nan_x_preferred":[
        "Zzyzx"
    ],
    "name:nld_x_preferred":[
        "Zzyzx"
    ],
    "name:pol_x_preferred":[
        "Zzyzx"
    ],
    "name:por_x_preferred":[
        "Zzyzx"
    ],
    "name:rus_x_preferred":[
        "Zzyzx"
    ],
    "name:rus_x_variant":[
        "\u0417\u0430\u0439\u0437\u0438\u043a\u0441"
    ],
    "name:tur_x_preferred":[
        "Zzyzx"
    ],
    "name:und_x_variant":[
        "Soda Springs"
    ],
    "name:vol_x_preferred":[
        "Zzyzx"
    ],
    "name:zho_x_preferred":[
        "\u5bb0\u5179\u514b\u65af"
    ],
    "qs_pg:aaroncc":"US",
    "qs_pg:gn_country":"US",
    "qs_pg:gn_fcode":"PPL",
    "qs_pg:gn_pop":0,
    "qs_pg:name":"Zzyzx",
    "qs_pg:name_adm0":"United States",
    "qs_pg:name_adm1":"California",
    "qs_pg:photos":619,
    "qs_pg:photos_1k":125,
    "qs_pg:photos_9k":3,
    "qs_pg:photos_9r":5,
    "qs_pg:photos_all":619,
    "qs_pg:photos_sr":8,
    "qs_pg:pop_sr":0,
    "qs_pg:qs_pg_placetype":"locality",
    "qs_pg:qs_pg_placetype_gp":"Town",
    "qs_pg:woe_adm0":23424977,
    "woe:adm0_id":23424977,
    "woe:name_adm0":"United States",
    "woe:name_adm1":"California",
    "woe:placetype":"Town",
    "wof:name":"Zzyzx",
    "wof:placetype":"locality"
},
  "geometry": {"coordinates":[-116.10474000000001,35.14276],"type":"Point"}
}