{
  "type": "Feature",
  "properties": {
    "gn:admin1_code":"KY",
    "gn:admin2_code":"235",
    "gn:asciiname":"Faber",
    "gn:country_code":"US",
    "gn:dem":322,
    "gn:elevation":"321.0",
    "gn:feature_class":"P",
    "gn:feature_code":"PPL",
    "gn:name":"Faber",
    "gn:population":0,
    "gn:timezone":"America/New_York",
    "iso:country":"US",
    "name:cat_x_preferred":[
        "Faber"
    ],
    "name:deu_x_preferred":[
        "Faber"
    ],
    "name:eng_x_preferred":[
        "Faber"
    ],
    "name:fin_x_preferred":[
        "Faber"
    ],
    "name:fra_x_preferred":[
        "Faber"
    ],
    "name:fry_x_preferred":[
        "Faber"
    ],
    "name:ita_x_preferred":[
        "Faber"
    ],
    "name:ltz_x_preferred":[
        "Faber"
    ],
    "name:nds_x_preferred":[
        "Faber"
    ],
    "name:nld_x_preferred":[
        "Faber"
    ],
    "name:pol_x_preferred":[
        "Faber"
    ],
    "name:por_x_preferred":[
        "Faber"
    ],
    "name:rus_x_preferred":[
        "\u0424\u0430\u0431\u0435\u0440"
    ],
    "name:spa_x_preferred":[
        "Faber"
    ],
    "name:swe_x_preferred":[
        "Faber"
    ],
    "name:und_x_variant":[
        "Watts"
    ],
    "wof:name":"Faber",
    "wof:placetype":"locality"
},
  "geometry": {"coordinates":[-84.13020999999998,36.8737],"type":"Point"}
}