{
  "type": "Feature",
  "properties": {
    "gn:admin1_code":"AL",
    "gn:admin2_code":"77.0",
    "gn:asciiname":"Petersville",
    "gn:country_code":"US",
    "gn:dem":186,
    "gn:elevation":"186.0",
    "gn:feature_class":"P",
    "gn:feature_code":"PPL",
    "gn:name":"Petersville",
    "gn:population":0,
    "gn:timezone":"America/Chicago",
    "iso:country":"US",
    "wof:name":"Petersville",
    "wof:placetype":"locality"
},
  "geometry": {"coordinates":[-87.69169000000002,34.85536],"type":"Point"}
}