{
  "type": "Feature",
  "properties": {
    "iso:country":"US",
    "name:deu_x_preferred":[
        "Ludington"
    ],
    "name:eng_x_preferred":[
        "Ludington"
    ],
    "name:fra_x_preferred":[
        "Ludington"
    ],
    "name:ita_x_preferred":[
        "Ludington"
    ],
    "name:pol_x_preferred":[
        "Ludington"
    ],
    "name:swe_x_preferred":[
        "Ludington"
    ],
    "name:ukr_x_preferred":[
        "\u041b\u0430\u0434\u0456\u043d\u0433\u0442\u043e\u043d"
    ],
    "wd:wordcount":62,
    "wof:name":"Ludington",
    "wof:placetype":"neighbourhood",
    "wof:population":191,
    "zs:area_m":593538.655515,
    "zs:blockids":[
        220119603003022,
        220119603003021,
        220119603004001,
        220119603003041,
        220119603004007
    ],
    "zs:housing10":92,
    "zs:label":"Ludington",
    "zs:pop10":191
},
  "geometry": {"coordinates":[-93.287549,30.863377],"type":"Point"}
}