{
  "type": "Feature",
  "properties": {
    "gn:admin1_code":"FL",
    "gn:admin2_code":"105.0",
    "gn:asciiname":"Lake Fox Village Mobile Home Park",
    "gn:country_code":"US",
    "gn:dem":44,
    "gn:elevation":"43.0",
    "gn:feature_class":"P",
    "gn:feature_code":"PPL",
    "gn:name":"Lake Fox Village Mobile Home Park",
    "gn:population":0,
    "gn:timezone":"America/New_York",
    "iso:country":"US",
    "wof:name":"Lake Fox Village Mobile Home Park",
    "wof:placetype":"campus"
},
  "geometry": {"coordinates":[-81.65989999999999,27.9869],"type":"Point"}
}