{
  "type": "Feature",
  "properties": {
    "iso:country":"US",
    "name:eng_x_preferred":[
        "Joliet Regional Airport"
    ],
    "name:eng_x_variant":[
        "JOT",
        "KJOT"
    ],
    "name:fas_x_preferred":[
        "\u0641\u0631\u0648\u062f\u06af\u0627\u0647 \u0645\u0646\u0637\u0642\u0647\u200c\u0627\u06cc \u0698\u0648\u0644\u06cc\u062a"
    ],
    "name:pol_x_preferred":[
        "Port lotniczy Joliet"
    ],
    "name:ron_x_preferred":[
        "Aeroportul Regional Joliet"
    ],
    "name:tgk_x_preferred":[
        "\u0424\u0443\u0440\u0443\u0434\u0433\u043e\u04b3\u0438 \u043c\u0430\u043d\u0442\u0430\u049b\u0430\u200c\u0438\u0439 \u0436\u0443\u043b\u0438\u0442"
    ],
    "name:urd_x_preferred":[
        "\u062c\u0648\u0644\u06cc\u0679 \u0631\u06cc\u062c\u0646\u0644 \u06c1\u0648\u0627\u0626\u06cc \u0627\u0688\u0627"
    ],
    "oa:elevation_ft":"582",
    "oa:type":"small_airport",
    "wd:wordcount":364,
    "woe:hierarchy":{
        "country_id":23424977,
        "county_id":12588176,
        "planet_id":1,
        "state_id":2347572
    },
    "wof:name":"Joliet Regional Airport",
    "wof:placetype":"campus"
},
  "geometry": {"coordinates":[-88.175499,41.517799],"type":"Point"}
}