{
  "type": "Feature",
  "properties": {
    "gn:admin1_code":"KY",
    "gn:admin2_code":"27",
    "gn:asciiname":"Mystic",
    "gn:country_code":"US",
    "gn:dem":134,
    "gn:elevation":"127.0",
    "gn:feature_class":"P",
    "gn:feature_code":"PPL",
    "gn:name":"Mystic",
    "gn:population":0,
    "gn:timezone":"America/Chicago",
    "iso:country":"US",
    "name:fas_x_preferred":[
        "\u0645\u06cc\u0633\u062a\u06cc\u06a9"
    ],
    "name:urd_x_preferred":[
        "\u0645\u0627\u0626\u06cc \u0633\u0679\u06a9"
    ],
    "wof:name":"Mystic",
    "wof:placetype":"locality"
},
  "geometry": {"coordinates":[-86.44275999999998,37.89701],"type":"Point"}
}