{
  "type": "Feature",
  "properties": {
    "gn:admin1_code":"VT",
    "gn:admin2_code":"5.0",
    "gn:admin3_code":"17125.0",
    "gn:asciiname":"West Danville",
    "gn:country_code":"US",
    "gn:dem":478,
    "gn:elevation":"480.0",
    "gn:feature_class":"P",
    "gn:feature_code":"PPL",
    "gn:name":"West Danville",
    "gn:population":0,
    "gn:timezone":"America/New_York",
    "iso:country":"US",
    "wof:name":"West Danville",
    "wof:placetype":"locality"
},
  "geometry": {"coordinates":[-72.1951,44.4095],"type":"Point"}
}