{
  "type": "Feature",
  "properties": {
    "gn:admin1_code":"KY",
    "gn:admin2_code":"59.0",
    "gn:asciiname":"Hunters Ridge",
    "gn:country_code":"US",
    "gn:dem":145,
    "gn:elevation":"144.0",
    "gn:feature_class":"P",
    "gn:feature_code":"PPL",
    "gn:name":"Hunters Ridge",
    "gn:population":0,
    "gn:timezone":"America/Chicago",
    "iso:country":"US",
    "wof:name":"Hunters Ridge",
    "wof:placetype":"locality"
},
  "geometry": {"coordinates":[-87.06995000000001,37.73047],"type":"Point"}
}