{
  "type": "Feature",
  "properties": {
    "gn:admin1_code":"VA",
    "gn:admin2_code":"179.0",
    "gn:asciiname":"Michaelbrooke Estates",
    "gn:country_code":"US",
    "gn:dem":36,
    "gn:elevation":"31.0",
    "gn:feature_class":"P",
    "gn:feature_code":"PPL",
    "gn:name":"Michaelbrooke Estates",
    "gn:population":0,
    "gn:timezone":"America/New_York",
    "iso:country":"US",
    "wof:name":"Michaelbrooke Estates",
    "wof:placetype":"locality"
},
  "geometry": {"coordinates":[-77.3956,38.3649],"type":"Point"}
}