{
  "type": "Feature",
  "properties": {
    "gn:admin1_code":"WA",
    "gn:admin2_code":"33.0",
    "gn:asciiname":"Mirrormount Estates",
    "gn:country_code":"US",
    "gn:dem":166,
    "gn:elevation":"148.0",
    "gn:feature_class":"P",
    "gn:feature_code":"PPL",
    "gn:name":"Mirrormount Estates",
    "gn:population":0,
    "gn:timezone":"America/Los_Angeles",
    "iso:country":"US",
    "wof:name":"Mirrormount Estates",
    "wof:placetype":"locality"
},
  "geometry": {"coordinates":[-122.00789,47.45066],"type":"Point"}
}