{
  "type": "Feature",
  "properties": {
    "gn:admin1_code":"MO",
    "gn:admin2_code":"55.0",
    "gn:admin3_code":"42086.0",
    "gn:asciiname":"Vilander",
    "gn:country_code":"US",
    "gn:dem":228,
    "gn:elevation":"220.0",
    "gn:feature_class":"P",
    "gn:feature_code":"PPL",
    "gn:name":"Vilander",
    "gn:population":0,
    "gn:timezone":"America/Chicago",
    "iso:country":"US",
    "wof:name":"Vilander",
    "wof:placetype":"locality"
},
  "geometry": {"coordinates":[-91.13153,38.09644],"type":"Point"}
}