{
  "type": "Feature",
  "properties": {
    "gn:admin1_code":"TX",
    "gn:admin2_code":"429",
    "gn:asciiname":"Gunsight",
    "gn:country_code":"US",
    "gn:dem":437,
    "gn:elevation":"433.0",
    "gn:feature_class":"P",
    "gn:feature_code":"PPL",
    "gn:name":"Gunsight",
    "gn:population":0,
    "gn:timezone":"America/Chicago",
    "iso:country":"US",
    "wof:name":"Gunsight",
    "wof:placetype":"locality"
},
  "geometry": {"coordinates":[-98.87118,32.54152],"type":"Point"}
}