{
  "type": "Feature",
  "properties": {
    "gn:admin1_code":"WV",
    "gn:admin2_code":"77",
    "gn:asciiname":"Beech Run",
    "gn:country_code":"US",
    "gn:dem":620,
    "gn:elevation":"623.0",
    "gn:feature_class":"P",
    "gn:feature_code":"PPL",
    "gn:name":"Beech Run",
    "gn:population":0,
    "gn:timezone":"America/New_York",
    "iso:country":"US",
    "wof:name":"Beech Run",
    "wof:placetype":"locality"
},
  "geometry": {"coordinates":[-79.66089000000002,39.53703],"type":"Point"}
}