{
  "type": "Feature",
  "properties": {
    "gn:admin1_code":"AZ",
    "gn:admin2_code":"27.0",
    "gn:asciiname":"Owl",
    "gn:country_code":"US",
    "gn:dem":134,
    "gn:elevation":"135.0",
    "gn:feature_class":"P",
    "gn:feature_code":"PPL",
    "gn:name":"Owl",
    "gn:population":0,
    "gn:timezone":"America/Phoenix",
    "iso:country":"US",
    "name:eng_x_preferred":[
        "Owl"
    ],
    "name:und_x_variant":[
        "Mohawk Inn"
    ],
    "wof:name":"Owl",
    "wof:placetype":"locality"
},
  "geometry": {"coordinates":[-113.79215000000001,32.72199000000001],"type":"Point"}
}