{
  "type": "Feature",
  "properties": {
    "gn:country":"US",
    "gn:fcode":"PPL",
    "gn:population":0,
    "iso:country":"US",
    "name:azb_x_preferred":[
        "\u0642\u0644\u0646"
    ],
    "name:eng_x_preferred":[
        "Glen"
    ],
    "name:fas_x_preferred":[
        "\u06af\u0644\u0646"
    ],
    "name:fra_x_preferred":[
        "Glen"
    ],
    "name:jpn_x_preferred":[
        "\u30b0\u30ec\u30f3"
    ],
    "name:tur_x_preferred":[
        "Glen"
    ],
    "name:und_x_variant":[
        "Glen Station"
    ],
    "name:urd_x_preferred":[
        "\u06af\u0644\u06cc\u0646"
    ],
    "qs_pg:aaroncc":"US",
    "qs_pg:gn_country":"US",
    "qs_pg:gn_fcode":"PPL",
    "qs_pg:gn_pop":0,
    "qs_pg:name":"Glen",
    "qs_pg:name_adm0":"United States",
    "qs_pg:name_adm1":"New Hampshire",
    "qs_pg:photos":403,
    "qs_pg:photos_1k":82,
    "qs_pg:photos_9k":2,
    "qs_pg:photos_9r":5,
    "qs_pg:photos_all":403,
    "qs_pg:photos_sr":6,
    "qs_pg:pop_sr":5,
    "qs_pg:qs_pg_placetype":"locality",
    "qs_pg:qs_pg_placetype_gp":"Town",
    "qs_pg:woe_adm0":23424977,
    "woe:adm0_id":23424977,
    "woe:name_adm0":"United States",
    "woe:name_adm1":"New Hampshire",
    "woe:placetype":"Town",
    "wof:name":"Glen",
    "wof:placetype":"locality"
},
  "geometry": {"coordinates":[-71.18257,44.11007],"type":"Point"}
}