{
  "type": "Feature",
  "properties": {
    "gn:admin1_code":"TX",
    "gn:admin2_code":"215.0",
    "gn:asciiname":"Yokum-Hall Colonia",
    "gn:country_code":"US",
    "gn:dem":31,
    "gn:elevation":"28.0",
    "gn:feature_class":"P",
    "gn:feature_code":"PPL",
    "gn:name":"Yokum-Hall Colonia",
    "gn:population":0,
    "gn:timezone":"America/Chicago",
    "iso:country":"US",
    "name:eng_x_preferred":[
        "Yokum-Hall Colonia"
    ],
    "name:und_x_variant":[
        "Yokum-Hall Subdivision Colonia"
    ],
    "wof:name":"Yokum-Hall Colonia",
    "wof:placetype":"locality"
},
  "geometry": {"coordinates":[-98.12139999999999,26.28535],"type":"Point"}
}