{
  "type": "Feature",
  "properties": {
    "gn:admin1_code":"TN",
    "gn:admin2_code":"31.0",
    "gn:asciiname":"Tara Estates",
    "gn:country_code":"US",
    "gn:dem":327,
    "gn:elevation":"325.0",
    "gn:feature_class":"P",
    "gn:feature_code":"PPL",
    "gn:name":"Tara Estates",
    "gn:population":0,
    "gn:timezone":"America/Chicago",
    "iso:country":"US",
    "wof:name":"Tara Estates",
    "wof:placetype":"locality"
},
  "geometry": {"coordinates":[-86.19915999999998,35.38508],"type":"Point"}
}