{
  "type": "Feature",
  "properties": {
    "gn:admin1_code":"IN",
    "gn:admin2_code":"173.0",
    "gn:admin3_code":"1540.0",
    "gn:asciiname":"Dayville",
    "gn:country_code":"US",
    "gn:dem":119,
    "gn:elevation":"119.0",
    "gn:feature_class":"P",
    "gn:feature_code":"PPL",
    "gn:name":"Dayville",
    "gn:population":0,
    "gn:timezone":"America/Chicago",
    "iso:country":"US",
    "wof:name":"Dayville",
    "wof:placetype":"locality"
},
  "geometry": {"coordinates":[-87.32223,37.95421],"type":"Point"}
}