{
  "type": "Feature",
  "properties": {
    "gn:admin1_code":"MD",
    "gn:admin2_code":"31.0",
    "gn:asciiname":"Charlene",
    "gn:country_code":"US",
    "gn:dem":128,
    "gn:elevation":"126.0",
    "gn:feature_class":"P",
    "gn:feature_code":"PPL",
    "gn:name":"Charlene",
    "gn:population":0,
    "gn:timezone":"America/New_York",
    "iso:country":"US",
    "name:cym_x_preferred":[
        "Charlene"
    ],
    "name:fra_x_preferred":[
        "Charl\u00e8ne"
    ],
    "name:jpn_x_preferred":[
        "\u30b7\u30e3\u30fc\u30ea\u30fc\u30f3"
    ],
    "name:nld_x_preferred":[
        "Charlene"
    ],
    "name:spa_x_preferred":[
        "Charlene"
    ],
    "wof:name":"Charlene",
    "wof:placetype":"locality"
},
  "geometry": {"coordinates":[-77.18748000000002,39.1765],"type":"Point"}
}