{
  "type": "Feature",
  "properties": {
    "gn:admin1_code":"LA",
    "gn:admin2_code":"119.0",
    "gn:asciiname":"Pine Hill Subdivision",
    "gn:country_code":"US",
    "gn:dem":77,
    "gn:elevation":"73.0",
    "gn:feature_class":"P",
    "gn:feature_code":"PPL",
    "gn:name":"Pine Hill Subdivision",
    "gn:population":0,
    "gn:timezone":"America/Chicago",
    "iso:country":"US",
    "wof:name":"Pine Hill Subdivision",
    "wof:placetype":"locality"
},
  "geometry": {"coordinates":[-93.45573,32.97958],"type":"Point"}
}