{
  "type": "Feature",
  "properties": {
    "gn:admin1_code":"LA",
    "gn:admin2_code":"101.0",
    "gn:asciiname":"Mobile Home Park",
    "gn:country_code":"US",
    "gn:dem":3,
    "gn:elevation":"1.0",
    "gn:feature_class":"P",
    "gn:feature_code":"PPL",
    "gn:name":"Mobile Home Park",
    "gn:population":0,
    "gn:timezone":"America/Chicago",
    "iso:country":"US",
    "wof:name":"Mobile Home Park",
    "wof:placetype":"campus"
},
  "geometry": {"coordinates":[-91.17896,29.69225],"type":"Point"}
}