{
  "type": "Feature",
  "properties": {
    "iso:country":"US",
    "name:eng_x_preferred":[
        "Western Star"
    ],
    "wd:wordcount":120,
    "wof:name":"Western Star",
    "wof:placetype":"neighbourhood",
    "wof:population":36,
    "zs:area_m":1053771.457278,
    "zs:blockids":[
        391535320013003,
        391535320013002
    ],
    "zs:housing10":31,
    "zs:label":"Western Star",
    "zs:pop10":36
},
  "geometry": {"coordinates":[-81.68200299999999,41.021626],"type":"Point"}
}