{
  "type": "Feature",
  "properties": {
    "gn:admin1_code":"NY",
    "gn:admin2_code":"119",
    "gn:asciiname":"Knollwood Manor",
    "gn:country_code":"US",
    "gn:dem":151,
    "gn:elevation":"146.0",
    "gn:feature_class":"P",
    "gn:feature_code":"PPL",
    "gn:name":"Knollwood Manor",
    "gn:population":0,
    "gn:timezone":"America/New_York",
    "iso:country":"US",
    "wof:name":"Knollwood Manor",
    "wof:placetype":"locality"
},
  "geometry": {"coordinates":[-73.79694000000001,41.06889],"type":"Point"}
}