{
  "type": "Feature",
  "properties": {
    "gn:admin1_code":"SC",
    "gn:admin2_code":"79.0",
    "gn:asciiname":"State Park",
    "gn:country_code":"US",
    "gn:dem":115,
    "gn:elevation":"109.0",
    "gn:feature_class":"P",
    "gn:feature_code":"PPL",
    "gn:name":"State Park",
    "gn:population":0,
    "gn:timezone":"America/New_York",
    "iso:country":"US",
    "wof:name":"State Park",
    "wof:placetype":"locality"
},
  "geometry": {"coordinates":[-80.9662,34.09070999999999],"type":"Point"}
}