{
  "type": "Feature",
  "properties": {
    "gn:admin1_code":"MI",
    "gn:admin2_code":"21.0",
    "gn:admin3_code":"74440.0",
    "gn:asciiname":"Oxbow",
    "gn:country_code":"US",
    "gn:dem":197,
    "gn:elevation":"195.0",
    "gn:feature_class":"P",
    "gn:feature_code":"PPL",
    "gn:name":"Oxbow",
    "gn:population":0,
    "gn:timezone":"America/Detroit",
    "iso:country":"US",
    "name:sah_x_preferred":[
        "\u0422\u043e\u0495\u043e\u0439"
    ],
    "wof:name":"Oxbow",
    "wof:placetype":"locality"
},
  "geometry": {"coordinates":[-86.38696,42.02171],"type":"Point"}
}