{
  "type": "Feature",
  "properties": {
    "gn:admin1_code":"CA",
    "gn:admin2_code":"5.0",
    "gn:asciiname":"Pine Acres",
    "gn:country_code":"US",
    "gn:dem":832,
    "gn:elevation":"818.0",
    "gn:feature_class":"P",
    "gn:feature_code":"PPL",
    "gn:name":"Pine Acres",
    "gn:population":0,
    "gn:timezone":"America/Los_Angeles",
    "iso:country":"US",
    "name:fas_x_preferred":[
        "\u067e\u0627\u06cc\u0646 \u0627\u06cc\u06a9\u0631\u0632"
    ],
    "name:zho_x_preferred":[
        "\u6d3e\u6069\u963f\u514b\u91cc\u65af"
    ],
    "wof:name":"Pine Acres",
    "wof:placetype":"locality"
},
  "geometry": {"coordinates":[-120.64354,38.39602],"type":"Point"}
}