{
  "type": "Feature",
  "properties": {
    "iso:country":"US",
    "name:eng_x_preferred":[
        "Helen Mills"
    ],
    "wof:name":"Helen Mills",
    "wof:placetype":"neighbourhood",
    "wof:population":796,
    "zs:area_m":50837239.893456,
    "zs:blockids":[
        420479510005083,
        420479510002031,
        420479510005074,
        420479510005047,
        420479510005050,
        420479510005077,
        420479510005069,
        420479510002028,
        420479510005040,
        420479510005026,
        420479510005027,
        420479510005028,
        420479510005045,
        420479510005041,
        420479510005006,
        420479510004059,
        420479510005031,
        420479510005015,
        420479510005011,
        420479510004054,
        420479510004070,
        420479510005075,
        420479510005071,
        420479510005078,
        420479510005033,
        420479510005076,
        420479510005070,
        420479510005007,
        420479510005005,
        420479510005009,
        420479510005034,
        420479510004073,
        420479510005039,
        420479510004067,
        420479510005019,
        420479510005025,
        420479510005018,
        420479510002050,
        420479510004027,
        420479510005010,
        420479510005012,
        420479510002032,
        420479510005024,
        420479510005000,
        420479510005085,
        420479510004025,
        420479510005053,
        420479510005042,
        420479510004071,
        420479510004028,
        420479510004058,
        420479510005030,
        420479510004056,
        420479510004066,
        420479510005029,
        420479510004074,
        420479510005013,
        420479510005054,
        420479510004026,
        420479510005021,
        420479510004057,
        420479510005032,
        420479510005068,
        420479510005038,
        420479510004055,
        420479510005003,
        420479510005002,
        420479510004072,
        420479510005020,
        420479510005052,
        420479510005017,
        420479510005073,
        420479510005043,
        420479510005001,
        420479510005004,
        420479510005044,
        420479510005022,
        420479510005016,
        420479510005008,
        420479510005048,
        420479510005046,
        420479510004029,
        420479510005014,
        420479510004063
    ],
    "zs:housing10":402,
    "zs:label":"Helen Mills",
    "zs:pop10":796
},
  "geometry": {"coordinates":[-78.703115,41.25976],"type":"Point"}
}