{
  "type": "Feature",
  "properties": {
    "gn:admin1_code":"VA",
    "gn:admin2_code":"153",
    "gn:asciiname":"Oak Hill Farms",
    "gn:country_code":"US",
    "gn:dem":115,
    "gn:elevation":"111.0",
    "gn:feature_class":"P",
    "gn:feature_code":"PPL",
    "gn:name":"Oak Hill Farms",
    "gn:population":0,
    "gn:timezone":"America/New_York",
    "iso:country":"US",
    "wof:name":"Oak Hill Farms",
    "wof:placetype":"locality"
},
  "geometry": {"coordinates":[-77.42499000000002,38.66512],"type":"Point"}
}