{
  "type": "Feature",
  "properties": {
    "gn:admin1_code":"NC",
    "gn:admin2_code":"195.0",
    "gn:admin3_code":"91208.0",
    "gn:asciiname":"Wilbanks",
    "gn:country_code":"US",
    "gn:dem":38,
    "gn:elevation":"37.0",
    "gn:feature_class":"P",
    "gn:feature_code":"PPL",
    "gn:name":"Wilbanks",
    "gn:population":0,
    "gn:timezone":"America/New_York",
    "iso:country":"US",
    "wof:name":"Wilbanks",
    "wof:placetype":"locality"
},
  "geometry": {"coordinates":[-77.77136999999998,35.74794],"type":"Point"}
}