{
  "type": "Feature",
  "properties": {
    "gn:admin1_code":"CA",
    "gn:admin2_code":"31",
    "gn:asciiname":"Four Seasons Mobile And Recreational Vehicle Park",
    "gn:country_code":"US",
    "gn:dem":72,
    "gn:elevation":"74.0",
    "gn:feature_class":"P",
    "gn:feature_code":"PPL",
    "gn:name":"Four Seasons Mobile And Recreational Vehicle Park",
    "gn:population":0,
    "gn:timezone":"America/Los_Angeles",
    "iso:country":"US",
    "wof:name":"Four Seasons Mobile And Recreational Vehicle Park",
    "wof:placetype":"locality"
},
  "geometry": {"coordinates":[-119.68778,36.32917],"type":"Point"}
}