{
  "type": "Feature",
  "properties": {
    "gn:admin1_code":"PA",
    "gn:admin2_code":"65.0",
    "gn:admin3_code":"45888.0",
    "gn:asciiname":"Battle Hollow",
    "gn:country_code":"US",
    "gn:dem":488,
    "gn:elevation":"478.0",
    "gn:feature_class":"P",
    "gn:feature_code":"PPL",
    "gn:name":"Battle Hollow",
    "gn:population":0,
    "gn:timezone":"America/New_York",
    "iso:country":"US",
    "wof:name":"Battle Hollow",
    "wof:placetype":"locality"
},
  "geometry": {"coordinates":[-78.9967,41.0059],"type":"Point"}
}