{
  "type": "Feature",
  "properties": {
    "iso:country":"US",
    "name:eng_x_preferred":[
        "Mountain Memories"
    ],
    "wof:name":"Mountain Memories",
    "wof:placetype":"neighbourhood",
    "wof:population":205,
    "zs:area_m":267224761.942859,
    "zs:blockids":[
        80679707011002,
        80679707011019,
        80679707011013,
        80679707011022
    ],
    "zs:housing10":84,
    "zs:label":"Mountain Memories",
    "zs:pop10":205
},
  "geometry": {"coordinates":[-107.981295,37.496133],"type":"Point"}
}