{
  "type": "Feature",
  "properties": {
    "gn:country":"US",
    "gn:fcode":"PPL",
    "gn:population":0,
    "iso:country":"US",
    "name:eng_x_preferred":[
        "Loysburg Gap"
    ],
    "qs_pg:aaroncc":"US",
    "qs_pg:gn_country":"US",
    "qs_pg:gn_fcode":"PPL",
    "qs_pg:gn_pop":0,
    "qs_pg:name":"Loysburg Gap",
    "qs_pg:name_adm0":"United States",
    "qs_pg:name_adm1":"Pennsylvania",
    "qs_pg:photos":3,
    "qs_pg:photos_1k":1,
    "qs_pg:photos_9k":1,
    "qs_pg:photos_9r":1,
    "qs_pg:photos_all":3,
    "qs_pg:photos_sr":1,
    "qs_pg:pop_sr":0,
    "qs_pg:qs_pg_placetype":"neighbourhood",
    "qs_pg:qs_pg_placetype_gp":"Suburb",
    "qs_pg:woe_adm0":23424977,
    "wd:wordcount":86,
    "wof:name":"Loysburg Gap",
    "wof:placetype":"neighbourhood",
    "wof:population":809,
    "zs:area_m":29775354.404432,
    "zs:blockids":[
        420099604003099,
        420099604003019,
        420099604004156,
        420099604003026,
        420099604003098,
        420099604003080,
        420099604003081,
        420099604004179,
        420099604003094,
        420099604004178,
        420099604004161,
        420099604004149,
        420099604003101,
        420099604003077,
        420099604003114,
        420099604003079,
        420099604004160,
        420099604003009,
        420099604003100,
        420099604003016,
        420099604003021,
        420099604003096,
        420099604003075,
        420099604003072,
        420099604003013,
        420099604003141,
        420099604003071,
        420099604003151,
        420099604003024,
        420099604003092,
        420099604003106,
        420099604003000,
        420099604003001,
        420099604003107,
        420099604003105,
        420099604003142,
        420099604003093,
        420099604003082,
        420099604003074,
        420099604003113,
        420099604004177,
        420099604003029,
        420099604003032,
        420099604003110,
        420099604003028,
        420099604003111,
        420099604003088,
        420099604003104,
        420099604003076,
        420099604003143,
        420099604003018,
        420099604003085,
        420099604003015,
        420099604004158,
        420099604003090,
        420099604003073,
        420099604003115,
        420099604003022,
        420099604003017,
        420099604003150,
        420099604003112,
        420099604003140,
        420099604003108,
        420099604003004,
        420099604003102,
        420099604004150,
        420099604003091,
        420099604003089,
        420099604003103,
        420099604003003,
        420099604003097,
        420099604004151,
        420099604004175,
        420099604004176,
        420099604004180,
        420099604003020,
        420099604003144,
        420099604003087,
        420099604003023,
        420099604003006,
        420099604003025,
        420099604003014,
        420099604004159,
        420099604003109
    ],
    "zs:housing10":328,
    "zs:label":"Loysburg Gap",
    "zs:pop10":809
},
  "geometry": {"coordinates":[-78.38232499999999,40.165782],"type":"Point"}
}