{
  "type": "Feature",
  "properties": {
    "gn:admin1_code":"MS",
    "gn:admin2_code":"67",
    "gn:asciiname":"Springhill",
    "gn:country_code":"US",
    "gn:dem":113,
    "gn:elevation":"99.0",
    "gn:feature_class":"P",
    "gn:feature_code":"PPL",
    "gn:name":"Springhill",
    "gn:population":0,
    "gn:timezone":"America/Chicago",
    "iso:country":"US",
    "name:ceb_x_preferred":[
        "Springhill"
    ],
    "name:deu_x_preferred":[
        "Springhill"
    ],
    "name:fra_x_preferred":[
        "Springhill"
    ],
    "name:ita_x_preferred":[
        "Springhill"
    ],
    "name:nld_x_preferred":[
        "Springhill"
    ],
    "name:pol_x_preferred":[
        "Springhill"
    ],
    "name:spa_x_preferred":[
        "Springhill"
    ],
    "name:srp_x_preferred":[
        "\u0421\u043f\u0440\u0438\u043d\u0433\u0445\u0438\u043b"
    ],
    "name:swe_x_preferred":[
        "Springhill"
    ],
    "wof:name":"Springhill",
    "wof:placetype":"locality"
},
  "geometry": {"coordinates":[-89.21423,31.7446],"type":"Point"}
}