{
  "type": "Feature",
  "properties": {
    "iso:country":"US",
    "name:eng_x_preferred":[
        "Washington Junction"
    ],
    "wof:name":"Washington Junction",
    "wof:placetype":"neighbourhood",
    "wof:population":5218,
    "zs:area_m":2519309.973461,
    "zs:blockids":[
        420034734013012,
        420034734011004,
        420034734023001,
        420034761005009,
        420034751011016,
        420034751013004,
        420034762003027,
        420034754011010,
        420034762003026,
        420034751011006,
        420034751012000,
        420034761004011,
        420034751011005,
        420034734011003,
        420034734022003,
        420034761005003,
        420034751011007,
        420034761005000,
        420034751012009,
        420034751012004,
        420034751012007,
        420034751011002,
        420034734023015,
        420034751012022,
        420034734022007,
        420034734022005,
        420034751012016,
        420034751011009,
        420034751012011,
        420034734022002,
        420034734014011,
        420034751011001,
        420034751011003,
        420034761005007,
        420034761005012,
        420034754011011,
        420034751012006,
        420034762003024,
        420034734022004,
        420034751011018,
        420034734022001,
        420034761005002,
        420034751011015,
        420034761005006,
        420034762003029,
        420034761005010,
        420034751011004,
        420034751012008,
        420034751012017,
        420034751012001,
        420034734023025,
        420034734011010,
        420034751011008,
        420034751011000,
        420034754011004,
        420034751012010,
        420034751012002,
        420034761004010,
        420034761005008,
        420034734011006,
        420034761005001,
        420034761005011,
        420034751012012,
        420034754011009,
        420034734014010,
        420034734022000,
        420034762003025,
        420034734023000,
        420034734022006,
        420034761005005,
        420034761004012,
        420034762003017,
        420034751011017,
        420034751012003,
        420034751012005,
        420034734022008
    ],
    "zs:housing10":2344,
    "zs:label":"Washington Junction",
    "zs:pop10":5218
},
  "geometry": {"coordinates":[-80.030018,40.355899],"type":"Point"}
}