{
  "type": "Feature",
  "properties": {
    "gn:admin1_code":"TX",
    "gn:admin2_code":"201.0",
    "gn:asciiname":"Shannon Forest",
    "gn:country_code":"US",
    "gn:dem":45,
    "gn:elevation":"42.0",
    "gn:feature_class":"P",
    "gn:feature_code":"PPL",
    "gn:name":"Shannon Forest",
    "gn:population":0,
    "gn:timezone":"America/Chicago",
    "iso:country":"US",
    "wof:name":"Shannon Forest",
    "wof:placetype":"locality"
},
  "geometry": {"coordinates":[-95.5427,30.037],"type":"Point"}
}