{
  "type": "Feature",
  "properties": {
    "gn:country":"US",
    "gn:fcode":"PPL",
    "gn:population":0,
    "iso:country":"US",
    "name:ben_x_preferred":[
        "\u09b2\u09c7\u0995\u09ad\u09bf\u09b2\u09c7"
    ],
    "name:ell_x_preferred":[
        "\u039b\u03ad\u03b9\u03ba\u03b2\u03b9\u03bb"
    ],
    "name:eng_x_preferred":[
        "Lakeville"
    ],
    "name:fra_x_preferred":[
        "Lakeville"
    ],
    "name:hin_x_preferred":[
        "\u0932\u0947\u0915\u0935\u093f\u0932"
    ],
    "name:hun_x_preferred":[
        "Lakeville"
    ],
    "name:ind_x_preferred":[
        "Lakeville"
    ],
    "name:kor_x_preferred":[
        "\ub808\uc774\ud06c\ube4c"
    ],
    "name:und_x_variant":[
        "Lakeville Station"
    ],
    "name:vol_x_preferred":[
        "Lakeville"
    ],
    "qs_pg:aaroncc":"US",
    "qs_pg:gn_country":"US",
    "qs_pg:gn_fcode":"PPL",
    "qs_pg:gn_pop":0,
    "qs_pg:name":"Lakeville",
    "qs_pg:name_adm0":"United States",
    "qs_pg:name_adm1":"Ohio",
    "qs_pg:photos_9k":1,
    "qs_pg:photos_9r":1,
    "qs_pg:photos_all":3,
    "qs_pg:photos_sr":0,
    "qs_pg:pop_sr":0,
    "qs_pg:qs_pg_placetype":"locality",
    "qs_pg:qs_pg_placetype_gp":"Town",
    "qs_pg:woe_adm0":23424977,
    "woe:adm0_id":23424977,
    "woe:name_adm0":"United States",
    "woe:name_adm1":"Ohio",
    "woe:placetype":"Town",
    "wof:name":"Lakeville",
    "wof:placetype":"locality"
},
  "geometry": {"coordinates":[-82.1271,40.65617],"type":"Point"}
}