{
  "type": "Feature",
  "properties": {
    "gn:admin1_code":"TX",
    "gn:admin2_code":"455.0",
    "gn:asciiname":"Nigton",
    "gn:country_code":"US",
    "gn:dem":78,
    "gn:elevation":"73.0",
    "gn:feature_class":"P",
    "gn:feature_code":"PPL",
    "gn:name":"Nigton",
    "gn:population":0,
    "gn:timezone":"America/Chicago",
    "iso:country":"US",
    "wof:name":"Nigton",
    "wof:placetype":"locality"
},
  "geometry": {"coordinates":[-94.90770999999999,31.22157],"type":"Point"}
}