{
  "type": "Feature",
  "properties": {
    "gn:admin1_code":"KY",
    "gn:admin2_code":"65.0",
    "gn:asciiname":"Bogie",
    "gn:country_code":"US",
    "gn:dem":245,
    "gn:elevation":"245.0",
    "gn:feature_class":"P",
    "gn:feature_code":"PPL",
    "gn:name":"Bogie",
    "gn:population":0,
    "gn:timezone":"America/New_York",
    "iso:country":"US",
    "wof:name":"Bogie",
    "wof:placetype":"locality"
},
  "geometry": {"coordinates":[-84.05119999999999,37.77903],"type":"Point"}
}