{
  "type": "Feature",
  "properties": {
    "gn:elevation":13,
    "iso:country":"US",
    "name:afr_x_preferred":[
        "Sunset Acres"
    ],
    "name:eng_x_preferred":[
        "Sunset Acres"
    ],
    "qs:gn_adm0_cc":"US",
    "qs:gn_fcode":"PPLX",
    "qs:gn_local":4473083,
    "qs:gn_nam_loc":"Jacksonville, Onslow, North Carolina, US",
    "qs:gn_namadm1":"NC",
    "qs:gn_name":"Sunset Acres",
    "qs:local_max":168,
    "qs:local_sum":517,
    "qs:localhoods":8,
    "qs:name":"Sunset Acres",
    "qs:name_adm0":"United States",
    "qs:name_adm1":"North Carolina",
    "qs:name_adm2":"Onslow",
    "qs:name_local":"Jacksonville",
    "qs:photo_max":10,
    "qs:photo_sum":30,
    "qs:placetype":"Suburb",
    "qs:quad_count":7,
    "qs:woe_adm0":23424977,
    "qs:woe_adm1":2347592,
    "qs:woe_adm2":12589440,
    "qs:woe_lau":0,
    "qs:woe_local":2428347,
    "qs:woe_ver":"7.10.0",
    "wof:lang":[
        "eng"
    ],
    "wof:name":"Sunset Acres",
    "wof:placetype":"neighbourhood",
    "wof:population":4560,
    "zs:blockids":[
        371330013002030,
        371330013002038,
        371330013002046,
        371330013002041,
        371330013002047,
        371330013002048,
        371330013002031,
        371330013002033,
        371330013002045,
        371330021001006,
        371330013002036,
        371330021002018,
        371330013002051,
        371330013002049,
        371330013002035,
        371330013002034,
        371330013002050,
        371330013002043,
        371330013002044,
        371330021001016,
        371330013002037,
        371330013002042
    ],
    "zs:housing10":1796,
    "zs:pop10":4560
},
  "geometry": {"coordinates":[-77.393372,34.782679],"type":"Point"}
}