{
  "type": "Feature",
  "properties": {
    "gn:admin1_code":"OH",
    "gn:admin2_code":"109.0",
    "gn:admin3_code":"18224.0",
    "gn:asciiname":"Meadowlawn",
    "gn:country_code":"US",
    "gn:dem":252,
    "gn:elevation":"252.0",
    "gn:feature_class":"P",
    "gn:feature_code":"PPL",
    "gn:name":"Meadowlawn",
    "gn:population":0,
    "gn:timezone":"America/New_York",
    "iso:country":"US",
    "wof:name":"Meadowlawn",
    "wof:placetype":"locality"
},
  "geometry": {"coordinates":[-84.1885,40.04718],"type":"Point"}
}