{
  "type": "Feature",
  "properties": {
    "gn:admin1_code":"WA",
    "gn:admin2_code":"33.0",
    "gn:asciiname":"Riverside Mobile Estates",
    "gn:country_code":"US",
    "gn:dem":7,
    "gn:elevation":"7.0",
    "gn:feature_class":"P",
    "gn:feature_code":"PPL",
    "gn:name":"Riverside Mobile Estates",
    "gn:population":0,
    "gn:timezone":"America/Los_Angeles",
    "iso:country":"US",
    "wof:name":"Riverside Mobile Estates",
    "wof:placetype":"locality"
},
  "geometry": {"coordinates":[-122.18814,47.75511],"type":"Point"}
}