{
  "type": "Feature",
  "properties": {
    "iso:country":"US",
    "name:eng_x_preferred":[
        "Back Cove"
    ],
    "name:eng_x_variant":[
        "Back Cv"
    ],
    "qs:gn_adm0_cc":"US",
    "qs:gn_local":4975603,
    "qs:gn_nam_loc":"weeks mills",
    "qs:gn_namadm1":"ME",
    "qs:local_max":12027,
    "qs:local_sum":30761,
    "qs:localhoods":27,
    "qs:name":"Back Cove",
    "qs:name_adm0":"United States",
    "qs:name_adm1":"Maine",
    "qs:name_adm2":"Cumberland",
    "qs:name_local":"Portland",
    "qs:photo_max":429,
    "qs:photo_sum":694,
    "qs:placetype":"Suburb",
    "qs:quad_count":8,
    "qs:woe_adm0":23424977,
    "qs:woe_adm1":2347578,
    "qs:woe_adm2":12588662,
    "qs:woe_funk":"Grouping neighborhood",
    "qs:woe_lau":0,
    "qs:woe_local":2475688,
    "qs:woe_ver":"7.10.0",
    "wd:wordcount":77,
    "wof:lang":[
        "eng"
    ],
    "wof:name":"Back Cove",
    "wof:placetype":"neighbourhood",
    "wof:population":1862,
    "zs:blockids":[
        230050018001025,
        230050018001016,
        230050018002004,
        230050018001022,
        230050018002000,
        230050018001002,
        230050018001020,
        230050018002018,
        230050023001047,
        230050018001021,
        230050018001019,
        230050018002001,
        230050018002023,
        230050023001041,
        230050018001001,
        230050018001024,
        230050022001012,
        230050018001023,
        230050018001006,
        230050018002002,
        230050018002003,
        230050018002014,
        230050022001014,
        230050023001042,
        230050018001004,
        230050018001003,
        230050018001018,
        230050018002019,
        230050018001000,
        230050018001005,
        230050022002012,
        230050023001049,
        230050018001017
    ],
    "zs:housing10":971,
    "zs:pop10":1862
},
  "geometry": {"coordinates":[-70.278952,43.67926],"type":"Point"}
}