{
  "type": "Feature",
  "properties": {
    "gn:country":"US",
    "gn:fcode":"ADMD",
    "gn:population":0,
    "iso:country":"US",
    "name:cym_x_preferred":[
        "Lower Nazareth Township"
    ],
    "name:deu_x_preferred":[
        "Lower Nazareth Township"
    ],
    "name:eng_x_preferred":[
        "Lower Nazareth Township"
    ],
    "name:spa_x_preferred":[
        "Municipio de Lower Nazareth"
    ],
    "name:ukr_x_preferred":[
        "\u041b\u043e\u0432\u0435\u0440-\u041d\u0430\u0437\u0430\u0440\u0435\u0442 \u0422\u0430\u0443\u043d\u0448\u0438\u043f"
    ],
    "name:vie_x_preferred":[
        "Lower Nazareth"
    ],
    "name:vie_x_variant":[
        "X\u00e3 Lower Nazareth"
    ],
    "qs_pg:aaroncc":"US",
    "qs_pg:gn_country":"US",
    "qs_pg:gn_fcode":"ADMD",
    "qs_pg:gn_pop":0,
    "qs_pg:name":"Lower Nazareth",
    "qs_pg:name_adm0":"United States",
    "qs_pg:name_adm1":"Pennsylvania",
    "qs_pg:photos":23,
    "qs_pg:photos_1k":5,
    "qs_pg:photos_9k":1,
    "qs_pg:photos_9r":3,
    "qs_pg:photos_all":91,
    "qs_pg:photos_sr":1,
    "qs_pg:pop_sr":0,
    "qs_pg:qs_pg_placetype":"locality",
    "qs_pg:qs_pg_placetype_gp":"Town",
    "qs_pg:woe_adm0":23424977,
    "woe:adm0_id":23424977,
    "woe:name_adm0":"United States",
    "woe:name_adm1":"Pennsylvania",
    "woe:placetype":"Town",
    "wof:name":"Lower Nazareth",
    "wof:placetype":"locality"
},
  "geometry": {"coordinates":[-75.37657,40.70843],"type":"Point"}
}