{
  "type": "Feature",
  "properties": {
    "iso:country":"US",
    "name:eng_x_preferred":[
        "Crilly Acres"
    ],
    "wof:name":"Crilly Acres",
    "wof:placetype":"neighbourhood",
    "wof:population":2,
    "zs:area_m":19898.96673,
    "zs:blockids":[
        120570110052020
    ],
    "zs:housing10":5,
    "zs:label":"Crilly Acres",
    "zs:pop10":2
},
  "geometry": {"coordinates":[-82.462228,28.146271],"type":"Point"}
}