{
  "type": "Feature",
  "properties": {
    "gn:country":"US",
    "gn:fcode":"PPL",
    "gn:population":0,
    "iso:country":"US",
    "name:cat_x_preferred":[
        "Five Points"
    ],
    "name:ceb_x_preferred":[
        "Five Points"
    ],
    "name:deu_x_preferred":[
        "Five Points"
    ],
    "name:fra_x_preferred":[
        "Five Points"
    ],
    "name:ita_x_preferred":[
        "Five Points"
    ],
    "name:kor_x_preferred":[
        "\ud30c\uc774\ube0c\ud3ec\uc778\uce20"
    ],
    "name:nld_x_preferred":[
        "Five Points"
    ],
    "name:pol_x_preferred":[
        "Five Points"
    ],
    "name:por_x_preferred":[
        "Five Points"
    ],
    "name:spa_x_preferred":[
        "Five Points"
    ],
    "name:srp_x_preferred":[
        "\u0424\u0430\u0458\u0432 \u041f\u043e\u0458\u043d\u0442\u0441"
    ],
    "name:ukr_x_preferred":[
        "\u0424\u0430\u0439\u0432-\u041f\u043e\u0439\u043d\u0442\u0441"
    ],
    "name:vol_x_preferred":[
        "Five Points"
    ],
    "qs_pg:aaroncc":"US",
    "qs_pg:gn_country":"US",
    "qs_pg:gn_fcode":"PPL",
    "qs_pg:gn_pop":0,
    "qs_pg:name":"Five Points",
    "qs_pg:name_adm0":"United States",
    "qs_pg:name_adm1":"New Mexico",
    "qs_pg:photos":23,
    "qs_pg:photos_1k":5,
    "qs_pg:photos_9k":1,
    "qs_pg:photos_9r":1,
    "qs_pg:photos_all":23,
    "qs_pg:photos_sr":1,
    "qs_pg:pop_sr":0,
    "qs_pg:qs_pg_placetype":"locality",
    "qs_pg:qs_pg_placetype_gp":"Town",
    "qs_pg:woe_adm0":23424977,
    "woe:adm0_id":23424977,
    "woe:name_adm0":"United States",
    "woe:name_adm1":"New Mexico",
    "woe:placetype":"Town",
    "wof:name":"Five Points",
    "wof:placetype":"locality"
},
  "geometry": {"coordinates":[-106.66669,35.06616],"type":"Point"}
}