{
  "type": "Feature",
  "properties": {
    "iso:country":"US",
    "name:eng_x_preferred":[
        "Evelyn City"
    ],
    "wof:name":"Evelyn City",
    "wof:placetype":"neighbourhood",
    "wof:population":78,
    "zs:area_m":55274.10001,
    "zs:blockids":[
        120570011001013,
        120570011001014,
        120570011001012,
        120570011001011
    ],
    "zs:housing10":50,
    "zs:label":"Evelyn City",
    "zs:pop10":78
},
  "geometry": {"coordinates":[-82.45016800000001,28.014376],"type":"Point"}
}