{
  "type": "Feature",
  "properties": {
    "iso:country":"US",
    "name:eng_x_preferred":[
        "Baja Oso"
    ],
    "wof:name":"Baja Oso",
    "wof:placetype":"neighbourhood",
    "wof:population":796,
    "zs:area_m":350252.042187,
    "zs:blockids":[
        60590320133017,
        60590320133022,
        60590320133019,
        60590320133010,
        60590320133018,
        60590320133016
    ],
    "zs:housing10":297,
    "zs:label":"Baja Oso",
    "zs:pop10":796
},
  "geometry": {"coordinates":[-117.65966299999999,33.575983],"type":"Point"}
}