{
  "type": "Feature",
  "properties": {
    "gn:admin1_code":"MI",
    "gn:admin2_code":"121",
    "gn:admin3_code":"14100.0",
    "gn:asciiname":"Timberline Estates Mobile Home Park",
    "gn:country_code":"US",
    "gn:dem":203,
    "gn:elevation":"201.0",
    "gn:feature_class":"P",
    "gn:feature_code":"PPL",
    "gn:name":"Timberline Estates Mobile Home Park",
    "gn:population":0,
    "gn:timezone":"America/Detroit",
    "iso:country":"US",
    "wof:name":"Timberline Estates Mobile Home Park",
    "wof:placetype":"campus"
},
  "geometry": {"coordinates":[-86.15333000000003,43.29667],"type":"Point"}
}