{
  "type": "Feature",
  "properties": {
    "iso:country":"US",
    "name:eng_x_preferred":[
        "Sturbridge"
    ],
    "qs:gn_adm0_cc":"US",
    "qs:gn_local":4076784,
    "qs:local_max":2993,
    "qs:local_sum":14433,
    "qs:localhoods":45,
    "qs:name":"Sturbridge",
    "qs:name_adm0":"United States",
    "qs:name_adm1":"Alabama",
    "qs:name_adm2":"Montgomery",
    "qs:name_local":"Montgomery",
    "qs:photo_max":45,
    "qs:photo_sum":163,
    "qs:placetype":"Suburb",
    "qs:quad_count":19,
    "qs:woe_adm0":23424977,
    "qs:woe_adm1":2347559,
    "qs:woe_adm2":12587537,
    "qs:woe_lau":0,
    "qs:woe_local":2453369,
    "qs:woe_ver":"7.10.0",
    "wof:lang":[
        "eng"
    ],
    "wof:name":"Sturbridge",
    "wof:placetype":"neighbourhood",
    "wof:population":7664,
    "zs:blockids":[
        11010056091011,
        11010054064037,
        11010054064040,
        11010054062013,
        11010054062019,
        11010056091012,
        11010056091008,
        11010056091005,
        11010054064041,
        11010056111000,
        11010054062012,
        11010054062009,
        11010054062010,
        11010054062017,
        11010056091017,
        11010056091016,
        11010056091010,
        11010054062018,
        11010054064042,
        11010056111014,
        11010054064047,
        11010054062003,
        11010054064036,
        11010054062006,
        11010056091009,
        11010054064046,
        11010056111007,
        11010054064032,
        11010054062007,
        11010056091000,
        11010056111016,
        11010054062008,
        11010054064027,
        11010056091002,
        11010054063029,
        11010056091001,
        11010054064035,
        11010054064039,
        11010054064033,
        11010056091029,
        11010054063031,
        11010056091003,
        11010054062016,
        11010054063027,
        11010054063030,
        11010056091004,
        11010054063025,
        11010054063028,
        11010056091006,
        11010054062011,
        11010054063026,
        11010054064045,
        11010054064038,
        11010054062014,
        11010056091007,
        11010054064048
    ],
    "zs:housing10":3739,
    "zs:pop10":7664
},
  "geometry": {"coordinates":[-86.180728,32.340717],"type":"Point"}
}