{
  "type": "Feature",
  "properties": {
    "gn:country":"US",
    "gn:fcode":"PPL",
    "gn:population":0,
    "iso:country":"US",
    "name:ceb_x_preferred":[
        "Fisk"
    ],
    "name:dan_x_preferred":[
        "Fisk"
    ],
    "name:deu_x_preferred":[
        "Fisk"
    ],
    "name:eng_x_preferred":[
        "Fisk"
    ],
    "name:fin_x_preferred":[
        "Fisk"
    ],
    "name:fra_x_preferred":[
        "Fisk"
    ],
    "name:ita_x_preferred":[
        "Fisk"
    ],
    "name:jpn_x_preferred":[
        "\u30d5\u30a3\u30b9\u30af"
    ],
    "name:nld_x_preferred":[
        "Fisk"
    ],
    "name:por_x_preferred":[
        "Fisk"
    ],
    "name:rus_x_preferred":[
        "\u0424\u0438\u0441\u043a"
    ],
    "name:swe_x_preferred":[
        "Fisk"
    ],
    "name:und_x_variant":[
        "Fisk Corners"
    ],
    "qs_pg:aaroncc":"US",
    "qs_pg:gn_country":"US",
    "qs_pg:gn_fcode":"PPL",
    "qs_pg:gn_pop":0,
    "qs_pg:name":"Fisk",
    "qs_pg:name_adm0":"United States",
    "qs_pg:name_adm1":"Wisconsin",
    "qs_pg:photos":1,
    "qs_pg:photos_1k":1,
    "qs_pg:photos_9k":1,
    "qs_pg:photos_9r":1,
    "qs_pg:photos_all":1,
    "qs_pg:photos_sr":1,
    "qs_pg:pop_sr":0,
    "qs_pg:qs_pg_placetype":"neighbourhood",
    "qs_pg:qs_pg_placetype_gp":"Suburb",
    "qs_pg:woe_adm0":23424977,
    "woe:adm0_id":23424977,
    "woe:name_adm0":"United States",
    "woe:name_adm1":"Wisconsin",
    "woe:placetype":"Suburb",
    "wof:name":"Fisk",
    "wof:placetype":"neighbourhood"
},
  "geometry": {"coordinates":[-88.67816999999999,43.95582],"type":"Point"}
}