{
  "type": "Feature",
  "properties": {
    "gn:admin1_code":"MD",
    "gn:admin2_code":"35.0",
    "gn:asciiname":"Overlook",
    "gn:country_code":"US",
    "gn:dem":20,
    "gn:elevation":"21.0",
    "gn:feature_class":"P",
    "gn:feature_code":"PPL",
    "gn:name":"Overlook",
    "gn:population":0,
    "gn:timezone":"America/New_York",
    "iso:country":"US",
    "wof:name":"Overlook",
    "wof:placetype":"locality"
},
  "geometry": {"coordinates":[-76.13021999999999,38.94345],"type":"Point"}
}