{
  "type": "Feature",
  "properties": {
    "gn:admin1_code":"AR",
    "gn:admin2_code":"7.0",
    "gn:admin3_code":"93647.0",
    "gn:asciiname":"Gallatin",
    "gn:country_code":"US",
    "gn:dem":339,
    "gn:elevation":"333.0",
    "gn:feature_class":"P",
    "gn:feature_code":"PPL",
    "gn:name":"Gallatin",
    "gn:population":0,
    "gn:timezone":"America/Chicago",
    "iso:country":"US",
    "name:ceb_x_preferred":[
        "Gallatin"
    ],
    "name:deu_x_preferred":[
        "Gallatin"
    ],
    "name:eng_x_preferred":[
        "Gallatin"
    ],
    "name:fra_x_preferred":[
        "Gallatin"
    ],
    "name:ita_x_preferred":[
        "Gallatin"
    ],
    "name:jpn_x_preferred":[
        "\u30ae\u30e3\u30e9\u30c6\u30a3\u30f3"
    ],
    "name:kor_x_preferred":[
        "\uac24\ub7ec\ud2f4"
    ],
    "name:nld_x_preferred":[
        "Gallatin"
    ],
    "name:pol_x_preferred":[
        "Gallatin"
    ],
    "name:por_x_preferred":[
        "Gallatin"
    ],
    "name:rus_x_preferred":[
        "\u0413\u0430\u043b\u043b\u0430\u0442\u0438\u043d"
    ],
    "name:spa_x_preferred":[
        "Gallatin"
    ],
    "name:srp_x_preferred":[
        "\u0413\u0430\u043b\u0430\u0442\u0438\u043d"
    ],
    "name:swe_x_preferred":[
        "Gallatin"
    ],
    "name:ukr_x_preferred":[
        "\u0413\u0430\u043b\u043b\u0430\u0442\u0456\u043d"
    ],
    "name:und_x_variant":[
        "Gallitin"
    ],
    "name:vol_x_preferred":[
        "Gallatin"
    ],
    "wof:name":"Gallatin",
    "wof:placetype":"locality"
},
  "geometry": {"coordinates":[-94.42716,36.20619],"type":"Point"}
}