{
  "type": "Feature",
  "properties": {
    "gn:admin1_code":"WV",
    "gn:admin2_code":"25",
    "gn:asciiname":"Marfrance",
    "gn:country_code":"US",
    "gn:dem":942,
    "gn:elevation":"940.0",
    "gn:feature_class":"P",
    "gn:feature_code":"PPL",
    "gn:name":"Marfrance",
    "gn:population":0,
    "gn:timezone":"America/New_York",
    "iso:country":"US",
    "name:eng_x_preferred":[
        "Marfrance"
    ],
    "name:und_x_variant":[
        "Margaret"
    ],
    "wof:name":"Marfrance",
    "wof:placetype":"locality"
},
  "geometry": {"coordinates":[-80.69119999999999,38.05567],"type":"Point"}
}