{
  "type": "Feature",
  "properties": {
    "gn:admin1_code":"MO",
    "gn:admin2_code":"221.0",
    "gn:admin3_code":"4078.0",
    "gn:asciiname":"Peoria",
    "gn:country_code":"US",
    "gn:dem":290,
    "gn:elevation":"284.0",
    "gn:feature_class":"P",
    "gn:feature_code":"PPL",
    "gn:name":"Peoria",
    "gn:population":0,
    "gn:timezone":"America/Chicago",
    "iso:country":"US",
    "name:bel_x_preferred":[
        "\u041f\u0435\u043e\u0440\u044b\u044f"
    ],
    "name:bre_x_preferred":[
        "Peoria"
    ],
    "name:bul_x_preferred":[
        "\u041f\u0435\u043e\u0440\u0438\u044f"
    ],
    "name:cat_x_preferred":[
        "Peoria"
    ],
    "name:ceb_x_preferred":[
        "Peoria"
    ],
    "name:dan_x_preferred":[
        "Peoria"
    ],
    "name:deu_x_preferred":[
        "Peoria"
    ],
    "name:fin_x_preferred":[
        "Peoria"
    ],
    "name:fra_x_preferred":[
        "Peoria"
    ],
    "name:hun_x_preferred":[
        "Peoria"
    ],
    "name:ita_x_preferred":[
        "Peoria"
    ],
    "name:jpn_x_preferred":[
        "\u30d4\u30aa\u30ea\u30a2"
    ],
    "name:kor_x_preferred":[
        "\ud53c\uc624\ub9ac\uc544"
    ],
    "name:nld_x_preferred":[
        "Peoria"
    ],
    "name:pol_x_preferred":[
        "Peoria"
    ],
    "name:por_x_preferred":[
        "Peoria"
    ],
    "name:ron_x_preferred":[
        "Peoria"
    ],
    "name:rus_x_preferred":[
        "\u041f\u0435\u043e\u0440\u0438\u044f"
    ],
    "name:spa_x_preferred":[
        "Peoria"
    ],
    "name:srp_x_preferred":[
        "\u041f\u0438\u043e\u0440\u0438\u0458\u0430"
    ],
    "name:swa_x_preferred":[
        "Peoria"
    ],
    "name:swe_x_preferred":[
        "Peoria"
    ],
    "name:ukr_x_preferred":[
        "\u041f\u0456\u043e\u0440\u0456\u044f"
    ],
    "name:vol_x_preferred":[
        "Peoria"
    ],
    "wof:name":"Peoria",
    "wof:placetype":"locality"
},
  "geometry": {"coordinates":[-90.8843,37.75616],"type":"Point"}
}