{
  "type": "Feature",
  "properties": {
    "gn:admin1_code":"PA",
    "gn:admin2_code":"19.0",
    "gn:admin3_code":"85784.0",
    "gn:asciiname":"Leasureville",
    "gn:country_code":"US",
    "gn:dem":337,
    "gn:elevation":"335.0",
    "gn:feature_class":"P",
    "gn:feature_code":"PPL",
    "gn:name":"Leasureville",
    "gn:population":0,
    "gn:timezone":"America/New_York",
    "iso:country":"US",
    "name:eng_x_preferred":[
        "Leasureville"
    ],
    "name:und_x_variant":[
        "Leasuresville"
    ],
    "wof:name":"Leasureville",
    "wof:placetype":"locality"
},
  "geometry": {"coordinates":[-79.70366,40.74701],"type":"Point"}
}