{
  "type": "Feature",
  "properties": {
    "gn:admin1_code":"AR",
    "gn:admin2_code":"63.0",
    "gn:admin3_code":"91794.0",
    "gn:asciiname":"Huff",
    "gn:country_code":"US",
    "gn:dem":104,
    "gn:elevation":"103.0",
    "gn:feature_class":"P",
    "gn:feature_code":"PPL",
    "gn:name":"Huff",
    "gn:population":0,
    "gn:timezone":"America/Chicago",
    "iso:country":"US",
    "name:deu_x_preferred":[
        "Huff"
    ],
    "name:eng_x_preferred":[
        "Huff"
    ],
    "name:fin_x_preferred":[
        "Huff"
    ],
    "name:fra_x_preferred":[
        "Huff"
    ],
    "name:pol_x_preferred":[
        "Huff"
    ],
    "name:rus_x_preferred":[
        "\u0425\u0430\u0444\u0444"
    ],
    "name:und_x_variant":[
        "Cave Springs"
    ],
    "wof:name":"Huff",
    "wof:placetype":"locality"
},
  "geometry": {"coordinates":[-91.60597,35.62369],"type":"Point"}
}