{
  "type": "Feature",
  "properties": {
    "gn:admin1_code":"TX",
    "gn:admin2_code":"465.0",
    "gn:asciiname":"Juno",
    "gn:country_code":"US",
    "gn:dem":520,
    "gn:elevation":"520.0",
    "gn:feature_class":"P",
    "gn:feature_code":"PPL",
    "gn:name":"Juno",
    "gn:population":0,
    "gn:timezone":"America/Chicago",
    "iso:country":"US",
    "wof:name":"Juno",
    "wof:placetype":"locality"
},
  "geometry": {"coordinates":[-101.11538,30.15186],"type":"Point"}
}