{
  "type": "Feature",
  "properties": {
    "gn:admin1_code":"CO",
    "gn:admin2_code":"119.0",
    "gn:asciiname":"Elkton",
    "gn:country_code":"US",
    "gn:dem":2994,
    "gn:elevation":"2978.0",
    "gn:feature_class":"P",
    "gn:feature_code":"PPL",
    "gn:name":"Elkton",
    "gn:population":0,
    "gn:timezone":"America/Denver",
    "iso:country":"US",
    "name:ceb_x_preferred":[
        "Elkton"
    ],
    "name:deu_x_preferred":[
        "Elkton"
    ],
    "name:fas_x_preferred":[
        "\u0627\u0644\u06a9\u062a\u0648\u0646"
    ],
    "name:fra_x_preferred":[
        "Elkton"
    ],
    "name:hun_x_preferred":[
        "Elkton"
    ],
    "name:ido_x_preferred":[
        "Elkton"
    ],
    "name:ita_x_preferred":[
        "Elkton"
    ],
    "name:nld_x_preferred":[
        "Elkton"
    ],
    "name:pol_x_preferred":[
        "Elkton"
    ],
    "name:por_x_preferred":[
        "Elkton"
    ],
    "name:rus_x_preferred":[
        "\u042d\u043b\u043a\u0442\u043e\u043d"
    ],
    "name:spa_x_preferred":[
        "Elkton"
    ],
    "name:srp_x_preferred":[
        "\u0415\u043b\u043a\u0442\u043e\u043d"
    ],
    "name:swe_x_preferred":[
        "Elkton"
    ],
    "name:vol_x_preferred":[
        "Elkton"
    ],
    "wof:name":"Elkton",
    "wof:placetype":"locality"
},
  "geometry": {"coordinates":[-105.15054000000001,38.72221],"type":"Point"}
}