{
  "type": "Feature",
  "properties": {
    "gn:admin1_code":"AR",
    "gn:admin2_code":"63.0",
    "gn:admin3_code":"92739.0",
    "gn:asciiname":"Dunnington",
    "gn:country_code":"US",
    "gn:dem":71,
    "gn:elevation":"69.0",
    "gn:feature_class":"P",
    "gn:feature_code":"PPL",
    "gn:name":"Dunnington",
    "gn:population":0,
    "gn:timezone":"America/Chicago",
    "iso:country":"US",
    "name:ang_x_preferred":[
        "Dunnan t\u016bn"
    ],
    "name:ceb_x_preferred":[
        "Dunnington"
    ],
    "name:fas_x_preferred":[
        "\u062f\u0627\u0646\u06cc\u0646\u06af\u062a\u0648\u0646"
    ],
    "name:fra_x_preferred":[
        "Dunnington"
    ],
    "name:gle_x_preferred":[
        "Dunnington"
    ],
    "name:ita_x_preferred":[
        "Dunnington"
    ],
    "name:nld_x_preferred":[
        "Dunnington"
    ],
    "name:pol_x_preferred":[
        "Dunnington"
    ],
    "name:swe_x_preferred":[
        "Dunnington"
    ],
    "wof:name":"Dunnington",
    "wof:placetype":"locality"
},
  "geometry": {"coordinates":[-91.42874,35.62536],"type":"Point"}
}