{
  "type": "Feature",
  "properties": {
    "gn:admin1_code":"VA",
    "gn:admin2_code":"3",
    "gn:asciiname":"Hessian Hills",
    "gn:country_code":"US",
    "gn:dem":181,
    "gn:elevation":"177.0",
    "gn:feature_class":"P",
    "gn:feature_code":"PPL",
    "gn:name":"Hessian Hills",
    "gn:population":0,
    "gn:timezone":"America/New_York",
    "iso:country":"US",
    "wof:name":"Hessian Hills",
    "wof:placetype":"locality"
},
  "geometry": {"coordinates":[-78.50251,38.06347],"type":"Point"}
}