{
  "type": "Feature",
  "properties": {
    "iso:country":"US",
    "name:ara_x_preferred":[
        "\u063a\u0631\u0627\u0641\u062a\u0648\u0646"
    ],
    "name:cat_x_preferred":[
        "Grafton"
    ],
    "name:ceb_x_preferred":[
        "Grafton"
    ],
    "name:cym_x_preferred":[
        "Grafton"
    ],
    "name:deu_x_preferred":[
        "Grafton"
    ],
    "name:fin_x_preferred":[
        "Grafton"
    ],
    "name:fra_x_preferred":[
        "Grafton"
    ],
    "name:heb_x_preferred":[
        "\u05d2\u05e8\u05e4\u05d8\u05d5\u05df"
    ],
    "name:ita_x_preferred":[
        "Grafton"
    ],
    "name:jpn_x_preferred":[
        "\u30b0\u30e9\u30d5\u30c8\u30f3"
    ],
    "name:kor_x_preferred":[
        "\uadf8\ub798\ud504\ud134"
    ],
    "name:mlg_x_preferred":[
        "Grafton"
    ],
    "name:nld_x_preferred":[
        "Grafton"
    ],
    "name:pol_x_preferred":[
        "Grafton"
    ],
    "name:por_x_preferred":[
        "Grafton"
    ],
    "name:rus_x_preferred":[
        "\u0413\u0440\u0430\u0444\u0442\u043e\u043d"
    ],
    "name:slv_x_preferred":[
        "Grafton"
    ],
    "name:spa_x_preferred":[
        "Grafton"
    ],
    "name:srp_x_preferred":[
        "\u0413\u0440\u0430\u0444\u0442\u043e\u043d"
    ],
    "name:swe_x_preferred":[
        "Grafton"
    ],
    "name:ukr_x_preferred":[
        "\u0413\u0440\u0430\u0444\u0442\u043e\u043d"
    ],
    "name:vol_x_preferred":[
        "Grafton"
    ],
    "qs_pg:aaroncc":"US",
    "qs_pg:name":"Grafton",
    "qs_pg:name_adm0":"United States",
    "qs_pg:name_adm1":"Maine",
    "qs_pg:photos":455,
    "qs_pg:photos_1k":92,
    "qs_pg:photos_9k":2,
    "qs_pg:photos_9r":5,
    "qs_pg:photos_all":455,
    "qs_pg:photos_sr":7,
    "qs_pg:pop_sr":0,
    "qs_pg:qs_pg_placetype":"locality",
    "qs_pg:qs_pg_placetype_gp":"Town",
    "qs_pg:woe_adm0":23424977,
    "woe:adm0_id":23424977,
    "woe:name_adm0":"United States",
    "woe:name_adm1":"Maine",
    "woe:placetype":"Town",
    "wof:name":"Grafton",
    "wof:placetype":"locality"
},
  "geometry": {"coordinates":[-70.938377,44.582245],"type":"Point"}
}