{
  "type": "Feature",
  "properties": {
    "gn:admin1_code":"ME",
    "gn:admin2_code":"25.0",
    "gn:admin3_code":"64850.0",
    "gn:asciiname":"Wildwood",
    "gn:country_code":"US",
    "gn:dem":120,
    "gn:elevation":"116.0",
    "gn:feature_class":"P",
    "gn:feature_code":"PPL",
    "gn:name":"Wildwood",
    "gn:population":0,
    "gn:timezone":"America/New_York",
    "iso:country":"US",
    "name:ceb_x_preferred":[
        "Wildwood"
    ],
    "name:deu_x_preferred":[
        "Wildwood"
    ],
    "name:fas_x_preferred":[
        "\u0648\u0627\u06cc\u0644\u062f\u0648\u0648\u062f"
    ],
    "name:ido_x_preferred":[
        "Wildwood"
    ],
    "name:ita_x_preferred":[
        "Wildwood"
    ],
    "name:nld_x_preferred":[
        "Wildwood"
    ],
    "name:pol_x_preferred":[
        "Wildwood"
    ],
    "name:por_x_preferred":[
        "Wildwood"
    ],
    "name:rus_x_preferred":[
        "\u0412\u0430\u0439\u043b\u0434\u0432\u0443\u0434"
    ],
    "name:srp_x_preferred":[
        "\u0412\u0430\u0458\u043b\u0434\u0432\u0443\u0434"
    ],
    "name:swe_x_preferred":[
        "Wildwood"
    ],
    "name:urd_x_preferred":[
        "\u0648\u0627\u0626\u0644\u0688\u0648\u0648\u0688"
    ],
    "name:vol_x_preferred":[
        "Wildwood"
    ],
    "wof:name":"Wildwood",
    "wof:placetype":"locality"
},
  "geometry": {"coordinates":[-69.46420999999999,44.90589],"type":"Point"}
}