{
  "type": "Feature",
  "properties": {
    "iso:country":"US",
    "name:eng_x_preferred":[
        "Northside Acres"
    ],
    "wof:name":"Northside Acres",
    "wof:placetype":"neighbourhood",
    "wof:population":878,
    "zs:area_m":2476300.836354,
    "zs:blockids":[
        51430101063072,
        51430101023071,
        51430101023063,
        51430101023065,
        51430101023038,
        51430101063063,
        51430101023072,
        51430101063071,
        51430101063059,
        51430101023074,
        51430101023060,
        51430101023062,
        51430101023064,
        51430101023082,
        51430101063061,
        51430101063060,
        51430101023079,
        51430101023076,
        51430101064011,
        51430101063062,
        51430101023085,
        51430101023081,
        51430101023084,
        51430101023080,
        51430101023059,
        51430101023083,
        51430101064012,
        51430101023061,
        51430101023086,
        51430101063064,
        51430101063058,
        51430101023073,
        51430101023189,
        51430101023078,
        51430101023077,
        51430101063065,
        51430101063005,
        51430101064008,
        51430101064010
    ],
    "zs:housing10":386,
    "zs:label":"Northside Acres",
    "zs:pop10":878
},
  "geometry": {"coordinates":[-94.123763,36.125973],"type":"Point"}
}