{
  "type": "Feature",
  "properties": {
    "iso:country":"US",
    "name:eng_x_preferred":[
        "Park Creek Addition"
    ],
    "wof:name":"Park Creek Addition",
    "wof:placetype":"neighbourhood",
    "wof:population":23,
    "zs:area_m":12387.516316,
    "zs:blockids":[
        480850316233001
    ],
    "zs:housing10":13,
    "zs:label":"Park Creek Addition",
    "zs:pop10":23
},
  "geometry": {"coordinates":[-96.73324,33.026093],"type":"Point"}
}