{
  "type": "Feature",
  "properties": {
    "gn:admin1_code":"KY",
    "gn:admin2_code":"71",
    "gn:asciiname":"Glo",
    "gn:country_code":"US",
    "gn:dem":216,
    "gn:elevation":"219.0",
    "gn:feature_class":"P",
    "gn:feature_code":"PPL",
    "gn:name":"Glo",
    "gn:population":0,
    "gn:timezone":"America/New_York",
    "iso:country":"US",
    "wof:name":"Glo",
    "wof:placetype":"locality"
},
  "geometry": {"coordinates":[-82.80933,37.44788],"type":"Point"}
}