{
  "type": "Feature",
  "properties": {
    "gn:admin1_code":"AL",
    "gn:admin2_code":"83",
    "gn:asciiname":"Lawngate",
    "gn:country_code":"US",
    "gn:dem":196,
    "gn:elevation":"195.0",
    "gn:feature_class":"P",
    "gn:feature_code":"PPL",
    "gn:name":"Lawngate",
    "gn:population":0,
    "gn:timezone":"America/Chicago",
    "iso:country":"US",
    "wof:name":"Lawngate",
    "wof:placetype":"locality"
},
  "geometry": {"coordinates":[-87.09307,34.72592],"type":"Point"}
}