{
  "type": "Feature",
  "properties": {
    "gn:admin1_code":"AR",
    "gn:admin2_code":"139.0",
    "gn:admin3_code":"92121.0",
    "gn:asciiname":"Bolding",
    "gn:country_code":"US",
    "gn:dem":43,
    "gn:elevation":"36.0",
    "gn:feature_class":"P",
    "gn:feature_code":"PPL",
    "gn:name":"Bolding",
    "gn:population":0,
    "gn:timezone":"America/Chicago",
    "iso:country":"US",
    "name:fas_x_preferred":[
        "\u0628\u0627\u0644\u062f\u06cc\u0646\u06af"
    ],
    "name:zho_x_preferred":[
        "\u535a\u4e01"
    ],
    "wof:name":"Bolding",
    "wof:placetype":"locality"
},
  "geometry": {"coordinates":[-92.22929999999999,33.08374],"type":"Point"}
}