{
  "type": "Feature",
  "properties": {
    "gn:elevation":2,
    "iso:country":"US",
    "name:eng_x_preferred":[
        "Walnut Beach"
    ],
    "name:eng_x_variant":[
        "Walnut Bch"
    ],
    "qs:gn_adm0_cc":"US",
    "qs:gn_fcode":"PPL",
    "qs:gn_local":4838652,
    "qs:gn_nam_loc":"milford",
    "qs:gn_namadm1":"CT",
    "qs:gn_name":"Walnut Beach",
    "qs:local_max":1732,
    "qs:local_sum":6661,
    "qs:localhoods":13,
    "qs:name":"Walnut Beach",
    "qs:name_adm0":"United States",
    "qs:name_adm1":"Connecticut",
    "qs:name_adm2":"New Haven",
    "qs:name_local":"Milford",
    "qs:photo_max":127,
    "qs:photo_sum":281,
    "qs:placetype":"Suburb",
    "qs:quad_count":10,
    "qs:woe_adm0":23424977,
    "qs:woe_adm1":2347565,
    "qs:woe_adm2":12587795,
    "qs:woe_lau":0,
    "qs:woe_local":2450978,
    "qs:woe_ver":"7.10.0",
    "wof:lang":[
        "eng"
    ],
    "wof:name":"Walnut Beach",
    "wof:placetype":"neighbourhood",
    "wof:population":2078,
    "zs:blockids":[
        90091504001012,
        90091504003003,
        90091503002025,
        90091504002006,
        90091504003002,
        90091504001011,
        90091504002010,
        90091503002029,
        90091503002030,
        90091504001013,
        90091504002001,
        90091504002008,
        90091504001004,
        90091504002012,
        90091504003012,
        90091504002011,
        90091503002024,
        90091504002003,
        90091504001014,
        90091504003005,
        90091504002013,
        90091504002004,
        90091503002031,
        90091504002005,
        90091504002009,
        90091503002023,
        90091504002002,
        90091504003004,
        90091503002034,
        90091504003001,
        90091504001005,
        90091504002007
    ],
    "zs:housing10":978,
    "zs:pop10":2078
},
  "geometry": {"coordinates":[-73.084107,41.19341],"type":"Point"}
}