{
  "type": "Feature",
  "properties": {
    "iso:country":"US",
    "name:eng_x_preferred":[
        "Hilliard Forest"
    ],
    "wof:name":"Hilliard Forest",
    "wof:placetype":"neighbourhood",
    "wof:population":1481,
    "zs:area_m":3916729.710046,
    "zs:blockids":[
        371830534112009,
        371830534112008,
        371830534112005,
        371830534111029,
        371830534111028,
        371830534111021,
        371830534111031,
        371830534111027,
        371830534111026,
        371830534112011,
        371830534112010,
        371830534112014,
        371830534111032,
        371830534112013,
        371830534111025
    ],
    "zs:housing10":461,
    "zs:label":"Hilliard Forest",
    "zs:pop10":1481
},
  "geometry": {"coordinates":[-78.89497900000001,35.80155],"type":"Point"}
}