{
  "type": "Feature",
  "properties": {
    "gn:admin1_code":"WV",
    "gn:admin2_code":"85.0",
    "gn:asciiname":"Pike",
    "gn:country_code":"US",
    "gn:dem":253,
    "gn:elevation":"246.0",
    "gn:feature_class":"P",
    "gn:feature_code":"PPL",
    "gn:name":"Pike",
    "gn:population":0,
    "gn:timezone":"America/New_York",
    "iso:country":"US",
    "wof:name":"Pike",
    "wof:placetype":"locality"
},
  "geometry": {"coordinates":[-81.08150000000001,39.28341],"type":"Point"}
}