{
  "type": "Feature",
  "properties": {
    "gn:admin1_code":"MD",
    "gn:admin2_code":"17.0",
    "gn:asciiname":"Marshalls Corner",
    "gn:country_code":"US",
    "gn:dem":64,
    "gn:elevation":"59.0",
    "gn:feature_class":"P",
    "gn:feature_code":"PPL",
    "gn:name":"Marshalls Corner",
    "gn:population":0,
    "gn:timezone":"America/New_York",
    "iso:country":"US",
    "wof:name":"Marshalls Corner",
    "wof:placetype":"locality"
},
  "geometry": {"coordinates":[-77.03914,38.54956],"type":"Point"}
}