{
  "type": "Feature",
  "properties": {
    "gn:admin1_code":"VA",
    "gn:admin2_code":"19",
    "gn:asciiname":"Woodlands",
    "gn:country_code":"US",
    "gn:dem":270,
    "gn:elevation":"265.0",
    "gn:feature_class":"P",
    "gn:feature_code":"PPL",
    "gn:name":"Woodlands",
    "gn:population":0,
    "gn:timezone":"America/New_York",
    "iso:country":"US",
    "name:bar_x_preferred":[
        "Woodlands"
    ],
    "name:ceb_x_preferred":[
        "Woodlands"
    ],
    "name:deu_x_preferred":[
        "Woodlands"
    ],
    "name:ita_x_preferred":[
        "Woodlands"
    ],
    "name:nld_x_preferred":[
        "Woodlands"
    ],
    "name:pol_x_preferred":[
        "Woodlands"
    ],
    "name:rus_x_preferred":[
        "\u0412\u0443\u0434\u043b\u0435\u043d\u0434\u0441"
    ],
    "name:srp_x_preferred":[
        "\u0412\u0443\u0434\u043b\u0430\u043d\u0434\u0441"
    ],
    "name:swe_x_preferred":[
        "Woodlands"
    ],
    "wof:name":"Woodlands",
    "wof:placetype":"locality"
},
  "geometry": {"coordinates":[-79.29392,37.34514],"type":"Point"}
}