{
  "type": "Feature",
  "properties": {
    "iso:country":"US",
    "name:eng_x_preferred":[
        "Hendrickson Hideway"
    ],
    "wof:name":"Hendrickson Hideway",
    "wof:placetype":"neighbourhood",
    "wof:population":2450,
    "zs:area_m":13339944.060216,
    "zs:blockids":[
        530110409052020,
        530110409091020,
        530110409071000,
        530110409101010,
        530110409052024,
        530110409052034,
        530110409052018,
        530110409052007,
        530110409052021,
        530110409101035,
        530110409051031,
        530110409052026,
        530110409052014,
        530110409052002,
        530110409052010,
        530110409101016,
        530110409052030,
        530110409052022,
        530110409052013,
        530110409052025,
        530110409052017,
        530110409051012,
        530110409052000,
        530110409101008,
        530110409101011,
        530110409052028,
        530110409052029,
        530110409052033,
        530110409091021,
        530110409052011,
        530110409052001,
        530110409101012,
        530110409052009,
        530110409091019,
        530110409052012,
        530110409052003,
        530110409052015,
        530110409052027,
        530110409052019,
        530110409051026,
        530110409101009,
        530110409052023,
        530110409052016,
        530110409101036,
        530110409052008
    ],
    "zs:housing10":880,
    "zs:label":"Hendrickson Hideway",
    "zs:pop10":2450
},
  "geometry": {"coordinates":[-122.697487,45.743149],"type":"Point"}
}