{
  "type": "Feature",
  "properties": {
    "gn:admin1_code":"MO",
    "gn:admin2_code":"23.0",
    "gn:admin3_code":"6076.0",
    "gn:asciiname":"Wilby",
    "gn:country_code":"US",
    "gn:dem":110,
    "gn:elevation":"110.0",
    "gn:feature_class":"P",
    "gn:feature_code":"PPL",
    "gn:name":"Wilby",
    "gn:population":0,
    "gn:timezone":"America/Chicago",
    "iso:country":"US",
    "name:ceb_x_preferred":[
        "Wilby"
    ],
    "name:fra_x_preferred":[
        "Wilby"
    ],
    "name:ita_x_preferred":[
        "Wilby"
    ],
    "name:jpn_x_preferred":[
        "\u30a6\u30a3\u30eb\u30d3\u30fc"
    ],
    "name:nld_x_preferred":[
        "Wilby"
    ],
    "name:pol_x_preferred":[
        "Wilby"
    ],
    "name:spa_x_preferred":[
        "Wilby"
    ],
    "name:swe_x_preferred":[
        "Wilby"
    ],
    "wof:name":"Wilby",
    "wof:placetype":"locality"
},
  "geometry": {"coordinates":[-90.43983,36.87089],"type":"Point"}
}