{
  "type": "Feature",
  "properties": {
    "gn:country":"US",
    "gn:fcode":"PPL",
    "gn:population":0,
    "iso:country":"US",
    "name:cat_x_preferred":[
        "Lawrenceville"
    ],
    "name:ceb_x_preferred":[
        "Lawrenceville"
    ],
    "name:deu_x_preferred":[
        "Lawrenceville"
    ],
    "name:eng_x_preferred":[
        "Lawrenceville"
    ],
    "name:fra_x_preferred":[
        "Lawrenceville"
    ],
    "name:ita_x_preferred":[
        "Lawrenceville"
    ],
    "name:kor_x_preferred":[
        "\ub85c\ub80c\uc2a4\ube4c"
    ],
    "name:nld_x_preferred":[
        "Lawrenceville"
    ],
    "name:pol_x_preferred":[
        "Lawrenceville"
    ],
    "name:por_x_preferred":[
        "Lawrenceville"
    ],
    "name:rus_x_preferred":[
        "\u041b\u043e\u0440\u0435\u043d\u0441\u0432\u0438\u043b\u043b"
    ],
    "name:spa_x_preferred":[
        "Lawrenceville"
    ],
    "name:srp_x_preferred":[
        "\u041b\u043e\u0440\u0435\u043d\u0441\u0432\u0438\u043b"
    ],
    "name:swe_x_preferred":[
        "Lawrenceville"
    ],
    "name:und_x_variant":[
        "Websters Landing"
    ],
    "name:vol_x_preferred":[
        "Lawrenceville"
    ],
    "qs_pg:aaroncc":"US",
    "qs_pg:gn_country":"US",
    "qs_pg:gn_fcode":"PPL",
    "qs_pg:gn_pop":0,
    "qs_pg:name":"Lawrenceville",
    "qs_pg:name_adm0":"United States",
    "qs_pg:name_adm1":"Arkansas",
    "qs_pg:photos":7,
    "qs_pg:photos_1k":1,
    "qs_pg:photos_9k":1,
    "qs_pg:photos_9r":1,
    "qs_pg:photos_all":7,
    "qs_pg:photos_sr":1,
    "qs_pg:pop_sr":0,
    "qs_pg:qs_pg_placetype":"locality",
    "qs_pg:qs_pg_placetype_gp":"Town",
    "qs_pg:woe_adm0":23424977,
    "woe:adm0_id":23424977,
    "woe:name_adm0":"United States",
    "woe:name_adm1":"Arkansas",
    "woe:placetype":"Town",
    "wof:name":"Lawrenceville",
    "wof:placetype":"locality"
},
  "geometry": {"coordinates":[-91.18095,34.50927],"type":"Point"}
}