{
  "type": "Feature",
  "properties": {
    "gn:admin1_code":"SC",
    "gn:admin2_code":"7.0",
    "gn:asciiname":"Burris",
    "gn:country_code":"US",
    "gn:dem":244,
    "gn:elevation":"243.0",
    "gn:feature_class":"P",
    "gn:feature_code":"PPL",
    "gn:name":"Burris",
    "gn:population":0,
    "gn:timezone":"America/New_York",
    "iso:country":"US",
    "name:rus_x_preferred":[
        "\u0411\u0451\u0440\u0440\u0438\u0441"
    ],
    "wof:name":"Burris",
    "wof:placetype":"locality"
},
  "geometry": {"coordinates":[-82.43456999999999,34.47344],"type":"Point"}
}