{
  "type": "Feature",
  "properties": {
    "gn:admin1_code":"AR",
    "gn:admin2_code":"149.0",
    "gn:admin3_code":"93240.0",
    "gn:asciiname":"Rover",
    "gn:country_code":"US",
    "gn:dem":120,
    "gn:elevation":"120.0",
    "gn:feature_class":"P",
    "gn:feature_code":"PPL",
    "gn:name":"Rover",
    "gn:population":0,
    "gn:timezone":"America/Chicago",
    "iso:country":"US",
    "name:fas_x_preferred":[
        "\u0631\u0648\u0648\u0631"
    ],
    "name:zho_x_preferred":[
        "\u7f85\u5f17"
    ],
    "wof:name":"Rover",
    "wof:placetype":"locality"
},
  "geometry": {"coordinates":[-93.40546000000001,34.94648],"type":"Point"}
}