{
  "type": "Feature",
  "properties": {
    "gn:admin1_code":"VA",
    "gn:admin2_code":"710",
    "gn:asciiname":"Elizabeth Park",
    "gn:country_code":"US",
    "gn:dem":9,
    "gn:elevation":"3.0",
    "gn:feature_class":"P",
    "gn:feature_code":"PPL",
    "gn:name":"Elizabeth Park",
    "gn:population":0,
    "gn:timezone":"America/New_York",
    "iso:country":"US",
    "name:ceb_x_preferred":[
        "Elizabeth Park"
    ],
    "name:deu_x_preferred":[
        "Elizabeth Park"
    ],
    "name:swe_x_preferred":[
        "Elizabeth Park"
    ],
    "wof:name":"Elizabeth Park",
    "wof:placetype":"locality"
},
  "geometry": {"coordinates":[-76.21799,36.84043],"type":"Point"}
}