{
  "type": "Feature",
  "properties": {
    "gn:country":"US",
    "gn:fcode":"PPLX",
    "gn:population":0,
    "iso:country":"US",
    "name:eng_x_preferred":[
        "Beverly Hills"
    ],
    "qs_pg:aaroncc":"US",
    "qs_pg:gn_country":"US",
    "qs_pg:gn_fcode":"PPLX",
    "qs_pg:gn_pop":0,
    "qs_pg:name":"Beverly Hills",
    "qs_pg:name_adm0":"United States",
    "qs_pg:name_adm1":"Louisiana",
    "qs_pg:photos":2,
    "qs_pg:photos_1k":1,
    "qs_pg:photos_9k":1,
    "qs_pg:photos_9r":1,
    "qs_pg:photos_all":2,
    "qs_pg:photos_sr":1,
    "qs_pg:pop_sr":0,
    "qs_pg:qs_pg_placetype":"neighbourhood",
    "qs_pg:qs_pg_placetype_gp":"Suburb",
    "qs_pg:woe_adm0":23424977,
    "woe:adm0_id":23424977,
    "woe:name_adm0":"United States",
    "woe:name_adm1":"Louisiana",
    "woe:placetype":"Suburb",
    "wof:name":"Beverly Hills",
    "wof:placetype":"neighbourhood",
    "wof:population":184
},
  "geometry": {"coordinates":[-89.75201,30.26631],"type":"Point"}
}