{
  "type": "Feature",
  "properties": {
    "iso:country":"US",
    "name:eng_x_preferred":[
        "Moores Corners"
    ],
    "wof:name":"Moores Corners",
    "wof:placetype":"neighbourhood",
    "wof:population":525,
    "zs:area_m":8644423.030919,
    "zs:blockids":[
        250277191002020,
        250277191002027,
        250277191002016,
        250277191002023,
        250277191002021,
        250277191004028,
        250277191004034,
        250277191002029,
        250277191002019,
        250277191002007,
        250277191002018,
        250277191002013,
        250277191002017
    ],
    "zs:housing10":197,
    "zs:label":"Moores Corners",
    "zs:pop10":525
},
  "geometry": {"coordinates":[-71.81462000000001,42.419775],"type":"Point"}
}