{
  "type": "Feature",
  "properties": {
    "gn:admin1_code":"NY",
    "gn:admin2_code":"89.0",
    "gn:admin3_code":"12342.0",
    "gn:asciiname":"Boyden Brook Mobile Home Park",
    "gn:country_code":"US",
    "gn:dem":119,
    "gn:elevation":"120.0",
    "gn:feature_class":"P",
    "gn:feature_code":"PPL",
    "gn:name":"Boyden Brook Mobile Home Park",
    "gn:population":0,
    "gn:timezone":"America/New_York",
    "iso:country":"US",
    "wof:name":"Boyden Brook Mobile Home Park",
    "wof:placetype":"campus"
},
  "geometry": {"coordinates":[-75.21149,44.56065],"type":"Point"}
}