{
  "type": "Feature",
  "properties": {
    "gn:admin1_code":"KS",
    "gn:admin2_code":"175.0",
    "gn:admin3_code":"39825.0",
    "gn:asciiname":"Gas Light Village Mobile Home Park",
    "gn:country_code":"US",
    "gn:dem":863,
    "gn:elevation":"862.0",
    "gn:feature_class":"P",
    "gn:feature_code":"PPL",
    "gn:name":"Gas Light Village Mobile Home Park",
    "gn:population":0,
    "gn:timezone":"America/Chicago",
    "iso:country":"US",
    "wof:name":"Gas Light Village Mobile Home Park",
    "wof:placetype":"campus"
},
  "geometry": {"coordinates":[-100.90922999999999,37.03965],"type":"Point"}
}