{
  "type": "Feature",
  "properties": {
    "gn:admin1_code":"OH",
    "gn:admin2_code":"119.0",
    "gn:admin3_code":"82236.0",
    "gn:asciiname":"Forest Hills",
    "gn:country_code":"US",
    "gn:dem":242,
    "gn:elevation":"239.0",
    "gn:feature_class":"P",
    "gn:feature_code":"PPL",
    "gn:name":"Forest Hills",
    "gn:population":0,
    "gn:timezone":"America/New_York",
    "iso:country":"US",
    "name:ceb_x_preferred":[
        "Forest Hills"
    ],
    "name:ces_x_preferred":[
        "Forest Hills"
    ],
    "name:deu_x_preferred":[
        "Forest Hills"
    ],
    "name:fra_x_preferred":[
        "Forest Hills"
    ],
    "name:ita_x_preferred":[
        "Forest Hills"
    ],
    "name:kor_x_preferred":[
        "\ud3ec\ub9ac\uc2a4\ud2b8\ud790\uc2a4"
    ],
    "name:nld_x_preferred":[
        "Forest Hills"
    ],
    "name:pol_x_preferred":[
        "Forest Hills"
    ],
    "name:por_x_preferred":[
        "Forest Hills"
    ],
    "name:spa_x_preferred":[
        "Forest Hills"
    ],
    "name:srp_x_preferred":[
        "\u0424\u043e\u0440\u0438\u0441\u0442 \u0425\u0438\u043b\u0441"
    ],
    "name:swe_x_preferred":[
        "Forest Hills"
    ],
    "name:ukr_x_preferred":[
        "\u0424\u043e\u0440\u0435\u0441\u0442-\u0413\u0456\u043b\u043b\u0441"
    ],
    "name:urd_x_preferred":[
        "\u0641\u0627\u0631\u0633\u0679 \u06c1\u0644\u0632"
    ],
    "name:vol_x_preferred":[
        "Forest Hills"
    ],
    "wof:name":"Forest Hills",
    "wof:placetype":"locality"
},
  "geometry": {"coordinates":[-81.97306999999998,39.92346],"type":"Point"}
}