{
  "type": "Feature",
  "properties": {
    "iso:country":"US",
    "name:bar_x_preferred":[
        "North End"
    ],
    "name:ceb_x_preferred":[
        "North End"
    ],
    "name:ces_x_preferred":[
        "North End"
    ],
    "name:eng_x_preferred":[
        "North End"
    ],
    "name:ita_x_preferred":[
        "North End"
    ],
    "name:spa_x_preferred":[
        "North End"
    ],
    "name:swe_x_preferred":[
        "North End"
    ],
    "wd:wordcount":230,
    "wof:name":"North End",
    "wof:placetype":"neighbourhood",
    "wof:population":2074,
    "zs:area_m":7855716.77291,
    "zs:blockids":[
        240010004003011,
        240010004002026,
        240010004003003,
        240010004003009,
        240010004002024,
        240010004002031,
        240010003001011,
        240010003002014,
        240010003001007,
        240010003002004,
        240010004002018,
        240010004002045,
        240010003001014,
        240010004002061,
        240010003001024,
        240010003002006,
        240010003001032,
        240010004002023,
        240010003002015,
        240010003001002,
        240010003002012,
        240010003002005,
        240010004003010,
        240010004003040,
        240010004003005,
        240010003001008,
        240010004002063,
        240010004002064,
        240010004003002,
        240010004002013,
        240010003002002,
        240010003002013,
        240010003001018,
        240010004003000,
        240010003001004,
        240010004002016,
        240010004002041,
        240010004002060,
        240010004002034,
        240010004002042,
        240010003001027,
        240010004002044,
        240010003002011,
        240010004002038,
        240010003002008,
        240010004003007,
        240010004002040,
        240010003002010,
        240010004002062,
        240010004002022,
        240010004002019,
        240010004002015,
        240010003002007,
        240010003002009,
        240010003002001,
        240010003002016,
        240010004002025,
        240010003001012,
        240010003001015,
        240010003001019,
        240010003001029,
        240010003002000,
        240010003002017,
        240010003002019,
        240010004003004,
        240010004002037,
        240010004002039,
        240010004003008,
        240010003002003,
        240010003001003,
        240010003001056,
        240010003002018,
        240010003001017,
        240010003001010,
        240010004003001,
        240010004002043
    ],
    "zs:housing10":921,
    "zs:label":"North End",
    "zs:pop10":2074
},
  "geometry": {"coordinates":[-78.756135,39.677844],"type":"Point"}
}