{
  "type": "Feature",
  "properties": {
    "gn:admin1_code":"CO",
    "gn:admin2_code":"21.0",
    "gn:asciiname":"Ortiz",
    "gn:country_code":"US",
    "gn:dem":2437,
    "gn:elevation":"2434.0",
    "gn:feature_class":"P",
    "gn:feature_code":"PPL",
    "gn:name":"Ortiz",
    "gn:population":0,
    "gn:timezone":"America/Denver",
    "iso:country":"US",
    "name:deu_x_preferred":[
        "Ortiz"
    ],
    "name:ita_x_preferred":[
        "Ortiz"
    ],
    "name:spa_x_preferred":[
        "Ortiz"
    ],
    "wof:name":"Ortiz",
    "wof:placetype":"locality"
},
  "geometry": {"coordinates":[-106.04419,37.00418],"type":"Point"}
}