{
  "type": "Feature",
  "properties": {
    "gn:admin1_code":"TN",
    "gn:admin2_code":"35",
    "gn:asciiname":"Old Winesap",
    "gn:country_code":"US",
    "gn:dem":531,
    "gn:elevation":"523.0",
    "gn:feature_class":"P",
    "gn:feature_code":"PPL",
    "gn:name":"Old Winesap",
    "gn:population":0,
    "gn:timezone":"America/Chicago",
    "iso:country":"US",
    "name:eng_x_preferred":[
        "Old Winesap"
    ],
    "name:und_x_variant":[
        "Winesap"
    ],
    "wof:name":"Old Winesap",
    "wof:placetype":"locality"
},
  "geometry": {"coordinates":[-85.16524,35.79035],"type":"Point"}
}