{
  "type": "Feature",
  "properties": {
    "gn:admin1_code":"TX",
    "gn:admin2_code":"499",
    "gn:asciiname":"Little Hope",
    "gn:country_code":"US",
    "gn:dem":130,
    "gn:elevation":"126.0",
    "gn:feature_class":"P",
    "gn:feature_code":"PPL",
    "gn:name":"Little Hope",
    "gn:population":0,
    "gn:timezone":"America/Chicago",
    "iso:country":"US",
    "name:deu_x_preferred":[
        "Little Hope"
    ],
    "wof:name":"Little Hope",
    "wof:placetype":"locality"
},
  "geometry": {"coordinates":[-95.25689,32.77958],"type":"Point"}
}