{
  "type": "Feature",
  "properties": {
    "gn:admin1_code":"NY",
    "gn:admin2_code":"111.0",
    "gn:admin3_code":"54749.0",
    "gn:asciiname":"Krumville",
    "gn:country_code":"US",
    "gn:dem":238,
    "gn:elevation":"236.0",
    "gn:feature_class":"P",
    "gn:feature_code":"PPL",
    "gn:name":"Krumville",
    "gn:population":0,
    "gn:timezone":"America/New_York",
    "iso:country":"US",
    "name:eng_x_preferred":[
        "Krumville"
    ],
    "name:und_x_variant":[
        "Kromville"
    ],
    "wof:name":"Krumville",
    "wof:placetype":"locality"
},
  "geometry": {"coordinates":[-74.24236999999999,41.88482],"type":"Point"}
}