{
  "type": "Feature",
  "properties": {
    "gn:admin1_code":"NC",
    "gn:admin2_code":"123.0",
    "gn:admin3_code":"93848.0",
    "gn:asciiname":"Sugarloaf Shores",
    "gn:country_code":"US",
    "gn:dem":91,
    "gn:elevation":"89.0",
    "gn:feature_class":"P",
    "gn:feature_code":"PPL",
    "gn:name":"Sugarloaf Shores",
    "gn:population":0,
    "gn:timezone":"America/New_York",
    "iso:country":"US",
    "wof:name":"Sugarloaf Shores",
    "wof:placetype":"locality"
},
  "geometry": {"coordinates":[-80.06310999999999,35.35597999999999],"type":"Point"}
}