{
  "type": "Feature",
  "properties": {
    "gn:admin1_code":"NV",
    "gn:admin2_code":"7",
    "gn:asciiname":"Williams Cabin",
    "gn:country_code":"US",
    "gn:dem":2009,
    "gn:elevation":"2000.0",
    "gn:feature_class":"P",
    "gn:feature_code":"PPL",
    "gn:name":"Williams Cabin",
    "gn:population":0,
    "gn:timezone":"America/Los_Angeles",
    "iso:country":"US",
    "wof:name":"Williams Cabin",
    "wof:placetype":"locality"
},
  "geometry": {"coordinates":[-115.67119,41.71713],"type":"Point"}
}