{
  "type": "Feature",
  "properties": {
    "iso:country":"US",
    "name:eng_x_preferred":[
        "Powder House"
    ],
    "qs:gn_adm0_cc":"US",
    "qs:gn_local":4951257,
    "qs:gn_nam_loc":"Somerville, Middlesex, Massachusetts, US",
    "qs:gn_namadm1":"MA",
    "qs:local_max":8565,
    "qs:local_sum":32967,
    "qs:localhoods":16,
    "qs:name":"Powder House",
    "qs:name_adm0":"United States",
    "qs:name_adm1":"Massachusetts",
    "qs:name_adm2":"Middlesex",
    "qs:name_local":"Somerville",
    "qs:photo_max":237,
    "qs:photo_sum":1277,
    "qs:placetype":"Suburb",
    "qs:quad_count":37,
    "qs:woe_adm0":23424977,
    "qs:woe_adm1":2347580,
    "qs:woe_adm2":12588708,
    "qs:woe_lau":0,
    "qs:woe_local":2495739,
    "qs:woe_ver":"7.10.0",
    "wof:lang":[
        "eng"
    ],
    "wof:name":"Powder House",
    "wof:placetype":"neighbourhood",
    "wof:population":3942,
    "zs:blockids":[
        250173504004000,
        250173509002000,
        250173510005004,
        250173504003000,
        250173504004011,
        250173504004001,
        250173509001000,
        250173504003006,
        250173509001007,
        250173504002001,
        250173504004002,
        250173504004013,
        250173504002002,
        250173504003007,
        250173510005000,
        250173509001008,
        250173509001005,
        250173509001006,
        250173504001008,
        250173504005008,
        250173504003004,
        250173504005005,
        250173510005002,
        250173504005000,
        250173504002003,
        250173504003005,
        250173504002006,
        250173504003003,
        250173510005001,
        250173504003001,
        250173504001009,
        250173504003002,
        250173504002005,
        250173504002004
    ],
    "zs:housing10":1817,
    "zs:pop10":3942
},
  "geometry": {"coordinates":[-71.115611,42.397391],"type":"Point"}
}