{
  "type": "Feature",
  "properties": {
    "gn:elevation":142,
    "iso:country":"US",
    "name:eng_x_preferred":[
        "Wyola"
    ],
    "name:fra_x_preferred":[
        "Wyola"
    ],
    "qs:gn_adm0_cc":"US",
    "qs:gn_fcode":"PPL",
    "qs:gn_local":4560007,
    "qs:gn_nam_loc":"Newtown, Delaware, Pennsylvania, US",
    "qs:gn_namadm1":"PA",
    "qs:gn_name":"Wyola",
    "qs:local_max":117,
    "qs:local_sum":147,
    "qs:localhoods":2,
    "qs:name":"Wyola",
    "qs:name_adm0":"United States",
    "qs:name_adm1":"Pennsylvania",
    "qs:name_adm2":"Delaware",
    "qs:name_local":"Newtown",
    "qs:photo_max":49,
    "qs:photo_sum":117,
    "qs:placetype":"Suburb",
    "qs:quad_count":9,
    "qs:woe_adm0":23424977,
    "qs:woe_adm1":2347597,
    "qs:woe_adm2":12589750,
    "qs:woe_lau":0,
    "qs:woe_local":28745642,
    "qs:woe_ver":"7.10.0",
    "wd:wordcount":113,
    "wof:lang":[
        "eng"
    ],
    "wof:name":"Wyola",
    "wof:placetype":"neighbourhood",
    "wof:population":1750,
    "zs:blockids":[
        420454099041009,
        420454099041018,
        420454099041012,
        420454099042024,
        420454099041015,
        420454099042018,
        420454099042028,
        420454099042014,
        420454099042015,
        420454099042019,
        420454099041010,
        420454099042009,
        420454099041017,
        420454099041016,
        420454099042017,
        420454099041005,
        420454099041008,
        420454099042026,
        420454099041014,
        420454099041019,
        420454099042030,
        420454099042001,
        420454099042021,
        420454099042025,
        420454099042013,
        420454099042023,
        420454099042020,
        420454099041007,
        420454099041006,
        420454099042016,
        420454099042027
    ],
    "zs:housing10":534,
    "zs:pop10":1750
},
  "geometry": {"coordinates":[-75.412397,40.000708],"type":"Point"}
}