{
  "type": "Feature",
  "properties": {
    "gn:admin1_code":"FL",
    "gn:admin2_code":"35.0",
    "gn:asciiname":"Beverly Beach Trailer Park",
    "gn:country_code":"US",
    "gn:dem":7,
    "gn:elevation":"5.0",
    "gn:feature_class":"P",
    "gn:feature_code":"PPL",
    "gn:name":"Beverly Beach Trailer Park",
    "gn:population":0,
    "gn:timezone":"America/New_York",
    "iso:country":"US",
    "wof:name":"Beverly Beach Trailer Park",
    "wof:placetype":"campus"
},
  "geometry": {"coordinates":[-81.152,29.5273],"type":"Point"}
}