{
  "type": "Feature",
  "properties": {
    "gn:admin1_code":"PA",
    "gn:admin2_code":"63.0",
    "gn:admin3_code":"87160.0",
    "gn:asciiname":"McIntyre",
    "gn:country_code":"US",
    "gn:dem":358,
    "gn:elevation":"356.0",
    "gn:feature_class":"P",
    "gn:feature_code":"PPL",
    "gn:name":"McIntyre",
    "gn:population":0,
    "gn:timezone":"America/New_York",
    "iso:country":"US",
    "wof:name":"McIntyre",
    "wof:placetype":"locality"
},
  "geometry": {"coordinates":[-79.29559,40.56979000000001],"type":"Point"}
}