{
  "type": "Feature",
  "properties": {
    "gn:admin1_code":"IL",
    "gn:admin2_code":"91.0",
    "gn:admin3_code":"58538.0",
    "gn:asciiname":"Leesville",
    "gn:country_code":"US",
    "gn:dem":195,
    "gn:elevation":"195.0",
    "gn:feature_class":"P",
    "gn:feature_code":"PPL",
    "gn:name":"Leesville",
    "gn:population":0,
    "gn:timezone":"America/Chicago",
    "iso:country":"US",
    "name:cat_x_preferred":[
        "Leesville"
    ],
    "name:ceb_x_preferred":[
        "Leesville"
    ],
    "name:deu_x_preferred":[
        "Leesville"
    ],
    "name:fra_x_preferred":[
        "Leesville"
    ],
    "name:ita_x_preferred":[
        "Leesville"
    ],
    "name:nld_x_preferred":[
        "Leesville"
    ],
    "name:pol_x_preferred":[
        "Leesville"
    ],
    "name:srp_x_preferred":[
        "\u041b\u0438\u0441\u0432\u0438\u043b"
    ],
    "name:swe_x_preferred":[
        "Leesville"
    ],
    "name:ukr_x_preferred":[
        "\u041b\u0456\u0441\u0432\u0456\u043b\u043b"
    ],
    "name:vol_x_preferred":[
        "Leesville"
    ],
    "wof:name":"Leesville",
    "wof:placetype":"locality"
},
  "geometry": {"coordinates":[-87.62503000000002,41.02476],"type":"Point"}
}