{
  "type": "Feature",
  "properties": {
    "gn:admin1_code":"TN",
    "gn:admin2_code":"57",
    "gn:asciiname":"Elm Springs",
    "gn:country_code":"US",
    "gn:dem":438,
    "gn:elevation":"432.0",
    "gn:feature_class":"P",
    "gn:feature_code":"PPL",
    "gn:name":"Elm Springs",
    "gn:population":0,
    "gn:timezone":"America/New_York",
    "iso:country":"US",
    "name:ceb_x_preferred":[
        "Elm Springs"
    ],
    "name:deu_x_preferred":[
        "Elm Springs"
    ],
    "name:ita_x_preferred":[
        "Elm Springs"
    ],
    "name:pol_x_preferred":[
        "Elm Springs"
    ],
    "wof:name":"Elm Springs",
    "wof:placetype":"locality"
},
  "geometry": {"coordinates":[-83.60074,36.3362],"type":"Point"}
}