{
  "type": "Feature",
  "properties": {
    "gn:admin1_code":"AL",
    "gn:admin2_code":"95.0",
    "gn:asciiname":"Rocky Ridge",
    "gn:country_code":"US",
    "gn:dem":189,
    "gn:elevation":"187.0",
    "gn:feature_class":"P",
    "gn:feature_code":"PPL",
    "gn:name":"Rocky Ridge",
    "gn:population":0,
    "gn:timezone":"America/Chicago",
    "iso:country":"US",
    "name:ceb_x_preferred":[
        "Rocky Ridge"
    ],
    "name:ces_x_preferred":[
        "Rocky Ridge"
    ],
    "name:deu_x_preferred":[
        "Rocky Ridge"
    ],
    "name:ita_x_preferred":[
        "Rocky Ridge"
    ],
    "name:nld_x_preferred":[
        "Rocky Ridge"
    ],
    "name:pol_x_preferred":[
        "Rocky Ridge"
    ],
    "name:por_x_preferred":[
        "Rocky Ridge"
    ],
    "name:srp_x_preferred":[
        "\u0420\u043e\u043a\u0438 \u0420\u0438\u045f"
    ],
    "name:swe_x_preferred":[
        "Rocky Ridge"
    ],
    "name:vol_x_preferred":[
        "Rocky Ridge"
    ],
    "wof:name":"Rocky Ridge",
    "wof:placetype":"locality"
},
  "geometry": {"coordinates":[-86.27498,34.59592],"type":"Point"}
}