{
  "type": "Feature",
  "properties": {
    "gn:admin1_code":"ID",
    "gn:admin2_code":"9.0",
    "gn:asciiname":"Chat'u'washa'lqs Bluff",
    "gn:country_code":"US",
    "gn:dem":671,
    "gn:elevation":"676.0",
    "gn:feature_class":"P",
    "gn:feature_code":"PPL",
    "gn:name":"Chat'u'washa'lqs Bluff",
    "gn:population":0,
    "gn:timezone":"America/Los_Angeles",
    "iso:country":"US",
    "wof:name":"Chat'u'washa'lqs Bluff",
    "wof:placetype":"locality"
},
  "geometry": {"coordinates":[-116.60346,47.33415],"type":"Point"}
}