{
  "type": "Feature",
  "properties": {
    "gn:admin1_code":"AL",
    "gn:admin2_code":"81",
    "gn:asciiname":"Mitchell Crossroads",
    "gn:country_code":"US",
    "gn:dem":185,
    "gn:elevation":"177.0",
    "gn:feature_class":"P",
    "gn:feature_code":"PPL",
    "gn:name":"Mitchell Crossroads",
    "gn:population":0,
    "gn:timezone":"America/Chicago",
    "iso:country":"US",
    "name:eng_x_preferred":[
        "Mitchell Crossroads"
    ],
    "name:und_x_variant":[
        "Mitchell Cross Road",
        "Mitchells Crossroads"
    ],
    "wof:name":"Mitchell Crossroads",
    "wof:placetype":"locality"
},
  "geometry": {"coordinates":[-85.41328,32.53875],"type":"Point"}
}