{
  "type": "Feature",
  "properties": {
    "gn:admin1_code":"ID",
    "gn:admin2_code":"67.0",
    "gn:asciiname":"Amalga",
    "gn:country_code":"US",
    "gn:dem":1266,
    "gn:elevation":"1266.0",
    "gn:feature_class":"P",
    "gn:feature_code":"PPL",
    "gn:name":"Amalga",
    "gn:population":0,
    "gn:timezone":"America/Boise",
    "iso:country":"US",
    "wof:name":"Amalga",
    "wof:placetype":"locality"
},
  "geometry": {"coordinates":[-113.72474,42.57685],"type":"Point"}
}