{
  "type": "Feature",
  "properties": {
    "gn:admin1_code":"KY",
    "gn:admin2_code":"57",
    "gn:asciiname":"Littrell",
    "gn:country_code":"US",
    "gn:dem":323,
    "gn:elevation":"321.0",
    "gn:feature_class":"P",
    "gn:feature_code":"PPL",
    "gn:name":"Littrell",
    "gn:population":0,
    "gn:timezone":"America/Chicago",
    "iso:country":"US",
    "wof:name":"Littrell",
    "wof:placetype":"locality"
},
  "geometry": {"coordinates":[-85.39635,36.6859],"type":"Point"}
}