{
  "type": "Feature",
  "properties": {
    "gn:admin1_code":"TX",
    "gn:admin2_code":"387",
    "gn:asciiname":"English",
    "gn:country_code":"US",
    "gn:dem":140,
    "gn:elevation":"135.0",
    "gn:feature_class":"P",
    "gn:feature_code":"PPL",
    "gn:name":"English",
    "gn:population":0,
    "gn:timezone":"America/Chicago",
    "iso:country":"US",
    "name:ara_x_preferred":[
        "\u0643\u0644\u0645\u0629 \u0627\u0644\u0625\u0646\u062c\u0644\u064a\u0632\u064a\u0629"
    ],
    "name:ben_x_preferred":[
        "\u0987\u0982\u09b0\u09c7\u099c\u09bf"
    ],
    "name:deu_x_preferred":[
        "English"
    ],
    "name:fas_x_preferred":[
        "\u0627\u0646\u06af\u0644\u06cc\u0633"
    ],
    "name:fas_x_variant":[
        "\u0627\u0646\u06af\u0644\u06cc\u0633\u06cc"
    ],
    "name:fra_x_preferred":[
        "English"
    ],
    "name:glk_x_preferred":[
        "\u0627\u06cc\u0646\u06af\u06cc\u0644\u06cc\u0633\u06cc"
    ],
    "name:heb_x_preferred":[
        "\u05d0\u05d9\u05e0\u05d2\u05dc\u05d9\u05e9"
    ],
    "name:hin_x_preferred":[
        "\u0907\u0902\u0917\u0932\u093f\u0936"
    ],
    "name:hun_x_preferred":[
        "English"
    ],
    "name:ilo_x_preferred":[
        "English"
    ],
    "name:ind_x_preferred":[
        "English"
    ],
    "name:ita_x_preferred":[
        "English"
    ],
    "name:jpn_x_preferred":[
        "\u30a4\u30f3\u30b0\u30ea\u30c3\u30b7\u30e5"
    ],
    "name:kor_x_preferred":[
        "\uc789\uae00\ub9ac\uc2dc"
    ],
    "name:lav_x_preferred":[
        "English"
    ],
    "name:mai_x_preferred":[
        "\u0905\u0919\u094d\u0917\u094d\u0930\u0947\u091c\u0940"
    ],
    "name:mal_x_preferred":[
        "\u0d07\u0d02\u0d17\u0d4d\u0d32\u0d3f\u0d37\u0d4d"
    ],
    "name:ori_x_preferred":[
        "\u0b07\u0b02\u0b30\u0b3e\u0b1c\u0b40"
    ],
    "name:pol_x_preferred":[
        "English"
    ],
    "name:por_x_preferred":[
        "English"
    ],
    "name:rus_x_preferred":[
        "English"
    ],
    "name:snd_x_preferred":[
        "\u0627\u0646\u06af\u0631\u06cc\u0632\u064a"
    ],
    "name:spa_x_preferred":[
        "English"
    ],
    "name:tha_x_preferred":[
        "\u0e2d\u0e31\u0e07\u0e01\u0e24\u0e29"
    ],
    "name:tur_x_preferred":[
        "English"
    ],
    "name:ukr_x_preferred":[
        "\u0410\u043d\u0433\u043b\u0456\u0439\u0441\u044c\u043a\u0435"
    ],
    "name:ukr_x_variant":[
        "English"
    ],
    "name:urd_x_preferred":[
        "\u0627\u0646\u06af\u0644\u0634"
    ],
    "name:vie_x_preferred":[
        "S\u00f4ng English"
    ],
    "name:vol_x_preferred":[
        "English"
    ],
    "name:zho_cn_x_preferred":[
        "\u82f1\u683c\u5229\u5e0c\u6cb3"
    ],
    "name:zho_tw_x_preferred":[
        "\u82f1\u5409\u5229\u6cb3"
    ],
    "wof:name":"English",
    "wof:placetype":"locality"
},
  "geometry": {"coordinates":[-94.85938,33.62761],"type":"Point"}
}