{
  "type": "Feature",
  "properties": {
    "gn:admin1_code":"WV",
    "gn:admin2_code":"39",
    "gn:asciiname":"Kelly Hill",
    "gn:country_code":"US",
    "gn:dem":200,
    "gn:elevation":"189.0",
    "gn:feature_class":"P",
    "gn:feature_code":"PPL",
    "gn:name":"Kelly Hill",
    "gn:population":0,
    "gn:timezone":"America/New_York",
    "iso:country":"US",
    "name:ceb_x_preferred":[
        "Kelly Hill"
    ],
    "wof:name":"Kelly Hill",
    "wof:placetype":"locality"
},
  "geometry": {"coordinates":[-81.36345,38.48315],"type":"Point"}
}