{
  "type": "Feature",
  "properties": {
    "iso:country":"US",
    "name:eng_x_preferred":[
        "Belle Heth"
    ],
    "wof:name":"Belle Heth",
    "wof:placetype":"neighbourhood",
    "wof:population":1165,
    "zs:area_m":2193162.676891,
    "zs:blockids":[
        517500101012014,
        517500101012017,
        517500101013018,
        517500101013010,
        517500101013000,
        517500101013012,
        517500101012022,
        517500101012019,
        517500101013002,
        517500101012021,
        517500101012020,
        517500101012015,
        517500101012011,
        517500101012018,
        517500101013003,
        517500101013013,
        517500101013008,
        517500101013016
    ],
    "zs:housing10":650,
    "zs:label":"Belle Heth",
    "zs:pop10":1165
},
  "geometry": {"coordinates":[-80.546244,37.123318],"type":"Point"}
}