{
  "type": "Feature",
  "properties": {
    "gn:elevation":232,
    "iso:country":"US",
    "name:arz_x_preferred":[
        "\u0645\u0637\u0627\u0631 \u0645\u0643\u0627\u0644\u064a\u0633\u062a\u0631 \u0627\u0644\u0627\u0642\u0644\u064a\u0645\u0649"
    ],
    "name:ceb_x_preferred":[
        "Mc Alester Regional Airport"
    ],
    "name:eng_x_preferred":[
        "Mcalester Regional Airport"
    ],
    "name:eng_x_variant":[
        "MLC",
        "KMLC",
        "McAlester Regional Airport"
    ],
    "name:fas_x_preferred":[
        "\u0641\u0631\u0648\u062f\u06af\u0627\u0647 \u0645\u0646\u0637\u0642\u0647\u200c\u0627\u06cc \u0645\u06a9\u0644\u06cc\u0633\u062a\u0631"
    ],
    "name:jpn_x_preferred":[
        "McAlester\u5730\u57df\u7a7a\u6e2f"
    ],
    "name:ron_x_preferred":[
        "Aeroportul Regional McAlester"
    ],
    "name:tgk_x_preferred":[
        "\u0424\u0443\u0440\u0443\u0434\u0433\u043e\u04b3\u0438 \u043c\u0430\u043d\u0442\u0430\u049b\u0430\u200c\u0438\u0439 \u043c\u043a\u043b\u0438\u0441\u0442\u0440"
    ],
    "name:urd_x_preferred":[
        "\u0645\u06a9\u0627\u06cc\u0644\u06cc\u0633\u0679\u0631 \u0631\u06cc\u062c\u0646\u0644 \u06c1\u0648\u0627\u0626\u06cc \u0627\u0688\u0627"
    ],
    "oa:elevation_ft":"770",
    "oa:type":"medium_airport",
    "wd:wordcount":199,
    "woe:hierarchy":{
        "country_id":23424977,
        "county_id":12589675,
        "planet_id":1,
        "state_id":2347595
    },
    "wof:name":"Mcalester Regional Airport",
    "wof:placetype":"campus"
},
  "geometry": {"coordinates":[-95.783333,34.8825],"type":"Point"}
}