{
  "type": "Feature",
  "properties": {
    "iso:country":"US",
    "name:eng_x_preferred":[
        "Talaya Hill"
    ],
    "name:eng_x_variant":[
        "Talaya Hl"
    ],
    "qs:gn_adm0_cc":"US",
    "qs:gn_local":5490263,
    "qs:gn_nam_loc":"Santa Fe, Santa Fe, New Mexico, US",
    "qs:gn_namadm1":"NM",
    "qs:local_max":8972,
    "qs:local_sum":19509,
    "qs:localhoods":43,
    "qs:name":"Talaya Hill",
    "qs:name_adm0":"United States",
    "qs:name_adm1":"New Mexico",
    "qs:name_adm2":"Santa Fe",
    "qs:name_local":"Santa Fe",
    "qs:photo_max":29,
    "qs:photo_sum":46,
    "qs:placetype":"Suburb",
    "qs:quad_count":8,
    "qs:woe_adm0":23424977,
    "qs:woe_adm1":2347590,
    "qs:woe_adm2":12589305,
    "qs:woe_lau":0,
    "qs:woe_local":2488867,
    "qs:woe_ver":"7.10.0",
    "wof:lang":[
        "eng"
    ],
    "wof:name":"Talaya Hill",
    "wof:placetype":"neighbourhood",
    "wof:population":7,
    "zs:blockids":[
        350490104001025,
        350490104001024
    ],
    "zs:housing10":4,
    "zs:pop10":7
},
  "geometry": {"coordinates":[-105.894121,35.667028],"type":"Point"}
}