{
  "type": "Feature",
  "properties": {
    "gn:admin1_code":"MD",
    "gn:admin2_code":"9.0",
    "gn:asciiname":"Chesapeake Cove Estates",
    "gn:country_code":"US",
    "gn:dem":40,
    "gn:elevation":"33.0",
    "gn:feature_class":"P",
    "gn:feature_code":"PPL",
    "gn:name":"Chesapeake Cove Estates",
    "gn:population":0,
    "gn:timezone":"America/New_York",
    "iso:country":"US",
    "wof:name":"Chesapeake Cove Estates",
    "wof:placetype":"locality"
},
  "geometry": {"coordinates":[-76.41551,38.37679],"type":"Point"}
}