{
  "type": "Feature",
  "properties": {
    "gn:admin1_code":"TN",
    "gn:admin2_code":"149.0",
    "gn:asciiname":"Ridgefield",
    "gn:country_code":"US",
    "gn:dem":177,
    "gn:elevation":"177.0",
    "gn:feature_class":"P",
    "gn:feature_code":"PPL",
    "gn:name":"Ridgefield",
    "gn:population":0,
    "gn:timezone":"America/Chicago",
    "iso:country":"US",
    "name:cat_x_preferred":[
        "Ridgefield"
    ],
    "name:ceb_x_preferred":[
        "Ridgefield"
    ],
    "name:deu_x_preferred":[
        "Ridgefield"
    ],
    "name:fra_x_preferred":[
        "Ridgefield"
    ],
    "name:ita_x_preferred":[
        "Ridgefield"
    ],
    "name:nld_x_preferred":[
        "Ridgefield"
    ],
    "name:pol_x_preferred":[
        "Ridgefield"
    ],
    "name:por_x_preferred":[
        "Ridgefield"
    ],
    "name:rus_x_preferred":[
        "\u0420\u0438\u0434\u0436\u0444\u0438\u043b\u0434"
    ],
    "name:srp_x_preferred":[
        "\u0420\u0438\u045f\u0444\u0438\u043b\u0434"
    ],
    "name:szl_x_preferred":[
        "Ridgefield"
    ],
    "name:vol_x_preferred":[
        "Ridgefield"
    ],
    "wof:name":"Ridgefield",
    "wof:placetype":"locality"
},
  "geometry": {"coordinates":[-86.41970999999999,35.91673],"type":"Point"}
}