{
  "type": "Feature",
  "properties": {
    "iso:country":"US",
    "name:eng_x_preferred":[
        "Northtowne"
    ],
    "qs:gn_adm0_cc":"US",
    "qs:gn_local":5786882,
    "qs:gn_nam_loc":"Bellevue, King, Washington, US",
    "qs:gn_namadm1":"WA",
    "qs:local_max":5360,
    "qs:local_sum":48946,
    "qs:localhoods":55,
    "qs:name":"Northtowne",
    "qs:name_adm0":"United States",
    "qs:name_adm1":"Washington",
    "qs:name_adm2":"King",
    "qs:name_local":"Bellevue",
    "qs:photo_max":102,
    "qs:photo_sum":119,
    "qs:placetype":"Suburb",
    "qs:quad_count":3,
    "qs:woe_adm0":23424977,
    "qs:woe_adm1":2347606,
    "qs:woe_adm2":12590456,
    "qs:woe_lau":0,
    "qs:woe_local":2362031,
    "qs:woe_ver":"7.10.0",
    "wof:lang":[
        "eng"
    ],
    "wof:name":"Northtowne",
    "wof:placetype":"neighbourhood"
},
  "geometry": {"coordinates":[-122.206076,47.63199],"type":"Point"}
}