{
  "type": "Feature",
  "properties": {
    "gn:admin1_code":"GA",
    "gn:admin2_code":"45.0",
    "gn:asciiname":"Colonial Estates",
    "gn:country_code":"US",
    "gn:dem":319,
    "gn:elevation":"312.0",
    "gn:feature_class":"P",
    "gn:feature_code":"PPL",
    "gn:name":"Colonial Estates",
    "gn:population":0,
    "gn:timezone":"America/New_York",
    "iso:country":"US",
    "wof:name":"Colonial Estates",
    "wof:placetype":"locality"
},
  "geometry": {"coordinates":[-85.11717,33.55011],"type":"Point"}
}