{
  "type": "Feature",
  "properties": {
    "gn:admin1_code":"WA",
    "gn:admin2_code":"71.0",
    "gn:asciiname":"Lowden",
    "gn:country_code":"US",
    "gn:dem":148,
    "gn:elevation":"150.0",
    "gn:feature_class":"P",
    "gn:feature_code":"PPL",
    "gn:name":"Lowden",
    "gn:population":0,
    "gn:timezone":"America/Los_Angeles",
    "iso:country":"US",
    "name:spa_x_preferred":[
        "Lowden"
    ],
    "wof:name":"Lowden",
    "wof:placetype":"locality"
},
  "geometry": {"coordinates":[-118.58581,46.05625],"type":"Point"}
}