{
  "type": "Feature",
  "properties": {
    "gn:country":"US",
    "gn:fcode":"PPL",
    "gn:population":0,
    "iso:country":"US",
    "name:cym_x_preferred":[
        "Napier Township"
    ],
    "name:deu_x_preferred":[
        "Napier Township"
    ],
    "name:eng_x_preferred":[
        "Napier Township"
    ],
    "name:fra_x_preferred":[
        "Napier Township"
    ],
    "name:ita_x_preferred":[
        "Napier"
    ],
    "name:nld_x_preferred":[
        "Napier Township"
    ],
    "name:spa_x_preferred":[
        "Municipio de Napier"
    ],
    "name:ukr_x_preferred":[
        "\u041d\u0435\u043f\u0435\u0440 \u0422\u0430\u0443\u043d\u0448\u0438\u043f"
    ],
    "name:vie_x_preferred":[
        "Napier"
    ],
    "name:vie_x_variant":[
        "X\u00e3 Napier"
    ],
    "qs_pg:aaroncc":"US",
    "qs_pg:gn_country":"US",
    "qs_pg:gn_fcode":"PPL",
    "qs_pg:gn_pop":0,
    "qs_pg:name":"Napier",
    "qs_pg:name_adm0":"United States",
    "qs_pg:name_adm1":"Pennsylvania",
    "qs_pg:photos":40,
    "qs_pg:photos_1k":8,
    "qs_pg:photos_9k":1,
    "qs_pg:photos_9r":2,
    "qs_pg:photos_all":54,
    "qs_pg:photos_sr":2,
    "qs_pg:pop_sr":0,
    "qs_pg:qs_pg_placetype":"locality",
    "qs_pg:qs_pg_placetype_gp":"Town",
    "qs_pg:woe_adm0":23424977,
    "woe:adm0_id":23424977,
    "woe:name_adm0":"United States",
    "woe:name_adm1":"Pennsylvania",
    "woe:placetype":"Town",
    "wof:name":"Napier",
    "wof:placetype":"locality"
},
  "geometry": {"coordinates":[-78.55835,40.03702],"type":"Point"}
}