{
  "type": "Feature",
  "properties": {
    "gn:admin1_code":"AR",
    "gn:admin2_code":"41.0",
    "gn:admin3_code":"93063.0",
    "gn:asciiname":"Pendleton",
    "gn:country_code":"US",
    "gn:dem":55,
    "gn:elevation":"52.0",
    "gn:feature_class":"P",
    "gn:feature_code":"PPL",
    "gn:name":"Pendleton",
    "gn:population":0,
    "gn:timezone":"America/Chicago",
    "iso:country":"US",
    "name:ceb_x_preferred":[
        "Pendleton"
    ],
    "name:deu_x_preferred":[
        "Pendleton"
    ],
    "name:fas_x_preferred":[
        "\u067e\u0646\u062f\u0644\u062a\u0646"
    ],
    "name:fra_x_preferred":[
        "Pendleton"
    ],
    "name:ita_x_preferred":[
        "Pendleton"
    ],
    "name:jpn_x_preferred":[
        "\u30da\u30f3\u30c7\u30eb\u30c8\u30f3"
    ],
    "name:nld_x_preferred":[
        "Pendleton"
    ],
    "name:pol_x_preferred":[
        "Pendleton"
    ],
    "name:por_x_preferred":[
        "Pendleton"
    ],
    "name:rus_x_preferred":[
        "\u041f\u0435\u043d\u0434\u043b\u0442\u043e\u043d"
    ],
    "name:srp_x_preferred":[
        "\u041f\u0435\u043d\u0434\u043b\u0442\u043e\u043d"
    ],
    "name:swe_x_preferred":[
        "Pendleton"
    ],
    "name:ukr_x_preferred":[
        "\u041f\u0435\u043d\u0434\u043b\u0442\u043e\u043d"
    ],
    "name:vol_x_preferred":[
        "Pendleton"
    ],
    "wof:name":"Pendleton",
    "wof:placetype":"locality"
},
  "geometry": {"coordinates":[-91.38206,33.97732],"type":"Point"}
}