{
  "type": "Feature",
  "properties": {
    "gn:admin1_code":"IL",
    "gn:admin2_code":"75.0",
    "gn:admin3_code":"61665.0",
    "gn:asciiname":"Hallock",
    "gn:country_code":"US",
    "gn:dem":223,
    "gn:elevation":"223.0",
    "gn:feature_class":"P",
    "gn:feature_code":"PPL",
    "gn:name":"Hallock",
    "gn:population":0,
    "gn:timezone":"America/Chicago",
    "iso:country":"US",
    "name:deu_x_preferred":[
        "Hallock"
    ],
    "name:epo_x_preferred":[
        "Hallock"
    ],
    "name:pol_x_preferred":[
        "Hallock"
    ],
    "name:rus_x_preferred":[
        "\u0425\u0430\u043b\u043b\u043e\u043a"
    ],
    "name:swe_x_preferred":[
        "Hallock"
    ],
    "wof:name":"Hallock",
    "wof:placetype":"locality"
},
  "geometry": {"coordinates":[-87.59614000000001,40.56143],"type":"Point"}
}