{
  "type": "Feature",
  "properties": {
    "gn:admin1_code":"OH",
    "gn:admin2_code":"29.0",
    "gn:admin3_code":"28238.0",
    "gn:asciiname":"Five Forks",
    "gn:country_code":"US",
    "gn:dem":362,
    "gn:elevation":"363.0",
    "gn:feature_class":"P",
    "gn:feature_code":"PPL",
    "gn:name":"Five Forks",
    "gn:population":0,
    "gn:timezone":"America/New_York",
    "iso:country":"US",
    "name:deu_x_preferred":[
        "Five Forks"
    ],
    "wof:name":"Five Forks",
    "wof:placetype":"locality"
},
  "geometry": {"coordinates":[-80.90980999999999,40.66284],"type":"Point"}
}