{
  "type": "Feature",
  "properties": {
    "gn:gn_country":"US",
    "gn:gn_fcode":"PPLX",
    "gn:gn_pop":0,
    "iso:country":"US",
    "name:aze_x_preferred":[
        "Miras"
    ],
    "name:deu_x_preferred":[
        "Heritage"
    ],
    "name:fas_x_preferred":[
        "\u0645\u06cc\u0631\u0627\u062b"
    ],
    "name:hrv_x_preferred":[
        "Ba\u0161tina"
    ],
    "name:kor_x_preferred":[
        "\ud5e4\ub9ac\ud2f0\uc9c0"
    ],
    "name:nld_x_preferred":[
        "Heritage"
    ],
    "name:por_x_preferred":[
        "Heritage"
    ],
    "name:rus_x_preferred":[
        "\u0425\u0435\u0440\u0438\u0442\u0435\u0439\u0434\u0436"
    ],
    "name:ukr_x_preferred":[
        "\u0421\u043f\u0430\u0434\u0449\u0438\u043d\u0430"
    ],
    "qs_pg:aaroncc":"US",
    "qs_pg:gn_country":"US",
    "qs_pg:gn_fcode":"PPLX",
    "qs_pg:gn_pop":0,
    "qs_pg:name":"Heritage",
    "qs_pg:name_adm0":"United States",
    "qs_pg:name_adm1":"Virginia",
    "qs_pg:photos":126,
    "qs_pg:photos_1k":26,
    "qs_pg:photos_9k":1,
    "qs_pg:photos_9r":3,
    "qs_pg:photos_all":126,
    "qs_pg:photos_sr":3,
    "qs_pg:pop_sr":0,
    "qs_pg:qs_pg_placetype":"neighbourhood",
    "qs_pg:qs_pg_placetype_gp":"Suburb",
    "qs_pg:woe_adm0":23424977,
    "woe:adm0_id":23424977,
    "woe:name_adm0":"United States",
    "woe:name_adm1":"Virginia",
    "woe:placetype":"Suburb",
    "wof:name":"Heritage",
    "wof:placetype":"neighbourhood"
},
  "geometry": {"coordinates":[-78.15694000000001,38.90817],"type":"Point"}
}