{
  "type": "Feature",
  "properties": {
    "gn:elevation":24,
    "iso:country":"US",
    "name:eng_x_preferred":[
        "Nonatum Mills"
    ],
    "name:eng_x_variant":[
        "Nonatum Mls"
    ],
    "qs:gn_adm0_cc":"US",
    "qs:gn_fcode":"PPL",
    "qs:gn_local":4143861,
    "qs:gn_nam_loc":"newark",
    "qs:gn_namadm1":"DE",
    "qs:gn_name":"Nonatum Mills",
    "qs:local_max":1158,
    "qs:local_sum":4935,
    "qs:localhoods":11,
    "qs:name":"Nonatum Mills",
    "qs:name_adm0":"United States",
    "qs:name_adm1":"Delaware",
    "qs:name_adm2":"New Castle",
    "qs:name_local":"Newark",
    "qs:photo_max":223,
    "qs:photo_sum":994,
    "qs:placetype":"Suburb",
    "qs:quad_count":25,
    "qs:woe_adm0":23424977,
    "qs:woe_adm1":2347566,
    "qs:woe_adm2":12587800,
    "qs:woe_lau":0,
    "qs:woe_local":2459271,
    "qs:woe_ver":"7.10.0",
    "wof:name":"Nonatum Mills",
    "wof:placetype":"neighbourhood",
    "wof:population":9173,
    "zs:blockids":[
        100030136103006,
        100030136102009,
        100030143003015,
        100030136102016,
        100030143003013,
        100030145011017,
        100030136103024,
        100030136102008,
        100030143002018,
        100030145011006,
        100030136103018,
        100030136103004,
        100030145011002,
        100030143002017,
        100030145011005,
        100030136104007,
        100030136104009,
        100030136103009,
        100030136102013,
        100030145022001,
        100030145011004,
        100030136102014,
        100030136101023,
        100030143002013,
        100030143002005,
        100030145011018,
        100030136101021,
        100030136103014,
        100030136101022,
        100030136102011,
        100030136103025,
        100030143002010,
        100030143003024,
        100030136103017,
        100030145022004,
        100030136103023,
        100030143003018,
        100030136102018,
        100030136102015,
        100030136103005,
        100030143002004,
        100030143003014,
        100030143003016,
        100030143003020,
        100030136103016,
        100030136104001,
        100030136104006,
        100030136102012,
        100030145022002,
        100030136103007,
        100030143002016,
        100030143003017,
        100030145011003,
        100030143003019,
        100030136102017,
        100030143003025,
        100030145022003,
        100030136103015,
        100030136101024,
        100030143002007,
        100030143003009,
        100030136101025,
        100030143003023,
        100030145011007,
        100030136104000,
        100030136104008,
        100030136104010,
        100030136102007,
        100030145011019,
        100030143003022,
        100030143002006,
        100030136103008
    ],
    "zs:housing10":2292,
    "zs:pop10":9173
},
  "geometry": {"coordinates":[-75.753181,39.684773],"type":"Point"}
}