{
  "type": "Feature",
  "properties": {
    "gn:country":"US",
    "gn:elevation":111,
    "gn:fcode":"PPL",
    "gn:population":0,
    "iso:country":"US",
    "name:azb_x_preferred":[
        "\u0644\u0648\u06cc\u0646\u0632\u0648\u06cc\u0644"
    ],
    "name:eng_x_preferred":[
        "Lewinsville"
    ],
    "name:fas_x_preferred":[
        "\u0644\u0648\u06cc\u0646\u0632\u0648\u06cc\u0644"
    ],
    "name:fra_x_preferred":[
        "Lewinsville"
    ],
    "name:hun_x_preferred":[
        "Lewinsville"
    ],
    "name:tur_x_preferred":[
        "Lewinsville"
    ],
    "name:und_x_variant":[
        "Lewisville"
    ],
    "name:vol_x_preferred":[
        "Lewinsville"
    ],
    "qs_pg:aaroncc":"US",
    "qs_pg:gn_country":"US",
    "qs_pg:gn_fcode":"PPL",
    "qs_pg:gn_pop":0,
    "qs_pg:name":"Lewinsville",
    "qs_pg:name_adm0":"United States",
    "qs_pg:name_adm1":"Virginia",
    "qs_pg:photos":2417,
    "qs_pg:photos_1k":490,
    "qs_pg:photos_9k":11,
    "qs_pg:photos_9r":10,
    "qs_pg:photos_all":2417,
    "qs_pg:photos_sr":17,
    "qs_pg:pop_sr":0,
    "qs_pg:qs_pg_placetype":"neighbourhood",
    "qs_pg:qs_pg_placetype_gp":"Suburb",
    "qs_pg:woe_adm0":23424977,
    "woe:adm0_id":23424977,
    "woe:name_adm0":"United States",
    "woe:name_adm1":"Virginia",
    "woe:placetype":"Suburb",
    "wof:name":"Lewinsville",
    "wof:placetype":"neighbourhood",
    "wof:population":9078
},
  "geometry": {"coordinates":[-77.19776,38.929],"type":"Point"}
}