{
  "type": "Feature",
  "properties": {
    "gn:admin1_code":"TN",
    "gn:admin2_code":"27.0",
    "gn:asciiname":"Clementsville",
    "gn:country_code":"US",
    "gn:dem":239,
    "gn:elevation":"240.0",
    "gn:feature_class":"P",
    "gn:feature_code":"PPL",
    "gn:name":"Clementsville",
    "gn:population":0,
    "gn:timezone":"America/Chicago",
    "iso:country":"US",
    "name:deu_x_preferred":[
        "Clementsville"
    ],
    "name:eng_x_preferred":[
        "Clementsville"
    ],
    "name:und_x_variant":[
        "McLeansville"
    ],
    "wof:name":"Clementsville",
    "wof:placetype":"locality"
},
  "geometry": {"coordinates":[-85.72581,36.61172],"type":"Point"}
}