{
  "type": "Feature",
  "properties": {
    "gn:admin1_code":"OH",
    "gn:admin2_code":"73",
    "gn:admin3_code":"42056.0",
    "gn:asciiname":"Gibisonville",
    "gn:country_code":"US",
    "gn:dem":334,
    "gn:elevation":"336.0",
    "gn:feature_class":"P",
    "gn:feature_code":"PPL",
    "gn:name":"Gibisonville",
    "gn:population":0,
    "gn:timezone":"America/New_York",
    "iso:country":"US",
    "name:azb_x_preferred":[
        "\u0642\u06cc\u0628\u0633\u0648\u0646\u0648\u06cc\u0644"
    ],
    "name:eng_x_preferred":[
        "Gibisonville"
    ],
    "name:fas_x_preferred":[
        "\u06af\u06cc\u0628\u0633\u0648\u0646\u0648\u06cc\u0644"
    ],
    "name:und_x_variant":[
        "Gibesonville"
    ],
    "wof:name":"Gibisonville",
    "wof:placetype":"locality"
},
  "geometry": {"coordinates":[-82.56655000000001,39.49979],"type":"Point"}
}