{
  "type": "Feature",
  "properties": {
    "gn:admin1_code":"FL",
    "gn:admin2_code":"21.0",
    "gn:asciiname":"Rock Island",
    "gn:country_code":"US",
    "gn:dem":10,
    "gn:elevation":"3.0",
    "gn:feature_class":"P",
    "gn:feature_code":"PPL",
    "gn:name":"Rock Island",
    "gn:population":0,
    "gn:timezone":"America/New_York",
    "iso:country":"US",
    "name:ceb_x_preferred":[
        "Rock Island"
    ],
    "name:ces_x_preferred":[
        "Rock Island"
    ],
    "name:deu_x_preferred":[
        "Rock Island"
    ],
    "name:fra_x_preferred":[
        "Rock Island"
    ],
    "name:ita_x_preferred":[
        "Rock Island"
    ],
    "name:nld_x_preferred":[
        "Rock Island"
    ],
    "name:pol_x_preferred":[
        "Rock Island"
    ],
    "name:por_x_preferred":[
        "Rock Island"
    ],
    "name:rus_x_preferred":[
        "\u0420\u043e\u043a-\u0410\u0439\u043b\u0435\u043d\u0434"
    ],
    "name:spa_x_preferred":[
        "Rock Island"
    ],
    "name:srp_x_preferred":[
        "\u0420\u043e\u043a \u0410\u0458\u043b\u0430\u043d\u0434"
    ],
    "name:swe_x_preferred":[
        "Rock Island"
    ],
    "name:vol_x_preferred":[
        "Rock Island"
    ],
    "wof:name":"Rock Island",
    "wof:placetype":"locality"
},
  "geometry": {"coordinates":[-81.34424,26.11259],"type":"Point"}
}