{
  "type": "Feature",
  "properties": {
    "gn:admin1_code":"FL",
    "gn:admin2_code":"21.0",
    "gn:asciiname":"Rock Island",
    "gn:country_code":"US",
    "gn:dem":10,
    "gn:elevation":"3.0",
    "gn:feature_class":"P",
    "gn:feature_code":"PPL",
    "gn:name":"Rock Island",
    "gn:population":0,
    "gn:timezone":"America/New_York",
    "iso:country":"US",
    "name:ben_x_preferred":[
        "\u09b0\u0995 \u0986\u0987\u09b2\u09cd\u09af\u09be\u09a8\u09cd\u09a1"
    ],
    "name:ceb_x_preferred":[
        "Rock Island"
    ],
    "name:ces_x_preferred":[
        "Rock Island"
    ],
    "name:deu_x_preferred":[
        "Rock Island"
    ],
    "name:ell_x_preferred":[
        "\u03a1\u03bf\u03ba \u0386\u03b9\u03bb\u03b1\u03bd\u03c4"
    ],
    "name:fra_x_preferred":[
        "Rock Island"
    ],
    "name:hin_x_preferred":[
        "\u0930\u0949\u0915 \u0906\u0907\u0932\u0948\u0902\u0921"
    ],
    "name:ita_x_preferred":[
        "Rock Island"
    ],
    "name:kor_x_preferred":[
        "\ub85d \uc544\uc77c\ub79c\ub4dc"
    ],
    "name:nld_x_preferred":[
        "Rock Island"
    ],
    "name:pol_x_preferred":[
        "Rock Island"
    ],
    "name:por_x_preferred":[
        "Rock Island"
    ],
    "name:rus_x_preferred":[
        "\u0420\u043e\u043a-\u0410\u0439\u043b\u0435\u043d\u0434"
    ],
    "name:spa_x_preferred":[
        "Rock Island"
    ],
    "name:srp_x_preferred":[
        "\u0420\u043e\u043a \u0410\u0458\u043b\u0430\u043d\u0434"
    ],
    "name:swe_x_preferred":[
        "Rock Island"
    ],
    "name:vol_x_preferred":[
        "Rock Island"
    ],
    "wof:name":"Rock Island",
    "wof:placetype":"locality"
},
  "geometry": {"coordinates":[-81.34424,26.11259],"type":"Point"}
}