{
  "type": "Feature",
  "properties": {
    "gn:admin1_code":"TN",
    "gn:admin2_code":"123",
    "gn:asciiname":"Howard",
    "gn:country_code":"US",
    "gn:dem":275,
    "gn:elevation":"268.0",
    "gn:feature_class":"P",
    "gn:feature_code":"PPL",
    "gn:name":"Howard",
    "gn:population":0,
    "gn:timezone":"America/New_York",
    "iso:country":"US",
    "name:ara_x_preferred":[
        "\u0647\u0648\u0627\u0631\u062f"
    ],
    "name:ita_x_preferred":[
        "Howard"
    ],
    "wof:name":"Howard",
    "wof:placetype":"locality"
},
  "geometry": {"coordinates":[-84.15825,35.55090999999999],"type":"Point"}
}