{
  "type": "Feature",
  "properties": {
    "gn:country":"US",
    "gn:fcode":"PPL",
    "gn:population":0,
    "iso:country":"US",
    "name:cat_x_preferred":[
        "White Hall"
    ],
    "name:ceb_x_preferred":[
        "White Hall"
    ],
    "name:deu_x_preferred":[
        "White Hall"
    ],
    "name:eng_x_preferred":[
        "White Hall"
    ],
    "name:fra_x_preferred":[
        "White Hall"
    ],
    "name:ita_x_preferred":[
        "White Hall"
    ],
    "name:nld_x_preferred":[
        "White Hall"
    ],
    "name:pol_x_preferred":[
        "White Hall"
    ],
    "name:por_x_preferred":[
        "White Hall"
    ],
    "name:srp_x_preferred":[
        "\u0412\u0430\u0458\u0442 \u0425\u043e\u043b"
    ],
    "name:und_x_variant":[
        "Whitehall"
    ],
    "name:vol_x_preferred":[
        "White Hall"
    ],
    "qs_pg:aaroncc":"US",
    "qs_pg:gn_country":"US",
    "qs_pg:gn_fcode":"PPL",
    "qs_pg:gn_pop":0,
    "qs_pg:name":"White Hall",
    "qs_pg:name_adm0":"United States",
    "qs_pg:name_adm1":"Maryland",
    "qs_pg:photos":163,
    "qs_pg:photos_1k":33,
    "qs_pg:photos_9k":1,
    "qs_pg:photos_9r":4,
    "qs_pg:photos_all":163,
    "qs_pg:photos_sr":4,
    "qs_pg:pop_sr":5,
    "qs_pg:qs_pg_placetype":"locality",
    "qs_pg:qs_pg_placetype_gp":"Town",
    "qs_pg:woe_adm0":23424977,
    "woe:adm0_id":23424977,
    "woe:name_adm0":"United States",
    "woe:name_adm1":"Maryland",
    "woe:placetype":"Town",
    "wof:name":"White Hall",
    "wof:placetype":"locality"
},
  "geometry": {"coordinates":[-76.62858,39.62177],"type":"Point"}
}