{
  "type": "Feature",
  "properties": {
    "gn:admin1_code":"LA",
    "gn:admin2_code":"73.0",
    "gn:asciiname":"Eastwood Estates",
    "gn:country_code":"US",
    "gn:dem":31,
    "gn:elevation":"25.0",
    "gn:feature_class":"P",
    "gn:feature_code":"PPL",
    "gn:name":"Eastwood Estates",
    "gn:population":0,
    "gn:timezone":"America/Chicago",
    "iso:country":"US",
    "wof:name":"Eastwood Estates",
    "wof:placetype":"locality"
},
  "geometry": {"coordinates":[-91.99818999999999,32.54598],"type":"Point"}
}