{
  "type": "Feature",
  "properties": {
    "gn:admin1_code":"LA",
    "gn:admin2_code":"81.0",
    "gn:asciiname":"Redoak",
    "gn:country_code":"US",
    "gn:dem":58,
    "gn:elevation":"50.0",
    "gn:feature_class":"P",
    "gn:feature_code":"PPL",
    "gn:name":"Redoak",
    "gn:population":0,
    "gn:timezone":"America/Chicago",
    "iso:country":"US",
    "name:fas_x_preferred":[
        "\u0631\u062f\u0627\u0631\u06a9"
    ],
    "wof:name":"Redoak",
    "wof:placetype":"locality"
},
  "geometry": {"coordinates":[-93.27239,31.94627],"type":"Point"}
}