{
  "type": "Feature",
  "properties": {
    "gn:admin1_code":"PA",
    "gn:admin2_code":"15.0",
    "gn:admin3_code":"11168.0",
    "gn:asciiname":"Cedar Ledge",
    "gn:country_code":"US",
    "gn:dem":366,
    "gn:elevation":"364.0",
    "gn:feature_class":"P",
    "gn:feature_code":"PPL",
    "gn:name":"Cedar Ledge",
    "gn:population":0,
    "gn:timezone":"America/New_York",
    "iso:country":"US",
    "wof:name":"Cedar Ledge",
    "wof:placetype":"locality"
},
  "geometry": {"coordinates":[-76.87052,41.63952000000001],"type":"Point"}
}