{
  "type": "Feature",
  "properties": {
    "iso:country":"US",
    "name:cat_x_preferred":[
        "Mount Hope"
    ],
    "name:ceb_x_preferred":[
        "Mount Hope"
    ],
    "name:deu_x_preferred":[
        "Mount Hope"
    ],
    "name:eng_x_preferred":[
        "Mount Hope"
    ],
    "name:fra_x_preferred":[
        "Mont Hope"
    ],
    "name:ita_x_preferred":[
        "Mount Hope"
    ],
    "name:jpn_x_preferred":[
        "\u30de\u30a6\u30f3\u30c8\u30fb\u30db\u30fc\u30d7"
    ],
    "name:nds_x_preferred":[
        "Mount Hope"
    ],
    "name:nld_x_preferred":[
        "Mount Hope"
    ],
    "name:pol_x_preferred":[
        "Mount Hope"
    ],
    "name:por_x_preferred":[
        "Mount Hope"
    ],
    "name:srp_x_preferred":[
        "\u041c\u0430\u0443\u043d\u0442 \u0425\u043e\u0443\u043f"
    ],
    "name:swe_x_preferred":[
        "Mount Hope"
    ],
    "name:ukr_x_preferred":[
        "\u041c\u0430\u0443\u043d\u0442-\u0413\u043e\u0443\u043f"
    ],
    "name:vol_x_preferred":[
        "Mount Hope"
    ],
    "wd:wordcount":476,
    "wof:name":"Mount Hope",
    "wof:placetype":"neighbourhood",
    "wof:population":68,
    "zs:area_m":33071914.461165,
    "zs:blockids":[
        361150810003002
    ],
    "zs:housing10":32,
    "zs:label":"Mount Hope",
    "zs:pop10":68
},
  "geometry": {"coordinates":[-73.477524,43.477235],"type":"Point"}
}