{
  "type": "Feature",
  "properties": {
    "gn:admin1_code":"TX",
    "gn:admin2_code":"77.0",
    "gn:asciiname":"Vashti",
    "gn:country_code":"US",
    "gn:dem":333,
    "gn:elevation":"330.0",
    "gn:feature_class":"P",
    "gn:feature_code":"PPL",
    "gn:name":"Vashti",
    "gn:population":0,
    "gn:timezone":"America/Chicago",
    "iso:country":"US",
    "name:vol_x_preferred":[
        "Vashti"
    ],
    "wof:name":"Vashti",
    "wof:placetype":"locality"
},
  "geometry": {"coordinates":[-98.04087,33.55566],"type":"Point"}
}