{
  "type": "Feature",
  "properties": {
    "gn:country":"US",
    "gn:fcode":"PPL",
    "gn:population":0,
    "iso:country":"US",
    "name:ceb_x_preferred":[
        "Cherry Hill"
    ],
    "name:deu_x_preferred":[
        "Cherry Hill"
    ],
    "name:pol_x_preferred":[
        "Cherry Hill"
    ],
    "name:swe_x_preferred":[
        "Cherry Hill"
    ],
    "name:ukr_x_preferred":[
        "\u0427\u0435\u0440\u0440\u0456-\u0413\u0456\u043b\u043b"
    ],
    "qs_pg:aaroncc":"US",
    "qs_pg:gn_country":"US",
    "qs_pg:gn_fcode":"PPL",
    "qs_pg:gn_pop":0,
    "qs_pg:name":"Cherry Hill",
    "qs_pg:name_adm0":"United States",
    "qs_pg:name_adm1":"Maryland",
    "qs_pg:photos":7,
    "qs_pg:photos_1k":1,
    "qs_pg:photos_9k":1,
    "qs_pg:photos_9r":1,
    "qs_pg:photos_all":7,
    "qs_pg:photos_sr":1,
    "qs_pg:pop_sr":0,
    "qs_pg:qs_pg_placetype":"locality",
    "qs_pg:qs_pg_placetype_gp":"Town",
    "qs_pg:woe_adm0":23424977,
    "woe:adm0_id":23424977,
    "woe:name_adm0":"United States",
    "woe:name_adm1":"Maryland",
    "woe:placetype":"Town",
    "wof:name":"Cherry Hill",
    "wof:placetype":"locality"
},
  "geometry": {"coordinates":[-76.43356,38.35457],"type":"Point"}
}