{
  "type": "Feature",
  "properties": {
    "gn:admin1_code":"OH",
    "gn:admin2_code":"155.0",
    "gn:admin3_code":"80892.0",
    "gn:asciiname":"Country Club Estates",
    "gn:country_code":"US",
    "gn:dem":285,
    "gn:feature_class":"P",
    "gn:feature_code":"PPL",
    "gn:name":"Country Club Estates",
    "gn:population":0,
    "gn:timezone":"America/New_York",
    "iso:country":"US",
    "wof:name":"Country Club Estates",
    "wof:placetype":"locality"
},
  "geometry": {"coordinates":[-80.77363000000003,41.23354000000001],"type":"Point"}
}