{
  "type": "Feature",
  "properties": {
    "gn:admin1_code":"SC",
    "gn:admin2_code":"79.0",
    "gn:asciiname":"Northgate",
    "gn:country_code":"US",
    "gn:dem":79,
    "gn:elevation":"80.0",
    "gn:feature_class":"P",
    "gn:feature_code":"PPL",
    "gn:name":"Northgate",
    "gn:population":0,
    "gn:timezone":"America/New_York",
    "iso:country":"US",
    "name:deu_x_preferred":[
        "Northgate"
    ],
    "name:fra_x_preferred":[
        "Northgate"
    ],
    "name:pol_x_preferred":[
        "Northgate"
    ],
    "wof:name":"Northgate",
    "wof:placetype":"locality"
},
  "geometry": {"coordinates":[-81.03036999999998,34.09737],"type":"Point"}
}