{
  "type": "Feature",
  "properties": {
    "gn:admin1_code":"IL",
    "gn:admin2_code":"79",
    "gn:admin3_code":"78357.0",
    "gn:asciiname":"Lis",
    "gn:country_code":"US",
    "gn:dem":169,
    "gn:elevation":"171.0",
    "gn:feature_class":"P",
    "gn:feature_code":"PPL",
    "gn:name":"Lis",
    "gn:population":0,
    "gn:timezone":"America/Chicago",
    "iso:country":"US",
    "wof:name":"Lis",
    "wof:placetype":"locality"
},
  "geometry": {"coordinates":[-88.26031999999999,39.02004],"type":"Point"}
}