{
  "type": "Feature",
  "properties": {
    "gn:admin1_code":"IN",
    "gn:admin2_code":"155.0",
    "gn:admin3_code":"61380.0",
    "gn:asciiname":"Gurley Corner",
    "gn:country_code":"US",
    "gn:dem":265,
    "gn:elevation":"266.0",
    "gn:feature_class":"P",
    "gn:feature_code":"PPL",
    "gn:name":"Gurley Corner",
    "gn:population":0,
    "gn:timezone":"America/Indiana/Vevay",
    "iso:country":"US",
    "wof:name":"Gurley Corner",
    "wof:placetype":"locality"
},
  "geometry": {"coordinates":[-84.85828000000002,38.85923],"type":"Point"}
}