{
  "type": "Feature",
  "properties": {
    "gn:admin1_code":"MS",
    "gn:admin2_code":"103.0",
    "gn:asciiname":"Prairie Point",
    "gn:country_code":"US",
    "gn:dem":60,
    "gn:elevation":"59.0",
    "gn:feature_class":"P",
    "gn:feature_code":"PPL",
    "gn:name":"Prairie Point",
    "gn:population":0,
    "gn:timezone":"America/Chicago",
    "iso:country":"US",
    "name:eng_x_preferred":[
        "Prairie Point"
    ],
    "name:und_x_variant":[
        "Hogeye Community",
        "Hogeye"
    ],
    "wof:name":"Prairie Point",
    "wof:placetype":"locality"
},
  "geometry": {"coordinates":[-88.39364999999999,33.14735],"type":"Point"}
}