{
  "type": "Feature",
  "properties": {
    "gn:admin1_code":"GA",
    "gn:admin2_code":"21",
    "gn:asciiname":"Rivoli Plantation",
    "gn:country_code":"US",
    "gn:dem":170,
    "gn:elevation":"162.0",
    "gn:feature_class":"P",
    "gn:feature_code":"PPL",
    "gn:name":"Rivoli Plantation",
    "gn:population":0,
    "gn:timezone":"America/New_York",
    "iso:country":"US",
    "wof:name":"Rivoli Plantation",
    "wof:placetype":"locality"
},
  "geometry": {"coordinates":[-83.75129,32.90514],"type":"Point"}
}