{
  "type": "Feature",
  "properties": {
    "gn:admin1_code":"SC",
    "gn:admin2_code":"47.0",
    "gn:asciiname":"Parkwood",
    "gn:country_code":"US",
    "gn:dem":186,
    "gn:elevation":"183.0",
    "gn:feature_class":"P",
    "gn:feature_code":"PPL",
    "gn:name":"Parkwood",
    "gn:population":0,
    "gn:timezone":"America/New_York",
    "iso:country":"US",
    "name:ceb_x_preferred":[
        "Parkwood"
    ],
    "name:deu_x_preferred":[
        "Parkwood"
    ],
    "name:fra_x_preferred":[
        "Parkwood"
    ],
    "name:ita_x_preferred":[
        "Parkwood"
    ],
    "name:nld_x_preferred":[
        "Parkwood"
    ],
    "name:srp_x_preferred":[
        "\u041f\u0430\u0440\u043a\u0432\u0443\u0434"
    ],
    "name:vol_x_preferred":[
        "Parkwood"
    ],
    "wof:name":"Parkwood",
    "wof:placetype":"locality"
},
  "geometry": {"coordinates":[-82.12401,34.18123],"type":"Point"}
}