{
  "type": "Feature",
  "properties": {
    "gn:admin1_code":"GA",
    "gn:admin2_code":"135.0",
    "gn:asciiname":"Covered Bridge",
    "gn:country_code":"US",
    "gn:dem":301,
    "gn:elevation":"289.0",
    "gn:feature_class":"P",
    "gn:feature_code":"PPL",
    "gn:name":"Covered Bridge",
    "gn:population":0,
    "gn:timezone":"America/New_York",
    "iso:country":"US",
    "wof:name":"Covered Bridge",
    "wof:placetype":"locality"
},
  "geometry": {"coordinates":[-84.16797,33.95871],"type":"Point"}
}