{
  "type": "Feature",
  "properties": {
    "gn:admin1_code":"DE",
    "gn:admin2_code":"3.0",
    "gn:asciiname":"Drummond North",
    "gn:country_code":"US",
    "gn:dem":57,
    "gn:elevation":"59.0",
    "gn:feature_class":"P",
    "gn:feature_code":"PPL",
    "gn:name":"Drummond North",
    "gn:population":0,
    "gn:timezone":"America/New_York",
    "iso:country":"US",
    "wof:name":"Drummond North",
    "wof:placetype":"locality"
},
  "geometry": {"coordinates":[-75.71632,39.7265],"type":"Point"}
}