{
  "type": "Feature",
  "properties": {
    "gn:admin1_code":"CA",
    "gn:admin2_code":"7",
    "gn:asciiname":"Merrimac",
    "gn:country_code":"US",
    "gn:dem":1238,
    "gn:elevation":"1219.0",
    "gn:feature_class":"P",
    "gn:feature_code":"PPL",
    "gn:name":"Merrimac",
    "gn:population":0,
    "gn:timezone":"America/Los_Angeles",
    "iso:country":"US",
    "name:ara_x_preferred":[
        "\u0645\u064a\u0631\u064a\u0645\u0627\u0643"
    ],
    "name:eng_x_preferred":[
        "Merrimac"
    ],
    "name:fas_x_preferred":[
        "\u0645\u0631\u06cc\u0645\u0627\u06a9"
    ],
    "name:und_x_variant":[
        "Merrimack",
        "Pea Vine",
        "Peavine"
    ],
    "name:vol_x_preferred":[
        "Merrimac"
    ],
    "name:zho_x_preferred":[
        "\u9ed8\u91cc\u99ac\u514b"
    ],
    "wof:name":"Merrimac",
    "wof:placetype":"locality"
},
  "geometry": {"coordinates":[-121.30746000000001,39.766],"type":"Point"}
}