{
  "type": "Feature",
  "properties": {
    "gn:admin1_code":"TN",
    "gn:admin2_code":"181",
    "gn:asciiname":"Holly Creek",
    "gn:country_code":"US",
    "gn:dem":208,
    "gn:elevation":"203.0",
    "gn:feature_class":"P",
    "gn:feature_code":"PPL",
    "gn:name":"Holly Creek",
    "gn:population":0,
    "gn:timezone":"America/Chicago",
    "iso:country":"US",
    "wof:name":"Holly Creek",
    "wof:placetype":"locality"
},
  "geometry": {"coordinates":[-87.60252,35.08647],"type":"Point"}
}