{
  "type": "Feature",
  "properties": {
    "gn:admin1_code":"OH",
    "gn:admin2_code":"97.0",
    "gn:admin3_code":"11234.0",
    "gn:asciiname":"Canaan Community Mobile Home Park",
    "gn:country_code":"US",
    "gn:dem":281,
    "gn:elevation":"282.0",
    "gn:feature_class":"P",
    "gn:feature_code":"PPL",
    "gn:name":"Canaan Community Mobile Home Park",
    "gn:population":0,
    "gn:timezone":"America/New_York",
    "iso:country":"US",
    "wof:name":"Canaan Community Mobile Home Park",
    "wof:placetype":"campus"
},
  "geometry": {"coordinates":[-83.26472,40.01556],"type":"Point"}
}