{
  "type": "Feature",
  "properties": {
    "iso:country":"US",
    "name:ceb_x_preferred":[
        "Willow Brook"
    ],
    "name:deu_x_preferred":[
        "Willow Brook"
    ],
    "name:eng_x_preferred":[
        "Willow Brook"
    ],
    "name:fra_x_preferred":[
        "Willow Brook"
    ],
    "name:swe_x_preferred":[
        "Willow Brook"
    ],
    "qs:gn_adm0_cc":"US",
    "qs:gn_local":5089178,
    "qs:gn_nam_loc":"manchester",
    "qs:gn_namadm1":"NH",
    "qs:local_max":3386,
    "qs:local_sum":6998,
    "qs:localhoods":11,
    "qs:name":"Willow Brook",
    "qs:name_adm0":"United States",
    "qs:name_adm1":"New Hampshire",
    "qs:name_adm2":"Hillsborough",
    "qs:name_local":"Manchester",
    "qs:photo_max":39,
    "qs:photo_sum":102,
    "qs:placetype":"Suburb",
    "qs:quad_count":6,
    "qs:woe_adm0":23424977,
    "qs:woe_adm1":2347588,
    "qs:woe_adm2":12589253,
    "qs:woe_lau":0,
    "qs:woe_local":2444674,
    "qs:woe_ver":"7.10.0",
    "wd:wordcount":58,
    "wof:lang":[
        "eng"
    ],
    "wof:name":"Willow Brook",
    "wof:placetype":"neighbourhood",
    "wof:population":3896,
    "zs:blockids":[
        330110010004009,
        330110026001017,
        330110010004018,
        330110026001012,
        330110026001000,
        330110010004016,
        330110026001006,
        330110026001010,
        330110026001015,
        330110026001013,
        330110010004027,
        330110026001001,
        330110010004023,
        330110026001009,
        330110010004020,
        330119801011010,
        330110026002027,
        330110010004014,
        330110026001004,
        330110026002023,
        330110010004007,
        330110026002026,
        330110010004015,
        330110026001014,
        330110026002025,
        330110026001005,
        330110026001008,
        330110010004024,
        330110026001011,
        330110026002028,
        330110010004025,
        330110010004021,
        330119801011009,
        330110010004019,
        330110026002017,
        330110010004004,
        330110010004013,
        330110010004017,
        330110026001016,
        330110026001002,
        330110026002024,
        330110026001007,
        330110010004011,
        330110010004008,
        330110010004022,
        330110010004029
    ],
    "zs:housing10":1571,
    "zs:pop10":3896
},
  "geometry": {"coordinates":[-71.415992,42.93759],"type":"Point"}
}