{
  "type": "Feature",
  "properties": {
    "gn:admin1_code":"NC",
    "gn:admin2_code":"147",
    "gn:admin3_code":"90224.0",
    "gn:asciiname":"Victory Mobile Home Park",
    "gn:country_code":"US",
    "gn:dem":8,
    "gn:elevation":"10.0",
    "gn:feature_class":"P",
    "gn:feature_code":"PPL",
    "gn:name":"Victory Mobile Home Park",
    "gn:population":0,
    "gn:timezone":"America/New_York",
    "iso:country":"US",
    "wof:name":"Victory Mobile Home Park",
    "wof:placetype":"campus"
},
  "geometry": {"coordinates":[-77.4157,35.6736],"type":"Point"}
}