{
  "type": "Feature",
  "properties": {
    "gn:admin1_code":"TX",
    "gn:admin2_code":"97",
    "gn:asciiname":"Freemound",
    "gn:country_code":"US",
    "gn:dem":278,
    "gn:elevation":"276.0",
    "gn:feature_class":"P",
    "gn:feature_code":"PPL",
    "gn:name":"Freemound",
    "gn:population":0,
    "gn:timezone":"America/Chicago",
    "iso:country":"US",
    "wof:name":"Freemound",
    "wof:placetype":"locality"
},
  "geometry": {"coordinates":[-97.47641,33.56066],"type":"Point"}
}