{
  "type": "Feature",
  "properties": {
    "gn:country":"US",
    "gn:fcode":"PPL",
    "gn:population":0,
    "iso:country":"US",
    "name:azb_x_preferred":[
        "\u0642\u0627\u0645\u0628\u0648\u0631\u0648"
    ],
    "name:eng_x_preferred":[
        "Gumboro"
    ],
    "name:fas_x_preferred":[
        "\u06af\u0627\u0645\u0628\u0648\u0631\u0648"
    ],
    "name:fra_x_preferred":[
        "Gumboro"
    ],
    "name:spa_x_preferred":[
        "Gumboro"
    ],
    "name:und_x_variant":[
        "Pear Tree"
    ],
    "name:zho_x_preferred":[
        "\u7518\u4fdd\u7f85"
    ],
    "qs_pg:aaroncc":"US",
    "qs_pg:gn_country":"US",
    "qs_pg:gn_fcode":"PPL",
    "qs_pg:gn_pop":0,
    "qs_pg:name":"Gumboro",
    "qs_pg:name_adm0":"United States",
    "qs_pg:name_adm1":"Delaware",
    "qs_pg:photos_9k":1,
    "qs_pg:photos_9r":1,
    "qs_pg:photos_all":1,
    "qs_pg:photos_sr":0,
    "qs_pg:pop_sr":0,
    "qs_pg:qs_pg_placetype":"locality",
    "qs_pg:qs_pg_placetype_gp":"Town",
    "qs_pg:woe_adm0":23424977,
    "woe:adm0_id":23424977,
    "woe:name_adm0":"United States",
    "woe:name_adm1":"Delaware",
    "woe:placetype":"Town",
    "wof:name":"Gumboro",
    "wof:placetype":"locality"
},
  "geometry": {"coordinates":[-75.36519,38.47761],"type":"Point"}
}