{
  "type": "Feature",
  "properties": {
    "gn:admin1_code":"NJ",
    "gn:admin2_code":"19.0",
    "gn:admin3_code":"24870.0",
    "gn:asciiname":"Allens Corner",
    "gn:country_code":"US",
    "gn:dem":201,
    "gn:elevation":"198.0",
    "gn:feature_class":"P",
    "gn:feature_code":"PPL",
    "gn:name":"Allens Corner",
    "gn:population":0,
    "gn:timezone":"America/New_York",
    "iso:country":"US",
    "name:eng_x_preferred":[
        "Allens Corner"
    ],
    "name:und_x_variant":[
        "Allerton"
    ],
    "wof:name":"Allens Corner",
    "wof:placetype":"locality"
},
  "geometry": {"coordinates":[-74.9385,40.54677],"type":"Point"}
}