{
  "type": "Feature",
  "properties": {
    "gn:admin1_code":"NY",
    "gn:admin2_code":"5.0",
    "gn:asciiname":"Eastchester Heights",
    "gn:country_code":"US",
    "gn:dem":52,
    "gn:elevation":"42.0",
    "gn:feature_class":"P",
    "gn:feature_code":"PPL",
    "gn:name":"Eastchester Heights",
    "gn:population":0,
    "gn:timezone":"America/New_York",
    "iso:country":"US",
    "name:und_x_variant":[
        "Hillside Homes",
        "Eastchester Heights"
    ],
    "wof:name":"Eastchester Heights",
    "wof:placetype":"locality"
},
  "geometry": {"coordinates":[-73.84917,40.87722],"type":"Point"}
}