{
  "type": "Feature",
  "properties": {
    "iso:country":"US",
    "name:ceb_x_preferred":[
        "Timberlane"
    ],
    "name:deu_x_preferred":[
        "Timberlane"
    ],
    "name:eng_x_preferred":[
        "Timberlane"
    ],
    "name:fra_x_preferred":[
        "Timberlane"
    ],
    "name:ita_x_preferred":[
        "Timberlane"
    ],
    "name:nld_x_preferred":[
        "Timberlane"
    ],
    "name:pol_x_preferred":[
        "Timberlane"
    ],
    "name:spa_x_preferred":[
        "Timberlane"
    ],
    "name:srp_x_preferred":[
        "\u0422\u0438\u043c\u0431\u0435\u0440\u043b\u0435\u0458\u043d"
    ],
    "name:vol_x_preferred":[
        "Timberlane"
    ],
    "wd:wordcount":61,
    "wof:name":"Timberlane",
    "wof:placetype":"neighbourhood",
    "wof:population":1138,
    "zs:area_m":11445764.029188,
    "zs:blockids":[
        11010056041027,
        11010055032031,
        11010055032036,
        11010055033051,
        11010055033110,
        11010055031027,
        11010056082028,
        11010056082008,
        11010055032037,
        11010055031022,
        11010055033113,
        11010055031025,
        11010056082005,
        11010056082004,
        11010056082033,
        11010055012039,
        11010055031030,
        11010056082007,
        11010055032034,
        11010055031021,
        11010055031029,
        11010055031023,
        11010055033007,
        11010055033006,
        11010055031015,
        11010055033008,
        11010056082003,
        11010055032032,
        11010055031043,
        11010055033047,
        11010055012040,
        11010055031019,
        11010055031049,
        11010055032035,
        11010055032038,
        11010055031045,
        11010055031050,
        11010055012030,
        11010055031046,
        11010055031003,
        11010056082018,
        11010056082006,
        11010055031028,
        11010055032040,
        11010055031024,
        11010055031020,
        11010055032000,
        11010055031017,
        11010055032001,
        11010055032033,
        11010055031048,
        11010055033121,
        11010056082001,
        11010055033049,
        11010055031026,
        11010055033120,
        11010055031018,
        11010056082000,
        11010056041028,
        11010055033122,
        11010056082019,
        11010055032039,
        11010056082002,
        11010055033050,
        11010055033048
    ],
    "zs:housing10":369,
    "zs:label":"Timberlane",
    "zs:pop10":1138
},
  "geometry": {"coordinates":[-86.095844,32.359553],"type":"Point"}
}