{
  "type": "Feature",
  "properties": {
    "iso:country":"US",
    "name:dan_x_preferred":[
        "Olsen"
    ],
    "name:deu_x_preferred":[
        "Olsen"
    ],
    "name:eng_x_preferred":[
        "Olsen"
    ],
    "name:fao_x_preferred":[
        "Olsen"
    ],
    "name:fin_x_preferred":[
        "Olsen"
    ],
    "name:fra_x_preferred":[
        "Olsen"
    ],
    "name:heb_x_preferred":[
        "\u05d0\u05d5\u05dc\u05e1\u05df"
    ],
    "name:hun_x_preferred":[
        "Olsen"
    ],
    "name:ita_x_preferred":[
        "Olsen"
    ],
    "name:jpn_x_preferred":[
        "\u30aa\u30eb\u30bb\u30f3"
    ],
    "name:pol_x_preferred":[
        "Olsen"
    ],
    "name:rus_x_preferred":[
        "\u041e\u043b\u0441\u0435\u043d"
    ],
    "name:ukr_x_preferred":[
        "\u041e\u043b\u0441\u0435\u043d"
    ],
    "wd:wordcount":65,
    "wof:name":"Olsen",
    "wof:placetype":"neighbourhood",
    "wof:population":2,
    "zs:area_m":925654.378386,
    "zs:blockids":[
        490572019001150,
        490572105112012,
        490572019001142,
        490572019001146,
        490572019001145,
        490572019001151,
        490572019001143,
        490572019001144,
        490572019001138,
        490572105112007,
        490572019001147,
        490572105112001,
        490572011001036,
        490572019001149,
        490572105112008,
        490572018001013,
        490572105112009,
        490572019001169,
        490572105112011,
        490572019001139,
        490572019001156,
        490572105112002,
        490572105112010,
        490572105112054
    ],
    "zs:housing10":1,
    "zs:label":"Olsen",
    "zs:pop10":2
},
  "geometry": {"coordinates":[-111.98998400000001,41.200751],"type":"Point"}
}