{
  "type": "Feature",
  "properties": {
    "gn:admin1_code":"PA",
    "gn:admin2_code":"33.0",
    "gn:admin3_code":"18456.0",
    "gn:asciiname":"New Castle",
    "gn:country_code":"US",
    "gn:dem":610,
    "gn:elevation":"606.0",
    "gn:feature_class":"P",
    "gn:feature_code":"PPL",
    "gn:name":"New Castle",
    "gn:population":0,
    "gn:timezone":"America/New_York",
    "iso:country":"US",
    "wof:name":"New Castle",
    "wof:placetype":"locality"
},
  "geometry": {"coordinates":[-78.34251999999999,40.87784],"type":"Point"}
}