{
  "type": "Feature",
  "properties": {
    "gn:country":"US",
    "gn:fcode":"PPL",
    "gn:population":0,
    "iso:country":"US",
    "name:eng_x_preferred":[
        "Thames View"
    ],
    "name:und_x_variant":[
        "Thomas View"
    ],
    "qs_pg:aaroncc":"US",
    "qs_pg:gn_country":"US",
    "qs_pg:gn_fcode":"PPL",
    "qs_pg:gn_pop":0,
    "qs_pg:name":"Thames View",
    "qs_pg:name_adm0":"United States",
    "qs_pg:name_adm1":"Connecticut",
    "qs_pg:photos":2,
    "qs_pg:photos_1k":1,
    "qs_pg:photos_9k":1,
    "qs_pg:photos_9r":1,
    "qs_pg:photos_all":2,
    "qs_pg:photos_sr":1,
    "qs_pg:pop_sr":0,
    "qs_pg:qs_pg_placetype":"neighbourhood",
    "qs_pg:qs_pg_placetype_gp":"Suburb",
    "qs_pg:woe_adm0":23424977,
    "wd:wordcount":154,
    "wof:name":"Thames View",
    "wof:placetype":"neighbourhood",
    "wof:population":2944,
    "zs:area_m":13533297.960555,
    "zs:blockids":[
        90119800001007,
        90119800001012,
        90116936002025,
        90116936001015,
        90116936002008,
        90116936002030,
        90116936001002,
        90116937002022,
        90116937002020,
        90116937002023,
        90119800001010,
        90119800001004,
        90119800001023,
        90116936002006,
        90116936002000,
        90119800001006,
        90117012003059,
        90119800001024,
        90116936002022,
        90116937002013,
        90116936001021,
        90116937002028,
        90116937002014,
        90116936002004,
        90116936001022,
        90116936002019,
        90116936002009,
        90116936002015,
        90116936002024,
        90116936002001,
        90117012003048,
        90119800001011,
        90116936001024,
        90116936001027,
        90119800001005,
        90116937002019,
        90116936002002,
        90116936001023,
        90119800001008,
        90117012003038,
        90119800001001,
        90116937002011,
        90116936003002,
        90116936002017,
        90116936003006,
        90116936001026,
        90116936002023,
        90116936002021,
        90116936001000,
        90116937002012,
        90116936003000,
        90116936002011,
        90116937002015,
        90116936001028,
        90116936001017,
        90116936001011,
        90116936001016,
        90116936001012,
        90117012005013,
        90116936003009,
        90116937002018,
        90116937002017,
        90116936002003,
        90116936002005,
        90116936002018,
        90119800001003,
        90116936003001,
        90116936002014,
        90116936001001,
        90117012005015,
        90116936001010,
        90116936001013,
        90116936002016,
        90116936002026,
        90116936003005,
        90116936001020,
        90116936003008,
        90117012005026,
        90117012003039,
        90117012003049,
        90116936003007,
        90119800001009,
        90116936001018,
        90116936001025,
        90116936002007,
        90119800001070,
        90119800001013
    ],
    "zs:housing10":1292,
    "zs:label":"Thames View",
    "zs:pop10":2944
},
  "geometry": {"coordinates":[-72.10741,41.410082],"type":"Point"}
}