{
  "type": "Feature",
  "properties": {
    "gn:admin1_code":"TN",
    "gn:admin2_code":"35",
    "gn:asciiname":"Haleys Grove",
    "gn:country_code":"US",
    "gn:dem":542,
    "gn:elevation":"544.0",
    "gn:feature_class":"P",
    "gn:feature_code":"PPL",
    "gn:name":"Haleys Grove",
    "gn:population":0,
    "gn:timezone":"America/Chicago",
    "iso:country":"US",
    "wof:name":"Haleys Grove",
    "wof:placetype":"locality"
},
  "geometry": {"coordinates":[-84.89161999999997,35.90979],"type":"Point"}
}