{
  "type": "Feature",
  "properties": {
    "gn:admin1_code":"AL",
    "gn:admin2_code":"49",
    "gn:asciiname":"Luttrell",
    "gn:country_code":"US",
    "gn:dem":383,
    "gn:elevation":"385.0",
    "gn:feature_class":"P",
    "gn:feature_code":"PPL",
    "gn:name":"Luttrell",
    "gn:population":0,
    "gn:timezone":"America/Chicago",
    "iso:country":"US",
    "name:deu_x_preferred":[
        "Luttrell"
    ],
    "name:ita_x_preferred":[
        "Luttrell"
    ],
    "name:nld_x_preferred":[
        "Luttrell"
    ],
    "name:por_x_preferred":[
        "Luttrell"
    ],
    "wof:name":"Luttrell",
    "wof:placetype":"locality"
},
  "geometry": {"coordinates":[-85.93470000000001,34.44037],"type":"Point"}
}