{
  "type": "Feature",
  "properties": {
    "gn:country":"US",
    "gn:fcode":"PPL",
    "gn:population":0,
    "iso:country":"US",
    "name:ara_x_preferred":[
        "\u0648\u0627\u0644\u062f\u0646"
    ],
    "name:aze_x_preferred":[
        "Uolden"
    ],
    "name:bul_x_preferred":[
        "\u0423\u043e\u043b\u0434\u044a\u043d"
    ],
    "name:cat_x_preferred":[
        "Walden"
    ],
    "name:ces_x_preferred":[
        "Walden"
    ],
    "name:deu_x_preferred":[
        "Walden"
    ],
    "name:est_x_preferred":[
        "Walden"
    ],
    "name:eus_x_preferred":[
        "Walden"
    ],
    "name:fas_x_preferred":[
        "\u0648\u0627\u0644\u062f\u0646"
    ],
    "name:fin_x_preferred":[
        "El\u00e4m\u00e4\u00e4 mets\u00e4ss\u00e4"
    ],
    "name:hrv_x_preferred":[
        "Walden"
    ],
    "name:ind_x_preferred":[
        "Walden"
    ],
    "name:jpn_x_preferred":[
        "\u30a6\u30a9\u30fc\u30eb\u30c7\u30f3 \u68ee\u306e\u751f\u6d3b"
    ],
    "name:lat_x_preferred":[
        "Walden"
    ],
    "name:lit_x_preferred":[
        "Voldenas"
    ],
    "name:nep_x_preferred":[
        "\u0935\u093e\u0932\u0921\u0947\u0928"
    ],
    "name:nld_x_preferred":[
        "Walden"
    ],
    "name:pan_x_preferred":[
        "\u0a35\u0a3e\u0a32\u0a21\u0a28"
    ],
    "name:pol_x_preferred":[
        "Walden"
    ],
    "name:por_x_preferred":[
        "Walden"
    ],
    "name:ron_x_preferred":[
        "Walden"
    ],
    "name:rus_x_preferred":[
        "\u0423\u043e\u043b\u0434\u0435\u043d"
    ],
    "name:slk_x_preferred":[
        "Walden"
    ],
    "name:spa_x_preferred":[
        "Walden"
    ],
    "name:swe_x_preferred":[
        "Walden"
    ],
    "name:tha_x_preferred":[
        "\u0e27\u0e2d\u0e25\u0e40\u0e14\u0e19"
    ],
    "name:ukr_x_preferred":[
        "\u0412\u043e\u043b\u0434\u0435\u043d"
    ],
    "name:zho_x_preferred":[
        "\u74e6\u723e\u767b\u6e56"
    ],
    "qs_pg:aaroncc":"US",
    "qs_pg:gn_country":"US",
    "qs_pg:gn_fcode":"PPL",
    "qs_pg:gn_pop":0,
    "qs_pg:name":"Walden",
    "qs_pg:name_adm0":"United States",
    "qs_pg:name_adm1":"Maryland",
    "qs_pg:photos":9,
    "qs_pg:photos_1k":2,
    "qs_pg:photos_9k":1,
    "qs_pg:photos_9r":1,
    "qs_pg:photos_all":9,
    "qs_pg:photos_sr":1,
    "qs_pg:pop_sr":0,
    "qs_pg:qs_pg_placetype":"locality",
    "qs_pg:qs_pg_placetype_gp":"Town",
    "qs_pg:woe_adm0":23424977,
    "woe:adm0_id":23424977,
    "woe:name_adm0":"United States",
    "woe:name_adm1":"Maryland",
    "woe:placetype":"Town",
    "wof:name":"Walden",
    "wof:placetype":"locality"
},
  "geometry": {"coordinates":[-76.67301999999999,39.02511],"type":"Point"}
}