{
  "type": "Feature",
  "properties": {
    "iso:country":"US",
    "name:eng_x_preferred":[
        "Comstock Corners"
    ],
    "name:nld_x_preferred":[
        "Comstock Corners"
    ],
    "name:tur_x_preferred":[
        "Comstock Corners"
    ],
    "wd:wordcount":49,
    "wof:name":"Comstock Corners",
    "wof:placetype":"neighbourhood",
    "wof:population":132,
    "zs:area_m":2518079.076972,
    "zs:blockids":[
        360630243033009,
        360630243033006,
        360630243033036,
        360630243033010,
        360630243033012
    ],
    "zs:housing10":46,
    "zs:label":"Comstock Corners",
    "zs:pop10":132
},
  "geometry": {"coordinates":[-78.789131,43.142088],"type":"Point"}
}