{
  "type": "Feature",
  "properties": {
    "gn:admin1_code":"NM",
    "gn:admin2_code":"49",
    "gn:asciiname":"Dennison Place",
    "gn:country_code":"US",
    "gn:dem":2000,
    "gn:elevation":"2000.0",
    "gn:feature_class":"P",
    "gn:feature_code":"PPL",
    "gn:name":"Dennison Place",
    "gn:population":0,
    "gn:timezone":"America/Denver",
    "iso:country":"US",
    "name:eng_x_preferred":[
        "Dennison Place"
    ],
    "name:und_x_variant":[
        "Dennison"
    ],
    "wof:name":"Dennison Place",
    "wof:placetype":"locality"
},
  "geometry": {"coordinates":[-106.05029999999999,35.25504],"type":"Point"}
}