{
  "type": "Feature",
  "properties": {
    "gn:admin1_code":"KY",
    "gn:admin2_code":"183",
    "gn:asciiname":"Aetnaville",
    "gn:country_code":"US",
    "gn:dem":150,
    "gn:elevation":"147.0",
    "gn:feature_class":"P",
    "gn:feature_code":"PPL",
    "gn:name":"Aetnaville",
    "gn:population":0,
    "gn:timezone":"America/Chicago",
    "iso:country":"US",
    "wof:name":"Aetnaville",
    "wof:placetype":"locality"
},
  "geometry": {"coordinates":[-86.79054000000002,37.67283],"type":"Point"}
}