{
  "type": "Feature",
  "properties": {
    "gn:admin1_code":"PA",
    "gn:admin2_code":"133.0",
    "gn:admin3_code":"44872.0",
    "gn:asciiname":"Kyleville",
    "gn:country_code":"US",
    "gn:dem":204,
    "gn:elevation":"200.0",
    "gn:feature_class":"P",
    "gn:feature_code":"PPL",
    "gn:name":"Kyleville",
    "gn:population":0,
    "gn:timezone":"America/New_York",
    "iso:country":"US",
    "wof:name":"Kyleville",
    "wof:placetype":"locality"
},
  "geometry": {"coordinates":[-76.38718,39.81871],"type":"Point"}
}