{
  "type": "Feature",
  "properties": {
    "gn:admin1_code":"NC",
    "gn:admin2_code":"65.0",
    "gn:asciiname":"Scotts Crossroads",
    "gn:country_code":"US",
    "gn:dem":14,
    "gn:elevation":"12.0",
    "gn:feature_class":"P",
    "gn:feature_code":"PPL",
    "gn:name":"Scotts Crossroads",
    "gn:population":0,
    "gn:timezone":"America/New_York",
    "iso:country":"US",
    "wof:name":"Scotts Crossroads",
    "wof:placetype":"locality"
},
  "geometry": {"coordinates":[-77.53664000000001,35.79488],"type":"Point"}
}