{
  "type": "Feature",
  "properties": {
    "gn:admin1_code":"PA",
    "gn:admin2_code":"33.0",
    "gn:admin3_code":"86440.0",
    "gn:asciiname":"Goss Run Junction",
    "gn:country_code":"US",
    "gn:dem":458,
    "gn:elevation":"456.0",
    "gn:feature_class":"P",
    "gn:feature_code":"PPL",
    "gn:name":"Goss Run Junction",
    "gn:population":0,
    "gn:timezone":"America/New_York",
    "iso:country":"US",
    "wof:name":"Goss Run Junction",
    "wof:placetype":"locality"
},
  "geometry": {"coordinates":[-78.33224,40.832],"type":"Point"}
}