{
  "type": "Feature",
  "properties": {
    "gn:admin1_code":"MI",
    "gn:admin2_code":"65.0",
    "gn:admin3_code":"87440.0",
    "gn:asciiname":"Willow Village Home Court",
    "gn:country_code":"US",
    "gn:dem":267,
    "gn:elevation":"265.0",
    "gn:feature_class":"P",
    "gn:feature_code":"PPL",
    "gn:name":"Willow Village Home Court",
    "gn:population":0,
    "gn:timezone":"America/Detroit",
    "iso:country":"US",
    "wof:name":"Willow Village Home Court",
    "wof:placetype":"locality"
},
  "geometry": {"coordinates":[-84.26444000000002,42.68611],"type":"Point"}
}