{
  "type": "Feature",
  "properties": {
    "gn:admin1_code":"KS",
    "gn:admin2_code":"173.0",
    "gn:admin3_code":"3125.0",
    "gn:asciiname":"Saint Marks",
    "gn:country_code":"US",
    "gn:dem":447,
    "gn:elevation":"437.0",
    "gn:feature_class":"P",
    "gn:feature_code":"PPL",
    "gn:name":"Saint Marks",
    "gn:population":0,
    "gn:timezone":"America/Chicago",
    "iso:country":"US",
    "name:eng_x_preferred":[
        "Saint Marks"
    ],
    "name:und_x_variant":[
        "Saint Mark"
    ],
    "wof:name":"Saint Marks",
    "wof:placetype":"locality"
},
  "geometry": {"coordinates":[-97.56227,37.73585],"type":"Point"}
}