{
  "type": "Feature",
  "properties": {
    "gn:admin1_code":"AL",
    "gn:admin2_code":"107",
    "gn:asciiname":"Lois Spring",
    "gn:country_code":"US",
    "gn:dem":64,
    "gn:elevation":"57.0",
    "gn:feature_class":"P",
    "gn:feature_code":"PPL",
    "gn:name":"Lois Spring",
    "gn:population":0,
    "gn:timezone":"America/Chicago",
    "iso:country":"US",
    "name:eng_x_preferred":[
        "Lois Spring"
    ],
    "name:und_x_variant":[
        "Lois Springs"
    ],
    "wof:name":"Lois Spring",
    "wof:placetype":"locality"
},
  "geometry": {"coordinates":[-88.09390999999999,33.23068],"type":"Point"}
}