{
  "type": "Feature",
  "properties": {
    "gn:admin1_code":"MI",
    "gn:admin2_code":"127",
    "gn:admin3_code":"36940.0",
    "gn:asciiname":"Pines Mobile Home Park",
    "gn:country_code":"US",
    "gn:dem":210,
    "gn:elevation":"208.0",
    "gn:feature_class":"P",
    "gn:feature_code":"PPL",
    "gn:name":"Pines Mobile Home Park",
    "gn:population":0,
    "gn:timezone":"America/Detroit",
    "iso:country":"US",
    "wof:name":"Pines Mobile Home Park",
    "wof:placetype":"campus"
},
  "geometry": {"coordinates":[-86.37917,43.70444000000001],"type":"Point"}
}