{
  "type": "Feature",
  "properties": {
    "gn:admin1_code":"VA",
    "gn:admin2_code":"61",
    "gn:asciiname":"Scuffleburg",
    "gn:country_code":"US",
    "gn:dem":188,
    "gn:elevation":"175.0",
    "gn:feature_class":"P",
    "gn:feature_code":"PPL",
    "gn:name":"Scuffleburg",
    "gn:population":0,
    "gn:timezone":"America/New_York",
    "iso:country":"US",
    "name:eng_x_preferred":[
        "Scuffleburg"
    ],
    "name:und_x_variant":[
        "Kerbys Shop",
        "Mechanicsville"
    ],
    "wof:name":"Scuffleburg",
    "wof:placetype":"locality"
},
  "geometry": {"coordinates":[-77.95388,38.94205],"type":"Point"}
}