{
  "type": "Feature",
  "properties": {
    "iso:country":"US",
    "name:ceb_x_preferred":[
        "Creekside"
    ],
    "name:deu_x_preferred":[
        "Creekside"
    ],
    "name:eng_x_preferred":[
        "Creekside"
    ],
    "name:ita_x_preferred":[
        "Creekside"
    ],
    "name:nld_x_preferred":[
        "Creekside"
    ],
    "name:pol_x_preferred":[
        "Creekside"
    ],
    "name:por_x_preferred":[
        "Creekside"
    ],
    "name:srp_x_preferred":[
        "\u041a\u0440\u0438\u043a\u0441\u0430\u0458\u0434"
    ],
    "name:swe_x_preferred":[
        "Creekside"
    ],
    "name:ukr_x_preferred":[
        "\u041a\u0440\u0456\u043a\u0441\u0430\u0439\u0434"
    ],
    "name:vol_x_preferred":[
        "Creekside"
    ],
    "wd:wordcount":74,
    "wof:name":"Creekside",
    "wof:placetype":"neighbourhood",
    "wof:population":212,
    "zs:area_m":188555.988257,
    "zs:blockids":[
        191530102033012,
        191530102033013,
        191530102033011,
        191530102033014
    ],
    "zs:housing10":85,
    "zs:label":"Creekside",
    "zs:pop10":212
},
  "geometry": {"coordinates":[-93.58373,41.771993],"type":"Point"}
}