{
  "type": "Feature",
  "properties": {
    "iso:country":"US",
    "name:eng_x_preferred":[
        "Hollypark"
    ],
    "wof:name":"Hollypark",
    "wof:placetype":"neighbourhood",
    "wof:population":7291,
    "zs:area_m":2260647.21293,
    "zs:blockids":[
        80010093211004,
        80010093211000,
        80010093191003,
        80010094112008,
        80010093165000,
        80010094061014,
        80010093164006,
        80010093191011,
        80010093211030,
        80010093165011,
        80010093165001,
        80010093162009,
        80010093164000,
        80010093165006,
        80010093165009,
        80010094061004,
        80010093164001,
        80010094061010,
        80010093191002,
        80010093211026,
        80010093211016,
        80010093162004,
        80010093165002,
        80010093162008,
        80010093211029,
        80010094061020,
        80010093211028,
        80010094061021,
        80010094112004,
        80010094061003,
        80010094061005,
        80010094061025,
        80010093164013,
        80010093164009,
        80010093164014,
        80010093211012,
        80010093211014,
        80010093211021,
        80010093211020,
        80010093211017,
        80010093211027,
        80010093162013,
        80010093165010,
        80010094061001,
        80010093165004,
        80010093165003,
        80010094112007,
        80010094061026,
        80010094061015,
        80010094061008,
        80010094061000,
        80010093165007,
        80010093211025,
        80010093211023,
        80010094112005,
        80010093191000,
        80010094061024,
        80010094061009,
        80010094061013,
        80010094061011,
        80010093191008,
        80010093211007,
        80010093164003,
        80010093164008,
        80010093164002,
        80010093211009,
        80010093211011,
        80010093211018,
        80010093164010,
        80010093191005,
        80010094061002,
        80010093164005,
        80010094071000,
        80010093191007,
        80010094112009,
        80010093211024,
        80010094061019,
        80010093191010,
        80010093211010,
        80010093211003,
        80010094061007,
        80010094071025,
        80010094071024,
        80010093165005,
        80010093211022,
        80010093211008,
        80010093164007,
        80010093164011,
        80010093211013,
        80010093211005,
        80010093211006,
        80010094112006,
        80010093165008,
        80010094112003,
        80010093191006,
        80010093211015,
        80010094061016,
        80010094061006,
        80010094061017,
        80010094061018,
        80010094061012,
        80010093191009,
        80010093162007,
        80010093164004,
        80010093164012,
        80010094071004,
        80010093211002,
        80010093211001,
        80010093211019
    ],
    "zs:housing10":2500,
    "zs:label":"Hollypark",
    "zs:pop10":7291
},
  "geometry": {"coordinates":[-105.021413,39.86882],"type":"Point"}
}