{
  "type": "Feature",
  "properties": {
    "iso:country":"US",
    "name:eng_x_preferred":[
        "East Hillsdale"
    ],
    "qs:gn_adm0_cc":"US",
    "qs:gn_local":5392423,
    "qs:gn_nam_loc":"San Mateo, San Mateo, California, US",
    "qs:gn_namadm1":"CA",
    "qs:local_max":12077,
    "qs:local_sum":31677,
    "qs:localhoods":37,
    "qs:name":"East Hillsdale",
    "qs:name_adm0":"United States",
    "qs:name_adm1":"California",
    "qs:name_adm2":"San Mateo",
    "qs:name_local":"San Mateo",
    "qs:photo_max":4268,
    "qs:photo_sum":12077,
    "qs:placetype":"Suburb",
    "qs:quad_count":26,
    "qs:woe_adm0":23424977,
    "qs:woe_adm1":2347563,
    "qs:woe_adm2":12587710,
    "qs:woe_lau":0,
    "qs:woe_local":2488142,
    "qs:woe_ver":"7.10.0",
    "wof:lang":[
        "eng"
    ],
    "wof:name":"East Hillsdale",
    "wof:placetype":"neighbourhood",
    "wof:population":2352,
    "zs:blockids":[
        60816074003002,
        60816074003005,
        60816075001015,
        60816075001022,
        60816074002005,
        60816075001018,
        60816075001027,
        60816075001020,
        60816074003003,
        60816075001019,
        60816075001035,
        60816075001014,
        60816075001029,
        60816075001006,
        60816075001042,
        60816075001009,
        60816075001045,
        60816074002000,
        60816074003000,
        60816075001043,
        60816075001004,
        60816074003006,
        60816074003013,
        60816074003004,
        60816075001021,
        60816074001016,
        60816075001016,
        60816075001013,
        60816075001034
    ],
    "zs:housing10":953,
    "zs:pop10":2352
},
  "geometry": {"coordinates":[-122.301777,37.546939],"type":"Point"}
}