{
  "type": "Feature",
  "properties": {
    "iso:country":"US",
    "name:eng_x_preferred":[
        "Newport Haven"
    ],
    "wof:name":"Newport Haven",
    "wof:placetype":"neighbourhood",
    "wof:population":3,
    "zs:area_m":18995744.834452,
    "zs:blockids":[
        490111254033041,
        490111254033055
    ],
    "zs:housing10":2,
    "zs:label":"Newport Haven",
    "zs:pop10":3
},
  "geometry": {"coordinates":[-112.065698,41.034482],"type":"Point"}
}