{
  "type": "Feature",
  "properties": {
    "gn:admin1_code":"MD",
    "gn:admin2_code":"15.0",
    "gn:asciiname":"Colonial Acres",
    "gn:country_code":"US",
    "gn:dem":36,
    "gn:elevation":"36.0",
    "gn:feature_class":"P",
    "gn:feature_code":"PPL",
    "gn:name":"Colonial Acres",
    "gn:population":0,
    "gn:timezone":"America/New_York",
    "iso:country":"US",
    "wof:name":"Colonial Acres",
    "wof:placetype":"locality"
},
  "geometry": {"coordinates":[-75.84577,39.63261],"type":"Point"}
}