{
  "type": "Feature",
  "properties": {
    "gn:admin1_code":"VA",
    "gn:admin2_code":"770",
    "gn:asciiname":"Jefferson Hills",
    "gn:country_code":"US",
    "gn:dem":354,
    "gn:elevation":"357.0",
    "gn:feature_class":"P",
    "gn:feature_code":"PPL",
    "gn:name":"Jefferson Hills",
    "gn:population":0,
    "gn:timezone":"America/New_York",
    "iso:country":"US",
    "wof:name":"Jefferson Hills",
    "wof:placetype":"locality"
},
  "geometry": {"coordinates":[-79.97476,37.24069],"type":"Point"}
}