{
  "type": "Feature",
  "properties": {
    "gn:admin1_code":"ND",
    "gn:admin2_code":"15.0",
    "gn:admin3_code":"11045.0",
    "gn:asciiname":"Arnold",
    "gn:country_code":"US",
    "gn:dem":576,
    "gn:elevation":"577.0",
    "gn:feature_class":"P",
    "gn:feature_code":"PPL",
    "gn:name":"Arnold",
    "gn:population":0,
    "gn:timezone":"America/Chicago",
    "iso:country":"US",
    "name:ara_x_preferred":[
        "\u0623\u0631\u0646\u0648\u0644\u062f"
    ],
    "name:bul_x_preferred":[
        "\u0410\u0440\u043d\u043e\u043b\u0434"
    ],
    "name:cat_x_preferred":[
        "Arnold"
    ],
    "name:ceb_x_preferred":[
        "Arnold"
    ],
    "name:ces_x_preferred":[
        "Arnold"
    ],
    "name:dan_x_preferred":[
        "Arnold"
    ],
    "name:deu_x_preferred":[
        "Arnold"
    ],
    "name:est_x_preferred":[
        "Arnold"
    ],
    "name:fas_x_preferred":[
        "\u0622\u0631\u0646\u0648\u0644\u062f"
    ],
    "name:fra_x_preferred":[
        "Arnold"
    ],
    "name:heb_x_preferred":[
        "\u05d0\u05e8\u05e0\u05d5\u05dc\u05d3"
    ],
    "name:hun_x_preferred":[
        "Arnold"
    ],
    "name:hye_x_preferred":[
        "\u0531\u057c\u0576\u0578\u056c\u0564"
    ],
    "name:ita_x_preferred":[
        "Arnold"
    ],
    "name:jpn_x_preferred":[
        "\u30a2\u30fc\u30ce\u30eb\u30c9"
    ],
    "name:kor_x_preferred":[
        "\uc544\ub110\ub4dc"
    ],
    "name:nld_x_preferred":[
        "Arnold"
    ],
    "name:pol_x_preferred":[
        "Arnold"
    ],
    "name:por_x_preferred":[
        "Arnold"
    ],
    "name:ron_x_preferred":[
        "Arnold"
    ],
    "name:rus_x_preferred":[
        "\u0410\u0440\u043d\u043e\u043b\u044c\u0434"
    ],
    "name:slv_x_preferred":[
        "Arnold"
    ],
    "name:spa_x_preferred":[
        "Arnold"
    ],
    "name:srp_x_preferred":[
        "\u0410\u0440\u043d\u043e\u043b\u0434"
    ],
    "name:swe_x_preferred":[
        "Arnold"
    ],
    "name:tur_x_preferred":[
        "Arnold"
    ],
    "name:ukr_x_preferred":[
        "\u0410\u0440\u043d\u043e\u043b\u044c\u0434"
    ],
    "name:urd_x_preferred":[
        "\u0622\u0631\u0646\u0644\u0688"
    ],
    "name:vol_x_preferred":[
        "Arnold"
    ],
    "wof:name":"Arnold",
    "wof:placetype":"locality"
},
  "geometry": {"coordinates":[-100.75346,46.92388],"type":"Point"}
}