{
  "type": "Feature",
  "properties": {
    "gn:admin1_code":"UT",
    "gn:admin2_code":"35.0",
    "gn:asciiname":"Aspen Glen Condominium",
    "gn:country_code":"US",
    "gn:dem":1327,
    "gn:elevation":"1319.0",
    "gn:feature_class":"P",
    "gn:feature_code":"PPL",
    "gn:name":"Aspen Glen Condominium",
    "gn:population":0,
    "gn:timezone":"America/Denver",
    "iso:country":"US",
    "wof:name":"Aspen Glen Condominium",
    "wof:placetype":"locality"
},
  "geometry": {"coordinates":[-111.88466,40.64939],"type":"Point"}
}