{
  "type": "Feature",
  "properties": {
    "gn:admin1_code":"NY",
    "gn:admin2_code":"95.0",
    "gn:admin3_code":"16639.0",
    "gn:asciiname":"Colonial Village Mobile Home Park",
    "gn:country_code":"US",
    "gn:dem":282,
    "gn:elevation":"286.0",
    "gn:feature_class":"P",
    "gn:feature_code":"PPL",
    "gn:name":"Colonial Village Mobile Home Park",
    "gn:population":0,
    "gn:timezone":"America/New_York",
    "iso:country":"US",
    "wof:name":"Colonial Village Mobile Home Park",
    "wof:placetype":"campus"
},
  "geometry": {"coordinates":[-74.40885,42.68289],"type":"Point"}
}