{
  "type": "Feature",
  "properties": {
    "iso:country":"US",
    "name:ast_x_preferred":[
        "Country and West"
    ],
    "name:deu_x_preferred":[
        "Country and West"
    ],
    "name:eng_x_preferred":[
        "Country West"
    ],
    "name:eng_x_variant":[
        "Country and West"
    ],
    "name:fin_x_preferred":[
        "Country and West"
    ],
    "name:fra_x_preferred":[
        "Country and West"
    ],
    "name:heb_x_preferred":[
        "Country and West"
    ],
    "name:ind_x_preferred":[
        "Country and West"
    ],
    "name:nld_x_preferred":[
        "Country and West"
    ],
    "name:spa_x_preferred":[
        "Country and West"
    ],
    "wd:wordcount":154,
    "wof:name":"Country West",
    "wof:placetype":"neighbourhood",
    "wof:population":348,
    "zs:area_m":145698.686621,
    "zs:blockids":[
        490351139054001
    ],
    "zs:housing10":136,
    "zs:label":"Country West",
    "zs:pop10":348
},
  "geometry": {"coordinates":[-112.087154,40.695069],"type":"Point"}
}