{
  "type": "Feature",
  "properties": {
    "iso:country":"US",
    "name:eng_x_preferred":[
        "Estherton"
    ],
    "name:fra_x_preferred":[
        "Estherton"
    ],
    "qs:gn_adm0_cc":"US",
    "qs:gn_fcode":"PPL",
    "qs:gn_local":5214930,
    "qs:gn_nam_loc":"Susquehanna, Dauphin, Pennsylvania, US",
    "qs:gn_namadm1":"PA",
    "qs:gn_name":"Asherton",
    "qs:local_max":366,
    "qs:local_sum":1340,
    "qs:localhoods":6,
    "qs:name":"Estherton",
    "qs:name_adm0":"United States",
    "qs:name_adm1":"Pennsylvania",
    "qs:name_adm2":"Dauphin",
    "qs:name_local":"Susquehanna",
    "qs:photo_max":63,
    "qs:photo_sum":334,
    "qs:placetype":"Suburb",
    "qs:quad_count":27,
    "qs:woe_adm0":23424977,
    "qs:woe_adm1":2347597,
    "qs:woe_adm2":12589749,
    "qs:woe_lau":0,
    "qs:woe_local":28745214,
    "qs:woe_ver":"7.10.0",
    "wd:wordcount":130,
    "wof:lang":[
        "eng"
    ],
    "wof:name":"Estherton",
    "wof:placetype":"neighbourhood",
    "wof:population":13,
    "zs:blockids":[
        420410101001052,
        420410103001018,
        420410101001034,
        420410101001030,
        420410103001007,
        420410101001023,
        420410101001031,
        420410101001033,
        420410101001032
    ],
    "zs:housing10":5,
    "zs:pop10":13
},
  "geometry": {"coordinates":[-76.887395,40.306595],"type":"Point"}
}