{
  "type": "Feature",
  "properties": {
    "gn:admin1_code":"IN",
    "gn:admin2_code":"93.0",
    "gn:admin3_code":"72044.0",
    "gn:asciiname":"Huron",
    "gn:country_code":"US",
    "gn:dem":170,
    "gn:elevation":"167.0",
    "gn:feature_class":"P",
    "gn:feature_code":"PPL",
    "gn:name":"Huron",
    "gn:population":0,
    "gn:timezone":"America/Indiana/Indianapolis",
    "iso:country":"US",
    "name:eng_x_preferred":[
        "Huron"
    ],
    "name:und_x_variant":[
        "Hoards Station"
    ],
    "wof:name":"Huron",
    "wof:placetype":"locality"
},
  "geometry": {"coordinates":[-86.67055000000001,38.72227],"type":"Point"}
}