{
  "type": "Feature",
  "properties": {
    "gn:admin1_code":"IL",
    "gn:admin2_code":"197",
    "gn:admin3_code":"35827.0",
    "gn:asciiname":"Kingstone Hills",
    "gn:country_code":"US",
    "gn:dem":230,
    "gn:elevation":"232.0",
    "gn:feature_class":"P",
    "gn:feature_code":"PPL",
    "gn:name":"Kingstone Hills",
    "gn:population":0,
    "gn:timezone":"America/Chicago",
    "iso:country":"US",
    "wof:name":"Kingstone Hills",
    "wof:placetype":"locality"
},
  "geometry": {"coordinates":[-87.92639,41.615],"type":"Point"}
}