{
  "type": "Feature",
  "properties": {
    "gn:admin1_code":"IN",
    "gn:admin2_code":"85.0",
    "gn:admin3_code":"60228.0",
    "gn:asciiname":"Monoquet",
    "gn:country_code":"US",
    "gn:dem":260,
    "gn:elevation":"258.0",
    "gn:feature_class":"P",
    "gn:feature_code":"PPL",
    "gn:name":"Monoquet",
    "gn:population":0,
    "gn:timezone":"America/Indiana/Indianapolis",
    "iso:country":"US",
    "wof:name":"Monoquet",
    "wof:placetype":"locality"
},
  "geometry": {"coordinates":[-85.86166,41.28949],"type":"Point"}
}