{
  "type": "Feature",
  "properties": {
    "gn:admin1_code":"IL",
    "gn:admin2_code":"127.0",
    "gn:asciiname":"Unionville",
    "gn:country_code":"US",
    "gn:dem":114,
    "gn:elevation":"113.0",
    "gn:feature_class":"P",
    "gn:feature_code":"PPL",
    "gn:name":"Unionville",
    "gn:population":0,
    "gn:timezone":"America/Chicago",
    "iso:country":"US",
    "name:eng_x_preferred":[
        "Unionville"
    ],
    "name:fas_x_preferred":[
        "\u06cc\u0648\u0646\u06cc\u0648\u0646\u0648\u06cc\u0644"
    ],
    "name:und_x_variant":[
        "Union Village"
    ],
    "name:urd_x_preferred":[
        "\u06cc\u0648\u0646\u06cc\u0646\u0648\u06cc\u0644"
    ],
    "wof:name":"Unionville",
    "wof:placetype":"locality"
},
  "geometry": {"coordinates":[-88.54671,37.12228],"type":"Point"}
}