{
  "type": "Feature",
  "properties": {
    "gn:admin1_code":"NC",
    "gn:admin2_code":"161",
    "gn:admin3_code":"91892.0",
    "gn:asciiname":"Logan",
    "gn:country_code":"US",
    "gn:dem":273,
    "gn:elevation":"271.0",
    "gn:feature_class":"P",
    "gn:feature_code":"PPL",
    "gn:name":"Logan",
    "gn:population":0,
    "gn:timezone":"America/New_York",
    "iso:country":"US",
    "name:bel_x_preferred":[
        "\u041b\u043e\u0433\u0430\u043d"
    ],
    "name:ceb_x_preferred":[
        "Logan"
    ],
    "name:ces_x_preferred":[
        "Logan"
    ],
    "name:cym_x_preferred":[
        "Logan"
    ],
    "name:deu_x_preferred":[
        "Logan"
    ],
    "name:eng_x_preferred":[
        "Logan"
    ],
    "name:fas_x_preferred":[
        "\u0644\u0648\u06af\u0627\u0646"
    ],
    "name:fin_x_preferred":[
        "Logan"
    ],
    "name:fra_x_preferred":[
        "Logan"
    ],
    "name:heb_x_preferred":[
        "\u05dc\u05d5\u05d2\u05df"
    ],
    "name:hun_x_preferred":[
        "Logan"
    ],
    "name:ita_x_preferred":[
        "Logan"
    ],
    "name:jpn_x_preferred":[
        "\u30ed\u30fc\u30ac\u30f3"
    ],
    "name:nld_x_preferred":[
        "Logan"
    ],
    "name:pol_x_preferred":[
        "Logan"
    ],
    "name:por_x_preferred":[
        "Logan"
    ],
    "name:ron_x_preferred":[
        "Logan"
    ],
    "name:rus_x_preferred":[
        "\u041b\u043e\u0433\u0430\u043d"
    ],
    "name:spa_x_preferred":[
        "Logan"
    ],
    "name:srp_x_preferred":[
        "\u041b\u043e\u0433\u0430\u043d"
    ],
    "name:swe_x_preferred":[
        "Logan"
    ],
    "name:tgk_x_preferred":[
        "\u041b\u043e\u0433\u0430\u043d"
    ],
    "name:tur_x_preferred":[
        "Logan"
    ],
    "name:ukr_x_preferred":[
        "\u041b\u043e\u0433\u0430\u043d"
    ],
    "name:und_x_variant":[
        "Logan Station",
        "Itom",
        "Iton"
    ],
    "name:vie_x_preferred":[
        "Logan"
    ],
    "name:vol_x_preferred":[
        "Logan"
    ],
    "wof:name":"Logan",
    "wof:placetype":"locality"
},
  "geometry": {"coordinates":[-81.89927,35.42735],"type":"Point"}
}