{
  "type": "Feature",
  "properties": {
    "gn:admin1_code":"MS",
    "gn:admin2_code":"77.0",
    "gn:asciiname":"Arm",
    "gn:country_code":"US",
    "gn:dem":80,
    "gn:elevation":"74.0",
    "gn:feature_class":"P",
    "gn:feature_code":"PPL",
    "gn:name":"Arm",
    "gn:population":0,
    "gn:timezone":"America/Chicago",
    "iso:country":"US",
    "wof:name":"Arm",
    "wof:placetype":"locality"
},
  "geometry": {"coordinates":[-90.01619000000002,31.50295],"type":"Point"}
}