{
  "type": "Feature",
  "properties": {
    "gn:admin1_code":"MN",
    "gn:admin2_code":"93.0",
    "gn:admin3_code":"25730.0",
    "gn:asciiname":"Beckville",
    "gn:country_code":"US",
    "gn:dem":362,
    "gn:elevation":"363.0",
    "gn:feature_class":"P",
    "gn:feature_code":"PPL",
    "gn:name":"Beckville",
    "gn:population":0,
    "gn:timezone":"America/Chicago",
    "iso:country":"US",
    "name:fas_x_preferred":[
        "\u0628\u06a9\u0648\u06cc\u0644"
    ],
    "wof:name":"Beckville",
    "wof:placetype":"locality"
},
  "geometry": {"coordinates":[-94.56388,45.04441],"type":"Point"}
}