{
  "type": "Feature",
  "properties": {
    "gn:country":"US",
    "gn:fcode":"PPL",
    "gn:population":0,
    "iso:country":"US",
    "name:eng_x_preferred":[
        "Altamont"
    ],
    "name:fas_x_preferred":[
        "\u0627\u0644\u062a\u0627\u0645\u0627\u0646\u062a\u060c \u0634\u0645\u0627\u0644 \u06a9\u0627\u0631\u0648\u0644\u06cc\u0646\u0627"
    ],
    "name:fas_x_variant":[
        "\u0627\u0644\u062a\u0627\u0645\u0627\u0646\u062a"
    ],
    "name:fra_x_preferred":[
        "Altamont"
    ],
    "name:jpn_x_preferred":[
        "\u30a2\u30eb\u30bf\u30e2\u30f3\u30c8"
    ],
    "qs_pg:aaroncc":"US",
    "qs_pg:gn_country":"US",
    "qs_pg:gn_fcode":"PPL",
    "qs_pg:gn_pop":0,
    "qs_pg:name":"Altamont",
    "qs_pg:name_adm0":"United States",
    "qs_pg:name_adm1":"North Carolina",
    "qs_pg:photos":6,
    "qs_pg:photos_1k":1,
    "qs_pg:photos_9k":1,
    "qs_pg:photos_9r":1,
    "qs_pg:photos_all":6,
    "qs_pg:photos_sr":1,
    "qs_pg:pop_sr":0,
    "qs_pg:qs_pg_placetype":"locality",
    "qs_pg:qs_pg_placetype_gp":"Town",
    "qs_pg:woe_adm0":23424977,
    "woe:adm0_id":23424977,
    "woe:name_adm0":"United States",
    "woe:name_adm1":"North Carolina",
    "woe:placetype":"Town",
    "wof:name":"Altamont",
    "wof:placetype":"locality"
},
  "geometry": {"coordinates":[-81.94428000000001,35.99096],"type":"Point"}
}