{
  "type": "Feature",
  "properties": {
    "gn:admin1_code":"MI",
    "gn:admin2_code":"105.0",
    "gn:admin3_code":"73060.0",
    "gn:asciiname":"Millerton",
    "gn:country_code":"US",
    "gn:dem":220,
    "gn:elevation":"219.0",
    "gn:feature_class":"P",
    "gn:feature_code":"PPL",
    "gn:name":"Millerton",
    "gn:population":0,
    "gn:timezone":"America/Detroit",
    "iso:country":"US",
    "name:cat_x_preferred":[
        "Millerton"
    ],
    "name:ceb_x_preferred":[
        "Millerton"
    ],
    "name:deu_x_preferred":[
        "Millerton"
    ],
    "name:fra_x_preferred":[
        "Millerton"
    ],
    "name:ita_x_preferred":[
        "Millerton"
    ],
    "name:nld_x_preferred":[
        "Millerton"
    ],
    "name:pol_x_preferred":[
        "Millerton"
    ],
    "name:por_x_preferred":[
        "Millerton"
    ],
    "name:srp_x_preferred":[
        "\u041c\u0438\u043b\u0435\u0440\u0442\u043e\u043d"
    ],
    "name:vol_x_preferred":[
        "Millerton"
    ],
    "wof:name":"Millerton",
    "wof:placetype":"locality"
},
  "geometry": {"coordinates":[-86.05034999999999,44.03973],"type":"Point"}
}