{
  "type": "Feature",
  "properties": {
    "gn:admin1_code":"MD",
    "gn:admin2_code":"3.0",
    "gn:asciiname":"Merrywood Manor",
    "gn:country_code":"US",
    "gn:dem":48,
    "gn:elevation":"43.0",
    "gn:feature_class":"P",
    "gn:feature_code":"PPL",
    "gn:name":"Merrywood Manor",
    "gn:population":0,
    "gn:timezone":"America/New_York",
    "iso:country":"US",
    "wof:name":"Merrywood Manor",
    "wof:placetype":"locality"
},
  "geometry": {"coordinates":[-76.63441,38.89845],"type":"Point"}
}