{
  "type": "Feature",
  "properties": {
    "gn:admin1_code":"WV",
    "gn:admin2_code":"69.0",
    "gn:asciiname":"Leewood Park",
    "gn:country_code":"US",
    "gn:dem":358,
    "gn:elevation":"363.0",
    "gn:feature_class":"P",
    "gn:feature_code":"PPL",
    "gn:name":"Leewood Park",
    "gn:population":0,
    "gn:timezone":"America/New_York",
    "iso:country":"US",
    "wof:name":"Leewood Park",
    "wof:placetype":"locality"
},
  "geometry": {"coordinates":[-80.65146999999997,40.10452],"type":"Point"}
}