{
  "type": "Feature",
  "properties": {
    "gn:admin1_code":"NC",
    "gn:admin2_code":"171.0",
    "gn:admin3_code":"90412.0",
    "gn:asciiname":"Mountain Park",
    "gn:country_code":"US",
    "gn:dem":388,
    "gn:elevation":"392.0",
    "gn:feature_class":"P",
    "gn:feature_code":"PPL",
    "gn:name":"Mountain Park",
    "gn:population":0,
    "gn:timezone":"America/New_York",
    "iso:country":"US",
    "name:azb_x_preferred":[
        "\u0645\u0627\u0648\u0646\u062a\u06cc\u0646 \u067e\u0627\u0631\u06a9"
    ],
    "name:fas_x_preferred":[
        "\u0645\u0627\u0648\u0646\u062a\u06cc\u0646 \u067e\u0627\u0631\u06a9"
    ],
    "name:spa_x_preferred":[
        "Mountain Park"
    ],
    "name:vol_x_preferred":[
        "Mountain Park"
    ],
    "wof:name":"Mountain Park",
    "wof:placetype":"locality"
},
  "geometry": {"coordinates":[-80.85479000000002,36.3743],"type":"Point"}
}