{
  "type": "Feature",
  "properties": {
    "gn:admin1_code":"MD",
    "gn:admin2_code":"35.0",
    "gn:asciiname":"Shipping Creek",
    "gn:country_code":"US",
    "gn:dem":3,
    "gn:elevation":"4.0",
    "gn:feature_class":"P",
    "gn:feature_code":"PPL",
    "gn:name":"Shipping Creek",
    "gn:population":0,
    "gn:timezone":"America/New_York",
    "iso:country":"US",
    "wof:name":"Shipping Creek",
    "wof:placetype":"locality"
},
  "geometry": {"coordinates":[-76.33995,38.91817],"type":"Point"}
}