{
  "type": "Feature",
  "properties": {
    "iso:country":"US",
    "name:eng_x_preferred":[
        "Fairmount"
    ],
    "name:unk_x_variant":[
        "Fairmount"
    ],
    "qs:gn_adm0_cc":"US",
    "qs:gn_fcode":"PPL",
    "qs:gn_local":4391812,
    "qs:gn_nam_loc":"Independence, Jackson, Missouri, US",
    "qs:gn_namadm1":"MO",
    "qs:gn_name":"Fairmount",
    "qs:local_max":1662,
    "qs:local_sum":3548,
    "qs:localhoods":8,
    "qs:name":"Fairmount",
    "qs:name_adm0":"United States",
    "qs:name_adm1":"Missouri",
    "qs:name_adm2":"Jackson",
    "qs:name_local":"Independence",
    "qs:photo_max":41,
    "qs:photo_sum":41,
    "qs:placetype":"Suburb",
    "qs:quad_count":1,
    "qs:woe_adm0":23424977,
    "qs:woe_adm1":2347584,
    "qs:woe_adm2":12589013,
    "qs:woe_lau":0,
    "qs:woe_local":2426709,
    "qs:woe_ver":"7.10.0",
    "wof:lang":[
        "eng"
    ],
    "wof:name":"Fairmount",
    "wof:placetype":"neighbourhood",
    "wof:population":31,
    "zs:blockids":[
        290950111002010,
        290950111002016
    ],
    "zs:housing10":12,
    "zs:pop10":31
},
  "geometry": {"coordinates":[-94.43435700000001,39.11834],"type":"Point"}
}