{
  "type": "Feature",
  "properties": {
    "iso:country":"US",
    "qs_pg:aaroncc":"US",
    "qs_pg:name":"Billarp",
    "qs_pg:name_adm0":"United States",
    "qs_pg:name_adm1":"Georgia",
    "qs_pg:photos":80,
    "qs_pg:photos_1k":16,
    "qs_pg:photos_9k":1,
    "qs_pg:photos_9r":3,
    "qs_pg:photos_all":80,
    "qs_pg:photos_sr":3,
    "qs_pg:pop_sr":0,
    "qs_pg:qs_pg_placetype":"locality",
    "qs_pg:qs_pg_placetype_gp":"Town",
    "qs_pg:woe_adm0":23424977,
    "woe:adm0_id":23424977,
    "woe:name_adm0":"United States",
    "woe:name_adm1":"Georgia",
    "woe:placetype":"Town",
    "wof:name":"Billarp",
    "wof:placetype":"locality"
},
  "geometry": {"coordinates":[-84.80624,33.671354],"type":"Point"}
}