{
  "type": "Feature",
  "properties": {
    "gn:admin1_code":"KY",
    "gn:admin2_code":"57",
    "gn:asciiname":"Waterview",
    "gn:country_code":"US",
    "gn:dem":175,
    "gn:elevation":"174.0",
    "gn:feature_class":"P",
    "gn:feature_code":"PPL",
    "gn:name":"Waterview",
    "gn:population":0,
    "gn:timezone":"America/Chicago",
    "iso:country":"US",
    "wof:name":"Waterview",
    "wof:placetype":"locality"
},
  "geometry": {"coordinates":[-85.45829999999999,36.817],"type":"Point"}
}