{
  "type": "Feature",
  "properties": {
    "gn:admin1_code":"VA",
    "gn:admin2_code":"1.0",
    "gn:asciiname":"Chincoteague Island",
    "gn:country_code":"US",
    "gn:dem":3,
    "gn:feature_class":"P",
    "gn:feature_code":"PPL",
    "gn:name":"Chincoteague Island",
    "gn:population":0,
    "gn:timezone":"America/New_York",
    "iso:country":"US",
    "wof:name":"Chincoteague Island",
    "wof:placetype":"locality"
},
  "geometry": {"coordinates":[-75.36243,37.92994],"type":"Point"}
}