{
  "type": "Feature",
  "properties": {
    "gn:admin1_code":"KY",
    "gn:admin2_code":"53",
    "gn:asciiname":"Huntersville",
    "gn:country_code":"US",
    "gn:dem":278,
    "gn:elevation":"278.0",
    "gn:feature_class":"P",
    "gn:feature_code":"PPL",
    "gn:name":"Huntersville",
    "gn:population":0,
    "gn:timezone":"America/Chicago",
    "iso:country":"US",
    "name:deu_x_preferred":[
        "Huntersville"
    ],
    "name:fra_x_preferred":[
        "Huntersville"
    ],
    "name:pol_x_preferred":[
        "Huntersville"
    ],
    "name:srp_x_preferred":[
        "\u0425\u0430\u043d\u0442\u0435\u0440\u0441\u0432\u0438\u043b"
    ],
    "name:vol_x_preferred":[
        "Huntersville"
    ],
    "wof:name":"Huntersville",
    "wof:placetype":"locality"
},
  "geometry": {"coordinates":[-85.13551,36.62479],"type":"Point"}
}