{
  "type": "Feature",
  "properties": {
    "gn:country":"US",
    "gn:fcode":"ADMD",
    "gn:population":0,
    "iso:country":"US",
    "name:ara_x_preferred":[
        "\u0628\u0644\u062f\u0629 \u0647\u0627\u0645\u064a\u0644\u062a\u0648\u0646\u060c \u0645\u0642\u0627\u0637\u0639\u0629 \u063a\u0631\u062a\u064a\u0648\u062a"
    ],
    "name:ara_x_variant":[
        "\u0628\u0644\u062f\u0629 \u0647\u0627\u0645\u064a\u0644\u062a\u0648\u0646"
    ],
    "name:ben_x_preferred":[
        "\u09b9\u09cd\u09af\u09be\u09ae\u09bf\u09b2\u09cd\u099f\u09a8"
    ],
    "name:deu_x_preferred":[
        "Hamilton"
    ],
    "name:ell_x_preferred":[
        "\u03a7\u03ac\u03bc\u03b9\u03bb\u03c4\u03bf\u03bd"
    ],
    "name:eng_x_preferred":[
        "Hamilton Township"
    ],
    "name:fas_x_preferred":[
        "\u0646\u0627\u062d\u06cc\u0647 \u0647\u0645\u06cc\u0644\u062a\u0648\u0646"
    ],
    "name:fra_x_preferred":[
        "Hamilton"
    ],
    "name:heb_x_preferred":[
        "\u05d4\u05de\u05d9\u05dc\u05d8\u05d5\u05df"
    ],
    "name:hin_x_preferred":[
        "\u0939\u0948\u092e\u093f\u0932\u094d\u091f\u0928"
    ],
    "name:hun_x_preferred":[
        "Hamilton"
    ],
    "name:ind_x_preferred":[
        "Hamilton"
    ],
    "name:ita_x_preferred":[
        "Hamilton"
    ],
    "name:jpn_x_preferred":[
        "\u30cf\u30df\u30eb\u30c8\u30f3"
    ],
    "name:kor_x_preferred":[
        "\ud574\ubc00\ud134"
    ],
    "name:nld_x_preferred":[
        "Hamilton"
    ],
    "name:pol_x_preferred":[
        "Hamilton"
    ],
    "name:por_x_preferred":[
        "Hamilton"
    ],
    "name:rus_x_preferred":[
        "\u0413\u0430\u043c\u0438\u043b\u044c\u0442\u043e\u043d"
    ],
    "name:spa_x_preferred":[
        "Municipio de Hamilton"
    ],
    "name:swe_x_preferred":[
        "Hamilton"
    ],
    "name:tur_x_preferred":[
        "Hamilton"
    ],
    "name:ukr_x_preferred":[
        "\u0413\u0430\u043c\u0456\u043b\u044c\u0442\u043e\u043d"
    ],
    "name:urd_x_preferred":[
        "\u06c1\u06cc\u0645\u0644\u0679\u0646"
    ],
    "name:vie_x_preferred":[
        "Hamilton"
    ],
    "name:vie_x_variant":[
        "X\u00e3 Hamilton"
    ],
    "name:zho_cn_x_preferred":[
        "\u54c8\u5bc6\u5c14\u987f"
    ],
    "name:zho_tw_x_preferred":[
        "\u6f22\u7c73\u9813"
    ],
    "qs_pg:aaroncc":"US",
    "qs_pg:gn_country":"US",
    "qs_pg:gn_fcode":"ADMD",
    "qs_pg:gn_pop":0,
    "qs_pg:name":"Hamilton",
    "qs_pg:name_adm0":"United States",
    "qs_pg:name_adm1":"Michigan",
    "qs_pg:photos_9k":1,
    "qs_pg:photos_9r":1,
    "qs_pg:photos_all":5,
    "qs_pg:photos_sr":0,
    "qs_pg:pop_sr":0,
    "qs_pg:qs_pg_placetype":"locality",
    "qs_pg:qs_pg_placetype_gp":"Town",
    "qs_pg:woe_adm0":23424977,
    "woe:adm0_id":23424977,
    "woe:name_adm0":"United States",
    "woe:name_adm1":"Michigan",
    "woe:placetype":"Town",
    "wof:coterminous":[
        404505679
    ],
    "wof:name":"Hamilton",
    "wof:placetype":"locality",
    "wof:statistical_gore":1
},
  "geometry": {"coordinates":[-84.42359999999999,43.25114],"type":"Point"}
}