{
  "type": "Feature",
  "properties": {
    "gn:country":"US",
    "gn:fcode":"ADMD",
    "gn:population":0,
    "iso:country":"US",
    "name:ara_x_preferred":[
        "\u0628\u0644\u062f\u0629 \u0647\u0627\u0645\u064a\u0644\u062a\u0648\u0646\u060c \u0645\u0642\u0627\u0637\u0639\u0629 \u063a\u0631\u062a\u064a\u0648\u062a"
    ],
    "name:ara_x_variant":[
        "\u0628\u0644\u062f\u0629 \u0647\u0627\u0645\u064a\u0644\u062a\u0648\u0646"
    ],
    "name:eng_x_preferred":[
        "Hamilton Township"
    ],
    "name:spa_x_preferred":[
        "Municipio de Hamilton"
    ],
    "name:vie_x_preferred":[
        "X\u00e3 Hamilton"
    ],
    "qs_pg:aaroncc":"US",
    "qs_pg:gn_country":"US",
    "qs_pg:gn_fcode":"ADMD",
    "qs_pg:gn_pop":0,
    "qs_pg:name":"Hamilton",
    "qs_pg:name_adm0":"United States",
    "qs_pg:name_adm1":"Michigan",
    "qs_pg:photos_9k":1,
    "qs_pg:photos_9r":1,
    "qs_pg:photos_all":5,
    "qs_pg:photos_sr":0,
    "qs_pg:pop_sr":0,
    "qs_pg:qs_pg_placetype":"locality",
    "qs_pg:qs_pg_placetype_gp":"Town",
    "qs_pg:woe_adm0":23424977,
    "woe:adm0_id":23424977,
    "woe:name_adm0":"United States",
    "woe:name_adm1":"Michigan",
    "woe:placetype":"Town",
    "wof:name":"Hamilton",
    "wof:placetype":"locality"
},
  "geometry": {"coordinates":[-84.42359999999999,43.25114],"type":"Point"}
}