{
  "type": "Feature",
  "properties": {
    "gn:admin1_code":"NY",
    "gn:admin2_code":"011",
    "gn:admin3_code":"10297.0",
    "gn:asciiname":"Pump Corners",
    "gn:country_code":"US",
    "gn:dem":126,
    "gn:elevation":"122.0",
    "gn:feature_class":"P",
    "gn:feature_code":"PPL",
    "gn:name":"Pump Corners",
    "gn:population":0,
    "gn:timezone":"America/New_York",
    "iso:country":"US",
    "wof:name":"Pump Corners",
    "wof:placetype":"locality"
},
  "geometry": {"coordinates":[-76.50166999999998,43.06667],"type":"Point"}
}