{
  "type": "Feature",
  "properties": {
    "gn:admin1_code":"ID",
    "gn:admin2_code":"19.0",
    "gn:asciiname":"Gray",
    "gn:country_code":"US",
    "gn:dem":1951,
    "gn:elevation":"1951.0",
    "gn:feature_class":"P",
    "gn:feature_code":"PPL",
    "gn:name":"Gray",
    "gn:population":0,
    "gn:timezone":"America/Boise",
    "iso:country":"US",
    "wof:name":"Gray",
    "wof:placetype":"locality"
},
  "geometry": {"coordinates":[-111.37911,43.04992],"type":"Point"}
}