{
  "type": "Feature",
  "properties": {
    "gn:admin1_code":"MN",
    "gn:admin2_code":"75.0",
    "gn:admin3_code":"60304.0",
    "gn:asciiname":"Whyte",
    "gn:country_code":"US",
    "gn:dem":585,
    "gn:elevation":"586.0",
    "gn:feature_class":"P",
    "gn:feature_code":"PPL",
    "gn:name":"Whyte",
    "gn:population":0,
    "gn:timezone":"America/Chicago",
    "iso:country":"US",
    "name:deu_x_preferred":[
        "Whyte"
    ],
    "name:fra_x_preferred":[
        "Whyte"
    ],
    "name:ita_x_preferred":[
        "Whyte"
    ],
    "name:rus_x_preferred":[
        "\u0423\u0430\u0439\u0442"
    ],
    "wof:name":"Whyte",
    "wof:placetype":"locality"
},
  "geometry": {"coordinates":[-91.56211,47.45158],"type":"Point"}
}