{
  "type": "Feature",
  "properties": {
    "gn:admin1_code":"SC",
    "gn:admin2_code":"35.0",
    "gn:asciiname":"University Park",
    "gn:country_code":"US",
    "gn:dem":8,
    "gn:elevation":"12.0",
    "gn:feature_class":"P",
    "gn:feature_code":"PPL",
    "gn:name":"University Park",
    "gn:population":0,
    "gn:timezone":"America/New_York",
    "iso:country":"US",
    "name:ceb_x_preferred":[
        "University Park"
    ],
    "name:deu_x_preferred":[
        "University Park"
    ],
    "name:fra_x_preferred":[
        "University Park"
    ],
    "name:ita_x_preferred":[
        "University Park"
    ],
    "name:nld_x_preferred":[
        "University Park"
    ],
    "name:pol_x_preferred":[
        "University Park"
    ],
    "name:por_x_preferred":[
        "University Park"
    ],
    "name:rus_x_preferred":[
        "\u042e\u043d\u0438\u0432\u0435\u0440\u0441\u0438\u0442\u0438-\u041f\u0430\u0440\u043a"
    ],
    "name:srp_x_preferred":[
        "\u0408\u0443\u043d\u0438\u0432\u0435\u0440\u0441\u0438\u0442\u0438 \u041f\u0430\u0440\u043a"
    ],
    "name:vol_x_preferred":[
        "University Park"
    ],
    "wof:name":"University Park",
    "wof:placetype":"locality"
},
  "geometry": {"coordinates":[-80.09509,32.91962],"type":"Point"}
}