{
  "type": "Feature",
  "properties": {
    "gn:admin1_code":"MD",
    "gn:admin2_code":"5.0",
    "gn:asciiname":"Blenheim",
    "gn:country_code":"US",
    "gn:dem":172,
    "gn:elevation":"168.0",
    "gn:feature_class":"P",
    "gn:feature_code":"PPL",
    "gn:name":"Blenheim",
    "gn:population":0,
    "gn:timezone":"America/New_York",
    "iso:country":"US",
    "name:ceb_x_preferred":[
        "Blenheim"
    ],
    "name:dan_x_preferred":[
        "Blenheim"
    ],
    "name:deu_x_preferred":[
        "Blenheim"
    ],
    "name:fas_x_preferred":[
        "\u0628\u0644\u0646\u0647\u0627\u06cc\u0645"
    ],
    "name:fra_x_preferred":[
        "Blenheim"
    ],
    "name:heb_x_preferred":[
        "\u05d1\u05dc\u05d9\u05d9\u05e0\u05d4\u05d9\u05d9\u05dd"
    ],
    "name:heb_x_variant":[
        "\u05d1\u05dc\u05e0\u05d4\u05d9\u05d9\u05dd"
    ],
    "name:hun_x_preferred":[
        "Blenheim"
    ],
    "name:ita_x_preferred":[
        "Blenheim"
    ],
    "name:jpn_x_preferred":[
        "\u30d6\u30ec\u30cb\u30e0"
    ],
    "name:kor_x_preferred":[
        "\ube14\ub808\ub118"
    ],
    "name:mkd_x_preferred":[
        "\u0411\u043b\u0435\u043d\u0435\u043c"
    ],
    "name:nld_x_preferred":[
        "Blenheim"
    ],
    "name:nor_x_preferred":[
        "Blenheim"
    ],
    "name:pol_x_preferred":[
        "Blenheim"
    ],
    "name:ron_x_preferred":[
        "Blenheim"
    ],
    "name:rus_x_preferred":[
        "\u0411\u043b\u0435\u043d\u0445\u0435\u0439\u043c"
    ],
    "name:spa_x_preferred":[
        "Blenheim"
    ],
    "name:swe_x_preferred":[
        "Blenheim"
    ],
    "name:ukr_x_preferred":[
        "\u0411\u043b\u0435\u043d\u0433\u0435\u0439\u043c"
    ],
    "wof:name":"Blenheim",
    "wof:placetype":"locality"
},
  "geometry": {"coordinates":[-76.54608,39.48955],"type":"Point"}
}