{
  "type": "Feature",
  "properties": {
    "gn:admin1_code":"MS",
    "gn:admin2_code":"133.0",
    "gn:asciiname":"Roundaway",
    "gn:country_code":"US",
    "gn:dem":38,
    "gn:elevation":"36.0",
    "gn:feature_class":"P",
    "gn:feature_code":"PPL",
    "gn:name":"Roundaway",
    "gn:population":0,
    "gn:timezone":"America/Chicago",
    "iso:country":"US",
    "wof:name":"Roundaway",
    "wof:placetype":"locality"
},
  "geometry": {"coordinates":[-90.6062,33.58484],"type":"Point"}
}