{
  "type": "Feature",
  "properties": {
    "iso:country":"US",
    "name:eng_x_preferred":[
        "La Paz South"
    ],
    "wof:name":"La Paz South",
    "wof:placetype":"neighbourhood",
    "wof:population":2010,
    "zs:area_m":1032881.032743,
    "zs:blockids":[
        60590320121029,
        60590320121004,
        60590320121023,
        60590320033008,
        60590320121021,
        60590320121020,
        60590320121028,
        60590320121017,
        60590320033009,
        60590320121002,
        60590320122006,
        60590320121016,
        60590320121026,
        60590320121001,
        60590320121018,
        60590320032018,
        60590320121012,
        60590320122003,
        60590320122001,
        60590320121032,
        60590320122004,
        60590320121027,
        60590320121024,
        60590320121019,
        60590320121000,
        60590320121022
    ],
    "zs:housing10":662,
    "zs:label":"La Paz South",
    "zs:pop10":2010
},
  "geometry": {"coordinates":[-117.665904,33.596756],"type":"Point"}
}