{
  "type": "Feature",
  "properties": {
    "gn:admin1_code":"AL",
    "gn:admin2_code":"117",
    "gn:asciiname":"Kingdom Crossroads",
    "gn:country_code":"US",
    "gn:dem":146,
    "gn:elevation":"140.0",
    "gn:feature_class":"P",
    "gn:feature_code":"PPL",
    "gn:name":"Kingdom Crossroads",
    "gn:population":0,
    "gn:timezone":"America/Chicago",
    "iso:country":"US",
    "wof:name":"Kingdom Crossroads",
    "wof:placetype":"locality"
},
  "geometry": {"coordinates":[-86.55498,33.16095],"type":"Point"}
}