{
  "type": "Feature",
  "properties": {
    "gn:admin1_code":"NC",
    "gn:admin2_code":"65.0",
    "gn:asciiname":"Webbs",
    "gn:country_code":"US",
    "gn:dem":35,
    "gn:elevation":"34.0",
    "gn:feature_class":"P",
    "gn:feature_code":"PPL",
    "gn:name":"Webbs",
    "gn:population":0,
    "gn:timezone":"America/New_York",
    "iso:country":"US",
    "wof:name":"Webbs",
    "wof:placetype":"locality"
},
  "geometry": {"coordinates":[-77.68609000000002,35.73488],"type":"Point"}
}