{
  "type": "Feature",
  "properties": {
    "gn:admin1_code":"KY",
    "gn:admin2_code":"203",
    "gn:asciiname":"Boone",
    "gn:country_code":"US",
    "gn:dem":314,
    "gn:elevation":"316.0",
    "gn:feature_class":"P",
    "gn:feature_code":"PPL",
    "gn:name":"Boone",
    "gn:population":0,
    "gn:timezone":"America/New_York",
    "iso:country":"US",
    "name:bul_x_preferred":[
        "\u0411\u0443\u043d"
    ],
    "name:ceb_x_preferred":[
        "Boone"
    ],
    "name:deu_x_preferred":[
        "Boone"
    ],
    "name:fin_x_preferred":[
        "Boone"
    ],
    "name:fra_x_preferred":[
        "Boone"
    ],
    "name:ita_x_preferred":[
        "Boone"
    ],
    "name:jpn_x_preferred":[
        "\u30d6\u30fc\u30f3"
    ],
    "name:nld_x_preferred":[
        "Boone"
    ],
    "name:pol_x_preferred":[
        "Boone"
    ],
    "name:por_x_preferred":[
        "Boone"
    ],
    "name:rus_x_preferred":[
        "\u0411\u0443\u043d"
    ],
    "name:srp_x_preferred":[
        "\u0411\u0443\u043d"
    ],
    "name:swe_x_preferred":[
        "Boone"
    ],
    "name:ukr_x_preferred":[
        "\u0411\u0443\u043d"
    ],
    "name:vol_x_preferred":[
        "Boone"
    ],
    "wof:name":"Boone",
    "wof:placetype":"locality"
},
  "geometry": {"coordinates":[-84.31659999999999,37.51758],"type":"Point"}
}