{
  "type": "Feature",
  "properties": {
    "iso:country":"US",
    "name:deu_x_preferred":[
        "Ormond"
    ],
    "name:nds_x_preferred":[
        "Ormond"
    ],
    "name:por_x_preferred":[
        "Ormond"
    ],
    "qs_pg:aaroncc":"US",
    "qs_pg:name":"Ormond",
    "qs_pg:name_adm0":"United States",
    "qs_pg:name_adm1":"Louisiana",
    "qs_pg:photos":1,
    "qs_pg:photos_1k":1,
    "qs_pg:photos_9k":1,
    "qs_pg:photos_9r":1,
    "qs_pg:photos_all":1,
    "qs_pg:photos_sr":1,
    "qs_pg:pop_sr":0,
    "qs_pg:qs_pg_placetype":"locality",
    "qs_pg:qs_pg_placetype_gp":"Town",
    "qs_pg:woe_adm0":23424977,
    "woe:adm0_id":23424977,
    "woe:name_adm0":"United States",
    "woe:name_adm1":"Louisiana",
    "woe:placetype":"Town",
    "wof:name":"Ormond",
    "wof:placetype":"locality"
},
  "geometry": {"coordinates":[-90.382509,29.96383],"type":"Point"}
}