{
  "type": "Feature",
  "properties": {
    "gn:admin1_code":"TX",
    "gn:admin2_code":"291",
    "gn:asciiname":"Fuqua",
    "gn:country_code":"US",
    "gn:dem":39,
    "gn:elevation":"35.0",
    "gn:feature_class":"P",
    "gn:feature_code":"PPL",
    "gn:name":"Fuqua",
    "gn:population":0,
    "gn:timezone":"America/Chicago",
    "iso:country":"US",
    "wof:name":"Fuqua",
    "wof:placetype":"locality"
},
  "geometry": {"coordinates":[-94.73632000000001,30.44715],"type":"Point"}
}