{
  "type": "Feature",
  "properties": {
    "gn:admin1_code":"GA",
    "gn:admin2_code":"181.0",
    "gn:asciiname":"Martins Crossroads",
    "gn:country_code":"US",
    "gn:dem":148,
    "gn:elevation":"144.0",
    "gn:feature_class":"P",
    "gn:feature_code":"PPL",
    "gn:name":"Martins Crossroads",
    "gn:population":0,
    "gn:timezone":"America/New_York",
    "iso:country":"US",
    "name:eng_x_preferred":[
        "Martins Crossroads"
    ],
    "name:und_x_variant":[
        "Kena",
        "Kenna"
    ],
    "wof:name":"Martins Crossroads",
    "wof:placetype":"locality"
},
  "geometry": {"coordinates":[-82.37179,33.77235],"type":"Point"}
}