{
  "type": "Feature",
  "properties": {
    "gn:country":"US",
    "gn:fcode":"PPL",
    "gn:population":180,
    "iso:country":"US",
    "name:azb_x_preferred":[
        "\u0645\u0627\u062f\u0631\u06cc\u062f"
    ],
    "name:ben_x_preferred":[
        "\u09ae\u09be\u09a6\u09cd\u09b0\u09bf\u09a6"
    ],
    "name:deu_x_preferred":[
        "Madrid"
    ],
    "name:eng_x_preferred":[
        "Madrid"
    ],
    "name:fas_x_preferred":[
        "\u0645\u0627\u062f\u0631\u06cc\u062f"
    ],
    "name:fra_x_preferred":[
        "Madrid"
    ],
    "name:hin_x_preferred":[
        "\u092e\u0948\u0921\u094d\u0930\u093f\u0921"
    ],
    "name:jpn_x_preferred":[
        "\u30de\u30c9\u30ea\u30c3\u30c9"
    ],
    "name:pol_x_preferred":[
        "Madrid"
    ],
    "name:spa_x_preferred":[
        "Madrid"
    ],
    "name:urd_x_preferred":[
        "\u0645\u06cc\u0688\u0631\u0688\u060c \u0645\u0627\u0626\u06cc\u0646\u06cc"
    ],
    "name:urd_x_variant":[
        "\u0645\u06cc\u0688\u0631\u0688"
    ],
    "qs_pg:aaroncc":"US",
    "qs_pg:gn_country":"US",
    "qs_pg:gn_fcode":"PPL",
    "qs_pg:gn_pop":180,
    "qs_pg:name":"Madrid",
    "qs_pg:name_adm0":"United States",
    "qs_pg:name_adm1":"Maine",
    "qs_pg:photos":81,
    "qs_pg:photos_1k":16,
    "qs_pg:photos_9k":1,
    "qs_pg:photos_9r":3,
    "qs_pg:photos_all":83,
    "qs_pg:photos_sr":3,
    "qs_pg:pop_sr":1,
    "qs_pg:qs_pg_placetype":"locality",
    "qs_pg:qs_pg_placetype_gp":"Town",
    "qs_pg:woe_adm0":23424977,
    "woe:adm0_id":23424977,
    "woe:name_adm0":"United States",
    "woe:name_adm1":"Maine",
    "woe:placetype":"Town",
    "wof:name":"Madrid",
    "wof:placetype":"locality",
    "wof:population":180
},
  "geometry": {"coordinates":[-70.46201000000001,44.8645],"type":"Point"}
}