{
  "type": "Feature",
  "properties": {
    "iso:country":"US",
    "name:eng_x_preferred":[
        "Lions Gate at Regency"
    ],
    "qs:gn_adm0_cc":"US",
    "qs:gn_local":4459467,
    "qs:gn_nam_loc":"Cary, Wake, North Carolina, US",
    "qs:gn_namadm1":"NC",
    "qs:local_max":1353,
    "qs:local_sum":11778,
    "qs:localhoods":52,
    "qs:name":"Lions Gate at Regency",
    "qs:name_adm0":"United States",
    "qs:name_adm1":"North Carolina",
    "qs:name_adm2":"Wake",
    "qs:name_local":"Cary",
    "qs:photo_max":104,
    "qs:photo_sum":219,
    "qs:placetype":"Suburb",
    "qs:quad_count":5,
    "qs:woe_adm0":23424977,
    "qs:woe_adm1":2347592,
    "qs:woe_adm2":12589465,
    "qs:woe_lau":0,
    "qs:woe_local":2375810,
    "qs:woe_ver":"7.10.0",
    "wof:lang":[
        "eng"
    ],
    "wof:name":"Lions Gate at Regency",
    "wof:placetype":"neighbourhood",
    "wof:population":151,
    "zs:blockids":[
        371830534052023,
        371830534052003,
        371830534053004,
        371830534053005,
        371830534052026,
        371830534052021,
        371830534052022,
        371830534053006
    ],
    "zs:housing10":71,
    "zs:pop10":151
},
  "geometry": {"coordinates":[-78.79508800000001,35.728809],"type":"Point"}
}