{
  "type": "Feature",
  "properties": {
    "gn:admin1_code":"NE",
    "gn:admin2_code":"145.0",
    "gn:asciiname":"Youngs Trailer Court",
    "gn:country_code":"US",
    "gn:dem":729,
    "gn:elevation":"726.0",
    "gn:feature_class":"P",
    "gn:feature_code":"PPL",
    "gn:name":"Youngs Trailer Court",
    "gn:population":0,
    "gn:timezone":"America/Chicago",
    "iso:country":"US",
    "wof:name":"Youngs Trailer Court",
    "wof:placetype":"locality"
},
  "geometry": {"coordinates":[-100.41737000000001,40.23445],"type":"Point"}
}