{
  "type": "Feature",
  "properties": {
    "gn:admin1_code":"NC",
    "gn:admin2_code":"141",
    "gn:admin3_code":"90444.0",
    "gn:asciiname":"Twin Oaks Mobile Home Park",
    "gn:country_code":"US",
    "gn:dem":14,
    "gn:elevation":"16.0",
    "gn:feature_class":"P",
    "gn:feature_code":"PPL",
    "gn:name":"Twin Oaks Mobile Home Park",
    "gn:population":0,
    "gn:timezone":"America/New_York",
    "iso:country":"US",
    "wof:name":"Twin Oaks Mobile Home Park",
    "wof:placetype":"campus"
},
  "geometry": {"coordinates":[-77.89749999999999,34.499],"type":"Point"}
}