{
  "type": "Feature",
  "properties": {
    "gn:admin1_code":"WI",
    "gn:admin2_code":"61.0",
    "gn:admin3_code":"85775.0",
    "gn:asciiname":"Krok",
    "gn:country_code":"US",
    "gn:dem":222,
    "gn:elevation":"222.0",
    "gn:feature_class":"P",
    "gn:feature_code":"PPL",
    "gn:name":"Krok",
    "gn:population":0,
    "gn:timezone":"America/Chicago",
    "iso:country":"US",
    "name:eng_x_preferred":[
        "Krok"
    ],
    "name:und_x_variant":[
        "Norman"
    ],
    "wof:name":"Krok",
    "wof:placetype":"locality"
},
  "geometry": {"coordinates":[-87.63314,44.42889],"type":"Point"}
}