{
  "type": "Feature",
  "properties": {
    "gn:admin1_code":"MO",
    "gn:admin2_code":"125.0",
    "gn:admin3_code":"36872.0",
    "gn:asciiname":"Lindell",
    "gn:country_code":"US",
    "gn:dem":311,
    "gn:elevation":"311.0",
    "gn:feature_class":"P",
    "gn:feature_code":"PPL",
    "gn:name":"Lindell",
    "gn:population":0,
    "gn:timezone":"America/Chicago",
    "iso:country":"US",
    "name:deu_x_preferred":[
        "Lindell"
    ],
    "name:fin_x_preferred":[
        "Lindell"
    ],
    "name:fra_x_preferred":[
        "Lindell"
    ],
    "wof:name":"Lindell",
    "wof:placetype":"locality"
},
  "geometry": {"coordinates":[-91.79183,38.17088],"type":"Point"}
}