{
  "type": "Feature",
  "properties": {
    "gn:admin1_code":"TN",
    "gn:admin2_code":"89",
    "gn:asciiname":"Fairview Heights",
    "gn:country_code":"US",
    "gn:dem":329,
    "gn:elevation":"327.0",
    "gn:feature_class":"P",
    "gn:feature_code":"PPL",
    "gn:name":"Fairview Heights",
    "gn:population":0,
    "gn:timezone":"America/New_York",
    "iso:country":"US",
    "name:deu_x_preferred":[
        "Fairview Heights"
    ],
    "wof:name":"Fairview Heights",
    "wof:placetype":"locality"
},
  "geometry": {"coordinates":[-83.52516999999997,35.97287],"type":"Point"}
}