{
  "type": "Feature",
  "properties": {
    "gn:admin1_code":"MO",
    "gn:admin2_code":"33.0",
    "gn:admin3_code":"76552.0",
    "gn:asciiname":"W B Junction",
    "gn:country_code":"US",
    "gn:dem":208,
    "gn:elevation":"203.0",
    "gn:feature_class":"P",
    "gn:feature_code":"PPL",
    "gn:name":"W B Junction",
    "gn:population":0,
    "gn:timezone":"America/Chicago",
    "iso:country":"US",
    "name:eng_x_preferred":[
        "W B Junction"
    ],
    "name:und_x_variant":[
        "Carrollton Junction"
    ],
    "wof:name":"W B Junction",
    "wof:placetype":"locality"
},
  "geometry": {"coordinates":[-93.53021,39.33502],"type":"Point"}
}