{
  "type": "Feature",
  "properties": {
    "gn:admin1_code":"MO",
    "gn:admin2_code":"171.0",
    "gn:admin3_code":"74896.0",
    "gn:asciiname":"Unionville",
    "gn:country_code":"US",
    "gn:dem":327,
    "gn:elevation":"324.0",
    "gn:feature_class":"P",
    "gn:feature_code":"PPLA2",
    "gn:name":"Unionville",
    "gn:population":1815,
    "gn:timezone":"America/Chicago",
    "iso:country":"US",
    "name:azb_x_preferred":[
        "\u06cc\u0648\u0646\u06cc\u0648\u0646 \u0648\u06cc\u0644"
    ],
    "name:cat_x_preferred":[
        "Unionville"
    ],
    "name:ceb_x_preferred":[
        "Unionville"
    ],
    "name:eng_x_preferred":[
        "Unionville"
    ],
    "name:eus_x_preferred":[
        "Unionville"
    ],
    "name:fas_x_preferred":[
        "\u06cc\u0648\u0646\u06cc\u0648\u0646 \u0648\u06cc\u0644"
    ],
    "name:fra_x_preferred":[
        "Unionville"
    ],
    "name:hat_x_preferred":[
        "Unionville"
    ],
    "name:ido_x_preferred":[
        "Unionville"
    ],
    "name:ita_x_preferred":[
        "Unionville"
    ],
    "name:kaz_x_preferred":[
        "\u042e\u043d\u0438\u043e\u043d\u0432\u0438\u043b\u043b"
    ],
    "name:kir_x_preferred":[
        "\u042e\u043d\u0438\u043e\u043d\u0432\u0438\u043b\u043b"
    ],
    "name:nld_x_preferred":[
        "Unionville"
    ],
    "name:pol_x_preferred":[
        "Unionville"
    ],
    "name:por_x_preferred":[
        "Unionville"
    ],
    "name:rus_x_preferred":[
        "\u0423\u043d\u0430\u0439\u043e\u043d\u0432\u0438\u043b\u043b"
    ],
    "name:spa_x_preferred":[
        "Unionville"
    ],
    "name:srp_x_preferred":[
        "\u0408\u0443\u043d\u0438\u043e\u043d\u0432\u0438\u043b"
    ],
    "name:swe_x_preferred":[
        "Unionville"
    ],
    "name:und_x_variant":[
        "Harmony"
    ],
    "name:urd_x_preferred":[
        "\u06cc\u0648\u0646\u06cc\u0646\u0648\u06cc\u0644"
    ],
    "name:uzb_x_preferred":[
        "Unionville"
    ],
    "name:vol_x_preferred":[
        "Unionville"
    ],
    "wof:name":"Unionville",
    "wof:placetype":"locality",
    "wof:population":1815
},
  "geometry": {"coordinates":[-93.00326,40.47696],"type":"Point"}
}