{
  "type": "Feature",
  "properties": {
    "gn:admin1_code":"TN",
    "gn:admin2_code":"65.0",
    "gn:asciiname":"Ridgewood Acres",
    "gn:country_code":"US",
    "gn:dem":254,
    "gn:elevation":"248.0",
    "gn:feature_class":"P",
    "gn:feature_code":"PPL",
    "gn:name":"Ridgewood Acres",
    "gn:population":0,
    "gn:timezone":"America/New_York",
    "iso:country":"US",
    "wof:name":"Ridgewood Acres",
    "wof:placetype":"locality"
},
  "geometry": {"coordinates":[-85.24468,35.05285],"type":"Point"}
}