{
  "type": "Feature",
  "properties": {
    "gn:country":"US",
    "gn:fcode":"PPL",
    "gn:population":0,
    "iso:country":"US",
    "name:azb_x_preferred":[
        "\u0645\u062f\u0648\u0648\u06cc\u0648"
    ],
    "name:ceb_x_preferred":[
        "Meadowview"
    ],
    "name:che_x_preferred":[
        "\u041c\u0435\u0434\u043e\u0443\u0432\u044a\u044e"
    ],
    "name:cym_x_preferred":[
        "Meadowview"
    ],
    "name:deu_x_preferred":[
        "Meadowview"
    ],
    "name:eng_x_preferred":[
        "Meadowview"
    ],
    "name:eus_x_preferred":[
        "Meadowview"
    ],
    "name:fas_x_preferred":[
        "\u0645\u062f\u0648\u0648\u06cc\u0648"
    ],
    "name:fra_x_preferred":[
        "Meadowview"
    ],
    "name:gle_x_preferred":[
        "Meadowview"
    ],
    "name:ita_x_preferred":[
        "Meadowview"
    ],
    "name:lld_x_preferred":[
        "Meadowview"
    ],
    "name:mlg_x_preferred":[
        "Meadowview"
    ],
    "name:spa_x_preferred":[
        "Meadowview"
    ],
    "name:srp_x_preferred":[
        "\u041c\u0435\u0434\u043e\u0443 \u0412\u0458\u0443"
    ],
    "name:tat_x_preferred":[
        "\u041c\u0435\u0434\u043e\u0443\u0432\u044a\u044e"
    ],
    "name:ukr_x_preferred":[
        "\u041c\u0435\u0434\u043e\u0443\u0432'\u044e"
    ],
    "name:und_x_variant":[
        "Meadow View"
    ],
    "qs_pg:aaroncc":"US",
    "qs_pg:gn_country":"US",
    "qs_pg:gn_fcode":"PPL",
    "qs_pg:gn_pop":0,
    "qs_pg:name":"Meadowview",
    "qs_pg:name_adm0":"United States",
    "qs_pg:name_adm1":"Virginia",
    "qs_pg:photos":73,
    "qs_pg:photos_1k":15,
    "qs_pg:photos_9k":1,
    "qs_pg:photos_9r":2,
    "qs_pg:photos_all":73,
    "qs_pg:photos_sr":2,
    "qs_pg:pop_sr":5,
    "qs_pg:qs_pg_placetype":"locality",
    "qs_pg:qs_pg_placetype_gp":"Town",
    "qs_pg:woe_adm0":23424977,
    "woe:adm0_id":23424977,
    "woe:name_adm0":"United States",
    "woe:name_adm1":"Virginia",
    "woe:placetype":"Town",
    "wof:name":"Meadowview",
    "wof:placetype":"locality",
    "wof:population":967
},
  "geometry": {"coordinates":[-81.8629,36.76039],"type":"Point"}
}