{
  "type": "Feature",
  "properties": {
    "gn:admin1_code":"SD",
    "gn:admin2_code":"105.0",
    "gn:admin3_code":"45575.0",
    "gn:asciiname":"Coal Springs",
    "gn:country_code":"US",
    "gn:dem":783,
    "gn:elevation":"785.0",
    "gn:feature_class":"P",
    "gn:feature_code":"PPL",
    "gn:name":"Coal Springs",
    "gn:population":0,
    "gn:timezone":"America/Denver",
    "iso:country":"US",
    "wof:name":"Coal Springs",
    "wof:placetype":"locality"
},
  "geometry": {"coordinates":[-102.10766,45.44165],"type":"Point"}
}