{
  "type": "Feature",
  "properties": {
    "gn:admin1_code":"DE",
    "gn:admin2_code":"1.0",
    "gn:asciiname":"Melvin Crossroads",
    "gn:country_code":"US",
    "gn:dem":18,
    "gn:elevation":"19.0",
    "gn:feature_class":"P",
    "gn:feature_code":"PPL",
    "gn:name":"Melvin Crossroads",
    "gn:population":0,
    "gn:timezone":"America/New_York",
    "iso:country":"US",
    "name:eng_x_preferred":[
        "Melvin Crossroads"
    ],
    "name:und_x_variant":[
        "Melvin Corners",
        "Melvins Corner"
    ],
    "wof:name":"Melvin Crossroads",
    "wof:placetype":"locality"
},
  "geometry": {"coordinates":[-75.72104,38.91872],"type":"Point"}
}