{
  "type": "Feature",
  "properties": {
    "gn:admin1_code":"TX",
    "gn:admin2_code":"215.0",
    "gn:asciiname":"Que Pasa Acres Colonia",
    "gn:country_code":"US",
    "gn:dem":55,
    "gn:elevation":"52.0",
    "gn:feature_class":"P",
    "gn:feature_code":"PPL",
    "gn:name":"Que Pasa Acres Colonia",
    "gn:population":0,
    "gn:timezone":"America/Chicago",
    "iso:country":"US",
    "name:eng_x_preferred":[
        "Que Pasa Acres Colonia"
    ],
    "name:und_x_variant":[
        "Que Pasa Acres Subdivision Colonia"
    ],
    "wof:name":"Que Pasa Acres Colonia",
    "wof:placetype":"locality"
},
  "geometry": {"coordinates":[-98.36141000000001,26.25535],"type":"Point"}
}