{
  "type": "Feature",
  "properties": {
    "gn:admin1_code":"PA",
    "gn:admin2_code":"15.0",
    "gn:admin3_code":"80984.0",
    "gn:asciiname":"Warrenham",
    "gn:country_code":"US",
    "gn:dem":419,
    "gn:elevation":"418.0",
    "gn:feature_class":"P",
    "gn:feature_code":"PPL",
    "gn:name":"Warrenham",
    "gn:population":0,
    "gn:timezone":"America/New_York",
    "iso:country":"US",
    "wof:name":"Warrenham",
    "wof:placetype":"locality"
},
  "geometry": {"coordinates":[-76.15271,41.97174],"type":"Point"}
}