{
  "type": "Feature",
  "properties": {
    "gn:admin1_code":"MO",
    "gn:admin2_code":"133.0",
    "gn:admin3_code":"48926.0",
    "gn:asciiname":"Thirtyfour Corner",
    "gn:country_code":"US",
    "gn:dem":92,
    "gn:elevation":"92.0",
    "gn:feature_class":"P",
    "gn:feature_code":"PPL",
    "gn:name":"Thirtyfour Corner",
    "gn:population":0,
    "gn:timezone":"America/Chicago",
    "iso:country":"US",
    "wof:name":"Thirtyfour Corner",
    "wof:placetype":"locality"
},
  "geometry": {"coordinates":[-89.2109,36.77672000000001],"type":"Point"}
}