{
  "type": "Feature",
  "properties": {
    "gn:admin1_code":"TX",
    "gn:admin2_code":"377.0",
    "gn:asciiname":"Casa Piedra",
    "gn:country_code":"US",
    "gn:dem":1048,
    "gn:elevation":"1049.0",
    "gn:feature_class":"P",
    "gn:feature_code":"PPL",
    "gn:name":"Casa Piedra",
    "gn:population":0,
    "gn:timezone":"America/Chicago",
    "iso:country":"US",
    "wof:name":"Casa Piedra",
    "wof:placetype":"locality"
},
  "geometry": {"coordinates":[-104.05409,29.73851],"type":"Point"}
}