{
  "type": "Feature",
  "properties": {
    "gn:admin1_code":"PA",
    "gn:admin2_code":"69.0",
    "gn:admin3_code":"29504.0",
    "gn:asciiname":"Humphreysville",
    "gn:country_code":"US",
    "gn:dem":324,
    "gn:elevation":"319.0",
    "gn:feature_class":"P",
    "gn:feature_code":"PPL",
    "gn:name":"Humphreysville",
    "gn:population":0,
    "gn:timezone":"America/New_York",
    "iso:country":"US",
    "wof:name":"Humphreysville",
    "wof:placetype":"locality"
},
  "geometry": {"coordinates":[-75.72547,41.51841],"type":"Point"}
}