{
  "type": "Feature",
  "properties": {
    "gn:admin1_code":"NC",
    "gn:admin2_code":"69.0",
    "gn:admin3_code":"92822.0",
    "gn:asciiname":"Oswego",
    "gn:country_code":"US",
    "gn:dem":118,
    "gn:elevation":"117.0",
    "gn:feature_class":"P",
    "gn:feature_code":"PPL",
    "gn:name":"Oswego",
    "gn:population":0,
    "gn:timezone":"America/New_York",
    "iso:country":"US",
    "wof:name":"Oswego",
    "wof:placetype":"locality"
},
  "geometry": {"coordinates":[-78.19721,36.15015],"type":"Point"}
}