{
  "type": "Feature",
  "properties": {
    "gn:admin1_code":"MO",
    "gn:admin2_code":"173.0",
    "gn:admin3_code":"65378.0",
    "gn:asciiname":"Hassard",
    "gn:country_code":"US",
    "gn:dem":226,
    "gn:elevation":"225.0",
    "gn:feature_class":"P",
    "gn:feature_code":"PPL",
    "gn:name":"Hassard",
    "gn:population":0,
    "gn:timezone":"America/Chicago",
    "iso:country":"US",
    "wof:name":"Hassard",
    "wof:placetype":"locality"
},
  "geometry": {"coordinates":[-91.6596,39.65699],"type":"Point"}
}