{
  "type": "Feature",
  "properties": {
    "gn:elevation":44,
    "iso:country":"US",
    "name:eng_x_preferred":[
        "Thrasher's Corner"
    ],
    "name:eng_x_variant":[
        "Thrashers Cor",
        "Thrashers Corner"
    ],
    "qs:gn_adm0_cc":"US",
    "qs:gn_fcode":"PPL",
    "qs:gn_local":5787829,
    "qs:gn_nam_loc":"Bothell, King, Washington, US",
    "qs:gn_namadm1":"WA",
    "qs:gn_name":"Thrashers Corner",
    "qs:local_max":1024,
    "qs:local_sum":5156,
    "qs:localhoods":13,
    "qs:name":"Thrasher's Corner",
    "qs:name_adm0":"United States",
    "qs:name_adm1":"Washington",
    "qs:name_adm2":"Snohomish",
    "qs:name_local":"Bothell",
    "qs:photo_max":172,
    "qs:photo_sum":521,
    "qs:placetype":"Suburb",
    "qs:quad_count":27,
    "qs:woe_adm0":23424977,
    "qs:woe_adm1":2347606,
    "qs:woe_adm2":12590470,
    "qs:woe_lau":0,
    "qs:woe_local":2367188,
    "qs:woe_ver":"7.10.0",
    "wof:lang":[
        "eng"
    ],
    "wof:name":"Thrasher's Corner",
    "wof:placetype":"neighbourhood",
    "wof:population":6731,
    "zs:blockids":[
        530610519252006,
        530610519241009,
        530610519243011,
        530610519243012,
        530610519241013,
        530610519241006,
        530610519241011,
        530610519241019,
        530610519223012,
        530610519241000,
        530610519212004,
        530610519252015,
        530610519252007,
        530610519242003,
        530610519213002,
        530610519252013,
        530610519241018,
        530610519243006,
        530610519241008,
        530610519242010,
        530610519242002,
        530610519243014,
        530610519223013,
        530610519222001,
        530610519242001,
        530610519241002,
        530610519243008,
        530610519241015,
        530610519252005,
        530610519241005,
        530610519242009,
        530610519223011,
        530610519213008,
        530610519241021,
        530610519252014,
        530610519241004,
        530610519212007,
        530610519243005,
        530610519241001,
        530610519212002,
        530610519241010,
        530610519223000,
        530610519243009,
        530610519222004,
        530610519252021,
        530610519212003,
        530610519241023,
        530610519252020,
        530610519212005,
        530610519212001,
        530610519222011,
        530610519242014,
        530610519252012,
        530610519212006,
        530610519242000,
        530610519241012,
        530610519241003,
        530610519241007,
        530610519241016,
        530610519222000,
        530610519212000,
        530610519243015,
        530610519242012,
        530610519242013,
        530610519223014,
        530610519241014,
        530610519243007,
        530610519241020,
        530610519243016,
        530610519241017,
        530610519241022,
        530610519242011
    ],
    "zs:housing10":3143,
    "zs:pop10":6731
},
  "geometry": {"coordinates":[-122.19843899999999,47.817619],"type":"Point"}
}