{
  "type": "Feature",
  "properties": {
    "iso:country":"US",
    "name:eng_x_preferred":[
        "Betty Jean Heights"
    ],
    "wof:name":"Betty Jean Heights",
    "wof:placetype":"neighbourhood",
    "wof:population":108,
    "zs:area_m":483745.734643,
    "zs:blockids":[
        120570010024001,
        120570018002015,
        120570010024000,
        120570018002014,
        120570105022021,
        120570018002000
    ],
    "zs:housing10":45,
    "zs:label":"Betty Jean Heights",
    "zs:pop10":108
},
  "geometry": {"coordinates":[-82.400954,27.998174],"type":"Point"}
}