{
  "type": "Feature",
  "properties": {
    "gn:admin1_code":"IL",
    "gn:admin2_code":"81",
    "gn:admin3_code":"51193.0",
    "gn:asciiname":"Idlewood",
    "gn:country_code":"US",
    "gn:dem":167,
    "gn:elevation":"167.0",
    "gn:feature_class":"P",
    "gn:feature_code":"PPL",
    "gn:name":"Idlewood",
    "gn:population":0,
    "gn:timezone":"America/Chicago",
    "iso:country":"US",
    "wof:name":"Idlewood",
    "wof:placetype":"locality"
},
  "geometry": {"coordinates":[-88.92284000000002,38.38033],"type":"Point"}
}