{
  "type": "Feature",
  "properties": {
    "gn:admin1_code":"KY",
    "gn:admin2_code":"149.0",
    "gn:asciiname":"Wrightsburg",
    "gn:country_code":"US",
    "gn:dem":131,
    "gn:elevation":"128.0",
    "gn:feature_class":"P",
    "gn:feature_code":"PPL",
    "gn:name":"Wrightsburg",
    "gn:population":0,
    "gn:timezone":"America/Chicago",
    "iso:country":"US",
    "wof:name":"Wrightsburg",
    "wof:placetype":"locality"
},
  "geometry": {"coordinates":[-87.40306,37.59143],"type":"Point"}
}