{
  "type": "Feature",
  "properties": {
    "gn:admin1_code":"CO",
    "gn:admin2_code":"99.0",
    "gn:asciiname":"Culp",
    "gn:country_code":"US",
    "gn:dem":1117,
    "gn:elevation":"1114.0",
    "gn:feature_class":"P",
    "gn:feature_code":"PPL",
    "gn:name":"Culp",
    "gn:population":0,
    "gn:timezone":"America/Denver",
    "iso:country":"US",
    "wof:name":"Culp",
    "wof:placetype":"locality"
},
  "geometry": {"coordinates":[-102.60936,38.13584],"type":"Point"}
}