{
  "type": "Feature",
  "properties": {
    "gn:admin1_code":"CA",
    "gn:admin2_code":"111.0",
    "gn:asciiname":"Strickland Acres",
    "gn:country_code":"US",
    "gn:dem":36,
    "gn:elevation":"35.0",
    "gn:feature_class":"P",
    "gn:feature_code":"PPL",
    "gn:name":"Strickland Acres",
    "gn:population":0,
    "gn:timezone":"America/Los_Angeles",
    "iso:country":"US",
    "wof:name":"Strickland Acres",
    "wof:placetype":"locality"
},
  "geometry": {"coordinates":[-119.14955,34.25834],"type":"Point"}
}