{
  "type": "Feature",
  "properties": {
    "gn:admin1_code":"DE",
    "gn:admin2_code":"3.0",
    "gn:asciiname":"The Timbers",
    "gn:country_code":"US",
    "gn:dem":91,
    "gn:elevation":"87.0",
    "gn:feature_class":"P",
    "gn:feature_code":"PPL",
    "gn:name":"The Timbers",
    "gn:population":0,
    "gn:timezone":"America/New_York",
    "iso:country":"US",
    "wof:name":"The Timbers",
    "wof:placetype":"locality"
},
  "geometry": {"coordinates":[-75.47909,39.82567],"type":"Point"}
}