{
  "type": "Feature",
  "properties": {
    "iso:country":"US",
    "name:eng_x_preferred":[
        "Willemette"
    ],
    "qs:gn_adm0_cc":"US",
    "qs:gn_local":4257227,
    "qs:gn_nam_loc":"Evansville, Vanderburgh, Indiana, US",
    "qs:gn_namadm1":"IN",
    "qs:local_max":7165,
    "qs:local_sum":16261,
    "qs:localhoods":34,
    "qs:name":"Willemette",
    "qs:name_adm0":"United States",
    "qs:name_adm1":"Indiana",
    "qs:name_adm2":"Vanderburgh",
    "qs:name_local":"Evansville",
    "qs:photo_max":13,
    "qs:photo_sum":14,
    "qs:placetype":"Suburb",
    "qs:quad_count":2,
    "qs:woe_adm0":23424977,
    "qs:woe_adm1":2347573,
    "qs:woe_adm2":12588261,
    "qs:woe_lau":0,
    "qs:woe_local":2400767,
    "qs:woe_ver":"7.10.0",
    "wof:lang":[
        "eng"
    ],
    "wof:name":"Willemette",
    "wof:placetype":"neighbourhood",
    "wof:population":1779,
    "zs:blockids":[
        181630001002014,
        181630001001027,
        181630001002002,
        181630001001031,
        181630001002006,
        181630001002013,
        181630001002007,
        181630001003006,
        181630001003010,
        181630001003000,
        181630001001002,
        181630001002008,
        181630001003004,
        181630001001029,
        181630001002003,
        181630001002015,
        181630001001016,
        181630001001014,
        181630001003008,
        181630001001004,
        181630001001015,
        181630001001021,
        181630001002017,
        181630001003009,
        181630001003001,
        181630001002010,
        181630001002011,
        181630001002001,
        181630001002009,
        181630001001026,
        181630001001030,
        181630001001006,
        181630001001020,
        181630001001007,
        181630001001012,
        181630001003007,
        181630001002012,
        181630001003002,
        181630001001028,
        181630001001005,
        181630001001019,
        181630001002005,
        181630001002016,
        181630001003003,
        181630001003011,
        181630001001003,
        181630001001017,
        181630001001018,
        181630001002018,
        181630001001009,
        181630001001013,
        181630001003005,
        181630001002004
    ],
    "zs:housing10":986,
    "zs:pop10":1779
},
  "geometry": {"coordinates":[-87.54142,37.998636],"type":"Point"}
}