{
  "type": "Feature",
  "properties": {
    "gn:country":"US",
    "gn:fcode":"PPL",
    "gn:population":0,
    "iso:country":"US",
    "name:ara_x_preferred":[
        "\u0648\u064a\u0633\u062a\u0641\u0648\u0631\u062f"
    ],
    "name:arz_x_preferred":[
        "\u0648\u064a\u0633\u062a\u0641\u0648\u0631\u062f"
    ],
    "name:azb_x_preferred":[
        "\u0648\u0632\u062a\u0641\u0648\u0631\u062f"
    ],
    "name:che_x_preferred":[
        "\u0412\u0435\u0441\u0442\u0444\u043e\u0440\u0434"
    ],
    "name:deu_x_preferred":[
        "Westford"
    ],
    "name:eng_x_preferred":[
        "Westford"
    ],
    "name:eus_x_preferred":[
        "Westford"
    ],
    "name:fra_x_preferred":[
        "Westford"
    ],
    "name:hat_x_preferred":[
        "Westford"
    ],
    "name:hun_x_preferred":[
        "Westford"
    ],
    "name:lld_x_preferred":[
        "Westford"
    ],
    "name:spa_x_preferred":[
        "Westford"
    ],
    "name:tat_x_preferred":[
        "\u0412\u0435\u0441\u0442\u0444\u043e\u0440\u0434"
    ],
    "name:tur_x_preferred":[
        "Westford"
    ],
    "name:ukr_x_preferred":[
        "\u0412\u0435\u0441\u0442\u0444\u043e\u0440\u0434"
    ],
    "name:uzb_x_preferred":[
        "Westford"
    ],
    "qs_pg:aaroncc":"US",
    "qs_pg:gn_country":"US",
    "qs_pg:gn_fcode":"PPL",
    "qs_pg:gn_pop":0,
    "qs_pg:name":"Westford",
    "qs_pg:name_adm0":"United States",
    "qs_pg:name_adm1":"New York",
    "qs_pg:photos":421,
    "qs_pg:photos_1k":85,
    "qs_pg:photos_9k":2,
    "qs_pg:photos_9r":5,
    "qs_pg:photos_all":421,
    "qs_pg:photos_sr":6,
    "qs_pg:pop_sr":0,
    "qs_pg:qs_pg_placetype":"locality",
    "qs_pg:qs_pg_placetype_gp":"Town",
    "qs_pg:woe_adm0":23424977,
    "woe:adm0_id":23424977,
    "woe:name_adm0":"United States",
    "woe:name_adm1":"New York",
    "woe:placetype":"Town",
    "wof:coterminous":[
        404523041
    ],
    "wof:name":"Westford",
    "wof:placetype":"locality",
    "wof:statistical_gore":1
},
  "geometry": {"coordinates":[-74.79765,42.65008],"type":"Point"}
}