{
  "type": "Feature",
  "properties": {
    "gn:admin1_code":"IL",
    "gn:admin2_code":"187.0",
    "gn:admin3_code":"42847.0",
    "gn:asciiname":"Phelps",
    "gn:country_code":"US",
    "gn:dem":235,
    "gn:elevation":"236.0",
    "gn:feature_class":"P",
    "gn:feature_code":"PPL",
    "gn:name":"Phelps",
    "gn:population":0,
    "gn:timezone":"America/Chicago",
    "iso:country":"US",
    "name:bul_x_preferred":[
        "\u0424\u0435\u043b\u043f\u0441"
    ],
    "name:cat_x_preferred":[
        "Phelps"
    ],
    "name:ceb_x_preferred":[
        "Phelps"
    ],
    "name:ces_x_preferred":[
        "Phelps"
    ],
    "name:deu_x_preferred":[
        "Phelps"
    ],
    "name:epo_x_preferred":[
        "Phelps"
    ],
    "name:fin_x_preferred":[
        "Phelps"
    ],
    "name:fra_x_preferred":[
        "Phelps"
    ],
    "name:heb_x_preferred":[
        "\u05e4\u05dc\u05e4\u05e1"
    ],
    "name:ita_x_preferred":[
        "Phelps"
    ],
    "name:jpn_x_preferred":[
        "\u30d5\u30a7\u30eb\u30d7\u30b9"
    ],
    "name:kor_x_preferred":[
        "\ud3a0\ud504\uc2a4"
    ],
    "name:nds_x_preferred":[
        "Phelps"
    ],
    "name:nld_x_preferred":[
        "Phelps"
    ],
    "name:pol_x_preferred":[
        "Phelps"
    ],
    "name:por_x_preferred":[
        "Phelps"
    ],
    "name:rus_x_preferred":[
        "\u0424\u0435\u043b\u043f\u0441"
    ],
    "name:srp_x_preferred":[
        "\u0424\u0435\u043b\u043f\u0441"
    ],
    "name:tur_x_preferred":[
        "Phelps"
    ],
    "name:ukr_x_preferred":[
        "\u0424\u0435\u043b\u043f\u0441"
    ],
    "name:vol_x_preferred":[
        "Phelps"
    ],
    "wof:name":"Phelps",
    "wof:placetype":"locality"
},
  "geometry": {"coordinates":[-90.57486,40.84865],"type":"Point"}
}