{
  "type": "Feature",
  "properties": {
    "gn:admin1_code":"OH",
    "gn:admin2_code":"19.0",
    "gn:admin3_code":"28126.0",
    "gn:asciiname":"Wattsville",
    "gn:country_code":"US",
    "gn:dem":317,
    "gn:elevation":"316.0",
    "gn:feature_class":"P",
    "gn:feature_code":"PPL",
    "gn:name":"Wattsville",
    "gn:population":0,
    "gn:timezone":"America/New_York",
    "iso:country":"US",
    "name:eng_x_preferred":[
        "Wattsville"
    ],
    "name:und_x_variant":[
        "Wattsville Station"
    ],
    "wof:name":"Wattsville",
    "wof:placetype":"locality"
},
  "geometry": {"coordinates":[-80.93286999999999,40.5734],"type":"Point"}
}