{
  "type": "Feature",
  "properties": {
    "gn:country":"US",
    "gn:fcode":"PPL",
    "gn:population":0,
    "iso:country":"US",
    "name:eng_x_preferred":[
        "Upper Stepney"
    ],
    "name:und_x_variant":[
        "Birdsley Plain"
    ],
    "qs_pg:aaroncc":"US",
    "qs_pg:gn_country":"US",
    "qs_pg:gn_fcode":"PPL",
    "qs_pg:gn_pop":0,
    "qs_pg:name":"Upper Stepney",
    "qs_pg:name_adm0":"United States",
    "qs_pg:name_adm1":"Connecticut",
    "qs_pg:photos":86,
    "qs_pg:photos_1k":17,
    "qs_pg:photos_9k":1,
    "qs_pg:photos_9r":3,
    "qs_pg:photos_all":86,
    "qs_pg:photos_sr":3,
    "qs_pg:pop_sr":0,
    "qs_pg:qs_pg_placetype":"locality",
    "qs_pg:qs_pg_placetype_gp":"Town",
    "qs_pg:woe_adm0":23424977,
    "woe:adm0_id":23424977,
    "woe:name_adm0":"United States",
    "woe:name_adm1":"Connecticut",
    "woe:placetype":"Town",
    "wof:name":"Upper Stepney",
    "wof:placetype":"locality"
},
  "geometry": {"coordinates":[-73.26512,41.3226],"type":"Point"}
}