{
  "type": "Feature",
  "properties": {
    "gn:admin1_code":"NM",
    "gn:admin2_code":"57",
    "gn:asciiname":"Glover Place",
    "gn:country_code":"US",
    "gn:dem":2130,
    "gn:elevation":"2123.0",
    "gn:feature_class":"P",
    "gn:feature_code":"PPL",
    "gn:name":"Glover Place",
    "gn:population":0,
    "gn:timezone":"America/Denver",
    "iso:country":"US",
    "wof:name":"Glover Place",
    "wof:placetype":"locality"
},
  "geometry": {"coordinates":[-106.29558,34.80089],"type":"Point"}
}