{
  "type": "Feature",
  "properties": {
    "iso:country":"US",
    "name:eng_x_preferred":[
        "South Durham"
    ],
    "qs:gn_adm0_cc":"US",
    "qs:gn_local":4464368,
    "qs:local_max":5486,
    "qs:local_sum":39943,
    "qs:localhoods":72,
    "qs:name":"South Durham",
    "qs:name_adm0":"United States",
    "qs:name_adm1":"North Carolina",
    "qs:name_adm2":"Durham",
    "qs:name_local":"Durham",
    "qs:photo_max":194,
    "qs:photo_sum":451,
    "qs:placetype":"Suburb",
    "qs:quad_count":24,
    "qs:woe_adm0":23424977,
    "qs:woe_adm1":2347592,
    "qs:woe_adm2":12589405,
    "qs:woe_funk":"Grouping neighborhood",
    "qs:woe_lau":0,
    "qs:woe_local":2394734,
    "qs:woe_ver":"7.10.0",
    "wof:name":"South Durham",
    "wof:placetype":"neighbourhood",
    "wof:population":7640,
    "zs:blockids":[
        370630020261003,
        370630020251010,
        370630020251019,
        370630020251015,
        370630020241038,
        370630020262032,
        370630020251000,
        370630020251009,
        370630020251017,
        370630020251004,
        370630020272003,
        370630020251013,
        370630020262031,
        370630020251011,
        370630020252006,
        370630020252011,
        370630020251018,
        370630020262033,
        370630020251005,
        370630020272002,
        370630020251020,
        370630020222000,
        370630020261004,
        370630020262015,
        370630020262009,
        370630020272005,
        370630020252003,
        370630020252010,
        370630020222001,
        370630020252000,
        370630020252001,
        370630020272000,
        370630020252004,
        370630020251014,
        370630020252012,
        370630020252009,
        370630020251006,
        370630020252002,
        370630020262010,
        370630020261006,
        370630020222008,
        370630020251008,
        370630020251012,
        370630020262024,
        370630020243002,
        370630020251016
    ],
    "zs:housing10":3259,
    "zs:pop10":7640
},
  "geometry": {"coordinates":[-78.93284300000001,35.920216],"type":"Point"}
}