{
  "type": "Feature",
  "properties": {
    "gn:admin1_code":"MD",
    "gn:admin2_code":"13.0",
    "gn:asciiname":"Hillandale Trailer Park",
    "gn:country_code":"US",
    "gn:dem":184,
    "gn:elevation":"191.0",
    "gn:feature_class":"P",
    "gn:feature_code":"PPL",
    "gn:name":"Hillandale Trailer Park",
    "gn:population":0,
    "gn:timezone":"America/New_York",
    "iso:country":"US",
    "wof:name":"Hillandale Trailer Park",
    "wof:placetype":"campus"
},
  "geometry": {"coordinates":[-76.90748000000001,39.50871],"type":"Point"}
}