{
  "type": "Feature",
  "properties": {
    "iso:country":"US",
    "name:eng_x_preferred":[
        "Artesian Heights"
    ],
    "wof:name":"Artesian Heights",
    "wof:placetype":"neighbourhood",
    "wof:population":284,
    "zs:area_m":295143.312816,
    "zs:blockids":[
        261251582002020,
        261251582002022,
        261251582002021,
        261251582003018,
        261251582003017
    ],
    "zs:housing10":130,
    "zs:label":"Artesian Heights",
    "zs:pop10":284
},
  "geometry": {"coordinates":[-83.207982,42.51947],"type":"Point"}
}