{
  "type": "Feature",
  "properties": {
    "gn:admin1_code":"KY",
    "gn:admin2_code":"235",
    "gn:asciiname":"Carpenter",
    "gn:country_code":"US",
    "gn:dem":315,
    "gn:elevation":"310.0",
    "gn:feature_class":"P",
    "gn:feature_code":"PPL",
    "gn:name":"Carpenter",
    "gn:population":0,
    "gn:timezone":"America/New_York",
    "iso:country":"US",
    "wof:name":"Carpenter",
    "wof:placetype":"locality"
},
  "geometry": {"coordinates":[-83.97131999999998,36.71592],"type":"Point"}
}