{
  "type": "Feature",
  "properties": {
    "gn:admin1_code":"HI",
    "gn:admin2_code":"1.0",
    "gn:asciiname":"Kuka'iau",
    "gn:country_code":"US",
    "gn:dem":250,
    "gn:elevation":"249.0",
    "gn:feature_class":"P",
    "gn:feature_code":"PPL",
    "gn:name":"K\u016bka\u2018iau",
    "gn:population":0,
    "gn:timezone":"Pacific/Honolulu",
    "iso:country":"US",
    "name:eng_x_preferred":[
        "K\u016bka\u2018iau"
    ],
    "name:haw_x_preferred":[
        "K\u016bka\u2018iau"
    ],
    "name:und_x_variant":[
        "Kukaiau",
        "Kuka\u2018iau"
    ],
    "wof:name":"Kuka'iau",
    "wof:placetype":"locality"
},
  "geometry": {"coordinates":[-155.34843999999995,20.02999],"type":"Point"}
}