{
  "type": "Feature",
  "properties": {
    "gn:admin1_code":"IN",
    "gn:admin2_code":"117.0",
    "gn:admin3_code":"57798.0",
    "gn:asciiname":"Chambersburg",
    "gn:country_code":"US",
    "gn:dem":201,
    "gn:elevation":"201.0",
    "gn:feature_class":"P",
    "gn:feature_code":"PPL",
    "gn:name":"Chambersburg",
    "gn:population":0,
    "gn:timezone":"America/Indiana/Indianapolis",
    "iso:country":"US",
    "name:azb_x_preferred":[
        "\u0686\u0627\u0645\u0628\u0631\u0632\u0628\u0648\u0631\u0642"
    ],
    "name:eng_x_preferred":[
        "Chambersburg"
    ],
    "name:fas_x_preferred":[
        "\u0686\u0627\u0645\u0628\u0631\u0632\u0628\u0648\u0631\u06af"
    ],
    "name:und_x_variant":[
        "Chambersburgh"
    ],
    "name:urd_x_preferred":[
        "\u0686\u06cc\u0645\u0628\u0631\u0632\u0628\u0631\u06af"
    ],
    "wof:name":"Chambersburg",
    "wof:placetype":"locality"
},
  "geometry": {"coordinates":[-86.39220999999998,38.51811],"type":"Point"}
}