{
  "type": "Feature",
  "properties": {
    "gn:admin1_code":"IA",
    "gn:admin2_code":"3.0",
    "gn:admin3_code":"92916.0",
    "gn:asciiname":"Mercer",
    "gn:country_code":"US",
    "gn:dem":380,
    "gn:elevation":"385.0",
    "gn:feature_class":"P",
    "gn:feature_code":"PPL",
    "gn:name":"Mercer",
    "gn:population":0,
    "gn:timezone":"America/Chicago",
    "iso:country":"US",
    "name:fas_x_preferred":[
        "\u0645\u0631\u0633\u0631"
    ],
    "name:fra_x_preferred":[
        "Mercer"
    ],
    "wof:name":"Mercer",
    "wof:placetype":"locality"
},
  "geometry": {"coordinates":[-94.64914,40.94332],"type":"Point"}
}