{
  "type": "Feature",
  "properties": {
    "iso:country":"US",
    "name:eng_x_preferred":[
        "Sunshine Heights"
    ],
    "qs_pg:aaroncc":"US",
    "qs_pg:name":"Sunshine Heights",
    "qs_pg:name_adm0":"United States",
    "qs_pg:name_adm1":"Florida",
    "qs_pg:photos":3,
    "qs_pg:photos_1k":1,
    "qs_pg:photos_9k":1,
    "qs_pg:photos_9r":1,
    "qs_pg:photos_all":3,
    "qs_pg:photos_sr":1,
    "qs_pg:pop_sr":0,
    "qs_pg:qs_pg_placetype":"neighbourhood",
    "qs_pg:qs_pg_placetype_gp":"Suburb",
    "qs_pg:woe_adm0":23424977,
    "wof:name":"Sunshine Heights",
    "wof:placetype":"neighbourhood",
    "wof:population":521,
    "zs:area_m":15342611.462471,
    "zs:blockids":[
        121050123051002
    ],
    "zs:housing10":180,
    "zs:label":"Sunshine Heights",
    "zs:pop10":521
},
  "geometry": {"coordinates":[-81.84430999999999,28.201566],"type":"Point"}
}