{
  "type": "Feature",
  "properties": {
    "gn:admin1_code":"AZ",
    "gn:admin2_code":"21.0",
    "gn:asciiname":"Hayden Junction",
    "gn:country_code":"US",
    "gn:dem":580,
    "gn:elevation":"583.0",
    "gn:feature_class":"P",
    "gn:feature_code":"PPL",
    "gn:name":"Hayden Junction",
    "gn:population":0,
    "gn:timezone":"America/Phoenix",
    "iso:country":"US",
    "wof:name":"Hayden Junction",
    "wof:placetype":"locality"
},
  "geometry": {"coordinates":[-110.81538,33.00979],"type":"Point"}
}