{
  "type": "Feature",
  "properties": {
    "iso:country":"US",
    "name:eng_x_preferred":[
        "Waywin Acres"
    ],
    "wof:name":"Waywin Acres",
    "wof:placetype":"neighbourhood",
    "wof:population":503,
    "zs:area_m":270294.556457,
    "zs:blockids":[
        191530102122004,
        191530102122005,
        191530102122003,
        191530102123012,
        191530102122013,
        191530102123000,
        191530102122014
    ],
    "zs:housing10":185,
    "zs:label":"Waywin Acres",
    "zs:pop10":503
},
  "geometry": {"coordinates":[-93.58905799999999,41.720472],"type":"Point"}
}