{
  "type": "Feature",
  "properties": {
    "gn:gn_country":"US",
    "gn:gn_fcode":"PPL",
    "gn:gn_pop":0,
    "iso:country":"US",
    "name:ceb_x_preferred":[
        "Hagan"
    ],
    "name:deu_x_preferred":[
        "Hagan"
    ],
    "name:fra_x_preferred":[
        "Hagan"
    ],
    "name:kor_x_preferred":[
        "\ud5e4\uc774\uac74"
    ],
    "name:nld_x_preferred":[
        "Hagan"
    ],
    "name:nor_x_preferred":[
        "Hagan"
    ],
    "name:por_x_preferred":[
        "Hagan"
    ],
    "qs_pg:aaroncc":"US",
    "qs_pg:gn_country":"US",
    "qs_pg:gn_fcode":"PPL",
    "qs_pg:gn_pop":0,
    "qs_pg:name":"Hagan",
    "qs_pg:name_adm0":"United States",
    "qs_pg:name_adm1":"Virginia",
    "qs_pg:photos":10,
    "qs_pg:photos_1k":2,
    "qs_pg:photos_9k":1,
    "qs_pg:photos_9r":1,
    "qs_pg:photos_all":10,
    "qs_pg:photos_sr":1,
    "qs_pg:pop_sr":0,
    "qs_pg:qs_pg_placetype":"locality",
    "qs_pg:qs_pg_placetype_gp":"Town",
    "qs_pg:woe_adm0":23424977,
    "woe:adm0_id":23424977,
    "woe:name_adm0":"United States",
    "woe:name_adm1":"Virginia",
    "woe:placetype":"Town",
    "wof:name":"Hagan",
    "wof:placetype":"locality"
},
  "geometry": {"coordinates":[-83.28657,36.70425],"type":"Point"}
}