{
  "type": "Feature",
  "properties": {
    "gn:admin1_code":"MD",
    "gn:admin2_code":"21.0",
    "gn:asciiname":"Akers Acres",
    "gn:country_code":"US",
    "gn:dem":222,
    "gn:elevation":"210.0",
    "gn:feature_class":"P",
    "gn:feature_code":"PPL",
    "gn:name":"Akers Acres",
    "gn:population":0,
    "gn:timezone":"America/New_York",
    "iso:country":"US",
    "wof:name":"Akers Acres",
    "wof:placetype":"locality"
},
  "geometry": {"coordinates":[-77.47749,39.44538],"type":"Point"}
}