{
  "type": "Feature",
  "properties": {
    "iso:country":"US",
    "name:eng_x_preferred":[
        "Valley Green Acres"
    ],
    "wof:name":"Valley Green Acres",
    "wof:placetype":"neighbourhood",
    "wof:population":3334,
    "zs:area_m":3181320.654751,
    "zs:blockids":[
        471490403021066,
        471490403031028,
        471490403021000,
        471490403081019,
        471490403021011,
        471490403021024,
        471490403021075,
        471490403021010,
        471490403021063,
        471490403082001,
        471490403082002,
        471490403081014,
        471490403081012,
        471490403082036,
        471490403082000,
        471490403081025,
        471490403021064,
        471490403021014,
        471490403021013,
        471490403021058,
        471490403021006,
        471490403082007,
        471490403021061,
        471490403021003,
        471490403022021,
        471490403021023,
        471490403021068,
        471490403081030,
        471490403021069,
        471490403081029,
        471490403081028,
        471490403021001,
        471490403021012,
        471490403021073,
        471490403021060,
        471490403021062,
        471490403021005,
        471490403021015,
        471490403021065,
        471490403081032,
        471490403082006,
        471490403031023,
        471490403031027,
        471490403082003,
        471490403021067,
        471490403081011,
        471490403022020,
        471490403082004,
        471490403082005,
        471490403021007,
        471490403081018,
        471490403031014
    ],
    "zs:housing10":1258,
    "zs:label":"Valley Green Acres",
    "zs:pop10":3334
},
  "geometry": {"coordinates":[-86.522293,35.951434],"type":"Point"}
}