{
  "type": "Feature",
  "properties": {
    "gn:admin1_code":"FL",
    "gn:admin2_code":"67.0",
    "gn:asciiname":"Mayo Junction",
    "gn:country_code":"US",
    "gn:dem":27,
    "gn:elevation":"23.0",
    "gn:feature_class":"P",
    "gn:feature_code":"PPL",
    "gn:name":"Mayo Junction",
    "gn:population":0,
    "gn:timezone":"America/New_York",
    "iso:country":"US",
    "wof:name":"Mayo Junction",
    "wof:placetype":"locality"
},
  "geometry": {"coordinates":[-83.26653,30.20578],"type":"Point"}
}