{
  "type": "Feature",
  "properties": {
    "gn:admin1_code":"TN",
    "gn:admin2_code":"131.0",
    "gn:asciiname":"Webb Chapel",
    "gn:country_code":"US",
    "gn:dem":97,
    "gn:elevation":"94.0",
    "gn:feature_class":"P",
    "gn:feature_code":"PPL",
    "gn:name":"Webb Chapel",
    "gn:population":0,
    "gn:timezone":"America/Chicago",
    "iso:country":"US",
    "wof:name":"Webb Chapel",
    "wof:placetype":"locality"
},
  "geometry": {"coordinates":[-89.37785,36.32729000000001],"type":"Point"}
}