{
  "type": "Feature",
  "properties": {
    "gn:country":"US",
    "gn:fcode":"PPL",
    "gn:population":9505,
    "iso:country":"US",
    "name:eng_x_preferred":[
        "Fort George G Mead Junction"
    ],
    "name:und_x_variant":[
        "Junction"
    ],
    "qs_pg:aaroncc":"US",
    "qs_pg:gn_country":"US",
    "qs_pg:gn_fcode":"PPL",
    "qs_pg:gn_pop":9505,
    "qs_pg:name":"Fort George G Mead Junction",
    "qs_pg:photos_9r":0,
    "qs_pg:photos_sr":0,
    "qs_pg:pop_sr":5,
    "qs_pg:qs_pg_placetype":"locality",
    "wof:name":"Fort George G Mead Junction",
    "wof:placetype":"locality",
    "wof:population":9505
},
  "geometry": {"coordinates":[-76.78914,39.12594],"type":"Point"}
}