{
  "type": "Feature",
  "properties": {
    "iso:country":"US",
    "name:eng_x_preferred":[
        "Thornton Junction"
    ],
    "wof:name":"Thornton Junction",
    "wof:placetype":"neighbourhood",
    "wof:population":1367,
    "zs:area_m":990929.55418,
    "zs:blockids":[
        170318278051002,
        170318278011007,
        170318278012009,
        170318278051012,
        170318278011008,
        170318278011006,
        170318278051004,
        170318278051001,
        170318278051000,
        170318278011010,
        170318278011004,
        170318278051006,
        170318278011009,
        170318278043010,
        170318278051005,
        170318278043005,
        170318278012008,
        170318278012010,
        170318278012006,
        170318278051003,
        170318278012007,
        170318278013017,
        170318278043015
    ],
    "zs:housing10":492,
    "zs:label":"Thornton Junction",
    "zs:pop10":1367
},
  "geometry": {"coordinates":[-87.611177,41.590392],"type":"Point"}
}