{
  "type": "Feature",
  "properties": {
    "gn:admin1_code":"MO",
    "gn:admin2_code":"171.0",
    "gn:admin3_code":"36026.0",
    "gn:asciiname":"Midway",
    "gn:country_code":"US",
    "gn:dem":309,
    "gn:elevation":"305.0",
    "gn:feature_class":"P",
    "gn:feature_code":"PPL",
    "gn:name":"Midway",
    "gn:population":0,
    "gn:timezone":"America/Chicago",
    "iso:country":"US",
    "name:ara_x_preferred":[
        "\u0645\u064a\u062f\u0648\u0627\u0649"
    ],
    "name:bre_x_preferred":[
        "Midway"
    ],
    "name:cat_x_preferred":[
        "Midway"
    ],
    "name:ceb_x_preferred":[
        "Midway"
    ],
    "name:dan_x_preferred":[
        "Midway"
    ],
    "name:deu_x_preferred":[
        "Midway"
    ],
    "name:fas_x_preferred":[
        "\u0645\u06cc\u062f\u0648\u06cc"
    ],
    "name:fin_x_preferred":[
        "Midway"
    ],
    "name:fra_x_preferred":[
        "Midway"
    ],
    "name:glg_x_preferred":[
        "Midway"
    ],
    "name:heb_x_preferred":[
        "\u05de\u05d9\u05d3\u05d5\u05d5\u05d9\u05d9"
    ],
    "name:ido_x_preferred":[
        "Midway"
    ],
    "name:ind_x_preferred":[
        "Midway"
    ],
    "name:ita_x_preferred":[
        "Midway"
    ],
    "name:jpn_x_preferred":[
        "\u30df\u30c3\u30c9\u30a6\u30a7\u30fc"
    ],
    "name:kor_x_preferred":[
        "\ubbf8\ub4dc\uc6e8\uc774"
    ],
    "name:nds_x_preferred":[
        "Midway"
    ],
    "name:nld_x_preferred":[
        "Midway"
    ],
    "name:nno_x_preferred":[
        "Midway"
    ],
    "name:pol_x_preferred":[
        "Midway"
    ],
    "name:por_x_preferred":[
        "Midway"
    ],
    "name:ron_x_preferred":[
        "Midway"
    ],
    "name:rus_x_preferred":[
        "\u041c\u0438\u0434\u0443\u044d\u0439"
    ],
    "name:srp_x_preferred":[
        "\u041c\u0438\u0434\u0432\u0435\u0458"
    ],
    "name:swe_x_preferred":[
        "Midway"
    ],
    "name:tha_x_preferred":[
        "\u0e21\u0e34\u0e14\u0e40\u0e27\u0e22\u0e4c"
    ],
    "name:ukr_x_preferred":[
        "\u041c\u0456\u0434\u0432\u0435\u0439"
    ],
    "name:vie_x_preferred":[
        "Midway"
    ],
    "name:vol_x_preferred":[
        "Midway"
    ],
    "wof:name":"Midway",
    "wof:placetype":"locality"
},
  "geometry": {"coordinates":[-93.16215,40.47529],"type":"Point"}
}