{
  "type": "Feature",
  "properties": {
    "gn:admin1_code":"MO",
    "gn:admin2_code":"145.0",
    "gn:admin3_code":"4744.0",
    "gn:asciiname":"Boulder City",
    "gn:country_code":"US",
    "gn:dem":331,
    "gn:elevation":"329.0",
    "gn:feature_class":"P",
    "gn:feature_code":"PPL",
    "gn:name":"Boulder City",
    "gn:population":0,
    "gn:timezone":"America/Chicago",
    "iso:country":"US",
    "wof:name":"Boulder City",
    "wof:placetype":"locality"
},
  "geometry": {"coordinates":[-94.24938,36.79396],"type":"Point"}
}