{
  "type": "Feature",
  "properties": {
    "gn:admin1_code":"FL",
    "gn:admin2_code":"99.0",
    "gn:asciiname":"A Garden Walk Mobile Home Park",
    "gn:country_code":"US",
    "gn:dem":2,
    "gn:elevation":"4.0",
    "gn:feature_class":"P",
    "gn:feature_code":"PPL",
    "gn:name":"A Garden Walk Mobile Home Park",
    "gn:population":0,
    "gn:timezone":"America/New_York",
    "iso:country":"US",
    "wof:name":"A Garden Walk Mobile Home Park",
    "wof:placetype":"campus"
},
  "geometry": {"coordinates":[-80.10290000000001,26.7964],"type":"Point"}
}