{
  "type": "Feature",
  "properties": {
    "gn:admin1_code":"ID",
    "gn:admin2_code":"7.0",
    "gn:asciiname":"Lanark",
    "gn:country_code":"US",
    "gn:dem":1816,
    "gn:elevation":"1815.0",
    "gn:feature_class":"P",
    "gn:feature_code":"PPL",
    "gn:name":"Lanark",
    "gn:population":0,
    "gn:timezone":"America/Boise",
    "iso:country":"US",
    "name:ast_x_preferred":[
        "Lanark"
    ],
    "name:azb_x_preferred":[
        "\u0644\u0646\u0627\u0631\u06a9"
    ],
    "name:ceb_x_preferred":[
        "Lanark"
    ],
    "name:cym_x_preferred":[
        "Lanark"
    ],
    "name:deu_x_preferred":[
        "Lanark"
    ],
    "name:eng_x_preferred":[
        "Lanark"
    ],
    "name:epo_x_preferred":[
        "Lanark"
    ],
    "name:eus_x_preferred":[
        "Lanark"
    ],
    "name:fas_x_preferred":[
        "\u0644\u0646\u0627\u0631\u06a9"
    ],
    "name:fin_x_preferred":[
        "Lanark"
    ],
    "name:fra_x_preferred":[
        "Lanark"
    ],
    "name:gla_x_preferred":[
        "Lannraig"
    ],
    "name:gle_x_preferred":[
        "Lannraig"
    ],
    "name:ita_x_preferred":[
        "Lanark"
    ],
    "name:jpn_x_preferred":[
        "\u30e9\u30ca\u30fc\u30af"
    ],
    "name:kor_x_preferred":[
        "\ub798\ub108\ud06c"
    ],
    "name:nld_x_preferred":[
        "Lanark"
    ],
    "name:pol_x_preferred":[
        "Lanark"
    ],
    "name:por_x_preferred":[
        "Lanark"
    ],
    "name:sco_x_preferred":[
        "Lanrik"
    ],
    "name:spa_x_preferred":[
        "Lanark"
    ],
    "name:swe_x_preferred":[
        "Lanark"
    ],
    "name:tur_x_preferred":[
        "Lanark"
    ],
    "name:ukr_x_preferred":[
        "\u041b\u0430\u043d\u0430\u0440\u043a"
    ],
    "name:und_x_variant":[
        "Freedom",
        "South Liberty"
    ],
    "name:zho_x_preferred":[
        "\u62c9\u5948\u514b"
    ],
    "wof:name":"Lanark",
    "wof:placetype":"locality"
},
  "geometry": {"coordinates":[-111.42853999999998,42.28159],"type":"Point"}
}