{
  "type": "Feature",
  "properties": {
    "iso:country":"US",
    "name:eng_x_preferred":[
        "Heathermeade"
    ],
    "wof:name":"Heathermeade",
    "wof:placetype":"neighbourhood",
    "wof:population":120,
    "zs:area_m":8310360.518712,
    "zs:blockids":[
        80130136022078,
        80130136021044,
        80130136022077,
        80130136022076,
        80130136022055,
        80130136021066,
        80130136022079,
        80130136022061,
        80130136021099,
        80130136021097,
        80130136021072,
        80130136022065,
        80130136021092,
        80130136021095,
        80130136021093,
        80130136021098,
        80130136021065,
        80130136021069,
        80130136022062,
        80130136021094
    ],
    "zs:housing10":153,
    "zs:label":"Heathermeade",
    "zs:pop10":120
},
  "geometry": {"coordinates":[-105.462673,40.180653],"type":"Point"}
}