{
  "type": "Feature",
  "properties": {
    "iso:country":"US",
    "name:eng_x_preferred":[
        "Johnson Ranch"
    ],
    "name:eng_x_variant":[
        "Johnson Rnch"
    ],
    "qs:gn_adm0_cc":"US",
    "qs:gn_local":5388881,
    "qs:gn_nam_loc":"Roseville, Placer, California, US",
    "qs:gn_namadm1":"CA",
    "qs:local_max":728,
    "qs:local_sum":5764,
    "qs:localhoods":35,
    "qs:name":"Johnson Ranch",
    "qs:name_adm0":"United States",
    "qs:name_adm1":"California",
    "qs:name_adm2":"Placer",
    "qs:name_local":"Roseville",
    "qs:photo_max":24,
    "qs:photo_sum":62,
    "qs:placetype":"Suburb",
    "qs:quad_count":8,
    "qs:woe_adm0":23424977,
    "qs:woe_adm1":2347563,
    "qs:woe_adm2":12587700,
    "qs:woe_lau":0,
    "qs:woe_local":2484861,
    "qs:woe_ver":"7.10.0",
    "wof:lang":[
        "eng"
    ],
    "wof:name":"Johnson Ranch",
    "wof:placetype":"neighbourhood",
    "wof:population":3170,
    "zs:blockids":[
        60610207101000,
        60610207101008,
        60610206062003,
        60610207101018,
        60610207112013,
        60610207112014,
        60610206053009,
        60610206062014,
        60610206062008,
        60610206062006,
        60610206063001,
        60610206063003,
        60610206063007,
        60610206063016,
        60610207101017,
        60610206062011,
        60610206063002,
        60610207101025,
        60610206062010,
        60610206063006,
        60610206062002,
        60610207112012,
        60610207101021,
        60610206062012,
        60610206063009,
        60610207101019,
        60610206063014,
        60610207113015,
        60610206062017,
        60610206062015,
        60610206062009,
        60610206063005,
        60610207101026,
        60610206062000,
        60610206063015,
        60610206053011,
        60610207101016,
        60610206062001,
        60610206062005,
        60610206062007,
        60610206063000,
        60610206063004,
        60610206062016,
        60610207101020,
        60610207101003,
        60610206063008,
        60610207101024,
        60610206062013,
        60610207101027,
        60610207113017
    ],
    "zs:housing10":1028,
    "zs:pop10":3170
},
  "geometry": {"coordinates":[-121.22890599999999,38.724504],"type":"Point"}
}