{
  "type": "Feature",
  "properties": {
    "gn:admin1_code":"TX",
    "gn:admin2_code":"339.0",
    "gn:asciiname":"Wigginsville",
    "gn:country_code":"US",
    "gn:dem":51,
    "gn:elevation":"48.0",
    "gn:feature_class":"P",
    "gn:feature_code":"PPL",
    "gn:name":"Wigginsville",
    "gn:population":0,
    "gn:timezone":"America/Chicago",
    "iso:country":"US",
    "wof:name":"Wigginsville",
    "wof:placetype":"locality"
},
  "geometry": {"coordinates":[-95.33716,30.25827],"type":"Point"}
}