{
  "type": "Feature",
  "properties": {
    "gn:admin1_code":"TX",
    "gn:admin2_code":"167.0",
    "gn:asciiname":"Park Place",
    "gn:country_code":"US",
    "gn:dem":14,
    "gn:elevation":"8.0",
    "gn:feature_class":"P",
    "gn:feature_code":"PPL",
    "gn:name":"Park Place",
    "gn:population":0,
    "gn:timezone":"America/Chicago",
    "iso:country":"US",
    "name:ceb_x_preferred":[
        "Park Place"
    ],
    "name:deu_x_preferred":[
        "Park Place"
    ],
    "name:fra_x_preferred":[
        "Park Place"
    ],
    "name:jpn_x_preferred":[
        "\u30d1\u30fc\u30af\u30d7\u30ec\u30a4\u30b9"
    ],
    "name:pol_x_preferred":[
        "Park Place"
    ],
    "name:spa_x_preferred":[
        "Park Place"
    ],
    "wof:name":"Park Place",
    "wof:placetype":"locality"
},
  "geometry": {"coordinates":[-95.19410000000001,29.5221],"type":"Point"}
}