{
  "type": "Feature",
  "properties": {
    "gn:admin1_code":"OH",
    "gn:admin2_code":"113",
    "gn:admin3_code":"33922.0",
    "gn:asciiname":"Shiloh",
    "gn:country_code":"US",
    "gn:dem":260,
    "gn:elevation":"258.0",
    "gn:feature_class":"P",
    "gn:feature_code":"PPL",
    "gn:name":"Shiloh",
    "gn:population":0,
    "gn:timezone":"America/New_York",
    "iso:country":"US",
    "name:fas_x_preferred":[
        "\u0634\u06cc\u0644\u0648"
    ],
    "name:nld_x_preferred":[
        "Shiloh"
    ],
    "name:por_x_preferred":[
        "Shiloh"
    ],
    "name:srp_x_preferred":[
        "\u0428\u0430\u0458\u043b\u043e"
    ],
    "name:und_x_variant":[
        "Shiloh CDP",
        "Shiloh"
    ],
    "name:vol_x_preferred":[
        "Shiloh"
    ],
    "wof:name":"Shiloh",
    "wof:placetype":"locality"
},
  "geometry": {"coordinates":[-84.23175000000001,39.81589],"type":"Point"}
}