{
  "type": "Feature",
  "properties": {
    "iso:country":"US",
    "name:eng_x_preferred":[
        "Middlesex"
    ],
    "name:unk_x_variant":[
        "Middlesex"
    ],
    "qs:gn_adm0_cc":"US",
    "qs:gn_local":4853828,
    "qs:gn_nam_loc":"Des Moines, Polk, Iowa, US",
    "qs:gn_namadm1":"IA",
    "qs:local_max":12745,
    "qs:local_sum":45077,
    "qs:localhoods":63,
    "qs:name":"Middlesex",
    "qs:name_adm0":"United States",
    "qs:name_adm1":"Iowa",
    "qs:name_adm2":"Polk",
    "qs:name_local":"Des Moines",
    "qs:photo_max":49,
    "qs:photo_sum":83,
    "qs:placetype":"Suburb",
    "qs:quad_count":4,
    "qs:woe_adm0":23424977,
    "qs:woe_adm1":2347574,
    "qs:woe_adm2":12588348,
    "qs:woe_lau":0,
    "qs:woe_local":2391446,
    "qs:woe_ver":"7.10.0",
    "wof:lang":[
        "eng"
    ],
    "wof:name":"Middlesex Plat",
    "wof:placetype":"neighbourhood",
    "wof:population":851,
    "zs:blockids":[
        191530029001016,
        191530029001010,
        191530029001011,
        191530029001014,
        191530029001003,
        191530029001008,
        191530029001009,
        191530029001007,
        191530029001002,
        191530029001012
    ],
    "zs:housing10":534,
    "zs:pop10":851
},
  "geometry": {"coordinates":[-93.66075600000001,41.595454],"type":"Point"}
}