{
  "type": "Feature",
  "properties": {
    "gn:admin1_code":"AL",
    "gn:admin2_code":"7",
    "gn:asciiname":"McCulley Creek",
    "gn:country_code":"US",
    "gn:dem":147,
    "gn:elevation":"146.0",
    "gn:feature_class":"P",
    "gn:feature_code":"PPL",
    "gn:name":"McCulley Creek",
    "gn:population":0,
    "gn:timezone":"America/Chicago",
    "iso:country":"US",
    "wof:name":"McCulley Creek",
    "wof:placetype":"locality"
},
  "geometry": {"coordinates":[-87.19444,33.08734],"type":"Point"}
}