{
  "type": "Feature",
  "properties": {
    "gn:admin1_code":"MN",
    "gn:admin2_code":"125.0",
    "gn:admin3_code":"38276.0",
    "gn:asciiname":"Huot",
    "gn:country_code":"US",
    "gn:dem":273,
    "gn:elevation":"276.0",
    "gn:feature_class":"P",
    "gn:feature_code":"PPL",
    "gn:name":"Huot",
    "gn:population":0,
    "gn:timezone":"America/Chicago",
    "iso:country":"US",
    "wof:name":"Huot",
    "wof:placetype":"locality"
},
  "geometry": {"coordinates":[-96.42339,47.86525],"type":"Point"}
}