{
  "type": "Feature",
  "properties": {
    "gn:admin1_code":"OK",
    "gn:admin2_code":"23.0",
    "gn:asciiname":"Unger",
    "gn:country_code":"US",
    "gn:dem":159,
    "gn:elevation":"155.0",
    "gn:feature_class":"P",
    "gn:feature_code":"PPL",
    "gn:name":"Unger",
    "gn:population":0,
    "gn:timezone":"America/Chicago",
    "iso:country":"US",
    "name:ces_x_preferred":[
        "Unger"
    ],
    "name:dan_x_preferred":[
        "Unger"
    ],
    "name:deu_x_preferred":[
        "Unger"
    ],
    "name:epo_x_preferred":[
        "Unger"
    ],
    "name:fra_x_preferred":[
        "Unger"
    ],
    "name:rus_x_preferred":[
        "\u0423\u043d\u0433\u0435\u0440"
    ],
    "name:slv_x_preferred":[
        "Unger"
    ],
    "wof:name":"Unger",
    "wof:placetype":"locality"
},
  "geometry": {"coordinates":[-95.78192,34.02621],"type":"Point"}
}