{
  "type": "Feature",
  "properties": {
    "gn:admin1_code":"NC",
    "gn:admin2_code":"21.0",
    "gn:admin3_code":"93840.0",
    "gn:asciiname":"South Hominy",
    "gn:country_code":"US",
    "gn:dem":706,
    "gn:elevation":"708.0",
    "gn:feature_class":"P",
    "gn:feature_code":"PPL",
    "gn:name":"South Hominy",
    "gn:population":0,
    "gn:timezone":"America/New_York",
    "iso:country":"US",
    "wof:name":"South Hominy",
    "wof:placetype":"locality"
},
  "geometry": {"coordinates":[-82.73819,35.49205],"type":"Point"}
}