{
  "type": "Feature",
  "properties": {
    "gn:admin1_code":"CO",
    "gn:admin2_code":"9.0",
    "gn:asciiname":"Frick",
    "gn:country_code":"US",
    "gn:dem":1443,
    "gn:elevation":"1447.0",
    "gn:feature_class":"P",
    "gn:feature_code":"PPL",
    "gn:name":"Frick",
    "gn:population":0,
    "gn:timezone":"America/Denver",
    "iso:country":"US",
    "name:als_x_preferred":[
        "Frick"
    ],
    "name:bel_x_preferred":[
        "\u0424\u0440\u044b\u043a"
    ],
    "name:ceb_x_preferred":[
        "Frick"
    ],
    "name:ces_x_preferred":[
        "Frick"
    ],
    "name:dan_x_preferred":[
        "Frick"
    ],
    "name:deu_x_preferred":[
        "Frick"
    ],
    "name:epo_x_preferred":[
        "Frick"
    ],
    "name:fin_x_preferred":[
        "Frick"
    ],
    "name:fra_x_preferred":[
        "Frick"
    ],
    "name:ita_x_preferred":[
        "Frick"
    ],
    "name:jpn_x_preferred":[
        "\u30d5\u30ea\u30c3\u30af"
    ],
    "name:lav_x_preferred":[
        "Friks"
    ],
    "name:nds_x_preferred":[
        "Frick"
    ],
    "name:nld_x_preferred":[
        "Frick"
    ],
    "name:pol_x_preferred":[
        "Frick"
    ],
    "name:rus_x_preferred":[
        "\u0424\u0440\u0438\u043a"
    ],
    "name:swe_x_preferred":[
        "Frick"
    ],
    "name:ukr_x_preferred":[
        "\u0424\u0440\u0456\u043a"
    ],
    "wof:name":"Frick",
    "wof:placetype":"locality"
},
  "geometry": {"coordinates":[-102.95547999999999,37.58529],"type":"Point"}
}