{
  "type": "Feature",
  "properties": {
    "iso:country":"US",
    "name:eng_x_preferred":[
        "The Cottages at Woodstock"
    ],
    "wof:name":"The Cottages at Woodstock",
    "wof:placetype":"neighbourhood",
    "wof:population":928,
    "zs:area_m":1171912.306176,
    "zs:blockids":[
        130570909052002,
        130570909052008,
        130570909043028,
        130570909024011,
        130570909024008,
        130570909023022,
        130570909052009,
        130570909024012,
        130570909052007,
        130570909024006,
        130570909024007,
        130570909023039,
        130570909052000,
        130570909052001,
        130570909052006,
        130570909052004,
        130570909052003,
        130570909024009,
        130570909052005,
        130570909024010
    ],
    "zs:housing10":547,
    "zs:label":"The Cottages at Woodstock",
    "zs:pop10":928
},
  "geometry": {"coordinates":[-84.48110800000001,34.085053],"type":"Point"}
}