{
  "type": "Feature",
  "properties": {
    "iso:country":"US",
    "name:eng_x_preferred":[
        "Grand View"
    ],
    "wof:name":"Grand View",
    "wof:placetype":"neighbourhood",
    "wof:population":843,
    "zs:area_m":57294028.131831,
    "zs:blockids":[
        51430110022030,
        51430105044074,
        51430110023006,
        51430105044082,
        51430105044083,
        51430105044067,
        51430105044087,
        51430105044073,
        51430105044078,
        51430110023009,
        51430105044077,
        51430110023003,
        51430110023001,
        51430110023090,
        51430105044086,
        51430105044084,
        51430105044085,
        51430105044096,
        51430105044072,
        51430110023002,
        51430105044075,
        51430105044070,
        51430105044071,
        51430110023010,
        51430110023012,
        51430105044065,
        51430110023004,
        51430110023013,
        51430105044097,
        51430105044076,
        51430105044069,
        51430105044079,
        51430110023005,
        51430105044081,
        51430110023007,
        51430110023000,
        51430105044080,
        51430105044043,
        51430105044066,
        51430105044062,
        51430110023011,
        51430110022029,
        51430105044068,
        51430105044045
    ],
    "zs:housing10":361,
    "zs:label":"Grand View",
    "zs:pop10":843
},
  "geometry": {"coordinates":[-94.494727,35.968351],"type":"Point"}
}