{
  "type": "Feature",
  "properties": {
    "gn:admin1_code":"PA",
    "gn:admin2_code":"77.0",
    "gn:admin3_code":"45656.0",
    "gn:asciiname":"Lynnport",
    "gn:country_code":"US",
    "gn:dem":147,
    "gn:elevation":"148.0",
    "gn:feature_class":"P",
    "gn:feature_code":"PPL",
    "gn:name":"Lynnport",
    "gn:population":0,
    "gn:timezone":"America/New_York",
    "iso:country":"US",
    "name:fas_x_preferred":[
        "\u0644\u06cc\u0646\u067e\u0648\u0631\u062a"
    ],
    "wof:name":"Lynnport",
    "wof:placetype":"locality"
},
  "geometry": {"coordinates":[-75.80492,40.67537],"type":"Point"}
}