{
  "type": "Feature",
  "properties": {
    "gn:admin1_code":"IA",
    "gn:admin2_code":"1.0",
    "gn:admin3_code":"94443.0",
    "gn:asciiname":"Gilead",
    "gn:country_code":"US",
    "gn:dem":387,
    "gn:elevation":"390.0",
    "gn:feature_class":"P",
    "gn:feature_code":"PPL",
    "gn:name":"Gilead",
    "gn:population":0,
    "gn:timezone":"America/Chicago",
    "iso:country":"US",
    "name:fas_x_preferred":[
        "\u06af\u06cc\u0644\u06cc\u062f"
    ],
    "name:fra_x_preferred":[
        "Gilead"
    ],
    "wof:name":"Gilead",
    "wof:placetype":"locality"
},
  "geometry": {"coordinates":[-94.58580000000001,41.17249],"type":"Point"}
}