{
  "type": "Feature",
  "properties": {
    "gn:admin1_code":"WA",
    "gn:admin2_code":"49.0",
    "gn:asciiname":"Bruceport",
    "gn:country_code":"US",
    "gn:dem":25,
    "gn:elevation":"7.0",
    "gn:feature_class":"P",
    "gn:feature_code":"PPL",
    "gn:name":"Bruceport",
    "gn:population":0,
    "gn:timezone":"America/Los_Angeles",
    "iso:country":"US",
    "name:eng_x_preferred":[
        "Bruceport"
    ],
    "name:und_x_variant":[
        "Bruceville"
    ],
    "wof:name":"Bruceport",
    "wof:placetype":"locality"
},
  "geometry": {"coordinates":[-123.90016,46.67926],"type":"Point"}
}