{
  "type": "Feature",
  "properties": {
    "gn:admin1_code":"CO",
    "gn:admin2_code":"29.0",
    "gn:asciiname":"Bowie",
    "gn:country_code":"US",
    "gn:dem":1824,
    "gn:elevation":"1818.0",
    "gn:feature_class":"P",
    "gn:feature_code":"PPL",
    "gn:name":"Bowie",
    "gn:population":0,
    "gn:timezone":"America/Denver",
    "iso:country":"US",
    "name:cat_x_preferred":[
        "Bowie"
    ],
    "name:ceb_x_preferred":[
        "Bowie"
    ],
    "name:ces_x_preferred":[
        "Bowie"
    ],
    "name:chv_x_preferred":[
        "\u0411\u043e\u0443\u0438"
    ],
    "name:deu_x_preferred":[
        "Bowie"
    ],
    "name:eng_x_preferred":[
        "Bowie"
    ],
    "name:fas_x_preferred":[
        "\u0628\u0648\u06cc\u06cc"
    ],
    "name:fin_x_preferred":[
        "Bowie"
    ],
    "name:fra_x_preferred":[
        "Bowie"
    ],
    "name:heb_x_preferred":[
        "\u05d1\u05d5\u05d0\u05d9"
    ],
    "name:ita_x_preferred":[
        "Bowie"
    ],
    "name:jpn_x_preferred":[
        "\u30dc\u30a6\u30a4"
    ],
    "name:lit_x_preferred":[
        "Bowie"
    ],
    "name:nld_x_preferred":[
        "Bowie"
    ],
    "name:nor_x_preferred":[
        "Bowie"
    ],
    "name:pol_x_preferred":[
        "Bowie"
    ],
    "name:por_x_preferred":[
        "Bowie"
    ],
    "name:rus_x_preferred":[
        "\u0411\u043e\u0443\u0438"
    ],
    "name:spa_x_preferred":[
        "Bowie"
    ],
    "name:swe_x_preferred":[
        "Bowie"
    ],
    "name:ukr_x_preferred":[
        "\u0411\u043e\u0432\u0456"
    ],
    "name:und_x_variant":[
        "Reading"
    ],
    "name:vol_x_preferred":[
        "Bowie"
    ],
    "wof:name":"Bowie",
    "wof:placetype":"locality"
},
  "geometry": {"coordinates":[-107.54006,38.92138],"type":"Point"}
}