{
  "type": "Feature",
  "properties": {
    "gn:admin1_code":"NY",
    "gn:admin2_code":"27.0",
    "gn:admin3_code":"25978.0",
    "gn:asciiname":"Oak Meadows Mobile Home Park",
    "gn:country_code":"US",
    "gn:dem":32,
    "gn:elevation":"27.0",
    "gn:feature_class":"P",
    "gn:feature_code":"PPL",
    "gn:name":"Oak Meadows Mobile Home Park",
    "gn:population":0,
    "gn:timezone":"America/New_York",
    "iso:country":"US",
    "wof:name":"Oak Meadows Mobile Home Park",
    "wof:placetype":"campus"
},
  "geometry": {"coordinates":[-73.97731999999998,41.47613],"type":"Point"}
}