{
  "type": "Feature",
  "properties": {
    "gn:admin1_code":"TX",
    "gn:admin2_code":"175.0",
    "gn:asciiname":"Berclair",
    "gn:country_code":"US",
    "gn:dem":59,
    "gn:elevation":"58.0",
    "gn:feature_class":"P",
    "gn:feature_code":"PPL",
    "gn:name":"Berclair",
    "gn:population":0,
    "gn:timezone":"America/Chicago",
    "iso:country":"US",
    "wof:name":"Berclair",
    "wof:placetype":"locality"
},
  "geometry": {"coordinates":[-97.59111,28.53083],"type":"Point"}
}