{
  "type": "Feature",
  "properties": {
    "gn:admin1_code":"FL",
    "gn:admin2_code":"23.0",
    "gn:asciiname":"Mount Carrie",
    "gn:country_code":"US",
    "gn:dem":64,
    "gn:elevation":"60.0",
    "gn:feature_class":"P",
    "gn:feature_code":"PPL",
    "gn:name":"Mount Carrie",
    "gn:population":0,
    "gn:timezone":"America/New_York",
    "iso:country":"US",
    "wof:name":"Mount Carrie",
    "wof:placetype":"locality"
},
  "geometry": {"coordinates":[-82.50373,30.19523],"type":"Point"}
}