{
  "type": "Feature",
  "properties": {
    "gn:country":"US",
    "gn:fcode":"PPL",
    "gn:population":0,
    "iso:country":"US",
    "name:eng_x_preferred":[
        "Rocky Point"
    ],
    "name:fra_x_preferred":[
        "Rocky Point"
    ],
    "name:lld_x_preferred":[
        "Rocky Point"
    ],
    "name:und_x_variant":[
        "Harriman"
    ],
    "qs_pg:aaroncc":"US",
    "qs_pg:gn_country":"US",
    "qs_pg:gn_fcode":"PPL",
    "qs_pg:gn_pop":0,
    "qs_pg:name":"Rocky Point",
    "qs_pg:name_adm0":"United States",
    "qs_pg:name_adm1":"Oregon",
    "qs_pg:photos":253,
    "qs_pg:photos_1k":51,
    "qs_pg:photos_9k":1,
    "qs_pg:photos_9r":4,
    "qs_pg:photos_all":253,
    "qs_pg:photos_sr":5,
    "qs_pg:pop_sr":0,
    "qs_pg:qs_pg_placetype":"locality",
    "qs_pg:qs_pg_placetype_gp":"Town",
    "qs_pg:woe_adm0":23424977,
    "woe:adm0_id":23424977,
    "woe:name_adm0":"United States",
    "woe:name_adm1":"Oregon",
    "woe:placetype":"Town",
    "wof:name":"Rocky Point",
    "wof:placetype":"locality"
},
  "geometry": {"coordinates":[-122.08419000000001,42.48069],"type":"Point"}
}