{
  "type": "Feature",
  "properties": {
    "gn:admin1_code":"TX",
    "gn:admin2_code":"479.0",
    "gn:asciiname":"San Carlos Number 2 Colonia",
    "gn:country_code":"US",
    "gn:dem":167,
    "gn:elevation":"166.0",
    "gn:feature_class":"P",
    "gn:feature_code":"PPL",
    "gn:name":"San Carlos Number 2 Colonia",
    "gn:population":0,
    "gn:timezone":"America/Chicago",
    "iso:country":"US",
    "name:eng_x_preferred":[
        "San Carlos Number 2 Colonia"
    ],
    "name:und_x_variant":[
        "San Carlos and San Enrique Colonia"
    ],
    "wof:name":"San Carlos Number 2 Colonia",
    "wof:placetype":"locality"
},
  "geometry": {"coordinates":[-99.36837,27.4903],"type":"Point"}
}