{
  "type": "Feature",
  "properties": {
    "gn:country":"US",
    "gn:fcode":"PPL",
    "gn:population":0,
    "iso:country":"US",
    "name:eng_x_preferred":[
        "Sherman Corner"
    ],
    "name:und_x_variant":[
        "Sherman's Corner"
    ],
    "qs_pg:aaroncc":"US",
    "qs_pg:gn_country":"US",
    "qs_pg:gn_fcode":"PPL",
    "qs_pg:gn_pop":0,
    "qs_pg:name":"Sherman Corner",
    "qs_pg:name_adm0":"United States",
    "qs_pg:name_adm1":"Connecticut",
    "qs_pg:photos":35,
    "qs_pg:photos_1k":7,
    "qs_pg:photos_9k":1,
    "qs_pg:photos_9r":2,
    "qs_pg:photos_all":35,
    "qs_pg:photos_sr":2,
    "qs_pg:pop_sr":0,
    "qs_pg:qs_pg_placetype":"neighbourhood",
    "qs_pg:qs_pg_placetype_gp":"Suburb",
    "qs_pg:woe_adm0":23424977,
    "wof:name":"Sherman Corner",
    "wof:placetype":"neighbourhood",
    "wof:population":90,
    "zs:area_m":1240467.145681,
    "zs:blockids":[
        90158150001034,
        90158150001028
    ],
    "zs:housing10":41,
    "zs:label":"Sherman Corner",
    "zs:pop10":90
},
  "geometry": {"coordinates":[-72.124021,41.78451],"type":"Point"}
}