{
  "type": "Feature",
  "properties": {
    "iso:country":"US",
    "name:eng_x_preferred":[
        "Gamesway"
    ],
    "qs:gn_adm0_cc":"US",
    "qs:gn_fcode":"PPL",
    "qs:gn_local":4297983,
    "qs:gn_nam_loc":"Lexington, Fayette, Kentucky, US",
    "qs:gn_namadm1":"KY",
    "qs:gn_name":"Gamesway",
    "qs:local_max":4034,
    "qs:local_sum":30708,
    "qs:localhoods":91,
    "qs:name":"Gamesway",
    "qs:name_adm0":"United States",
    "qs:name_adm1":"Kentucky",
    "qs:name_adm2":"Fayette",
    "qs:name_local":"Lexington",
    "qs:photo_max":167,
    "qs:photo_sum":249,
    "qs:placetype":"Suburb",
    "qs:quad_count":14,
    "qs:woe_adm0":23424977,
    "qs:woe_adm1":2347576,
    "qs:woe_adm2":12588509,
    "qs:woe_funk":"Parented by a neighborhood",
    "qs:woe_lau":0,
    "qs:woe_local":2438841,
    "qs:woe_ver":"7.10.0",
    "wof:lang":[
        "eng"
    ],
    "wof:name":"Gamesway",
    "wof:placetype":"neighbourhood",
    "wof:population":1836,
    "zs:blockids":[
        210670034042010,
        210670034042012,
        210670034042000,
        210670034041004,
        210670034042003,
        210670023023003,
        210670034042011,
        210670023023008,
        210670034042017,
        210670023023010,
        210670023023004,
        210670034042016,
        210670034042009,
        210670023023002,
        210670034042002,
        210670034042004,
        210670034042014,
        210670034051015,
        210670023023007,
        210670034042013,
        210670034042005,
        210670034042008,
        210670034042015,
        210670034042001,
        210670023023011,
        210670023022009,
        210670023023009,
        210670034042006,
        210670023023012
    ],
    "zs:housing10":882,
    "zs:pop10":1836
},
  "geometry": {"coordinates":[-84.483389,37.987928],"type":"Point"}
}