{
  "type": "Feature",
  "properties": {
    "iso:country":"US",
    "name:eng_x_preferred":[
        "Little Point"
    ],
    "wof:name":"Little Point",
    "wof:placetype":"neighbourhood",
    "zs:area_m":15600092.377991,
    "zs:blockids":[
        551390019003000
    ],
    "zs:housing10":0,
    "zs:label":"Little Point",
    "zs:pop10":0
},
  "geometry": {"coordinates":[-88.436666,43.906551],"type":"Point"}
}