{
  "type": "Feature",
  "properties": {
    "gn:admin1_code":"FL",
    "gn:admin2_code":"91.0",
    "gn:asciiname":"Beaver Creek",
    "gn:country_code":"US",
    "gn:dem":83,
    "gn:elevation":"75.0",
    "gn:feature_class":"P",
    "gn:feature_code":"PPL",
    "gn:name":"Beaver Creek",
    "gn:population":0,
    "gn:timezone":"America/Chicago",
    "iso:country":"US",
    "name:ceb_x_preferred":[
        "Beaver Creek"
    ],
    "name:deu_x_preferred":[
        "Beaver Creek"
    ],
    "name:fra_x_preferred":[
        "Beaver Creek"
    ],
    "name:ita_x_preferred":[
        "Beaver Creek"
    ],
    "name:nld_x_preferred":[
        "Beaver Creek"
    ],
    "name:pol_x_preferred":[
        "Beaver Creek"
    ],
    "name:por_x_preferred":[
        "Beaver Creek"
    ],
    "name:rus_x_preferred":[
        "\u0411\u0438\u0432\u0435\u0440-\u041a\u0440\u0438\u043a"
    ],
    "name:spa_x_preferred":[
        "Beaver Creek"
    ],
    "name:srp_x_preferred":[
        "\u0411\u0438\u0432\u0435\u0440 \u041a\u0440\u0438\u043a"
    ],
    "name:swe_x_preferred":[
        "Beaver Creek"
    ],
    "name:ukr_x_preferred":[
        "\u0411\u0456\u0432\u0435\u0440-\u041a\u0440\u0456\u043a"
    ],
    "name:urd_x_preferred":[
        "\u0628\u06cc\u0648\u0631 \u06a9\u0631\u06cc\u06a9"
    ],
    "name:vol_x_preferred":[
        "Beaver Creek"
    ],
    "wof:name":"Beaver Creek",
    "wof:placetype":"locality"
},
  "geometry": {"coordinates":[-86.77857,30.88019],"type":"Point"}
}