{
  "type": "Feature",
  "properties": {
    "gn:admin1_code":"OH",
    "gn:admin2_code":"91.0",
    "gn:admin3_code":"69134.0",
    "gn:asciiname":"Walnut Grove",
    "gn:country_code":"US",
    "gn:dem":353,
    "gn:elevation":"353.0",
    "gn:feature_class":"P",
    "gn:feature_code":"PPL",
    "gn:name":"Walnut Grove",
    "gn:population":0,
    "gn:timezone":"America/New_York",
    "iso:country":"US",
    "name:cat_x_preferred":[
        "Walnut Grove"
    ],
    "name:ceb_x_preferred":[
        "Walnut Grove"
    ],
    "name:deu_x_preferred":[
        "Walnut Grove"
    ],
    "name:eng_x_preferred":[
        "Walnut Grove"
    ],
    "name:fin_x_preferred":[
        "Walnut Grove"
    ],
    "name:fra_x_preferred":[
        "Walnut Grove"
    ],
    "name:ido_x_preferred":[
        "Walnut Grove"
    ],
    "name:ind_x_preferred":[
        "Walnut Grove"
    ],
    "name:ita_x_preferred":[
        "Walnut Grove"
    ],
    "name:nld_x_preferred":[
        "Walnut Grove"
    ],
    "name:pol_x_preferred":[
        "Walnut Grove"
    ],
    "name:por_x_preferred":[
        "Walnut Grove"
    ],
    "name:spa_x_preferred":[
        "Walnut Grove"
    ],
    "name:srp_x_preferred":[
        "\u0412\u043e\u043b\u043d\u0430\u0442 \u0413\u0440\u043e\u0443\u0432"
    ],
    "name:swe_x_preferred":[
        "Walnut Grove"
    ],
    "name:und_x_variant":[
        "Walnutgrove",
        "Nelson Station"
    ],
    "name:vol_x_preferred":[
        "Walnut Grove"
    ],
    "wof:name":"Walnut Grove",
    "wof:placetype":"locality"
},
  "geometry": {"coordinates":[-83.62326,40.42728],"type":"Point"}
}