{
  "type": "Feature",
  "properties": {
    "gn:admin1_code":"VA",
    "gn:admin2_code":"161",
    "gn:asciiname":"Hidden Valley Homes",
    "gn:country_code":"US",
    "gn:dem":375,
    "gn:elevation":"372.0",
    "gn:feature_class":"P",
    "gn:feature_code":"PPL",
    "gn:name":"Hidden Valley Homes",
    "gn:population":0,
    "gn:timezone":"America/New_York",
    "iso:country":"US",
    "wof:name":"Hidden Valley Homes",
    "wof:placetype":"locality"
},
  "geometry": {"coordinates":[-80.03948000000003,37.2443],"type":"Point"}
}