{
  "type": "Feature",
  "properties": {
    "gn:admin1_code":"NE",
    "gn:admin2_code":"109.0",
    "gn:asciiname":"Center Court Mobile Home Park",
    "gn:country_code":"US",
    "gn:dem":352,
    "gn:elevation":"350.0",
    "gn:feature_class":"P",
    "gn:feature_code":"PPL",
    "gn:name":"Center Court Mobile Home Park",
    "gn:population":0,
    "gn:timezone":"America/Chicago",
    "iso:country":"US",
    "wof:name":"Center Court Mobile Home Park",
    "wof:placetype":"campus"
},
  "geometry": {"coordinates":[-96.66696,40.84583],"type":"Point"}
}