{
  "type": "Feature",
  "properties": {
    "gn:admin1_code":"LA",
    "gn:admin2_code":"33.0",
    "gn:asciiname":"Woodlawn Acres",
    "gn:country_code":"US",
    "gn:dem":9,
    "gn:elevation":"7.0",
    "gn:feature_class":"P",
    "gn:feature_code":"PPL",
    "gn:name":"Woodlawn Acres",
    "gn:population":0,
    "gn:timezone":"America/Chicago",
    "iso:country":"US",
    "wof:name":"Woodlawn Acres",
    "wof:placetype":"locality"
},
  "geometry": {"coordinates":[-91.00315999999999,30.38297],"type":"Point"}
}