{
  "type": "Feature",
  "properties": {
    "iso:country":"US",
    "name:eng_x_preferred":[
        "La`iewai Ahupua`a"
    ],
    "qs:gn_adm0_cc":"US",
    "qs:gn_local":5850027,
    "qs:gn_nam_loc":"ho'olehua",
    "qs:gn_namadm1":"HI",
    "qs:local_max":3253,
    "qs:local_sum":3745,
    "qs:localhoods":2,
    "qs:name":"La`iewai Ahupua`a",
    "qs:name_adm0":"United States",
    "qs:name_adm1":"Hawaii",
    "qs:name_adm2":"Honolulu",
    "qs:name_local":"Laie",
    "qs:photo_max":194,
    "qs:photo_sum":492,
    "qs:placetype":"Suburb",
    "qs:quad_count":18,
    "qs:woe_adm0":23424977,
    "qs:woe_adm1":2347570,
    "qs:woe_adm2":12588030,
    "qs:woe_lau":0,
    "qs:woe_local":2434676,
    "qs:woe_ver":"7.10.0",
    "wof:name":"La`iewai Ahupua`a",
    "wof:placetype":"neighbourhood",
    "wof:population":3787,
    "zs:blockids":[
        150030102022008,
        150030102022011,
        150030102024020,
        150030102024021,
        150030102023008,
        150030102022005,
        150030102022006,
        150030102021006,
        150030102024011,
        150030102021007,
        150030102024018,
        150030102024027,
        150030102024033,
        150030102024026,
        150030102024003,
        150030102022009,
        150030102022004,
        150030102022010,
        150030102022013,
        150030102022014,
        150030102024016,
        150030102024014,
        150030102024019,
        150030102024005,
        150030102024022,
        150030102022015,
        150030102024013,
        150030102024023,
        150030102024025,
        150030102024032,
        150030102024001,
        150030102024009,
        150030102024007,
        150030102022003,
        150030102024017,
        150030102023007,
        150030102024010,
        150030102024000,
        150030102024008,
        150030102024002,
        150030102021008,
        150030102022002,
        150030102022001,
        150030102022012,
        150030102024024,
        150030102024012,
        150030102024004,
        150030102024015
    ],
    "zs:housing10":926,
    "zs:pop10":3787
},
  "geometry": {"coordinates":[-157.91786400000001,21.653087],"type":"Point"}
}