{
  "type": "Feature",
  "properties": {
    "gn:admin1_code":"IL",
    "gn:admin2_code":"45.0",
    "gn:admin3_code":"38999.0",
    "gn:asciiname":"Warrington",
    "gn:country_code":"US",
    "gn:dem":206,
    "gn:elevation":"208.0",
    "gn:feature_class":"P",
    "gn:feature_code":"PPL",
    "gn:name":"Warrington",
    "gn:population":0,
    "gn:timezone":"America/Chicago",
    "iso:country":"US",
    "name:ast_x_preferred":[
        "Warrington"
    ],
    "name:azb_x_preferred":[
        "\u0648\u0627\u0631\u06cc\u0646\u0642\u062a\u0648\u0646"
    ],
    "name:cat_x_preferred":[
        "Warrington"
    ],
    "name:ceb_x_preferred":[
        "Warrington"
    ],
    "name:cym_x_preferred":[
        "Warrington"
    ],
    "name:dan_x_preferred":[
        "Warrington"
    ],
    "name:deu_x_preferred":[
        "Warrington"
    ],
    "name:epo_x_preferred":[
        "Warrington"
    ],
    "name:est_x_preferred":[
        "Warrington"
    ],
    "name:fas_x_preferred":[
        "\u0648\u0627\u0631\u06cc\u0646\u06af\u062a\u0648\u0646"
    ],
    "name:fin_x_preferred":[
        "Warrington"
    ],
    "name:fra_x_preferred":[
        "Warrington"
    ],
    "name:gle_x_preferred":[
        "Warrington"
    ],
    "name:ita_x_preferred":[
        "Warrington"
    ],
    "name:jpn_x_preferred":[
        "\u30a6\u30a9\u30ea\u30f3\u30c8\u30f3"
    ],
    "name:kor_x_preferred":[
        "\uc6cc\ub9c1\ud134"
    ],
    "name:lit_x_preferred":[
        "Voringtonas"
    ],
    "name:ltz_x_preferred":[
        "Warrington"
    ],
    "name:nld_x_preferred":[
        "Warrington"
    ],
    "name:nno_x_preferred":[
        "Warrington"
    ],
    "name:nor_x_preferred":[
        "Warrington"
    ],
    "name:pol_x_preferred":[
        "Warrington"
    ],
    "name:por_x_preferred":[
        "Warrington"
    ],
    "name:ron_x_preferred":[
        "Warrington"
    ],
    "name:rus_x_preferred":[
        "\u0423\u043e\u0440\u0440\u0438\u043d\u0433\u0442\u043e\u043d"
    ],
    "name:sco_x_preferred":[
        "Warrington"
    ],
    "name:slk_x_preferred":[
        "Warrington"
    ],
    "name:spa_x_preferred":[
        "Warrington"
    ],
    "name:srp_x_preferred":[
        "\u0412\u043e\u0440\u0438\u043d\u0433\u0442\u043e\u043d"
    ],
    "name:swe_x_preferred":[
        "Warrington"
    ],
    "name:szl_x_preferred":[
        "Warrington"
    ],
    "name:tat_x_preferred":[
        "\u0412\u043e\u0440\u0440\u0438\u04a3\u0442\u043e\u043d"
    ],
    "name:tur_x_preferred":[
        "Warrington"
    ],
    "name:ukr_x_preferred":[
        "\u0412\u043e\u0440\u0440\u0456\u043d\u0433\u0442\u043e\u043d"
    ],
    "name:urd_x_preferred":[
        "\u0648\u0627\u0631\u0646\u06af\u0679\u0646"
    ],
    "name:vol_x_preferred":[
        "Warrington"
    ],
    "name:war_x_preferred":[
        "Warrington"
    ],
    "name:zho_x_preferred":[
        "\u6c83\u7075\u987f"
    ],
    "wof:name":"Warrington",
    "wof:placetype":"locality"
},
  "geometry": {"coordinates":[-87.93753000000002,39.61281],"type":"Point"}
}