{
  "type": "Feature",
  "properties": {
    "gn:admin1_code":"NY",
    "gn:admin2_code":"75.0",
    "gn:admin3_code":"56352.0",
    "gn:asciiname":"Liberty Park Mobile Home Park",
    "gn:country_code":"US",
    "gn:dem":164,
    "gn:elevation":"166.0",
    "gn:feature_class":"P",
    "gn:feature_code":"PPL",
    "gn:name":"Liberty Park Mobile Home Park",
    "gn:population":0,
    "gn:timezone":"America/New_York",
    "iso:country":"US",
    "wof:name":"Liberty Park Mobile Home Park",
    "wof:placetype":"campus"
},
  "geometry": {"coordinates":[-76.06981999999998,43.3951],"type":"Point"}
}