{
  "type": "Feature",
  "properties": {
    "gn:admin1_code":"FL",
    "gn:admin2_code":"57",
    "gn:asciiname":"Rutland Acres",
    "gn:country_code":"US",
    "gn:dem":36,
    "gn:elevation":"33.0",
    "gn:feature_class":"P",
    "gn:feature_code":"PPL",
    "gn:name":"Rutland Acres",
    "gn:population":0,
    "gn:timezone":"America/New_York",
    "iso:country":"US",
    "wof:name":"Rutland Acres",
    "wof:placetype":"locality"
},
  "geometry": {"coordinates":[-82.09050000000001,27.9386],"type":"Point"}
}