{
  "type": "Feature",
  "properties": {
    "gn:country":"US",
    "gn:fcode":"PPL",
    "gn:population":0,
    "iso:country":"US",
    "name:ceb_x_preferred":[
        "Forest Beach"
    ],
    "name:deu_x_preferred":[
        "Forest Beach"
    ],
    "name:eng_x_preferred":[
        "Forest Beach"
    ],
    "name:swe_x_preferred":[
        "Forest Beach"
    ],
    "qs_pg:aaroncc":"US",
    "qs_pg:gn_country":"US",
    "qs_pg:gn_fcode":"PPL",
    "qs_pg:gn_pop":0,
    "qs_pg:name":"Forest Beach",
    "qs_pg:name_adm0":"United States",
    "qs_pg:name_adm1":"New York",
    "qs_pg:photos":1,
    "qs_pg:photos_1k":1,
    "qs_pg:photos_9k":1,
    "qs_pg:photos_9r":1,
    "qs_pg:photos_all":1,
    "qs_pg:photos_sr":1,
    "qs_pg:pop_sr":0,
    "qs_pg:qs_pg_placetype":"neighbourhood",
    "qs_pg:qs_pg_placetype_gp":"Suburb",
    "qs_pg:woe_adm0":23424977,
    "wd:wordcount":25,
    "wof:name":"Forest Beach",
    "wof:placetype":"neighbourhood",
    "wof:population":545,
    "zs:area_m":4642141.649648,
    "zs:blockids":[
        360670102002000,
        360670102003003,
        360670102003001
    ],
    "zs:housing10":258,
    "zs:label":"Forest Beach",
    "zs:pop10":545
},
  "geometry": {"coordinates":[-76.099525,43.217592],"type":"Point"}
}