{
  "type": "Feature",
  "properties": {
    "iso:country":"US",
    "wof:name":"Cuyahoga Valley",
    "wof:placetype":"neighbourhood"
},
  "geometry": {"coordinates":[-81.67145435440482,41.46941722434143],"type":"Point"}
}