{
  "type": "Feature",
  "properties": {
    "gn:admin1_code":"VA",
    "gn:admin2_code":"3.0",
    "gn:asciiname":"Arbor Park",
    "gn:country_code":"US",
    "gn:dem":155,
    "gn:elevation":"158.0",
    "gn:feature_class":"P",
    "gn:feature_code":"PPL",
    "gn:name":"Arbor Park",
    "gn:population":0,
    "gn:timezone":"America/New_York",
    "iso:country":"US",
    "wof:name":"Arbor Park",
    "wof:placetype":"locality"
},
  "geometry": {"coordinates":[-78.50861999999999,38.12236],"type":"Point"}
}