{
  "type": "Feature",
  "properties": {
    "gn:admin1_code":"TN",
    "gn:admin2_code":"113.0",
    "gn:asciiname":"Adair",
    "gn:country_code":"US",
    "gn:dem":127,
    "gn:elevation":"126.0",
    "gn:feature_class":"P",
    "gn:feature_code":"PPL",
    "gn:name":"Adair",
    "gn:population":0,
    "gn:timezone":"America/Chicago",
    "iso:country":"US",
    "name:cat_x_preferred":[
        "Adair"
    ],
    "name:ceb_x_preferred":[
        "Adair"
    ],
    "name:ces_x_preferred":[
        "Adair"
    ],
    "name:deu_x_preferred":[
        "Adair"
    ],
    "name:eus_x_preferred":[
        "Adair"
    ],
    "name:fra_x_preferred":[
        "Adair"
    ],
    "name:ido_x_preferred":[
        "Adair"
    ],
    "name:ita_x_preferred":[
        "Adair"
    ],
    "name:nld_x_preferred":[
        "Adair"
    ],
    "name:pol_x_preferred":[
        "Adair"
    ],
    "name:por_x_preferred":[
        "Adair"
    ],
    "name:ron_x_preferred":[
        "Adair"
    ],
    "name:rus_x_preferred":[
        "\u0410\u0434\u044d\u0440"
    ],
    "name:spa_x_preferred":[
        "Adair"
    ],
    "name:srp_x_preferred":[
        "\u0410\u0434\u0435\u0440"
    ],
    "name:swe_x_preferred":[
        "Adair"
    ],
    "name:ukr_x_preferred":[
        "\u0410\u0434\u0435\u0439\u0440"
    ],
    "name:vol_x_preferred":[
        "Adair"
    ],
    "wof:name":"Adair",
    "wof:placetype":"locality"
},
  "geometry": {"coordinates":[-88.9609,35.71424000000001],"type":"Point"}
}