{
  "type": "Feature",
  "properties": {
    "gn:admin1_code":"TX",
    "gn:admin2_code":"3.0",
    "gn:asciiname":"Coyote Corner",
    "gn:country_code":"US",
    "gn:dem":989,
    "gn:elevation":"990.0",
    "gn:feature_class":"P",
    "gn:feature_code":"PPL",
    "gn:name":"Coyote Corner",
    "gn:population":0,
    "gn:timezone":"America/Chicago",
    "iso:country":"US",
    "wof:name":"Coyote Corner",
    "wof:placetype":"locality"
},
  "geometry": {"coordinates":[-102.72432000000001,32.10706],"type":"Point"}
}