{
  "type": "Feature",
  "properties": {
    "gn:admin1_code":"AL",
    "gn:admin2_code":"91",
    "gn:asciiname":"Consul",
    "gn:country_code":"US",
    "gn:dem":78,
    "gn:elevation":"73.0",
    "gn:feature_class":"P",
    "gn:feature_code":"PPL",
    "gn:name":"Consul",
    "gn:population":0,
    "gn:timezone":"America/Chicago",
    "iso:country":"US",
    "name:azb_x_preferred":[
        "\u06a9\u0648\u0646\u0633\u0648\u0644"
    ],
    "name:bar_x_preferred":[
        "Consul"
    ],
    "name:deu_x_preferred":[
        "Consul"
    ],
    "name:eng_x_preferred":[
        "Consul"
    ],
    "name:fas_x_preferred":[
        "\u06a9\u0648\u0646\u0633\u0648\u0644"
    ],
    "name:und_x_variant":[
        "Cross Roads"
    ],
    "name:zho_x_preferred":[
        "\u5b54\u6558\u723e"
    ],
    "wof:name":"Consul",
    "wof:placetype":"locality"
},
  "geometry": {"coordinates":[-87.54000000000001,32.26430999999999],"type":"Point"}
}