{
  "type": "Feature",
  "properties": {
    "gn:admin1_code":"WA",
    "gn:admin2_code":"33.0",
    "gn:asciiname":"Wildwood Mobile Home Estates",
    "gn:country_code":"US",
    "gn:dem":105,
    "gn:elevation":"98.0",
    "gn:feature_class":"P",
    "gn:feature_code":"PPL",
    "gn:name":"Wildwood Mobile Home Estates",
    "gn:population":0,
    "gn:timezone":"America/Los_Angeles",
    "iso:country":"US",
    "wof:name":"Wildwood Mobile Home Estates",
    "wof:placetype":"campus"
},
  "geometry": {"coordinates":[-122.17458999999999,47.28736],"type":"Point"}
}