{
  "type": "Feature",
  "properties": {
    "gn:admin1_code":"PA",
    "gn:admin2_code":"91",
    "gn:admin3_code":"77304.0",
    "gn:asciiname":"Pennington Reserve at Upper Providence",
    "gn:country_code":"US",
    "gn:dem":73,
    "gn:elevation":"71.0",
    "gn:feature_class":"P",
    "gn:feature_code":"PPL",
    "gn:name":"Pennington Reserve at Upper Providence",
    "gn:population":0,
    "gn:timezone":"America/New_York",
    "iso:country":"US",
    "wof:name":"Pennington Reserve at Upper Providence",
    "wof:placetype":"locality"
},
  "geometry": {"coordinates":[-75.46040000000001,40.2033],"type":"Point"}
}