{
  "type": "Feature",
  "properties": {
    "gn:country":"US",
    "gn:fcode":"PPL",
    "gn:population":0,
    "iso:country":"US",
    "name:eng_x_preferred":[
        "Shirley Meadows"
    ],
    "name:fas_x_preferred":[
        "\u0634\u06cc\u0631\u0644\u06cc \u0645\u06cc\u062f\u0648\u0632"
    ],
    "name:fra_x_preferred":[
        "Shirley Meadows"
    ],
    "name:pol_x_preferred":[
        "Shirley Meadows"
    ],
    "name:tur_x_preferred":[
        "Shirley Meadows"
    ],
    "name:zho_x_preferred":[
        "\u96ea\u8389\u8349\u7538"
    ],
    "qs_pg:aaroncc":"US",
    "qs_pg:gn_country":"US",
    "qs_pg:gn_fcode":"PPL",
    "qs_pg:gn_pop":0,
    "qs_pg:name":"Shirley Meadows",
    "qs_pg:name_adm0":"United States",
    "qs_pg:name_adm1":"California",
    "qs_pg:photos":57,
    "qs_pg:photos_1k":12,
    "qs_pg:photos_9k":1,
    "qs_pg:photos_9r":2,
    "qs_pg:photos_all":57,
    "qs_pg:photos_sr":2,
    "qs_pg:pop_sr":0,
    "qs_pg:qs_pg_placetype":"locality",
    "qs_pg:qs_pg_placetype_gp":"Town",
    "qs_pg:woe_adm0":23424977,
    "woe:adm0_id":23424977,
    "woe:name_adm0":"United States",
    "woe:name_adm1":"California",
    "woe:placetype":"Town",
    "wof:name":"Shirley Meadows",
    "wof:placetype":"locality"
},
  "geometry": {"coordinates":[-118.55647999999999,35.71079],"type":"Point"}
}