{
  "type": "Feature",
  "properties": {
    "gn:admin1_code":"SC",
    "gn:admin2_code":"85.0",
    "gn:asciiname":"Tindal",
    "gn:country_code":"US",
    "gn:dem":58,
    "gn:elevation":"55.0",
    "gn:feature_class":"P",
    "gn:feature_code":"PPL",
    "gn:name":"Tindal",
    "gn:population":0,
    "gn:timezone":"America/New_York",
    "iso:country":"US",
    "name:deu_x_preferred":[
        "Tindal"
    ],
    "name:fra_x_preferred":[
        "Tindall"
    ],
    "name:nld_x_preferred":[
        "Tindal"
    ],
    "name:por_x_preferred":[
        "Tindall"
    ],
    "wof:name":"Tindal",
    "wof:placetype":"locality"
},
  "geometry": {"coordinates":[-80.35675000000001,33.82155],"type":"Point"}
}