{
  "type": "Feature",
  "properties": {
    "iso:country":"US",
    "name:eng_x_preferred":[
        "Atlantic Heights"
    ],
    "qs_pg:aaroncc":"US",
    "qs_pg:name":"Atlantic Heights",
    "qs_pg:name_adm0":"United States",
    "qs_pg:name_adm1":"Florida",
    "qs_pg:photos":1,
    "qs_pg:photos_1k":1,
    "qs_pg:photos_9k":1,
    "qs_pg:photos_9r":1,
    "qs_pg:photos_all":1,
    "qs_pg:photos_sr":1,
    "qs_pg:pop_sr":0,
    "qs_pg:qs_pg_placetype":"neighbourhood",
    "qs_pg:qs_pg_placetype_gp":"Suburb",
    "qs_pg:woe_adm0":23424977,
    "woe:adm0_id":23424977,
    "woe:name_adm0":"United States",
    "woe:name_adm1":"Florida",
    "woe:placetype":"Suburb",
    "wof:name":"Atlantic Heights",
    "wof:placetype":"neighbourhood",
    "wof:population":367
},
  "geometry": {"coordinates":[-81.79777199999999,28.070484],"type":"Point"}
}