{
  "type": "Feature",
  "properties": {
    "gn:admin1_code":"VA",
    "gn:admin2_code":"161",
    "gn:asciiname":"Ruxton",
    "gn:country_code":"US",
    "gn:dem":377,
    "gn:elevation":"373.0",
    "gn:feature_class":"P",
    "gn:feature_code":"PPL",
    "gn:name":"Ruxton",
    "gn:population":0,
    "gn:timezone":"America/New_York",
    "iso:country":"US",
    "wof:name":"Ruxton",
    "wof:placetype":"locality"
},
  "geometry": {"coordinates":[-79.99004000000002,37.22097],"type":"Point"}
}