{
  "type": "Feature",
  "properties": {
    "gn:admin1_code":"UT",
    "gn:admin2_code":"27.0",
    "gn:asciiname":"Iron Basin",
    "gn:country_code":"US",
    "gn:dem":1755,
    "gn:elevation":"1757.0",
    "gn:feature_class":"P",
    "gn:feature_code":"PPL",
    "gn:name":"Iron Basin",
    "gn:population":0,
    "gn:timezone":"America/Denver",
    "iso:country":"US",
    "wof:name":"Iron Basin",
    "wof:placetype":"locality"
},
  "geometry": {"coordinates":[-112.95523,38.93024000000001],"type":"Point"}
}