{
  "type": "Feature",
  "properties": {
    "iso:country":"US",
    "name:eng_x_preferred":[
        "Tarawoods"
    ],
    "wof:name":"Tarawoods",
    "wof:placetype":"neighbourhood",
    "wof:population":4168,
    "zs:area_m":9048308.41883,
    "zs:blockids":[
        371190057113019,
        371190057113027,
        371190057113008,
        371190057131010,
        371190057131012,
        371190057113015,
        371190057112029,
        371190057131000,
        371190057061010,
        371190057111001,
        371190057111005,
        371190057113026,
        371190057113033,
        371190057113003,
        371190057113012,
        371190057113020,
        371190057064017,
        371190057111008,
        371190057131001,
        371190057113005,
        371190057113032,
        371190057113024,
        371190057061007,
        371190057113009,
        371190057113021,
        371190057113031,
        371190057113010,
        371190057113034,
        371190057113011,
        371190057113002,
        371190057113018,
        371190057111006,
        371190057113025,
        371190057113035,
        371190057112022,
        371190057113036,
        371190057113030,
        371190057113022,
        371190057112027,
        371190057113001,
        371190057113013,
        371190057113007,
        371190057111007,
        371190057111003,
        371190057061008,
        371190057113029,
        371190057113028,
        371190057112034,
        371190057112028,
        371190057113037,
        371190057113014,
        371190057113016,
        371190057113004,
        371190057113023,
        371190057113017,
        371190057113006
    ],
    "zs:housing10":1736,
    "zs:label":"Tarawoods",
    "zs:pop10":4168
},
  "geometry": {"coordinates":[-80.67349400000001,35.167772],"type":"Point"}
}