{
  "type": "Feature",
  "properties": {
    "gn:admin1_code":"MO",
    "gn:admin2_code":"181.0",
    "gn:admin3_code":"19810.0",
    "gn:asciiname":"Owenmont",
    "gn:country_code":"US",
    "gn:dem":153,
    "gn:elevation":"153.0",
    "gn:feature_class":"P",
    "gn:feature_code":"PPL",
    "gn:name":"Owenmont",
    "gn:population":0,
    "gn:timezone":"America/Chicago",
    "iso:country":"US",
    "name:eng_x_preferred":[
        "Owenmont"
    ],
    "name:und_x_variant":[
        "Brinkerhoff Spur"
    ],
    "wof:name":"Owenmont",
    "wof:placetype":"locality"
},
  "geometry": {"coordinates":[-90.78373000000001,36.62006],"type":"Point"}
}