{
  "type": "Feature",
  "properties": {
    "gn:admin1_code":"FL",
    "gn:admin2_code":"57",
    "gn:asciiname":"Habana Gardens North",
    "gn:country_code":"US",
    "gn:dem":20,
    "gn:elevation":"10.0",
    "gn:feature_class":"P",
    "gn:feature_code":"PPL",
    "gn:name":"Habana Gardens North",
    "gn:population":0,
    "gn:timezone":"America/New_York",
    "iso:country":"US",
    "wof:name":"Habana Gardens North",
    "wof:placetype":"locality"
},
  "geometry": {"coordinates":[-82.4877,27.9855],"type":"Point"}
}