{
  "type": "Feature",
  "properties": {
    "iso:country":"US",
    "name:eng_x_preferred":[
        "Twin Lakes at Christina"
    ],
    "wof:name":"Twin Lakes at Christina",
    "wof:placetype":"neighbourhood",
    "wof:population":1,
    "zs:area_m":1023193.156229,
    "zs:blockids":[
        121050118352030,
        121050148043087,
        121050148043081,
        121050148043086,
        121050149013000,
        121050118352027,
        121050118352034,
        121050118352028,
        121050148043084,
        121050118352031,
        121050148043082,
        121050148043083,
        121050118352029,
        121050118352032,
        121050118352033,
        121050118352024,
        121050118352026,
        121050148043088,
        121050148041019,
        121050148043085,
        121050118352025
    ],
    "zs:housing10":1,
    "zs:label":"Twin Lakes at Christina",
    "zs:pop10":1
},
  "geometry": {"coordinates":[-81.976615,27.925868],"type":"Point"}
}