{
  "type": "Feature",
  "properties": {
    "iso:country":"US",
    "name:ceb_x_preferred":[
        "Rosedale"
    ],
    "name:deu_x_preferred":[
        "Rosedale"
    ],
    "name:fra_x_preferred":[
        "Rosedale"
    ],
    "name:ita_x_preferred":[
        "Rosedale"
    ],
    "name:kor_x_preferred":[
        "\ub85c\uc988\ub370\uc77c"
    ],
    "name:nld_x_preferred":[
        "Rosedale"
    ],
    "name:pol_x_preferred":[
        "Rosedale"
    ],
    "name:por_x_preferred":[
        "Rosedale"
    ],
    "name:spa_x_preferred":[
        "Rosedale"
    ],
    "name:srp_x_preferred":[
        "\u0420\u043e\u0443\u0437\u0434\u0435\u0458\u043b"
    ],
    "name:swe_x_preferred":[
        "Rosedale"
    ],
    "name:vol_x_preferred":[
        "Rosedale"
    ],
    "qs_pg:aaroncc":"US",
    "qs_pg:name":"Rosedale",
    "qs_pg:name_adm0":"United States",
    "qs_pg:name_adm1":"Colorado",
    "qs_pg:photos":297,
    "qs_pg:photos_1k":60,
    "qs_pg:photos_9k":1,
    "qs_pg:photos_9r":4,
    "qs_pg:photos_all":297,
    "qs_pg:photos_sr":5,
    "qs_pg:pop_sr":0,
    "qs_pg:qs_pg_placetype":"locality",
    "qs_pg:qs_pg_placetype_gp":"Town",
    "qs_pg:woe_adm0":23424977,
    "woe:adm0_id":23424977,
    "woe:name_adm0":"United States",
    "woe:name_adm1":"Colorado",
    "woe:placetype":"Town",
    "wof:name":"Rosedale",
    "wof:placetype":"locality"
},
  "geometry": {"coordinates":[-105.37866699999999,39.6655],"type":"Point"}
}