{
  "type": "Feature",
  "properties": {
    "gn:admin1_code":"CA",
    "gn:admin2_code":"5.0",
    "gn:asciiname":"Dagon",
    "gn:country_code":"US",
    "gn:dem":80,
    "gn:elevation":"80.0",
    "gn:feature_class":"P",
    "gn:feature_code":"PPL",
    "gn:name":"Dagon",
    "gn:population":0,
    "gn:timezone":"America/Los_Angeles",
    "iso:country":"US",
    "name:fas_x_preferred":[
        "\u062f\u0627\u06af\u0646"
    ],
    "name:zho_x_preferred":[
        "\u9054\u8ca2"
    ],
    "wof:name":"Dagon",
    "wof:placetype":"locality"
},
  "geometry": {"coordinates":[-120.96133,38.34464000000001],"type":"Point"}
}