{
  "type": "Feature",
  "properties": {
    "gn:admin1_code":"IL",
    "gn:admin2_code":"197",
    "gn:admin3_code":"60300.0",
    "gn:asciiname":"Spangler Farms",
    "gn:country_code":"US",
    "gn:dem":184,
    "gn:elevation":"185.0",
    "gn:feature_class":"P",
    "gn:feature_code":"PPL",
    "gn:name":"Spangler Farms",
    "gn:population":0,
    "gn:timezone":"America/Chicago",
    "iso:country":"US",
    "wof:name":"Spangler Farms",
    "wof:placetype":"locality"
},
  "geometry": {"coordinates":[-88.21028000000003,41.59833],"type":"Point"}
}