{
  "type": "Feature",
  "properties": {
    "gn:country":"US",
    "gn:fcode":"PPL",
    "gn:population":0,
    "iso:country":"US",
    "name:eng_x_preferred":[
        "Hancock Corner"
    ],
    "name:zho_x_preferred":[
        "\u6f22\u8003\u514b\u89d2"
    ],
    "qs_pg:aaroncc":"US",
    "qs_pg:gn_country":"US",
    "qs_pg:gn_fcode":"PPL",
    "qs_pg:gn_pop":0,
    "qs_pg:name":"Hancock Corner",
    "qs_pg:name_adm0":"United States",
    "qs_pg:name_adm1":"Indiana",
    "qs_pg:photos":358,
    "qs_pg:photos_1k":73,
    "qs_pg:photos_9k":2,
    "qs_pg:photos_9r":5,
    "qs_pg:photos_all":358,
    "qs_pg:photos_sr":6,
    "qs_pg:pop_sr":0,
    "qs_pg:qs_pg_placetype":"locality",
    "qs_pg:qs_pg_placetype_gp":"Town",
    "qs_pg:woe_adm0":23424977,
    "woe:adm0_id":23424977,
    "woe:name_adm0":"United States",
    "woe:name_adm1":"Indiana",
    "woe:placetype":"Town",
    "wof:name":"Hancock Corner",
    "wof:placetype":"locality"
},
  "geometry": {"coordinates":[-86.8289,39.27532],"type":"Point"}
}