{
  "type": "Feature",
  "properties": {
    "gn:admin1_code":"KY",
    "gn:admin2_code":"187",
    "gn:asciiname":"Eagle Hill",
    "gn:country_code":"US",
    "gn:dem":266,
    "gn:elevation":"266.0",
    "gn:feature_class":"P",
    "gn:feature_code":"PPL",
    "gn:name":"Eagle Hill",
    "gn:population":0,
    "gn:timezone":"America/New_York",
    "iso:country":"US",
    "wof:name":"Eagle Hill",
    "wof:placetype":"locality"
},
  "geometry": {"coordinates":[-84.78856,38.70312],"type":"Point"}
}