{
  "type": "Feature",
  "properties": {
    "gn:admin1_code":"WI",
    "gn:admin2_code":"53.0",
    "gn:admin3_code":"35075.0",
    "gn:asciiname":"Sechlerville",
    "gn:country_code":"US",
    "gn:dem":281,
    "gn:elevation":"283.0",
    "gn:feature_class":"P",
    "gn:feature_code":"PPL",
    "gn:name":"Sechlerville",
    "gn:population":0,
    "gn:timezone":"America/Chicago",
    "iso:country":"US",
    "wof:name":"Sechlerville",
    "wof:placetype":"locality"
},
  "geometry": {"coordinates":[-91.03098,44.37274],"type":"Point"}
}