{
  "type": "Feature",
  "properties": {
    "iso:country":"US",
    "name:eng_x_preferred":[
        "Biazza Ridge"
    ],
    "name:eng_x_variant":[
        "Bizza Ridge"
    ],
    "wof:name":"Biazza Ridge",
    "wof:placetype":"neighbourhood",
    "wof:population":2404,
    "zs:area_m":7286747.185855,
    "zs:blockids":[
        370510034042018,
        370510034042002,
        370510034071001,
        370510034042013,
        370510034042019,
        370510034071002,
        370510034042011,
        370510034042017,
        370510034071006,
        370510034071004,
        370510034042015,
        370510034071007,
        370510034071013,
        370510034071014,
        370510034042001,
        370510034042000,
        370510034071011,
        370510034071005,
        370510034071010,
        370519801001044,
        370510034071017,
        370519801001045,
        370510034071003,
        370510034042014,
        370510034071018,
        370510034071008,
        370519801001047,
        370510034071009,
        370510034071015,
        370519801001046,
        370510034042016,
        370510034071016,
        370510034071012,
        370510034042010
    ],
    "zs:housing10":318,
    "zs:label":"Bizza Ridge",
    "zs:pop10":2404
},
  "geometry": {"coordinates":[-78.994602,35.116044],"type":"Point"}
}