{
  "type": "Feature",
  "properties": {
    "iso:country":"US",
    "name:ceb_x_preferred":[
        "Prichard"
    ],
    "name:deu_x_preferred":[
        "Prichard"
    ],
    "name:eng_x_preferred":[
        "Prichard"
    ],
    "name:fra_x_preferred":[
        "Prichard"
    ],
    "name:hbs_x_preferred":[
        "Pri\u010dard"
    ],
    "name:jpn_x_preferred":[
        "\u30d7\u30ea\u30c1\u30e3\u30fc\u30c9"
    ],
    "name:pol_x_preferred":[
        "Prichard"
    ],
    "name:por_x_preferred":[
        "Prichard"
    ],
    "name:rus_x_preferred":[
        "\u041f\u0440\u0438\u0447\u0430\u0440\u0434"
    ],
    "name:spa_x_preferred":[
        "Prichard"
    ],
    "name:srp_x_preferred":[
        "\u041f\u0440\u0438\u0447\u0430\u0440\u0434"
    ],
    "name:swe_x_preferred":[
        "Prichard"
    ],
    "name:ukr_x_preferred":[
        "\u041f\u0440\u0456\u0447\u0430\u0440\u0434"
    ],
    "wd:wordcount":195,
    "wof:name":"Prichard",
    "wof:placetype":"neighbourhood",
    "wof:population":116,
    "zs:area_m":2373573.064516,
    "zs:blockids":[
        420792157011021
    ],
    "zs:housing10":52,
    "zs:label":"Prichard",
    "zs:pop10":116
},
  "geometry": {"coordinates":[-76.127865,41.245647],"type":"Point"}
}