{
  "type": "Feature",
  "properties": {
    "gn:admin1_code":"FL",
    "gn:admin2_code":"57",
    "gn:asciiname":"Surfside Estates",
    "gn:country_code":"US",
    "gn:dem":3,
    "gn:elevation":"0.0",
    "gn:feature_class":"P",
    "gn:feature_code":"PPL",
    "gn:name":"Surfside Estates",
    "gn:population":0,
    "gn:timezone":"America/New_York",
    "iso:country":"US",
    "wof:name":"Surfside Estates",
    "wof:placetype":"locality"
},
  "geometry": {"coordinates":[-82.4224,27.7879],"type":"Point"}
}