{
  "type": "Feature",
  "properties": {
    "gn:gn_country":"US",
    "gn:gn_fcode":"PPL",
    "gn:gn_pop":0,
    "iso:country":"US",
    "name:eng_x_preferred":[
        "Verner"
    ],
    "name:fas_x_preferred":[
        "\u0648\u0631\u0646\u0631\u060c \u0648\u06cc\u0631\u062c\u06cc\u0646\u06cc\u0627 \u063a\u0631\u0628\u06cc"
    ],
    "name:fas_x_variant":[
        "\u0648\u0631\u0646\u0631"
    ],
    "name:fra_x_preferred":[
        "Verner"
    ],
    "qs_pg:aaroncc":"US",
    "qs_pg:gn_country":"US",
    "qs_pg:gn_fcode":"PPL",
    "qs_pg:gn_pop":0,
    "qs_pg:name":"Verner",
    "qs_pg:name_adm0":"United States",
    "qs_pg:name_adm1":"West Virginia",
    "qs_pg:photos_9k":1,
    "qs_pg:photos_9r":1,
    "qs_pg:photos_all":2,
    "qs_pg:photos_sr":0,
    "qs_pg:pop_sr":0,
    "qs_pg:qs_pg_placetype":"locality",
    "qs_pg:qs_pg_placetype_gp":"Town",
    "qs_pg:woe_adm0":23424977,
    "woe:adm0_id":23424977,
    "woe:name_adm0":"United States",
    "woe:name_adm1":"West Virginia",
    "woe:placetype":"Town",
    "wof:name":"Verner",
    "wof:placetype":"locality"
},
  "geometry": {"coordinates":[-81.85039999999999,37.66344],"type":"Point"}
}