{
  "type": "Feature",
  "properties": {
    "iso:country":"US",
    "name:eng_x_preferred":[
        "Centre Pointe"
    ],
    "wof:name":"Centre Pointe",
    "wof:placetype":"neighbourhood",
    "zs:area_m":593530.973724,
    "zs:blockids":[
        50070204051025,
        50070204052035,
        50070204051023,
        50070204051026,
        50070204051024,
        50070213102014
    ],
    "zs:housing10":0,
    "zs:label":"Centre Pointe",
    "zs:pop10":0
},
  "geometry": {"coordinates":[-94.16036699999999,36.291345],"type":"Point"}
}