{
  "type": "Feature",
  "properties": {
    "gn:admin1_code":"WV",
    "gn:admin2_code":"11",
    "gn:asciiname":"Hillview",
    "gn:country_code":"US",
    "gn:dem":270,
    "gn:elevation":"240.0",
    "gn:feature_class":"P",
    "gn:feature_code":"PPL",
    "gn:name":"Hillview",
    "gn:population":0,
    "gn:timezone":"America/New_York",
    "iso:country":"US",
    "name:ceb_x_preferred":[
        "Hillview"
    ],
    "name:deu_x_preferred":[
        "Hillview"
    ],
    "name:fra_x_preferred":[
        "Hillview"
    ],
    "name:ita_x_preferred":[
        "Hillview"
    ],
    "name:nld_x_preferred":[
        "Hillview"
    ],
    "name:pol_x_preferred":[
        "Hillview"
    ],
    "name:por_x_preferred":[
        "Hillview"
    ],
    "name:srp_x_preferred":[
        "\u0425\u0438\u043b\u0432\u0458\u0443"
    ],
    "name:swe_x_preferred":[
        "Hillview"
    ],
    "name:ukr_x_preferred":[
        "\u0413\u0456\u043b\u043b\u0432'\u044e"
    ],
    "name:vol_x_preferred":[
        "Hillview"
    ],
    "wof:name":"Hillview",
    "wof:placetype":"locality"
},
  "geometry": {"coordinates":[-82.35987,38.4287],"type":"Point"}
}