{
  "type": "Feature",
  "properties": {
    "gn:admin1_code":"FL",
    "gn:admin2_code":"57",
    "gn:asciiname":"Morrison Court",
    "gn:country_code":"US",
    "gn:dem":11,
    "gn:elevation":"5.0",
    "gn:feature_class":"P",
    "gn:feature_code":"PPL",
    "gn:name":"Morrison Court",
    "gn:population":0,
    "gn:timezone":"America/New_York",
    "iso:country":"US",
    "wof:name":"Morrison Court",
    "wof:placetype":"locality"
},
  "geometry": {"coordinates":[-82.51299999999998,27.933],"type":"Point"}
}