{
  "type": "Feature",
  "properties": {
    "gn:admin1_code":"MD",
    "gn:admin2_code":"3.0",
    "gn:asciiname":"Epping Forest",
    "gn:country_code":"US",
    "gn:dem":28,
    "gn:elevation":"22.0",
    "gn:feature_class":"P",
    "gn:feature_code":"PPL",
    "gn:name":"Epping Forest",
    "gn:population":0,
    "gn:timezone":"America/New_York",
    "iso:country":"US",
    "name:ceb_x_preferred":[
        "Epping Forest"
    ],
    "name:ces_x_preferred":[
        "Epping Forest"
    ],
    "name:deu_x_preferred":[
        "Epping Forest"
    ],
    "name:fas_x_preferred":[
        "\u0627\u067e\u06cc\u0646\u06af \u0641\u0648\u0631\u0633\u062a"
    ],
    "name:fin_x_preferred":[
        "Epping Forest"
    ],
    "name:fra_x_preferred":[
        "Epping Forest"
    ],
    "name:gle_x_preferred":[
        "Foraois Epping"
    ],
    "name:heb_x_preferred":[
        "\u05d9\u05e2\u05e8 \u05d0\u05e4\u05d9\u05e0\u05d2"
    ],
    "name:isl_x_preferred":[
        "Eppingsk\u00f3gur"
    ],
    "name:ita_x_preferred":[
        "Epping Forest"
    ],
    "name:kor_x_preferred":[
        "\uc5d0\ud551\uc758 \uc232"
    ],
    "name:nor_x_preferred":[
        "Eppingskogen"
    ],
    "name:pol_x_preferred":[
        "Epping Forest"
    ],
    "name:swe_x_preferred":[
        "Epping Forest"
    ],
    "name:zho_x_preferred":[
        "\u827e\u576a\u68ee\u6797"
    ],
    "wof:name":"Epping Forest",
    "wof:placetype":"locality"
},
  "geometry": {"coordinates":[-76.53163000000001,39.01428],"type":"Point"}
}