{
  "type": "Feature",
  "properties": {
    "gn:admin1_code":"MO",
    "gn:admin2_code":"43.0",
    "gn:admin3_code":"42968.0",
    "gn:asciiname":"Pembina",
    "gn:country_code":"US",
    "gn:dem":422,
    "gn:elevation":"422.0",
    "gn:feature_class":"P",
    "gn:feature_code":"PPL",
    "gn:name":"Pembina",
    "gn:population":0,
    "gn:timezone":"America/Chicago",
    "iso:country":"US",
    "name:fra_x_preferred":[
        "Pembina"
    ],
    "name:ita_x_preferred":[
        "Pembina"
    ],
    "name:pol_x_preferred":[
        "Pembina"
    ],
    "name:rus_x_preferred":[
        "\u041f\u0435\u043c\u0431\u0438\u043d\u0430"
    ],
    "name:srp_x_preferred":[
        "\u041f\u0435\u043c\u0431\u0438\u043d\u0430"
    ],
    "wof:name":"Pembina",
    "wof:placetype":"locality"
},
  "geometry": {"coordinates":[-93.12184999999999,37.067],"type":"Point"}
}