{
  "type": "Feature",
  "properties": {
    "iso:country":"US",
    "name:eng_x_preferred":[
        "Silver Beach Heights"
    ],
    "wof:name":"Silver Beach Heights",
    "wof:placetype":"neighbourhood",
    "wof:population":754,
    "zs:area_m":6336674.823703,
    "zs:blockids":[
        120690301054022,
        120690301041067,
        120690301054019,
        120690301041070,
        120690301041055,
        120690301053017,
        120690301054017,
        120690301054010,
        120690301054057,
        120690301041072,
        120690301041054,
        120690301054006,
        120690301041049,
        120690301041052,
        120690301041051,
        120690301054014,
        120690301054003,
        120690301041050,
        120690301041069,
        120690301054004,
        120690301054002,
        120690301041065,
        120690301054013,
        120690301054005,
        120690301041053,
        120690301054015,
        120690301054000,
        120690301041045,
        120690301041066,
        120690301041044,
        120690301041071,
        120690301054001,
        120690301041048,
        120690301054007,
        120690301053014,
        120690301054008,
        120690301054009,
        120690301054016
    ],
    "zs:housing10":468,
    "zs:label":"Silver Beach Heights",
    "zs:pop10":754
},
  "geometry": {"coordinates":[-81.670126,28.952095],"type":"Point"}
}