{
  "type": "Feature",
  "properties": {
    "gn:admin1_code":"WV",
    "gn:admin2_code":"87.0",
    "gn:asciiname":"Morning Star",
    "gn:country_code":"US",
    "gn:dem":259,
    "gn:elevation":"250.0",
    "gn:feature_class":"P",
    "gn:feature_code":"PPL",
    "gn:name":"Morning Star",
    "gn:population":0,
    "gn:timezone":"America/New_York",
    "iso:country":"US",
    "name:bih_x_preferred":[
        "\u092d\u0941\u0930\u0941\u0915\u0941\u0906"
    ],
    "name:ceb_x_preferred":[
        "Morning Star"
    ],
    "name:fra_x_preferred":[
        "Morning Star"
    ],
    "name:ita_x_preferred":[
        "Morning Star"
    ],
    "name:jpn_x_preferred":[
        "\u30e2\u30fc\u30cb\u30f3\u30b0\u30b9\u30bf\u30fc"
    ],
    "name:kor_x_preferred":[
        "\ubaa8\ub2dd \uc2a4\ud0c0"
    ],
    "name:pol_x_preferred":[
        "Morning Star"
    ],
    "name:rus_x_preferred":[
        "Morning Star"
    ],
    "name:swa_x_preferred":[
        "Nyota ya asubuhi"
    ],
    "name:swe_x_preferred":[
        "Morning Star"
    ],
    "wof:name":"Morning Star",
    "wof:placetype":"locality"
},
  "geometry": {"coordinates":[-81.4554,38.77481],"type":"Point"}
}