{
  "type": "Feature",
  "properties": {
    "gn:admin1_code":"ID",
    "gn:admin2_code":"49",
    "gn:asciiname":"Red River Hot Springs",
    "gn:country_code":"US",
    "gn:dem":1525,
    "gn:elevation":"1526.0",
    "gn:feature_class":"P",
    "gn:feature_code":"PPL",
    "gn:name":"Red River Hot Springs",
    "gn:population":0,
    "gn:timezone":"America/Los_Angeles",
    "iso:country":"US",
    "wof:name":"Red River Hot Springs",
    "wof:placetype":"locality"
},
  "geometry": {"coordinates":[-115.20012,45.78769000000001],"type":"Point"}
}