{
  "type": "Feature",
  "properties": {
    "gn:admin1_code":"TX",
    "gn:admin2_code":"427.0",
    "gn:asciiname":"Rafael Pena Colonia",
    "gn:country_code":"US",
    "gn:dem":64,
    "gn:elevation":"63.0",
    "gn:feature_class":"P",
    "gn:feature_code":"PPL",
    "gn:name":"Rafael Pena Colonia",
    "gn:population":0,
    "gn:timezone":"America/Chicago",
    "iso:country":"US",
    "name:eng_x_preferred":[
        "Rafael Pena Colonia"
    ],
    "name:und_x_variant":[
        "Pena Brothers Subdivision Colonia"
    ],
    "wof:name":"Rafael Pena Colonia",
    "wof:placetype":"locality"
},
  "geometry": {"coordinates":[-98.64140999999999,26.30146],"type":"Point"}
}