{
  "type": "Feature",
  "properties": {
    "iso:country":"US",
    "name:eng_x_preferred":[
        "West Manchester"
    ],
    "name:eng_x_variant":[
        "W Manchester"
    ],
    "name:ita_x_preferred":[
        "West Manchester"
    ],
    "name:pol_x_preferred":[
        "West Manchester"
    ],
    "name:ukr_x_preferred":[
        "\u0412\u0435\u0441\u0442-\u041c\u0430\u043d\u0447\u0435\u0441\u0442\u0435\u0440"
    ],
    "qs:gn_fcode":"PPL",
    "qs:gn_local":0,
    "qs:gn_namadm1":"MA",
    "qs:gn_name":"West Manchester",
    "qs:local_max":815,
    "qs:local_sum":815,
    "qs:localhoods":1,
    "qs:name":"West Manchester",
    "qs:name_adm0":"United States",
    "qs:name_adm1":"Massachusetts",
    "qs:name_adm2":"Essex",
    "qs:name_local":"Manchester-by-the-Sea",
    "qs:photo_max":129,
    "qs:photo_sum":815,
    "qs:placetype":"Suburb",
    "qs:quad_count":52,
    "qs:woe_adm0":23424977,
    "qs:woe_adm1":2347580,
    "qs:woe_adm2":12588704,
    "qs:woe_lau":0,
    "qs:woe_local":2444698,
    "qs:woe_ver":"7.10.0",
    "wd:wordcount":14,
    "wof:lang":[
        "eng"
    ],
    "wof:name":"West Manchester",
    "wof:placetype":"neighbourhood"
},
  "geometry": {"coordinates":[-70.775446,42.568613],"type":"Point"}
}