{
  "type": "Feature",
  "properties": {
    "iso:country":"US",
    "name:eng_x_preferred":[
        "Jefferson Place"
    ],
    "name:eng_x_variant":[
        "Jefferson Pl",
        "Jefferson Place Gallery"
    ],
    "qs:gn_adm0_cc":"US",
    "qs:gn_fcode":"PPLX",
    "qs:gn_local":4315588,
    "qs:gn_nam_loc":"Baton Rouge, East Baton Rouge Parish, Louisiana, US",
    "qs:gn_namadm1":"LA",
    "qs:gn_name":"Jefferson Place",
    "qs:local_max":4803,
    "qs:local_sum":39503,
    "qs:localhoods":84,
    "qs:name":"Jefferson Place",
    "qs:name_adm0":"United States",
    "qs:name_adm1":"Louisiana",
    "qs:name_adm2":"East Baton Rouge Parish",
    "qs:name_local":"Baton Rouge",
    "qs:photo_max":9,
    "qs:photo_sum":16,
    "qs:placetype":"Suburb",
    "qs:quad_count":4,
    "qs:woe_adm0":23424977,
    "qs:woe_adm1":2347577,
    "qs:woe_adm2":12588612,
    "qs:woe_lau":0,
    "qs:woe_local":2359991,
    "qs:woe_ver":"7.10.0",
    "wd:wordcount":818,
    "wof:lang":[
        "eng"
    ],
    "wof:name":"Jefferson Place",
    "wof:placetype":"neighbourhood",
    "wof:population":1489,
    "zs:blockids":[
        220330038011008,
        220330038011009,
        220330038011010,
        220330038011006,
        220330038012020,
        220330038011005,
        220330038011011,
        220330038012008,
        220330038011007,
        220330038013006,
        220330038013005,
        220330038012009,
        220330038012019,
        220330038012011,
        220330038011012,
        220330038013004,
        220330038012017,
        220330038011017,
        220330038011016
    ],
    "zs:housing10":752,
    "zs:pop10":1489
},
  "geometry": {"coordinates":[-91.12164900000001,30.421154],"type":"Point"}
}