{
  "type": "Feature",
  "properties": {
    "gn:admin1_code":"NE",
    "gn:admin2_code":"129.0",
    "gn:asciiname":"Saint Stephens",
    "gn:country_code":"US",
    "gn:dem":570,
    "gn:elevation":"567.0",
    "gn:feature_class":"P",
    "gn:feature_code":"PPL",
    "gn:name":"Saint Stephens",
    "gn:population":0,
    "gn:timezone":"America/Chicago",
    "iso:country":"US",
    "wof:name":"Saint Stephens",
    "wof:placetype":"locality"
},
  "geometry": {"coordinates":[-98.25615999999999,40.25362],"type":"Point"}
}