{
  "type": "Feature",
  "properties": {
    "gn:gn_country":"US",
    "gn:gn_fcode":"PPL",
    "gn:gn_pop":0,
    "iso:country":"US",
    "name:ceb_x_preferred":[
        "Ramah"
    ],
    "name:deu_x_preferred":[
        "Ramah"
    ],
    "name:ita_x_preferred":[
        "Ramah"
    ],
    "name:nld_x_preferred":[
        "Ramah"
    ],
    "name:pol_x_preferred":[
        "Ramah"
    ],
    "name:por_x_preferred":[
        "Ramah"
    ],
    "name:srp_x_preferred":[
        "\u0420\u0435\u0458\u043c\u0430"
    ],
    "name:swe_x_preferred":[
        "Ramah"
    ],
    "name:vol_x_preferred":[
        "Ramah"
    ],
    "qs_pg:aaroncc":"US",
    "qs_pg:gn_country":"US",
    "qs_pg:gn_fcode":"PPL",
    "qs_pg:gn_pop":0,
    "qs_pg:name":"Ramah",
    "qs_pg:name_adm0":"United States",
    "qs_pg:name_adm1":"Louisiana",
    "qs_pg:photos":46,
    "qs_pg:photos_1k":9,
    "qs_pg:photos_9k":1,
    "qs_pg:photos_9r":2,
    "qs_pg:photos_all":46,
    "qs_pg:photos_sr":2,
    "qs_pg:pop_sr":0,
    "qs_pg:qs_pg_placetype":"locality",
    "qs_pg:qs_pg_placetype_gp":"Town",
    "qs_pg:woe_adm0":23424977,
    "woe:adm0_id":23424977,
    "woe:name_adm0":"United States",
    "woe:name_adm1":"Louisiana",
    "woe:placetype":"Town",
    "wof:name":"Ramah",
    "wof:placetype":"locality"
},
  "geometry": {"coordinates":[-91.50733,30.40242],"type":"Point"}
}