{
  "type": "Feature",
  "properties": {
    "gn:admin1_code":"SC",
    "gn:admin2_code":"81.0",
    "gn:asciiname":"Eulala",
    "gn:country_code":"US",
    "gn:dem":173,
    "gn:elevation":"173.0",
    "gn:feature_class":"P",
    "gn:feature_code":"PPL",
    "gn:name":"Eulala",
    "gn:population":0,
    "gn:timezone":"America/New_York",
    "iso:country":"US",
    "wof:name":"Eulala",
    "wof:placetype":"locality"
},
  "geometry": {"coordinates":[-81.91928,34.03069],"type":"Point"}
}