{
  "type": "Feature",
  "properties": {
    "gn:admin1_code":"WA",
    "gn:admin2_code":"61.0",
    "gn:asciiname":"Kellogg Village Mobile Home Park",
    "gn:country_code":"US",
    "gn:dem":22,
    "gn:elevation":"24.0",
    "gn:feature_class":"P",
    "gn:feature_code":"PPL",
    "gn:name":"Kellogg Village Mobile Home Park",
    "gn:population":0,
    "gn:timezone":"America/Los_Angeles",
    "iso:country":"US",
    "wof:name":"Kellogg Village Mobile Home Park",
    "wof:placetype":"campus"
},
  "geometry": {"coordinates":[-122.15209,48.08777],"type":"Point"}
}