{
  "type": "Feature",
  "properties": {
    "iso:country":"US",
    "qs_pg:aaroncc":"US",
    "qs_pg:name":"Amhurst",
    "qs_pg:name_adm0":"United States",
    "qs_pg:name_adm1":"Georgia",
    "qs_pg:photos":18,
    "qs_pg:photos_1k":4,
    "qs_pg:photos_9k":1,
    "qs_pg:photos_9r":1,
    "qs_pg:photos_all":18,
    "qs_pg:photos_sr":1,
    "qs_pg:pop_sr":0,
    "qs_pg:qs_pg_placetype":"neighbourhood",
    "qs_pg:qs_pg_placetype_gp":"Suburb",
    "qs_pg:woe_adm0":23424977,
    "woe:adm0_id":23424977,
    "woe:name_adm0":"United States",
    "woe:name_adm1":"Georgia",
    "woe:placetype":"Suburb",
    "wof:name":"Amhurst",
    "wof:placetype":"neighbourhood"
},
  "geometry": {"coordinates":[-84.548592,33.582233],"type":"Point"}
}