{
  "type": "Feature",
  "properties": {
    "iso:country":"US",
    "name:eng_x_preferred":[
        "Wyndhorse"
    ],
    "wof:name":"Wyndhorse",
    "wof:placetype":"neighbourhood",
    "wof:population":95,
    "zs:area_m":6001865.884711,
    "zs:blockids":[
        370779706032050,
        370779706032049,
        370779706033078
    ],
    "zs:housing10":41,
    "zs:label":"Wyndhorse",
    "zs:pop10":95
},
  "geometry": {"coordinates":[-78.697374,36.084363],"type":"Point"}
}