{
  "type": "Feature",
  "properties": {
    "gn:admin1_code":"FL",
    "gn:admin2_code":"77.0",
    "gn:asciiname":"Clio",
    "gn:country_code":"US",
    "gn:dem":43,
    "gn:elevation":"33.0",
    "gn:feature_class":"P",
    "gn:feature_code":"PPL",
    "gn:name":"Clio",
    "gn:population":0,
    "gn:timezone":"America/New_York",
    "iso:country":"US",
    "name:ara_x_preferred":[
        "\u0643\u0644\u064a\u0648"
    ],
    "name:aze_x_preferred":[
        "Klio"
    ],
    "name:bel_x_preferred":[
        "\u041a\u043b\u0456\u043e"
    ],
    "name:ben_x_preferred":[
        "\u0995\u09cd\u09b2\u09bf\u0993"
    ],
    "name:bos_x_preferred":[
        "Klio"
    ],
    "name:bre_x_preferred":[
        "Kleio"
    ],
    "name:bul_x_preferred":[
        "\u041a\u043b\u0438\u043e"
    ],
    "name:cat_x_preferred":[
        "Clio"
    ],
    "name:ces_x_preferred":[
        "Klei\u00f3"
    ],
    "name:dan_x_preferred":[
        "Kleio"
    ],
    "name:deu_x_preferred":[
        "Klio"
    ],
    "name:ell_x_preferred":[
        "\u039a\u03bb\u03b5\u03b9\u03ce"
    ],
    "name:epo_x_preferred":[
        "Klio"
    ],
    "name:est_x_preferred":[
        "Kleio"
    ],
    "name:eus_x_preferred":[
        "Klio"
    ],
    "name:fas_x_preferred":[
        "\u06a9\u0644\u06cc\u0648"
    ],
    "name:fin_x_preferred":[
        "Kleio"
    ],
    "name:fra_x_preferred":[
        "Clio"
    ],
    "name:glg_x_preferred":[
        "Cl\u00edo"
    ],
    "name:heb_x_preferred":[
        "\u05e7\u05dc\u05d9\u05d0\u05d5"
    ],
    "name:hrv_x_preferred":[
        "Klio"
    ],
    "name:hun_x_preferred":[
        "Klei\u00f3"
    ],
    "name:hye_x_preferred":[
        "\u053f\u056c\u056b\u0578"
    ],
    "name:ind_x_preferred":[
        "Kleio"
    ],
    "name:isl_x_preferred":[
        "Kl\u00ed\u00f3"
    ],
    "name:ita_x_preferred":[
        "Clio"
    ],
    "name:jpn_x_preferred":[
        "\u30af\u30ec\u30a4\u30aa\u30fc"
    ],
    "name:kat_x_preferred":[
        "\u10d9\u10da\u10d8\u10dd"
    ],
    "name:kor_x_preferred":[
        "\ud074\ub9ac\uc624"
    ],
    "name:lat_x_preferred":[
        "Clio"
    ],
    "name:lij_x_preferred":[
        "Clio"
    ],
    "name:lit_x_preferred":[
        "Kl\u0117jo"
    ],
    "name:ltz_x_preferred":[
        "Klio"
    ],
    "name:mkd_x_preferred":[
        "\u041a\u043b\u0438\u043e"
    ],
    "name:nds_x_preferred":[
        "Klio"
    ],
    "name:nld_x_preferred":[
        "Clio"
    ],
    "name:nor_x_preferred":[
        "Kleio"
    ],
    "name:pol_x_preferred":[
        "Klio"
    ],
    "name:por_x_preferred":[
        "Clio"
    ],
    "name:ron_x_preferred":[
        "Clio"
    ],
    "name:rus_x_preferred":[
        "\u041a\u043b\u0438\u043e"
    ],
    "name:sco_x_preferred":[
        "Clio"
    ],
    "name:slk_x_preferred":[
        "Kleio"
    ],
    "name:slv_x_preferred":[
        "Klio"
    ],
    "name:spa_x_preferred":[
        "Cl\u00edo"
    ],
    "name:srp_x_preferred":[
        "\u041a\u043b\u0438\u043e"
    ],
    "name:swe_x_preferred":[
        "Klio"
    ],
    "name:tur_x_preferred":[
        "Kleio"
    ],
    "name:ukr_x_preferred":[
        "\u041a\u043b\u0456\u043e"
    ],
    "name:uzb_x_preferred":[
        "Klio"
    ],
    "name:zho_x_preferred":[
        "\u514b\u5229\u4fc4"
    ],
    "wof:name":"Clio",
    "wof:placetype":"locality"
},
  "geometry": {"coordinates":[-84.82602,30.31936],"type":"Point"}
}