{
  "type": "Feature",
  "properties": {
    "iso:country":"US",
    "name:eng_x_preferred":[
        "Sierra Shores"
    ],
    "wof:name":"Sierra Shores",
    "wof:placetype":"neighbourhood",
    "wof:population":36,
    "zs:area_m":191019.228575,
    "zs:blockids":[
        60170302003005,
        60170302002031,
        60170302003004,
        60170302002030
    ],
    "zs:housing10":45,
    "zs:label":"Sierra Shores",
    "zs:pop10":36
},
  "geometry": {"coordinates":[-119.96627599999999,38.946076],"type":"Point"}
}