{
  "type": "Feature",
  "properties": {
    "gn:admin1_code":"OH",
    "gn:admin2_code":"39.0",
    "gn:admin3_code":"21420.0",
    "gn:asciiname":"The Bend",
    "gn:country_code":"US",
    "gn:dem":213,
    "gn:elevation":"214.0",
    "gn:feature_class":"P",
    "gn:feature_code":"PPL",
    "gn:name":"The Bend",
    "gn:population":0,
    "gn:timezone":"America/New_York",
    "iso:country":"US",
    "name:eng_x_preferred":[
        "The Bend"
    ],
    "name:und_x_variant":[
        "Delaware",
        "Delaware Bend"
    ],
    "wof:name":"The Bend",
    "wof:placetype":"locality"
},
  "geometry": {"coordinates":[-84.5155,41.28394],"type":"Point"}
}