{
  "type": "Feature",
  "properties": {
    "iso:country":"US",
    "name:eng_x_preferred":[
        "Fish Creek Station"
    ],
    "wd:wordcount":96,
    "wof:name":"Fish Creek Station",
    "wof:placetype":"neighbourhood",
    "wof:population":420,
    "zs:area_m":8968479.640126,
    "zs:blockids":[
        360659401001037,
        360650267004081,
        360659401001012,
        360659401001042,
        360659401001020,
        360659401001026,
        360659401001032,
        360650267004046,
        360650267004049,
        360659401001041,
        360650267004084,
        360659401001027,
        360659401001028,
        360650267004085,
        360659401001046,
        360659401001050,
        360650267004047,
        360659401001029,
        360659401001030,
        360659401001022,
        360659401001038,
        360659401001034,
        360659401001017,
        360659401001040,
        360659401001014,
        360659401001039,
        360650267004083,
        360659401001018,
        360659401001033,
        360659401001036,
        360650267004045,
        360659401001031,
        360659401001019,
        360659401001035,
        360659401001024,
        360659401001015,
        360650267004082,
        360650267004048,
        360659401001021,
        360659401001025,
        360659401001023,
        360659401001016,
        360659401001013
    ],
    "zs:housing10":403,
    "zs:label":"Fish Creek Station",
    "zs:pop10":420
},
  "geometry": {"coordinates":[-75.721918,43.185962],"type":"Point"}
}