{
  "type": "Feature",
  "properties": {
    "gn:admin1_code":"MT",
    "gn:admin2_code":"39.0",
    "gn:asciiname":"Byrne",
    "gn:country_code":"US",
    "gn:dem":1134,
    "gn:elevation":"1135.0",
    "gn:feature_class":"P",
    "gn:feature_code":"PPL",
    "gn:name":"Byrne",
    "gn:population":0,
    "gn:timezone":"America/Denver",
    "iso:country":"US",
    "wof:name":"Byrne",
    "wof:placetype":"locality"
},
  "geometry": {"coordinates":[-113.45341999999999,46.70382],"type":"Point"}
}