{
  "type": "Feature",
  "properties": {
    "gn:admin1_code":"NM",
    "gn:admin2_code":"57.0",
    "gn:asciiname":"Saiz Place",
    "gn:country_code":"US",
    "gn:dem":2083,
    "gn:elevation":"2085.0",
    "gn:feature_class":"P",
    "gn:feature_code":"PPL",
    "gn:name":"Saiz Place",
    "gn:population":0,
    "gn:timezone":"America/Denver",
    "iso:country":"US",
    "wof:name":"Saiz Place",
    "wof:placetype":"locality"
},
  "geometry": {"coordinates":[-106.32696,34.65228],"type":"Point"}
}