{
  "type": "Feature",
  "properties": {
    "gn:admin1_code":"NE",
    "gn:admin2_code":"159.0",
    "gn:asciiname":"Grover",
    "gn:country_code":"US",
    "gn:dem":434,
    "gn:elevation":"431.0",
    "gn:feature_class":"P",
    "gn:feature_code":"PPL",
    "gn:name":"Grover",
    "gn:population":0,
    "gn:timezone":"America/Chicago",
    "iso:country":"US",
    "name:eng_x_preferred":[
        "Grover"
    ],
    "name:und_x_variant":[
        "East Milford"
    ],
    "wof:name":"Grover",
    "wof:placetype":"locality"
},
  "geometry": {"coordinates":[-97.03780999999999,40.77973],"type":"Point"}
}