{
  "type": "Feature",
  "properties": {
    "gn:admin1_code":"WV",
    "gn:admin2_code":"39",
    "gn:asciiname":"Annfred",
    "gn:country_code":"US",
    "gn:dem":289,
    "gn:elevation":"273.0",
    "gn:feature_class":"P",
    "gn:feature_code":"PPL",
    "gn:name":"Annfred",
    "gn:population":0,
    "gn:timezone":"America/New_York",
    "iso:country":"US",
    "name:eng_x_preferred":[
        "Annfred"
    ],
    "name:fas_x_preferred":[
        "\u0627\u0646\u0641\u0631\u062f"
    ],
    "name:und_x_variant":[
        "Ten Mile"
    ],
    "wof:name":"Annfred",
    "wof:placetype":"locality"
},
  "geometry": {"coordinates":[-81.41373,38.30427],"type":"Point"}
}