{
  "type": "Feature",
  "properties": {
    "gn:admin1_code":"MS",
    "gn:admin2_code":"35.0",
    "gn:asciiname":"Eastside",
    "gn:country_code":"US",
    "gn:dem":62,
    "gn:elevation":"56.0",
    "gn:feature_class":"P",
    "gn:feature_code":"PPL",
    "gn:name":"Eastside",
    "gn:population":0,
    "gn:timezone":"America/Chicago",
    "iso:country":"US",
    "name:eng_x_preferred":[
        "Eastside"
    ],
    "name:und_x_variant":[
        "Myers",
        "Sheep Low"
    ],
    "wof:name":"Eastside",
    "wof:placetype":"locality"
},
  "geometry": {"coordinates":[-89.19367,31.28212000000001],"type":"Point"}
}