{
  "type": "Feature",
  "properties": {
    "iso:country":"US",
    "name:eng_x_preferred":[
        "Scotts Mill"
    ],
    "wof:name":"Scotts Mill",
    "wof:placetype":"neighbourhood",
    "wof:population":2576,
    "zs:area_m":1568018.357549,
    "zs:blockids":[
        371830534141006,
        371830534141012,
        371830534141035,
        371830534141021,
        371830534141002,
        371830534141026,
        371830534141036,
        371830534141001,
        371830534141016,
        371830534141004,
        371830534141013,
        371830534141038,
        371830534141018,
        371830534141020,
        371830534141032,
        371830534141009,
        371830534141010,
        371830534141051,
        371830534141042
    ],
    "zs:housing10":909,
    "zs:label":"Scotts Mill",
    "zs:pop10":2576
},
  "geometry": {"coordinates":[-78.886669,35.728181],"type":"Point"}
}