{
  "type": "Feature",
  "properties": {
    "gn:admin1_code":"IL",
    "gn:admin2_code":"65.0",
    "gn:admin3_code":"17627.0",
    "gn:asciiname":"Thurber",
    "gn:country_code":"US",
    "gn:dem":146,
    "gn:elevation":"146.0",
    "gn:feature_class":"P",
    "gn:feature_code":"PPL",
    "gn:name":"Thurber",
    "gn:population":0,
    "gn:timezone":"America/Chicago",
    "iso:country":"US",
    "name:deu_x_preferred":[
        "Thurber"
    ],
    "name:rus_x_preferred":[
        "\u0422\u0451\u0440\u0431\u0435\u0440"
    ],
    "wof:name":"Thurber",
    "wof:placetype":"locality"
},
  "geometry": {"coordinates":[-88.42755,38.08255],"type":"Point"}
}