{
  "type": "Feature",
  "properties": {
    "gn:admin1_code":"OH",
    "gn:admin2_code":"7.0",
    "gn:admin3_code":"21672.0",
    "gn:asciiname":"Bulah",
    "gn:country_code":"US",
    "gn:dem":285,
    "gn:elevation":"283.0",
    "gn:feature_class":"P",
    "gn:feature_code":"PPL",
    "gn:name":"Bulah",
    "gn:population":0,
    "gn:timezone":"America/New_York",
    "iso:country":"US",
    "wof:name":"Bulah",
    "wof:placetype":"locality"
},
  "geometry": {"coordinates":[-80.66840999999999,41.782],"type":"Point"}
}