{
  "type": "Feature",
  "properties": {
    "gn:admin1_code":"UT",
    "gn:admin2_code":"35.0",
    "gn:asciiname":"Sunburst Meadows",
    "gn:country_code":"US",
    "gn:dem":1370,
    "gn:elevation":"1368.0",
    "gn:feature_class":"P",
    "gn:feature_code":"PPL",
    "gn:name":"Sunburst Meadows",
    "gn:population":0,
    "gn:timezone":"America/Denver",
    "iso:country":"US",
    "wof:name":"Sunburst Meadows",
    "wof:placetype":"locality"
},
  "geometry": {"coordinates":[-111.87632000000001,40.59995],"type":"Point"}
}