{
  "type": "Feature",
  "properties": {
    "gn:admin1_code":"MI",
    "gn:admin2_code":"57.0",
    "gn:admin3_code":"25880.0",
    "gn:asciiname":"Beebe",
    "gn:country_code":"US",
    "gn:dem":228,
    "gn:elevation":"226.0",
    "gn:feature_class":"P",
    "gn:feature_code":"PPL",
    "gn:name":"Beebe",
    "gn:population":0,
    "gn:timezone":"America/Detroit",
    "iso:country":"US",
    "name:deu_x_preferred":[
        "Beebe"
    ],
    "name:glg_x_preferred":[
        "Beebe"
    ],
    "name:ita_x_preferred":[
        "Beebe"
    ],
    "name:por_x_preferred":[
        "Beebe"
    ],
    "name:spa_x_preferred":[
        "Beebe"
    ],
    "wof:name":"Beebe",
    "wof:placetype":"locality"
},
  "geometry": {"coordinates":[-84.54805,43.33531],"type":"Point"}
}