{
  "type": "Feature",
  "properties": {
    "gn:admin1_code":"WY",
    "gn:admin2_code":"33.0",
    "gn:asciiname":"Kleenburn",
    "gn:country_code":"US",
    "gn:dem":1104,
    "gn:elevation":"1110.0",
    "gn:feature_class":"P",
    "gn:feature_code":"PPL",
    "gn:name":"Kleenburn",
    "gn:population":0,
    "gn:timezone":"America/Denver",
    "iso:country":"US",
    "name:eng_x_preferred":[
        "Kleenburn"
    ],
    "name:und_x_variant":[
        "Carneyville"
    ],
    "wof:name":"Kleenburn",
    "wof:placetype":"locality"
},
  "geometry": {"coordinates":[-107.01257,44.90358],"type":"Point"}
}