{
  "type": "Feature",
  "properties": {
    "gn:admin1_code":"IA",
    "gn:admin2_code":"55.0",
    "gn:admin3_code":"90783.0",
    "gn:asciiname":"Holy Cross",
    "gn:country_code":"US",
    "gn:dem":328,
    "gn:elevation":"327.0",
    "gn:feature_class":"P",
    "gn:feature_code":"PPL",
    "gn:name":"Holy Cross",
    "gn:population":343,
    "gn:timezone":"America/Chicago",
    "iso:country":"US",
    "name:ara_x_preferred":[
        "\u0647\u0648\u0644\u064a \u0643\u0631\u0648\u0633"
    ],
    "name:ceb_x_preferred":[
        "Holy Cross"
    ],
    "name:deu_x_preferred":[
        "Holy Cross"
    ],
    "name:ita_x_preferred":[
        "Holy Cross"
    ],
    "name:nld_x_preferred":[
        "Holy Cross"
    ],
    "name:pol_x_preferred":[
        "Holy Cross"
    ],
    "name:rus_x_preferred":[
        "\u0425\u043e\u043b\u0438-\u041a\u0440\u043e\u0441\u0441"
    ],
    "name:srp_x_preferred":[
        "\u0425\u043e\u043b\u0438 \u041a\u0440\u043e\u0441"
    ],
    "name:ukr_x_preferred":[
        "\u0413\u043e\u043b\u0456-\u041a\u0440\u043e\u0441\u0441"
    ],
    "name:vol_x_preferred":[
        "Holy Cross"
    ],
    "wof:name":"Holy Cross",
    "wof:placetype":"locality",
    "wof:population":343
},
  "geometry": {"coordinates":[-91.22347000000001,42.59527],"type":"Point"}
}