{
  "type": "Feature",
  "properties": {
    "iso:country":"US",
    "name:eng_x_preferred":[
        "Diamond Willow"
    ],
    "name:eng_x_variant":[
        "Diamond willow",
        "diamond willow"
    ],
    "wd:wordcount":595,
    "wof:name":"Diamond Willow",
    "wof:placetype":"neighbourhood",
    "wof:population":117,
    "zs:area_m":95213.472621,
    "zs:blockids":[
        530110407031022,
        530110407031023
    ],
    "zs:housing10":45,
    "zs:label":"Diamond Willow",
    "zs:pop10":117
},
  "geometry": {"coordinates":[-122.56979,45.680956],"type":"Point"}
}