{
  "type": "Feature",
  "properties": {
    "gn:admin1_code":"AR",
    "gn:admin2_code":"129.0",
    "gn:admin3_code":"94062.0",
    "gn:asciiname":"Noahs",
    "gn:country_code":"US",
    "gn:dem":300,
    "gn:elevation":"286.0",
    "gn:feature_class":"P",
    "gn:feature_code":"PPL",
    "gn:name":"Noahs",
    "gn:population":0,
    "gn:timezone":"America/Chicago",
    "iso:country":"US",
    "wof:name":"Noahs",
    "wof:placetype":"locality"
},
  "geometry": {"coordinates":[-92.55043999999999,35.81590999999999],"type":"Point"}
}