{
  "type": "Feature",
  "properties": {
    "iso:country":"US",
    "name:eng_x_preferred":[
        "North Lansing"
    ],
    "wof:name":"North Lansing",
    "wof:placetype":"neighbourhood",
    "wof:population":438,
    "zs:area_m":469940.81435,
    "zs:blockids":[
        260650001002035,
        260650066002000,
        260650066002016,
        260650066002011,
        260650066002007,
        260650066002024,
        260650001001024,
        260650066002019,
        260650066002018,
        260650066002023,
        260650066002009,
        260650066002008,
        260650066002026,
        260650066002022,
        260650001002036,
        260650001002037,
        260650066002010,
        260650001002038,
        260650066002001,
        260650066002037,
        260650066002021,
        260650066002027,
        260650066002020,
        260650066002041,
        260650066002017,
        260650066002025
    ],
    "zs:housing10":217,
    "zs:label":"North Lansing",
    "zs:pop10":438
},
  "geometry": {"coordinates":[-84.545699,42.748501],"type":"Point"}
}