{
  "type": "Feature",
  "properties": {
    "gn:admin1_code":"UT",
    "gn:admin2_code":"11.0",
    "gn:asciiname":"Colonial Gardens Condominium",
    "gn:country_code":"US",
    "gn:dem":1346,
    "gn:elevation":"1342.0",
    "gn:feature_class":"P",
    "gn:feature_code":"PPL",
    "gn:name":"Colonial Gardens Condominium",
    "gn:population":0,
    "gn:timezone":"America/Denver",
    "iso:country":"US",
    "wof:name":"Colonial Gardens Condominium",
    "wof:placetype":"locality"
},
  "geometry": {"coordinates":[-111.87299,40.89467],"type":"Point"}
}