{
  "type": "Feature",
  "properties": {
    "gn:admin1_code":"VA",
    "gn:admin2_code":"169",
    "gn:asciiname":"Spivey Store",
    "gn:country_code":"US",
    "gn:dem":381,
    "gn:elevation":"378.0",
    "gn:feature_class":"P",
    "gn:feature_code":"PPL",
    "gn:name":"Spivey Store",
    "gn:population":0,
    "gn:timezone":"America/New_York",
    "iso:country":"US",
    "wof:name":"Spivey Store",
    "wof:placetype":"locality"
},
  "geometry": {"coordinates":[-82.68377,36.69649],"type":"Point"}
}