{
  "type": "Feature",
  "properties": {
    "iso:country":"US",
    "name:eng_x_preferred":[
        "Hot Springs Junction"
    ],
    "name:eng_x_variant":[
        "Hot Springs Jct"
    ],
    "qs:gn_adm0_cc":"US",
    "qs:gn_local":4119403,
    "qs:gn_nam_loc":"Little Rock, Pulaski, Arkansas, US",
    "qs:gn_namadm1":"AR",
    "qs:local_max":10871,
    "qs:local_sum":36947,
    "qs:localhoods":46,
    "qs:name":"Hot Springs Junction",
    "qs:name_adm0":"United States",
    "qs:name_adm1":"Arkansas",
    "qs:name_adm2":"Pulaski",
    "qs:name_local":"Little Rock",
    "qs:photo_max":155,
    "qs:photo_sum":162,
    "qs:placetype":"Suburb",
    "qs:quad_count":3,
    "qs:woe_adm0":23424977,
    "qs:woe_adm1":2347562,
    "qs:woe_adm2":12587654,
    "qs:woe_funk":"Parented by a neighborhood",
    "qs:woe_lau":0,
    "qs:woe_local":2440351,
    "qs:woe_ver":"7.10.0",
    "wof:lang":[
        "eng"
    ],
    "wof:name":"Hot Springs Junction",
    "wof:placetype":"neighbourhood",
    "wof:population":84,
    "zs:blockids":[
        51190020021026,
        51190020011000,
        51190011003068,
        51190020021016,
        51190020021015,
        51190020021014,
        51190020021017,
        51190011003069,
        51190020021008,
        51190011003053,
        51190011003084,
        51190011003070,
        51190011003085,
        51190020021004,
        51190020021009,
        51190011003046,
        51190012001064,
        51190011001029,
        51190011003042,
        51190020021048,
        51190020021018,
        51190011003083,
        51190011003073,
        51190020021006,
        51190020021011,
        51190012001063,
        51190011003080,
        51190011003054,
        51190011003047,
        51190020021007,
        51190011001032,
        51190020021028,
        51190020021012,
        51190011003067,
        51190020021013,
        51190011003045,
        51190011003056,
        51190011003058,
        51190020021005,
        51190011003049,
        51190020021052,
        51190011003077,
        51190011003051,
        51190011003048,
        51190011003052,
        51190011003057,
        51190020021010
    ],
    "zs:housing10":36,
    "zs:pop10":84
},
  "geometry": {"coordinates":[-92.29752999999999,34.718072],"type":"Point"}
}