{
  "type": "Feature",
  "properties": {
    "gn:gn_country":"US",
    "gn:gn_fcode":"PPL",
    "gn:gn_pop":0,
    "iso:country":"US",
    "name:eng_x_preferred":[
        "Beaver"
    ],
    "name:fra_x_preferred":[
        "Beaver"
    ],
    "name:spa_x_preferred":[
        "Beaver"
    ],
    "name:unk_x_variant":[
        "Pleasant"
    ],
    "qs_pg:aaroncc":"US",
    "qs_pg:gn_country":"US",
    "qs_pg:gn_fcode":"PPL",
    "qs_pg:gn_pop":0,
    "qs_pg:name":"Beaver",
    "qs_pg:name_adm0":"United States",
    "qs_pg:name_adm1":"Washington",
    "qs_pg:photos":68,
    "qs_pg:photos_1k":14,
    "qs_pg:photos_9k":1,
    "qs_pg:photos_9r":2,
    "qs_pg:photos_all":68,
    "qs_pg:photos_sr":2,
    "qs_pg:pop_sr":5,
    "qs_pg:qs_pg_placetype":"locality",
    "qs_pg:qs_pg_placetype_gp":"Town",
    "qs_pg:woe_adm0":23424977,
    "woe:adm0_id":23424977,
    "woe:name_adm0":"United States",
    "woe:name_adm1":"Washington",
    "woe:placetype":"Town",
    "wof:name":"Beaver",
    "wof:placetype":"locality"
},
  "geometry": {"coordinates":[-124.34744000000001,48.0573],"type":"Point"}
}