{
  "type": "Feature",
  "properties": {
    "gn:country":"US",
    "gn:fcode":"PPL",
    "gn:population":0,
    "iso:country":"US",
    "name:ara_x_preferred":[
        "\u0628\u064a\u0641\u0631"
    ],
    "name:azb_x_preferred":[
        "\u0628\u06cc\u0648\u0631"
    ],
    "name:ben_x_preferred":[
        "\u09ac\u09c0\u09ad\u09be\u09b0"
    ],
    "name:cym_x_preferred":[
        "Beaver"
    ],
    "name:deu_x_preferred":[
        "Beaver"
    ],
    "name:ell_x_preferred":[
        "\u039c\u03c0\u03af\u03c9\u03b5\u03c1"
    ],
    "name:eng_x_preferred":[
        "Beaver"
    ],
    "name:fas_x_preferred":[
        "\u0628\u06cc\u0648\u0631"
    ],
    "name:fra_x_preferred":[
        "Beaver"
    ],
    "name:heb_x_preferred":[
        "\u05d1\u05bc\u05d9\u05d5\u05b6\u05d5\u05e8"
    ],
    "name:hin_x_preferred":[
        "\u092c\u0940\u0935\u0930"
    ],
    "name:hun_x_preferred":[
        "Beaver"
    ],
    "name:ind_x_preferred":[
        "Beaver"
    ],
    "name:jpn_x_preferred":[
        "\u30d3\u30fc\u30d0\u30fc\u5ddd"
    ],
    "name:kor_x_preferred":[
        "\ube44\ubc84"
    ],
    "name:nld_x_preferred":[
        "Beaver"
    ],
    "name:spa_x_preferred":[
        "Beaver"
    ],
    "name:tur_x_preferred":[
        "Beaver"
    ],
    "name:ukr_x_preferred":[
        "\u0411\u0456\u0432\u0435\u0440"
    ],
    "name:und_x_variant":[
        "Pleasant"
    ],
    "name:urd_x_preferred":[
        "\u0628\u06cc\u0648\u0631"
    ],
    "name:vie_x_preferred":[
        "S\u00f4ng Beaver"
    ],
    "name:zho_cn_x_preferred":[
        "\u6bd4\u5f17\u6cb3"
    ],
    "name:zho_tw_x_preferred":[
        "\u6bd4\u4f5b\u6cb3"
    ],
    "qs_pg:aaroncc":"US",
    "qs_pg:gn_country":"US",
    "qs_pg:gn_fcode":"PPL",
    "qs_pg:gn_pop":0,
    "qs_pg:name":"Beaver",
    "qs_pg:name_adm0":"United States",
    "qs_pg:name_adm1":"Washington",
    "qs_pg:photos":68,
    "qs_pg:photos_1k":14,
    "qs_pg:photos_9k":1,
    "qs_pg:photos_9r":2,
    "qs_pg:photos_all":68,
    "qs_pg:photos_sr":2,
    "qs_pg:pop_sr":5,
    "qs_pg:qs_pg_placetype":"locality",
    "qs_pg:qs_pg_placetype_gp":"Town",
    "qs_pg:woe_adm0":23424977,
    "woe:adm0_id":23424977,
    "woe:name_adm0":"United States",
    "woe:name_adm1":"Washington",
    "woe:placetype":"Town",
    "wof:name":"Beaver",
    "wof:placetype":"locality"
},
  "geometry": {"coordinates":[-124.34744000000001,48.0573],"type":"Point"}
}