{
  "type": "Feature",
  "properties": {
    "gn:admin1_code":"GA",
    "gn:admin2_code":"285.0",
    "gn:asciiname":"Creek Ridge",
    "gn:country_code":"US",
    "gn:dem":222,
    "gn:elevation":"211.0",
    "gn:feature_class":"P",
    "gn:feature_code":"PPL",
    "gn:name":"Creek Ridge",
    "gn:population":0,
    "gn:timezone":"America/New_York",
    "iso:country":"US",
    "wof:name":"Creek Ridge",
    "wof:placetype":"locality"
},
  "geometry": {"coordinates":[-85.04411,33.10179],"type":"Point"}
}