{
  "type": "Feature",
  "properties": {
    "gn:admin1_code":"WA",
    "gn:admin2_code":"53.0",
    "gn:asciiname":"Pinecrest Mobile Home Park",
    "gn:country_code":"US",
    "gn:dem":95,
    "gn:elevation":"96.0",
    "gn:feature_class":"P",
    "gn:feature_code":"PPL",
    "gn:name":"Pinecrest Mobile Home Park",
    "gn:population":0,
    "gn:timezone":"America/Los_Angeles",
    "iso:country":"US",
    "wof:name":"Pinecrest Mobile Home Park",
    "wof:placetype":"campus"
},
  "geometry": {"coordinates":[-122.45667,47.15988],"type":"Point"}
}