{
  "type": "Feature",
  "properties": {
    "gn:admin1_code":"TX",
    "gn:admin2_code":"255",
    "gn:asciiname":"Conquista Crossing",
    "gn:country_code":"US",
    "gn:dem":95,
    "gn:elevation":"84.0",
    "gn:feature_class":"P",
    "gn:feature_code":"PPL",
    "gn:name":"Conquista Crossing",
    "gn:population":0,
    "gn:timezone":"America/Chicago",
    "iso:country":"US",
    "wof:name":"Conquista Crossing",
    "wof:placetype":"locality"
},
  "geometry": {"coordinates":[-98.05723,28.94275],"type":"Point"}
}