{
  "type": "Feature",
  "properties": {
    "gn:admin1_code":"IL",
    "gn:admin2_code":"195.0",
    "gn:admin3_code":"38700.0",
    "gn:asciiname":"Penrose",
    "gn:country_code":"US",
    "gn:dem":222,
    "gn:elevation":"220.0",
    "gn:feature_class":"P",
    "gn:feature_code":"PPL",
    "gn:name":"Penrose",
    "gn:population":0,
    "gn:timezone":"America/Chicago",
    "iso:country":"US",
    "name:ceb_x_preferred":[
        "Penrose"
    ],
    "name:deu_x_preferred":[
        "Penrose"
    ],
    "name:fas_x_preferred":[
        "\u067e\u0646\u0631\u0648\u0632"
    ],
    "name:fin_x_preferred":[
        "Penrose"
    ],
    "name:fra_x_preferred":[
        "Penrose"
    ],
    "name:ita_x_preferred":[
        "Penrose"
    ],
    "name:lav_x_preferred":[
        "Penrouzs"
    ],
    "name:nds_x_preferred":[
        "Penrose"
    ],
    "name:nld_x_preferred":[
        "Penrose"
    ],
    "name:por_x_preferred":[
        "Penrose"
    ],
    "name:rus_x_preferred":[
        "\u041f\u0435\u043d\u0440\u043e\u0443\u0437"
    ],
    "name:spa_x_preferred":[
        "Penrose"
    ],
    "wof:name":"Penrose",
    "wof:placetype":"locality"
},
  "geometry": {"coordinates":[-89.66789,41.88753],"type":"Point"}
}