{
  "type": "Feature",
  "properties": {
    "iso:country":"US",
    "name:ceb_x_preferred":[
        "Eagle Ridge"
    ],
    "name:eng_x_preferred":[
        "Eagle Ridge"
    ],
    "name:swe_x_preferred":[
        "Eagle Ridge"
    ],
    "wd:wordcount":106,
    "wof:name":"Eagle Ridge",
    "wof:placetype":"neighbourhood",
    "wof:population":703,
    "zs:area_m":728001.841679,
    "zs:blockids":[
        120710401083014,
        120710401083013,
        120710401083006,
        120710401083012
    ],
    "zs:housing10":382,
    "zs:label":"Eagle Ridge",
    "zs:pop10":703
},
  "geometry": {"coordinates":[-81.826572,26.535636],"type":"Point"}
}