{
  "type": "Feature",
  "properties": {
    "gn:admin1_code":"AL",
    "gn:admin2_code":"125.0",
    "gn:asciiname":"Abernant",
    "gn:country_code":"US",
    "gn:dem":146,
    "gn:elevation":"142.0",
    "gn:feature_class":"P",
    "gn:feature_code":"PPL",
    "gn:name":"Abernant",
    "gn:population":0,
    "gn:timezone":"America/Chicago",
    "iso:country":"US",
    "name:deu_x_preferred":[
        "Abernant"
    ],
    "name:eng_x_preferred":[
        "Abernant"
    ],
    "name:fas_x_preferred":[
        "\u0627\u0628\u0631\u0646\u0627\u0646\u062a"
    ],
    "name:hat_x_preferred":[
        "Abernant"
    ],
    "name:por_x_preferred":[
        "Abernant"
    ],
    "name:und_x_variant":[
        "Abernath",
        "Abernanth",
        "Abernath City"
    ],
    "name:zho_x_preferred":[
        "\u963f\u4f2f\u5357\u7279"
    ],
    "wof:name":"Abernant",
    "wof:placetype":"locality"
},
  "geometry": {"coordinates":[-87.19804999999999,33.29039],"type":"Point"}
}