{
  "type": "Feature",
  "properties": {
    "gn:admin1_code":"VA",
    "gn:admin2_code":"53",
    "gn:asciiname":"Truit",
    "gn:country_code":"US",
    "gn:dem":68,
    "gn:elevation":"64.0",
    "gn:feature_class":"P",
    "gn:feature_code":"PPL",
    "gn:name":"Truit",
    "gn:population":0,
    "gn:timezone":"America/New_York",
    "iso:country":"US",
    "wof:name":"Truit",
    "wof:placetype":"locality"
},
  "geometry": {"coordinates":[-77.54971,36.93571],"type":"Point"}
}