{
  "type": "Feature",
  "properties": {
    "gn:admin1_code":"PA",
    "gn:admin2_code":"133.0",
    "gn:admin3_code":"72992.0",
    "gn:asciiname":"Stonewood Farms",
    "gn:country_code":"US",
    "gn:dem":147,
    "gn:elevation":"146.0",
    "gn:feature_class":"P",
    "gn:feature_code":"PPL",
    "gn:name":"Stonewood Farms",
    "gn:population":0,
    "gn:timezone":"America/New_York",
    "iso:country":"US",
    "wof:name":"Stonewood Farms",
    "wof:placetype":"locality"
},
  "geometry": {"coordinates":[-76.62719,39.97954],"type":"Point"}
}