{
  "type": "Feature",
  "properties": {
    "gn:admin1_code":"TX",
    "gn:admin2_code":"141.0",
    "gn:asciiname":"Mary Lou Park Colonia",
    "gn:country_code":"US",
    "gn:dem":1112,
    "gn:elevation":"1116.0",
    "gn:feature_class":"P",
    "gn:feature_code":"PPL",
    "gn:name":"Mary Lou Park Colonia",
    "gn:population":0,
    "gn:timezone":"America/Denver",
    "iso:country":"US",
    "wof:name":"Mary Lou Park Colonia",
    "wof:placetype":"locality"
},
  "geometry": {"coordinates":[-106.26358999999999,31.65122],"type":"Point"}
}