{
  "type": "Feature",
  "properties": {
    "gn:admin1_code":"TX",
    "gn:admin2_code":"257",
    "gn:asciiname":"Gastonia",
    "gn:country_code":"US",
    "gn:dem":137,
    "gn:elevation":"136.0",
    "gn:feature_class":"P",
    "gn:feature_code":"PPL",
    "gn:name":"Gastonia",
    "gn:population":0,
    "gn:timezone":"America/Chicago",
    "iso:country":"US",
    "wof:name":"Gastonia",
    "wof:placetype":"locality"
},
  "geometry": {"coordinates":[-96.40248,32.6118],"type":"Point"}
}