{
  "type": "Feature",
  "properties": {
    "gn:admin1_code":"VA",
    "gn:admin2_code":"71",
    "gn:asciiname":"Prospectdale",
    "gn:country_code":"US",
    "gn:dem":602,
    "gn:elevation":"592.0",
    "gn:feature_class":"P",
    "gn:feature_code":"PPL",
    "gn:name":"Prospectdale",
    "gn:population":0,
    "gn:timezone":"America/New_York",
    "iso:country":"US",
    "wof:name":"Prospectdale",
    "wof:placetype":"locality"
},
  "geometry": {"coordinates":[-80.74313000000002,37.27818],"type":"Point"}
}