{
  "type": "Feature",
  "properties": {
    "gn:admin1_code":"TN",
    "gn:admin2_code":"11",
    "gn:asciiname":"Mapleton Hills",
    "gn:country_code":"US",
    "gn:dem":243,
    "gn:elevation":"244.0",
    "gn:feature_class":"P",
    "gn:feature_code":"PPL",
    "gn:name":"Mapleton Hills",
    "gn:population":0,
    "gn:timezone":"America/New_York",
    "iso:country":"US",
    "wof:name":"Mapleton Hills",
    "wof:placetype":"locality"
},
  "geometry": {"coordinates":[-84.84716999999998,35.23424],"type":"Point"}
}