{
  "type": "Feature",
  "properties": {
    "iso:country":"US",
    "name:eng_x_preferred":[
        "Chateaux Versailles"
    ],
    "name:fra_x_preferred":[
        "Charles-Fran\u00e7ois Nanteuil-Leboeuf"
    ],
    "name:rus_x_preferred":[
        "\u041d\u0430\u043d\u0442\u0451\u0439\u043b\u044c"
    ],
    "name:spa_x_preferred":[
        "Charles-Fran\u00e7ois Leb\u0153uf"
    ],
    "wof:name":"Chateaux Versailles",
    "wof:placetype":"neighbourhood",
    "wof:population":2114,
    "zs:area_m":1175429.129321,
    "zs:blockids":[
        121030246021000,
        121030242002025,
        121030242003001,
        121030243023000,
        121030242002005,
        121030243022026,
        121030242002009,
        121030242002010,
        121030243023005,
        121030243022025,
        121030246021011,
        121030243023006,
        121030242002007,
        121030243023013,
        121030242003002,
        121030243021020,
        121030246021010,
        121030243023010,
        121030242002008,
        121030242002022,
        121030242002021,
        121030243023009,
        121030243023001,
        121030243023008,
        121030243023007,
        121030242002006,
        121030242002024,
        121030242002020,
        121030243021016,
        121030243023004,
        121030243023012,
        121030246012017,
        121030242002023,
        121030243021015,
        121030243023002,
        121030243023011
    ],
    "zs:housing10":1377,
    "zs:label":"Chateaux Versailles",
    "zs:pop10":2114
},
  "geometry": {"coordinates":[-82.661654,27.824272],"type":"Point"}
}