{
  "type": "Feature",
  "properties": {
    "iso:country":"US",
    "name:eng_x_preferred":[
        "The East Side"
    ],
    "qs:gn_adm0_cc":"US",
    "qs:gn_local":5175496,
    "qs:gn_nam_loc":"Wadsworth, Medina, Ohio, US",
    "qs:gn_namadm1":"OH",
    "qs:local_max":449,
    "qs:local_sum":551,
    "qs:localhoods":4,
    "qs:name":"The East Side",
    "qs:name_adm0":"United States",
    "qs:name_adm1":"Ohio",
    "qs:name_adm2":"Medina",
    "qs:name_local":"Wadsworth",
    "qs:photo_max":46,
    "qs:photo_sum":46,
    "qs:placetype":"Suburb",
    "qs:quad_count":1,
    "qs:woe_adm0":23424977,
    "qs:woe_adm1":2347594,
    "qs:woe_adm2":12589578,
    "qs:woe_lau":0,
    "qs:woe_local":2513035,
    "qs:woe_ver":"7.10.0",
    "wof:lang":[
        "eng"
    ],
    "wof:name":"The East Side",
    "wof:placetype":"neighbourhood",
    "wof:population":537,
    "zs:blockids":[
        391034171005023,
        391034172003000
    ],
    "zs:housing10":219,
    "zs:pop10":537
},
  "geometry": {"coordinates":[-81.709442,41.022392],"type":"Point"}
}