{
  "type": "Feature",
  "properties": {
    "gn:admin1_code":"TN",
    "gn:admin2_code":"57",
    "gn:asciiname":"Idol",
    "gn:country_code":"US",
    "gn:dem":436,
    "gn:elevation":"429.0",
    "gn:feature_class":"P",
    "gn:feature_code":"PPL",
    "gn:name":"Idol",
    "gn:population":0,
    "gn:timezone":"America/New_York",
    "iso:country":"US",
    "name:ces_x_preferred":[
        "Idol"
    ],
    "name:dan_x_preferred":[
        "Idol"
    ],
    "name:deu_x_preferred":[
        "Idol"
    ],
    "name:eng_x_preferred":[
        "Idol"
    ],
    "name:fra_x_preferred":[
        "Idol"
    ],
    "name:gla_x_preferred":[
        "Iodhal"
    ],
    "name:hun_x_preferred":[
        "Idol"
    ],
    "name:ind_x_preferred":[
        "Idol"
    ],
    "name:ita_x_preferred":[
        "Idol"
    ],
    "name:jpn_x_preferred":[
        "\u30a2\u30a4\u30c9\u30eb"
    ],
    "name:kor_x_preferred":[
        "\uc544\uc774\ub3cc"
    ],
    "name:nld_x_preferred":[
        "Idool"
    ],
    "name:pol_x_preferred":[
        "Idol"
    ],
    "name:rus_x_preferred":[
        "\u0418\u0434\u043e\u043b"
    ],
    "name:slk_x_preferred":[
        "Idol"
    ],
    "name:srp_x_preferred":[
        "\u0418\u0434\u043e\u043b"
    ],
    "name:und_x_variant":[
        "Idol Cross Roads"
    ],
    "name:vie_x_preferred":[
        "Th\u1ea7n t\u01b0\u1ee3ng"
    ],
    "wof:name":"Idol",
    "wof:placetype":"locality"
},
  "geometry": {"coordinates":[-83.40156999999998,36.36675],"type":"Point"}
}