{
  "type": "Feature",
  "properties": {
    "iso:country":"US",
    "name:eng_x_preferred":[
        "Choctaw Corner"
    ],
    "wd:wordcount":562,
    "wof:name":"Choctaw Corner",
    "wof:placetype":"neighbourhood",
    "wof:population":13,
    "zs:area_m":28795.246168,
    "zs:blockids":[
        10259576022029
    ],
    "zs:housing10":5,
    "zs:label":"Choctaw Corner",
    "zs:pop10":13
},
  "geometry": {"coordinates":[-87.753046,31.92707],"type":"Point"}
}