{
  "type": "Feature",
  "properties": {
    "gn:elevation":294,
    "iso:country":"US",
    "name:cat_x_preferred":[
        "Groveland"
    ],
    "name:ceb_x_preferred":[
        "Groveland"
    ],
    "name:deu_x_preferred":[
        "Groveland"
    ],
    "name:eng_x_preferred":[
        "Groveland"
    ],
    "name:fra_x_preferred":[
        "Groveland"
    ],
    "name:hbs_x_preferred":[
        "Grovland"
    ],
    "name:ita_x_preferred":[
        "Groveland"
    ],
    "name:pol_x_preferred":[
        "Groveland"
    ],
    "name:srp_x_preferred":[
        "\u0413\u0440\u043e\u0432\u043b\u0430\u043d\u0434"
    ],
    "name:ukr_x_preferred":[
        "\u0413\u0440\u043e\u0443\u0432\u043b\u0435\u043d\u0434"
    ],
    "name:vol_x_preferred":[
        "Groveland"
    ],
    "qs:gn_fcode":"PPL",
    "qs:gn_local":0,
    "qs:gn_namadm1":"MN",
    "qs:gn_name":"Groveland",
    "qs:local_max":829,
    "qs:local_sum":1764,
    "qs:localhoods":4,
    "qs:name":"Groveland",
    "qs:name_adm0":"United States",
    "qs:name_adm1":"Minnesota",
    "qs:name_adm2":"Hennepin",
    "qs:name_local":"Minnetonka",
    "qs:photo_max":490,
    "qs:photo_sum":829,
    "qs:placetype":"Suburb",
    "qs:quad_count":31,
    "qs:woe_adm0":23424977,
    "qs:woe_adm1":2347582,
    "qs:woe_adm2":12588823,
    "qs:woe_lau":0,
    "qs:woe_local":2452147,
    "qs:woe_ver":"7.10.0",
    "wd:wordcount":80,
    "wof:lang":[
        "eng"
    ],
    "wof:name":"Groveland",
    "wof:placetype":"neighbourhood"
},
  "geometry": {"coordinates":[-93.485305,44.935845],"type":"Point"}
}