{
  "type": "Feature",
  "properties": {
    "gn:admin1_code":"ME",
    "gn:admin2_code":"25.0",
    "gn:admin3_code":"14555.0",
    "gn:asciiname":"Mitchell Corner",
    "gn:country_code":"US",
    "gn:dem":98,
    "gn:elevation":"95.0",
    "gn:feature_class":"P",
    "gn:feature_code":"PPL",
    "gn:name":"Mitchell Corner",
    "gn:population":0,
    "gn:timezone":"America/New_York",
    "iso:country":"US",
    "wof:name":"Mitchell Corner",
    "wof:placetype":"locality"
},
  "geometry": {"coordinates":[-69.60533000000001,44.83228],"type":"Point"}
}