{
  "type": "Feature",
  "properties": {
    "gn:gn_country":"US",
    "gn:gn_fcode":"PPL",
    "gn:gn_pop":0,
    "iso:country":"US",
    "name:ceb_x_preferred":[
        "Bay View"
    ],
    "name:deu_x_preferred":[
        "Bay View"
    ],
    "name:eng_x_preferred":[
        "Bay View"
    ],
    "name:fra_x_preferred":[
        "Bay View"
    ],
    "name:ita_x_preferred":[
        "Bay View"
    ],
    "name:mlg_x_preferred":[
        "Bay View"
    ],
    "name:nld_x_preferred":[
        "Bay View"
    ],
    "name:pol_x_preferred":[
        "Bay View"
    ],
    "name:por_x_preferred":[
        "Bay View"
    ],
    "name:srp_x_preferred":[
        "\u0411\u0435\u0458 \u0412\u0458\u0443"
    ],
    "name:swe_x_preferred":[
        "Bay View"
    ],
    "name:ukr_x_preferred":[
        "\u0411\u0435\u0439-\u0412'\u044e"
    ],
    "name:unk_x_variant":[
        "Bayview"
    ],
    "name:vol_x_preferred":[
        "Bay View"
    ],
    "qs_pg:aaroncc":"US",
    "qs_pg:gn_country":"US",
    "qs_pg:gn_fcode":"PPL",
    "qs_pg:gn_pop":0,
    "qs_pg:name":"Bay View",
    "qs_pg:name_adm0":"United States",
    "qs_pg:name_adm1":"Maryland",
    "qs_pg:photos":34,
    "qs_pg:photos_1k":7,
    "qs_pg:photos_9k":1,
    "qs_pg:photos_9r":2,
    "qs_pg:photos_all":34,
    "qs_pg:photos_sr":2,
    "qs_pg:pop_sr":5,
    "qs_pg:qs_pg_placetype":"locality",
    "qs_pg:qs_pg_placetype_gp":"Town",
    "qs_pg:woe_adm0":23424977,
    "woe:adm0_id":23424977,
    "woe:name_adm0":"United States",
    "woe:name_adm1":"Maryland",
    "woe:placetype":"Town",
    "wof:name":"Bay View",
    "wof:placetype":"locality"
},
  "geometry": {"coordinates":[-75.96133,39.64345],"type":"Point"}
}