{
  "type": "Feature",
  "properties": {
    "gn:admin1_code":"OH",
    "gn:admin2_code":"113",
    "gn:admin3_code":"33922.0",
    "gn:asciiname":"Woodland Hills Mobile Home Park",
    "gn:country_code":"US",
    "gn:dem":245,
    "gn:elevation":"244.0",
    "gn:feature_class":"P",
    "gn:feature_code":"PPL",
    "gn:name":"Woodland Hills Mobile Home Park",
    "gn:population":0,
    "gn:timezone":"America/New_York",
    "iso:country":"US",
    "wof:name":"Woodland Hills Mobile Home Park",
    "wof:placetype":"campus"
},
  "geometry": {"coordinates":[-84.18805999999999,39.8075],"type":"Point"}
}