{
  "type": "Feature",
  "properties": {
    "iso:country":"US",
    "name:arz_x_preferred":[
        "\u0645\u0637\u0627\u0631 \u0622\u0631\u062b\u0631 \u0627\u0646 \u0646\u064a\u0648"
    ],
    "name:ceb_x_preferred":[
        "Arthur N Neu Airport"
    ],
    "name:eng_x_preferred":[
        "Arthur N Neu Airport"
    ],
    "name:eng_x_variant":[
        "CIN",
        "KCIN",
        "Arthur N. Neu Airport"
    ],
    "name:fas_x_preferred":[
        "\u0641\u0631\u0648\u062f\u06af\u0627\u0647 \u0622\u0631\u062a\u0648\u0631 \u0627\u0646. \u0646\u0648\u0627"
    ],
    "name:fra_x_preferred":[
        "a\u00e9rodrome d'Arthur N Neu"
    ],
    "name:ron_x_preferred":[
        "Aeroportul Arthur N. Neu"
    ],
    "name:tgk_x_preferred":[
        "\u0424\u0443\u0440\u0443\u0434\u0433\u043e\u04b3\u0438 \u0410\u0440\u0442\u0443\u0440 \u041d\u0435\u0443"
    ],
    "name:tgk_x_variant":[
        "\u0424\u0443\u0440\u0443\u0434\u0433\u043e\u04b3\u0438 \u043e\u0440\u0442\u04ef\u0440 \u0430\u043d. \u043d\u0443\u043e"
    ],
    "name:urd_x_preferred":[
        "\u0622\u0631\u062a\u06be\u0631 \u0627\u06cc\u0646 \u0646\u0626\u0648 \u06c1\u0648\u0627\u0626\u06cc \u0627\u0688\u0627"
    ],
    "name:zho_x_preferred":[
        "Arthur N. Neu\u6a5f\u5834"
    ],
    "oa:elevation_ft":"1204",
    "oa:type":"small_airport",
    "wd:wordcount":262,
    "woe:hierarchy":{
        "country_id":23424977,
        "county_id":12588285,
        "planet_id":1,
        "state_id":2347574
    },
    "wof:name":"Arthur N Neu Airport",
    "wof:placetype":"campus"
},
  "geometry": {"coordinates":[-94.789001,42.0462],"type":"Point"}
}