{
  "type": "Feature",
  "properties": {
    "gn:country":"US",
    "gn:fcode":"PPL",
    "gn:population":0,
    "iso:country":"US",
    "qs_pg:aaroncc":"US",
    "qs_pg:gn_country":"US",
    "qs_pg:gn_fcode":"PPL",
    "qs_pg:gn_pop":0,
    "qs_pg:name":"Harbert",
    "qs_pg:name_adm0":"United States",
    "qs_pg:name_adm1":"Michigan",
    "qs_pg:photos":389,
    "qs_pg:photos_1k":79,
    "qs_pg:photos_9k":2,
    "qs_pg:photos_9r":5,
    "qs_pg:photos_all":389,
    "qs_pg:photos_sr":6,
    "qs_pg:pop_sr":0,
    "qs_pg:qs_pg_placetype":"locality",
    "qs_pg:qs_pg_placetype_gp":"Town",
    "qs_pg:woe_adm0":23424977,
    "woe:adm0_id":23424977,
    "woe:name_adm0":"United States",
    "woe:name_adm1":"Michigan",
    "woe:placetype":"Town",
    "wof:name":"Harbert",
    "wof:placetype":"locality"
},
  "geometry": {"coordinates":[-86.62891,41.87199],"type":"Point"}
}