{
  "type": "Feature",
  "properties": {
    "iso:country":"US",
    "wof:name":"Downtown Trussville",
    "wof:placetype":"neighbourhood"
},
  "geometry": {"coordinates":[-86.61149403927882,33.62038669360621],"type":"Point"}
}