{
  "type": "Feature",
  "properties": {
    "gn:admin1_code":"VA",
    "gn:admin2_code":"153",
    "gn:asciiname":"Brent Turf Acres",
    "gn:country_code":"US",
    "gn:dem":57,
    "gn:elevation":"55.0",
    "gn:feature_class":"P",
    "gn:feature_code":"PPL",
    "gn:name":"Brent Turf Acres",
    "gn:population":0,
    "gn:timezone":"America/New_York",
    "iso:country":"US",
    "wof:name":"Brent Turf Acres",
    "wof:placetype":"locality"
},
  "geometry": {"coordinates":[-77.51499,38.69595],"type":"Point"}
}