{
  "type": "Feature",
  "properties": {
    "gn:admin1_code":"MS",
    "gn:admin2_code":"55.0",
    "gn:asciiname":"Booth",
    "gn:country_code":"US",
    "gn:dem":31,
    "gn:elevation":"32.0",
    "gn:feature_class":"P",
    "gn:feature_code":"PPL",
    "gn:name":"Booth",
    "gn:population":0,
    "gn:timezone":"America/Chicago",
    "iso:country":"US",
    "name:ceb_x_preferred":[
        "Booth"
    ],
    "name:ces_x_preferred":[
        "Booth"
    ],
    "name:deu_x_preferred":[
        "Booth"
    ],
    "name:fin_x_preferred":[
        "Booth"
    ],
    "name:fra_x_preferred":[
        "Booth"
    ],
    "name:heb_x_preferred":[
        "\u05d1\u05d5\u05ea'"
    ],
    "name:ita_x_preferred":[
        "Booth"
    ],
    "name:jpn_x_preferred":[
        "\u30d6\u30fc\u30b9"
    ],
    "name:nld_x_preferred":[
        "Booth"
    ],
    "name:pol_x_preferred":[
        "Booth"
    ],
    "name:rus_x_preferred":[
        "\u0411\u0443\u0442"
    ],
    "name:spa_x_preferred":[
        "Booth"
    ],
    "name:srp_x_preferred":[
        "\u0411\u0443\u0442"
    ],
    "name:swe_x_preferred":[
        "Booth"
    ],
    "name:ukr_x_preferred":[
        "\u0411\u0443\u0442"
    ],
    "wof:name":"Booth",
    "wof:placetype":"locality"
},
  "geometry": {"coordinates":[-90.93177,32.96068],"type":"Point"}
}