{
  "type": "Feature",
  "properties": {
    "gn:admin1_code":"WV",
    "gn:admin2_code":"107",
    "gn:asciiname":"Humphrey",
    "gn:country_code":"US",
    "gn:dem":182,
    "gn:elevation":"183.0",
    "gn:feature_class":"P",
    "gn:feature_code":"PPL",
    "gn:name":"Humphrey",
    "gn:population":0,
    "gn:timezone":"America/New_York",
    "iso:country":"US",
    "wof:name":"Humphrey",
    "wof:placetype":"locality"
},
  "geometry": {"coordinates":[-81.73151999999997,39.14258],"type":"Point"}
}