{
  "type": "Feature",
  "properties": {
    "gn:country":"US",
    "gn:fcode":"PPL",
    "gn:population":0,
    "iso:country":"US",
    "name:ara_x_preferred":[
        "\u062d\u0645\u064a\u0644"
    ],
    "name:ces_x_preferred":[
        "Samorost"
    ],
    "name:cym_x_preferred":[
        "Broc m\u00f4r"
    ],
    "name:dan_x_preferred":[
        "Drivt\u00f8mmer"
    ],
    "name:dan_x_variant":[
        "drivt\u00f8mmer"
    ],
    "name:deu_x_preferred":[
        "Treibholz"
    ],
    "name:eng_x_preferred":[
        "Driftwood"
    ],
    "name:eng_x_variant":[
        "driftwood"
    ],
    "name:epo_x_preferred":[
        "Flosligno"
    ],
    "name:epo_x_variant":[
        "flosligno"
    ],
    "name:fas_x_preferred":[
        "\u0686\u0648\u0628 \u0622\u0628\u200c\u0622\u0648\u0631\u062f"
    ],
    "name:fin_x_preferred":[
        "ajopuu"
    ],
    "name:fra_x_preferred":[
        "bois flott\u00e9"
    ],
    "name:ind_x_preferred":[
        "Kapar"
    ],
    "name:isl_x_preferred":[
        "Rekavi\u00f0ur"
    ],
    "name:jpn_x_preferred":[
        "\u6d41\u6728"
    ],
    "name:kor_x_preferred":[
        "\uc720\ubaa9"
    ],
    "name:nld_x_preferred":[
        "Drijfhout"
    ],
    "name:nld_x_variant":[
        "drijfhout"
    ],
    "name:nno_x_preferred":[
        "rekved"
    ],
    "name:nob_x_preferred":[
        "rekved"
    ],
    "name:rus_x_preferred":[
        "\u043f\u043b\u0430\u0432\u043d\u0438\u043a"
    ],
    "name:spa_x_preferred":[
        "madera flotante"
    ],
    "name:swe_x_preferred":[
        "Drivved"
    ],
    "name:zho_x_preferred":[
        "\u6f02\u6d41\u6728"
    ],
    "qs_pg:aaroncc":"US",
    "qs_pg:gn_country":"US",
    "qs_pg:gn_fcode":"PPL",
    "qs_pg:gn_pop":0,
    "qs_pg:name":"Driftwood",
    "qs_pg:name_adm0":"United States",
    "qs_pg:name_adm1":"New York",
    "qs_pg:photos":1,
    "qs_pg:photos_1k":1,
    "qs_pg:photos_9k":1,
    "qs_pg:photos_9r":1,
    "qs_pg:photos_all":1,
    "qs_pg:photos_sr":1,
    "qs_pg:pop_sr":0,
    "qs_pg:qs_pg_placetype":"neighbourhood",
    "qs_pg:qs_pg_placetype_gp":"Suburb",
    "qs_pg:woe_adm0":23424977,
    "wd:wordcount":818,
    "wof:name":"Driftwood",
    "wof:placetype":"neighbourhood",
    "wof:population":66,
    "zs:area_m":708184.063568,
    "zs:blockids":[
        360130369023003
    ],
    "zs:housing10":29,
    "zs:label":"Driftwood",
    "zs:pop10":66
},
  "geometry": {"coordinates":[-79.33766900000001,42.132371],"type":"Point"}
}