{
  "type": "Feature",
  "properties": {
    "gn:admin1_code":"ID",
    "gn:admin2_code":"65.0",
    "gn:asciiname":"Edmonds",
    "gn:country_code":"US",
    "gn:dem":1482,
    "gn:elevation":"1482.0",
    "gn:feature_class":"P",
    "gn:feature_code":"PPL",
    "gn:name":"Edmonds",
    "gn:population":0,
    "gn:timezone":"America/Boise",
    "iso:country":"US",
    "name:ces_x_preferred":[
        "Edmonds"
    ],
    "name:deu_x_preferred":[
        "Edmonds"
    ],
    "name:fra_x_preferred":[
        "Edmonds"
    ],
    "name:nld_x_preferred":[
        "Edmonds"
    ],
    "name:rus_x_preferred":[
        "\u042d\u0434\u043c\u043e\u043d\u0434\u0441"
    ],
    "wof:name":"Edmonds",
    "wof:placetype":"locality"
},
  "geometry": {"coordinates":[-111.88079999999999,43.91297],"type":"Point"}
}