{
  "type": "Feature",
  "properties": {
    "iso:country":"US",
    "name:ceb_x_preferred":[
        "Gallows Hill"
    ],
    "name:eng_x_preferred":[
        "Gallows Hill"
    ],
    "name:und_x_variant":[
        "Brackenridges"
    ],
    "wd:wordcount":166,
    "wof:name":"Gallows Hill",
    "wof:placetype":"neighbourhood",
    "wof:population":1465,
    "zs:area_m":724397.19258,
    "zs:blockids":[
        420454050003003,
        420454050003004,
        420454049001007,
        420454049002016,
        420454050003005,
        420454047001004,
        420454049001009,
        420454050003000,
        420454050001002,
        420454050003011,
        420454049001006,
        420454047001003,
        420454047001008,
        420454047002042,
        420454050001000,
        420454047001000,
        420454063001000,
        420454046001014,
        420454047002031,
        420454050003002,
        420454049001004,
        420454050003009,
        420454047001007,
        420454050003007,
        420454050003010,
        420454050003008,
        420454047002041,
        420454049001008,
        420454047002030,
        420454047001006,
        420454047001010,
        420454049001013,
        420454049002011,
        420454049002010,
        420454047001002,
        420454050003006,
        420454047001005,
        420454047002037,
        420454050003012,
        420454047001001,
        420454047001009,
        420454049001005,
        420454050003001
    ],
    "zs:housing10":699,
    "zs:label":"Gallows Hill",
    "zs:pop10":1465
},
  "geometry": {"coordinates":[-75.363049,39.855565],"type":"Point"}
}