{
  "type": "Feature",
  "properties": {
    "gn:admin1_code":"NC",
    "gn:admin2_code":"167.0",
    "gn:admin3_code":"91416.0",
    "gn:asciiname":"Palmerville",
    "gn:country_code":"US",
    "gn:dem":186,
    "gn:elevation":"184.0",
    "gn:feature_class":"P",
    "gn:feature_code":"PPL",
    "gn:name":"Palmerville",
    "gn:population":0,
    "gn:timezone":"America/New_York",
    "iso:country":"US",
    "name:eng_x_preferred":[
        "Palmerville"
    ],
    "name:und_x_variant":[
        "Palmeryville"
    ],
    "wof:name":"Palmerville",
    "wof:placetype":"locality"
},
  "geometry": {"coordinates":[-80.11754999999999,35.42736],"type":"Point"}
}