{
  "type": "Feature",
  "properties": {
    "gn:admin1_code":"TX",
    "gn:admin2_code":"427.0",
    "gn:asciiname":"Valle Hermosa Colonia",
    "gn:country_code":"US",
    "gn:dem":52,
    "gn:elevation":"49.0",
    "gn:feature_class":"P",
    "gn:feature_code":"PPL",
    "gn:name":"Valle Hermosa Colonia",
    "gn:population":0,
    "gn:timezone":"America/Chicago",
    "iso:country":"US",
    "name:eng_x_preferred":[
        "Valle Hermosa Colonia"
    ],
    "name:und_x_variant":[
        "Valle Hermosa Subdivision Colonia"
    ],
    "wof:name":"Valle Hermosa Colonia",
    "wof:placetype":"locality"
},
  "geometry": {"coordinates":[-98.78725,26.38145],"type":"Point"}
}