{
  "type": "Feature",
  "properties": {
    "gn:elevation":141,
    "gn:population":1025,
    "iso:country":"US",
    "name:ara_x_preferred":[
        "\u062a\u064a\u0631\u0627\u0645\u0648\u063a\u0648\u0633"
    ],
    "name:azb_x_preferred":[
        "\u062a\u0631\u0627\u0645\u0627\u0642\u0648\u0633"
    ],
    "name:ceb_x_preferred":[
        "Terramuggus"
    ],
    "name:che_x_preferred":[
        "\u0422\u0435\u0440\u0440\u0430\u043c\u0443\u0433\u0433\u0443\u0441"
    ],
    "name:cym_x_preferred":[
        "Terramuggus"
    ],
    "name:deu_x_preferred":[
        "Terramuggus"
    ],
    "name:eng_x_preferred":[
        "Terramuggus"
    ],
    "name:eus_x_preferred":[
        "Terramuggus"
    ],
    "name:fas_x_preferred":[
        "\u062a\u0631\u0627\u0645\u0627\u06af\u0648\u0633"
    ],
    "name:fra_x_preferred":[
        "Terramuggus"
    ],
    "name:gle_x_preferred":[
        "Terramuggus"
    ],
    "name:ita_x_preferred":[
        "Terramuggus"
    ],
    "name:lld_x_preferred":[
        "Terramuggus"
    ],
    "name:nan_x_preferred":[
        "Terramuggus"
    ],
    "name:nld_x_preferred":[
        "Terramuggus"
    ],
    "name:por_x_preferred":[
        "Terramuggus"
    ],
    "name:spa_x_preferred":[
        "Terramuggus"
    ],
    "name:srp_x_preferred":[
        "Terramuggus"
    ],
    "name:tat_x_preferred":[
        "\u0422\u0435\u0440\u0440\u0430\u043c\u0443\u0433\u0433\u0443\u0441"
    ],
    "name:tur_x_preferred":[
        "Terramuggus"
    ],
    "name:ukr_x_preferred":[
        "\u0422\u0435\u0440\u0440\u0430\u043c\u0443\u0433\u0433\u0443\u0441"
    ],
    "name:uzb_x_preferred":[
        "Terramuggus"
    ],
    "name:vol_x_preferred":[
        "Terramuggus"
    ],
    "qs:gn_fcode":"PPL",
    "qs:gn_local":0,
    "qs:gn_namadm1":"CT",
    "qs:gn_name":"Terramuggus",
    "qs:local_max":34,
    "qs:local_sum":34,
    "qs:localhoods":1,
    "qs:name":"Terramuggus",
    "qs:name_adm0":"United States",
    "qs:name_adm1":"Connecticut",
    "qs:name_adm2":"Hartford",
    "qs:name_local":"Marlborough",
    "qs:photo_max":20,
    "qs:photo_sum":34,
    "qs:placetype":"Suburb",
    "qs:quad_count":10,
    "qs:woe_adm0":23424977,
    "qs:woe_adm1":2347565,
    "qs:woe_adm2":12587792,
    "qs:woe_lau":0,
    "qs:woe_local":2445916,
    "qs:woe_ver":"7.10.0",
    "wof:lang":[
        "eng"
    ],
    "wof:name":"Terramuggus",
    "wof:placetype":"neighbourhood",
    "wof:population":1025
},
  "geometry": {"coordinates":[-72.464849,41.651428],"type":"Point"}
}