{
  "type": "Feature",
  "properties": {
    "iso:country":"US",
    "name:eng_x_preferred":[
        "Chatsworth Acres"
    ],
    "wd:elevation":298.0,
    "wd:wordcount":3478,
    "wof:name":"Chatsworth Acres",
    "wof:placetype":"neighbourhood",
    "wof:population":228,
    "zs:area_m":326424.83215,
    "zs:blockids":[
        220330040052006,
        220330040052001
    ],
    "zs:housing10":119,
    "zs:label":"Chatsworth Acres",
    "zs:pop10":228
},
  "geometry": {"coordinates":[-91.120323,30.369511],"type":"Point"}
}