{
  "type": "Feature",
  "properties": {
    "iso:country":"US",
    "qs_pg:aaroncc":"US",
    "qs_pg:name":"Clinton Stock Yards",
    "qs_pg:name_adm0":"United States",
    "qs_pg:name_adm1":"Iowa",
    "qs_pg:photos":25,
    "qs_pg:photos_1k":5,
    "qs_pg:photos_9k":1,
    "qs_pg:photos_9r":1,
    "qs_pg:photos_all":25,
    "qs_pg:photos_sr":1,
    "qs_pg:pop_sr":0,
    "qs_pg:qs_pg_placetype":"locality",
    "qs_pg:qs_pg_placetype_gp":"Town",
    "qs_pg:woe_adm0":23424977,
    "woe:adm0_id":23424977,
    "woe:name_adm0":"United States",
    "woe:name_adm1":"Iowa",
    "woe:placetype":"Town",
    "wof:name":"Clinton Stock Yards",
    "wof:placetype":"locality"
},
  "geometry": {"coordinates":[-90.21938299999999,41.817272],"type":"Point"}
}