{
  "type": "Feature",
  "properties": {
    "gn:admin1_code":"TN",
    "gn:admin2_code":"141.0",
    "gn:asciiname":"Pinhook",
    "gn:country_code":"US",
    "gn:dem":568,
    "gn:elevation":"561.0",
    "gn:feature_class":"P",
    "gn:feature_code":"PPL",
    "gn:name":"Pinhook",
    "gn:population":0,
    "gn:timezone":"America/Chicago",
    "iso:country":"US",
    "wof:name":"Pinhook",
    "wof:placetype":"locality"
},
  "geometry": {"coordinates":[-85.3133,36.1334],"type":"Point"}
}