{
  "type": "Feature",
  "properties": {
    "iso:country":"US",
    "name:ceb_x_preferred":[
        "Plainview"
    ],
    "name:deu_x_preferred":[
        "Plainview"
    ],
    "name:fra_x_preferred":[
        "Plainview"
    ],
    "name:ita_x_preferred":[
        "Plainview"
    ],
    "name:nld_x_preferred":[
        "Plainview"
    ],
    "name:pol_x_preferred":[
        "Plainview"
    ],
    "name:por_x_preferred":[
        "Plainview"
    ],
    "name:rus_x_preferred":[
        "\u041f\u043b\u0435\u0439\u043d\u0432\u044c\u044e"
    ],
    "name:srp_x_preferred":[
        "\u041f\u043b\u0435\u0458\u043d\u0432\u0458\u0443"
    ],
    "name:swe_x_preferred":[
        "Plainview"
    ],
    "name:vol_x_preferred":[
        "Plainview"
    ],
    "qs_pg:aaroncc":"US",
    "qs_pg:name":"Plainview",
    "qs_pg:name_adm0":"United States",
    "qs_pg:name_adm1":"Oregon",
    "qs_pg:photos":175,
    "qs_pg:photos_1k":35,
    "qs_pg:photos_9k":1,
    "qs_pg:photos_9r":4,
    "qs_pg:photos_all":175,
    "qs_pg:photos_sr":4,
    "qs_pg:pop_sr":0,
    "qs_pg:qs_pg_placetype":"locality",
    "qs_pg:qs_pg_placetype_gp":"Town",
    "qs_pg:woe_adm0":23424977,
    "woe:adm0_id":23424977,
    "woe:name_adm0":"United States",
    "woe:name_adm1":"Oregon",
    "woe:placetype":"Town",
    "wof:name":"Plainview",
    "wof:placetype":"locality"
},
  "geometry": {"coordinates":[-121.436862,44.215293],"type":"Point"}
}