{
  "type": "Feature",
  "properties": {
    "gn:admin1_code":"TN",
    "gn:admin2_code":"29.0",
    "gn:asciiname":"Redwine",
    "gn:country_code":"US",
    "gn:dem":354,
    "gn:elevation":"348.0",
    "gn:feature_class":"P",
    "gn:feature_code":"PPL",
    "gn:name":"Redwine",
    "gn:population":0,
    "gn:timezone":"America/New_York",
    "iso:country":"US",
    "wof:name":"Redwine",
    "wof:placetype":"locality"
},
  "geometry": {"coordinates":[-83.19294000000002,36.09426],"type":"Point"}
}