{
  "type": "Feature",
  "properties": {
    "gn:admin1_code":"AR",
    "gn:admin2_code":"87.0",
    "gn:admin3_code":"93759.0",
    "gn:asciiname":"Brannon",
    "gn:country_code":"US",
    "gn:dem":699,
    "gn:elevation":"699.0",
    "gn:feature_class":"P",
    "gn:feature_code":"PPL",
    "gn:name":"Brannon",
    "gn:population":0,
    "gn:timezone":"America/Chicago",
    "iso:country":"US",
    "wof:name":"Brannon",
    "wof:placetype":"locality"
},
  "geometry": {"coordinates":[-93.94631,35.81786],"type":"Point"}
}