{
  "type": "Feature",
  "properties": {
    "gn:admin1_code":"KY",
    "gn:admin2_code":"149.0",
    "gn:asciiname":"Johnson Island",
    "gn:country_code":"US",
    "gn:dem":126,
    "gn:elevation":"130.0",
    "gn:feature_class":"P",
    "gn:feature_code":"PPL",
    "gn:name":"Johnson Island",
    "gn:population":0,
    "gn:timezone":"America/Chicago",
    "iso:country":"US",
    "name:ceb_x_preferred":[
        "Johnson Island"
    ],
    "name:deu_x_preferred":[
        "Johnson Island"
    ],
    "name:swe_x_preferred":[
        "Johnson Island"
    ],
    "wof:name":"Johnson Island",
    "wof:placetype":"locality"
},
  "geometry": {"coordinates":[-87.30371,37.59376],"type":"Point"}
}