{
  "type": "Feature",
  "properties": {
    "gn:admin1_code":"VA",
    "gn:admin2_code":"143",
    "gn:asciiname":"Woodlake Park",
    "gn:country_code":"US",
    "gn:dem":169,
    "gn:elevation":"164.0",
    "gn:feature_class":"P",
    "gn:feature_code":"PPL",
    "gn:name":"Woodlake Park",
    "gn:population":0,
    "gn:timezone":"America/New_York",
    "iso:country":"US",
    "wof:name":"Woodlake Park",
    "wof:placetype":"locality"
},
  "geometry": {"coordinates":[-79.38308000000001,36.64958],"type":"Point"}
}