{
  "type": "Feature",
  "properties": {
    "gn:admin1_code":"NM",
    "gn:admin2_code":"59",
    "gn:asciiname":"Gladstone",
    "gn:country_code":"US",
    "gn:dem":1793,
    "gn:elevation":"1793.0",
    "gn:feature_class":"P",
    "gn:feature_code":"PPL",
    "gn:name":"Gladstone",
    "gn:population":0,
    "gn:timezone":"America/Denver",
    "iso:country":"US",
    "name:azb_x_preferred":[
        "\u0642\u0644\u0627\u062f\u0633\u062a\u0648\u0646"
    ],
    "name:fas_x_preferred":[
        "\u06af\u0644\u0627\u062f\u0633\u062a\u0648\u0646"
    ],
    "name:hun_x_preferred":[
        "Gladstone"
    ],
    "name:urd_x_preferred":[
        "\u06af\u0644\u06cc\u0688\u0633\u0679\u0648\u0646"
    ],
    "wof:name":"Gladstone",
    "wof:placetype":"locality"
},
  "geometry": {"coordinates":[-103.97302999999999,36.30475],"type":"Point"}
}