{
  "type": "Feature",
  "properties": {
    "iso:country":"US",
    "name:eng_x_preferred":[
        "Copper Hills"
    ],
    "wof:name":"Copper Hills",
    "wof:placetype":"neighbourhood",
    "wof:population":4032,
    "zs:area_m":11384914.954682,
    "zs:blockids":[
        60710104123059,
        60710104123066,
        60710104123052,
        60710104123055,
        60710104123014,
        60710104123019,
        60710104122008,
        60710104122009,
        60710104121050,
        60710104121008,
        60710104121039,
        60710104122042,
        60710104122028,
        60710104122022,
        60710104122027,
        60710104123073,
        60710104123057,
        60710104123013,
        60710104123007,
        60710104123001,
        60710104123000,
        60710104122016,
        60710104121044,
        60710104123060,
        60710104123054,
        60710104123056,
        60710104123058,
        60710104123064,
        60710104123012,
        60710104123068,
        60710104122026,
        60710104122015,
        60710104122029,
        60710104122012,
        60710104121051,
        60710104121052,
        60710104121035,
        60710104122019,
        60710104123018,
        60710104122020,
        60710104123070,
        60710104191022,
        60710104123017,
        60710104122031,
        60710104121009,
        60710104121042,
        60710104121049,
        60710104121041,
        60710104121037,
        60710104122025,
        60710104122018,
        60710104191041,
        60710104122032,
        60710104123069,
        60710104123071,
        60710104123051,
        60710104123077,
        60710104123005,
        60710104122023,
        60710104122030,
        60710104122014,
        60710104123078,
        60710104123053,
        60710104123004,
        60710104122017,
        60710104121045,
        60710104121038,
        60710104121040,
        60710104122024,
        60710104191027,
        60710104122021,
        60710104123067,
        60710104123061,
        60710104123062,
        60710104123010,
        60710104123003,
        60710104122013,
        60710104122011,
        60710104121007,
        60710104123086,
        60710104123011,
        60710104123063,
        60710104123006,
        60710104123002,
        60710104121043,
        60710104121036
    ],
    "zs:housing10":1610,
    "zs:label":"Copper Hills",
    "zs:pop10":4032
},
  "geometry": {"coordinates":[-116.38939999999999,34.108954],"type":"Point"}
}