{
  "type": "Feature",
  "properties": {
    "gn:admin1_code":"WI",
    "gn:admin2_code":"53.0",
    "gn:admin3_code":"28325.0",
    "gn:asciiname":"Price",
    "gn:country_code":"US",
    "gn:dem":330,
    "gn:elevation":"331.0",
    "gn:feature_class":"P",
    "gn:feature_code":"PPL",
    "gn:name":"Price",
    "gn:population":0,
    "gn:timezone":"America/Chicago",
    "iso:country":"US",
    "name:ben_x_preferred":[
        "\u09aa\u09cd\u09b0\u09be\u0987\u09b8"
    ],
    "name:ell_x_preferred":[
        "\u03a0\u03c1\u03ac\u03b9\u03c2"
    ],
    "name:heb_x_preferred":[
        "\u05e4\u05e8\u05d9\u05d9\u05e1"
    ],
    "name:hin_x_preferred":[
        "\u092a\u094d\u0930\u093e\u0907\u0938"
    ],
    "name:ind_x_preferred":[
        "Price"
    ],
    "name:urd_x_preferred":[
        "\u067e\u0631\u0627\u0626\u0633"
    ],
    "name:vie_x_preferred":[
        "Price"
    ],
    "wof:name":"Price",
    "wof:placetype":"locality"
},
  "geometry": {"coordinates":[-91.05459999999999,44.58163],"type":"Point"}
}