{
  "type": "Feature",
  "properties": {
    "gn:admin1_code":"TX",
    "gn:admin2_code":"409.0",
    "gn:asciiname":"Bayview Estates Colonia",
    "gn:country_code":"US",
    "gn:dem":6,
    "gn:elevation":"3.0",
    "gn:feature_class":"P",
    "gn:feature_code":"PPL",
    "gn:name":"Bayview Estates Colonia",
    "gn:population":0,
    "gn:timezone":"America/Chicago",
    "iso:country":"US",
    "wof:name":"Bayview Estates Colonia",
    "wof:placetype":"locality"
},
  "geometry": {"coordinates":[-97.21720999999999,28.01418],"type":"Point"}
}