{
  "type": "Feature",
  "properties": {
    "gn:admin1_code":"SC",
    "gn:admin2_code":"87.0",
    "gn:asciiname":"Tuckertown",
    "gn:country_code":"US",
    "gn:dem":145,
    "gn:elevation":"134.0",
    "gn:feature_class":"P",
    "gn:feature_code":"PPL",
    "gn:name":"Tuckertown",
    "gn:population":0,
    "gn:timezone":"America/New_York",
    "iso:country":"US",
    "name:deu_x_preferred":[
        "Tuckertown"
    ],
    "name:eng_x_preferred":[
        "Tuckertown"
    ],
    "name:und_x_variant":[
        "Richardsville",
        "Tucker Town"
    ],
    "wof:name":"Tuckertown",
    "wof:placetype":"locality"
},
  "geometry": {"coordinates":[-81.48593000000002,34.52625],"type":"Point"}
}