{
  "type": "Feature",
  "properties": {
    "gn:admin1_code":"KY",
    "gn:admin2_code":"205",
    "gn:asciiname":"Hays Crossing",
    "gn:country_code":"US",
    "gn:dem":281,
    "gn:elevation":"272.0",
    "gn:feature_class":"P",
    "gn:feature_code":"PPL",
    "gn:name":"Hays Crossing",
    "gn:population":0,
    "gn:timezone":"America/New_York",
    "iso:country":"US",
    "name:eng_x_preferred":[
        "Hays Crossing"
    ],
    "name:und_x_variant":[
        "Hayes",
        "Eadston"
    ],
    "wof:name":"Hays Crossing",
    "wof:placetype":"locality"
},
  "geometry": {"coordinates":[-83.34435000000001,38.24425],"type":"Point"}
}