{
  "type": "Feature",
  "properties": {
    "gn:admin1_code":"TN",
    "gn:admin2_code":"13.0",
    "gn:asciiname":"Agee (historical)",
    "gn:country_code":"US",
    "gn:dem":305,
    "gn:elevation":"311.0",
    "gn:feature_class":"P",
    "gn:feature_code":"PPL",
    "gn:name":"Agee (historical)",
    "gn:population":0,
    "gn:timezone":"America/New_York",
    "iso:country":"US",
    "wof:name":"Agee (historical)",
    "wof:placetype":"locality"
},
  "geometry": {"coordinates":[-84.02353000000002,36.29869],"type":"Point"}
}