{
  "type": "Feature",
  "properties": {
    "gn:gn_country":"US",
    "gn:gn_fcode":"PPL",
    "gn:gn_pop":0,
    "iso:country":"US",
    "name:ceb_x_preferred":[
        "Ellendale"
    ],
    "name:deu_x_preferred":[
        "Ellendale"
    ],
    "name:fra_x_preferred":[
        "Ellendale"
    ],
    "name:ido_x_preferred":[
        "Ellendale"
    ],
    "name:ita_x_preferred":[
        "Ellendale"
    ],
    "name:nld_x_preferred":[
        "Ellendale"
    ],
    "name:pol_x_preferred":[
        "Ellendale"
    ],
    "name:por_x_preferred":[
        "Ellendale"
    ],
    "name:srp_x_preferred":[
        "\u0415\u043b\u0435\u043d\u0434\u0435\u0458\u043b"
    ],
    "name:swe_x_preferred":[
        "Ellendale"
    ],
    "name:vol_x_preferred":[
        "Ellendale"
    ],
    "qs_pg:aaroncc":"US",
    "qs_pg:gn_country":"US",
    "qs_pg:gn_fcode":"PPL",
    "qs_pg:gn_pop":0,
    "qs_pg:name":"Ellendale",
    "qs_pg:name_adm0":"United States",
    "qs_pg:name_adm1":"Virginia",
    "qs_pg:photos":292,
    "qs_pg:photos_1k":59,
    "qs_pg:photos_9k":1,
    "qs_pg:photos_9r":4,
    "qs_pg:photos_all":292,
    "qs_pg:photos_sr":5,
    "qs_pg:pop_sr":0,
    "qs_pg:qs_pg_placetype":"locality",
    "qs_pg:qs_pg_placetype_gp":"Town",
    "qs_pg:woe_adm0":23424977,
    "woe:adm0_id":23424977,
    "woe:name_adm0":"United States",
    "woe:name_adm1":"Virginia",
    "woe:placetype":"Town",
    "wof:name":"Ellendale",
    "wof:placetype":"locality"
},
  "geometry": {"coordinates":[-81.56984,36.9165],"type":"Point"}
}