{
  "type": "Feature",
  "properties": {
    "gn:admin1_code":"IN",
    "gn:admin2_code":"109.0",
    "gn:admin3_code":"8344.0",
    "gn:asciiname":"Brookmoor",
    "gn:country_code":"US",
    "gn:dem":214,
    "gn:elevation":"211.0",
    "gn:feature_class":"P",
    "gn:feature_code":"PPL",
    "gn:name":"Brookmoor",
    "gn:population":0,
    "gn:timezone":"America/Indiana/Indianapolis",
    "iso:country":"US",
    "wof:name":"Brookmoor",
    "wof:placetype":"locality"
},
  "geometry": {"coordinates":[-86.37472,39.56755],"type":"Point"}
}