{
  "type": "Feature",
  "properties": {
    "gn:admin1_code":"OK",
    "gn:admin2_code":"21.0",
    "gn:asciiname":"White Oak",
    "gn:country_code":"US",
    "gn:dem":239,
    "gn:elevation":"234.0",
    "gn:feature_class":"P",
    "gn:feature_code":"PPL",
    "gn:name":"White Oak",
    "gn:population":0,
    "gn:timezone":"America/Chicago",
    "iso:country":"US",
    "wof:name":"White Oak",
    "wof:placetype":"locality"
},
  "geometry": {"coordinates":[-95.02968,35.72565],"type":"Point"}
}