{
  "type": "Feature",
  "properties": {
    "gn:admin1_code":"KS",
    "gn:admin2_code":"191",
    "gn:admin3_code":"26975.0",
    "gn:asciiname":"Mulvane Mobile Home Park",
    "gn:country_code":"US",
    "gn:dem":385,
    "gn:elevation":"379.0",
    "gn:feature_class":"P",
    "gn:feature_code":"PPL",
    "gn:name":"Mulvane Mobile Home Park",
    "gn:population":0,
    "gn:timezone":"America/Chicago",
    "iso:country":"US",
    "wof:name":"Mulvane Mobile Home Park",
    "wof:placetype":"campus"
},
  "geometry": {"coordinates":[-97.22358,37.46904],"type":"Point"}
}