{
  "type": "Feature",
  "properties": {
    "iso:country":"US",
    "name:eng_x_preferred":[
        "Brook Green"
    ],
    "name:gle_x_preferred":[
        "Brook Green"
    ],
    "wd:wordcount":705,
    "wof:name":"Brook Green",
    "wof:placetype":"neighbourhood",
    "wof:population":3099,
    "zs:area_m":870983.171301,
    "zs:blockids":[
        371470002013024,
        371470004002000,
        371470002013025,
        371470004003004,
        371470004002003,
        371470002022002,
        371470004002002,
        371470004003006,
        371470002013015,
        371470004003002,
        371470004003009,
        371470004003003,
        371470004003008,
        371470002013022,
        371470004003005,
        371470004003007,
        371470002013021,
        371470004003000,
        371470002022003,
        371470004003001
    ],
    "zs:housing10":342,
    "zs:label":"Brook Green",
    "zs:pop10":3099
},
  "geometry": {"coordinates":[-77.357782,35.599986],"type":"Point"}
}