{
  "type": "Feature",
  "properties": {
    "gn:admin1_code":"MO",
    "gn:admin2_code":"23.0",
    "gn:admin3_code":"3826.0",
    "gn:asciiname":"Lone Hill",
    "gn:country_code":"US",
    "gn:dem":139,
    "gn:elevation":"140.0",
    "gn:feature_class":"P",
    "gn:feature_code":"PPL",
    "gn:name":"Lone Hill",
    "gn:population":0,
    "gn:timezone":"America/Chicago",
    "iso:country":"US",
    "name:afr_x_preferred":[
        "Lone Hill"
    ],
    "wof:name":"Lone Hill",
    "wof:placetype":"locality"
},
  "geometry": {"coordinates":[-90.53734,36.70117],"type":"Point"}
}