{
  "type": "Feature",
  "properties": {
    "gn:admin1_code":"MT",
    "gn:admin2_code":"27.0",
    "gn:asciiname":"Ware",
    "gn:country_code":"US",
    "gn:dem":1093,
    "gn:elevation":"1097.0",
    "gn:feature_class":"P",
    "gn:feature_code":"PPL",
    "gn:name":"Ware",
    "gn:population":0,
    "gn:timezone":"America/Denver",
    "iso:country":"US",
    "name:ceb_x_preferred":[
        "Ware"
    ],
    "name:deu_x_preferred":[
        "Ware"
    ],
    "name:fra_x_preferred":[
        "Ware"
    ],
    "name:jpn_x_preferred":[
        "\u30a6\u30a7\u30a2"
    ],
    "name:nld_x_preferred":[
        "Ware"
    ],
    "name:pol_x_preferred":[
        "Ware"
    ],
    "name:por_x_preferred":[
        "Ware"
    ],
    "name:ron_x_preferred":[
        "Ware"
    ],
    "name:rus_x_preferred":[
        "\u0423\u044d\u0439\u0440"
    ],
    "name:sco_x_preferred":[
        "Ware"
    ],
    "name:swe_x_preferred":[
        "Ware"
    ],
    "name:ukr_x_preferred":[
        "\u0412\u0435\u0430\u0440"
    ],
    "name:vol_x_preferred":[
        "Ware"
    ],
    "wof:name":"Ware",
    "wof:placetype":"locality"
},
  "geometry": {"coordinates":[-109.66797,47.18442],"type":"Point"}
}