{
  "type": "Feature",
  "properties": {
    "gn:admin1_code":"TN",
    "gn:admin2_code":"125.0",
    "gn:asciiname":"Round Pond",
    "gn:country_code":"US",
    "gn:dem":185,
    "gn:elevation":"183.0",
    "gn:feature_class":"P",
    "gn:feature_code":"PPL",
    "gn:name":"Round Pond",
    "gn:population":0,
    "gn:timezone":"America/Chicago",
    "iso:country":"US",
    "name:ceb_x_preferred":[
        "Round Pond"
    ],
    "name:deu_x_preferred":[
        "Round Pond"
    ],
    "name:eng_x_preferred":[
        "Round Pond"
    ],
    "name:und_x_variant":[
        "Mount Zion"
    ],
    "wof:name":"Round Pond",
    "wof:placetype":"locality"
},
  "geometry": {"coordinates":[-87.37779,36.45672],"type":"Point"}
}