{
  "type": "Feature",
  "properties": {
    "gn:admin1_code":"NH",
    "gn:admin2_code":"9.0",
    "gn:admin3_code":"24340.0",
    "gn:asciiname":"Upper Shaker Village",
    "gn:country_code":"US",
    "gn:dem":247,
    "gn:elevation":"237.0",
    "gn:feature_class":"P",
    "gn:feature_code":"PPL",
    "gn:name":"Upper Shaker Village",
    "gn:population":0,
    "gn:timezone":"America/New_York",
    "iso:country":"US",
    "wof:name":"Upper Shaker Village",
    "wof:placetype":"locality"
},
  "geometry": {"coordinates":[-72.13814000000001,43.61174000000001],"type":"Point"}
}