{
  "type": "Feature",
  "properties": {
    "iso:country":"US",
    "name:eng_x_preferred":[
        "Wills Acres"
    ],
    "wof:name":"Wills Acres",
    "wof:placetype":"neighbourhood",
    "wof:population":4214,
    "zs:area_m":1622251.777088,
    "zs:blockids":[
        60670067024002,
        60670067025000,
        60670068001002,
        60670068001003,
        60670067024008,
        60670067025001,
        60670067025005,
        60670068001019,
        60670068001013,
        60670068001018,
        60670067021018,
        60670067025009,
        60670067025006,
        60670067024007,
        60670068001009,
        60670068001005,
        60670067025007,
        60670068001020,
        60670068001004,
        60670068001000,
        60670070011044,
        60670067024006,
        60670068001001,
        60670067025003,
        60670068001007,
        60670067024003,
        60670067025002,
        60670067024004,
        60670070011033,
        60670067025004,
        60670068001021,
        60670068001016
    ],
    "zs:housing10":1127,
    "zs:label":"Wills Acres",
    "zs:pop10":4214
},
  "geometry": {"coordinates":[-121.46315,38.622529],"type":"Point"}
}