{
  "type": "Feature",
  "properties": {
    "gn:admin1_code":"WA",
    "gn:admin2_code":"73.0",
    "gn:asciiname":"Cedar Crossing",
    "gn:country_code":"US",
    "gn:dem":839,
    "gn:elevation":"812.0",
    "gn:feature_class":"P",
    "gn:feature_code":"PPL",
    "gn:name":"Cedar Crossing",
    "gn:population":0,
    "gn:timezone":"America/Los_Angeles",
    "iso:country":"US",
    "wof:name":"Cedar Crossing",
    "wof:placetype":"locality"
},
  "geometry": {"coordinates":[-120.81816999999999,48.7468],"type":"Point"}
}