{
  "type": "Feature",
  "properties": {
    "gn:admin1_code":"SC",
    "gn:admin2_code":"35.0",
    "gn:asciiname":"Iron Gate",
    "gn:country_code":"US",
    "gn:dem":16,
    "gn:elevation":"16.0",
    "gn:feature_class":"P",
    "gn:feature_code":"PPL",
    "gn:name":"Iron Gate",
    "gn:population":0,
    "gn:timezone":"America/New_York",
    "iso:country":"US",
    "name:ceb_x_preferred":[
        "Iron Gate"
    ],
    "name:rus_x_preferred":[
        "\u0416\u0435\u043b\u0435\u0437\u043d\u044b\u0435 \u0432\u043e\u0440\u043e\u0442\u0430"
    ],
    "name:ukr_x_preferred":[
        "\u0417\u0430\u043b\u0456\u0437\u043d\u0456 \u0412\u043e\u0440\u043e\u0442\u0430"
    ],
    "wof:name":"Iron Gate",
    "wof:placetype":"locality"
},
  "geometry": {"coordinates":[-80.17537,32.97712],"type":"Point"}
}