{
  "type": "Feature",
  "properties": {
    "gn:admin1_code":"AR",
    "gn:admin2_code":"81.0",
    "gn:admin3_code":"91356.0",
    "gn:asciiname":"Red Bluff",
    "gn:country_code":"US",
    "gn:dem":95,
    "gn:elevation":"92.0",
    "gn:feature_class":"P",
    "gn:feature_code":"PPL",
    "gn:name":"Red Bluff",
    "gn:population":0,
    "gn:timezone":"America/Chicago",
    "iso:country":"US",
    "name:ceb_x_preferred":[
        "Red Bluff"
    ],
    "name:deu_x_preferred":[
        "Red Bluff"
    ],
    "name:eng_x_preferred":[
        "Red Bluff"
    ],
    "name:ita_x_preferred":[
        "Red Bluff"
    ],
    "name:swe_x_preferred":[
        "Red Bluff"
    ],
    "name:und_x_variant":[
        "Redbluff",
        "Red Bluffs"
    ],
    "wof:name":"Red Bluff",
    "wof:placetype":"locality"
},
  "geometry": {"coordinates":[-93.95824,33.64595],"type":"Point"}
}