{
  "type": "Feature",
  "properties": {
    "gn:admin1_code":"OH",
    "gn:admin2_code":"173.0",
    "gn:admin3_code":"63002.0",
    "gn:asciiname":"Country Manor Estates",
    "gn:country_code":"US",
    "gn:dem":205,
    "gn:elevation":"203.0",
    "gn:feature_class":"P",
    "gn:feature_code":"PPL",
    "gn:name":"Country Manor Estates",
    "gn:population":0,
    "gn:timezone":"America/New_York",
    "iso:country":"US",
    "wof:name":"Country Manor Estates",
    "wof:placetype":"locality"
},
  "geometry": {"coordinates":[-83.67631999999998,41.42894],"type":"Point"}
}