{
  "type": "Feature",
  "properties": {
    "gn:admin1_code":"SD",
    "gn:admin2_code":"93.0",
    "gn:admin3_code":"4400.0",
    "gn:asciiname":"Fairpoint",
    "gn:country_code":"US",
    "gn:dem":892,
    "gn:elevation":"894.0",
    "gn:feature_class":"P",
    "gn:feature_code":"PPL",
    "gn:name":"Fairpoint",
    "gn:population":0,
    "gn:timezone":"America/Denver",
    "iso:country":"US",
    "wof:name":"Fairpoint",
    "wof:placetype":"locality"
},
  "geometry": {"coordinates":[-102.79656,44.74832],"type":"Point"}
}