{
  "type": "Feature",
  "properties": {
    "gn:admin1_code":"VA",
    "gn:admin2_code":"165",
    "gn:asciiname":"Swift Run",
    "gn:country_code":"US",
    "gn:dem":415,
    "gn:elevation":"415.0",
    "gn:feature_class":"P",
    "gn:feature_code":"PPL",
    "gn:name":"Swift Run",
    "gn:population":0,
    "gn:timezone":"America/New_York",
    "iso:country":"US",
    "name:eng_x_preferred":[
        "Swift Run"
    ],
    "name:und_x_variant":[
        "Swiftrun"
    ],
    "wof:name":"Swift Run",
    "wof:placetype":"locality"
},
  "geometry": {"coordinates":[-78.58085,38.36846],"type":"Point"}
}