{
  "type": "Feature",
  "properties": {
    "gn:admin1_code":"MT",
    "gn:admin2_code":"97.0",
    "gn:asciiname":"Sourdough",
    "gn:country_code":"US",
    "gn:dem":1421,
    "gn:elevation":"1421.0",
    "gn:feature_class":"P",
    "gn:feature_code":"PPL",
    "gn:name":"Sourdough",
    "gn:population":0,
    "gn:timezone":"America/Denver",
    "iso:country":"US",
    "wof:name":"Sourdough",
    "wof:placetype":"locality"
},
  "geometry": {"coordinates":[-109.81435,45.90189],"type":"Point"}
}