{
  "type": "Feature",
  "properties": {
    "gn:admin1_code":"PA",
    "gn:admin2_code":"129.0",
    "gn:admin3_code":"51888.0",
    "gn:asciiname":"Bridgeport",
    "gn:country_code":"US",
    "gn:dem":321,
    "gn:elevation":"322.0",
    "gn:feature_class":"P",
    "gn:feature_code":"PPL",
    "gn:name":"Bridgeport",
    "gn:population":0,
    "gn:timezone":"America/New_York",
    "iso:country":"US",
    "wof:name":"Bridgeport",
    "wof:placetype":"locality"
},
  "geometry": {"coordinates":[-79.53254,40.12924],"type":"Point"}
}