{
  "type": "Feature",
  "properties": {
    "gn:country":"US",
    "gn:fcode":"PPL",
    "gn:population":0,
    "iso:country":"US",
    "name:ceb_x_preferred":[
        "Busch"
    ],
    "name:deu_x_preferred":[
        "Busch"
    ],
    "name:fra_x_preferred":[
        "Busch"
    ],
    "name:frr_x_preferred":[
        "Bosk"
    ],
    "name:ita_x_preferred":[
        "Busch"
    ],
    "name:nld_x_preferred":[
        "Busch"
    ],
    "name:spa_x_preferred":[
        "Busch"
    ],
    "name:swe_x_preferred":[
        "Busch"
    ],
    "qs_pg:aaroncc":"US",
    "qs_pg:gn_country":"US",
    "qs_pg:gn_fcode":"PPL",
    "qs_pg:gn_pop":0,
    "qs_pg:name":"Busch",
    "qs_pg:name_adm0":"United States",
    "qs_pg:name_adm1":"Montana",
    "qs_pg:photos":24,
    "qs_pg:photos_1k":5,
    "qs_pg:photos_9k":1,
    "qs_pg:photos_9r":1,
    "qs_pg:photos_all":24,
    "qs_pg:photos_sr":1,
    "qs_pg:pop_sr":0,
    "qs_pg:qs_pg_placetype":"locality",
    "qs_pg:qs_pg_placetype_gp":"Town",
    "qs_pg:woe_adm0":23424977,
    "woe:adm0_id":23424977,
    "woe:name_adm0":"United States",
    "woe:name_adm1":"Montana",
    "woe:placetype":"Town",
    "wof:name":"Busch",
    "wof:placetype":"locality"
},
  "geometry": {"coordinates":[-111.083,45.80354],"type":"Point"}
}