{
  "type": "Feature",
  "properties": {
    "gn:admin1_code":"TN",
    "gn:admin2_code":"3",
    "gn:asciiname":"Himesville",
    "gn:country_code":"US",
    "gn:dem":252,
    "gn:elevation":"249.0",
    "gn:feature_class":"P",
    "gn:feature_code":"PPL",
    "gn:name":"Himesville",
    "gn:population":0,
    "gn:timezone":"America/Chicago",
    "iso:country":"US",
    "wof:name":"Himesville",
    "wof:placetype":"locality"
},
  "geometry": {"coordinates":[-86.43444000000002,35.43119],"type":"Point"}
}