{
  "type": "Feature",
  "properties": {
    "iso:country":"US",
    "name:cat_x_preferred":[
        "Green Valley"
    ],
    "name:ceb_x_preferred":[
        "Green Valley"
    ],
    "name:deu_x_preferred":[
        "Green Valley"
    ],
    "name:eng_x_preferred":[
        "Green Valley"
    ],
    "name:ita_x_preferred":[
        "Green Valley"
    ],
    "name:nld_x_preferred":[
        "Green Valley"
    ],
    "name:pol_x_preferred":[
        "Green Valley"
    ],
    "name:por_x_preferred":[
        "Green Valley"
    ],
    "name:rus_x_preferred":[
        "\u0413\u0440\u0438\u043d-\u0412\u0430\u043b\u043b\u0438"
    ],
    "name:srp_x_preferred":[
        "\u0413\u0440\u0438\u043d \u0412\u0430\u043b\u0438"
    ],
    "name:swe_x_preferred":[
        "Green Valley"
    ],
    "name:ukr_x_preferred":[
        "\u0413\u0440\u0456\u043d-\u0412\u0435\u043b\u043b\u0456"
    ],
    "name:vol_x_preferred":[
        "Green Valley"
    ],
    "wof:name":"Green Valley",
    "wof:placetype":"neighbourhood",
    "wof:population":497,
    "zs:area_m":348760.450917,
    "zs:blockids":[
        371790205021014,
        371790205021002,
        371790205021013
    ],
    "zs:housing10":155,
    "zs:label":"Green Valley",
    "zs:pop10":497
},
  "geometry": {"coordinates":[-80.545586,34.971909],"type":"Point"}
}