{
  "type": "Feature",
  "properties": {
    "gn:admin1_code":"NC",
    "gn:admin2_code":"91.0",
    "gn:admin3_code":"91968.0",
    "gn:asciiname":"Mill Neck",
    "gn:country_code":"US",
    "gn:dem":17,
    "gn:elevation":"12.0",
    "gn:feature_class":"P",
    "gn:feature_code":"PPL",
    "gn:name":"Mill Neck",
    "gn:population":0,
    "gn:timezone":"America/New_York",
    "iso:country":"US",
    "wof:name":"Mill Neck",
    "wof:placetype":"locality"
},
  "geometry": {"coordinates":[-76.98663000000001,36.51349],"type":"Point"}
}