{
  "type": "Feature",
  "properties": {
    "gn:elevation":21,
    "iso:country":"US",
    "name:eng_x_preferred":[
        "Annisquam"
    ],
    "name:nld_x_preferred":[
        "Annisquam"
    ],
    "name:und_x_variant":[
        "Annis-squam Village"
    ],
    "qs:gn_adm0_cc":"US",
    "qs:gn_fcode":"PPL",
    "qs:gn_local":4937829,
    "qs:gn_nam_loc":"gloucester",
    "qs:gn_namadm1":"MA",
    "qs:gn_name":"Annisquam",
    "qs:local_max":4060,
    "qs:local_sum":13041,
    "qs:localhoods":18,
    "qs:name":"Annisquam",
    "qs:name_adm0":"United States",
    "qs:name_adm1":"Massachusetts",
    "qs:name_adm2":"Essex",
    "qs:name_local":"Gloucester",
    "qs:photo_max":145,
    "qs:photo_sum":730,
    "qs:placetype":"Suburb",
    "qs:quad_count":28,
    "qs:woe_adm0":23424977,
    "qs:woe_adm1":2347580,
    "qs:woe_adm2":12588704,
    "qs:woe_lau":0,
    "qs:woe_local":2411521,
    "qs:woe_ver":"7.10.0",
    "wd:wordcount":266,
    "wof:lang":[
        "eng"
    ],
    "wof:name":"Annisquam",
    "wof:placetype":"neighbourhood",
    "wof:population":734,
    "zs:blockids":[
        250092211002016,
        250092211002013,
        250092211002021,
        250092211002036,
        250092211002049,
        250092211002008,
        250092211002027,
        250092211002024,
        250092211002055,
        250092211002020,
        250092211002037,
        250092211002048,
        250092211002026,
        250092211001047,
        250092211002050,
        250092211002034,
        250092211002005,
        250092211002007,
        250092211002054,
        250092211002022,
        250092211002051,
        250092211002035,
        250092211002017,
        250092211003004,
        250092211002018,
        250092211002032,
        250092211002002,
        250092211002023,
        250092211002003,
        250092211002010,
        250092211002014,
        250092211002033,
        250092211002052,
        250092211002011,
        250092211002009,
        250092211002047,
        250092211002015,
        250092211002025,
        250092211002004,
        250092211002053,
        250092211002012,
        250092211001046,
        250092211002031
    ],
    "zs:housing10":470,
    "zs:pop10":734
},
  "geometry": {"coordinates":[-70.684781,42.656648],"type":"Point"}
}