{
  "type": "Feature",
  "properties": {
    "gn:elevation":1,
    "iso:country":"US",
    "name:eng_x_preferred":[
        "Waterway Arms"
    ],
    "qs:gn_adm0_cc":"US",
    "qs:gn_fcode":"PPLX",
    "qs:gn_local":4588165,
    "qs:gn_nam_loc":"Mount Pleasant, Charleston, South Carolina, US",
    "qs:gn_namadm1":"SC",
    "qs:gn_name":"Waterway Arms",
    "qs:local_max":6062,
    "qs:local_sum":9531,
    "qs:localhoods":13,
    "qs:name":"Waterway Arms",
    "qs:name_adm0":"United States",
    "qs:name_adm1":"South Carolina",
    "qs:name_adm2":"Charleston",
    "qs:name_local":"Mount Pleasant",
    "qs:photo_max":222,
    "qs:photo_sum":299,
    "qs:placetype":"Suburb",
    "qs:quad_count":17,
    "qs:woe_adm0":23424977,
    "qs:woe_adm1":2347599,
    "qs:woe_adm2":12589809,
    "qs:woe_lau":0,
    "qs:woe_local":2455374,
    "qs:woe_ver":"7.10.0",
    "wof:name":"Waterway Arms",
    "wof:placetype":"neighbourhood",
    "wof:population":1427,
    "zs:blockids":[
        450190047013001,
        450190047013006,
        450190047015018,
        450190047013015,
        450190047015022,
        450190047015028,
        450190047015014,
        450190046112051,
        450190046112050,
        450190047013002,
        450190047015029,
        450190046112070,
        450190047012027,
        450190047012026,
        450190046114034,
        450190046112092,
        450190047015012,
        450190047015013,
        450190046112083,
        450190046114035,
        450190047013016,
        450190047013005,
        450190047015009,
        450190046114033,
        450190046114028,
        450190047015010,
        450190048002000,
        450190047013009,
        450190047013013,
        450190046114027,
        450190047015027,
        450190047015019,
        450190047015023,
        450190047015025,
        450190047015016,
        450190047013008,
        450190047013003,
        450190047013019,
        450190047015026,
        450190046114032,
        450190047015030,
        450190047015015,
        450190047015017,
        450190047015020,
        450190047011018,
        450190047013014,
        450190047013004,
        450190047013020,
        450190047015021,
        450190046112090,
        450190047015024,
        450190047015031,
        450190047015032,
        450190046112071
    ],
    "zs:housing10":685,
    "zs:pop10":1427
},
  "geometry": {"coordinates":[-79.86322199999999,32.773058],"type":"Point"}
}