{
  "type": "Feature",
  "properties": {
    "gn:elevation":103,
    "iso:country":"US",
    "name:eng_x_preferred":[
        "Salem Center"
    ],
    "name:eng_x_variant":[
        "Salem Ctr"
    ],
    "name:und_x_variant":[
        "Salem Centre"
    ],
    "qs:gn_adm0_cc":"US",
    "qs:gn_fcode":"PPL",
    "qs:gn_local":5129201,
    "qs:gn_nam_loc":"North Salem, Westchester, New York, US",
    "qs:gn_namadm1":"NY",
    "qs:gn_name":"Salem Center",
    "qs:local_max":143,
    "qs:local_sum":235,
    "qs:localhoods":2,
    "qs:name":"Salem Center",
    "qs:name_adm0":"United States",
    "qs:name_adm1":"New York",
    "qs:name_adm2":"Westchester",
    "qs:name_local":"North Salem",
    "qs:photo_max":26,
    "qs:photo_sum":92,
    "qs:placetype":"Suburb",
    "qs:quad_count":21,
    "qs:woe_adm0":23424977,
    "qs:woe_adm1":2347591,
    "qs:woe_adm2":12589371,
    "qs:woe_lau":0,
    "qs:woe_local":2461583,
    "qs:woe_ver":"7.10.0",
    "wd:wordcount":35,
    "wof:lang":[
        "eng"
    ],
    "wof:name":"Salem Center",
    "wof:placetype":"neighbourhood",
    "wof:population":1965,
    "zs:blockids":[
        361190150002016,
        361190150004006,
        361190150001000,
        361190150003005,
        361190150001019,
        361190150004005,
        361190150001018,
        361190150001014,
        361190150003028,
        361190150003064,
        361190150004014,
        361190125023002,
        361190150003008,
        361190150003006,
        361190150001016,
        361190150001001,
        361190150004029,
        361190150004013,
        361190125023001,
        361190150003021,
        361190150003065,
        361190150004010,
        361190150004020,
        361190150004009,
        361190150003030,
        361190150004025,
        361190150004007,
        361190150004012,
        361190150004019,
        361190150003001,
        361190150003000,
        361190125021005,
        361190150004011,
        361190150003003,
        361190150001013,
        361190150003026,
        361190125011000,
        361190125011001,
        361190150004008,
        361190150004026,
        361190150003031,
        361190150003027,
        361190150004036,
        361190150003029,
        361190150001017,
        361190150004015,
        361190150004021,
        361190150002017,
        361190150003002,
        361190150001015,
        361190150003025,
        361190150003036,
        361190150001010,
        361190150004024,
        361190150004027,
        361190125023000,
        361190150003004
    ],
    "zs:housing10":831,
    "zs:pop10":1965
},
  "geometry": {"coordinates":[-73.582306,41.334888],"type":"Point"}
}