{
  "type": "Feature",
  "properties": {
    "gn:admin1_code":"VA",
    "gn:admin2_code":"680",
    "gn:asciiname":"Lavino Village",
    "gn:country_code":"US",
    "gn:dem":210,
    "gn:elevation":"205.0",
    "gn:feature_class":"P",
    "gn:feature_code":"PPL",
    "gn:name":"Lavino Village",
    "gn:population":0,
    "gn:timezone":"America/New_York",
    "iso:country":"US",
    "wof:name":"Lavino Village",
    "wof:placetype":"locality"
},
  "geometry": {"coordinates":[-79.18308,37.45153],"type":"Point"}
}