{
  "type": "Feature",
  "properties": {
    "iso:country":"US",
    "name:eng_x_preferred":[
        "Glendale Acres"
    ],
    "wof:name":"Glendale Acres",
    "wof:placetype":"neighbourhood",
    "wof:population":2770,
    "zs:area_m":2564194.675046,
    "zs:blockids":[
        370510006003023,
        370510006004006,
        370510017002033,
        370510017002008,
        370510018001053,
        370510017002002,
        370510017003003,
        370510006003021,
        370510017002003,
        370510006002008,
        370510006003019,
        370510006003006,
        370510006003002,
        370510006004008,
        370510017003007,
        370510017003004,
        370510006002006,
        370510006002005,
        370510006003025,
        370510017002018,
        370510017002022,
        370510006003022,
        370510006003011,
        370510006004009,
        370510017002014,
        370510017002016,
        370510018001058,
        370510006002000,
        370510017002001,
        370510017002010,
        370510017002035,
        370510006003018,
        370510006003012,
        370510006003008,
        370510006003013,
        370510006002004,
        370510017002011,
        370510006004007,
        370510006003010,
        370510006003024,
        370510006003016,
        370510017002021,
        370510017002023,
        370510006002001,
        370510006002003,
        370510006002007,
        370510017002000,
        370510017002007,
        370510006003007,
        370510017003002,
        370510017002019,
        370510017002034,
        370510017002009,
        370510006001016,
        370510006003020,
        370510017002004
    ],
    "zs:housing10":1413,
    "zs:label":"Glendale Acres",
    "zs:pop10":2770
},
  "geometry": {"coordinates":[-78.924154,35.030962],"type":"Point"}
}