{
  "type": "Feature",
  "properties": {
    "iso:country":"US",
    "name:eng_x_preferred":[
        "Fountain View"
    ],
    "wof:name":"Fountain View",
    "wof:placetype":"neighbourhood",
    "wof:population":16,
    "zs:area_m":323914.778465,
    "zs:blockids":[
        191530102093001
    ],
    "zs:housing10":8,
    "zs:label":"Fountain View",
    "zs:pop10":16
},
  "geometry": {"coordinates":[-93.57477299999999,41.743037],"type":"Point"}
}