{
  "type": "Feature",
  "properties": {
    "gn:admin1_code":"VA",
    "gn:admin2_code":"195",
    "gn:asciiname":"Lipps",
    "gn:country_code":"US",
    "gn:dem":713,
    "gn:elevation":"711.0",
    "gn:feature_class":"P",
    "gn:feature_code":"PPL",
    "gn:name":"Lipps",
    "gn:population":0,
    "gn:timezone":"America/New_York",
    "iso:country":"US",
    "wof:name":"Lipps",
    "wof:placetype":"locality"
},
  "geometry": {"coordinates":[-82.65127,37.00427],"type":"Point"}
}