{
  "type": "Feature",
  "properties": {
    "gn:admin1_code":"WV",
    "gn:admin2_code":"51",
    "gn:asciiname":"Andersonville",
    "gn:country_code":"US",
    "gn:dem":313,
    "gn:elevation":"304.0",
    "gn:feature_class":"P",
    "gn:feature_code":"PPL",
    "gn:name":"Andersonville",
    "gn:population":0,
    "gn:timezone":"America/New_York",
    "iso:country":"US",
    "name:ceb_x_preferred":[
        "Andersonville"
    ],
    "name:ces_x_preferred":[
        "Andersonville"
    ],
    "name:deu_x_preferred":[
        "Andersonville"
    ],
    "name:eng_x_preferred":[
        "Andersonville"
    ],
    "name:fra_x_preferred":[
        "Andersonville"
    ],
    "name:ita_x_preferred":[
        "Andersonville"
    ],
    "name:nld_x_preferred":[
        "Andersonville"
    ],
    "name:pol_x_preferred":[
        "Andersonville"
    ],
    "name:srp_x_preferred":[
        "\u0410\u043d\u0434\u0435\u0440\u0441\u043e\u043d\u0432\u0438\u043b"
    ],
    "name:swe_x_preferred":[
        "Andersonville"
    ],
    "name:ukr_x_preferred":[
        "\u0410\u043d\u0434\u0435\u0440\u0441\u043e\u043d\u0432\u0456\u043b\u043b"
    ],
    "name:und_x_variant":[
        "Balls"
    ],
    "wof:name":"Andersonville",
    "wof:placetype":"locality"
},
  "geometry": {"coordinates":[-80.52174000000002,39.78008],"type":"Point"}
}