{
  "type": "Feature",
  "properties": {
    "gn:admin1_code":"TX",
    "gn:admin2_code":"409",
    "gn:asciiname":"Mooney Lane Colonia",
    "gn:country_code":"US",
    "gn:dem":10,
    "gn:elevation":"5.0",
    "gn:feature_class":"P",
    "gn:feature_code":"PPL",
    "gn:name":"Mooney Lane Colonia",
    "gn:population":0,
    "gn:timezone":"America/Chicago",
    "iso:country":"US",
    "name:eng_x_preferred":[
        "Mooney Lane Colonia"
    ],
    "name:und_x_variant":[
        "Ingleside Colonia"
    ],
    "wof:name":"Mooney Lane Colonia",
    "wof:placetype":"locality"
},
  "geometry": {"coordinates":[-97.18527,27.89141],"type":"Point"}
}