{
  "type": "Feature",
  "properties": {
    "gn:admin1_code":"AR",
    "gn:admin2_code":"115.0",
    "gn:admin3_code":"91875.0",
    "gn:asciiname":"Lost Corner",
    "gn:country_code":"US",
    "gn:dem":515,
    "gn:elevation":"514.0",
    "gn:feature_class":"P",
    "gn:feature_code":"PPL",
    "gn:name":"Lost Corner",
    "gn:population":0,
    "gn:timezone":"America/Chicago",
    "iso:country":"US",
    "name:fas_x_preferred":[
        "\u0644\u0627\u0633\u062a \u06a9\u0648\u0631\u0646\u0631"
    ],
    "name:zho_x_preferred":[
        "\u6d1b\u65af\u7279\u79d1\u7d0d"
    ],
    "wof:name":"Lost Corner",
    "wof:placetype":"locality"
},
  "geometry": {"coordinates":[-92.83405999999999,35.57175],"type":"Point"}
}