{
  "type": "Feature",
  "properties": {
    "iso:country":"US",
    "name:eng_x_preferred":[
        "Vista Del Prado"
    ],
    "wof:name":"Vista Del Prado",
    "wof:placetype":"neighbourhood",
    "wof:population":892,
    "zs:area_m":1230363.898239,
    "zs:blockids":[
        350490011062012,
        350490103141028,
        350490103141001,
        350490011062005,
        350490011062011,
        350490103141000,
        350490011062022,
        350490011062007,
        350490011062014,
        350490011062025,
        350490011062017,
        350490011062015,
        350490011062024,
        350490011062020,
        350490103141004,
        350490011062016,
        350490011062021,
        350490012022017,
        350490011062006,
        350490011062004,
        350490011062018,
        350490103141010,
        350490011062009,
        350490011062023,
        350490011062013,
        350490103141005,
        350490011062019,
        350490103141002,
        350490103141003,
        350490011062010
    ],
    "zs:housing10":604,
    "zs:label":"Vista Del Prado",
    "zs:pop10":892
},
  "geometry": {"coordinates":[-106.005072,35.639569],"type":"Point"}
}