{
  "type": "Feature",
  "properties": {
    "gn:admin1_code":"OH",
    "gn:admin2_code":"171.0",
    "gn:admin3_code":"69638.0",
    "gn:asciiname":"Valley Springs Addition",
    "gn:country_code":"US",
    "gn:dem":266,
    "gn:elevation":"260.0",
    "gn:feature_class":"P",
    "gn:feature_code":"PPL",
    "gn:name":"Valley Springs Addition",
    "gn:population":0,
    "gn:timezone":"America/New_York",
    "iso:country":"US",
    "wof:name":"Valley Springs Addition",
    "wof:placetype":"locality"
},
  "geometry": {"coordinates":[-84.74773,41.49033],"type":"Point"}
}