{
  "type": "Feature",
  "properties": {
    "gn:country":"US",
    "gn:fcode":"PPLX",
    "gn:population":0,
    "iso:country":"US",
    "name:ceb_x_preferred":[
        "Indian Hills"
    ],
    "name:deu_x_preferred":[
        "Indian Hills"
    ],
    "name:eng_x_preferred":[
        "Indian Hills"
    ],
    "name:ita_x_preferred":[
        "Indian Hills"
    ],
    "name:nld_x_preferred":[
        "Indian Hills"
    ],
    "name:pol_x_preferred":[
        "Indian Hills"
    ],
    "name:por_x_preferred":[
        "Indian Hills"
    ],
    "name:spa_x_preferred":[
        "Indian Hills"
    ],
    "name:srp_x_preferred":[
        "\u0418\u043d\u0434\u0438\u0458\u0430\u043d \u0425\u0438\u043b\u0441"
    ],
    "name:vol_x_preferred":[
        "Indian Hills"
    ],
    "qs_pg:aaroncc":"US",
    "qs_pg:gn_country":"US",
    "qs_pg:gn_fcode":"PPLX",
    "qs_pg:gn_pop":0,
    "qs_pg:name":"Indian Hills",
    "qs_pg:name_adm0":"United States",
    "qs_pg:name_adm1":"Alabama",
    "qs_pg:photos":22,
    "qs_pg:photos_1k":4,
    "qs_pg:photos_9k":1,
    "qs_pg:photos_9r":1,
    "qs_pg:photos_all":22,
    "qs_pg:photos_sr":1,
    "qs_pg:pop_sr":0,
    "qs_pg:qs_pg_placetype":"neighbourhood",
    "qs_pg:qs_pg_placetype_gp":"Suburb",
    "qs_pg:woe_adm0":23424977,
    "wof:name":"Indian Hills",
    "wof:placetype":"neighbourhood",
    "wof:population":738,
    "zs:area_m":11464869.180456,
    "zs:blockids":[
        10810411004015,
        10810417003009,
        10810417003039,
        10810417003086,
        10810417003008,
        10810417003036,
        10810405002013,
        10810405002012,
        10810411004020,
        10810405002001,
        10810417003041,
        10810411004031,
        10810417003010,
        10810405002000,
        10810417003037,
        10810411004030,
        10810411004016
    ],
    "zs:housing10":302,
    "zs:label":"Indian Hills",
    "zs:pop10":738
},
  "geometry": {"coordinates":[-85.402075,32.595351],"type":"Point"}
}