{
  "type": "Feature",
  "properties": {
    "gn:admin1_code":"TX",
    "gn:admin2_code":"091",
    "gn:asciiname":"Fischer",
    "gn:country_code":"US",
    "gn:dem":357,
    "gn:elevation":"350.0",
    "gn:feature_class":"P",
    "gn:feature_code":"PPL",
    "gn:name":"Fischer",
    "gn:population":0,
    "gn:timezone":"America/Chicago",
    "iso:country":"US",
    "name:eng_x_preferred":[
        "Fischer"
    ],
    "name:fas_x_preferred":[
        "\u0641\u06cc\u0634\u0631"
    ],
    "name:und_x_variant":[
        "Fischer Store",
        "Fischer's Store"
    ],
    "wof:name":"Fischer",
    "wof:placetype":"locality"
},
  "geometry": {"coordinates":[-98.26585,29.97688],"type":"Point"}
}