{
  "type": "Feature",
  "properties": {
    "iso:country":"US",
    "name:eng_x_preferred":[
        "Rancho Sante Fe"
    ],
    "wof:name":"Rancho Sante Fe",
    "wof:placetype":"neighbourhood",
    "wof:population":1138,
    "zs:area_m":569840.578655,
    "zs:blockids":[
        320030025051000,
        320030017112000,
        320030025042000,
        320030017121008,
        320030025052008,
        320030025052005,
        320030025052006,
        320030025052007,
        320030017112004,
        320030017112001,
        320030025051003,
        320030025052004,
        320030017112002,
        320030025042001,
        320030017112005,
        320030017112003
    ],
    "zs:housing10":708,
    "zs:label":"Rancho Sante Fe",
    "zs:pop10":1138
},
  "geometry": {"coordinates":[-115.119845,36.109144],"type":"Point"}
}