{
  "type": "Feature",
  "properties": {
    "gn:admin1_code":"MI",
    "gn:admin2_code":"57.0",
    "gn:admin3_code":"36160.0",
    "gn:asciiname":"Sickles",
    "gn:country_code":"US",
    "gn:dem":212,
    "gn:elevation":"211.0",
    "gn:feature_class":"P",
    "gn:feature_code":"PPL",
    "gn:name":"Sickles",
    "gn:population":0,
    "gn:timezone":"America/Detroit",
    "iso:country":"US",
    "name:deu_x_preferred":[
        "Sickles"
    ],
    "name:fra_x_preferred":[
        "Sickles"
    ],
    "wof:name":"Sickles",
    "wof:placetype":"locality"
},
  "geometry": {"coordinates":[-84.44888,43.27781],"type":"Point"}
}