{
  "type": "Feature",
  "properties": {
    "iso:country":"US",
    "name:eng_x_preferred":[
        "Brookhill"
    ],
    "wof:name":"Brookhill",
    "wof:placetype":"neighbourhood",
    "wof:population":102,
    "zs:area_m":334538.525416,
    "zs:blockids":[
        261251604002001,
        261251604002002
    ],
    "zs:housing10":65,
    "zs:label":"Brookhill",
    "zs:pop10":102
},
  "geometry": {"coordinates":[-83.31656099999999,42.502473],"type":"Point"}
}