{
  "type": "Feature",
  "properties": {
    "gn:admin1_code":"MO",
    "gn:admin2_code":"73.0",
    "gn:admin3_code":"9100.0",
    "gn:asciiname":"Bem",
    "gn:country_code":"US",
    "gn:dem":253,
    "gn:elevation":"253.0",
    "gn:feature_class":"P",
    "gn:feature_code":"PPL",
    "gn:name":"Bem",
    "gn:population":0,
    "gn:timezone":"America/Chicago",
    "iso:country":"US",
    "name:eng_x_preferred":[
        "Bem"
    ],
    "name:und_x_variant":[
        "Beaver"
    ],
    "wof:name":"Bem",
    "wof:placetype":"locality"
},
  "geometry": {"coordinates":[-91.46988,38.26588],"type":"Point"}
}