{
  "type": "Feature",
  "properties": {
    "gn:admin1_code":"OH",
    "gn:admin2_code":"37.0",
    "gn:admin3_code":"43092.0",
    "gn:asciiname":"Clark",
    "gn:country_code":"US",
    "gn:dem":328,
    "gn:elevation":"333.0",
    "gn:feature_class":"P",
    "gn:feature_code":"PPL",
    "gn:name":"Clark",
    "gn:population":0,
    "gn:timezone":"America/New_York",
    "iso:country":"US",
    "name:ces_x_preferred":[
        "Clark"
    ],
    "name:deu_x_preferred":[
        "Clark"
    ],
    "name:eng_x_preferred":[
        "Clark"
    ],
    "name:fas_x_preferred":[
        "\u06a9\u0644\u0627\u0631\u06a9"
    ],
    "name:lit_x_preferred":[
        "Clark"
    ],
    "name:rus_x_preferred":[
        "\u041a\u043b\u0430\u0440\u043a"
    ],
    "name:slv_x_preferred":[
        "Clark"
    ],
    "name:und_x_variant":[
        "Clark Station",
        "Noggle"
    ],
    "wof:name":"Clark",
    "wof:placetype":"locality"
},
  "geometry": {"coordinates":[-84.72412,40.0131],"type":"Point"}
}