{
  "type": "Feature",
  "properties": {
    "gn:admin1_code":"IA",
    "gn:admin2_code":"185.0",
    "gn:admin3_code":"90747.0",
    "gn:asciiname":"Clinton Center",
    "gn:country_code":"US",
    "gn:dem":333,
    "gn:elevation":"326.0",
    "gn:feature_class":"P",
    "gn:feature_code":"PPL",
    "gn:name":"Clinton Center",
    "gn:population":0,
    "gn:timezone":"America/Chicago",
    "iso:country":"US",
    "wof:name":"Clinton Center",
    "wof:placetype":"locality"
},
  "geometry": {"coordinates":[-93.38466,40.60917],"type":"Point"}
}