{
  "type": "Feature",
  "properties": {
    "gn:admin1_code":"VA",
    "gn:admin2_code":"77",
    "gn:asciiname":"Peach Bottom",
    "gn:country_code":"US",
    "gn:dem":721,
    "gn:elevation":"718.0",
    "gn:feature_class":"P",
    "gn:feature_code":"PPL",
    "gn:name":"Peach Bottom",
    "gn:population":0,
    "gn:timezone":"America/New_York",
    "iso:country":"US",
    "wof:name":"Peach Bottom",
    "wof:placetype":"locality"
},
  "geometry": {"coordinates":[-81.06675,36.58902],"type":"Point"}
}