{
  "type": "Feature",
  "properties": {
    "gn:admin1_code":"OH",
    "gn:admin2_code":"27",
    "gn:admin3_code":"66642.0",
    "gn:asciiname":"Rolfe Mobile Home Park",
    "gn:country_code":"US",
    "gn:dem":317,
    "gn:elevation":"317.0",
    "gn:feature_class":"P",
    "gn:feature_code":"PPL",
    "gn:name":"Rolfe Mobile Home Park",
    "gn:population":0,
    "gn:timezone":"America/New_York",
    "iso:country":"US",
    "wof:name":"Rolfe Mobile Home Park",
    "wof:placetype":"campus"
},
  "geometry": {"coordinates":[-83.64444,39.48972],"type":"Point"}
}