{
  "type": "Feature",
  "properties": {
    "iso:country":"US",
    "name:deu_x_preferred":[
        "DeLong"
    ],
    "name:rus_x_preferred":[
        "\u0414\u0435\u043b\u043e\u043d\u0433"
    ],
    "name:ukr_x_preferred":[
        "\u0414\u0435\u043b\u043e\u043d\u0433"
    ],
    "wof:name":"Delong",
    "wof:placetype":"neighbourhood"
},
  "geometry": {"coordinates":[-122.50103586800967,47.25024784707685],"type":"Point"}
}