{
  "type": "Feature",
  "properties": {
    "iso:country":"US",
    "name:eng_x_preferred":[
        "The Corridor"
    ],
    "wd:wordcount":210,
    "wof:name":"The Corridor",
    "wof:placetype":"neighbourhood",
    "wof:population":59,
    "zs:area_m":25045.85109,
    "zs:blockids":[
        390950016001015
    ],
    "zs:housing10":30,
    "zs:label":"The Corridor",
    "zs:pop10":59
},
  "geometry": {"coordinates":[-83.558447,41.674932],"type":"Point"}
}