{
  "type": "Feature",
  "properties": {
    "gn:admin1_code":"AL",
    "gn:admin2_code":"69",
    "gn:asciiname":"Lucy",
    "gn:country_code":"US",
    "gn:dem":46,
    "gn:elevation":"39.0",
    "gn:feature_class":"P",
    "gn:feature_code":"PPL",
    "gn:name":"Lucy",
    "gn:population":0,
    "gn:timezone":"America/Chicago",
    "iso:country":"US",
    "name:fas_x_preferred":[
        "\u0644\u0648\u0633\u06cc"
    ],
    "name:zho_x_preferred":[
        "\u9732\u831c"
    ],
    "wof:name":"Lucy",
    "wof:placetype":"locality"
},
  "geometry": {"coordinates":[-85.04104,31.02018],"type":"Point"}
}