{
  "type": "Feature",
  "properties": {
    "gn:admin1_code":"OH",
    "gn:admin2_code":"145",
    "gn:admin3_code":"69092.0",
    "gn:asciiname":"Owensville",
    "gn:country_code":"US",
    "gn:dem":172,
    "gn:elevation":"172.0",
    "gn:feature_class":"P",
    "gn:feature_code":"PPL",
    "gn:name":"Owensville",
    "gn:population":0,
    "gn:timezone":"America/New_York",
    "iso:country":"US",
    "name:cat_x_preferred":[
        "Owensville"
    ],
    "name:ceb_x_preferred":[
        "Owensville"
    ],
    "name:deu_x_preferred":[
        "Owensville"
    ],
    "name:fra_x_preferred":[
        "Owensville"
    ],
    "name:ita_x_preferred":[
        "Owensville"
    ],
    "name:nld_x_preferred":[
        "Owensville"
    ],
    "name:pol_x_preferred":[
        "Owensville"
    ],
    "name:por_x_preferred":[
        "Owensville"
    ],
    "name:srp_x_preferred":[
        "\u041e\u0443\u0432\u0435\u043d\u0441\u0432\u0438\u043b"
    ],
    "name:vol_x_preferred":[
        "Owensville"
    ],
    "wof:name":"Owensville",
    "wof:placetype":"locality"
},
  "geometry": {"coordinates":[-83.04018000000001,38.85119],"type":"Point"}
}