{
  "type": "Feature",
  "properties": {
    "gn:admin1_code":"TN",
    "gn:admin2_code":"149.0",
    "gn:asciiname":"Pioneer Estates",
    "gn:country_code":"US",
    "gn:dem":171,
    "gn:elevation":"171.0",
    "gn:feature_class":"P",
    "gn:feature_code":"PPL",
    "gn:name":"Pioneer Estates",
    "gn:population":0,
    "gn:timezone":"America/Chicago",
    "iso:country":"US",
    "wof:name":"Pioneer Estates",
    "wof:placetype":"locality"
},
  "geometry": {"coordinates":[-86.49721,35.94729],"type":"Point"}
}