{
  "type": "Feature",
  "properties": {
    "gn:elevation":551,
    "iso:country":"US",
    "name:eng_x_preferred":[
        "Timberlinks"
    ],
    "name:und_x_variant":[
        "Timberlink"
    ],
    "qs:gn_adm0_cc":"US",
    "qs:gn_fcode":"PPL",
    "qs:gn_local":4657633,
    "qs:gn_nam_loc":"Signal Mountain, Hamilton, Tennessee, US",
    "qs:gn_namadm1":"TN",
    "qs:gn_name":"Timberlinks",
    "qs:local_max":126,
    "qs:local_sum":126,
    "qs:localhoods":1,
    "qs:name":"Timberlinks",
    "qs:name_adm0":"United States",
    "qs:name_adm1":"Tennessee",
    "qs:name_adm2":"Hamilton",
    "qs:name_local":"Signal Mountain",
    "qs:photo_max":43,
    "qs:photo_sum":126,
    "qs:placetype":"Suburb",
    "qs:quad_count":10,
    "qs:woe_adm0":23424977,
    "qs:woe_adm1":2347601,
    "qs:woe_adm2":12589944,
    "qs:woe_lau":0,
    "qs:woe_local":2493473,
    "qs:woe_ver":"7.10.0",
    "wof:name":"Timberlinks",
    "wof:placetype":"neighbourhood",
    "wof:population":2107,
    "zs:blockids":[
        470650110021043,
        470650111003027,
        470650111001053,
        470650111001055,
        470650111003020,
        470650111003009,
        470650110021040,
        470650111001057,
        470650111001027,
        470650110021050,
        470650111003007,
        470650110021041,
        470650110021029,
        470650111003000,
        470650111001010,
        470650111001009,
        470650111003028,
        470650111003016,
        470650111003032,
        470650111001022,
        470650110021033,
        470650111001011,
        470650111001013,
        470650111003018,
        470650111003011,
        470650111003012,
        470650111003003,
        470650110021048,
        470650111003029,
        470650111001017,
        470650111001020,
        470650111001012,
        470650110021047,
        470650111003004,
        470650111003013,
        470650111001008,
        470650111003005,
        470650111001023,
        470650110021049,
        470650111001026,
        470650110021046,
        470650110021034,
        470650111003017,
        470650111003030,
        470650111003015,
        470650111003021,
        470650110021042,
        470650111003008,
        470650111003010,
        470650109021018,
        470650111003001,
        470650111003019,
        470650111003006,
        470650111003031,
        470650110021028
    ],
    "zs:housing10":1035,
    "zs:pop10":2107
},
  "geometry": {"coordinates":[-85.369243,35.122377],"type":"Point"}
}