{
  "type": "Feature",
  "properties": {
    "gn:admin1_code":"AK",
    "gn:admin2_code":"105.0",
    "gn:asciiname":"Eight Fathom Bight",
    "gn:country_code":"US",
    "gn:dem":16,
    "gn:feature_class":"P",
    "gn:feature_code":"PPLL",
    "gn:name":"Eight Fathom Bight",
    "gn:population":0,
    "gn:timezone":"America/Juneau",
    "iso:country":"US",
    "name:eng_x_preferred":[
        "Eight Fathom Bight"
    ],
    "wof:name":"Eight Fathom Bight",
    "wof:placetype":"locality"
},
  "geometry": {"coordinates":[-135.77831,57.99864],"type":"Point"}
}