{
  "type": "Feature",
  "properties": {
    "iso:country":"US",
    "name:eng_x_preferred":[
        "Patriot's Colony"
    ],
    "wof:name":"Patriot's Colony",
    "wof:placetype":"neighbourhood",
    "wof:population":413,
    "zs:area_m":992389.670992,
    "zs:blockids":[
        510950803041088,
        510950803041084,
        510950803041083,
        510950803041081,
        510950803041079,
        510950803041082,
        510950803041080,
        510950803041087,
        510950803041086,
        510950803041085
    ],
    "zs:housing10":296,
    "zs:label":"Patriot's Colony",
    "zs:pop10":413
},
  "geometry": {"coordinates":[-76.806772,37.257582],"type":"Point"}
}