{
  "type": "Feature",
  "properties": {
    "gn:admin1_code":"GA",
    "gn:admin2_code":"77",
    "gn:asciiname":"Saint Charles",
    "gn:country_code":"US",
    "gn:dem":275,
    "gn:elevation":"275.0",
    "gn:feature_class":"P",
    "gn:feature_code":"PPL",
    "gn:name":"Saint Charles",
    "gn:population":0,
    "gn:timezone":"America/New_York",
    "iso:country":"US",
    "name:cat_x_preferred":[
        "Saint Charles"
    ],
    "name:ceb_x_preferred":[
        "Saint Charles"
    ],
    "name:deu_x_preferred":[
        "St. Charles"
    ],
    "name:fin_x_preferred":[
        "St. Charles"
    ],
    "name:fra_x_preferred":[
        "Saint Charles"
    ],
    "name:hun_x_preferred":[
        "Saint Charles"
    ],
    "name:ita_x_preferred":[
        "Saint Charles"
    ],
    "name:nld_x_preferred":[
        "St. Charles"
    ],
    "name:pol_x_preferred":[
        "St. Charles"
    ],
    "name:por_x_preferred":[
        "Saint Charles"
    ],
    "name:rus_x_preferred":[
        "\u0421\u0435\u043d\u0442-\u0427\u0430\u0440\u043b\u044c\u0437"
    ],
    "name:srp_x_preferred":[
        "\u0421\u0435\u043d\u0442 \u0427\u0430\u0440\u043b\u0441"
    ],
    "name:swe_x_preferred":[
        "Saint Charles"
    ],
    "name:urd_x_preferred":[
        "\u0633\u06cc\u0646\u0679 \u0686\u0627\u0631\u0644\u0633"
    ],
    "name:vol_x_preferred":[
        "St. Charles"
    ],
    "wof:name":"Saint Charles",
    "wof:placetype":"locality"
},
  "geometry": {"coordinates":[-84.77576999999999,33.26873],"type":"Point"}
}