{
  "type": "Feature",
  "properties": {
    "iso:country":"US",
    "name:eng_x_preferred":[
        "Lake Halice Plat"
    ],
    "wof:name":"Lake Halice Plat",
    "wof:placetype":"neighbourhood",
    "wof:population":493,
    "zs:area_m":275262.794318,
    "zs:blockids":[
        191530104062058,
        191530104053026
    ],
    "zs:housing10":345,
    "zs:label":"Lake Halice Plat",
    "zs:pop10":493
},
  "geometry": {"coordinates":[-93.733372,41.623952],"type":"Point"}
}