{
  "type": "Feature",
  "properties": {
    "gn:admin1_code":"VA",
    "gn:admin2_code":"81",
    "gn:asciiname":"Green Plain",
    "gn:country_code":"US",
    "gn:dem":40,
    "gn:elevation":"39.0",
    "gn:feature_class":"P",
    "gn:feature_code":"PPL",
    "gn:name":"Green Plain",
    "gn:population":0,
    "gn:timezone":"America/New_York",
    "iso:country":"US",
    "name:eng_x_preferred":[
        "Green Plain"
    ],
    "name:und_x_variant":[
        "Greenplain"
    ],
    "wof:name":"Green Plain",
    "wof:placetype":"locality"
},
  "geometry": {"coordinates":[-77.45192,36.69682],"type":"Point"}
}