{
  "type": "Feature",
  "properties": {
    "gn:admin1_code":"PA",
    "gn:admin2_code":"59.0",
    "gn:admin3_code":"73248.0",
    "gn:asciiname":"Ned",
    "gn:country_code":"US",
    "gn:dem":449,
    "gn:elevation":"456.0",
    "gn:feature_class":"P",
    "gn:feature_code":"PPL",
    "gn:name":"Ned",
    "gn:population":0,
    "gn:timezone":"America/New_York",
    "iso:country":"US",
    "wof:name":"Ned",
    "wof:placetype":"locality"
},
  "geometry": {"coordinates":[-80.4823,39.72592],"type":"Point"}
}