{
  "type": "Feature",
  "properties": {
    "iso:country":"US",
    "name:arz_x_preferred":[
        "\u0645\u0627\u0631\u0644\u064a\u0646 \u0647\u0648\u0631\u062a"
    ],
    "name:ast_x_preferred":[
        "Marlin Hurt"
    ],
    "name:cat_x_preferred":[
        "Marlin Hurt"
    ],
    "name:dan_x_preferred":[
        "Marlin Hurt"
    ],
    "name:deu_x_preferred":[
        "Marlin Hurt"
    ],
    "name:eng_x_preferred":[
        "Marlin Forest"
    ],
    "name:eng_x_variant":[
        "Marlin Hurt"
    ],
    "name:eus_x_preferred":[
        "Marlin Hurt"
    ],
    "name:fin_x_preferred":[
        "Marlin Hurt"
    ],
    "name:fra_x_preferred":[
        "Marlin Hurt"
    ],
    "name:gle_x_preferred":[
        "Marlin Hurt"
    ],
    "name:ita_x_preferred":[
        "Marlin Hurt"
    ],
    "name:nld_x_preferred":[
        "Marlin Hurt"
    ],
    "name:nno_x_preferred":[
        "Marlin Hurt"
    ],
    "name:nob_x_preferred":[
        "Marlin Hurt"
    ],
    "name:pap_x_preferred":[
        "Marlin Hurt"
    ],
    "name:pol_x_preferred":[
        "Marlin Hurt"
    ],
    "name:por_x_preferred":[
        "Marlin Hurt"
    ],
    "name:slv_x_preferred":[
        "Marlin Hurt"
    ],
    "name:spa_x_preferred":[
        "Marlin Hurt"
    ],
    "name:sqi_x_preferred":[
        "Marlin Hurt"
    ],
    "name:swe_x_preferred":[
        "Marlin Hurt"
    ],
    "name:yor_x_preferred":[
        "Marlin Hurt"
    ],
    "wd:wordcount":363,
    "wof:name":"Marlin Forest",
    "wof:placetype":"neighbourhood",
    "wof:population":3265,
    "zs:blockids":[
        240338014043048,
        240338014102010,
        240338014102020,
        240338014102016,
        240338014102015,
        240338014043037,
        240338014043047,
        240338014102014,
        510594152001005,
        510594152004011,
        510594152004024,
        510594152003004,
        510594152001011,
        510594152001006,
        510594152004030,
        510594156001006,
        510594152004015,
        510594152003012,
        510594152004010,
        510594152002002,
        510594156001007,
        510594152001007,
        510594152004035,
        510594152004028,
        510594152004026,
        510594152004033,
        510594152003007,
        510594152001010,
        510594152004031,
        510594152004014,
        510594152004012,
        510594156001003,
        510594156001005,
        510594152003003,
        510594152004032,
        510594152001004,
        510594152003008,
        510594152001009,
        510594152004013,
        510594152003011,
        510594152003009,
        510594152004016,
        510594152004034,
        510594152003000,
        510594152003010,
        510594152003002,
        510594152004025,
        510594152003001,
        510594152004027,
        510594152004029,
        510594152001008,
        510594152002003,
        510594152002000,
        510594152001012
    ],
    "zs:housing10":1830,
    "zs:label":"Marlin Forest",
    "zs:pop10":3265
},
  "geometry": {"coordinates":[-77.048877,38.774192],"type":"Point"}
}