{
  "type": "Feature",
  "properties": {
    "gn:admin1_code":"TX",
    "gn:admin2_code":"331.0",
    "gn:asciiname":"Bowers",
    "gn:country_code":"US",
    "gn:dem":162,
    "gn:elevation":"158.0",
    "gn:feature_class":"P",
    "gn:feature_code":"PPL",
    "gn:name":"Bowers",
    "gn:population":0,
    "gn:timezone":"America/Chicago",
    "iso:country":"US",
    "name:ceb_x_preferred":[
        "Bowers"
    ],
    "name:deu_x_preferred":[
        "Bowers"
    ],
    "name:fra_x_preferred":[
        "Bowers"
    ],
    "name:pol_x_preferred":[
        "Bowers"
    ],
    "name:por_x_preferred":[
        "Bowers"
    ],
    "name:rus_x_preferred":[
        "\u0411\u0430\u0443\u044d\u0440\u0441"
    ],
    "name:srp_x_preferred":[
        "\u0411\u0430\u0443\u0435\u0440\u0441"
    ],
    "name:swe_x_preferred":[
        "Bowers"
    ],
    "name:ukr_x_preferred":[
        "\u0411\u0430\u0443\u0435\u0440\u0441"
    ],
    "wof:name":"Bowers",
    "wof:placetype":"locality"
},
  "geometry": {"coordinates":[-97.18611,30.91185],"type":"Point"}
}