{
  "type": "Feature",
  "properties": {
    "gn:admin1_code":"AZ",
    "gn:admin2_code":"12.0",
    "gn:asciiname":"Parker Trailer Park",
    "gn:country_code":"US",
    "gn:dem":128,
    "gn:elevation":"128.0",
    "gn:feature_class":"P",
    "gn:feature_code":"PPL",
    "gn:name":"Parker Trailer Park",
    "gn:population":0,
    "gn:timezone":"America/Phoenix",
    "iso:country":"US",
    "wof:name":"Parker Trailer Park",
    "wof:placetype":"campus"
},
  "geometry": {"coordinates":[-114.28788,34.14400999999999],"type":"Point"}
}