{
  "type": "Feature",
  "properties": {
    "iso:country":"US",
    "name:deu_x_preferred":[
        "J\u00e4ger"
    ],
    "name:eng_x_preferred":[
        "Jaeger"
    ],
    "name:fin_x_preferred":[
        "J\u00e4ger"
    ],
    "name:heb_x_preferred":[
        "\u05d9\u05d2\u05e8"
    ],
    "name:ita_x_preferred":[
        "J\u00e4ger"
    ],
    "name:jpn_x_preferred":[
        "\u30a4\u30a7\u30fc\u30ac\u30fc"
    ],
    "name:kor_x_preferred":[
        "\uc608\uac70"
    ],
    "name:lav_x_preferred":[
        "J\u0113gers"
    ],
    "name:lit_x_preferred":[
        "J\u0117geris"
    ],
    "name:nld_x_preferred":[
        "Jaeger"
    ],
    "name:pol_x_preferred":[
        "J\u00e4ger"
    ],
    "qs:gn_adm0_cc":"US",
    "qs:gn_local":4165565,
    "qs:gn_nam_loc":"Naples, Collier, Florida, US",
    "qs:gn_namadm1":"FL",
    "qs:local_max":2235,
    "qs:local_sum":5122,
    "qs:localhoods":15,
    "qs:name":"Jaeger",
    "qs:name_adm0":"United States",
    "qs:name_adm1":"Florida",
    "qs:name_adm2":"Collier",
    "qs:name_local":"Naples",
    "qs:photo_max":29,
    "qs:photo_sum":56,
    "qs:placetype":"Suburb",
    "qs:quad_count":9,
    "qs:woe_adm0":23424977,
    "qs:woe_adm1":2347568,
    "qs:woe_adm2":12587813,
    "qs:woe_lau":0,
    "qs:woe_local":2457027,
    "qs:woe_ver":"7.10.0",
    "wof:lang":[
        "eng"
    ],
    "wof:name":"Jaeger",
    "wof:placetype":"neighbourhood",
    "wof:population":1594,
    "zs:blockids":[
        120210102123001,
        120210102123016,
        120210102123015,
        120210102123006,
        120210102123009,
        120210102123010,
        120210102123014,
        120210102123017,
        120210102102000,
        120210102111001,
        120210102123029,
        120210102123012,
        120210102123028
    ],
    "zs:housing10":719,
    "zs:pop10":1594
},
  "geometry": {"coordinates":[-81.780192,26.212942],"type":"Point"}
}