{
  "type": "Feature",
  "properties": {
    "gn:admin1_code":"GA",
    "gn:admin2_code":"153",
    "gn:asciiname":"Stathams Landing",
    "gn:country_code":"US",
    "gn:dem":97,
    "gn:elevation":"87.0",
    "gn:feature_class":"P",
    "gn:feature_code":"PPL",
    "gn:name":"Stathams Landing",
    "gn:population":0,
    "gn:timezone":"America/New_York",
    "iso:country":"US",
    "wof:name":"Stathams Landing",
    "wof:placetype":"locality"
},
  "geometry": {"coordinates":[-83.57352,32.57098],"type":"Point"}
}