{
  "type": "Feature",
  "properties": {
    "gn:admin1_code":"MI",
    "gn:admin2_code":"149",
    "gn:admin3_code":"59400.0",
    "gn:asciiname":"Centre Chateaux Mobile Home Park",
    "gn:country_code":"US",
    "gn:dem":246,
    "gn:elevation":"247.0",
    "gn:feature_class":"P",
    "gn:feature_code":"PPL",
    "gn:name":"Centre Chateaux Mobile Home Park",
    "gn:population":0,
    "gn:timezone":"America/Detroit",
    "iso:country":"US",
    "wof:name":"Centre Chateaux Mobile Home Park",
    "wof:placetype":"campus"
},
  "geometry": {"coordinates":[-85.53083000000002,41.92583],"type":"Point"}
}