{
  "type": "Feature",
  "properties": {
    "gn:country":"US",
    "gn:fcode":"PPL",
    "gn:population":0,
    "iso:country":"US",
    "name:cat_x_preferred":[
        "Klondike"
    ],
    "name:ceb_x_preferred":[
        "Klondike"
    ],
    "name:ces_x_preferred":[
        "Klondike"
    ],
    "name:dan_x_preferred":[
        "Klondike"
    ],
    "name:deu_x_preferred":[
        "Klondike"
    ],
    "name:fra_x_preferred":[
        "Klondike"
    ],
    "name:heb_x_preferred":[
        "\u05e7\u05dc\u05d5\u05e0\u05d3\u05d9\u05d9\u05e7"
    ],
    "name:ita_x_preferred":[
        "Klondike"
    ],
    "name:nor_x_preferred":[
        "Klondike"
    ],
    "name:ron_x_preferred":[
        "Klondike"
    ],
    "name:rus_x_preferred":[
        "\u041a\u043b\u043e\u043d\u0434\u0430\u0439\u043a"
    ],
    "name:slk_x_preferred":[
        "Klondike"
    ],
    "name:spa_x_preferred":[
        "Klondike"
    ],
    "name:swe_x_preferred":[
        "Klondike"
    ],
    "name:ukr_x_preferred":[
        "\u041a\u043b\u043e\u043d\u0434\u0430\u0439\u043a"
    ],
    "qs_pg:aaroncc":"US",
    "qs_pg:gn_country":"US",
    "qs_pg:gn_fcode":"PPL",
    "qs_pg:gn_pop":0,
    "qs_pg:name":"Klondike",
    "qs_pg:name_adm0":"United States",
    "qs_pg:name_adm1":"Ohio",
    "qs_pg:photos":6,
    "qs_pg:photos_1k":1,
    "qs_pg:photos_9k":1,
    "qs_pg:photos_9r":1,
    "qs_pg:photos_all":6,
    "qs_pg:photos_sr":1,
    "qs_pg:pop_sr":0,
    "qs_pg:qs_pg_placetype":"locality",
    "qs_pg:qs_pg_placetype_gp":"Town",
    "qs_pg:woe_adm0":23424977,
    "woe:adm0_id":23424977,
    "woe:name_adm0":"United States",
    "woe:name_adm1":"Ohio",
    "woe:placetype":"Town",
    "wof:name":"Klondike",
    "wof:placetype":"locality"
},
  "geometry": {"coordinates":[-83.14408,40.27201],"type":"Point"}
}