{
  "type": "Feature",
  "properties": {
    "gn:admin1_code":"MO",
    "gn:admin2_code":"65.0",
    "gn:admin3_code":"72808.0",
    "gn:asciiname":"Rhyse",
    "gn:country_code":"US",
    "gn:dem":377,
    "gn:elevation":"375.0",
    "gn:feature_class":"P",
    "gn:feature_code":"PPL",
    "gn:name":"Rhyse",
    "gn:population":0,
    "gn:timezone":"America/Chicago",
    "iso:country":"US",
    "wof:name":"Rhyse",
    "wof:placetype":"locality"
},
  "geometry": {"coordinates":[-91.68626,37.56921],"type":"Point"}
}