{
  "type": "Feature",
  "properties": {
    "gn:admin1_code":"NC",
    "gn:admin2_code":"17.0",
    "gn:admin3_code":"90604.0",
    "gn:asciiname":"Ruskin",
    "gn:country_code":"US",
    "gn:dem":23,
    "gn:elevation":"19.0",
    "gn:feature_class":"P",
    "gn:feature_code":"PPL",
    "gn:name":"Ruskin",
    "gn:population":0,
    "gn:timezone":"America/New_York",
    "iso:country":"US",
    "name:ceb_x_preferred":[
        "Ruskin"
    ],
    "name:deu_x_preferred":[
        "Ruskin"
    ],
    "name:fra_x_preferred":[
        "Ruskin"
    ],
    "name:ita_x_preferred":[
        "Ruskin"
    ],
    "name:nds_x_preferred":[
        "Ruskin"
    ],
    "name:nld_x_preferred":[
        "Ruskin"
    ],
    "name:pol_x_preferred":[
        "Ruskin"
    ],
    "name:por_x_preferred":[
        "Ruskin"
    ],
    "name:ukr_x_preferred":[
        "\u0420\u0430\u0441\u043a\u0456\u043d"
    ],
    "name:vol_x_preferred":[
        "Ruskin"
    ],
    "wof:name":"Ruskin",
    "wof:placetype":"locality"
},
  "geometry": {"coordinates":[-78.67446,34.70989],"type":"Point"}
}