{
  "type": "Feature",
  "properties": {
    "gn:admin1_code":"MO",
    "gn:admin2_code":"127.0",
    "gn:admin3_code":"42230.0",
    "gn:asciiname":"Helton",
    "gn:country_code":"US",
    "gn:dem":150,
    "gn:elevation":"145.0",
    "gn:feature_class":"P",
    "gn:feature_code":"PPL",
    "gn:name":"Helton",
    "gn:population":0,
    "gn:timezone":"America/Chicago",
    "iso:country":"US",
    "name:deu_x_preferred":[
        "Helton"
    ],
    "name:eng_x_preferred":[
        "Helton"
    ],
    "name:pol_x_preferred":[
        "Helton"
    ],
    "name:swe_x_preferred":[
        "Helton"
    ],
    "name:und_x_variant":[
        "Helton Station"
    ],
    "wof:name":"Helton",
    "wof:placetype":"locality"
},
  "geometry": {"coordinates":[-91.42126,39.77477],"type":"Point"}
}