{
  "type": "Feature",
  "properties": {
    "gn:admin1_code":"MD",
    "gn:admin2_code":"31.0",
    "gn:asciiname":"Londonderry",
    "gn:country_code":"US",
    "gn:dem":147,
    "gn:elevation":"142.0",
    "gn:feature_class":"P",
    "gn:feature_code":"PPL",
    "gn:name":"Londonderry",
    "gn:population":0,
    "gn:timezone":"America/New_York",
    "iso:country":"US",
    "wof:name":"Londonderry",
    "wof:placetype":"locality"
},
  "geometry": {"coordinates":[-77.20804,39.13733],"type":"Point"}
}