{
  "type": "Feature",
  "properties": {
    "gn:admin1_code":"ME",
    "gn:admin2_code":"21.0",
    "gn:admin3_code":"51105.0",
    "gn:asciiname":"Mooresville",
    "gn:country_code":"US",
    "gn:dem":193,
    "gn:elevation":"191.0",
    "gn:feature_class":"P",
    "gn:feature_code":"PPL",
    "gn:name":"Mooresville",
    "gn:population":0,
    "gn:timezone":"America/New_York",
    "iso:country":"US",
    "name:ceb_x_preferred":[
        "Mooresville"
    ],
    "name:deu_x_preferred":[
        "Mooresville"
    ],
    "name:ita_x_preferred":[
        "Mooresville"
    ],
    "name:nld_x_preferred":[
        "Mooresville"
    ],
    "name:pol_x_preferred":[
        "Mooresville"
    ],
    "name:por_x_preferred":[
        "Mooresville"
    ],
    "name:spa_x_preferred":[
        "Mooresville"
    ],
    "name:srp_x_preferred":[
        "\u041c\u0443\u0440\u0441\u0432\u0438\u043b"
    ],
    "name:urd_x_preferred":[
        "\u0645\u0648\u0631\u0632\u0648\u06cc\u0644"
    ],
    "name:vol_x_preferred":[
        "Mooresville"
    ],
    "wof:name":"Mooresville",
    "wof:placetype":"locality"
},
  "geometry": {"coordinates":[-69.09976999999999,45.41422],"type":"Point"}
}