{
  "type": "Feature",
  "properties": {
    "gn:admin1_code":"KY",
    "gn:admin2_code":"35.0",
    "gn:asciiname":"South Murray",
    "gn:country_code":"US",
    "gn:dem":160,
    "gn:elevation":"157.0",
    "gn:feature_class":"P",
    "gn:feature_code":"PPL",
    "gn:name":"South Murray",
    "gn:population":0,
    "gn:timezone":"America/Chicago",
    "iso:country":"US",
    "wof:name":"South Murray",
    "wof:placetype":"locality"
},
  "geometry": {"coordinates":[-88.32158000000003,36.5848],"type":"Point"}
}