{
  "type": "Feature",
  "properties": {
    "gn:admin1_code":"MD",
    "gn:admin2_code":"25.0",
    "gn:asciiname":"Glenora",
    "gn:country_code":"US",
    "gn:dem":112,
    "gn:elevation":"120.0",
    "gn:feature_class":"P",
    "gn:feature_code":"PPL",
    "gn:name":"Glenora",
    "gn:population":0,
    "gn:timezone":"America/New_York",
    "iso:country":"US",
    "wof:name":"Glenora",
    "wof:placetype":"locality"
},
  "geometry": {"coordinates":[-76.14773000000002,39.58372],"type":"Point"}
}