{
  "type": "Feature",
  "properties": {
    "gn:admin1_code":"GA",
    "gn:admin2_code":"115",
    "gn:asciiname":"Rice Springs Estates",
    "gn:country_code":"US",
    "gn:dem":220,
    "gn:elevation":"213.0",
    "gn:feature_class":"P",
    "gn:feature_code":"PPL",
    "gn:name":"Rice Springs Estates",
    "gn:population":0,
    "gn:timezone":"America/New_York",
    "iso:country":"US",
    "wof:name":"Rice Springs Estates",
    "wof:placetype":"locality"
},
  "geometry": {"coordinates":[-85.25273,34.26676],"type":"Point"}
}