{
  "type": "Feature",
  "properties": {
    "gn:admin1_code":"TN",
    "gn:admin2_code":"59.0",
    "gn:asciiname":"Brittontown",
    "gn:country_code":"US",
    "gn:dem":472,
    "gn:elevation":"466.0",
    "gn:feature_class":"P",
    "gn:feature_code":"PPL",
    "gn:name":"Brittontown",
    "gn:population":0,
    "gn:timezone":"America/New_York",
    "iso:country":"US",
    "wof:name":"Brittontown",
    "wof:placetype":"locality"
},
  "geometry": {"coordinates":[-82.78655000000001,36.27288],"type":"Point"}
}