{
  "type": "Feature",
  "properties": {
    "gn:admin1_code":"KY",
    "gn:admin2_code":"13",
    "gn:asciiname":"Varilla",
    "gn:country_code":"US",
    "gn:dem":320,
    "gn:elevation":"312.0",
    "gn:feature_class":"P",
    "gn:feature_code":"PPL",
    "gn:name":"Varilla",
    "gn:population":0,
    "gn:timezone":"America/New_York",
    "iso:country":"US",
    "name:fas_x_preferred":[
        "\u0648\u0631\u06cc\u0644\u0627"
    ],
    "wof:name":"Varilla",
    "wof:placetype":"locality"
},
  "geometry": {"coordinates":[-83.59992,36.73953],"type":"Point"}
}