{
  "type": "Feature",
  "properties": {
    "iso:country":"US",
    "name:cat_x_preferred":[
        "Branchville"
    ],
    "name:ceb_x_preferred":[
        "Branchville"
    ],
    "name:deu_x_preferred":[
        "Branchville"
    ],
    "name:eng_x_preferred":[
        "Branchville"
    ],
    "name:fra_x_preferred":[
        "Branchville"
    ],
    "name:ido_x_preferred":[
        "Branchville"
    ],
    "name:ita_x_preferred":[
        "Branchville"
    ],
    "name:nld_x_preferred":[
        "Branchville"
    ],
    "name:pol_x_preferred":[
        "Branchville"
    ],
    "name:por_x_preferred":[
        "Branchville"
    ],
    "name:spa_x_preferred":[
        "Branchville"
    ],
    "name:srp_x_preferred":[
        "\u0411\u0440\u0430\u043d\u0447\u0432\u0438\u043b"
    ],
    "name:ukr_x_preferred":[
        "\u0411\u0440\u0430\u043d\u0447\u0432\u0456\u043b\u043b"
    ],
    "name:vol_x_preferred":[
        "Branchville"
    ],
    "wd:wordcount":29,
    "wof:name":"Branchville",
    "wof:placetype":"neighbourhood",
    "wof:population":816,
    "zs:area_m":764716.081804,
    "zs:blockids":[
        240338067142039,
        240338070001004,
        240338070002035,
        240338070001012,
        240338070001015,
        240338070001020,
        240338070001021,
        240338067142025,
        240338067142033,
        240338067142010,
        240338070001009,
        240338070001001,
        240338067142031,
        240338067142021,
        240338070001007,
        240338067142007,
        240338070001026,
        240338067142032,
        240338067142027,
        240338069002036,
        240338070001023,
        240338067142019,
        240338070001017,
        240338070001024,
        240338070001013,
        240338070001027,
        240338070002037,
        240338067142028,
        240338070001005,
        240338070001022,
        240338070001011,
        240338070001014,
        240338070001025,
        240338070001018,
        240338070002033,
        240338067142024,
        240338067142036,
        240338070002034,
        240338070001010,
        240338068001010,
        240338067142022,
        240338070001006,
        240338067142026,
        240338067142020,
        240338070001003,
        240338070002038,
        240338070001008,
        240338070001002,
        240338070001019,
        240338067142030,
        240338067142029,
        240338070001028,
        240338067142023,
        240338070001031,
        240338069002033,
        240338070001016
    ],
    "zs:housing10":285,
    "zs:label":"Branchville",
    "zs:pop10":816
},
  "geometry": {"coordinates":[-76.921488,39.002942],"type":"Point"}
}