{
  "type": "Feature",
  "properties": {
    "gn:admin1_code":"TX",
    "gn:admin2_code":"97.0",
    "gn:asciiname":"Rosston",
    "gn:country_code":"US",
    "gn:dem":267,
    "gn:elevation":"260.0",
    "gn:feature_class":"P",
    "gn:feature_code":"PPL",
    "gn:name":"Rosston",
    "gn:population":0,
    "gn:timezone":"America/Chicago",
    "iso:country":"US",
    "wof:name":"Rosston",
    "wof:placetype":"locality"
},
  "geometry": {"coordinates":[-97.44225,33.48344],"type":"Point"}
}