{
  "type": "Feature",
  "properties": {
    "gn:country":"US",
    "gn:fcode":"PPL",
    "gn:population":0,
    "iso:country":"US",
    "name:ceb_x_preferred":[
        "Oak Hill"
    ],
    "name:deu_x_preferred":[
        "Oak Hill"
    ],
    "name:eng_x_preferred":[
        "Oak Hill"
    ],
    "name:fas_x_preferred":[
        "\u0627\u0648\u06a9 \u0647\u06cc\u0644"
    ],
    "name:fra_x_preferred":[
        "Oak Hill"
    ],
    "name:ita_x_preferred":[
        "Oak Hill"
    ],
    "name:kor_x_preferred":[
        "\uc624\ud06c\ud790"
    ],
    "name:nld_x_preferred":[
        "Oak Hill"
    ],
    "name:pol_x_preferred":[
        "Oak Hill"
    ],
    "name:por_x_preferred":[
        "Oak Hill"
    ],
    "name:spa_x_preferred":[
        "Oak Hill"
    ],
    "name:srp_x_preferred":[
        "\u041e\u0443\u043a \u0425\u0438\u043b"
    ],
    "name:swe_x_preferred":[
        "Oak Hill"
    ],
    "name:urd_x_preferred":[
        "\u0627\u0648\u06a9 \u06c1\u0644"
    ],
    "name:vol_x_preferred":[
        "Oak Hill"
    ],
    "qs_pg:aaroncc":"US",
    "qs_pg:gn_country":"US",
    "qs_pg:gn_fcode":"PPL",
    "qs_pg:gn_pop":0,
    "qs_pg:name":"Oak Hill",
    "qs_pg:name_adm0":"United States",
    "qs_pg:name_adm1":"New York",
    "qs_pg:photos":35,
    "qs_pg:photos_1k":7,
    "qs_pg:photos_9k":1,
    "qs_pg:photos_9r":2,
    "qs_pg:photos_all":35,
    "qs_pg:photos_sr":2,
    "qs_pg:pop_sr":0,
    "qs_pg:qs_pg_placetype":"neighbourhood",
    "qs_pg:qs_pg_placetype_gp":"Suburb",
    "qs_pg:woe_adm0":23424977,
    "woe:adm0_id":23424977,
    "woe:name_adm0":"United States",
    "woe:name_adm1":"New York",
    "woe:placetype":"Suburb",
    "wof:name":"Oak Hill",
    "wof:placetype":"neighbourhood",
    "wof:population":2587
},
  "geometry": {"coordinates":[-73.404,42.97091],"type":"Point"}
}