{
  "type": "Feature",
  "properties": {
    "iso:country":"US",
    "qs_pg:aaroncc":"US",
    "qs_pg:name":"Kaneeleele Heiau",
    "qs_pg:name_adm0":"United States",
    "qs_pg:name_adm1":"Hawaii",
    "qs_pg:photos":1206,
    "qs_pg:photos_1k":244,
    "qs_pg:photos_9k":5,
    "qs_pg:photos_9r":7,
    "qs_pg:photos_all":1206,
    "qs_pg:photos_sr":11,
    "qs_pg:pop_sr":0,
    "qs_pg:qs_pg_placetype":"locality",
    "qs_pg:qs_pg_placetype_gp":"Town",
    "qs_pg:woe_adm0":23424977,
    "woe:adm0_id":23424977,
    "woe:name_adm0":"United States",
    "woe:name_adm1":"Hawaii",
    "woe:placetype":"Town",
    "wof:name":"Kaneeleele Heiau",
    "wof:placetype":"locality"
},
  "geometry": {"coordinates":[-155.504865,19.135762],"type":"Point"}
}