{
  "type": "Feature",
  "properties": {
    "gn:admin1_code":"IN",
    "gn:admin2_code":"121.0",
    "gn:admin3_code":"63846.0",
    "gn:asciiname":"Coloma",
    "gn:country_code":"US",
    "gn:dem":190,
    "gn:elevation":"188.0",
    "gn:feature_class":"P",
    "gn:feature_code":"PPL",
    "gn:name":"Coloma",
    "gn:population":0,
    "gn:timezone":"America/Indiana/Indianapolis",
    "iso:country":"US",
    "name:eng_x_preferred":[
        "Coloma"
    ],
    "name:und_x_variant":[
        "Rocky Run"
    ],
    "wof:name":"Coloma",
    "wof:placetype":"locality"
},
  "geometry": {"coordinates":[-87.29196,39.78837],"type":"Point"}
}