{
  "type": "Feature",
  "properties": {
    "gn:admin1_code":"NY",
    "gn:admin2_code":"73",
    "gn:admin3_code":"61742.0",
    "gn:asciiname":"Applewood Mobile Home Estates",
    "gn:country_code":"US",
    "gn:dem":163,
    "gn:elevation":"162.0",
    "gn:feature_class":"P",
    "gn:feature_code":"PPL",
    "gn:name":"Applewood Mobile Home Estates",
    "gn:population":0,
    "gn:timezone":"America/New_York",
    "iso:country":"US",
    "wof:name":"Applewood Mobile Home Estates",
    "wof:placetype":"campus"
},
  "geometry": {"coordinates":[-78.41056,43.21861],"type":"Point"}
}