{
  "type": "Feature",
  "properties": {
    "gn:admin1_code":"TX",
    "gn:admin2_code":"225.0",
    "gn:asciiname":"Smith Grove",
    "gn:country_code":"US",
    "gn:dem":75,
    "gn:elevation":"71.0",
    "gn:feature_class":"P",
    "gn:feature_code":"PPL",
    "gn:name":"Smith Grove",
    "gn:population":0,
    "gn:timezone":"America/Chicago",
    "iso:country":"US",
    "wof:name":"Smith Grove",
    "wof:placetype":"locality"
},
  "geometry": {"coordinates":[-95.38549999999999,31.13907],"type":"Point"}
}