{
  "type": "Feature",
  "properties": {
    "gn:admin1_code":"SC",
    "gn:admin2_code":"19.0",
    "gn:asciiname":"Old Orchard",
    "gn:country_code":"US",
    "gn:dem":4,
    "gn:elevation":"5.0",
    "gn:feature_class":"P",
    "gn:feature_code":"PPL",
    "gn:name":"Old Orchard",
    "gn:population":0,
    "gn:timezone":"America/New_York",
    "iso:country":"US",
    "wof:name":"Old Orchard",
    "wof:placetype":"locality"
},
  "geometry": {"coordinates":[-79.94287,32.72129],"type":"Point"}
}