{
  "type": "Feature",
  "properties": {
    "gn:admin1_code":"CA",
    "gn:admin2_code":"21",
    "gn:asciiname":"Mills Orchard",
    "gn:country_code":"US",
    "gn:dem":55,
    "gn:elevation":"54.0",
    "gn:feature_class":"P",
    "gn:feature_code":"PPL",
    "gn:name":"Mills Orchard",
    "gn:population":0,
    "gn:timezone":"America/Los_Angeles",
    "iso:country":"US",
    "name:zho_x_preferred":[
        "\u7c73\u723e\u65af\u5967\u67e5\u5fb7"
    ],
    "wof:name":"Mills Orchard",
    "wof:placetype":"locality"
},
  "geometry": {"coordinates":[-122.05637,39.73766],"type":"Point"}
}