{
  "type": "Feature",
  "properties": {
    "gn:country":"US",
    "gn:fcode":"PPL",
    "gn:population":0,
    "iso:country":"US",
    "name:azb_x_preferred":[
        "\u0628\u0627\u06cc\u0648 \u0648\u06cc\u0633\u062a\u0627"
    ],
    "name:eng_x_preferred":[
        "Bayo Vista"
    ],
    "name:fas_x_preferred":[
        "\u0628\u0627\u06cc\u0627 \u0648\u06cc\u0633\u062a\u0627"
    ],
    "name:fra_x_preferred":[
        "Bayo Vista"
    ],
    "name:zho_x_preferred":[
        "\u8c9d\u7d04\u7dad\u65af\u5854"
    ],
    "qs_pg:aaroncc":"US",
    "qs_pg:gn_country":"US",
    "qs_pg:gn_fcode":"PPL",
    "qs_pg:gn_pop":0,
    "qs_pg:name":"Bayo Vista",
    "qs_pg:name_adm0":"United States",
    "qs_pg:name_adm1":"California",
    "qs_pg:photos":6,
    "qs_pg:photos_1k":1,
    "qs_pg:photos_9k":1,
    "qs_pg:photos_9r":1,
    "qs_pg:photos_all":6,
    "qs_pg:photos_sr":1,
    "qs_pg:pop_sr":0,
    "qs_pg:qs_pg_placetype":"locality",
    "qs_pg:qs_pg_placetype_gp":"Town",
    "qs_pg:woe_adm0":23424977,
    "woe:adm0_id":23424977,
    "woe:name_adm0":"United States",
    "woe:name_adm1":"California",
    "woe:placetype":"Town",
    "wof:name":"Bayo Vista",
    "wof:placetype":"locality"
},
  "geometry": {"coordinates":[-122.26136,38.03687],"type":"Point"}
}