{
  "type": "Feature",
  "properties": {
    "gn:admin1_code":"NY",
    "gn:admin2_code":"103.0",
    "gn:admin3_code":"10000.0",
    "gn:asciiname":"Greenwood Village",
    "gn:country_code":"US",
    "gn:dem":30,
    "gn:elevation":"28.0",
    "gn:feature_class":"P",
    "gn:feature_code":"PPL",
    "gn:name":"Greenwood Village",
    "gn:population":0,
    "gn:timezone":"America/New_York",
    "iso:country":"US",
    "wof:name":"Greenwood Village",
    "wof:placetype":"locality"
},
  "geometry": {"coordinates":[-72.79083,40.83472],"type":"Point"}
}