{
  "type": "Feature",
  "properties": {
    "gn:admin1_code":"SC",
    "gn:admin2_code":"45.0",
    "gn:asciiname":"Staunton Heights",
    "gn:country_code":"US",
    "gn:dem":300,
    "gn:elevation":"295.0",
    "gn:feature_class":"P",
    "gn:feature_code":"PPL",
    "gn:name":"Staunton Heights",
    "gn:population":0,
    "gn:timezone":"America/New_York",
    "iso:country":"US",
    "wof:name":"Staunton Heights",
    "wof:placetype":"locality"
},
  "geometry": {"coordinates":[-82.44096,34.80512],"type":"Point"}
}