{
  "type": "Feature",
  "properties": {
    "gn:elevation":9,
    "iso:country":"US",
    "name:eng_x_preferred":[
        "Thumpertown Beach"
    ],
    "name:eng_x_variant":[
        "Thumpertown Bch"
    ],
    "qs:gn_adm0_cc":"US",
    "qs:gn_fcode":"PPL",
    "qs:gn_local":4935578,
    "qs:gn_nam_loc":"eastham",
    "qs:gn_namadm1":"MA",
    "qs:gn_name":"Thumpertown Beach",
    "qs:local_max":667,
    "qs:local_sum":1442,
    "qs:localhoods":5,
    "qs:name":"Thumpertown Beach",
    "qs:name_adm0":"United States",
    "qs:name_adm1":"Massachusetts",
    "qs:name_adm2":"Barnstable",
    "qs:name_local":"Eastham",
    "qs:photo_max":56,
    "qs:photo_sum":185,
    "qs:placetype":"Suburb",
    "qs:quad_count":12,
    "qs:woe_adm0":23424977,
    "qs:woe_adm1":2347580,
    "qs:woe_adm2":12588700,
    "qs:woe_lau":0,
    "qs:woe_local":2396430,
    "qs:woe_ver":"7.10.0",
    "wof:lang":[
        "eng"
    ],
    "wof:name":"Thumpertown Beach",
    "wof:placetype":"neighbourhood",
    "wof:population":125,
    "zs:blockids":[
        250010103062048,
        250010103042003,
        250010103062041,
        250010103042013,
        250010103062046,
        250010103062045,
        250010103062049,
        250010103062040,
        250010103062026,
        250010103062042,
        250010103042012
    ],
    "zs:housing10":206,
    "zs:pop10":125
},
  "geometry": {"coordinates":[-69.997086,41.842636],"type":"Point"}
}