{
  "type": "Feature",
  "properties": {
    "gn:admin1_code":"TX",
    "gn:admin2_code":"301.0",
    "gn:asciiname":"Mentone",
    "gn:country_code":"US",
    "gn:dem":820,
    "gn:elevation":"819.0",
    "gn:feature_class":"P",
    "gn:feature_code":"PPL",
    "gn:name":"Mentone",
    "gn:population":0,
    "gn:timezone":"America/Chicago",
    "iso:country":"US",
    "name:ara_x_preferred":[
        "\u0645\u064a\u0646\u062a\u0648\u0646"
    ],
    "name:azb_x_preferred":[
        "\u0645\u06cc\u0646\u062a\u0648\u0646"
    ],
    "name:eus_x_preferred":[
        "Mentone"
    ],
    "name:fas_x_preferred":[
        "\u0645\u06cc\u0646\u062a\u0648\u0646"
    ],
    "name:fra_x_preferred":[
        "Mentone"
    ],
    "name:gle_x_preferred":[
        "Mentone"
    ],
    "name:hrv_x_preferred":[
        "Mentone"
    ],
    "name:ita_x_preferred":[
        "Mentone"
    ],
    "name:jpn_x_preferred":[
        "\u30e1\u30f3\u30c8\u30fc\u30cd"
    ],
    "name:pol_x_preferred":[
        "Mentone"
    ],
    "name:por_x_preferred":[
        "Mentone"
    ],
    "name:rus_x_preferred":[
        "\u041c\u0435\u043d\u0442\u043e\u043d"
    ],
    "name:spa_x_preferred":[
        "Mentone"
    ],
    "name:srp_x_preferred":[
        "\u041c\u0435\u043d\u0442\u043e\u043d"
    ],
    "name:swe_x_preferred":[
        "Mentone"
    ],
    "wof:name":"Mentone",
    "wof:placetype":"locality"
},
  "geometry": {"coordinates":[-103.59878999999999,31.7068],"type":"Point"}
}