{
  "type": "Feature",
  "properties": {
    "gn:admin1_code":"AZ",
    "gn:admin2_code":"17.0",
    "gn:asciiname":"Silver Creek",
    "gn:country_code":"US",
    "gn:dem":1860,
    "gn:elevation":"1859.0",
    "gn:feature_class":"P",
    "gn:feature_code":"PPL",
    "gn:name":"Silver Creek",
    "gn:population":0,
    "gn:timezone":"America/Phoenix",
    "iso:country":"US",
    "wof:name":"Silver Creek",
    "wof:placetype":"locality"
},
  "geometry": {"coordinates":[-109.94955,34.34004],"type":"Point"}
}