{
  "type": "Feature",
  "properties": {
    "gn:admin1_code":"VA",
    "gn:admin2_code":"59",
    "gn:asciiname":"Farrs Corner",
    "gn:country_code":"US",
    "gn:dem":110,
    "gn:elevation":"106.0",
    "gn:feature_class":"P",
    "gn:feature_code":"PPL",
    "gn:name":"Farrs Corner",
    "gn:population":0,
    "gn:timezone":"America/New_York",
    "iso:country":"US",
    "wof:name":"Farrs Corner",
    "wof:placetype":"locality"
},
  "geometry": {"coordinates":[-77.34081999999999,38.74234000000001],"type":"Point"}
}