{
  "type": "Feature",
  "properties": {
    "iso:country":"US",
    "name:eng_x_preferred":[
        "Cross William Mhp"
    ],
    "wof:name":"Cross William Mhp",
    "wof:placetype":"neighbourhood",
    "wof:population":298,
    "zs:area_m":2549948.262846,
    "zs:blockids":[
        370899310001007,
        370899310001005,
        370899310001002,
        370899310001008,
        370899310005007,
        370899310005004,
        370899310001000,
        370899310005005,
        370899310001004,
        370899310005006,
        370899310001009,
        370899310001006
    ],
    "zs:housing10":177,
    "zs:label":"Cross William Mhp",
    "zs:pop10":298
},
  "geometry": {"coordinates":[-82.450686,35.358577],"type":"Point"}
}