{
  "type": "Feature",
  "properties": {
    "iso:country":"US",
    "name:eng_x_preferred":[
        "Down Cove"
    ],
    "qs:gn_adm0_cc":"US",
    "qs:gn_local":4178501,
    "qs:gn_nam_loc":"Windermere, Orange, Florida, US",
    "qs:gn_namadm1":"FL",
    "qs:local_max":50029,
    "qs:local_sum":50857,
    "qs:localhoods":8,
    "qs:name":"Down Cove",
    "qs:name_adm0":"United States",
    "qs:name_adm1":"Florida",
    "qs:name_adm2":"Orange",
    "qs:name_local":"Windermere",
    "qs:photo_max":5,
    "qs:photo_sum":10,
    "qs:placetype":"Suburb",
    "qs:quad_count":2,
    "qs:woe_adm0":23424977,
    "qs:woe_adm1":2347568,
    "qs:woe_adm2":12587850,
    "qs:woe_lau":0,
    "qs:woe_local":2521747,
    "qs:woe_ver":"7.10.0",
    "wof:name":"Down Cove",
    "wof:placetype":"neighbourhood",
    "wof:population":665,
    "zs:blockids":[
        120950148081032,
        120950148081034,
        120950148081072,
        120950148081057,
        120950148081035,
        120950148081031
    ],
    "zs:housing10":238,
    "zs:pop10":665
},
  "geometry": {"coordinates":[-81.52404799999999,28.51697],"type":"Point"}
}