{
  "type": "Feature",
  "properties": {
    "gn:admin1_code":"MD",
    "gn:admin2_code":"47.0",
    "gn:asciiname":"Goodwill",
    "gn:country_code":"US",
    "gn:dem":9,
    "gn:elevation":"9.0",
    "gn:feature_class":"P",
    "gn:feature_code":"PPL",
    "gn:name":"Goodwill",
    "gn:population":0,
    "gn:timezone":"America/New_York",
    "iso:country":"US",
    "name:eng_x_preferred":[
        "Goodwill"
    ],
    "name:und_x_variant":[
        "Davis Cross Roads"
    ],
    "wof:name":"Goodwill",
    "wof:placetype":"locality"
},
  "geometry": {"coordinates":[-75.49159,38.07068],"type":"Point"}
}