{
  "type": "Feature",
  "properties": {
    "gn:admin1_code":"TX",
    "gn:admin2_code":"141.0",
    "gn:asciiname":"Paso del Rey Number 2 Colonia",
    "gn:country_code":"US",
    "gn:dem":1258,
    "gn:elevation":"1264.0",
    "gn:feature_class":"P",
    "gn:feature_code":"PPL",
    "gn:name":"Paso del Rey Number 2 Colonia",
    "gn:population":0,
    "gn:timezone":"America/Denver",
    "iso:country":"US",
    "wof:name":"Paso del Rey Number 2 Colonia",
    "wof:placetype":"locality"
},
  "geometry": {"coordinates":[-106.13942,31.86622],"type":"Point"}
}