{
  "type": "Feature",
  "properties": {
    "iso:country":"US",
    "name:ceb_x_preferred":[
        "Stillwater"
    ],
    "name:deu_x_preferred":[
        "Stillwater"
    ],
    "name:eng_x_preferred":[
        "Stillwater"
    ],
    "name:fin_x_preferred":[
        "Stillwater"
    ],
    "name:fra_x_preferred":[
        "Stillwater"
    ],
    "name:ita_x_preferred":[
        "Stillwater"
    ],
    "name:jpn_x_preferred":[
        "\u30b9\u30c6\u30a3\u30eb\u30a6\u30a9\u30fc\u30bf\u30fc"
    ],
    "name:kor_x_preferred":[
        "\uc2a4\ud2f8\uc6cc\ud130"
    ],
    "name:nld_x_preferred":[
        "Stillwater"
    ],
    "name:pol_x_preferred":[
        "Stillwater"
    ],
    "name:por_x_preferred":[
        "Stillwater"
    ],
    "name:rus_x_preferred":[
        "\u0421\u0442\u0438\u043b\u043b\u0443\u043e\u0442\u0435\u0440"
    ],
    "name:srp_x_preferred":[
        "\u0421\u0442\u0438\u043b\u0432\u043e\u0442\u0435\u0440"
    ],
    "name:swe_x_preferred":[
        "Stillwater"
    ],
    "name:vol_x_preferred":[
        "Stillwater"
    ],
    "name:zho_x_preferred":[
        "\u65af\u8482\u5c14\u6c83\u7279"
    ],
    "wof:name":"Stillwater",
    "wof:placetype":"neighbourhood",
    "wof:population":1190,
    "zs:area_m":1517575.989332,
    "zs:blockids":[
        80010085371029,
        80010085371054,
        80010085371060,
        80010085371055,
        80010085371010,
        80010085351025,
        80010085371061,
        80010085371018,
        80010085371041,
        80010085371042,
        80010085371019,
        80010085371063,
        80010085351009,
        80010085351007,
        80010085351000,
        80010085351026,
        80010085351023,
        80010085351019,
        80010085371044,
        80010085351018,
        80010085371062,
        80010085371059,
        80010085351008,
        80010085371016,
        80010085371043,
        80010085371020,
        80010085371017,
        80010085351006,
        80010085371040,
        80010085351002,
        80010085351003,
        80010085351022,
        80010085371015,
        80010085371066,
        80010085371058
    ],
    "zs:housing10":365,
    "zs:label":"Stillwater",
    "zs:pop10":1190
},
  "geometry": {"coordinates":[-104.85232499999999,39.914358],"type":"Point"}
}