{
  "type": "Feature",
  "properties": {
    "gn:admin1_code":"PA",
    "gn:admin2_code":"5.0",
    "gn:admin3_code":"59440.0",
    "gn:asciiname":"Millers Eddy",
    "gn:country_code":"US",
    "gn:dem":278,
    "gn:elevation":"270.0",
    "gn:feature_class":"P",
    "gn:feature_code":"PPL",
    "gn:name":"Millers Eddy",
    "gn:population":0,
    "gn:timezone":"America/New_York",
    "iso:country":"US",
    "name:eng_x_preferred":[
        "Millers Eddy"
    ],
    "name:und_x_variant":[
        "Monterey"
    ],
    "wof:name":"Millers Eddy",
    "wof:placetype":"locality"
},
  "geometry": {"coordinates":[-79.64255,41.03979],"type":"Point"}
}