{
  "type": "Feature",
  "properties": {
    "gn:admin1_code":"TN",
    "gn:admin2_code":"119",
    "gn:asciiname":"Forrest Hills",
    "gn:country_code":"US",
    "gn:dem":232,
    "gn:elevation":"224.0",
    "gn:feature_class":"P",
    "gn:feature_code":"PPL",
    "gn:name":"Forrest Hills",
    "gn:population":0,
    "gn:timezone":"America/Chicago",
    "iso:country":"US",
    "wof:name":"Forrest Hills",
    "wof:placetype":"locality"
},
  "geometry": {"coordinates":[-87.05362,35.62368],"type":"Point"}
}