{
  "type": "Feature",
  "properties": {
    "gn:admin1_code":"KY",
    "gn:admin2_code":"173",
    "gn:asciiname":"Prewitt",
    "gn:country_code":"US",
    "gn:dem":322,
    "gn:elevation":"320.0",
    "gn:feature_class":"P",
    "gn:feature_code":"PPL",
    "gn:name":"Prewitt",
    "gn:population":0,
    "gn:timezone":"America/New_York",
    "iso:country":"US",
    "wof:name":"Prewitt",
    "wof:placetype":"locality"
},
  "geometry": {"coordinates":[-83.98103,38.02813],"type":"Point"}
}