{
  "type": "Feature",
  "properties": {
    "gn:admin1_code":"SD",
    "gn:admin2_code":"89.0",
    "gn:admin3_code":"70400.0",
    "gn:asciiname":"Greenway",
    "gn:country_code":"US",
    "gn:dem":586,
    "gn:elevation":"589.0",
    "gn:feature_class":"P",
    "gn:feature_code":"PPL",
    "gn:name":"Greenway",
    "gn:population":0,
    "gn:timezone":"America/Chicago",
    "iso:country":"US",
    "name:deu_x_preferred":[
        "Greenway"
    ],
    "name:ita_x_preferred":[
        "Greenway"
    ],
    "name:nld_x_preferred":[
        "Greenway"
    ],
    "name:pol_x_preferred":[
        "Greenway"
    ],
    "name:por_x_preferred":[
        "Greenway"
    ],
    "name:rus_x_preferred":[
        "\u0413\u0440\u0438\u043d\u0443\u044d\u0439"
    ],
    "wof:name":"Greenway",
    "wof:placetype":"locality"
},
  "geometry": {"coordinates":[-99.71095,45.9097],"type":"Point"}
}