{
  "type": "Feature",
  "properties": {
    "gn:admin1_code":"TX",
    "gn:admin2_code":"223",
    "gn:asciiname":"Humble",
    "gn:country_code":"US",
    "gn:dem":158,
    "gn:elevation":"153.0",
    "gn:feature_class":"P",
    "gn:feature_code":"PPL",
    "gn:name":"Humble",
    "gn:population":0,
    "gn:timezone":"America/Chicago",
    "iso:country":"US",
    "name:ceb_x_preferred":[
        "Humble"
    ],
    "name:deu_x_preferred":[
        "Humble"
    ],
    "name:ita_x_preferred":[
        "Humble"
    ],
    "name:nld_x_preferred":[
        "Humble"
    ],
    "name:pol_x_preferred":[
        "Humble"
    ],
    "name:spa_x_preferred":[
        "Humble"
    ],
    "name:swe_x_preferred":[
        "Humble"
    ],
    "wof:name":"Humble",
    "wof:placetype":"locality"
},
  "geometry": {"coordinates":[-95.36745000000001,33.01679],"type":"Point"}
}