{
  "type": "Feature",
  "properties": {
    "gn:admin1_code":"MI",
    "gn:admin2_code":"139.0",
    "gn:admin3_code":"18800.0",
    "gn:asciiname":"Nunica",
    "gn:country_code":"US",
    "gn:dem":198,
    "gn:elevation":"192.0",
    "gn:feature_class":"P",
    "gn:feature_code":"PPL",
    "gn:name":"Nunica",
    "gn:population":0,
    "gn:timezone":"America/Detroit",
    "iso:country":"US",
    "wof:name":"Nunica",
    "wof:placetype":"locality"
},
  "geometry": {"coordinates":[-86.06726999999999,43.07974],"type":"Point"}
}