{
  "type": "Feature",
  "properties": {
    "gn:admin1_code":"VA",
    "gn:admin2_code":"153",
    "gn:asciiname":"Landview Estates",
    "gn:country_code":"US",
    "gn:dem":105,
    "gn:elevation":"98.0",
    "gn:feature_class":"P",
    "gn:feature_code":"PPL",
    "gn:name":"Landview Estates",
    "gn:population":0,
    "gn:timezone":"America/New_York",
    "iso:country":"US",
    "wof:name":"Landview Estates",
    "wof:placetype":"locality"
},
  "geometry": {"coordinates":[-77.44915,38.68067],"type":"Point"}
}