{
  "type": "Feature",
  "properties": {
    "gn:admin1_code":"KS",
    "gn:admin2_code":"207.0",
    "gn:admin3_code":"12250.0",
    "gn:asciiname":"Durand",
    "gn:country_code":"US",
    "gn:dem":304,
    "gn:elevation":"304.0",
    "gn:feature_class":"P",
    "gn:feature_code":"PPL",
    "gn:name":"Durand",
    "gn:population":0,
    "gn:timezone":"America/Chicago",
    "iso:country":"US",
    "name:fas_x_preferred":[
        "\u062f\u0648\u0631\u0627\u0646\u062f"
    ],
    "name:ind_x_preferred":[
        "Durand"
    ],
    "name:urd_x_preferred":[
        "\u0688\u0648\u0631\u06cc\u0646\u0688"
    ],
    "wof:name":"Durand",
    "wof:placetype":"locality"
},
  "geometry": {"coordinates":[-95.69304,37.88976],"type":"Point"}
}