{
  "type": "Feature",
  "properties": {
    "iso:country":"US",
    "name:eng_x_preferred":[
        "Davies"
    ],
    "wof:name":"Davies",
    "wof:placetype":"neighbourhood"
},
  "geometry": {"coordinates":[-96.81142109966494,46.78358030654625],"type":"Point"}
}