{
  "type": "Feature",
  "properties": {
    "gn:admin1_code":"AL",
    "gn:admin2_code":"21.0",
    "gn:asciiname":"Union Grove",
    "gn:country_code":"US",
    "gn:dem":234,
    "gn:elevation":"233.0",
    "gn:feature_class":"P",
    "gn:feature_code":"PPL",
    "gn:name":"Union Grove",
    "gn:population":0,
    "gn:timezone":"America/Chicago",
    "iso:country":"US",
    "name:ceb_x_preferred":[
        "Union Grove"
    ],
    "name:deu_x_preferred":[
        "Union Grove"
    ],
    "name:fra_x_preferred":[
        "Union Grove"
    ],
    "name:ita_x_preferred":[
        "Union Grove"
    ],
    "name:nld_x_preferred":[
        "Union Grove"
    ],
    "name:pol_x_preferred":[
        "Union Grove"
    ],
    "name:por_x_preferred":[
        "Union Grove"
    ],
    "name:srp_x_preferred":[
        "\u0408\u0443\u043d\u0438\u043e\u043d \u0413\u0440\u043e\u0443\u0432"
    ],
    "name:ukr_x_preferred":[
        "\u042e\u043d\u0456\u043e\u043d-\u0490\u0440\u043e\u0432"
    ],
    "name:vol_x_preferred":[
        "Union Grove"
    ],
    "wof:name":"Union Grove",
    "wof:placetype":"locality"
},
  "geometry": {"coordinates":[-86.68082,32.98262],"type":"Point"}
}