{
  "type": "Feature",
  "properties": {
    "gn:admin1_code":"AL",
    "gn:admin2_code":"23.0",
    "gn:asciiname":"Water Valley",
    "gn:country_code":"US",
    "gn:dem":37,
    "gn:elevation":"34.0",
    "gn:feature_class":"P",
    "gn:feature_code":"PPL",
    "gn:name":"Water Valley",
    "gn:population":0,
    "gn:timezone":"America/Chicago",
    "iso:country":"US",
    "name:ceb_x_preferred":[
        "Water Valley"
    ],
    "name:deu_x_preferred":[
        "Water Valley"
    ],
    "name:fra_x_preferred":[
        "Water Valley"
    ],
    "name:ita_x_preferred":[
        "Water Valley"
    ],
    "name:nld_x_preferred":[
        "Water Valley"
    ],
    "name:pol_x_preferred":[
        "Water Valley"
    ],
    "name:por_x_preferred":[
        "Water Valley"
    ],
    "name:spa_x_preferred":[
        "Water Valley"
    ],
    "name:srp_x_preferred":[
        "\u0412\u043e\u0442\u0435\u0440 \u0412\u0430\u043b\u0438"
    ],
    "name:swe_x_preferred":[
        "Water Valley"
    ],
    "name:vol_x_preferred":[
        "Water Valley"
    ],
    "wof:name":"Water Valley",
    "wof:placetype":"locality"
},
  "geometry": {"coordinates":[-88.39308,31.89404],"type":"Point"}
}