{
  "type": "Feature",
  "properties": {
    "gn:admin1_code":"NY",
    "gn:admin2_code":"1.0",
    "gn:admin3_code":"61181.0",
    "gn:asciiname":"Preston Hollow",
    "gn:country_code":"US",
    "gn:dem":263,
    "gn:elevation":"258.0",
    "gn:feature_class":"P",
    "gn:feature_code":"PPL",
    "gn:name":"Preston Hollow",
    "gn:population":0,
    "gn:timezone":"America/New_York",
    "iso:country":"US",
    "name:eng_x_preferred":[
        "Preston Hollow"
    ],
    "name:und_x_variant":[
        "Monclova"
    ],
    "wof:name":"Preston Hollow",
    "wof:placetype":"locality"
},
  "geometry": {"coordinates":[-74.20792,42.44452],"type":"Point"}
}