{
  "type": "Feature",
  "properties": {
    "gn:admin1_code":"AR",
    "gn:admin2_code":"39.0",
    "gn:admin3_code":"91860.0",
    "gn:asciiname":"Ramsey",
    "gn:country_code":"US",
    "gn:dem":94,
    "gn:elevation":"86.0",
    "gn:feature_class":"P",
    "gn:feature_code":"PPL",
    "gn:name":"Ramsey",
    "gn:population":0,
    "gn:timezone":"America/Chicago",
    "iso:country":"US",
    "name:cat_x_preferred":[
        "Ramsey"
    ],
    "name:ceb_x_preferred":[
        "Ramsey"
    ],
    "name:ces_x_preferred":[
        "Ramsey"
    ],
    "name:deu_x_preferred":[
        "Ramsey"
    ],
    "name:eus_x_preferred":[
        "Ramsey"
    ],
    "name:fas_x_preferred":[
        "\u0631\u0645\u0632\u06cc"
    ],
    "name:fin_x_preferred":[
        "Ramsey"
    ],
    "name:fra_x_preferred":[
        "Ramsey"
    ],
    "name:heb_x_preferred":[
        "\u05e8\u05de\u05d6\u05d9"
    ],
    "name:ita_x_preferred":[
        "Ramsey"
    ],
    "name:nds_x_preferred":[
        "Ramsey"
    ],
    "name:nld_x_preferred":[
        "Ramsey"
    ],
    "name:pol_x_preferred":[
        "Ramsey"
    ],
    "name:por_x_preferred":[
        "Ramsey"
    ],
    "name:rus_x_preferred":[
        "\u0420\u0430\u043c\u0437\u0430\u0439"
    ],
    "name:slk_x_preferred":[
        "Ramsey"
    ],
    "name:spa_x_preferred":[
        "Ramsey"
    ],
    "name:srp_x_preferred":[
        "\u0420\u0435\u043c\u0437\u0438"
    ],
    "name:swa_x_preferred":[
        "Ramsey"
    ],
    "name:swe_x_preferred":[
        "Ramsey"
    ],
    "name:ukr_x_preferred":[
        "\u0420\u0435\u043c\u0441\u0456"
    ],
    "name:urd_x_preferred":[
        "\u0631\u06cc\u0645\u0633\u06cc"
    ],
    "name:vol_x_preferred":[
        "Ramsey"
    ],
    "wof:name":"Ramsey",
    "wof:placetype":"locality"
},
  "geometry": {"coordinates":[-92.55377,33.87427],"type":"Point"}
}