{
  "type": "Feature",
  "properties": {
    "gn:admin1_code":"IL",
    "gn:admin2_code":"23.0",
    "gn:admin3_code":"83934.0",
    "gn:asciiname":"Walnut Prairie",
    "gn:country_code":"US",
    "gn:dem":148,
    "gn:elevation":"147.0",
    "gn:feature_class":"P",
    "gn:feature_code":"PPL",
    "gn:name":"Walnut Prairie",
    "gn:population":0,
    "gn:timezone":"America/Chicago",
    "iso:country":"US",
    "wof:name":"Walnut Prairie",
    "wof:placetype":"locality"
},
  "geometry": {"coordinates":[-87.66614,39.24004],"type":"Point"}
}