{
  "type": "Feature",
  "properties": {
    "iso:country":"US",
    "name:deu_x_preferred":[
        "Brookview"
    ],
    "name:eng_x_preferred":[
        "Brookview"
    ],
    "qs:gn_adm0_cc":"US",
    "qs:gn_local":5393485,
    "qs:gn_nam_loc":"Saratoga, Santa Clara, California, US",
    "qs:gn_namadm1":"CA",
    "qs:local_max":2497,
    "qs:local_sum":5809,
    "qs:localhoods":10,
    "qs:name":"Brookview",
    "qs:name_adm0":"United States",
    "qs:name_adm1":"California",
    "qs:name_adm2":"Santa Clara",
    "qs:name_local":"Saratoga",
    "qs:photo_max":28,
    "qs:photo_sum":28,
    "qs:placetype":"Suburb",
    "qs:quad_count":1,
    "qs:woe_adm0":23424977,
    "qs:woe_adm1":2347563,
    "qs:woe_adm2":12587712,
    "qs:woe_lau":0,
    "qs:woe_local":2489047,
    "qs:woe_ver":"7.10.0",
    "wd:wordcount":12,
    "wof:name":"Brookview",
    "wof:placetype":"neighbourhood",
    "wof:population":2461,
    "zs:blockids":[
        60855079042020,
        60855074013007,
        60855074015005,
        60855074014013,
        60855074014004,
        60855074014003,
        60855074014001,
        60855074013011,
        60855074013017,
        60855074013016,
        60855074015006,
        60855074015002,
        60855074014010,
        60855074013012,
        60855074015013,
        60855079042016,
        60855074015007,
        60855074014008,
        60855074014005,
        60855074013013,
        60855074013020,
        60855074015003,
        60855074014011,
        60855074014000,
        60855074014007,
        60855074013019,
        60855079042015,
        60855074014002,
        60855074015008,
        60855074013018,
        60855074015014,
        60855074014014,
        60855074014009,
        60855074013008,
        60855074013015,
        60855074014006,
        60855074015011,
        60855074015001,
        60855074012012,
        60855074013021,
        60855074013006,
        60855074015012,
        60855074014015,
        60855074014012,
        60855074013010,
        60855074015009
    ],
    "zs:housing10":877,
    "zs:pop10":2461
},
  "geometry": {"coordinates":[-122.010727,37.29208],"type":"Point"}
}