{
  "type": "Feature",
  "properties": {
    "gn:admin1_code":"VA",
    "gn:admin2_code":"85",
    "gn:asciiname":"Teman",
    "gn:country_code":"US",
    "gn:dem":87,
    "gn:elevation":"89.0",
    "gn:feature_class":"P",
    "gn:feature_code":"PPL",
    "gn:name":"Teman",
    "gn:population":0,
    "gn:timezone":"America/New_York",
    "iso:country":"US",
    "name:ceb_x_preferred":[
        "Teman"
    ],
    "name:heb_x_preferred":[
        "\u05ea\u05d9\u05de\u05df"
    ],
    "name:swe_x_preferred":[
        "Teman"
    ],
    "wof:name":"Teman",
    "wof:placetype":"locality"
},
  "geometry": {"coordinates":[-77.62860000000001,37.93708],"type":"Point"}
}