{
  "type": "Feature",
  "properties": {
    "gn:admin1_code":"WV",
    "gn:admin2_code":"39.0",
    "gn:asciiname":"Rensford",
    "gn:country_code":"US",
    "gn:dem":259,
    "gn:elevation":"234.0",
    "gn:feature_class":"P",
    "gn:feature_code":"PPL",
    "gn:name":"Rensford",
    "gn:population":0,
    "gn:timezone":"America/New_York",
    "iso:country":"US",
    "name:eng_x_preferred":[
        "Rensford"
    ],
    "name:und_x_variant":[
        "Point Lick"
    ],
    "wof:name":"Rensford",
    "wof:placetype":"locality"
},
  "geometry": {"coordinates":[-81.48095000000001,38.31399],"type":"Point"}
}