{
  "type": "Feature",
  "properties": {
    "gn:admin1_code":"HI",
    "gn:admin2_code":"3.0",
    "gn:asciiname":"Sisal",
    "gn:country_code":"US",
    "gn:dem":26,
    "gn:elevation":"19.0",
    "gn:feature_class":"P",
    "gn:feature_code":"PPL",
    "gn:name":"Sisal",
    "gn:population":0,
    "gn:timezone":"Pacific/Honolulu",
    "iso:country":"US",
    "name:afr_x_preferred":[
        "Garingboom"
    ],
    "name:ara_x_preferred":[
        "\u0623\u063a\u0627\u0641 \u0633\u064a\u0632\u0627\u0644"
    ],
    "name:aze_x_preferred":[
        "Sizal aqavas\u0131"
    ],
    "name:bcl_x_preferred":[
        "Sisal"
    ],
    "name:ben_x_preferred":[
        "\u09b8\u09bf\u09b8\u09be\u09b2"
    ],
    "name:bul_x_preferred":[
        "\u0421\u0438\u0437\u0430\u043b"
    ],
    "name:cat_x_preferred":[
        "Sisal"
    ],
    "name:ceb_x_preferred":[
        "Agave sisalana"
    ],
    "name:ces_x_preferred":[
        "Ag\u00e1ve sisalov\u00e1"
    ],
    "name:dan_x_preferred":[
        "Sisal"
    ],
    "name:deu_x_preferred":[
        "Sisal-Agave"
    ],
    "name:epo_x_preferred":[
        "Sisalo"
    ],
    "name:eus_x_preferred":[
        "Sisal"
    ],
    "name:fas_x_preferred":[
        "\u0633\u06cc\u0633\u0627\u0644"
    ],
    "name:fin_x_preferred":[
        "Sisalagaave"
    ],
    "name:fra_x_preferred":[
        "Agave sisalana"
    ],
    "name:hat_x_preferred":[
        "Pit"
    ],
    "name:heb_x_preferred":[
        "\u05e1\u05d9\u05d6\u05d0\u05dc"
    ],
    "name:hrv_x_preferred":[
        "Sisal"
    ],
    "name:hsb_x_preferred":[
        "Zizalowc"
    ],
    "name:ind_x_preferred":[
        "Agave sisalana"
    ],
    "name:isl_x_preferred":[
        "S\u00edsallilja"
    ],
    "name:ita_x_preferred":[
        "Agave sisalana"
    ],
    "name:jpn_x_preferred":[
        "\u30b5\u30a4\u30b6\u30eb\u30a2\u30b5"
    ],
    "name:lit_x_preferred":[
        "Sizalin\u0117 agava"
    ],
    "name:mal_x_preferred":[
        "\u0d38\u0d48\u0d38\u0d7d"
    ],
    "name:nah_x_preferred":[
        "Nequ\u0113nnetl"
    ],
    "name:nld_x_preferred":[
        "Sisal"
    ],
    "name:nor_x_preferred":[
        "Sisal"
    ],
    "name:pol_x_preferred":[
        "Agawa sizalowa"
    ],
    "name:por_x_preferred":[
        "Sisal"
    ],
    "name:que_x_preferred":[
        "Sisal"
    ],
    "name:ron_x_preferred":[
        "Sisal"
    ],
    "name:rus_x_preferred":[
        "\u0421\u0438\u0437\u0430\u043b\u044c"
    ],
    "name:slk_x_preferred":[
        "Sisal"
    ],
    "name:sna_x_preferred":[
        "Gonje"
    ],
    "name:spa_x_preferred":[
        "Agave sisalana"
    ],
    "name:swa_x_preferred":[
        "Mkonge Dume"
    ],
    "name:swe_x_preferred":[
        "Sisal"
    ],
    "name:tam_x_preferred":[
        "\u0b95\u0ba4\u0bb2\u0bc8"
    ],
    "name:tur_x_preferred":[
        "Sisal"
    ],
    "name:ukr_x_preferred":[
        "\u0410\u0433\u0430\u0432\u0430 \u0441\u0438\u0437\u0430\u043b\u044c\u0441\u044c\u043a\u0430"
    ],
    "name:vie_x_preferred":[
        "Th\u00f9a s\u1ee3i"
    ],
    "name:war_x_preferred":[
        "Agave sisalana"
    ],
    "wof:name":"Sisal",
    "wof:placetype":"locality"
},
  "geometry": {"coordinates":[-158.06666999999999,21.33333],"type":"Point"}
}