{
  "type": "Feature",
  "properties": {
    "gn:admin1_code":"LA",
    "gn:admin2_code":"1.0",
    "gn:asciiname":"Hundley",
    "gn:country_code":"US",
    "gn:dem":14,
    "gn:elevation":"11.0",
    "gn:feature_class":"P",
    "gn:feature_code":"PPL",
    "gn:name":"Hundley",
    "gn:population":0,
    "gn:timezone":"America/Chicago",
    "iso:country":"US",
    "name:rus_x_preferred":[
        "\u0425\u0430\u043d\u0434\u043b\u0438"
    ],
    "wof:name":"Hundley",
    "wof:placetype":"locality"
},
  "geometry": {"coordinates":[-92.36624,30.44103],"type":"Point"}
}