{
  "type": "Feature",
  "properties": {
    "gn:admin1_code":"KY",
    "gn:admin2_code":"13",
    "gn:asciiname":"Capito",
    "gn:country_code":"US",
    "gn:dem":535,
    "gn:elevation":"533.0",
    "gn:feature_class":"P",
    "gn:feature_code":"PPL",
    "gn:name":"Capito",
    "gn:population":0,
    "gn:timezone":"America/New_York",
    "iso:country":"US",
    "name:ara_x_preferred":[
        "\u0628\u0631\u0628\u064a\u062a"
    ],
    "name:bre_x_preferred":[
        "Capito"
    ],
    "name:cat_x_preferred":[
        "Capito"
    ],
    "name:ceb_x_preferred":[
        "Capito"
    ],
    "name:deu_x_preferred":[
        "Buntb\u00e4rtlinge"
    ],
    "name:epo_x_preferred":[
        "Kapitoj"
    ],
    "name:fin_x_preferred":[
        "Kruunusep\u00e4t"
    ],
    "name:fra_x_preferred":[
        "Capito"
    ],
    "name:hun_x_preferred":[
        "Capito"
    ],
    "name:nld_x_preferred":[
        "Capito"
    ],
    "name:pol_x_preferred":[
        "Capito"
    ],
    "name:por_x_preferred":[
        "Capito"
    ],
    "name:spa_x_preferred":[
        "Capito"
    ],
    "name:swe_x_preferred":[
        "Capito"
    ],
    "name:vie_x_preferred":[
        "Capito"
    ],
    "name:war_x_preferred":[
        "Capito"
    ],
    "wof:name":"Capito",
    "wof:placetype":"locality"
},
  "geometry": {"coordinates":[-83.83048000000002,36.61425],"type":"Point"}
}