{
  "type": "Feature",
  "properties": {
    "gn:admin1_code":"NY",
    "gn:admin2_code":"65",
    "gn:admin3_code":"75280.0",
    "gn:asciiname":"Mapledale Acres",
    "gn:country_code":"US",
    "gn:dem":244,
    "gn:elevation":"243.0",
    "gn:feature_class":"P",
    "gn:feature_code":"PPL",
    "gn:name":"Mapledale Acres",
    "gn:population":0,
    "gn:timezone":"America/New_York",
    "iso:country":"US",
    "wof:name":"Mapledale Acres",
    "wof:placetype":"locality"
},
  "geometry": {"coordinates":[-75.19028,43.25194000000001],"type":"Point"}
}