{
  "type": "Feature",
  "properties": {
    "iso:country":"US",
    "name:eng_x_preferred":[
        "South Westville"
    ],
    "wof:name":"South Westville",
    "wof:placetype":"neighbourhood",
    "wof:population":1884,
    "zs:area_m":1090972.925895,
    "zs:blockids":[
        340155001003013,
        340155001002005,
        340155001004015,
        340155001004020,
        340155001004013,
        340155001004019,
        340155001003006,
        340155001003002,
        340155001002015,
        340155002011043,
        340155001004023,
        340155011011000,
        340155011011002,
        340155001004024,
        340155001003003,
        340155001004009,
        340155001003009,
        340155001002014,
        340155001004017,
        340155001003015,
        340155001004012,
        340155001004022,
        340155001002013,
        340155011011003,
        340155001003008,
        340155001003010,
        340155001003007,
        340155001004010,
        340155001002002,
        340155002011004,
        340155002011044,
        340155001004016,
        340155001004008,
        340155001003012,
        340155001002004,
        340155011011001,
        340155001004014,
        340155001004025,
        340155001004021,
        340155001003011,
        340155001004011,
        340155001004018
    ],
    "zs:housing10":862,
    "zs:label":"South Westville",
    "zs:pop10":1884
},
  "geometry": {"coordinates":[-75.13676599999999,39.863892],"type":"Point"}
}