{
  "type": "Feature",
  "properties": {
    "gn:admin1_code":"SC",
    "gn:admin2_code":"35.0",
    "gn:asciiname":"Ashley Retreat",
    "gn:country_code":"US",
    "gn:dem":13,
    "gn:elevation":"9.0",
    "gn:feature_class":"P",
    "gn:feature_code":"PPL",
    "gn:name":"Ashley Retreat",
    "gn:population":0,
    "gn:timezone":"America/New_York",
    "iso:country":"US",
    "wof:name":"Ashley Retreat",
    "wof:placetype":"locality"
},
  "geometry": {"coordinates":[-80.24509999999999,32.96628],"type":"Point"}
}