{
  "type": "Feature",
  "properties": {
    "gn:admin1_code":"CA",
    "gn:admin2_code":"107",
    "gn:asciiname":"East Farmersville",
    "gn:country_code":"US",
    "gn:dem":114,
    "gn:elevation":"110.0",
    "gn:feature_class":"P",
    "gn:feature_code":"PPL",
    "gn:name":"East Farmersville",
    "gn:population":0,
    "gn:timezone":"America/Los_Angeles",
    "iso:country":"US",
    "wof:name":"East Farmersville",
    "wof:placetype":"locality"
},
  "geometry": {"coordinates":[-119.19483,36.30162],"type":"Point"}
}