{
  "type": "Feature",
  "properties": {
    "gn:admin1_code":"GA",
    "gn:admin2_code":"293.0",
    "gn:asciiname":"Logtown",
    "gn:country_code":"US",
    "gn:dem":208,
    "gn:elevation":"206.0",
    "gn:feature_class":"P",
    "gn:feature_code":"PPL",
    "gn:name":"Logtown",
    "gn:population":0,
    "gn:timezone":"America/New_York",
    "iso:country":"US",
    "name:deu_x_preferred":[
        "Logtown"
    ],
    "wof:name":"Logtown",
    "wof:placetype":"locality"
},
  "geometry": {"coordinates":[-84.18853,32.85041],"type":"Point"}
}