{
  "type": "Feature",
  "properties": {
    "iso:country":"US",
    "name:ara_x_preferred":[
        "\u062d\u0646\u0637\u0648\u0631"
    ],
    "name:eng_x_preferred":[
        "Horse and Carriage"
    ],
    "name:eng_x_variant":[
        "horse and buggy"
    ],
    "name:fas_x_preferred":[
        "\u062f\u0631\u0634\u06a9\u0647"
    ],
    "name:fra_x_preferred":[
        "Boquet"
    ],
    "name:fra_x_variant":[
        "boquet"
    ],
    "name:fry_x_preferred":[
        "Hynder en wein"
    ],
    "name:fry_x_variant":[
        "Kategory:Hynder en wein"
    ],
    "name:jpn_x_preferred":[
        "\u30d0\u30ae\u30fc"
    ],
    "name:nld_x_preferred":[
        "Paard en wagen"
    ],
    "name:nld_x_variant":[
        "buggy"
    ],
    "name:pnb_x_preferred":[
        "\u06af\u06be\u0648\u0691\u0627 \u0628\u06af\u06be\u06cc"
    ],
    "name:por_x_preferred":[
        "Buggy"
    ],
    "name:por_x_variant":[
        "buggy"
    ],
    "name:zho_x_preferred":[
        "\u8f15\u4fbf\u99ac\u8eca"
    ],
    "qs:gn_adm0_cc":"US",
    "qs:gn_local":4297983,
    "qs:gn_nam_loc":"Lexington, Fayette, Kentucky, US",
    "qs:gn_namadm1":"KY",
    "qs:local_max":4034,
    "qs:local_sum":30708,
    "qs:localhoods":91,
    "qs:name":"Horse and Carriage",
    "qs:name_adm0":"United States",
    "qs:name_adm1":"Kentucky",
    "qs:name_adm2":"Fayette",
    "qs:name_local":"Lexington",
    "qs:photo_max":55,
    "qs:photo_sum":99,
    "qs:placetype":"Suburb",
    "qs:quad_count":4,
    "qs:woe_adm0":23424977,
    "qs:woe_adm1":2347576,
    "qs:woe_adm2":12588509,
    "qs:woe_lau":0,
    "qs:woe_local":2438841,
    "qs:woe_ver":"7.10.0",
    "wd:wordcount":647,
    "wof:lang":[
        "eng"
    ],
    "wof:name":"Horse and Carriage",
    "wof:placetype":"neighbourhood",
    "wof:population":5041,
    "zs:blockids":[
        210670019002000,
        210670019002001,
        210670020013015,
        210670019002005,
        210670019002003,
        210670019002014,
        210670009002011,
        210670019001003,
        210670019002004,
        210670009002006,
        210670019001004,
        210670009002005,
        210670019001002,
        210670019001000,
        210670020013011,
        210670009002004
    ],
    "zs:housing10":2285,
    "zs:pop10":5041
},
  "geometry": {"coordinates":[-84.51988799999999,38.041349],"type":"Point"}
}