{
  "type": "Feature",
  "properties": {
    "iso:country":"US",
    "name:cat_x_preferred":[
        "Bagdad"
    ],
    "name:ceb_x_preferred":[
        "Bagdad"
    ],
    "name:deu_x_preferred":[
        "Bagdad"
    ],
    "name:eng_x_preferred":[
        "Bagdad"
    ],
    "name:fra_x_preferred":[
        "Bagdad"
    ],
    "name:hun_x_preferred":[
        "Bagdad"
    ],
    "name:nep_x_preferred":[
        "\u092c\u0917\u0926\u093e\u0926"
    ],
    "name:nld_x_preferred":[
        "Bagdad"
    ],
    "name:pol_x_preferred":[
        "Bagdad"
    ],
    "name:ron_x_preferred":[
        "Bagdad"
    ],
    "name:slv_x_preferred":[
        "Bagdad"
    ],
    "name:spa_x_preferred":[
        "Bagdad"
    ],
    "name:srp_x_preferred":[
        "\u0411\u0430\u0433\u0434\u0430\u0434"
    ],
    "name:swe_x_preferred":[
        "Bagdad"
    ],
    "name:vol_x_preferred":[
        "Bagdad"
    ],
    "wd:wordcount":95,
    "wof:name":"Bagdad",
    "wof:placetype":"neighbourhood",
    "wof:population":1260,
    "zs:blockids":[
        420059513002030,
        420059513002020,
        420059513003002,
        420059513002035,
        420059513003005,
        420059513003006,
        420059513002031,
        420059513003003,
        420059513003007,
        420059513002033,
        420059513003004,
        421298012003001,
        421298012001010,
        421298013001007,
        421298013001002,
        421298013001003,
        421298013001008,
        421298013001020,
        421298012001013,
        421298012001014,
        421298012001008,
        421298013001004,
        421298012001012,
        421298012003003,
        421298013001000,
        421298012001009
    ],
    "zs:housing10":566,
    "zs:label":"Bagdad",
    "zs:pop10":1260
},
  "geometry": {"coordinates":[-79.652871,40.64689],"type":"Point"}
}