{
  "type": "Feature",
  "properties": {
    "gn:admin1_code":"AZ",
    "gn:admin2_code":"7.0",
    "gn:asciiname":"Oak Park Mobile Home Park",
    "gn:country_code":"US",
    "gn:dem":1521,
    "gn:elevation":"1525.0",
    "gn:feature_class":"P",
    "gn:feature_code":"PPL",
    "gn:name":"Oak Park Mobile Home Park",
    "gn:population":0,
    "gn:timezone":"America/Phoenix",
    "iso:country":"US",
    "wof:name":"Oak Park Mobile Home Park",
    "wof:placetype":"campus"
},
  "geometry": {"coordinates":[-111.32398999999999,34.25841],"type":"Point"}
}