{
  "type": "Feature",
  "properties": {
    "gn:admin1_code":"AZ",
    "gn:admin2_code":"15.0",
    "gn:asciiname":"Catfish Paradise",
    "gn:country_code":"US",
    "gn:dem":147,
    "gn:elevation":"146.0",
    "gn:feature_class":"P",
    "gn:feature_code":"PPL",
    "gn:name":"Catfish Paradise",
    "gn:population":0,
    "gn:timezone":"America/Phoenix",
    "iso:country":"US",
    "wof:name":"Catfish Paradise",
    "wof:placetype":"locality"
},
  "geometry": {"coordinates":[-114.48746,34.74501],"type":"Point"}
}