{
  "type": "Feature",
  "properties": {
    "gn:admin1_code":"GA",
    "gn:admin2_code":"57.0",
    "gn:asciiname":"Ashley Forest",
    "gn:country_code":"US",
    "gn:dem":314,
    "gn:elevation":"307.0",
    "gn:feature_class":"P",
    "gn:feature_code":"PPL",
    "gn:name":"Ashley Forest",
    "gn:population":0,
    "gn:timezone":"America/New_York",
    "iso:country":"US",
    "wof:name":"Ashley Forest",
    "wof:placetype":"locality"
},
  "geometry": {"coordinates":[-84.57021,34.07649],"type":"Point"}
}