{
  "type": "Feature",
  "properties": {
    "gn:admin1_code":"TX",
    "gn:admin2_code":"335.0",
    "gn:asciiname":"Valley View",
    "gn:country_code":"US",
    "gn:dem":680,
    "gn:elevation":"680.0",
    "gn:feature_class":"P",
    "gn:feature_code":"PPL",
    "gn:name":"Valley View",
    "gn:population":0,
    "gn:timezone":"America/Chicago",
    "iso:country":"US",
    "name:cat_x_preferred":[
        "Valley View"
    ],
    "name:ceb_x_preferred":[
        "Valley View"
    ],
    "name:deu_x_preferred":[
        "Valley View"
    ],
    "name:ita_x_preferred":[
        "Valley View"
    ],
    "name:nld_x_preferred":[
        "Valley View"
    ],
    "name:pol_x_preferred":[
        "Valley View"
    ],
    "name:por_x_preferred":[
        "Valley View"
    ],
    "name:spa_x_preferred":[
        "Valley View"
    ],
    "name:srp_x_preferred":[
        "\u0412\u0430\u043b\u0438 \u0412\u0458\u0443"
    ],
    "name:vol_x_preferred":[
        "Valley View"
    ],
    "wof:name":"Valley View",
    "wof:placetype":"locality"
},
  "geometry": {"coordinates":[-100.77594999999999,32.494],"type":"Point"}
}