{
  "type": "Feature",
  "properties": {
    "gn:admin1_code":"GA",
    "gn:admin2_code":"99",
    "gn:asciiname":"Saffold",
    "gn:country_code":"US",
    "gn:dem":54,
    "gn:elevation":"48.0",
    "gn:feature_class":"P",
    "gn:feature_code":"PPL",
    "gn:name":"Saffold",
    "gn:population":0,
    "gn:timezone":"America/New_York",
    "iso:country":"US",
    "wof:name":"Saffold",
    "wof:placetype":"locality"
},
  "geometry": {"coordinates":[-85.03326,31.12018],"type":"Point"}
}