{
  "type": "Feature",
  "properties": {
    "gn:admin1_code":"NY",
    "gn:admin2_code":"91.0",
    "gn:admin3_code":"65255.0",
    "gn:asciiname":"Louden Meadows",
    "gn:country_code":"US",
    "gn:dem":95,
    "gn:elevation":"82.0",
    "gn:feature_class":"P",
    "gn:feature_code":"PPL",
    "gn:name":"Louden Meadows",
    "gn:population":0,
    "gn:timezone":"America/New_York",
    "iso:country":"US",
    "wof:name":"Louden Meadows",
    "wof:placetype":"locality"
},
  "geometry": {"coordinates":[-73.73194000000002,43.09639],"type":"Point"}
}