{
  "type": "Feature",
  "properties": {
    "gn:admin1_code":"IL",
    "gn:admin2_code":"177.0",
    "gn:admin3_code":"64057.0",
    "gn:asciiname":"Ridott Corners",
    "gn:country_code":"US",
    "gn:dem":257,
    "gn:elevation":"256.0",
    "gn:feature_class":"P",
    "gn:feature_code":"PPL",
    "gn:name":"Ridott Corners",
    "gn:population":0,
    "gn:timezone":"America/Chicago",
    "iso:country":"US",
    "wof:name":"Ridott Corners",
    "wof:placetype":"locality"
},
  "geometry": {"coordinates":[-89.47566999999999,42.2753],"type":"Point"}
}