{
  "type": "Feature",
  "properties": {
    "gn:admin1_code":"MD",
    "gn:admin2_code":"3.0",
    "gn:asciiname":"Brandy Farms",
    "gn:country_code":"US",
    "gn:dem":40,
    "gn:elevation":"42.0",
    "gn:feature_class":"P",
    "gn:feature_code":"PPL",
    "gn:name":"Brandy Farms",
    "gn:population":0,
    "gn:timezone":"America/New_York",
    "iso:country":"US",
    "wof:name":"Brandy Farms",
    "wof:placetype":"locality"
},
  "geometry": {"coordinates":[-76.66274,39.04261],"type":"Point"}
}