{
  "type": "Feature",
  "properties": {
    "gn:country":"US",
    "gn:fcode":"PPL",
    "gn:population":0,
    "iso:country":"US",
    "name:bug_x_preferred":[
        "Exermont"
    ],
    "name:cat_x_preferred":[
        "Exermont"
    ],
    "name:ceb_x_preferred":[
        "Exermont"
    ],
    "name:ces_x_preferred":[
        "Exermont"
    ],
    "name:deu_x_preferred":[
        "Exermont"
    ],
    "name:eus_x_preferred":[
        "Exermont"
    ],
    "name:fra_x_preferred":[
        "Exermont"
    ],
    "name:hun_x_preferred":[
        "Exermont"
    ],
    "name:hye_x_preferred":[
        "\u0537\u0584\u057d\u0565\u0580\u0574\u0578\u0576"
    ],
    "name:ita_x_preferred":[
        "Exermont"
    ],
    "name:lat_x_preferred":[
        "Exermont"
    ],
    "name:ltz_x_preferred":[
        "Exermont"
    ],
    "name:mlg_x_preferred":[
        "Exermont"
    ],
    "name:msa_x_preferred":[
        "Exermont"
    ],
    "name:nld_x_preferred":[
        "Exermont"
    ],
    "name:oci_x_preferred":[
        "Exermont"
    ],
    "name:pms_x_preferred":[
        "Exermont"
    ],
    "name:pol_x_preferred":[
        "Exermont"
    ],
    "name:por_x_preferred":[
        "Exermont"
    ],
    "name:ron_x_preferred":[
        "Exermont"
    ],
    "name:rus_x_preferred":[
        "\u042d\u043a\u0441\u0435\u0440\u043c\u043e\u043d"
    ],
    "name:slk_x_preferred":[
        "Exermont"
    ],
    "name:spa_x_preferred":[
        "Exermont"
    ],
    "name:sqi_x_preferred":[
        "Exermont"
    ],
    "name:srp_x_preferred":[
        "\u0415\u043a\u0441\u0435\u0440\u043c\u043e\u043d"
    ],
    "name:swe_x_preferred":[
        "Exermont"
    ],
    "name:ukr_x_preferred":[
        "\u0415\u043a\u0441\u0435\u0440\u043c\u043e\u043d"
    ],
    "name:vie_x_preferred":[
        "Exermont"
    ],
    "name:vol_x_preferred":[
        "Exermont"
    ],
    "name:war_x_preferred":[
        "Exermont"
    ],
    "name:zho_x_preferred":[
        "\u57c3\u514b\u585e\u5c14\u8499"
    ],
    "qs_pg:aaroncc":"US",
    "qs_pg:gn_country":"US",
    "qs_pg:gn_fcode":"PPL",
    "qs_pg:gn_pop":0,
    "qs_pg:name":"Exermont",
    "qs_pg:name_adm0":"United States",
    "qs_pg:name_adm1":"Illinois",
    "qs_pg:photos":8,
    "qs_pg:photos_1k":2,
    "qs_pg:photos_9k":1,
    "qs_pg:photos_9r":1,
    "qs_pg:photos_all":8,
    "qs_pg:photos_sr":1,
    "qs_pg:pop_sr":0,
    "qs_pg:qs_pg_placetype":"locality",
    "qs_pg:qs_pg_placetype_gp":"Town",
    "qs_pg:woe_adm0":23424977,
    "woe:adm0_id":23424977,
    "woe:name_adm0":"United States",
    "woe:name_adm1":"Illinois",
    "woe:placetype":"Town",
    "wof:name":"Exermont",
    "wof:placetype":"locality"
},
  "geometry": {"coordinates":[-90.04649000000001,38.64783],"type":"Point"}
}