{
  "type": "Feature",
  "properties": {
    "gn:admin1_code":"GA",
    "gn:admin2_code":"115.0",
    "gn:asciiname":"Boozeville",
    "gn:country_code":"US",
    "gn:dem":213,
    "gn:elevation":"211.0",
    "gn:feature_class":"P",
    "gn:feature_code":"PPL",
    "gn:name":"Boozeville",
    "gn:population":0,
    "gn:timezone":"America/New_York",
    "iso:country":"US",
    "name:eng_x_preferred":[
        "Boozeville"
    ],
    "name:und_x_variant":[
        "Booger Hollow"
    ],
    "wof:name":"Boozeville",
    "wof:placetype":"locality"
},
  "geometry": {"coordinates":[-85.17523,34.17148],"type":"Point"}
}