{
  "type": "Feature",
  "properties": {
    "gn:country":"US",
    "gn:fcode":"PPL",
    "gn:population":0,
    "iso:country":"US",
    "name:eng_x_preferred":[
        "Campville"
    ],
    "name:und_x_variant":[
        "Wolcottville"
    ],
    "qs_pg:aaroncc":"US",
    "qs_pg:gn_country":"US",
    "qs_pg:gn_fcode":"PPL",
    "qs_pg:gn_pop":0,
    "qs_pg:name":"Campville",
    "qs_pg:name_adm0":"United States",
    "qs_pg:name_adm1":"Connecticut",
    "qs_pg:photos":1,
    "qs_pg:photos_1k":1,
    "qs_pg:photos_9k":1,
    "qs_pg:photos_9r":1,
    "qs_pg:photos_all":1,
    "qs_pg:photos_sr":1,
    "qs_pg:pop_sr":0,
    "qs_pg:qs_pg_placetype":"neighbourhood",
    "qs_pg:qs_pg_placetype_gp":"Suburb",
    "qs_pg:woe_adm0":23424977,
    "wof:name":"Campville",
    "wof:placetype":"neighbourhood",
    "wof:population":101,
    "zs:area_m":2216839.370522,
    "zs:blockids":[
        90052984001025,
        90052984001043,
        90052984001044,
        90052984001024,
        90052984001042
    ],
    "zs:housing10":41,
    "zs:label":"Campville",
    "zs:pop10":101
},
  "geometry": {"coordinates":[-73.09298,41.734708],"type":"Point"}
}