{
  "type": "Feature",
  "properties": {
    "gn:elevation":10,
    "iso:country":"US",
    "name:eng_x_preferred":[
        "Highlands"
    ],
    "qs:gn_adm0_cc":"US",
    "qs:gn_fcode":"PPLX",
    "qs:gn_local":4588718,
    "qs:gn_nam_loc":"Myrtle Beach, Horry, South Carolina, US",
    "qs:gn_namadm1":"SC",
    "qs:gn_name":"Highlands",
    "qs:local_max":9308,
    "qs:local_sum":20973,
    "qs:localhoods":17,
    "qs:name":"Highlands",
    "qs:name_adm0":"United States",
    "qs:name_adm1":"South Carolina",
    "qs:name_adm2":"Horry",
    "qs:name_local":"Myrtle Beach",
    "qs:photo_max":175,
    "qs:photo_sum":525,
    "qs:placetype":"Suburb",
    "qs:quad_count":19,
    "qs:woe_adm0":23424977,
    "qs:woe_adm1":2347599,
    "qs:woe_adm2":12589825,
    "qs:woe_lau":0,
    "qs:woe_local":2456750,
    "qs:woe_ver":"7.10.0",
    "wof:lang":[
        "eng"
    ],
    "wof:name":"Highlands",
    "wof:placetype":"neighbourhood",
    "wof:population":1675,
    "zs:blockids":[
        450510504022014,
        450510504022027,
        450510504012015,
        450510504012003,
        450510504012011,
        450510504021004,
        450510504012034,
        450510504012010,
        450510504022022,
        450510504012005,
        450510504011008,
        450510504012006,
        450510504012012,
        450510504012013,
        450510504021017,
        450510504021019,
        450510504022016,
        450510504012008,
        450510504022010,
        450510504012032,
        450510504022023,
        450510504022011,
        450510504012021,
        450510504022001,
        450510504012014,
        450510504012029,
        450510504012020,
        450510504012033,
        450510504012031,
        450510504022039,
        450510504022013,
        450510504011017,
        450510504022015,
        450510504022019,
        450510504011015,
        450510504022021,
        450510504022003,
        450510504012007,
        450510504012022,
        450510504022012,
        450510504021001,
        450510504022002,
        450510504022000,
        450510504021006,
        450510504021018,
        450510504022018,
        450510504022004,
        450510504022020,
        450510504022017,
        450510504012009,
        450510504012023,
        450510504012030,
        450510504021002,
        450510504022040,
        450510504022006,
        450510504012004
    ],
    "zs:housing10":1564,
    "zs:pop10":1675
},
  "geometry": {"coordinates":[-78.83327800000001,33.732115],"type":"Point"}
}