{
  "type": "Feature",
  "properties": {
    "gn:admin1_code":"AL",
    "gn:admin2_code":"73",
    "gn:asciiname":"Cherokee Brook Estates",
    "gn:country_code":"US",
    "gn:dem":304,
    "gn:elevation":"300.0",
    "gn:feature_class":"P",
    "gn:feature_code":"PPL",
    "gn:name":"Cherokee Brook Estates",
    "gn:population":0,
    "gn:timezone":"America/Chicago",
    "iso:country":"US",
    "wof:name":"Cherokee Brook Estates",
    "wof:placetype":"locality"
},
  "geometry": {"coordinates":[-86.68777,33.52677],"type":"Point"}
}