{
  "type": "Feature",
  "properties": {
    "iso:country":"US",
    "name:ara_x_preferred":[
        "\u0641\u064a\u0644\u0627 \u062f\u064a\u0644 \u0631\u064a"
    ],
    "name:cat_x_preferred":[
        "Villa del Rey"
    ],
    "name:ceb_x_preferred":[
        "Villa del Rey"
    ],
    "name:eng_x_preferred":[
        "Villa del Rey"
    ],
    "name:epo_x_preferred":[
        "Villa del Rey"
    ],
    "name:eus_x_preferred":[
        "Villa del Rey"
    ],
    "name:fra_x_preferred":[
        "Villa del Rey"
    ],
    "name:hun_x_preferred":[
        "Villa del Rey"
    ],
    "name:ina_x_preferred":[
        "Villa del Rey"
    ],
    "name:ita_x_preferred":[
        "Villa del Rey"
    ],
    "name:msa_x_preferred":[
        "Villa del Rey"
    ],
    "name:nld_x_preferred":[
        "Villa del Rey"
    ],
    "name:oci_x_preferred":[
        "Villa del Rey"
    ],
    "name:pol_x_preferred":[
        "Villa del Rey"
    ],
    "name:por_x_preferred":[
        "Villa del Rey"
    ],
    "name:ron_x_preferred":[
        "Villa del Rey"
    ],
    "name:rus_x_preferred":[
        "\u0412\u0438\u043b\u044c\u044f-\u0434\u0435\u043b\u044c-\u0420\u0435\u0439"
    ],
    "name:spa_x_preferred":[
        "Villa del Rey"
    ],
    "name:swe_x_preferred":[
        "Villa del Rey"
    ],
    "name:ukr_x_preferred":[
        "\u0412\u0456\u043b\u044c\u044f-\u0434\u0435\u043b\u044c-\u0420\u0435\u0439"
    ],
    "name:uzb_x_preferred":[
        "Villa del Rey"
    ],
    "name:vie_x_preferred":[
        "Villa del Rey"
    ],
    "name:war_x_preferred":[
        "Villa del Rey"
    ],
    "name:zho_min_nan_x_preferred":[
        "Villa del Rey"
    ],
    "name:zho_x_preferred":[
        "\u6bd4\u5229\u4e9a\u5fb7\u5c14\u96f7"
    ],
    "wd:wordcount":45,
    "wof:name":"Villa del Rey",
    "wof:placetype":"neighbourhood",
    "wof:population":34,
    "zs:area_m":35285.990595,
    "zs:blockids":[
        280730203014024
    ],
    "zs:housing10":16,
    "zs:label":"Villa del Rey",
    "zs:pop10":34
},
  "geometry": {"coordinates":[-89.35838099999999,31.311518],"type":"Point"}
}