{
  "type": "Feature",
  "properties": {
    "gn:admin1_code":"WV",
    "gn:admin2_code":"41",
    "gn:asciiname":"Fisher Hill",
    "gn:country_code":"US",
    "gn:dem":381,
    "gn:elevation":"372.0",
    "gn:feature_class":"P",
    "gn:feature_code":"PPL",
    "gn:name":"Fisher Hill",
    "gn:population":0,
    "gn:timezone":"America/New_York",
    "iso:country":"US",
    "wof:name":"Fisher Hill",
    "wof:placetype":"locality"
},
  "geometry": {"coordinates":[-80.41925999999999,39.0737],"type":"Point"}
}