{
  "type": "Feature",
  "properties": {
    "iso:country":"US",
    "name:ceb_x_preferred":[
        "Elizabeth Park"
    ],
    "name:deu_x_preferred":[
        "Elizabeth Park"
    ],
    "name:swe_x_preferred":[
        "Elizabeth Park"
    ],
    "wof:name":"Elizabeth Park",
    "wof:placetype":"neighbourhood"
},
  "geometry": {"coordinates":[-86.8051945340865,36.17594191889454],"type":"Point"}
}