{
  "type": "Feature",
  "properties": {
    "gn:admin1_code":"OH",
    "gn:admin2_code":"153.0",
    "gn:admin3_code":"7790.0",
    "gn:asciiname":"Penisula",
    "gn:country_code":"US",
    "gn:dem":265,
    "gn:feature_class":"P",
    "gn:feature_code":"PPL",
    "gn:name":"Penisula",
    "gn:population":0,
    "gn:timezone":"America/New_York",
    "iso:country":"US",
    "wof:name":"Penisula",
    "wof:placetype":"locality"
},
  "geometry": {"coordinates":[-81.53090999999998,41.25406],"type":"Point"}
}