{
  "type": "Feature",
  "properties": {
    "gn:admin1_code":"SC",
    "gn:admin2_code":"7.0",
    "gn:asciiname":"Green Hill Plantation",
    "gn:country_code":"US",
    "gn:dem":227,
    "gn:elevation":"229.0",
    "gn:feature_class":"P",
    "gn:feature_code":"PPL",
    "gn:name":"Green Hill Plantation",
    "gn:population":0,
    "gn:timezone":"America/New_York",
    "iso:country":"US",
    "wof:name":"Green Hill Plantation",
    "wof:placetype":"locality"
},
  "geometry": {"coordinates":[-82.67291,34.56955],"type":"Point"}
}