{
  "type": "Feature",
  "properties": {
    "gn:admin1_code":"LA",
    "gn:admin2_code":"45.0",
    "gn:asciiname":"Duboin",
    "gn:country_code":"US",
    "gn:dem":5,
    "gn:elevation":"2.0",
    "gn:feature_class":"P",
    "gn:feature_code":"PPL",
    "gn:name":"Duboin",
    "gn:population":0,
    "gn:timezone":"America/Chicago",
    "iso:country":"US",
    "wof:name":"Duboin",
    "wof:placetype":"locality"
},
  "geometry": {"coordinates":[-91.82067000000001,29.92354000000001],"type":"Point"}
}