{
  "type": "Feature",
  "properties": {
    "iso:country":"US",
    "name:eng_x_preferred":[
        "Wheless"
    ],
    "wof:name":"Wheless",
    "wof:placetype":"neighbourhood",
    "wof:population":32,
    "zs:area_m":33345.363171,
    "zs:blockids":[
        132450103004024
    ],
    "zs:housing10":14,
    "zs:label":"Wheless",
    "zs:pop10":32
},
  "geometry": {"coordinates":[-82.040527,33.449345],"type":"Point"}
}