{
  "type": "Feature",
  "properties": {
    "gn:admin1_code":"OH",
    "gn:admin2_code":"25",
    "gn:admin3_code":"81130.0",
    "gn:asciiname":"Point Isabel",
    "gn:country_code":"US",
    "gn:dem":270,
    "gn:elevation":"268.0",
    "gn:feature_class":"P",
    "gn:feature_code":"PPL",
    "gn:name":"Point Isabel",
    "gn:population":0,
    "gn:timezone":"America/New_York",
    "iso:country":"US",
    "name:eng_x_preferred":[
        "Point Isabel"
    ],
    "name:und_x_variant":[
        "Port Isabel",
        "Pekin",
        "Point Isabell"
    ],
    "wof:name":"Point Isabel",
    "wof:placetype":"locality"
},
  "geometry": {"coordinates":[-84.13160000000001,38.89451],"type":"Point"}
}