{
  "type": "Feature",
  "properties": {
    "gn:admin1_code":"SC",
    "gn:admin2_code":"91.0",
    "gn:asciiname":"Willow Acres",
    "gn:country_code":"US",
    "gn:dem":207,
    "gn:elevation":"198.0",
    "gn:feature_class":"P",
    "gn:feature_code":"PPL",
    "gn:name":"Willow Acres",
    "gn:population":0,
    "gn:timezone":"America/New_York",
    "iso:country":"US",
    "wof:name":"Willow Acres",
    "wof:placetype":"locality"
},
  "geometry": {"coordinates":[-81.0873,34.99264],"type":"Point"}
}