{
  "type": "Feature",
  "properties": {
    "gn:admin1_code":"PA",
    "gn:admin2_code":"11.0",
    "gn:admin3_code":"78280.0",
    "gn:asciiname":"Kulptown",
    "gn:country_code":"US",
    "gn:dem":167,
    "gn:elevation":"163.0",
    "gn:feature_class":"P",
    "gn:feature_code":"PPL",
    "gn:name":"Kulptown",
    "gn:population":0,
    "gn:timezone":"America/New_York",
    "iso:country":"US",
    "wof:name":"Kulptown",
    "wof:placetype":"locality"
},
  "geometry": {"coordinates":[-75.79575,40.24454],"type":"Point"}
}