{
  "type": "Feature",
  "properties": {
    "gn:country":"US",
    "gn:fcode":"PPL",
    "gn:population":0,
    "iso:country":"US",
    "name:bre_x_preferred":[
        "Concord"
    ],
    "name:bul_x_preferred":[
        "\u041a\u043e\u043d\u043a\u043e\u0440\u0434"
    ],
    "name:cat_x_preferred":[
        "Concord"
    ],
    "name:ceb_x_preferred":[
        "Concord"
    ],
    "name:ces_x_preferred":[
        "Concord"
    ],
    "name:dan_x_preferred":[
        "Concord"
    ],
    "name:deu_x_preferred":[
        "Concord"
    ],
    "name:ell_x_preferred":[
        "\u039a\u03cc\u03bd\u03ba\u03bf\u03c1\u03bd\u03c4"
    ],
    "name:epo_x_preferred":[
        "Concord"
    ],
    "name:eus_x_preferred":[
        "Concord"
    ],
    "name:fas_x_preferred":[
        "\u06a9\u0646\u06a9\u0648\u0631\u062f"
    ],
    "name:fin_x_preferred":[
        "Concord"
    ],
    "name:fra_x_preferred":[
        "Concord"
    ],
    "name:hrv_x_preferred":[
        "Concord"
    ],
    "name:hun_x_preferred":[
        "Concord"
    ],
    "name:ind_x_preferred":[
        "Concord"
    ],
    "name:ita_x_preferred":[
        "Concord"
    ],
    "name:jpn_x_preferred":[
        "\u30b3\u30f3\u30b3\u30fc\u30c9"
    ],
    "name:kor_x_preferred":[
        "\ucf69\ucf54\ub4dc"
    ],
    "name:kur_x_preferred":[
        "Concord"
    ],
    "name:mlg_x_preferred":[
        "Concord"
    ],
    "name:nds_x_preferred":[
        "Concord"
    ],
    "name:nld_x_preferred":[
        "Concord"
    ],
    "name:nor_x_preferred":[
        "Concord"
    ],
    "name:pol_x_preferred":[
        "Concord"
    ],
    "name:por_x_preferred":[
        "Concord"
    ],
    "name:ron_x_preferred":[
        "Concord"
    ],
    "name:rus_x_preferred":[
        "\u041a\u043e\u043d\u043a\u043e\u0440\u0434"
    ],
    "name:sco_x_preferred":[
        "Concord"
    ],
    "name:slk_x_preferred":[
        "Concord"
    ],
    "name:spa_x_preferred":[
        "Concord"
    ],
    "name:srp_x_preferred":[
        "\u041a\u043e\u043d\u043a\u043e\u0440\u0434"
    ],
    "name:swa_x_preferred":[
        "Concord"
    ],
    "name:swe_x_preferred":[
        "Concord"
    ],
    "name:tgl_x_preferred":[
        "Concord"
    ],
    "name:ukr_x_preferred":[
        "\u041a\u043e\u043d\u043a\u043e\u0440\u0434"
    ],
    "name:urd_x_preferred":[
        "\u06a9\u0627\u0646\u06a9\u0648\u0631\u0688"
    ],
    "name:vol_x_preferred":[
        "Concord"
    ],
    "name:zho_x_preferred":[
        "\u5eb7\u79d1\u5fb7"
    ],
    "qs_pg:aaroncc":"US",
    "qs_pg:gn_country":"US",
    "qs_pg:gn_fcode":"PPL",
    "qs_pg:gn_pop":0,
    "qs_pg:name":"Concord",
    "qs_pg:name_adm0":"United States",
    "qs_pg:name_adm1":"New York",
    "qs_pg:photos_9k":1,
    "qs_pg:photos_9r":3,
    "qs_pg:photos_all":92,
    "qs_pg:photos_sr":0,
    "qs_pg:pop_sr":0,
    "qs_pg:qs_pg_placetype":"locality",
    "qs_pg:qs_pg_placetype_gp":"Town",
    "qs_pg:woe_adm0":23424977,
    "woe:adm0_id":23424977,
    "woe:name_adm0":"United States",
    "woe:name_adm1":"New York",
    "woe:placetype":"Town",
    "wof:name":"Concord",
    "wof:placetype":"locality"
},
  "geometry": {"coordinates":[-78.73086000000001,42.53534],"type":"Point"}
}