{
  "type": "Feature",
  "properties": {
    "gn:country":"US",
    "gn:fcode":"PPL",
    "gn:population":593,
    "iso:country":"US",
    "name:azb_x_preferred":[
        "\u0628\u0648\u0642\u0631\u0633\u06cc\u062a\u06cc"
    ],
    "name:cat_x_preferred":[
        "Boger City"
    ],
    "name:ceb_x_preferred":[
        "Boger City"
    ],
    "name:eng_x_preferred":[
        "Boger City"
    ],
    "name:fas_x_preferred":[
        "\u0628\u0648\u06af\u0631\u0633\u06cc\u062a\u06cc"
    ],
    "name:lld_x_preferred":[
        "Boger City"
    ],
    "name:nan_x_preferred":[
        "Boger City"
    ],
    "name:nld_x_preferred":[
        "Boger City"
    ],
    "name:por_x_preferred":[
        "Boger City"
    ],
    "name:spa_x_preferred":[
        "Boger City"
    ],
    "name:srp_x_preferred":[
        "\u0411\u043e\u0433\u0435\u0440"
    ],
    "name:und_x_variant":[
        "Goodsons Store"
    ],
    "name:uzb_x_preferred":[
        "Boger City"
    ],
    "name:vol_x_preferred":[
        "Boger City"
    ],
    "name:vol_x_variant":[
        "Parishfield"
    ],
    "qs_pg:aaroncc":"US",
    "qs_pg:gn_country":"US",
    "qs_pg:gn_fcode":"PPL",
    "qs_pg:gn_pop":593,
    "qs_pg:name":"Boger City",
    "qs_pg:name_adm0":"United States",
    "qs_pg:name_adm1":"North Carolina",
    "qs_pg:photos":8,
    "qs_pg:photos_1k":2,
    "qs_pg:photos_9k":1,
    "qs_pg:photos_9r":1,
    "qs_pg:photos_all":8,
    "qs_pg:photos_sr":1,
    "qs_pg:pop_sr":2,
    "qs_pg:qs_pg_placetype":"locality",
    "qs_pg:qs_pg_placetype_gp":"Town",
    "qs_pg:woe_adm0":23424977,
    "woe:adm0_id":23424977,
    "woe:name_adm0":"United States",
    "woe:name_adm1":"North Carolina",
    "woe:placetype":"Town",
    "wof:name":"Boger City",
    "wof:placetype":"locality",
    "wof:population":593
},
  "geometry": {"coordinates":[-81.21341,35.48069],"type":"Point"}
}