{
  "type": "Feature",
  "properties": {
    "iso:country":"US",
    "name:eng_x_preferred":[
        "Kerby Hill"
    ],
    "name:eng_x_variant":[
        "Kerby Hl"
    ],
    "name:und_x_variant":[
        "Kerby Hills"
    ],
    "qs:gn_adm0_cc":"US",
    "qs:gn_fcode":"PPL",
    "qs:gn_local":4364759,
    "qs:gn_nam_loc":"Oxon Hill, Prince George's, Maryland, US",
    "qs:gn_namadm1":"MD",
    "qs:gn_name":"Kerby Hill",
    "qs:local_max":13158,
    "qs:local_sum":13305,
    "qs:localhoods":2,
    "qs:name":"Kerby Hill",
    "qs:name_adm0":"United States",
    "qs:name_adm1":"Maryland",
    "qs:name_adm2":"Prince George's",
    "qs:name_local":"Oxon Hill",
    "qs:photo_max":8910,
    "qs:photo_sum":13158,
    "qs:placetype":"Suburb",
    "qs:quad_count":26,
    "qs:woe_adm0":23424977,
    "qs:woe_adm1":2347579,
    "qs:woe_adm2":12588692,
    "qs:woe_lau":0,
    "qs:woe_local":2467215,
    "qs:woe_ver":"7.10.0",
    "wof:name":"Kerby Hill",
    "wof:placetype":"neighbourhood",
    "wof:population":1995,
    "zs:blockids":[
        240338014043022,
        240338014043008,
        240338014043050,
        240338014043012,
        240338014043025,
        240338014042007,
        240338014111008,
        240338014043031,
        240338014042000,
        240338014042009,
        240338014043011,
        240338014042005,
        240338014043004,
        240338014111006,
        240338014043005,
        240338014043049,
        240338014043010,
        240338014042006,
        240338014043015,
        240338014043033,
        240338014043009,
        240338014043020,
        240338014043030,
        240338014043032,
        240338014042013,
        240338014043006,
        240338014043027,
        240338014043007,
        240338014043003,
        240338014111007,
        240338014043018,
        240338014043035,
        240338014043029,
        240338014043026,
        240338014043051,
        240338014043019,
        240338014043034,
        240338014042004,
        240338014042002,
        240338014043013,
        240338014043017,
        240338014043028,
        240338014043036
    ],
    "zs:housing10":1015,
    "zs:pop10":1995
},
  "geometry": {"coordinates":[-77.017573,38.784853],"type":"Point"}
}