{
  "type": "Feature",
  "properties": {
    "gn:admin1_code":"MD",
    "gn:admin2_code":"13.0",
    "gn:asciiname":"Fairhaven",
    "gn:country_code":"US",
    "gn:dem":173,
    "gn:elevation":"173.0",
    "gn:feature_class":"P",
    "gn:feature_code":"PPL",
    "gn:name":"Fairhaven",
    "gn:population":0,
    "gn:timezone":"America/New_York",
    "iso:country":"US",
    "name:cat_x_preferred":[
        "Fairhaven"
    ],
    "name:ceb_x_preferred":[
        "Fairhaven"
    ],
    "name:ces_x_preferred":[
        "Fairhaven"
    ],
    "name:deu_x_preferred":[
        "Fairhaven"
    ],
    "name:pol_x_preferred":[
        "Fairhaven"
    ],
    "name:swe_x_preferred":[
        "Fairhaven"
    ],
    "name:ukr_x_preferred":[
        "\u0424\u0435\u0439\u0440\u0433\u0435\u0439\u0432\u0435\u043d"
    ],
    "name:vol_x_preferred":[
        "Fairhaven"
    ],
    "wof:name":"Fairhaven",
    "wof:placetype":"locality"
},
  "geometry": {"coordinates":[-76.97136999999999,39.37733],"type":"Point"}
}