{
  "type": "Feature",
  "properties": {
    "gn:admin1_code":"MD",
    "gn:admin2_code":"3.0",
    "gn:asciiname":"Holly Hill",
    "gn:country_code":"US",
    "gn:dem":41,
    "gn:elevation":"39.0",
    "gn:feature_class":"P",
    "gn:feature_code":"PPL",
    "gn:name":"Holly Hill",
    "gn:population":0,
    "gn:timezone":"America/New_York",
    "iso:country":"US",
    "name:ceb_x_preferred":[
        "Holly Hill"
    ],
    "name:deu_x_preferred":[
        "Holly Hill"
    ],
    "name:ita_x_preferred":[
        "Holly Hill"
    ],
    "name:nld_x_preferred":[
        "Holly Hill"
    ],
    "name:pol_x_preferred":[
        "Holly Hill"
    ],
    "name:por_x_preferred":[
        "Holly Hill"
    ],
    "name:spa_x_preferred":[
        "Holly Hill"
    ],
    "name:srp_x_preferred":[
        "\u0425\u043e\u043b\u0438 \u0425\u0438\u043b"
    ],
    "name:swe_x_preferred":[
        "Holly Hill"
    ],
    "name:ukr_x_preferred":[
        "\u0413\u043e\u043b\u043b\u0456-\u0413\u0456\u043b\u043b"
    ],
    "name:vol_x_preferred":[
        "Holly Hill"
    ],
    "wof:name":"Holly Hill",
    "wof:placetype":"locality"
},
  "geometry": {"coordinates":[-76.56524,38.73206],"type":"Point"}
}