{
  "type": "Feature",
  "properties": {
    "gn:admin1_code":"AR",
    "gn:admin2_code":"143.0",
    "gn:admin3_code":"93465.0",
    "gn:asciiname":"Sonora",
    "gn:country_code":"US",
    "gn:dem":399,
    "gn:elevation":"399.0",
    "gn:feature_class":"P",
    "gn:feature_code":"PPL",
    "gn:name":"Sonora",
    "gn:population":0,
    "gn:timezone":"America/Chicago",
    "iso:country":"US",
    "name:fas_x_preferred":[
        "\u0633\u0648\u0646\u0648\u0631\u0627"
    ],
    "name:zho_x_preferred":[
        "\u7d22\u8afe\u62c9"
    ],
    "wof:name":"Sonora",
    "wof:placetype":"locality"
},
  "geometry": {"coordinates":[-94.04492,36.16535],"type":"Point"}
}