{
  "type": "Feature",
  "properties": {
    "iso:country":"US",
    "name:eng_x_preferred":[
        "Strathaven Forest"
    ],
    "wof:name":"Strathaven Forest",
    "wof:placetype":"neighbourhood",
    "wof:population":225,
    "zs:area_m":399887.958347,
    "zs:blockids":[
        450790116086007,
        450790116086008,
        450790116086004,
        450790116086009
    ],
    "zs:housing10":97,
    "zs:label":"Strathaven Forest",
    "zs:pop10":225
},
  "geometry": {"coordinates":[-80.915706,33.973976],"type":"Point"}
}