{
  "type": "Feature",
  "properties": {
    "gn:admin1_code":"WV",
    "gn:admin2_code":"51.0",
    "gn:asciiname":"Wolf Run",
    "gn:country_code":"US",
    "gn:dem":306,
    "gn:elevation":"295.0",
    "gn:feature_class":"P",
    "gn:feature_code":"PPL",
    "gn:name":"Wolf Run",
    "gn:population":0,
    "gn:timezone":"America/New_York",
    "iso:country":"US",
    "name:ceb_x_preferred":[
        "Wolf Run"
    ],
    "name:eng_x_preferred":[
        "Wolf Run"
    ],
    "name:und_x_variant":[
        "Wolfrun"
    ],
    "wof:name":"Wolf Run",
    "wof:placetype":"locality"
},
  "geometry": {"coordinates":[-80.56535,39.9073],"type":"Point"}
}