{
  "type": "Feature",
  "properties": {
    "gn:admin1_code":"OR",
    "gn:admin2_code":"65.0",
    "gn:asciiname":"Petersburg",
    "gn:country_code":"US",
    "gn:dem":97,
    "gn:elevation":"97.0",
    "gn:feature_class":"P",
    "gn:feature_code":"PPL",
    "gn:name":"Petersburg",
    "gn:population":0,
    "gn:timezone":"America/Los_Angeles",
    "iso:country":"US",
    "name:cat_x_preferred":[
        "Petersburg"
    ],
    "name:ceb_x_preferred":[
        "Petersburg"
    ],
    "name:deu_x_preferred":[
        "Petersburg"
    ],
    "name:est_x_preferred":[
        "Petersburg"
    ],
    "name:fin_x_preferred":[
        "Petersburg"
    ],
    "name:fra_x_preferred":[
        "Petersburg"
    ],
    "name:ita_x_preferred":[
        "Petersburg"
    ],
    "name:jpn_x_preferred":[
        "\u30d4\u30fc\u30bf\u30fc\u30ba\u30d0\u30fc\u30b0"
    ],
    "name:kor_x_preferred":[
        "\ud53c\ud130\uc988\ubc84\uadf8"
    ],
    "name:nld_x_preferred":[
        "Petersburg"
    ],
    "name:nor_x_preferred":[
        "Petersburg"
    ],
    "name:pol_x_preferred":[
        "Petersburg"
    ],
    "name:ron_x_preferred":[
        "Petersburg"
    ],
    "name:rus_x_preferred":[
        "\u041f\u0435\u0442\u0435\u0440\u0441\u0431\u0443\u0440\u0433"
    ],
    "name:sco_x_preferred":[
        "Petersburg"
    ],
    "name:slk_x_preferred":[
        "Petersburg"
    ],
    "name:spa_x_preferred":[
        "Petersburg"
    ],
    "name:srp_x_preferred":[
        "\u041f\u0438\u0442\u0435\u0440\u0441\u0431\u0443\u0440\u0433"
    ],
    "name:swe_x_preferred":[
        "Petersburg"
    ],
    "name:tur_x_preferred":[
        "Petersburg"
    ],
    "name:ukr_x_preferred":[
        "\u041f\u0456\u0442\u0435\u0440\u0441\u0431\u0435\u0440\u0433"
    ],
    "name:urd_x_preferred":[
        "\u067e\u06cc\u0679\u0631\u0632\u0628\u0631\u06af"
    ],
    "name:vol_x_preferred":[
        "Petersburg"
    ],
    "name:zho_x_preferred":[
        "\u5f7c\u5fb7\u5821"
    ],
    "wof:name":"Petersburg",
    "wof:placetype":"locality"
},
  "geometry": {"coordinates":[-121.07812,45.61095],"type":"Point"}
}