{
  "type": "Feature",
  "properties": {
    "gn:admin1_code":"TX",
    "gn:admin2_code":"401",
    "gn:asciiname":"Glenfawn",
    "gn:country_code":"US",
    "gn:dem":142,
    "gn:elevation":"138.0",
    "gn:feature_class":"P",
    "gn:feature_code":"PPL",
    "gn:name":"Glenfawn",
    "gn:population":0,
    "gn:timezone":"America/Chicago",
    "iso:country":"US",
    "wof:name":"Glenfawn",
    "wof:placetype":"locality"
},
  "geometry": {"coordinates":[-94.85688,31.91378],"type":"Point"}
}