{
  "type": "Feature",
  "properties": {
    "gn:admin1_code":"PA",
    "gn:admin2_code":"129.0",
    "gn:admin3_code":"58880.0",
    "gn:asciiname":"Harrison City",
    "gn:country_code":"US",
    "gn:dem":299,
    "gn:elevation":"298.0",
    "gn:feature_class":"P",
    "gn:feature_code":"PPL",
    "gn:name":"Harrison City",
    "gn:population":134,
    "gn:timezone":"America/New_York",
    "iso:country":"US",
    "name:ceb_x_preferred":[
        "Harrison City"
    ],
    "name:nld_x_preferred":[
        "Harrison City"
    ],
    "name:por_x_preferred":[
        "Harrison City"
    ],
    "name:spa_x_preferred":[
        "Harrison City"
    ],
    "name:srp_x_preferred":[
        "\u0425\u0430\u0440\u0438\u0441\u043e\u043d \u0421\u0438\u0442\u0438"
    ],
    "name:uzb_x_preferred":[
        "Harrison City"
    ],
    "name:vol_x_preferred":[
        "Harrison City"
    ],
    "wof:name":"Harrison City",
    "wof:placetype":"locality",
    "wof:population":134
},
  "geometry": {"coordinates":[-79.64838,40.35424],"type":"Point"}
}