{
  "type": "Feature",
  "properties": {
    "gn:admin1_code":"AZ",
    "gn:admin2_code":"9.0",
    "gn:asciiname":"Sanchez",
    "gn:country_code":"US",
    "gn:dem":935,
    "gn:elevation":"933.0",
    "gn:feature_class":"P",
    "gn:feature_code":"PPL",
    "gn:name":"Sanchez",
    "gn:population":0,
    "gn:timezone":"America/Phoenix",
    "iso:country":"US",
    "wof:name":"Sanchez",
    "wof:placetype":"locality"
},
  "geometry": {"coordinates":[-109.54285,32.86951],"type":"Point"}
}