{
  "type": "Feature",
  "properties": {
    "gn:admin1_code":"MD",
    "gn:admin2_code":"3.0",
    "gn:asciiname":"Allwood",
    "gn:country_code":"US",
    "gn:dem":30,
    "gn:elevation":"29.0",
    "gn:feature_class":"P",
    "gn:feature_code":"PPL",
    "gn:name":"Allwood",
    "gn:population":0,
    "gn:timezone":"America/New_York",
    "iso:country":"US",
    "wof:name":"Allwood",
    "wof:placetype":"locality"
},
  "geometry": {"coordinates":[-76.64775,39.18011],"type":"Point"}
}