{
  "type": "Feature",
  "properties": {
    "gn:admin1_code":"VA",
    "gn:admin2_code":"107.0",
    "gn:asciiname":"Belmont Greene",
    "gn:country_code":"US",
    "gn:dem":92,
    "gn:elevation":"91.0",
    "gn:feature_class":"P",
    "gn:feature_code":"PPL",
    "gn:name":"Belmont Greene",
    "gn:population":0,
    "gn:timezone":"America/New_York",
    "iso:country":"US",
    "name:eng_x_preferred":[
        "Belmont Greene"
    ],
    "name:und_x_variant":[
        "Belmont Forest"
    ],
    "wof:name":"Belmont Greene",
    "wof:placetype":"locality"
},
  "geometry": {"coordinates":[-77.51026999999998,39.064],"type":"Point"}
}