{
  "type": "Feature",
  "properties": {
    "gn:admin1_code":"AL",
    "gn:admin2_code":"47",
    "gn:asciiname":"Eleanor",
    "gn:country_code":"US",
    "gn:dem":53,
    "gn:elevation":"48.0",
    "gn:feature_class":"P",
    "gn:feature_code":"PPL",
    "gn:name":"Eleanor",
    "gn:population":0,
    "gn:timezone":"America/Chicago",
    "iso:country":"US",
    "name:arg_x_preferred":[
        "Alionor"
    ],
    "name:bre_x_preferred":[
        "Eleanor"
    ],
    "name:est_x_preferred":[
        "Eleanor"
    ],
    "name:rus_x_preferred":[
        "\u042d\u043b\u0435\u043e\u043d\u043e\u0440\u0430"
    ],
    "name:spa_x_preferred":[
        "Eleanor"
    ],
    "wof:name":"Eleanor",
    "wof:placetype":"locality"
},
  "geometry": {"coordinates":[-87.31916,32.34014000000001],"type":"Point"}
}