{
  "type": "Feature",
  "properties": {
    "gn:admin1_code":"VA",
    "gn:admin2_code":"3",
    "gn:asciiname":"Gilbert Heights",
    "gn:country_code":"US",
    "gn:dem":146,
    "gn:elevation":"145.0",
    "gn:feature_class":"P",
    "gn:feature_code":"PPL",
    "gn:name":"Gilbert Heights",
    "gn:population":0,
    "gn:timezone":"America/New_York",
    "iso:country":"US",
    "wof:name":"Gilbert Heights",
    "wof:placetype":"locality"
},
  "geometry": {"coordinates":[-78.38973,38.15486],"type":"Point"}
}