{
  "type": "Feature",
  "properties": {
    "gn:admin1_code":"MO",
    "gn:admin2_code":"185.0",
    "gn:admin3_code":"10108.0",
    "gn:asciiname":"Ninnescah Park",
    "gn:country_code":"US",
    "gn:dem":224,
    "gn:elevation":"226.0",
    "gn:feature_class":"P",
    "gn:feature_code":"PPL",
    "gn:name":"Ninnescah Park",
    "gn:population":0,
    "gn:timezone":"America/Chicago",
    "iso:country":"US",
    "wof:name":"Ninnescah Park",
    "wof:placetype":"locality"
},
  "geometry": {"coordinates":[-93.61493,38.18836],"type":"Point"}
}