{
  "type": "Feature",
  "properties": {
    "gn:admin1_code":"CA",
    "gn:admin2_code":"97.0",
    "gn:asciiname":"Ross",
    "gn:country_code":"US",
    "gn:dem":52,
    "gn:elevation":"53.0",
    "gn:feature_class":"P",
    "gn:feature_code":"PPL",
    "gn:name":"Ross",
    "gn:population":0,
    "gn:timezone":"America/Los_Angeles",
    "iso:country":"US",
    "name:bre_x_preferred":[
        "Ross"
    ],
    "name:cat_x_preferred":[
        "Ross"
    ],
    "name:ceb_x_preferred":[
        "Ross"
    ],
    "name:ces_x_preferred":[
        "Ross"
    ],
    "name:deu_x_preferred":[
        "Ross"
    ],
    "name:fin_x_preferred":[
        "Ross"
    ],
    "name:fra_x_preferred":[
        "Ross"
    ],
    "name:heb_x_preferred":[
        "\u05e8\u05d5\u05e1"
    ],
    "name:hye_x_preferred":[
        "\u054c\u0578\u057d\u057d"
    ],
    "name:ita_x_preferred":[
        "Ross"
    ],
    "name:lav_x_preferred":[
        "Ross"
    ],
    "name:nld_x_preferred":[
        "Ross"
    ],
    "name:nor_x_preferred":[
        "Ross"
    ],
    "name:pol_x_preferred":[
        "Ross"
    ],
    "name:por_x_preferred":[
        "Ross"
    ],
    "name:rus_x_preferred":[
        "\u0420\u043e\u0441\u0441"
    ],
    "name:spa_x_preferred":[
        "Ross"
    ],
    "name:srp_x_preferred":[
        "Ross"
    ],
    "name:swe_x_preferred":[
        "Ross"
    ],
    "name:tur_x_preferred":[
        "Ross"
    ],
    "name:ukr_x_preferred":[
        "\u0420\u043e\u0441\u0441"
    ],
    "name:vol_x_preferred":[
        "Ross"
    ],
    "wof:name":"Ross",
    "wof:placetype":"locality"
},
  "geometry": {"coordinates":[-122.88583,38.45852],"type":"Point"}
}