{
  "type": "Feature",
  "properties": {
    "gn:admin1_code":"WV",
    "gn:admin2_code":"79.0",
    "gn:asciiname":"Wheeler Ridge",
    "gn:country_code":"US",
    "gn:dem":278,
    "gn:elevation":"278.0",
    "gn:feature_class":"P",
    "gn:feature_code":"PPL",
    "gn:name":"Wheeler Ridge",
    "gn:population":0,
    "gn:timezone":"America/New_York",
    "iso:country":"US",
    "wof:name":"Wheeler Ridge",
    "wof:placetype":"locality"
},
  "geometry": {"coordinates":[-82.02903000000001,38.40703],"type":"Point"}
}