{
  "type": "Feature",
  "properties": {
    "gn:country":"US",
    "gn:fcode":"PPL",
    "gn:population":0,
    "iso:country":"US",
    "name:ara_x_preferred":[
        "\u0628\u0648\u062a\u0631\u0632\u0641\u064a\u0644\u060c \u0645\u064a\u0632\u0648\u0631\u064a"
    ],
    "name:ara_x_variant":[
        "\u0628\u0648\u062a\u0631\u0632\u0641\u064a\u0644"
    ],
    "name:eng_x_preferred":[
        "Pottersville"
    ],
    "name:fra_x_preferred":[
        "Pottersville"
    ],
    "name:vol_x_preferred":[
        "Pottersville"
    ],
    "qs_pg:aaroncc":"US",
    "qs_pg:gn_country":"US",
    "qs_pg:gn_fcode":"PPL",
    "qs_pg:gn_pop":0,
    "qs_pg:name":"Pottersville",
    "qs_pg:name_adm0":"United States",
    "qs_pg:name_adm1":"Missouri",
    "qs_pg:photos_9k":1,
    "qs_pg:photos_9r":1,
    "qs_pg:photos_all":8,
    "qs_pg:photos_sr":0,
    "qs_pg:pop_sr":0,
    "qs_pg:qs_pg_placetype":"locality",
    "qs_pg:qs_pg_placetype_gp":"Town",
    "qs_pg:woe_adm0":23424977,
    "woe:adm0_id":23424977,
    "woe:name_adm0":"United States",
    "woe:name_adm1":"Missouri",
    "woe:placetype":"Town",
    "wof:name":"Pottersville",
    "wof:placetype":"locality"
},
  "geometry": {"coordinates":[-92.03126,36.69589],"type":"Point"}
}