{
  "type": "Feature",
  "properties": {
    "gn:admin1_code":"LA",
    "gn:admin2_code":"117.0",
    "gn:asciiname":"Richardson",
    "gn:country_code":"US",
    "gn:dem":66,
    "gn:elevation":"60.0",
    "gn:feature_class":"P",
    "gn:feature_code":"PPL",
    "gn:name":"Richardson",
    "gn:population":0,
    "gn:timezone":"America/Chicago",
    "iso:country":"US",
    "name:bel_x_preferred":[
        "\u0420\u044b\u0447\u0430\u0440\u0434\u0441\u0430\u043d"
    ],
    "name:cat_x_preferred":[
        "Richardson"
    ],
    "name:ceb_x_preferred":[
        "Richardson"
    ],
    "name:ces_x_preferred":[
        "Richardson"
    ],
    "name:deu_x_preferred":[
        "Richardson"
    ],
    "name:eng_x_preferred":[
        "Richardson"
    ],
    "name:fas_x_preferred":[
        "\u0631\u06cc\u0686\u0627\u0631\u062f\u0633\u0648\u0646"
    ],
    "name:fin_x_preferred":[
        "Richardson"
    ],
    "name:fra_x_preferred":[
        "Richardson"
    ],
    "name:heb_x_preferred":[
        "\u05e8\u05d9\u05e6'\u05e8\u05d3\u05e1\u05d5\u05df"
    ],
    "name:ita_x_preferred":[
        "Richardson"
    ],
    "name:jpn_x_preferred":[
        "\u30ea\u30c1\u30e3\u30fc\u30c9\u30bd\u30f3"
    ],
    "name:kor_x_preferred":[
        "\ub9ac\ucc98\ub4dc\uc2a8"
    ],
    "name:nds_x_preferred":[
        "Richardson"
    ],
    "name:nld_x_preferred":[
        "Richardson"
    ],
    "name:pol_x_preferred":[
        "Richardson"
    ],
    "name:por_x_preferred":[
        "Richardson"
    ],
    "name:rus_x_preferred":[
        "\u0420\u0438\u0447\u0430\u0440\u0434\u0441\u043e\u043d"
    ],
    "name:slv_x_preferred":[
        "Richardson"
    ],
    "name:spa_x_preferred":[
        "Richardson"
    ],
    "name:srp_x_preferred":[
        "\u0420\u0438\u0447\u0430\u0440\u0434\u0441\u043e\u043d"
    ],
    "name:swe_x_preferred":[
        "Richardson"
    ],
    "name:ukr_x_preferred":[
        "\u0420\u0456\u0447\u0430\u0440\u0434\u0441\u043e\u043d"
    ],
    "name:und_x_variant":[
        "Richardsons Store"
    ],
    "name:urd_x_preferred":[
        "\u0631\u0686\u0631\u0688\u0633\u0646"
    ],
    "name:zho_x_preferred":[
        "\u7406\u67e5\u68ee"
    ],
    "wof:name":"Richardson",
    "wof:placetype":"locality"
},
  "geometry": {"coordinates":[-90.21314,30.85463],"type":"Point"}
}