{
  "type": "Feature",
  "properties": {
    "gn:admin1_code":"CA",
    "gn:admin2_code":"19",
    "gn:asciiname":"Gravesboro",
    "gn:country_code":"US",
    "gn:dem":146,
    "gn:elevation":"147.0",
    "gn:feature_class":"P",
    "gn:feature_code":"PPL",
    "gn:name":"Gravesboro",
    "gn:population":0,
    "gn:timezone":"America/Los_Angeles",
    "iso:country":"US",
    "name:zho_x_preferred":[
        "\u683c\u96f7\u592b\u65af\u4f2f\u52d2"
    ],
    "wof:name":"Gravesboro",
    "wof:placetype":"locality"
},
  "geometry": {"coordinates":[-119.41152,36.77301],"type":"Point"}
}