{
  "type": "Feature",
  "properties": {
    "gn:gn_country":"US",
    "gn:gn_fcode":"PPL",
    "gn:gn_pop":0,
    "iso:country":"US",
    "name:afr_x_preferred":[
        "Mountain View"
    ],
    "name:cat_x_preferred":[
        "Mountain View"
    ],
    "name:ceb_x_preferred":[
        "Mountain View"
    ],
    "name:deu_x_preferred":[
        "Mountain View"
    ],
    "name:fin_x_preferred":[
        "Mountain View"
    ],
    "name:fra_x_preferred":[
        "Mountain View"
    ],
    "name:hun_x_preferred":[
        "Mountain View"
    ],
    "name:ita_x_preferred":[
        "Mountain View"
    ],
    "name:kor_x_preferred":[
        "\ub9c8\uc6b4\ud2f4\ubdf0"
    ],
    "name:nld_x_preferred":[
        "Mountain View"
    ],
    "name:pol_x_preferred":[
        "Mountain View"
    ],
    "name:por_x_preferred":[
        "Mountain View"
    ],
    "name:rus_x_preferred":[
        "\u041c\u0430\u0443\u043d\u0442\u0438\u043d-\u0412\u044c\u044e"
    ],
    "name:spa_x_preferred":[
        "Mountain View"
    ],
    "name:srp_x_preferred":[
        "\u041c\u0430\u0443\u043d\u0442\u0438\u043d \u0412\u0458\u0443"
    ],
    "name:swe_x_preferred":[
        "Mountain View"
    ],
    "name:ukr_x_preferred":[
        "\u041c\u0430\u0443\u043d\u0442\u0435\u043d-\u0412'\u044e"
    ],
    "name:urd_x_preferred":[
        "\u0645\u0627\u0624\u0646\u0679\u06cc\u0646 \u0648\u06cc\u0648"
    ],
    "name:vol_x_preferred":[
        "Mountain View"
    ],
    "name:zho_x_preferred":[
        "\u5c71\u666f\u57ce"
    ],
    "qs_pg:aaroncc":"US",
    "qs_pg:gn_country":"US",
    "qs_pg:gn_fcode":"PPL",
    "qs_pg:gn_pop":0,
    "qs_pg:name":"Mountain View",
    "qs_pg:name_adm0":"United States",
    "qs_pg:name_adm1":"Montana",
    "qs_pg:photos":97,
    "qs_pg:photos_1k":20,
    "qs_pg:photos_9k":1,
    "qs_pg:photos_9r":3,
    "qs_pg:photos_all":97,
    "qs_pg:photos_sr":3,
    "qs_pg:pop_sr":0,
    "qs_pg:qs_pg_placetype":"locality",
    "qs_pg:qs_pg_placetype_gp":"Town",
    "qs_pg:woe_adm0":23424977,
    "woe:adm0_id":23424977,
    "woe:name_adm0":"United States",
    "woe:name_adm1":"Montana",
    "woe:placetype":"Town",
    "wof:name":"Mountain View",
    "wof:placetype":"locality"
},
  "geometry": {"coordinates":[-109.89935,45.38966],"type":"Point"}
}