{
  "type": "Feature",
  "properties": {
    "gn:admin1_code":"AR",
    "gn:admin2_code":"99.0",
    "gn:admin3_code":"90423.0",
    "gn:asciiname":"Boughton",
    "gn:country_code":"US",
    "gn:dem":76,
    "gn:elevation":"72.0",
    "gn:feature_class":"P",
    "gn:feature_code":"PPL",
    "gn:name":"Boughton",
    "gn:population":0,
    "gn:timezone":"America/Chicago",
    "iso:country":"US",
    "name:ceb_x_preferred":[
        "Boughton"
    ],
    "name:deu_x_preferred":[
        "Boughton"
    ],
    "name:fra_x_preferred":[
        "Boughton"
    ],
    "name:ita_x_preferred":[
        "Boughton"
    ],
    "name:nld_x_preferred":[
        "Boughton"
    ],
    "name:pol_x_preferred":[
        "Boughton"
    ],
    "name:spa_x_preferred":[
        "Boughton"
    ],
    "name:swe_x_preferred":[
        "Boughton"
    ],
    "wof:name":"Boughton",
    "wof:placetype":"locality"
},
  "geometry": {"coordinates":[-93.32572999999999,33.85011],"type":"Point"}
}