{
  "type": "Feature",
  "properties": {
    "gn:admin1_code":"SC",
    "gn:admin2_code":"73.0",
    "gn:asciiname":"Dixon Crossroads",
    "gn:country_code":"US",
    "gn:dem":244,
    "gn:elevation":"232.0",
    "gn:feature_class":"P",
    "gn:feature_code":"PPL",
    "gn:name":"Dixon Crossroads",
    "gn:population":0,
    "gn:timezone":"America/New_York",
    "iso:country":"US",
    "name:eng_x_preferred":[
        "Dixon Crossroads"
    ],
    "name:und_x_variant":[
        "Dixons Crossroads"
    ],
    "wof:name":"Dixon Crossroads",
    "wof:placetype":"locality"
},
  "geometry": {"coordinates":[-83.14709999999999,34.60927],"type":"Point"}
}