{
  "type": "Feature",
  "properties": {
    "gn:country":"US",
    "gn:fcode":"PPL",
    "gn:population":0,
    "iso:country":"US",
    "name:eng_x_preferred":[
        "Guyencourt"
    ],
    "name:fra_x_preferred":[
        "Guyencourt"
    ],
    "name:zho_x_preferred":[
        "\u84cb\u6069\u8003\u7279"
    ],
    "qs_pg:aaroncc":"US",
    "qs_pg:gn_country":"US",
    "qs_pg:gn_fcode":"PPL",
    "qs_pg:gn_pop":0,
    "qs_pg:name":"Guyencourt",
    "qs_pg:name_adm0":"United States",
    "qs_pg:name_adm1":"Delaware",
    "qs_pg:photos":24,
    "qs_pg:photos_1k":5,
    "qs_pg:photos_9k":1,
    "qs_pg:photos_9r":1,
    "qs_pg:photos_all":24,
    "qs_pg:photos_sr":1,
    "qs_pg:pop_sr":0,
    "qs_pg:qs_pg_placetype":"locality",
    "qs_pg:qs_pg_placetype_gp":"Town",
    "qs_pg:woe_adm0":23424977,
    "woe:adm0_id":23424977,
    "woe:name_adm0":"United States",
    "woe:name_adm1":"Delaware",
    "woe:placetype":"Town",
    "wof:name":"Guyencourt",
    "wof:placetype":"locality"
},
  "geometry": {"coordinates":[-75.58632,39.81372],"type":"Point"}
}