{
  "type": "Feature",
  "properties": {
    "gn:country":"US",
    "gn:fcode":"PPL",
    "gn:population":0,
    "iso:country":"US",
    "name:ara_x_preferred":[
        "\u0646\u0648\u0631\u062b\u0627\u0645\u0628\u0631\u0644\u0627\u0646\u062f"
    ],
    "name:arz_x_preferred":[
        "\u0646\u0648\u0631\u062b\u0627\u0645\u0628\u0631\u0644\u0627\u0646\u062f"
    ],
    "name:che_x_preferred":[
        "\u041d\u043e\u0440\u0442\u0430\u043c\u0431\u0435\u0440\u043b\u0435\u043d\u0434"
    ],
    "name:deu_x_preferred":[
        "Northumberland"
    ],
    "name:eng_x_preferred":[
        "Northumberland"
    ],
    "name:eus_x_preferred":[
        "Northumberland"
    ],
    "name:fra_x_preferred":[
        "Northumberland"
    ],
    "name:hat_x_preferred":[
        "Northumberland"
    ],
    "name:hun_x_preferred":[
        "Northumberland"
    ],
    "name:jpn_x_preferred":[
        "\u30ce\u30fc\u30b5\u30f3\u30d0\u30fc\u30e9\u30f3\u30c9"
    ],
    "name:pol_x_preferred":[
        "Northumberland"
    ],
    "name:rus_x_preferred":[
        "\u041d\u043e\u0440\u0442\u0443\u043c\u0431\u0435\u0440\u043b\u0435\u043d\u0434"
    ],
    "name:spa_x_preferred":[
        "Northumberland"
    ],
    "name:tat_x_preferred":[
        "\u041d\u043e\u0440\u0442\u0430\u043c\u0431\u0435\u0440\u043b\u0435\u043d\u0434"
    ],
    "name:tur_x_preferred":[
        "Northumberland"
    ],
    "name:ukr_x_preferred":[
        "\u041d\u043e\u0440\u0442\u0430\u043c\u0431\u0435\u0440\u043b\u0435\u043d\u0434"
    ],
    "name:uzb_x_preferred":[
        "Northumberland"
    ],
    "qs_pg:aaroncc":"US",
    "qs_pg:gn_country":"US",
    "qs_pg:gn_fcode":"PPL",
    "qs_pg:gn_pop":0,
    "qs_pg:name":"Northumberland",
    "qs_pg:name_adm0":"United States",
    "qs_pg:name_adm1":"New York",
    "qs_pg:photos":6,
    "qs_pg:photos_1k":1,
    "qs_pg:photos_9k":1,
    "qs_pg:photos_9r":3,
    "qs_pg:photos_all":103,
    "qs_pg:photos_sr":1,
    "qs_pg:pop_sr":0,
    "qs_pg:qs_pg_placetype":"locality",
    "qs_pg:qs_pg_placetype_gp":"Town",
    "qs_pg:woe_adm0":23424977,
    "woe:adm0_id":23424977,
    "woe:name_adm0":"United States",
    "woe:name_adm1":"New York",
    "woe:placetype":"Town",
    "wof:name":"Northumberland",
    "wof:placetype":"locality",
    "wof:population":5159
},
  "geometry": {"coordinates":[-73.58817000000001,43.1273],"type":"Point"}
}