{
  "type": "Feature",
  "properties": {
    "gn:country":"US",
    "gn:fcode":"PPL",
    "gn:population":0,
    "iso:country":"US",
    "name:azb_x_preferred":[
        "\u0628\u0631\u0627\u0648\u0646\u0632\u0628\u0631\u0648"
    ],
    "name:cym_x_preferred":[
        "Brownsboro"
    ],
    "name:deu_x_preferred":[
        "Brownsboro"
    ],
    "name:eng_x_preferred":[
        "Brownsboro"
    ],
    "name:fas_x_preferred":[
        "\u0628\u0631\u0627\u0648\u0646\u0632\u0628\u0631\u0648"
    ],
    "name:fra_x_preferred":[
        "Brownsboro"
    ],
    "name:und_x_variant":[
        "Brownsborough"
    ],
    "name:zho_x_preferred":[
        "\u5e03\u6717\u65af\u535a\u7f85"
    ],
    "qs_pg:aaroncc":"US",
    "qs_pg:gn_country":"US",
    "qs_pg:gn_fcode":"PPL",
    "qs_pg:gn_pop":0,
    "qs_pg:name":"Brownsboro",
    "qs_pg:name_adm0":"United States",
    "qs_pg:name_adm1":"Alabama",
    "qs_pg:photos":202,
    "qs_pg:photos_1k":41,
    "qs_pg:photos_9k":1,
    "qs_pg:photos_9r":4,
    "qs_pg:photos_all":202,
    "qs_pg:photos_sr":4,
    "qs_pg:pop_sr":0,
    "qs_pg:qs_pg_placetype":"locality",
    "qs_pg:qs_pg_placetype_gp":"Town",
    "qs_pg:woe_adm0":23424977,
    "woe:adm0_id":23424977,
    "woe:name_adm0":"United States",
    "woe:name_adm1":"Alabama",
    "woe:placetype":"Town",
    "wof:name":"Brownsboro",
    "wof:placetype":"locality"
},
  "geometry": {"coordinates":[-86.44304,34.74926],"type":"Point"}
}