{
  "type": "Feature",
  "properties": {
    "gn:admin1_code":"FL",
    "gn:admin2_code":"113.0",
    "gn:asciiname":"Ward Basin",
    "gn:country_code":"US",
    "gn:dem":12,
    "gn:elevation":"2.0",
    "gn:feature_class":"P",
    "gn:feature_code":"PPL",
    "gn:name":"Ward Basin",
    "gn:population":0,
    "gn:timezone":"America/Chicago",
    "iso:country":"US",
    "wof:name":"Ward Basin",
    "wof:placetype":"locality"
},
  "geometry": {"coordinates":[-86.99691,30.58519],"type":"Point"}
}