{
  "type": "Feature",
  "properties": {
    "gn:country":"US",
    "gn:fcode":"PPLX",
    "gn:population":44610,
    "iso:country":"US",
    "qs_pg:aaroncc":"US",
    "qs_pg:gn_country":"US",
    "qs_pg:gn_fcode":"PPLX",
    "qs_pg:gn_pop":44610,
    "qs_pg:name":"Penn Hills",
    "qs_pg:photos_9r":0,
    "qs_pg:photos_sr":0,
    "qs_pg:pop_sr":7,
    "qs_pg:qs_pg_placetype":"neighbourhood",
    "wof:name":"Penn Hills",
    "wof:placetype":"neighbourhood",
    "wof:population":44610
},
  "geometry": {"coordinates":[-79.83922,40.50118],"type":"Point"}
}