{
  "type": "Feature",
  "properties": {
    "gn:admin1_code":"DE",
    "gn:admin2_code":"5.0",
    "gn:asciiname":"Lazy Lagoon Mobile Home Park",
    "gn:country_code":"US",
    "gn:dem":9,
    "gn:elevation":"11.0",
    "gn:feature_class":"P",
    "gn:feature_code":"PPL",
    "gn:name":"Lazy Lagoon Mobile Home Park",
    "gn:population":0,
    "gn:timezone":"America/New_York",
    "iso:country":"US",
    "wof:name":"Lazy Lagoon Mobile Home Park",
    "wof:placetype":"campus"
},
  "geometry": {"coordinates":[-75.23352,38.50261],"type":"Point"}
}