{
  "type": "Feature",
  "properties": {
    "gn:admin1_code":"FL",
    "gn:admin2_code":"57",
    "gn:asciiname":"West Pinecrest",
    "gn:country_code":"US",
    "gn:dem":47,
    "gn:elevation":"37.0",
    "gn:feature_class":"P",
    "gn:feature_code":"PPL",
    "gn:name":"West Pinecrest",
    "gn:population":0,
    "gn:timezone":"America/New_York",
    "iso:country":"US",
    "wof:name":"West Pinecrest",
    "wof:placetype":"locality"
},
  "geometry": {"coordinates":[-82.1521,28.0123],"type":"Point"}
}