{
  "type": "Feature",
  "properties": {
    "gn:elevation":296,
    "iso:country":"US",
    "name:eng_x_preferred":[
        "Overbrook"
    ],
    "name:fra_x_preferred":[
        "Overbrook"
    ],
    "name:nld_x_preferred":[
        "Overbrook"
    ],
    "name:und_x_variant":[
        "Over Brook"
    ],
    "qs:gn_adm0_cc":"US",
    "qs:gn_fcode":"PPL",
    "qs:gn_local":4580543,
    "qs:gn_nam_loc":"Greenville, Greenville, South Carolina, US",
    "qs:gn_namadm1":"SC",
    "qs:gn_name":"Overbrook",
    "qs:local_max":8320,
    "qs:local_sum":14160,
    "qs:localhoods":19,
    "qs:name":"Overbrook",
    "qs:name_adm0":"United States",
    "qs:name_adm1":"South Carolina",
    "qs:name_adm2":"Greenville",
    "qs:name_local":"Greenville",
    "qs:photo_max":23,
    "qs:photo_sum":85,
    "qs:placetype":"Suburb",
    "qs:quad_count":13,
    "qs:woe_adm0":23424977,
    "qs:woe_adm1":2347599,
    "qs:woe_adm2":12589822,
    "qs:woe_lau":0,
    "qs:woe_local":2414583,
    "qs:woe_ver":"7.10.0",
    "wof:lang":[
        "eng"
    ],
    "wof:name":"Overbrook",
    "wof:placetype":"neighbourhood",
    "wof:population":1403,
    "zs:blockids":[
        450450012052013,
        450450012052011,
        450450012052009,
        450450001002002,
        450450012042007,
        450450001002005,
        450450012052000,
        450450012042021,
        450450012051006,
        450450012052012,
        450450012042018,
        450450012042008,
        450450012051003,
        450450012042009,
        450450012042011,
        450450012052008,
        450450012052020,
        450450011014029,
        450450012052010,
        450450012051000,
        450450012042023,
        450450012042016,
        450450012052019,
        450450012052021,
        450450012052014,
        450450012052015,
        450450012051005,
        450450012042012,
        450450012052017,
        450450012051001,
        450450012052018,
        450450012042010,
        450450012042022,
        450450012051007,
        450450012042029
    ],
    "zs:housing10":787,
    "zs:pop10":1403
},
  "geometry": {"coordinates":[-82.376198,34.856515],"type":"Point"}
}