{
  "type": "Feature",
  "properties": {
    "gn:admin1_code":"MD",
    "gn:admin2_code":"35.0",
    "gn:asciiname":"Sayers Forest",
    "gn:country_code":"US",
    "gn:dem":6,
    "gn:elevation":"5.0",
    "gn:feature_class":"P",
    "gn:feature_code":"PPL",
    "gn:name":"Sayers Forest",
    "gn:population":0,
    "gn:timezone":"America/New_York",
    "iso:country":"US",
    "wof:name":"Sayers Forest",
    "wof:placetype":"locality"
},
  "geometry": {"coordinates":[-76.1705,38.93067],"type":"Point"}
}