{
  "type": "Feature",
  "properties": {
    "gn:admin1_code":"WV",
    "gn:admin2_code":"107",
    "gn:asciiname":"Bickel Estates",
    "gn:country_code":"US",
    "gn:dem":213,
    "gn:elevation":"217.0",
    "gn:feature_class":"P",
    "gn:feature_code":"PPL",
    "gn:name":"Bickel Estates",
    "gn:population":0,
    "gn:timezone":"America/New_York",
    "iso:country":"US",
    "wof:name":"Bickel Estates",
    "wof:placetype":"locality"
},
  "geometry": {"coordinates":[-81.58318,39.24869],"type":"Point"}
}