{
  "type": "Feature",
  "properties": {
    "iso:country":"US",
    "name:eng_x_preferred":[
        "East Broomfield"
    ],
    "qs:gn_local":0,
    "qs:local_max":2502,
    "qs:local_sum":10799,
    "qs:localhoods":32,
    "qs:name":"East Broomfield",
    "qs:name_adm0":"United States",
    "qs:name_adm1":"Colorado",
    "qs:name_adm2":"Broomfield",
    "qs:name_local":"Broomfield",
    "qs:photo_max":22,
    "qs:photo_sum":41,
    "qs:placetype":"Suburb",
    "qs:quad_count":5,
    "qs:woe_adm0":23424977,
    "qs:woe_adm1":2347564,
    "qs:woe_adm2":26343011,
    "qs:woe_lau":0,
    "qs:woe_local":2370243,
    "qs:woe_ver":"7.10.0",
    "wof:lang":[
        "eng"
    ],
    "wof:name":"East Broomfield",
    "wof:placetype":"neighbourhood",
    "wof:population":145,
    "zs:blockids":[
        80140302001044,
        80140302001043,
        80140302001048
    ],
    "zs:housing10":62,
    "zs:pop10":145
},
  "geometry": {"coordinates":[-105.08208399999999,39.915337],"type":"Point"}
}