{
  "type": "Feature",
  "properties": {
    "gn:admin1_code":"MD",
    "gn:admin2_code":"3.0",
    "gn:asciiname":"Drury",
    "gn:country_code":"US",
    "gn:dem":23,
    "gn:elevation":"13.0",
    "gn:feature_class":"P",
    "gn:feature_code":"PPL",
    "gn:name":"Drury",
    "gn:population":0,
    "gn:timezone":"America/New_York",
    "iso:country":"US",
    "name:deu_x_preferred":[
        "Drury"
    ],
    "name:fra_x_preferred":[
        "Drury"
    ],
    "name:pol_x_preferred":[
        "Drury"
    ],
    "name:rus_x_preferred":[
        "\u0414\u0440\u0443\u0440\u0438"
    ],
    "wof:name":"Drury",
    "wof:placetype":"locality"
},
  "geometry": {"coordinates":[-76.69274,38.81234],"type":"Point"}
}