{
  "type": "Feature",
  "properties": {
    "gn:admin1_code":"FL",
    "gn:admin2_code":"81.0",
    "gn:asciiname":"Rye",
    "gn:country_code":"US",
    "gn:dem":8,
    "gn:elevation":"3.0",
    "gn:feature_class":"P",
    "gn:feature_code":"PPL",
    "gn:name":"Rye",
    "gn:population":0,
    "gn:timezone":"America/New_York",
    "iso:country":"US",
    "name:zho_x_preferred":[
        "\u8cf4\u4f0a"
    ],
    "wof:name":"Rye",
    "wof:placetype":"locality"
},
  "geometry": {"coordinates":[-82.36787,27.51448],"type":"Point"}
}