{
  "type": "Feature",
  "properties": {
    "iso:country":"US",
    "name:eng_x_preferred":[
        "Country Club Woods"
    ],
    "wof:name":"Country Club Woods",
    "wof:placetype":"neighbourhood",
    "wof:population":23,
    "zs:area_m":124066.815723,
    "zs:blockids":[
        280890301085004
    ],
    "zs:housing10":20,
    "zs:label":"Country Club Woods",
    "zs:pop10":23
},
  "geometry": {"coordinates":[-90.10735200000001,32.400729],"type":"Point"}
}