{
  "type": "Feature",
  "properties": {
    "gn:admin1_code":"MD",
    "gn:admin2_code":"13.0",
    "gn:asciiname":"Chestnut Oaks",
    "gn:country_code":"US",
    "gn:dem":236,
    "gn:elevation":"230.0",
    "gn:feature_class":"P",
    "gn:feature_code":"PPL",
    "gn:name":"Chestnut Oaks",
    "gn:population":0,
    "gn:timezone":"America/New_York",
    "iso:country":"US",
    "wof:name":"Chestnut Oaks",
    "wof:placetype":"locality"
},
  "geometry": {"coordinates":[-77.02804,39.41955],"type":"Point"}
}