{
  "type": "Feature",
  "properties": {
    "gn:admin1_code":"WV",
    "gn:admin2_code":"17.0",
    "gn:asciiname":"Sedalia",
    "gn:country_code":"US",
    "gn:dem":260,
    "gn:elevation":"257.0",
    "gn:feature_class":"P",
    "gn:feature_code":"PPL",
    "gn:name":"Sedalia",
    "gn:population":0,
    "gn:timezone":"America/New_York",
    "iso:country":"US",
    "wof:name":"Sedalia",
    "wof:placetype":"locality"
},
  "geometry": {"coordinates":[-80.57871,39.35981],"type":"Point"}
}