{
  "type": "Feature",
  "properties": {
    "gn:admin1_code":"IA",
    "gn:admin2_code":"177.0",
    "gn:admin3_code":"94275.0",
    "gn:asciiname":"Utica",
    "gn:country_code":"US",
    "gn:dem":225,
    "gn:elevation":"226.0",
    "gn:feature_class":"P",
    "gn:feature_code":"PPL",
    "gn:name":"Utica",
    "gn:population":0,
    "gn:timezone":"America/Chicago",
    "iso:country":"US",
    "name:bul_x_preferred":[
        "\u042e\u0442\u0438\u043a\u0430"
    ],
    "name:cat_x_preferred":[
        "Utica"
    ],
    "name:ceb_x_preferred":[
        "Utica"
    ],
    "name:cym_x_preferred":[
        "Utica"
    ],
    "name:deu_x_preferred":[
        "Utica"
    ],
    "name:fas_x_preferred":[
        "\u06cc\u0648\u062a\u06cc\u06a9\u0627"
    ],
    "name:fra_x_preferred":[
        "Utica"
    ],
    "name:ita_x_preferred":[
        "Utica"
    ],
    "name:jpn_x_preferred":[
        "\u30e6\u30fc\u30c6\u30a3\u30ab"
    ],
    "name:lat_x_preferred":[
        "Utica"
    ],
    "name:nld_x_preferred":[
        "Utica"
    ],
    "name:nor_x_preferred":[
        "Utica"
    ],
    "name:pol_x_preferred":[
        "Utica"
    ],
    "name:por_x_preferred":[
        "Utica"
    ],
    "name:rus_x_preferred":[
        "\u042e\u0442\u0438\u043a\u0430"
    ],
    "name:spa_x_preferred":[
        "\u00datica"
    ],
    "name:srp_x_preferred":[
        "\u0408\u0443\u0442\u0438\u043a\u0430"
    ],
    "name:swe_x_preferred":[
        "Utica"
    ],
    "name:tur_x_preferred":[
        "Utica"
    ],
    "name:vie_x_preferred":[
        "Utica"
    ],
    "name:vol_x_preferred":[
        "Utica"
    ],
    "wof:name":"Utica",
    "wof:placetype":"locality"
},
  "geometry": {"coordinates":[-91.83489,40.81475],"type":"Point"}
}