{
  "type": "Feature",
  "properties": {
    "gn:gn_country":"US",
    "gn:gn_fcode":"PPL",
    "gn:gn_pop":0,
    "iso:country":"US",
    "name:arg_x_preferred":[
        "White Plains"
    ],
    "name:cat_x_preferred":[
        "White Plains"
    ],
    "name:ceb_x_preferred":[
        "White Plains"
    ],
    "name:ces_x_preferred":[
        "White Plains"
    ],
    "name:deu_x_preferred":[
        "White Plains"
    ],
    "name:fra_x_preferred":[
        "White Plains"
    ],
    "name:ita_x_preferred":[
        "White Plains"
    ],
    "name:jpn_x_preferred":[
        "\u30db\u30ef\u30a4\u30c8\u30fb\u30d7\u30ec\u30a4\u30f3\u30ba"
    ],
    "name:kor_x_preferred":[
        "\ud654\uc774\ud2b8\ud50c\ub808\uc778\uc2a4"
    ],
    "name:nld_x_preferred":[
        "White Plains"
    ],
    "name:nor_x_preferred":[
        "White Plains"
    ],
    "name:pol_x_preferred":[
        "White Plains"
    ],
    "name:por_x_preferred":[
        "White Plains"
    ],
    "name:slk_x_preferred":[
        "White Plains"
    ],
    "name:spa_x_preferred":[
        "White Plains"
    ],
    "name:srp_x_preferred":[
        "\u0412\u0430\u0458\u0442 \u041f\u043b\u0435\u0458\u043d\u0441"
    ],
    "name:swe_x_preferred":[
        "White Plains"
    ],
    "name:urd_x_preferred":[
        "\u0648\u0627\u0626\u0679 \u067e\u0644\u06cc\u0646\u0632"
    ],
    "name:vol_x_preferred":[
        "White Plains"
    ],
    "name:zho_x_preferred":[
        "\u6000\u7279\u666e\u83b1\u6069\u65af"
    ],
    "qs_pg:aaroncc":"US",
    "qs_pg:gn_country":"US",
    "qs_pg:gn_fcode":"PPL",
    "qs_pg:gn_pop":0,
    "qs_pg:name":"White Plains",
    "qs_pg:name_adm0":"United States",
    "qs_pg:name_adm1":"Maryland",
    "qs_pg:photos":10,
    "qs_pg:photos_1k":2,
    "qs_pg:photos_9k":1,
    "qs_pg:photos_9r":1,
    "qs_pg:photos_all":10,
    "qs_pg:photos_sr":1,
    "qs_pg:pop_sr":0,
    "qs_pg:qs_pg_placetype":"locality",
    "qs_pg:qs_pg_placetype_gp":"Town",
    "qs_pg:woe_adm0":23424977,
    "woe:adm0_id":23424977,
    "woe:name_adm0":"United States",
    "woe:name_adm1":"Maryland",
    "woe:placetype":"Town",
    "wof:name":"White Plains",
    "wof:placetype":"locality"
},
  "geometry": {"coordinates":[-75.54576,38.37178],"type":"Point"}
}