{
  "type": "Feature",
  "properties": {
    "gn:admin1_code":"NC",
    "gn:admin2_code":"199",
    "gn:admin3_code":"90980.0",
    "gn:asciiname":"Hawk Branch",
    "gn:country_code":"US",
    "gn:dem":843,
    "gn:elevation":"843.0",
    "gn:feature_class":"P",
    "gn:feature_code":"PPL",
    "gn:name":"Hawk Branch",
    "gn:population":0,
    "gn:timezone":"America/New_York",
    "iso:country":"US",
    "wof:name":"Hawk Branch",
    "wof:placetype":"locality"
},
  "geometry": {"coordinates":[-82.37151999999998,35.964],"type":"Point"}
}