{
  "type": "Feature",
  "properties": {
    "gn:admin1_code":"FL",
    "gn:admin2_code":"57",
    "gn:asciiname":"Clewis Muck Farms",
    "gn:country_code":"US",
    "gn:dem":12,
    "gn:elevation":"5.0",
    "gn:feature_class":"P",
    "gn:feature_code":"PPL",
    "gn:name":"Clewis Muck Farms",
    "gn:population":0,
    "gn:timezone":"America/New_York",
    "iso:country":"US",
    "wof:name":"Clewis Muck Farms",
    "wof:placetype":"locality"
},
  "geometry": {"coordinates":[-82.3493,28.0213],"type":"Point"}
}