{
  "type": "Feature",
  "properties": {
    "gn:admin1_code":"AL",
    "gn:admin2_code":"105.0",
    "gn:asciiname":"Perryville",
    "gn:country_code":"US",
    "gn:dem":124,
    "gn:elevation":"120.0",
    "gn:feature_class":"P",
    "gn:feature_code":"PPL",
    "gn:name":"Perryville",
    "gn:population":0,
    "gn:timezone":"America/Chicago",
    "iso:country":"US",
    "name:fas_x_preferred":[
        "\u067e\u0631\u06cc\u0648\u06cc\u0644"
    ],
    "name:zho_x_preferred":[
        "\u4f69\u91cc\u7dad\u723e"
    ],
    "wof:name":"Perryville",
    "wof:placetype":"locality"
},
  "geometry": {"coordinates":[-87.11416,32.6168],"type":"Point"}
}