{
  "type": "Feature",
  "properties": {
    "gn:admin1_code":"DE",
    "gn:admin2_code":"3.0",
    "gn:asciiname":"Belmoor",
    "gn:country_code":"US",
    "gn:dem":24,
    "gn:elevation":"24.0",
    "gn:feature_class":"P",
    "gn:feature_code":"PPL",
    "gn:name":"Belmoor",
    "gn:population":0,
    "gn:timezone":"America/New_York",
    "iso:country":"US",
    "name:eng_x_preferred":[
        "Belmoor"
    ],
    "name:und_x_variant":[
        "Bellemoor"
    ],
    "wof:name":"Belmoor",
    "wof:placetype":"locality"
},
  "geometry": {"coordinates":[-75.59269999999999,39.72511],"type":"Point"}
}