{
  "type": "Feature",
  "properties": {
    "gn:admin1_code":"VA",
    "gn:admin2_code":"179",
    "gn:asciiname":"Skidmore Corner",
    "gn:country_code":"US",
    "gn:dem":103,
    "gn:elevation":"95.0",
    "gn:feature_class":"P",
    "gn:feature_code":"PPL",
    "gn:name":"Skidmore Corner",
    "gn:population":0,
    "gn:timezone":"America/New_York",
    "iso:country":"US",
    "wof:name":"Skidmore Corner",
    "wof:placetype":"locality"
},
  "geometry": {"coordinates":[-77.52136999999998,38.46818],"type":"Point"}
}