{
  "type": "Feature",
  "properties": {
    "iso:country":"US",
    "name:eng_x_preferred":[
        "Winkler 10 acres"
    ],
    "wof:name":"Winkler 10 acres",
    "wof:placetype":"neighbourhood",
    "wof:population":836,
    "zs:area_m":15397873.813207,
    "zs:blockids":[
        120710019074006,
        120710019071018,
        120710019071011,
        120710019071023,
        120710019071013,
        120710019071049,
        120710019071017,
        120710019071041,
        120710019071010,
        120710019071019,
        120710019071040,
        120710019071016,
        120710019071042,
        120710019071053,
        120710019071050,
        120710019071014,
        120710019071015,
        120710019071022,
        120710019071006,
        120710019071007
    ],
    "zs:housing10":847,
    "zs:label":"Winkler 10 acres",
    "zs:pop10":836
},
  "geometry": {"coordinates":[-81.89280599999999,26.466587],"type":"Point"}
}