{
  "type": "Feature",
  "properties": {
    "iso:country":"US",
    "name:eng_x_preferred":[
        "Tamiami Square"
    ],
    "wof:name":"Tamiami Square",
    "wof:placetype":"neighbourhood",
    "wof:population":2669,
    "zs:area_m":3237444.624821,
    "zs:blockids":[
        120710502051013,
        120710502081021,
        120710501062045,
        120710501062040,
        120710502052002,
        120710502081027,
        120710502052006,
        120710502051016,
        120710502051017,
        120710502052005,
        120710502051010,
        120710502081029,
        120710502051015,
        120710502051023,
        120710502063005,
        120710502081030,
        120710502063008,
        120710502081020,
        120710502081034,
        120710501062043,
        120710501031003,
        120710502081033,
        120710501062037,
        120710502081023,
        120710501062038,
        120710501062044,
        120710502052004,
        120710502051008,
        120710502051042,
        120710502051040,
        120710501062035,
        120710501062042,
        120710502081024,
        120710502051039,
        120710501062036,
        120710501062039,
        120710502051006,
        120710502051009,
        120710502051012,
        120710502051014,
        120710502051022,
        120710501031001,
        120710502081022,
        120710502081028,
        120710502051011,
        120710502051034,
        120710501062041,
        120710502052003,
        120710502051019,
        120710502051031,
        120710502051018,
        120710502051041,
        120710502051033,
        120710502051001,
        120710502051007
    ],
    "zs:housing10":1514,
    "zs:label":"Tamiami Square",
    "zs:pop10":2669
},
  "geometry": {"coordinates":[-81.835216,26.483248],"type":"Point"}
}