{
  "type": "Feature",
  "properties": {
    "gn:admin1_code":"WV",
    "gn:admin2_code":"53",
    "gn:asciiname":"Mercers Bottom",
    "gn:country_code":"US",
    "gn:dem":178,
    "gn:elevation":"178.0",
    "gn:feature_class":"P",
    "gn:feature_code":"PPL",
    "gn:name":"Mercers Bottom",
    "gn:population":0,
    "gn:timezone":"America/New_York",
    "iso:country":"US",
    "name:eng_x_preferred":[
        "Mercers Bottom"
    ],
    "name:und_x_variant":[
        "Mercer Bottom"
    ],
    "wof:name":"Mercers Bottom",
    "wof:placetype":"locality"
},
  "geometry": {"coordinates":[-82.16237,38.64481],"type":"Point"}
}