{
  "type": "Feature",
  "properties": {
    "gn:admin1_code":"OH",
    "gn:admin2_code":"9.0",
    "gn:admin3_code":"44590.0",
    "gn:asciiname":"Anthony",
    "gn:country_code":"US",
    "gn:dem":277,
    "gn:elevation":"280.0",
    "gn:feature_class":"P",
    "gn:feature_code":"PPL",
    "gn:name":"Anthony",
    "gn:population":0,
    "gn:timezone":"America/New_York",
    "iso:country":"US",
    "name:ara_x_preferred":[
        "\u0623\u0646\u062a\u0648\u0646\u064a"
    ],
    "name:bre_x_preferred":[
        "Anthony"
    ],
    "name:ceb_x_preferred":[
        "Anthony"
    ],
    "name:deu_x_preferred":[
        "Anthony"
    ],
    "name:fin_x_preferred":[
        "Anthony"
    ],
    "name:fra_x_preferred":[
        "Anthony"
    ],
    "name:heb_x_preferred":[
        "\u05d0\u05e0\u05ea\u05d5\u05e0\u05d9"
    ],
    "name:ita_x_preferred":[
        "Anthony"
    ],
    "name:jpn_x_preferred":[
        "\u30a2\u30f3\u30bd\u30cb\u30fc"
    ],
    "name:kor_x_preferred":[
        "\uc564\uc11c\ub2c8"
    ],
    "name:nld_x_preferred":[
        "Anthony"
    ],
    "name:pol_x_preferred":[
        "Anthony"
    ],
    "name:por_x_preferred":[
        "Anthony"
    ],
    "name:rus_x_preferred":[
        "\u0410\u043d\u0442\u043e\u043d\u0438"
    ],
    "name:spa_x_preferred":[
        "Anthony"
    ],
    "name:srp_x_preferred":[
        "\u0415\u043d\u0442\u043e\u043d\u0438"
    ],
    "name:vie_x_preferred":[
        "Anthony"
    ],
    "name:vol_x_preferred":[
        "Anthony"
    ],
    "name:zho_x_preferred":[
        "\u5b89\u4e1c\u5c3c\u5965"
    ],
    "wof:name":"Anthony",
    "wof:placetype":"locality"
},
  "geometry": {"coordinates":[-81.98236,39.23619],"type":"Point"}
}