{
  "type": "Feature",
  "properties": {
    "gn:admin1_code":"SC",
    "gn:admin2_code":"31.0",
    "gn:asciiname":"Kingsville Heights",
    "gn:country_code":"US",
    "gn:dem":69,
    "gn:elevation":"65.0",
    "gn:feature_class":"P",
    "gn:feature_code":"PPL",
    "gn:name":"Kingsville Heights",
    "gn:population":0,
    "gn:timezone":"America/New_York",
    "iso:country":"US",
    "wof:name":"Kingsville Heights",
    "wof:placetype":"locality"
},
  "geometry": {"coordinates":[-80.07646,34.34043],"type":"Point"}
}