{
  "type": "Feature",
  "properties": {
    "gn:admin1_code":"VA",
    "gn:admin2_code":"131",
    "gn:asciiname":"Middletown",
    "gn:country_code":"US",
    "gn:dem":11,
    "gn:elevation":"10.0",
    "gn:feature_class":"P",
    "gn:feature_code":"PPL",
    "gn:name":"Middletown",
    "gn:population":0,
    "gn:timezone":"America/New_York",
    "iso:country":"US",
    "name:eng_x_preferred":[
        "Middletown"
    ],
    "name:und_x_variant":[
        "Senseny Town"
    ],
    "wof:name":"Middletown",
    "wof:placetype":"locality"
},
  "geometry": {"coordinates":[-75.86743,37.48402],"type":"Point"}
}