{
  "type": "Feature",
  "properties": {
    "gn:admin1_code":"MD",
    "gn:admin2_code":"25.0",
    "gn:asciiname":"Mill Green Acres",
    "gn:country_code":"US",
    "gn:dem":100,
    "gn:elevation":"96.0",
    "gn:feature_class":"P",
    "gn:feature_code":"PPL",
    "gn:name":"Mill Green Acres",
    "gn:population":0,
    "gn:timezone":"America/New_York",
    "iso:country":"US",
    "wof:name":"Mill Green Acres",
    "wof:placetype":"locality"
},
  "geometry": {"coordinates":[-76.30301,39.65733],"type":"Point"}
}