{
  "type": "Feature",
  "properties": {
    "gn:admin1_code":"MI",
    "gn:admin2_code":"145.0",
    "gn:admin3_code":"68340.0",
    "gn:asciiname":"Iva",
    "gn:country_code":"US",
    "gn:dem":198,
    "gn:elevation":"197.0",
    "gn:feature_class":"P",
    "gn:feature_code":"PPL",
    "gn:name":"Iva",
    "gn:population":0,
    "gn:timezone":"America/Detroit",
    "iso:country":"US",
    "name:bos_x_preferred":[
        "Iva"
    ],
    "name:ceb_x_preferred":[
        "Iva"
    ],
    "name:fra_x_preferred":[
        "Iva"
    ],
    "name:ita_x_preferred":[
        "IVA"
    ],
    "name:nld_x_preferred":[
        "Iva"
    ],
    "name:pol_x_preferred":[
        "Iva"
    ],
    "name:por_x_preferred":[
        "Iva"
    ],
    "name:slv_x_preferred":[
        "Iva"
    ],
    "name:spa_x_preferred":[
        "Iva"
    ],
    "name:srp_x_preferred":[
        "Iva"
    ],
    "wof:name":"Iva",
    "wof:placetype":"locality"
},
  "geometry": {"coordinates":[-84.26943,43.46336],"type":"Point"}
}