{
  "type": "Feature",
  "properties": {
    "gn:admin1_code":"WA",
    "gn:admin2_code":"49.0",
    "gn:asciiname":"Holcomb",
    "gn:country_code":"US",
    "gn:dem":34,
    "gn:elevation":"35.0",
    "gn:feature_class":"P",
    "gn:feature_code":"PPL",
    "gn:name":"Holcomb",
    "gn:population":0,
    "gn:timezone":"America/Los_Angeles",
    "iso:country":"US",
    "name:fas_x_preferred":[
        "\u0647\u0648\u0644\u06a9\u0648\u0645\u0628"
    ],
    "name:spa_x_preferred":[
        "Holcomb"
    ],
    "wof:name":"Holcomb",
    "wof:placetype":"locality"
},
  "geometry": {"coordinates":[-123.61738,46.57205],"type":"Point"}
}