{
  "type": "Feature",
  "properties": {
    "iso:country":"US",
    "name:ceb_x_preferred":[
        "Highwood"
    ],
    "name:deu_x_preferred":[
        "Highwood"
    ],
    "name:eng_x_preferred":[
        "Highwood"
    ],
    "name:eng_x_variant":[
        "Hamden Plains"
    ],
    "name:ita_x_preferred":[
        "Highwood"
    ],
    "name:nld_x_preferred":[
        "Highwood"
    ],
    "name:pol_x_preferred":[
        "Highwood"
    ],
    "name:por_x_preferred":[
        "Highwood"
    ],
    "name:srp_x_preferred":[
        "\u0425\u0430\u0458\u0432\u0443\u0434"
    ],
    "name:ukr_x_preferred":[
        "\u0413\u0430\u0439\u0432\u0443\u0434"
    ],
    "name:vol_x_preferred":[
        "Highwood"
    ],
    "qs:gn_adm0_cc":"US",
    "qs:gn_local":4839366,
    "qs:gn_nam_loc":"New Haven, New Haven, Connecticut, US",
    "qs:gn_namadm1":"CT",
    "qs:local_max":11609,
    "qs:local_sum":24771,
    "qs:localhoods":21,
    "qs:name":"Highwood",
    "qs:name_adm0":"United States",
    "qs:name_adm1":"Connecticut",
    "qs:name_adm2":"New Haven",
    "qs:name_en":"Highwood",
    "qs:name_local":"New Haven",
    "qs:photo_max":432,
    "qs:photo_sum":749,
    "qs:placetype":"Suburb",
    "qs:quad_count":22,
    "qs:woe_adm0":23424977,
    "qs:woe_adm1":2347565,
    "qs:woe_adm2":12587795,
    "qs:woe_lau":0,
    "qs:woe_local":2458410,
    "qs:woe_ver":"7.3.1",
    "wd:wordcount":74,
    "wof:name":"Highwood",
    "wof:placetype":"neighbourhood"
},
  "geometry": {"coordinates":[-72.935192,41.347043],"type":"Point"}
}