{
  "type": "Feature",
  "properties": {
    "gn:elevation":9,
    "iso:country":"US",
    "name:eng_x_preferred":[
        "Essex Falls"
    ],
    "name:eng_x_variant":[
        "Essex Fls"
    ],
    "qs:gn_adm0_cc":"US",
    "qs:gn_fcode":"PPL",
    "qs:gn_local":4935946,
    "qs:gn_nam_loc":"Essex, Essex, Massachusetts, US",
    "qs:gn_namadm1":"MA",
    "qs:gn_name":"Essex Falls",
    "qs:local_max":424,
    "qs:local_sum":475,
    "qs:localhoods":2,
    "qs:name":"Essex Falls",
    "qs:name_adm0":"United States",
    "qs:name_adm1":"Massachusetts",
    "qs:name_adm2":"Essex",
    "qs:name_local":"Essex",
    "qs:photo_max":23,
    "qs:photo_sum":51,
    "qs:placetype":"Suburb",
    "qs:quad_count":7,
    "qs:woe_adm0":23424977,
    "qs:woe_adm1":2347580,
    "qs:woe_adm2":12588704,
    "qs:woe_lau":0,
    "qs:woe_local":2400270,
    "qs:woe_ver":"7.10.0",
    "wof:lang":[
        "eng"
    ],
    "wof:name":"Essex Falls",
    "wof:placetype":"neighbourhood",
    "wof:population":2569,
    "zs:blockids":[
        250092221001057,
        250092221003009,
        250092151011009,
        250092221003004,
        250092151011019,
        250092221003006,
        250092151011007,
        250092151011029,
        250092221003011,
        250092151011017,
        250092221003002,
        250092221003013,
        250092151011006,
        250092221003018,
        250092221001056,
        250092151011025,
        250092151011018,
        250092221003008,
        250092221003019,
        250092221003014,
        250092221003005,
        250092221003010,
        250092151011020,
        250092151011021,
        250092221003015,
        250092151011004,
        250092221003012,
        250092151011008,
        250092221003007,
        250092221001058,
        250092151011003,
        250092221003016,
        250092221002029,
        250092151011005,
        250092221003017,
        250092221003003
    ],
    "zs:housing10":1005,
    "zs:pop10":2569
},
  "geometry": {"coordinates":[-70.812325,42.614978],"type":"Point"}
}