{
  "type": "Feature",
  "properties": {
    "gn:admin1_code":"NM",
    "gn:admin2_code":"61",
    "gn:asciiname":"Tome Designated Place",
    "gn:country_code":"US",
    "gn:dem":1472,
    "gn:elevation":"1472.0",
    "gn:feature_class":"P",
    "gn:feature_code":"PPL",
    "gn:name":"Tome Designated Place",
    "gn:population":0,
    "gn:timezone":"America/Denver",
    "iso:country":"US",
    "name:eng_x_preferred":[
        "Tome Designated Place"
    ],
    "name:und_x_variant":[
        "Tome-Adelino CDP"
    ],
    "wof:name":"Tome Designated Place",
    "wof:placetype":"locality"
},
  "geometry": {"coordinates":[-106.72342,34.73393],"type":"Point"}
}