{
  "type": "Feature",
  "properties": {
    "gn:admin1_code":"IN",
    "gn:admin2_code":"61.0",
    "gn:admin3_code":"31810.0",
    "gn:asciiname":"Kings Store",
    "gn:country_code":"US",
    "gn:dem":212,
    "gn:elevation":"215.0",
    "gn:feature_class":"P",
    "gn:feature_code":"PPL",
    "gn:name":"Kings Store",
    "gn:population":0,
    "gn:timezone":"America/Kentucky/Louisville",
    "iso:country":"US",
    "wof:name":"Kings Store",
    "wof:placetype":"locality"
},
  "geometry": {"coordinates":[-86.06108,38.20368],"type":"Point"}
}