{
  "type": "Feature",
  "properties": {
    "gn:admin1_code":"TX",
    "gn:admin2_code":"215",
    "gn:asciiname":"L D Morgan's Colonia",
    "gn:country_code":"US",
    "gn:dem":23,
    "gn:elevation":"18.0",
    "gn:feature_class":"P",
    "gn:feature_code":"PPL",
    "gn:name":"L D Morgan's Colonia",
    "gn:population":0,
    "gn:timezone":"America/Chicago",
    "iso:country":"US",
    "name:eng_x_preferred":[
        "L D Morgan's Colonia"
    ],
    "name:und_x_variant":[
        "L D Morgan's Subdivision Colonia"
    ],
    "wof:name":"L D Morgan's Colonia",
    "wof:placetype":"locality"
},
  "geometry": {"coordinates":[-97.95834000000001,26.29229],"type":"Point"}
}