{
  "type": "Feature",
  "properties": {
    "gn:admin1_code":"TX",
    "gn:admin2_code":"215.0",
    "gn:asciiname":"Palm Acres Estates Colonia",
    "gn:country_code":"US",
    "gn:dem":47,
    "gn:elevation":"43.0",
    "gn:feature_class":"P",
    "gn:feature_code":"PPL",
    "gn:name":"Palm Acres Estates Colonia",
    "gn:population":0,
    "gn:timezone":"America/Chicago",
    "iso:country":"US",
    "wof:name":"Palm Acres Estates Colonia",
    "wof:placetype":"locality"
},
  "geometry": {"coordinates":[-98.36835000000001,26.24035],"type":"Point"}
}