{
  "type": "Feature",
  "properties": {
    "gn:admin1_code":"WI",
    "gn:admin2_code":"27.0",
    "gn:admin3_code":"34000.0",
    "gn:asciiname":"Hochheim",
    "gn:country_code":"US",
    "gn:dem":358,
    "gn:elevation":"355.0",
    "gn:feature_class":"P",
    "gn:feature_code":"PPL",
    "gn:name":"Hochheim",
    "gn:population":0,
    "gn:timezone":"America/Chicago",
    "iso:country":"US",
    "wof:name":"Hochheim",
    "wof:placetype":"locality"
},
  "geometry": {"coordinates":[-88.46926999999999,43.45694],"type":"Point"}
}