{
  "type": "Feature",
  "properties": {
    "gn:elevation":1,
    "iso:country":"US",
    "name:eng_x_preferred":[
        "Tracy Terrace"
    ],
    "qs:gn_adm0_cc":"US",
    "qs:gn_fcode":"PPL",
    "qs:gn_local":4157827,
    "qs:gn_nam_loc":"haines city",
    "qs:gn_namadm1":"FL",
    "qs:gn_name":"Gray Terrace",
    "qs:local_max":218,
    "qs:local_sum":334,
    "qs:localhoods":4,
    "qs:name":"Tracy Terrace",
    "qs:name_adm0":"United States",
    "qs:name_adm1":"Florida",
    "qs:name_adm2":"Polk",
    "qs:name_local":"Haines City",
    "qs:photo_max":3,
    "qs:photo_sum":3,
    "qs:placetype":"Suburb",
    "qs:quad_count":1,
    "qs:woe_adm0":23424977,
    "qs:woe_adm1":2347568,
    "qs:woe_adm2":12587855,
    "qs:woe_lau":0,
    "qs:woe_local":2416093,
    "qs:woe_ver":"7.10.0",
    "wof:lang":[
        "eng"
    ],
    "wof:name":"Tracy Terrace",
    "wof:placetype":"neighbourhood",
    "wof:population":200,
    "zs:blockids":[
        121050127001025,
        121050127001070,
        121050127001019,
        121050127002031,
        121050127001001,
        121050127002033,
        121050127001018,
        121050127002032
    ],
    "zs:housing10":119,
    "zs:pop10":200
},
  "geometry": {"coordinates":[-81.642151,28.113171],"type":"Point"}
}