{
  "type": "Feature",
  "properties": {
    "iso:country":"US",
    "name:eng_x_preferred":[
        "Suicide Corners"
    ],
    "wof:name":"Suicide Corners",
    "wof:placetype":"neighbourhood",
    "wof:population":76,
    "zs:area_m":5802071.467133,
    "zs:blockids":[
        360379513004019,
        360379513004022
    ],
    "zs:housing10":29,
    "zs:label":"Suicide Corners",
    "zs:pop10":76
},
  "geometry": {"coordinates":[-78.118235,42.888728],"type":"Point"}
}