{
  "type": "Feature",
  "properties": {
    "gn:admin1_code":"PA",
    "gn:admin2_code":"125.0",
    "gn:admin3_code":"12848.0",
    "gn:asciiname":"McNary",
    "gn:country_code":"US",
    "gn:dem":329,
    "gn:elevation":"328.0",
    "gn:feature_class":"P",
    "gn:feature_code":"PPL",
    "gn:name":"McNary",
    "gn:population":0,
    "gn:timezone":"America/New_York",
    "iso:country":"US",
    "name:cat_x_preferred":[
        "McNary"
    ],
    "name:ceb_x_preferred":[
        "McNary"
    ],
    "name:deu_x_preferred":[
        "McNary"
    ],
    "name:ita_x_preferred":[
        "McNary"
    ],
    "name:nld_x_preferred":[
        "McNary"
    ],
    "name:pol_x_preferred":[
        "McNary"
    ],
    "name:por_x_preferred":[
        "McNary"
    ],
    "name:srp_x_preferred":[
        "\u041c\u0430\u043a\u043d\u0435\u0440\u0438"
    ],
    "name:ukr_x_preferred":[
        "\u041c\u0430\u043a\u041d\u0435\u0440\u0456"
    ],
    "name:vol_x_preferred":[
        "McNary"
    ],
    "wof:name":"McNary",
    "wof:placetype":"locality"
},
  "geometry": {"coordinates":[-80.21895000000001,40.2759],"type":"Point"}
}