{
  "type": "Feature",
  "properties": {
    "gn:country":"US",
    "gn:fcode":"PPL",
    "gn:population":0,
    "iso:country":"US",
    "name:deu_x_preferred":[
        "Greely"
    ],
    "name:eng_x_preferred":[
        "Greely"
    ],
    "name:und_x_variant":[
        "Greeley"
    ],
    "qs_pg:aaroncc":"US",
    "qs_pg:gn_country":"US",
    "qs_pg:gn_fcode":"PPL",
    "qs_pg:gn_pop":0,
    "qs_pg:name":"Greely",
    "qs_pg:name_adm0":"United States",
    "qs_pg:name_adm1":"Georgia",
    "qs_pg:photos":34,
    "qs_pg:photos_1k":7,
    "qs_pg:photos_9k":1,
    "qs_pg:photos_9r":2,
    "qs_pg:photos_all":34,
    "qs_pg:photos_sr":2,
    "qs_pg:pop_sr":0,
    "qs_pg:qs_pg_placetype":"locality",
    "qs_pg:qs_pg_placetype_gp":"Town",
    "qs_pg:woe_adm0":23424977,
    "woe:adm0_id":23424977,
    "woe:name_adm0":"United States",
    "woe:name_adm1":"Georgia",
    "woe:placetype":"Town",
    "wof:name":"Greely",
    "wof:placetype":"locality"
},
  "geometry": {"coordinates":[-84.64493,34.39315],"type":"Point"}
}