{
  "type": "Feature",
  "properties": {
    "gn:elevation":27,
    "gn:population":24836,
    "iso:country":"US",
    "name:azb_x_preferred":[
        "\u0648\u0627\u06cc\u0646\u06cc\u0627\u0631\u062f"
    ],
    "name:cat_x_preferred":[
        "Vineyard"
    ],
    "name:ceb_x_preferred":[
        "Vineyard"
    ],
    "name:che_x_preferred":[
        "\u0412\u0430\u0439\u043d\u044f\u0440\u0434"
    ],
    "name:deu_x_preferred":[
        "Vineyard"
    ],
    "name:eng_x_preferred":[
        "Vineyard"
    ],
    "name:eus_x_preferred":[
        "Vineyard"
    ],
    "name:fas_x_preferred":[
        "\u0648\u0627\u06cc\u0646\u06cc\u0627\u0631\u062f"
    ],
    "name:fra_x_preferred":[
        "Vineyard"
    ],
    "name:gle_x_preferred":[
        "Vineyard"
    ],
    "name:hrv_x_preferred":[
        "Vineyard"
    ],
    "name:ita_x_preferred":[
        "Vineyard"
    ],
    "name:lld_x_preferred":[
        "Vineyard"
    ],
    "name:nan_x_preferred":[
        "Vineyard"
    ],
    "name:new_x_preferred":[
        "\u092d\u093e\u0907\u0928\u092f\u093e\u0930\u094d\u0921"
    ],
    "name:nld_x_preferred":[
        "Vineyard"
    ],
    "name:pol_x_preferred":[
        "Vineyard"
    ],
    "name:por_x_preferred":[
        "Vineyard"
    ],
    "name:spa_x_preferred":[
        "Vineyard"
    ],
    "name:srp_x_preferred":[
        "\u0412\u0438\u043d\u0458\u0430\u0440\u0434"
    ],
    "name:swe_x_preferred":[
        "Vineyard"
    ],
    "name:tat_x_preferred":[
        "\u0412\u0430\u0439\u043d\u044f\u0440\u0434"
    ],
    "name:tur_x_preferred":[
        "Vineyard"
    ],
    "name:ukr_x_preferred":[
        "\u0412\u0430\u0439\u043d\u044f\u0440\u0434"
    ],
    "name:vol_x_preferred":[
        "Vineyard"
    ],
    "name:zho_x_preferred":[
        "\u97cb\u6069\u4e9e\u5fb7"
    ],
    "qs:gn_adm0_cc":"US",
    "qs:gn_fcode":"PPL",
    "qs:gn_local":5388881,
    "qs:gn_nam_loc":"Roseville, Placer, California, US",
    "qs:gn_namadm1":"CA",
    "qs:gn_name":"Vineyard",
    "qs:local_max":728,
    "qs:local_sum":5764,
    "qs:localhoods":35,
    "qs:name":"Vineyard",
    "qs:name_adm0":"United States",
    "qs:name_adm1":"California",
    "qs:name_adm2":"Placer",
    "qs:name_local":"Roseville",
    "qs:photo_max":3,
    "qs:photo_sum":4,
    "qs:placetype":"Suburb",
    "qs:quad_count":2,
    "qs:woe_adm0":23424977,
    "qs:woe_adm1":2347563,
    "qs:woe_adm2":12587700,
    "qs:woe_lau":0,
    "qs:woe_local":2484861,
    "qs:woe_ver":"7.10.0",
    "wof:lang":[
        "eng"
    ],
    "wof:name":"Vineyard",
    "wof:placetype":"neighbourhood",
    "wof:population":24836,
    "zs:blockids":[
        60610209082012,
        60610209081008,
        60610209082014,
        60610209082016,
        60610209082015,
        60610209081007,
        60610209081009,
        60610209083029
    ],
    "zs:housing10":465,
    "zs:pop10":1040
},
  "geometry": {"coordinates":[-121.308289,38.744444],"type":"Point"}
}