{
  "type": "Feature",
  "properties": {
    "gn:admin1_code":"LA",
    "gn:admin2_code":"57.0",
    "gn:asciiname":"Brandywine",
    "gn:country_code":"US",
    "gn:dem":6,
    "gn:elevation":"2.0",
    "gn:feature_class":"P",
    "gn:feature_code":"PPL",
    "gn:name":"Brandywine",
    "gn:population":0,
    "gn:timezone":"America/Chicago",
    "iso:country":"US",
    "name:ceb_x_preferred":[
        "Brandywine"
    ],
    "name:deu_x_preferred":[
        "Brandywine"
    ],
    "name:pol_x_preferred":[
        "Brandywine"
    ],
    "name:srp_x_preferred":[
        "\u0411\u0440\u0435\u043d\u0434\u0438\u0432\u0430\u0458\u043d"
    ],
    "name:ukr_x_preferred":[
        "\u0411\u0440\u0435\u043d\u0434\u0456\u0432\u0430\u0439\u043d"
    ],
    "name:vol_x_preferred":[
        "Brandywine"
    ],
    "wof:name":"Brandywine",
    "wof:placetype":"locality"
},
  "geometry": {"coordinates":[-90.77925999999999,29.77215],"type":"Point"}
}