{
  "type": "Feature",
  "properties": {
    "gn:admin1_code":"MO",
    "gn:admin2_code":"161.0",
    "gn:admin3_code":"47432.0",
    "gn:asciiname":"Winkler",
    "gn:country_code":"US",
    "gn:dem":355,
    "gn:elevation":"352.0",
    "gn:feature_class":"P",
    "gn:feature_code":"PPL",
    "gn:name":"Winkler",
    "gn:population":0,
    "gn:timezone":"America/Chicago",
    "iso:country":"US",
    "name:bel_x_preferred":[
        "\u0412\u0456\u043d\u043a\u043b\u0435\u0440"
    ],
    "name:ces_x_preferred":[
        "Winkler"
    ],
    "name:deu_x_preferred":[
        "Winkler"
    ],
    "name:fra_x_preferred":[
        "Winkler"
    ],
    "name:heb_x_preferred":[
        "\u05d5\u05d9\u05e0\u05e7\u05dc\u05e8"
    ],
    "name:hun_x_preferred":[
        "Winkler"
    ],
    "name:ita_x_preferred":[
        "Winkler"
    ],
    "name:jpn_x_preferred":[
        "\u30a6\u30a3\u30f3\u30af\u30e9\u30fc"
    ],
    "name:nld_x_preferred":[
        "Winkler"
    ],
    "name:pol_x_preferred":[
        "Winkler"
    ],
    "name:por_x_preferred":[
        "Winkler"
    ],
    "name:rus_x_preferred":[
        "\u0412\u0438\u043d\u043a\u043b\u0435\u0440"
    ],
    "name:ukr_x_preferred":[
        "\u0412\u0456\u043d\u043a\u043b\u0435\u0440"
    ],
    "wof:name":"Winkler",
    "wof:placetype":"locality"
},
  "geometry": {"coordinates":[-91.55710000000001,37.83588],"type":"Point"}
}