{
  "type": "Feature",
  "properties": {
    "gn:admin1_code":"PA",
    "gn:admin2_code":"31.0",
    "gn:admin3_code":"59456.0",
    "gn:asciiname":"West Freedom",
    "gn:country_code":"US",
    "gn:dem":385,
    "gn:elevation":"385.0",
    "gn:feature_class":"P",
    "gn:feature_code":"PPL",
    "gn:name":"West Freedom",
    "gn:population":0,
    "gn:timezone":"America/New_York",
    "iso:country":"US",
    "wof:name":"West Freedom",
    "wof:placetype":"locality"
},
  "geometry": {"coordinates":[-79.62420999999998,41.10728],"type":"Point"}
}