{
  "type": "Feature",
  "properties": {
    "gn:admin1_code":"DE",
    "gn:admin2_code":"3.0",
    "gn:asciiname":"Eagles Nest Landing",
    "gn:country_code":"US",
    "gn:dem":4,
    "gn:elevation":"3.0",
    "gn:feature_class":"P",
    "gn:feature_code":"PPL",
    "gn:name":"Eagles Nest Landing",
    "gn:population":0,
    "gn:timezone":"America/New_York",
    "iso:country":"US",
    "wof:name":"Eagles Nest Landing",
    "wof:placetype":"locality"
},
  "geometry": {"coordinates":[-75.56326,39.34539],"type":"Point"}
}