{
  "type": "Feature",
  "properties": {
    "gn:admin1_code":"NY",
    "gn:admin2_code":"101.0",
    "gn:admin3_code":"12265.0",
    "gn:asciiname":"South Canisteo",
    "gn:country_code":"US",
    "gn:dem":455,
    "gn:elevation":"448.0",
    "gn:feature_class":"P",
    "gn:feature_code":"PPL",
    "gn:name":"South Canisteo",
    "gn:population":0,
    "gn:timezone":"America/New_York",
    "iso:country":"US",
    "wof:name":"South Canisteo",
    "wof:placetype":"locality"
},
  "geometry": {"coordinates":[-77.55054,42.1959],"type":"Point"}
}