{
  "type": "Feature",
  "properties": {
    "gn:admin1_code":"TN",
    "gn:admin2_code":"107.0",
    "gn:asciiname":"Pond Hill",
    "gn:country_code":"US",
    "gn:dem":306,
    "gn:elevation":"308.0",
    "gn:feature_class":"P",
    "gn:feature_code":"PPL",
    "gn:name":"Pond Hill",
    "gn:population":0,
    "gn:timezone":"America/New_York",
    "iso:country":"US",
    "wof:name":"Pond Hill",
    "wof:placetype":"locality"
},
  "geometry": {"coordinates":[-84.61494,35.55174],"type":"Point"}
}