{
  "type": "Feature",
  "properties": {
    "iso:country":"US",
    "name:eng_x_preferred":[
        "Village Glen"
    ],
    "name:eng_x_variant":[
        "Village Gln"
    ],
    "qs:gn_adm0_cc":"US",
    "qs:gn_fcode":"PPLX",
    "qs:gn_local":4431410,
    "qs:gn_nam_loc":"Jackson, Hinds, Mississippi, US",
    "qs:gn_namadm1":"MS",
    "qs:gn_name":"Village Glen",
    "qs:local_max":1538,
    "qs:local_sum":8499,
    "qs:localhoods":30,
    "qs:name":"Village Glen",
    "qs:name_adm0":"United States",
    "qs:name_adm1":"Mississippi",
    "qs:name_adm2":"Madison",
    "qs:name_local":"Jackson",
    "qs:photo_max":6,
    "qs:photo_sum":9,
    "qs:placetype":"Suburb",
    "qs:quad_count":3,
    "qs:woe_adm0":23424977,
    "qs:woe_adm1":2347583,
    "qs:woe_adm2":12588928,
    "qs:woe_lau":0,
    "qs:woe_local":2428184,
    "qs:woe_ver":"7.10.0",
    "wof:lang":[
        "eng"
    ],
    "wof:name":"Village Glen",
    "wof:placetype":"neighbourhood",
    "wof:population":5446,
    "zs:blockids":[
        280890301064001,
        280890301082003,
        280890301082007,
        280890301082008,
        280890301064009,
        280890301064011,
        280890301062015,
        280890301082002,
        280890301085003,
        280890301062016,
        280890301062005,
        280890301064008,
        280890301085005,
        280890301064007,
        280890301064000,
        280890301084004,
        280890301082015,
        280890301064012,
        280890301082009,
        280890301062008,
        280890301082019,
        280890301062007,
        280890301062004,
        280890301084002,
        280890301062009,
        280890301085000,
        280890301062014,
        280890301064005,
        280890301085006,
        280890301085002,
        280890301081004,
        280890301062000,
        280890301082013,
        280890301081003,
        280890301084001,
        280890301084003,
        280890301084005,
        280890301064003,
        280890301062001,
        280890301082018,
        280890301084000,
        280890301064002,
        280890301064004,
        280890301063000,
        280890301081002,
        280890301062003,
        280890301062006,
        280890301064006,
        280890301085001,
        280890301082012,
        280890301082014,
        280890301062017,
        280890301082006,
        280890301064010
    ],
    "zs:housing10":2996,
    "zs:pop10":5446
},
  "geometry": {"coordinates":[-90.10253899999999,32.40676],"type":"Point"}
}