{
  "type": "Feature",
  "properties": {
    "gn:admin1_code":"AZ",
    "gn:admin2_code":"19.0",
    "gn:asciiname":"Queens Well",
    "gn:country_code":"US",
    "gn:dem":620,
    "gn:elevation":"622.0",
    "gn:feature_class":"P",
    "gn:feature_code":"PPL",
    "gn:name":"Queens Well",
    "gn:population":0,
    "gn:timezone":"America/Phoenix",
    "iso:country":"US",
    "wof:name":"Queens Well",
    "wof:placetype":"locality"
},
  "geometry": {"coordinates":[-111.63345,32.26757],"type":"Point"}
}