{
  "type": "Feature",
  "properties": {
    "iso:country":"US",
    "name:eng_x_preferred":[
        "Oakland"
    ],
    "qs:gn_local":0,
    "qs:local_max":161,
    "qs:local_sum":309,
    "qs:localhoods":4,
    "qs:name":"Oakland",
    "qs:name_adm0":"United States",
    "qs:name_adm1":"Vermont",
    "qs:name_adm2":"Franklin",
    "qs:name_local":"Georgia",
    "qs:photo_max":69,
    "qs:photo_sum":95,
    "qs:placetype":"Suburb",
    "qs:quad_count":3,
    "qs:woe_adm0":23424977,
    "qs:woe_adm1":2347604,
    "qs:woe_adm2":12590295,
    "qs:woe_lau":0,
    "qs:woe_local":2409718,
    "qs:woe_ver":"7.10.0",
    "wof:lang":[
        "eng"
    ],
    "wof:name":"Oakland",
    "wof:placetype":"neighbourhood",
    "wof:population":88,
    "zs:blockids":[
        500110109001005,
        500110109003000,
        500110109001008,
        500110109001009,
        500110109001006
    ],
    "zs:housing10":33,
    "zs:pop10":88
},
  "geometry": {"coordinates":[-73.087604,44.752574],"type":"Point"}
}