{
  "type": "Feature",
  "properties": {
    "gn:admin1_code":"FL",
    "gn:admin2_code":"57",
    "gn:asciiname":"Central Village",
    "gn:country_code":"US",
    "gn:dem":23,
    "gn:elevation":"16.0",
    "gn:feature_class":"P",
    "gn:feature_code":"PPL",
    "gn:name":"Central Village",
    "gn:population":0,
    "gn:timezone":"America/New_York",
    "iso:country":"US",
    "wof:name":"Central Village",
    "wof:placetype":"locality"
},
  "geometry": {"coordinates":[-82.4195,27.9805],"type":"Point"}
}