{
  "type": "Feature",
  "properties": {
    "gn:admin1_code":"NY",
    "gn:admin2_code":"77.0",
    "gn:admin3_code":"24845.0",
    "gn:asciiname":"Lidell Corners",
    "gn:country_code":"US",
    "gn:dem":405,
    "gn:elevation":"402.0",
    "gn:feature_class":"P",
    "gn:feature_code":"PPL",
    "gn:name":"Lidell Corners",
    "gn:population":0,
    "gn:timezone":"America/New_York",
    "iso:country":"US",
    "wof:name":"Lidell Corners",
    "wof:placetype":"locality"
},
  "geometry": {"coordinates":[-75.02849000000001,42.76257],"type":"Point"}
}