{
  "type": "Feature",
  "properties": {
    "gn:admin1_code":"NC",
    "gn:admin2_code":"129",
    "gn:admin3_code":"91092.0",
    "gn:asciiname":"Richardsons Mobile Home Park",
    "gn:country_code":"US",
    "gn:dem":4,
    "gn:elevation":"5.0",
    "gn:feature_class":"P",
    "gn:feature_code":"PPL",
    "gn:name":"Richardsons Mobile Home Park",
    "gn:population":0,
    "gn:timezone":"America/New_York",
    "iso:country":"US",
    "wof:name":"Richardsons Mobile Home Park",
    "wof:placetype":"campus"
},
  "geometry": {"coordinates":[-77.9011,34.0796],"type":"Point"}
}