{
  "type": "Feature",
  "properties": {
    "gn:admin1_code":"DE",
    "gn:admin2_code":"1.0",
    "gn:asciiname":"Greenview",
    "gn:country_code":"US",
    "gn:dem":17,
    "gn:elevation":"13.0",
    "gn:feature_class":"P",
    "gn:feature_code":"PPL",
    "gn:name":"Greenview",
    "gn:population":0,
    "gn:timezone":"America/New_York",
    "iso:country":"US",
    "name:ceb_x_preferred":[
        "Greenview"
    ],
    "name:deu_x_preferred":[
        "Greenview"
    ],
    "name:ita_x_preferred":[
        "Greenview"
    ],
    "name:nld_x_preferred":[
        "Greenview"
    ],
    "name:pol_x_preferred":[
        "Greenview"
    ],
    "name:por_x_preferred":[
        "Greenview"
    ],
    "name:srp_x_preferred":[
        "\u0413\u0440\u0438\u043d\u0432\u0458\u0443"
    ],
    "name:ukr_x_preferred":[
        "\u0413\u0440\u0456\u043d\u0432'\u044e"
    ],
    "name:vol_x_preferred":[
        "Greenview"
    ],
    "wof:name":"Greenview",
    "wof:placetype":"locality"
},
  "geometry": {"coordinates":[-75.52464999999999,39.11817],"type":"Point"}
}