{
  "type": "Feature",
  "properties": {
    "gn:admin1_code":"SC",
    "gn:admin2_code":"91.0",
    "gn:asciiname":"Coventry Estates",
    "gn:country_code":"US",
    "gn:dem":203,
    "gn:elevation":"203.0",
    "gn:feature_class":"P",
    "gn:feature_code":"PPL",
    "gn:name":"Coventry Estates",
    "gn:population":0,
    "gn:timezone":"America/New_York",
    "iso:country":"US",
    "wof:name":"Coventry Estates",
    "wof:placetype":"locality"
},
  "geometry": {"coordinates":[-81.05008000000002,34.97153],"type":"Point"}
}