{
  "type": "Feature",
  "properties": {
    "gn:admin1_code":"NC",
    "gn:admin2_code":"129",
    "gn:admin3_code":"90508.0",
    "gn:asciiname":"Glynnwood Mobile Home Park",
    "gn:country_code":"US",
    "gn:dem":11,
    "gn:elevation":"9.0",
    "gn:feature_class":"P",
    "gn:feature_code":"PPL",
    "gn:name":"Glynnwood Mobile Home Park",
    "gn:population":0,
    "gn:timezone":"America/New_York",
    "iso:country":"US",
    "wof:name":"Glynnwood Mobile Home Park",
    "wof:placetype":"campus"
},
  "geometry": {"coordinates":[-77.8802,34.2788],"type":"Point"}
}