{
  "type": "Feature",
  "properties": {
    "gn:admin1_code":"LA",
    "gn:admin2_code":"33.0",
    "gn:asciiname":"Red Oak",
    "gn:country_code":"US",
    "gn:dem":26,
    "gn:elevation":"15.0",
    "gn:feature_class":"P",
    "gn:feature_code":"PPL",
    "gn:name":"Red Oak",
    "gn:population":0,
    "gn:timezone":"America/Chicago",
    "iso:country":"US",
    "name:eng_x_preferred":[
        "Red Oak"
    ],
    "name:und_x_variant":[
        "Red Oaks"
    ],
    "wof:name":"Red Oak",
    "wof:placetype":"locality"
},
  "geometry": {"coordinates":[-91.0676,30.46575],"type":"Point"}
}