{
  "type": "Feature",
  "properties": {
    "gn:admin1_code":"OH",
    "gn:admin2_code":"79.0",
    "gn:admin3_code":"28322.0",
    "gn:asciiname":"Banner",
    "gn:country_code":"US",
    "gn:dem":217,
    "gn:elevation":"218.0",
    "gn:feature_class":"P",
    "gn:feature_code":"PPL",
    "gn:name":"Banner",
    "gn:population":0,
    "gn:timezone":"America/New_York",
    "iso:country":"US",
    "name:ara_x_preferred":[
        "\u0631\u0627\u064a\u0629"
    ],
    "name:cat_x_preferred":[
        "Banderola"
    ],
    "name:deu_x_preferred":[
        "Banner"
    ],
    "name:eng_x_preferred":[
        "Banner"
    ],
    "name:fas_x_preferred":[
        "\u0628\u0646\u0631"
    ],
    "name:fry_x_preferred":[
        "Banier"
    ],
    "name:ind_x_preferred":[
        "Spanduk"
    ],
    "name:jpn_x_preferred":[
        "\u6a2a\u65ad\u5e55"
    ],
    "name:kaz_x_preferred":[
        "\u0411\u0430\u0439\u0440\u0430\u049b"
    ],
    "name:kor_x_preferred":[
        "\ud604\uc218\ub9c9"
    ],
    "name:nld_x_preferred":[
        "Banier"
    ],
    "name:nor_x_preferred":[
        "Banner"
    ],
    "name:scn_x_preferred":[
        "Stinnardu"
    ],
    "name:slv_x_preferred":[
        "Prapor"
    ],
    "name:spa_x_preferred":[
        "Pend\u00f3n"
    ],
    "name:swe_x_preferred":[
        "Baner"
    ],
    "name:tam_x_preferred":[
        "\u0baa\u0ba4\u0bbe\u0b95\u0bc8"
    ],
    "name:ukr_x_preferred":[
        "\u0421\u0442\u044f\u0433"
    ],
    "name:und_x_variant":[
        "Vaughns Station",
        "Vaughns"
    ],
    "wof:name":"Banner",
    "wof:placetype":"locality"
},
  "geometry": {"coordinates":[-82.59489000000001,38.94007],"type":"Point"}
}