{
  "type": "Feature",
  "properties": {
    "gn:admin1_code":"TX",
    "gn:admin2_code":"181",
    "gn:asciiname":"Gover",
    "gn:country_code":"US",
    "gn:dem":170,
    "gn:elevation":"166.0",
    "gn:feature_class":"P",
    "gn:feature_code":"PPL",
    "gn:name":"Gover",
    "gn:population":0,
    "gn:timezone":"America/Chicago",
    "iso:country":"US",
    "wof:name":"Gover",
    "wof:placetype":"locality"
},
  "geometry": {"coordinates":[-96.42415,33.73594],"type":"Point"}
}