{
  "type": "Feature",
  "properties": {
    "gn:admin1_code":"FL",
    "gn:admin2_code":"105.0",
    "gn:asciiname":"Lakeside Gardens Mobile Home Park",
    "gn:country_code":"US",
    "gn:dem":41,
    "gn:elevation":"38.0",
    "gn:feature_class":"P",
    "gn:feature_code":"PPL",
    "gn:name":"Lakeside Gardens Mobile Home Park",
    "gn:population":0,
    "gn:timezone":"America/New_York",
    "iso:country":"US",
    "wof:name":"Lakeside Gardens Mobile Home Park",
    "wof:placetype":"campus"
},
  "geometry": {"coordinates":[-81.59269999999999,27.8223],"type":"Point"}
}