{
  "type": "Feature",
  "properties": {
    "gn:elevation":245,
    "iso:country":"US",
    "name:eng_x_preferred":[
        "Quentin Corners"
    ],
    "name:eng_x_variant":[
        "Quentin Cors"
    ],
    "name:und_x_variant":[
        "Ela"
    ],
    "qs:gn_adm0_cc":"US",
    "qs:gn_fcode":"PPL",
    "qs:gn_local":4905211,
    "qs:gn_nam_loc":"Palatine, Cook, Illinois, US",
    "qs:gn_namadm1":"IL",
    "qs:gn_name":"Quentin Corners",
    "qs:local_max":1122,
    "qs:local_sum":4840,
    "qs:localhoods":9,
    "qs:name":"Quentin Corners",
    "qs:name_adm0":"United States",
    "qs:name_adm1":"Illinois",
    "qs:name_adm2":"Lake",
    "qs:name_local":"Palatine",
    "qs:photo_max":1,
    "qs:photo_sum":1,
    "qs:placetype":"Suburb",
    "qs:quad_count":1,
    "qs:woe_adm0":23424977,
    "qs:woe_adm1":2347572,
    "qs:woe_adm2":12588127,
    "qs:woe_lau":0,
    "qs:woe_local":2467572,
    "qs:woe_ver":"7.10.0",
    "wof:lang":[
        "eng"
    ],
    "wof:name":"Quentin Corners",
    "wof:placetype":"neighbourhood",
    "wof:population":259,
    "zs:blockids":[
        170978644122033,
        170978644122035,
        170978644033053,
        170978644103016,
        170978644122031,
        170978644122030,
        170978644103010,
        170978644122014,
        170978644103011,
        170978644122012,
        170978644122017,
        170978644122016,
        170978644033050,
        170978644033051,
        170978644122015,
        170978644103009,
        170978644122034,
        170978644122013,
        170978644103017,
        170978644122032,
        170978644122048
    ],
    "zs:housing10":101,
    "zs:pop10":259
},
  "geometry": {"coordinates":[-88.06366,42.177654],"type":"Point"}
}