{
  "type": "Feature",
  "properties": {
    "gn:admin1_code":"NY",
    "gn:admin2_code":"75.0",
    "gn:admin3_code":"55453.0",
    "gn:asciiname":"Chateaugay",
    "gn:country_code":"US",
    "gn:dem":312,
    "gn:elevation":"311.0",
    "gn:feature_class":"P",
    "gn:feature_code":"PPL",
    "gn:name":"Chateaugay",
    "gn:population":0,
    "gn:timezone":"America/New_York",
    "iso:country":"US",
    "name:ceb_x_preferred":[
        "Chateaugay"
    ],
    "name:deu_x_preferred":[
        "Chateaugay"
    ],
    "name:jpn_x_preferred":[
        "\u30b7\u30e3\u30c8\u30fc\u30b2\u30a4"
    ],
    "name:pol_x_preferred":[
        "Chateaugay"
    ],
    "name:swe_x_preferred":[
        "Chateaugay"
    ],
    "name:ukr_x_preferred":[
        "\u0428\u0430\u0442\u043e\u0433\u0435\u0439"
    ],
    "wof:name":"Chateaugay",
    "wof:placetype":"locality"
},
  "geometry": {"coordinates":[-75.96214000000001,43.57396],"type":"Point"}
}