{
  "type": "Feature",
  "properties": {
    "gn:admin1_code":"MI",
    "gn:admin2_code":"33.0",
    "gn:admin3_code":"86700.0",
    "gn:asciiname":"Shelldrake",
    "gn:country_code":"US",
    "gn:dem":185,
    "gn:elevation":"185.0",
    "gn:feature_class":"P",
    "gn:feature_code":"PPL",
    "gn:name":"Shelldrake",
    "gn:population":0,
    "gn:timezone":"America/Detroit",
    "iso:country":"US",
    "wof:name":"Shelldrake",
    "wof:placetype":"locality"
},
  "geometry": {"coordinates":[-85.0337,46.6778],"type":"Point"}
}