{
  "type": "Feature",
  "properties": {
    "iso:country":"US",
    "name:eng_x_preferred":[
        "Norwest"
    ],
    "name:fra_x_preferred":[
        "Norwest"
    ],
    "wd:wordcount":117,
    "wof:name":"Norwest",
    "wof:placetype":"neighbourhood",
    "wof:population":875,
    "zs:blockids":[
        80010094081051,
        80010094081050,
        80010094081001,
        80010094081002,
        80010094081009,
        80140308004011,
        80140308004015,
        80140308004012,
        80140308002004,
        80140308004013,
        80140308004010,
        80140308004014
    ],
    "zs:housing10":337,
    "zs:label":"Norwest",
    "zs:pop10":875
},
  "geometry": {"coordinates":[-105.03676900000001,39.918125],"type":"Point"}
}