{
  "type": "Feature",
  "properties": {
    "gn:country":"US",
    "gn:fcode":"PPL",
    "gn:population":0,
    "iso:country":"US",
    "name:azb_x_preferred":[
        "\u0645\u0648\u0646\u062a\u0627"
    ],
    "name:deu_x_preferred":[
        "Moneta"
    ],
    "name:eng_x_preferred":[
        "Moneta"
    ],
    "name:fas_x_preferred":[
        "\u0645\u0648\u0646\u062a\u0627"
    ],
    "name:fra_x_preferred":[
        "Moneta"
    ],
    "name:lld_x_preferred":[
        "Moneta"
    ],
    "name:spa_x_preferred":[
        "Moneta"
    ],
    "name:und_x_variant":[
        "Monita"
    ],
    "name:zho_x_preferred":[
        "\u83ab\u5c3c\u5854"
    ],
    "qs_pg:aaroncc":"US",
    "qs_pg:gn_country":"US",
    "qs_pg:gn_fcode":"PPL",
    "qs_pg:gn_pop":0,
    "qs_pg:name":"Moneta",
    "qs_pg:name_adm0":"United States",
    "qs_pg:name_adm1":"Virginia",
    "qs_pg:photos":96,
    "qs_pg:photos_1k":19,
    "qs_pg:photos_9k":1,
    "qs_pg:photos_9r":3,
    "qs_pg:photos_all":96,
    "qs_pg:photos_sr":3,
    "qs_pg:pop_sr":5,
    "qs_pg:qs_pg_placetype":"locality",
    "qs_pg:qs_pg_placetype_gp":"Town",
    "qs_pg:woe_adm0":23424977,
    "woe:adm0_id":23424977,
    "woe:name_adm0":"United States",
    "woe:name_adm1":"Virginia",
    "woe:placetype":"Town",
    "wof:name":"Moneta",
    "wof:placetype":"locality"
},
  "geometry": {"coordinates":[-79.61725,37.18125],"type":"Point"}
}