{
  "type": "Feature",
  "properties": {
    "iso:country":"US",
    "name:eng_x_preferred":[
        "Carriage Hills North"
    ],
    "name:eng_x_variant":[
        "Carriage Hills"
    ],
    "name:fra_x_preferred":[
        "Carriage Hills"
    ],
    "name:nld_x_preferred":[
        "Carriage Hills"
    ],
    "qs:gn_adm0_cc":"US",
    "qs:gn_local":5345888,
    "qs:gn_nam_loc":"El Sobrante, Contra Costa, California, US",
    "qs:gn_namadm1":"CA",
    "qs:local_max":976,
    "qs:local_sum":2662,
    "qs:localhoods":9,
    "qs:name":"Carriage Hills North",
    "qs:name_adm0":"United States",
    "qs:name_adm1":"California",
    "qs:name_adm2":"Contra Costa",
    "qs:name_local":"El Sobrante",
    "qs:photo_max":5,
    "qs:photo_sum":22,
    "qs:placetype":"Suburb",
    "qs:quad_count":9,
    "qs:woe_adm0":23424977,
    "qs:woe_adm1":2347563,
    "qs:woe_adm2":12587676,
    "qs:woe_lau":0,
    "qs:woe_local":2397979,
    "qs:woe_ver":"7.10.0",
    "wd:wordcount":359,
    "wof:lang":[
        "eng"
    ],
    "wof:name":"Carriage Hills North",
    "wof:placetype":"neighbourhood",
    "wof:population":1211,
    "zs:blockids":[
        60133601022013,
        60133601022011,
        60133601022014,
        60133601022007,
        60133601022016
    ],
    "zs:housing10":410,
    "zs:pop10":1211
},
  "geometry": {"coordinates":[-122.255915,37.972567],"type":"Point"}
}