{
  "type": "Feature",
  "properties": {
    "iso:country":"US",
    "name:ara_x_preferred":[
        "\u062f\u0644\u0628\u0644"
    ],
    "name:cym_x_preferred":[
        "Delabole"
    ],
    "name:eng_x_preferred":[
        "Delabole"
    ],
    "name:eus_x_preferred":[
        "Delabole"
    ],
    "name:pol_x_preferred":[
        "Delabole"
    ],
    "name:spa_x_preferred":[
        "Delabole"
    ],
    "name:swe_x_preferred":[
        "Delabole"
    ],
    "wd:wordcount":1284,
    "wof:name":"Delabole",
    "wof:placetype":"neighbourhood",
    "wof:population":242,
    "zs:area_m":5491860.493645,
    "zs:blockids":[
        420950155002019,
        420950155002026,
        420950155002023,
        420950155002053,
        420950155002044,
        420950155002034,
        420950155002045,
        420950155002027,
        420950155002025,
        420950155002038,
        420950155002035,
        420950155002028,
        420950155002046,
        420950155002032,
        420950155002036,
        420950155002020,
        420950155002052,
        420950155002021,
        420950155002022,
        420950155002033,
        420950155002024,
        420950155002043,
        420950155002108
    ],
    "zs:housing10":95,
    "zs:label":"Delabole",
    "zs:pop10":242
},
  "geometry": {"coordinates":[-75.253469,40.846698],"type":"Point"}
}