{
  "type": "Feature",
  "properties": {
    "iso:country":"US",
    "name:eng_x_preferred":[
        "Westview Terrace"
    ],
    "wof:name":"Westview Terrace",
    "wof:placetype":"neighbourhood",
    "wof:population":776,
    "zs:area_m":190571.770677,
    "zs:blockids":[
        490351138013002,
        490351138013008,
        490351138013006,
        490351138031001,
        490351138013009,
        490351138031002,
        490351138013005,
        490351138013007
    ],
    "zs:housing10":210,
    "zs:label":"Westview Terrace",
    "zs:pop10":776
},
  "geometry": {"coordinates":[-112.01089399999999,40.6534],"type":"Point"}
}