{
  "type": "Feature",
  "properties": {
    "gn:admin1_code":"IN",
    "gn:admin2_code":"55.0",
    "gn:admin3_code":"80648.0",
    "gn:asciiname":"Stalcup Corner",
    "gn:country_code":"US",
    "gn:dem":167,
    "gn:elevation":"166.0",
    "gn:feature_class":"P",
    "gn:feature_code":"PPL",
    "gn:name":"Stalcup Corner",
    "gn:population":0,
    "gn:timezone":"America/Indiana/Indianapolis",
    "iso:country":"US",
    "wof:name":"Stalcup Corner",
    "wof:placetype":"locality"
},
  "geometry": {"coordinates":[-87.01612,38.99449],"type":"Point"}
}