{
  "type": "Feature",
  "properties": {
    "iso:country":"US",
    "name:ceb_x_preferred":[
        "Kings Canyon"
    ],
    "name:deu_x_preferred":[
        "Kings Canyon"
    ],
    "name:fra_x_preferred":[
        "Kings canyon"
    ],
    "name:nld_x_preferred":[
        "Kings Canyon"
    ],
    "name:swe_x_preferred":[
        "Kings Canyon"
    ],
    "qs_pg:aaroncc":"US",
    "qs_pg:name":"Kings Canyon",
    "qs_pg:name_adm0":"United States",
    "qs_pg:name_adm1":"California",
    "qs_pg:photos":215,
    "qs_pg:photos_1k":44,
    "qs_pg:photos_9k":1,
    "qs_pg:photos_9r":4,
    "qs_pg:photos_all":215,
    "qs_pg:photos_sr":4,
    "qs_pg:pop_sr":0,
    "qs_pg:qs_pg_placetype":"locality",
    "qs_pg:qs_pg_placetype_gp":"Town",
    "qs_pg:woe_adm0":23424977,
    "woe:adm0_id":23424977,
    "woe:name_adm0":"United States",
    "woe:name_adm1":"California",
    "woe:placetype":"Town",
    "wof:name":"Kings Canyon",
    "wof:placetype":"locality"
},
  "geometry": {"coordinates":[-118.906997,36.785779],"type":"Point"}
}