{
  "type": "Feature",
  "properties": {
    "gn:admin1_code":"OH",
    "gn:admin2_code":"139",
    "gn:admin3_code":"46578.0",
    "gn:asciiname":"Forest Hills Mobile Park",
    "gn:country_code":"US",
    "gn:dem":390,
    "gn:elevation":"390.0",
    "gn:feature_class":"P",
    "gn:feature_code":"PPL",
    "gn:name":"Forest Hills Mobile Park",
    "gn:population":0,
    "gn:timezone":"America/New_York",
    "iso:country":"US",
    "wof:name":"Forest Hills Mobile Park",
    "wof:placetype":"locality"
},
  "geometry": {"coordinates":[-82.48778,40.76556],"type":"Point"}
}