{
  "type": "Feature",
  "properties": {
    "gn:admin1_code":"GA",
    "gn:admin2_code":"127",
    "gn:asciiname":"Pine Forest",
    "gn:country_code":"US",
    "gn:dem":14,
    "gn:elevation":"6.0",
    "gn:feature_class":"P",
    "gn:feature_code":"PPL",
    "gn:name":"Pine Forest",
    "gn:population":0,
    "gn:timezone":"America/New_York",
    "iso:country":"US",
    "name:ceb_x_preferred":[
        "Pine Forest"
    ],
    "name:ukr_x_preferred":[
        "\u0421\u043e\u0441\u043d\u043e\u0432\u0438\u0439 \u043b\u0456\u0441"
    ],
    "wof:name":"Pine Forest",
    "wof:placetype":"locality"
},
  "geometry": {"coordinates":[-81.49899000000001,31.21467],"type":"Point"}
}