{
  "type": "Feature",
  "properties": {
    "gn:country":"US",
    "gn:fcode":"PPL",
    "gn:population":0,
    "iso:country":"US",
    "name:azb_x_preferred":[
        "\u06a9\u0627\u0631\u0644\u062a\u0648\u0646"
    ],
    "name:cym_x_preferred":[
        "Carlton"
    ],
    "name:deu_x_preferred":[
        "Carlton"
    ],
    "name:eng_x_preferred":[
        "Carlton"
    ],
    "name:fas_x_preferred":[
        "\u06a9\u0627\u0631\u0644\u062a\u0648\u0646"
    ],
    "name:fra_x_preferred":[
        "Carlton"
    ],
    "name:hun_x_preferred":[
        "Carlton"
    ],
    "name:urd_x_preferred":[
        "\u06a9\u0627\u0631\u0644\u0679\u0646\u060c \u0648\u0627\u0634\u0646\u06af\u0679\u0646"
    ],
    "name:urd_x_variant":[
        "\u06a9\u0627\u0631\u0644\u0679\u0646"
    ],
    "qs_pg:aaroncc":"US",
    "qs_pg:gn_country":"US",
    "qs_pg:gn_fcode":"PPL",
    "qs_pg:gn_pop":0,
    "qs_pg:name":"Carlton",
    "qs_pg:name_adm0":"United States",
    "qs_pg:name_adm1":"Washington",
    "qs_pg:photos":38,
    "qs_pg:photos_1k":8,
    "qs_pg:photos_9k":1,
    "qs_pg:photos_9r":2,
    "qs_pg:photos_all":38,
    "qs_pg:photos_sr":2,
    "qs_pg:pop_sr":5,
    "qs_pg:qs_pg_placetype":"locality",
    "qs_pg:qs_pg_placetype_gp":"Town",
    "qs_pg:woe_adm0":23424977,
    "woe:adm0_id":23424977,
    "woe:name_adm0":"United States",
    "woe:name_adm1":"Washington",
    "woe:placetype":"Town",
    "wof:name":"Carlton",
    "wof:placetype":"locality"
},
  "geometry": {"coordinates":[-120.11619,48.2482],"type":"Point"}
}