{
  "type": "Feature",
  "properties": {
    "gn:admin1_code":"PA",
    "gn:admin2_code":"113.0",
    "gn:admin3_code":"18296.0",
    "gn:asciiname":"Beech Glen",
    "gn:country_code":"US",
    "gn:dem":254,
    "gn:elevation":"254.0",
    "gn:feature_class":"P",
    "gn:feature_code":"PPL",
    "gn:name":"Beech Glen",
    "gn:population":0,
    "gn:timezone":"America/New_York",
    "iso:country":"US",
    "name:eng_x_preferred":[
        "Beech Glen"
    ],
    "name:und_x_variant":[
        "Beach Glen"
    ],
    "wof:name":"Beech Glen",
    "wof:placetype":"locality"
},
  "geometry": {"coordinates":[-76.58773000000002,41.32925],"type":"Point"}
}