{
  "type": "Feature",
  "properties": {
    "gn:admin1_code":"MS",
    "gn:admin2_code":"51",
    "gn:asciiname":"Wyatt",
    "gn:country_code":"US",
    "gn:dem":37,
    "gn:elevation":"34.0",
    "gn:feature_class":"P",
    "gn:feature_code":"PPL",
    "gn:name":"Wyatt",
    "gn:population":0,
    "gn:timezone":"America/Chicago",
    "iso:country":"US",
    "name:kor_x_preferred":[
        "\uc640\uc774\uc5c7"
    ],
    "name:rus_x_preferred":[
        "\u0423\u0430\u0439\u0430\u0442\u0442"
    ],
    "name:slv_x_preferred":[
        "Wyatt"
    ],
    "wof:name":"Wyatt",
    "wof:placetype":"locality"
},
  "geometry": {"coordinates":[-90.22036,33.23318],"type":"Point"}
}