{
  "type": "Feature",
  "properties": {
    "gn:admin1_code":"OH",
    "gn:admin2_code":"173.0",
    "gn:admin3_code":"77630.0",
    "gn:asciiname":"Troy Villa Mobile Home Park",
    "gn:country_code":"US",
    "gn:dem":194,
    "gn:elevation":"195.0",
    "gn:feature_class":"P",
    "gn:feature_code":"PPL",
    "gn:name":"Troy Villa Mobile Home Park",
    "gn:population":0,
    "gn:timezone":"America/New_York",
    "iso:country":"US",
    "wof:name":"Troy Villa Mobile Home Park",
    "wof:placetype":"campus"
},
  "geometry": {"coordinates":[-83.46632,41.50283],"type":"Point"}
}