{
  "type": "Feature",
  "properties": {
    "gn:country":"US",
    "gn:fcode":"PPLX",
    "gn:population":0,
    "iso:country":"US",
    "qs_pg:aaroncc":"US",
    "qs_pg:gn_country":"US",
    "qs_pg:gn_fcode":"PPLX",
    "qs_pg:gn_pop":0,
    "qs_pg:name":"Illahee Hills",
    "qs_pg:name_adm0":"United States",
    "qs_pg:name_adm1":"North Carolina",
    "qs_pg:photos":53,
    "qs_pg:photos_1k":11,
    "qs_pg:photos_9k":1,
    "qs_pg:photos_9r":2,
    "qs_pg:photos_all":53,
    "qs_pg:photos_sr":2,
    "qs_pg:pop_sr":0,
    "qs_pg:qs_pg_placetype":"neighbourhood",
    "qs_pg:qs_pg_placetype_gp":"Suburb",
    "qs_pg:woe_adm0":23424977,
    "woe:adm0_id":23424977,
    "woe:name_adm0":"United States",
    "woe:name_adm1":"North Carolina",
    "woe:placetype":"Suburb",
    "wof:name":"Illahee Hills",
    "wof:placetype":"neighbourhood"
},
  "geometry": {"coordinates":[-82.75485,35.21095],"type":"Point"}
}