{
  "type": "Feature",
  "properties": {
    "gn:admin1_code":"IN",
    "gn:admin2_code":"153.0",
    "gn:admin3_code":"30672.0",
    "gn:asciiname":"Campbell Corner",
    "gn:country_code":"US",
    "gn:dem":152,
    "gn:elevation":"152.0",
    "gn:feature_class":"P",
    "gn:feature_code":"PPL",
    "gn:name":"Campbell Corner",
    "gn:population":0,
    "gn:timezone":"America/Indiana/Indianapolis",
    "iso:country":"US",
    "wof:name":"Campbell Corner",
    "wof:placetype":"locality"
},
  "geometry": {"coordinates":[-87.40890999999998,39.14282],"type":"Point"}
}