{
  "type": "Feature",
  "properties": {
    "gn:admin1_code":"MD",
    "gn:admin2_code":"27.0",
    "gn:asciiname":"Lennox Park",
    "gn:country_code":"US",
    "gn:dem":59,
    "gn:elevation":"56.0",
    "gn:feature_class":"P",
    "gn:feature_code":"PPL",
    "gn:name":"Lennox Park",
    "gn:population":0,
    "gn:timezone":"America/New_York",
    "iso:country":"US",
    "wof:name":"Lennox Park",
    "wof:placetype":"locality"
},
  "geometry": {"coordinates":[-76.75164000000002,39.1765],"type":"Point"}
}