{
  "type": "Feature",
  "properties": {
    "gn:admin1_code":"TX",
    "gn:admin2_code":"293.0",
    "gn:asciiname":"Calina",
    "gn:country_code":"US",
    "gn:dem":165,
    "gn:elevation":"164.0",
    "gn:feature_class":"P",
    "gn:feature_code":"PPL",
    "gn:name":"Calina",
    "gn:population":0,
    "gn:timezone":"America/Chicago",
    "iso:country":"US",
    "wof:name":"Calina",
    "wof:placetype":"locality"
},
  "geometry": {"coordinates":[-96.69999,31.75655],"type":"Point"}
}