{
  "type": "Feature",
  "properties": {
    "gn:admin1_code":"AZ",
    "gn:admin2_code":"7.0",
    "gn:asciiname":"Tonto Estate",
    "gn:country_code":"US",
    "gn:dem":1767,
    "gn:elevation":"1755.0",
    "gn:feature_class":"P",
    "gn:feature_code":"PPL",
    "gn:name":"Tonto Estate",
    "gn:population":0,
    "gn:timezone":"America/Phoenix",
    "iso:country":"US",
    "wof:name":"Tonto Estate",
    "wof:placetype":"locality"
},
  "geometry": {"coordinates":[-111.09457999999999,34.35892],"type":"Point"}
}