{
  "type": "Feature",
  "properties": {
    "iso:country":"US",
    "name:ceb_x_preferred":[
        "Pine Crest"
    ],
    "name:deu_x_preferred":[
        "Pine Crest"
    ],
    "name:eng_x_preferred":[
        "Pine Crest"
    ],
    "wd:wordcount":13,
    "wof:name":"Pine Crest",
    "wof:placetype":"neighbourhood",
    "wof:population":789,
    "zs:area_m":410588.245952,
    "zs:blockids":[
        51430105073000,
        51430105071018,
        51430105071013,
        51430105071002,
        51430105071005,
        51430105071006,
        51430105071010,
        51430105071001,
        51430105071003,
        51430105071004,
        51430105073008,
        51430105071000,
        51430105073007,
        51430105073002,
        51430105073004,
        51430105073013
    ],
    "zs:housing10":387,
    "zs:label":"Pine Crest",
    "zs:pop10":789
},
  "geometry": {"coordinates":[-94.20446800000001,36.0863],"type":"Point"}
}