{
  "type": "Feature",
  "properties": {
    "gn:elevation":228,
    "iso:country":"US",
    "name:bul_x_preferred":[
        "\u041c\u0435\u0440\u0438\u0441\u0432\u0438\u043b"
    ],
    "name:cat_x_preferred":[
        "Marysville"
    ],
    "name:ceb_x_preferred":[
        "Marysville"
    ],
    "name:ces_x_preferred":[
        "Marysville"
    ],
    "name:deu_x_preferred":[
        "Marysville"
    ],
    "name:eng_x_preferred":[
        "Marysville"
    ],
    "name:fas_x_preferred":[
        "\u0645\u0627\u0631\u06cc\u0633 \u0648\u06cc\u0644"
    ],
    "name:fra_x_preferred":[
        "Marysville"
    ],
    "name:hun_x_preferred":[
        "Marysville"
    ],
    "name:ita_x_preferred":[
        "Marysville"
    ],
    "name:kor_x_preferred":[
        "\uba54\ub9ac\uc988\ube4c"
    ],
    "name:nld_x_preferred":[
        "Marysville"
    ],
    "name:pol_x_preferred":[
        "Marysville"
    ],
    "name:por_x_preferred":[
        "Marysville"
    ],
    "name:rus_x_preferred":[
        "\u041c\u044d\u0440\u0438\u0441\u0432\u0438\u043b\u043b"
    ],
    "name:spa_x_preferred":[
        "Marysville"
    ],
    "name:srp_x_preferred":[
        "\u041c\u0435\u0440\u0438\u0441\u0432\u0438\u043b"
    ],
    "name:swe_x_preferred":[
        "Marysville"
    ],
    "name:urd_x_preferred":[
        "\u0645\u06cc\u0631\u06cc\u0632\u0648\u06cc\u0644"
    ],
    "name:vol_x_preferred":[
        "Marysville"
    ],
    "qs:gn_adm0_cc":"US",
    "qs:gn_fcode":"PPL",
    "qs:gn_local":5138286,
    "qs:gn_nam_loc":"Skaneateles, Onondaga, New York, US",
    "qs:gn_namadm1":"NY",
    "qs:gn_name":"Marysville",
    "qs:local_max":1301,
    "qs:local_sum":1333,
    "qs:localhoods":3,
    "qs:name":"Marysville",
    "qs:name_adm0":"United States",
    "qs:name_adm1":"New York",
    "qs:name_adm2":"Onondaga",
    "qs:name_local":"Skaneateles",
    "qs:photo_max":4,
    "qs:photo_sum":23,
    "qs:placetype":"Suburb",
    "qs:quad_count":12,
    "qs:woe_adm0":23424977,
    "qs:woe_adm1":2347591,
    "qs:woe_adm2":12589345,
    "qs:woe_lau":0,
    "qs:woe_local":2494273,
    "qs:woe_ver":"7.10.0",
    "wd:wordcount":72,
    "wof:lang":[
        "eng"
    ],
    "wof:name":"Marysville",
    "wof:placetype":"neighbourhood",
    "wof:population":470,
    "zs:blockids":[
        360670166002029,
        360670166002030,
        360670166002020,
        360670166002031,
        360670166002014,
        360670166002032,
        360670166002017,
        360670166002028,
        360670166002024,
        360670166002033,
        360670166002023,
        360670166002046,
        360670166002016,
        360670166002015,
        360670166002027,
        360670166002021,
        360670166002022,
        360670166002045
    ],
    "zs:housing10":177,
    "zs:pop10":470
},
  "geometry": {"coordinates":[-76.457081,42.987266],"type":"Point"}
}