{
  "type": "Feature",
  "properties": {
    "iso:country":"US",
    "name:eng_x_preferred":[
        "Dobson Woods"
    ],
    "wof:name":"Dobson Woods",
    "wof:placetype":"neighbourhood",
    "wof:population":1598,
    "zs:area_m":624930.582146,
    "zs:blockids":[
        40134222033010,
        40134222163012,
        40134222163006,
        40134222163001,
        40134222163009,
        40134222163011,
        40134222163013,
        40134222163014,
        40134222163003,
        40134222164013,
        40134222163002,
        40134222163008,
        40134222033009,
        40134222163004,
        40134222033008,
        40134222163005,
        40134222163016,
        40134222163007,
        40134222164011,
        40134222163017
    ],
    "zs:housing10":740,
    "zs:label":"Dobson Woods",
    "zs:pop10":1598
},
  "geometry": {"coordinates":[-111.856076,33.375725],"type":"Point"}
}