{
  "type": "Feature",
  "properties": {
    "gn:admin1_code":"VA",
    "gn:admin2_code":"179.0",
    "gn:asciiname":"Aquia Creek",
    "gn:country_code":"US",
    "gn:dem":52,
    "gn:elevation":"41.0",
    "gn:feature_class":"P",
    "gn:feature_code":"PPL",
    "gn:name":"Aquia Creek",
    "gn:population":0,
    "gn:timezone":"America/New_York",
    "iso:country":"US",
    "name:ceb_x_preferred":[
        "Aquia Creek"
    ],
    "name:und_x_variant":[
        "Acquia Creek",
        "Acquia Landing"
    ],
    "wof:name":"Aquia Creek",
    "wof:placetype":"locality"
},
  "geometry": {"coordinates":[-77.3764,38.4307],"type":"Point"}
}