{
  "type": "Feature",
  "properties": {
    "gn:admin1_code":"TX",
    "gn:admin2_code":"43.0",
    "gn:asciiname":"Pettits",
    "gn:country_code":"US",
    "gn:dem":621,
    "gn:elevation":"624.0",
    "gn:feature_class":"P",
    "gn:feature_code":"PPL",
    "gn:name":"Pettits",
    "gn:population":0,
    "gn:timezone":"America/Chicago",
    "iso:country":"US",
    "wof:name":"Pettits",
    "wof:placetype":"locality"
},
  "geometry": {"coordinates":[-103.28406,28.99854],"type":"Point"}
}