{
  "type": "Feature",
  "properties": {
    "gn:admin1_code":"OH",
    "gn:admin2_code":"87",
    "gn:admin3_code":"48174.0",
    "gn:asciiname":"Okey",
    "gn:country_code":"US",
    "gn:dem":237,
    "gn:elevation":"228.0",
    "gn:feature_class":"P",
    "gn:feature_code":"PPL",
    "gn:name":"Okey",
    "gn:population":0,
    "gn:timezone":"America/New_York",
    "iso:country":"US",
    "name:deu_x_preferred":[
        "Okey"
    ],
    "name:fra_x_preferred":[
        "Okey"
    ],
    "name:hun_x_preferred":[
        "Okey"
    ],
    "name:jpn_x_preferred":[
        "\u30aa\u30b1\u30a4"
    ],
    "name:tur_x_preferred":[
        "Okey"
    ],
    "wof:name":"Okey",
    "wof:placetype":"locality"
},
  "geometry": {"coordinates":[-82.36820999999998,38.62925],"type":"Point"}
}