{
  "type": "Feature",
  "properties": {
    "gn:admin1_code":"WI",
    "gn:admin2_code":"17.0",
    "gn:admin3_code":"16125.0",
    "gn:asciiname":"Brownville",
    "gn:country_code":"US",
    "gn:dem":347,
    "gn:elevation":"351.0",
    "gn:feature_class":"P",
    "gn:feature_code":"PPL",
    "gn:name":"Brownville",
    "gn:population":0,
    "gn:timezone":"America/Chicago",
    "iso:country":"US",
    "wof:name":"Brownville",
    "wof:placetype":"locality"
},
  "geometry": {"coordinates":[-90.93375,45.03136],"type":"Point"}
}