{
  "type": "Feature",
  "properties": {
    "gn:admin1_code":"WV",
    "gn:admin2_code":"51",
    "gn:asciiname":"Bannen",
    "gn:country_code":"US",
    "gn:dem":280,
    "gn:elevation":"272.0",
    "gn:feature_class":"P",
    "gn:feature_code":"PPL",
    "gn:name":"Bannen",
    "gn:population":0,
    "gn:timezone":"America/New_York",
    "iso:country":"US",
    "name:fas_x_preferred":[
        "\u0628\u0627\u0648\u0646\u0646"
    ],
    "wof:name":"Bannen",
    "wof:placetype":"locality"
},
  "geometry": {"coordinates":[-80.58674999999999,39.72841],"type":"Point"}
}