{
  "type": "Feature",
  "properties": {
    "gn:country":"US",
    "gn:fcode":"PPL",
    "gn:population":0,
    "iso:country":"US",
    "name:eng_x_preferred":[
        "Freedom"
    ],
    "name:fas_x_preferred":[
        "\u0641\u0631\u06cc\u062f\u0627\u0645"
    ],
    "name:fra_x_preferred":[
        "Freedom"
    ],
    "qs_pg:aaroncc":"US",
    "qs_pg:gn_country":"US",
    "qs_pg:gn_fcode":"PPL",
    "qs_pg:gn_pop":0,
    "qs_pg:name":"Freedom",
    "qs_pg:name_adm0":"United States",
    "qs_pg:name_adm1":"Indiana",
    "qs_pg:photos":243,
    "qs_pg:photos_1k":49,
    "qs_pg:photos_9k":1,
    "qs_pg:photos_9r":4,
    "qs_pg:photos_all":243,
    "qs_pg:photos_sr":4,
    "qs_pg:pop_sr":5,
    "qs_pg:qs_pg_placetype":"locality",
    "qs_pg:qs_pg_placetype_gp":"Town",
    "qs_pg:woe_adm0":23424977,
    "woe:adm0_id":23424977,
    "woe:name_adm0":"United States",
    "woe:name_adm1":"Indiana",
    "woe:placetype":"Town",
    "wof:name":"Freedom",
    "wof:placetype":"locality"
},
  "geometry": {"coordinates":[-86.86917,39.20699],"type":"Point"}
}