{
  "type": "Feature",
  "properties": {
    "gn:admin1_code":"AR",
    "gn:admin2_code":"93.0",
    "gn:admin3_code":"91659.0",
    "gn:asciiname":"Cole Ridge",
    "gn:country_code":"US",
    "gn:dem":70,
    "gn:elevation":"72.0",
    "gn:feature_class":"P",
    "gn:feature_code":"PPL",
    "gn:name":"Cole Ridge",
    "gn:population":0,
    "gn:timezone":"America/Chicago",
    "iso:country":"US",
    "wof:name":"Cole Ridge",
    "wof:placetype":"locality"
},
  "geometry": {"coordinates":[-89.99925999999998,35.84285],"type":"Point"}
}