{
  "type": "Feature",
  "properties": {
    "gn:admin1_code":"PA",
    "gn:admin2_code":"79.0",
    "gn:admin3_code":"26928.0",
    "gn:asciiname":"Sandy Run",
    "gn:country_code":"US",
    "gn:dem":504,
    "gn:elevation":"504.0",
    "gn:feature_class":"P",
    "gn:feature_code":"PPL",
    "gn:name":"Sandy Run",
    "gn:population":0,
    "gn:timezone":"America/New_York",
    "iso:country":"US",
    "name:ceb_x_preferred":[
        "Sandy Run"
    ],
    "name:deu_x_preferred":[
        "Sandy Run"
    ],
    "wof:name":"Sandy Run",
    "wof:placetype":"locality"
},
  "geometry": {"coordinates":[-75.85686,41.01953],"type":"Point"}
}