{
  "type": "Feature",
  "properties": {
    "gn:admin1_code":"MS",
    "gn:admin2_code":"59.0",
    "gn:asciiname":"Pelican Mobile Home Park",
    "gn:country_code":"US",
    "gn:dem":10,
    "gn:elevation":"6.0",
    "gn:feature_class":"P",
    "gn:feature_code":"PPL",
    "gn:name":"Pelican Mobile Home Park",
    "gn:population":0,
    "gn:timezone":"America/Chicago",
    "iso:country":"US",
    "wof:name":"Pelican Mobile Home Park",
    "wof:placetype":"campus"
},
  "geometry": {"coordinates":[-88.86452,30.44422],"type":"Point"}
}