{
  "type": "Feature",
  "properties": {
    "gn:admin1_code":"FL",
    "gn:admin2_code":"77.0",
    "gn:asciiname":"Twin Pole",
    "gn:country_code":"US",
    "gn:dem":27,
    "gn:elevation":"14.0",
    "gn:feature_class":"P",
    "gn:feature_code":"PPL",
    "gn:name":"Twin Pole",
    "gn:population":0,
    "gn:timezone":"America/New_York",
    "iso:country":"US",
    "wof:name":"Twin Pole",
    "wof:placetype":"locality"
},
  "geometry": {"coordinates":[-84.84963,30.10242],"type":"Point"}
}