{
  "type": "Feature",
  "properties": {
    "iso:country":"US",
    "name:eng_x_preferred":[
        "Spanish Oaks"
    ],
    "wd:wordcount":11,
    "wof:name":"Spanish Oaks",
    "wof:placetype":"neighbourhood",
    "wof:population":1052,
    "zs:area_m":313822.594953,
    "zs:blockids":[
        320030010062005,
        320030010062004,
        320030010062006
    ],
    "zs:housing10":515,
    "zs:label":"Spanish Oaks",
    "zs:pop10":1052
},
  "geometry": {"coordinates":[-115.18764400000001,36.148434],"type":"Point"}
}