{
  "type": "Feature",
  "properties": {
    "iso:country":"US",
    "name:eng_x_preferred":[
        "Glade-Nelson"
    ],
    "wof:name":"Glade-Nelson",
    "wof:placetype":"neighbourhood",
    "wof:population":974,
    "zs:area_m":659522.919943,
    "zs:blockids":[
        490572107011004,
        490572107011013,
        490572107011022,
        490572107011017,
        490572107011019,
        490572107012007,
        490572107011012,
        490572107012009,
        490572106003013,
        490572107011005,
        490572107012005,
        490572107011006,
        490572107011021,
        490572107011010,
        490572107011020,
        490572107011016,
        490572107011007,
        490572107011014,
        490572107011018,
        490572107011011,
        490572107012004
    ],
    "zs:housing10":432,
    "zs:label":"Glade-Nelson",
    "zs:pop10":974
},
  "geometry": {"coordinates":[-112.02718900000001,41.171803],"type":"Point"}
}