{
  "type": "Feature",
  "properties": {
    "iso:country":"US",
    "name:eng_x_preferred":[
        "Heatherwilde Villas"
    ],
    "wof:name":"Heatherwilde Villas",
    "wof:placetype":"neighbourhood",
    "wof:population":703,
    "zs:area_m":589529.469143,
    "zs:blockids":[
        484530018621033
    ],
    "zs:housing10":256,
    "zs:label":"Heatherwilde Villas",
    "zs:pop10":703
},
  "geometry": {"coordinates":[-97.634378,30.450315],"type":"Point"}
}