{
  "type": "Feature",
  "properties": {
    "gn:admin1_code":"TX",
    "gn:admin2_code":"307.0",
    "gn:asciiname":"Walker Crossing",
    "gn:country_code":"US",
    "gn:dem":411,
    "gn:elevation":"406.0",
    "gn:feature_class":"P",
    "gn:feature_code":"PPL",
    "gn:name":"Walker Crossing",
    "gn:population":0,
    "gn:timezone":"America/Chicago",
    "iso:country":"US",
    "wof:name":"Walker Crossing",
    "wof:placetype":"locality"
},
  "geometry": {"coordinates":[-99.36228,31.4346],"type":"Point"}
}