{
  "type": "Feature",
  "properties": {
    "gn:admin1_code":"IN",
    "gn:admin2_code":"057",
    "gn:admin3_code":"22612.0",
    "gn:asciiname":"Chateau Court",
    "gn:country_code":"US",
    "gn:dem":254,
    "gn:elevation":"252.0",
    "gn:feature_class":"P",
    "gn:feature_code":"PPL",
    "gn:name":"Chateau Court",
    "gn:population":0,
    "gn:timezone":"America/Indiana/Indianapolis",
    "iso:country":"US",
    "wof:name":"Chateau Court",
    "wof:placetype":"locality"
},
  "geometry": {"coordinates":[-85.97750000000001,39.96556],"type":"Point"}
}