{
  "type": "Feature",
  "properties": {
    "gn:admin1_code":"CA",
    "gn:admin2_code":"17.0",
    "gn:asciiname":"Spanish Flat",
    "gn:country_code":"US",
    "gn:dem":740,
    "gn:elevation":"741.0",
    "gn:feature_class":"P",
    "gn:feature_code":"PPL",
    "gn:name":"Spanish Flat",
    "gn:population":0,
    "gn:timezone":"America/Los_Angeles",
    "iso:country":"US",
    "name:zho_x_preferred":[
        "\u65af\u6f58\u5c3c\u4ec0\u5f17\u62c9\u7279"
    ],
    "wof:name":"Spanish Flat",
    "wof:placetype":"locality"
},
  "geometry": {"coordinates":[-120.80938,38.82323],"type":"Point"}
}