{
  "type": "Feature",
  "properties": {
    "gn:admin1_code":"OK",
    "gn:admin2_code":"43",
    "gn:asciiname":"Burmah",
    "gn:country_code":"US",
    "gn:dem":573,
    "gn:elevation":"567.0",
    "gn:feature_class":"P",
    "gn:feature_code":"PPL",
    "gn:name":"Burmah",
    "gn:population":0,
    "gn:timezone":"America/Chicago",
    "iso:country":"US",
    "name:ceb_x_preferred":[
        "Burmah"
    ],
    "name:swe_x_preferred":[
        "Burmah"
    ],
    "wof:name":"Burmah",
    "wof:placetype":"locality"
},
  "geometry": {"coordinates":[-99.07482,35.82699],"type":"Point"}
}