{
  "type": "Feature",
  "properties": {
    "gn:admin1_code":"IL",
    "gn:admin2_code":"197",
    "gn:admin3_code":"21241.0",
    "gn:asciiname":"Indian Boundary",
    "gn:country_code":"US",
    "gn:dem":198,
    "gn:elevation":"198.0",
    "gn:feature_class":"P",
    "gn:feature_code":"PPL",
    "gn:name":"Indian Boundary",
    "gn:population":0,
    "gn:timezone":"America/Chicago",
    "iso:country":"US",
    "wof:name":"Indian Boundary",
    "wof:placetype":"locality"
},
  "geometry": {"coordinates":[-88.1375,41.69194],"type":"Point"}
}