{
  "type": "Feature",
  "properties": {
    "gn:country":"US",
    "gn:fcode":"PPL",
    "gn:population":0,
    "iso:country":"US",
    "name:azb_x_preferred":[
        "\u0648\u06cc\u0631\u0632 \u0648\u0644\u06cc"
    ],
    "name:eng_x_preferred":[
        "Wear Valley"
    ],
    "name:eng_x_variant":[
        "Wears Valley"
    ],
    "name:fas_x_preferred":[
        "\u0648\u06cc\u0631\u0632 \u0648\u0644\u06cc"
    ],
    "name:fra_x_preferred":[
        "Wears Valley"
    ],
    "name:und_x_variant":[
        "Wears Cove"
    ],
    "name:vol_x_preferred":[
        "Wears Valley"
    ],
    "name:zho_x_preferred":[
        "\u6c83\u5c14\u65af\u8c37"
    ],
    "qs_pg:aaroncc":"US",
    "qs_pg:gn_country":"US",
    "qs_pg:gn_fcode":"PPL",
    "qs_pg:gn_pop":0,
    "qs_pg:name":"Wear Valley",
    "qs_pg:name_adm0":"United States",
    "qs_pg:name_adm1":"Tennessee",
    "qs_pg:photos":198,
    "qs_pg:photos_1k":40,
    "qs_pg:photos_9k":1,
    "qs_pg:photos_9r":4,
    "qs_pg:photos_all":198,
    "qs_pg:photos_sr":4,
    "qs_pg:pop_sr":0,
    "qs_pg:qs_pg_placetype":"locality",
    "qs_pg:qs_pg_placetype_gp":"Town",
    "qs_pg:woe_adm0":23424977,
    "woe:adm0_id":23424977,
    "woe:name_adm0":"United States",
    "woe:name_adm1":"Tennessee",
    "woe:placetype":"Town",
    "wof:name":"Wear Valley",
    "wof:placetype":"locality"
},
  "geometry": {"coordinates":[-83.65322,35.71398],"type":"Point"}
}