{
  "type": "Feature",
  "properties": {
    "iso:country":"US",
    "name:afr_x_preferred":[
        "Brahman"
    ],
    "name:cat_x_preferred":[
        "Brahman"
    ],
    "name:ces_x_preferred":[
        "Brahmansk\u00fd skot"
    ],
    "name:ces_x_variant":[
        "brahmansk\u00fd skot"
    ],
    "name:deu_x_preferred":[
        "Brahman"
    ],
    "name:eng_x_preferred":[
        "Brahman Valley"
    ],
    "name:eng_x_variant":[
        "Brahman"
    ],
    "name:fra_x_preferred":[
        "Brahmane"
    ],
    "name:fry_x_preferred":[
        "Brachmaan"
    ],
    "name:fry_x_variant":[
        "Brahman"
    ],
    "name:glg_x_preferred":[
        "Brahman"
    ],
    "name:hun_x_preferred":[
        "Brahma marha"
    ],
    "name:ind_x_preferred":[
        "Sapi brahman"
    ],
    "name:jpn_x_preferred":[
        "\u30d6\u30e9\u30fc\u30de\u30f3\u7a2e"
    ],
    "name:nld_x_preferred":[
        "Brahman"
    ],
    "name:por_x_preferred":[
        "Brahman"
    ],
    "name:rus_x_preferred":[
        "\u0411\u0440\u0430\u0445\u043c\u0430\u043d"
    ],
    "name:snd_x_preferred":[
        "\u067f\u0648\u0647\u064a \u062f\u0627\u0631 \u068d\u06b3\u0648"
    ],
    "name:spa_x_preferred":[
        "Brahman"
    ],
    "name:tam_x_preferred":[
        "\u0baa\u0bbf\u0bb0\u0bae\u0bcd\u0bae\u0ba9\u0bcd \u0bae\u0bbe\u0b9f\u0bc1"
    ],
    "name:ukr_x_preferred":[
        "\u0411\u0440\u0430\u0445\u043c\u0430\u043d"
    ],
    "name:vie_x_preferred":[
        "B\u00f2 Brahman"
    ],
    "wd:wordcount":556,
    "wof:name":"Brahman Valley",
    "wof:placetype":"neighbourhood",
    "wof:population":837,
    "zs:area_m":290026.478845,
    "zs:blockids":[
        490351122021010,
        490351123012012,
        490351123012015,
        490351123012010,
        490351123012014,
        490351123012013,
        490351123012009
    ],
    "zs:housing10":332,
    "zs:label":"Brahman Valley",
    "zs:pop10":837
},
  "geometry": {"coordinates":[-111.886065,40.650977],"type":"Point"}
}