{
  "type": "Feature",
  "properties": {
    "gn:country":"US",
    "gn:fcode":"PPL",
    "gn:population":1900,
    "iso:country":"US",
    "name:ara_x_preferred":[
        "\u0625\u064a\u0633\u062a \u0643\u064a\u0646\u063a\u0633\u062a\u0648\u0646"
    ],
    "name:cat_x_preferred":[
        "East Kingston"
    ],
    "name:ceb_x_preferred":[
        "East Kingston"
    ],
    "name:che_x_preferred":[
        "\u0418\u0441\u0442-\u041a\u0438\u043d\u0433\u0441\u0442\u043e\u043d"
    ],
    "name:cym_x_preferred":[
        "East Kingston"
    ],
    "name:deu_x_preferred":[
        "East Kingston"
    ],
    "name:eng_x_preferred":[
        "East Kingston"
    ],
    "name:eus_x_preferred":[
        "East Kingston"
    ],
    "name:fra_x_preferred":[
        "East Kingston"
    ],
    "name:hat_x_preferred":[
        "East Kingston"
    ],
    "name:hun_x_preferred":[
        "East Kingston"
    ],
    "name:ita_x_preferred":[
        "East Kingston"
    ],
    "name:kaz_x_preferred":[
        "\u0418\u0441\u0442 \u041a\u0438\u043d\u0433\u0441\u0442\u043e\u043d"
    ],
    "name:kir_x_preferred":[
        "\u0418\u0441\u0442 \u041a\u0438\u043d\u0433\u0441\u0442\u043e\u043d"
    ],
    "name:nld_x_preferred":[
        "East Kingston"
    ],
    "name:pol_x_preferred":[
        "East Kingston"
    ],
    "name:spa_x_preferred":[
        "East Kingston"
    ],
    "name:swe_x_preferred":[
        "East Kingston"
    ],
    "name:tat_x_preferred":[
        "\u0418\u0441\u0442-\u041a\u0438\u043d\u0433\u0441\u0442\u043e\u043d"
    ],
    "name:tur_x_preferred":[
        "East Kingston"
    ],
    "name:ukr_x_preferred":[
        "\u0406\u0441\u0442-\u041a\u0456\u043d\u0433\u0441\u0442\u043e\u043d"
    ],
    "name:urd_x_preferred":[
        "\u0627\u06cc\u0633\u0679 \u06a9\u0646\u06af\u0633\u0679\u0646\u060c \u0646\u06cc\u0648 \u06c1\u06cc\u0645\u067e\u0634\u0627\u0626\u0631"
    ],
    "name:urd_x_variant":[
        "\u0627\u06cc\u0633\u0679 \u06a9\u0646\u06af\u0633\u0679\u0646"
    ],
    "name:vol_x_preferred":[
        "East Kingston"
    ],
    "name:war_x_preferred":[
        "East Kingston"
    ],
    "qs_pg:aaroncc":"US",
    "qs_pg:gn_country":"US",
    "qs_pg:gn_fcode":"PPL",
    "qs_pg:gn_pop":1900,
    "qs_pg:name":"East Kingston",
    "qs_pg:name_adm0":"United States",
    "qs_pg:name_adm1":"New Hampshire",
    "qs_pg:photos":71,
    "qs_pg:photos_1k":14,
    "qs_pg:photos_9k":1,
    "qs_pg:photos_9r":2,
    "qs_pg:photos_all":74,
    "qs_pg:photos_sr":2,
    "qs_pg:pop_sr":3,
    "qs_pg:qs_pg_placetype":"locality",
    "qs_pg:qs_pg_placetype_gp":"Town",
    "qs_pg:woe_adm0":23424977,
    "woe:adm0_id":23424977,
    "woe:name_adm0":"United States",
    "woe:name_adm1":"New Hampshire",
    "woe:placetype":"Town",
    "wof:coterminous":[
        404476705
    ],
    "wof:name":"East Kingston",
    "wof:placetype":"locality",
    "wof:population":1900,
    "wof:statistical_gore":1
},
  "geometry": {"coordinates":[-71.01672000000001,42.92564],"type":"Point"}
}