{
  "type": "Feature",
  "properties": {
    "iso:country":"US",
    "name:eng_x_preferred":[
        "Sunrise Place"
    ],
    "wof:name":"Sunrise Place",
    "wof:placetype":"neighbourhood",
    "wof:population":1095,
    "zs:area_m":1354576.866993,
    "zs:blockids":[
        530110408102002,
        530110408102019,
        530110408102015,
        530110408102001,
        530110408102018,
        530110408102011,
        530110411051007,
        530110408102016,
        530110408102017,
        530110411051009,
        530110408102004,
        530110410101000
    ],
    "zs:housing10":434,
    "zs:label":"Sunrise Place",
    "zs:pop10":1095
},
  "geometry": {"coordinates":[-122.634897,45.678804],"type":"Point"}
}