{
  "type": "Feature",
  "properties": {
    "gn:admin1_code":"AR",
    "gn:admin2_code":"121.0",
    "gn:admin3_code":"92220.0",
    "gn:asciiname":"Supply",
    "gn:country_code":"US",
    "gn:dem":128,
    "gn:elevation":"129.0",
    "gn:feature_class":"P",
    "gn:feature_code":"PPL",
    "gn:name":"Supply",
    "gn:population":0,
    "gn:timezone":"America/Chicago",
    "iso:country":"US",
    "name:ita_x_preferred":[
        "Supply"
    ],
    "name:jpn_x_preferred":[
        "\u30b5\u30d7\u30e9\u30a4"
    ],
    "wof:name":"Supply",
    "wof:placetype":"locality"
},
  "geometry": {"coordinates":[-90.84151,36.45701],"type":"Point"}
}