{
  "type": "Feature",
  "properties": {
    "gn:admin1_code":"PA",
    "gn:admin2_code":"61.0",
    "gn:admin3_code":"81104.0",
    "gn:asciiname":"Frogtown",
    "gn:country_code":"US",
    "gn:dem":338,
    "gn:elevation":"335.0",
    "gn:feature_class":"P",
    "gn:feature_code":"PPL",
    "gn:name":"Frogtown",
    "gn:population":0,
    "gn:timezone":"America/New_York",
    "iso:country":"US",
    "wof:name":"Frogtown",
    "wof:placetype":"locality"
},
  "geometry": {"coordinates":[-78.10973,40.71478],"type":"Point"}
}