{
  "type": "Feature",
  "properties": {
    "gn:admin1_code":"KY",
    "gn:admin2_code":"51",
    "gn:asciiname":"Chestnutburg",
    "gn:country_code":"US",
    "gn:dem":249,
    "gn:elevation":"254.0",
    "gn:feature_class":"P",
    "gn:feature_code":"PPL",
    "gn:name":"Chestnutburg",
    "gn:population":0,
    "gn:timezone":"America/New_York",
    "iso:country":"US",
    "name:eng_x_preferred":[
        "Chestnutburg"
    ],
    "name:und_x_variant":[
        "Chesnutburg"
    ],
    "wof:name":"Chestnutburg",
    "wof:placetype":"locality"
},
  "geometry": {"coordinates":[-83.79659000000002,37.28898],"type":"Point"}
}