{
  "type": "Feature",
  "properties": {
    "gn:admin1_code":"WI",
    "gn:admin2_code":"81.0",
    "gn:admin3_code":"11625.0",
    "gn:asciiname":"Shennington",
    "gn:country_code":"US",
    "gn:dem":279,
    "gn:elevation":"277.0",
    "gn:feature_class":"P",
    "gn:feature_code":"PPL",
    "gn:name":"Shennington",
    "gn:population":0,
    "gn:timezone":"America/Chicago",
    "iso:country":"US",
    "wof:name":"Shennington",
    "wof:placetype":"locality"
},
  "geometry": {"coordinates":[-90.31762999999999,44.0258],"type":"Point"}
}