{
  "type": "Feature",
  "properties": {
    "iso:country":"US",
    "name:eng_x_preferred":[
        "Chumasero Heights"
    ],
    "wof:name":"Chumasero Heights",
    "wof:placetype":"neighbourhood",
    "wof:population":555,
    "zs:area_m":225736.772798,
    "zs:blockids":[
        530110419001005,
        530110419001029,
        530110419001033,
        530110419001034,
        530110419001021,
        530110419001023,
        530110419001022,
        530110420001015,
        530110419001017,
        530110419001024,
        530110419001018,
        530110419001025,
        530110419001030,
        530110419001036,
        530110419001035
    ],
    "zs:housing10":314,
    "zs:label":"Chumasero Heights",
    "zs:pop10":555
},
  "geometry": {"coordinates":[-122.667413,45.648684],"type":"Point"}
}