{
  "type": "Feature",
  "properties": {
    "gn:admin1_code":"TX",
    "gn:admin2_code":"39",
    "gn:asciiname":"Gulf Park",
    "gn:country_code":"US",
    "gn:dem":5,
    "gn:elevation":"2.0",
    "gn:feature_class":"P",
    "gn:feature_code":"PPL",
    "gn:name":"Gulf Park",
    "gn:population":0,
    "gn:timezone":"America/Chicago",
    "iso:country":"US",
    "wof:name":"Gulf Park",
    "wof:placetype":"locality"
},
  "geometry": {"coordinates":[-95.41383,28.96108],"type":"Point"}
}