{
  "type": "Feature",
  "properties": {
    "gn:admin1_code":"NC",
    "gn:admin2_code":"129",
    "gn:admin3_code":"91404.0",
    "gn:asciiname":"Highland Pines Mobile Home Park",
    "gn:country_code":"US",
    "gn:dem":11,
    "gn:elevation":"11.0",
    "gn:feature_class":"P",
    "gn:feature_code":"PPL",
    "gn:name":"Highland Pines Mobile Home Park",
    "gn:population":0,
    "gn:timezone":"America/New_York",
    "iso:country":"US",
    "wof:name":"Highland Pines Mobile Home Park",
    "wof:placetype":"campus"
},
  "geometry": {"coordinates":[-77.8456,34.268],"type":"Point"}
}