{
  "type": "Feature",
  "properties": {
    "gn:admin1_code":"GA",
    "gn:admin2_code":"179",
    "gn:asciiname":"Oakview Mobile Home Park",
    "gn:country_code":"US",
    "gn:dem":27,
    "gn:elevation":"24.0",
    "gn:feature_class":"P",
    "gn:feature_code":"PPL",
    "gn:name":"Oakview Mobile Home Park",
    "gn:population":0,
    "gn:timezone":"America/New_York",
    "iso:country":"US",
    "wof:name":"Oakview Mobile Home Park",
    "wof:placetype":"campus"
},
  "geometry": {"coordinates":[-81.6404,31.8261],"type":"Point"}
}