{
  "type": "Feature",
  "properties": {
    "gn:admin1_code":"PA",
    "gn:admin2_code":"133.0",
    "gn:admin3_code":"57872.0",
    "gn:asciiname":"Maple Grove",
    "gn:country_code":"US",
    "gn:dem":189,
    "gn:elevation":"193.0",
    "gn:feature_class":"P",
    "gn:feature_code":"PPL",
    "gn:name":"Maple Grove",
    "gn:population":0,
    "gn:timezone":"America/New_York",
    "iso:country":"US",
    "name:ceb_x_preferred":[
        "Maple Grove"
    ],
    "name:deu_x_preferred":[
        "Maple Grove"
    ],
    "name:fra_x_preferred":[
        "Maple Grove"
    ],
    "name:ita_x_preferred":[
        "Maple Grove"
    ],
    "name:pol_x_preferred":[
        "Maple Grove"
    ],
    "name:spa_x_preferred":[
        "Maple Grove"
    ],
    "name:swe_x_preferred":[
        "Maple Grove"
    ],
    "name:ukr_x_preferred":[
        "\u041c\u0435\u0439\u043f\u043b-\u0413\u0440\u043e\u0443\u0432"
    ],
    "wof:name":"Maple Grove",
    "wof:placetype":"locality"
},
  "geometry": {"coordinates":[-76.95303,39.88065],"type":"Point"}
}