{
  "type": "Feature",
  "properties": {
    "gn:admin1_code":"NY",
    "gn:admin2_code":"49.0",
    "gn:admin3_code":"30796.0",
    "gn:asciiname":"Brantingham",
    "gn:country_code":"US",
    "gn:dem":386,
    "gn:elevation":"382.0",
    "gn:feature_class":"P",
    "gn:feature_code":"PPL",
    "gn:name":"Brantingham",
    "gn:population":0,
    "gn:timezone":"America/New_York",
    "iso:country":"US",
    "name:ceb_x_preferred":[
        "Brantingham"
    ],
    "name:fas_x_preferred":[
        "\u0628\u0631\u0627\u0646\u062a\u06cc\u0646\u06af\u0647\u0627\u0645"
    ],
    "name:ita_x_preferred":[
        "Brantingham"
    ],
    "name:nld_x_preferred":[
        "Brantingham"
    ],
    "name:pol_x_preferred":[
        "Brantingham"
    ],
    "name:swe_x_preferred":[
        "Brantingham"
    ],
    "wof:name":"Brantingham",
    "wof:placetype":"locality"
},
  "geometry": {"coordinates":[-75.29212,43.68868],"type":"Point"}
}