{
  "type": "Feature",
  "properties": {
    "gn:admin1_code":"NC",
    "gn:admin2_code":"193.0",
    "gn:admin3_code":"93024.0",
    "gn:asciiname":"Windy Gap",
    "gn:country_code":"US",
    "gn:dem":367,
    "gn:elevation":"363.0",
    "gn:feature_class":"P",
    "gn:feature_code":"PPL",
    "gn:name":"Windy Gap",
    "gn:population":0,
    "gn:timezone":"America/New_York",
    "iso:country":"US",
    "name:ceb_x_preferred":[
        "Windy Gap"
    ],
    "name:deu_x_preferred":[
        "Windy Gap"
    ],
    "name:nno_x_preferred":[
        "Windy Gap"
    ],
    "wof:name":"Windy Gap",
    "wof:placetype":"locality"
},
  "geometry": {"coordinates":[-80.98952,36.11847],"type":"Point"}
}