{
  "type": "Feature",
  "properties": {
    "iso:country":"US",
    "qs_pg:aaroncc":"US",
    "qs_pg:name":"Lake Jacksonville",
    "qs_pg:name_adm0":"United States",
    "qs_pg:name_adm1":"Texas",
    "qs_pg:photos":6,
    "qs_pg:photos_1k":1,
    "qs_pg:photos_9k":1,
    "qs_pg:photos_9r":1,
    "qs_pg:photos_all":6,
    "qs_pg:photos_sr":1,
    "qs_pg:pop_sr":0,
    "qs_pg:qs_pg_placetype":"locality",
    "qs_pg:qs_pg_placetype_gp":"Town",
    "qs_pg:woe_adm0":23424977,
    "woe:adm0_id":23424977,
    "woe:name_adm0":"United States",
    "woe:name_adm1":"Texas",
    "woe:placetype":"Town",
    "wof:name":"Lake Jacksonville",
    "wof:placetype":"locality"
},
  "geometry": {"coordinates":[-95.288864,31.909484],"type":"Point"}
}