{
  "type": "Feature",
  "properties": {
    "gn:admin1_code":"NJ",
    "gn:admin2_code":"11.0",
    "gn:admin3_code":"74870.0",
    "gn:asciiname":"Big Oak",
    "gn:country_code":"US",
    "gn:dem":35,
    "gn:elevation":"32.0",
    "gn:feature_class":"P",
    "gn:feature_code":"PPL",
    "gn:name":"Big Oak",
    "gn:population":0,
    "gn:timezone":"America/New_York",
    "iso:country":"US",
    "wof:name":"Big Oak",
    "wof:placetype":"locality"
},
  "geometry": {"coordinates":[-75.20851999999999,39.48623],"type":"Point"}
}