{
  "type": "Feature",
  "properties": {
    "iso:country":"US",
    "name:ceb_x_preferred":[
        "Howard Heights"
    ],
    "name:deu_x_preferred":[
        "Howard Heights"
    ],
    "name:eng_x_preferred":[
        "Howard Heights"
    ],
    "name:nno_x_preferred":[
        "Howard Heights"
    ],
    "name:swe_x_preferred":[
        "Howard Heights"
    ],
    "name:zho_x_preferred":[
        "\u970d\u83ef\u5fb7\u9ad8\u5730"
    ],
    "wd:wordcount":170,
    "wof:name":"Howard Heights",
    "wof:placetype":"neighbourhood",
    "wof:population":362,
    "zs:area_m":1430903.460059,
    "zs:blockids":[
        371070106003002,
        371070105001000,
        371070108002024,
        371070106002001,
        371070106003000,
        371070105002013,
        371070108003044,
        371070108003033,
        371070108002034,
        371070108003045,
        371070108003042,
        371070108003046,
        371070106003003,
        371070108003040,
        371070108003031,
        371070106003001,
        371070108003030,
        371070108002025,
        371070108003032,
        371070108003047,
        371070108003041
    ],
    "zs:housing10":196,
    "zs:label":"Howard Heights",
    "zs:pop10":362
},
  "geometry": {"coordinates":[-77.58428600000001,35.288854],"type":"Point"}
}