{
  "type": "Feature",
  "properties": {
    "gn:country":"US",
    "gn:fcode":"PPL",
    "gn:population":0,
    "iso:country":"US",
    "name:eng_x_preferred":[
        "Griffins Corners"
    ],
    "qs_pg:aaroncc":"US",
    "qs_pg:gn_country":"US",
    "qs_pg:gn_fcode":"PPL",
    "qs_pg:gn_pop":0,
    "qs_pg:name":"Griffins Corners",
    "qs_pg:name_adm0":"United States",
    "qs_pg:name_adm1":"New York",
    "qs_pg:photos":2,
    "qs_pg:photos_1k":1,
    "qs_pg:photos_9k":1,
    "qs_pg:photos_9r":1,
    "qs_pg:photos_all":2,
    "qs_pg:photos_sr":1,
    "qs_pg:pop_sr":0,
    "qs_pg:qs_pg_placetype":"neighbourhood",
    "qs_pg:qs_pg_placetype_gp":"Suburb",
    "qs_pg:woe_adm0":23424977,
    "wof:name":"Griffins Corners",
    "wof:placetype":"neighbourhood",
    "wof:population":209,
    "zs:area_m":3070783.949309,
    "zs:blockids":[
        360670160012008,
        360670160012017,
        360670160012013,
        360670160012018
    ],
    "zs:housing10":83,
    "zs:label":"Griffins Corners",
    "zs:pop10":209
},
  "geometry": {"coordinates":[-76.203551,42.929543],"type":"Point"}
}