{
  "type": "Feature",
  "properties": {
    "gn:admin1_code":"AK",
    "gn:admin2_code":"261.0",
    "gn:asciiname":"Ptarmigan",
    "gn:country_code":"US",
    "gn:dem":613,
    "gn:elevation":"513.0",
    "gn:feature_class":"P",
    "gn:feature_code":"PPL",
    "gn:name":"Ptarmigan",
    "gn:population":0,
    "gn:timezone":"America/Anchorage",
    "iso:country":"US",
    "name:eng_x_preferred":[
        "Ptarmigan"
    ],
    "name:und_x_variant":[
        "Ptarmigan Drop Roadhouse"
    ],
    "wof:name":"Ptarmigan",
    "wof:placetype":"locality"
},
  "geometry": {"coordinates":[-145.62166999999999,61.18861],"type":"Point"}
}