{
  "type": "Feature",
  "properties": {
    "gn:admin1_code":"AR",
    "gn:admin2_code":"95.0",
    "gn:admin3_code":"92895.0",
    "gn:asciiname":"Park Grove",
    "gn:country_code":"US",
    "gn:dem":53,
    "gn:elevation":"55.0",
    "gn:feature_class":"P",
    "gn:feature_code":"PPL",
    "gn:name":"Park Grove",
    "gn:population":0,
    "gn:timezone":"America/Chicago",
    "iso:country":"US",
    "wof:name":"Park Grove",
    "wof:placetype":"locality"
},
  "geometry": {"coordinates":[-91.21178999999999,34.69232],"type":"Point"}
}