{
  "type": "Feature",
  "properties": {
    "gn:admin1_code":"TX",
    "gn:admin2_code":"323.0",
    "gn:asciiname":"Rosita Valley Colonia",
    "gn:country_code":"US",
    "gn:dem":219,
    "gn:elevation":"220.0",
    "gn:feature_class":"P",
    "gn:feature_code":"PPL",
    "gn:name":"Rosita Valley Colonia",
    "gn:population":0,
    "gn:timezone":"America/Chicago",
    "iso:country":"US",
    "wof:name":"Rosita Valley Colonia",
    "wof:placetype":"locality"
},
  "geometry": {"coordinates":[-100.42923999999999,28.61831],"type":"Point"}
}