{
  "type": "Feature",
  "properties": {
    "gn:country":"US",
    "gn:fcode":"PPL",
    "gn:population":0,
    "iso:country":"US",
    "name:ara_x_preferred":[
        "\u0645\u0627\u0648\u0646\u062a \u0645\u0648\u0631\u064a\u0633"
    ],
    "name:eng_x_preferred":[
        "Mount Morris"
    ],
    "name:hat_x_preferred":[
        "Mount Morris"
    ],
    "name:pol_x_preferred":[
        "Mount Morris"
    ],
    "name:spa_x_preferred":[
        "Mount Morris"
    ],
    "name:vie_x_preferred":[
        "Mount Morris"
    ],
    "qs_pg:aaroncc":"US",
    "qs_pg:gn_country":"US",
    "qs_pg:gn_fcode":"PPL",
    "qs_pg:gn_pop":0,
    "qs_pg:name":"Mount Morris",
    "qs_pg:name_adm0":"United States",
    "qs_pg:name_adm1":"Wisconsin",
    "qs_pg:photos":103,
    "qs_pg:photos_1k":21,
    "qs_pg:photos_9k":1,
    "qs_pg:photos_9r":3,
    "qs_pg:photos_all":103,
    "qs_pg:photos_sr":3,
    "qs_pg:pop_sr":0,
    "qs_pg:qs_pg_placetype":"locality",
    "qs_pg:qs_pg_placetype_gp":"Town",
    "qs_pg:woe_adm0":23424977,
    "woe:adm0_id":23424977,
    "woe:name_adm0":"United States",
    "woe:name_adm1":"Wisconsin",
    "woe:placetype":"Town",
    "wof:name":"Mount Morris",
    "wof:placetype":"locality",
    "wof:population":1085
},
  "geometry": {"coordinates":[-89.19067,44.11442],"type":"Point"}
}