{
  "type": "Feature",
  "properties": {
    "iso:country":"US",
    "name:eng_x_preferred":[
        "Holmes and Hendersons"
    ],
    "wof:name":"Holmes and Hendersons",
    "wof:placetype":"neighbourhood",
    "zs:area_m":101185.190661,
    "zs:blockids":[
        490351003062019,
        490351027021005,
        490351145003039,
        490351027021002,
        490351145003000,
        490351145003001
    ],
    "zs:housing10":0,
    "zs:label":"Holmes and Hendersons",
    "zs:pop10":0
},
  "geometry": {"coordinates":[-111.940005,40.765977],"type":"Point"}
}