{
  "type": "Feature",
  "properties": {
    "iso:country":"US",
    "name:eng_x_preferred":[
        "Walker Cove"
    ],
    "wof:name":"Walker Cove",
    "wof:placetype":"neighbourhood",
    "wof:population":1409,
    "zs:area_m":7477347.286814,
    "zs:blockids":[
        120950166012145,
        120950166012146,
        120950166012144,
        120950166012142,
        120950166012147,
        120950166012148,
        120950166012140,
        120950166012143
    ],
    "zs:housing10":482,
    "zs:label":"Walker Cove",
    "zs:pop10":1409
},
  "geometry": {"coordinates":[-81.14258,28.577819],"type":"Point"}
}