{
  "type": "Feature",
  "properties": {
    "iso:country":"US",
    "name:eng_x_preferred":[
        "Country Meadows"
    ],
    "wof:name":"Country Meadows",
    "wof:placetype":"neighbourhood",
    "wof:population":358,
    "zs:area_m":1620601.03576,
    "zs:blockids":[
        120810020142022,
        120810020142032,
        120810020142027,
        120810020142019,
        120810020142017,
        120810020142018,
        120810020142023,
        120810020142034,
        120810020142024,
        120810020142028,
        120810020142026,
        120810020142015,
        120810020142020,
        120810020142031,
        120810020142039,
        120810020142030,
        120810020142036,
        120810020142010,
        120810020142021,
        120810020142016,
        120810020142035,
        120810020142025,
        120810019131045,
        120810020142029
    ],
    "zs:housing10":212,
    "zs:label":"Country Meadows",
    "zs:pop10":358
},
  "geometry": {"coordinates":[-82.405483,27.517777],"type":"Point"}
}