{
  "type": "Feature",
  "properties": {
    "gn:admin1_code":"MN",
    "gn:admin2_code":"9.0",
    "gn:admin3_code":"21536.0",
    "gn:asciiname":"Foley Mobile Home Park South",
    "gn:country_code":"US",
    "gn:dem":342,
    "gn:elevation":"343.0",
    "gn:feature_class":"P",
    "gn:feature_code":"PPL",
    "gn:name":"Foley Mobile Home Park South",
    "gn:population":0,
    "gn:timezone":"America/Chicago",
    "iso:country":"US",
    "wof:name":"Foley Mobile Home Park South",
    "wof:placetype":"campus"
},
  "geometry": {"coordinates":[-93.90389,45.66333],"type":"Point"}
}