{
  "type": "Feature",
  "properties": {
    "gn:country":"US",
    "gn:fcode":"PPL",
    "gn:population":0,
    "iso:country":"US",
    "name:azb_x_preferred":[
        "\u0627\u0648\u0646\u062f\u0631\u0648\u0648\u062f"
    ],
    "name:cym_x_preferred":[
        "Underwood"
    ],
    "name:deu_x_preferred":[
        "Underwood"
    ],
    "name:eng_x_preferred":[
        "Underwood"
    ],
    "name:fra_x_preferred":[
        "Underwood"
    ],
    "name:hun_x_preferred":[
        "Underwood"
    ],
    "name:jpn_x_preferred":[
        "\u30a2\u30f3\u30c0\u30fc\u30a6\u30c3\u30c9"
    ],
    "name:nld_x_preferred":[
        "Underwood"
    ],
    "qs_pg:aaroncc":"US",
    "qs_pg:gn_country":"US",
    "qs_pg:gn_fcode":"PPL",
    "qs_pg:gn_pop":0,
    "qs_pg:name":"Underwood",
    "qs_pg:name_adm0":"United States",
    "qs_pg:name_adm1":"Washington",
    "qs_pg:photos":530,
    "qs_pg:photos_1k":107,
    "qs_pg:photos_9k":2,
    "qs_pg:photos_9r":5,
    "qs_pg:photos_all":530,
    "qs_pg:photos_sr":7,
    "qs_pg:pop_sr":0,
    "qs_pg:qs_pg_placetype":"locality",
    "qs_pg:qs_pg_placetype_gp":"Town",
    "qs_pg:woe_adm0":23424977,
    "woe:adm0_id":23424977,
    "woe:name_adm0":"United States",
    "woe:name_adm1":"Washington",
    "woe:placetype":"Town",
    "wof:name":"Underwood",
    "wof:placetype":"locality"
},
  "geometry": {"coordinates":[-121.52618,45.72956],"type":"Point"}
}