{
  "type": "Feature",
  "properties": {
    "iso:country":"US",
    "name:eng_x_preferred":[
        "Allendale"
    ],
    "name:fra_x_preferred":[
        "Allendale"
    ],
    "name:nld_x_preferred":[
        "Allendale"
    ],
    "wof:name":"Allendale",
    "wof:placetype":"neighbourhood",
    "wof:population":1410,
    "zs:area_m":1362412.44667,
    "zs:blockids":[
        132150104022016,
        132150104021006,
        132150104023028,
        132150104023029,
        132150104022013,
        132150104022012,
        132150104021013,
        132150104022009,
        132150104012017,
        132150104012038,
        132150104022010,
        132150104022011,
        132150104012023,
        132150104012016,
        132150104011013,
        132150104011016,
        132150104012019,
        132150104011017,
        132150104021011,
        132150104011019,
        132150104011022,
        132150104023027,
        132150104011025,
        132150104012030,
        132150104022015,
        132150104012020,
        132150104011024,
        132150104011020,
        132150104022007,
        132150104021000,
        132150104011018,
        132150104022005,
        132150104022008,
        132150104012018,
        132150104011023,
        132150104012039,
        132150104012040,
        132150104022018,
        132150104021014,
        132150104021009,
        132150104012022,
        132150104011021,
        132150104012015,
        132150104012036,
        132150104021012,
        132150104022006,
        132150104022014,
        132150104012027,
        132150104012026
    ],
    "zs:housing10":630,
    "zs:label":"Allendale",
    "zs:pop10":1410
},
  "geometry": {"coordinates":[-84.92997099999999,32.526595],"type":"Point"}
}