{
  "type": "Feature",
  "properties": {
    "gn:gn_country":"US",
    "gn:gn_fcode":"PPL",
    "gn:gn_pop":279,
    "iso:country":"US",
    "name:ara_x_preferred":[
        "\u0628\u0627\u0643\u064a\u0631\u0647\u064a\u0644"
    ],
    "name:deu_x_preferred":[
        "Bakerhill"
    ],
    "name:eng_x_preferred":[
        "Bakerhill"
    ],
    "name:eus_x_preferred":[
        "Bakerhill"
    ],
    "name:fas_x_preferred":[
        "\u0628\u06cc\u06a9\u0631\u0647\u06cc\u0644\u060c \u0622\u0644\u0627\u0628\u0627\u0645\u0627"
    ],
    "name:fra_x_preferred":[
        "Bakerhill"
    ],
    "name:hun_x_preferred":[
        "Bakerhill"
    ],
    "name:ind_x_preferred":[
        "Bakerhill"
    ],
    "name:ita_x_preferred":[
        "Bakerhill"
    ],
    "name:mlg_x_preferred":[
        "Bakerhill"
    ],
    "name:nld_x_preferred":[
        "Bakerhill"
    ],
    "name:nob_x_preferred":[
        "Bakerhill"
    ],
    "name:pol_x_preferred":[
        "Bakerhill"
    ],
    "name:por_x_preferred":[
        "Bakerhill"
    ],
    "name:spa_x_preferred":[
        "Bakerhill"
    ],
    "name:srp_x_preferred":[
        "\u0411\u0435\u0458\u043a\u0435\u0440\u0445\u0438\u043b"
    ],
    "name:ukr_x_preferred":[
        "\u0411\u0435\u0439\u043a\u0435\u0440\u0433\u0456\u043b\u043b"
    ],
    "name:uzb_x_preferred":[
        "Bakerhill"
    ],
    "name:zho_x_preferred":[
        "\u8d1d\u514b\u5c71"
    ],
    "qs_pg:aaroncc":"US",
    "qs_pg:gn_country":"US",
    "qs_pg:gn_fcode":"PPL",
    "qs_pg:gn_pop":279,
    "qs_pg:name":"Baker Hill",
    "qs_pg:name_adm0":"United States",
    "qs_pg:name_adm1":"Alabama",
    "qs_pg:photos_9r":0,
    "qs_pg:photos_sr":0,
    "qs_pg:pop_sr":5,
    "qs_pg:qs_pg_placetype":"locality",
    "qs_pg:qs_pg_placetype_gp":"Town",
    "qs_pg:woe_adm0":23424977,
    "woe:adm0_id":23424977,
    "woe:name_adm0":"United States",
    "woe:name_adm1":"Alabama",
    "woe:placetype":"Town",
    "wof:name":"Baker Hill",
    "wof:placetype":"locality",
    "wof:population":279
},
  "geometry": {"coordinates":[-85.30216,31.78127],"type":"Point"}
}