{
  "type": "Feature",
  "properties": {
    "iso:country":"US",
    "name:eng_x_preferred":[
        "Melody Hill"
    ],
    "qs:gn_adm0_cc":"US",
    "qs:gn_local":5804191,
    "qs:gn_nam_loc":"Mountlake Terrace, Snohomish, Washington, US",
    "qs:gn_namadm1":"WA",
    "qs:local_max":287,
    "qs:local_sum":811,
    "qs:localhoods":4,
    "qs:name":"Melody Hill",
    "qs:name_adm0":"United States",
    "qs:name_adm1":"Washington",
    "qs:name_adm2":"Snohomish",
    "qs:name_local":"Mountlake Terrace",
    "qs:photo_max":78,
    "qs:photo_sum":203,
    "qs:placetype":"Suburb",
    "qs:quad_count":17,
    "qs:woe_adm0":23424977,
    "qs:woe_adm1":2347606,
    "qs:woe_adm2":12590470,
    "qs:woe_lau":0,
    "qs:woe_local":2456005,
    "qs:woe_ver":"7.10.0",
    "wof:name":"Melody Hill",
    "wof:placetype":"neighbourhood",
    "wof:population":3651,
    "zs:blockids":[
        530610510001018,
        530610510001028,
        530610510001007,
        530610512003005,
        530610504021011,
        530610514002018,
        530610514002029,
        530610510001009,
        530610512004006,
        530610510001015,
        530610509001000,
        530610510003002,
        530610510001019,
        530610510003001,
        530610510001016,
        530610510001012,
        530610510001004,
        530610510001006,
        530610512004008,
        530610510001029,
        530610510003007,
        530610510003005,
        530610510001023,
        530610510001003,
        530610510001002,
        530610510003006,
        530610510001005,
        530610512004000,
        530610510001000,
        530610510001022,
        530610510003004,
        530610510003003,
        530610510001013,
        530610510001008,
        530610510001001,
        530610512003002,
        530610512004005,
        530610510001027,
        530610510001017,
        530610514002028,
        530610510001011,
        530610510001010,
        530610510001014,
        530610512003001,
        530610510001020,
        530610512003000,
        530610514002017,
        530610512003003,
        530610512004007,
        530610510001021
    ],
    "zs:housing10":1543,
    "zs:pop10":3651
},
  "geometry": {"coordinates":[-122.328174,47.803522],"type":"Point"}
}