{
  "type": "Feature",
  "properties": {
    "gn:admin1_code":"TN",
    "gn:admin2_code":"53",
    "gn:asciiname":"Grizzard",
    "gn:country_code":"US",
    "gn:dem":103,
    "gn:elevation":"102.0",
    "gn:feature_class":"P",
    "gn:feature_code":"PPL",
    "gn:name":"Grizzard",
    "gn:population":0,
    "gn:timezone":"America/Chicago",
    "iso:country":"US",
    "wof:name":"Grizzard",
    "wof:placetype":"locality"
},
  "geometry": {"coordinates":[-88.98562,36.0284],"type":"Point"}
}