{
  "type": "Feature",
  "properties": {
    "iso:country":"US",
    "name:deu_x_preferred":[
        "Rockton"
    ],
    "name:pol_x_preferred":[
        "Rockton"
    ],
    "qs_pg:aaroncc":"US",
    "qs_pg:name":"Rockton",
    "qs_pg:name_adm0":"United States",
    "qs_pg:name_adm1":"Oregon",
    "qs_pg:photos":567,
    "qs_pg:photos_1k":115,
    "qs_pg:photos_9k":3,
    "qs_pg:photos_9r":5,
    "qs_pg:photos_all":567,
    "qs_pg:photos_sr":8,
    "qs_pg:pop_sr":0,
    "qs_pg:qs_pg_placetype":"locality",
    "qs_pg:qs_pg_placetype_gp":"Town",
    "qs_pg:woe_adm0":23424977,
    "woe:adm0_id":23424977,
    "woe:name_adm0":"United States",
    "woe:name_adm1":"Oregon",
    "woe:placetype":"Town",
    "wof:name":"Rockton",
    "wof:placetype":"locality"
},
  "geometry": {"coordinates":[-122.87050000000001,45.607695],"type":"Point"}
}