{
  "type": "Feature",
  "properties": {
    "gn:admin1_code":"NY",
    "gn:admin2_code":"101.0",
    "gn:admin3_code":"81457.0",
    "gn:asciiname":"Marshalls",
    "gn:country_code":"US",
    "gn:dem":374,
    "gn:elevation":"368.0",
    "gn:feature_class":"P",
    "gn:feature_code":"PPL",
    "gn:name":"Marshalls",
    "gn:population":0,
    "gn:timezone":"America/New_York",
    "iso:country":"US",
    "name:azb_x_preferred":[
        "\u0645\u0627\u0631\u0634\u0627\u0644\u0632"
    ],
    "name:fas_x_preferred":[
        "\u0645\u0627\u0631\u0634\u0627\u0644\u0632"
    ],
    "name:rus_x_preferred":[
        "Marshalls"
    ],
    "name:ukr_x_preferred":[
        "Marshalls"
    ],
    "wof:name":"Marshalls",
    "wof:placetype":"locality"
},
  "geometry": {"coordinates":[-77.34498000000001,42.41174],"type":"Point"}
}