{
  "type": "Feature",
  "properties": {
    "gn:elevation":1,
    "iso:country":"US",
    "name:eng_x_preferred":[
        "Palm Grove Colony"
    ],
    "qs:gn_adm0_cc":"US",
    "qs:gn_fcode":"PPL",
    "qs:gn_local":4173838,
    "qs:gn_nam_loc":"Spring Hill, Hernando, Florida, US",
    "qs:gn_namadm1":"FL",
    "qs:gn_name":"Palm Grove Colony",
    "qs:local_max":831,
    "qs:local_sum":1340,
    "qs:localhoods":10,
    "qs:name":"Palm Grove Colony",
    "qs:name_adm0":"United States",
    "qs:name_adm1":"Florida",
    "qs:name_adm2":"Hernando",
    "qs:name_local":"Spring Hill",
    "qs:photo_max":466,
    "qs:photo_sum":831,
    "qs:placetype":"Suburb",
    "qs:quad_count":31,
    "qs:woe_adm0":23424977,
    "qs:woe_adm1":2347568,
    "qs:woe_adm2":12587829,
    "qs:woe_lau":0,
    "qs:woe_local":2497970,
    "qs:woe_ver":"7.10.0",
    "wof:name":"Palm Grove Colony",
    "wof:placetype":"neighbourhood",
    "wof:population":90,
    "zs:blockids":[
        120530416001000,
        120530416003069,
        120530416001004
    ],
    "zs:housing10":45,
    "zs:pop10":90
},
  "geometry": {"coordinates":[-82.65322500000001,28.567383],"type":"Point"}
}