{
  "type": "Feature",
  "properties": {
    "gn:admin1_code":"LA",
    "gn:admin2_code":"25.0",
    "gn:asciiname":"Peck",
    "gn:country_code":"US",
    "gn:dem":24,
    "gn:elevation":"23.0",
    "gn:feature_class":"P",
    "gn:feature_code":"PPL",
    "gn:name":"Peck",
    "gn:population":0,
    "gn:timezone":"America/Chicago",
    "iso:country":"US",
    "name:deu_x_preferred":[
        "Peck"
    ],
    "name:epo_x_preferred":[
        "Bu\u015delo"
    ],
    "name:fas_x_preferred":[
        "\u067e\u06a9"
    ],
    "name:gla_x_preferred":[
        "Peic"
    ],
    "name:jpn_x_preferred":[
        "\u30da\u30c3\u30af"
    ],
    "name:nno_x_preferred":[
        "Peck"
    ],
    "wof:name":"Peck",
    "wof:placetype":"locality"
},
  "geometry": {"coordinates":[-91.66124000000001,31.92516],"type":"Point"}
}