{
  "type": "Feature",
  "properties": {
    "gn:admin1_code":"VA",
    "gn:admin2_code":"131.0",
    "gn:asciiname":"Beverly",
    "gn:country_code":"US",
    "gn:dem":16,
    "gn:elevation":"11.0",
    "gn:feature_class":"P",
    "gn:feature_code":"PPL",
    "gn:name":"Beverly",
    "gn:population":0,
    "gn:timezone":"America/New_York",
    "iso:country":"US",
    "wof:name":"Beverly",
    "wof:placetype":"locality"
},
  "geometry": {"coordinates":[-75.93326,37.30292],"type":"Point"}
}