{
  "type": "Feature",
  "properties": {
    "gn:admin1_code":"AL",
    "gn:admin2_code":"97.0",
    "gn:asciiname":"Plantation Trailer Park",
    "gn:country_code":"US",
    "gn:dem":31,
    "gn:elevation":"28.0",
    "gn:feature_class":"P",
    "gn:feature_code":"PPL",
    "gn:name":"Plantation Trailer Park",
    "gn:population":0,
    "gn:timezone":"America/Chicago",
    "iso:country":"US",
    "wof:name":"Plantation Trailer Park",
    "wof:placetype":"campus"
},
  "geometry": {"coordinates":[-88.18034,30.57856],"type":"Point"}
}