{
  "type": "Feature",
  "properties": {
    "iso:country":"US",
    "name:eng_x_preferred":[
        "Chicago Avenue"
    ],
    "wd:wordcount":325,
    "wof:name":"Chicago Avenue",
    "wof:placetype":"neighbourhood",
    "wof:population":200,
    "zs:area_m":51240.637126,
    "zs:blockids":[
        120570060006007,
        120570060006002
    ],
    "zs:housing10":124,
    "zs:label":"Chicago Avenue",
    "zs:pop10":200
},
  "geometry": {"coordinates":[-82.488787,27.926982],"type":"Point"}
}