{
  "type": "Feature",
  "properties": {
    "gn:admin1_code":"SC",
    "gn:admin2_code":"47.0",
    "gn:asciiname":"Country Homes",
    "gn:country_code":"US",
    "gn:dem":160,
    "gn:elevation":"159.0",
    "gn:feature_class":"P",
    "gn:feature_code":"PPL",
    "gn:name":"Country Homes",
    "gn:population":0,
    "gn:timezone":"America/New_York",
    "iso:country":"US",
    "wof:name":"Country Homes",
    "wof:placetype":"locality"
},
  "geometry": {"coordinates":[-82.09345,34.21262],"type":"Point"}
}