{
  "type": "Feature",
  "properties": {
    "gn:admin1_code":"VA",
    "gn:admin2_code":"1",
    "gn:asciiname":"Chesconessex",
    "gn:country_code":"US",
    "gn:dem":7,
    "gn:elevation":"1.0",
    "gn:feature_class":"P",
    "gn:feature_code":"PPL",
    "gn:name":"Chesconessex",
    "gn:population":0,
    "gn:timezone":"America/New_York",
    "iso:country":"US",
    "name:eng_x_preferred":[
        "Chesconessex"
    ],
    "name:und_x_variant":[
        "Chesconnessex"
    ],
    "wof:name":"Chesconessex",
    "wof:placetype":"locality"
},
  "geometry": {"coordinates":[-75.76631999999999,37.75207],"type":"Point"}
}