{
  "type": "Feature",
  "properties": {
    "gn:admin1_code":"WV",
    "gn:admin2_code":"33.0",
    "gn:asciiname":"O'Neill",
    "gn:country_code":"US",
    "gn:dem":316,
    "gn:elevation":"310.0",
    "gn:feature_class":"P",
    "gn:feature_code":"PPL",
    "gn:name":"O'Neill",
    "gn:population":0,
    "gn:timezone":"America/New_York",
    "iso:country":"US",
    "wof:name":"O'Neill",
    "wof:placetype":"locality"
},
  "geometry": {"coordinates":[-80.41119999999999,39.29314],"type":"Point"}
}