{
  "type": "Feature",
  "properties": {
    "gn:admin1_code":"MN",
    "gn:admin2_code":"17.0",
    "gn:admin3_code":"3628.0",
    "gn:asciiname":"Barnum Mobile Home Park",
    "gn:country_code":"US",
    "gn:dem":340,
    "gn:elevation":"338.0",
    "gn:feature_class":"P",
    "gn:feature_code":"PPL",
    "gn:name":"Barnum Mobile Home Park",
    "gn:population":0,
    "gn:timezone":"America/Chicago",
    "iso:country":"US",
    "wof:name":"Barnum Mobile Home Park",
    "wof:placetype":"campus"
},
  "geometry": {"coordinates":[-92.68832999999999,46.50306],"type":"Point"}
}