{
  "type": "Feature",
  "properties": {
    "gn:admin1_code":"MD",
    "gn:admin2_code":"17.0",
    "gn:asciiname":"Arborview",
    "gn:country_code":"US",
    "gn:dem":57,
    "gn:elevation":"52.0",
    "gn:feature_class":"P",
    "gn:feature_code":"PPL",
    "gn:name":"Arborview",
    "gn:population":0,
    "gn:timezone":"America/New_York",
    "iso:country":"US",
    "wof:name":"Arborview",
    "wof:placetype":"locality"
},
  "geometry": {"coordinates":[-76.78246999999998,38.49734],"type":"Point"}
}