{
  "type": "Feature",
  "properties": {
    "gn:admin1_code":"GA",
    "gn:admin2_code":"63",
    "gn:asciiname":"Stoneridge",
    "gn:country_code":"US",
    "gn:dem":289,
    "gn:elevation":"281.0",
    "gn:feature_class":"P",
    "gn:feature_code":"PPL",
    "gn:name":"Stoneridge",
    "gn:population":0,
    "gn:timezone":"America/New_York",
    "iso:country":"US",
    "wof:name":"Stoneridge",
    "wof:placetype":"locality"
},
  "geometry": {"coordinates":[-84.42187,33.55428],"type":"Point"}
}