{
  "type": "Feature",
  "properties": {
    "gn:admin1_code":"OH",
    "gn:admin2_code":"69.0",
    "gn:admin3_code":"66502.0",
    "gn:asciiname":"Grelton",
    "gn:country_code":"US",
    "gn:dem":207,
    "gn:elevation":"207.0",
    "gn:feature_class":"P",
    "gn:feature_code":"PPL",
    "gn:name":"Grelton",
    "gn:population":0,
    "gn:timezone":"America/New_York",
    "iso:country":"US",
    "name:eng_x_preferred":[
        "Grelton"
    ],
    "name:und_x_variant":[
        "Gratton",
        "Grellton"
    ],
    "name:vol_x_preferred":[
        "Grelton"
    ],
    "wof:name":"Grelton",
    "wof:placetype":"locality"
},
  "geometry": {"coordinates":[-83.99966999999999,41.34172],"type":"Point"}
}