{
  "type": "Feature",
  "properties": {
    "gn:admin1_code":"OR",
    "gn:admin2_code":"7",
    "gn:asciiname":"Hamlet",
    "gn:country_code":"US",
    "gn:dem":172,
    "gn:elevation":"164.0",
    "gn:feature_class":"P",
    "gn:feature_code":"PPL",
    "gn:name":"Hamlet",
    "gn:population":0,
    "gn:timezone":"America/Los_Angeles",
    "iso:country":"US",
    "name:hat_x_preferred":[
        "Hamlet"
    ],
    "wof:name":"Hamlet",
    "wof:placetype":"locality"
},
  "geometry": {"coordinates":[-123.70068000000001,45.84622],"type":"Point"}
}