{
  "type": "Feature",
  "properties": {
    "gn:admin1_code":"CO",
    "gn:admin2_code":"37.0",
    "gn:asciiname":"Burns",
    "gn:country_code":"US",
    "gn:dem":1984,
    "gn:elevation":"1980.0",
    "gn:feature_class":"P",
    "gn:feature_code":"PPL",
    "gn:name":"Burns",
    "gn:population":0,
    "gn:timezone":"America/Denver",
    "iso:country":"US",
    "name:azb_x_preferred":[
        "\u0628\u0631\u0646\u0632"
    ],
    "name:fas_x_preferred":[
        "\u0628\u0631\u0646\u0632"
    ],
    "name:vol_x_preferred":[
        "Burns"
    ],
    "name:zho_x_preferred":[
        "\u4f2f\u6069\u65af"
    ],
    "wof:name":"Burns",
    "wof:placetype":"locality"
},
  "geometry": {"coordinates":[-106.8856,39.87388],"type":"Point"}
}