{
  "type": "Feature",
  "properties": {
    "gn:admin1_code":"WV",
    "gn:admin2_code":"19.0",
    "gn:asciiname":"Wyndal",
    "gn:country_code":"US",
    "gn:dem":213,
    "gn:elevation":"211.0",
    "gn:feature_class":"P",
    "gn:feature_code":"PPL",
    "gn:name":"Wyndal",
    "gn:population":0,
    "gn:timezone":"America/New_York",
    "iso:country":"US",
    "wof:name":"Wyndal",
    "wof:placetype":"locality"
},
  "geometry": {"coordinates":[-81.18205,38.21455],"type":"Point"}
}