{
  "type": "Feature",
  "properties": {
    "iso:country":"US",
    "name:eng_x_preferred":[
        "Alta Vista Neighborhood Association"
    ],
    "wof:name":"Alta Vista Neighborhood Association",
    "wof:placetype":"neighbourhood",
    "wof:population":3230,
    "zs:area_m":7411175.698284,
    "zs:blockids":[
        80690013082039,
        80690013071139,
        80690013071042,
        80690013071140,
        80690013082038,
        80690013071015,
        80690013083023,
        80690013082072,
        80690013051006,
        80690013051007,
        80690013082070,
        80690013082020,
        80690013082089,
        80690013082015,
        80690013071069,
        80690013071045,
        80690013071012,
        80690013082014,
        80690013082068,
        80690013051008,
        80690013071025,
        80690013071023,
        80690013082086,
        80690013051017,
        80690013071027,
        80690013082081,
        80690013082090,
        80690013071048,
        80690013051014,
        80690013071039,
        80690013082017,
        80690013083012,
        80690013071049,
        80690013082023,
        80690013082073,
        80690013082021,
        80690013071043,
        80690013071040,
        80690013071046,
        80690013082016,
        80690013071144,
        80690013082069,
        80690013051012,
        80690013082026,
        80690013051002,
        80690013082088,
        80690013082084,
        80690013071044,
        80690013071014,
        80690013082071,
        80690013071070,
        80690013082091,
        80690013082082,
        80690013051010,
        80690013051001,
        80690013082060,
        80690013071137,
        80690013071010,
        80690013082025,
        80690013082027,
        80690013071038,
        80690013051013,
        80690013082085,
        80690013071031,
        80690013082078,
        80690013082019,
        80690013082079,
        80690013082087,
        80690013082065,
        80690013071033,
        80690013082083,
        80690013051003,
        80690013051009,
        80690013051016,
        80690013083000,
        80690013071013,
        80690013071138,
        80690013071034,
        80690013071024,
        80690013082067,
        80690013051011,
        80690013082024,
        80690013071035,
        80690013071041,
        80690013082080,
        80690013083022,
        80690013071141,
        80690013082018,
        80690013082066,
        80690013071047,
        80690013071032,
        80690013051015,
        80690013082029,
        80690013051000,
        80690013071026,
        80690013082028
    ],
    "zs:housing10":1261,
    "zs:label":"Alta Vista Neighborhood Association",
    "zs:pop10":3230
},
  "geometry": {"coordinates":[-105.04586500000001,40.62463],"type":"Point"}
}