{
  "type": "Feature",
  "properties": {
    "gn:admin1_code":"MT",
    "gn:admin2_code":"19.0",
    "gn:asciiname":"Brenna Trailer Court",
    "gn:country_code":"US",
    "gn:dem":762,
    "gn:elevation":"763.0",
    "gn:feature_class":"P",
    "gn:feature_code":"PPL",
    "gn:name":"Brenna Trailer Court",
    "gn:population":0,
    "gn:timezone":"America/Denver",
    "iso:country":"US",
    "wof:name":"Brenna Trailer Court",
    "wof:placetype":"locality"
},
  "geometry": {"coordinates":[-105.41555,48.78947],"type":"Point"}
}