{
  "type": "Feature",
  "properties": {
    "gn:admin1_code":"SC",
    "gn:admin2_code":"3.0",
    "gn:asciiname":"Spiderweb",
    "gn:country_code":"US",
    "gn:dem":108,
    "gn:elevation":"107.0",
    "gn:feature_class":"P",
    "gn:feature_code":"PPL",
    "gn:name":"Spiderweb",
    "gn:population":0,
    "gn:timezone":"America/New_York",
    "iso:country":"US",
    "wof:name":"Spiderweb",
    "wof:placetype":"locality"
},
  "geometry": {"coordinates":[-81.83122,33.41014000000001],"type":"Point"}
}