{
  "type": "Feature",
  "properties": {
    "iso:country":"US",
    "name:eng_x_preferred":[
        "Stafford Market Place"
    ],
    "qs:gn_adm0_cc":"US",
    "qs:gn_local":4787247,
    "qs:gn_nam_loc":"Stafford, Stafford, Virginia, US",
    "qs:gn_namadm1":"VA",
    "qs:local_max":242,
    "qs:local_sum":511,
    "qs:localhoods":7,
    "qs:name":"Stafford Market Place",
    "qs:name_adm0":"United States",
    "qs:name_adm1":"Virginia",
    "qs:name_adm2":"Stafford",
    "qs:name_local":"Stafford",
    "qs:photo_max":8,
    "qs:photo_sum":19,
    "qs:placetype":"Suburb",
    "qs:quad_count":6,
    "qs:woe_adm0":23424977,
    "qs:woe_adm1":2347605,
    "qs:woe_adm2":12590424,
    "qs:woe_lau":0,
    "qs:woe_local":2498747,
    "qs:woe_ver":"7.10.0",
    "qs_pg:name":"Stafford Market Place",
    "qs_pg:name_adm0":"United States",
    "qs_pg:name_adm1":"Virginia",
    "qs_pg:photos":19,
    "qs_pg:photos_1k":4,
    "qs_pg:photos_9k":1,
    "qs_pg:photos_9r":1,
    "qs_pg:photos_all":19,
    "qs_pg:photos_sr":1,
    "qs_pg:pop_sr":0,
    "qs_pg:qs_pg_placetype":"neighbourhood",
    "qs_pg:qs_pg_placetype_gp":"Suburb",
    "qs_pg:woe_adm0":23424977,
    "woe:adm0_id":23424977,
    "woe:name_adm0":"United States",
    "woe:name_adm1":"Virginia",
    "woe:placetype":"Suburb",
    "wof:lang":[
        "eng"
    ],
    "wof:name":"Stafford Market Place",
    "wof:placetype":"neighbourhood",
    "wof:population":4047,
    "zs:blockids":[
        511790102072049,
        511790102111000,
        511790102072015,
        511790102072029,
        511790102072013,
        511790102072028,
        511790102072018,
        511790102111002,
        511790102072026,
        511790102072020,
        511790102072041,
        511790102111011,
        511790102072025,
        511790102072016,
        511790102072017,
        511790102072027,
        511790102111010,
        511790102072038,
        511790102072007,
        511790102072010,
        511790102072051,
        511790102072023,
        511790102072052,
        511790102072050,
        511790102072019,
        511790102072039,
        511790102072024,
        511790102072040,
        511790102072048,
        511790102072011,
        511790102072009,
        511790102072012,
        511790102072008,
        511790102111001,
        511790102111003,
        511790102072021,
        511790102072014,
        511790102072046,
        511790102072047,
        511790102072022
    ],
    "zs:housing10":1540,
    "zs:pop10":4047
},
  "geometry": {"coordinates":[-77.405477,38.468868],"type":"Point"}
}