{
  "type": "Feature",
  "properties": {
    "gn:admin1_code":"CA",
    "gn:admin2_code":"41",
    "gn:asciiname":"Harbor Point",
    "gn:country_code":"US",
    "gn:dem":36,
    "gn:elevation":"40.0",
    "gn:feature_class":"P",
    "gn:feature_code":"PPL",
    "gn:name":"Harbor Point",
    "gn:population":0,
    "gn:timezone":"America/Los_Angeles",
    "iso:country":"US",
    "name:zho_x_preferred":[
        "\u6e2f\u53e3\u9ede"
    ],
    "wof:name":"Harbor Point",
    "wof:placetype":"locality"
},
  "geometry": {"coordinates":[-122.50081000000002,37.88187],"type":"Point"}
}