{
  "type": "Feature",
  "properties": {
    "gn:country":"US",
    "gn:fcode":"PPL",
    "gn:population":0,
    "iso:country":"US",
    "name:azb_x_preferred":[
        "\u062c\u0648\u0646\u0632 \u0645\u06cc\u0644"
    ],
    "name:eng_x_preferred":[
        "Jones Mills"
    ],
    "name:eng_x_variant":[
        "Jones Mill"
    ],
    "name:fas_x_preferred":[
        "\u062c\u0648\u0646\u0632 \u0645\u06cc\u0644"
    ],
    "name:fra_x_preferred":[
        "Jones Mill"
    ],
    "name:lld_x_preferred":[
        "Jones Mill"
    ],
    "name:zho_x_preferred":[
        "\u74ca\u65af\u7c73\u723e"
    ],
    "qs_pg:aaroncc":"US",
    "qs_pg:gn_country":"US",
    "qs_pg:gn_fcode":"PPL",
    "qs_pg:gn_pop":0,
    "qs_pg:name":"Jones Mill",
    "qs_pg:name_adm0":"United States",
    "qs_pg:name_adm1":"Arkansas",
    "qs_pg:photos":154,
    "qs_pg:photos_1k":31,
    "qs_pg:photos_9k":1,
    "qs_pg:photos_9r":4,
    "qs_pg:photos_all":154,
    "qs_pg:photos_sr":4,
    "qs_pg:pop_sr":0,
    "qs_pg:qs_pg_placetype":"locality",
    "qs_pg:qs_pg_placetype_gp":"Town",
    "qs_pg:woe_adm0":23424977,
    "woe:adm0_id":23424977,
    "woe:name_adm0":"United States",
    "woe:name_adm1":"Arkansas",
    "woe:placetype":"Town",
    "wof:name":"Jones Mill",
    "wof:placetype":"locality",
    "wof:population":90
},
  "geometry": {"coordinates":[-92.88767,34.43759],"type":"Point"}
}