{
  "type": "Feature",
  "properties": {
    "gn:admin1_code":"IN",
    "gn:admin2_code":"129.0",
    "gn:admin3_code":"60858.0",
    "gn:asciiname":"Hovey",
    "gn:country_code":"US",
    "gn:dem":113,
    "gn:elevation":"113.0",
    "gn:feature_class":"P",
    "gn:feature_code":"PPL",
    "gn:name":"Hovey",
    "gn:population":0,
    "gn:timezone":"America/Chicago",
    "iso:country":"US",
    "wof:name":"Hovey",
    "wof:placetype":"locality"
},
  "geometry": {"coordinates":[-87.94197,37.89227],"type":"Point"}
}