{
  "type": "Feature",
  "properties": {
    "gn:country":"US",
    "gn:fcode":"PPL",
    "gn:population":53,
    "iso:country":"US",
    "qs_pg:aaroncc":"US",
    "qs_pg:gn_country":"US",
    "qs_pg:gn_fcode":"PPL",
    "qs_pg:gn_pop":53,
    "qs_pg:name":"Amistad Acres",
    "qs_pg:name_adm0":"United States",
    "qs_pg:name_adm1":"Texas",
    "qs_pg:photos_9k":1,
    "qs_pg:photos_9r":1,
    "qs_pg:photos_all":10,
    "qs_pg:photos_sr":0,
    "qs_pg:pop_sr":1,
    "qs_pg:qs_pg_placetype":"locality",
    "qs_pg:qs_pg_placetype_gp":"Town",
    "qs_pg:woe_adm0":23424977,
    "woe:adm0_id":23424977,
    "woe:name_adm0":"United States",
    "woe:name_adm1":"Texas",
    "woe:placetype":"Town",
    "wof:name":"Amistad Acres",
    "wof:placetype":"locality",
    "wof:population":53
},
  "geometry": {"coordinates":[-101.16732,29.51522],"type":"Point"}
}