{
  "type": "Feature",
  "properties": {
    "gn:admin1_code":"TN",
    "gn:admin2_code":"81.0",
    "gn:asciiname":"Buffalo",
    "gn:country_code":"US",
    "gn:dem":264,
    "gn:elevation":"264.0",
    "gn:feature_class":"P",
    "gn:feature_code":"PPL",
    "gn:name":"Buffalo",
    "gn:population":0,
    "gn:timezone":"America/Chicago",
    "iso:country":"US",
    "name:ara_x_preferred":[
        "\u0628\u0648\u0641\u0627\u0644\u0648"
    ],
    "name:bre_x_preferred":[
        "Buffalo"
    ],
    "name:bul_x_preferred":[
        "\u0411\u044a\u0444\u0430\u043b\u043e"
    ],
    "name:cat_x_preferred":[
        "Buffalo"
    ],
    "name:ceb_x_preferred":[
        "Buffalo"
    ],
    "name:ces_x_preferred":[
        "Buffalo"
    ],
    "name:cym_x_preferred":[
        "Buffalo"
    ],
    "name:dan_x_preferred":[
        "Buffalo"
    ],
    "name:deu_x_preferred":[
        "Buffalo"
    ],
    "name:eng_x_preferred":[
        "Buffalo"
    ],
    "name:eus_x_preferred":[
        "Buffalo"
    ],
    "name:fas_x_preferred":[
        "\u0628\u0648\u0641\u0627\u0644\u0648"
    ],
    "name:fin_x_preferred":[
        "Buffalo"
    ],
    "name:fra_x_preferred":[
        "Buffalo"
    ],
    "name:glg_x_preferred":[
        "Buffalo"
    ],
    "name:heb_x_preferred":[
        "\u05d1\u05d0\u05e4\u05dc\u05d5"
    ],
    "name:hrv_x_preferred":[
        "Buffalo"
    ],
    "name:hun_x_preferred":[
        "Buffalo"
    ],
    "name:ita_x_preferred":[
        "Buffalo"
    ],
    "name:jpn_x_preferred":[
        "\u30d0\u30c3\u30d5\u30a1\u30ed\u30fc"
    ],
    "name:kor_x_preferred":[
        "\ubc84\ud384\ub85c"
    ],
    "name:nld_x_preferred":[
        "Buffalo"
    ],
    "name:pol_x_preferred":[
        "Baw\u00f3\u0142"
    ],
    "name:por_x_preferred":[
        "Buffalo"
    ],
    "name:ron_x_preferred":[
        "Buffalo"
    ],
    "name:rus_x_preferred":[
        "\u0411\u0443\u0444\u0444\u0430\u043b\u043e"
    ],
    "name:sco_x_preferred":[
        "Buffalo"
    ],
    "name:slk_x_preferred":[
        "Buffalo"
    ],
    "name:spa_x_preferred":[
        "Buffalo"
    ],
    "name:srp_x_preferred":[
        "\u0411\u0443\u0444\u0430\u043b\u043e"
    ],
    "name:swe_x_preferred":[
        "Buffalo"
    ],
    "name:tam_x_preferred":[
        "\u0b8e\u0bb0\u0bc1\u0bae\u0bc8"
    ],
    "name:tgl_x_preferred":[
        "Bupalo"
    ],
    "name:tur_x_preferred":[
        "Buffalo"
    ],
    "name:ukr_x_preferred":[
        "\u0411\u0430\u0444\u0444\u0430\u043b\u043e"
    ],
    "name:und_x_variant":[
        "Buffalo Switch"
    ],
    "name:urd_x_preferred":[
        "\u0628\u0641\u06cc\u0644\u0648"
    ],
    "name:vie_x_preferred":[
        "Tr\u00e2u"
    ],
    "name:vol_x_preferred":[
        "Buffalo"
    ],
    "name:war_x_preferred":[
        "Buffalo"
    ],
    "name:zho_x_preferred":[
        "\u5e03\u6cd5\u7f57"
    ],
    "wof:name":"Buffalo",
    "wof:placetype":"locality"
},
  "geometry": {"coordinates":[-87.48806999999999,35.68757],"type":"Point"}
}