{
  "type": "Feature",
  "properties": {
    "gn:admin1_code":"CT",
    "gn:admin2_code":"1.0",
    "gn:admin3_code":"73070.0",
    "gn:asciiname":"High Ridge",
    "gn:country_code":"US",
    "gn:dem":147,
    "gn:elevation":"136.0",
    "gn:feature_class":"P",
    "gn:feature_code":"PPL",
    "gn:name":"High Ridge",
    "gn:population":0,
    "gn:timezone":"America/New_York",
    "iso:country":"US",
    "name:eng_x_preferred":[
        "High Ridge"
    ],
    "name:und_x_variant":[
        "High Ridge Village",
        "High Ridges"
    ],
    "wof:name":"High Ridge",
    "wof:placetype":"locality"
},
  "geometry": {"coordinates":[-73.56374,41.16898],"type":"Point"}
}