{
  "type": "Feature",
  "properties": {
    "gn:admin1_code":"TN",
    "gn:admin2_code":"125",
    "gn:asciiname":"Excell",
    "gn:country_code":"US",
    "gn:dem":181,
    "gn:elevation":"179.0",
    "gn:feature_class":"P",
    "gn:feature_code":"PPL",
    "gn:name":"Excell",
    "gn:population":0,
    "gn:timezone":"America/Chicago",
    "iso:country":"US",
    "name:eng_x_preferred":[
        "Excell"
    ],
    "name:und_x_variant":[
        "Exel"
    ],
    "wof:name":"Excell",
    "wof:placetype":"locality"
},
  "geometry": {"coordinates":[-87.26000999999999,36.48616],"type":"Point"}
}