{
  "type": "Feature",
  "properties": {
    "gn:admin1_code":"AL",
    "gn:admin2_code":"41",
    "gn:asciiname":"Carmen",
    "gn:country_code":"US",
    "gn:dem":94,
    "gn:elevation":"92.0",
    "gn:feature_class":"P",
    "gn:feature_code":"PPL",
    "gn:name":"Carmen",
    "gn:population":0,
    "gn:timezone":"America/Chicago",
    "iso:country":"US",
    "name:afr_x_preferred":[
        "Carmen"
    ],
    "name:ara_x_preferred":[
        "\u0643\u0627\u0631\u0645\u0646"
    ],
    "name:aze_x_preferred":[
        "Karmen"
    ],
    "name:bak_x_preferred":[
        "\u041a\u0430\u0440\u043c\u0435\u043d"
    ],
    "name:bel_x_preferred":[
        "\u041a\u0430\u0440\u043c\u044d\u043d"
    ],
    "name:bul_x_preferred":[
        "\u041a\u0430\u0440\u043c\u0435\u043d"
    ],
    "name:cat_x_preferred":[
        "Carmen"
    ],
    "name:ces_x_preferred":[
        "Carmen"
    ],
    "name:cym_x_preferred":[
        "Carmen"
    ],
    "name:dan_x_preferred":[
        "Carmen"
    ],
    "name:deu_x_preferred":[
        "Carmen"
    ],
    "name:ell_x_preferred":[
        "\u039a\u03ac\u03c1\u03bc\u03b5\u03bd"
    ],
    "name:epo_x_preferred":[
        "Carmen"
    ],
    "name:est_x_preferred":[
        "Carmen"
    ],
    "name:eus_x_preferred":[
        "Carmen"
    ],
    "name:fas_x_preferred":[
        "\u06a9\u0627\u0631\u0645\u0646"
    ],
    "name:fin_x_preferred":[
        "Carmen"
    ],
    "name:fra_x_preferred":[
        "Carmen"
    ],
    "name:glg_x_preferred":[
        "Carmen"
    ],
    "name:heb_x_preferred":[
        "\u05db\u05e8\u05de\u05df"
    ],
    "name:hrv_x_preferred":[
        "Carmen"
    ],
    "name:hun_x_preferred":[
        "Carmen"
    ],
    "name:hye_x_preferred":[
        "\u053f\u0561\u0580\u0574\u0565\u0576"
    ],
    "name:ita_x_preferred":[
        "Carmen"
    ],
    "name:jpn_x_preferred":[
        "\u30ab\u30eb\u30e1\u30f3"
    ],
    "name:kab_x_preferred":[
        "Karmen"
    ],
    "name:kat_x_preferred":[
        "\u10d9\u10d0\u10e0\u10db\u10d4\u10dc\u10d8"
    ],
    "name:kor_x_preferred":[
        "\uce74\ub974\uba58"
    ],
    "name:lav_x_preferred":[
        "Karmena"
    ],
    "name:mal_x_preferred":[
        "\u0d15\u0d3e\u0d7c\u0d2e\u0d46\u0d7b"
    ],
    "name:msa_x_preferred":[
        "Carmen"
    ],
    "name:nld_x_preferred":[
        "Carmen"
    ],
    "name:nno_x_preferred":[
        "Carmen"
    ],
    "name:nor_x_preferred":[
        "Carmen"
    ],
    "name:pol_x_preferred":[
        "Carmen"
    ],
    "name:por_x_preferred":[
        "Carmen"
    ],
    "name:que_x_preferred":[
        "Carmen"
    ],
    "name:ron_x_preferred":[
        "Carmen"
    ],
    "name:rus_x_preferred":[
        "\u041a\u0430\u0440\u043c\u0435\u043d"
    ],
    "name:sco_x_preferred":[
        "Carmen"
    ],
    "name:slk_x_preferred":[
        "Carmen"
    ],
    "name:slv_x_preferred":[
        "Carmen"
    ],
    "name:spa_x_preferred":[
        "Carmen"
    ],
    "name:srp_x_preferred":[
        "\u041a\u0430\u0440\u043c\u0435\u043d"
    ],
    "name:swe_x_preferred":[
        "Carmen"
    ],
    "name:tam_x_preferred":[
        "\u0b95\u0bbe\u0bb0\u0bcd\u0bae\u0bc6\u0ba9\u0bcd"
    ],
    "name:tat_x_preferred":[
        "Karmen"
    ],
    "name:tha_x_preferred":[
        "\u0e01\u0e32\u0e23\u0e4c\u0e40\u0e21\u0e19"
    ],
    "name:tur_x_preferred":[
        "Carmen"
    ],
    "name:ukr_x_preferred":[
        "\u041a\u0430\u0440\u043c\u0435\u043d"
    ],
    "name:vie_x_preferred":[
        "Carmen"
    ],
    "wof:name":"Carmen",
    "wof:placetype":"locality"
},
  "geometry": {"coordinates":[-86.18911999999997,31.63238],"type":"Point"}
}