{
  "type": "Feature",
  "properties": {
    "gn:gn_country":"US",
    "gn:gn_fcode":"PPL",
    "gn:gn_pop":0,
    "iso:country":"US",
    "name:azb_x_preferred":[
        "\u062f\u0627\u0632"
    ],
    "name:eng_x_preferred":[
        "Dawes"
    ],
    "name:fas_x_preferred":[
        "\u062f\u0627\u0632"
    ],
    "name:fra_x_preferred":[
        "Dawes"
    ],
    "name:mlg_x_preferred":[
        "Dawes"
    ],
    "qs_pg:aaroncc":"US",
    "qs_pg:gn_country":"US",
    "qs_pg:gn_fcode":"PPL",
    "qs_pg:gn_pop":0,
    "qs_pg:name":"Dawes",
    "qs_pg:name_adm0":"United States",
    "qs_pg:name_adm1":"West Virginia",
    "qs_pg:photos_9r":0,
    "qs_pg:photos_sr":0,
    "qs_pg:pop_sr":0,
    "qs_pg:qs_pg_placetype":"locality",
    "qs_pg:qs_pg_placetype_gp":"Town",
    "qs_pg:woe_adm0":23424977,
    "woe:adm0_id":23424977,
    "woe:name_adm0":"United States",
    "woe:name_adm1":"West Virginia",
    "woe:placetype":"Town",
    "wof:name":"Dawes",
    "wof:placetype":"locality"
},
  "geometry": {"coordinates":[-81.45206,38.14288],"type":"Point"}
}