{
  "type": "Feature",
  "properties": {
    "gn:admin1_code":"KS",
    "gn:admin2_code":"169.0",
    "gn:admin3_code":"40350.0",
    "gn:asciiname":"Hallville",
    "gn:country_code":"US",
    "gn:dem":429,
    "gn:elevation":"428.0",
    "gn:feature_class":"P",
    "gn:feature_code":"PPL",
    "gn:name":"Hallville",
    "gn:population":0,
    "gn:timezone":"America/Chicago",
    "iso:country":"US",
    "name:eng_x_preferred":[
        "Hallville"
    ],
    "name:und_x_variant":[
        "Laura"
    ],
    "wof:name":"Hallville",
    "wof:placetype":"locality"
},
  "geometry": {"coordinates":[-97.53809,38.64862],"type":"Point"}
}