{
  "type": "Feature",
  "properties": {
    "gn:admin1_code":"OH",
    "gn:admin2_code":"143.0",
    "gn:admin3_code":"28826.0",
    "gn:asciiname":"Riviera Mobile Manor",
    "gn:country_code":"US",
    "gn:dem":183,
    "gn:elevation":"186.0",
    "gn:feature_class":"P",
    "gn:feature_code":"PPL",
    "gn:name":"Riviera Mobile Manor",
    "gn:population":0,
    "gn:timezone":"America/New_York",
    "iso:country":"US",
    "wof:name":"Riviera Mobile Manor",
    "wof:placetype":"locality"
},
  "geometry": {"coordinates":[-83.10972,41.38139],"type":"Point"}
}