{
  "type": "Feature",
  "properties": {
    "gn:admin1_code":"NY",
    "gn:admin2_code":"3.0",
    "gn:admin3_code":"1451.0",
    "gn:asciiname":"Bishopville",
    "gn:country_code":"US",
    "gn:dem":426,
    "gn:elevation":"422.0",
    "gn:feature_class":"P",
    "gn:feature_code":"PPL",
    "gn:name":"Bishopville",
    "gn:population":0,
    "gn:timezone":"America/New_York",
    "iso:country":"US",
    "wof:name":"Bishopville",
    "wof:placetype":"locality"
},
  "geometry": {"coordinates":[-77.74722,42.36868],"type":"Point"}
}