{
  "type": "Feature",
  "properties": {
    "gn:elevation":349,
    "iso:country":"US",
    "name:bar_x_preferred":[
        "Lakeside"
    ],
    "name:ceb_x_preferred":[
        "Lakeside"
    ],
    "name:deu_x_preferred":[
        "Lakeside"
    ],
    "name:eng_x_preferred":[
        "Lakeside"
    ],
    "name:fra_x_preferred":[
        "Lakeside"
    ],
    "name:hun_x_preferred":[
        "Lakeside"
    ],
    "name:ita_x_preferred":[
        "Lakeside"
    ],
    "name:nld_x_preferred":[
        "Lakeside"
    ],
    "name:pol_x_preferred":[
        "Lakeside"
    ],
    "name:por_x_preferred":[
        "Lakeside"
    ],
    "name:rus_x_preferred":[
        "\u041b\u0435\u0439\u043a\u0441\u0430\u0439\u0434"
    ],
    "name:slk_x_preferred":[
        "Lakeside"
    ],
    "name:spa_x_preferred":[
        "Lakeside"
    ],
    "name:srp_x_preferred":[
        "\u041b\u0435\u0458\u043a\u0441\u0430\u0458\u0434"
    ],
    "name:ukr_x_preferred":[
        "\u041b\u0435\u0439\u043a\u0441\u0430\u0439\u0434"
    ],
    "name:vol_x_preferred":[
        "Lakeside"
    ],
    "qs:gn_adm0_cc":"US",
    "qs:gn_fcode":"PPL",
    "qs:gn_local":5236670,
    "qs:gn_nam_loc":"groton",
    "qs:gn_namadm1":"VT",
    "qs:gn_name":"Lakeside",
    "qs:local_max":27,
    "qs:local_sum":43,
    "qs:localhoods":2,
    "qs:name":"Lakeside",
    "qs:name_adm0":"United States",
    "qs:name_adm1":"Vermont",
    "qs:name_adm2":"Caledonia",
    "qs:name_local":"Groton",
    "qs:photo_max":9,
    "qs:photo_sum":27,
    "qs:placetype":"Suburb",
    "qs:quad_count":10,
    "qs:woe_adm0":23424977,
    "qs:woe_adm1":2347604,
    "qs:woe_adm2":12590292,
    "qs:woe_lau":0,
    "qs:woe_local":2415221,
    "qs:woe_ver":"7.10.0",
    "wof:lang":[
        "eng"
    ],
    "wof:name":"Lakeside",
    "wof:placetype":"neighbourhood",
    "wof:population":47,
    "zs:blockids":[
        500059578002066,
        500059578002046,
        500059578002033,
        500059578002176,
        500059578002171,
        500059578002050,
        500059578002077,
        500059578002027,
        500059578002031,
        500059578002006,
        500059578002035,
        500059578002038,
        500059578002076,
        500059578002175,
        500059578002036,
        500059578002067,
        500059578002069,
        500059578002032,
        500059578002037,
        500059578002173,
        500059578002026,
        500059578002023,
        500059578002020,
        500059578002004,
        500059578002021,
        500059578002025,
        500059578002012,
        500059578002029,
        500059578002068,
        500059578002007,
        500059578002051,
        500059578002022,
        500059578002030,
        500059578002048,
        500059578002014,
        500059578002024,
        500059578002028,
        500059578002172,
        500059578002174,
        500059578002042,
        500059578002034
    ],
    "zs:housing10":118,
    "zs:pop10":47
},
  "geometry": {"coordinates":[-72.262676,44.26028],"type":"Point"}
}