{
  "type": "Feature",
  "properties": {
    "iso:country":"US",
    "name:eng_x_preferred":[
        "Willard Addition"
    ],
    "wof:name":"Willard Addition",
    "wof:placetype":"neighbourhood",
    "wof:population":894,
    "zs:area_m":677135.302229,
    "zs:blockids":[
        470090106002019,
        470090106002026,
        470090106003009,
        470090106002024,
        470090106003017,
        470090106003010,
        470090106003015,
        470090106003014,
        470090105002021,
        470090106003012,
        470090105002022,
        470090106003013,
        470090106002021,
        470090106003018,
        470090106002023,
        470090106002022,
        470090106002007,
        470090105002042,
        470090106002020,
        470090106003011,
        470090105002023,
        470090106003016
    ],
    "zs:housing10":415,
    "zs:label":"Willard Addition",
    "zs:pop10":894
},
  "geometry": {"coordinates":[-83.981825,35.744137],"type":"Point"}
}