{
  "type": "Feature",
  "properties": {
    "iso:country":"US",
    "name:cat_x_preferred":[
        "Smithfield"
    ],
    "name:ceb_x_preferred":[
        "Smithfield"
    ],
    "name:ces_x_preferred":[
        "Smithfield"
    ],
    "name:deu_x_preferred":[
        "Smithfield"
    ],
    "name:est_x_preferred":[
        "Smithfield"
    ],
    "name:fin_x_preferred":[
        "Smithfield"
    ],
    "name:fra_x_preferred":[
        "Smithfield"
    ],
    "name:ind_x_preferred":[
        "Smithfield"
    ],
    "name:ita_x_preferred":[
        "Smithfield"
    ],
    "name:nds_x_preferred":[
        "Smithfield"
    ],
    "name:nld_x_preferred":[
        "Smithfield"
    ],
    "name:nor_x_preferred":[
        "Smithfield"
    ],
    "name:pol_x_preferred":[
        "Smithfield"
    ],
    "name:por_x_preferred":[
        "Smithfield"
    ],
    "name:ron_x_preferred":[
        "Smithfield"
    ],
    "name:rus_x_preferred":[
        "\u0421\u043c\u0438\u0442\u0444\u0438\u043b\u0434"
    ],
    "name:spa_x_preferred":[
        "Smithfield"
    ],
    "name:srp_x_preferred":[
        "\u0421\u043c\u0438\u0442\u0444\u0438\u043b\u0434"
    ],
    "name:swe_x_preferred":[
        "Smithfield"
    ],
    "name:urd_x_preferred":[
        "\u0633\u0645\u062a\u06be\u0641\u06cc\u0644\u0688"
    ],
    "name:vol_x_preferred":[
        "Smithfield"
    ],
    "qs_pg:aaroncc":"US",
    "qs_pg:name":"Smithfield",
    "qs_pg:name_adm0":"United States",
    "qs_pg:name_adm1":"Oregon",
    "qs_pg:photos":36,
    "qs_pg:photos_1k":7,
    "qs_pg:photos_9k":1,
    "qs_pg:photos_9r":2,
    "qs_pg:photos_all":36,
    "qs_pg:photos_sr":2,
    "qs_pg:pop_sr":0,
    "qs_pg:qs_pg_placetype":"locality",
    "qs_pg:qs_pg_placetype_gp":"Town",
    "qs_pg:woe_adm0":23424977,
    "woe:adm0_id":23424977,
    "woe:name_adm0":"United States",
    "woe:name_adm1":"Oregon",
    "woe:placetype":"Town",
    "wof:name":"Smithfield",
    "wof:placetype":"locality"
},
  "geometry": {"coordinates":[-123.24417750000001,44.9646],"type":"Point"}
}