{
  "type": "Feature",
  "properties": {
    "gn:admin1_code":"IA",
    "gn:admin2_code":"65.0",
    "gn:admin3_code":"93411.0",
    "gn:asciiname":"Brainard",
    "gn:country_code":"US",
    "gn:dem":281,
    "gn:elevation":"281.0",
    "gn:feature_class":"P",
    "gn:feature_code":"PPL",
    "gn:name":"Brainard",
    "gn:population":0,
    "gn:timezone":"America/Chicago",
    "iso:country":"US",
    "name:deu_x_preferred":[
        "Brainard"
    ],
    "name:fra_x_preferred":[
        "Brainard"
    ],
    "name:ita_x_preferred":[
        "Brainard"
    ],
    "name:pol_x_preferred":[
        "Brainard"
    ],
    "name:por_x_preferred":[
        "Brainard"
    ],
    "name:rus_x_preferred":[
        "\u0411\u0440\u044d\u0439\u043d\u0430\u0440\u0434"
    ],
    "wof:name":"Brainard",
    "wof:placetype":"locality"
},
  "geometry": {"coordinates":[-91.70516000000001,42.93081],"type":"Point"}
}