{
  "type": "Feature",
  "properties": {
    "iso:country":"US",
    "name:ceb_x_preferred":[
        "Timber Ridge"
    ],
    "name:eng_x_preferred":[
        "Timber Ridge"
    ],
    "wd:wordcount":122,
    "wof:name":"Timber Ridge",
    "wof:placetype":"neighbourhood",
    "wof:population":114,
    "zs:area_m":1055558.241013,
    "zs:blockids":[
        370210026041025
    ],
    "zs:housing10":41,
    "zs:label":"Timber Ridge",
    "zs:pop10":114
},
  "geometry": {"coordinates":[-82.69776,35.692695],"type":"Point"}
}