{
  "type": "Feature",
  "properties": {
    "gn:admin1_code":"VA",
    "gn:admin2_code":"135",
    "gn:asciiname":"Oliveville",
    "gn:country_code":"US",
    "gn:dem":168,
    "gn:elevation":"167.0",
    "gn:feature_class":"P",
    "gn:feature_code":"PPL",
    "gn:name":"Oliveville",
    "gn:population":0,
    "gn:timezone":"America/New_York",
    "iso:country":"US",
    "wof:name":"Oliveville",
    "wof:placetype":"locality"
},
  "geometry": {"coordinates":[-78.23305000000001,37.14738],"type":"Point"}
}