{
  "type": "Feature",
  "properties": {
    "gn:admin1_code":"TX",
    "gn:admin2_code":"141.0",
    "gn:asciiname":"Warren Allen Road Colonia",
    "gn:country_code":"US",
    "gn:dem":1108,
    "gn:elevation":"1113.0",
    "gn:feature_class":"P",
    "gn:feature_code":"PPL",
    "gn:name":"Warren Allen Road Colonia",
    "gn:population":0,
    "gn:timezone":"America/Denver",
    "iso:country":"US",
    "wof:name":"Warren Allen Road Colonia",
    "wof:placetype":"locality"
},
  "geometry": {"coordinates":[-106.23859,31.629],"type":"Point"}
}