{
  "type": "Feature",
  "properties": {
    "gn:country":"US",
    "gn:fcode":"PPL",
    "gn:population":0,
    "iso:country":"US",
    "name:ceb_x_preferred":[
        "Mountain Home"
    ],
    "name:deu_x_preferred":[
        "Mountain Home"
    ],
    "name:fra_x_preferred":[
        "Mountain Home"
    ],
    "name:ita_x_preferred":[
        "Mountain Home"
    ],
    "name:nld_x_preferred":[
        "Mountain Home"
    ],
    "name:pol_x_preferred":[
        "Mountain Home"
    ],
    "name:por_x_preferred":[
        "Mountain Home"
    ],
    "name:rus_x_preferred":[
        "\u041c\u0430\u0443\u043d\u0442\u0438\u043d-\u0425\u043e\u043c"
    ],
    "name:srp_x_preferred":[
        "\u041c\u0430\u0443\u043d\u0442\u0438\u043d \u0425\u043e\u0443\u043c"
    ],
    "name:swe_x_preferred":[
        "Mountain Home"
    ],
    "name:ukr_x_preferred":[
        "\u041c\u0430\u0443\u043d\u0442\u0435\u043d-\u0413\u043e\u0443\u043c"
    ],
    "name:vol_x_preferred":[
        "Mountain Home"
    ],
    "qs_pg:aaroncc":"US",
    "qs_pg:gn_country":"US",
    "qs_pg:gn_fcode":"PPL",
    "qs_pg:gn_pop":0,
    "qs_pg:name":"Mountain Home",
    "qs_pg:name_adm0":"United States",
    "qs_pg:name_adm1":"Tennessee",
    "qs_pg:photos_9k":1,
    "qs_pg:photos_9r":1,
    "qs_pg:photos_all":3,
    "qs_pg:photos_sr":0,
    "qs_pg:pop_sr":0,
    "qs_pg:qs_pg_placetype":"locality",
    "qs_pg:qs_pg_placetype_gp":"Town",
    "qs_pg:woe_adm0":23424977,
    "woe:adm0_id":23424977,
    "woe:name_adm0":"United States",
    "woe:name_adm1":"Tennessee",
    "woe:placetype":"Town",
    "wof:name":"Mountain Home",
    "wof:placetype":"locality"
},
  "geometry": {"coordinates":[-82.3732,36.31066],"type":"Point"}
}