{
  "type": "Feature",
  "properties": {
    "gn:admin1_code":"MD",
    "gn:admin2_code":"35.0",
    "gn:asciiname":"Pine Cove",
    "gn:country_code":"US",
    "gn:dem":15,
    "gn:elevation":"8.0",
    "gn:feature_class":"P",
    "gn:feature_code":"PPL",
    "gn:name":"Pine Cove",
    "gn:population":0,
    "gn:timezone":"America/New_York",
    "iso:country":"US",
    "wof:name":"Pine Cove",
    "wof:placetype":"locality"
},
  "geometry": {"coordinates":[-75.95939,39.239],"type":"Point"}
}