{
  "type": "Feature",
  "properties": {
    "gn:country":"US",
    "gn:fcode":"PPL",
    "gn:population":0,
    "iso:country":"US",
    "name:azb_x_preferred":[
        "\u062c\u0631\u0648\u0633\u0626\u06cc\u0644\u0645"
    ],
    "name:ben_x_preferred":[
        "\u099c\u09c7\u09b0\u09c1\u099c\u09be\u09b2\u09c7\u09ae"
    ],
    "name:ell_x_preferred":[
        "\u0399\u03b5\u03c1\u03bf\u03c5\u03c3\u03b1\u03bb\u03ae\u03bc"
    ],
    "name:eng_x_preferred":[
        "Jerusalem"
    ],
    "name:fas_x_preferred":[
        "\u0627\u0648\u0631\u0634\u0644\u06cc\u0645"
    ],
    "name:fra_x_preferred":[
        "Jerusalem"
    ],
    "name:hin_x_preferred":[
        "\u092f\u0930\u0942\u0936\u0932\u0947\u092e"
    ],
    "name:lld_x_preferred":[
        "Jerusalem"
    ],
    "name:zho_x_preferred":[
        "\u8036\u8def\u6492\u51b7"
    ],
    "qs_pg:aaroncc":"US",
    "qs_pg:gn_country":"US",
    "qs_pg:gn_fcode":"PPL",
    "qs_pg:gn_pop":0,
    "qs_pg:name":"Jerusalem",
    "qs_pg:name_adm0":"United States",
    "qs_pg:name_adm1":"Arkansas",
    "qs_pg:photos_9k":1,
    "qs_pg:photos_9r":1,
    "qs_pg:photos_all":1,
    "qs_pg:photos_sr":0,
    "qs_pg:pop_sr":5,
    "qs_pg:qs_pg_placetype":"locality",
    "qs_pg:qs_pg_placetype_gp":"Town",
    "qs_pg:woe_adm0":23424977,
    "woe:adm0_id":23424977,
    "woe:name_adm0":"United States",
    "woe:name_adm1":"Arkansas",
    "woe:placetype":"Town",
    "wof:name":"Jerusalem",
    "wof:placetype":"locality"
},
  "geometry": {"coordinates":[-92.81683,35.4048],"type":"Point"}
}