{
  "type": "Feature",
  "properties": {
    "gn:admin1_code":"WV",
    "gn:admin2_code":"99.0",
    "gn:asciiname":"Stepptown",
    "gn:country_code":"US",
    "gn:dem":191,
    "gn:elevation":"190.0",
    "gn:feature_class":"P",
    "gn:feature_code":"PPL",
    "gn:name":"Stepptown",
    "gn:population":0,
    "gn:timezone":"America/New_York",
    "iso:country":"US",
    "name:eng_x_preferred":[
        "Stepptown"
    ],
    "name:und_x_variant":[
        "Steptown"
    ],
    "wof:name":"Stepptown",
    "wof:placetype":"locality"
},
  "geometry": {"coordinates":[-82.41654,37.86315],"type":"Point"}
}