{
  "type": "Feature",
  "properties": {
    "iso:country":"US",
    "name:eng_x_preferred":[
        "Cedar Cliff"
    ],
    "wof:name":"Cedar Cliff",
    "wof:placetype":"neighbourhood",
    "wof:population":1826,
    "zs:area_m":1166593.172072,
    "zs:blockids":[
        420410109002009,
        420410109004030,
        420410109001003,
        420410109003013,
        420410109002010,
        420410109004032,
        420410106004074,
        420410109002007,
        420410106004076,
        420410109001010,
        420410109001008,
        420410109002002,
        420410109002012,
        420410109002000,
        420410109003008,
        420410109001009,
        420410109002011,
        420410109003014,
        420410109001004,
        420410109001011,
        420410109004029,
        420410109003015,
        420410106004061,
        420410109001002,
        420410109003007,
        420410109002008,
        420410109001005,
        420410109001000,
        420410109001007,
        420410109003011,
        420410109003002,
        420410109002004,
        420410109003005,
        420410109002001,
        420410109001006,
        420410109004031,
        420410109001001,
        420410109003012,
        420410109003009,
        420410109003010,
        420410109002003
    ],
    "zs:housing10":873,
    "zs:label":"Cedar Cliff",
    "zs:pop10":1826
},
  "geometry": {"coordinates":[-76.90533499999999,40.234288],"type":"Point"}
}