{
  "type": "Feature",
  "properties": {
    "gn:admin1_code":"WV",
    "gn:admin2_code":"109",
    "gn:asciiname":"Long Branch",
    "gn:country_code":"US",
    "gn:dem":380,
    "gn:elevation":"365.0",
    "gn:feature_class":"P",
    "gn:feature_code":"PPL",
    "gn:name":"Long Branch",
    "gn:population":0,
    "gn:timezone":"America/New_York",
    "iso:country":"US",
    "name:deu_x_preferred":[
        "Long Branch"
    ],
    "name:fra_x_preferred":[
        "Long Branch"
    ],
    "name:ita_x_preferred":[
        "Long Branch"
    ],
    "name:kor_x_preferred":[
        "\ub871\ube0c\ub79c\uce58"
    ],
    "name:nld_x_preferred":[
        "Long Branch"
    ],
    "name:pol_x_preferred":[
        "Long Branch"
    ],
    "name:por_x_preferred":[
        "Long Branch"
    ],
    "name:spa_x_preferred":[
        "Long Branch"
    ],
    "name:srp_x_preferred":[
        "\u041b\u043e\u043d\u0433 \u0411\u0440\u0430\u043d\u0447"
    ],
    "name:swe_x_preferred":[
        "Long Branch"
    ],
    "name:ukr_x_preferred":[
        "\u041b\u043e\u043d\u0433-\u0411\u0440\u0430\u043d\u0447"
    ],
    "name:vol_x_preferred":[
        "Long Branch"
    ],
    "wof:name":"Long Branch",
    "wof:placetype":"locality"
},
  "geometry": {"coordinates":[-81.76428,37.61789],"type":"Point"}
}