{
  "type": "Feature",
  "properties": {
    "gn:admin1_code":"SC",
    "gn:admin2_code":"85.0",
    "gn:asciiname":"Carolina Mobile Home Park",
    "gn:country_code":"US",
    "gn:dem":87,
    "gn:elevation":"87.0",
    "gn:feature_class":"P",
    "gn:feature_code":"PPL",
    "gn:name":"Carolina Mobile Home Park",
    "gn:population":0,
    "gn:timezone":"America/New_York",
    "iso:country":"US",
    "wof:name":"Carolina Mobile Home Park",
    "wof:placetype":"campus"
},
  "geometry": {"coordinates":[-80.49424999999999,33.96543],"type":"Point"}
}