{
  "type": "Feature",
  "properties": {
    "iso:country":"US",
    "name:eng_x_preferred":[
        "Maplenol Heights"
    ],
    "name:unk_x_variant":[
        "Maplenol Heights"
    ],
    "qs:gn_adm0_cc":"US",
    "qs:gn_local":4881346,
    "qs:gn_nam_loc":"West Des Moines, Polk, Iowa, US",
    "qs:gn_namadm1":"IA",
    "qs:local_max":1646,
    "qs:local_sum":4232,
    "qs:localhoods":14,
    "qs:name":"Maplenol Heights",
    "qs:name_adm0":"United States",
    "qs:name_adm1":"Iowa",
    "qs:name_adm2":"Polk",
    "qs:name_local":"West des Moines",
    "qs:photo_max":221,
    "qs:photo_sum":236,
    "qs:placetype":"Suburb",
    "qs:quad_count":6,
    "qs:woe_adm0":23424977,
    "qs:woe_adm1":2347574,
    "qs:woe_adm2":12588348,
    "qs:woe_lau":0,
    "qs:woe_local":2516909,
    "qs:woe_ver":"7.10.0",
    "wof:lang":[
        "eng"
    ],
    "wof:name":"Maplenol Heights",
    "wof:placetype":"neighbourhood",
    "wof:population":2381,
    "zs:blockids":[
        191530111143016,
        191530111123002,
        191530111123005,
        191530110211005,
        191530110211004,
        191530111143017,
        191530111143018,
        191530111123006,
        191530110211008,
        191530110211014,
        191530111123008,
        191530110211006,
        191530110211012,
        191530111123003,
        191530111143011,
        191530111143015,
        191530111123001,
        191530111123012,
        191530111123007,
        191530110211003,
        191530110211019,
        191530110211000,
        191530111123009,
        191530111143001,
        191530111123004,
        191530111143000,
        191530111143008,
        191530111143003,
        191530110211015,
        191530111123010,
        191530111123011,
        191530110211010,
        191530110211037,
        191530111143010,
        191530111143007,
        191530111143013,
        191530111143006,
        191530110211009,
        191530111143005,
        191530111143009,
        191530110211016,
        191530111141030,
        191530111141031,
        191530111143014,
        191530110211011,
        191530110211038,
        191530110211002,
        191530110211001
    ],
    "zs:housing10":1101,
    "zs:pop10":2381
},
  "geometry": {"coordinates":[-93.75748299999999,41.590337],"type":"Point"}
}