{
  "type": "Feature",
  "properties": {
    "gn:admin1_code":"MT",
    "gn:admin2_code":"63.0",
    "gn:asciiname":"Schley",
    "gn:country_code":"US",
    "gn:dem":1080,
    "gn:elevation":"1078.0",
    "gn:feature_class":"P",
    "gn:feature_code":"PPL",
    "gn:name":"Schley",
    "gn:population":0,
    "gn:timezone":"America/Denver",
    "iso:country":"US",
    "name:deu_x_preferred":[
        "Schley"
    ],
    "name:fra_x_preferred":[
        "Schley"
    ],
    "name:pol_x_preferred":[
        "Schley"
    ],
    "name:rus_x_preferred":[
        "\u0428\u043b\u0435\u0439"
    ],
    "name:swe_x_preferred":[
        "Schley"
    ],
    "wof:name":"Schley",
    "wof:placetype":"locality"
},
  "geometry": {"coordinates":[-114.054,47.10326],"type":"Point"}
}