{
  "type": "Feature",
  "properties": {
    "gn:admin1_code":"TN",
    "gn:admin2_code":"163",
    "gn:asciiname":"Pactolus",
    "gn:country_code":"US",
    "gn:dem":406,
    "gn:elevation":"406.0",
    "gn:feature_class":"P",
    "gn:feature_code":"PPL",
    "gn:name":"Pactolus",
    "gn:population":0,
    "gn:timezone":"America/New_York",
    "iso:country":"US",
    "name:bul_x_preferred":[
        "\u041f\u0430\u043a\u0442\u043e\u043b"
    ],
    "name:cat_x_preferred":[
        "Pactol"
    ],
    "name:ces_x_preferred":[
        "Paktol\u00f3s"
    ],
    "name:deu_x_preferred":[
        "Paktolos"
    ],
    "name:ell_x_preferred":[
        "\u03a0\u03b1\u03ba\u03c4\u03c9\u03bb\u03cc\u03c2"
    ],
    "name:ext_x_preferred":[
        "Patolu"
    ],
    "name:fra_x_preferred":[
        "Pactole"
    ],
    "name:ita_x_preferred":[
        "Pattolo"
    ],
    "name:lat_x_preferred":[
        "Pactolus"
    ],
    "name:nld_x_preferred":[
        "Paktolos"
    ],
    "name:nno_x_preferred":[
        "Sart \u00c7ay\u0131"
    ],
    "name:nor_x_preferred":[
        "Sart \u00c7ay\u0131"
    ],
    "name:oci_x_preferred":[
        "Pact\u00f2l"
    ],
    "name:pol_x_preferred":[
        "Paktol"
    ],
    "name:por_x_preferred":[
        "Pactolo"
    ],
    "name:rus_x_preferred":[
        "\u041f\u0430\u043a\u0442\u043e\u043b"
    ],
    "name:spa_x_preferred":[
        "R\u00edo Pactolo"
    ],
    "name:tur_x_preferred":[
        "Sart \u00c7ay\u0131"
    ],
    "name:ukr_x_preferred":[
        "\u041f\u0430\u043a\u0442\u043e\u043b"
    ],
    "wof:name":"Pactolus",
    "wof:placetype":"locality"
},
  "geometry": {"coordinates":[-82.52154,36.49899],"type":"Point"}
}