{
  "type": "Feature",
  "properties": {
    "gn:admin1_code":"OH",
    "gn:admin2_code":"127",
    "gn:admin3_code":"70226.0",
    "gn:asciiname":"McCuneville",
    "gn:country_code":"US",
    "gn:dem":248,
    "gn:elevation":"241.0",
    "gn:feature_class":"P",
    "gn:feature_code":"PPL",
    "gn:name":"McCuneville",
    "gn:population":0,
    "gn:timezone":"America/New_York",
    "iso:country":"US",
    "name:eng_x_preferred":[
        "McCuneville"
    ],
    "name:und_x_variant":[
        "Tallyho",
        "Salt Works"
    ],
    "wof:name":"McCuneville",
    "wof:placetype":"locality"
},
  "geometry": {"coordinates":[-82.23432,39.62896],"type":"Point"}
}