{
  "type": "Feature",
  "properties": {
    "gn:admin1_code":"MT",
    "gn:admin2_code":"67.0",
    "gn:asciiname":"Hoppers",
    "gn:country_code":"US",
    "gn:dem":1580,
    "gn:elevation":"1576.0",
    "gn:feature_class":"P",
    "gn:feature_code":"PPL",
    "gn:name":"Hoppers",
    "gn:population":0,
    "gn:timezone":"America/Denver",
    "iso:country":"US",
    "wof:name":"Hoppers",
    "wof:placetype":"locality"
},
  "geometry": {"coordinates":[-110.71827,45.66549000000001],"type":"Point"}
}