{
  "type": "Feature",
  "properties": {
    "gn:admin1_code":"FL",
    "gn:admin2_code":"103.0",
    "gn:asciiname":"Oakhurst Terrace",
    "gn:country_code":"US",
    "gn:dem":21,
    "gn:elevation":"18.0",
    "gn:feature_class":"P",
    "gn:feature_code":"PPL",
    "gn:name":"Oakhurst Terrace",
    "gn:population":0,
    "gn:timezone":"America/New_York",
    "iso:country":"US",
    "wof:name":"Oakhurst Terrace",
    "wof:placetype":"locality"
},
  "geometry": {"coordinates":[-82.82483000000001,27.85308],"type":"Point"}
}