{
  "type": "Feature",
  "properties": {
    "gn:country":"US",
    "gn:fcode":"PPL",
    "gn:population":0,
    "iso:country":"US",
    "name:deu_x_preferred":[
        "Keeler"
    ],
    "name:fra_x_preferred":[
        "Keeler"
    ],
    "name:ita_x_preferred":[
        "Keeler"
    ],
    "name:nds_x_preferred":[
        "Keeler"
    ],
    "name:nld_x_preferred":[
        "Keeler"
    ],
    "name:pol_x_preferred":[
        "Keeler"
    ],
    "name:por_x_preferred":[
        "Keeler"
    ],
    "name:rus_x_preferred":[
        "\u041a\u0438\u043b\u0435\u0440"
    ],
    "name:spa_x_preferred":[
        "Keeler"
    ],
    "name:srp_x_preferred":[
        "\u041a\u0438\u043b\u0435\u0440"
    ],
    "qs_pg:aaroncc":"US",
    "qs_pg:gn_country":"US",
    "qs_pg:gn_fcode":"PPL",
    "qs_pg:gn_pop":0,
    "qs_pg:name":"Keeler",
    "qs_pg:name_adm0":"United States",
    "qs_pg:name_adm1":"Kansas",
    "qs_pg:photos":1,
    "qs_pg:photos_1k":1,
    "qs_pg:photos_9k":1,
    "qs_pg:photos_9r":1,
    "qs_pg:photos_all":1,
    "qs_pg:photos_sr":1,
    "qs_pg:pop_sr":0,
    "qs_pg:qs_pg_placetype":"locality",
    "qs_pg:qs_pg_placetype_gp":"Town",
    "qs_pg:woe_adm0":23424977,
    "woe:adm0_id":23424977,
    "woe:name_adm0":"United States",
    "woe:name_adm1":"Kansas",
    "woe:placetype":"Town",
    "wof:name":"Keeler",
    "wof:placetype":"locality"
},
  "geometry": {"coordinates":[-97.29143000000001,37.61196],"type":"Point"}
}