{
  "type": "Feature",
  "properties": {
    "gn:admin1_code":"KY",
    "gn:admin2_code":"57.0",
    "gn:asciiname":"Big Renox",
    "gn:country_code":"US",
    "gn:dem":189,
    "gn:elevation":"188.0",
    "gn:feature_class":"P",
    "gn:feature_code":"PPL",
    "gn:name":"Big Renox",
    "gn:population":0,
    "gn:timezone":"America/Chicago",
    "iso:country":"US",
    "wof:name":"Big Renox",
    "wof:placetype":"locality"
},
  "geometry": {"coordinates":[-85.39012,36.87152],"type":"Point"}
}