{
  "type": "Feature",
  "properties": {
    "gn:admin1_code":"NC",
    "gn:admin2_code":"191",
    "gn:admin3_code":"92848.0",
    "gn:asciiname":"Hood Swamp",
    "gn:country_code":"US",
    "gn:dem":31,
    "gn:elevation":"37.0",
    "gn:feature_class":"P",
    "gn:feature_code":"PPL",
    "gn:name":"Hood Swamp",
    "gn:population":0,
    "gn:timezone":"America/New_York",
    "iso:country":"US",
    "wof:name":"Hood Swamp",
    "wof:placetype":"locality"
},
  "geometry": {"coordinates":[-77.8747,35.40655],"type":"Point"}
}