{
  "type": "Feature",
  "properties": {
    "gn:admin1_code":"SC",
    "gn:admin2_code":"15.0",
    "gn:asciiname":"Wing Road",
    "gn:country_code":"US",
    "gn:dem":25,
    "gn:elevation":"24.0",
    "gn:feature_class":"P",
    "gn:feature_code":"PPL",
    "gn:name":"Wing Road",
    "gn:population":0,
    "gn:timezone":"America/New_York",
    "iso:country":"US",
    "wof:name":"Wing Road",
    "wof:placetype":"locality"
},
  "geometry": {"coordinates":[-80.06647,33.421],"type":"Point"}
}