{
  "type": "Feature",
  "properties": {
    "gn:admin1_code":"LA",
    "gn:admin2_code":"23.0",
    "gn:asciiname":"Sweet Lake",
    "gn:country_code":"US",
    "gn:dem":8,
    "gn:elevation":"1.0",
    "gn:feature_class":"P",
    "gn:feature_code":"PPL",
    "gn:name":"Sweet Lake",
    "gn:population":0,
    "gn:timezone":"America/Chicago",
    "iso:country":"US",
    "name:eng_x_preferred":[
        "Sweet Lake"
    ],
    "name:und_x_variant":[
        "Sweetlake"
    ],
    "wof:name":"Sweet Lake",
    "wof:placetype":"locality"
},
  "geometry": {"coordinates":[-93.12932000000001,29.9841],"type":"Point"}
}