{
  "type": "Feature",
  "properties": {
    "gn:admin1_code":"MD",
    "gn:admin2_code":"5.0",
    "gn:asciiname":"Westview Park",
    "gn:country_code":"US",
    "gn:dem":137,
    "gn:elevation":"134.0",
    "gn:feature_class":"P",
    "gn:feature_code":"PPL",
    "gn:name":"Westview Park",
    "gn:population":0,
    "gn:timezone":"America/New_York",
    "iso:country":"US",
    "wof:name":"Westview Park",
    "wof:placetype":"locality"
},
  "geometry": {"coordinates":[-76.73886,39.29677],"type":"Point"}
}