{
  "type": "Feature",
  "properties": {
    "iso:country":"US",
    "name:bpy_x_preferred":[
        "\u09b2\u09be\u09a8\u09cd\u09b8\u09a6\u09cb\u09f1\u09a8\u09c7"
    ],
    "name:ceb_x_preferred":[
        "Lansdowne"
    ],
    "name:deu_x_preferred":[
        "Lansdowne"
    ],
    "name:eng_x_preferred":[
        "Lansdowne"
    ],
    "name:ita_x_preferred":[
        "Lansdowne"
    ],
    "name:nds_x_preferred":[
        "Lansdowne"
    ],
    "name:new_x_preferred":[
        "\u0932\u0928\u094d\u0938\u094d\u0926\u094b\u0935\u094d\u0928\u0947"
    ],
    "name:nld_x_preferred":[
        "Lansdowne"
    ],
    "name:pol_x_preferred":[
        "Lansdowne"
    ],
    "name:srp_x_preferred":[
        "\u041b\u0430\u043d\u0441\u0434\u0430\u0443\u043d"
    ],
    "name:swe_x_preferred":[
        "Lansdowne"
    ],
    "name:ukr_x_preferred":[
        "\u041b\u0430\u043d\u0441\u0434\u0430\u0443\u043d"
    ],
    "name:vol_x_preferred":[
        "Lansdowne"
    ],
    "wof:name":"Lansdowne",
    "wof:placetype":"neighbourhood",
    "wof:population":446,
    "zs:area_m":685877.659035,
    "zs:blockids":[
        371190020042005,
        371190020042011
    ],
    "zs:housing10":201,
    "zs:label":"Lansdowne",
    "zs:pop10":446
},
  "geometry": {"coordinates":[-80.77812400000001,35.14154],"type":"Point"}
}