{
  "type": "Feature",
  "properties": {
    "gn:admin1_code":"NC",
    "gn:admin2_code":"81.0",
    "gn:admin3_code":"92124.0",
    "gn:asciiname":"Starmount Forest",
    "gn:country_code":"US",
    "gn:dem":257,
    "gn:elevation":"251.0",
    "gn:feature_class":"P",
    "gn:feature_code":"PPL",
    "gn:name":"Starmount Forest",
    "gn:population":0,
    "gn:timezone":"America/New_York",
    "iso:country":"US",
    "wof:name":"Starmount Forest",
    "wof:placetype":"locality"
},
  "geometry": {"coordinates":[-79.8442,36.07958],"type":"Point"}
}