{
  "type": "Feature",
  "properties": {
    "gn:admin1_code":"KY",
    "gn:admin2_code":"203",
    "gn:asciiname":"Sand Springs",
    "gn:country_code":"US",
    "gn:dem":300,
    "gn:elevation":"296.0",
    "gn:feature_class":"P",
    "gn:feature_code":"PPL",
    "gn:name":"Sand Springs",
    "gn:population":0,
    "gn:timezone":"America/New_York",
    "iso:country":"US",
    "name:ceb_x_preferred":[
        "Sand Springs"
    ],
    "name:deu_x_preferred":[
        "Sand Springs"
    ],
    "name:ita_x_preferred":[
        "Sand Springs"
    ],
    "name:spa_x_preferred":[
        "Sand Springs"
    ],
    "name:srp_x_preferred":[
        "\u0421\u0430\u043d\u0434 \u0421\u043f\u0440\u0438\u043d\u0433\u0441"
    ],
    "wof:name":"Sand Springs",
    "wof:placetype":"locality"
},
  "geometry": {"coordinates":[-84.3591,37.29703],"type":"Point"}
}