{
  "type": "Feature",
  "properties": {
    "gn:admin1_code":"FL",
    "gn:admin2_code":"117.0",
    "gn:asciiname":"Pine Crest Trailer Park",
    "gn:country_code":"US",
    "gn:dem":24,
    "gn:elevation":"17.0",
    "gn:feature_class":"P",
    "gn:feature_code":"PPL",
    "gn:name":"Pine Crest Trailer Park",
    "gn:population":0,
    "gn:timezone":"America/New_York",
    "iso:country":"US",
    "wof:name":"Pine Crest Trailer Park",
    "wof:placetype":"campus"
},
  "geometry": {"coordinates":[-81.26738,28.77689],"type":"Point"}
}