{
  "type": "Feature",
  "properties": {
    "gn:admin1_code":"TX",
    "gn:admin2_code":"1",
    "gn:asciiname":"Jarvis",
    "gn:country_code":"US",
    "gn:dem":98,
    "gn:elevation":"91.0",
    "gn:feature_class":"P",
    "gn:feature_code":"PPL",
    "gn:name":"Jarvis",
    "gn:population":0,
    "gn:timezone":"America/Chicago",
    "iso:country":"US",
    "name:deu_x_preferred":[
        "Jarvis"
    ],
    "name:est_x_preferred":[
        "Jarvis"
    ],
    "name:fra_x_preferred":[
        "Jarvis"
    ],
    "name:ita_x_preferred":[
        "Jarvis"
    ],
    "name:jpn_x_preferred":[
        "\u30b8\u30e3\u30fc\u30f4\u30a3\u30b9"
    ],
    "name:kor_x_preferred":[
        "\uc790\ube44\uc2a4"
    ],
    "name:nld_x_preferred":[
        "Jarvis"
    ],
    "name:ron_x_preferred":[
        "Jarvis"
    ],
    "name:rus_x_preferred":[
        "\u043e\u0441\u0442\u0440\u043e\u0432 \u0414\u0436\u0430\u0440\u0432\u0438\u0441"
    ],
    "name:rus_x_variant":[
        "\u0414\u0436\u0430\u0440\u0432\u0438\u0441"
    ],
    "name:spa_x_preferred":[
        "Jarvis"
    ],
    "name:swe_x_preferred":[
        "Jarvis\u00f6n"
    ],
    "name:tur_x_preferred":[
        "Jarvis"
    ],
    "name:ukr_x_preferred":[
        "\u0414\u0436\u0430\u0440\u0432\u0456\u0441"
    ],
    "name:urd_x_preferred":[
        "\u062c\u0627\u0631\u0648\u0633"
    ],
    "name:vie_x_preferred":[
        "\u0110\u1ea3o Jarvis"
    ],
    "name:zho_cn_x_preferred":[
        "\u8d3e\u7ef4\u65af\u5c9b"
    ],
    "name:zho_tw_x_preferred":[
        "\u96c5\u7dad\u65af\u5cf6"
    ],
    "wof:name":"Jarvis",
    "wof:placetype":"locality"
},
  "geometry": {"coordinates":[-95.44495000000001,31.75517],"type":"Point"}
}