{
  "type": "Feature",
  "properties": {
    "gn:admin1_code":"WV",
    "gn:admin2_code":"83",
    "gn:asciiname":"Aggregates",
    "gn:country_code":"US",
    "gn:dem":579,
    "gn:elevation":"589.0",
    "gn:feature_class":"P",
    "gn:feature_code":"PPL",
    "gn:name":"Aggregates",
    "gn:population":0,
    "gn:timezone":"America/New_York",
    "iso:country":"US",
    "name:fas_x_preferred":[
        "\u0627\u06af\u0631\u06cc\u06af\u06cc\u062a\u0633"
    ],
    "name:urd_x_preferred":[
        "\u0627\u06cc\u06af\u0631\u06cc\u06af\u06cc\u0679\u0633"
    ],
    "wof:name":"Aggregates",
    "wof:placetype":"locality"
},
  "geometry": {"coordinates":[-79.91868000000002,38.93622],"type":"Point"}
}