{
  "type": "Feature",
  "properties": {
    "iso:country":"US",
    "name:eng_x_preferred":[
        "Pines West"
    ],
    "wof:name":"Pines West",
    "wof:placetype":"neighbourhood",
    "wof:population":27,
    "zs:area_m":8096.238626,
    "zs:blockids":[
        121050124031094
    ],
    "zs:housing10":10,
    "zs:label":"Pines West",
    "zs:pop10":27
},
  "geometry": {"coordinates":[-81.665469,28.267405],"type":"Point"}
}