{
  "type": "Feature",
  "properties": {
    "gn:admin1_code":"MD",
    "gn:admin2_code":"25.0",
    "gn:asciiname":"Nobles Mill Estates",
    "gn:country_code":"US",
    "gn:dem":35,
    "gn:elevation":"34.0",
    "gn:feature_class":"P",
    "gn:feature_code":"PPL",
    "gn:name":"Nobles Mill Estates",
    "gn:population":0,
    "gn:timezone":"America/New_York",
    "iso:country":"US",
    "wof:name":"Nobles Mill Estates",
    "wof:placetype":"locality"
},
  "geometry": {"coordinates":[-76.24134000000002,39.61761],"type":"Point"}
}