{
  "type": "Feature",
  "properties": {
    "gn:admin1_code":"MI",
    "gn:admin2_code":"139",
    "gn:admin3_code":"1360.0",
    "gn:asciiname":"Chateau Deerfield Manor Mobile Home Park",
    "gn:country_code":"US",
    "gn:dem":202,
    "gn:elevation":"203.0",
    "gn:feature_class":"P",
    "gn:feature_code":"PPL",
    "gn:name":"Chateau Deerfield Manor Mobile Home Park",
    "gn:population":0,
    "gn:timezone":"America/Detroit",
    "iso:country":"US",
    "wof:name":"Chateau Deerfield Manor Mobile Home Park",
    "wof:placetype":"campus"
},
  "geometry": {"coordinates":[-85.89778000000003,42.98278],"type":"Point"}
}