{
  "type": "Feature",
  "properties": {
    "iso:country":"US",
    "name:eng_x_preferred":[
        "Zeal"
    ],
    "name:jpn_x_preferred":[
        "\u30b8\u30fc\u30eb"
    ],
    "name:tgl_x_preferred":[
        "Sigla"
    ],
    "name:zho_yue_x_preferred":[
        "Zeal"
    ],
    "wd:wordcount":77,
    "wof:name":"Zeal",
    "wof:placetype":"neighbourhood",
    "wof:population":507,
    "zs:area_m":1473079.928716,
    "zs:blockids":[
        511850205001000,
        511850205001093,
        511850205001016,
        511850205001015,
        511850205001013,
        511850205001012
    ],
    "zs:housing10":251,
    "zs:label":"Zeal",
    "zs:pop10":507
},
  "geometry": {"coordinates":[-81.82515600000001,37.087196],"type":"Point"}
}