{
  "type": "Feature",
  "properties": {
    "gn:admin1_code":"MN",
    "gn:admin2_code":"75.0",
    "gn:asciiname":"Bell Harbor",
    "gn:country_code":"US",
    "gn:dem":185,
    "gn:elevation":"185.0",
    "gn:feature_class":"P",
    "gn:feature_code":"PPL",
    "gn:name":"Bell Harbor",
    "gn:population":0,
    "gn:timezone":"America/Chicago",
    "iso:country":"US",
    "wof:name":"Bell Harbor",
    "wof:placetype":"locality"
},
  "geometry": {"coordinates":[-91.13876999999999,47.38908],"type":"Point"}
}