{
  "type": "Feature",
  "properties": {
    "gn:admin1_code":"TX",
    "gn:admin2_code":"193.0",
    "gn:asciiname":"Schoolerville",
    "gn:country_code":"US",
    "gn:dem":370,
    "gn:elevation":"365.0",
    "gn:feature_class":"P",
    "gn:feature_code":"PPL",
    "gn:name":"Schoolerville",
    "gn:population":0,
    "gn:timezone":"America/Chicago",
    "iso:country":"US",
    "wof:name":"Schoolerville",
    "wof:placetype":"locality"
},
  "geometry": {"coordinates":[-98.18309000000001,31.61655],"type":"Point"}
}