{
  "type": "Feature",
  "properties": {
    "iso:country":"US",
    "name:eng_x_preferred":[
        "Forest Oaks"
    ],
    "wof:name":"Forest Oaks",
    "wof:placetype":"neighbourhood",
    "wof:population":157,
    "zs:area_m":63429.301203,
    "zs:blockids":[
        60610210031009,
        60610210031008,
        60610210031007
    ],
    "zs:housing10":68,
    "zs:label":"Forest Oaks",
    "zs:pop10":157
},
  "geometry": {"coordinates":[-121.28572800000001,38.75773],"type":"Point"}
}