{
  "type": "Feature",
  "properties": {
    "gn:admin1_code":"KY",
    "gn:admin2_code":"181",
    "gn:asciiname":"Moorefield",
    "gn:country_code":"US",
    "gn:dem":299,
    "gn:elevation":"301.0",
    "gn:feature_class":"P",
    "gn:feature_code":"PPL",
    "gn:name":"Moorefield",
    "gn:population":0,
    "gn:timezone":"America/New_York",
    "iso:country":"US",
    "name:fas_x_preferred":[
        "\u0645\u0648\u0631\u0641\u06cc\u0644\u062f"
    ],
    "name:urd_x_preferred":[
        "\u0645\u0648\u0631\u0641\u06cc\u0644\u0688"
    ],
    "wof:name":"Moorefield",
    "wof:placetype":"locality"
},
  "geometry": {"coordinates":[-83.93104,38.27313],"type":"Point"}
}