{
  "type": "Feature",
  "properties": {
    "gn:country":"US",
    "gn:fcode":"PPL",
    "gn:population":0,
    "iso:country":"US",
    "name:eng_x_preferred":[
        "Cedar Level"
    ],
    "qs_pg:aaroncc":"US",
    "qs_pg:gn_country":"US",
    "qs_pg:gn_fcode":"PPL",
    "qs_pg:gn_pop":0,
    "qs_pg:name":"Cedar Level",
    "qs_pg:name_adm0":"United States",
    "qs_pg:name_adm1":"Virginia",
    "qs_pg:photos":4,
    "qs_pg:photos_1k":1,
    "qs_pg:photos_9k":1,
    "qs_pg:photos_9r":1,
    "qs_pg:photos_all":4,
    "qs_pg:photos_sr":1,
    "qs_pg:pop_sr":0,
    "qs_pg:qs_pg_placetype":"neighbourhood",
    "qs_pg:qs_pg_placetype_gp":"Suburb",
    "qs_pg:woe_adm0":23424977,
    "wof:name":"Cedar Level",
    "wof:placetype":"neighbourhood",
    "wof:population":239,
    "zs:blockids":[
        511498502001005,
        511498503012011,
        516708206003081,
        516708206004018,
        516708206003075,
        516708204003042,
        516708206003077,
        516708206003072,
        516708206003071,
        516708206003067,
        516708206003069,
        516708206003079,
        516708206003076,
        516708206003074,
        516708206003080,
        516708206003078,
        516708206003068,
        516708206003073
    ],
    "zs:housing10":114,
    "zs:label":"Cedar Level",
    "zs:pop10":239
},
  "geometry": {"coordinates":[-77.342078,37.272946],"type":"Point"}
}