{
  "type": "Feature",
  "properties": {
    "gn:admin1_code":"SC",
    "gn:admin2_code":"33.0",
    "gn:asciiname":"Mallory",
    "gn:country_code":"US",
    "gn:dem":31,
    "gn:elevation":"35.0",
    "gn:feature_class":"P",
    "gn:feature_code":"PPL",
    "gn:name":"Mallory",
    "gn:population":0,
    "gn:timezone":"America/New_York",
    "iso:country":"US",
    "wof:name":"Mallory",
    "wof:placetype":"locality"
},
  "geometry": {"coordinates":[-79.51311,34.38849],"type":"Point"}
}