{
  "type": "Feature",
  "properties": {
    "gn:gn_country":"US",
    "gn:gn_fcode":"PPL",
    "gn:gn_pop":0,
    "iso:country":"US",
    "name:eng_x_preferred":[
        "Buffalo"
    ],
    "name:fas_x_preferred":[
        "\u0628\u0648\u0641\u0627\u0644\u0648"
    ],
    "name:fra_x_preferred":[
        "Buffalo"
    ],
    "name:ita_x_preferred":[
        "Buffalo"
    ],
    "name:urd_x_preferred":[
        "\u0628\u0641\u06cc\u0644\u0648\u060c \u0627\u06cc\u0646\u0688\u0631\u0633\u0646 \u06a9\u0627\u0624\u0646\u0679\u06cc\u060c \u0679\u06cc\u0646\u06cc\u0633\u06cc"
    ],
    "name:urd_x_variant":[
        "\u0628\u0641\u06cc\u0644\u0648"
    ],
    "qs_pg:aaroncc":"US",
    "qs_pg:gn_country":"US",
    "qs_pg:gn_fcode":"PPL",
    "qs_pg:gn_pop":0,
    "qs_pg:name":"Buffalo",
    "qs_pg:name_adm0":"United States",
    "qs_pg:name_adm1":"Tennessee",
    "qs_pg:photos":6,
    "qs_pg:photos_1k":1,
    "qs_pg:photos_9k":1,
    "qs_pg:photos_9r":1,
    "qs_pg:photos_all":6,
    "qs_pg:photos_sr":1,
    "qs_pg:pop_sr":0,
    "qs_pg:qs_pg_placetype":"locality",
    "qs_pg:qs_pg_placetype_gp":"Town",
    "qs_pg:woe_adm0":23424977,
    "woe:adm0_id":23424977,
    "woe:name_adm0":"United States",
    "woe:name_adm1":"Tennessee",
    "woe:placetype":"Town",
    "wof:name":"Buffalo",
    "wof:placetype":"locality"
},
  "geometry": {"coordinates":[-84.38742999999999,36.13702],"type":"Point"}
}