{
  "type": "Feature",
  "properties": {
    "gn:admin1_code":"OH",
    "gn:admin2_code":"25.0",
    "gn:admin3_code":"74825.0",
    "gn:asciiname":"Ashdale",
    "gn:country_code":"US",
    "gn:dem":265,
    "gn:elevation":"266.0",
    "gn:feature_class":"P",
    "gn:feature_code":"PPL",
    "gn:name":"Ashdale",
    "gn:population":0,
    "gn:timezone":"America/New_York",
    "iso:country":"US",
    "wof:name":"Ashdale",
    "wof:placetype":"locality"
},
  "geometry": {"coordinates":[-84.15188000000001,39.17228],"type":"Point"}
}