{
  "type": "Feature",
  "properties": {
    "iso:country":"US",
    "name:eng_x_preferred":[
        "Map of Avondale"
    ],
    "wof:name":"Map of Avondale",
    "wof:placetype":"neighbourhood",
    "wof:population":495,
    "zs:area_m":2300718.727369,
    "zs:blockids":[
        121050142012042,
        121050142012039,
        121050142012041,
        121050142012037,
        121050142012046,
        121050142012036,
        121050142012038,
        121050142012035,
        121050143023050,
        121050142012045,
        121050143023034,
        121050142012030,
        121050142012044,
        121050142012033,
        121050143023048,
        121050142012031,
        121050142012029,
        121050142012043,
        121050143023037,
        121050143023026
    ],
    "zs:housing10":348,
    "zs:label":"Map of Avondale",
    "zs:pop10":495
},
  "geometry": {"coordinates":[-81.596886,27.931169],"type":"Point"}
}