{
  "type": "Feature",
  "properties": {
    "gn:admin1_code":"OH",
    "gn:admin2_code":"131",
    "gn:admin3_code":"50078.0",
    "gn:asciiname":"Lapperell",
    "gn:country_code":"US",
    "gn:dem":220,
    "gn:elevation":"225.0",
    "gn:feature_class":"P",
    "gn:feature_code":"PPL",
    "gn:name":"Lapperell",
    "gn:population":0,
    "gn:timezone":"America/New_York",
    "iso:country":"US",
    "name:eng_x_preferred":[
        "Lapperell"
    ],
    "name:und_x_variant":[
        "Lapparel"
    ],
    "wof:name":"Lapperell",
    "wof:placetype":"locality"
},
  "geometry": {"coordinates":[-83.27797,39.13035],"type":"Point"}
}