{
  "type": "Feature",
  "properties": {
    "gn:country":"US",
    "gn:fcode":"PPL",
    "gn:population":0,
    "iso:country":"US",
    "name:azb_x_preferred":[
        "\u0622\u0644\u0632\u0633\u0646\u062f\u0631\u0648"
    ],
    "name:eng_x_preferred":[
        "Alessandro"
    ],
    "name:fas_x_preferred":[
        "\u0627\u0644\u0633\u0627\u0646\u062f\u0631\u0648\u060c \u06a9\u0627\u0644\u06cc\u0641\u0631\u0646\u06cc\u0627"
    ],
    "name:fas_x_variant":[
        "\u0627\u0644\u0633\u0627\u0646\u062f\u0631\u0648"
    ],
    "name:fra_x_preferred":[
        "Alessandro"
    ],
    "name:spa_x_preferred":[
        "Alessandro"
    ],
    "name:tur_x_preferred":[
        "Alessandro"
    ],
    "name:zho_x_preferred":[
        "\u4e9e\u6b77\u5c71\u5fb7\u7f85"
    ],
    "qs_pg:aaroncc":"US",
    "qs_pg:gn_country":"US",
    "qs_pg:gn_fcode":"PPL",
    "qs_pg:gn_pop":0,
    "qs_pg:name":"Alessandro",
    "qs_pg:name_adm0":"United States",
    "qs_pg:name_adm1":"California",
    "qs_pg:photos":1846,
    "qs_pg:photos_1k":374,
    "qs_pg:photos_9k":8,
    "qs_pg:photos_9r":9,
    "qs_pg:photos_all":1846,
    "qs_pg:photos_sr":14,
    "qs_pg:pop_sr":0,
    "qs_pg:qs_pg_placetype":"locality",
    "qs_pg:qs_pg_placetype_gp":"Town",
    "qs_pg:woe_adm0":23424977,
    "woe:adm0_id":23424977,
    "woe:name_adm0":"United States",
    "woe:name_adm1":"California",
    "woe:placetype":"Town",
    "wof:name":"Alessandro",
    "wof:placetype":"locality"
},
  "geometry": {"coordinates":[-117.27032,33.88613],"type":"Point"}
}