{
  "type": "Feature",
  "properties": {
    "gn:admin1_code":"AK",
    "gn:admin2_code":"240.0",
    "gn:asciiname":"Kechumstuk",
    "gn:country_code":"US",
    "gn:dem":641,
    "gn:elevation":"640.0",
    "gn:feature_class":"P",
    "gn:feature_code":"PPL",
    "gn:name":"Kechumstuk",
    "gn:population":0,
    "gn:timezone":"America/Anchorage",
    "iso:country":"US",
    "name:eng_x_preferred":[
        "Kechumstuk"
    ],
    "name:und_x_variant":[
        "Ketchumstock Village",
        "Ketchumstuck",
        "Saages Cheeg"
    ],
    "wof:name":"Kechumstuk",
    "wof:placetype":"locality"
},
  "geometry": {"coordinates":[-142.57778000000005,64.01916999999999],"type":"Point"}
}