{
  "type": "Feature",
  "properties": {
    "iso:country":"US",
    "name:eng_x_preferred":[
        "West Mansfield"
    ],
    "wof:name":"West Mansfield",
    "wof:placetype":"neighbourhood",
    "wof:population":3559,
    "zs:area_m":12794385.309681,
    "zs:blockids":[
        250056112021014,
        250056102023004,
        250056112021024,
        250056313001001,
        250056302001023,
        250056112021017,
        250056302002020,
        250056102023016,
        250056112021022,
        250056112021016,
        250056313001004,
        250056302002042,
        250056302002032,
        250056112021020,
        250056313001003,
        250056112021012,
        250056112021023,
        250056102023009,
        250056317001000,
        250056302002021,
        250056102023015,
        250056313001010,
        250056112021018,
        250056102023005,
        250056313001007,
        250056102023002,
        250056102023019,
        250056112021019,
        250056313001005,
        250056112021021,
        250056302002033,
        250056302002019,
        250056302002025,
        250056302002048,
        250056302002043,
        250056313001018,
        250056102023000,
        250056302002027,
        250056102023017,
        250056102023018,
        250056112021011,
        250056112021015,
        250056313001008,
        250056317003002,
        250056302002026,
        250056102023008,
        250056313001000,
        250056102023020,
        250056313001002
    ],
    "zs:housing10":1251,
    "zs:label":"West Mansfield",
    "zs:pop10":3559
},
  "geometry": {"coordinates":[-71.261652,41.979378],"type":"Point"}
}