{
  "type": "Feature",
  "properties": {
    "gn:admin1_code":"IL",
    "gn:admin2_code":"31.0",
    "gn:admin3_code":"53676.0",
    "gn:asciiname":"Kingsport Court",
    "gn:country_code":"US",
    "gn:dem":211,
    "gn:elevation":"207.0",
    "gn:feature_class":"P",
    "gn:feature_code":"PPL",
    "gn:name":"Kingsport Court",
    "gn:population":0,
    "gn:timezone":"America/Chicago",
    "iso:country":"US",
    "wof:name":"Kingsport Court",
    "wof:placetype":"locality"
},
  "geometry": {"coordinates":[-87.855,42.12667],"type":"Point"}
}