{
  "type": "Feature",
  "properties": {
    "gn:admin1_code":"TX",
    "gn:admin2_code":"213.0",
    "gn:asciiname":"Shady Oaks",
    "gn:country_code":"US",
    "gn:dem":156,
    "gn:elevation":"152.0",
    "gn:feature_class":"P",
    "gn:feature_code":"PPL",
    "gn:name":"Shady Oaks",
    "gn:population":0,
    "gn:timezone":"America/Chicago",
    "iso:country":"US",
    "wof:name":"Shady Oaks",
    "wof:placetype":"locality"
},
  "geometry": {"coordinates":[-95.90246999999999,32.11654],"type":"Point"}
}