{
  "type": "Feature",
  "properties": {
    "gn:admin1_code":"NE",
    "gn:admin2_code":"17.0",
    "gn:asciiname":"Sandridge",
    "gn:country_code":"US",
    "gn:dem":784,
    "gn:elevation":"784.0",
    "gn:feature_class":"P",
    "gn:feature_code":"PPL",
    "gn:name":"Sandridge",
    "gn:population":0,
    "gn:timezone":"America/Chicago",
    "iso:country":"US",
    "name:ceb_x_preferred":[
        "Sandridge"
    ],
    "name:cym_x_preferred":[
        "Sandridge"
    ],
    "name:eng_x_preferred":[
        "Sandridge"
    ],
    "name:fas_x_preferred":[
        "\u0633\u0646\u0628\u0631\u06cc\u062c"
    ],
    "name:ita_x_preferred":[
        "Sandridge"
    ],
    "name:nld_x_preferred":[
        "Sandridge"
    ],
    "name:pol_x_preferred":[
        "Sandridge"
    ],
    "name:por_x_preferred":[
        "Sandridge"
    ],
    "name:swe_x_preferred":[
        "Sandridge"
    ],
    "name:und_x_variant":[
        "Sand Ridge"
    ],
    "wof:name":"Sandridge",
    "wof:placetype":"locality"
},
  "geometry": {"coordinates":[-99.94956999999999,42.55639],"type":"Point"}
}