{
  "type": "Feature",
  "properties": {
    "iso:country":"US",
    "name:bul_x_preferred":[
        "Hearthstone"
    ],
    "name:cat_x_preferred":[
        "Hearthstone"
    ],
    "name:ces_x_preferred":[
        "Hearthstone"
    ],
    "name:eng_x_preferred":[
        "Hearthstone"
    ],
    "name:fin_x_preferred":[
        "Hearthstone"
    ],
    "name:fra_x_preferred":[
        "Hearthstone"
    ],
    "name:heb_x_preferred":[
        "\u05d4\u05d0\u05e8\u05d8\u05e1\u05d8\u05d5\u05df"
    ],
    "name:jpn_x_preferred":[
        "\u30cf\u30fc\u30b9\u30b9\u30c8\u30fc\u30f3"
    ],
    "name:kor_x_preferred":[
        "\ud558\uc2a4\uc2a4\ud1a4"
    ],
    "name:lav_x_preferred":[
        "Hearthstone"
    ],
    "name:lit_x_preferred":[
        "Hearthstone"
    ],
    "name:pol_x_preferred":[
        "Hearthstone"
    ],
    "name:por_x_preferred":[
        "Hearthstone"
    ],
    "name:rus_x_preferred":[
        "Hearthstone"
    ],
    "name:srp_x_preferred":[
        "Hearthstone"
    ],
    "name:ukr_x_preferred":[
        "Hearthstone"
    ],
    "name:wuu_x_preferred":[
        "\u7089\u77f3\u4f20\u8bf4"
    ],
    "name:zho_x_preferred":[
        "\u7089\u77f3\u4f20\u8bf4"
    ],
    "wd:wordcount":61,
    "wof:name":"Hearthstone",
    "wof:placetype":"neighbourhood",
    "wof:population":285,
    "zs:area_m":835058.685504,
    "zs:blockids":[
        130570910051013,
        130570910051008
    ],
    "zs:housing10":90,
    "zs:label":"Hearthstone",
    "zs:pop10":285
},
  "geometry": {"coordinates":[-84.541686,34.100525],"type":"Point"}
}