{
  "type": "Feature",
  "properties": {
    "gn:admin1_code":"AL",
    "gn:admin2_code":"79",
    "gn:asciiname":"Lovettville",
    "gn:country_code":"US",
    "gn:dem":177,
    "gn:elevation":"181.0",
    "gn:feature_class":"P",
    "gn:feature_code":"PPL",
    "gn:name":"Lovettville",
    "gn:population":0,
    "gn:timezone":"America/Chicago",
    "iso:country":"US",
    "wof:name":"Lovettville",
    "wof:placetype":"locality"
},
  "geometry": {"coordinates":[-87.21056999999998,34.64898],"type":"Point"}
}