{
  "type": "Feature",
  "properties": {
    "gn:admin1_code":"NE",
    "gn:admin2_code":"71.0",
    "gn:asciiname":"Deverre",
    "gn:country_code":"US",
    "gn:dem":740,
    "gn:elevation":"741.0",
    "gn:feature_class":"P",
    "gn:feature_code":"PPL",
    "gn:name":"Deverre",
    "gn:population":0,
    "gn:timezone":"America/Chicago",
    "iso:country":"US",
    "wof:name":"Deverre",
    "wof:placetype":"locality"
},
  "geometry": {"coordinates":[-99.08704,41.89251],"type":"Point"}
}