{
  "type": "Feature",
  "properties": {
    "gn:admin1_code":"IL",
    "gn:admin2_code":"45",
    "gn:admin3_code":"30822.0",
    "gn:asciiname":"Conlogue",
    "gn:country_code":"US",
    "gn:dem":219,
    "gn:elevation":"219.0",
    "gn:feature_class":"P",
    "gn:feature_code":"PPL",
    "gn:name":"Conlogue",
    "gn:population":0,
    "gn:timezone":"America/Chicago",
    "iso:country":"US",
    "wof:name":"Conlogue",
    "wof:placetype":"locality"
},
  "geometry": {"coordinates":[-87.79308,39.59003],"type":"Point"}
}