{
  "type": "Feature",
  "properties": {
    "gn:admin1_code":"IL",
    "gn:admin2_code":"163.0",
    "gn:admin3_code":"49399.0",
    "gn:asciiname":"Roachtown",
    "gn:country_code":"US",
    "gn:dem":169,
    "gn:elevation":"165.0",
    "gn:feature_class":"P",
    "gn:feature_code":"PPL",
    "gn:name":"Roachtown",
    "gn:population":0,
    "gn:timezone":"America/Chicago",
    "iso:country":"US",
    "wof:name":"Roachtown",
    "wof:placetype":"locality"
},
  "geometry": {"coordinates":[-90.04094000000001,38.46311],"type":"Point"}
}