{
  "type": "Feature",
  "properties": {
    "gn:admin1_code":"TX",
    "gn:admin2_code":"83.0",
    "gn:asciiname":"Silver Valley",
    "gn:country_code":"US",
    "gn:dem":613,
    "gn:elevation":"615.0",
    "gn:feature_class":"P",
    "gn:feature_code":"PPL",
    "gn:name":"Silver Valley",
    "gn:population":0,
    "gn:timezone":"America/Chicago",
    "iso:country":"US",
    "name:ita_x_preferred":[
        "Silver Valley"
    ],
    "wof:name":"Silver Valley",
    "wof:placetype":"locality"
},
  "geometry": {"coordinates":[-99.54618000000001,31.95653],"type":"Point"}
}