{
  "type": "Feature",
  "properties": {
    "gn:admin1_code":"VA",
    "gn:admin2_code":"83",
    "gn:asciiname":"Wolf Trap",
    "gn:country_code":"US",
    "gn:dem":116,
    "gn:elevation":"111.0",
    "gn:feature_class":"P",
    "gn:feature_code":"PPL",
    "gn:name":"Wolf Trap",
    "gn:population":0,
    "gn:timezone":"America/New_York",
    "iso:country":"US",
    "name:ceb_x_preferred":[
        "Wolf Trap"
    ],
    "wof:name":"Wolf Trap",
    "wof:placetype":"locality"
},
  "geometry": {"coordinates":[-78.82862,36.71347],"type":"Point"}
}