{
  "type": "Feature",
  "properties": {
    "gn:country":"US",
    "gn:fcode":"PPL",
    "gn:population":0,
    "iso:country":"US",
    "qs_pg:aaroncc":"US",
    "qs_pg:gn_country":"US",
    "qs_pg:gn_fcode":"PPL",
    "qs_pg:gn_pop":0,
    "qs_pg:name":"Marys Corner",
    "qs_pg:name_adm0":"United States",
    "qs_pg:name_adm1":"Washington",
    "qs_pg:photos":140,
    "qs_pg:photos_1k":28,
    "qs_pg:photos_9k":1,
    "qs_pg:photos_9r":3,
    "qs_pg:photos_all":140,
    "qs_pg:photos_sr":3,
    "qs_pg:pop_sr":5,
    "qs_pg:qs_pg_placetype":"locality",
    "qs_pg:qs_pg_placetype_gp":"Town",
    "qs_pg:woe_adm0":23424977,
    "woe:adm0_id":23424977,
    "woe:name_adm0":"United States",
    "woe:name_adm1":"Washington",
    "woe:placetype":"Town",
    "wof:name":"Marys Corner",
    "wof:placetype":"locality"
},
  "geometry": {"coordinates":[-122.82262,46.54705],"type":"Point"}
}