{
  "type": "Feature",
  "properties": {
    "gn:admin1_code":"LA",
    "gn:admin2_code":"55.0",
    "gn:asciiname":"A and M Mobile Home Park",
    "gn:country_code":"US",
    "gn:dem":19,
    "gn:elevation":"12.0",
    "gn:feature_class":"P",
    "gn:feature_code":"PPL",
    "gn:name":"A and M Mobile Home Park",
    "gn:population":0,
    "gn:timezone":"America/Chicago",
    "iso:country":"US",
    "wof:name":"A and M Mobile Home Park",
    "wof:placetype":"campus"
},
  "geometry": {"coordinates":[-92.04451,30.32699],"type":"Point"}
}