{
  "type": "Feature",
  "properties": {
    "gn:admin1_code":"FL",
    "gn:admin2_code":"107.0",
    "gn:asciiname":"Georgetown",
    "gn:country_code":"US",
    "gn:dem":14,
    "gn:elevation":"7.0",
    "gn:feature_class":"P",
    "gn:feature_code":"PPL",
    "gn:name":"Georgetown",
    "gn:population":0,
    "gn:timezone":"America/New_York",
    "iso:country":"US",
    "name:azb_x_preferred":[
        "\u062c\u0631\u062c\u200c\u062a\u0627\u0648\u0646"
    ],
    "name:fas_x_preferred":[
        "\u062c\u0631\u062c\u200c\u062a\u0627\u0648\u0646"
    ],
    "name:spa_x_preferred":[
        "Georgetown"
    ],
    "name:urd_x_preferred":[
        "\u062c\u0627\u0631\u062c \u0679\u0627\u0624\u0646"
    ],
    "name:zho_x_preferred":[
        "\u55ac\u6cbb\u6566"
    ],
    "wof:name":"Georgetown",
    "wof:placetype":"locality"
},
  "geometry": {"coordinates":[-81.63869,29.39136],"type":"Point"}
}