{
  "type": "Feature",
  "properties": {
    "gn:admin1_code":"FL",
    "gn:admin2_code":"107.0",
    "gn:asciiname":"Georgetown",
    "gn:country_code":"US",
    "gn:dem":14,
    "gn:elevation":"7.0",
    "gn:feature_class":"P",
    "gn:feature_code":"PPL",
    "gn:name":"Georgetown",
    "gn:population":0,
    "gn:timezone":"America/New_York",
    "iso:country":"US",
    "name:ara_x_preferred":[
        "\u062c\u0648\u0631\u062c \u062a\u0627\u0648\u0646"
    ],
    "name:azb_x_preferred":[
        "\u062c\u0631\u062c\u200c\u062a\u0627\u0648\u0646"
    ],
    "name:ben_x_preferred":[
        "\u099c\u09b0\u09cd\u099c\u099f\u09be\u0989\u09a8"
    ],
    "name:ell_x_preferred":[
        "\u03a4\u03b6\u03cc\u03c1\u03c4\u03b6\u03c4\u03b1\u03bf\u03c5\u03bd"
    ],
    "name:fas_x_preferred":[
        "\u062c\u0631\u062c\u200c\u062a\u0627\u0648\u0646"
    ],
    "name:heb_x_preferred":[
        "\u05d2'\u05d5\u05e8\u05d2'\u05d8\u05d0\u05d5\u05df"
    ],
    "name:hin_x_preferred":[
        "\u091c\u0949\u0930\u094d\u091c\u091f\u093e\u0909\u0928"
    ],
    "name:hun_x_preferred":[
        "Georgetown"
    ],
    "name:ind_x_preferred":[
        "Georgetown"
    ],
    "name:ita_x_preferred":[
        "Georgetown"
    ],
    "name:kor_x_preferred":[
        "\uc870\uc9c0\ud0c0\uc6b4"
    ],
    "name:rus_x_preferred":[
        "\u0414\u0436\u043e\u0440\u0434\u0436\u0442\u0430\u0443\u043d"
    ],
    "name:spa_x_preferred":[
        "Georgetown"
    ],
    "name:tur_x_preferred":[
        "Georgetown"
    ],
    "name:ukr_x_preferred":[
        "\u0414\u0436\u043e\u0440\u0434\u0436\u0442\u0430\u0443\u043d"
    ],
    "name:urd_x_preferred":[
        "\u062c\u0627\u0631\u062c \u0679\u0627\u0624\u0646"
    ],
    "name:vie_x_preferred":[
        "Georgetown"
    ],
    "name:zho_cn_x_preferred":[
        "\u4e54\u6cbb\u6566"
    ],
    "name:zho_tw_x_preferred":[
        "\u55ac\u6cbb\u6566"
    ],
    "name:zho_x_preferred":[
        "\u55ac\u6cbb\u6566"
    ],
    "wof:name":"Georgetown",
    "wof:placetype":"locality"
},
  "geometry": {"coordinates":[-81.63869,29.39136],"type":"Point"}
}