{
  "type": "Feature",
  "properties": {
    "gn:admin1_code":"AZ",
    "gn:admin2_code":"19.0",
    "gn:asciiname":"Secundino",
    "gn:country_code":"US",
    "gn:dem":993,
    "gn:elevation":"993.0",
    "gn:feature_class":"P",
    "gn:feature_code":"PPL",
    "gn:name":"Secundino",
    "gn:population":0,
    "gn:timezone":"America/Phoenix",
    "iso:country":"US",
    "wof:name":"Secundino",
    "wof:placetype":"locality"
},
  "geometry": {"coordinates":[-111.44288,31.69398],"type":"Point"}
}