{
  "type": "Feature",
  "properties": {
    "gn:admin1_code":"ID",
    "gn:admin2_code":"35.0",
    "gn:asciiname":"Best Corner",
    "gn:country_code":"US",
    "gn:dem":963,
    "gn:elevation":"962.0",
    "gn:feature_class":"P",
    "gn:feature_code":"PPL",
    "gn:name":"Best Corner",
    "gn:population":0,
    "gn:timezone":"America/Los_Angeles",
    "iso:country":"US",
    "wof:name":"Best Corner",
    "wof:placetype":"locality"
},
  "geometry": {"coordinates":[-116.1507,46.56185],"type":"Point"}
}