{
  "type": "Feature",
  "properties": {
    "gn:country":"US",
    "gn:fcode":"PPL",
    "gn:population":0,
    "iso:country":"US",
    "name:bar_x_preferred":[
        "Hillside"
    ],
    "name:ceb_x_preferred":[
        "Hillside"
    ],
    "name:cym_x_preferred":[
        "Hillside"
    ],
    "name:deu_x_preferred":[
        "Hillside"
    ],
    "name:ita_x_preferred":[
        "Hillside"
    ],
    "name:mlg_x_preferred":[
        "Hillside"
    ],
    "name:nld_x_preferred":[
        "Hillside"
    ],
    "name:pol_x_preferred":[
        "Hillside"
    ],
    "name:por_x_preferred":[
        "Hillside"
    ],
    "name:srp_x_preferred":[
        "\u0425\u0438\u043b\u0441\u0430\u0458\u0434"
    ],
    "name:swe_x_preferred":[
        "Hillside"
    ],
    "name:ukr_x_preferred":[
        "\u0413\u0456\u043b\u043b\u0441\u0430\u0439\u0434"
    ],
    "name:vol_x_preferred":[
        "Hillside"
    ],
    "qs_pg:aaroncc":"US",
    "qs_pg:gn_country":"US",
    "qs_pg:gn_fcode":"PPL",
    "qs_pg:gn_pop":0,
    "qs_pg:name":"Hillside",
    "qs_pg:name_adm0":"United States",
    "qs_pg:name_adm1":"New York",
    "qs_pg:photos":1,
    "qs_pg:photos_1k":1,
    "qs_pg:photos_9k":1,
    "qs_pg:photos_9r":1,
    "qs_pg:photos_all":1,
    "qs_pg:photos_sr":1,
    "qs_pg:pop_sr":0,
    "qs_pg:qs_pg_placetype":"neighbourhood",
    "qs_pg:qs_pg_placetype_gp":"Suburb",
    "qs_pg:woe_adm0":23424977,
    "woe:adm0_id":23424977,
    "woe:name_adm0":"United States",
    "woe:name_adm1":"New York",
    "woe:placetype":"Suburb",
    "wof:name":"Hillside",
    "wof:placetype":"neighbourhood"
},
  "geometry": {"coordinates":[-75.3874,43.35701],"type":"Point"}
}