{
  "type": "Feature",
  "properties": {
    "gn:admin1_code":"NC",
    "gn:admin2_code":"147.0",
    "gn:admin3_code":"94072.0",
    "gn:asciiname":"Redallia",
    "gn:country_code":"US",
    "gn:dem":20,
    "gn:elevation":"19.0",
    "gn:feature_class":"P",
    "gn:feature_code":"PPL",
    "gn:name":"Redallia",
    "gn:population":0,
    "gn:timezone":"America/New_York",
    "iso:country":"US",
    "name:eng_x_preferred":[
        "Redallia"
    ],
    "name:und_x_variant":[
        "Redalia",
        "Redalir"
    ],
    "wof:name":"Redallia",
    "wof:placetype":"locality"
},
  "geometry": {"coordinates":[-77.37635,35.48488],"type":"Point"}
}