{
  "type": "Feature",
  "properties": {
    "iso:country":"US",
    "name:eng_x_preferred":[
        "Soda Creek Highlands"
    ],
    "wof:name":"Soda Creek Highlands",
    "wof:placetype":"neighbourhood",
    "wof:population":119,
    "zs:area_m":100590472.656849,
    "zs:blockids":[
        81070001001171,
        81070001001135,
        81070001001142
    ],
    "zs:housing10":75,
    "zs:label":"Soda Creek Highlands",
    "zs:pop10":119
},
  "geometry": {"coordinates":[-106.788229,40.568045],"type":"Point"}
}