{
  "type": "Feature",
  "properties": {
    "gn:admin1_code":"TX",
    "gn:admin2_code":"125.0",
    "gn:asciiname":"Gilpin",
    "gn:country_code":"US",
    "gn:dem":654,
    "gn:elevation":"652.0",
    "gn:feature_class":"P",
    "gn:feature_code":"PPL",
    "gn:name":"Gilpin",
    "gn:population":0,
    "gn:timezone":"America/Chicago",
    "iso:country":"US",
    "name:deu_x_preferred":[
        "Gilpin"
    ],
    "name:fra_x_preferred":[
        "Gilpin"
    ],
    "name:ita_x_preferred":[
        "Gilpin"
    ],
    "name:nld_x_preferred":[
        "Gilpin"
    ],
    "name:pol_x_preferred":[
        "Gilpin"
    ],
    "name:rus_x_preferred":[
        "\u0413\u0438\u043b\u043f\u0438\u043d"
    ],
    "wof:name":"Gilpin",
    "wof:placetype":"locality"
},
  "geometry": {"coordinates":[-100.71651,33.41509],"type":"Point"}
}