{
  "type": "Feature",
  "properties": {
    "gn:admin1_code":"MD",
    "gn:admin2_code":"47.0",
    "gn:asciiname":"Sea Isle Mobile Home Park",
    "gn:country_code":"US",
    "gn:dem":6,
    "gn:elevation":"3.0",
    "gn:feature_class":"P",
    "gn:feature_code":"PPL",
    "gn:name":"Sea Isle Mobile Home Park",
    "gn:population":0,
    "gn:timezone":"America/New_York",
    "iso:country":"US",
    "wof:name":"Sea Isle Mobile Home Park",
    "wof:placetype":"campus"
},
  "geometry": {"coordinates":[-75.11018,38.33595],"type":"Point"}
}