{
  "type": "Feature",
  "properties": {
    "gn:admin1_code":"NC",
    "gn:admin2_code":"29.0",
    "gn:admin3_code":"92920.0",
    "gn:asciiname":"Smiths Corner",
    "gn:country_code":"US",
    "gn:dem":2,
    "gn:elevation":"2.0",
    "gn:feature_class":"P",
    "gn:feature_code":"PPL",
    "gn:name":"Smiths Corner",
    "gn:population":0,
    "gn:timezone":"America/New_York",
    "iso:country":"US",
    "wof:name":"Smiths Corner",
    "wof:placetype":"locality"
},
  "geometry": {"coordinates":[-76.06493,36.30127],"type":"Point"}
}