{
  "type": "Feature",
  "properties": {
    "gn:admin1_code":"SD",
    "gn:admin2_code":"47.0",
    "gn:admin3_code":"45560.0",
    "gn:asciiname":"Smithwick",
    "gn:country_code":"US",
    "gn:dem":991,
    "gn:elevation":"989.0",
    "gn:feature_class":"P",
    "gn:feature_code":"PPL",
    "gn:name":"Smithwick",
    "gn:population":0,
    "gn:timezone":"America/Denver",
    "iso:country":"US",
    "wof:name":"Smithwick",
    "wof:placetype":"locality"
},
  "geometry": {"coordinates":[-103.21825,43.30137],"type":"Point"}
}