{
  "type": "Feature",
  "properties": {
    "gn:admin1_code":"WV",
    "gn:admin2_code":"87",
    "gn:asciiname":"Clio",
    "gn:country_code":"US",
    "gn:dem":234,
    "gn:elevation":"226.0",
    "gn:feature_class":"P",
    "gn:feature_code":"PPL",
    "gn:name":"Clio",
    "gn:population":0,
    "gn:timezone":"America/New_York",
    "iso:country":"US",
    "wof:name":"Clio",
    "wof:placetype":"locality"
},
  "geometry": {"coordinates":[-81.30123,38.58121],"type":"Point"}
}