{
  "type": "Feature",
  "properties": {
    "iso:country":"US",
    "name:eng_x_preferred":[
        "Ivy Creek"
    ],
    "qs:gn_adm0_cc":"US",
    "qs:gn_local":4499359,
    "qs:gn_nam_loc":"Willow Springs, Wake, North Carolina, US",
    "qs:gn_namadm1":"NC",
    "qs:local_max":387,
    "qs:local_sum":601,
    "qs:localhoods":2,
    "qs:name":"Ivy Creek",
    "qs:name_adm0":"United States",
    "qs:name_adm1":"North Carolina",
    "qs:name_adm2":"Wake",
    "qs:name_local":"Willow Springs",
    "qs:photo_max":245,
    "qs:photo_sum":387,
    "qs:placetype":"Suburb",
    "qs:quad_count":6,
    "qs:woe_adm0":23424977,
    "qs:woe_adm1":2347592,
    "qs:woe_adm2":12589465,
    "qs:woe_lau":0,
    "qs:woe_local":2521204,
    "qs:woe_ver":"7.10.0",
    "wof:name":"Ivy Creek",
    "wof:placetype":"neighbourhood",
    "wof:population":1038,
    "zs:blockids":[
        371830531082053,
        371830531082051,
        371830531082054,
        371830531082082,
        371830531071045,
        371830531071052,
        371830531082081,
        371830531082052,
        371830531082055,
        371830531082060,
        371830531082063,
        371830531082057,
        371830531082056
    ],
    "zs:housing10":346,
    "zs:pop10":1038
},
  "geometry": {"coordinates":[-78.756426,35.542243],"type":"Point"}
}