{
  "type": "Feature",
  "properties": {
    "gn:admin1_code":"KY",
    "gn:admin2_code":"155",
    "gn:asciiname":"Phillipsburg",
    "gn:country_code":"US",
    "gn:dem":218,
    "gn:elevation":"216.0",
    "gn:feature_class":"P",
    "gn:feature_code":"PPL",
    "gn:name":"Phillipsburg",
    "gn:population":0,
    "gn:timezone":"America/New_York",
    "iso:country":"US",
    "name:bre_x_preferred":[
        "Phillipsburg"
    ],
    "name:cat_x_preferred":[
        "Phillipsburg"
    ],
    "name:ceb_x_preferred":[
        "Phillipsburg"
    ],
    "name:deu_x_preferred":[
        "Phillipsburg"
    ],
    "name:fra_x_preferred":[
        "Phillipsburg"
    ],
    "name:ita_x_preferred":[
        "Phillipsburg"
    ],
    "name:nld_x_preferred":[
        "Phillipsburg"
    ],
    "name:nor_x_preferred":[
        "Phillipsburg"
    ],
    "name:pol_x_preferred":[
        "Phillipsburg"
    ],
    "name:por_x_preferred":[
        "Phillipsburg"
    ],
    "name:spa_x_preferred":[
        "Phillipsburg"
    ],
    "name:srp_x_preferred":[
        "\u0424\u0438\u043b\u0438\u043f\u0441\u0431\u0443\u0440\u0433"
    ],
    "name:swe_x_preferred":[
        "Phillipsburg"
    ],
    "name:vol_x_preferred":[
        "Phillipsburg"
    ],
    "wof:name":"Phillipsburg",
    "wof:placetype":"locality"
},
  "geometry": {"coordinates":[-85.25995999999998,37.45645],"type":"Point"}
}