{
  "type": "Feature",
  "properties": {
    "gn:admin1_code":"IL",
    "gn:admin2_code":"31.0",
    "gn:admin3_code":"42808.0",
    "gn:asciiname":"Sag Bridge",
    "gn:country_code":"US",
    "gn:dem":193,
    "gn:elevation":"190.0",
    "gn:feature_class":"P",
    "gn:feature_code":"PPL",
    "gn:name":"Sag Bridge",
    "gn:population":0,
    "gn:timezone":"America/Chicago",
    "iso:country":"US",
    "wof:name":"Sag Bridge",
    "wof:placetype":"locality"
},
  "geometry": {"coordinates":[-87.93311,41.68836],"type":"Point"}
}