{
  "type": "Feature",
  "properties": {
    "gn:admin1_code":"IL",
    "gn:admin2_code":"89.0",
    "gn:asciiname":"Knoll Creek West",
    "gn:country_code":"US",
    "gn:dem":234,
    "gn:elevation":"229.0",
    "gn:feature_class":"P",
    "gn:feature_code":"PPL",
    "gn:name":"Knoll Creek West",
    "gn:population":0,
    "gn:timezone":"America/Chicago",
    "iso:country":"US",
    "wof:name":"Knoll Creek West",
    "wof:placetype":"locality"
},
  "geometry": {"coordinates":[-88.35647,41.93031],"type":"Point"}
}