{
  "type": "Feature",
  "properties": {
    "gn:admin1_code":"UT",
    "gn:admin2_code":"35.0",
    "gn:asciiname":"Harvest Lane Condo",
    "gn:country_code":"US",
    "gn:dem":1381,
    "gn:elevation":"1378.0",
    "gn:feature_class":"P",
    "gn:feature_code":"PPL",
    "gn:name":"Harvest Lane Condo",
    "gn:population":0,
    "gn:timezone":"America/Denver",
    "iso:country":"US",
    "wof:name":"Harvest Lane Condo",
    "wof:placetype":"locality"
},
  "geometry": {"coordinates":[-111.86993,40.58967],"type":"Point"}
}