{
  "type": "Feature",
  "properties": {
    "gn:admin1_code":"CA",
    "gn:admin2_code":"115.0",
    "gn:asciiname":"Oak Valley",
    "gn:country_code":"US",
    "gn:dem":933,
    "gn:elevation":"918.0",
    "gn:feature_class":"P",
    "gn:feature_code":"PPL",
    "gn:name":"Oak Valley",
    "gn:population":0,
    "gn:timezone":"America/Los_Angeles",
    "iso:country":"US",
    "name:fas_x_preferred":[
        "\u0627\u0648\u06a9 \u0648\u0644\u06cc"
    ],
    "name:urd_x_preferred":[
        "\u0627\u0648\u06a9 \u0648\u06cc\u0644\u06cc"
    ],
    "name:zho_x_preferred":[
        "\u5967\u514b\u8c37"
    ],
    "wof:name":"Oak Valley",
    "wof:placetype":"locality"
},
  "geometry": {"coordinates":[-121.03801,39.4985],"type":"Point"}
}