{
  "type": "Feature",
  "properties": {
    "gn:admin1_code":"IN",
    "gn:admin2_code":"5.0",
    "gn:admin3_code":"31612.0",
    "gn:asciiname":"Bethany",
    "gn:country_code":"US",
    "gn:dem":273,
    "gn:elevation":"273.0",
    "gn:feature_class":"P",
    "gn:feature_code":"PPL",
    "gn:name":"Bethany",
    "gn:population":0,
    "gn:timezone":"America/Indiana/Indianapolis",
    "iso:country":"US",
    "name:afr_x_preferred":[
        "Betani\u00eb"
    ],
    "name:ara_x_preferred":[
        "\u0628\u064a\u062a \u0639\u0628\u0631\u0629"
    ],
    "name:bel_x_preferred":[
        "\u0412\u0456\u0444\u0430\u043d\u0456\u044f"
    ],
    "name:cat_x_preferred":[
        "Bet\u00e0nia"
    ],
    "name:ces_x_preferred":[
        "Bet\u00e1nie"
    ],
    "name:deu_x_preferred":[
        "Bethanien"
    ],
    "name:ell_x_preferred":[
        "\u0392\u03b7\u03b8\u03b1\u03bd\u03af\u03b1"
    ],
    "name:eng_x_preferred":[
        "Bethany"
    ],
    "name:fin_x_preferred":[
        "Betania"
    ],
    "name:fra_x_preferred":[
        "B\u00e9thanie"
    ],
    "name:fry_x_preferred":[
        "Betani\u00eb"
    ],
    "name:heb_x_preferred":[
        "\u05d1\u05d9\u05ea \u05e2\u05e0\u05d9\u05d4"
    ],
    "name:hun_x_preferred":[
        "Bet\u00e1nia"
    ],
    "name:ind_x_preferred":[
        "Betania"
    ],
    "name:ita_x_preferred":[
        "Betania"
    ],
    "name:jpn_x_preferred":[
        "\u30d9\u30bf\u30cb\u30a2"
    ],
    "name:kor_x_preferred":[
        "\ubca0\ud0c0\ub2c8\uc544"
    ],
    "name:nld_x_preferred":[
        "Bethani\u00eb"
    ],
    "name:nor_x_preferred":[
        "Betania"
    ],
    "name:por_x_preferred":[
        "Bet\u00e2nia"
    ],
    "name:rus_x_preferred":[
        "\u0412\u0438\u0444\u0430\u043d\u0438\u044f"
    ],
    "name:spa_x_preferred":[
        "Betania"
    ],
    "name:swe_x_preferred":[
        "Betania"
    ],
    "name:tam_x_preferred":[
        "\u0baa\u0bc6\u0ba4\u0bcd\u0ba4\u0bbe\u0ba9\u0bbf\u0baf\u0bbe"
    ],
    "name:ukr_x_preferred":[
        "\u0412\u0456\u0444\u0430\u043d\u0456\u044f"
    ],
    "name:und_x_variant":[
        "South Bethany"
    ],
    "name:urd_x_preferred":[
        "\u0628\u06cc\u062a \u0639\u0646\u06cc\u0627\u06c1"
    ],
    "name:wol_x_preferred":[
        "Betani"
    ],
    "name:zho_x_preferred":[
        "\u4f2f\u5927\u5c3c"
    ],
    "wof:name":"Bethany",
    "wof:placetype":"locality"
},
  "geometry": {"coordinates":[-86.06527,39.17394],"type":"Point"}
}