{
  "type": "Feature",
  "properties": {
    "gn:admin1_code":"SC",
    "gn:admin2_code":"27.0",
    "gn:asciiname":"Central Crossroads",
    "gn:country_code":"US",
    "gn:dem":33,
    "gn:elevation":"31.0",
    "gn:feature_class":"P",
    "gn:feature_code":"PPL",
    "gn:name":"Central Crossroads",
    "gn:population":0,
    "gn:timezone":"America/New_York",
    "iso:country":"US",
    "name:eng_x_preferred":[
        "Central Crossroads"
    ],
    "name:und_x_variant":[
        "Central"
    ],
    "wof:name":"Central Crossroads",
    "wof:placetype":"locality"
},
  "geometry": {"coordinates":[-79.91285000000001,33.88794],"type":"Point"}
}