{
  "type": "Feature",
  "properties": {
    "iso:country":"US",
    "name:eng_x_preferred":[
        "Tuxedo Heights"
    ],
    "wof:name":"Tuxedo Heights",
    "wof:placetype":"neighbourhood",
    "wof:population":38,
    "zs:area_m":121600.319454,
    "zs:blockids":[
        10730012001039,
        10730012001040,
        10730012001095,
        10730012001067,
        10730012001069,
        10730012001048,
        10730012001092,
        10730012001041,
        10730012001093,
        10730012001050,
        10730012001051,
        10730012001068,
        10730012001094,
        10730012001049
    ],
    "zs:housing10":20,
    "zs:label":"Tuxedo Heights",
    "zs:pop10":38
},
  "geometry": {"coordinates":[-86.851364,33.529379],"type":"Point"}
}