{
  "type": "Feature",
  "properties": {
    "gn:admin1_code":"NH",
    "gn:admin2_code":"7.0",
    "gn:admin3_code":"30260.0",
    "gn:asciiname":"Upper Village",
    "gn:country_code":"US",
    "gn:dem":247,
    "gn:elevation":"246.0",
    "gn:feature_class":"P",
    "gn:feature_code":"PPL",
    "gn:name":"Upper Village",
    "gn:population":0,
    "gn:timezone":"America/New_York",
    "iso:country":"US",
    "wof:name":"Upper Village",
    "wof:placetype":"locality"
},
  "geometry": {"coordinates":[-71.19508,44.39812],"type":"Point"}
}