{
  "type": "Feature",
  "properties": {
    "gn:admin1_code":"GA",
    "gn:admin2_code":"303.0",
    "gn:asciiname":"Heidrich",
    "gn:country_code":"US",
    "gn:dem":100,
    "gn:elevation":"91.0",
    "gn:feature_class":"P",
    "gn:feature_code":"PPL",
    "gn:name":"Heidrich",
    "gn:population":0,
    "gn:timezone":"America/New_York",
    "iso:country":"US",
    "wof:name":"Heidrich",
    "wof:placetype":"locality"
},
  "geometry": {"coordinates":[-82.65097,32.97654],"type":"Point"}
}