{
  "type": "Feature",
  "properties": {
    "iso:country":"US",
    "name:eng_x_preferred":[
        "Las Americas"
    ],
    "wof:name":"Las Americas",
    "wof:placetype":"neighbourhood",
    "wof:population":1796,
    "zs:area_m":1627480.096776,
    "zs:blockids":[
        350490012032043,
        350490012023010,
        350490011062008,
        350490012023009,
        350490012023013,
        350490011062000,
        350490012021053,
        350490012022006,
        350490011061013,
        350490011062003,
        350490012023036,
        350490012021054,
        350490012022012,
        350490012022009,
        350490012023014,
        350490012022005,
        350490012022007,
        350490012023031,
        350490012022004,
        350490012023016,
        350490012022010,
        350490012023032,
        350490011062002,
        350490012023011,
        350490012022008,
        350490012022003,
        350490011062001,
        350490012023015,
        350490011061027,
        350490012023008
    ],
    "zs:housing10":898,
    "zs:label":"Las Americas",
    "zs:pop10":1796
},
  "geometry": {"coordinates":[-106.007214,35.649549],"type":"Point"}
}