{
  "type": "Feature",
  "properties": {
    "iso:country":"US",
    "name:ara_x_preferred":[
        "\u0631\u0648\u0632\u0641\u0644\u062a"
    ],
    "name:bak_x_preferred":[
        "\u0420\u0443\u0437\u0432\u0435\u043b\u044c\u0442"
    ],
    "name:bel_x_preferred":[
        "\u0420\u0443\u0437\u0432\u0435\u043b\u044c\u0442"
    ],
    "name:cat_x_preferred":[
        "Roosevelt"
    ],
    "name:ceb_x_preferred":[
        "Roosevelt"
    ],
    "name:ces_x_preferred":[
        "Roosevelt"
    ],
    "name:dan_x_preferred":[
        "Roosevelt"
    ],
    "name:deu_x_preferred":[
        "Roosevelt"
    ],
    "name:ell_x_preferred":[
        "\u03a1\u03bf\u03cd\u03b6\u03b2\u03b5\u03bb\u03c4"
    ],
    "name:eng_x_preferred":[
        "Roosevelt"
    ],
    "name:epo_x_preferred":[
        "Roosevelt"
    ],
    "name:eus_x_preferred":[
        "Roosevelt"
    ],
    "name:fas_x_preferred":[
        "\u0631\u0648\u0632\u0648\u0644\u062a"
    ],
    "name:fin_x_preferred":[
        "Roosevelt"
    ],
    "name:fra_x_preferred":[
        "Roosevelt"
    ],
    "name:glg_x_preferred":[
        "Roosevelt"
    ],
    "name:heb_x_preferred":[
        "\u05e8\u05d5\u05d6\u05d5\u05d5\u05dc\u05d8"
    ],
    "name:hrv_x_preferred":[
        "Roosevelt"
    ],
    "name:hun_x_preferred":[
        "Roosevelt"
    ],
    "name:hye_x_preferred":[
        "\u054c\u0578\u0582\u0566\u057e\u0565\u056c\u057f"
    ],
    "name:ita_x_preferred":[
        "Roosevelt"
    ],
    "name:jpn_x_preferred":[
        "\u30eb\u30fc\u30ba\u30d9\u30eb\u30c8"
    ],
    "name:kor_x_preferred":[
        "\ub8e8\uc2a4\ubca8\ud2b8"
    ],
    "name:lav_x_preferred":[
        "R\u016bzvelts"
    ],
    "name:lit_x_preferred":[
        "Ruzveltas"
    ],
    "name:nds_x_preferred":[
        "Roosevelt"
    ],
    "name:nld_x_preferred":[
        "Roosevelt"
    ],
    "name:nno_x_preferred":[
        "Roosevelt"
    ],
    "name:nor_x_preferred":[
        "Roosevelt"
    ],
    "name:pol_x_preferred":[
        "Roosevelt"
    ],
    "name:por_x_preferred":[
        "Roosevelt"
    ],
    "name:ron_x_preferred":[
        "Roosevelt"
    ],
    "name:rus_x_preferred":[
        "\u0420\u0443\u0437\u0432\u0435\u043b\u044c\u0442"
    ],
    "name:slk_x_preferred":[
        "Roosevelt"
    ],
    "name:spa_x_preferred":[
        "Roosevelt"
    ],
    "name:srp_x_preferred":[
        "\u0420\u0443\u0437\u0432\u0435\u043b\u0442"
    ],
    "name:swa_x_preferred":[
        "Roosevelt"
    ],
    "name:tha_x_preferred":[
        "\u0e23\u0e39\u0e2a\u0e40\u0e27\u0e25\u0e15\u0e4c"
    ],
    "name:tur_x_preferred":[
        "Roosevelt"
    ],
    "name:ukr_x_preferred":[
        "\u0420\u0443\u0437\u0432\u0435\u043b\u044c\u0442"
    ],
    "name:vol_x_preferred":[
        "Roosevelt"
    ],
    "name:zho_x_preferred":[
        "\u7f57\u65af\u798f"
    ],
    "wof:name":"Roosevelt",
    "wof:placetype":"neighbourhood",
    "wof:population":373
},
  "geometry": {"coordinates":[-86.92695058838197,33.44046780791186],"type":"Point"}
}