{
  "type": "Feature",
  "properties": {
    "iso:country":"US",
    "name:ceb_x_preferred":[
        "Edgemont"
    ],
    "name:deu_x_preferred":[
        "Edgemont"
    ],
    "name:eng_x_preferred":[
        "Edgemont"
    ],
    "name:pol_x_preferred":[
        "Edgemont"
    ],
    "name:spa_x_preferred":[
        "Edgemont"
    ],
    "name:srp_x_preferred":[
        "\u0415\u045f\u043c\u043e\u043d\u0442"
    ],
    "name:ukr_x_preferred":[
        "\u0415\u0434\u0436\u043c\u043e\u043d\u0442"
    ],
    "wof:name":"Edgemont",
    "wof:placetype":"neighbourhood",
    "wof:population":273,
    "zs:area_m":262686.998894,
    "zs:blockids":[
        490351126041001,
        490351126041004,
        490351126041007,
        490351126132028
    ],
    "zs:housing10":85,
    "zs:label":"Edgemont",
    "zs:pop10":273
},
  "geometry": {"coordinates":[-111.854508,40.574964],"type":"Point"}
}