{
  "type": "Feature",
  "properties": {
    "iso:country":"US",
    "name:eng_x_preferred":[
        "Mirramont"
    ],
    "qs:gn_adm0_cc":"US",
    "qs:gn_local":4231874,
    "qs:gn_nam_loc":"Woodstock, Cherokee, Georgia, US",
    "qs:gn_namadm1":"GA",
    "qs:local_max":2462,
    "qs:local_sum":4587,
    "qs:localhoods":35,
    "qs:name":"Mirramont",
    "qs:name_adm0":"United States",
    "qs:name_adm1":"Georgia",
    "qs:name_adm2":"Cherokee",
    "qs:name_local":"Woodstock",
    "qs:photo_max":2,
    "qs:photo_sum":3,
    "qs:placetype":"Suburb",
    "qs:quad_count":2,
    "qs:woe_adm0":23424977,
    "qs:woe_adm1":2347569,
    "qs:woe_adm2":12587897,
    "qs:woe_lau":0,
    "qs:woe_local":2523748,
    "qs:woe_ver":"7.10.0",
    "wof:lang":[
        "eng"
    ],
    "wof:name":"Mirramont",
    "wof:placetype":"neighbourhood"
},
  "geometry": {"coordinates":[-84.58648700000001,34.120141],"type":"Point"}
}