{
  "type": "Feature",
  "properties": {
    "gn:admin1_code":"LA",
    "gn:admin2_code":"101.0",
    "gn:asciiname":"Richland",
    "gn:country_code":"US",
    "gn:dem":5,
    "gn:elevation":"2.0",
    "gn:feature_class":"P",
    "gn:feature_code":"PPL",
    "gn:name":"Richland",
    "gn:population":0,
    "gn:timezone":"America/Chicago",
    "iso:country":"US",
    "name:ara_x_preferred":[
        "\u0631\u064a\u062a\u0634\u0644\u0627\u0646\u062f"
    ],
    "name:cat_x_preferred":[
        "Richland"
    ],
    "name:ceb_x_preferred":[
        "Richland"
    ],
    "name:deu_x_preferred":[
        "Richland"
    ],
    "name:fra_x_preferred":[
        "Richland"
    ],
    "name:hun_x_preferred":[
        "Richland"
    ],
    "name:ita_x_preferred":[
        "Richland"
    ],
    "name:kor_x_preferred":[
        "\ub9ac\uce60\ub79c\ub4dc"
    ],
    "name:nld_x_preferred":[
        "Richland"
    ],
    "name:pol_x_preferred":[
        "Richland"
    ],
    "name:por_x_preferred":[
        "Richland"
    ],
    "name:rus_x_preferred":[
        "\u0420\u0438\u0447\u043b\u0435\u043d\u0434"
    ],
    "name:slk_x_preferred":[
        "Richland"
    ],
    "name:spa_x_preferred":[
        "Richland"
    ],
    "name:srp_x_preferred":[
        "\u0420\u0438\u0447\u043b\u0430\u043d\u0434"
    ],
    "name:swe_x_preferred":[
        "Richland"
    ],
    "name:ukr_x_preferred":[
        "\u0420\u0438\u0447\u043b\u0435\u043d\u0434"
    ],
    "name:urd_x_preferred":[
        "\u0631\u0686\u0644\u06cc\u0646\u0688"
    ],
    "name:vol_x_preferred":[
        "Richland"
    ],
    "wof:name":"Richland",
    "wof:placetype":"locality"
},
  "geometry": {"coordinates":[-91.69512,29.78632],"type":"Point"}
}