{
  "type": "Feature",
  "properties": {
    "gn:admin1_code":"TN",
    "gn:admin2_code":"37.0",
    "gn:asciiname":"Cane Ridge",
    "gn:country_code":"US",
    "gn:dem":192,
    "gn:elevation":"194.0",
    "gn:feature_class":"P",
    "gn:feature_code":"PPL",
    "gn:name":"Cane Ridge",
    "gn:population":0,
    "gn:timezone":"America/Chicago",
    "iso:country":"US",
    "wof:name":"Cane Ridge",
    "wof:placetype":"locality"
},
  "geometry": {"coordinates":[-86.64419000000002,36.02285999999999],"type":"Point"}
}