{
  "type": "Feature",
  "properties": {
    "gn:admin1_code":"WA",
    "gn:admin2_code":"5.0",
    "gn:asciiname":"East White Bluffs",
    "gn:country_code":"US",
    "gn:dem":117,
    "gn:elevation":"120.0",
    "gn:feature_class":"P",
    "gn:feature_code":"PPL",
    "gn:name":"East White Bluffs",
    "gn:population":0,
    "gn:timezone":"America/Los_Angeles",
    "iso:country":"US",
    "wof:name":"East White Bluffs",
    "wof:placetype":"locality"
},
  "geometry": {"coordinates":[-119.46114,46.67347],"type":"Point"}
}