{
  "type": "Feature",
  "properties": {
    "gn:admin1_code":"MD",
    "gn:admin2_code":"21.0",
    "gn:asciiname":"Kittyhawk Estates",
    "gn:country_code":"US",
    "gn:dem":204,
    "gn:elevation":"207.0",
    "gn:feature_class":"P",
    "gn:feature_code":"PPL",
    "gn:name":"Kittyhawk Estates",
    "gn:population":0,
    "gn:timezone":"America/New_York",
    "iso:country":"US",
    "wof:name":"Kittyhawk Estates",
    "wof:placetype":"locality"
},
  "geometry": {"coordinates":[-77.22915,39.33233],"type":"Point"}
}