{
  "type": "Feature",
  "properties": {
    "gn:admin1_code":"NY",
    "gn:admin2_code":"101.0",
    "gn:admin3_code":"35683.0",
    "gn:asciiname":"Pine Knoll Mobile Home Park",
    "gn:country_code":"US",
    "gn:dem":367,
    "gn:elevation":"366.0",
    "gn:feature_class":"P",
    "gn:feature_code":"PPL",
    "gn:name":"Pine Knoll Mobile Home Park",
    "gn:population":0,
    "gn:timezone":"America/New_York",
    "iso:country":"US",
    "wof:name":"Pine Knoll Mobile Home Park",
    "wof:placetype":"campus"
},
  "geometry": {"coordinates":[-77.71173,42.40251],"type":"Point"}
}