{
  "type": "Feature",
  "properties": {
    "gn:admin1_code":"TX",
    "gn:admin2_code":"249",
    "gn:asciiname":"Gallimore Addition Colonia",
    "gn:country_code":"US",
    "gn:dem":72,
    "gn:elevation":"67.0",
    "gn:feature_class":"P",
    "gn:feature_code":"PPL",
    "gn:name":"Gallimore Addition Colonia",
    "gn:population":0,
    "gn:timezone":"America/Chicago",
    "iso:country":"US",
    "wof:name":"Gallimore Addition Colonia",
    "wof:placetype":"locality"
},
  "geometry": {"coordinates":[-98.09833999999999,27.73919],"type":"Point"}
}