{
  "type": "Feature",
  "properties": {
    "gn:admin1_code":"VA",
    "gn:admin2_code":"161",
    "gn:asciiname":"Pinkard Court",
    "gn:country_code":"US",
    "gn:dem":358,
    "gn:elevation":"353.0",
    "gn:feature_class":"P",
    "gn:feature_code":"PPL",
    "gn:name":"Pinkard Court",
    "gn:population":0,
    "gn:timezone":"America/New_York",
    "iso:country":"US",
    "wof:name":"Pinkard Court",
    "wof:placetype":"locality"
},
  "geometry": {"coordinates":[-79.9717,37.22375],"type":"Point"}
}