{
  "type": "Feature",
  "properties": {
    "gn:admin1_code":"KS",
    "gn:admin2_code":"95.0",
    "gn:admin3_code":"72175.0",
    "gn:asciiname":"Calista",
    "gn:country_code":"US",
    "gn:dem":490,
    "gn:elevation":"485.0",
    "gn:feature_class":"P",
    "gn:feature_code":"PPL",
    "gn:name":"Calista",
    "gn:population":0,
    "gn:timezone":"America/Chicago",
    "iso:country":"US",
    "name:eng_x_preferred":[
        "Calista"
    ],
    "name:und_x_variant":[
        "Maud"
    ],
    "wof:name":"Calista",
    "wof:placetype":"locality"
},
  "geometry": {"coordinates":[-98.28257000000001,37.63974],"type":"Point"}
}