{
  "type": "Feature",
  "properties": {
    "iso:country":"US",
    "name:eng_x_preferred":[
        "Downtown River Corridor"
    ],
    "wof:name":"Downtown River Corridor",
    "wof:placetype":"neighbourhood",
    "wof:population":54,
    "zs:area_m":235217.711451,
    "zs:blockids":[
        80690013061078,
        80690013061080,
        80690013061079,
        80690001002005
    ],
    "zs:housing10":0,
    "zs:label":"Downtown River Corridor",
    "zs:pop10":54
},
  "geometry": {"coordinates":[-105.071021,40.593945],"type":"Point"}
}