{
  "type": "Feature",
  "properties": {
    "gn:admin1_code":"MD",
    "gn:admin2_code":"25.0",
    "gn:asciiname":"Swan Harbour Dell Mobile Home Park",
    "gn:country_code":"US",
    "gn:dem":23,
    "gn:elevation":"23.0",
    "gn:feature_class":"P",
    "gn:feature_code":"PPL",
    "gn:name":"Swan Harbour Dell Mobile Home Park",
    "gn:population":0,
    "gn:timezone":"America/New_York",
    "iso:country":"US",
    "name:eng_x_preferred":[
        "Swan Harbour Dell Mobile Home Park"
    ],
    "name:und_x_variant":[
        "Swan Harbor Dell Trailer Park"
    ],
    "wof:name":"Swan Harbour Dell Mobile Home Park",
    "wof:placetype":"campus"
},
  "geometry": {"coordinates":[-76.14385,39.52563],"type":"Point"}
}