{
  "type": "Feature",
  "properties": {
    "gn:admin1_code":"DE",
    "gn:admin2_code":"1.0",
    "gn:asciiname":"Brownsville",
    "gn:country_code":"US",
    "gn:dem":18,
    "gn:elevation":"19.0",
    "gn:feature_class":"P",
    "gn:feature_code":"PPL",
    "gn:name":"Brownsville",
    "gn:population":0,
    "gn:timezone":"America/New_York",
    "iso:country":"US",
    "name:bre_x_preferred":[
        "Brownsville"
    ],
    "name:cat_x_preferred":[
        "Brownsville"
    ],
    "name:ceb_x_preferred":[
        "Brownsville"
    ],
    "name:ces_x_preferred":[
        "Brownsville"
    ],
    "name:dan_x_preferred":[
        "Brownsville"
    ],
    "name:deu_x_preferred":[
        "Brownsville"
    ],
    "name:fin_x_preferred":[
        "Brownsville"
    ],
    "name:fra_x_preferred":[
        "Brownsville"
    ],
    "name:hun_x_preferred":[
        "Brownsville"
    ],
    "name:ita_x_preferred":[
        "Brownsville"
    ],
    "name:jpn_x_preferred":[
        "\u30d6\u30e9\u30a6\u30f3\u30ba\u30d3\u30eb"
    ],
    "name:kor_x_preferred":[
        "\ube0c\ub77c\uc6b4\uc988\ube4c"
    ],
    "name:nld_x_preferred":[
        "Brownsville"
    ],
    "name:pol_x_preferred":[
        "Brownsville"
    ],
    "name:por_x_preferred":[
        "Brownsville"
    ],
    "name:rus_x_preferred":[
        "\u0411\u0440\u0430\u0443\u043d\u0441\u0432\u0438\u043b\u043b"
    ],
    "name:sco_x_preferred":[
        "Brownsville"
    ],
    "name:spa_x_preferred":[
        "Brownsville"
    ],
    "name:srp_x_preferred":[
        "\u0411\u0440\u0430\u0443\u043d\u0441\u0432\u0438\u043b"
    ],
    "name:swe_x_preferred":[
        "Brownsville"
    ],
    "name:vol_x_preferred":[
        "Brownsville"
    ],
    "name:zho_x_preferred":[
        "\u5e03\u6717\u65af\u7ef4\u5c14"
    ],
    "wof:name":"Brownsville",
    "wof:placetype":"locality"
},
  "geometry": {"coordinates":[-75.67965,38.91372],"type":"Point"}
}