{
  "type": "Feature",
  "properties": {
    "gn:admin1_code":"OH",
    "gn:admin2_code":"173.0",
    "gn:admin3_code":"62162.0",
    "gn:asciiname":"Holiday Park",
    "gn:country_code":"US",
    "gn:dem":195,
    "gn:elevation":"192.0",
    "gn:feature_class":"P",
    "gn:feature_code":"PPL",
    "gn:name":"Holiday Park",
    "gn:population":0,
    "gn:timezone":"America/New_York",
    "iso:country":"US",
    "name:ceb_x_preferred":[
        "Holiday Park"
    ],
    "wof:name":"Holiday Park",
    "wof:placetype":"locality"
},
  "geometry": {"coordinates":[-83.59827,41.55005],"type":"Point"}
}