{
  "type": "Feature",
  "properties": {
    "gn:admin1_code":"IN",
    "gn:admin2_code":"167.0",
    "gn:admin3_code":"73970.0",
    "gn:asciiname":"Larimer Hill",
    "gn:country_code":"US",
    "gn:dem":169,
    "gn:elevation":"166.0",
    "gn:feature_class":"P",
    "gn:feature_code":"PPL",
    "gn:name":"Larimer Hill",
    "gn:population":0,
    "gn:timezone":"America/Indiana/Indianapolis",
    "iso:country":"US",
    "wof:name":"Larimer Hill",
    "wof:placetype":"locality"
},
  "geometry": {"coordinates":[-87.47197,39.45559],"type":"Point"}
}