{
  "type": "Feature",
  "properties": {
    "gn:admin1_code":"MO",
    "gn:admin2_code":"133.0",
    "gn:admin3_code":"74392.0",
    "gn:asciiname":"Hough",
    "gn:country_code":"US",
    "gn:dem":95,
    "gn:elevation":"97.0",
    "gn:feature_class":"P",
    "gn:feature_code":"PPL",
    "gn:name":"Hough",
    "gn:population":0,
    "gn:timezone":"America/Chicago",
    "iso:country":"US",
    "name:deu_x_preferred":[
        "Hough"
    ],
    "name:fra_x_preferred":[
        "Hough"
    ],
    "name:pol_x_preferred":[
        "Hough"
    ],
    "name:rus_x_preferred":[
        "\u0425\u0430\u0444"
    ],
    "wof:name":"Hough",
    "wof:placetype":"locality"
},
  "geometry": {"coordinates":[-89.26702,36.94561],"type":"Point"}
}