{
  "type": "Feature",
  "properties": {
    "gn:admin1_code":"MD",
    "gn:admin2_code":"15.0",
    "gn:asciiname":"Woodlawn",
    "gn:country_code":"US",
    "gn:dem":141,
    "gn:elevation":"142.0",
    "gn:feature_class":"P",
    "gn:feature_code":"PPL",
    "gn:name":"Woodlawn",
    "gn:population":0,
    "gn:timezone":"America/New_York",
    "iso:country":"US",
    "name:cat_x_preferred":[
        "Woodlawn"
    ],
    "name:ceb_x_preferred":[
        "Woodlawn"
    ],
    "name:deu_x_preferred":[
        "Woodlawn"
    ],
    "name:eng_x_preferred":[
        "Woodlawn"
    ],
    "name:ind_x_preferred":[
        "Woodlawn"
    ],
    "name:ita_x_preferred":[
        "Woodlawn"
    ],
    "name:kor_x_preferred":[
        "\uc6b0\ub4e4\ub860"
    ],
    "name:nld_x_preferred":[
        "Woodlawn"
    ],
    "name:pol_x_preferred":[
        "Woodlawn"
    ],
    "name:por_x_preferred":[
        "Woodlawn"
    ],
    "name:rus_x_preferred":[
        "\u0412\u0443\u0434\u043b\u043e\u043d"
    ],
    "name:spa_x_preferred":[
        "Woodlawn"
    ],
    "name:srp_x_preferred":[
        "\u0412\u0443\u0434\u043b\u043e\u043d"
    ],
    "name:und_x_variant":[
        "Battle Swamp"
    ],
    "name:vol_x_preferred":[
        "Woodlawn"
    ],
    "wof:name":"Woodlawn",
    "wof:placetype":"locality"
},
  "geometry": {"coordinates":[-76.07578000000002,39.63428],"type":"Point"}
}