{
  "type": "Feature",
  "properties": {
    "gn:admin1_code":"MD",
    "gn:admin2_code":"13.0",
    "gn:asciiname":"Pleasant Dale",
    "gn:country_code":"US",
    "gn:dem":204,
    "gn:elevation":"208.0",
    "gn:feature_class":"P",
    "gn:feature_code":"PPL",
    "gn:name":"Pleasant Dale",
    "gn:population":0,
    "gn:timezone":"America/New_York",
    "iso:country":"US",
    "wof:name":"Pleasant Dale",
    "wof:placetype":"locality"
},
  "geometry": {"coordinates":[-77.06693,39.61427],"type":"Point"}
}