{
  "type": "Feature",
  "properties": {
    "gn:admin1_code":"SC",
    "gn:admin2_code":"15.0",
    "gn:asciiname":"Old Joe",
    "gn:country_code":"US",
    "gn:dem":8,
    "gn:elevation":"9.0",
    "gn:feature_class":"P",
    "gn:feature_code":"PPL",
    "gn:name":"Old Joe",
    "gn:population":0,
    "gn:timezone":"America/New_York",
    "iso:country":"US",
    "wof:name":"Old Joe",
    "wof:placetype":"locality"
},
  "geometry": {"coordinates":[-79.80785999999998,33.05573],"type":"Point"}
}