{
  "type": "Feature",
  "properties": {
    "iso:country":"US",
    "name:eng_x_preferred":[
        "Parkview Heights"
    ],
    "wof:name":"Parkview Heights",
    "wof:placetype":"neighbourhood",
    "wof:population":1975,
    "zs:area_m":4031878.952102,
    "zs:blockids":[
        60170307061017,
        60170307061019,
        60170307062009,
        60170307061014,
        60170307061020,
        60170307061025,
        60170307061021,
        60170307061024,
        60170307062007,
        60170307062006,
        60170307061004,
        60170307062003,
        60170307061022,
        60170307062002,
        60170307061015,
        60170307062004,
        60170307062001,
        60170307062010,
        60170307062008,
        60170307062011,
        60170307061018,
        60170307061013,
        60170307061016
    ],
    "zs:housing10":682,
    "zs:label":"Parkview Heights",
    "zs:pop10":1975
},
  "geometry": {"coordinates":[-121.091657,38.675034],"type":"Point"}
}