{
  "type": "Feature",
  "properties": {
    "gn:admin1_code":"WV",
    "gn:admin2_code":"13.0",
    "gn:asciiname":"Orma",
    "gn:country_code":"US",
    "gn:dem":230,
    "gn:elevation":"225.0",
    "gn:feature_class":"P",
    "gn:feature_code":"PPL",
    "gn:name":"Orma",
    "gn:population":0,
    "gn:timezone":"America/New_York",
    "iso:country":"US",
    "name:eng_x_preferred":[
        "Orma"
    ],
    "name:und_x_variant":[
        "Rilla",
        "Fez"
    ],
    "wof:name":"Orma",
    "wof:placetype":"locality"
},
  "geometry": {"coordinates":[-81.09983000000003,38.74815],"type":"Point"}
}