{
  "type": "Feature",
  "properties": {
    "gn:admin1_code":"IL",
    "gn:admin2_code":"105.0",
    "gn:admin3_code":"57056.0",
    "gn:asciiname":"Rugby",
    "gn:country_code":"US",
    "gn:dem":212,
    "gn:elevation":"208.0",
    "gn:feature_class":"P",
    "gn:feature_code":"PPL",
    "gn:name":"Rugby",
    "gn:population":0,
    "gn:timezone":"America/Chicago",
    "iso:country":"US",
    "name:bul_x_preferred":[
        "\u0420\u044a\u0433\u0431\u0438"
    ],
    "name:cat_x_preferred":[
        "Rugby"
    ],
    "name:ceb_x_preferred":[
        "Rugby"
    ],
    "name:dan_x_preferred":[
        "Rugby"
    ],
    "name:deu_x_preferred":[
        "Rugby"
    ],
    "name:ell_x_preferred":[
        "\u03a1\u03ac\u03b3\u03ba\u03bc\u03c0\u03b9"
    ],
    "name:eng_x_preferred":[
        "Rugby"
    ],
    "name:fas_x_preferred":[
        "\u0631\u0627\u06af\u0628\u06cc"
    ],
    "name:fin_x_preferred":[
        "Rugby"
    ],
    "name:fra_x_preferred":[
        "Rugby"
    ],
    "name:gle_x_preferred":[
        "Rugby"
    ],
    "name:ind_x_preferred":[
        "Rugbi"
    ],
    "name:ita_x_preferred":[
        "Rugby"
    ],
    "name:jpn_x_preferred":[
        "\u30e9\u30b0\u30d3\u30fc"
    ],
    "name:kor_x_preferred":[
        "\ub7ed\ube44"
    ],
    "name:lav_x_preferred":[
        "Regbijs"
    ],
    "name:lim_x_preferred":[
        "Rugby"
    ],
    "name:nld_x_preferred":[
        "Rugby"
    ],
    "name:nor_x_preferred":[
        "Rugby"
    ],
    "name:pms_x_preferred":[
        "Rugby"
    ],
    "name:pol_x_preferred":[
        "Rugby"
    ],
    "name:por_x_preferred":[
        "Rugby"
    ],
    "name:rus_x_preferred":[
        "\u0420\u0435\u0433\u0431\u0438"
    ],
    "name:slk_x_preferred":[
        "Rugby"
    ],
    "name:spa_x_preferred":[
        "Rugby"
    ],
    "name:szl_x_preferred":[
        "Rugby"
    ],
    "name:tam_x_preferred":[
        "\u0b87\u0bb0\u0b95\u0bcd\u0baa\u0bbf"
    ],
    "name:tur_x_preferred":[
        "Rugby"
    ],
    "name:ukr_x_preferred":[
        "\u0420\u0435\u0433\u0431\u0456"
    ],
    "name:und_x_variant":[
        "Rugby Station"
    ],
    "name:vol_x_preferred":[
        "Rugby"
    ],
    "name:zho_x_preferred":[
        "\u6a44\u6b16\u7403"
    ],
    "wof:name":"Rugby",
    "wof:placetype":"locality"
},
  "geometry": {"coordinates":[-88.49033,40.91198],"type":"Point"}
}