{
  "type": "Feature",
  "properties": {
    "gn:admin1_code":"KY",
    "gn:admin2_code":"51",
    "gn:asciiname":"Sidell",
    "gn:country_code":"US",
    "gn:dem":303,
    "gn:elevation":"301.0",
    "gn:feature_class":"P",
    "gn:feature_code":"PPL",
    "gn:name":"Sidell",
    "gn:population":0,
    "gn:timezone":"America/New_York",
    "iso:country":"US",
    "wof:name":"Sidell",
    "wof:placetype":"locality"
},
  "geometry": {"coordinates":[-83.82491999999998,37.19259],"type":"Point"}
}