{
  "type": "Feature",
  "properties": {
    "gn:admin1_code":"OH",
    "gn:admin2_code":"125.0",
    "gn:admin3_code":"5634.0",
    "gn:asciiname":"Mooney Meadows Subdivision",
    "gn:country_code":"US",
    "gn:dem":228,
    "gn:elevation":"227.0",
    "gn:feature_class":"P",
    "gn:feature_code":"PPL",
    "gn:name":"Mooney Meadows Subdivision",
    "gn:population":0,
    "gn:timezone":"America/New_York",
    "iso:country":"US",
    "wof:name":"Mooney Meadows Subdivision",
    "wof:placetype":"locality"
},
  "geometry": {"coordinates":[-84.72856999999998,41.06755],"type":"Point"}
}