{
  "type": "Feature",
  "properties": {
    "gn:admin1_code":"WA",
    "gn:admin2_code":"33.0",
    "gn:asciiname":"Circle H Mobile Home Park",
    "gn:country_code":"US",
    "gn:dem":218,
    "gn:elevation":"222.0",
    "gn:feature_class":"P",
    "gn:feature_code":"PPL",
    "gn:name":"Circle H Mobile Home Park",
    "gn:population":0,
    "gn:timezone":"America/Los_Angeles",
    "iso:country":"US",
    "wof:name":"Circle H Mobile Home Park",
    "wof:placetype":"campus"
},
  "geometry": {"coordinates":[-121.99084000000001,47.22142],"type":"Point"}
}