{
  "type": "Feature",
  "properties": {
    "gn:admin1_code":"VA",
    "gn:admin2_code":"179.0",
    "gn:asciiname":"Hartlake Estates",
    "gn:country_code":"US",
    "gn:dem":101,
    "gn:elevation":"87.0",
    "gn:feature_class":"P",
    "gn:feature_code":"PPL",
    "gn:name":"Hartlake Estates",
    "gn:population":0,
    "gn:timezone":"America/New_York",
    "iso:country":"US",
    "wof:name":"Hartlake Estates",
    "wof:placetype":"locality"
},
  "geometry": {"coordinates":[-77.6142,38.4319],"type":"Point"}
}