{
  "type": "Feature",
  "properties": {
    "iso:country":"US",
    "name:ara_x_preferred":[
        "\u064a\u0648\u0646\u063a"
    ],
    "name:bel_x_preferred":[
        "\u042f\u043d\u0433"
    ],
    "name:ben_x_preferred":[
        "\u0987\u09df\u0982"
    ],
    "name:cat_x_preferred":[
        "Young"
    ],
    "name:ceb_x_preferred":[
        "Young"
    ],
    "name:ces_x_preferred":[
        "Young"
    ],
    "name:deu_x_preferred":[
        "Young"
    ],
    "name:ell_x_preferred":[
        "\u0393\u03b9\u03b1\u03bd\u03b3\u03ba"
    ],
    "name:fas_x_preferred":[
        "\u06cc\u0627\u0646\u06af"
    ],
    "name:fin_x_preferred":[
        "Young"
    ],
    "name:fra_x_preferred":[
        "Young"
    ],
    "name:heb_x_preferred":[
        "\u05d9\u05d0\u05e0\u05d2"
    ],
    "name:hin_x_preferred":[
        "\u092f\u0902\u0917"
    ],
    "name:hun_x_preferred":[
        "Young"
    ],
    "name:ind_x_preferred":[
        "Young"
    ],
    "name:ita_x_preferred":[
        "Young"
    ],
    "name:jpn_x_preferred":[
        "\u30e4\u30f3\u30b0"
    ],
    "name:kor_x_preferred":[
        "\uc601"
    ],
    "name:lav_x_preferred":[
        "Jangs"
    ],
    "name:nld_x_preferred":[
        "Young"
    ],
    "name:pol_x_preferred":[
        "Young"
    ],
    "name:por_x_preferred":[
        "Young"
    ],
    "name:rus_x_preferred":[
        "\u042f\u043d\u0433"
    ],
    "name:spa_x_preferred":[
        "Young"
    ],
    "name:srp_x_preferred":[
        "\u0408\u0430\u043d\u0433"
    ],
    "name:swe_x_preferred":[
        "Young"
    ],
    "name:tur_x_preferred":[
        "Young"
    ],
    "name:ukr_x_preferred":[
        "\u042f\u043d\u0433"
    ],
    "name:urd_x_preferred":[
        "\u06cc\u0646\u06af"
    ],
    "name:vie_x_preferred":[
        "Young"
    ],
    "name:zho_cn_x_preferred":[
        "\u626c"
    ],
    "name:zho_tw_x_preferred":[
        "\u694a\u93ae"
    ],
    "qs_pg:aaroncc":"US",
    "qs_pg:name":"Young",
    "qs_pg:name_adm0":"United States",
    "qs_pg:name_adm1":"Indiana",
    "qs_pg:photos":503,
    "qs_pg:photos_1k":102,
    "qs_pg:photos_9k":2,
    "qs_pg:photos_9r":5,
    "qs_pg:photos_all":503,
    "qs_pg:photos_sr":7,
    "qs_pg:pop_sr":0,
    "qs_pg:qs_pg_placetype":"locality",
    "qs_pg:qs_pg_placetype_gp":"Town",
    "qs_pg:woe_adm0":23424977,
    "woe:adm0_id":23424977,
    "woe:name_adm0":"United States",
    "woe:name_adm1":"Indiana",
    "woe:placetype":"Town",
    "wof:name":"Young",
    "wof:placetype":"locality"
},
  "geometry": {"coordinates":[-86.325588,39.062782],"type":"Point"}
}