{
  "type": "Feature",
  "properties": {
    "gn:admin1_code":"NY",
    "gn:admin2_code":"91.0",
    "gn:admin3_code":"65255.0",
    "gn:asciiname":"Waters Edge",
    "gn:country_code":"US",
    "gn:dem":73,
    "gn:elevation":"72.0",
    "gn:feature_class":"P",
    "gn:feature_code":"PPL",
    "gn:name":"Waters Edge",
    "gn:population":0,
    "gn:timezone":"America/New_York",
    "iso:country":"US",
    "name:fin_x_preferred":[
        "Waters Edge"
    ],
    "name:ita_x_preferred":[
        "Waters Edge"
    ],
    "name:spa_x_preferred":[
        "Waters Edge"
    ],
    "name:swe_x_preferred":[
        "Waters Edge"
    ],
    "wof:name":"Waters Edge",
    "wof:placetype":"locality"
},
  "geometry": {"coordinates":[-73.73416999999998,43.04639],"type":"Point"}
}