{
  "type": "Feature",
  "properties": {
    "gn:admin1_code":"IA",
    "gn:admin2_code":"43.0",
    "gn:admin3_code":"90705.0",
    "gn:asciiname":"Eckards",
    "gn:country_code":"US",
    "gn:dem":195,
    "gn:elevation":"187.0",
    "gn:feature_class":"P",
    "gn:feature_code":"PPL",
    "gn:name":"Eckards",
    "gn:population":0,
    "gn:timezone":"America/Chicago",
    "iso:country":"US",
    "wof:name":"Eckards",
    "wof:placetype":"locality"
},
  "geometry": {"coordinates":[-91.10429999999999,42.85638],"type":"Point"}
}