{
  "type": "Feature",
  "properties": {
    "gn:admin1_code":"AZ",
    "gn:admin2_code":"13.0",
    "gn:asciiname":"Kensington",
    "gn:country_code":"US",
    "gn:dem":435,
    "gn:elevation":"434.0",
    "gn:feature_class":"P",
    "gn:feature_code":"PPL",
    "gn:name":"Kensington",
    "gn:population":0,
    "gn:timezone":"America/Phoenix",
    "iso:country":"US",
    "name:afr_x_preferred":[
        "Kensington"
    ],
    "name:azb_x_preferred":[
        "\u06a9\u0646\u0632\u06cc\u0646\u0642\u062a\u0648\u0646"
    ],
    "name:aze_x_preferred":[
        "Kensinqton"
    ],
    "name:bar_x_preferred":[
        "Kensington"
    ],
    "name:bel_x_preferred":[
        "\u041a\u0435\u043d\u0441\u0456\u043d\u0433\u0442\u0430\u043d"
    ],
    "name:bul_x_preferred":[
        "\u041a\u0435\u043d\u0441\u0438\u043d\u0433\u0442\u044a\u043d"
    ],
    "name:dan_x_preferred":[
        "Kensington"
    ],
    "name:deu_x_preferred":[
        "Kensington"
    ],
    "name:eng_x_preferred":[
        "Kensington"
    ],
    "name:epo_x_preferred":[
        "Kensington"
    ],
    "name:eus_x_preferred":[
        "Kensington"
    ],
    "name:fas_x_preferred":[
        "\u06a9\u0646\u0632\u06cc\u0646\u06af\u062a\u0648\u0646"
    ],
    "name:fin_x_preferred":[
        "Kensington"
    ],
    "name:fra_x_preferred":[
        "Kensington"
    ],
    "name:fry_x_preferred":[
        "Kensington"
    ],
    "name:gle_x_preferred":[
        "Kensington"
    ],
    "name:heb_x_preferred":[
        "\u05e7\u05e0\u05d6\u05d9\u05e0\u05d2\u05d8\u05d5\u05df"
    ],
    "name:hin_x_preferred":[
        "\u0915\u0947\u0902\u0938\u093f\u0902\u0917\u094d\u091f\u0928"
    ],
    "name:ita_x_preferred":[
        "Kensington"
    ],
    "name:jpn_x_preferred":[
        "\u30b1\u30f3\u30b8\u30f3\u30c8\u30f3"
    ],
    "name:kor_x_preferred":[
        "\ucf04\uc9d5\ud134"
    ],
    "name:mlg_x_preferred":[
        "Kensington"
    ],
    "name:msa_x_preferred":[
        "Kensington"
    ],
    "name:nld_x_preferred":[
        "Kensington"
    ],
    "name:nno_x_preferred":[
        "Kensington"
    ],
    "name:nor_x_preferred":[
        "Kensington"
    ],
    "name:pol_x_preferred":[
        "Kensington"
    ],
    "name:por_x_preferred":[
        "Kensington"
    ],
    "name:ron_x_preferred":[
        "Kensington"
    ],
    "name:rus_x_preferred":[
        "\u041a\u0435\u043d\u0441\u0438\u043d\u0433\u0442\u043e\u043d"
    ],
    "name:sco_x_preferred":[
        "Kensington"
    ],
    "name:spa_x_preferred":[
        "Kensington"
    ],
    "name:tur_x_preferred":[
        "Kensington"
    ],
    "name:ukr_x_preferred":[
        "\u041a\u0435\u043d\u0441\u0456\u043d\u0433\u0442\u043e\u043d"
    ],
    "name:und_x_variant":[
        "North Ranch II"
    ],
    "name:vie_x_preferred":[
        "Kensington"
    ],
    "name:zho_x_preferred":[
        "\u80af\u8f9b\u9813"
    ],
    "wof:name":"Kensington",
    "wof:placetype":"locality"
},
  "geometry": {"coordinates":[-111.97431,33.61671],"type":"Point"}
}