{
  "type": "Feature",
  "properties": {
    "gn:admin1_code":"PA",
    "gn:admin2_code":"13.0",
    "gn:admin3_code":"2680.0",
    "gn:asciiname":"Roots",
    "gn:country_code":"US",
    "gn:dem":380,
    "gn:elevation":"374.0",
    "gn:feature_class":"P",
    "gn:feature_code":"PPL",
    "gn:name":"Roots",
    "gn:population":0,
    "gn:timezone":"America/New_York",
    "iso:country":"US",
    "wof:name":"Roots",
    "wof:placetype":"locality"
},
  "geometry": {"coordinates":[-78.36113,40.6134],"type":"Point"}
}