{
  "type": "Feature",
  "properties": {
    "gn:admin1_code":"CA",
    "gn:admin2_code":"105.0",
    "gn:asciiname":"Willie Hoaglin Place",
    "gn:country_code":"US",
    "gn:dem":686,
    "gn:elevation":"672.0",
    "gn:feature_class":"P",
    "gn:feature_code":"PPL",
    "gn:name":"Willie Hoaglin Place",
    "gn:population":0,
    "gn:timezone":"America/Los_Angeles",
    "iso:country":"US",
    "name:eng_x_preferred":[
        "Willie Hoaglin Place"
    ],
    "name:und_x_variant":[
        "Hoaglin Place"
    ],
    "wof:name":"Willie Hoaglin Place",
    "wof:placetype":"locality"
},
  "geometry": {"coordinates":[-123.33641,40.11404],"type":"Point"}
}