{
  "type": "Feature",
  "properties": {
    "gn:admin1_code":"FL",
    "gn:admin2_code":"83.0",
    "gn:asciiname":"Shady Acres Adult Mobile Home Park",
    "gn:country_code":"US",
    "gn:dem":35,
    "gn:elevation":"27.0",
    "gn:feature_class":"P",
    "gn:feature_code":"PPL",
    "gn:name":"Shady Acres Adult Mobile Home Park",
    "gn:population":0,
    "gn:timezone":"America/New_York",
    "iso:country":"US",
    "wof:name":"Shady Acres Adult Mobile Home Park",
    "wof:placetype":"campus"
},
  "geometry": {"coordinates":[-82.04234,29.01953],"type":"Point"}
}