{
  "type": "Feature",
  "properties": {
    "gn:country":"US",
    "gn:fcode":"PPL",
    "gn:population":0,
    "iso:country":"US",
    "name:cym_x_preferred":[
        "Moon Township"
    ],
    "name:deu_x_preferred":[
        "Moon Township"
    ],
    "name:eng_x_preferred":[
        "Moon Township"
    ],
    "name:fra_x_preferred":[
        "Moon Township"
    ],
    "name:heb_x_preferred":[
        "\u05de\u05d5\u05df \u05d8\u05d0\u05d5\u05e0\u05e9\u05d9\u05e4"
    ],
    "name:ita_x_preferred":[
        "Moon"
    ],
    "name:jpn_x_preferred":[
        "\u30e0\u30fc\u30f3\u30bf\u30a6\u30f3\u30b7\u30c3\u30d7"
    ],
    "name:nld_x_preferred":[
        "Moon Township"
    ],
    "name:spa_x_preferred":[
        "Municipio de Moon"
    ],
    "name:ukr_x_preferred":[
        "\u041c\u0443\u043d \u0422\u0430\u0443\u043d\u0448\u0438\u043f"
    ],
    "name:vie_x_preferred":[
        "X\u00e3 Moon"
    ],
    "name:vie_x_variant":[
        "Moon"
    ],
    "name:zho_x_preferred":[
        "\u6708\u4eae\u9547"
    ],
    "qs_pg:aaroncc":"US",
    "qs_pg:gn_country":"US",
    "qs_pg:gn_fcode":"PPL",
    "qs_pg:gn_pop":0,
    "qs_pg:name":"Moon",
    "qs_pg:name_adm0":"United States",
    "qs_pg:name_adm1":"Pennsylvania",
    "qs_pg:photos":472,
    "qs_pg:photos_1k":96,
    "qs_pg:photos_9k":6,
    "qs_pg:photos_9r":7,
    "qs_pg:photos_all":1281,
    "qs_pg:photos_sr":7,
    "qs_pg:pop_sr":5,
    "qs_pg:qs_pg_placetype":"locality",
    "qs_pg:qs_pg_placetype_gp":"Town",
    "qs_pg:woe_adm0":23424977,
    "woe:adm0_id":23424977,
    "woe:name_adm0":"United States",
    "woe:name_adm1":"Pennsylvania",
    "woe:placetype":"Town",
    "wof:name":"Moon",
    "wof:placetype":"locality"
},
  "geometry": {"coordinates":[-80.24062000000001,40.51165],"type":"Point"}
}