{
  "type": "Feature",
  "properties": {
    "gn:country":"US",
    "gn:fcode":"PPL",
    "gn:population":0,
    "iso:country":"US",
    "name:deu_x_preferred":[
        "Moon Township"
    ],
    "name:eng_x_preferred":[
        "Moon Township"
    ],
    "name:ita_x_preferred":[
        "Moon"
    ],
    "name:nld_x_preferred":[
        "Moon Township"
    ],
    "name:spa_x_preferred":[
        "Municipio de Moon"
    ],
    "name:vie_x_preferred":[
        "X\u00e3 Moon"
    ],
    "name:vie_x_variant":[
        "Moon"
    ],
    "qs_pg:aaroncc":"US",
    "qs_pg:gn_country":"US",
    "qs_pg:gn_fcode":"PPL",
    "qs_pg:gn_pop":0,
    "qs_pg:name":"Moon",
    "qs_pg:name_adm0":"United States",
    "qs_pg:name_adm1":"Pennsylvania",
    "qs_pg:photos":472,
    "qs_pg:photos_1k":96,
    "qs_pg:photos_9k":6,
    "qs_pg:photos_9r":7,
    "qs_pg:photos_all":1281,
    "qs_pg:photos_sr":7,
    "qs_pg:pop_sr":5,
    "qs_pg:qs_pg_placetype":"locality",
    "qs_pg:qs_pg_placetype_gp":"Town",
    "qs_pg:woe_adm0":23424977,
    "woe:adm0_id":23424977,
    "woe:name_adm0":"United States",
    "woe:name_adm1":"Pennsylvania",
    "woe:placetype":"Town",
    "wof:name":"Moon",
    "wof:placetype":"locality"
},
  "geometry": {"coordinates":[-80.24062000000001,40.51165],"type":"Point"}
}