{
  "type": "Feature",
  "properties": {
    "gn:admin1_code":"TX",
    "gn:admin2_code":"409",
    "gn:asciiname":"Friendswood Acres Number 2 Colonia",
    "gn:country_code":"US",
    "gn:dem":18,
    "gn:elevation":"16.0",
    "gn:feature_class":"P",
    "gn:feature_code":"PPL",
    "gn:name":"Friendswood Acres Number 2 Colonia",
    "gn:population":0,
    "gn:timezone":"America/Chicago",
    "iso:country":"US",
    "name:eng_x_preferred":[
        "Friendswood Acres Number 2 Colonia"
    ],
    "name:und_x_variant":[
        "Southeast Odem Colonia"
    ],
    "wof:name":"Friendswood Acres Number 2 Colonia",
    "wof:placetype":"locality"
},
  "geometry": {"coordinates":[-97.57138,27.93724000000001],"type":"Point"}
}