{
  "type": "Feature",
  "properties": {
    "gn:admin1_code":"VA",
    "gn:admin2_code":"93",
    "gn:asciiname":"Clyde's Dale Mobile Community",
    "gn:country_code":"US",
    "gn:dem":20,
    "gn:elevation":"21.0",
    "gn:feature_class":"P",
    "gn:feature_code":"PPL",
    "gn:name":"Clyde's Dale Mobile Community",
    "gn:population":0,
    "gn:timezone":"America/New_York",
    "iso:country":"US",
    "wof:name":"Clyde's Dale Mobile Community",
    "wof:placetype":"locality"
},
  "geometry": {"coordinates":[-76.75544000000002,36.84481],"type":"Point"}
}