{
  "type": "Feature",
  "properties": {
    "gn:admin1_code":"VA",
    "gn:admin2_code":"111",
    "gn:asciiname":"Reekes Mill",
    "gn:country_code":"US",
    "gn:dem":91,
    "gn:elevation":"82.0",
    "gn:feature_class":"P",
    "gn:feature_code":"PPL",
    "gn:name":"Reekes Mill",
    "gn:population":0,
    "gn:timezone":"America/New_York",
    "iso:country":"US",
    "wof:name":"Reekes Mill",
    "wof:placetype":"locality"
},
  "geometry": {"coordinates":[-78.28278,36.82264],"type":"Point"}
}