{
  "type": "Feature",
  "properties": {
    "gn:admin1_code":"MD",
    "gn:admin2_code":"33.0",
    "gn:asciiname":"Broad Creek",
    "gn:country_code":"US",
    "gn:dem":12,
    "gn:elevation":"9.0",
    "gn:feature_class":"P",
    "gn:feature_code":"PPL",
    "gn:name":"Broad Creek",
    "gn:population":0,
    "gn:timezone":"America/New_York",
    "iso:country":"US",
    "name:ceb_x_preferred":[
        "Broad Creek"
    ],
    "name:swe_x_preferred":[
        "Broad Creek"
    ],
    "wof:name":"Broad Creek",
    "wof:placetype":"locality"
},
  "geometry": {"coordinates":[-76.99691999999997,38.75789],"type":"Point"}
}