{
  "type": "Feature",
  "properties": {
    "iso:country":"US",
    "wof:name":"Echo Highlands",
    "wof:placetype":"neighbourhood"
},
  "geometry": {"coordinates":[-86.72118571434331,33.63315563100682],"type":"Point"}
}