{
  "type": "Feature",
  "properties": {
    "iso:country":"US",
    "name:eng_x_preferred":[
        "Hartford"
    ],
    "wof:name":"Hartford",
    "wof:placetype":"neighbourhood",
    "wof:population":134,
    "zs:area_m":41153.527196,
    "zs:blockids":[
        80130125052045
    ],
    "zs:housing10":47,
    "zs:label":"Hartford",
    "zs:pop10":134
},
  "geometry": {"coordinates":[-105.26014000000001,39.982056],"type":"Point"}
}