{
  "type": "Feature",
  "properties": {
    "gn:admin1_code":"TN",
    "gn:admin2_code":"51",
    "gn:asciiname":"Gum Creek",
    "gn:country_code":"US",
    "gn:dem":303,
    "gn:elevation":"305.0",
    "gn:feature_class":"P",
    "gn:feature_code":"PPL",
    "gn:name":"Gum Creek",
    "gn:population":0,
    "gn:timezone":"America/Chicago",
    "iso:country":"US",
    "name:ceb_x_preferred":[
        "Gum Creek"
    ],
    "name:deu_x_preferred":[
        "Gum Creek"
    ],
    "name:swe_x_preferred":[
        "Gum Creek"
    ],
    "wof:name":"Gum Creek",
    "wof:placetype":"locality"
},
  "geometry": {"coordinates":[-86.00693000000003,35.29258],"type":"Point"}
}