{
  "type": "Feature",
  "properties": {
    "gn:admin1_code":"OH",
    "gn:admin2_code":"55.0",
    "gn:admin3_code":"3590.0",
    "gn:asciiname":"Chagrin Falls Park",
    "gn:country_code":"US",
    "gn:dem":295,
    "gn:elevation":"297.0",
    "gn:feature_class":"P",
    "gn:feature_code":"PPL",
    "gn:name":"Chagrin Falls Park",
    "gn:population":0,
    "gn:timezone":"America/New_York",
    "iso:country":"US",
    "wof:name":"Chagrin Falls Park",
    "wof:placetype":"locality"
},
  "geometry": {"coordinates":[-81.3865,41.41394],"type":"Point"}
}