{
  "type": "Feature",
  "properties": {
    "iso:country":"US",
    "name:eng_x_preferred":[
        "Nicolet Drive"
    ],
    "name:eng_x_variant":[
        "Nicolet Dr"
    ],
    "qs:gn_adm0_cc":"US",
    "qs:gn_local":5254962,
    "qs:local_max":8223,
    "qs:local_sum":15088,
    "qs:localhoods":13,
    "qs:name":"Nicolet Drive",
    "qs:name_adm0":"United States",
    "qs:name_adm1":"Wisconsin",
    "qs:name_adm2":"Brown",
    "qs:name_local":"Green Bay",
    "qs:photo_max":179,
    "qs:photo_sum":273,
    "qs:placetype":"Suburb",
    "qs:quad_count":13,
    "qs:woe_adm0":23424977,
    "qs:woe_adm1":2347608,
    "qs:woe_adm2":12590538,
    "qs:woe_lau":0,
    "qs:woe_local":2413753,
    "qs:woe_ver":"7.10.0",
    "wof:lang":[
        "eng"
    ],
    "wof:name":"Nicolet Drive",
    "wof:placetype":"neighbourhood",
    "wof:population":186,
    "zs:blockids":[
        550090201002103,
        550090018022004
    ],
    "zs:housing10":95,
    "zs:pop10":186
},
  "geometry": {"coordinates":[-87.91120100000001,44.55316],"type":"Point"}
}