{
  "type": "Feature",
  "properties": {
    "iso:country":"US",
    "name:eng_x_preferred":[
        "Alafia River Country Meadows"
    ],
    "wof:name":"Alafia River Country Meadows",
    "wof:placetype":"neighbourhood",
    "wof:population":33,
    "zs:area_m":814406.667526,
    "zs:blockids":[
        120570138022006,
        120570138022008
    ],
    "zs:housing10":13,
    "zs:label":"Alafia River Country Meadows",
    "zs:pop10":33
},
  "geometry": {"coordinates":[-82.340187,27.858973],"type":"Point"}
}