{
  "type": "Feature",
  "properties": {
    "iso:country":"US",
    "name:eng_x_preferred":[
        "Ridge Manor Coountry Club"
    ],
    "wof:name":"Ridge Manor Coountry Club",
    "wof:placetype":"neighbourhood",
    "wof:population":479,
    "zs:area_m":4364454.893021,
    "zs:blockids":[
        120530401012010,
        120530401013075,
        120530401013074,
        120530401022000,
        120530401013080
    ],
    "zs:housing10":237,
    "zs:label":"Ridge Manor Coountry Club",
    "zs:pop10":479
},
  "geometry": {"coordinates":[-82.166398,28.496093],"type":"Point"}
}