{
  "type": "Feature",
  "properties": {
    "gn:admin1_code":"OH",
    "gn:admin2_code":"1",
    "gn:admin3_code":"28196.0",
    "gn:asciiname":"Locust Grove",
    "gn:country_code":"US",
    "gn:dem":240,
    "gn:elevation":"239.0",
    "gn:feature_class":"P",
    "gn:feature_code":"PPL",
    "gn:name":"Locust Grove",
    "gn:population":0,
    "gn:timezone":"America/New_York",
    "iso:country":"US",
    "name:ceb_x_preferred":[
        "Locust Grove"
    ],
    "name:deu_x_preferred":[
        "Locust Grove"
    ],
    "name:eng_x_preferred":[
        "Locust Grove"
    ],
    "name:ita_x_preferred":[
        "Locust Grove"
    ],
    "name:nld_x_preferred":[
        "Locust Grove"
    ],
    "name:pol_x_preferred":[
        "Locust Grove"
    ],
    "name:por_x_preferred":[
        "Locust Grove"
    ],
    "name:srp_x_preferred":[
        "\u041b\u043e\u043a\u0443\u0441\u0442 \u0413\u0440\u043e\u0443\u0432"
    ],
    "name:und_x_variant":[
        "Locustgrove"
    ],
    "name:vol_x_preferred":[
        "Locust Grove"
    ],
    "wof:name":"Locust Grove",
    "wof:placetype":"locality"
},
  "geometry": {"coordinates":[-83.37796999999998,38.9884],"type":"Point"}
}