{
  "type": "Feature",
  "properties": {
    "gn:admin1_code":"KY",
    "gn:admin2_code":"231",
    "gn:asciiname":"Murl",
    "gn:country_code":"US",
    "gn:dem":314,
    "gn:elevation":"316.0",
    "gn:feature_class":"P",
    "gn:feature_code":"PPL",
    "gn:name":"Murl",
    "gn:population":0,
    "gn:timezone":"America/Kentucky/Monticello",
    "iso:country":"US",
    "wof:name":"Murl",
    "wof:placetype":"locality"
},
  "geometry": {"coordinates":[-84.95801,36.8134],"type":"Point"}
}