{
  "type": "Feature",
  "properties": {
    "gn:admin1_code":"SC",
    "gn:admin2_code":"1.0",
    "gn:asciiname":"Keowee",
    "gn:country_code":"US",
    "gn:dem":233,
    "gn:elevation":"235.0",
    "gn:feature_class":"P",
    "gn:feature_code":"PPL",
    "gn:name":"Keowee",
    "gn:population":0,
    "gn:timezone":"America/New_York",
    "iso:country":"US",
    "wof:name":"Keowee",
    "wof:placetype":"locality"
},
  "geometry": {"coordinates":[-82.4254,34.38706],"type":"Point"}
}