{
  "type": "Feature",
  "properties": {
    "gn:admin1_code":"MD",
    "gn:admin2_code":"3.0",
    "gn:asciiname":"Indian Landing Estates",
    "gn:country_code":"US",
    "gn:dem":32,
    "gn:elevation":"26.0",
    "gn:feature_class":"P",
    "gn:feature_code":"PPL",
    "gn:name":"Indian Landing Estates",
    "gn:population":0,
    "gn:timezone":"America/New_York",
    "iso:country":"US",
    "wof:name":"Indian Landing Estates",
    "wof:placetype":"locality"
},
  "geometry": {"coordinates":[-76.61747,39.06955],"type":"Point"}
}