{
  "type": "Feature",
  "properties": {
    "gn:admin1_code":"AR",
    "gn:admin2_code":"5.0",
    "gn:admin3_code":"93669.0",
    "gn:asciiname":"Sycamore Heights",
    "gn:country_code":"US",
    "gn:dem":234,
    "gn:elevation":"231.0",
    "gn:feature_class":"P",
    "gn:feature_code":"PPL",
    "gn:name":"Sycamore Heights",
    "gn:population":0,
    "gn:timezone":"America/Chicago",
    "iso:country":"US",
    "wof:name":"Sycamore Heights",
    "wof:placetype":"locality"
},
  "geometry": {"coordinates":[-92.26542999999999,36.28562],"type":"Point"}
}