{
  "type": "Feature",
  "properties": {
    "gn:admin1_code":"AR",
    "gn:admin2_code":"5.0",
    "gn:admin3_code":"92616.0",
    "gn:asciiname":"Heritage Estates",
    "gn:country_code":"US",
    "gn:dem":232,
    "gn:elevation":"232.0",
    "gn:feature_class":"P",
    "gn:feature_code":"PPL",
    "gn:name":"Heritage Estates",
    "gn:population":0,
    "gn:timezone":"America/Chicago",
    "iso:country":"US",
    "wof:name":"Heritage Estates",
    "wof:placetype":"locality"
},
  "geometry": {"coordinates":[-92.36516,36.29035],"type":"Point"}
}