{
  "type": "Feature",
  "properties": {
    "gn:admin1_code":"FL",
    "gn:admin2_code":"57",
    "gn:asciiname":"North Rome Estates",
    "gn:country_code":"US",
    "gn:dem":14,
    "gn:elevation":"6.0",
    "gn:feature_class":"P",
    "gn:feature_code":"PPL",
    "gn:name":"North Rome Estates",
    "gn:population":0,
    "gn:timezone":"America/New_York",
    "iso:country":"US",
    "wof:name":"North Rome Estates",
    "wof:placetype":"locality"
},
  "geometry": {"coordinates":[-82.4772,28.0043],"type":"Point"}
}