{
  "type": "Feature",
  "properties": {
    "gn:admin1_code":"MO",
    "gn:admin2_code":"171.0",
    "gn:admin3_code":"21952.0",
    "gn:asciiname":"Martinstown",
    "gn:country_code":"US",
    "gn:dem":297,
    "gn:elevation":"300.0",
    "gn:feature_class":"P",
    "gn:feature_code":"PPL",
    "gn:name":"Martinstown",
    "gn:population":0,
    "gn:timezone":"America/Chicago",
    "iso:country":"US",
    "name:deu_x_preferred":[
        "Martinstown"
    ],
    "wof:name":"Martinstown",
    "wof:placetype":"locality"
},
  "geometry": {"coordinates":[-92.77048000000001,40.41058],"type":"Point"}
}