{
  "type": "Feature",
  "properties": {
    "gn:admin1_code":"MD",
    "gn:admin2_code":"27.0",
    "gn:asciiname":"Timberleigh Village",
    "gn:country_code":"US",
    "gn:dem":205,
    "gn:elevation":"203.0",
    "gn:feature_class":"P",
    "gn:feature_code":"PPL",
    "gn:name":"Timberleigh Village",
    "gn:population":0,
    "gn:timezone":"America/New_York",
    "iso:country":"US",
    "wof:name":"Timberleigh Village",
    "wof:placetype":"locality"
},
  "geometry": {"coordinates":[-77.12248000000002,39.30149],"type":"Point"}
}