{
  "type": "Feature",
  "properties": {
    "gn:admin1_code":"KS",
    "gn:admin2_code":"37.0",
    "gn:admin3_code":"75575.0",
    "gn:asciiname":"Ringo",
    "gn:country_code":"US",
    "gn:dem":304,
    "gn:elevation":"301.0",
    "gn:feature_class":"P",
    "gn:feature_code":"PPL",
    "gn:name":"Ringo",
    "gn:population":0,
    "gn:timezone":"America/Chicago",
    "iso:country":"US",
    "name:zho_x_preferred":[
        "\u6797\u6208"
    ],
    "wof:name":"Ringo",
    "wof:placetype":"locality"
},
  "geometry": {"coordinates":[-94.76134999999999,37.50949],"type":"Point"}
}