{
  "type": "Feature",
  "properties": {
    "gn:admin1_code":"MS",
    "gn:admin2_code":"5.0",
    "gn:asciiname":"Busy Corner",
    "gn:country_code":"US",
    "gn:dem":145,
    "gn:elevation":"135.0",
    "gn:feature_class":"P",
    "gn:feature_code":"PPL",
    "gn:name":"Busy Corner",
    "gn:population":0,
    "gn:timezone":"America/Chicago",
    "iso:country":"US",
    "wof:name":"Busy Corner",
    "wof:placetype":"locality"
},
  "geometry": {"coordinates":[-90.86344,31.27878],"type":"Point"}
}