{
  "type": "Feature",
  "properties": {
    "gn:admin1_code":"NY",
    "gn:admin2_code":"9.0",
    "gn:admin3_code":"84055.0",
    "gn:asciiname":"Pioneer Estates Mobile Home Park",
    "gn:country_code":"US",
    "gn:dem":434,
    "gn:elevation":"434.0",
    "gn:feature_class":"P",
    "gn:feature_code":"PPL",
    "gn:name":"Pioneer Estates Mobile Home Park",
    "gn:population":0,
    "gn:timezone":"America/New_York",
    "iso:country":"US",
    "wof:name":"Pioneer Estates Mobile Home Park",
    "wof:placetype":"campus"
},
  "geometry": {"coordinates":[-78.48116999999998,42.52117],"type":"Point"}
}