{
  "type": "Feature",
  "properties": {
    "gn:admin1_code":"OK",
    "gn:admin2_code":"51",
    "gn:asciiname":"Farwell",
    "gn:country_code":"US",
    "gn:dem":363,
    "gn:elevation":"359.0",
    "gn:feature_class":"P",
    "gn:feature_code":"PPL",
    "gn:name":"Farwell",
    "gn:population":0,
    "gn:timezone":"America/Chicago",
    "iso:country":"US",
    "name:ceb_x_preferred":[
        "Farwell"
    ],
    "name:deu_x_preferred":[
        "Farwell"
    ],
    "name:fra_x_preferred":[
        "Farwell"
    ],
    "name:ido_x_preferred":[
        "Farwell"
    ],
    "name:ita_x_preferred":[
        "Farwell"
    ],
    "name:nld_x_preferred":[
        "Farwell"
    ],
    "name:pol_x_preferred":[
        "Farwell"
    ],
    "name:rus_x_preferred":[
        "\u0424\u0430\u0440\u0443\u044d\u043b\u043b"
    ],
    "name:srp_x_preferred":[
        "\u0424\u0430\u0440\u0432\u0435\u043b"
    ],
    "name:swe_x_preferred":[
        "Farwell"
    ],
    "name:ukr_x_preferred":[
        "\u0424\u0430\u0440\u0432\u0435\u043b\u043b"
    ],
    "name:vol_x_preferred":[
        "Farwell"
    ],
    "wof:name":"Farwell",
    "wof:placetype":"locality"
},
  "geometry": {"coordinates":[-98.0056,34.8859],"type":"Point"}
}