{
  "type": "Feature",
  "properties": {
    "gn:admin1_code":"OH",
    "gn:admin2_code":"109.0",
    "gn:admin3_code":"74475.0",
    "gn:asciiname":"Halifax",
    "gn:country_code":"US",
    "gn:dem":262,
    "gn:elevation":"266.0",
    "gn:feature_class":"P",
    "gn:feature_code":"PPL",
    "gn:name":"Halifax",
    "gn:population":0,
    "gn:timezone":"America/New_York",
    "iso:country":"US",
    "name:afr_x_preferred":[
        "Halifax"
    ],
    "name:bre_x_preferred":[
        "Halifax"
    ],
    "name:bul_x_preferred":[
        "\u0425\u0430\u043b\u0438\u0444\u0430\u043a\u0441"
    ],
    "name:cat_x_preferred":[
        "Halifax"
    ],
    "name:ceb_x_preferred":[
        "Halifax"
    ],
    "name:ces_x_preferred":[
        "Halifax"
    ],
    "name:cym_x_preferred":[
        "Halifax"
    ],
    "name:dan_x_preferred":[
        "Halifax"
    ],
    "name:deu_x_preferred":[
        "Halifax"
    ],
    "name:epo_x_preferred":[
        "Halifax"
    ],
    "name:fas_x_preferred":[
        "\u0647\u0644\u06cc\u0641\u06a9\u0633"
    ],
    "name:fin_x_preferred":[
        "Halifax"
    ],
    "name:fra_x_preferred":[
        "Halifax"
    ],
    "name:gla_x_preferred":[
        "Halifax"
    ],
    "name:glg_x_preferred":[
        "Halifax"
    ],
    "name:heb_x_preferred":[
        "\u05d4\u05dc\u05d9\u05e4\u05e7\u05e1"
    ],
    "name:hun_x_preferred":[
        "Halifax"
    ],
    "name:isl_x_preferred":[
        "Halifax"
    ],
    "name:ita_x_preferred":[
        "Halifax"
    ],
    "name:jpn_x_preferred":[
        "\u30cf\u30ea\u30d5\u30a1\u30c3\u30af\u30b9"
    ],
    "name:kor_x_preferred":[
        "\ud57c\ub9ac\ud329\uc2a4"
    ],
    "name:nld_x_preferred":[
        "Halifax"
    ],
    "name:nor_x_preferred":[
        "Halifax"
    ],
    "name:oci_x_preferred":[
        "Halifax"
    ],
    "name:pol_x_preferred":[
        "Halifax"
    ],
    "name:por_x_preferred":[
        "Halifax"
    ],
    "name:ron_x_preferred":[
        "Halifax"
    ],
    "name:rus_x_preferred":[
        "\u0413\u0430\u043b\u0438\u0444\u0430\u043a\u0441"
    ],
    "name:slk_x_preferred":[
        "Halifax"
    ],
    "name:slv_x_preferred":[
        "Halifax"
    ],
    "name:spa_x_preferred":[
        "Halifax"
    ],
    "name:srp_x_preferred":[
        "\u0425\u0430\u043b\u0438\u0444\u0430\u043a\u0441"
    ],
    "name:swe_x_preferred":[
        "Halifax"
    ],
    "name:ukr_x_preferred":[
        "\u0413\u0430\u043b\u0456\u0444\u0430\u043a\u0441"
    ],
    "name:vol_x_preferred":[
        "Halifax"
    ],
    "wof:name":"Halifax",
    "wof:placetype":"locality"
},
  "geometry": {"coordinates":[-84.1837,40.06007],"type":"Point"}
}