{
  "type": "Feature",
  "properties": {
    "gn:country":"US",
    "gn:fcode":"PPL",
    "gn:population":0,
    "iso:country":"US",
    "name:azb_x_preferred":[
        "\u0633\u06cc\u0644\u0648\u0631 \u0631\u06cc\u0641"
    ],
    "name:ces_x_preferred":[
        "Silver Reef"
    ],
    "name:deu_x_preferred":[
        "Silver Reef"
    ],
    "name:eng_x_preferred":[
        "Silver Reef"
    ],
    "name:slk_x_preferred":[
        "Silver Reef"
    ],
    "qs_pg:aaroncc":"US",
    "qs_pg:gn_country":"US",
    "qs_pg:gn_fcode":"PPL",
    "qs_pg:gn_pop":0,
    "qs_pg:name":"Silver Reef",
    "qs_pg:name_adm0":"United States",
    "qs_pg:name_adm1":"Utah",
    "qs_pg:photos":195,
    "qs_pg:photos_1k":40,
    "qs_pg:photos_9k":1,
    "qs_pg:photos_9r":4,
    "qs_pg:photos_all":195,
    "qs_pg:photos_sr":4,
    "qs_pg:pop_sr":0,
    "qs_pg:qs_pg_placetype":"locality",
    "qs_pg:qs_pg_placetype_gp":"Town",
    "qs_pg:woe_adm0":23424977,
    "woe:adm0_id":23424977,
    "woe:name_adm0":"United States",
    "woe:name_adm1":"Utah",
    "woe:placetype":"Town",
    "wof:name":"Silver Reef",
    "wof:placetype":"locality"
},
  "geometry": {"coordinates":[-113.36772999999999,37.25276],"type":"Point"}
}