{
  "type": "Feature",
  "properties": {
    "iso:country":"US",
    "name:eng_x_preferred":[
        "Sanctuary at Sweetwater Creek"
    ],
    "wof:name":"Sanctuary at Sweetwater Creek",
    "wof:placetype":"neighbourhood",
    "wof:population":296,
    "zs:area_m":656933.766793,
    "zs:blockids":[
        120570117064008,
        120570117065003,
        120570117065002,
        120570117064009,
        120570117065012,
        120570117065007,
        120570116053053,
        120570117064001,
        120570117065008,
        120570116053054,
        120570117065010,
        120570117064000,
        120570117064011,
        120570117065005,
        120570117065004,
        120570117065006,
        120570117064003,
        120570117064002,
        120570117065009,
        120570117065001,
        120579806001046,
        120570116053057
    ],
    "zs:housing10":122,
    "zs:label":"Sanctuary at Sweetwater Creek",
    "zs:pop10":296
},
  "geometry": {"coordinates":[-82.548101,27.990923],"type":"Point"}
}