{
  "type": "Feature",
  "properties": {
    "gn:admin1_code":"ME",
    "gn:admin2_code":"11.0",
    "gn:admin3_code":"62190.0",
    "gn:asciiname":"Readfield Depot",
    "gn:country_code":"US",
    "gn:dem":97,
    "gn:elevation":"97.0",
    "gn:feature_class":"P",
    "gn:feature_code":"PPL",
    "gn:name":"Readfield Depot",
    "gn:population":0,
    "gn:timezone":"America/New_York",
    "iso:country":"US",
    "name:eng_x_preferred":[
        "Readfield Depot"
    ],
    "name:und_x_variant":[
        "Readfield Station"
    ],
    "wof:name":"Readfield Depot",
    "wof:placetype":"locality"
},
  "geometry": {"coordinates":[-69.93977,44.37923],"type":"Point"}
}