{
  "type": "Feature",
  "properties": {
    "gn:country":"US",
    "gn:fcode":"PPL",
    "gn:population":0,
    "iso:country":"US",
    "name:bul_x_preferred":[
        "\u041b\u0435\u0439\u043a\u043f\u043e\u0440\u0442"
    ],
    "name:ceb_x_preferred":[
        "Lakeport"
    ],
    "name:deu_x_preferred":[
        "Lakeport"
    ],
    "name:fra_x_preferred":[
        "Lakeport"
    ],
    "name:ita_x_preferred":[
        "Lakeport"
    ],
    "name:nld_x_preferred":[
        "Lakeport"
    ],
    "name:pol_x_preferred":[
        "Lakeport"
    ],
    "name:por_x_preferred":[
        "Lakeport"
    ],
    "name:spa_x_preferred":[
        "Lakeport"
    ],
    "name:srp_x_preferred":[
        "\u041b\u0435\u0458\u043a\u043f\u043e\u0440\u0442"
    ],
    "name:swe_x_preferred":[
        "Lakeport"
    ],
    "name:ukr_x_preferred":[
        "\u041b\u0435\u0439\u043a\u043f\u043e\u0440\u0442"
    ],
    "name:vol_x_preferred":[
        "Lakeport"
    ],
    "qs_pg:aaroncc":"US",
    "qs_pg:gn_country":"US",
    "qs_pg:gn_fcode":"PPL",
    "qs_pg:gn_pop":0,
    "qs_pg:name":"Lakeport",
    "qs_pg:name_adm0":"United States",
    "qs_pg:name_adm1":"Michigan",
    "qs_pg:photos":39,
    "qs_pg:photos_1k":8,
    "qs_pg:photos_9k":1,
    "qs_pg:photos_9r":2,
    "qs_pg:photos_all":39,
    "qs_pg:photos_sr":2,
    "qs_pg:pop_sr":5,
    "qs_pg:qs_pg_placetype":"locality",
    "qs_pg:qs_pg_placetype_gp":"Town",
    "qs_pg:woe_adm0":23424977,
    "woe:adm0_id":23424977,
    "woe:name_adm0":"United States",
    "woe:name_adm1":"Michigan",
    "woe:placetype":"Town",
    "wof:name":"Lakeport",
    "wof:placetype":"locality"
},
  "geometry": {"coordinates":[-82.4902,43.11503],"type":"Point"}
}