{
  "type": "Feature",
  "properties": {
    "gn:admin1_code":"OR",
    "gn:admin2_code":"11",
    "gn:asciiname":"Gravelford",
    "gn:country_code":"US",
    "gn:dem":15,
    "gn:elevation":"17.0",
    "gn:feature_class":"P",
    "gn:feature_code":"PPL",
    "gn:name":"Gravelford",
    "gn:population":0,
    "gn:timezone":"America/Los_Angeles",
    "iso:country":"US",
    "name:fas_x_preferred":[
        "\u06af\u0631\u0648\u0644\u0641\u0648\u0631\u062f"
    ],
    "name:hat_x_preferred":[
        "Gravelford"
    ],
    "wof:name":"Gravelford",
    "wof:placetype":"locality"
},
  "geometry": {"coordinates":[-124.07816,43.10511],"type":"Point"}
}