{
  "type": "Feature",
  "properties": {
    "gn:admin1_code":"FL",
    "gn:admin2_code":"57",
    "gn:asciiname":"Cumberland Manors",
    "gn:country_code":"US",
    "gn:dem":18,
    "gn:elevation":"13.0",
    "gn:feature_class":"P",
    "gn:feature_code":"PPL",
    "gn:name":"Cumberland Manors",
    "gn:population":0,
    "gn:timezone":"America/New_York",
    "iso:country":"US",
    "wof:name":"Cumberland Manors",
    "wof:placetype":"locality"
},
  "geometry": {"coordinates":[-82.56189999999999,28.0904],"type":"Point"}
}