{
  "type": "Feature",
  "properties": {
    "iso:country":"US",
    "name:eng_x_preferred":[
        "Diamond Bar"
    ],
    "wof:name":"Diamond Bar",
    "wof:placetype":"neighbourhood",
    "wof:population":4060,
    "zs:area_m":1858410.73984,
    "zs:blockids":[
        61110047041017,
        61110047101029,
        61110047101015,
        61110047101014,
        61110047042004,
        61110047042006,
        61110047042007,
        61110047171008,
        61110047101006,
        61110047101007,
        61110047101008,
        61110047101022,
        61110047171005,
        61110047171017,
        61110047042003,
        61110047151008,
        61110047101018,
        61110047042001,
        61110047041016,
        61110047171011,
        61110047171001,
        61110047101024,
        61110047101017,
        61110047101010,
        61110047042022,
        61110047042021,
        61110047171000,
        61110047101016,
        61110047101028,
        61110047101012,
        61110047101025,
        61110047042009,
        61110047042010,
        61110047101001,
        61110047101011,
        61110047171013,
        61110047042002,
        61110047041018,
        61110047101000,
        61110047101023,
        61110047101003,
        61110047101026,
        61110047151000,
        61110047171012,
        61110047151007,
        61110047041015,
        61110047103001,
        61110047171004,
        61110047171006,
        61110047171003,
        61110047101002,
        61110047101004,
        61110047042008,
        61110047042011,
        61110047042019,
        61110047171015,
        61110047171018,
        61110047101021,
        61110047101027,
        61110047101013,
        61110047101009,
        61110047042020,
        61110047042018,
        61110047042016,
        61110047101019,
        61110047101020,
        61110047101005,
        61110047171007,
        61110047171014,
        61110047042017,
        61110047042015
    ],
    "zs:housing10":1155,
    "zs:label":"Diamond Bar",
    "zs:pop10":4060
},
  "geometry": {"coordinates":[-119.14936299999999,34.167814],"type":"Point"}
}