{
  "type": "Feature",
  "properties": {
    "gn:admin1_code":"NC",
    "gn:admin2_code":"47.0",
    "gn:admin3_code":"90436.0",
    "gn:asciiname":"Pireway",
    "gn:country_code":"US",
    "gn:dem":7,
    "gn:elevation":"12.0",
    "gn:feature_class":"P",
    "gn:feature_code":"PPL",
    "gn:name":"Pireway",
    "gn:population":0,
    "gn:timezone":"America/New_York",
    "iso:country":"US",
    "name:eng_x_preferred":[
        "Pireway"
    ],
    "name:und_x_variant":[
        "Pireway Ferry"
    ],
    "wof:name":"Pireway",
    "wof:placetype":"locality"
},
  "geometry": {"coordinates":[-78.63779,34.02712],"type":"Point"}
}