{
  "type": "Feature",
  "properties": {
    "gn:country":"US",
    "gn:fcode":"PPL",
    "gn:population":0,
    "iso:country":"US",
    "name:azb_x_preferred":[
        "\u0647\u0627\u0628\u0631\u062a\u0648\u0646"
    ],
    "name:eng_x_preferred":[
        "Habberton"
    ],
    "name:fas_x_preferred":[
        "\u0647\u0627\u0628\u0631\u062a\u0648\u0646"
    ],
    "name:fra_x_preferred":[
        "Habberton"
    ],
    "name:und_x_variant":[
        "Haberton"
    ],
    "name:zho_x_preferred":[
        "\u54c8\u4f2f\u9813"
    ],
    "qs_pg:aaroncc":"US",
    "qs_pg:gn_country":"US",
    "qs_pg:gn_fcode":"PPL",
    "qs_pg:gn_pop":0,
    "qs_pg:name":"Habberton",
    "qs_pg:name_adm0":"United States",
    "qs_pg:name_adm1":"Arkansas",
    "qs_pg:photos":4,
    "qs_pg:photos_1k":1,
    "qs_pg:photos_9k":1,
    "qs_pg:photos_9r":1,
    "qs_pg:photos_all":4,
    "qs_pg:photos_sr":1,
    "qs_pg:pop_sr":0,
    "qs_pg:qs_pg_placetype":"locality",
    "qs_pg:qs_pg_placetype_gp":"Town",
    "qs_pg:woe_adm0":23424977,
    "woe:adm0_id":23424977,
    "woe:name_adm0":"United States",
    "woe:name_adm1":"Arkansas",
    "woe:placetype":"Town",
    "wof:name":"Habberton",
    "wof:placetype":"locality"
},
  "geometry": {"coordinates":[-94.05159,36.11508],"type":"Point"}
}