{
  "type": "Feature",
  "properties": {
    "gn:admin1_code":"MD",
    "gn:admin2_code":"37.0",
    "gn:asciiname":"North Town Creek Manor",
    "gn:country_code":"US",
    "gn:dem":37,
    "gn:elevation":"35.0",
    "gn:feature_class":"P",
    "gn:feature_code":"PPL",
    "gn:name":"North Town Creek Manor",
    "gn:population":0,
    "gn:timezone":"America/New_York",
    "iso:country":"US",
    "wof:name":"North Town Creek Manor",
    "wof:placetype":"locality"
},
  "geometry": {"coordinates":[-76.50384,38.30235],"type":"Point"}
}