{
  "type": "Feature",
  "properties": {
    "gn:country":"US",
    "gn:fcode":"PPL",
    "gn:population":0,
    "iso:country":"US",
    "name:azb_x_preferred":[
        "\u0644\u0648\u06a9\u062a\u0633"
    ],
    "name:eng_x_preferred":[
        "Lucketts"
    ],
    "name:fas_x_preferred":[
        "\u0644\u0648\u06a9\u062a\u0633"
    ],
    "name:fra_x_preferred":[
        "Lucketts"
    ],
    "name:und_x_variant":[
        "Luckets"
    ],
    "name:vol_x_preferred":[
        "Lucketts"
    ],
    "qs_pg:aaroncc":"US",
    "qs_pg:gn_country":"US",
    "qs_pg:gn_fcode":"PPL",
    "qs_pg:gn_pop":0,
    "qs_pg:name":"Lucketts",
    "qs_pg:name_adm0":"United States",
    "qs_pg:name_adm1":"Virginia",
    "qs_pg:photos":1253,
    "qs_pg:photos_1k":254,
    "qs_pg:photos_9k":6,
    "qs_pg:photos_9r":7,
    "qs_pg:photos_all":1253,
    "qs_pg:photos_sr":12,
    "qs_pg:pop_sr":0,
    "qs_pg:qs_pg_placetype":"locality",
    "qs_pg:qs_pg_placetype_gp":"Town",
    "qs_pg:woe_adm0":23424977,
    "woe:adm0_id":23424977,
    "woe:name_adm0":"United States",
    "woe:name_adm1":"Virginia",
    "woe:placetype":"Town",
    "wof:name":"Lucketts",
    "wof:placetype":"locality"
},
  "geometry": {"coordinates":[-77.53443,39.21566],"type":"Point"}
}