{
  "type": "Feature",
  "properties": {
    "gn:admin1_code":"CA",
    "gn:admin2_code":"45.0",
    "gn:asciiname":"Spyrock",
    "gn:country_code":"US",
    "gn:dem":268,
    "gn:elevation":"259.0",
    "gn:feature_class":"P",
    "gn:feature_code":"PPL",
    "gn:name":"Spyrock",
    "gn:population":0,
    "gn:timezone":"America/Los_Angeles",
    "iso:country":"US",
    "name:eng_x_preferred":[
        "Spyrock"
    ],
    "name:und_x_variant":[
        "Spy Rock"
    ],
    "name:zho_x_preferred":[
        "\u65af\u6d3e\u7f85\u514b"
    ],
    "wof:name":"Spyrock",
    "wof:placetype":"locality"
},
  "geometry": {"coordinates":[-123.44391,39.87654000000001],"type":"Point"}
}