{
  "type": "Feature",
  "properties": {
    "gn:admin1_code":"VA",
    "gn:admin2_code":"191",
    "gn:asciiname":"Three Springs",
    "gn:country_code":"US",
    "gn:dem":611,
    "gn:elevation":"609.0",
    "gn:feature_class":"P",
    "gn:feature_code":"PPL",
    "gn:name":"Three Springs",
    "gn:population":0,
    "gn:timezone":"America/New_York",
    "iso:country":"US",
    "name:ben_x_preferred":[
        "\u09a5\u09cd\u09b0\u09bf \u09b8\u09cd\u09aa\u09cd\u09b0\u09bf\u0982\u09b8"
    ],
    "name:ceb_x_preferred":[
        "Three Springs"
    ],
    "name:deu_x_preferred":[
        "Three Springs"
    ],
    "name:ell_x_preferred":[
        "\u0398\u03c1\u03b9 \u03a3\u03c0\u03c1\u03b9\u03bd\u03b3\u03ba\u03c2"
    ],
    "name:fra_x_preferred":[
        "Three Springs"
    ],
    "name:heb_x_preferred":[
        "\u05d8\u05e8\u05d9 \u05e1\u05e4\u05e8\u05d9\u05e0\u05d2\u05e1"
    ],
    "name:hin_x_preferred":[
        "\u0925\u094d\u0930\u0940 \u0938\u094d\u092a\u094d\u0930\u093f\u0902\u0917\u094d\u0938"
    ],
    "name:hun_x_preferred":[
        "Three Springs"
    ],
    "name:ind_x_preferred":[
        "Three Springs"
    ],
    "name:kor_x_preferred":[
        "\uc4f0\ub9ac \uc2a4\ud504\ub9c1\uc2a4"
    ],
    "name:nld_x_preferred":[
        "Three Springs"
    ],
    "name:rus_x_preferred":[
        "\u0422\u0440\u0438-\u0421\u043f\u0440\u0438\u043d\u0433\u0441"
    ],
    "name:spa_x_preferred":[
        "Three Springs"
    ],
    "name:swe_x_preferred":[
        "Three Springs"
    ],
    "name:tur_x_preferred":[
        "Three Springs"
    ],
    "name:ukr_x_preferred":[
        "\u0422\u0440\u0456-\u0421\u043f\u0440\u0456\u043d\u0433\u0441"
    ],
    "name:urd_x_preferred":[
        "\u062a\u06be\u0631\u06cc \u0627\u0633\u067e\u0631\u0646\u06af\u0632"
    ],
    "name:vie_x_preferred":[
        "Three Springs"
    ],
    "name:zho_cn_x_preferred":[
        "\u4e09\u6cc9\u6751"
    ],
    "name:zho_tw_x_preferred":[
        "\u4e09\u6cc9\u93ae"
    ],
    "wof:name":"Three Springs",
    "wof:placetype":"locality"
},
  "geometry": {"coordinates":[-82.24375000000001,36.61872],"type":"Point"}
}