{
  "type": "Feature",
  "properties": {
    "gn:admin1_code":"VA",
    "gn:admin2_code":"191",
    "gn:asciiname":"Three Springs",
    "gn:country_code":"US",
    "gn:dem":611,
    "gn:elevation":"609.0",
    "gn:feature_class":"P",
    "gn:feature_code":"PPL",
    "gn:name":"Three Springs",
    "gn:population":0,
    "gn:timezone":"America/New_York",
    "iso:country":"US",
    "name:ceb_x_preferred":[
        "Three Springs"
    ],
    "name:deu_x_preferred":[
        "Three Springs"
    ],
    "name:fra_x_preferred":[
        "Three Springs"
    ],
    "name:nld_x_preferred":[
        "Three Springs"
    ],
    "name:swe_x_preferred":[
        "Three Springs"
    ],
    "wof:name":"Three Springs",
    "wof:placetype":"locality"
},
  "geometry": {"coordinates":[-82.24375000000001,36.61872],"type":"Point"}
}