{
  "type": "Feature",
  "properties": {
    "gn:admin1_code":"PA",
    "gn:admin2_code":"29.0",
    "gn:admin3_code":"22056.0",
    "gn:asciiname":"Glenloch",
    "gn:country_code":"US",
    "gn:dem":139,
    "gn:elevation":"134.0",
    "gn:feature_class":"P",
    "gn:feature_code":"PPL",
    "gn:name":"Glenloch",
    "gn:population":0,
    "gn:timezone":"America/New_York",
    "iso:country":"US",
    "name:eng_x_preferred":[
        "Glenloch"
    ],
    "name:und_x_variant":[
        "Glen Loch"
    ],
    "wof:name":"Glenloch",
    "wof:placetype":"locality"
},
  "geometry": {"coordinates":[-75.58465,40.03011],"type":"Point"}
}