{
  "type": "Feature",
  "properties": {
    "gn:admin1_code":"IL",
    "gn:admin2_code":"31.0",
    "gn:admin3_code":"53676.0",
    "gn:asciiname":"Pine Grove",
    "gn:country_code":"US",
    "gn:dem":210,
    "gn:elevation":"206.0",
    "gn:feature_class":"P",
    "gn:feature_code":"PPL",
    "gn:name":"Pine Grove",
    "gn:population":0,
    "gn:timezone":"America/Chicago",
    "iso:country":"US",
    "name:cat_x_preferred":[
        "Pine Grove"
    ],
    "name:ceb_x_preferred":[
        "Pine Grove"
    ],
    "name:deu_x_preferred":[
        "Pine Grove"
    ],
    "name:ita_x_preferred":[
        "Pine Grove"
    ],
    "name:nld_x_preferred":[
        "Pine Grove"
    ],
    "name:pol_x_preferred":[
        "Pine Grove"
    ],
    "name:por_x_preferred":[
        "Pine Grove"
    ],
    "name:spa_x_preferred":[
        "Pine Grove"
    ],
    "name:srp_x_preferred":[
        "\u041f\u0430\u0458\u043d \u0413\u0440\u043e\u0443\u0432"
    ],
    "name:vol_x_preferred":[
        "Pine Grove"
    ],
    "wof:name":"Pine Grove",
    "wof:placetype":"locality"
},
  "geometry": {"coordinates":[-87.85083,42.11333],"type":"Point"}
}