{
  "type": "Feature",
  "properties": {
    "gn:admin1_code":"MT",
    "gn:admin2_code":"109.0",
    "gn:asciiname":"Carlyle",
    "gn:country_code":"US",
    "gn:dem":960,
    "gn:elevation":"963.0",
    "gn:feature_class":"P",
    "gn:feature_code":"PPL",
    "gn:name":"Carlyle",
    "gn:population":0,
    "gn:timezone":"America/Denver",
    "iso:country":"US",
    "wof:name":"Carlyle",
    "wof:placetype":"locality"
},
  "geometry": {"coordinates":[-104.07604000000001,46.65501],"type":"Point"}
}