{
  "type": "Feature",
  "properties": {
    "gn:admin1_code":"AR",
    "gn:admin2_code":"139.0",
    "gn:admin3_code":"91440.0",
    "gn:asciiname":"Shuler",
    "gn:country_code":"US",
    "gn:dem":85,
    "gn:elevation":"78.0",
    "gn:feature_class":"P",
    "gn:feature_code":"PPL",
    "gn:name":"Shuler",
    "gn:population":0,
    "gn:timezone":"America/Chicago",
    "iso:country":"US",
    "wof:name":"Shuler",
    "wof:placetype":"locality"
},
  "geometry": {"coordinates":[-92.90155,33.17874],"type":"Point"}
}