{
  "type": "Feature",
  "properties": {
    "gn:admin1_code":"WV",
    "gn:admin2_code":"5.0",
    "gn:asciiname":"Rocklick",
    "gn:country_code":"US",
    "gn:dem":360,
    "gn:elevation":"357.0",
    "gn:feature_class":"P",
    "gn:feature_code":"PPL",
    "gn:name":"Rocklick",
    "gn:population":0,
    "gn:timezone":"America/New_York",
    "iso:country":"US",
    "name:eng_x_preferred":[
        "Rocklick"
    ],
    "name:und_x_variant":[
        "Rock Lick"
    ],
    "wof:name":"Rocklick",
    "wof:placetype":"locality"
},
  "geometry": {"coordinates":[-81.62872,37.84622],"type":"Point"}
}