{
  "type": "Feature",
  "properties": {
    "gn:admin1_code":"MD",
    "gn:admin2_code":"15.0",
    "gn:asciiname":"Jacks Corner",
    "gn:country_code":"US",
    "gn:dem":103,
    "gn:elevation":"101.0",
    "gn:feature_class":"P",
    "gn:feature_code":"PPL",
    "gn:name":"Jacks Corner",
    "gn:population":0,
    "gn:timezone":"America/New_York",
    "iso:country":"US",
    "wof:name":"Jacks Corner",
    "wof:placetype":"locality"
},
  "geometry": {"coordinates":[-76.12634,39.6415],"type":"Point"}
}