{
  "type": "Feature",
  "properties": {
    "gn:admin1_code":"TX",
    "gn:admin2_code":"225.0",
    "gn:asciiname":"Pearsons Chapel",
    "gn:country_code":"US",
    "gn:dem":100,
    "gn:elevation":"99.0",
    "gn:feature_class":"P",
    "gn:feature_code":"PPL",
    "gn:name":"Pearsons Chapel",
    "gn:population":0,
    "gn:timezone":"America/Chicago",
    "iso:country":"US",
    "name:eng_x_preferred":[
        "Pearsons Chapel"
    ],
    "name:und_x_variant":[
        "Post Oak"
    ],
    "wof:name":"Pearsons Chapel",
    "wof:placetype":"locality"
},
  "geometry": {"coordinates":[-95.54356,31.15185],"type":"Point"}
}