{
  "type": "Feature",
  "properties": {
    "gn:country":"US",
    "gn:elevation":8,
    "gn:fcode":"PPL",
    "gn:population":0,
    "iso:country":"US",
    "name:eng_x_preferred":[
        "Waldon Woods"
    ],
    "qs:gn_adm0_cc":"US",
    "qs:gn_fcode":"PPL",
    "qs:gn_local":4744091,
    "qs:gn_nam_loc":"Alexandria, Alexandria, City of Alexandria, Virginia, US",
    "qs:gn_namadm1":"VA",
    "qs:gn_name":"Waldon Woods",
    "qs:local_max":10517,
    "qs:local_sum":43062,
    "qs:localhoods":58,
    "qs:name":"Waldon Woods",
    "qs:name_adm0":"United States",
    "qs:name_adm1":"Virginia",
    "qs:name_adm2":"Fairfax",
    "qs:name_local":"Alexandria",
    "qs:photo_max":1,
    "qs:photo_sum":1,
    "qs:placetype":"Suburb",
    "qs:quad_count":1,
    "qs:woe_adm0":23424977,
    "qs:woe_adm1":2347605,
    "qs:woe_adm2":12590343,
    "qs:woe_lau":0,
    "qs:woe_local":2353019,
    "qs:woe_ver":"7.10.0",
    "qs_pg:aaroncc":"US",
    "qs_pg:gn_country":"US",
    "qs_pg:gn_fcode":"PPL",
    "qs_pg:gn_pop":0,
    "qs_pg:name":"Waldon Woods",
    "qs_pg:name_adm0":"United States",
    "qs_pg:name_adm1":"Virginia",
    "qs_pg:photos":197,
    "qs_pg:photos_1k":40,
    "qs_pg:photos_9k":1,
    "qs_pg:photos_9r":4,
    "qs_pg:photos_all":197,
    "qs_pg:photos_sr":4,
    "qs_pg:pop_sr":0,
    "qs_pg:qs_pg_placetype":"neighbourhood",
    "qs_pg:qs_pg_placetype_gp":"Suburb",
    "qs_pg:woe_adm0":23424977,
    "wof:lang":[
        "eng"
    ],
    "wof:name":"Waldon Woods",
    "wof:placetype":"neighbourhood",
    "wof:population":750,
    "zs:blockids":[
        510594159002015,
        510594159002022,
        510594159002021,
        510594159001006,
        510594159002020,
        510594159002019,
        510594159001015,
        510594159001004,
        510594159002023,
        510594159001005,
        510594159002017,
        510594159001007,
        510594159002018
    ],
    "zs:housing10":300,
    "zs:pop10":750
},
  "geometry": {"coordinates":[-77.088318,38.717663],"type":"Point"}
}