{
  "type": "Feature",
  "properties": {
    "iso:country":"US",
    "name:bul_x_preferred":[
        "\u0421\u043b\u0438\u0439\u043f\u0438 \u0425\u043e\u043b\u043e\u0443"
    ],
    "name:cat_x_preferred":[
        "Sleepy Hollow"
    ],
    "name:ceb_x_preferred":[
        "Sleepy Hollow"
    ],
    "name:cym_x_preferred":[
        "Sleepy Hollow"
    ],
    "name:dan_x_preferred":[
        "Sleepy Hollow"
    ],
    "name:deu_x_preferred":[
        "Sleepy Hollow"
    ],
    "name:eng_x_preferred":[
        "Sleepy Hollow"
    ],
    "name:fas_x_preferred":[
        "\u0627\u0633\u0644\u06cc\u067e\u06cc \u0647\u0627\u0644\u0648"
    ],
    "name:fin_x_preferred":[
        "Sleepy Hollow"
    ],
    "name:fra_x_preferred":[
        "Sleepy Hollow"
    ],
    "name:ita_x_preferred":[
        "Sleepy Hollow"
    ],
    "name:kor_x_preferred":[
        "\uc2ac\ub9ac\ud53c \ud640\ub85c"
    ],
    "name:nld_x_preferred":[
        "Sleepy Hollow"
    ],
    "name:nor_x_preferred":[
        "Sleepy Hollow"
    ],
    "name:pol_x_preferred":[
        "Sleepy Hollow"
    ],
    "name:por_x_preferred":[
        "Sleepy Hollow"
    ],
    "name:ron_x_preferred":[
        "Sleepy Hollow"
    ],
    "name:rus_x_preferred":[
        "\u0421\u043b\u0438\u043f\u0438-\u0425\u043e\u043b\u043b\u043e\u0443"
    ],
    "name:spa_x_preferred":[
        "Sleepy Hollow"
    ],
    "name:srp_x_preferred":[
        "\u0421\u043b\u0438\u043f\u0438 \u0425\u043e\u043b\u043e\u0443"
    ],
    "name:swe_x_preferred":[
        "Sleepy Hollow"
    ],
    "name:vol_x_preferred":[
        "Sleepy Hollow"
    ],
    "wof:name":"Sleepy Hollow",
    "wof:placetype":"neighbourhood",
    "wof:population":180,
    "zs:area_m":243629.111754,
    "zs:blockids":[
        120570122072012,
        120570121063042,
        120570122071000,
        120570122072011,
        120570121081017
    ],
    "zs:housing10":74,
    "zs:label":"Sleepy Hollow",
    "zs:pop10":180
},
  "geometry": {"coordinates":[-82.27900200000001,27.980719],"type":"Point"}
}