{
  "type": "Feature",
  "properties": {
    "gn:gn_country":"US",
    "gn:gn_fcode":"PPL",
    "gn:gn_pop":0,
    "iso:country":"US",
    "name:eng_x_preferred":[
        "Cataumet Station"
    ],
    "name:eng_x_variant":[
        "Cataumet Train Station"
    ],
    "qs_pg:aaroncc":"US",
    "qs_pg:gn_country":"US",
    "qs_pg:gn_fcode":"PPL",
    "qs_pg:gn_pop":0,
    "qs_pg:name":"Cataumet Station",
    "qs_pg:name_adm0":"United States",
    "qs_pg:name_adm1":"Massachusetts",
    "qs_pg:photos":11,
    "qs_pg:photos_1k":2,
    "qs_pg:photos_9k":1,
    "qs_pg:photos_9r":1,
    "qs_pg:photos_all":11,
    "qs_pg:photos_sr":1,
    "qs_pg:pop_sr":0,
    "qs_pg:qs_pg_placetype":"neighbourhood",
    "qs_pg:qs_pg_placetype_gp":"Suburb",
    "qs_pg:woe_adm0":23424977,
    "wd:wordcount":117,
    "wof:name":"Cataumet Station",
    "wof:placetype":"neighbourhood",
    "wof:population":253,
    "zs:area_m":940598.931947,
    "zs:blockids":[
        250010140024051,
        250010140024041,
        250010140024032,
        250010140024031,
        250010140024046,
        250010140024047,
        250010140024030,
        250010140024028,
        250010140024035,
        250010140024045,
        250010140024036,
        250010140024044,
        250010140024040,
        250010140024026,
        250010140024048,
        250010140024034,
        250010140024033,
        250010140024049,
        250010140024050,
        250010140024029
    ],
    "zs:housing10":156,
    "zs:label":"Cataumet Station",
    "zs:pop10":253
},
  "geometry": {"coordinates":[-70.610986,41.662179],"type":"Point"}
}