{
  "type": "Feature",
  "properties": {
    "gn:admin1_code":"IA",
    "gn:admin2_code":"61.0",
    "gn:admin3_code":"93024.0",
    "gn:asciiname":"Massey",
    "gn:country_code":"US",
    "gn:dem":199,
    "gn:elevation":"197.0",
    "gn:feature_class":"P",
    "gn:feature_code":"PPL",
    "gn:name":"Massey",
    "gn:population":0,
    "gn:timezone":"America/Chicago",
    "iso:country":"US",
    "name:deu_x_preferred":[
        "Massey"
    ],
    "name:fra_x_preferred":[
        "Massey"
    ],
    "name:heb_x_preferred":[
        "\u05de\u05d0\u05e1\u05d9"
    ],
    "name:ita_x_preferred":[
        "Massey"
    ],
    "name:jpn_x_preferred":[
        "\u30de\u30c3\u30bb\u30a4"
    ],
    "name:nld_x_preferred":[
        "Massey"
    ],
    "name:pol_x_preferred":[
        "Massey"
    ],
    "name:por_x_preferred":[
        "Massey"
    ],
    "name:spa_x_preferred":[
        "Massey"
    ],
    "name:ukr_x_preferred":[
        "\u041c\u0430\u0441\u0441\u0435"
    ],
    "wof:name":"Massey",
    "wof:placetype":"locality"
},
  "geometry": {"coordinates":[-90.58513000000001,42.43028],"type":"Point"}
}