{
  "type": "Feature",
  "properties": {
    "gn:admin1_code":"WA",
    "gn:admin2_code":"47.0",
    "gn:asciiname":"Koontzville",
    "gn:country_code":"US",
    "gn:dem":313,
    "gn:elevation":"319.0",
    "gn:feature_class":"P",
    "gn:feature_code":"PPL",
    "gn:name":"Koontzville",
    "gn:population":0,
    "gn:timezone":"America/Los_Angeles",
    "iso:country":"US",
    "name:eng_x_preferred":[
        "Koontzville"
    ],
    "name:und_x_variant":[
        "Kootzville"
    ],
    "wof:name":"Koontzville",
    "wof:placetype":"locality"
},
  "geometry": {"coordinates":[-118.94723999999999,48.01571],"type":"Point"}
}