{
  "type": "Feature",
  "properties": {
    "gn:admin1_code":"VA",
    "gn:admin2_code":"75",
    "gn:asciiname":"Oaklands",
    "gn:country_code":"US",
    "gn:dem":88,
    "gn:elevation":"76.0",
    "gn:feature_class":"P",
    "gn:feature_code":"PPL",
    "gn:name":"Oaklands",
    "gn:population":0,
    "gn:timezone":"America/New_York",
    "iso:country":"US",
    "name:deu_x_preferred":[
        "Oaklands"
    ],
    "name:swe_x_preferred":[
        "Oaklands"
    ],
    "wof:name":"Oaklands",
    "wof:placetype":"locality"
},
  "geometry": {"coordinates":[-77.85250000000001,37.69181],"type":"Point"}
}