{
  "type": "Feature",
  "properties": {
    "gn:admin1_code":"MI",
    "gn:admin2_code":"21",
    "gn:admin3_code":"7400.0",
    "gn:asciiname":"North Shore Estates Mobile Home Park",
    "gn:country_code":"US",
    "gn:dem":209,
    "gn:elevation":"207.0",
    "gn:feature_class":"P",
    "gn:feature_code":"PPL",
    "gn:name":"North Shore Estates Mobile Home Park",
    "gn:population":0,
    "gn:timezone":"America/Detroit",
    "iso:country":"US",
    "wof:name":"North Shore Estates Mobile Home Park",
    "wof:placetype":"campus"
},
  "geometry": {"coordinates":[-86.4525,42.1425],"type":"Point"}
}