{
  "type": "Feature",
  "properties": {
    "gn:admin1_code":"WY",
    "gn:admin2_code":"1.0",
    "gn:asciiname":"Mountain Home",
    "gn:country_code":"US",
    "gn:dem":2680,
    "gn:elevation":"2673.0",
    "gn:feature_class":"P",
    "gn:feature_code":"PPL",
    "gn:name":"Mountain Home",
    "gn:population":0,
    "gn:timezone":"America/Denver",
    "iso:country":"US",
    "name:ceb_x_preferred":[
        "Mountain Home"
    ],
    "name:deu_x_preferred":[
        "Mountain Home"
    ],
    "name:fra_x_preferred":[
        "Mountain Home"
    ],
    "name:ita_x_preferred":[
        "Mountain Home"
    ],
    "name:nld_x_preferred":[
        "Mountain Home"
    ],
    "name:pol_x_preferred":[
        "Mountain Home"
    ],
    "name:por_x_preferred":[
        "Mountain Home"
    ],
    "name:rus_x_preferred":[
        "\u041c\u0430\u0443\u043d\u0442\u0438\u043d-\u0425\u043e\u043c"
    ],
    "name:srp_x_preferred":[
        "\u041c\u0430\u0443\u043d\u0442\u0438\u043d \u0425\u043e\u0443\u043c"
    ],
    "name:swe_x_preferred":[
        "Mountain Home"
    ],
    "name:ukr_x_preferred":[
        "\u041c\u0430\u0443\u043d\u0442\u0435\u043d-\u0413\u043e\u0443\u043c"
    ],
    "name:vol_x_preferred":[
        "Mountain Home"
    ],
    "wof:name":"Mountain Home",
    "wof:placetype":"locality"
},
  "geometry": {"coordinates":[-106.17252000000001,41.00803],"type":"Point"}
}