{
  "type": "Feature",
  "properties": {
    "gn:admin1_code":"OH",
    "gn:admin2_code":"129",
    "gn:admin3_code":"70184.0",
    "gn:asciiname":"Stringtown",
    "gn:country_code":"US",
    "gn:dem":251,
    "gn:elevation":"253.0",
    "gn:feature_class":"P",
    "gn:feature_code":"PPL",
    "gn:name":"Stringtown",
    "gn:population":0,
    "gn:timezone":"America/New_York",
    "iso:country":"US",
    "name:deu_x_preferred":[
        "Stringtown"
    ],
    "name:eng_x_preferred":[
        "Stringtown"
    ],
    "name:und_x_variant":[
        "String Town"
    ],
    "name:vol_x_preferred":[
        "Stringtown"
    ],
    "wof:name":"Stringtown",
    "wof:placetype":"locality"
},
  "geometry": {"coordinates":[-82.77405999999998,39.5034],"type":"Point"}
}