{
  "type": "Feature",
  "properties": {
    "gn:elevation":1536,
    "iso:country":"US",
    "name:arz_x_preferred":[
        "\u0645\u0637\u0627\u0631 \u062a\u0634\u0627\u0644\u064a\u0633"
    ],
    "name:ceb_x_preferred":[
        "Challis Airport"
    ],
    "name:eng_x_preferred":[
        "Challis Airport"
    ],
    "name:eng_x_variant":[
        "LLJ",
        "CHL",
        "KLLJ"
    ],
    "name:fas_x_preferred":[
        "\u0641\u0631\u0648\u062f\u06af\u0627\u0647 \u0634\u0644\u06cc"
    ],
    "name:ron_x_preferred":[
        "Aeroportul Challis"
    ],
    "name:tgk_x_preferred":[
        "\u0424\u0443\u0440\u0443\u0434\u0433\u043e\u04b3\u0438 \u0448\u0443\u043b"
    ],
    "name:urd_x_preferred":[
        "\u0634\u0627\u0644\u06cc \u06c1\u0648\u0627\u0626\u06cc \u0627\u0688\u0627"
    ],
    "name:zho_x_preferred":[
        "\u67e5\u5229\u65af\u6a5f\u5834"
    ],
    "oa:elevation_ft":"5072",
    "oa:type":"small_airport",
    "wd:wordcount":199,
    "woe:hierarchy":{
        "country_id":23424977,
        "county_id":12588052,
        "planet_id":1,
        "state_id":2347571
    },
    "wof:name":"Challis Airport",
    "wof:placetype":"campus"
},
  "geometry": {"coordinates":[-114.218002,44.522999],"type":"Point"}
}