{
  "type": "Feature",
  "properties": {
    "iso:country":"US",
    "name:ceb_x_preferred":[
        "Groesbeck"
    ],
    "name:deu_x_preferred":[
        "Groesbeck"
    ],
    "name:eng_x_preferred":[
        "Groesbeck"
    ],
    "name:fra_x_preferred":[
        "Groesbeck"
    ],
    "name:hbs_x_preferred":[
        "Grozbek"
    ],
    "name:ita_x_preferred":[
        "Groesbeck"
    ],
    "name:nld_x_preferred":[
        "Groesbeck"
    ],
    "name:pol_x_preferred":[
        "Groesbeck"
    ],
    "name:por_x_preferred":[
        "Groesbeck"
    ],
    "name:srp_x_preferred":[
        "\u0413\u0440\u043e\u0437\u0431\u0435\u043a"
    ],
    "name:ukr_x_preferred":[
        "\u0413\u0440\u043e\u0435\u0441\u0431\u0435\u043a"
    ],
    "qs:gn_local":0,
    "qs:local_max":18459,
    "qs:local_sum":37660,
    "qs:localhoods":26,
    "qs:name":"Groesbeck",
    "qs:name_adm0":"United States",
    "qs:name_adm1":"Michigan",
    "qs:name_adm2":"Ingham",
    "qs:name_local":"Lansing",
    "qs:photo_max":181,
    "qs:photo_sum":725,
    "qs:placetype":"Suburb",
    "qs:quad_count":64,
    "qs:woe_adm0":23424977,
    "qs:woe_adm1":2347581,
    "qs:woe_adm2":12588746,
    "qs:woe_lau":0,
    "qs:woe_local":2436453,
    "qs:woe_ver":"7.10.0",
    "wd:wordcount":70,
    "wof:lang":[
        "eng"
    ],
    "wof:name":"Groesbeck",
    "wof:placetype":"neighbourhood",
    "wof:population":216,
    "zs:blockids":[
        260370101041137,
        260370101041146,
        260370112002002,
        260370101041106,
        260370101041135,
        260370101041112,
        260370112002003
    ],
    "zs:housing10":135,
    "zs:pop10":216
},
  "geometry": {"coordinates":[-84.503277,42.756322],"type":"Point"}
}