{
  "type": "Feature",
  "properties": {
    "iso:country":"US",
    "name:eng_x_preferred":[
        "Villages at Weston Place"
    ],
    "wof:name":"Villages at Weston Place",
    "wof:placetype":"neighbourhood",
    "wof:population":1676,
    "zs:area_m":2813190.430961,
    "zs:blockids":[
        180571110011072,
        180571110011068,
        180571110011084,
        180571110011056,
        180571110011050,
        180571110011062,
        180571110011060,
        180571110011073,
        180571110011066,
        180571110011086,
        180571110011067,
        180571110011079,
        180571110011059,
        180571110011063,
        180571110011076,
        180571110011080,
        180571110011054,
        180571110011074,
        180571110011083,
        180571110011077,
        180571110011061,
        180571110011078,
        180571110011069,
        180571110011055,
        180571110011085,
        180571110011081,
        180571110011075,
        180571110011082,
        180571110011071
    ],
    "zs:housing10":622,
    "zs:label":"Villages at Weston Place",
    "zs:pop10":1676
},
  "geometry": {"coordinates":[-86.228945,39.948173],"type":"Point"}
}