{
  "type": "Feature",
  "properties": {
    "gn:admin1_code":"TX",
    "gn:admin2_code":"215.0",
    "gn:asciiname":"Bustamante Colonia",
    "gn:country_code":"US",
    "gn:dem":20,
    "gn:elevation":"19.0",
    "gn:feature_class":"P",
    "gn:feature_code":"PPL",
    "gn:name":"Bustamante Colonia",
    "gn:population":0,
    "gn:timezone":"America/Chicago",
    "iso:country":"US",
    "name:eng_x_preferred":[
        "Bustamante Colonia"
    ],
    "name:und_x_variant":[
        "Olympia Colonia",
        "Bustamante Subdivision Colonia"
    ],
    "wof:name":"Bustamante Colonia",
    "wof:placetype":"locality"
},
  "geometry": {"coordinates":[-97.87917,26.10424],"type":"Point"}
}