{
  "type": "Feature",
  "properties": {
    "gn:admin1_code":"WV",
    "gn:admin2_code":"73.0",
    "gn:asciiname":"Wiley",
    "gn:country_code":"US",
    "gn:dem":262,
    "gn:elevation":"261.0",
    "gn:feature_class":"P",
    "gn:feature_code":"PPL",
    "gn:name":"Wiley",
    "gn:population":0,
    "gn:timezone":"America/New_York",
    "iso:country":"US",
    "name:deu_x_preferred":[
        "Wiley"
    ],
    "name:fin_x_preferred":[
        "Wiley"
    ],
    "name:fra_x_preferred":[
        "Wiley"
    ],
    "name:heb_x_preferred":[
        "\u05d5\u05d9\u05d9\u05dc\u05d9"
    ],
    "name:ita_x_preferred":[
        "Wiley"
    ],
    "name:jpn_x_preferred":[
        "Wiley"
    ],
    "name:nld_x_preferred":[
        "Wiley"
    ],
    "name:pol_x_preferred":[
        "Wiley"
    ],
    "name:por_x_preferred":[
        "Wiley"
    ],
    "name:rus_x_preferred":[
        "\u0423\u0430\u0439\u043b\u0438"
    ],
    "name:slk_x_preferred":[
        "Wiley"
    ],
    "wof:name":"Wiley",
    "wof:placetype":"locality"
},
  "geometry": {"coordinates":[-81.12539,39.33035],"type":"Point"}
}