{
  "type": "Feature",
  "properties": {
    "gn:admin1_code":"AL",
    "gn:admin2_code":"37",
    "gn:asciiname":"Cottage Grove",
    "gn:country_code":"US",
    "gn:dem":227,
    "gn:elevation":"219.0",
    "gn:feature_class":"P",
    "gn:feature_code":"PPL",
    "gn:name":"Cottage Grove",
    "gn:population":0,
    "gn:timezone":"America/Chicago",
    "iso:country":"US",
    "name:ceb_x_preferred":[
        "Cottage Grove"
    ],
    "name:deu_x_preferred":[
        "Cottage Grove"
    ],
    "name:fra_x_preferred":[
        "Cottage Grove"
    ],
    "name:hun_x_preferred":[
        "Cottage Grove"
    ],
    "name:ido_x_preferred":[
        "Cottage Grove"
    ],
    "name:ita_x_preferred":[
        "Cottage Grove"
    ],
    "name:kor_x_preferred":[
        "\ucf54\ud2f0\uc9c0\uadf8\ub85c\ube0c"
    ],
    "name:nld_x_preferred":[
        "Cottage Grove"
    ],
    "name:pol_x_preferred":[
        "Cottage Grove"
    ],
    "name:por_x_preferred":[
        "Cottage Grove"
    ],
    "name:rus_x_preferred":[
        "\u041a\u043e\u0442\u0442\u0438\u0434\u0436-\u0413\u0440\u043e\u0432"
    ],
    "name:srp_x_preferred":[
        "\u041a\u043e\u0442\u0438\u045f \u0413\u0440\u043e\u0443\u0432"
    ],
    "name:vol_x_preferred":[
        "Cottage Grove"
    ],
    "wof:name":"Cottage Grove",
    "wof:placetype":"locality"
},
  "geometry": {"coordinates":[-86.12246999999998,32.85568],"type":"Point"}
}