{
  "type": "Feature",
  "properties": {
    "gn:admin1_code":"NE",
    "gn:admin2_code":"25.0",
    "gn:asciiname":"Mynard",
    "gn:country_code":"US",
    "gn:dem":333,
    "gn:elevation":"332.0",
    "gn:feature_class":"P",
    "gn:feature_code":"PPL",
    "gn:name":"Mynard",
    "gn:population":0,
    "gn:timezone":"America/Chicago",
    "iso:country":"US",
    "wof:name":"Mynard",
    "wof:placetype":"locality"
},
  "geometry": {"coordinates":[-95.9239,40.97361],"type":"Point"}
}