{
  "type": "Feature",
  "properties": {
    "iso:country":"US",
    "name:eng_x_preferred":[
        "Great Works"
    ],
    "name:und_x_variant":[
        "Assabumbadock Falls"
    ],
    "qs:gn_adm0_cc":"US",
    "qs:gn_fcode":"PPL",
    "qs:gn_local":4979050,
    "qs:gn_nam_loc":"South Berwick, York, Maine, US",
    "qs:gn_namadm1":"ME",
    "qs:gn_name":"Great Works",
    "qs:local_max":143,
    "qs:local_sum":161,
    "qs:localhoods":2,
    "qs:name":"Great Works",
    "qs:name_adm0":"United States",
    "qs:name_adm1":"Maine",
    "qs:name_adm2":"York",
    "qs:name_local":"South Berwick",
    "qs:photo_max":59,
    "qs:photo_sum":143,
    "qs:placetype":"Suburb",
    "qs:quad_count":17,
    "qs:woe_adm0":23424977,
    "qs:woe_adm1":2347578,
    "qs:woe_adm2":12588675,
    "qs:woe_lau":0,
    "qs:woe_local":2495990,
    "qs:woe_ver":"7.10.0",
    "wof:lang":[
        "eng"
    ],
    "wof:name":"Great Works",
    "wof:placetype":"neighbourhood",
    "wof:population":2027,
    "zs:blockids":[
        230310350004007,
        230310350001059,
        230310350001063,
        230310350002036,
        230310350004020,
        230310350001060,
        230310350004019,
        230310350002031,
        230310350004015,
        230310350002016,
        230310350002037,
        230310350004027,
        230310350004003,
        230310350002022,
        230310350002034,
        230310350001061,
        230310350004011,
        230310350004021,
        230310350004028,
        230310350004018,
        230310350004002,
        230310350002020,
        230310350002017,
        230310350004024,
        230310350002030,
        230310350002032,
        230310350004001,
        230310350004017,
        230310350002018,
        230310350002029,
        230310350002027,
        230310350004012,
        230310350002015,
        230310350004026,
        230310350002035,
        230310350002025,
        230310350002024,
        230310350002042,
        230310350002028,
        230310350002019,
        230310350004005,
        230310350002026,
        230310350002023,
        230310350001058,
        230310350001057,
        230310350002021,
        230310350004016,
        230310350004006,
        230310350004025
    ],
    "zs:housing10":803,
    "zs:pop10":2027
},
  "geometry": {"coordinates":[-70.806346,43.21594],"type":"Point"}
}