{
  "type": "Feature",
  "properties": {
    "gn:admin1_code":"DE",
    "gn:admin2_code":"3.0",
    "gn:asciiname":"Radnor Green",
    "gn:country_code":"US",
    "gn:dem":50,
    "gn:elevation":"43.0",
    "gn:feature_class":"P",
    "gn:feature_code":"PPL",
    "gn:name":"Radnor Green",
    "gn:population":0,
    "gn:timezone":"America/New_York",
    "iso:country":"US",
    "wof:name":"Radnor Green",
    "wof:placetype":"locality"
},
  "geometry": {"coordinates":[-75.4727,39.80845],"type":"Point"}
}