{
  "type": "Feature",
  "properties": {
    "gn:admin1_code":"GA",
    "gn:admin2_code":"313.0",
    "gn:asciiname":"Callaway Mill",
    "gn:country_code":"US",
    "gn:dem":247,
    "gn:elevation":"247.0",
    "gn:feature_class":"P",
    "gn:feature_code":"PPL",
    "gn:name":"Callaway Mill",
    "gn:population":0,
    "gn:timezone":"America/New_York",
    "iso:country":"US",
    "wof:name":"Callaway Mill",
    "wof:placetype":"locality"
},
  "geometry": {"coordinates":[-85.06023,34.83313],"type":"Point"}
}