{
  "type": "Feature",
  "properties": {
    "gn:elevation":1317,
    "iso:country":"US",
    "name:eng_x_preferred":[
        "H D Wise"
    ],
    "qs:gn_adm0_cc":"US",
    "qs:gn_fcode":"PPLX",
    "qs:gn_local":5779206,
    "qs:gn_nam_loc":"Ogden, Weber, Utah, US",
    "qs:gn_namadm1":"UT",
    "qs:gn_name":"H D Wise",
    "qs:local_max":3320,
    "qs:local_sum":9934,
    "qs:localhoods":47,
    "qs:name":"H D Wise",
    "qs:name_adm0":"United States",
    "qs:name_adm1":"Utah",
    "qs:name_adm2":"Weber",
    "qs:name_local":"Ogden",
    "qs:photo_max":283,
    "qs:photo_sum":712,
    "qs:placetype":"Suburb",
    "qs:quad_count":14,
    "qs:woe_adm0":23424977,
    "qs:woe_adm1":2347603,
    "qs:woe_adm2":12590289,
    "qs:woe_lau":0,
    "qs:woe_local":2464337,
    "qs:woe_ver":"7.10.0",
    "wof:lang":[
        "eng"
    ],
    "wof:name":"H D Wise",
    "wof:placetype":"neighbourhood",
    "wof:population":6733,
    "zs:blockids":[
        490572013012003,
        490572011001048,
        490572008003009,
        490572013023002,
        490572009002004,
        490572008002006,
        490572013011016,
        490572017001001,
        490572013023006,
        490572011001047,
        490572011001045,
        490572013012006,
        490572009001032,
        490572013012005,
        490572013023003,
        490572013011006,
        490572008003004,
        490572013023000,
        490572008003005,
        490572013011015,
        490572013023012,
        490572013021007,
        490572009001038,
        490572009002007,
        490572009003003,
        490572013012007,
        490572013011005,
        490572008003006,
        490572013012009,
        490572013023008,
        490572009002002,
        490572011001057,
        490572009003002,
        490572009003000,
        490572013012000,
        490572013023011,
        490572013012002,
        490572011001053,
        490572011001054,
        490572011001058,
        490572009002006,
        490572009003006,
        490572013021006,
        490572013023009,
        490572013011007,
        490572009002001,
        490572009002003,
        490572011001066,
        490572009003001,
        490572009003004,
        490572013011008,
        490572013023005,
        490572011001055,
        490572011001046,
        490572011001075,
        490572013012001,
        490572009001039,
        490572011001056,
        490572011001059,
        490572011001067,
        490572011001065,
        490572009003005,
        490572009003007,
        490572013012004,
        490572013012008,
        490572008003003,
        490572013023001,
        490572013023007
    ],
    "zs:housing10":3063,
    "zs:pop10":6733
},
  "geometry": {"coordinates":[-111.971457,41.222124],"type":"Point"}
}