{
  "type": "Feature",
  "properties": {
    "gn:admin1_code":"VA",
    "gn:admin2_code":"93.0",
    "gn:asciiname":"Battery Park",
    "gn:country_code":"US",
    "gn:dem":11,
    "gn:elevation":"7.0",
    "gn:feature_class":"P",
    "gn:feature_code":"PPL",
    "gn:name":"Battery Park",
    "gn:population":0,
    "gn:timezone":"America/New_York",
    "iso:country":"US",
    "name:eng_x_preferred":[
        "Battery Park"
    ],
    "name:fas_x_preferred":[
        "\u0628\u0627\u062a\u0631\u06cc \u067e\u0627\u0631\u06a9"
    ],
    "name:und_x_variant":[
        "Old Town",
        "Newport",
        "Patersville",
        "Batterypark",
        "Patesville"
    ],
    "wof:name":"Battery Park",
    "wof:placetype":"locality"
},
  "geometry": {"coordinates":[-76.57411999999999,36.99654],"type":"Point"}
}