{
  "type": "Feature",
  "properties": {
    "gn:country":"US",
    "gn:fcode":"PPL",
    "gn:population":0,
    "iso:country":"US",
    "name:cat_x_preferred":[
        "Confidence"
    ],
    "name:eng_x_preferred":[
        "Confidence"
    ],
    "name:fra_x_preferred":[
        "Confidence"
    ],
    "name:jpn_x_preferred":[
        "\u30b3\u30f3\u30d5\u30a3\u30c7\u30f3\u30b9"
    ],
    "name:por_x_preferred":[
        "Confidence"
    ],
    "name:spa_x_preferred":[
        "Confidence"
    ],
    "name:tur_x_preferred":[
        "Confidence"
    ],
    "name:vol_x_preferred":[
        "Confidence"
    ],
    "name:zho_x_preferred":[
        "\u5eb7\u83f2\u767b\u65af"
    ],
    "qs_pg:aaroncc":"US",
    "qs_pg:gn_country":"US",
    "qs_pg:gn_fcode":"PPL",
    "qs_pg:gn_pop":0,
    "qs_pg:name":"Confidence",
    "qs_pg:name_adm0":"United States",
    "qs_pg:name_adm1":"California",
    "qs_pg:photos":21,
    "qs_pg:photos_1k":4,
    "qs_pg:photos_9k":1,
    "qs_pg:photos_9r":1,
    "qs_pg:photos_all":21,
    "qs_pg:photos_sr":1,
    "qs_pg:pop_sr":0,
    "qs_pg:qs_pg_placetype":"locality",
    "qs_pg:qs_pg_placetype_gp":"Town",
    "qs_pg:woe_adm0":23424977,
    "woe:adm0_id":23424977,
    "woe:name_adm0":"United States",
    "woe:name_adm1":"California",
    "woe:placetype":"Town",
    "wof:name":"Confidence",
    "wof:placetype":"locality"
},
  "geometry": {"coordinates":[-120.2013,38.04742],"type":"Point"}
}