{
  "type": "Feature",
  "properties": {
    "gn:elevation":122,
    "iso:country":"US",
    "name:ceb_x_preferred":[
        "Locust Grove"
    ],
    "name:deu_x_preferred":[
        "Locust Grove"
    ],
    "name:eng_x_preferred":[
        "Locust Grove"
    ],
    "name:eng_x_variant":[
        "Locust Grv"
    ],
    "name:ita_x_preferred":[
        "Locust Grove"
    ],
    "name:nld_x_preferred":[
        "Locust Grove"
    ],
    "name:pol_x_preferred":[
        "Locust Grove"
    ],
    "name:por_x_preferred":[
        "Locust Grove"
    ],
    "name:srp_x_preferred":[
        "\u041b\u043e\u043a\u0443\u0441\u0442 \u0413\u0440\u043e\u0443\u0432"
    ],
    "name:vol_x_preferred":[
        "Locust Grove"
    ],
    "qs:gn_adm0_cc":"US",
    "qs:gn_fcode":"PPLX",
    "qs:gn_local":4752031,
    "qs:gn_nam_loc":"Charlottesville, Charlottesville, Virginia, US",
    "qs:gn_namadm1":"VA",
    "qs:gn_name":"Locust Grove",
    "qs:local_max":5518,
    "qs:local_sum":30406,
    "qs:localhoods":28,
    "qs:name":"Locust Grove",
    "qs:name_adm0":"United States",
    "qs:name_adm1":"Virginia",
    "qs:name_adm2":"Charlottesville City",
    "qs:name_local":"Charlottesville",
    "qs:photo_max":70,
    "qs:photo_sum":504,
    "qs:placetype":"Suburb",
    "qs:quad_count":31,
    "qs:woe_adm0":23424977,
    "qs:woe_adm1":2347605,
    "qs:woe_adm2":12590328,
    "qs:woe_lau":0,
    "qs:woe_local":2378489,
    "qs:woe_ver":"7.10.0",
    "wd:wordcount":269,
    "wof:lang":[
        "eng"
    ],
    "wof:name":"Locust Grove",
    "wof:placetype":"neighbourhood",
    "wof:population":2049,
    "zs:blockids":[
        515400009001000,
        515400009001019,
        515400009002018,
        515400009002019,
        515400009002001,
        515400009001016,
        515400009001011,
        515400009001008,
        515400009001020,
        515400009001012,
        515400009001005,
        515400009001010,
        515400009001015,
        515400009002004,
        515400009002005,
        515400009002017,
        515400009002003,
        515400009001002,
        515400009002006,
        515400009001013,
        515400009002002,
        515400009002014,
        515400009001025,
        515400009001009,
        515400009001017,
        515400009002016,
        515400009001007,
        515400009001022,
        515400009002000,
        515400009001004,
        515400009001018,
        515400009001006,
        515400009001003,
        515400009001001,
        515400009001021
    ],
    "zs:housing10":998,
    "zs:pop10":2049
},
  "geometry": {"coordinates":[-78.459194,38.044819],"type":"Point"}
}