{
  "type": "Feature",
  "properties": {
    "gn:country":"US",
    "gn:fcode":"PPL",
    "gn:population":0,
    "iso:country":"US",
    "name:eng_x_preferred":[
        "Bowman Creek"
    ],
    "qs_pg:aaroncc":"US",
    "qs_pg:gn_country":"US",
    "qs_pg:gn_fcode":"PPL",
    "qs_pg:gn_pop":0,
    "qs_pg:name":"Bowman Creek",
    "qs_pg:name_adm0":"United States",
    "qs_pg:name_adm1":"Pennsylvania",
    "qs_pg:photos":3,
    "qs_pg:photos_1k":1,
    "qs_pg:photos_9k":1,
    "qs_pg:photos_9r":1,
    "qs_pg:photos_all":3,
    "qs_pg:photos_sr":1,
    "qs_pg:pop_sr":0,
    "qs_pg:qs_pg_placetype":"neighbourhood",
    "qs_pg:qs_pg_placetype_gp":"Suburb",
    "qs_pg:woe_adm0":23424977,
    "wd:wordcount":5050,
    "wof:name":"Bowman Creek",
    "wof:placetype":"neighbourhood",
    "wof:population":402,
    "zs:area_m":20600225.458277,
    "zs:blockids":[
        421314007002013,
        421314007002010,
        421314007002046,
        421314007002054,
        421314007002050,
        421314007002012,
        421314007002044,
        421314007002041,
        421314007002048,
        421314007002042,
        421314007002040,
        421314007002045,
        421314007002105,
        421314007002043,
        421314007002039,
        421314007002011,
        421314007002038,
        421314007002037
    ],
    "zs:housing10":180,
    "zs:label":"Bowman Creek",
    "zs:pop10":402
},
  "geometry": {"coordinates":[-76.02963800000001,41.444024],"type":"Point"}
}