{
  "type": "Feature",
  "properties": {
    "iso:country":"US",
    "name:eng_x_preferred":[
        "Ponderosa Valley"
    ],
    "qs:gn_adm0_cc":"US",
    "qs:gn_local":4881346,
    "qs:gn_nam_loc":"West Des Moines, Polk, Iowa, US",
    "qs:gn_namadm1":"IA",
    "qs:local_max":1646,
    "qs:local_sum":4232,
    "qs:localhoods":14,
    "qs:name":"Ponderosa Valley",
    "qs:name_adm0":"United States",
    "qs:name_adm1":"Iowa",
    "qs:name_adm2":"Polk",
    "qs:name_local":"West des Moines",
    "qs:photo_max":10,
    "qs:photo_sum":42,
    "qs:placetype":"Suburb",
    "qs:quad_count":7,
    "qs:woe_adm0":23424977,
    "qs:woe_adm1":2347574,
    "qs:woe_adm2":12588348,
    "qs:woe_lau":0,
    "qs:woe_local":2516909,
    "qs:woe_ver":"7.10.0",
    "wof:name":"Ponderosa Valley",
    "wof:placetype":"neighbourhood",
    "wof:population":234,
    "zs:blockids":[
        191530110262018,
        191530110262000
    ],
    "zs:housing10":67,
    "zs:pop10":234
},
  "geometry": {"coordinates":[-93.781729,41.567893],"type":"Point"}
}