{
  "type": "Feature",
  "properties": {
    "gn:elevation":1,
    "iso:country":"US",
    "name:eng_x_preferred":[
        "The Haystacks"
    ],
    "qs:gn_adm0_cc":"US",
    "qs:gn_fcode":"PPLX",
    "qs:gn_local":4480153,
    "qs:gn_nam_loc":"Morehead City, Carteret, North Carolina, US",
    "qs:gn_namadm1":"NC",
    "qs:gn_name":"The Haystacks",
    "qs:local_max":132,
    "qs:local_sum":429,
    "qs:localhoods":6,
    "qs:name":"The Haystacks",
    "qs:name_adm0":"United States",
    "qs:name_adm1":"North Carolina",
    "qs:name_adm2":"Carteret",
    "qs:name_local":"Morehead City",
    "qs:photo_max":67,
    "qs:photo_sum":71,
    "qs:placetype":"Suburb",
    "qs:quad_count":5,
    "qs:woe_adm0":23424977,
    "qs:woe_adm1":2347592,
    "qs:woe_adm2":12589389,
    "qs:woe_lau":0,
    "qs:woe_local":2453947,
    "qs:woe_ver":"7.10.0",
    "wof:lang":[
        "eng"
    ],
    "wof:name":"The Haystacks",
    "wof:placetype":"neighbourhood",
    "wof:population":50,
    "zs:blockids":[
        370319707041063,
        370319704033002,
        370319704033029,
        370319703022012,
        370319704022000,
        370319705041008,
        370319703022013,
        370319704033039,
        370319704022001,
        370319704033001,
        370319704033023,
        370319704022003,
        370319703031041,
        370319703031043,
        370319707041075,
        370319705041004,
        370319704033037,
        370319704033025,
        370319704033000,
        370319704022074,
        370319707041061,
        370319705041001,
        370319704033024,
        370319707041064,
        370319703022010,
        370319703031044,
        370319711021000,
        370319703031040,
        370319705041005,
        370319704033040,
        370319705041000,
        370319711021001,
        370319703031039
    ],
    "zs:housing10":100,
    "zs:pop10":50
},
  "geometry": {"coordinates":[-76.686098,34.723573],"type":"Point"}
}