{
  "type": "Feature",
  "properties": {
    "gn:admin1_code":"OH",
    "gn:admin2_code":"33.0",
    "gn:admin3_code":"84644.0",
    "gn:asciiname":"New Winchester",
    "gn:country_code":"US",
    "gn:dem":313,
    "gn:elevation":"315.0",
    "gn:feature_class":"P",
    "gn:feature_code":"PPL",
    "gn:name":"New Winchester",
    "gn:population":0,
    "gn:timezone":"America/New_York",
    "iso:country":"US",
    "name:eng_x_preferred":[
        "New Winchester"
    ],
    "name:und_x_variant":[
        "Winchester"
    ],
    "wof:name":"New Winchester",
    "wof:placetype":"locality"
},
  "geometry": {"coordinates":[-82.91906999999998,40.71895],"type":"Point"}
}