{
  "type": "Feature",
  "properties": {
    "gn:admin1_code":"IA",
    "gn:admin2_code":"127.0",
    "gn:admin3_code":"91749.0",
    "gn:asciiname":"Dunbar",
    "gn:country_code":"US",
    "gn:dem":283,
    "gn:elevation":"284.0",
    "gn:feature_class":"P",
    "gn:feature_code":"PPL",
    "gn:name":"Dunbar",
    "gn:population":0,
    "gn:timezone":"America/Chicago",
    "iso:country":"US",
    "wof:name":"Dunbar",
    "wof:placetype":"locality"
},
  "geometry": {"coordinates":[-92.79658999999999,41.94082],"type":"Point"}
}