{
  "type": "Feature",
  "properties": {
    "gn:admin1_code":"NH",
    "gn:admin2_code":"15.0",
    "gn:admin3_code":"66660.0",
    "gn:asciiname":"Millville",
    "gn:country_code":"US",
    "gn:dem":55,
    "gn:elevation":"44.0",
    "gn:feature_class":"P",
    "gn:feature_code":"PPL",
    "gn:name":"Millville",
    "gn:population":0,
    "gn:timezone":"America/New_York",
    "iso:country":"US",
    "name:bul_x_preferred":[
        "\u041c\u0438\u043b\u0432\u0438\u043b"
    ],
    "name:cat_x_preferred":[
        "Millville"
    ],
    "name:ceb_x_preferred":[
        "Millville"
    ],
    "name:ces_x_preferred":[
        "Millville"
    ],
    "name:deu_x_preferred":[
        "Millville"
    ],
    "name:fra_x_preferred":[
        "Millville"
    ],
    "name:ita_x_preferred":[
        "Millville"
    ],
    "name:nld_x_preferred":[
        "Millville"
    ],
    "name:pol_x_preferred":[
        "Millville"
    ],
    "name:por_x_preferred":[
        "Millville"
    ],
    "name:rus_x_preferred":[
        "\u041c\u0438\u043b\u0432\u0438\u043b\u043b"
    ],
    "name:srp_x_preferred":[
        "\u041c\u0438\u043b\u0432\u0438\u043b"
    ],
    "name:swe_x_preferred":[
        "Millville"
    ],
    "name:vol_x_preferred":[
        "Millville"
    ],
    "wof:name":"Millville",
    "wof:placetype":"locality"
},
  "geometry": {"coordinates":[-71.2145,42.80259],"type":"Point"}
}