{
  "type": "Feature",
  "properties": {
    "iso:country":"US",
    "name:eng_x_preferred":[
        "Cambridge Villas"
    ],
    "wof:name":"Cambridge Villas",
    "wof:placetype":"neighbourhood",
    "wof:population":16,
    "zs:area_m":169527.754222,
    "zs:blockids":[
        120570114143023
    ],
    "zs:housing10":8,
    "zs:label":"Cambridge Villas",
    "zs:pop10":16
},
  "geometry": {"coordinates":[-82.546114,28.039256],"type":"Point"}
}