{
  "type": "Feature",
  "properties": {
    "iso:country":"US",
    "name:eng_x_preferred":[
        "Highlands"
    ],
    "wof:name":"Highlands",
    "wof:placetype":"neighbourhood",
    "wof:population":285,
    "zs:area_m":275395.910467,
    "zs:blockids":[
        60590320342020,
        60590320342021,
        60590320351024,
        60590320373000,
        60590320342022
    ],
    "zs:housing10":192,
    "zs:label":"Highlands",
    "zs:pop10":285
},
  "geometry": {"coordinates":[-117.634827,33.62769],"type":"Point"}
}