{
  "type": "Feature",
  "properties": {
    "iso:country":"US",
    "name:eng_x_preferred":[
        "Chippewa"
    ],
    "qs:gn_adm0_cc":"US",
    "qs:gn_local":4221552,
    "qs:local_max":19077,
    "qs:local_sum":44761,
    "qs:localhoods":36,
    "qs:name":"Chippewa",
    "qs:name_adm0":"United States",
    "qs:name_adm1":"Georgia",
    "qs:name_adm2":"Chatham",
    "qs:name_local":"Savannah",
    "qs:photo_max":26,
    "qs:photo_sum":109,
    "qs:placetype":"Suburb",
    "qs:quad_count":10,
    "qs:woe_adm0":23424977,
    "qs:woe_adm1":2347569,
    "qs:woe_adm2":12587894,
    "qs:woe_lau":0,
    "qs:woe_local":2489314,
    "qs:woe_ver":"7.10.0",
    "wof:lang":[
        "eng"
    ],
    "wof:name":"Chippewa",
    "wof:placetype":"neighbourhood",
    "zs:blockids":[
        130510042071001,
        130510040024010,
        130510042071000,
        130510040024009,
        130510040024011
    ],
    "zs:housing10":0,
    "zs:pop10":0
},
  "geometry": {"coordinates":[-81.123848,32.001],"type":"Point"}
}