{
  "type": "Feature",
  "properties": {
    "gn:admin1_code":"NY",
    "gn:admin2_code":"105.0",
    "gn:admin3_code":"49847.0",
    "gn:asciiname":"Grahamsville",
    "gn:country_code":"US",
    "gn:dem":288,
    "gn:elevation":"295.0",
    "gn:feature_class":"P",
    "gn:feature_code":"PPL",
    "gn:name":"Grahamsville",
    "gn:population":0,
    "gn:timezone":"America/New_York",
    "iso:country":"US",
    "name:azb_x_preferred":[
        "\u0642\u0631\u0627\u0647\u0627\u0645\u0632\u0648\u06cc\u0644"
    ],
    "name:eng_x_preferred":[
        "Grahamsville"
    ],
    "name:fas_x_preferred":[
        "\u06af\u0631\u0627\u0647\u0627\u0645\u0632\u0648\u06cc\u0644"
    ],
    "name:spa_x_preferred":[
        "Grahamsville"
    ],
    "name:sqi_x_preferred":[
        "Grahamsville"
    ],
    "name:und_x_variant":[
        "Chestnut Woods"
    ],
    "wof:name":"Grahamsville",
    "wof:placetype":"locality"
},
  "geometry": {"coordinates":[-74.54793000000002,41.84787],"type":"Point"}
}