{
  "type": "Feature",
  "properties": {
    "gn:admin1_code":"NC",
    "gn:admin2_code":"65.0",
    "gn:asciiname":"Mildred",
    "gn:country_code":"US",
    "gn:dem":18,
    "gn:elevation":"14.0",
    "gn:feature_class":"P",
    "gn:feature_code":"PPL",
    "gn:name":"Mildred",
    "gn:population":0,
    "gn:timezone":"America/New_York",
    "iso:country":"US",
    "name:ita_x_preferred":[
        "Mildred"
    ],
    "name:jpn_x_preferred":[
        "\u30df\u30eb\u30c9\u30ec\u30c3\u30c9"
    ],
    "name:nld_x_preferred":[
        "Mildred"
    ],
    "name:pol_x_preferred":[
        "Mildred"
    ],
    "name:por_x_preferred":[
        "Mildred"
    ],
    "name:rus_x_preferred":[
        "\u041c\u0438\u043b\u0434\u0440\u0435\u0434"
    ],
    "name:srp_x_preferred":[
        "\u041c\u0438\u043b\u0434\u0440\u0435\u0434"
    ],
    "name:ukr_x_preferred":[
        "\u041c\u0430\u0439\u043b\u0434\u0440\u0435\u0434"
    ],
    "wof:name":"Mildred",
    "wof:placetype":"locality"
},
  "geometry": {"coordinates":[-77.49053000000001,35.84849000000001],"type":"Point"}
}