{
  "type": "Feature",
  "properties": {
    "gn:admin1_code":"NV",
    "gn:admin2_code":"27",
    "gn:asciiname":"Humboldt House",
    "gn:country_code":"US",
    "gn:dem":1295,
    "gn:elevation":"1288.0",
    "gn:feature_class":"P",
    "gn:feature_code":"PPL",
    "gn:name":"Humboldt House",
    "gn:population":0,
    "gn:timezone":"America/Los_Angeles",
    "iso:country":"US",
    "wof:name":"Humboldt House",
    "wof:placetype":"locality"
},
  "geometry": {"coordinates":[-118.25515,40.59991],"type":"Point"}
}