{
  "type": "Feature",
  "properties": {
    "iso:country":"US",
    "name:eng_x_preferred":[
        "Elliottson"
    ],
    "wof:name":"Elliottson",
    "wof:placetype":"neighbourhood",
    "wof:population":936,
    "zs:area_m":10833400.655885,
    "zs:blockids":[
        420410130001073,
        420410128001021,
        420410128001008,
        420410128001000,
        420410130001054,
        420410128001011,
        420410128001025,
        420410130001079,
        420410130001055,
        420410130001074,
        420410128001006,
        420410128001002,
        420410130001067,
        420410128001005,
        420410130001065,
        420410130001071,
        420410130001052,
        420410128001010,
        420410130001075,
        420410130001057,
        420410130001068,
        420410128001007,
        420410130001051,
        420410130001077,
        420410130001064,
        420410128001001,
        420410130001053,
        420410130001072,
        420410130001056,
        420410128001003,
        420410130001076,
        420410128001026,
        420410128001022,
        420410130001066,
        420410128001004,
        420410130001078
    ],
    "zs:housing10":381,
    "zs:label":"Elliottson",
    "zs:pop10":936
},
  "geometry": {"coordinates":[-77.27640700000001,40.225097],"type":"Point"}
}