{
  "type": "Feature",
  "properties": {
    "iso:country":"US",
    "name:eng_x_preferred":[
        "The Highlands"
    ],
    "wof:name":"The Highlands",
    "wof:placetype":"neighbourhood",
    "wof:population":5805,
    "zs:area_m":956080.872828,
    "zs:blockids":[
        250092055002008,
        250092062003007,
        250092062003004,
        250092052005010,
        250092052004000,
        250092052004006,
        250092062002001,
        250092062003008,
        250092055002009,
        250092052004008,
        250092062002007,
        250092062003006,
        250092062003010,
        250092052004009,
        250092055002005,
        250092062003002,
        250092055001094,
        250092052004001,
        250092052004002,
        250092052004004,
        250092055001096,
        250092055002004,
        250092055001048,
        250092052004005,
        250092052004010,
        250092055002002,
        250092052004015,
        250092052004007,
        250092062002004,
        250092062002002,
        250092062002003,
        250092055001095,
        250092052005011,
        250092055002000,
        250092055002010,
        250092052004003,
        250092052004011,
        250092055002003,
        250092052004013,
        250092062002000,
        250092052004014,
        250092062001001,
        250092062002005,
        250092062003009,
        250092055002001,
        250092062001000,
        250092062003003
    ],
    "zs:housing10":1993,
    "zs:label":"The Highlands",
    "zs:pop10":5805
},
  "geometry": {"coordinates":[-70.952457,42.47341],"type":"Point"}
}