{
  "type": "Feature",
  "properties": {
    "iso:country":"US",
    "qs_pg:aaroncc":"US",
    "qs_pg:name":"Vanburen",
    "qs_pg:name_adm0":"United States",
    "qs_pg:name_adm1":"Ohio",
    "qs_pg:photos":539,
    "qs_pg:photos_1k":109,
    "qs_pg:photos_9k":2,
    "qs_pg:photos_9r":5,
    "qs_pg:photos_all":539,
    "qs_pg:photos_sr":7,
    "qs_pg:pop_sr":0,
    "qs_pg:qs_pg_placetype":"locality",
    "qs_pg:qs_pg_placetype_gp":"Town",
    "qs_pg:woe_adm0":23424977,
    "woe:adm0_id":23424977,
    "woe:name_adm0":"United States",
    "woe:name_adm1":"Ohio",
    "woe:placetype":"Town",
    "wof:name":"Vanburen",
    "wof:placetype":"locality"
},
  "geometry": {"coordinates":[-82.41323199999999,39.976051],"type":"Point"}
}