{
  "type": "Feature",
  "properties": {
    "gn:admin1_code":"AZ",
    "gn:admin2_code":"13.0",
    "gn:asciiname":"Elmwood Trailer Park",
    "gn:country_code":"US",
    "gn:dem":372,
    "gn:elevation":"372.0",
    "gn:feature_class":"P",
    "gn:feature_code":"PPL",
    "gn:name":"Elmwood Trailer Park",
    "gn:population":0,
    "gn:timezone":"America/Phoenix",
    "iso:country":"US",
    "wof:name":"Elmwood Trailer Park",
    "wof:placetype":"campus"
},
  "geometry": {"coordinates":[-111.82986,33.30644],"type":"Point"}
}