{
  "type": "Feature",
  "properties": {
    "gn:admin1_code":"OH",
    "gn:admin2_code":"85.0",
    "gn:admin3_code":"40642.0",
    "gn:asciiname":"Parks Corner",
    "gn:country_code":"US",
    "gn:dem":321,
    "gn:elevation":"320.0",
    "gn:feature_class":"P",
    "gn:feature_code":"PPL",
    "gn:name":"Parks Corner",
    "gn:population":0,
    "gn:timezone":"America/New_York",
    "iso:country":"US",
    "wof:name":"Parks Corner",
    "wof:placetype":"locality"
},
  "geometry": {"coordinates":[-81.32816,41.61116],"type":"Point"}
}