{
  "type": "Feature",
  "properties": {
    "iso:country":"US",
    "name:ces_x_preferred":[
        "Honeyville"
    ],
    "name:deu_x_preferred":[
        "Honeyville"
    ],
    "name:eng_x_preferred":[
        "Honeyville"
    ],
    "wd:wordcount":10,
    "wof:name":"Honeyville",
    "wof:placetype":"neighbourhood",
    "wof:population":2567,
    "zs:area_m":61137735.74649,
    "zs:blockids":[
        360450624003034,
        360450618003018,
        360450618002025,
        360450618005005,
        360450618002028,
        360450618005029,
        360450618005015,
        360450618003017,
        360450618005042,
        360450618001103,
        360450618003012,
        360450618002013,
        360450618002018,
        360450618002047,
        360450618005001,
        360450618003013,
        360450618005012,
        360450618002030,
        360450618003021,
        360450618002032,
        360450618002033,
        360450618002041,
        360450618002040,
        360450618002038,
        360450618002036,
        360450618001094,
        360450624003052,
        360450624003051,
        360450624003035,
        360450624003053,
        360450618005011,
        360450618003023,
        360450618001118,
        360450618005000,
        360450618002024,
        360450618002045,
        360450618005047,
        360450618003025,
        360450618003038,
        360450618002043,
        360450618002046,
        360450618001109,
        360450618005008,
        360450618005002,
        360450618003015,
        360450618003019,
        360450618003024,
        360450618001106,
        360450618003037,
        360450624003037,
        360450618003002,
        360450624003050,
        360450618002020,
        360450618001121,
        360450618001108,
        360450618001102,
        360450618005003,
        360450618002031,
        360450618005028,
        360450618002027,
        360450618003014,
        360450618005018,
        360450618002034,
        360450618005039,
        360450618005036,
        360450618001117,
        360450618005037,
        360450624003036,
        360450618005014,
        360450618001095,
        360450618003022,
        360450618005040,
        360450618005038,
        360450618002037,
        360450618005041,
        360450618003016,
        360450618005006,
        360450618005010,
        360450618003004,
        360450618005030,
        360450618002042,
        360450618005046,
        360450618005048,
        360450618001093,
        360450618005009,
        360450618005017,
        360450618002044,
        360450618005016,
        360450618003011,
        360450618002029,
        360450618005004,
        360450618002035,
        360450618005013,
        360450618002039,
        360450618003005,
        360450618003020,
        360450618002019,
        360450618002026,
        360450618003003,
        360450618002017,
        360450618001107
    ],
    "zs:housing10":1006,
    "zs:label":"Honeyville",
    "zs:pop10":2567
},
  "geometry": {"coordinates":[-76.012844,43.865382],"type":"Point"}
}