{
  "type": "Feature",
  "properties": {
    "gn:admin1_code":"LA",
    "gn:admin2_code":"107.0",
    "gn:asciiname":"Alphenia Landing",
    "gn:country_code":"US",
    "gn:dem":17,
    "gn:elevation":"11.0",
    "gn:feature_class":"P",
    "gn:feature_code":"PPL",
    "gn:name":"Alphenia Landing",
    "gn:population":0,
    "gn:timezone":"America/Chicago",
    "iso:country":"US",
    "wof:name":"Alphenia Landing",
    "wof:placetype":"locality"
},
  "geometry": {"coordinates":[-91.57068,31.81961],"type":"Point"}
}