{
  "type": "Feature",
  "properties": {
    "gn:admin1_code":"DE",
    "gn:admin2_code":"1",
    "gn:asciiname":"Pheasant Point II",
    "gn:country_code":"US",
    "gn:dem":14,
    "gn:elevation":"17.0",
    "gn:feature_class":"P",
    "gn:feature_code":"PPL",
    "gn:name":"Pheasant Point II",
    "gn:population":0,
    "gn:timezone":"America/New_York",
    "iso:country":"US",
    "wof:name":"Pheasant Point II",
    "wof:placetype":"locality"
},
  "geometry": {"coordinates":[-75.63760000000001,39.2742],"type":"Point"}
}