{
  "type": "Feature",
  "properties": {
    "iso:country":"US",
    "name:ceb_x_preferred":[
        "Shipley"
    ],
    "name:deu_x_preferred":[
        "Shipley"
    ],
    "name:fra_x_preferred":[
        "Shipley"
    ],
    "name:ita_x_preferred":[
        "Shipley"
    ],
    "name:nld_x_preferred":[
        "Shipley"
    ],
    "name:pol_x_preferred":[
        "Shipley"
    ],
    "name:swe_x_preferred":[
        "Shipley"
    ],
    "qs_pg:aaroncc":"US",
    "qs_pg:name":"Shipley",
    "qs_pg:name_adm0":"United States",
    "qs_pg:name_adm1":"Arizona",
    "qs_pg:photos":237,
    "qs_pg:photos_1k":48,
    "qs_pg:photos_9k":1,
    "qs_pg:photos_9r":4,
    "qs_pg:photos_all":237,
    "qs_pg:photos_sr":4,
    "qs_pg:pop_sr":0,
    "qs_pg:qs_pg_placetype":"locality",
    "qs_pg:qs_pg_placetype_gp":"Town",
    "qs_pg:woe_adm0":23424977,
    "woe:adm0_id":23424977,
    "woe:name_adm0":"United States",
    "woe:name_adm1":"Arizona",
    "woe:placetype":"Town",
    "wof:name":"Shipley",
    "wof:placetype":"locality"
},
  "geometry": {"coordinates":[-113.569182,35.819866],"type":"Point"}
}