{
  "type": "Feature",
  "properties": {
    "gn:country":"US",
    "gn:fcode":"PPL",
    "gn:population":0,
    "iso:country":"US",
    "name:ara_x_preferred":[
        "\u0633\u0627\u0641\u0648\u0631\u062f"
    ],
    "name:azb_x_preferred":[
        "\u0633\u0641\u0648\u0631\u062f"
    ],
    "name:ben_x_preferred":[
        "\u09b8\u09cd\u09af\u09be\u09ab\u09cb\u09b0\u09cd\u09a1"
    ],
    "name:cym_x_preferred":[
        "Safford"
    ],
    "name:ell_x_preferred":[
        "\u03a3\u03ac\u03c6\u03bf\u03c1\u03bd\u03c4"
    ],
    "name:eng_x_preferred":[
        "Safford"
    ],
    "name:fas_x_preferred":[
        "\u0633\u0641\u0648\u0631\u062f"
    ],
    "name:fra_x_preferred":[
        "Safford"
    ],
    "name:hat_x_preferred":[
        "Safford"
    ],
    "name:hin_x_preferred":[
        "\u0938\u0948\u092b\u093c\u094b\u0930\u094d\u0921"
    ],
    "name:ind_x_preferred":[
        "Safford"
    ],
    "name:kor_x_preferred":[
        "\uc0c8\ud3ec\ub4dc"
    ],
    "name:spa_x_preferred":[
        "Safford"
    ],
    "name:ukr_x_preferred":[
        "\u0421\u0435\u0444\u0444\u043e\u0440\u0434"
    ],
    "name:und_x_variant":[
        "Safford Station"
    ],
    "name:urd_x_preferred":[
        "\u0633\u0641\u0641\u0648\u0631\u0688\u060c \u0627\u0644\u0628\u0627\u0645\u0627"
    ],
    "name:urd_x_variant":[
        "\u0633\u0641\u0641\u0648\u0631\u0688"
    ],
    "name:vie_x_preferred":[
        "Safford"
    ],
    "name:zho_x_preferred":[
        "\u85a9\u798f\u5fb7"
    ],
    "qs_pg:aaroncc":"US",
    "qs_pg:gn_country":"US",
    "qs_pg:gn_fcode":"PPL",
    "qs_pg:gn_pop":0,
    "qs_pg:name":"Safford",
    "qs_pg:name_adm0":"United States",
    "qs_pg:name_adm1":"Alabama",
    "qs_pg:photos_9r":0,
    "qs_pg:photos_sr":0,
    "qs_pg:pop_sr":5,
    "qs_pg:qs_pg_placetype":"locality",
    "qs_pg:qs_pg_placetype_gp":"Town",
    "qs_pg:woe_adm0":23424977,
    "woe:adm0_id":23424977,
    "woe:name_adm0":"United States",
    "woe:name_adm1":"Alabama",
    "woe:placetype":"Town",
    "wof:name":"Safford",
    "wof:placetype":"locality"
},
  "geometry": {"coordinates":[-87.37139000000001,32.28792],"type":"Point"}
}