{
  "type": "Feature",
  "properties": {
    "gn:admin1_code":"CA",
    "gn:admin2_code":"103.0",
    "gn:asciiname":"Peligreen Place",
    "gn:country_code":"US",
    "gn:dem":958,
    "gn:elevation":"960.0",
    "gn:feature_class":"P",
    "gn:feature_code":"PPL",
    "gn:name":"Peligreen Place",
    "gn:population":0,
    "gn:timezone":"America/Los_Angeles",
    "iso:country":"US",
    "wof:name":"Peligreen Place",
    "wof:placetype":"locality"
},
  "geometry": {"coordinates":[-121.78832,40.20877],"type":"Point"}
}