{
  "type": "Feature",
  "properties": {
    "gn:admin1_code":"PA",
    "gn:admin2_code":"85.0",
    "gn:admin3_code":"37416.0",
    "gn:asciiname":"Nesbit Corners",
    "gn:country_code":"US",
    "gn:dem":391,
    "gn:elevation":"390.0",
    "gn:feature_class":"P",
    "gn:feature_code":"PPL",
    "gn:name":"Nesbit Corners",
    "gn:population":0,
    "gn:timezone":"America/New_York",
    "iso:country":"US",
    "name:eng_x_preferred":[
        "Nesbit Corners"
    ],
    "name:und_x_variant":[
        "Nesbits Corners"
    ],
    "wof:name":"Nesbit Corners",
    "wof:placetype":"locality"
},
  "geometry": {"coordinates":[-80.12505999999998,41.27645],"type":"Point"}
}