{
  "type": "Feature",
  "properties": {
    "gn:admin1_code":"MD",
    "gn:admin2_code":"31.0",
    "gn:asciiname":"Sunnymeade",
    "gn:country_code":"US",
    "gn:dem":113,
    "gn:elevation":"111.0",
    "gn:feature_class":"P",
    "gn:feature_code":"PPL",
    "gn:name":"Sunnymeade",
    "gn:population":0,
    "gn:timezone":"America/New_York",
    "iso:country":"US",
    "wof:name":"Sunnymeade",
    "wof:placetype":"locality"
},
  "geometry": {"coordinates":[-77.04414,39.18955],"type":"Point"}
}