{
  "type": "Feature",
  "properties": {
    "gn:admin1_code":"FL",
    "gn:admin2_code":"86.0",
    "gn:asciiname":"Coes Trailer Court",
    "gn:country_code":"US",
    "gn:dem":10,
    "gn:elevation":"1.0",
    "gn:feature_class":"P",
    "gn:feature_code":"PPL",
    "gn:name":"Coes Trailer Court",
    "gn:population":0,
    "gn:timezone":"America/New_York",
    "iso:country":"US",
    "wof:name":"Coes Trailer Court",
    "wof:placetype":"locality"
},
  "geometry": {"coordinates":[-80.1484,25.9576],"type":"Point"}
}