{
  "type": "Feature",
  "properties": {
    "gn:admin1_code":"VT",
    "gn:admin2_code":"21.0",
    "gn:admin3_code":"44125.0",
    "gn:asciiname":"Brookwood Estates",
    "gn:country_code":"US",
    "gn:dem":288,
    "gn:elevation":"282.0",
    "gn:feature_class":"P",
    "gn:feature_code":"PPL",
    "gn:name":"Brookwood Estates",
    "gn:population":0,
    "gn:timezone":"America/New_York",
    "iso:country":"US",
    "wof:name":"Brookwood Estates",
    "wof:placetype":"locality"
},
  "geometry": {"coordinates":[-72.93205,43.6134],"type":"Point"}
}