{
  "type": "Feature",
  "properties": {
    "gn:admin1_code":"IN",
    "gn:admin2_code":"081",
    "gn:admin3_code":"83924.0",
    "gn:asciiname":"Cedar Hills",
    "gn:country_code":"US",
    "gn:dem":238,
    "gn:elevation":"233.0",
    "gn:feature_class":"P",
    "gn:feature_code":"PPL",
    "gn:name":"Cedar Hills",
    "gn:population":0,
    "gn:timezone":"America/Indiana/Indianapolis",
    "iso:country":"US",
    "name:ceb_x_preferred":[
        "Cedar Hills"
    ],
    "name:ces_x_preferred":[
        "Cedar Hills"
    ],
    "name:deu_x_preferred":[
        "Cedar Hills"
    ],
    "name:fra_x_preferred":[
        "Cedar Hills"
    ],
    "name:hun_x_preferred":[
        "Cedar Hills"
    ],
    "name:ita_x_preferred":[
        "Cedar Hills"
    ],
    "name:nld_x_preferred":[
        "Cedar Hills"
    ],
    "name:pol_x_preferred":[
        "Cedar Hills"
    ],
    "name:por_x_preferred":[
        "Cedar Hills"
    ],
    "name:srp_x_preferred":[
        "\u0421\u0438\u0434\u0435\u0440 \u0425\u0438\u043b\u0441"
    ],
    "name:vol_x_preferred":[
        "Cedar Hills"
    ],
    "wof:name":"Cedar Hills",
    "wof:placetype":"locality"
},
  "geometry": {"coordinates":[-86.17971999999997,39.56778],"type":"Point"}
}