{
  "type": "Feature",
  "properties": {
    "iso:country":"US",
    "name:eng_x_preferred":[
        "Hemingway Ridge"
    ],
    "wd:wordcount":54,
    "wof:name":"Hemingway Ridge",
    "wof:placetype":"neighbourhood",
    "wof:population":362,
    "zs:area_m":706804.001122,
    "zs:blockids":[
        51430101064019,
        51430101064018,
        51430101061015,
        51430101064017
    ],
    "zs:housing10":111,
    "zs:label":"Hemingway Ridge",
    "zs:pop10":362
},
  "geometry": {"coordinates":[-94.12994,36.10681],"type":"Point"}
}