{
  "type": "Feature",
  "properties": {
    "gn:admin1_code":"VA",
    "gn:admin2_code":"137",
    "gn:asciiname":"Nasons",
    "gn:country_code":"US",
    "gn:dem":145,
    "gn:elevation":"145.0",
    "gn:feature_class":"P",
    "gn:feature_code":"PPL",
    "gn:name":"Nasons",
    "gn:population":0,
    "gn:timezone":"America/New_York",
    "iso:country":"US",
    "name:eng_x_preferred":[
        "Nasons"
    ],
    "name:und_x_variant":[
        "Nason"
    ],
    "wof:name":"Nasons",
    "wof:placetype":"locality"
},
  "geometry": {"coordinates":[-78.02667,38.25513],"type":"Point"}
}