{
  "type": "Feature",
  "properties": {
    "gn:admin1_code":"NM",
    "gn:admin2_code":"15.0",
    "gn:asciiname":"Pierce Canyon Crossing",
    "gn:country_code":"US",
    "gn:dem":883,
    "gn:elevation":"882.0",
    "gn:feature_class":"P",
    "gn:feature_code":"PPL",
    "gn:name":"Pierce Canyon Crossing",
    "gn:population":0,
    "gn:timezone":"America/Denver",
    "iso:country":"US",
    "wof:name":"Pierce Canyon Crossing",
    "wof:placetype":"locality"
},
  "geometry": {"coordinates":[-103.97799000000001,32.18929],"type":"Point"}
}