{
  "type": "Feature",
  "properties": {
    "gn:admin1_code":"OK",
    "gn:admin2_code":"11",
    "gn:asciiname":"Carleton",
    "gn:country_code":"US",
    "gn:dem":493,
    "gn:elevation":"485.0",
    "gn:feature_class":"P",
    "gn:feature_code":"PPL",
    "gn:name":"Carleton",
    "gn:population":0,
    "gn:timezone":"America/Chicago",
    "iso:country":"US",
    "name:ceb_x_preferred":[
        "Carleton"
    ],
    "name:deu_x_preferred":[
        "Carleton"
    ],
    "name:fra_x_preferred":[
        "Carleton"
    ],
    "name:ita_x_preferred":[
        "Carleton"
    ],
    "name:nld_x_preferred":[
        "Carleton"
    ],
    "name:pol_x_preferred":[
        "Carleton"
    ],
    "name:por_x_preferred":[
        "Carleton"
    ],
    "name:rus_x_preferred":[
        "\u041a\u0430\u0440\u043b\u0442\u043e\u043d"
    ],
    "name:swe_x_preferred":[
        "Carleton"
    ],
    "name:ukr_x_preferred":[
        "\u041a\u0430\u0440\u043b\u0442\u043e\u043d"
    ],
    "name:vol_x_preferred":[
        "Carleton"
    ],
    "wof:name":"Carleton",
    "wof:placetype":"locality"
},
  "geometry": {"coordinates":[-98.52036,36.01504],"type":"Point"}
}