{
  "type": "Feature",
  "properties": {
    "gn:admin1_code":"TX",
    "gn:admin2_code":"201.0",
    "gn:asciiname":"Oaks of Inwood",
    "gn:country_code":"US",
    "gn:dem":28,
    "gn:elevation":"25.0",
    "gn:feature_class":"P",
    "gn:feature_code":"PPL",
    "gn:name":"Oaks of Inwood",
    "gn:population":0,
    "gn:timezone":"America/Chicago",
    "iso:country":"US",
    "wof:name":"Oaks of Inwood",
    "wof:placetype":"locality"
},
  "geometry": {"coordinates":[-95.461,29.8659],"type":"Point"}
}