{
  "type": "Feature",
  "properties": {
    "gn:admin1_code":"OK",
    "gn:admin2_code":"111",
    "gn:asciiname":"Hectorville",
    "gn:country_code":"US",
    "gn:dem":209,
    "gn:elevation":"202.0",
    "gn:feature_class":"P",
    "gn:feature_code":"PPL",
    "gn:name":"Hectorville",
    "gn:population":0,
    "gn:timezone":"America/Chicago",
    "iso:country":"US",
    "name:eng_x_preferred":[
        "Hectorville"
    ],
    "name:und_x_variant":[
        "Hector"
    ],
    "wof:name":"Hectorville",
    "wof:placetype":"locality"
},
  "geometry": {"coordinates":[-95.92527,35.84204000000001],"type":"Point"}
}