{
  "type": "Feature",
  "properties": {
    "gn:admin1_code":"RI",
    "gn:admin2_code":"5.0",
    "gn:admin3_code":"70880.0",
    "gn:asciiname":"Grayville",
    "gn:country_code":"US",
    "gn:dem":-7,
    "gn:elevation":"16.0",
    "gn:feature_class":"P",
    "gn:feature_code":"PPL",
    "gn:name":"Grayville",
    "gn:population":0,
    "gn:timezone":"America/New_York",
    "iso:country":"US",
    "wof:name":"Grayville",
    "wof:placetype":"locality"
},
  "geometry": {"coordinates":[-71.19116,41.57927],"type":"Point"}
}