{
  "type": "Feature",
  "properties": {
    "iso:country":"US",
    "name:ceb_x_preferred":[
        "Farmingdale"
    ],
    "name:deu_x_preferred":[
        "Farmingdale"
    ],
    "name:eng_x_preferred":[
        "Farmingdale"
    ],
    "name:fra_x_preferred":[
        "Farmingdale"
    ],
    "name:ita_x_preferred":[
        "Farmingdale"
    ],
    "name:nld_x_preferred":[
        "Farmingdale"
    ],
    "name:pol_x_preferred":[
        "Farmingdale"
    ],
    "name:srp_x_preferred":[
        "\u0424\u0430\u0440\u043c\u0438\u043d\u0433\u0434\u0435\u0458\u043b"
    ],
    "name:swa_x_preferred":[
        "Farmingdale"
    ],
    "name:vol_x_preferred":[
        "Farmingdale"
    ],
    "wd:wordcount":26,
    "wof:name":"Farmingdale",
    "wof:placetype":"neighbourhood",
    "wof:population":162,
    "zs:area_m":2096067.49775,
    "zs:blockids":[
        360710133003013,
        360710133001044,
        360710133003040,
        360710133003039
    ],
    "zs:housing10":50,
    "zs:label":"Farmingdale",
    "zs:pop10":162
},
  "geometry": {"coordinates":[-74.23369,41.405901],"type":"Point"}
}