{
  "type": "Feature",
  "properties": {
    "iso:country":"US",
    "name:azb_x_preferred":[
        "\u0633\u0648\u062a\u0648\u0632\u062a \u0641\u06cc\u0644\u0626\u06cc\u062f\u0644\u0641\u06cc\u0627"
    ],
    "name:eng_x_preferred":[
        "Southwest Philadelphia"
    ],
    "name:fra_x_preferred":[
        "Southwest Philadelphia"
    ],
    "name:nld_x_preferred":[
        "Southwest Philadelphia"
    ],
    "wd:wordcount":1000,
    "wof:name":"Southwest Philadelphia",
    "wof:placetype":"neighbourhood",
    "wof:population":523,
    "zs:area_m":125822.442951,
    "zs:blockids":[
        420454025001008,
        420454025001016,
        420454025003003,
        420454025001010,
        420454025003002,
        420454025003001
    ],
    "zs:housing10":266,
    "zs:label":"Southwest Philadelphia",
    "zs:pop10":523
},
  "geometry": {"coordinates":[-75.25869,39.917533],"type":"Point"}
}