{
  "type": "Feature",
  "properties": {
    "gn:admin1_code":"AK",
    "gn:admin2_code":"150.0",
    "gn:asciiname":"Port Hobron",
    "gn:country_code":"US",
    "gn:dem":80,
    "gn:elevation":"0.0",
    "gn:feature_class":"P",
    "gn:feature_code":"PPL",
    "gn:name":"Port Hobron",
    "gn:population":0,
    "gn:timezone":"America/Anchorage",
    "iso:country":"US",
    "name:eng_x_preferred":[
        "Port Hobron"
    ],
    "name:und_x_variant":[
        "Fugitive"
    ],
    "wof:name":"Port Hobron",
    "wof:placetype":"locality"
},
  "geometry": {"coordinates":[-153.15638999999999,57.16056],"type":"Point"}
}