{
  "type": "Feature",
  "properties": {
    "gn:admin1_code":"NV",
    "gn:admin2_code":"23.0",
    "gn:asciiname":"Labbe Camp",
    "gn:country_code":"US",
    "gn:dem":1122,
    "gn:elevation":"1119.0",
    "gn:feature_class":"P",
    "gn:feature_code":"PPL",
    "gn:name":"Labbe Camp",
    "gn:population":0,
    "gn:timezone":"America/Los_Angeles",
    "iso:country":"US",
    "wof:name":"Labbe Camp",
    "wof:placetype":"locality"
},
  "geometry": {"coordinates":[-116.05642,36.45079000000001],"type":"Point"}
}