{
  "type": "Feature",
  "properties": {
    "gn:admin1_code":"TX",
    "gn:admin2_code":"227.0",
    "gn:asciiname":"Elbow",
    "gn:country_code":"US",
    "gn:dem":779,
    "gn:elevation":"777.0",
    "gn:feature_class":"P",
    "gn:feature_code":"PPL",
    "gn:name":"Elbow",
    "gn:population":0,
    "gn:timezone":"America/Chicago",
    "iso:country":"US",
    "wof:name":"Elbow",
    "wof:placetype":"locality"
},
  "geometry": {"coordinates":[-101.51206999999999,32.1604],"type":"Point"}
}