{
  "type": "Feature",
  "properties": {
    "gn:admin1_code":"AR",
    "gn:admin2_code":"55.0",
    "gn:admin3_code":"93288.0",
    "gn:asciiname":"Lorado",
    "gn:country_code":"US",
    "gn:dem":117,
    "gn:elevation":"115.0",
    "gn:feature_class":"P",
    "gn:feature_code":"PPL",
    "gn:name":"Lorado",
    "gn:population":0,
    "gn:timezone":"America/Chicago",
    "iso:country":"US",
    "wof:name":"Lorado",
    "wof:placetype":"locality"
},
  "geometry": {"coordinates":[-90.71760999999999,35.98924],"type":"Point"}
}