{
  "type": "Feature",
  "properties": {
    "gn:admin1_code":"VA",
    "gn:admin2_code":"117",
    "gn:asciiname":"Blackridge",
    "gn:country_code":"US",
    "gn:dem":115,
    "gn:elevation":"115.0",
    "gn:feature_class":"P",
    "gn:feature_code":"PPL",
    "gn:name":"Blackridge",
    "gn:population":0,
    "gn:timezone":"America/New_York",
    "iso:country":"US",
    "name:eng_x_preferred":[
        "Blackridge"
    ],
    "name:und_x_variant":[
        "Black Ridge"
    ],
    "wof:name":"Blackridge",
    "wof:placetype":"locality"
},
  "geometry": {"coordinates":[-78.05694,36.64515],"type":"Point"}
}