{
  "type": "Feature",
  "properties": {
    "gn:admin1_code":"IA",
    "gn:admin2_code":"113.0",
    "gn:admin3_code":"90577.0",
    "gn:asciiname":"Lincolnway Village",
    "gn:country_code":"US",
    "gn:dem":229,
    "gn:elevation":"226.0",
    "gn:feature_class":"P",
    "gn:feature_code":"PPL",
    "gn:name":"Lincolnway Village",
    "gn:population":0,
    "gn:timezone":"America/Chicago",
    "iso:country":"US",
    "wof:name":"Lincolnway Village",
    "wof:placetype":"locality"
},
  "geometry": {"coordinates":[-91.66546,41.92139],"type":"Point"}
}