{
  "type": "Feature",
  "properties": {
    "gn:admin1_code":"TN",
    "gn:admin2_code":"63",
    "gn:asciiname":"Holly Hills",
    "gn:country_code":"US",
    "gn:dem":455,
    "gn:elevation":"442.0",
    "gn:feature_class":"P",
    "gn:feature_code":"PPL",
    "gn:name":"Holly Hills",
    "gn:population":0,
    "gn:timezone":"America/New_York",
    "iso:country":"US",
    "name:fra_x_preferred":[
        "Holly Hills"
    ],
    "wof:name":"Holly Hills",
    "wof:placetype":"locality"
},
  "geometry": {"coordinates":[-83.28128000000002,36.18065],"type":"Point"}
}