{
  "type": "Feature",
  "properties": {
    "gn:admin1_code":"SC",
    "gn:admin2_code":"11.0",
    "gn:asciiname":"Whaley",
    "gn:country_code":"US",
    "gn:dem":71,
    "gn:elevation":"70.0",
    "gn:feature_class":"P",
    "gn:feature_code":"PPL",
    "gn:name":"Whaley",
    "gn:population":0,
    "gn:timezone":"America/New_York",
    "iso:country":"US",
    "name:cym_x_preferred":[
        "Whaley"
    ],
    "name:pol_x_preferred":[
        "Whaley"
    ],
    "wof:name":"Whaley",
    "wof:placetype":"locality"
},
  "geometry": {"coordinates":[-81.29844,33.44098],"type":"Point"}
}