{
  "type": "Feature",
  "properties": {
    "gn:admin1_code":"AZ",
    "gn:admin2_code":"25.0",
    "gn:asciiname":"Piedmont",
    "gn:country_code":"US",
    "gn:dem":1015,
    "gn:elevation":"1018.0",
    "gn:feature_class":"P",
    "gn:feature_code":"PPL",
    "gn:name":"Piedmont",
    "gn:population":0,
    "gn:timezone":"America/Phoenix",
    "iso:country":"US",
    "name:fra_x_preferred":[
        "Piedmont"
    ],
    "name:zho_x_preferred":[
        "\u76ae\u57c3\u8499\u7279"
    ],
    "wof:name":"Piedmont",
    "wof:placetype":"locality"
},
  "geometry": {"coordinates":[-112.86435,34.23891],"type":"Point"}
}