{
  "type": "Feature",
  "properties": {
    "gn:admin1_code":"TX",
    "gn:admin2_code":"201.0",
    "gn:asciiname":"Park Ridge",
    "gn:country_code":"US",
    "gn:dem":32,
    "gn:elevation":"30.0",
    "gn:feature_class":"P",
    "gn:feature_code":"PPL",
    "gn:name":"Park Ridge",
    "gn:population":0,
    "gn:timezone":"America/Chicago",
    "iso:country":"US",
    "name:cat_x_preferred":[
        "Park Ridge"
    ],
    "name:ceb_x_preferred":[
        "Park Ridge"
    ],
    "name:ces_x_preferred":[
        "Park Ridge"
    ],
    "name:deu_x_preferred":[
        "Park Ridge"
    ],
    "name:fra_x_preferred":[
        "Park Ridge"
    ],
    "name:ita_x_preferred":[
        "Park Ridge"
    ],
    "name:kor_x_preferred":[
        "\ud30c\ud06c\ub9ac\uc9c0"
    ],
    "name:nld_x_preferred":[
        "Park Ridge"
    ],
    "name:pol_x_preferred":[
        "Park Ridge"
    ],
    "name:por_x_preferred":[
        "Park Ridge"
    ],
    "name:rus_x_preferred":[
        "\u041f\u0430\u0440\u043a-\u0420\u0438\u0434\u0436"
    ],
    "name:srp_x_preferred":[
        "\u041f\u0430\u0440\u043a \u0420\u0438\u045f"
    ],
    "name:swa_x_preferred":[
        "Park Ridge"
    ],
    "name:vol_x_preferred":[
        "Park Ridge"
    ],
    "wof:name":"Park Ridge",
    "wof:placetype":"locality"
},
  "geometry": {"coordinates":[-95.67400000000001,29.7154],"type":"Point"}
}