{
  "type": "Feature",
  "properties": {
    "gn:country":"US",
    "gn:fcode":"PPL",
    "gn:population":0,
    "iso:country":"US",
    "name:azb_x_preferred":[
        "\u0645\u06cc\u0646\u0626\u0648\u0644\u0627"
    ],
    "name:eng_x_preferred":[
        "Mineola"
    ],
    "name:fas_x_preferred":[
        "\u0645\u06cc\u0646\u0648\u0644\u0627"
    ],
    "name:fra_x_preferred":[
        "Mineola"
    ],
    "name:und_x_variant":[
        "Minieola"
    ],
    "name:zho_x_preferred":[
        "\u7c73\u5c3c\u5967\u62c9"
    ],
    "qs_pg:aaroncc":"US",
    "qs_pg:gn_country":"US",
    "qs_pg:gn_fcode":"PPL",
    "qs_pg:gn_pop":0,
    "qs_pg:name":"Mineola",
    "qs_pg:name_adm0":"United States",
    "qs_pg:name_adm1":"Arkansas",
    "qs_pg:photos":23,
    "qs_pg:photos_1k":5,
    "qs_pg:photos_9k":1,
    "qs_pg:photos_9r":1,
    "qs_pg:photos_all":23,
    "qs_pg:photos_sr":1,
    "qs_pg:pop_sr":0,
    "qs_pg:qs_pg_placetype":"locality",
    "qs_pg:qs_pg_placetype_gp":"Town",
    "qs_pg:woe_adm0":23424977,
    "woe:adm0_id":23424977,
    "woe:name_adm0":"United States",
    "woe:name_adm1":"Arkansas",
    "woe:placetype":"Town",
    "wof:name":"Mineola",
    "wof:placetype":"locality"
},
  "geometry": {"coordinates":[-94.03075,34.31344],"type":"Point"}
}