{
  "type": "Feature",
  "properties": {
    "gn:admin1_code":"NM",
    "gn:admin2_code":"5.0",
    "gn:asciiname":"South Mill",
    "gn:country_code":"US",
    "gn:dem":1078,
    "gn:elevation":"1076.0",
    "gn:feature_class":"P",
    "gn:feature_code":"PPL",
    "gn:name":"South Mill",
    "gn:population":0,
    "gn:timezone":"America/Denver",
    "iso:country":"US",
    "wof:name":"South Mill",
    "wof:placetype":"locality"
},
  "geometry": {"coordinates":[-104.1444,33.16733],"type":"Point"}
}