{
  "type": "Feature",
  "properties": {
    "gn:gn_country":"US",
    "gn:gn_fcode":"PPL",
    "gn:gn_pop":0,
    "iso:country":"US",
    "name:ara_x_preferred":[
        "\u0633\u0627\u0631\u0629"
    ],
    "name:aze_x_preferred":[
        "Sara"
    ],
    "name:bel_x_preferred":[
        "\u0421\u0430\u0440\u0430"
    ],
    "name:bul_x_preferred":[
        "\u0421\u0430\u0440\u0430"
    ],
    "name:ceb_x_preferred":[
        "Sara"
    ],
    "name:deu_x_preferred":[
        "Sara"
    ],
    "name:eus_x_preferred":[
        "Sara"
    ],
    "name:fin_x_preferred":[
        "Sara"
    ],
    "name:fra_x_preferred":[
        "Sara"
    ],
    "name:ind_x_preferred":[
        "Sara"
    ],
    "name:ita_x_preferred":[
        "Sara"
    ],
    "name:jpn_x_preferred":[
        "\u30b5\u30e9"
    ],
    "name:kor_x_preferred":[
        "\uc0ac\ub77c"
    ],
    "name:kur_x_preferred":[
        "Sara"
    ],
    "name:lit_x_preferred":[
        "Sara"
    ],
    "name:nld_x_preferred":[
        "Sara"
    ],
    "name:pol_x_preferred":[
        "Sara"
    ],
    "name:por_x_preferred":[
        "Sara"
    ],
    "name:que_x_preferred":[
        "Sara"
    ],
    "name:rus_x_preferred":[
        "\u0421\u0430\u0440\u0430"
    ],
    "name:spa_x_preferred":[
        "Sara"
    ],
    "name:swe_x_preferred":[
        "Sara"
    ],
    "name:tgl_x_preferred":[
        "Sara"
    ],
    "name:tur_x_preferred":[
        "Sara"
    ],
    "name:ukr_x_preferred":[
        "\u0421\u0430\u0440\u0430"
    ],
    "name:war_x_preferred":[
        "Sara"
    ],
    "qs_pg:aaroncc":"US",
    "qs_pg:gn_country":"US",
    "qs_pg:gn_fcode":"PPL",
    "qs_pg:gn_pop":0,
    "qs_pg:name":"Sara",
    "qs_pg:name_adm0":"United States",
    "qs_pg:name_adm1":"Washington",
    "qs_pg:photos":126,
    "qs_pg:photos_1k":26,
    "qs_pg:photos_9k":1,
    "qs_pg:photos_9r":3,
    "qs_pg:photos_all":126,
    "qs_pg:photos_sr":3,
    "qs_pg:pop_sr":0,
    "qs_pg:qs_pg_placetype":"locality",
    "qs_pg:qs_pg_placetype_gp":"Town",
    "qs_pg:woe_adm0":23424977,
    "woe:adm0_id":23424977,
    "woe:name_adm0":"United States",
    "woe:name_adm1":"Washington",
    "woe:placetype":"Town",
    "wof:name":"Sara",
    "wof:placetype":"locality"
},
  "geometry": {"coordinates":[-122.71316,45.7515],"type":"Point"}
}