{
  "type": "Feature",
  "properties": {
    "iso:country":"US",
    "name:cat_x_preferred":[
        "Deer Valley"
    ],
    "name:eng_x_preferred":[
        "Deer Valley"
    ],
    "name:fra_x_preferred":[
        "Deer Valley"
    ],
    "name:pol_x_preferred":[
        "Deer Valley"
    ],
    "name:rus_x_preferred":[
        "\u0414\u0438\u0440-\u0412\u044d\u043b\u043b\u0438"
    ],
    "name:swe_x_preferred":[
        "Deer Valley Resort"
    ],
    "name:ukr_x_preferred":[
        "\u0414\u0456\u0440-\u0412\u0435\u043b\u043b\u0456"
    ],
    "wd:wordcount":1920,
    "wof:name":"Deer Valley",
    "wof:placetype":"neighbourhood",
    "wof:population":188,
    "zs:area_m":16491032.671223,
    "zs:blockids":[
        80679706002141
    ],
    "zs:housing10":89,
    "zs:label":"Deer Valley",
    "zs:pop10":188
},
  "geometry": {"coordinates":[-107.534751,37.268494],"type":"Point"}
}