{
  "type": "Feature",
  "properties": {
    "gn:admin1_code":"MD",
    "gn:admin2_code":"3.0",
    "gn:asciiname":"Poplar Point",
    "gn:country_code":"US",
    "gn:dem":18,
    "gn:elevation":"12.0",
    "gn:feature_class":"P",
    "gn:feature_code":"PPL",
    "gn:name":"Poplar Point",
    "gn:population":0,
    "gn:timezone":"America/New_York",
    "iso:country":"US",
    "wof:name":"Poplar Point",
    "wof:placetype":"locality"
},
  "geometry": {"coordinates":[-76.54413000000002,38.95511],"type":"Point"}
}