{
  "type": "Feature",
  "properties": {
    "gn:admin1_code":"NC",
    "gn:admin2_code":"141.0",
    "gn:admin3_code":"90548.0",
    "gn:asciiname":"Rooks",
    "gn:country_code":"US",
    "gn:dem":18,
    "gn:elevation":"17.0",
    "gn:feature_class":"P",
    "gn:feature_code":"PPL",
    "gn:name":"Rooks",
    "gn:population":0,
    "gn:timezone":"America/New_York",
    "iso:country":"US",
    "wof:name":"Rooks",
    "wof:placetype":"locality"
},
  "geometry": {"coordinates":[-78.14388000000002,34.49656],"type":"Point"}
}