{
  "type": "Feature",
  "properties": {
    "gn:admin1_code":"IL",
    "gn:admin2_code":"3",
    "gn:asciiname":"Golden Lily",
    "gn:country_code":"US",
    "gn:dem":99,
    "gn:elevation":"94.0",
    "gn:feature_class":"P",
    "gn:feature_code":"PPL",
    "gn:name":"Golden Lily",
    "gn:population":0,
    "gn:timezone":"America/Chicago",
    "iso:country":"US",
    "name:eng_x_preferred":[
        "Golden Lily"
    ],
    "name:und_x_variant":[
        "Golden Lilly"
    ],
    "wof:name":"Golden Lily",
    "wof:placetype":"locality"
},
  "geometry": {"coordinates":[-89.18590999999998,37.07561],"type":"Point"}
}