{
  "type": "Feature",
  "properties": {
    "gn:admin1_code":"OH",
    "gn:admin2_code":"153",
    "gn:admin3_code":"74944.0",
    "gn:asciiname":"Stow Mobile Home Village",
    "gn:country_code":"US",
    "gn:dem":338,
    "gn:elevation":"338.0",
    "gn:feature_class":"P",
    "gn:feature_code":"PPL",
    "gn:name":"Stow Mobile Home Village",
    "gn:population":0,
    "gn:timezone":"America/New_York",
    "iso:country":"US",
    "wof:name":"Stow Mobile Home Village",
    "wof:placetype":"campus"
},
  "geometry": {"coordinates":[-81.43472,41.16167],"type":"Point"}
}