{
  "type": "Feature",
  "properties": {
    "gn:admin1_code":"ID",
    "gn:admin2_code":"49.0",
    "gn:asciiname":"Florence",
    "gn:country_code":"US",
    "gn:dem":1858,
    "gn:elevation":"1854.0",
    "gn:feature_class":"P",
    "gn:feature_code":"PPL",
    "gn:name":"Florence",
    "gn:population":0,
    "gn:timezone":"America/Los_Angeles",
    "iso:country":"US",
    "name:eng_x_preferred":[
        "Florence"
    ],
    "name:ita_x_preferred":[
        "Florence"
    ],
    "name:und_x_variant":[
        "Millersburg"
    ],
    "wof:name":"Florence",
    "wof:placetype":"locality"
},
  "geometry": {"coordinates":[-116.02847,45.50101],"type":"Point"}
}