{
  "type": "Feature",
  "properties": {
    "gn:gn_country":"US",
    "gn:gn_fcode":"PPL",
    "gn:gn_pop":0,
    "iso:country":"US",
    "name:ceb_x_preferred":[
        "Stonehaven"
    ],
    "name:cym_x_preferred":[
        "Stonehaven"
    ],
    "name:dan_x_preferred":[
        "Stonehaven"
    ],
    "name:deu_x_preferred":[
        "Stonehaven"
    ],
    "name:eus_x_preferred":[
        "Stonehaven"
    ],
    "name:fas_x_preferred":[
        "\u0627\u0633\u062a\u0648\u0646\u0647\u0627\u0648\u0646"
    ],
    "name:fin_x_preferred":[
        "Stonehaven"
    ],
    "name:fra_x_preferred":[
        "Stonehaven"
    ],
    "name:glg_x_preferred":[
        "Stonehaven"
    ],
    "name:ind_x_preferred":[
        "Stonehaven"
    ],
    "name:ita_x_preferred":[
        "Stonehaven"
    ],
    "name:kor_x_preferred":[
        "\uc2a4\ud1a4\ud5e4\uc774\ubc88"
    ],
    "name:lit_x_preferred":[
        "Stonhevenas"
    ],
    "name:nld_x_preferred":[
        "Stonehaven"
    ],
    "name:nno_x_preferred":[
        "Stonehaven"
    ],
    "name:nor_x_preferred":[
        "Stonehaven"
    ],
    "name:oci_x_preferred":[
        "Stonehaven"
    ],
    "name:pol_x_preferred":[
        "Stonehaven"
    ],
    "name:rus_x_preferred":[
        "\u0421\u0442\u043e\u0443\u043d\u0445\u0435\u0439\u0432\u0435\u043d"
    ],
    "name:sco_x_preferred":[
        "Stanehyve"
    ],
    "name:spa_x_preferred":[
        "Stonehaven"
    ],
    "name:swe_x_preferred":[
        "Stonehaven"
    ],
    "name:ukr_x_preferred":[
        "\u0421\u0442\u043e\u043d\u0433\u0435\u0439\u0432\u0435\u043d"
    ],
    "name:zho_x_preferred":[
        "\u65af\u51ac\u5e0c\u6587"
    ],
    "qs_pg:aaroncc":"US",
    "qs_pg:gn_country":"US",
    "qs_pg:gn_fcode":"PPL",
    "qs_pg:gn_pop":0,
    "qs_pg:name":"Stonehaven",
    "qs_pg:name_adm0":"United States",
    "qs_pg:name_adm1":"Maryland",
    "qs_pg:photos":15,
    "qs_pg:photos_1k":3,
    "qs_pg:photos_9k":1,
    "qs_pg:photos_9r":1,
    "qs_pg:photos_all":15,
    "qs_pg:photos_sr":1,
    "qs_pg:pop_sr":0,
    "qs_pg:qs_pg_placetype":"locality",
    "qs_pg:qs_pg_placetype_gp":"Town",
    "qs_pg:woe_adm0":23424977,
    "woe:adm0_id":23424977,
    "woe:name_adm0":"United States",
    "woe:name_adm1":"Maryland",
    "woe:placetype":"Town",
    "wof:name":"Stonehaven",
    "wof:placetype":"locality"
},
  "geometry": {"coordinates":[-76.5633,39.1465],"type":"Point"}
}