{
  "type": "Feature",
  "properties": {
    "gn:admin1_code":"FL",
    "gn:admin2_code":"57",
    "gn:asciiname":"Bella Vita",
    "gn:country_code":"US",
    "gn:dem":28,
    "gn:elevation":"16.0",
    "gn:feature_class":"P",
    "gn:feature_code":"PPL",
    "gn:name":"Bella Vita",
    "gn:population":0,
    "gn:timezone":"America/New_York",
    "iso:country":"US",
    "name:ita_x_preferred":[
        "Bella vita"
    ],
    "wof:name":"Bella Vita",
    "wof:placetype":"locality"
},
  "geometry": {"coordinates":[-82.4796,28.1035],"type":"Point"}
}