{
  "type": "Feature",
  "properties": {
    "gn:admin1_code":"PA",
    "gn:admin2_code":"55.0",
    "gn:admin3_code":"32152.0",
    "gn:asciiname":"Turkeyfoot",
    "gn:country_code":"US",
    "gn:dem":213,
    "gn:elevation":"217.0",
    "gn:feature_class":"P",
    "gn:feature_code":"PPL",
    "gn:name":"Turkeyfoot",
    "gn:population":0,
    "gn:timezone":"America/New_York",
    "iso:country":"US",
    "wof:name":"Turkeyfoot",
    "wof:placetype":"locality"
},
  "geometry": {"coordinates":[-77.72277,39.88898],"type":"Point"}
}