{
  "type": "Feature",
  "properties": {
    "gn:admin1_code":"WV",
    "gn:admin2_code":"83",
    "gn:asciiname":"Blue Rock",
    "gn:country_code":"US",
    "gn:dem":900,
    "gn:elevation":"900.0",
    "gn:feature_class":"P",
    "gn:feature_code":"PPL",
    "gn:name":"Blue Rock",
    "gn:population":0,
    "gn:timezone":"America/New_York",
    "iso:country":"US",
    "name:ceb_x_preferred":[
        "Blue Rock"
    ],
    "name:deu_x_preferred":[
        "Blue Rock"
    ],
    "name:swe_x_preferred":[
        "Blue Rock"
    ],
    "wof:name":"Blue Rock",
    "wof:placetype":"locality"
},
  "geometry": {"coordinates":[-80.09090999999999,38.72483],"type":"Point"}
}