{
  "type": "Feature",
  "properties": {
    "gn:country":"US",
    "gn:fcode":"PPL",
    "gn:population":0,
    "iso:country":"US",
    "name:ara_x_preferred":[
        "\u0644\u064a\u0633\u0628\u0648\u0646"
    ],
    "name:arz_x_preferred":[
        "\u0644\u064a\u0633\u0628\u0648\u0646"
    ],
    "name:che_x_preferred":[
        "\u041b\u0438\u0437\u0431\u0435\u043d"
    ],
    "name:deu_x_preferred":[
        "Lisbon"
    ],
    "name:eng_x_preferred":[
        "Lisbon"
    ],
    "name:eus_x_preferred":[
        "Lisbon"
    ],
    "name:fin_x_preferred":[
        "Lisbon"
    ],
    "name:fra_x_preferred":[
        "Lisbon"
    ],
    "name:hat_x_preferred":[
        "Lisbon"
    ],
    "name:hun_x_preferred":[
        "Lisbon"
    ],
    "name:ita_x_preferred":[
        "Lisbon"
    ],
    "name:jpn_x_preferred":[
        "\u30ea\u30b9\u30dc\u30f3"
    ],
    "name:pol_x_preferred":[
        "Lisbon"
    ],
    "name:spa_x_preferred":[
        "Lisbon"
    ],
    "name:tat_x_preferred":[
        "\u041b\u0438\u0437\u0431\u0435\u043d"
    ],
    "name:ukr_x_preferred":[
        "\u041b\u0456\u0437\u0431\u0435\u043d"
    ],
    "name:und_x_variant":[
        "Red Mills"
    ],
    "name:urd_x_preferred":[
        "\u0644\u0632\u0628\u0646"
    ],
    "name:uzb_x_preferred":[
        "Lisbon"
    ],
    "qs_pg:aaroncc":"US",
    "qs_pg:gn_country":"US",
    "qs_pg:gn_fcode":"PPL",
    "qs_pg:gn_pop":0,
    "qs_pg:name":"Lisbon",
    "qs_pg:name_adm0":"United States",
    "qs_pg:name_adm1":"New York",
    "qs_pg:photos":38,
    "qs_pg:photos_1k":8,
    "qs_pg:photos_9k":1,
    "qs_pg:photos_9r":2,
    "qs_pg:photos_all":46,
    "qs_pg:photos_sr":2,
    "qs_pg:pop_sr":5,
    "qs_pg:qs_pg_placetype":"locality",
    "qs_pg:qs_pg_placetype_gp":"Town",
    "qs_pg:woe_adm0":23424977,
    "woe:adm0_id":23424977,
    "woe:name_adm0":"United States",
    "woe:name_adm1":"New York",
    "woe:placetype":"Town",
    "wof:coterminous":[
        404523125
    ],
    "wof:name":"Lisbon",
    "wof:placetype":"locality",
    "wof:statistical_gore":1
},
  "geometry": {"coordinates":[-75.32105,44.72728],"type":"Point"}
}