{
  "type": "Feature",
  "properties": {
    "iso:country":"US",
    "name:eng_x_preferred":[
        "Cadiz"
    ],
    "name:fas_x_preferred":[
        "\u06a9\u0627\u062f\u06cc\u0632"
    ],
    "name:heb_x_preferred":[
        "\u05e7\u05d0\u05d3\u05d9\u05e1"
    ],
    "wof:name":"Cadiz",
    "wof:placetype":"neighbourhood",
    "wof:population":63,
    "zs:area_m":73794.215016,
    "zs:blockids":[
        360099608005010
    ],
    "zs:housing10":30,
    "zs:label":"Cadiz",
    "zs:pop10":63
},
  "geometry": {"coordinates":[-78.46194,42.328126],"type":"Point"}
}