{
  "type": "Feature",
  "properties": {
    "gn:admin1_code":"IN",
    "gn:admin2_code":"115.0",
    "gn:admin3_code":"10738.0",
    "gn:asciiname":"Blue",
    "gn:country_code":"US",
    "gn:dem":267,
    "gn:elevation":"265.0",
    "gn:feature_class":"P",
    "gn:feature_code":"PPL",
    "gn:name":"Blue",
    "gn:population":0,
    "gn:timezone":"America/New_York",
    "iso:country":"US",
    "wof:name":"Blue",
    "wof:placetype":"locality"
},
  "geometry": {"coordinates":[-85.00466999999998,38.92506],"type":"Point"}
}