{
  "type": "Feature",
  "properties": {
    "gn:admin1_code":"IL",
    "gn:admin2_code":"197.0",
    "gn:admin3_code":"17536.0",
    "gn:asciiname":"Faithorn",
    "gn:country_code":"US",
    "gn:dem":225,
    "gn:elevation":"221.0",
    "gn:feature_class":"P",
    "gn:feature_code":"PPL",
    "gn:name":"Faithorn",
    "gn:population":0,
    "gn:timezone":"America/Chicago",
    "iso:country":"US",
    "wof:name":"Faithorn",
    "wof:placetype":"locality"
},
  "geometry": {"coordinates":[-87.60809999999999,41.42809000000001],"type":"Point"}
}