{
  "type": "Feature",
  "properties": {
    "gn:admin1_code":"OH",
    "gn:admin2_code":"61.0",
    "gn:admin3_code":"45108.0",
    "gn:asciiname":"North Heights",
    "gn:country_code":"US",
    "gn:dem":228,
    "gn:feature_class":"P",
    "gn:feature_code":"PPL",
    "gn:name":"North Heights",
    "gn:population":0,
    "gn:timezone":"America/New_York",
    "iso:country":"US",
    "wof:name":"North Heights",
    "wof:placetype":"locality"
},
  "geometry": {"coordinates":[-84.27930000000001,39.26971],"type":"Point"}
}