{
  "type": "Feature",
  "properties": {
    "gn:admin1_code":"IA",
    "gn:admin2_code":"17.0",
    "gn:admin3_code":"91389.0",
    "gn:asciiname":"Wapsie",
    "gn:country_code":"US",
    "gn:dem":313,
    "gn:elevation":"312.0",
    "gn:feature_class":"P",
    "gn:feature_code":"PPL",
    "gn:name":"Wapsie",
    "gn:population":0,
    "gn:timezone":"America/Chicago",
    "iso:country":"US",
    "wof:name":"Wapsie",
    "wof:placetype":"locality"
},
  "geometry": {"coordinates":[-92.19935,42.71498],"type":"Point"}
}