{
  "type": "Feature",
  "properties": {
    "gn:admin1_code":"KY",
    "gn:admin2_code":"185.0",
    "gn:asciiname":"Harmony Landing",
    "gn:country_code":"US",
    "gn:dem":138,
    "gn:elevation":"131.0",
    "gn:feature_class":"P",
    "gn:feature_code":"PPL",
    "gn:name":"Harmony Landing",
    "gn:population":0,
    "gn:timezone":"America/New_York",
    "iso:country":"US",
    "wof:name":"Harmony Landing",
    "wof:placetype":"locality"
},
  "geometry": {"coordinates":[-85.61745999999999,38.41145],"type":"Point"}
}