{
  "type": "Feature",
  "properties": {
    "gn:admin1_code":"MO",
    "gn:admin2_code":"186.0",
    "gn:admin3_code":"74968.0",
    "gn:asciiname":"Sprott",
    "gn:country_code":"US",
    "gn:dem":320,
    "gn:elevation":"318.0",
    "gn:feature_class":"P",
    "gn:feature_code":"PPL",
    "gn:name":"Sprott",
    "gn:population":0,
    "gn:timezone":"America/Chicago",
    "iso:country":"US",
    "wof:name":"Sprott",
    "wof:placetype":"locality"
},
  "geometry": {"coordinates":[-90.32845,37.86394],"type":"Point"}
}