{
  "type": "Feature",
  "properties": {
    "gn:admin1_code":"OH",
    "gn:admin2_code":"127.0",
    "gn:admin3_code":"51520.0",
    "gn:asciiname":"Chapel Hill",
    "gn:country_code":"US",
    "gn:dem":318,
    "gn:elevation":"316.0",
    "gn:feature_class":"P",
    "gn:feature_code":"PPL",
    "gn:name":"Chapel Hill",
    "gn:population":0,
    "gn:timezone":"America/New_York",
    "iso:country":"US",
    "name:ceb_x_preferred":[
        "Chapel Hill"
    ],
    "name:deu_x_preferred":[
        "Chapel Hill"
    ],
    "name:eng_x_preferred":[
        "Chapel Hill"
    ],
    "name:fra_x_preferred":[
        "Chapel Hill"
    ],
    "name:ita_x_preferred":[
        "Chapel Hill"
    ],
    "name:jpn_x_preferred":[
        "\u30c1\u30e3\u30da\u30eb\u30d2\u30eb"
    ],
    "name:kor_x_preferred":[
        "\ucc44\ud50c\ud790"
    ],
    "name:nld_x_preferred":[
        "Chapel Hill"
    ],
    "name:pol_x_preferred":[
        "Chapel Hill"
    ],
    "name:por_x_preferred":[
        "Chapel Hill"
    ],
    "name:srp_x_preferred":[
        "\u0427\u0430\u043f\u0435\u043b \u0425\u0438\u043b"
    ],
    "name:swe_x_preferred":[
        "Chapel Hill"
    ],
    "name:ukr_x_preferred":[
        "\u0427\u0430\u043f\u0435\u043b-\u0413\u0456\u043b\u043b"
    ],
    "name:und_x_variant":[
        "Thompsonville"
    ],
    "name:vol_x_preferred":[
        "Chapel Hill"
    ],
    "name:wuu_x_preferred":[
        "\u6559\u5802\u5c71"
    ],
    "name:zho_x_preferred":[
        "\u6559\u5802\u5c71"
    ],
    "wof:name":"Chapel Hill",
    "wof:placetype":"locality"
},
  "geometry": {"coordinates":[-82.05348000000002,39.62368],"type":"Point"}
}