{
  "type": "Feature",
  "properties": {
    "gn:elevation":12,
    "iso:country":"US",
    "name:eng_x_preferred":[
        "Old Spain"
    ],
    "qs:gn_adm0_cc":"US",
    "qs:gn_fcode":"PPL",
    "qs:gn_local":4945810,
    "qs:gn_nam_loc":"North Weymouth, Norfolk, Massachusetts, US",
    "qs:gn_namadm1":"MA",
    "qs:gn_name":"Old Spain",
    "qs:local_max":162,
    "qs:local_sum":252,
    "qs:localhoods":3,
    "qs:name":"Old Spain",
    "qs:name_adm0":"United States",
    "qs:name_adm1":"Massachusetts",
    "qs:name_adm2":"Norfolk",
    "qs:name_local":"North Weymouth",
    "qs:photo_max":5,
    "qs:photo_sum":19,
    "qs:placetype":"Suburb",
    "qs:quad_count":8,
    "qs:woe_adm0":23424977,
    "qs:woe_adm1":2347580,
    "qs:woe_adm2":12588710,
    "qs:woe_lau":0,
    "qs:woe_local":2461800,
    "qs:woe_ver":"7.10.0",
    "wof:lang":[
        "eng"
    ],
    "wof:name":"Old Spain",
    "wof:placetype":"neighbourhood",
    "zs:blockids":[
        250235011024005,
        250235011024018,
        250235011024030,
        250235011024016
    ],
    "zs:housing10":0,
    "zs:pop10":0
},
  "geometry": {"coordinates":[-70.937473,42.245156],"type":"Point"}
}