{
  "type": "Feature",
  "properties": {
    "gn:country":"US",
    "gn:fcode":"PPL",
    "gn:population":0,
    "iso:country":"US",
    "name:cat_x_preferred":[
        "Branchville"
    ],
    "name:ceb_x_preferred":[
        "Branchville"
    ],
    "name:deu_x_preferred":[
        "Branchville"
    ],
    "name:fra_x_preferred":[
        "Branchville"
    ],
    "name:ido_x_preferred":[
        "Branchville"
    ],
    "name:ita_x_preferred":[
        "Branchville"
    ],
    "name:nld_x_preferred":[
        "Branchville"
    ],
    "name:pol_x_preferred":[
        "Branchville"
    ],
    "name:por_x_preferred":[
        "Branchville"
    ],
    "name:spa_x_preferred":[
        "Branchville"
    ],
    "name:srp_x_preferred":[
        "\u0411\u0440\u0430\u043d\u0447\u0432\u0438\u043b"
    ],
    "name:ukr_x_preferred":[
        "\u0411\u0440\u0430\u043d\u0447\u0432\u0456\u043b\u043b"
    ],
    "name:vol_x_preferred":[
        "Branchville"
    ],
    "qs_pg:aaroncc":"US",
    "qs_pg:gn_country":"US",
    "qs_pg:gn_fcode":"PPL",
    "qs_pg:gn_pop":0,
    "qs_pg:name":"Branchville",
    "qs_pg:name_adm0":"United States",
    "qs_pg:name_adm1":"Pennsylvania",
    "qs_pg:photos":5,
    "qs_pg:photos_1k":1,
    "qs_pg:photos_9k":1,
    "qs_pg:photos_9r":1,
    "qs_pg:photos_all":5,
    "qs_pg:photos_sr":1,
    "qs_pg:pop_sr":0,
    "qs_pg:qs_pg_placetype":"neighbourhood",
    "qs_pg:qs_pg_placetype_gp":"Suburb",
    "qs_pg:woe_adm0":23424977,
    "woe:adm0_id":23424977,
    "woe:name_adm0":"United States",
    "woe:name_adm1":"Pennsylvania",
    "woe:placetype":"Suburb",
    "wof:name":"Branchville",
    "wof:placetype":"neighbourhood"
},
  "geometry": {"coordinates":[-80.14089,41.96006],"type":"Point"}
}