{
  "type": "Feature",
  "properties": {
    "gn:admin1_code":"IN",
    "gn:admin2_code":"173.0",
    "gn:admin3_code":"6472.0",
    "gn:asciiname":"Bullocktown",
    "gn:country_code":"US",
    "gn:dem":114,
    "gn:elevation":"116.0",
    "gn:feature_class":"P",
    "gn:feature_code":"PPL",
    "gn:name":"Bullocktown",
    "gn:population":0,
    "gn:timezone":"America/Chicago",
    "iso:country":"US",
    "name:eng_x_preferred":[
        "Bullocktown"
    ],
    "name:und_x_variant":[
        "Bullacktown",
        "Bullock",
        "Bullock Lock"
    ],
    "wof:name":"Bullocktown",
    "wof:placetype":"locality"
},
  "geometry": {"coordinates":[-87.22278,37.97477],"type":"Point"}
}