{
  "type": "Feature",
  "properties": {
    "iso:country":"US",
    "name:eng_x_preferred":[
        "Meadowvale"
    ],
    "wd:wordcount":53,
    "wof:name":"Meadowvale",
    "wof:placetype":"neighbourhood",
    "wof:population":7100,
    "zs:area_m":4625189.304949,
    "zs:blockids":[
        40134208001012,
        40134208001002,
        40134208004017,
        40134208004015,
        40134208004011,
        40134206032000,
        40134206021013,
        40134206023021,
        40134206021007,
        40134206021010,
        40134206022018,
        40134206023009,
        40134206022005,
        40134207043000,
        40134207043023,
        40134208001006,
        40134208001003,
        40134208004010,
        40134208004019,
        40134208004001,
        40134206042035,
        40134206021001,
        40134206021008,
        40134206023010,
        40134206022004,
        40134206022003,
        40134207043004,
        40134217012000,
        40134206023003,
        40134206023004,
        40134206022007,
        40134206023001,
        40134206023008,
        40134206022014,
        40134206023015,
        40134206023012,
        40134207042010,
        40134208001005,
        40134206042037,
        40134206032012,
        40134206031014,
        40134206021017,
        40134206023020,
        40134206023019,
        40134206022017,
        40134206022013,
        40134206022009,
        40134206022001,
        40134206022000,
        40134207042007,
        40134206042023,
        40134206032008,
        40134206023005,
        40134207043005,
        40134206021019,
        40134208001008,
        40134208004016,
        40134206021009,
        40134206021018,
        40134206021015,
        40134206021014,
        40134206023018,
        40134206023011,
        40134206022010,
        40134207043001,
        40134206042034,
        40134206032009,
        40134206021011,
        40134207043003,
        40134208001004,
        40134208001000,
        40134208004009,
        40134208004012,
        40134206042036,
        40134206042038,
        40134206021006,
        40134206022015,
        40134206023016,
        40134206023017,
        40134206022006,
        40134206022002,
        40134206022008,
        40134206023000,
        40134208004002,
        40134206032001,
        40134208001017,
        40134208001001,
        40134208004004,
        40134208004000,
        40134206022012,
        40134206023007,
        40134206021012,
        40134206021000,
        40134206022019,
        40134207043002,
        40134208001015,
        40134208004018,
        40134208004003,
        40134206022020,
        40134206022016,
        40134206023014,
        40134206023002,
        40134206023006,
        40134206023013,
        40134206022011,
        40134207043006
    ],
    "zs:housing10":2534,
    "zs:label":"Meadowvale",
    "zs:pop10":7100
},
  "geometry": {"coordinates":[-111.784058,33.430649],"type":"Point"}
}