{
  "type": "Feature",
  "properties": {
    "gn:admin1_code":"AL",
    "gn:admin2_code":"77",
    "gn:asciiname":"Indian Springs",
    "gn:country_code":"US",
    "gn:dem":177,
    "gn:elevation":"176.0",
    "gn:feature_class":"P",
    "gn:feature_code":"PPL",
    "gn:name":"Indian Springs",
    "gn:population":0,
    "gn:timezone":"America/Chicago",
    "iso:country":"US",
    "name:ceb_x_preferred":[
        "Indian Springs"
    ],
    "name:deu_x_preferred":[
        "Indian Springs"
    ],
    "name:ita_x_preferred":[
        "Indian Springs"
    ],
    "name:nld_x_preferred":[
        "Indian Springs"
    ],
    "name:pol_x_preferred":[
        "Indian Springs"
    ],
    "name:por_x_preferred":[
        "Indian Springs"
    ],
    "name:srp_x_preferred":[
        "\u0418\u043d\u0434\u0438\u0458\u0430\u043d \u0421\u043f\u0440\u0438\u043d\u0433\u0441"
    ],
    "name:swe_x_preferred":[
        "Indian Springs"
    ],
    "name:ukr_x_preferred":[
        "\u0406\u043d\u0434\u0456\u0430\u043d-\u0421\u043f\u0440\u0456\u043d\u0433\u0441"
    ],
    "name:vol_x_preferred":[
        "Indian Springs"
    ],
    "wof:name":"Indian Springs",
    "wof:placetype":"locality"
},
  "geometry": {"coordinates":[-87.60196999999999,34.8262],"type":"Point"}
}