{
  "type": "Feature",
  "properties": {
    "iso:country":"US",
    "name:eng_x_preferred":[
        "Pegville"
    ],
    "name:und_x_variant":[
        "Sandy's Brook"
    ],
    "wof:name":"Pegville",
    "wof:placetype":"neighbourhood",
    "wof:population":228,
    "zs:area_m":1132184.273951,
    "zs:blockids":[
        90034681021012,
        90034681013025,
        90034681021011,
        90034681021019,
        90034681013022,
        90034681013029
    ],
    "zs:housing10":85,
    "zs:label":"Pegville",
    "zs:pop10":228
},
  "geometry": {"coordinates":[-72.80901,41.967621],"type":"Point"}
}