{
  "type": "Feature",
  "properties": {
    "gn:admin1_code":"MT",
    "gn:admin2_code":"75.0",
    "gn:asciiname":"Sayle",
    "gn:country_code":"US",
    "gn:dem":1150,
    "gn:elevation":"1148.0",
    "gn:feature_class":"P",
    "gn:feature_code":"PPL",
    "gn:name":"Sayle",
    "gn:population":0,
    "gn:timezone":"America/Denver",
    "iso:country":"US",
    "wof:name":"Sayle",
    "wof:placetype":"locality"
},
  "geometry": {"coordinates":[-105.99557,45.22693],"type":"Point"}
}