{
  "type": "Feature",
  "properties": {
    "gn:admin1_code":"MD",
    "gn:admin2_code":"13.0",
    "gn:asciiname":"Quail Creek Acres",
    "gn:country_code":"US",
    "gn:dem":171,
    "gn:elevation":"171.0",
    "gn:feature_class":"P",
    "gn:feature_code":"PPL",
    "gn:name":"Quail Creek Acres",
    "gn:population":0,
    "gn:timezone":"America/New_York",
    "iso:country":"US",
    "wof:name":"Quail Creek Acres",
    "wof:placetype":"locality"
},
  "geometry": {"coordinates":[-77.01692,39.39621],"type":"Point"}
}