{
  "type": "Feature",
  "properties": {
    "gn:admin1_code":"AL",
    "gn:admin2_code":"123",
    "gn:asciiname":"Easton",
    "gn:country_code":"US",
    "gn:dem":251,
    "gn:elevation":"249.0",
    "gn:feature_class":"P",
    "gn:feature_code":"PPL",
    "gn:name":"Easton",
    "gn:population":0,
    "gn:timezone":"America/Chicago",
    "iso:country":"US",
    "name:cat_x_preferred":[
        "Easton"
    ],
    "name:ceb_x_preferred":[
        "Easton"
    ],
    "name:ces_x_preferred":[
        "Easton"
    ],
    "name:deu_x_preferred":[
        "Easton"
    ],
    "name:fin_x_preferred":[
        "Easton"
    ],
    "name:fra_x_preferred":[
        "Easton"
    ],
    "name:ido_x_preferred":[
        "Easton"
    ],
    "name:ita_x_preferred":[
        "Easton"
    ],
    "name:jpn_x_preferred":[
        "\u30a4\u30fc\u30b9\u30c8\u30f3"
    ],
    "name:kor_x_preferred":[
        "\uc774\uc2a4\ud134"
    ],
    "name:nld_x_preferred":[
        "Easton"
    ],
    "name:pol_x_preferred":[
        "Easton"
    ],
    "name:por_x_preferred":[
        "Easton"
    ],
    "name:rus_x_preferred":[
        "\u0418\u0441\u0442\u043e\u043d"
    ],
    "name:spa_x_preferred":[
        "Easton"
    ],
    "name:srp_x_preferred":[
        "\u0418\u0441\u0442\u043e\u043d"
    ],
    "name:swa_x_preferred":[
        "Easton"
    ],
    "name:swe_x_preferred":[
        "Easton"
    ],
    "name:ukr_x_preferred":[
        "\u0406\u0441\u0442\u043e\u043d"
    ],
    "name:vol_x_preferred":[
        "Easton"
    ],
    "wof:name":"Easton",
    "wof:placetype":"locality"
},
  "geometry": {"coordinates":[-85.69662,32.90929000000001],"type":"Point"}
}