{
  "type": "Feature",
  "properties": {
    "gn:country":"US",
    "gn:fcode":"PPLX",
    "gn:population":0,
    "iso:country":"US",
    "qs_pg:aaroncc":"US",
    "qs_pg:gn_country":"US",
    "qs_pg:gn_fcode":"PPLX",
    "qs_pg:gn_pop":0,
    "qs_pg:name":"Lincoln Court",
    "qs_pg:name_adm0":"United States",
    "qs_pg:name_adm1":"Ohio",
    "qs_pg:photos":2353,
    "qs_pg:photos_1k":477,
    "qs_pg:photos_9k":10,
    "qs_pg:photos_9r":10,
    "qs_pg:photos_all":2353,
    "qs_pg:photos_sr":17,
    "qs_pg:pop_sr":0,
    "qs_pg:qs_pg_placetype":"neighbourhood",
    "qs_pg:qs_pg_placetype_gp":"Suburb",
    "qs_pg:woe_adm0":23424977,
    "woe:adm0_id":23424977,
    "woe:name_adm0":"United States",
    "woe:name_adm1":"Ohio",
    "woe:placetype":"Suburb",
    "wof:name":"Lincoln Court",
    "wof:placetype":"neighbourhood"
},
  "geometry": {"coordinates":[-84.52578,39.10784],"type":"Point"}
}