{
  "type": "Feature",
  "properties": {
    "gn:admin1_code":"SC",
    "gn:admin2_code":"83.0",
    "gn:asciiname":"Shiloh",
    "gn:country_code":"US",
    "gn:dem":260,
    "gn:elevation":"258.0",
    "gn:feature_class":"P",
    "gn:feature_code":"PPL",
    "gn:name":"Shiloh",
    "gn:population":0,
    "gn:timezone":"America/New_York",
    "iso:country":"US",
    "name:bel_x_preferred":[
        "\u0428\u044b\u043b\u0430"
    ],
    "name:cat_x_preferred":[
        "Shiloh"
    ],
    "name:ceb_x_preferred":[
        "Shiloh"
    ],
    "name:deu_x_preferred":[
        "Shiloh"
    ],
    "name:fra_x_preferred":[
        "Shiloh"
    ],
    "name:heb_x_preferred":[
        "\u05e9\u05d9\u05dc\u05d4"
    ],
    "name:ita_x_preferred":[
        "Shiloh"
    ],
    "name:nld_x_preferred":[
        "Shiloh"
    ],
    "name:pol_x_preferred":[
        "Shiloh"
    ],
    "name:rus_x_preferred":[
        "\u0428\u0438\u043b\u043e"
    ],
    "name:spa_x_preferred":[
        "Shiloh"
    ],
    "name:srp_x_preferred":[
        "\u0428\u0430\u0458\u043b\u043e"
    ],
    "name:swe_x_preferred":[
        "Shiloh"
    ],
    "name:ukr_x_preferred":[
        "\u0428\u0438\u043b\u043e"
    ],
    "name:vol_x_preferred":[
        "Shiloh"
    ],
    "wof:name":"Shiloh",
    "wof:placetype":"locality"
},
  "geometry": {"coordinates":[-82.02261,35.02373],"type":"Point"}
}