{
  "type": "Feature",
  "properties": {
    "gn:admin1_code":"VA",
    "gn:admin2_code":"61",
    "gn:asciiname":"Eustacestown",
    "gn:country_code":"US",
    "gn:dem":79,
    "gn:elevation":"82.0",
    "gn:feature_class":"P",
    "gn:feature_code":"PPL",
    "gn:name":"Eustacestown",
    "gn:population":0,
    "gn:timezone":"America/New_York",
    "iso:country":"US",
    "wof:name":"Eustacestown",
    "wof:placetype":"locality"
},
  "geometry": {"coordinates":[-77.6811,38.60623],"type":"Point"}
}