{
  "type": "Feature",
  "properties": {
    "gn:admin1_code":"GA",
    "gn:admin2_code":"73",
    "gn:asciiname":"Shenandoah",
    "gn:country_code":"US",
    "gn:dem":120,
    "gn:elevation":"116.0",
    "gn:feature_class":"P",
    "gn:feature_code":"PPL",
    "gn:name":"Shenandoah",
    "gn:population":0,
    "gn:timezone":"America/New_York",
    "iso:country":"US",
    "name:cat_x_preferred":[
        "Shenandoah"
    ],
    "name:ceb_x_preferred":[
        "Shenandoah"
    ],
    "name:deu_x_preferred":[
        "Shenandoah"
    ],
    "name:fas_x_preferred":[
        "\u0634\u0646\u0646\u062f\u0648\u0627"
    ],
    "name:fin_x_preferred":[
        "Shenandoah"
    ],
    "name:fra_x_preferred":[
        "Shenandoah"
    ],
    "name:ita_x_preferred":[
        "Shenandoah"
    ],
    "name:jpn_x_preferred":[
        "\u30b7\u30a7\u30ca\u30f3\u30c9\u30fc"
    ],
    "name:nld_x_preferred":[
        "Shenandoah"
    ],
    "name:pol_x_preferred":[
        "Shenandoah"
    ],
    "name:por_x_preferred":[
        "Shenandoah"
    ],
    "name:rus_x_preferred":[
        "\u0428\u0435\u043d\u0430\u043d\u0434\u043e\u0430"
    ],
    "name:spa_x_preferred":[
        "Shenandoah"
    ],
    "name:srp_x_preferred":[
        "\u0428\u0435\u043d\u0430\u043d\u0434\u043e\u0430"
    ],
    "name:ukr_x_preferred":[
        "\u0428\u0435\u043d\u0430\u043d\u0434\u043e\u0430"
    ],
    "name:vol_x_preferred":[
        "Shenandoah"
    ],
    "name:zho_x_preferred":[
        "\u96ea\u5357\u591a\u74e6"
    ],
    "wof:name":"Shenandoah",
    "wof:placetype":"locality"
},
  "geometry": {"coordinates":[-82.10262,33.52791],"type":"Point"}
}