{
  "type": "Feature",
  "properties": {
    "gn:admin1_code":"TN",
    "gn:admin2_code":"105",
    "gn:asciiname":"Morganton",
    "gn:country_code":"US",
    "gn:dem":248,
    "gn:elevation":"248.0",
    "gn:feature_class":"P",
    "gn:feature_code":"PPL",
    "gn:name":"Morganton",
    "gn:population":0,
    "gn:timezone":"America/New_York",
    "iso:country":"US",
    "name:eng_x_preferred":[
        "Morganton"
    ],
    "name:und_x_variant":[
        "Morgantown",
        "Portsville"
    ],
    "wof:name":"Morganton",
    "wof:placetype":"locality"
},
  "geometry": {"coordinates":[-84.22714000000001,35.64341],"type":"Point"}
}