{
  "type": "Feature",
  "properties": {
    "gn:country":"US",
    "gn:fcode":"PPLX",
    "gn:population":0,
    "iso:country":"US",
    "name:eng_x_preferred":[
        "Willow Glenn"
    ],
    "name:tam_x_preferred":[
        "\u0bb5\u0bbf\u0bb2\u0bcb \u0b95\u0bbf\u0bb3\u0bc6\u0ba9\u0bcd"
    ],
    "qs_pg:aaroncc":"US",
    "qs_pg:gn_country":"US",
    "qs_pg:gn_fcode":"PPLX",
    "qs_pg:gn_pop":0,
    "qs_pg:name":"Willow Glenn",
    "qs_pg:name_adm0":"United States",
    "qs_pg:name_adm1":"Ohio",
    "qs_pg:photos":4,
    "qs_pg:photos_1k":1,
    "qs_pg:photos_9k":1,
    "qs_pg:photos_9r":1,
    "qs_pg:photos_all":4,
    "qs_pg:photos_sr":1,
    "qs_pg:pop_sr":0,
    "qs_pg:qs_pg_placetype":"neighbourhood",
    "qs_pg:qs_pg_placetype_gp":"Suburb",
    "qs_pg:woe_adm0":23424977,
    "wd:wordcount":114,
    "wof:name":"Willow Glenn",
    "wof:placetype":"neighbourhood",
    "wof:population":9,
    "zs:area_m":155754.04956,
    "zs:blockids":[
        391719508001117,
        391719508001118,
        391719508001046
    ],
    "zs:housing10":2,
    "zs:label":"Willow Glenn",
    "zs:pop10":9
},
  "geometry": {"coordinates":[-84.619404,41.469748],"type":"Point"}
}