{
  "type": "Feature",
  "properties": {
    "gn:admin1_code":"AR",
    "gn:admin2_code":"43.0",
    "gn:admin3_code":"90915.0",
    "gn:asciiname":"Cominto",
    "gn:country_code":"US",
    "gn:dem":62,
    "gn:elevation":"56.0",
    "gn:feature_class":"P",
    "gn:feature_code":"PPL",
    "gn:name":"Cominto",
    "gn:population":0,
    "gn:timezone":"America/Chicago",
    "iso:country":"US",
    "name:eng_x_preferred":[
        "Cominto"
    ],
    "name:und_x_variant":[
        "Highland Park"
    ],
    "wof:name":"Cominto",
    "wof:placetype":"locality"
},
  "geometry": {"coordinates":[-91.62679,33.54567],"type":"Point"}
}