{
  "type": "Feature",
  "properties": {
    "gn:admin1_code":"IN",
    "gn:admin2_code":"47.0",
    "gn:admin3_code":"3700.0",
    "gn:asciiname":"Mixersville",
    "gn:country_code":"US",
    "gn:dem":305,
    "gn:elevation":"305.0",
    "gn:feature_class":"P",
    "gn:feature_code":"PPL",
    "gn:name":"Mixersville",
    "gn:population":0,
    "gn:timezone":"America/Indiana/Indianapolis",
    "iso:country":"US",
    "name:eng_x_preferred":[
        "Mixersville"
    ],
    "name:und_x_variant":[
        "Mixerville"
    ],
    "wof:name":"Mixersville",
    "wof:placetype":"locality"
},
  "geometry": {"coordinates":[-84.82496,39.48839],"type":"Point"}
}