{
  "type": "Feature",
  "properties": {
    "gn:admin1_code":"LA",
    "gn:admin2_code":"39.0",
    "gn:asciiname":"Point Blue",
    "gn:country_code":"US",
    "gn:dem":21,
    "gn:elevation":"19.0",
    "gn:feature_class":"P",
    "gn:feature_code":"PPL",
    "gn:name":"Point Blue",
    "gn:population":0,
    "gn:timezone":"America/Chicago",
    "iso:country":"US",
    "wof:name":"Point Blue",
    "wof:placetype":"locality"
},
  "geometry": {"coordinates":[-92.30235,30.62714],"type":"Point"}
}