{
  "type": "Feature",
  "properties": {
    "iso:country":"US",
    "name:eng_x_preferred":[
        "Ensley Junction"
    ],
    "wof:name":"Ensley Junction",
    "wof:placetype":"neighbourhood",
    "wof:population":284,
    "zs:area_m":1926036.655409,
    "zs:blockids":[
        10730106024010,
        10730106023046,
        10730139011000,
        10730106024025,
        10730106021054,
        10730106021095,
        10730139011002,
        10730106021138,
        10730106021088,
        10730106021119,
        10730106021128,
        10730106021089,
        10730106021151,
        10730106024023,
        10730106024011,
        10730106021140,
        10730106024007,
        10730106024005,
        10730106024049,
        10730139011003,
        10730106021013,
        10730035003017,
        10730139011167,
        10730106021135,
        10730106021087,
        10730106021129,
        10730106024006,
        10730106021094,
        10730106021130,
        10730106021086,
        10730139011166,
        10730139011001,
        10730106021137,
        10730106021125,
        10730106021126,
        10730106021124,
        10730106024024,
        10730106021136,
        10730106021090,
        10730106024004,
        10730106021092,
        10730106021127,
        10730106021010,
        10730035003018,
        10730106024008,
        10730106024047,
        10730106024013,
        10730106024012,
        10730106021093,
        10730106024009
    ],
    "zs:housing10":148,
    "zs:label":"Ensley Junction",
    "zs:pop10":284
},
  "geometry": {"coordinates":[-86.92358400000001,33.488223],"type":"Point"}
}