{
  "type": "Feature",
  "properties": {
    "gn:admin1_code":"WV",
    "gn:admin2_code":"33.0",
    "gn:asciiname":"Owings",
    "gn:country_code":"US",
    "gn:dem":319,
    "gn:elevation":"320.0",
    "gn:feature_class":"P",
    "gn:feature_code":"PPL",
    "gn:name":"Owings",
    "gn:population":0,
    "gn:timezone":"America/New_York",
    "iso:country":"US",
    "name:deu_x_preferred":[
        "Owings"
    ],
    "wof:name":"Owings",
    "wof:placetype":"locality"
},
  "geometry": {"coordinates":[-80.25896999999998,39.37953],"type":"Point"}
}