{
  "type": "Feature",
  "properties": {
    "iso:country":"US",
    "name:eng_x_preferred":[
        "Bennett District"
    ],
    "wd:wordcount":174,
    "wof:name":"Bennett District",
    "wof:placetype":"neighbourhood",
    "wof:population":65,
    "zs:blockids":[
        80050071031009,
        80050071031028,
        80010083531004,
        80010083531094,
        80010083531095,
        80010083532063,
        80010084011151,
        80010084011152,
        80010083532013,
        80010083531001
    ],
    "zs:housing10":23,
    "zs:label":"Bennett District",
    "zs:pop10":65
},
  "geometry": {"coordinates":[-104.677391,39.778451],"type":"Point"}
}