{
  "type": "Feature",
  "properties": {
    "iso:country":"US",
    "name:ara_x_preferred":[
        "\u0648\u064a\u0644\u0633\u0648\u0646"
    ],
    "name:bel_x_preferred":[
        "\u0412\u0456\u043b\u044c\u0441\u0430\u043d"
    ],
    "name:bul_x_preferred":[
        "\u0423\u0438\u043b\u0441\u044a\u043d"
    ],
    "name:cat_x_preferred":[
        "Wilson"
    ],
    "name:ceb_x_preferred":[
        "Wilson"
    ],
    "name:ces_x_preferred":[
        "Wilson"
    ],
    "name:deu_x_preferred":[
        "Wilson"
    ],
    "name:eng_x_preferred":[
        "Wilson"
    ],
    "name:epo_x_preferred":[
        "Wilson"
    ],
    "name:fas_x_preferred":[
        "\u0648\u06cc\u0644\u0633\u0648\u0646"
    ],
    "name:fin_x_preferred":[
        "Wilson"
    ],
    "name:fra_x_preferred":[
        "Wilson"
    ],
    "name:heb_x_preferred":[
        "\u05d5\u05d9\u05dc\u05e1\u05d5\u05df"
    ],
    "name:hun_x_preferred":[
        "Wilson"
    ],
    "name:ita_x_preferred":[
        "Wilson"
    ],
    "name:jpn_x_preferred":[
        "\u30a6\u30a3\u30eb\u30bd\u30f3"
    ],
    "name:lav_x_preferred":[
        "Vilsons"
    ],
    "name:lit_x_preferred":[
        "Wilson"
    ],
    "name:nld_x_preferred":[
        "Wilson"
    ],
    "name:pol_x_preferred":[
        "Wilson"
    ],
    "name:por_x_preferred":[
        "Wilson"
    ],
    "name:ron_x_preferred":[
        "Wilson"
    ],
    "name:rus_x_preferred":[
        "\u0423\u0438\u043b\u0441\u043e\u043d"
    ],
    "name:slv_x_preferred":[
        "Wilson"
    ],
    "name:spa_x_preferred":[
        "Wilson"
    ],
    "name:srp_x_preferred":[
        "\u0412\u0438\u043b\u0441\u043e\u043d"
    ],
    "name:swe_x_preferred":[
        "Wilson"
    ],
    "name:tur_x_preferred":[
        "Wilson"
    ],
    "name:ukr_x_preferred":[
        "\u0412\u0456\u043b\u0441\u043e\u043d"
    ],
    "name:unk_x_variant":[
        "Wilson"
    ],
    "name:urd_x_preferred":[
        "\u0648\u0644\u0633\u0646"
    ],
    "name:vie_x_preferred":[
        "Wilson"
    ],
    "name:vol_x_preferred":[
        "Wilson"
    ],
    "name:yid_x_preferred":[
        "\u05d5\u05d5\u05d9\u05dc\u05e1\u05d0\u05df"
    ],
    "name:zho_x_preferred":[
        "\u5a01\u723e\u905c"
    ],
    "qs:gn_adm0_cc":"US",
    "qs:gn_local":5380184,
    "qs:gn_nam_loc":"Oxnard, Ventura, California, US",
    "qs:gn_namadm1":"CA",
    "qs:local_max":1503,
    "qs:local_sum":8135,
    "qs:localhoods":30,
    "qs:name":"Wilson",
    "qs:name_adm0":"United States",
    "qs:name_adm1":"California",
    "qs:name_adm2":"Ventura",
    "qs:name_local":"Oxnard",
    "qs:photo_max":26,
    "qs:photo_sum":88,
    "qs:placetype":"Suburb",
    "qs:quad_count":11,
    "qs:woe_adm0":23424977,
    "qs:woe_adm1":2347563,
    "qs:woe_adm2":12587725,
    "qs:woe_lau":0,
    "qs:woe_local":2467212,
    "qs:woe_ver":"7.10.0",
    "wof:lang":[
        "eng"
    ],
    "wof:name":"Wilson",
    "wof:placetype":"neighbourhood"
},
  "geometry": {"coordinates":[-119.181201,34.202469],"type":"Point"}
}