{
  "type": "Feature",
  "properties": {
    "gn:admin1_code":"MO",
    "gn:admin2_code":"123.0",
    "gn:admin3_code":"42212.0",
    "gn:asciiname":"French Mills",
    "gn:country_code":"US",
    "gn:dem":184,
    "gn:elevation":"186.0",
    "gn:feature_class":"P",
    "gn:feature_code":"PPL",
    "gn:name":"French Mills",
    "gn:population":0,
    "gn:timezone":"America/Chicago",
    "iso:country":"US",
    "wof:name":"French Mills",
    "wof:placetype":"locality"
},
  "geometry": {"coordinates":[-90.48929,37.45589],"type":"Point"}
}