{
  "type": "Feature",
  "properties": {
    "gn:admin1_code":"OH",
    "gn:admin2_code":"23",
    "gn:admin3_code":"74119.0",
    "gn:asciiname":"Durbin",
    "gn:country_code":"US",
    "gn:dem":271,
    "gn:elevation":"268.0",
    "gn:feature_class":"P",
    "gn:feature_code":"PPL",
    "gn:name":"Durbin",
    "gn:population":0,
    "gn:timezone":"America/New_York",
    "iso:country":"US",
    "name:ceb_x_preferred":[
        "Durbin"
    ],
    "name:deu_x_preferred":[
        "Durbin"
    ],
    "name:fra_x_preferred":[
        "Durbin"
    ],
    "name:ita_x_preferred":[
        "Durbin"
    ],
    "name:nld_x_preferred":[
        "Durbin"
    ],
    "name:pol_x_preferred":[
        "Durbin"
    ],
    "name:por_x_preferred":[
        "Durbin"
    ],
    "name:swe_x_preferred":[
        "Durbin"
    ],
    "wof:name":"Durbin",
    "wof:placetype":"locality"
},
  "geometry": {"coordinates":[-83.89104,39.91173],"type":"Point"}
}