{
  "type": "Feature",
  "properties": {
    "gn:admin1_code":"LA",
    "gn:admin2_code":"125.0",
    "gn:asciiname":"Retreat",
    "gn:country_code":"US",
    "gn:dem":71,
    "gn:elevation":"65.0",
    "gn:feature_class":"P",
    "gn:feature_code":"PPL",
    "gn:name":"Retreat",
    "gn:population":0,
    "gn:timezone":"America/Chicago",
    "iso:country":"US",
    "name:ceb_x_preferred":[
        "Retreat"
    ],
    "name:deu_x_preferred":[
        "Retreat"
    ],
    "name:eng_x_preferred":[
        "Retreat"
    ],
    "name:fra_x_preferred":[
        "Retreat"
    ],
    "name:mlg_x_preferred":[
        "Retreat"
    ],
    "name:rus_x_preferred":[
        "\u0420\u0435\u0442\u0440\u0438\u0442"
    ],
    "name:swe_x_preferred":[
        "Retreat"
    ],
    "name:und_x_variant":[
        "Retreat Plantation",
        "Soldiers Retreat"
    ],
    "wof:name":"Retreat",
    "wof:placetype":"locality"
},
  "geometry": {"coordinates":[-91.48511999999999,30.97212],"type":"Point"}
}