{
  "type": "Feature",
  "properties": {
    "gn:admin1_code":"WV",
    "gn:admin2_code":"35",
    "gn:asciiname":"Estar",
    "gn:country_code":"US",
    "gn:dem":179,
    "gn:elevation":"182.0",
    "gn:feature_class":"P",
    "gn:feature_code":"PPL",
    "gn:name":"Estar",
    "gn:population":0,
    "gn:timezone":"America/New_York",
    "iso:country":"US",
    "wof:name":"Estar",
    "wof:placetype":"locality"
},
  "geometry": {"coordinates":[-81.84151999999997,38.89814000000001],"type":"Point"}
}