{
  "type": "Feature",
  "properties": {
    "gn:elevation":128,
    "iso:country":"US",
    "name:eng_x_preferred":[
        "Lerchs"
    ],
    "qs:gn_adm0_cc":"US",
    "qs:gn_fcode":"PPL",
    "qs:gn_local":5187754,
    "qs:gn_nam_loc":"East Allen, Northampton, Pennsylvania, US",
    "qs:gn_namadm1":"PA",
    "qs:gn_name":"Lerchs",
    "qs:local_max":293,
    "qs:local_sum":304,
    "qs:localhoods":2,
    "qs:name":"Lerchs",
    "qs:name_adm0":"United States",
    "qs:name_adm1":"Pennsylvania",
    "qs:name_adm2":"Northampton",
    "qs:name_local":"East Allen",
    "qs:photo_max":157,
    "qs:photo_sum":293,
    "qs:placetype":"Suburb",
    "qs:quad_count":9,
    "qs:woe_adm0":23424977,
    "qs:woe_adm1":2347597,
    "qs:woe_adm2":12589775,
    "qs:woe_lau":0,
    "qs:woe_local":28745504,
    "qs:woe_ver":"7.10.0",
    "wof:lang":[
        "eng"
    ],
    "wof:name":"Lerchs",
    "wof:placetype":"neighbourhood",
    "wof:population":884,
    "zs:blockids":[
        420950165003030,
        420950165002023,
        420950165002024,
        420950165001015,
        420950165001013,
        420950165002002,
        420950165002030,
        420950165002001,
        420950165002022,
        420950165003010,
        420950165003040,
        420950165001008,
        420950165002003,
        420950165001016,
        420950165003027,
        420950165001019,
        420950165001018,
        420950165002020,
        420950165003020,
        420950165002025,
        420950165002000,
        420950165002004,
        420950165003026,
        420950165003028,
        420950165003029
    ],
    "zs:housing10":359,
    "zs:pop10":884
},
  "geometry": {"coordinates":[-75.426064,40.705407],"type":"Point"}
}