{
  "type": "Feature",
  "properties": {
    "gn:admin1_code":"VA",
    "gn:admin2_code":"83",
    "gn:asciiname":"Danripple",
    "gn:country_code":"US",
    "gn:dem":148,
    "gn:elevation":"153.0",
    "gn:feature_class":"P",
    "gn:feature_code":"PPL",
    "gn:name":"Danripple",
    "gn:population":0,
    "gn:timezone":"America/New_York",
    "iso:country":"US",
    "wof:name":"Danripple",
    "wof:placetype":"locality"
},
  "geometry": {"coordinates":[-79.0239,36.62986],"type":"Point"}
}