{
  "type": "Feature",
  "properties": {
    "iso:country":"US",
    "name:eng_x_preferred":[
        "Raintree Terrace"
    ],
    "wof:name":"Raintree Terrace",
    "wof:placetype":"neighbourhood",
    "wof:population":3243,
    "zs:area_m":2700639.017528,
    "zs:blockids":[
        120570108111028,
        120570108111012,
        120570108111029,
        120570108111020,
        120570108111004,
        120570108111022,
        120570108111006,
        120570108111010,
        120570108111011,
        120570108111019,
        120570108111001,
        120570110152034,
        120570108091012,
        120570108111025,
        120570108111015,
        120570109001009,
        120570108111003,
        120570109001000,
        120570108111009,
        120570108111016,
        120570108111023,
        120570108111021,
        120570108111024,
        120570108111005,
        120570108113006,
        120570108111013,
        120570108112000,
        120570108111027,
        120570108091000,
        120570108111026,
        120570108111014,
        120570108111000,
        120570108111007,
        120570108111018,
        120570108111002,
        120570109001003,
        120570108111017,
        120570108111008
    ],
    "zs:housing10":1568,
    "zs:label":"Raintree Terrace",
    "zs:pop10":3243
},
  "geometry": {"coordinates":[-82.39021200000001,28.06656],"type":"Point"}
}