{
  "type": "Feature",
  "properties": {
    "gn:admin1_code":"MA",
    "gn:admin2_code":"27.0",
    "gn:admin3_code":"17685.0",
    "gn:asciiname":"Grand View Estates",
    "gn:country_code":"US",
    "gn:dem":218,
    "gn:elevation":"212.0",
    "gn:feature_class":"P",
    "gn:feature_code":"PPL",
    "gn:name":"Grand View Estates",
    "gn:population":0,
    "gn:timezone":"America/New_York",
    "iso:country":"US",
    "wof:name":"Grand View Estates",
    "wof:placetype":"locality"
},
  "geometry": {"coordinates":[-71.89785000000001,42.0901],"type":"Point"}
}