{
  "type": "Feature",
  "properties": {
    "iso:country":"US",
    "name:eng_x_preferred":[
        "The Brooks at Maybrook Crossings"
    ],
    "wof:name":"The Brooks at Maybrook Crossings",
    "wof:placetype":"neighbourhood",
    "wof:population":1223,
    "zs:area_m":983675.58553,
    "zs:blockids":[
        371830528063014,
        371830528063011,
        371830528061013,
        371830528063015,
        371830528063013,
        371830528063017,
        371830528063012,
        371830528062028,
        371830528061009
    ],
    "zs:housing10":481,
    "zs:label":"The Brooks at Maybrook Crossings",
    "zs:pop10":1223
},
  "geometry": {"coordinates":[-78.559416,35.751252],"type":"Point"}
}