{
  "type": "Feature",
  "properties": {
    "gn:country":"US",
    "gn:fcode":"PPL",
    "gn:population":0,
    "iso:country":"US",
    "name:azb_x_preferred":[
        "\u0648\u0627\u06cc\u062a\u0633\u0648\u0646"
    ],
    "name:eng_x_preferred":[
        "Whiteson"
    ],
    "name:fas_x_preferred":[
        "\u0648\u0627\u06cc\u062a\u0633\u0648\u0646"
    ],
    "name:fra_x_preferred":[
        "Whiteson"
    ],
    "name:hat_x_preferred":[
        "Whiteson"
    ],
    "name:hun_x_preferred":[
        "Whiteson"
    ],
    "name:und_x_variant":[
        "Whites"
    ],
    "name:vol_x_preferred":[
        "Whiteson"
    ],
    "qs_pg:aaroncc":"US",
    "qs_pg:gn_country":"US",
    "qs_pg:gn_fcode":"PPL",
    "qs_pg:gn_pop":0,
    "qs_pg:name":"Whiteson",
    "qs_pg:name_adm0":"United States",
    "qs_pg:name_adm1":"Oregon",
    "qs_pg:photos":33,
    "qs_pg:photos_1k":7,
    "qs_pg:photos_9k":1,
    "qs_pg:photos_9r":2,
    "qs_pg:photos_all":33,
    "qs_pg:photos_sr":2,
    "qs_pg:pop_sr":5,
    "qs_pg:qs_pg_placetype":"locality",
    "qs_pg:qs_pg_placetype_gp":"Town",
    "qs_pg:woe_adm0":23424977,
    "woe:adm0_id":23424977,
    "woe:name_adm0":"United States",
    "woe:name_adm1":"Oregon",
    "woe:placetype":"Town",
    "wof:name":"Whiteson",
    "wof:placetype":"locality"
},
  "geometry": {"coordinates":[-123.19677,45.15151],"type":"Point"}
}