{
  "type": "Feature",
  "properties": {
    "iso:country":"US",
    "name:eng_x_preferred":[
        "Glen Oaks"
    ],
    "wd:wordcount":1272,
    "wof:name":"Glen Oaks",
    "wof:placetype":"neighbourhood",
    "wof:population":190,
    "zs:area_m":433988.656667,
    "zs:blockids":[
        481130130081003,
        481130130082004,
        481130130081005
    ],
    "zs:housing10":68,
    "zs:label":"Glen Oaks",
    "zs:pop10":190
},
  "geometry": {"coordinates":[-96.727777,32.886821],"type":"Point"}
}