{
  "type": "Feature",
  "properties": {
    "gn:admin1_code":"WV",
    "gn:admin2_code":"61.0",
    "gn:asciiname":"Price",
    "gn:country_code":"US",
    "gn:dem":286,
    "gn:elevation":"290.0",
    "gn:feature_class":"P",
    "gn:feature_code":"PPL",
    "gn:name":"Price",
    "gn:population":0,
    "gn:timezone":"America/New_York",
    "iso:country":"US",
    "wof:name":"Price",
    "wof:placetype":"locality"
},
  "geometry": {"coordinates":[-80.1284,39.70813],"type":"Point"}
}