{
  "type": "Feature",
  "properties": {
    "gn:admin1_code":"KY",
    "gn:admin2_code":"209",
    "gn:asciiname":"Peak",
    "gn:country_code":"US",
    "gn:dem":267,
    "gn:elevation":"267.0",
    "gn:feature_class":"P",
    "gn:feature_code":"PPL",
    "gn:name":"Peak",
    "gn:population":0,
    "gn:timezone":"America/New_York",
    "iso:country":"US",
    "name:ceb_x_preferred":[
        "Peak"
    ],
    "name:deu_x_preferred":[
        "Peak"
    ],
    "name:fra_x_preferred":[
        "Peak"
    ],
    "name:jpn_x_preferred":[
        "\u30d4\u30fc\u30af"
    ],
    "name:spa_x_preferred":[
        "Peak"
    ],
    "name:zho_x_preferred":[
        "Peak"
    ],
    "wof:name":"Peak",
    "wof:placetype":"locality"
},
  "geometry": {"coordinates":[-84.60966999999999,38.17535],"type":"Point"}
}