{
  "type": "Feature",
  "properties": {
    "gn:admin1_code":"VA",
    "gn:admin2_code":"177",
    "gn:asciiname":"Parker",
    "gn:country_code":"US",
    "gn:dem":130,
    "gn:elevation":"130.0",
    "gn:feature_class":"P",
    "gn:feature_code":"PPL",
    "gn:name":"Parker",
    "gn:population":0,
    "gn:timezone":"America/New_York",
    "iso:country":"US",
    "name:bel_x_preferred":[
        "\u041f\u0430\u0440\u043a\u0435\u0440"
    ],
    "name:ceb_x_preferred":[
        "Parker"
    ],
    "name:ces_x_preferred":[
        "Parker"
    ],
    "name:deu_x_preferred":[
        "Parker"
    ],
    "name:fas_x_preferred":[
        "\u067e\u0627\u0631\u06a9\u0631"
    ],
    "name:fin_x_preferred":[
        "Parker"
    ],
    "name:fra_x_preferred":[
        "Parker"
    ],
    "name:heb_x_preferred":[
        "\u05e4\u05d0\u05e8\u05e7\u05e8"
    ],
    "name:hun_x_preferred":[
        "Parker"
    ],
    "name:ita_x_preferred":[
        "Parker"
    ],
    "name:jpn_x_preferred":[
        "\u30d1\u30fc\u30ab\u30fc"
    ],
    "name:lav_x_preferred":[
        "P\u0101rkers"
    ],
    "name:lit_x_preferred":[
        "Parker"
    ],
    "name:nld_x_preferred":[
        "Parker"
    ],
    "name:nor_x_preferred":[
        "Parker"
    ],
    "name:pol_x_preferred":[
        "Parker"
    ],
    "name:por_x_preferred":[
        "Parker"
    ],
    "name:rus_x_preferred":[
        "\u041f\u0430\u0440\u043a\u0435\u0440"
    ],
    "name:spa_x_preferred":[
        "Parker"
    ],
    "name:srp_x_preferred":[
        "\u041f\u0430\u0440\u043a\u0435\u0440"
    ],
    "name:swe_x_preferred":[
        "Parker"
    ],
    "name:ukr_x_preferred":[
        "\u041f\u0430\u0440\u043a\u0435\u0440"
    ],
    "name:urd_x_preferred":[
        "\u067e\u0627\u0631\u06a9\u0631"
    ],
    "name:vie_x_preferred":[
        "Parker"
    ],
    "name:vol_x_preferred":[
        "Parker"
    ],
    "wof:name":"Parker",
    "wof:placetype":"locality"
},
  "geometry": {"coordinates":[-77.75721,38.27513],"type":"Point"}
}