{
  "type": "Feature",
  "properties": {
    "gn:admin1_code":"VA",
    "gn:admin2_code":"121",
    "gn:asciiname":"Reesedale",
    "gn:country_code":"US",
    "gn:dem":443,
    "gn:elevation":"445.0",
    "gn:feature_class":"P",
    "gn:feature_code":"PPL",
    "gn:name":"Reesedale",
    "gn:population":0,
    "gn:timezone":"America/New_York",
    "iso:country":"US",
    "wof:name":"Reesedale",
    "wof:placetype":"locality"
},
  "geometry": {"coordinates":[-80.29893,37.2293],"type":"Point"}
}