{
  "type": "Feature",
  "properties": {
    "gn:admin1_code":"TX",
    "gn:admin2_code":"401",
    "gn:asciiname":"Good Springs",
    "gn:country_code":"US",
    "gn:dem":136,
    "gn:elevation":"131.0",
    "gn:feature_class":"P",
    "gn:feature_code":"PPL",
    "gn:name":"Good Springs",
    "gn:population":0,
    "gn:timezone":"America/Chicago",
    "iso:country":"US",
    "wof:name":"Good Springs",
    "wof:placetype":"locality"
},
  "geometry": {"coordinates":[-94.91077,32.05627],"type":"Point"}
}