{
  "type": "Feature",
  "properties": {
    "gn:admin1_code":"FL",
    "gn:admin2_code":"109.0",
    "gn:asciiname":"Seven Pines Mobile Home Park",
    "gn:country_code":"US",
    "gn:dem":14,
    "gn:elevation":"10.0",
    "gn:feature_class":"P",
    "gn:feature_code":"PPL",
    "gn:name":"Seven Pines Mobile Home Park",
    "gn:population":0,
    "gn:timezone":"America/New_York",
    "iso:country":"US",
    "wof:name":"Seven Pines Mobile Home Park",
    "wof:placetype":"campus"
},
  "geometry": {"coordinates":[-81.35621999999999,29.91996],"type":"Point"}
}