{
  "type": "Feature",
  "properties": {
    "gn:admin1_code":"MI",
    "gn:admin2_code":"57.0",
    "gn:admin3_code":"44080.0",
    "gn:asciiname":"Langport",
    "gn:country_code":"US",
    "gn:dem":212,
    "gn:elevation":"212.0",
    "gn:feature_class":"P",
    "gn:feature_code":"PPL",
    "gn:name":"Langport",
    "gn:population":0,
    "gn:timezone":"America/Detroit",
    "iso:country":"US",
    "name:azb_x_preferred":[
        "\u0644\u0627\u0646\u0642\u067e\u0648\u0631\u062a"
    ],
    "name:ceb_x_preferred":[
        "Langport"
    ],
    "name:cym_x_preferred":[
        "Langport"
    ],
    "name:fas_x_preferred":[
        "\u0644\u0627\u0646\u06af\u067e\u0648\u0631\u062a"
    ],
    "name:fra_x_preferred":[
        "Langport"
    ],
    "name:gle_x_preferred":[
        "Langport"
    ],
    "name:ita_x_preferred":[
        "Langport"
    ],
    "name:lat_x_preferred":[
        "Langport"
    ],
    "name:nld_x_preferred":[
        "Langport"
    ],
    "name:pol_x_preferred":[
        "Langport"
    ],
    "name:spa_x_preferred":[
        "Langport"
    ],
    "name:swe_x_preferred":[
        "Langport"
    ],
    "wof:name":"Langport",
    "wof:placetype":"locality"
},
  "geometry": {"coordinates":[-84.38970999999999,43.36503],"type":"Point"}
}