{
  "type": "Feature",
  "properties": {
    "iso:country":"US",
    "name:ceb_x_preferred":[
        "Castlewood"
    ],
    "name:deu_x_preferred":[
        "Castlewood"
    ],
    "name:eng_x_preferred":[
        "Castlewood"
    ],
    "name:fra_x_preferred":[
        "Castlewood"
    ],
    "name:ita_x_preferred":[
        "Castlewood"
    ],
    "name:nld_x_preferred":[
        "Castlewood"
    ],
    "name:pol_x_preferred":[
        "Castlewood"
    ],
    "name:por_x_preferred":[
        "Castlewood"
    ],
    "name:srp_x_preferred":[
        "\u041a\u0430\u0441\u043b\u0432\u0443\u0434"
    ],
    "name:ukr_x_preferred":[
        "\u041a\u0430\u0441\u043b\u0432\u0443\u0434"
    ],
    "name:vol_x_preferred":[
        "Castlewood"
    ],
    "wd:wordcount":124,
    "wof:name":"Castlewood",
    "wof:placetype":"neighbourhood",
    "wof:population":1113,
    "zs:area_m":4298750.310743,
    "zs:blockids":[
        60170314051006,
        60170314051002,
        60170314064009,
        60170314051015,
        60170314051010,
        60170314064008,
        60170314051003,
        60170314051008,
        60170314051016,
        60170314051014,
        60170314051011,
        60170314051009
    ],
    "zs:housing10":522,
    "zs:label":"Castlewood",
    "zs:pop10":1113
},
  "geometry": {"coordinates":[-120.58019,38.751372],"type":"Point"}
}