{
  "type": "Feature",
  "properties": {
    "gn:country":"US",
    "gn:fcode":"PPLX",
    "gn:population":0,
    "iso:country":"US",
    "name:bul_x_preferred":[
        "\u0425\u043e\u043b\u0442"
    ],
    "name:cat_x_preferred":[
        "Holt"
    ],
    "name:ceb_x_preferred":[
        "Holt"
    ],
    "name:ces_x_preferred":[
        "Holt"
    ],
    "name:cor_x_preferred":[
        "Holt"
    ],
    "name:dan_x_preferred":[
        "Holt"
    ],
    "name:deu_x_preferred":[
        "Holt"
    ],
    "name:fra_x_preferred":[
        "Holt"
    ],
    "name:heb_x_preferred":[
        "\u05d4\u05d5\u05dc\u05d8"
    ],
    "name:ita_x_preferred":[
        "Holt"
    ],
    "name:jpn_x_preferred":[
        "\u30db\u30eb\u30c8"
    ],
    "name:nds_x_preferred":[
        "Holt"
    ],
    "name:nld_x_preferred":[
        "Holt"
    ],
    "name:nor_x_preferred":[
        "Holt"
    ],
    "name:pol_x_preferred":[
        "Holt"
    ],
    "name:por_x_preferred":[
        "Holt"
    ],
    "name:rus_x_preferred":[
        "\u0425\u043e\u043b\u044c\u0442"
    ],
    "name:spa_x_preferred":[
        "Holt"
    ],
    "name:srp_x_preferred":[
        "\u0425\u043e\u043b\u0442"
    ],
    "name:swe_x_preferred":[
        "Holt"
    ],
    "name:ukr_x_preferred":[
        "\u0413\u043e\u043b\u0442"
    ],
    "name:vol_x_preferred":[
        "Holt"
    ],
    "qs_pg:aaroncc":"US",
    "qs_pg:gn_country":"US",
    "qs_pg:gn_fcode":"PPLX",
    "qs_pg:gn_pop":0,
    "qs_pg:name":"Holt",
    "qs_pg:name_adm0":"United States",
    "qs_pg:name_adm1":"Utah",
    "qs_pg:photos":7,
    "qs_pg:photos_1k":1,
    "qs_pg:photos_9k":1,
    "qs_pg:photos_9r":1,
    "qs_pg:photos_all":7,
    "qs_pg:photos_sr":1,
    "qs_pg:pop_sr":0,
    "qs_pg:qs_pg_placetype":"neighbourhood",
    "qs_pg:qs_pg_placetype_gp":"Suburb",
    "qs_pg:woe_adm0":23424977,
    "woe:adm0_id":23424977,
    "woe:name_adm0":"United States",
    "woe:name_adm1":"Utah",
    "woe:placetype":"Suburb",
    "wof:name":"Holt",
    "wof:placetype":"neighbourhood"
},
  "geometry": {"coordinates":[-111.99772,41.07744],"type":"Point"}
}