{
  "type": "Feature",
  "properties": {
    "iso:country":"US",
    "name:eng_x_preferred":[
        "Andover Hills"
    ],
    "name:eng_x_variant":[
        "Andover Hls"
    ],
    "qs:gn_adm0_cc":"US",
    "qs:gn_local":4297983,
    "qs:gn_nam_loc":"Lexington, Fayette, Kentucky, US",
    "qs:gn_namadm1":"KY",
    "qs:local_max":4034,
    "qs:local_sum":30708,
    "qs:localhoods":91,
    "qs:name":"Andover Hills",
    "qs:name_adm0":"United States",
    "qs:name_adm1":"Kentucky",
    "qs:name_adm2":"Fayette",
    "qs:name_local":"Lexington",
    "qs:photo_max":118,
    "qs:photo_sum":119,
    "qs:placetype":"Suburb",
    "qs:quad_count":2,
    "qs:woe_adm0":23424977,
    "qs:woe_adm1":2347576,
    "qs:woe_adm2":12588509,
    "qs:woe_funk":"Parented by a neighborhood",
    "qs:woe_lau":0,
    "qs:woe_local":2438841,
    "qs:woe_ver":"7.10.0",
    "wof:lang":[
        "eng"
    ],
    "wof:name":"Andover Hills",
    "wof:placetype":"neighbourhood",
    "wof:population":3735,
    "zs:blockids":[
        210670039122008,
        210670039122012,
        210670039132007,
        210670039132004,
        210670039133006,
        210670039122007,
        210670039132000,
        210670039131000,
        210670039132005,
        210670039133017,
        210670039122004,
        210670039131001,
        210670039122002,
        210670039122009,
        210670039133013,
        210670039133014,
        210670039133011,
        210670039131005,
        210670039122015,
        210670039122010,
        210670039122001,
        210670039131007,
        210670039131009,
        210670039131006,
        210670039122013,
        210670039131008,
        210670039132003,
        210670039133019,
        210670039131004,
        210670039133016,
        210670039133009,
        210670039132001,
        210670039132006,
        210670039133037,
        210670039122011,
        210670039133036,
        210670039131002,
        210670039132002,
        210670039131003,
        210670039133002,
        210670039133007
    ],
    "zs:housing10":1415,
    "zs:pop10":3735
},
  "geometry": {"coordinates":[-84.406622,37.99507],"type":"Point"}
}