{
  "type": "Feature",
  "properties": {
    "gn:admin1_code":"FL",
    "gn:admin2_code":"57",
    "gn:asciiname":"The Manors of Nottingham",
    "gn:country_code":"US",
    "gn:dem":19,
    "gn:elevation":"10.0",
    "gn:feature_class":"P",
    "gn:feature_code":"PPL",
    "gn:name":"The Manors of Nottingham",
    "gn:population":0,
    "gn:timezone":"America/New_York",
    "iso:country":"US",
    "wof:name":"The Manors of Nottingham",
    "wof:placetype":"locality"
},
  "geometry": {"coordinates":[-82.39570000000001,28.0904],"type":"Point"}
}