{
  "type": "Feature",
  "properties": {
    "iso:country":"US",
    "name:eng_x_preferred":[
        "Willowcrest"
    ],
    "wof:name":"Willowcrest",
    "wof:placetype":"neighbourhood",
    "wof:population":1041,
    "zs:area_m":2539709.735152,
    "zs:blockids":[
        240217512032010,
        240217505043012,
        240217505035014,
        240217505035002,
        240217505043017,
        240217512032013,
        240217512032004,
        240217505035013,
        240217505035001,
        240217512032011,
        240217512032009,
        240217512024001,
        240217512032003,
        240217505043011,
        240217505044002,
        240217505035000,
        240217505035003,
        240217505035004,
        240217512032005
    ],
    "zs:housing10":343,
    "zs:label":"Willowcrest",
    "zs:pop10":1041
},
  "geometry": {"coordinates":[-77.452127,39.434724],"type":"Point"}
}