{
  "type": "Feature",
  "properties": {
    "iso:country":"US",
    "name:eng_x_preferred":[
        "Storey Creek"
    ],
    "wof:name":"Storey Creek",
    "wof:placetype":"neighbourhood",
    "wof:population":362,
    "zs:area_m":2533028.580031,
    "zs:blockids":[
        120570103041024,
        120570121061002,
        120570103041023,
        120570103041001,
        120570121061000,
        120570103041008,
        120570103041025,
        120570103041026
    ],
    "zs:housing10":132,
    "zs:label":"Storey Creek",
    "zs:pop10":362
},
  "geometry": {"coordinates":[-82.24249399999999,28.037707],"type":"Point"}
}