{
  "type": "Feature",
  "properties": {
    "gn:admin1_code":"AL",
    "gn:admin2_code":"79.0",
    "gn:asciiname":"Rocky Hill",
    "gn:country_code":"US",
    "gn:dem":183,
    "gn:elevation":"178.0",
    "gn:feature_class":"P",
    "gn:feature_code":"PPL",
    "gn:name":"Rocky Hill",
    "gn:population":0,
    "gn:timezone":"America/Chicago",
    "iso:country":"US",
    "name:ceb_x_preferred":[
        "Rocky Hill"
    ],
    "name:deu_x_preferred":[
        "Rocky Hill"
    ],
    "name:ita_x_preferred":[
        "Rocky Hill"
    ],
    "name:pol_x_preferred":[
        "Rocky Hill"
    ],
    "name:vol_x_preferred":[
        "Rocky Hill"
    ],
    "name:zho_x_preferred":[
        "\u7f85\u57fa\u5c71"
    ],
    "wof:name":"Rocky Hill",
    "wof:placetype":"locality"
},
  "geometry": {"coordinates":[-87.34447,34.67953],"type":"Point"}
}