{
  "type": "Feature",
  "properties": {
    "iso:country":"US",
    "name:eng_x_preferred":[
        "Trece"
    ],
    "qs:gn_adm0_cc":"US",
    "qs:gn_local":5756758,
    "qs:gn_nam_loc":"Tigard, Washington, Oregon, US",
    "qs:gn_namadm1":"OR",
    "qs:local_max":1199,
    "qs:local_sum":2880,
    "qs:localhoods":5,
    "qs:name":"Trece",
    "qs:name_adm0":"United States",
    "qs:name_adm1":"Oregon",
    "qs:name_adm2":"Washington",
    "qs:name_local":"Tigard",
    "qs:photo_max":52,
    "qs:photo_sum":475,
    "qs:placetype":"Suburb",
    "qs:quad_count":43,
    "qs:woe_adm0":23424977,
    "qs:woe_adm1":2347596,
    "qs:woe_adm2":12589725,
    "qs:woe_lau":0,
    "qs:woe_local":2506290,
    "qs:woe_ver":"7.10.0",
    "wof:lang":[
        "eng"
    ],
    "wof:name":"Trece",
    "wof:placetype":"neighbourhood",
    "zs:blockids":[
        410050203021006,
        410050203041028,
        410050203041029
    ],
    "zs:housing10":0,
    "zs:pop10":0
},
  "geometry": {"coordinates":[-122.755932,45.428573],"type":"Point"}
}