{
  "type": "Feature",
  "properties": {
    "gn:admin1_code":"WV",
    "gn:admin2_code":"107",
    "gn:asciiname":"Lowdell",
    "gn:country_code":"US",
    "gn:dem":202,
    "gn:elevation":"200.0",
    "gn:feature_class":"P",
    "gn:feature_code":"PPL",
    "gn:name":"Lowdell",
    "gn:population":0,
    "gn:timezone":"America/New_York",
    "iso:country":"US",
    "wof:name":"Lowdell",
    "wof:placetype":"locality"
},
  "geometry": {"coordinates":[-81.61124000000002,39.0598],"type":"Point"}
}