{
  "type": "Feature",
  "properties": {
    "gn:admin1_code":"ME",
    "gn:admin2_code":"21.0",
    "gn:admin3_code":"66950.0",
    "gn:asciiname":"South Sebec",
    "gn:country_code":"US",
    "gn:dem":95,
    "gn:elevation":"89.0",
    "gn:feature_class":"P",
    "gn:feature_code":"PPL",
    "gn:name":"South Sebec",
    "gn:population":0,
    "gn:timezone":"America/New_York",
    "iso:country":"US",
    "wof:name":"South Sebec",
    "wof:placetype":"locality"
},
  "geometry": {"coordinates":[-69.08365000000001,45.20811],"type":"Point"}
}