{
  "type": "Feature",
  "properties": {
    "gn:country":"US",
    "gn:fcode":"PPLX",
    "gn:population":0,
    "iso:country":"US",
    "name:eng_x_preferred":[
        "Nevitt Pines"
    ],
    "qs_pg:aaroncc":"US",
    "qs_pg:gn_country":"US",
    "qs_pg:gn_fcode":"PPLX",
    "qs_pg:gn_pop":0,
    "qs_pg:name":"Nevitt Pines",
    "qs_pg:name_adm0":"United States",
    "qs_pg:name_adm1":"South Carolina",
    "qs_pg:photos":1,
    "qs_pg:photos_1k":1,
    "qs_pg:photos_9k":1,
    "qs_pg:photos_9r":1,
    "qs_pg:photos_all":1,
    "qs_pg:photos_sr":1,
    "qs_pg:pop_sr":0,
    "qs_pg:qs_pg_placetype":"neighbourhood",
    "qs_pg:qs_pg_placetype_gp":"Suburb",
    "qs_pg:woe_adm0":23424977,
    "wof:name":"Nevitt Pines",
    "wof:placetype":"neighbourhood",
    "wof:population":280,
    "zs:area_m":3126673.534978,
    "zs:blockids":[
        450070113002031,
        450070113002032,
        450070113002025
    ],
    "zs:housing10":30,
    "zs:label":"Nevitt Pines",
    "zs:pop10":280
},
  "geometry": {"coordinates":[-82.577045,34.483906],"type":"Point"}
}