{
  "type": "Feature",
  "properties": {
    "gn:admin1_code":"TX",
    "gn:admin2_code":"181.0",
    "gn:asciiname":"Sperry",
    "gn:country_code":"US",
    "gn:dem":261,
    "gn:elevation":"260.0",
    "gn:feature_class":"P",
    "gn:feature_code":"PPL",
    "gn:name":"Sperry",
    "gn:population":0,
    "gn:timezone":"America/Chicago",
    "iso:country":"US",
    "name:deu_x_preferred":[
        "Sperry"
    ],
    "name:fra_x_preferred":[
        "Sperry"
    ],
    "name:ita_x_preferred":[
        "Sperry"
    ],
    "name:nds_x_preferred":[
        "Sperry"
    ],
    "name:nld_x_preferred":[
        "Sperry"
    ],
    "name:pol_x_preferred":[
        "Sperry"
    ],
    "name:por_x_preferred":[
        "Sperry"
    ],
    "name:rus_x_preferred":[
        "\u0421\u043f\u0435\u0440\u0440\u0438"
    ],
    "wof:name":"Sperry",
    "wof:placetype":"locality"
},
  "geometry": {"coordinates":[-96.7086,33.53066],"type":"Point"}
}