{
  "type": "Feature",
  "properties": {
    "gn:admin1_code":"MD",
    "gn:admin2_code":"15.0",
    "gn:asciiname":"Topeka East",
    "gn:country_code":"US",
    "gn:dem":81,
    "gn:elevation":"81.0",
    "gn:feature_class":"P",
    "gn:feature_code":"PPL",
    "gn:name":"Topeka East",
    "gn:population":0,
    "gn:timezone":"America/New_York",
    "iso:country":"US",
    "wof:name":"Topeka East",
    "wof:placetype":"locality"
},
  "geometry": {"coordinates":[-76.14494999999999,39.69539],"type":"Point"}
}