{
  "type": "Feature",
  "properties": {
    "gn:admin1_code":"MD",
    "gn:admin2_code":"9.0",
    "gn:asciiname":"Hunting Creek Farms",
    "gn:country_code":"US",
    "gn:dem":26,
    "gn:elevation":"27.0",
    "gn:feature_class":"P",
    "gn:feature_code":"PPL",
    "gn:name":"Hunting Creek Farms",
    "gn:population":0,
    "gn:timezone":"America/New_York",
    "iso:country":"US",
    "wof:name":"Hunting Creek Farms",
    "wof:placetype":"locality"
},
  "geometry": {"coordinates":[-76.59411999999998,38.5804],"type":"Point"}
}