{
  "type": "Feature",
  "properties": {
    "gn:admin1_code":"AZ",
    "gn:admin2_code":"13.0",
    "gn:asciiname":"Golden West Estates",
    "gn:country_code":"US",
    "gn:dem":392,
    "gn:elevation":"391.0",
    "gn:feature_class":"P",
    "gn:feature_code":"PPL",
    "gn:name":"Golden West Estates",
    "gn:population":0,
    "gn:timezone":"America/Phoenix",
    "iso:country":"US",
    "wof:name":"Golden West Estates",
    "wof:placetype":"locality"
},
  "geometry": {"coordinates":[-111.75903,33.42227],"type":"Point"}
}