{
  "type": "Feature",
  "properties": {
    "iso:country":"US",
    "name:ara_x_preferred":[
        "\u0644\u0648\u062f\u0644\u0648"
    ],
    "name:arz_x_preferred":[
        "\u0644\u0648\u062f\u0644\u0648"
    ],
    "name:azb_x_preferred":[
        "\u0644\u0648\u062f\u0644\u0648\u0648"
    ],
    "name:cat_x_preferred":[
        "Ludlow"
    ],
    "name:ceb_x_preferred":[
        "Ludlow"
    ],
    "name:ces_x_preferred":[
        "Ludlow"
    ],
    "name:che_x_preferred":[
        "\u041b\u0430\u0434\u043b\u043e\u0443"
    ],
    "name:cym_x_preferred":[
        "Ludlow"
    ],
    "name:dag_x_preferred":[
        "Ludlow"
    ],
    "name:dan_x_preferred":[
        "Ludlow"
    ],
    "name:deu_x_preferred":[
        "Ludlow"
    ],
    "name:eng_x_preferred":[
        "Ludlow"
    ],
    "name:eus_x_preferred":[
        "Ludlow"
    ],
    "name:fas_x_preferred":[
        "\u0644\u0648\u062f\u0644\u0627\u0648\u060c \u0645\u0627\u0633\u0627\u0686\u0648\u0633\u062a"
    ],
    "name:fas_x_variant":[
        "\u0644\u0648\u062f\u0644\u0627\u0648"
    ],
    "name:fra_x_preferred":[
        "Ludlow"
    ],
    "name:hat_x_preferred":[
        "Ludlow"
    ],
    "name:hun_x_preferred":[
        "Ludlow"
    ],
    "name:ita_x_preferred":[
        "Ludlow"
    ],
    "name:kaz_x_preferred":[
        "\u041b\u0430\u0434\u043b\u043e\u0443"
    ],
    "name:kir_x_preferred":[
        "\u041b\u0430\u0434\u043b\u043e\u0443"
    ],
    "name:nld_x_preferred":[
        "Ludlow"
    ],
    "name:pol_x_preferred":[
        "Ludlow"
    ],
    "name:por_x_preferred":[
        "Ludlow"
    ],
    "name:spa_x_preferred":[
        "Ludlow"
    ],
    "name:swe_x_preferred":[
        "Ludlow"
    ],
    "name:tat_x_preferred":[
        "\u041b\u0430\u0434\u043b\u043e\u0443"
    ],
    "name:tur_x_preferred":[
        "Ludlow"
    ],
    "name:ukr_x_preferred":[
        "\u041b\u0430\u0434\u043b\u043e\u0443"
    ],
    "name:vol_x_preferred":[
        "Ludlow"
    ],
    "qs_pg:aaroncc":"US",
    "qs_pg:name":"Ludlow",
    "qs_pg:name_adm0":"United States",
    "qs_pg:name_adm1":"Massachusetts",
    "qs_pg:photos":331,
    "qs_pg:photos_1k":67,
    "qs_pg:photos_9k":3,
    "qs_pg:photos_9r":5,
    "qs_pg:photos_all":694,
    "qs_pg:photos_sr":5,
    "qs_pg:pop_sr":0,
    "qs_pg:qs_pg_placetype":"locality",
    "qs_pg:qs_pg_placetype_gp":"Town",
    "qs_pg:woe_adm0":23424977,
    "woe:adm0_id":23424977,
    "woe:name_adm0":"United States",
    "woe:name_adm1":"Massachusetts",
    "woe:placetype":"Town",
    "wof:coterminous":[
        404476359
    ],
    "wof:name":"Ludlow",
    "wof:placetype":"locality",
    "wof:statistical_gore":1
},
  "geometry": {"coordinates":[-72.47164100000001,42.172659],"type":"Point"}
}