{
  "type": "Feature",
  "properties": {
    "gn:admin1_code":"DE",
    "gn:admin2_code":"5.0",
    "gn:asciiname":"Redden Crossroads",
    "gn:country_code":"US",
    "gn:dem":13,
    "gn:elevation":"14.0",
    "gn:feature_class":"P",
    "gn:feature_code":"PPL",
    "gn:name":"Redden Crossroads",
    "gn:population":0,
    "gn:timezone":"America/New_York",
    "iso:country":"US",
    "name:eng_x_preferred":[
        "Redden Crossroads"
    ],
    "name:und_x_variant":[
        "Reddens Crossroad"
    ],
    "wof:name":"Redden Crossroads",
    "wof:placetype":"locality"
},
  "geometry": {"coordinates":[-75.42296999999998,38.73928],"type":"Point"}
}