{
  "type": "Feature",
  "properties": {
    "gn:admin1_code":"KS",
    "gn:admin2_code":"35.0",
    "gn:admin3_code":"5025.0",
    "gn:asciiname":"Rainbow Bend",
    "gn:country_code":"US",
    "gn:dem":359,
    "gn:elevation":"358.0",
    "gn:feature_class":"P",
    "gn:feature_code":"PPL",
    "gn:name":"Rainbow Bend",
    "gn:population":0,
    "gn:timezone":"America/Chicago",
    "iso:country":"US",
    "wof:name":"Rainbow Bend",
    "wof:placetype":"locality"
},
  "geometry": {"coordinates":[-97.13087,37.17503],"type":"Point"}
}