{
  "type": "Feature",
  "properties": {
    "iso:country":"US",
    "name:eng_x_preferred":[
        "Willows"
    ],
    "wof:name":"Willows",
    "wof:placetype":"neighbourhood",
    "wof:population":503,
    "zs:area_m":1863812.939388,
    "zs:blockids":[
        80130127053036,
        80130127052011,
        80130127053025,
        80130127052021,
        80130127052022,
        80130127071109,
        80130127071011,
        80130127052013,
        80130127071009,
        80130127052014,
        80130127052024,
        80130127053024,
        80130127052015,
        80130127071044,
        80130127052016,
        80130127052023,
        80130127052012,
        80130127071010,
        80130127052020,
        80130127071008,
        80130127081019
    ],
    "zs:housing10":187,
    "zs:label":"Willows",
    "zs:pop10":503
},
  "geometry": {"coordinates":[-105.213724,40.050566],"type":"Point"}
}