{
  "type": "Feature",
  "properties": {
    "gn:country":"US",
    "gn:fcode":"ADMD",
    "gn:population":0,
    "iso:country":"US",
    "name:ara_x_preferred":[
        "\u0643\u0646\u0648\u0643\u0633"
    ],
    "name:arz_x_preferred":[
        "\u0643\u0646\u0648\u0643\u0633"
    ],
    "name:cat_x_preferred":[
        "Knox"
    ],
    "name:che_x_preferred":[
        "\u041d\u043e\u043a\u0441"
    ],
    "name:cym_x_preferred":[
        "Knox"
    ],
    "name:deu_x_preferred":[
        "Knox"
    ],
    "name:eng_x_preferred":[
        "Town of Knox"
    ],
    "name:eng_x_variant":[
        "Knox"
    ],
    "name:eus_x_preferred":[
        "Knox"
    ],
    "name:fra_x_preferred":[
        "Knox"
    ],
    "name:hat_x_preferred":[
        "Knox"
    ],
    "name:hun_x_preferred":[
        "Knox"
    ],
    "name:ita_x_preferred":[
        "Knox"
    ],
    "name:kaz_x_preferred":[
        "\u041a\u043d\u043e\u043a\u0441"
    ],
    "name:kir_x_preferred":[
        "\u041a\u043d\u043e\u043a\u0441"
    ],
    "name:nld_x_preferred":[
        "Knox"
    ],
    "name:nob_x_preferred":[
        "Knox"
    ],
    "name:pol_x_preferred":[
        "Knox"
    ],
    "name:spa_x_preferred":[
        "Knox"
    ],
    "name:tat_x_preferred":[
        "\u041d\u043e\u043a\u0441"
    ],
    "name:tur_x_preferred":[
        "Knox"
    ],
    "name:ukr_x_preferred":[
        "\u041d\u043e\u043a\u0441"
    ],
    "name:und_x_variant":[
        "Knox Township"
    ],
    "name:vol_x_preferred":[
        "Knox"
    ],
    "qs_pg:aaroncc":"US",
    "qs_pg:gn_country":"US",
    "qs_pg:gn_fcode":"ADMD",
    "qs_pg:gn_pop":0,
    "qs_pg:name":"Knox",
    "qs_pg:name_adm0":"United States",
    "qs_pg:name_adm1":"Maine",
    "qs_pg:photos":3,
    "qs_pg:photos_1k":1,
    "qs_pg:photos_9k":1,
    "qs_pg:photos_9r":2,
    "qs_pg:photos_all":46,
    "qs_pg:photos_sr":1,
    "qs_pg:pop_sr":0,
    "qs_pg:qs_pg_placetype":"locality",
    "qs_pg:qs_pg_placetype_gp":"Town",
    "qs_pg:woe_adm0":23424977,
    "woe:adm0_id":23424977,
    "woe:name_adm0":"United States",
    "woe:name_adm1":"Maine",
    "woe:placetype":"Town",
    "wof:coterminous":[
        404474815
    ],
    "wof:name":"Knox",
    "wof:placetype":"locality",
    "wof:population":805,
    "wof:statistical_gore":1
},
  "geometry": {"coordinates":[-69.21337,44.51729],"type":"Point"}
}