{
  "type": "Feature",
  "properties": {
    "gn:admin1_code":"NJ",
    "gn:admin2_code":"11.0",
    "gn:admin3_code":"28170.0",
    "gn:asciiname":"Sheppards Mill",
    "gn:country_code":"US",
    "gn:dem":9,
    "gn:elevation":"6.0",
    "gn:feature_class":"P",
    "gn:feature_code":"PPL",
    "gn:name":"Sheppards Mill",
    "gn:population":0,
    "gn:timezone":"America/New_York",
    "iso:country":"US",
    "wof:name":"Sheppards Mill",
    "wof:placetype":"locality"
},
  "geometry": {"coordinates":[-75.31796999999997,39.41039],"type":"Point"}
}