{
  "type": "Feature",
  "properties": {
    "gn:admin1_code":"AR",
    "gn:admin2_code":"27.0",
    "gn:admin3_code":"93822.0",
    "gn:asciiname":"Bethel",
    "gn:country_code":"US",
    "gn:dem":122,
    "gn:elevation":"110.0",
    "gn:feature_class":"P",
    "gn:feature_code":"PPL",
    "gn:name":"Bethel",
    "gn:population":0,
    "gn:timezone":"America/Chicago",
    "iso:country":"US",
    "name:amh_x_preferred":[
        "\u1264\u1274\u120d"
    ],
    "name:ast_x_preferred":[
        "Bethel"
    ],
    "name:cat_x_preferred":[
        "Betel"
    ],
    "name:ces_x_preferred":[
        "B\u00e9t-el"
    ],
    "name:cym_x_preferred":[
        "Bethel"
    ],
    "name:dan_x_preferred":[
        "Betel"
    ],
    "name:deu_x_preferred":[
        "Bet-El"
    ],
    "name:ell_x_preferred":[
        "\u0392\u03b1\u03b9\u03b8\u03ae\u03bb"
    ],
    "name:epo_x_preferred":[
        "Bet-El"
    ],
    "name:eus_x_preferred":[
        "Betel"
    ],
    "name:fra_x_preferred":[
        "B\u00e9thel"
    ],
    "name:heb_x_preferred":[
        "\u05d1\u05d9\u05ea \u05d0\u05dc"
    ],
    "name:hun_x_preferred":[
        "Bethel"
    ],
    "name:hun_x_variant":[
        "B\u00e9tel"
    ],
    "name:hye_x_preferred":[
        "\u0532\u0565\u0569 \u0537\u056c"
    ],
    "name:ind_x_preferred":[
        "Betel"
    ],
    "name:ita_x_preferred":[
        "Betel"
    ],
    "name:jpn_x_preferred":[
        "\u30d9\u30c6\u30eb"
    ],
    "name:lad_x_preferred":[
        "Bethel"
    ],
    "name:nld_x_preferred":[
        "Bethel"
    ],
    "name:nor_x_preferred":[
        "Betel"
    ],
    "name:pol_x_preferred":[
        "Betel"
    ],
    "name:por_x_preferred":[
        "Betel"
    ],
    "name:rus_x_preferred":[
        "\u0412\u0435\u0444\u0438\u043b\u044c"
    ],
    "name:spa_x_preferred":[
        "Bethel"
    ],
    "name:swe_x_preferred":[
        "Betel"
    ],
    "name:tam_x_preferred":[
        "\u0baa\u0bc6\u0ba4\u0bcd\u0ba4\u0bc7\u0bb2\u0bcd"
    ],
    "name:tgl_x_preferred":[
        "Betel"
    ],
    "name:ukr_x_preferred":[
        "\u0411\u0435\u0442-\u0415\u043b"
    ],
    "name:yid_x_preferred":[
        "\u05d1\u05d9\u05ea \u05d0\u05dc"
    ],
    "name:zho_x_preferred":[
        "\u4f2f\u7279\u5229"
    ],
    "wof:name":"Bethel",
    "wof:placetype":"locality"
},
  "geometry": {"coordinates":[-93.32767,33.42429],"type":"Point"}
}