{
  "type": "Feature",
  "properties": {
    "gn:admin1_code":"PA",
    "gn:admin2_code":"77.0",
    "gn:admin3_code":"55576.0",
    "gn:asciiname":"Lockridge",
    "gn:country_code":"US",
    "gn:dem":126,
    "gn:elevation":"126.0",
    "gn:feature_class":"P",
    "gn:feature_code":"PPL",
    "gn:name":"Lockridge",
    "gn:population":0,
    "gn:timezone":"America/New_York",
    "iso:country":"US",
    "name:deu_x_preferred":[
        "Lockridge"
    ],
    "name:fra_x_preferred":[
        "Lockridge"
    ],
    "name:ita_x_preferred":[
        "Lockridge"
    ],
    "name:pol_x_preferred":[
        "Lockridge"
    ],
    "name:por_x_preferred":[
        "Lockridge"
    ],
    "name:rus_x_preferred":[
        "\u041b\u043e\u043a\u0440\u0438\u0434\u0436"
    ],
    "wof:name":"Lockridge",
    "wof:placetype":"locality"
},
  "geometry": {"coordinates":[-75.59463000000002,40.63343],"type":"Point"}
}