{
  "type": "Feature",
  "properties": {
    "gn:admin1_code":"KS",
    "gn:admin2_code":"9.0",
    "gn:admin3_code":"4975.0",
    "gn:asciiname":"Dubuque",
    "gn:country_code":"US",
    "gn:dem":581,
    "gn:elevation":"574.0",
    "gn:feature_class":"P",
    "gn:feature_code":"PPL",
    "gn:name":"Dubuque",
    "gn:population":0,
    "gn:timezone":"America/Chicago",
    "iso:country":"US",
    "wof:name":"Dubuque",
    "wof:placetype":"locality"
},
  "geometry": {"coordinates":[-98.60896,38.69584],"type":"Point"}
}