{
  "type": "Feature",
  "properties": {
    "gn:admin1_code":"IN",
    "gn:admin2_code":"151.0",
    "gn:admin3_code":"37458.0",
    "gn:asciiname":"Flint",
    "gn:country_code":"US",
    "gn:dem":298,
    "gn:elevation":"293.0",
    "gn:feature_class":"P",
    "gn:feature_code":"PPL",
    "gn:name":"Flint",
    "gn:population":0,
    "gn:timezone":"America/Indiana/Indianapolis",
    "iso:country":"US",
    "wof:name":"Flint",
    "wof:placetype":"locality"
},
  "geometry": {"coordinates":[-85.12719,41.65005],"type":"Point"}
}