{
  "type": "Feature",
  "properties": {
    "gn:admin1_code":"WA",
    "gn:admin2_code":"57.0",
    "gn:asciiname":"Nelson Mobile Home Park",
    "gn:country_code":"US",
    "gn:dem":13,
    "gn:elevation":"13.0",
    "gn:feature_class":"P",
    "gn:feature_code":"PPL",
    "gn:name":"Nelson Mobile Home Park",
    "gn:population":0,
    "gn:timezone":"America/Los_Angeles",
    "iso:country":"US",
    "wof:name":"Nelson Mobile Home Park",
    "wof:placetype":"campus"
},
  "geometry": {"coordinates":[-122.30176000000002,48.48739000000001],"type":"Point"}
}