{
  "type": "Feature",
  "properties": {
    "iso:country":"US",
    "name:eng_x_preferred":[
        "South Cushing"
    ],
    "wof:name":"South Cushing",
    "wof:placetype":"neighbourhood",
    "wof:population":136,
    "zs:area_m":11134036.590298,
    "zs:blockids":[
        230139710002031,
        230139710002041,
        230139710002049,
        230139710002044,
        230139710002048,
        230139710002024,
        230139710002027,
        230139710002025
    ],
    "zs:housing10":77,
    "zs:label":"South Cushing",
    "zs:pop10":136
},
  "geometry": {"coordinates":[-69.27761099999999,44.007751],"type":"Point"}
}