{
  "type": "Feature",
  "properties": {
    "iso:country":"US",
    "name:ceb_x_preferred":[
        "Stewartville"
    ],
    "name:deu_x_preferred":[
        "Stewartville"
    ],
    "name:pol_x_preferred":[
        "Stewartville"
    ],
    "name:srp_x_preferred":[
        "\u0421\u0442\u0458\u0443\u0430\u0440\u0442\u0432\u0438\u043b"
    ],
    "qs_pg:aaroncc":"US",
    "qs_pg:name":"Stewartville",
    "qs_pg:name_adm0":"United States",
    "qs_pg:name_adm1":"Massachusetts",
    "qs_pg:photos":46,
    "qs_pg:photos_1k":9,
    "qs_pg:photos_9k":1,
    "qs_pg:photos_9r":2,
    "qs_pg:photos_all":46,
    "qs_pg:photos_sr":2,
    "qs_pg:pop_sr":0,
    "qs_pg:qs_pg_placetype":"locality",
    "qs_pg:qs_pg_placetype_gp":"Town",
    "qs_pg:woe_adm0":23424977,
    "woe:adm0_id":23424977,
    "woe:name_adm0":"United States",
    "woe:name_adm1":"Massachusetts",
    "woe:placetype":"Town",
    "wof:name":"Stewartville",
    "wof:placetype":"locality"
},
  "geometry": {"coordinates":[-71.115188,42.413215],"type":"Point"}
}