{
  "type": "Feature",
  "properties": {
    "gn:admin1_code":"TN",
    "gn:admin2_code":"149",
    "gn:asciiname":"Halls Hill",
    "gn:country_code":"US",
    "gn:dem":183,
    "gn:elevation":"184.0",
    "gn:feature_class":"P",
    "gn:feature_code":"PPL",
    "gn:name":"Halls Hill",
    "gn:population":0,
    "gn:timezone":"America/Chicago",
    "iso:country":"US",
    "wof:name":"Halls Hill",
    "wof:placetype":"locality"
},
  "geometry": {"coordinates":[-86.23499,35.86979],"type":"Point"}
}