{
  "type": "Feature",
  "properties": {
    "gn:country":"US",
    "gn:fcode":"PPL",
    "gn:population":113004,
    "iso:country":"US",
    "qs_pg:aaroncc":"US",
    "qs_pg:gn_country":"US",
    "qs_pg:gn_fcode":"PPL",
    "qs_pg:gn_pop":113004,
    "qs_pg:name":"North Peoria",
    "qs_pg:photos_9r":0,
    "qs_pg:photos_sr":0,
    "qs_pg:pop_sr":9,
    "qs_pg:qs_pg_placetype":"locality",
    "wof:name":"North Peoria",
    "wof:placetype":"locality",
    "wof:population":113004
},
  "geometry": {"coordinates":[-89.58426,40.71754],"type":"Point"}
}