{
  "type": "Feature",
  "properties": {
    "gn:admin1_code":"WA",
    "gn:admin2_code":"61.0",
    "gn:asciiname":"Manor Heights Mobile Home Park",
    "gn:country_code":"US",
    "gn:dem":190,
    "gn:elevation":"189.0",
    "gn:feature_class":"P",
    "gn:feature_code":"PPL",
    "gn:name":"Manor Heights Mobile Home Park",
    "gn:population":0,
    "gn:timezone":"America/Los_Angeles",
    "iso:country":"US",
    "wof:name":"Manor Heights Mobile Home Park",
    "wof:placetype":"campus"
},
  "geometry": {"coordinates":[-122.28773,47.85296],"type":"Point"}
}