{
  "type": "Feature",
  "properties": {
    "gn:admin1_code":"TN",
    "gn:admin2_code":"49.0",
    "gn:asciiname":"Cooktown",
    "gn:country_code":"US",
    "gn:dem":558,
    "gn:elevation":"555.0",
    "gn:feature_class":"P",
    "gn:feature_code":"PPL",
    "gn:name":"Cooktown",
    "gn:population":0,
    "gn:timezone":"America/Chicago",
    "iso:country":"US",
    "wof:name":"Cooktown",
    "wof:placetype":"locality"
},
  "geometry": {"coordinates":[-85.12413000000002,36.33979],"type":"Point"}
}