{
  "type": "Feature",
  "properties": {
    "gn:country":"US",
    "gn:fcode":"PPL",
    "gn:population":4686,
    "iso:country":"US",
    "name:eng_x_preferred":[
        "Sansom Park"
    ],
    "name:und_x_variant":[
        "Sansom Park Village"
    ],
    "qs_pg:aaroncc":"US",
    "qs_pg:gn_country":"US",
    "qs_pg:gn_fcode":"PPL",
    "qs_pg:gn_pop":4686,
    "qs_pg:name":"Sansom Park",
    "qs_pg:name_adm0":"United States",
    "qs_pg:name_adm1":"Texas",
    "qs_pg:photos_9r":0,
    "qs_pg:photos_sr":0,
    "qs_pg:pop_sr":4,
    "qs_pg:qs_pg_placetype":"neighbourhood",
    "qs_pg:qs_pg_placetype_gp":"Suburb",
    "qs_pg:woe_adm0":23424977,
    "woe:adm0_id":23424977,
    "woe:name_adm0":"United States",
    "woe:name_adm1":"Texas",
    "woe:placetype":"Suburb",
    "wof:name":"Sansom Park",
    "wof:placetype":"neighbourhood",
    "wof:population":4858
},
  "geometry": {"coordinates":[-97.40307,32.80596],"type":"Point"}
}