{
  "type": "Feature",
  "properties": {
    "iso:country":"US",
    "name:cat_x_preferred":[
        "La Salle"
    ],
    "name:ceb_x_preferred":[
        "La Salle"
    ],
    "name:deu_x_preferred":[
        "La Salle"
    ],
    "name:eng_x_preferred":[
        "La Salle"
    ],
    "name:eng_x_variant":[
        "Lasalle"
    ],
    "name:fra_x_preferred":[
        "La Salle"
    ],
    "name:jpn_x_preferred":[
        "\u30e9\u30b5\u30fc\u30eb"
    ],
    "name:lmo_x_preferred":[
        "La Salle"
    ],
    "name:nds_x_preferred":[
        "La Salle"
    ],
    "name:nld_x_preferred":[
        "La Salle"
    ],
    "name:pms_x_preferred":[
        "La Salle"
    ],
    "name:pol_x_preferred":[
        "La Salle"
    ],
    "name:por_x_preferred":[
        "La Salle"
    ],
    "name:rus_x_preferred":[
        "\u041b\u0430 \u0421\u0430\u043b\u043b\u044c"
    ],
    "name:slk_x_preferred":[
        "La Salle"
    ],
    "name:spa_x_preferred":[
        "La Salle"
    ],
    "name:srp_x_preferred":[
        "\u041b\u0430 \u0421\u0430\u043b"
    ],
    "name:swe_x_preferred":[
        "La Salle"
    ],
    "name:ukr_x_preferred":[
        "\u041b\u0430-\u0421\u0430\u043b\u043b"
    ],
    "name:vol_x_preferred":[
        "La Salle"
    ],
    "qs:gn_fcode":"PPL",
    "qs:gn_local":0,
    "qs:gn_namadm1":"NY",
    "qs:gn_name":"La Salle",
    "qs:local_max":391,
    "qs:local_sum":614,
    "qs:localhoods":2,
    "qs:name":"La Salle",
    "qs:name_adm0":"United States",
    "qs:name_adm1":"New York",
    "qs:name_adm2":"Niagara",
    "qs:name_local":"Niagara Falls",
    "qs:photo_max":33,
    "qs:photo_sum":223,
    "qs:placetype":"Suburb",
    "qs:quad_count":31,
    "qs:woe_adm0":23424977,
    "qs:woe_adm1":2347591,
    "qs:woe_adm2":12589343,
    "qs:woe_lau":0,
    "qs:woe_local":2459807,
    "qs:woe_ver":"7.10.0",
    "wof:lang":[
        "eng"
    ],
    "wof:name":"La Salle",
    "wof:placetype":"neighbourhood",
    "zs:blockids":[
        360290073024002,
        360290073024000,
        360290073032000,
        360290073024001,
        360290073024006
    ],
    "zs:housing10":0,
    "zs:pop10":0
},
  "geometry": {"coordinates":[-78.97832099999999,43.082411],"type":"Point"}
}