{
  "type": "Feature",
  "properties": {
    "iso:country":"US",
    "name:ceb_x_preferred":[
        "Stillwater"
    ],
    "name:deu_x_preferred":[
        "Stillwater"
    ],
    "name:eng_x_preferred":[
        "Stillwater"
    ],
    "name:fin_x_preferred":[
        "Stillwater"
    ],
    "name:fra_x_preferred":[
        "Stillwater"
    ],
    "name:ita_x_preferred":[
        "Stillwater"
    ],
    "name:jpn_x_preferred":[
        "\u30b9\u30c6\u30a3\u30eb\u30a6\u30a9\u30fc\u30bf\u30fc"
    ],
    "name:kor_x_preferred":[
        "\uc2a4\ud2f8\uc6cc\ud130"
    ],
    "name:nld_x_preferred":[
        "Stillwater"
    ],
    "name:pol_x_preferred":[
        "Stillwater"
    ],
    "name:por_x_preferred":[
        "Stillwater"
    ],
    "name:rus_x_preferred":[
        "\u0421\u0442\u0438\u043b\u043b\u0443\u043e\u0442\u0435\u0440"
    ],
    "name:srp_x_preferred":[
        "\u0421\u0442\u0438\u043b\u0432\u043e\u0442\u0435\u0440"
    ],
    "name:swe_x_preferred":[
        "Stillwater"
    ],
    "name:vol_x_preferred":[
        "Stillwater"
    ],
    "name:zho_x_preferred":[
        "\u65af\u8482\u5c14\u6c83\u7279"
    ],
    "wof:name":"Stillwater",
    "wof:placetype":"neighbourhood",
    "wof:population":3277,
    "zs:area_m":7611810.506869,
    "zs:blockids":[
        360790111001027,
        360790112003013,
        360790112002004,
        360790112003025,
        360790112004011,
        360790112002002,
        360790114003020,
        360790112002003,
        360790112002006,
        360790114003021,
        360790114002019,
        360790114003019,
        360790112003022,
        360790111001020,
        360790114003016,
        360790111001025,
        360790114002022,
        360790112003014,
        360790112002010,
        360790112002005,
        360790112002000,
        360790112002009,
        360790114003012,
        360790112004005,
        360790114003015,
        360790112002007,
        360790112003027,
        360790112003026,
        360790112002023,
        360790114002020,
        360790112003019,
        360790114003018,
        360790114003013,
        360790114003017,
        360790111001026,
        360790112002008,
        360790112003020,
        360790112002033,
        360790114003014,
        360790112002001,
        360790111001013,
        360790114002015,
        360790112002020
    ],
    "zs:housing10":1176,
    "zs:label":"Stillwater",
    "zs:pop10":3277
},
  "geometry": {"coordinates":[-73.75986899999999,41.360968],"type":"Point"}
}