{
  "type": "Feature",
  "properties": {
    "gn:admin1_code":"VA",
    "gn:admin2_code":"3",
    "gn:asciiname":"Patterson Store",
    "gn:country_code":"US",
    "gn:dem":187,
    "gn:elevation":"186.0",
    "gn:feature_class":"P",
    "gn:feature_code":"PPL",
    "gn:name":"Patterson Store",
    "gn:population":0,
    "gn:timezone":"America/New_York",
    "iso:country":"US",
    "name:eng_x_preferred":[
        "Patterson Store"
    ],
    "name:und_x_variant":[
        "Pattersons Store"
    ],
    "wof:name":"Patterson Store",
    "wof:placetype":"locality"
},
  "geometry": {"coordinates":[-78.57196,38.18958],"type":"Point"}
}