{
  "type": "Feature",
  "properties": {
    "gn:admin1_code":"OK",
    "gn:admin2_code":"113",
    "gn:asciiname":"Frankfort",
    "gn:country_code":"US",
    "gn:dem":356,
    "gn:elevation":"355.0",
    "gn:feature_class":"P",
    "gn:feature_code":"PPL",
    "gn:name":"Frankfort",
    "gn:population":0,
    "gn:timezone":"America/Chicago",
    "iso:country":"US",
    "name:bre_x_preferred":[
        "Frankfort"
    ],
    "name:cat_x_preferred":[
        "Frankfort"
    ],
    "name:ceb_x_preferred":[
        "Frankfort"
    ],
    "name:deu_x_preferred":[
        "Frankfort"
    ],
    "name:epo_x_preferred":[
        "Frankfort"
    ],
    "name:fra_x_preferred":[
        "Frankfort"
    ],
    "name:hun_x_preferred":[
        "Frankfort"
    ],
    "name:ido_x_preferred":[
        "Frankfort"
    ],
    "name:ind_x_preferred":[
        "Frankfort"
    ],
    "name:ita_x_preferred":[
        "Frankfort"
    ],
    "name:jpn_x_preferred":[
        "\u30d5\u30e9\u30f3\u30af\u30d5\u30a9\u30fc\u30c8"
    ],
    "name:kor_x_preferred":[
        "\ud504\ub7ad\ud06c\ud37c\ud2b8"
    ],
    "name:nds_x_preferred":[
        "Frankfort"
    ],
    "name:nld_x_preferred":[
        "Frankfort"
    ],
    "name:pol_x_preferred":[
        "Frankfort"
    ],
    "name:por_x_preferred":[
        "Frankfort"
    ],
    "name:rus_x_preferred":[
        "\u0424\u0440\u0430\u043d\u043a\u0444\u043e\u0440\u0442"
    ],
    "name:slk_x_preferred":[
        "Frankfort"
    ],
    "name:spa_x_preferred":[
        "Frankfort"
    ],
    "name:srp_x_preferred":[
        "\u0424\u0440\u0430\u043d\u043a\u0444\u043e\u0440\u0442"
    ],
    "name:swe_x_preferred":[
        "Frankfort"
    ],
    "name:tgl_x_preferred":[
        "Frankfort"
    ],
    "name:ukr_x_preferred":[
        "\u0424\u0440\u0430\u043d\u043a\u0444\u043e\u0440\u0442"
    ],
    "name:vol_x_preferred":[
        "Frankfort"
    ],
    "name:zho_x_preferred":[
        "\u6cd5\u862d\u514b\u798f"
    ],
    "wof:name":"Frankfort",
    "wof:placetype":"locality"
},
  "geometry": {"coordinates":[-96.67975,36.97587],"type":"Point"}
}