{
  "type": "Feature",
  "properties": {
    "gn:admin1_code":"NC",
    "gn:admin2_code":"163",
    "gn:admin3_code":"90904.0",
    "gn:asciiname":"Hays Mill",
    "gn:country_code":"US",
    "gn:dem":49,
    "gn:elevation":"46.0",
    "gn:feature_class":"P",
    "gn:feature_code":"PPL",
    "gn:name":"Hays Mill",
    "gn:population":0,
    "gn:timezone":"America/New_York",
    "iso:country":"US",
    "wof:name":"Hays Mill",
    "wof:placetype":"locality"
},
  "geometry": {"coordinates":[-78.62113000000002,35.11960999999999],"type":"Point"}
}