{
  "type": "Feature",
  "properties": {
    "gn:admin1_code":"VA",
    "gn:admin2_code":"3",
    "gn:asciiname":"Jefferson Village",
    "gn:country_code":"US",
    "gn:dem":157,
    "gn:elevation":"158.0",
    "gn:feature_class":"P",
    "gn:feature_code":"PPL",
    "gn:name":"Jefferson Village",
    "gn:population":0,
    "gn:timezone":"America/New_York",
    "iso:country":"US",
    "wof:name":"Jefferson Village",
    "wof:placetype":"locality"
},
  "geometry": {"coordinates":[-78.42084,38.12764],"type":"Point"}
}