{
  "type": "Feature",
  "properties": {
    "gn:admin1_code":"WA",
    "gn:admin2_code":"61.0",
    "gn:asciiname":"Lake Stickney Mobile Home Park",
    "gn:country_code":"US",
    "gn:dem":138,
    "gn:elevation":"138.0",
    "gn:feature_class":"P",
    "gn:feature_code":"PPL",
    "gn:name":"Lake Stickney Mobile Home Park",
    "gn:population":0,
    "gn:timezone":"America/Los_Angeles",
    "iso:country":"US",
    "wof:name":"Lake Stickney Mobile Home Park",
    "wof:placetype":"campus"
},
  "geometry": {"coordinates":[-122.25688,47.87932],"type":"Point"}
}