{
  "type": "Feature",
  "properties": {
    "gn:admin1_code":"NY",
    "gn:admin2_code":"43.0",
    "gn:admin3_code":"19686.0",
    "gn:asciiname":"Homestead Mobile Park",
    "gn:country_code":"US",
    "gn:dem":135,
    "gn:elevation":"134.0",
    "gn:feature_class":"P",
    "gn:feature_code":"PPL",
    "gn:name":"Homestead Mobile Park",
    "gn:population":0,
    "gn:timezone":"America/New_York",
    "iso:country":"US",
    "wof:name":"Homestead Mobile Park",
    "wof:placetype":"locality"
},
  "geometry": {"coordinates":[-74.81317,43.01913],"type":"Point"}
}