{
  "type": "Feature",
  "properties": {
    "gn:admin1_code":"SC",
    "gn:admin2_code":"45.0",
    "gn:asciiname":"Brookwood Forest",
    "gn:country_code":"US",
    "gn:dem":294,
    "gn:elevation":"293.0",
    "gn:feature_class":"P",
    "gn:feature_code":"PPL",
    "gn:name":"Brookwood Forest",
    "gn:population":0,
    "gn:timezone":"America/New_York",
    "iso:country":"US",
    "wof:name":"Brookwood Forest",
    "wof:placetype":"locality"
},
  "geometry": {"coordinates":[-82.33400999999998,34.91678],"type":"Point"}
}