{
  "type": "Feature",
  "properties": {
    "gn:admin1_code":"OK",
    "gn:admin2_code":"31.0",
    "gn:asciiname":"Peachtree Crossing",
    "gn:country_code":"US",
    "gn:dem":352,
    "gn:elevation":"339.0",
    "gn:feature_class":"P",
    "gn:feature_code":"PPL",
    "gn:name":"Peachtree Crossing",
    "gn:population":0,
    "gn:timezone":"America/Chicago",
    "iso:country":"US",
    "wof:name":"Peachtree Crossing",
    "wof:placetype":"locality"
},
  "geometry": {"coordinates":[-98.38172,34.68702],"type":"Point"}
}