{
  "type": "Feature",
  "properties": {
    "gn:admin1_code":"ME",
    "gn:admin2_code":"9.0",
    "gn:admin3_code":"7975.0",
    "gn:asciiname":"Flat Landing",
    "gn:country_code":"US",
    "gn:dem":29,
    "gn:elevation":"12.0",
    "gn:feature_class":"P",
    "gn:feature_code":"PPL",
    "gn:name":"Flat Landing",
    "gn:population":0,
    "gn:timezone":"America/New_York",
    "iso:country":"US",
    "wof:name":"Flat Landing",
    "wof:placetype":"locality"
},
  "geometry": {"coordinates":[-68.76947,44.35869],"type":"Point"}
}