{
  "type": "Feature",
  "properties": {
    "gn:admin1_code":"WA",
    "gn:admin2_code":"25.0",
    "gn:asciiname":"Ruff",
    "gn:country_code":"US",
    "gn:dem":413,
    "gn:elevation":"416.0",
    "gn:feature_class":"P",
    "gn:feature_code":"PPL",
    "gn:name":"Ruff",
    "gn:population":0,
    "gn:timezone":"America/Los_Angeles",
    "iso:country":"US",
    "wof:name":"Ruff",
    "wof:placetype":"locality"
},
  "geometry": {"coordinates":[-118.99833999999998,47.16959],"type":"Point"}
}