{
  "type": "Feature",
  "properties": {
    "gn:admin1_code":"KY",
    "gn:admin2_code":"231",
    "gn:asciiname":"Slickford",
    "gn:country_code":"US",
    "gn:dem":272,
    "gn:elevation":"268.0",
    "gn:feature_class":"P",
    "gn:feature_code":"PPL",
    "gn:name":"Slickford",
    "gn:population":0,
    "gn:timezone":"America/Kentucky/Monticello",
    "iso:country":"US",
    "wof:name":"Slickford",
    "wof:placetype":"locality"
},
  "geometry": {"coordinates":[-84.9205,36.68757],"type":"Point"}
}