{
  "type": "Feature",
  "properties": {
    "gn:admin1_code":"OH",
    "gn:admin2_code":"135.0",
    "gn:admin3_code":"38780.0",
    "gn:asciiname":"Brinley",
    "gn:country_code":"US",
    "gn:dem":344,
    "gn:elevation":"343.0",
    "gn:feature_class":"P",
    "gn:feature_code":"PPL",
    "gn:name":"Brinley",
    "gn:population":0,
    "gn:timezone":"America/New_York",
    "iso:country":"US",
    "name:eng_x_preferred":[
        "Brinley"
    ],
    "name:und_x_variant":[
        "Brinleys Station",
        "Brinleys"
    ],
    "wof:name":"Brinley",
    "wof:placetype":"locality"
},
  "geometry": {"coordinates":[-84.73968000000001,39.89449000000001],"type":"Point"}
}