{
  "type": "Feature",
  "properties": {
    "gn:admin1_code":"AR",
    "gn:admin2_code":"33.0",
    "gn:admin3_code":"91124.0",
    "gn:asciiname":"Greenwood Junction",
    "gn:country_code":"US",
    "gn:dem":134,
    "gn:elevation":"127.0",
    "gn:feature_class":"P",
    "gn:feature_code":"PPL",
    "gn:name":"Greenwood Junction",
    "gn:population":0,
    "gn:timezone":"America/Chicago",
    "iso:country":"US",
    "wof:name":"Greenwood Junction",
    "wof:placetype":"locality"
},
  "geometry": {"coordinates":[-94.43994000000001,35.44815],"type":"Point"}
}