{
  "type": "Feature",
  "properties": {
    "iso:country":"US",
    "name:ara_x_preferred":[
        "\u062f\u0648\u0641\u0631\u060c \u0645\u0642\u0627\u0637\u0639\u0629 \u0631\u0627\u0633\u064a\u0646"
    ],
    "name:ara_x_variant":[
        "\u062f\u0648\u0641\u0631"
    ],
    "name:eng_x_preferred":[
        "Dover"
    ],
    "name:ita_x_preferred":[
        "Dover"
    ],
    "name:pol_x_preferred":[
        "Dover"
    ],
    "name:spa_x_preferred":[
        "Dover"
    ],
    "name:vie_x_preferred":[
        "Dover"
    ],
    "qs_pg:aaroncc":"US",
    "qs_pg:name":"Dover",
    "qs_pg:name_adm0":"United States",
    "qs_pg:name_adm1":"Wisconsin",
    "qs_pg:photos":8,
    "qs_pg:photos_1k":2,
    "qs_pg:photos_9k":1,
    "qs_pg:photos_9r":2,
    "qs_pg:photos_all":31,
    "qs_pg:photos_sr":1,
    "qs_pg:pop_sr":0,
    "qs_pg:qs_pg_placetype":"locality",
    "qs_pg:qs_pg_placetype_gp":"Town",
    "qs_pg:woe_adm0":23424977,
    "woe:adm0_id":23424977,
    "woe:name_adm0":"United States",
    "woe:name_adm1":"Wisconsin",
    "woe:placetype":"Town",
    "wof:name":"Dover",
    "wof:placetype":"locality"
},
  "geometry": {"coordinates":[-88.18862849999998,42.6828135],"type":"Point"}
}