{
  "type": "Feature",
  "properties": {
    "gn:admin1_code":"MD",
    "gn:admin2_code":"45.0",
    "gn:asciiname":"Washington Heights",
    "gn:country_code":"US",
    "gn:dem":12,
    "gn:elevation":"10.0",
    "gn:feature_class":"P",
    "gn:feature_code":"PPL",
    "gn:name":"Washington Heights",
    "gn:population":0,
    "gn:timezone":"America/New_York",
    "iso:country":"US",
    "name:deu_x_preferred":[
        "Washington Heights"
    ],
    "name:ita_x_preferred":[
        "Washington Heights"
    ],
    "name:jpn_x_preferred":[
        "\u30ef\u30b7\u30f3\u30c8\u30f3\u30cf\u30a4\u30c4"
    ],
    "name:kor_x_preferred":[
        "\uc6cc\uc2f1\ud134\ud558\uc774\uce20"
    ],
    "name:vol_x_preferred":[
        "Washington Heights"
    ],
    "wof:name":"Washington Heights",
    "wof:placetype":"locality"
},
  "geometry": {"coordinates":[-75.57326,38.37234],"type":"Point"}
}