{
  "type": "Feature",
  "properties": {
    "gn:admin1_code":"FL",
    "gn:admin2_code":"57",
    "gn:asciiname":"Carrollwood Reserve",
    "gn:country_code":"US",
    "gn:dem":15,
    "gn:elevation":"11.0",
    "gn:feature_class":"P",
    "gn:feature_code":"PPL",
    "gn:name":"Carrollwood Reserve",
    "gn:population":0,
    "gn:timezone":"America/New_York",
    "iso:country":"US",
    "wof:name":"Carrollwood Reserve",
    "wof:placetype":"locality"
},
  "geometry": {"coordinates":[-82.5474,28.0646],"type":"Point"}
}