{
  "type": "Feature",
  "properties": {
    "gn:admin1_code":"SC",
    "gn:admin2_code":"63.0",
    "gn:asciiname":"Ridge Road Crossroads",
    "gn:country_code":"US",
    "gn:dem":155,
    "gn:elevation":"153.0",
    "gn:feature_class":"P",
    "gn:feature_code":"PPL",
    "gn:name":"Ridge Road Crossroads",
    "gn:population":0,
    "gn:timezone":"America/New_York",
    "iso:country":"US",
    "wof:name":"Ridge Road Crossroads",
    "wof:placetype":"locality"
},
  "geometry": {"coordinates":[-81.47205,34.00292],"type":"Point"}
}