{
  "type": "Feature",
  "properties": {
    "gn:admin1_code":"FL",
    "gn:admin2_code":"105.0",
    "gn:asciiname":"Palm Shores Mobile Village",
    "gn:country_code":"US",
    "gn:dem":43,
    "gn:elevation":"40.0",
    "gn:feature_class":"P",
    "gn:feature_code":"PPL",
    "gn:name":"Palm Shores Mobile Village",
    "gn:population":0,
    "gn:timezone":"America/New_York",
    "iso:country":"US",
    "wof:name":"Palm Shores Mobile Village",
    "wof:placetype":"locality"
},
  "geometry": {"coordinates":[-81.71283000000003,28.09578],"type":"Point"}
}