{
  "type": "Feature",
  "properties": {
    "gn:elevation":34,
    "gn:population":7443,
    "iso:country":"US",
    "name:cat_x_preferred":[
        "Twin Rivers"
    ],
    "name:ceb_x_preferred":[
        "Twin Rivers"
    ],
    "name:eng_x_preferred":[
        "Twin Rivers"
    ],
    "name:fra_x_preferred":[
        "Twin Rivers"
    ],
    "name:hbs_x_preferred":[
        "Twin Rivers"
    ],
    "name:ita_x_preferred":[
        "Twin Rivers"
    ],
    "name:kaz_x_preferred":[
        "\u0422\u0432\u0438\u043d \u0420\u0438\u0432\u044d\u0440\u0441"
    ],
    "name:kir_x_preferred":[
        "\u0422\u0432\u0438\u043d \u0420\u0438\u0432\u044d\u0440\u0441"
    ],
    "name:nan_x_preferred":[
        "Twin Rivers"
    ],
    "name:nld_x_preferred":[
        "Twin Rivers"
    ],
    "name:pol_x_preferred":[
        "Twin Rivers"
    ],
    "name:por_x_preferred":[
        "Twin Rivers"
    ],
    "name:spa_x_preferred":[
        "Twin Rivers"
    ],
    "name:srp_x_preferred":[
        "\u0422\u0432\u0438\u043d \u0420\u0438\u0432\u0435\u0440\u0441"
    ],
    "name:uzb_x_preferred":[
        "Twin Rivers"
    ],
    "name:vol_x_preferred":[
        "Twin Rivers"
    ],
    "name:vol_x_variant":[
        "Tysons Green"
    ],
    "qs:gn_adm0_cc":"US",
    "qs:gn_fcode":"PPL",
    "qs:gn_local":8354649,
    "qs:gn_nam_loc":"East Windsor, Mercer, New Jersey, US",
    "qs:gn_namadm1":"NJ",
    "qs:gn_name":"Twin Rivers",
    "qs:local_max":31,
    "qs:local_sum":67,
    "qs:localhoods":3,
    "qs:name":"Twin Rivers",
    "qs:name_adm0":"United States",
    "qs:name_adm1":"New Jersey",
    "qs:name_adm2":"Mercer",
    "qs:name_local":"East Windsor",
    "qs:photo_max":7,
    "qs:photo_sum":28,
    "qs:placetype":"Suburb",
    "qs:quad_count":11,
    "qs:woe_adm0":23424977,
    "qs:woe_adm1":2347589,
    "qs:woe_adm2":12589268,
    "qs:woe_lau":0,
    "qs:woe_local":26342930,
    "qs:woe_ver":"7.10.0",
    "wof:lang":[
        "eng"
    ],
    "wof:name":"Twin Rivers",
    "wof:placetype":"neighbourhood",
    "wof:population":7443,
    "zs:blockids":[
        340258125022007
    ],
    "zs:housing10":20,
    "zs:pop10":47
},
  "geometry": {"coordinates":[-74.500056,40.2674],"type":"Point"}
}