{
  "type": "Feature",
  "properties": {
    "gn:country":"US",
    "gn:fcode":"PPL",
    "gn:population":0,
    "iso:country":"US",
    "name:ceb_x_preferred":[
        "Westboro"
    ],
    "name:fra_x_preferred":[
        "Westboro"
    ],
    "name:ita_x_preferred":[
        "Westboro"
    ],
    "name:pol_x_preferred":[
        "Westboro"
    ],
    "name:rus_x_preferred":[
        "\u0423\u044d\u0441\u0442\u0431\u043e\u0440\u043e"
    ],
    "name:srp_x_preferred":[
        "\u0412\u0435\u0441\u0442\u0431\u043e\u0440\u043e"
    ],
    "qs_pg:aaroncc":"US",
    "qs_pg:gn_country":"US",
    "qs_pg:gn_fcode":"PPL",
    "qs_pg:gn_pop":0,
    "qs_pg:name":"Westboro",
    "qs_pg:name_adm0":"United States",
    "qs_pg:name_adm1":"Maryland",
    "qs_pg:photos_9k":1,
    "qs_pg:photos_9r":1,
    "qs_pg:photos_all":1,
    "qs_pg:photos_sr":0,
    "qs_pg:pop_sr":0,
    "qs_pg:qs_pg_placetype":"locality",
    "qs_pg:qs_pg_placetype_gp":"Town",
    "qs_pg:woe_adm0":23424977,
    "woe:adm0_id":23424977,
    "woe:name_adm0":"United States",
    "woe:name_adm1":"Maryland",
    "woe:placetype":"Town",
    "wof:name":"Westboro",
    "wof:placetype":"locality"
},
  "geometry": {"coordinates":[-77.09137,38.98928],"type":"Point"}
}