{
  "type": "Feature",
  "properties": {
    "iso:country":"US",
    "name:eng_x_preferred":[
        "Creekview Acres"
    ],
    "wof:name":"Creekview Acres",
    "wof:placetype":"neighbourhood",
    "wof:population":326,
    "zs:area_m":13862679.989817,
    "zs:blockids":[
        191530101011071,
        191530101011037,
        191530101011030,
        191530101011032,
        191530101011058,
        191530101011035,
        191530101011060,
        191530101011057,
        191530101011034,
        191530101011031,
        191530101011074,
        191530101011056,
        191530101011059,
        191530101011036,
        191530101011076,
        191530101011069,
        191530101011033
    ],
    "zs:housing10":109,
    "zs:label":"Creekview Acres",
    "zs:pop10":326
},
  "geometry": {"coordinates":[-93.595279,41.805831],"type":"Point"}
}