{
  "type": "Feature",
  "properties": {
    "iso:country":"US",
    "name:eng_x_preferred":[
        "Valley Pines"
    ],
    "wof:name":"Valley Pines",
    "wof:placetype":"neighbourhood",
    "wof:population":156,
    "zs:area_m":292587.159686,
    "zs:blockids":[
        132250403021050,
        132250402002070,
        132250402001109,
        132250403021030,
        132250403021062
    ],
    "zs:housing10":69,
    "zs:label":"Valley Pines",
    "zs:pop10":156
},
  "geometry": {"coordinates":[-83.888608,32.556558],"type":"Point"}
}