{
  "type": "Feature",
  "properties": {
    "gn:country":"US",
    "gn:fcode":"PPL",
    "gn:population":0,
    "iso:country":"US",
    "name:azb_x_preferred":[
        "\u0622\u0644\u0642\u0648\u0632\u0648"
    ],
    "name:cat_x_preferred":[
        "Algoso"
    ],
    "name:eng_x_preferred":[
        "Algoso"
    ],
    "name:fas_x_preferred":[
        "\u0627\u0644\u06af\u0627\u0633\u0648\u060c \u06a9\u0627\u0644\u06cc\u0641\u0631\u0646\u06cc\u0627"
    ],
    "name:fas_x_variant":[
        "\u0627\u0644\u06af\u0627\u0633\u0648"
    ],
    "name:fra_x_preferred":[
        "Algoso"
    ],
    "name:glg_x_preferred":[
        "Algoso"
    ],
    "name:pol_x_preferred":[
        "Algoso"
    ],
    "name:spa_x_preferred":[
        "Algoso"
    ],
    "name:und_x_variant":[
        "Weed Patch"
    ],
    "name:zho_x_preferred":[
        "\u963f\u723e\u6208\u7d22"
    ],
    "qs_pg:aaroncc":"US",
    "qs_pg:gn_country":"US",
    "qs_pg:gn_fcode":"PPL",
    "qs_pg:gn_pop":0,
    "qs_pg:name":"Algoso",
    "qs_pg:name_adm0":"United States",
    "qs_pg:name_adm1":"California",
    "qs_pg:photos":88,
    "qs_pg:photos_1k":18,
    "qs_pg:photos_9k":1,
    "qs_pg:photos_9r":3,
    "qs_pg:photos_all":88,
    "qs_pg:photos_sr":3,
    "qs_pg:pop_sr":0,
    "qs_pg:qs_pg_placetype":"locality",
    "qs_pg:qs_pg_placetype_gp":"Town",
    "qs_pg:woe_adm0":23424977,
    "woe:adm0_id":23424977,
    "woe:name_adm0":"United States",
    "woe:name_adm1":"California",
    "woe:placetype":"Town",
    "wof:name":"Algoso",
    "wof:placetype":"locality"
},
  "geometry": {"coordinates":[-118.9251,35.35968],"type":"Point"}
}