{
  "type": "Feature",
  "properties": {
    "gn:admin1_code":"OH",
    "gn:admin2_code":"29.0",
    "gn:admin3_code":"49784.0",
    "gn:asciiname":"Mill Rock",
    "gn:country_code":"US",
    "gn:dem":283,
    "gn:elevation":"281.0",
    "gn:feature_class":"P",
    "gn:feature_code":"PPL",
    "gn:name":"Mill Rock",
    "gn:population":0,
    "gn:timezone":"America/New_York",
    "iso:country":"US",
    "name:cat_x_preferred":[
        "Mill Rock"
    ],
    "name:ceb_x_preferred":[
        "Mill Rock"
    ],
    "name:ces_x_preferred":[
        "Mill Rock"
    ],
    "name:eng_x_preferred":[
        "Mill Rock"
    ],
    "name:est_x_preferred":[
        "Mill Rock"
    ],
    "name:eus_x_preferred":[
        "Mill Rock"
    ],
    "name:fra_x_preferred":[
        "Mill Rock"
    ],
    "name:heb_x_preferred":[
        "\u05de\u05d9\u05dc \u05e8\u05d5\u05e7"
    ],
    "name:jpn_x_preferred":[
        "\u30df\u30eb\u30fb\u30ed\u30c3\u30af"
    ],
    "name:kor_x_preferred":[
        "\ubc00 \ub85d"
    ],
    "name:pnb_x_preferred":[
        "\u0645\u0644 \u0631\u0627\u06a9"
    ],
    "name:rus_x_preferred":[
        "\u041c\u0438\u043b\u043b-\u0420\u043e\u043a"
    ],
    "name:slk_x_preferred":[
        "Mill Rock"
    ],
    "name:und_x_variant":[
        "Millrock"
    ],
    "wof:name":"Mill Rock",
    "wof:placetype":"locality"
},
  "geometry": {"coordinates":[-80.59146,40.79812],"type":"Point"}
}