{
  "type": "Feature",
  "properties": {
    "gn:admin1_code":"MD",
    "gn:admin2_code":"19.0",
    "gn:asciiname":"Blackwater",
    "gn:country_code":"US",
    "gn:dem":2,
    "gn:elevation":"1.0",
    "gn:feature_class":"P",
    "gn:feature_code":"PPL",
    "gn:name":"Blackwater",
    "gn:population":0,
    "gn:timezone":"America/New_York",
    "iso:country":"US",
    "name:ceb_x_preferred":[
        "Blackwater"
    ],
    "name:chv_x_preferred":[
        "\u0411\u043b\u044d\u043a\u0443\u043e\u0442\u0435\u0440"
    ],
    "name:cym_x_preferred":[
        "Blackwater"
    ],
    "name:deu_x_preferred":[
        "Blackwater"
    ],
    "name:fas_x_preferred":[
        "\u0628\u0644\u06a9\u200c\u0648\u0627\u062a\u0631"
    ],
    "name:fra_x_preferred":[
        "Blackwater"
    ],
    "name:ita_x_preferred":[
        "Blackwater"
    ],
    "name:jpn_x_preferred":[
        "\u30d6\u30e9\u30c3\u30af\u30a6\u30a9\u30fc\u30bf\u30fc"
    ],
    "name:kor_x_preferred":[
        "\ube14\ub799\uc6cc\ud130"
    ],
    "name:nds_x_preferred":[
        "Blackwater"
    ],
    "name:nld_x_preferred":[
        "Blackwater"
    ],
    "name:nno_x_preferred":[
        "Blackwater"
    ],
    "name:nor_x_preferred":[
        "Blackwater"
    ],
    "name:pol_x_preferred":[
        "Blackwater"
    ],
    "name:por_x_preferred":[
        "Blackwater"
    ],
    "name:rus_x_preferred":[
        "\u0411\u043b\u044d\u043a\u0443\u043e\u0442\u0435\u0440"
    ],
    "name:slk_x_preferred":[
        "Blackwater"
    ],
    "name:spa_x_preferred":[
        "Blackwater"
    ],
    "name:srp_x_preferred":[
        "\u0411\u043b\u0435\u043a\u0432\u043e\u0442\u0435\u0440"
    ],
    "name:swe_x_preferred":[
        "Blackwater"
    ],
    "name:ukr_x_preferred":[
        "\u0411\u043b\u0435\u043a\u0432\u043e\u0442\u0435\u0440"
    ],
    "name:urd_x_preferred":[
        "\u0628\u0644\u06cc\u06a9 \u0648\u0627\u0679\u0631"
    ],
    "name:vol_x_preferred":[
        "Blackwater"
    ],
    "wof:name":"Blackwater",
    "wof:placetype":"locality"
},
  "geometry": {"coordinates":[-76.14216,38.3854],"type":"Point"}
}