{
  "type": "Feature",
  "properties": {
    "gn:admin1_code":"WI",
    "gn:admin2_code":"19.0",
    "gn:admin3_code":"79650.0",
    "gn:asciiname":"Eidsvold",
    "gn:country_code":"US",
    "gn:dem":344,
    "gn:elevation":"345.0",
    "gn:feature_class":"P",
    "gn:feature_code":"PPL",
    "gn:name":"Eidsvold",
    "gn:population":0,
    "gn:timezone":"America/Chicago",
    "iso:country":"US",
    "name:ben_x_preferred":[
        "\u0987\u09a1\u09b8\u09ad\u09cb\u09b2\u09cd\u09a1"
    ],
    "name:deu_x_preferred":[
        "Eidsvold"
    ],
    "name:ell_x_preferred":[
        "\u0386\u03b9\u03bd\u03c4\u03c3\u03b2\u03bf\u03bb\u03bd\u03c4"
    ],
    "name:heb_x_preferred":[
        "\u05d0\u05d9\u05d9\u05d3\u05e1\u05d5\u05d5\u05dc\u05d3"
    ],
    "name:hin_x_preferred":[
        "\u0908\u0921\u094d\u0938\u0935\u094b\u0932\u094d\u0921"
    ],
    "name:hun_x_preferred":[
        "Eidsvold"
    ],
    "name:ind_x_preferred":[
        "Eidsvold"
    ],
    "name:jpn_x_preferred":[
        "\u30a2\u30a4\u30ba\u30dc\u30fc\u30eb\u30c9"
    ],
    "name:kor_x_preferred":[
        "\uc544\uc774\uc988\ubcfc\ub4dc"
    ],
    "name:rus_x_preferred":[
        "\u042d\u0438\u0434\u0441\u0432\u043e\u043b\u0434"
    ],
    "name:spa_x_preferred":[
        "Eidsvold"
    ],
    "name:swe_x_preferred":[
        "Eidsvold"
    ],
    "name:tur_x_preferred":[
        "Eidsvold"
    ],
    "name:ukr_x_preferred":[
        "\u0415\u0439\u0434\u0441\u0432\u043e\u043b\u0434"
    ],
    "name:urd_x_preferred":[
        "\u0627\u06cc\u062f\u0633\u0648\u0648\u0644\u0688"
    ],
    "name:vie_x_preferred":[
        "Eidsvold"
    ],
    "name:zho_cn_x_preferred":[
        "\u57c3\u5179\u6c83\u5c14\u5fb7"
    ],
    "name:zho_tw_x_preferred":[
        "\u827e\u8332\u6c83\u723e\u5fb7"
    ],
    "wof:name":"Eidsvold",
    "wof:placetype":"locality"
},
  "geometry": {"coordinates":[-90.86653,44.96413],"type":"Point"}
}