{
  "type": "Feature",
  "properties": {
    "gn:admin1_code":"WI",
    "gn:admin2_code":"19.0",
    "gn:admin3_code":"79650.0",
    "gn:asciiname":"Eidsvold",
    "gn:country_code":"US",
    "gn:dem":344,
    "gn:elevation":"345.0",
    "gn:feature_class":"P",
    "gn:feature_code":"PPL",
    "gn:name":"Eidsvold",
    "gn:population":0,
    "gn:timezone":"America/Chicago",
    "iso:country":"US",
    "wof:name":"Eidsvold",
    "wof:placetype":"locality"
},
  "geometry": {"coordinates":[-90.86653,44.96413],"type":"Point"}
}