{
  "type": "Feature",
  "properties": {
    "gn:elevation":16,
    "iso:country":"US",
    "name:eng_x_preferred":[
        "Lemon Creek"
    ],
    "name:eng_x_variant":[
        "Lemon Crk"
    ],
    "name:nld_x_preferred":[
        "Lemon Creek"
    ],
    "qs:gn_fcode":"PPL",
    "qs:gn_local":0,
    "qs:gn_namadm1":"AK",
    "qs:gn_name":"Lemon Creek",
    "qs:local_max":3634,
    "qs:local_sum":5506,
    "qs:localhoods":10,
    "qs:name":"Lemon Creek",
    "qs:name_adm0":"United States",
    "qs:name_adm1":"Alaska",
    "qs:name_adm2":"City and Borough of Juneau",
    "qs:name_local":"Juneau",
    "qs:photo_max":21,
    "qs:photo_sum":83,
    "qs:placetype":"Suburb",
    "qs:quad_count":27,
    "qs:woe_adm0":23424977,
    "qs:woe_adm1":2347560,
    "qs:woe_adm2":12587563,
    "qs:woe_lau":0,
    "qs:woe_local":2430300,
    "qs:woe_ver":"7.10.0",
    "wof:name":"Lemon Creek",
    "wof:placetype":"neighbourhood",
    "wof:population":3470,
    "zs:blockids":[
        21100004002006,
        21100004001001,
        21100004001019,
        21100004001016,
        21100004003014,
        21100004002012,
        21100004001024,
        21100004003005,
        21100004001003,
        21100004001009,
        21100004003016,
        21100004001012,
        21100004002005,
        21100004002008,
        21100004003000,
        21100004001000,
        21100004003006,
        21100004001017,
        21100004001018,
        21100004001026,
        21100004001015,
        21100004001010,
        21100004003015,
        21100004003007,
        21100004002010,
        21100004001025,
        21100004003012,
        21100004003009,
        21100004002003,
        21100004002004,
        21100004001002,
        21100004003002,
        21100004003004,
        21100004002007,
        21100004003003,
        21100004003013,
        21100004002002,
        21100004001011,
        21100004001014,
        21100004001021,
        21100004003001,
        21100004002014,
        21100004001020,
        21100004003010,
        21100004001004,
        21100004002015,
        21100004002009,
        21100004002001,
        21100004001023,
        21100004001013,
        21100004002013,
        21100004001022,
        21100004001028,
        21100004001008,
        21100004003011,
        21100004003008,
        21100004002011,
        21100004002016,
        21100004001027
    ],
    "zs:housing10":1163,
    "zs:pop10":3470
},
  "geometry": {"coordinates":[-134.503263,58.35655],"type":"Point"}
}