{
  "type": "Feature",
  "properties": {
    "gn:admin1_code":"MO",
    "gn:admin2_code":"117.0",
    "gn:admin3_code":"13708.0",
    "gn:asciiname":"Norville",
    "gn:country_code":"US",
    "gn:dem":220,
    "gn:elevation":"217.0",
    "gn:feature_class":"P",
    "gn:feature_code":"PPL",
    "gn:name":"Norville",
    "gn:population":0,
    "gn:timezone":"America/Chicago",
    "iso:country":"US",
    "name:cat_x_preferred":[
        "Norville"
    ],
    "name:ceb_x_preferred":[
        "Norville"
    ],
    "name:deu_x_preferred":[
        "Norville"
    ],
    "name:eus_x_preferred":[
        "Norville"
    ],
    "name:fra_x_preferred":[
        "Norville"
    ],
    "name:hun_x_preferred":[
        "Norville"
    ],
    "name:ita_x_preferred":[
        "Norville"
    ],
    "name:kaz_x_preferred":[
        "\u041d\u043e\u0440\u0432\u0438\u043b\u044c"
    ],
    "name:lat_x_preferred":[
        "Norville"
    ],
    "name:mlg_x_preferred":[
        "Norville"
    ],
    "name:msa_x_preferred":[
        "Norville"
    ],
    "name:nld_x_preferred":[
        "Norville"
    ],
    "name:oci_x_preferred":[
        "Norville"
    ],
    "name:pms_x_preferred":[
        "Norville"
    ],
    "name:pol_x_preferred":[
        "Norville"
    ],
    "name:por_x_preferred":[
        "Norville"
    ],
    "name:ron_x_preferred":[
        "Norville"
    ],
    "name:slk_x_preferred":[
        "Norville"
    ],
    "name:spa_x_preferred":[
        "Norville"
    ],
    "name:swe_x_preferred":[
        "Norville"
    ],
    "name:szl_x_preferred":[
        "Norville"
    ],
    "name:ukr_x_preferred":[
        "\u041d\u043e\u0440\u0432\u0456\u043b\u044c"
    ],
    "name:vie_x_preferred":[
        "Norville"
    ],
    "name:vol_x_preferred":[
        "Norville"
    ],
    "name:war_x_preferred":[
        "Norville"
    ],
    "wof:name":"Norville",
    "wof:placetype":"locality"
},
  "geometry": {"coordinates":[-93.47243,39.75446],"type":"Point"}
}