{
  "type": "Feature",
  "properties": {
    "gn:admin1_code":"IN",
    "gn:admin2_code":"45.0",
    "gn:admin3_code":"69084.0",
    "gn:asciiname":"Rob Roy",
    "gn:country_code":"US",
    "gn:dem":197,
    "gn:elevation":"195.0",
    "gn:feature_class":"P",
    "gn:feature_code":"PPL",
    "gn:name":"Rob Roy",
    "gn:population":0,
    "gn:timezone":"America/Indiana/Indianapolis",
    "iso:country":"US",
    "name:eng_x_preferred":[
        "Rob Roy"
    ],
    "name:fas_x_preferred":[
        "\u0631\u0627\u0628\u200c\u0631\u0648\u06cc"
    ],
    "name:und_x_variant":[
        "Robroy"
    ],
    "name:vol_x_preferred":[
        "Rob Roy"
    ],
    "wof:name":"Rob Roy",
    "wof:placetype":"locality"
},
  "geometry": {"coordinates":[-87.24334,40.2367],"type":"Point"}
}