{
  "type": "Feature",
  "properties": {
    "gn:admin1_code":"NY",
    "gn:admin2_code":"49.0",
    "gn:admin3_code":"42125.0",
    "gn:asciiname":"Freeman Mill",
    "gn:country_code":"US",
    "gn:dem":433,
    "gn:elevation":"428.0",
    "gn:feature_class":"P",
    "gn:feature_code":"PPL",
    "gn:name":"Freeman Mill",
    "gn:population":0,
    "gn:timezone":"America/New_York",
    "iso:country":"US",
    "wof:name":"Freeman Mill",
    "wof:placetype":"locality"
},
  "geometry": {"coordinates":[-75.57850999999999,43.4609],"type":"Point"}
}