{
  "type": "Feature",
  "properties": {
    "gn:admin1_code":"MD",
    "gn:admin2_code":"9.0",
    "gn:asciiname":"Williams Wharf",
    "gn:country_code":"US",
    "gn:dem":12,
    "gn:elevation":"16.0",
    "gn:feature_class":"P",
    "gn:feature_code":"PPL",
    "gn:name":"Williams Wharf",
    "gn:population":0,
    "gn:timezone":"America/New_York",
    "iso:country":"US",
    "wof:name":"Williams Wharf",
    "wof:placetype":"locality"
},
  "geometry": {"coordinates":[-76.58718,38.44373],"type":"Point"}
}