{
  "type": "Feature",
  "properties": {
    "gn:admin1_code":"NC",
    "gn:admin2_code":"163.0",
    "gn:admin3_code":"92516.0",
    "gn:asciiname":"Suttontown",
    "gn:country_code":"US",
    "gn:dem":50,
    "gn:elevation":"52.0",
    "gn:feature_class":"P",
    "gn:feature_code":"PPL",
    "gn:name":"Suttontown",
    "gn:population":0,
    "gn:timezone":"America/New_York",
    "iso:country":"US",
    "wof:name":"Suttontown",
    "wof:placetype":"locality"
},
  "geometry": {"coordinates":[-78.24055,35.2035],"type":"Point"}
}