{
  "type": "Feature",
  "properties": {
    "gn:admin1_code":"MO",
    "gn:admin2_code":"29.0",
    "gn:admin3_code":"63668.0",
    "gn:asciiname":"Only",
    "gn:country_code":"US",
    "gn:dem":340,
    "gn:elevation":"336.0",
    "gn:feature_class":"P",
    "gn:feature_code":"PPL",
    "gn:name":"Only",
    "gn:population":0,
    "gn:timezone":"America/Chicago",
    "iso:country":"US",
    "name:deu_x_preferred":[
        "Only"
    ],
    "name:est_x_preferred":[
        "Only"
    ],
    "name:fra_x_preferred":[
        "Only"
    ],
    "name:ita_x_preferred":[
        "Only"
    ],
    "name:jpn_x_preferred":[
        "\u30aa\u30f3\u30ea\u30fc"
    ],
    "name:por_x_preferred":[
        "Only"
    ],
    "name:rus_x_preferred":[
        "Only"
    ],
    "name:spa_x_preferred":[
        "Only"
    ],
    "wof:name":"Only",
    "wof:placetype":"locality"
},
  "geometry": {"coordinates":[-92.95047,37.9167],"type":"Point"}
}