{
  "type": "Feature",
  "properties": {
    "gn:admin1_code":"IA",
    "gn:admin2_code":"91.0",
    "gn:admin3_code":"90834.0",
    "gn:asciiname":"Jones Siding",
    "gn:country_code":"US",
    "gn:dem":325,
    "gn:elevation":"328.0",
    "gn:feature_class":"P",
    "gn:feature_code":"PPL",
    "gn:name":"Jones Siding",
    "gn:population":0,
    "gn:timezone":"America/Chicago",
    "iso:country":"US",
    "wof:name":"Jones Siding",
    "wof:placetype":"locality"
},
  "geometry": {"coordinates":[-94.20802,42.67997],"type":"Point"}
}