{
  "type": "Feature",
  "properties": {
    "gn:country":"US",
    "gn:fcode":"PPL",
    "gn:population":0,
    "iso:country":"US",
    "name:arz_x_preferred":[
        "\u0648\u064a\u062a\u0645\u0648\u0631"
    ],
    "name:azb_x_preferred":[
        "\u0648\u062a\u0645\u0648\u0631"
    ],
    "name:deu_x_preferred":[
        "Wetmore"
    ],
    "name:eng_x_preferred":[
        "Wetmore"
    ],
    "name:fas_x_preferred":[
        "\u0648\u062a\u0645\u0648\u0631"
    ],
    "name:fra_x_preferred":[
        "Wetmore"
    ],
    "name:nav_x_preferred":[
        "Bikooh H\u00f3t\u0142\u02bciz\u00ed"
    ],
    "name:uzb_x_preferred":[
        "Wetmore"
    ],
    "name:vol_x_preferred":[
        "Wetmore"
    ],
    "name:zho_x_preferred":[
        "\u97cb\u7279\u83ab\u723e"
    ],
    "qs_pg:aaroncc":"US",
    "qs_pg:gn_country":"US",
    "qs_pg:gn_fcode":"PPL",
    "qs_pg:gn_pop":0,
    "qs_pg:name":"Wetmore",
    "qs_pg:name_adm0":"United States",
    "qs_pg:name_adm1":"Colorado",
    "qs_pg:photos":26,
    "qs_pg:photos_1k":5,
    "qs_pg:photos_9k":1,
    "qs_pg:photos_9r":2,
    "qs_pg:photos_all":26,
    "qs_pg:photos_sr":2,
    "qs_pg:pop_sr":5,
    "qs_pg:qs_pg_placetype":"locality",
    "qs_pg:qs_pg_placetype_gp":"Town",
    "qs_pg:woe_adm0":23424977,
    "woe:adm0_id":23424977,
    "woe:name_adm0":"United States",
    "woe:name_adm1":"Colorado",
    "woe:placetype":"Town",
    "wof:name":"Wetmore",
    "wof:placetype":"locality"
},
  "geometry": {"coordinates":[-105.08471,38.23806],"type":"Point"}
}