{
  "type": "Feature",
  "properties": {
    "gn:admin1_code":"NC",
    "gn:admin2_code":"133",
    "gn:admin3_code":"93188.0",
    "gn:asciiname":"Reid Acres Mobile Home Park",
    "gn:country_code":"US",
    "gn:dem":5,
    "gn:elevation":"7.0",
    "gn:feature_class":"P",
    "gn:feature_code":"PPL",
    "gn:name":"Reid Acres Mobile Home Park",
    "gn:population":0,
    "gn:timezone":"America/New_York",
    "iso:country":"US",
    "wof:name":"Reid Acres Mobile Home Park",
    "wof:placetype":"campus"
},
  "geometry": {"coordinates":[-77.2264,34.708],"type":"Point"}
}