{
  "type": "Feature",
  "properties": {
    "iso:country":"US",
    "name:eng_x_preferred":[
        "Terrace Hills"
    ],
    "wof:name":"Terrace Hills",
    "wof:placetype":"neighbourhood",
    "wof:population":525,
    "zs:area_m":694198.40721,
    "zs:blockids":[
        10970037101040,
        10970037101057,
        10970037101035,
        10970037101033,
        10970037101037,
        10970037101036,
        10970037101034,
        10970037101032
    ],
    "zs:housing10":227,
    "zs:label":"Terrace Hills",
    "zs:pop10":525
},
  "geometry": {"coordinates":[-88.16895599999999,30.640699],"type":"Point"}
}