{
  "type": "Feature",
  "properties": {
    "gn:admin1_code":"KY",
    "gn:admin2_code":"99",
    "gn:asciiname":"Lone Star",
    "gn:country_code":"US",
    "gn:dem":269,
    "gn:elevation":"270.0",
    "gn:feature_class":"P",
    "gn:feature_code":"PPL",
    "gn:name":"Lone Star",
    "gn:population":0,
    "gn:timezone":"America/Chicago",
    "iso:country":"US",
    "name:fas_x_preferred":[
        "\u0644\u0648\u0646 \u0627\u0633\u062a\u0627\u0631"
    ],
    "name:urd_x_preferred":[
        "\u0644\u0648\u0646 \u0633\u0679\u0627\u0631"
    ],
    "wof:name":"Lone Star",
    "wof:placetype":"locality"
},
  "geometry": {"coordinates":[-85.94663,37.40478],"type":"Point"}
}