{
  "type": "Feature",
  "properties": {
    "gn:admin1_code":"MD",
    "gn:admin2_code":"5.0",
    "gn:asciiname":"Lawrence Hill",
    "gn:country_code":"US",
    "gn:dem":36,
    "gn:elevation":"30.0",
    "gn:feature_class":"P",
    "gn:feature_code":"PPL",
    "gn:name":"Lawrence Hill",
    "gn:population":0,
    "gn:timezone":"America/New_York",
    "iso:country":"US",
    "name:ara_x_preferred":[
        "\u0644\u0648\u0631\u0627\u0646\u0633 \u0647\u064a\u0644"
    ],
    "name:azb_x_preferred":[
        "\u0644\u0648\u0631\u0627\u0646\u0633 \u0647\u06cc\u0644"
    ],
    "name:deu_x_preferred":[
        "Lawrence Hill"
    ],
    "name:fra_x_preferred":[
        "Lawrence Hill"
    ],
    "name:ita_x_preferred":[
        "Lawrence Hill"
    ],
    "name:spa_x_preferred":[
        "Lawrence Hill"
    ],
    "name:zho_x_preferred":[
        "\u52de\u502b\u65af\u00b7\u5e0c\u723e"
    ],
    "wof:name":"Lawrence Hill",
    "wof:placetype":"locality"
},
  "geometry": {"coordinates":[-76.44996,39.38205],"type":"Point"}
}