{
  "type": "Feature",
  "properties": {
    "gn:admin1_code":"IN",
    "gn:admin2_code":"129.0",
    "gn:admin3_code":"47250.0",
    "gn:asciiname":"Saint Philip",
    "gn:country_code":"US",
    "gn:dem":149,
    "gn:elevation":"151.0",
    "gn:feature_class":"P",
    "gn:feature_code":"PPL",
    "gn:name":"Saint Philip",
    "gn:population":0,
    "gn:timezone":"America/Chicago",
    "iso:country":"US",
    "name:eng_x_preferred":[
        "Saint Philip"
    ],
    "name:und_x_variant":[
        "Saint Phillips"
    ],
    "wof:name":"Saint Philip",
    "wof:placetype":"locality"
},
  "geometry": {"coordinates":[-87.71585,37.98699000000001],"type":"Point"}
}