{
  "type": "Feature",
  "properties": {
    "iso:country":"US",
    "name:eng_x_preferred":[
        "Searsville"
    ],
    "wd:wordcount":2229,
    "wof:name":"Searsville",
    "wof:placetype":"neighbourhood",
    "wof:population":1234,
    "zs:area_m":59187784.286046,
    "zs:blockids":[
        250158226051080,
        250158226062017,
        250158226062008,
        250158226062032,
        250158226062018,
        250158226062042,
        250158226062030,
        250158226031004,
        250158226031006,
        250158226061102,
        250158226062043,
        250158226062020,
        250158226062029,
        250158226062000,
        250158226063023,
        250158226062031,
        250158226062003,
        250158226062040,
        250158226061100,
        250158226061104,
        250158226062045,
        250158226062022,
        250158226063022,
        250158226063025,
        250158226062028,
        250158226062036,
        250158226051092,
        250158226051094,
        250158226051081,
        250158226062001,
        250158226062049,
        250158226062047,
        250158226062033,
        250158226031003,
        250158226061106,
        250158226051095,
        250158226062011,
        250158226062037,
        250158226062044,
        250158226062004,
        250158226063024,
        250158226051091,
        250158226062038,
        250158226062035,
        250158226031005,
        250158226031012,
        250158226051093,
        250158226062023,
        250158226051090,
        250158226062052,
        250158226062005,
        250158226062014,
        250158226062046,
        250158226062039,
        250158226063021,
        250158226062016,
        250158226063026,
        250158226031000,
        250158226062019,
        250158226062006,
        250158226062054,
        250158226062048,
        250158226061101,
        250158226061082,
        250158226062050,
        250158226061103,
        250158226051097,
        250158226062041,
        250158226062015,
        250158226062034,
        250158226061105,
        250158226062013,
        250158226062012,
        250158226062002,
        250158226062007
    ],
    "zs:housing10":551,
    "zs:label":"Searsville",
    "zs:pop10":1234
},
  "geometry": {"coordinates":[-72.74100300000001,42.423796],"type":"Point"}
}