{
  "type": "Feature",
  "properties": {
    "iso:country":"US",
    "name:eng_x_preferred":[
        "West Texas Acres"
    ],
    "wof:name":"West Texas Acres",
    "wof:placetype":"neighbourhood",
    "zs:area_m":82781.825376,
    "zs:blockids":[
        120570130031014
    ],
    "zs:housing10":0,
    "zs:label":"West Texas Acres",
    "zs:pop10":0
},
  "geometry": {"coordinates":[-82.122541,27.978878],"type":"Point"}
}