{
  "type": "Feature",
  "properties": {
    "gn:admin1_code":"MI",
    "gn:admin2_code":"155.0",
    "gn:admin3_code":"11880.0",
    "gn:asciiname":"Union Plains",
    "gn:country_code":"US",
    "gn:dem":261,
    "gn:elevation":"261.0",
    "gn:feature_class":"P",
    "gn:feature_code":"PPL",
    "gn:name":"Union Plains",
    "gn:population":0,
    "gn:timezone":"America/Detroit",
    "iso:country":"US",
    "wof:name":"Union Plains",
    "wof:placetype":"locality"
},
  "geometry": {"coordinates":[-84.01274000000002,42.82975],"type":"Point"}
}