{
  "type": "Feature",
  "properties": {
    "gn:admin1_code":"MS",
    "gn:admin2_code":"137.0",
    "gn:asciiname":"Linwood",
    "gn:country_code":"US",
    "gn:dem":102,
    "gn:elevation":"97.0",
    "gn:feature_class":"P",
    "gn:feature_code":"PPL",
    "gn:name":"Linwood",
    "gn:population":0,
    "gn:timezone":"America/Chicago",
    "iso:country":"US",
    "name:ceb_x_preferred":[
        "Linwood"
    ],
    "name:deu_x_preferred":[
        "Linwood"
    ],
    "name:eng_x_preferred":[
        "Linwood"
    ],
    "name:ita_x_preferred":[
        "Linwood"
    ],
    "name:jpn_x_preferred":[
        "\u30ea\u30f3\u30a6\u30c3\u30c9"
    ],
    "name:kor_x_preferred":[
        "\ub9b0\uc6b0\ub4dc"
    ],
    "name:nld_x_preferred":[
        "Linwood"
    ],
    "name:pol_x_preferred":[
        "Linwood"
    ],
    "name:por_x_preferred":[
        "Linwood"
    ],
    "name:rus_x_preferred":[
        "\u041b\u0438\u043d\u0432\u0443\u0434"
    ],
    "name:spa_x_preferred":[
        "Linwood"
    ],
    "name:srp_x_preferred":[
        "\u041b\u0438\u043d\u0432\u0443\u0434"
    ],
    "name:swe_x_preferred":[
        "Linwood"
    ],
    "name:ukr_x_preferred":[
        "\u041b\u0456\u043d\u0432\u0443\u0434"
    ],
    "name:und_x_variant":[
        "Eckles",
        "Echols"
    ],
    "name:vol_x_preferred":[
        "Linwood"
    ],
    "wof:name":"Linwood",
    "wof:placetype":"locality"
},
  "geometry": {"coordinates":[-90.08898000000001,34.59733],"type":"Point"}
}