{
  "type": "Feature",
  "properties": {
    "iso:country":"US",
    "name:eng_x_preferred":[
        "Crossmans"
    ],
    "wd:wordcount":37,
    "wof:name":"Crossmans",
    "wof:placetype":"neighbourhood",
    "wof:population":2369,
    "zs:area_m":944559.984476,
    "zs:blockids":[
        340230073011004,
        340230072033004,
        340230072033023,
        340230072022000,
        340230072033022,
        340230072032005,
        340230072032000,
        340230072032012,
        340230072033008,
        340230072033007,
        340230072032002,
        340230072032001,
        340230073011005,
        340230072033002,
        340230092001012,
        340230072033006,
        340230072032016,
        340230072033019,
        340230072032026,
        340230072032003,
        340230072033012,
        340230072033020,
        340230072032018,
        340230072033017,
        340230072033018,
        340230072032006,
        340230072033005,
        340230072033013,
        340230072033011,
        340230072033016,
        340230072033009,
        340230072033021,
        340230072033025,
        340230092001008,
        340230072033010,
        340230072033015,
        340230072033003,
        340230072033014
    ],
    "zs:housing10":791,
    "zs:label":"Crossmans",
    "zs:pop10":2369
},
  "geometry": {"coordinates":[-74.30597899999999,40.472089],"type":"Point"}
}