{
  "type": "Feature",
  "properties": {
    "iso:country":"US",
    "name:eng_x_preferred":[
        "Horizon Crest"
    ],
    "wof:name":"Horizon Crest",
    "wof:placetype":"neighbourhood",
    "wof:population":1458,
    "zs:area_m":816682.341035,
    "zs:blockids":[
        530330249021018,
        530330249022018,
        530330249031018,
        530330249031014,
        530330249022019,
        530330249021021,
        530330249021007,
        530330249021009,
        530330249031015,
        530330249032002,
        530330249022016,
        530330249021019,
        530330249022015,
        530330249031013,
        530330249031011,
        530330249021022,
        530330249021020,
        530330249032003,
        530330249031004,
        530330249022014,
        530330249021008,
        530330249031012,
        530330249022017
    ],
    "zs:housing10":525,
    "zs:label":"Horizon Crest",
    "zs:pop10":1458
},
  "geometry": {"coordinates":[-122.13393000000001,47.559667],"type":"Point"}
}