{
  "type": "Feature",
  "properties": {
    "gn:elevation":1284,
    "iso:country":"US",
    "name:eng_x_preferred":[
        "Georgetown At Westpointe"
    ],
    "qs:gn_adm0_cc":"US",
    "qs:gn_fcode":"PPLX",
    "qs:gn_local":5780993,
    "qs:gn_nam_loc":"Salt Lake City, Salt Lake, Utah, US",
    "qs:gn_namadm1":"UT",
    "qs:gn_name":"Georgetown at Westpointe",
    "qs:local_max":24997,
    "qs:local_sum":103616,
    "qs:localhoods":160,
    "qs:name":"Georgetown At Westpointe",
    "qs:name_adm0":"United States",
    "qs:name_adm1":"Utah",
    "qs:name_adm2":"Salt Lake",
    "qs:name_local":"Salt Lake City",
    "qs:photo_max":11,
    "qs:photo_sum":25,
    "qs:placetype":"Suburb",
    "qs:quad_count":7,
    "qs:woe_adm0":23424977,
    "qs:woe_adm1":2347603,
    "qs:woe_adm2":12590278,
    "qs:woe_lau":0,
    "qs:woe_local":2487610,
    "qs:woe_ver":"7.10.0",
    "wof:lang":[
        "eng"
    ],
    "wof:name":"Georgetown At Westpointe",
    "wof:placetype":"neighbourhood",
    "wof:population":3441,
    "zs:blockids":[
        490351147001058,
        490351003082002,
        490351003072014,
        490351003082003,
        490351003073003,
        490351147001057,
        490351003072011,
        490351003073007,
        490351003072005,
        490351147001060,
        490359800001018,
        490351003072012,
        490351003072007,
        490351003072008,
        490351003073005,
        490351003072004,
        490351003082004,
        490351003072003,
        490351003073013,
        490351003073014,
        490351147001035,
        490351147001059,
        490351003072015,
        490351003072016,
        490351003072006,
        490351003073000,
        490351147001024,
        490351003072002,
        490351147001068,
        490351003072010,
        490351003073012,
        490351003073001,
        490351003073006,
        490351147001026,
        490351003073002,
        490351003073004,
        490351003072013,
        490351003072009,
        490351003073008
    ],
    "zs:housing10":809,
    "zs:pop10":3441
},
  "geometry": {"coordinates":[-111.941924,40.801777],"type":"Point"}
}