{
  "type": "Feature",
  "properties": {
    "gn:admin1_code":"GA",
    "gn:admin2_code":"63.0",
    "gn:asciiname":"Knollwood",
    "gn:country_code":"US",
    "gn:dem":253,
    "gn:elevation":"247.0",
    "gn:feature_class":"P",
    "gn:feature_code":"PPL",
    "gn:name":"Knollwood",
    "gn:population":0,
    "gn:timezone":"America/New_York",
    "iso:country":"US",
    "name:ceb_x_preferred":[
        "Knollwood"
    ],
    "name:deu_x_preferred":[
        "Knollwood"
    ],
    "name:ita_x_preferred":[
        "Knollwood"
    ],
    "name:srp_x_preferred":[
        "\u041d\u043e\u043b\u0432\u0443\u0434"
    ],
    "name:swe_x_preferred":[
        "Knollwood"
    ],
    "name:ukr_x_preferred":[
        "\u041d\u043e\u043b\u043b\u0432\u0443\u0434"
    ],
    "name:vol_x_preferred":[
        "Knollwood"
    ],
    "wof:name":"Knollwood",
    "wof:placetype":"locality"
},
  "geometry": {"coordinates":[-84.30464000000001,33.56678],"type":"Point"}
}