{
  "type": "Feature",
  "properties": {
    "iso:country":"US",
    "name:eng_x_preferred":[
        "Denbigh Plantation"
    ],
    "wof:name":"Denbigh Plantation",
    "wof:placetype":"neighbourhood",
    "zs:area_m":964389.632168,
    "zs:blockids":[
        517000320012007
    ],
    "zs:housing10":0,
    "zs:label":"Denbigh Plantation",
    "zs:pop10":0
},
  "geometry": {"coordinates":[-76.546407,37.091414],"type":"Point"}
}