{
  "type": "Feature",
  "properties": {
    "gn:admin1_code":"CO",
    "gn:admin2_code":"85",
    "gn:asciiname":"Ute",
    "gn:country_code":"US",
    "gn:dem":2318,
    "gn:elevation":"2307.0",
    "gn:feature_class":"P",
    "gn:feature_code":"PPL",
    "gn:name":"Ute",
    "gn:population":0,
    "gn:timezone":"America/Denver",
    "iso:country":"US",
    "name:cat_x_preferred":[
        "Ute"
    ],
    "name:deu_x_preferred":[
        "Ute"
    ],
    "name:fra_x_preferred":[
        "Ute"
    ],
    "name:nld_x_preferred":[
        "Ute"
    ],
    "name:nor_x_preferred":[
        "Ute"
    ],
    "name:por_x_preferred":[
        "Ute"
    ],
    "name:swe_x_preferred":[
        "Ute"
    ],
    "wof:name":"Ute",
    "wof:placetype":"locality"
},
  "geometry": {"coordinates":[-108.27119,38.25554],"type":"Point"}
}