{
  "type": "Feature",
  "properties": {
    "gn:admin1_code":"KY",
    "gn:admin2_code":"27",
    "gn:asciiname":"Rockvale",
    "gn:country_code":"US",
    "gn:dem":148,
    "gn:elevation":"142.0",
    "gn:feature_class":"P",
    "gn:feature_code":"PPL",
    "gn:name":"Rockvale",
    "gn:population":0,
    "gn:timezone":"America/Chicago",
    "iso:country":"US",
    "wof:name":"Rockvale",
    "wof:placetype":"locality"
},
  "geometry": {"coordinates":[-86.57665,37.63255],"type":"Point"}
}