{
  "type": "Feature",
  "properties": {
    "gn:admin1_code":"NY",
    "gn:admin2_code":"121.0",
    "gn:admin3_code":"46877.0",
    "gn:asciiname":"Millers Corner",
    "gn:country_code":"US",
    "gn:dem":470,
    "gn:elevation":"468.0",
    "gn:feature_class":"P",
    "gn:feature_code":"PPL",
    "gn:name":"Millers Corner",
    "gn:population":0,
    "gn:timezone":"America/New_York",
    "iso:country":"US",
    "wof:name":"Millers Corner",
    "wof:placetype":"locality"
},
  "geometry": {"coordinates":[-78.12446,42.81534],"type":"Point"}
}