{
  "type": "Feature",
  "properties": {
    "iso:country":"US",
    "name:eng_x_preferred":[
        "South Liberty"
    ],
    "wof:name":"South Liberty",
    "wof:placetype":"neighbourhood",
    "wof:population":90,
    "zs:area_m":11722628.426248,
    "zs:blockids":[
        482917012004020
    ],
    "zs:housing10":38,
    "zs:label":"South Liberty",
    "zs:pop10":90
},
  "geometry": {"coordinates":[-94.80571,30.030567],"type":"Point"}
}