{
  "type": "Feature",
  "properties": {
    "gn:admin1_code":"DE",
    "gn:admin2_code":"001",
    "gn:asciiname":"Brenford",
    "gn:country_code":"US",
    "gn:dem":16,
    "gn:elevation":"14.0",
    "gn:feature_class":"P",
    "gn:feature_code":"PPL",
    "gn:name":"Brenford",
    "gn:population":0,
    "gn:timezone":"America/New_York",
    "iso:country":"US",
    "wof:name":"Brenford",
    "wof:placetype":"locality"
},
  "geometry": {"coordinates":[-75.61076,39.2565],"type":"Point"}
}