{
  "type": "Feature",
  "properties": {
    "gn:country":"US",
    "gn:fcode":"PPL",
    "gn:population":0,
    "iso:country":"US",
    "name:azb_x_preferred":[
        "\u0628\u0631\u0627\u06a9\u062a\u0648\u0646"
    ],
    "name:eng_x_preferred":[
        "Brockton"
    ],
    "name:fas_x_preferred":[
        "\u0628\u0631\u0627\u06a9\u062a\u0648\u0646"
    ],
    "name:fra_x_preferred":[
        "Brockton"
    ],
    "name:und_x_variant":[
        "Patterson"
    ],
    "qs_pg:aaroncc":"US",
    "qs_pg:gn_country":"US",
    "qs_pg:gn_fcode":"PPL",
    "qs_pg:gn_pop":0,
    "qs_pg:name":"Brockton",
    "qs_pg:name_adm0":"United States",
    "qs_pg:name_adm1":"Pennsylvania",
    "qs_pg:photos_9k":1,
    "qs_pg:photos_9r":1,
    "qs_pg:photos_all":2,
    "qs_pg:photos_sr":0,
    "qs_pg:pop_sr":0,
    "qs_pg:qs_pg_placetype":"locality",
    "qs_pg:qs_pg_placetype_gp":"Town",
    "qs_pg:woe_adm0":23424977,
    "woe:adm0_id":23424977,
    "woe:name_adm0":"United States",
    "woe:name_adm1":"Pennsylvania",
    "woe:placetype":"Town",
    "wof:name":"Brockton",
    "wof:placetype":"locality"
},
  "geometry": {"coordinates":[-76.06854,40.74842],"type":"Point"}
}