{
  "type": "Feature",
  "properties": {
    "gn:admin1_code":"TX",
    "gn:admin2_code":"215",
    "gn:asciiname":"Coronado Colonia",
    "gn:country_code":"US",
    "gn:dem":43,
    "gn:elevation":"39.0",
    "gn:feature_class":"P",
    "gn:feature_code":"PPL",
    "gn:name":"Coronado Colonia",
    "gn:population":0,
    "gn:timezone":"America/Chicago",
    "iso:country":"US",
    "wof:name":"Coronado Colonia",
    "wof:placetype":"locality"
},
  "geometry": {"coordinates":[-98.28918,26.23841],"type":"Point"}
}