{
  "type": "Feature",
  "properties": {
    "gn:admin1_code":"TX",
    "gn:admin2_code":"193.0",
    "gn:asciiname":"Vista",
    "gn:country_code":"US",
    "gn:dem":465,
    "gn:elevation":"463.0",
    "gn:feature_class":"P",
    "gn:feature_code":"PPL",
    "gn:name":"Vista",
    "gn:population":0,
    "gn:timezone":"America/Chicago",
    "iso:country":"US",
    "name:ara_x_preferred":[
        "\u0641\u064a\u0633\u062a\u0627"
    ],
    "name:bul_x_preferred":[
        "\u0412\u0438\u0441\u0442\u0430"
    ],
    "name:ceb_x_preferred":[
        "Vista"
    ],
    "name:ces_x_preferred":[
        "Vista"
    ],
    "name:deu_x_preferred":[
        "Vista"
    ],
    "name:fas_x_preferred":[
        "\u0648\u06cc\u0633\u062a\u0627"
    ],
    "name:fin_x_preferred":[
        "Vista"
    ],
    "name:fra_x_preferred":[
        "Vista"
    ],
    "name:hun_x_preferred":[
        "Vista"
    ],
    "name:ita_x_preferred":[
        "Vista"
    ],
    "name:jpn_x_preferred":[
        "\u30d3\u30b9\u30bf"
    ],
    "name:kor_x_preferred":[
        "\ube44\uc2a4\ud0c0"
    ],
    "name:lav_x_preferred":[
        "Vista"
    ],
    "name:nld_x_preferred":[
        "Vista"
    ],
    "name:nor_x_preferred":[
        "Vista"
    ],
    "name:pol_x_preferred":[
        "Vista"
    ],
    "name:por_x_preferred":[
        "Vista"
    ],
    "name:rus_x_preferred":[
        "Vista"
    ],
    "name:slk_x_preferred":[
        "Vista"
    ],
    "name:spa_x_preferred":[
        "Vista"
    ],
    "name:srp_x_preferred":[
        "\u0412\u0438\u0441\u0442\u0430"
    ],
    "name:swa_x_preferred":[
        "Vista"
    ],
    "name:swe_x_preferred":[
        "Vista"
    ],
    "name:tur_x_preferred":[
        "Vista"
    ],
    "name:ukr_x_preferred":[
        "Vista"
    ],
    "name:vie_x_preferred":[
        "Vista"
    ],
    "name:zho_x_preferred":[
        "Vista"
    ],
    "wof:name":"Vista",
    "wof:placetype":"locality"
},
  "geometry": {"coordinates":[-98.21226,31.52488],"type":"Point"}
}