{
  "type": "Feature",
  "properties": {
    "gn:country":"US",
    "gn:fcode":"PPL",
    "gn:population":0,
    "iso:country":"US",
    "name:ceb_x_preferred":[
        "Queen City"
    ],
    "name:deu_x_preferred":[
        "Queen City"
    ],
    "name:fra_x_preferred":[
        "Queen City"
    ],
    "name:ita_x_preferred":[
        "Queen City"
    ],
    "name:nld_x_preferred":[
        "Queen City"
    ],
    "name:pol_x_preferred":[
        "Queen City"
    ],
    "name:srp_x_preferred":[
        "\u041a\u0432\u0438\u043d \u0421\u0438\u0442\u0438"
    ],
    "name:vie_x_preferred":[
        "Queen City"
    ],
    "name:vol_x_preferred":[
        "Queen City"
    ],
    "qs_pg:aaroncc":"US",
    "qs_pg:gn_country":"US",
    "qs_pg:gn_fcode":"PPL",
    "qs_pg:gn_pop":0,
    "qs_pg:name":"Queen City",
    "qs_pg:name_adm0":"United States",
    "qs_pg:name_adm1":"Pennsylvania",
    "qs_pg:photos_9k":1,
    "qs_pg:photos_9r":1,
    "qs_pg:photos_all":6,
    "qs_pg:photos_sr":0,
    "qs_pg:pop_sr":0,
    "qs_pg:qs_pg_placetype":"locality",
    "qs_pg:qs_pg_placetype_gp":"Town",
    "qs_pg:woe_adm0":23424977,
    "woe:adm0_id":23424977,
    "woe:name_adm0":"United States",
    "woe:name_adm1":"Pennsylvania",
    "woe:placetype":"Town",
    "wof:name":"Queen City",
    "wof:placetype":"locality"
},
  "geometry": {"coordinates":[-76.43577999999999,40.91509],"type":"Point"}
}