{
  "type": "Feature",
  "properties": {
    "gn:admin1_code":"PA",
    "gn:admin2_code":"51.0",
    "gn:admin3_code":"45560.0",
    "gn:asciiname":"West Bend",
    "gn:country_code":"US",
    "gn:dem":360,
    "gn:elevation":"360.0",
    "gn:feature_class":"P",
    "gn:feature_code":"PPL",
    "gn:name":"West Bend",
    "gn:population":0,
    "gn:timezone":"America/New_York",
    "iso:country":"US",
    "name:ben_x_preferred":[
        "\u0993\u09df\u09c7\u09b8\u09cd\u099f \u09ac\u09c7\u09a8\u09cd\u09a1"
    ],
    "name:ceb_x_preferred":[
        "West Bend"
    ],
    "name:deu_x_preferred":[
        "West Bend"
    ],
    "name:ell_x_preferred":[
        "\u0393\u03bf\u03c5\u03ad\u03c3\u03c4 \u039c\u03c0\u03b5\u03bd\u03c4"
    ],
    "name:eng_x_preferred":[
        "West Bend"
    ],
    "name:fas_x_preferred":[
        "\u0648\u0633\u062a \u0628\u0646\u062f"
    ],
    "name:fra_x_preferred":[
        "West Bend"
    ],
    "name:heb_x_preferred":[
        "\u05d5\u05d5\u05e1\u05d8 \u05d1\u05e0\u05d3"
    ],
    "name:hin_x_preferred":[
        "\u0935\u0947\u0938\u094d\u091f \u092c\u0947\u0902\u0921"
    ],
    "name:ind_x_preferred":[
        "West Bend"
    ],
    "name:ita_x_preferred":[
        "West Bend"
    ],
    "name:kor_x_preferred":[
        "\uc6e8\uc2a4\ud2b8 \ubca4\ub4dc"
    ],
    "name:nld_x_preferred":[
        "West Bend"
    ],
    "name:pol_x_preferred":[
        "West Bend"
    ],
    "name:por_x_preferred":[
        "West Bend"
    ],
    "name:srp_x_preferred":[
        "\u0412\u0435\u0441\u0442 \u0411\u0435\u043d\u0434"
    ],
    "name:swe_x_preferred":[
        "West Bend"
    ],
    "name:ukr_x_preferred":[
        "\u0412\u0435\u0441\u0442-\u0411\u0435\u043d\u0434"
    ],
    "name:und_x_variant":[
        "Ormond"
    ],
    "name:vol_x_preferred":[
        "West Bend"
    ],
    "wof:name":"West Bend",
    "wof:placetype":"locality"
},
  "geometry": {"coordinates":[-79.97311000000001,39.97313],"type":"Point"}
}