{
  "type": "Feature",
  "properties": {
    "gn:admin1_code":"PA",
    "gn:admin2_code":"51.0",
    "gn:admin3_code":"45560.0",
    "gn:asciiname":"West Bend",
    "gn:country_code":"US",
    "gn:dem":360,
    "gn:elevation":"360.0",
    "gn:feature_class":"P",
    "gn:feature_code":"PPL",
    "gn:name":"West Bend",
    "gn:population":0,
    "gn:timezone":"America/New_York",
    "iso:country":"US",
    "name:ceb_x_preferred":[
        "West Bend"
    ],
    "name:deu_x_preferred":[
        "West Bend"
    ],
    "name:eng_x_preferred":[
        "West Bend"
    ],
    "name:fas_x_preferred":[
        "\u0648\u0633\u062a \u0628\u0646\u062f"
    ],
    "name:fra_x_preferred":[
        "West Bend"
    ],
    "name:ita_x_preferred":[
        "West Bend"
    ],
    "name:nld_x_preferred":[
        "West Bend"
    ],
    "name:pol_x_preferred":[
        "West Bend"
    ],
    "name:por_x_preferred":[
        "West Bend"
    ],
    "name:srp_x_preferred":[
        "\u0412\u0435\u0441\u0442 \u0411\u0435\u043d\u0434"
    ],
    "name:swe_x_preferred":[
        "West Bend"
    ],
    "name:ukr_x_preferred":[
        "\u0412\u0435\u0441\u0442-\u0411\u0435\u043d\u0434"
    ],
    "name:und_x_variant":[
        "Ormond"
    ],
    "name:vol_x_preferred":[
        "West Bend"
    ],
    "wof:name":"West Bend",
    "wof:placetype":"locality"
},
  "geometry": {"coordinates":[-79.97310999999998,39.97313],"type":"Point"}
}