{
  "type": "Feature",
  "properties": {
    "gn:admin1_code":"OH",
    "gn:admin2_code":"151",
    "gn:admin3_code":"62078.0",
    "gn:asciiname":"Oak Manor",
    "gn:country_code":"US",
    "gn:dem":332,
    "gn:elevation":"333.0",
    "gn:feature_class":"P",
    "gn:feature_code":"PPL",
    "gn:name":"Oak Manor",
    "gn:population":0,
    "gn:timezone":"America/New_York",
    "iso:country":"US",
    "wof:name":"Oak Manor",
    "wof:placetype":"locality"
},
  "geometry": {"coordinates":[-81.47,40.80028],"type":"Point"}
}