{
  "type": "Feature",
  "properties": {
    "gn:admin1_code":"ME",
    "gn:admin2_code":"3.0",
    "gn:admin3_code":"69930.0",
    "gn:asciiname":"City Camp Landing",
    "gn:country_code":"US",
    "gn:dem":125,
    "gn:elevation":"121.0",
    "gn:feature_class":"P",
    "gn:feature_code":"PPL",
    "gn:name":"City Camp Landing",
    "gn:population":0,
    "gn:timezone":"America/New_York",
    "iso:country":"US",
    "wof:name":"City Camp Landing",
    "wof:placetype":"locality"
},
  "geometry": {"coordinates":[-68.08224,45.90033],"type":"Point"}
}