{
  "type": "Feature",
  "properties": {
    "gn:admin1_code":"MT",
    "gn:admin2_code":"9.0",
    "gn:asciiname":"Berts Trailer Court",
    "gn:country_code":"US",
    "gn:dem":1075,
    "gn:elevation":"1077.0",
    "gn:feature_class":"P",
    "gn:feature_code":"PPL",
    "gn:name":"Berts Trailer Court",
    "gn:population":0,
    "gn:timezone":"America/Denver",
    "iso:country":"US",
    "wof:name":"Berts Trailer Court",
    "wof:placetype":"locality"
},
  "geometry": {"coordinates":[-108.90653,45.39217],"type":"Point"}
}