{
  "type": "Feature",
  "properties": {
    "iso:country":"US",
    "name:eng_x_preferred":[
        "Glen Oaks"
    ],
    "qs:gn_adm0_cc":"US",
    "qs:gn_local":4992519,
    "qs:gn_nam_loc":"Farmington, Oakland, Michigan, US",
    "qs:gn_namadm1":"MI",
    "qs:local_max":4015,
    "qs:local_sum":7436,
    "qs:localhoods":18,
    "qs:name":"Glen Oaks",
    "qs:name_adm0":"United States",
    "qs:name_adm1":"Michigan",
    "qs:name_adm2":"Oakland",
    "qs:name_local":"Farmington",
    "qs:photo_max":42,
    "qs:photo_sum":154,
    "qs:placetype":"Suburb",
    "qs:quad_count":12,
    "qs:woe_adm0":23424977,
    "qs:woe_adm1":2347581,
    "qs:woe_adm2":12588776,
    "qs:woe_lau":0,
    "qs:woe_local":2402469,
    "qs:woe_ver":"7.10.0",
    "wof:lang":[
        "eng"
    ],
    "wof:name":"Glen Oaks",
    "wof:placetype":"neighbourhood",
    "wof:population":2528,
    "zs:blockids":[
        261251569002019,
        261251569002022,
        261251660002011,
        261251569002026,
        261251660002010,
        261251660002003,
        261251660002005,
        261251660002012,
        261251660002015,
        261251660002016,
        261251578003021,
        261251569001014,
        261251569001009,
        261251660002002,
        261251569002016,
        261251660003006,
        261251569001025,
        261251569002021,
        261251569002025,
        261251660002022,
        261251578002014,
        261251661001000,
        261251660002009,
        261251660003011,
        261251569002017,
        261251660002000,
        261251660002020,
        261251660002019,
        261251569002024,
        261251660002014,
        261251660002008,
        261251569001024,
        261251578003020,
        261251569001016,
        261251569001007,
        261251569001006,
        261251569001013,
        261251660002021,
        261251569001008,
        261251660002004,
        261251660002007,
        261251660003005,
        261251569001010,
        261251569001012,
        261251569001011,
        261251660003018,
        261251569002018,
        261251569001023,
        261251569001022,
        261251660002017,
        261251661001027,
        261251569002013,
        261251569002014,
        261251660003013,
        261251569002023,
        261251660003008,
        261251660002006,
        261251578003019,
        261251660002001,
        261251569002020,
        261251660003007,
        261251660002018,
        261251569001015
    ],
    "zs:housing10":1253,
    "zs:pop10":2528
},
  "geometry": {"coordinates":[-83.359932,42.522194],"type":"Point"}
}