{
  "type": "Feature",
  "properties": {
    "iso:country":"US",
    "name:eng_x_preferred":[
        "Evening Sky"
    ],
    "name:pol_x_preferred":[
        "C/1989 Y1"
    ],
    "name:rus_x_preferred":[
        "C/1989 Y1"
    ],
    "name:slk_x_preferred":[
        "Kom\u00e9ta Skorichenko-George"
    ],
    "name:slv_x_preferred":[
        "Komet Skori\u010denko-George"
    ],
    "wof:name":"Evening Sky",
    "wof:placetype":"neighbourhood",
    "wof:population":519,
    "zs:area_m":30187679.477731,
    "zs:blockids":[
        80839692002097,
        80839692002096,
        80839696001001,
        80839692002101,
        80839696001018,
        80839696001012,
        80839692002100,
        80839692002043,
        80839696001004,
        80839696001003,
        80839692002094,
        80839692002099,
        80839696001102,
        80839696001024,
        80839692002095,
        80839696001021,
        80839692002098,
        80839696001002,
        80839692002090,
        80839692002045
    ],
    "zs:housing10":238,
    "zs:label":"Evening Sky",
    "zs:pop10":519
},
  "geometry": {"coordinates":[-108.656941,37.425725],"type":"Point"}
}