{
  "type": "Feature",
  "properties": {
    "gn:admin1_code":"TX",
    "gn:admin2_code":"215.0",
    "gn:asciiname":"River Bend Colonia",
    "gn:country_code":"US",
    "gn:dem":30,
    "gn:elevation":"27.0",
    "gn:feature_class":"P",
    "gn:feature_code":"PPL",
    "gn:name":"River Bend Colonia",
    "gn:population":0,
    "gn:timezone":"America/Chicago",
    "iso:country":"US",
    "name:eng_x_preferred":[
        "River Bend Colonia"
    ],
    "name:und_x_variant":[
        "River Bend Subdivision Colonia"
    ],
    "wof:name":"River Bend Colonia",
    "wof:placetype":"locality"
},
  "geometry": {"coordinates":[-98.18528999999999,26.34229],"type":"Point"}
}