{
  "type": "Feature",
  "properties": {
    "gn:admin1_code":"MI",
    "gn:admin2_code":"49.0",
    "gn:admin3_code":"33300.0",
    "gn:asciiname":"Tudor Estates Mobile Home Park",
    "gn:country_code":"US",
    "gn:dem":238,
    "gn:elevation":"236.0",
    "gn:feature_class":"P",
    "gn:feature_code":"PPL",
    "gn:name":"Tudor Estates Mobile Home Park",
    "gn:population":0,
    "gn:timezone":"America/Detroit",
    "iso:country":"US",
    "wof:name":"Tudor Estates Mobile Home Park",
    "wof:placetype":"campus"
},
  "geometry": {"coordinates":[-83.68056,42.95861],"type":"Point"}
}