{
  "type": "Feature",
  "properties": {
    "gn:admin1_code":"NC",
    "gn:admin2_code":"163.0",
    "gn:admin3_code":"91944.0",
    "gn:asciiname":"Parkersburg",
    "gn:country_code":"US",
    "gn:dem":39,
    "gn:elevation":"36.0",
    "gn:feature_class":"P",
    "gn:feature_code":"PPL",
    "gn:name":"Parkersburg",
    "gn:population":0,
    "gn:timezone":"America/New_York",
    "iso:country":"US",
    "wof:name":"Parkersburg",
    "wof:placetype":"locality"
},
  "geometry": {"coordinates":[-78.44334000000001,34.83711],"type":"Point"}
}