{
  "type": "Feature",
  "properties": {
    "iso:country":"US",
    "name:eng_x_preferred":[
        "Rene Mont"
    ],
    "wof:name":"Rene Mont",
    "wof:placetype":"neighbourhood",
    "wof:population":97,
    "zs:area_m":3975077.112969,
    "zs:blockids":[
        421070029004035,
        421070029004033,
        421070029004034,
        421070029004016
    ],
    "zs:housing10":41,
    "zs:label":"Rene Mont",
    "zs:pop10":97
},
  "geometry": {"coordinates":[-75.96744099999999,40.691874],"type":"Point"}
}