{
  "type": "Feature",
  "properties": {
    "gn:admin1_code":"TX",
    "gn:admin2_code":"215",
    "gn:asciiname":"El Nopal Colonia",
    "gn:country_code":"US",
    "gn:dem":30,
    "gn:elevation":"28.0",
    "gn:feature_class":"P",
    "gn:feature_code":"PPL",
    "gn:name":"El Nopal Colonia",
    "gn:population":0,
    "gn:timezone":"America/Chicago",
    "iso:country":"US",
    "wof:name":"El Nopal Colonia",
    "wof:placetype":"locality"
},
  "geometry": {"coordinates":[-98.09139999999999,26.18535],"type":"Point"}
}