{
  "type": "Feature",
  "properties": {
    "gn:admin1_code":"IA",
    "gn:admin2_code":"105.0",
    "gn:admin3_code":"90519.0",
    "gn:asciiname":"Downers Grove",
    "gn:country_code":"US",
    "gn:dem":292,
    "gn:elevation":"291.0",
    "gn:feature_class":"P",
    "gn:feature_code":"PPL",
    "gn:name":"Downers Grove",
    "gn:population":0,
    "gn:timezone":"America/Chicago",
    "iso:country":"US",
    "wof:name":"Downers Grove",
    "wof:placetype":"locality"
},
  "geometry": {"coordinates":[-91.28099,42.245],"type":"Point"}
}