{
  "type": "Feature",
  "properties": {
    "gn:admin1_code":"FL",
    "gn:admin2_code":"57",
    "gn:asciiname":"Lakeside",
    "gn:country_code":"US",
    "gn:dem":22,
    "gn:elevation":"19.0",
    "gn:feature_class":"P",
    "gn:feature_code":"PPL",
    "gn:name":"Lakeside",
    "gn:population":0,
    "gn:timezone":"America/New_York",
    "iso:country":"US",
    "name:bar_x_preferred":[
        "Lakeside"
    ],
    "name:ceb_x_preferred":[
        "Lakeside"
    ],
    "name:deu_x_preferred":[
        "Lakeside"
    ],
    "name:fra_x_preferred":[
        "Lakeside"
    ],
    "name:hun_x_preferred":[
        "Lakeside"
    ],
    "name:ita_x_preferred":[
        "Lakeside"
    ],
    "name:nld_x_preferred":[
        "Lakeside"
    ],
    "name:pol_x_preferred":[
        "Lakeside"
    ],
    "name:por_x_preferred":[
        "Lakeside"
    ],
    "name:rus_x_preferred":[
        "\u041b\u0435\u0439\u043a\u0441\u0430\u0439\u0434"
    ],
    "name:slk_x_preferred":[
        "Lakeside"
    ],
    "name:spa_x_preferred":[
        "Lakeside"
    ],
    "name:srp_x_preferred":[
        "\u041b\u0435\u0458\u043a\u0441\u0430\u0458\u0434"
    ],
    "name:ukr_x_preferred":[
        "\u041b\u0435\u0439\u043a\u0441\u0430\u0439\u0434"
    ],
    "name:vol_x_preferred":[
        "Lakeside"
    ],
    "wof:name":"Lakeside",
    "wof:placetype":"locality"
},
  "geometry": {"coordinates":[-82.3227,27.8361],"type":"Point"}
}