{
  "type": "Feature",
  "properties": {
    "gn:admin1_code":"FL",
    "gn:admin2_code":"127.0",
    "gn:asciiname":"Riverview Pines Mobile Home Park",
    "gn:country_code":"US",
    "gn:dem":7,
    "gn:elevation":"4.0",
    "gn:feature_class":"P",
    "gn:feature_code":"PPL",
    "gn:name":"Riverview Pines Mobile Home Park",
    "gn:population":0,
    "gn:timezone":"America/New_York",
    "iso:country":"US",
    "wof:name":"Riverview Pines Mobile Home Park",
    "wof:placetype":"campus"
},
  "geometry": {"coordinates":[-80.90365,28.98574],"type":"Point"}
}