{
  "type": "Feature",
  "properties": {
    "gn:admin1_code":"OK",
    "gn:admin2_code":"79.0",
    "gn:asciiname":"Walls",
    "gn:country_code":"US",
    "gn:dem":165,
    "gn:elevation":"162.0",
    "gn:feature_class":"P",
    "gn:feature_code":"PPL",
    "gn:name":"Walls",
    "gn:population":0,
    "gn:timezone":"America/Chicago",
    "iso:country":"US",
    "name:deu_x_preferred":[
        "Walls"
    ],
    "name:fra_x_preferred":[
        "Walls"
    ],
    "name:ita_x_preferred":[
        "Walls"
    ],
    "name:pol_x_preferred":[
        "Walls"
    ],
    "wof:name":"Walls",
    "wof:placetype":"locality"
},
  "geometry": {"coordinates":[-94.90912,35.03704],"type":"Point"}
}