{
  "type": "Feature",
  "properties": {
    "gn:admin1_code":"GA",
    "gn:admin2_code":"95",
    "gn:asciiname":"Turner City",
    "gn:country_code":"US",
    "gn:dem":68,
    "gn:elevation":"64.0",
    "gn:feature_class":"P",
    "gn:feature_code":"PPL",
    "gn:name":"Turner City",
    "gn:population":0,
    "gn:timezone":"America/New_York",
    "iso:country":"US",
    "wof:name":"Turner City",
    "wof:placetype":"locality"
},
  "geometry": {"coordinates":[-84.10795999999998,31.59795],"type":"Point"}
}