{
  "type": "Feature",
  "properties": {
    "gn:admin1_code":"MD",
    "gn:admin2_code":"13.0",
    "gn:asciiname":"Eleven Meadows",
    "gn:country_code":"US",
    "gn:dem":166,
    "gn:elevation":"166.0",
    "gn:feature_class":"P",
    "gn:feature_code":"PPL",
    "gn:name":"Eleven Meadows",
    "gn:population":0,
    "gn:timezone":"America/New_York",
    "iso:country":"US",
    "wof:name":"Eleven Meadows",
    "wof:placetype":"locality"
},
  "geometry": {"coordinates":[-77.13193000000003,39.68538],"type":"Point"}
}