{
  "type": "Feature",
  "properties": {
    "gn:admin1_code":"KY",
    "gn:admin2_code":"91",
    "gn:asciiname":"Patesville",
    "gn:country_code":"US",
    "gn:dem":151,
    "gn:elevation":"148.0",
    "gn:feature_class":"P",
    "gn:feature_code":"PPL",
    "gn:name":"Patesville",
    "gn:population":0,
    "gn:timezone":"America/Chicago",
    "iso:country":"US",
    "name:eng_x_preferred":[
        "Patesville"
    ],
    "name:und_x_variant":[
        "Patesville Post Office"
    ],
    "wof:name":"Patesville",
    "wof:placetype":"locality"
},
  "geometry": {"coordinates":[-86.71888,37.782],"type":"Point"}
}