{
  "type": "Feature",
  "properties": {
    "gn:admin1_code":"TX",
    "gn:admin2_code":"41",
    "gn:asciiname":"Dinkins",
    "gn:country_code":"US",
    "gn:dem":61,
    "gn:elevation":"59.0",
    "gn:feature_class":"P",
    "gn:feature_code":"PPL",
    "gn:name":"Dinkins",
    "gn:population":0,
    "gn:timezone":"America/Chicago",
    "iso:country":"US",
    "name:deu_x_preferred":[
        "Dinkins"
    ],
    "wof:name":"Dinkins",
    "wof:placetype":"locality"
},
  "geometry": {"coordinates":[-96.1769,30.42159],"type":"Point"}
}