{
  "type": "Feature",
  "properties": {
    "gn:admin1_code":"NC",
    "gn:admin2_code":"183.0",
    "gn:admin3_code":"92440.0",
    "gn:asciiname":"Williams Crossroads",
    "gn:country_code":"US",
    "gn:dem":125,
    "gn:elevation":"123.0",
    "gn:feature_class":"P",
    "gn:feature_code":"PPL",
    "gn:name":"Williams Crossroads",
    "gn:population":0,
    "gn:timezone":"America/New_York",
    "iso:country":"US",
    "name:eng_x_preferred":[
        "Williams Crossroads"
    ],
    "name:und_x_variant":[
        "Williamson Crossroad"
    ],
    "wof:name":"Williams Crossroads",
    "wof:placetype":"locality"
},
  "geometry": {"coordinates":[-78.66611999999998,35.65571],"type":"Point"}
}