{
  "type": "Feature",
  "properties": {
    "gn:admin1_code":"WV",
    "gn:admin2_code":"79.0",
    "gn:asciiname":"Windsong Acres",
    "gn:country_code":"US",
    "gn:dem":252,
    "gn:elevation":"234.0",
    "gn:feature_class":"P",
    "gn:feature_code":"PPL",
    "gn:name":"Windsong Acres",
    "gn:population":0,
    "gn:timezone":"America/New_York",
    "iso:country":"US",
    "wof:name":"Windsong Acres",
    "wof:placetype":"locality"
},
  "geometry": {"coordinates":[-81.86513000000002,38.47454000000001],"type":"Point"}
}