{
  "type": "Feature",
  "properties": {
    "iso:country":"US",
    "name:eng_x_preferred":[
        "Timberline"
    ],
    "qs:gn_adm0_cc":"US",
    "qs:gn_local":4879890,
    "qs:gn_nam_loc":"Urbandale, Polk, Iowa, US",
    "qs:gn_namadm1":"IA",
    "qs:local_max":466,
    "qs:local_sum":1462,
    "qs:localhoods":10,
    "qs:name":"Timberline",
    "qs:name_adm0":"United States",
    "qs:name_adm1":"Iowa",
    "qs:name_adm2":"Polk",
    "qs:name_local":"Urbandale",
    "qs:photo_max":203,
    "qs:photo_sum":360,
    "qs:placetype":"Suburb",
    "qs:quad_count":7,
    "qs:woe_adm0":23424977,
    "qs:woe_adm1":2347574,
    "qs:woe_adm2":12588348,
    "qs:woe_lau":0,
    "qs:woe_local":2510443,
    "qs:woe_ver":"7.10.0",
    "wd:wordcount":78,
    "wof:lang":[
        "eng"
    ],
    "wof:name":"Timberline",
    "wof:placetype":"neighbourhood",
    "wof:population":737,
    "zs:blockids":[
        191530113004078,
        191530113004009,
        191530113004052,
        191530113004048,
        191530113004088,
        191530113004032,
        191530113004047,
        191530113004045,
        191530113004077,
        191530113004053,
        191530113004030,
        191530113004040,
        191530113004079,
        191530113004027,
        191530113004081,
        191530113004051,
        191530113004035,
        191530113004037,
        191530113004080,
        191530113004033,
        191530113004089,
        191530113004034,
        191530113004039,
        191530113004049,
        191530113004031,
        191530113004046
    ],
    "zs:housing10":328,
    "zs:pop10":737
},
  "geometry": {"coordinates":[-93.777517,41.624557],"type":"Point"}
}