{
  "type": "Feature",
  "properties": {
    "gn:admin1_code":"FL",
    "gn:admin2_code":"43.0",
    "gn:asciiname":"Shawnee",
    "gn:country_code":"US",
    "gn:dem":9,
    "gn:elevation":"4.0",
    "gn:feature_class":"P",
    "gn:feature_code":"PPL",
    "gn:name":"Shawnee",
    "gn:population":0,
    "gn:timezone":"America/New_York",
    "iso:country":"US",
    "name:ara_x_preferred":[
        "\u0634\u0627\u0648\u0646\u064a"
    ],
    "name:aze_x_preferred":[
        "\u015eauni"
    ],
    "name:bar_x_preferred":[
        "Shawnee"
    ],
    "name:bel_x_preferred":[
        "\u0428\u0430\u045e\u043d\u0456"
    ],
    "name:ben_x_preferred":[
        "\u09b6\u09a8\u09c0"
    ],
    "name:bul_x_preferred":[
        "\u0428\u043e\u0443\u043d\u0438"
    ],
    "name:cat_x_preferred":[
        "Shawnee"
    ],
    "name:ces_x_preferred":[
        "\u0160avan\u00e9"
    ],
    "name:dan_x_preferred":[
        "Shawnee"
    ],
    "name:deu_x_preferred":[
        "Shawnee"
    ],
    "name:ell_x_preferred":[
        "\u03a3\u03cc\u03bd\u03b9"
    ],
    "name:epo_x_preferred":[
        "Shawnee"
    ],
    "name:eus_x_preferred":[
        "Shawnee"
    ],
    "name:fin_x_preferred":[
        "Shawneet"
    ],
    "name:fra_x_preferred":[
        "Chaouanons"
    ],
    "name:hin_x_preferred":[
        "\u0936\u0949\u0928\u0940"
    ],
    "name:hrv_x_preferred":[
        "Shawnee"
    ],
    "name:ind_x_preferred":[
        "Shawnee"
    ],
    "name:ita_x_preferred":[
        "Shawnee"
    ],
    "name:jpn_x_preferred":[
        "\u30b7\u30e7\u30fc\u30cb\u30fc\u65cf"
    ],
    "name:kor_x_preferred":[
        "\uc1fc\ub2c8\uc871"
    ],
    "name:lit_x_preferred":[
        "\u0160oniai"
    ],
    "name:mlg_x_preferred":[
        "Shawnee"
    ],
    "name:nld_x_preferred":[
        "Shawnee"
    ],
    "name:nor_x_preferred":[
        "Shawnee"
    ],
    "name:pol_x_preferred":[
        "Szaunisi"
    ],
    "name:rus_x_preferred":[
        "\u0428\u0430\u0443\u043d\u0438"
    ],
    "name:slk_x_preferred":[
        "\u0160\u00f3n\u00edovia"
    ],
    "name:spa_x_preferred":[
        "Shawnee"
    ],
    "name:srp_x_preferred":[
        "\u0428\u043e\u043d\u0438"
    ],
    "name:swe_x_preferred":[
        "Shawnee"
    ],
    "name:tur_x_preferred":[
        "\u015eavniler"
    ],
    "name:vie_x_preferred":[
        "Ng\u01b0\u1eddi Shawnee"
    ],
    "wof:name":"Shawnee",
    "wof:placetype":"locality"
},
  "geometry": {"coordinates":[-80.96505999999999,26.77729],"type":"Point"}
}