{
  "type": "Feature",
  "properties": {
    "gn:admin1_code":"FL",
    "gn:admin2_code":"31.0",
    "gn:asciiname":"Rhondas Trailer Park",
    "gn:country_code":"US",
    "gn:dem":8,
    "gn:elevation":"5.0",
    "gn:feature_class":"P",
    "gn:feature_code":"PPL",
    "gn:name":"Rhondas Trailer Park",
    "gn:population":0,
    "gn:timezone":"America/New_York",
    "iso:country":"US",
    "wof:name":"Rhondas Trailer Park",
    "wof:placetype":"campus"
},
  "geometry": {"coordinates":[-81.72117,30.24143],"type":"Point"}
}