{
  "type": "Feature",
  "properties": {
    "gn:admin1_code":"PA",
    "gn:admin2_code":"25.0",
    "gn:admin3_code":"4048.0",
    "gn:asciiname":"Coxes Village",
    "gn:country_code":"US",
    "gn:dem":519,
    "gn:elevation":"519.0",
    "gn:feature_class":"P",
    "gn:feature_code":"PPL",
    "gn:name":"Coxes Village",
    "gn:population":0,
    "gn:timezone":"America/New_York",
    "iso:country":"US",
    "name:eng_x_preferred":[
        "Coxes Village"
    ],
    "name:und_x_variant":[
        "Cross Village"
    ],
    "wof:name":"Coxes Village",
    "wof:placetype":"locality"
},
  "geometry": {"coordinates":[-75.92631,40.93536],"type":"Point"}
}