{
  "type": "Feature",
  "properties": {
    "gn:admin1_code":"KY",
    "gn:admin2_code":"231",
    "gn:asciiname":"Short Mountain",
    "gn:country_code":"US",
    "gn:dem":371,
    "gn:elevation":"372.0",
    "gn:feature_class":"P",
    "gn:feature_code":"PPL",
    "gn:name":"Short Mountain",
    "gn:population":0,
    "gn:timezone":"America/Kentucky/Monticello",
    "iso:country":"US",
    "name:ceb_x_preferred":[
        "Short Mountain"
    ],
    "wof:name":"Short Mountain",
    "wof:placetype":"locality"
},
  "geometry": {"coordinates":[-84.8955,36.84174],"type":"Point"}
}