{
  "type": "Feature",
  "properties": {
    "gn:admin1_code":"GA",
    "gn:admin2_code":"57.0",
    "gn:asciiname":"Cherecobb Estates",
    "gn:country_code":"US",
    "gn:dem":304,
    "gn:elevation":"299.0",
    "gn:feature_class":"P",
    "gn:feature_code":"PPL",
    "gn:name":"Cherecobb Estates",
    "gn:population":0,
    "gn:timezone":"America/New_York",
    "iso:country":"US",
    "wof:name":"Cherecobb Estates",
    "wof:placetype":"locality"
},
  "geometry": {"coordinates":[-84.44382,34.0751],"type":"Point"}
}