{
  "type": "Feature",
  "properties": {
    "gn:admin1_code":"MO",
    "gn:admin2_code":"141.0",
    "gn:admin3_code":"49880.0",
    "gn:asciiname":"Marvin",
    "gn:country_code":"US",
    "gn:dem":312,
    "gn:elevation":"310.0",
    "gn:feature_class":"P",
    "gn:feature_code":"PPL",
    "gn:name":"Marvin",
    "gn:population":0,
    "gn:timezone":"America/Chicago",
    "iso:country":"US",
    "name:ces_x_preferred":[
        "Marvin"
    ],
    "name:fra_x_preferred":[
        "Marvin"
    ],
    "name:ita_x_preferred":[
        "Marvin"
    ],
    "name:jpn_x_preferred":[
        "\u30de\u30fc\u30f4\u30a3\u30f3"
    ],
    "name:nld_x_preferred":[
        "Marvin"
    ],
    "name:pol_x_preferred":[
        "Marvin"
    ],
    "name:por_x_preferred":[
        "Marvin"
    ],
    "name:rus_x_preferred":[
        "\u041c\u0430\u0440\u0432\u0438\u043d"
    ],
    "name:spa_x_preferred":[
        "Marvin"
    ],
    "name:srp_x_preferred":[
        "\u041c\u0430\u0440\u0432\u0438\u043d"
    ],
    "name:ukr_x_preferred":[
        "\u041c\u0430\u0440\u0432\u0456\u043d"
    ],
    "name:vol_x_preferred":[
        "Marvin"
    ],
    "wof:name":"Marvin",
    "wof:placetype":"locality"
},
  "geometry": {"coordinates":[-92.77075000000001,38.41642],"type":"Point"}
}