{
  "type": "Feature",
  "properties": {
    "gn:admin1_code":"MT",
    "gn:admin2_code":"91.0",
    "gn:asciiname":"Dooley",
    "gn:country_code":"US",
    "gn:dem":750,
    "gn:elevation":"750.0",
    "gn:feature_class":"P",
    "gn:feature_code":"PPL",
    "gn:name":"Dooley",
    "gn:population":0,
    "gn:timezone":"America/Denver",
    "iso:country":"US",
    "name:por_x_preferred":[
        "Dooley"
    ],
    "wof:name":"Dooley",
    "wof:placetype":"locality"
},
  "geometry": {"coordinates":[-104.38939000000001,48.88114],"type":"Point"}
}