{
  "type": "Feature",
  "properties": {
    "gn:elevation":75,
    "iso:country":"US",
    "name:eng_x_preferred":[
        "Middle Hope"
    ],
    "name:und_x_variant":[
        "Middletown"
    ],
    "qs:gn_adm0_cc":"US",
    "qs:gn_fcode":"PPL",
    "qs:gn_local":5128654,
    "qs:gn_nam_loc":"Newburgh, Orange, New York, US",
    "qs:gn_namadm1":"NY",
    "qs:gn_name":"Middle Hope",
    "qs:local_max":365,
    "qs:local_sum":687,
    "qs:localhoods":8,
    "qs:name":"Middle Hope",
    "qs:name_adm0":"United States",
    "qs:name_adm1":"New York",
    "qs:name_adm2":"Orange",
    "qs:name_local":"Newburgh",
    "qs:photo_max":45,
    "qs:photo_sum":78,
    "qs:placetype":"Suburb",
    "qs:quad_count":11,
    "qs:woe_adm0":23424977,
    "qs:woe_adm1":2347591,
    "qs:woe_adm2":12589347,
    "qs:woe_lau":0,
    "qs:woe_local":2459358,
    "qs:woe_ver":"7.10.0",
    "wof:lang":[
        "eng"
    ],
    "wof:name":"Middle Hope",
    "wof:placetype":"neighbourhood",
    "wof:population":1402,
    "zs:blockids":[
        360710101021009,
        360710101021019,
        360710101021001,
        360710101021021,
        360710101024011,
        360710101021012,
        360710101021022,
        360710101024007,
        360710101024010,
        360710101021016,
        360710101021013,
        360710101021020,
        360710101021007,
        360710101024005,
        360710101024002,
        360710101021018,
        360710101021014,
        360710101021006,
        360710101024004,
        360710101024009,
        360710101024003,
        360710101024006,
        360710101024001,
        360710101021015,
        360710101021017
    ],
    "zs:housing10":647,
    "zs:pop10":1402
},
  "geometry": {"coordinates":[-74.002375,41.571133],"type":"Point"}
}