{
  "type": "Feature",
  "properties": {
    "gn:admin1_code":"NC",
    "gn:admin2_code":"107.0",
    "gn:admin3_code":"90760.0",
    "gn:asciiname":"Tick Bite",
    "gn:country_code":"US",
    "gn:dem":8,
    "gn:elevation":"6.0",
    "gn:feature_class":"P",
    "gn:feature_code":"PPL",
    "gn:name":"Tick Bite",
    "gn:population":0,
    "gn:timezone":"America/New_York",
    "iso:country":"US",
    "name:vol_x_preferred":[
        "Tick Bite"
    ],
    "wof:name":"Tick Bite",
    "wof:placetype":"locality"
},
  "geometry": {"coordinates":[-77.4308,35.34822],"type":"Point"}
}