{
  "type": "Feature",
  "properties": {
    "gn:admin1_code":"MO",
    "gn:admin2_code":"145.0",
    "gn:admin3_code":"51590.0",
    "gn:asciiname":"Fredville",
    "gn:country_code":"US",
    "gn:dem":348,
    "gn:elevation":"345.0",
    "gn:feature_class":"P",
    "gn:feature_code":"PPL",
    "gn:name":"Fredville",
    "gn:population":0,
    "gn:timezone":"America/Chicago",
    "iso:country":"US",
    "wof:name":"Fredville",
    "wof:placetype":"locality"
},
  "geometry": {"coordinates":[-94.41271999999999,36.90951],"type":"Point"}
}