{
  "type": "Feature",
  "properties": {
    "gn:admin1_code":"WV",
    "gn:admin2_code":"23",
    "gn:asciiname":"Arthur",
    "gn:country_code":"US",
    "gn:dem":331,
    "gn:elevation":"334.0",
    "gn:feature_class":"P",
    "gn:feature_code":"PPL",
    "gn:name":"Arthur",
    "gn:population":0,
    "gn:timezone":"America/New_York",
    "iso:country":"US",
    "name:azb_x_preferred":[
        "\u0622\u0631\u062a\u0648\u0631"
    ],
    "name:fas_x_preferred":[
        "\u0622\u0631\u062a\u0648\u0631"
    ],
    "name:vol_x_preferred":[
        "Arthur"
    ],
    "wof:name":"Arthur",
    "wof:placetype":"locality"
},
  "geometry": {"coordinates":[-79.11198,39.06733],"type":"Point"}
}