{
  "type": "Feature",
  "properties": {
    "gn:elevation":1368,
    "iso:country":"US",
    "name:ceb_x_preferred":[
        "Dry Creek"
    ],
    "name:deu_x_preferred":[
        "Dry Creek"
    ],
    "name:eng_x_preferred":[
        "Dry Creek"
    ],
    "name:eng_x_variant":[
        "Dry Crk"
    ],
    "name:ita_x_preferred":[
        "Dry Creek"
    ],
    "name:nds_x_preferred":[
        "Dry Creek"
    ],
    "name:nld_x_preferred":[
        "Dry Creek"
    ],
    "name:pol_x_preferred":[
        "Dry Creek"
    ],
    "name:srp_x_preferred":[
        "\u0414\u0440\u0430\u0458 \u041a\u0440\u0438\u043a"
    ],
    "name:swe_x_preferred":[
        "Dry Creek"
    ],
    "name:ukr_x_preferred":[
        "\u0414\u0440\u0430\u0439-\u041a\u0440\u0456\u043a"
    ],
    "name:unk_x_variant":[
        "Dry Creek"
    ],
    "name:vol_x_preferred":[
        "Dry Creek"
    ],
    "qs:gn_adm0_cc":"US",
    "qs:gn_fcode":"PPLX",
    "qs:gn_local":5781061,
    "qs:gn_nam_loc":"Sandy, Salt Lake, Utah, US",
    "qs:gn_namadm1":"UT",
    "qs:gn_name":"Dry Creek",
    "qs:local_max":1544,
    "qs:local_sum":7671,
    "qs:localhoods":35,
    "qs:name":"Dry Creek",
    "qs:name_adm0":"United States",
    "qs:name_adm1":"Utah",
    "qs:name_adm2":"Salt Lake",
    "qs:name_local":"Sandy",
    "qs:photo_max":11,
    "qs:photo_sum":14,
    "qs:placetype":"Suburb",
    "qs:quad_count":3,
    "qs:woe_adm0":23424977,
    "qs:woe_adm1":2347603,
    "qs:woe_adm2":12590278,
    "qs:woe_lau":0,
    "qs:woe_local":2488558,
    "qs:woe_ver":"7.10.0",
    "wof:lang":[
        "eng"
    ],
    "wof:name":"Dry Creek",
    "wof:placetype":"neighbourhood",
    "wof:population":148,
    "zs:blockids":[
        490351128124004
    ],
    "zs:housing10":41,
    "zs:pop10":148
},
  "geometry": {"coordinates":[-111.871815,40.566876],"type":"Point"}
}