{
  "type": "Feature",
  "properties": {
    "gn:admin1_code":"NC",
    "gn:admin2_code":"195.0",
    "gn:admin3_code":"93244.0",
    "gn:asciiname":"Town Creek",
    "gn:country_code":"US",
    "gn:dem":41,
    "gn:elevation":"39.0",
    "gn:feature_class":"P",
    "gn:feature_code":"PPL",
    "gn:name":"Town Creek",
    "gn:population":0,
    "gn:timezone":"America/New_York",
    "iso:country":"US",
    "name:ceb_x_preferred":[
        "Town Creek"
    ],
    "name:ita_x_preferred":[
        "Town Creek"
    ],
    "name:pol_x_preferred":[
        "Town Creek"
    ],
    "name:swe_x_preferred":[
        "Town Creek"
    ],
    "wof:name":"Town Creek",
    "wof:placetype":"locality"
},
  "geometry": {"coordinates":[-77.80109,35.81516],"type":"Point"}
}