{
  "type": "Feature",
  "properties": {
    "iso:country":"US",
    "wof:name":"Shea Terrace",
    "wof:placetype":"neighbourhood"
},
  "geometry": {"coordinates":[-76.32419808684944,36.84292672889696],"type":"Point"}
}