{
  "type": "Feature",
  "properties": {
    "gn:admin1_code":"MD",
    "gn:admin2_code":"27.0",
    "gn:asciiname":"Linden Chapel Hills",
    "gn:country_code":"US",
    "gn:dem":159,
    "gn:elevation":"160.0",
    "gn:feature_class":"P",
    "gn:feature_code":"PPL",
    "gn:name":"Linden Chapel Hills",
    "gn:population":0,
    "gn:timezone":"America/New_York",
    "iso:country":"US",
    "wof:name":"Linden Chapel Hills",
    "wof:placetype":"locality"
},
  "geometry": {"coordinates":[-76.99191999999999,39.23122],"type":"Point"}
}