{
  "type": "Feature",
  "properties": {
    "gn:admin1_code":"WV",
    "gn:admin2_code":"87",
    "gn:asciiname":"Lattimer",
    "gn:country_code":"US",
    "gn:dem":228,
    "gn:elevation":"220.0",
    "gn:feature_class":"P",
    "gn:feature_code":"PPL",
    "gn:name":"Lattimer",
    "gn:population":0,
    "gn:timezone":"America/New_York",
    "iso:country":"US",
    "name:fas_x_preferred":[
        "\u0644\u0627\u062a\u06cc\u0645\u0631"
    ],
    "name:urd_x_preferred":[
        "\u0644\u0627\u062a\u06cc\u0645\u06cc\u0631"
    ],
    "wof:name":"Lattimer",
    "wof:placetype":"locality"
},
  "geometry": {"coordinates":[-81.51485,38.84203],"type":"Point"}
}