{
  "type": "Feature",
  "properties": {
    "gn:admin1_code":"LA",
    "gn:admin2_code":"19.0",
    "gn:asciiname":"Le Bleu",
    "gn:country_code":"US",
    "gn:dem":9,
    "gn:elevation":"6.0",
    "gn:feature_class":"P",
    "gn:feature_code":"PPL",
    "gn:name":"Le Bleu",
    "gn:population":0,
    "gn:timezone":"America/Chicago",
    "iso:country":"US",
    "wof:name":"Le Bleu",
    "wof:placetype":"locality"
},
  "geometry": {"coordinates":[-93.08126,30.27604],"type":"Point"}
}