{
  "type": "Feature",
  "properties": {
    "gn:admin1_code":"MO",
    "gn:admin2_code":"147.0",
    "gn:admin3_code":"42824.0",
    "gn:asciiname":"Dawsonville",
    "gn:country_code":"US",
    "gn:dem":288,
    "gn:elevation":"291.0",
    "gn:feature_class":"P",
    "gn:feature_code":"PPL",
    "gn:name":"Dawsonville",
    "gn:population":0,
    "gn:timezone":"America/Chicago",
    "iso:country":"US",
    "name:deu_x_preferred":[
        "Dawsonville"
    ],
    "name:eng_x_preferred":[
        "Dawsonville"
    ],
    "name:fra_x_preferred":[
        "Dawsonville"
    ],
    "name:pol_x_preferred":[
        "Dawsonville"
    ],
    "name:und_x_variant":[
        "City Bluff",
        "Dawson",
        "Halsas Ferry"
    ],
    "wof:name":"Dawsonville",
    "wof:placetype":"locality"
},
  "geometry": {"coordinates":[-95.09941999999999,40.46444],"type":"Point"}
}