{
  "type": "Feature",
  "properties": {
    "gn:admin1_code":"OH",
    "gn:admin2_code":"145.0",
    "gn:admin3_code":"79828.0",
    "gn:asciiname":"Bondclay",
    "gn:country_code":"US",
    "gn:dem":195,
    "gn:elevation":"182.0",
    "gn:feature_class":"P",
    "gn:feature_code":"PPL",
    "gn:name":"Bondclay",
    "gn:population":0,
    "gn:timezone":"America/New_York",
    "iso:country":"US",
    "wof:name":"Bondclay",
    "wof:placetype":"locality"
},
  "geometry": {"coordinates":[-82.72683000000001,38.71286],"type":"Point"}
}