{
  "type": "Feature",
  "properties": {
    "gn:admin1_code":"IN",
    "gn:admin2_code":"183.0",
    "gn:admin3_code":"77750.0",
    "gn:asciiname":"Coesse Corners",
    "gn:country_code":"US",
    "gn:dem":263,
    "gn:elevation":"263.0",
    "gn:feature_class":"P",
    "gn:feature_code":"PPL",
    "gn:name":"Coesse Corners",
    "gn:population":0,
    "gn:timezone":"America/Indiana/Indianapolis",
    "iso:country":"US",
    "wof:name":"Coesse Corners",
    "wof:placetype":"locality"
},
  "geometry": {"coordinates":[-85.39581,41.14005],"type":"Point"}
}