{
  "type": "Feature",
  "properties": {
    "gn:admin1_code":"VA",
    "gn:admin2_code":"770",
    "gn:asciiname":"Medmont Lake",
    "gn:country_code":"US",
    "gn:dem":328,
    "gn:elevation":"322.0",
    "gn:feature_class":"P",
    "gn:feature_code":"PPL",
    "gn:name":"Medmont Lake",
    "gn:population":0,
    "gn:timezone":"America/New_York",
    "iso:country":"US",
    "wof:name":"Medmont Lake",
    "wof:placetype":"locality"
},
  "geometry": {"coordinates":[-80.03198,37.25986],"type":"Point"}
}