{
  "type": "Feature",
  "properties": {
    "gn:admin1_code":"AL",
    "gn:admin2_code":"127.0",
    "gn:asciiname":"Short Camp",
    "gn:country_code":"US",
    "gn:dem":159,
    "gn:elevation":"161.0",
    "gn:feature_class":"P",
    "gn:feature_code":"PPL",
    "gn:name":"Short Camp",
    "gn:population":0,
    "gn:timezone":"America/Chicago",
    "iso:country":"US",
    "wof:name":"Short Camp",
    "wof:placetype":"locality"
},
  "geometry": {"coordinates":[-87.22417,33.65761],"type":"Point"}
}