{
  "type": "Feature",
  "properties": {
    "gn:admin1_code":"GA",
    "gn:admin2_code":"101",
    "gn:asciiname":"Potter",
    "gn:country_code":"US",
    "gn:dem":48,
    "gn:elevation":"44.0",
    "gn:feature_class":"P",
    "gn:feature_code":"PPL",
    "gn:name":"Potter",
    "gn:population":0,
    "gn:timezone":"America/New_York",
    "iso:country":"US",
    "name:bel_x_preferred":[
        "\u041f\u043e\u0442\u044d\u0440"
    ],
    "name:ben_x_preferred":[
        "\u0995\u09c1\u09ae\u09cb\u09b0"
    ],
    "name:ceb_x_preferred":[
        "Potter"
    ],
    "name:ces_x_preferred":[
        "Potter"
    ],
    "name:deu_x_preferred":[
        "Potter"
    ],
    "name:fin_x_preferred":[
        "Potter"
    ],
    "name:fra_x_preferred":[
        "Potter"
    ],
    "name:hin_x_preferred":[
        "\u0915\u0941\u092e\u094d\u0939\u093e\u0930"
    ],
    "name:ita_x_preferred":[
        "Potter"
    ],
    "name:jpn_x_preferred":[
        "\u30dd\u30c3\u30bf\u30fc"
    ],
    "name:nep_x_preferred":[
        "\u0915\u0941\u092e\u093e\u0932\u0947"
    ],
    "name:nld_x_preferred":[
        "Potter"
    ],
    "name:pol_x_preferred":[
        "Potter"
    ],
    "name:por_x_preferred":[
        "Potter"
    ],
    "name:rus_x_preferred":[
        "\u041f\u043e\u0442\u0442\u0435\u0440"
    ],
    "name:spa_x_preferred":[
        "Potter"
    ],
    "name:srp_x_preferred":[
        "\u041f\u043e\u0442\u0435\u0440"
    ],
    "name:swe_x_preferred":[
        "Potter"
    ],
    "name:tam_x_preferred":[
        "\u0b95\u0bc1\u0baf\u0bb5\u0bb0\u0bcd"
    ],
    "name:ukr_x_preferred":[
        "\u041f\u043e\u0442\u0442\u0435\u0440"
    ],
    "name:urd_x_preferred":[
        "\u06a9\u0645\u06c1\u0627\u0631"
    ],
    "name:vol_x_preferred":[
        "Potter"
    ],
    "wof:name":"Potter",
    "wof:placetype":"locality"
},
  "geometry": {"coordinates":[-82.93319,30.64688],"type":"Point"}
}