{
  "type": "Feature",
  "properties": {
    "gn:admin1_code":"IA",
    "gn:admin2_code":"45.0",
    "gn:admin3_code":"94593.0",
    "gn:asciiname":"Riggs",
    "gn:country_code":"US",
    "gn:dem":232,
    "gn:elevation":"230.0",
    "gn:feature_class":"P",
    "gn:feature_code":"PPL",
    "gn:name":"Riggs",
    "gn:population":0,
    "gn:timezone":"America/Chicago",
    "iso:country":"US",
    "wof:name":"Riggs",
    "wof:placetype":"locality"
},
  "geometry": {"coordinates":[-90.53013,42.00502],"type":"Point"}
}