{
  "type": "Feature",
  "properties": {
    "gn:admin1_code":"VA",
    "gn:admin2_code":"145",
    "gn:asciiname":"Plain View",
    "gn:country_code":"US",
    "gn:dem":120,
    "gn:elevation":"122.0",
    "gn:feature_class":"P",
    "gn:feature_code":"PPL",
    "gn:name":"Plain View",
    "gn:population":0,
    "gn:timezone":"America/New_York",
    "iso:country":"US",
    "wof:name":"Plain View",
    "wof:placetype":"locality"
},
  "geometry": {"coordinates":[-77.88833000000002,37.5382],"type":"Point"}
}