{
  "type": "Feature",
  "properties": {
    "gn:admin1_code":"TX",
    "gn:admin2_code":"291.0",
    "gn:asciiname":"Winter Valley Estates",
    "gn:country_code":"US",
    "gn:dem":32,
    "gn:elevation":"27.0",
    "gn:feature_class":"P",
    "gn:feature_code":"PPL",
    "gn:name":"Winter Valley Estates",
    "gn:population":0,
    "gn:timezone":"America/Chicago",
    "iso:country":"US",
    "wof:name":"Winter Valley Estates",
    "wof:placetype":"locality"
},
  "geometry": {"coordinates":[-94.88630999999999,30.12799],"type":"Point"}
}