{
  "type": "Feature",
  "properties": {
    "gn:admin1_code":"SD",
    "gn:admin2_code":"137.0",
    "gn:admin3_code":"59975.0",
    "gn:asciiname":"Cherry Creek",
    "gn:country_code":"US",
    "gn:dem":524,
    "gn:elevation":"527.0",
    "gn:feature_class":"P",
    "gn:feature_code":"PPL",
    "gn:name":"Cherry Creek",
    "gn:population":0,
    "gn:timezone":"America/Denver",
    "iso:country":"US",
    "wof:name":"Cherry Creek",
    "wof:placetype":"locality"
},
  "geometry": {"coordinates":[-101.49987,44.60554000000001],"type":"Point"}
}