{
  "type": "Feature",
  "properties": {
    "gn:country":"US",
    "gn:fcode":"PPL",
    "gn:population":0,
    "iso:country":"US",
    "name:ara_x_preferred":[
        "\u0645\u064a\u062f\u0648\u0627\u0649"
    ],
    "name:bre_x_preferred":[
        "Midway"
    ],
    "name:cat_x_preferred":[
        "Midway"
    ],
    "name:ceb_x_preferred":[
        "Midway"
    ],
    "name:dan_x_preferred":[
        "Midway"
    ],
    "name:deu_x_preferred":[
        "Midway"
    ],
    "name:fas_x_preferred":[
        "\u0645\u06cc\u062f\u0648\u06cc"
    ],
    "name:fin_x_preferred":[
        "Midway"
    ],
    "name:fra_x_preferred":[
        "Midway"
    ],
    "name:glg_x_preferred":[
        "Midway"
    ],
    "name:heb_x_preferred":[
        "\u05de\u05d9\u05d3\u05d5\u05d5\u05d9\u05d9"
    ],
    "name:ido_x_preferred":[
        "Midway"
    ],
    "name:ind_x_preferred":[
        "Midway"
    ],
    "name:ita_x_preferred":[
        "Midway"
    ],
    "name:jpn_x_preferred":[
        "\u30df\u30c3\u30c9\u30a6\u30a7\u30fc"
    ],
    "name:kor_x_preferred":[
        "\ubbf8\ub4dc\uc6e8\uc774"
    ],
    "name:nds_x_preferred":[
        "Midway"
    ],
    "name:nld_x_preferred":[
        "Midway"
    ],
    "name:nno_x_preferred":[
        "Midway"
    ],
    "name:pol_x_preferred":[
        "Midway"
    ],
    "name:por_x_preferred":[
        "Midway"
    ],
    "name:ron_x_preferred":[
        "Midway"
    ],
    "name:rus_x_preferred":[
        "\u041c\u0438\u0434\u0443\u044d\u0439"
    ],
    "name:srp_x_preferred":[
        "\u041c\u0438\u0434\u0432\u0435\u0458"
    ],
    "name:swe_x_preferred":[
        "Midway"
    ],
    "name:tha_x_preferred":[
        "\u0e21\u0e34\u0e14\u0e40\u0e27\u0e22\u0e4c"
    ],
    "name:ukr_x_preferred":[
        "\u041c\u0456\u0434\u0432\u0435\u0439"
    ],
    "name:vie_x_preferred":[
        "Midway"
    ],
    "name:vol_x_preferred":[
        "Midway"
    ],
    "qs_pg:aaroncc":"US",
    "qs_pg:gn_country":"US",
    "qs_pg:gn_fcode":"PPL",
    "qs_pg:gn_pop":0,
    "qs_pg:name":"Midway",
    "qs_pg:name_adm0":"United States",
    "qs_pg:name_adm1":"Missouri",
    "qs_pg:photos":64,
    "qs_pg:photos_1k":13,
    "qs_pg:photos_9k":1,
    "qs_pg:photos_9r":2,
    "qs_pg:photos_all":64,
    "qs_pg:photos_sr":2,
    "qs_pg:pop_sr":0,
    "qs_pg:qs_pg_placetype":"locality",
    "qs_pg:qs_pg_placetype_gp":"Town",
    "qs_pg:woe_adm0":23424977,
    "woe:adm0_id":23424977,
    "woe:name_adm0":"United States",
    "woe:name_adm1":"Missouri",
    "woe:placetype":"Town",
    "wof:name":"Midway",
    "wof:placetype":"locality"
},
  "geometry": {"coordinates":[-92.44935,38.98504],"type":"Point"}
}