{
  "type": "Feature",
  "properties": {
    "gn:admin1_code":"AK",
    "gn:admin2_code":"240.0",
    "gn:asciiname":"Alcan",
    "gn:country_code":"US",
    "gn:dem":670,
    "gn:elevation":"651.0",
    "gn:feature_class":"P",
    "gn:feature_code":"PPL",
    "gn:name":"Alcan",
    "gn:population":0,
    "gn:timezone":"America/Anchorage",
    "iso:country":"US",
    "name:fra_x_preferred":[
        "Alcan"
    ],
    "wof:name":"Alcan",
    "wof:placetype":"locality"
},
  "geometry": {"coordinates":[-141.18806000000001,62.72306],"type":"Point"}
}