{
  "type": "Feature",
  "properties": {
    "gn:admin1_code":"WA",
    "gn:admin2_code":"73.0",
    "gn:asciiname":"Mountain View Estates Mobile Home Park",
    "gn:country_code":"US",
    "gn:dem":13,
    "gn:elevation":"13.0",
    "gn:feature_class":"P",
    "gn:feature_code":"PPL",
    "gn:name":"Mountain View Estates Mobile Home Park",
    "gn:population":0,
    "gn:timezone":"America/Los_Angeles",
    "iso:country":"US",
    "wof:name":"Mountain View Estates Mobile Home Park",
    "wof:placetype":"campus"
},
  "geometry": {"coordinates":[-122.58257,48.85999],"type":"Point"}
}