{
  "type": "Feature",
  "properties": {
    "iso:country":"US",
    "name:eng_x_preferred":[
        "McKinley Woods"
    ],
    "qs:gn_adm0_cc":"US",
    "qs:gn_fcode":"PPLX",
    "qs:gn_local":5166516,
    "qs:gn_nam_loc":"Perrysburg, Wood, Ohio, US",
    "qs:gn_namadm1":"OH",
    "qs:gn_name":"McKinley Woods",
    "qs:local_max":1532,
    "qs:local_sum":5295,
    "qs:localhoods":11,
    "qs:name":"McKinley Woods",
    "qs:name_adm0":"United States",
    "qs:name_adm1":"Ohio",
    "qs:name_adm2":"Wood",
    "qs:name_local":"Perrysburg",
    "qs:photo_max":325,
    "qs:photo_sum":336,
    "qs:placetype":"Suburb",
    "qs:quad_count":6,
    "qs:woe_adm0":23424977,
    "qs:woe_adm1":2347594,
    "qs:woe_adm2":12589613,
    "qs:woe_lau":0,
    "qs:woe_local":2470758,
    "qs:woe_ver":"7.10.0",
    "wof:lang":[
        "eng"
    ],
    "wof:name":"McKinley Woods",
    "wof:placetype":"neighbourhood",
    "wof:population":403,
    "zs:blockids":[
        391730212001015,
        391730212001020,
        391730212001022,
        391730206023086,
        391730206023107,
        391730206023067,
        391730206023066,
        391730212001014,
        391730206023106,
        391730212001023,
        391730206023068,
        391730212001010,
        391730212001035,
        391730206023065,
        391730212001021,
        391730206023105,
        391730212001034,
        391730206023110,
        391730212001012,
        391730206023109,
        391730212002015,
        391730212002014,
        391730206023108
    ],
    "zs:housing10":268,
    "zs:pop10":403
},
  "geometry": {"coordinates":[-83.648634,41.527993],"type":"Point"}
}