{
  "type": "Feature",
  "properties": {
    "gn:admin1_code":"WV",
    "gn:admin2_code":"13",
    "gn:asciiname":"Five Forks",
    "gn:country_code":"US",
    "gn:dem":338,
    "gn:elevation":"337.0",
    "gn:feature_class":"P",
    "gn:feature_code":"PPL",
    "gn:name":"Five Forks",
    "gn:population":0,
    "gn:timezone":"America/New_York",
    "iso:country":"US",
    "wof:name":"Five Forks",
    "wof:placetype":"locality"
},
  "geometry": {"coordinates":[-81.06067,38.96925],"type":"Point"}
}