{
  "type": "Feature",
  "properties": {
    "gn:admin1_code":"UT",
    "gn:admin2_code":"35.0",
    "gn:asciiname":"Prowswood Plaza Condominium",
    "gn:country_code":"US",
    "gn:dem":1321,
    "gn:elevation":"1322.0",
    "gn:feature_class":"P",
    "gn:feature_code":"PPL",
    "gn:name":"Prowswood Plaza Condominium",
    "gn:population":0,
    "gn:timezone":"America/Denver",
    "iso:country":"US",
    "wof:name":"Prowswood Plaza Condominium",
    "wof:placetype":"locality"
},
  "geometry": {"coordinates":[-111.86327,40.66384],"type":"Point"}
}