{
  "type": "Feature",
  "properties": {
    "gn:country":"US",
    "gn:fcode":"PPL",
    "gn:population":0,
    "iso:country":"US",
    "name:cat_x_preferred":[
        "Collinsville"
    ],
    "name:ceb_x_preferred":[
        "Collinsville"
    ],
    "name:deu_x_preferred":[
        "Collinsville"
    ],
    "name:eng_x_preferred":[
        "Collinsville"
    ],
    "name:fas_x_preferred":[
        "\u06a9\u0627\u0644\u06cc\u0646\u0632\u0648\u06cc\u0644"
    ],
    "name:fra_x_preferred":[
        "Collinsville"
    ],
    "name:ita_x_preferred":[
        "Collinsville"
    ],
    "name:nld_x_preferred":[
        "Collinsville"
    ],
    "name:pol_x_preferred":[
        "Collinsville"
    ],
    "name:por_x_preferred":[
        "Collinsville"
    ],
    "name:spa_x_preferred":[
        "Collinsville"
    ],
    "name:srp_x_preferred":[
        "\u041a\u043e\u043b\u0438\u043d\u0441\u0432\u0438\u043b"
    ],
    "name:ukr_x_preferred":[
        "\u041a\u043e\u043b\u043b\u0456\u043d\u0441\u0432\u0456\u043b\u043b"
    ],
    "name:und_x_variant":[
        "Chanceford"
    ],
    "name:vol_x_preferred":[
        "Collinsville"
    ],
    "qs_pg:aaroncc":"US",
    "qs_pg:gn_country":"US",
    "qs_pg:gn_fcode":"PPL",
    "qs_pg:gn_pop":0,
    "qs_pg:name":"Collinsville",
    "qs_pg:name_adm0":"United States",
    "qs_pg:name_adm1":"Pennsylvania",
    "qs_pg:photos":97,
    "qs_pg:photos_1k":20,
    "qs_pg:photos_9k":1,
    "qs_pg:photos_9r":3,
    "qs_pg:photos_all":97,
    "qs_pg:photos_sr":3,
    "qs_pg:pop_sr":0,
    "qs_pg:qs_pg_placetype":"locality",
    "qs_pg:qs_pg_placetype_gp":"Town",
    "qs_pg:woe_adm0":23424977,
    "woe:adm0_id":23424977,
    "woe:name_adm0":"United States",
    "woe:name_adm1":"Pennsylvania",
    "woe:placetype":"Town",
    "wof:name":"Collinsville",
    "wof:placetype":"locality"
},
  "geometry": {"coordinates":[-76.4508,39.85677],"type":"Point"}
}