{
  "type": "Feature",
  "properties": {
    "gn:admin1_code":"NC",
    "gn:admin2_code":"161.0",
    "gn:admin3_code":"91892.0",
    "gn:asciiname":"Washburn",
    "gn:country_code":"US",
    "gn:dem":324,
    "gn:elevation":"317.0",
    "gn:feature_class":"P",
    "gn:feature_code":"PPL",
    "gn:name":"Washburn",
    "gn:population":0,
    "gn:timezone":"America/New_York",
    "iso:country":"US",
    "name:eng_x_preferred":[
        "Washburn"
    ],
    "name:und_x_variant":[
        "Washburns Store"
    ],
    "wof:name":"Washburn",
    "wof:placetype":"locality"
},
  "geometry": {"coordinates":[-81.81649,35.39318],"type":"Point"}
}