{
  "type": "Feature",
  "properties": {
    "gn:admin1_code":"TN",
    "gn:admin2_code":"99.0",
    "gn:asciiname":"Turkey Track",
    "gn:country_code":"US",
    "gn:dem":279,
    "gn:elevation":"276.0",
    "gn:feature_class":"P",
    "gn:feature_code":"PPL",
    "gn:name":"Turkey Track",
    "gn:population":0,
    "gn:timezone":"America/Chicago",
    "iso:country":"US",
    "wof:name":"Turkey Track",
    "wof:placetype":"locality"
},
  "geometry": {"coordinates":[-87.57391,35.3898],"type":"Point"}
}