{
  "type": "Feature",
  "properties": {
    "gn:admin1_code":"MO",
    "gn:admin2_code":"39.0",
    "gn:admin3_code":"4600.0",
    "gn:asciiname":"Tingley",
    "gn:country_code":"US",
    "gn:dem":303,
    "gn:elevation":"299.0",
    "gn:feature_class":"P",
    "gn:feature_code":"PPL",
    "gn:name":"Tingley",
    "gn:population":0,
    "gn:timezone":"America/Chicago",
    "iso:country":"US",
    "name:fra_x_preferred":[
        "Tingley"
    ],
    "name:gle_x_preferred":[
        "Tingley"
    ],
    "name:pol_x_preferred":[
        "Tingley"
    ],
    "wof:name":"Tingley",
    "wof:placetype":"locality"
},
  "geometry": {"coordinates":[-93.99911,37.66115],"type":"Point"}
}