{
  "type": "Feature",
  "properties": {
    "gn:country":"US",
    "gn:fcode":"PPL",
    "gn:population":0,
    "iso:country":"US",
    "name:cat_x_preferred":[
        "Groveton"
    ],
    "name:ceb_x_preferred":[
        "Groveton"
    ],
    "name:deu_x_preferred":[
        "Groveton"
    ],
    "name:fra_x_preferred":[
        "Groveton"
    ],
    "name:ita_x_preferred":[
        "Groveton"
    ],
    "name:nld_x_preferred":[
        "Groveton"
    ],
    "name:pol_x_preferred":[
        "Groveton"
    ],
    "name:srp_x_preferred":[
        "\u0413\u0440\u043e\u0432\u0442\u043e\u043d"
    ],
    "name:vol_x_preferred":[
        "Groveton"
    ],
    "qs_pg:aaroncc":"US",
    "qs_pg:gn_country":"US",
    "qs_pg:gn_fcode":"PPL",
    "qs_pg:gn_pop":0,
    "qs_pg:name":"Groveton",
    "qs_pg:name_adm0":"United States",
    "qs_pg:name_adm1":"Michigan",
    "qs_pg:photos":1,
    "qs_pg:photos_1k":1,
    "qs_pg:photos_9k":1,
    "qs_pg:photos_9r":1,
    "qs_pg:photos_all":1,
    "qs_pg:photos_sr":1,
    "qs_pg:pop_sr":0,
    "qs_pg:qs_pg_placetype":"locality",
    "qs_pg:qs_pg_placetype_gp":"Town",
    "qs_pg:woe_adm0":23424977,
    "woe:adm0_id":23424977,
    "woe:name_adm0":"United States",
    "woe:name_adm1":"Michigan",
    "woe:placetype":"Town",
    "wof:name":"Groveton",
    "wof:placetype":"locality"
},
  "geometry": {"coordinates":[-84.12914000000001,43.24253],"type":"Point"}
}