{
  "type": "Feature",
  "properties": {
    "gn:admin1_code":"TX",
    "gn:admin2_code":"459.0",
    "gn:asciiname":"New Mountain",
    "gn:country_code":"US",
    "gn:dem":129,
    "gn:elevation":"125.0",
    "gn:feature_class":"P",
    "gn:feature_code":"PPL",
    "gn:name":"New Mountain",
    "gn:population":0,
    "gn:timezone":"America/Chicago",
    "iso:country":"US",
    "name:ceb_x_preferred":[
        "New Mountain"
    ],
    "name:deu_x_preferred":[
        "New Mountain"
    ],
    "name:nno_x_preferred":[
        "New Mountain"
    ],
    "wof:name":"New Mountain",
    "wof:placetype":"locality"
},
  "geometry": {"coordinates":[-94.81049,32.82874],"type":"Point"}
}