{
  "type": "Feature",
  "properties": {
    "gn:admin1_code":"AL",
    "gn:admin2_code":"119.0",
    "gn:asciiname":"Sumterville",
    "gn:country_code":"US",
    "gn:dem":93,
    "gn:elevation":"90.0",
    "gn:feature_class":"P",
    "gn:feature_code":"PPL",
    "gn:name":"Sumterville",
    "gn:population":0,
    "gn:timezone":"America/Chicago",
    "iso:country":"US",
    "name:eng_x_preferred":[
        "Sumterville"
    ],
    "name:und_x_variant":[
        "Pattons Hill"
    ],
    "wof:name":"Sumterville",
    "wof:placetype":"locality"
},
  "geometry": {"coordinates":[-88.23891999999999,32.7118],"type":"Point"}
}