{
  "type": "Feature",
  "properties": {
    "gn:admin1_code":"NC",
    "gn:admin2_code":"101.0",
    "gn:admin3_code":"92500.0",
    "gn:asciiname":"Oliver",
    "gn:country_code":"US",
    "gn:dem":50,
    "gn:elevation":"50.0",
    "gn:feature_class":"P",
    "gn:feature_code":"PPL",
    "gn:name":"Oliver",
    "gn:population":0,
    "gn:timezone":"America/New_York",
    "iso:country":"US",
    "name:ara_x_preferred":[
        "\u0623\u0648\u0644\u064a\u0641\u0631"
    ],
    "name:bre_x_preferred":[
        "Oliver"
    ],
    "name:ceb_x_preferred":[
        "Oliver"
    ],
    "name:ces_x_preferred":[
        "Oliver"
    ],
    "name:deu_x_preferred":[
        "Oliver"
    ],
    "name:fra_x_preferred":[
        "Oliver"
    ],
    "name:heb_x_preferred":[
        "\u05d0\u05d5\u05dc\u05d9\u05d1\u05e8"
    ],
    "name:hye_x_preferred":[
        "\u0555\u056c\u056b\u057e\u0565\u0580"
    ],
    "name:ita_x_preferred":[
        "Oliver"
    ],
    "name:jpn_x_preferred":[
        "\u30aa\u30ea\u30f4\u30a1\u30fc"
    ],
    "name:kor_x_preferred":[
        "\uc62c\ub9ac\ubc84"
    ],
    "name:lav_x_preferred":[
        "Olivers"
    ],
    "name:nld_x_preferred":[
        "Oliver"
    ],
    "name:pol_x_preferred":[
        "Oliver"
    ],
    "name:por_x_preferred":[
        "Oliver"
    ],
    "name:rus_x_preferred":[
        "\u041e\u043b\u0438\u0432\u0435\u0440"
    ],
    "name:slv_x_preferred":[
        "Oliver"
    ],
    "name:spa_x_preferred":[
        "Oliver"
    ],
    "name:srp_x_preferred":[
        "\u041e\u043b\u0438\u0432\u0435\u0440"
    ],
    "name:swe_x_preferred":[
        "Oliver"
    ],
    "name:ukr_x_preferred":[
        "\u041e\u043b\u0456\u0432\u0435\u0440"
    ],
    "name:vie_x_preferred":[
        "Oliver"
    ],
    "name:vol_x_preferred":[
        "Oliver"
    ],
    "name:zho_x_preferred":[
        "\u5965\u5229\u5f17"
    ],
    "wof:name":"Oliver",
    "wof:placetype":"locality"
},
  "geometry": {"coordinates":[-78.25915999999999,35.49349],"type":"Point"}
}