{
  "type": "Feature",
  "properties": {
    "gn:admin1_code":"TX",
    "gn:admin2_code":"223",
    "gn:asciiname":"Hatchetville",
    "gn:country_code":"US",
    "gn:dem":157,
    "gn:elevation":"156.0",
    "gn:feature_class":"P",
    "gn:feature_code":"PPL",
    "gn:name":"Hatchetville",
    "gn:population":0,
    "gn:timezone":"America/Chicago",
    "iso:country":"US",
    "wof:name":"Hatchetville",
    "wof:placetype":"locality"
},
  "geometry": {"coordinates":[-95.52968,33.25956],"type":"Point"}
}