{
  "type": "Feature",
  "properties": {
    "gn:country":"US",
    "gn:fcode":"ADMD",
    "gn:population":0,
    "iso:country":"US",
    "name:cym_x_preferred":[
        "North Huntingdon Township"
    ],
    "name:deu_x_preferred":[
        "North Huntingdon Township"
    ],
    "name:eng_x_preferred":[
        "North Huntingdon Township"
    ],
    "name:jpn_x_preferred":[
        "\u30ce\u30fc\u30b9\u30cf\u30f3\u30c6\u30a3\u30f3\u30c9\u30f3"
    ],
    "name:jpn_x_variant":[
        "\u30ce\u30fc\u30b9\u30fb\u30cf\u30f3\u30c6\u30a3\u30f3\u30c9\u30f3\u90e1\u533a"
    ],
    "name:spa_x_preferred":[
        "Municipio de North Huntingdon"
    ],
    "name:ukr_x_preferred":[
        "\u041d\u043e\u0440\u0442-\u0413\u0430\u043d\u0442\u0456\u043d\u0433\u0434\u043e\u043d \u0422\u0430\u0443\u043d\u0448\u0438\u043f"
    ],
    "name:urd_x_preferred":[
        "\u0646\u0627\u0631\u062a\u06be \u06c1\u0646\u0679\u0646\u06af\u0688\u0646 \u0679\u0627\u0624\u0646 \u0634\u067e\u060c \u0648\u06cc\u0633\u0679\u0645\u0648\u0631\u0644\u06cc\u0646\u0688 \u06a9\u0627\u0624\u0646\u0679\u06cc\u060c \u067e\u0646\u0633\u0644\u0648\u0627\u0646\u06cc\u0627"
    ],
    "name:urd_x_variant":[
        "\u0646\u0627\u0631\u062a\u06be \u06c1\u0646\u0679\u0646\u06af\u0688\u0646 \u0679\u0627\u0624\u0646 \u0634\u067e"
    ],
    "name:vie_x_preferred":[
        "North Huntingdon"
    ],
    "name:vie_x_variant":[
        "X\u00e3 North Huntingdon"
    ],
    "name:zho_x_preferred":[
        "\u5317\u4ea8\u5ef7\u987f\u9547"
    ],
    "qs_pg:aaroncc":"US",
    "qs_pg:gn_country":"US",
    "qs_pg:gn_fcode":"ADMD",
    "qs_pg:gn_pop":0,
    "qs_pg:name":"North Huntingdon",
    "qs_pg:name_adm0":"United States",
    "qs_pg:name_adm1":"Pennsylvania",
    "qs_pg:photos":84,
    "qs_pg:photos_1k":17,
    "qs_pg:photos_9k":3,
    "qs_pg:photos_9r":6,
    "qs_pg:photos_all":773,
    "qs_pg:photos_sr":3,
    "qs_pg:pop_sr":0,
    "qs_pg:qs_pg_placetype":"locality",
    "qs_pg:qs_pg_placetype_gp":"Town",
    "qs_pg:woe_adm0":23424977,
    "woe:adm0_id":23424977,
    "woe:name_adm0":"United States",
    "woe:name_adm1":"Pennsylvania",
    "woe:placetype":"Town",
    "wof:name":"North Huntingdon",
    "wof:placetype":"locality"
},
  "geometry": {"coordinates":[-79.74142999999999,40.3834],"type":"Point"}
}