{
  "type": "Feature",
  "properties": {
    "gn:admin1_code":"IA",
    "gn:admin2_code":"15.0",
    "gn:admin3_code":"90756.0",
    "gn:asciiname":"Ericson",
    "gn:country_code":"US",
    "gn:dem":341,
    "gn:elevation":"343.0",
    "gn:feature_class":"P",
    "gn:feature_code":"PPL",
    "gn:name":"Ericson",
    "gn:population":0,
    "gn:timezone":"America/Chicago",
    "iso:country":"US",
    "wof:name":"Ericson",
    "wof:placetype":"locality"
},
  "geometry": {"coordinates":[-93.79634,42.0286],"type":"Point"}
}