{
  "type": "Feature",
  "properties": {
    "gn:admin1_code":"FL",
    "gn:admin2_code":"57",
    "gn:asciiname":"Rocky Pond",
    "gn:country_code":"US",
    "gn:dem":21,
    "gn:elevation":"14.0",
    "gn:feature_class":"P",
    "gn:feature_code":"PPL",
    "gn:name":"Rocky Pond",
    "gn:population":0,
    "gn:timezone":"America/New_York",
    "iso:country":"US",
    "wof:name":"Rocky Pond",
    "wof:placetype":"locality"
},
  "geometry": {"coordinates":[-82.5534,28.1079],"type":"Point"}
}