{
  "type": "Feature",
  "properties": {
    "gn:admin1_code":"IL",
    "gn:admin2_code":"17",
    "gn:admin3_code":"57550.0",
    "gn:asciiname":"Anderson",
    "gn:country_code":"US",
    "gn:dem":186,
    "gn:elevation":"187.0",
    "gn:feature_class":"P",
    "gn:feature_code":"PPL",
    "gn:name":"Anderson",
    "gn:population":0,
    "gn:timezone":"America/Chicago",
    "iso:country":"US",
    "name:ara_x_preferred":[
        "\u0623\u0646\u062f\u0631\u0633\u0648\u0646"
    ],
    "name:ben_x_preferred":[
        "\u0986\u09a8\u09cd\u09a1\u09be\u09b0\u09b8\u09a8"
    ],
    "name:ell_x_preferred":[
        "\u0386\u03bd\u03c4\u03b5\u03c1\u03c3\u03bf\u03bd"
    ],
    "name:fas_x_preferred":[
        "\u0627\u0646\u062f\u0631\u0633\u0648\u0646"
    ],
    "name:heb_x_preferred":[
        "\u05d0\u05e0\u05d3\u05e8\u05e1\u05d5\u05df"
    ],
    "name:hin_x_preferred":[
        "\u090f\u0902\u0921\u0930\u0938\u0928"
    ],
    "name:hun_x_preferred":[
        "Anderson"
    ],
    "name:ind_x_preferred":[
        "Anderson"
    ],
    "name:kor_x_preferred":[
        "\uc564\ub354\uc2a8"
    ],
    "name:pol_x_preferred":[
        "Anderson"
    ],
    "name:por_x_preferred":[
        "Anderson"
    ],
    "name:spa_x_preferred":[
        "Anderson"
    ],
    "name:tur_x_preferred":[
        "Anderson"
    ],
    "name:ukr_x_preferred":[
        "\u0410\u043d\u0434\u0435\u0440\u0441\u043e\u043d"
    ],
    "name:urd_x_preferred":[
        "\u0627\u06cc\u0646\u0688\u0631\u0633\u0646"
    ],
    "name:vie_x_preferred":[
        "S\u00f4ng Anderson"
    ],
    "wof:name":"Anderson",
    "wof:placetype":"locality"
},
  "geometry": {"coordinates":[-90.15900999999999,39.98227],"type":"Point"}
}