{
  "type": "Feature",
  "properties": {
    "gn:admin1_code":"IL",
    "gn:admin2_code":"17",
    "gn:admin3_code":"57550.0",
    "gn:asciiname":"Anderson",
    "gn:country_code":"US",
    "gn:dem":186,
    "gn:elevation":"187.0",
    "gn:feature_class":"P",
    "gn:feature_code":"PPL",
    "gn:name":"Anderson",
    "gn:population":0,
    "gn:timezone":"America/Chicago",
    "iso:country":"US",
    "name:fas_x_preferred":[
        "\u0627\u0646\u062f\u0631\u0633\u0648\u0646"
    ],
    "name:urd_x_preferred":[
        "\u0627\u06cc\u0646\u0688\u0631\u0633\u0646"
    ],
    "wof:name":"Anderson",
    "wof:placetype":"locality"
},
  "geometry": {"coordinates":[-90.15900999999999,39.98227],"type":"Point"}
}