{
  "type": "Feature",
  "properties": {
    "gn:admin1_code":"IN",
    "gn:admin2_code":"89",
    "gn:admin3_code":"34132.0",
    "gn:asciiname":"Mansard Du Lac",
    "gn:country_code":"US",
    "gn:dem":188,
    "gn:elevation":"200.0",
    "gn:feature_class":"P",
    "gn:feature_code":"PPL",
    "gn:name":"Mansard Du Lac",
    "gn:population":0,
    "gn:timezone":"America/Chicago",
    "iso:country":"US",
    "wof:name":"Mansard Du Lac",
    "wof:placetype":"locality"
},
  "geometry": {"coordinates":[-87.25471999999998,41.59278],"type":"Point"}
}