{
  "type": "Feature",
  "properties": {
    "gn:admin1_code":"VA",
    "gn:admin2_code":"161",
    "gn:asciiname":"Roanoke Red Sulphur Springs",
    "gn:country_code":"US",
    "gn:dem":573,
    "gn:elevation":"566.0",
    "gn:feature_class":"P",
    "gn:feature_code":"PPL",
    "gn:name":"Roanoke Red Sulphur Springs",
    "gn:population":0,
    "gn:timezone":"America/New_York",
    "iso:country":"US",
    "name:eng_x_preferred":[
        "Roanoke Red Sulphur Springs"
    ],
    "name:und_x_variant":[
        "Red Sulphur Springs",
        "Red Sulphur Spring"
    ],
    "wof:name":"Roanoke Red Sulphur Springs",
    "wof:placetype":"locality"
},
  "geometry": {"coordinates":[-80.10893,37.39235],"type":"Point"}
}