{
  "type": "Feature",
  "properties": {
    "gn:admin1_code":"IN",
    "gn:admin2_code":"161.0",
    "gn:admin3_code":"31522.0",
    "gn:asciiname":"Quakertown",
    "gn:country_code":"US",
    "gn:dem":229,
    "gn:elevation":"229.0",
    "gn:feature_class":"P",
    "gn:feature_code":"PPL",
    "gn:name":"Quakertown",
    "gn:population":0,
    "gn:timezone":"America/Indiana/Indianapolis",
    "iso:country":"US",
    "name:deu_x_preferred":[
        "Quakertown"
    ],
    "name:eng_x_preferred":[
        "Quakertown"
    ],
    "name:und_x_variant":[
        "Millboro"
    ],
    "wof:name":"Quakertown",
    "wof:placetype":"locality"
},
  "geometry": {"coordinates":[-85.00163000000001,39.58005],"type":"Point"}
}