{
  "type": "Feature",
  "properties": {
    "gn:admin1_code":"GA",
    "gn:admin2_code":"223.0",
    "gn:asciiname":"Brooks Estates",
    "gn:country_code":"US",
    "gn:dem":342,
    "gn:elevation":"330.0",
    "gn:feature_class":"P",
    "gn:feature_code":"PPL",
    "gn:name":"Brooks Estates",
    "gn:population":0,
    "gn:timezone":"America/New_York",
    "iso:country":"US",
    "wof:name":"Brooks Estates",
    "wof:placetype":"locality"
},
  "geometry": {"coordinates":[-84.75549000000002,33.93288],"type":"Point"}
}