{
  "type": "Feature",
  "properties": {
    "gn:admin1_code":"MD",
    "gn:admin2_code":"31.0",
    "gn:asciiname":"Capitol View Park",
    "gn:country_code":"US",
    "gn:dem":123,
    "gn:elevation":"119.0",
    "gn:feature_class":"P",
    "gn:feature_code":"PPL",
    "gn:name":"Capitol View Park",
    "gn:population":0,
    "gn:timezone":"America/New_York",
    "iso:country":"US",
    "name:eng_x_preferred":[
        "Capitol View Park"
    ],
    "name:und_x_variant":[
        "Capitol View"
    ],
    "wof:name":"Capitol View Park",
    "wof:placetype":"locality"
},
  "geometry": {"coordinates":[-77.06053,39.02233],"type":"Point"}
}