{
  "type": "Feature",
  "properties": {
    "gn:admin1_code":"NC",
    "gn:admin2_code":"101.0",
    "gn:admin3_code":"90992.0",
    "gn:asciiname":"Spilona",
    "gn:country_code":"US",
    "gn:dem":71,
    "gn:elevation":"68.0",
    "gn:feature_class":"P",
    "gn:feature_code":"PPL",
    "gn:name":"Spilona",
    "gn:population":0,
    "gn:timezone":"America/New_York",
    "iso:country":"US",
    "wof:name":"Spilona",
    "wof:placetype":"locality"
},
  "geometry": {"coordinates":[-78.47195000000001,35.48849000000001],"type":"Point"}
}