{
  "type": "Feature",
  "properties": {
    "iso:country":"US",
    "name:eng_x_preferred":[
        "Hickory Creek Meadows"
    ],
    "wof:name":"Hickory Creek Meadows",
    "wof:placetype":"neighbourhood",
    "wof:population":71,
    "zs:area_m":17308.96263,
    "zs:blockids":[
        481130172013008
    ],
    "zs:housing10":22,
    "zs:label":"Hickory Creek Meadows",
    "zs:pop10":71
},
  "geometry": {"coordinates":[-96.624228,32.740798],"type":"Point"}
}