{
  "type": "Feature",
  "properties": {
    "gn:admin1_code":"PA",
    "gn:admin2_code":"15.0",
    "gn:admin3_code":"86664.0",
    "gn:asciiname":"Homets Ferry",
    "gn:country_code":"US",
    "gn:dem":220,
    "gn:elevation":"217.0",
    "gn:feature_class":"P",
    "gn:feature_code":"PPL",
    "gn:name":"Homets Ferry",
    "gn:population":0,
    "gn:timezone":"America/New_York",
    "iso:country":"US",
    "name:eng_x_preferred":[
        "Homets Ferry"
    ],
    "name:und_x_variant":[
        "Hornets Ferry"
    ],
    "wof:name":"Homets Ferry",
    "wof:placetype":"locality"
},
  "geometry": {"coordinates":[-76.32271,41.69896],"type":"Point"}
}