{
  "type": "Feature",
  "properties": {
    "gn:admin1_code":"PA",
    "gn:admin2_code":"39.0",
    "gn:admin3_code":"80000.0",
    "gn:asciiname":"Watson Run",
    "gn:country_code":"US",
    "gn:dem":332,
    "gn:elevation":"330.0",
    "gn:feature_class":"P",
    "gn:feature_code":"PPL",
    "gn:name":"Watson Run",
    "gn:population":0,
    "gn:timezone":"America/New_York",
    "iso:country":"US",
    "wof:name":"Watson Run",
    "wof:placetype":"locality"
},
  "geometry": {"coordinates":[-80.21701,41.58978],"type":"Point"}
}