{
  "type": "Feature",
  "properties": {
    "gn:admin1_code":"FL",
    "gn:admin2_code":"11.0",
    "gn:asciiname":"College Park",
    "gn:country_code":"US",
    "gn:dem":4,
    "gn:elevation":"2.0",
    "gn:feature_class":"P",
    "gn:feature_code":"PPL",
    "gn:name":"College Park",
    "gn:population":0,
    "gn:timezone":"America/New_York",
    "iso:country":"US",
    "name:ceb_x_preferred":[
        "College Park"
    ],
    "name:ces_x_preferred":[
        "College Park"
    ],
    "name:deu_x_preferred":[
        "College Park"
    ],
    "name:fra_x_preferred":[
        "College Park"
    ],
    "name:ita_x_preferred":[
        "College Park"
    ],
    "name:kor_x_preferred":[
        "\uce7c\ub9ac\uc9c0\ud30c\ud06c"
    ],
    "name:nld_x_preferred":[
        "College Park"
    ],
    "name:pol_x_preferred":[
        "College Park"
    ],
    "name:por_x_preferred":[
        "College Park"
    ],
    "name:rus_x_preferred":[
        "\u041a\u043e\u043b\u043b\u0435\u0434\u0436-\u041f\u0430\u0440\u043a"
    ],
    "name:sco_x_preferred":[
        "College Park"
    ],
    "name:spa_x_preferred":[
        "College Park"
    ],
    "name:srp_x_preferred":[
        "\u041a\u043e\u043b\u0435\u045f \u041f\u0430\u0440\u043a"
    ],
    "name:swa_x_preferred":[
        "College Park"
    ],
    "name:swe_x_preferred":[
        "College Park"
    ],
    "name:ukr_x_preferred":[
        "\u041a\u043e\u043b\u043b\u0435\u0434\u0436-\u041f\u0430\u0440\u043a"
    ],
    "name:vol_x_preferred":[
        "College Park"
    ],
    "wof:name":"College Park",
    "wof:placetype":"locality"
},
  "geometry": {"coordinates":[-80.10615,26.32452],"type":"Point"}
}