{
  "type": "Feature",
  "properties": {
    "gn:admin1_code":"AL",
    "gn:admin2_code":"55",
    "gn:asciiname":"Keener",
    "gn:country_code":"US",
    "gn:dem":209,
    "gn:elevation":"206.0",
    "gn:feature_class":"P",
    "gn:feature_code":"PPL",
    "gn:name":"Keener",
    "gn:population":0,
    "gn:timezone":"America/Chicago",
    "iso:country":"US",
    "name:fra_x_preferred":[
        "Keener"
    ],
    "name:nld_x_preferred":[
        "Keener"
    ],
    "name:pol_x_preferred":[
        "Keener"
    ],
    "name:por_x_preferred":[
        "Keener"
    ],
    "wof:name":"Keener",
    "wof:placetype":"locality"
},
  "geometry": {"coordinates":[-85.95108,34.15620999999999],"type":"Point"}
}