{
  "type": "Feature",
  "properties": {
    "gn:admin1_code":"AR",
    "gn:admin2_code":"109.0",
    "gn:admin3_code":"90810.0",
    "gn:asciiname":"Caney Valley",
    "gn:country_code":"US",
    "gn:dem":179,
    "gn:elevation":"171.0",
    "gn:feature_class":"P",
    "gn:feature_code":"PPL",
    "gn:name":"Caney Valley",
    "gn:population":0,
    "gn:timezone":"America/Chicago",
    "iso:country":"US",
    "name:eng_x_preferred":[
        "Caney Valley"
    ],
    "name:und_x_variant":[
        "Pine Land",
        "Pineland"
    ],
    "wof:name":"Caney Valley",
    "wof:placetype":"locality"
},
  "geometry": {"coordinates":[-93.53991000000001,34.26232],"type":"Point"}
}