{
  "type": "Feature",
  "properties": {
    "gn:admin1_code":"AR",
    "gn:admin2_code":"5.0",
    "gn:admin3_code":"92709.0",
    "gn:asciiname":"Old Joe",
    "gn:country_code":"US",
    "gn:dem":215,
    "gn:elevation":"215.0",
    "gn:feature_class":"P",
    "gn:feature_code":"PPL",
    "gn:name":"Old Joe",
    "gn:population":0,
    "gn:timezone":"America/Chicago",
    "iso:country":"US",
    "wof:name":"Old Joe",
    "wof:placetype":"locality"
},
  "geometry": {"coordinates":[-92.23154,36.17451],"type":"Point"}
}