{
  "type": "Feature",
  "properties": {
    "gn:admin1_code":"MD",
    "gn:admin2_code":"37.0",
    "gn:asciiname":"Redgate",
    "gn:country_code":"US",
    "gn:dem":33,
    "gn:elevation":"31.0",
    "gn:feature_class":"P",
    "gn:feature_code":"PPL",
    "gn:name":"Redgate",
    "gn:population":0,
    "gn:timezone":"America/New_York",
    "iso:country":"US",
    "name:heb_x_preferred":[
        "\u05e8\u05d3\u05d2\u05d9\u05d9\u05d8"
    ],
    "wof:name":"Redgate",
    "wof:placetype":"locality"
},
  "geometry": {"coordinates":[-76.59857,38.25652],"type":"Point"}
}