{
  "type": "Feature",
  "properties": {
    "gn:admin1_code":"VA",
    "gn:admin2_code":"810",
    "gn:asciiname":"Birchwood-Gardens",
    "gn:country_code":"US",
    "gn:dem":8,
    "gn:elevation":"4.0",
    "gn:feature_class":"P",
    "gn:feature_code":"PPL",
    "gn:name":"Birchwood-Gardens",
    "gn:population":0,
    "gn:timezone":"America/New_York",
    "iso:country":"US",
    "wof:name":"Birchwood-Gardens",
    "wof:placetype":"locality"
},
  "geometry": {"coordinates":[-76.10493000000002,36.8457],"type":"Point"}
}