{
  "type": "Feature",
  "properties": {
    "gn:admin1_code":"AL",
    "gn:admin2_code":"97.0",
    "gn:asciiname":"Salco",
    "gn:country_code":"US",
    "gn:dem":20,
    "gn:elevation":"13.0",
    "gn:feature_class":"P",
    "gn:feature_code":"PPL",
    "gn:name":"Salco",
    "gn:population":0,
    "gn:timezone":"America/Chicago",
    "iso:country":"US",
    "wof:name":"Salco",
    "wof:placetype":"locality"
},
  "geometry": {"coordinates":[-88.03471999999999,30.96685],"type":"Point"}
}