{
  "type": "Feature",
  "properties": {
    "gn:admin1_code":"SC",
    "gn:admin2_code":"79.0",
    "gn:asciiname":"Padgett Acres",
    "gn:country_code":"US",
    "gn:dem":100,
    "gn:elevation":"93.0",
    "gn:feature_class":"P",
    "gn:feature_code":"PPL",
    "gn:name":"Padgett Acres",
    "gn:population":0,
    "gn:timezone":"America/New_York",
    "iso:country":"US",
    "wof:name":"Padgett Acres",
    "wof:placetype":"locality"
},
  "geometry": {"coordinates":[-80.88120000000001,33.98015],"type":"Point"}
}