{
  "type": "Feature",
  "properties": {
    "gn:country":"US",
    "gn:fcode":"PPL",
    "gn:population":0,
    "iso:country":"US",
    "name:cat_x_preferred":[
        "Jewett"
    ],
    "name:ceb_x_preferred":[
        "Jewett"
    ],
    "name:deu_x_preferred":[
        "Jewett"
    ],
    "name:ita_x_preferred":[
        "Jewett"
    ],
    "name:nld_x_preferred":[
        "Jewett"
    ],
    "name:pol_x_preferred":[
        "Jewett"
    ],
    "name:srp_x_preferred":[
        "\u040f\u0443\u0435\u0442"
    ],
    "name:ukr_x_preferred":[
        "\u0414\u0436\u044e\u0435\u0442\u0442"
    ],
    "name:vol_x_preferred":[
        "Jewett"
    ],
    "qs_pg:aaroncc":"US",
    "qs_pg:gn_country":"US",
    "qs_pg:gn_fcode":"PPL",
    "qs_pg:gn_pop":0,
    "qs_pg:name":"Jewett",
    "qs_pg:name_adm0":"United States",
    "qs_pg:name_adm1":"Maine",
    "qs_pg:photos":1,
    "qs_pg:photos_1k":1,
    "qs_pg:photos_9k":1,
    "qs_pg:photos_9r":1,
    "qs_pg:photos_all":1,
    "qs_pg:photos_sr":1,
    "qs_pg:pop_sr":0,
    "qs_pg:qs_pg_placetype":"neighbourhood",
    "qs_pg:qs_pg_placetype_gp":"Suburb",
    "qs_pg:woe_adm0":23424977,
    "woe:adm0_id":23424977,
    "woe:name_adm0":"United States",
    "woe:name_adm1":"Maine",
    "woe:placetype":"Suburb",
    "wof:name":"Jewett",
    "wof:placetype":"neighbourhood"
},
  "geometry": {"coordinates":[-70.7895,43.21231],"type":"Point"}
}