{
  "type": "Feature",
  "properties": {
    "iso:country":"US",
    "name:eng_x_preferred":[
        "60th Ave. Villa Maria Residents"
    ],
    "wof:name":"60th Ave. Villa Maria Residents",
    "wof:placetype":"neighbourhood",
    "wof:population":2469,
    "zs:area_m":1697689.839596,
    "zs:blockids":[
        40136180002014,
        40136180002005,
        40136180002003,
        40136180002008,
        40136159003012,
        40136160001018,
        40136180002018,
        40136180002011,
        40136159003011,
        40136159003009,
        40136179001021,
        40136179002003,
        40136180002019,
        40136180002001,
        40136159003014,
        40136159003013,
        40136178001000,
        40136179002009,
        40136180002012,
        40136159003008,
        40136179002000,
        40136180002002,
        40136179002005,
        40136179002002,
        40136180002004,
        40136179002006,
        40136179002001,
        40136179001002,
        40136179001004,
        40136180002007,
        40136159003015,
        40136178001001,
        40136179001009,
        40136179002007,
        40136179002004,
        40136179001022,
        40136179001005,
        40136179002008,
        40136180002013,
        40136180002006,
        40136159003010
    ],
    "zs:housing10":899,
    "zs:label":"60th Ave. Villa Maria Residents",
    "zs:pop10":2469
},
  "geometry": {"coordinates":[-112.18648,33.651986],"type":"Point"}
}