{
  "type": "Feature",
  "properties": {
    "gn:admin1_code":"MD",
    "gn:admin2_code":"33.0",
    "gn:asciiname":"Brandywine Forest",
    "gn:country_code":"US",
    "gn:dem":77,
    "gn:elevation":"68.0",
    "gn:feature_class":"P",
    "gn:feature_code":"PPL",
    "gn:name":"Brandywine Forest",
    "gn:population":0,
    "gn:timezone":"America/New_York",
    "iso:country":"US",
    "wof:name":"Brandywine Forest",
    "wof:placetype":"locality"
},
  "geometry": {"coordinates":[-76.84135999999999,38.69901],"type":"Point"}
}