{
  "type": "Feature",
  "properties": {
    "iso:country":"US",
    "name:bul_x_preferred":[
        "\u041d\u043e\u0440\u0442 \u0448\u043e\u0440"
    ],
    "name:ceb_x_preferred":[
        "North Shore"
    ],
    "name:deu_x_preferred":[
        "North Shore"
    ],
    "name:eng_x_preferred":[
        "North Shore"
    ],
    "name:fra_x_preferred":[
        "North Shore"
    ],
    "name:heb_x_preferred":[
        "\u05e0\u05d5\u05e8\u05ea' \u05e9\u05d5\u05e8"
    ],
    "name:ita_x_preferred":[
        "North Shore"
    ],
    "name:jpn_x_preferred":[
        "\u30ce\u30fc\u30b9\u30b7\u30e7\u30a2"
    ],
    "name:kor_x_preferred":[
        "\ub178\uc2a4\uc1fc\uc5b4"
    ],
    "name:mlg_x_preferred":[
        "North Shore"
    ],
    "name:pol_x_preferred":[
        "North Shore"
    ],
    "name:por_x_preferred":[
        "North Shore"
    ],
    "name:slk_x_preferred":[
        "North Shore"
    ],
    "name:spa_x_preferred":[
        "North Shore"
    ],
    "name:srp_x_preferred":[
        "\u041d\u043e\u0440\u0442 \u0428\u043e\u0440"
    ],
    "name:swe_x_preferred":[
        "North Shore"
    ],
    "name:ukr_x_preferred":[
        "\u041d\u043e\u0440\u0442-\u0428\u043e\u0440"
    ],
    "name:vol_x_preferred":[
        "North Shore"
    ],
    "wof:name":"North Shore",
    "wof:placetype":"neighbourhood",
    "wof:population":301,
    "zs:area_m":1089515.286337,
    "zs:blockids":[
        460299545023004,
        460299545023003
    ],
    "zs:housing10":209,
    "zs:label":"North Shore",
    "zs:pop10":301
},
  "geometry": {"coordinates":[-97.238708,44.918721],"type":"Point"}
}