{
  "type": "Feature",
  "properties": {
    "gn:admin1_code":"IN",
    "gn:admin2_code":"91.0",
    "gn:admin3_code":"26224.0",
    "gn:asciiname":"Birchim",
    "gn:country_code":"US",
    "gn:dem":251,
    "gn:elevation":"251.0",
    "gn:feature_class":"P",
    "gn:feature_code":"PPL",
    "gn:name":"Birchim",
    "gn:population":0,
    "gn:timezone":"America/Chicago",
    "iso:country":"US",
    "wof:name":"Birchim",
    "wof:placetype":"locality"
},
  "geometry": {"coordinates":[-86.6028,41.71032],"type":"Point"}
}