{
  "type": "Feature",
  "properties": {
    "gn:admin1_code":"WY",
    "gn:admin2_code":"37.0",
    "gn:asciiname":"Quealy",
    "gn:country_code":"US",
    "gn:dem":1949,
    "gn:elevation":"1947.0",
    "gn:feature_class":"P",
    "gn:feature_code":"PPL",
    "gn:name":"Quealy",
    "gn:population":0,
    "gn:timezone":"America/Denver",
    "iso:country":"US",
    "name:eng_x_preferred":[
        "Quealy"
    ],
    "name:und_x_variant":[
        "Sweetwater",
        "Sweetwater Queally"
    ],
    "wof:name":"Quealy",
    "wof:placetype":"locality"
},
  "geometry": {"coordinates":[-109.22263,41.5383],"type":"Point"}
}