{
  "type": "Feature",
  "properties": {
    "iso:country":"US",
    "name:eng_x_preferred":[
        "Keys at Harbour Island"
    ],
    "wof:name":"Keys at Harbour Island",
    "wof:placetype":"neighbourhood",
    "wof:population":576,
    "zs:area_m":158600.489348,
    "zs:blockids":[
        120570051021012,
        120570051021007,
        120570051021002,
        120570051021009,
        120570051021006,
        120570051021005
    ],
    "zs:housing10":330,
    "zs:label":"Keys at Harbour Island",
    "zs:pop10":576
},
  "geometry": {"coordinates":[-82.44905,27.933496],"type":"Point"}
}