{
  "type": "Feature",
  "properties": {
    "gn:admin1_code":"AL",
    "gn:admin2_code":"111",
    "gn:asciiname":"Forester Chapel",
    "gn:country_code":"US",
    "gn:dem":287,
    "gn:elevation":"288.0",
    "gn:feature_class":"P",
    "gn:feature_code":"PPL",
    "gn:name":"Forester Chapel",
    "gn:population":0,
    "gn:timezone":"America/Chicago",
    "iso:country":"US",
    "wof:name":"Forester Chapel",
    "wof:placetype":"locality"
},
  "geometry": {"coordinates":[-85.53884000000002,33.16123],"type":"Point"}
}