{
  "type": "Feature",
  "properties": {
    "iso:country":"US",
    "name:ceb_x_preferred":[
        "Iron Gate"
    ],
    "name:eng_x_preferred":[
        "Iron Gate"
    ],
    "name:rus_x_preferred":[
        "\u0416\u0435\u043b\u0435\u0437\u043d\u044b\u0435 \u0432\u043e\u0440\u043e\u0442\u0430"
    ],
    "name:ukr_x_preferred":[
        "\u0417\u0430\u043b\u0456\u0437\u043d\u0456 \u0412\u043e\u0440\u043e\u0442\u0430"
    ],
    "wd:wordcount":119,
    "wof:name":"Iron Gate",
    "wof:placetype":"neighbourhood",
    "wof:population":121,
    "zs:area_m":1302785.304347,
    "zs:blockids":[
        371830534171020,
        371830534171021
    ],
    "zs:housing10":43,
    "zs:label":"Iron Gate",
    "zs:pop10":121
},
  "geometry": {"coordinates":[-78.888716,35.69677],"type":"Point"}
}