{
  "type": "Feature",
  "properties": {
    "iso:country":"US",
    "name:ceb_x_preferred":[
        "Southside"
    ],
    "name:deu_x_preferred":[
        "Southside"
    ],
    "name:eng_x_preferred":[
        "Southside"
    ],
    "name:ita_x_preferred":[
        "Southside"
    ],
    "name:kor_x_preferred":[
        "\uc0ac\uc6b0\uc2a4\uc0ac\uc774\ub4dc"
    ],
    "name:nld_x_preferred":[
        "Southside"
    ],
    "name:pol_x_preferred":[
        "Southside"
    ],
    "name:por_x_preferred":[
        "Southside"
    ],
    "name:swe_x_preferred":[
        "Southside"
    ],
    "name:ukr_x_preferred":[
        "\u0421\u0430\u0443\u0442\u0441\u0430\u0439\u0434"
    ],
    "qs:gn_adm0_cc":"US",
    "qs:gn_fcode":"PPL",
    "qs:gn_local":4469146,
    "qs:gn_nam_loc":"Greensboro, Guilford, North Carolina, US",
    "qs:gn_namadm1":"NC",
    "qs:gn_name":"South Side",
    "qs:local_max":6528,
    "qs:local_sum":32173,
    "qs:localhoods":58,
    "qs:name":"Southside",
    "qs:name_adm0":"United States",
    "qs:name_adm1":"North Carolina",
    "qs:name_adm2":"Guilford",
    "qs:name_local":"Greensboro",
    "qs:photo_max":2680,
    "qs:photo_sum":3829,
    "qs:placetype":"Suburb",
    "qs:quad_count":19,
    "qs:woe_adm0":23424977,
    "qs:woe_adm1":2347592,
    "qs:woe_adm2":12589414,
    "qs:woe_lau":0,
    "qs:woe_local":2414469,
    "qs:woe_ver":"7.10.0",
    "wd:wordcount":228,
    "wof:lang":[
        "eng"
    ],
    "wof:name":"Southside",
    "wof:placetype":"neighbourhood",
    "wof:population":1161,
    "zs:blockids":[
        370810113001000,
        370810112001015,
        370810108002062,
        370810108002092,
        370810112003008,
        370810112003009,
        370810112001017,
        370810108002088,
        370810110002024,
        370810112001028,
        370810108002076,
        370810108002083,
        370810112001019,
        370810112001016,
        370810112001018,
        370810113001006,
        370810112004010,
        370810108002066,
        370810108002089,
        370810108002085,
        370810112003011,
        370810112001014,
        370810113001001,
        370810108002061,
        370810108002081,
        370810108002084,
        370810112001027,
        370810112001025,
        370810112001023,
        370810112001021,
        370810108002093,
        370810112001024,
        370810112001013,
        370810113001002,
        370810108002090,
        370810112001026,
        370810112001020,
        370810108002086,
        370810112004018,
        370810112001012,
        370810108002070,
        370810108002087,
        370810112001022,
        370810108002064,
        370810108002091,
        370810108002082,
        370810112004011,
        370810112003007
    ],
    "zs:housing10":679,
    "zs:pop10":1161
},
  "geometry": {"coordinates":[-79.790447,36.067877],"type":"Point"}
}