{
  "type": "Feature",
  "properties": {
    "gn:country":"US",
    "gn:elevation":250,
    "gn:fcode":"PPL",
    "gn:population":0,
    "iso:country":"US",
    "name:deu_x_preferred":[
        "Fairview Heights"
    ],
    "name:eng_x_preferred":[
        "Fairview Heights"
    ],
    "name:eng_x_variant":[
        "Fairview Hts"
    ],
    "name:und_x_variant":[
        "Fairview"
    ],
    "qs_pg:aaroncc":"US",
    "qs_pg:gn_country":"US",
    "qs_pg:gn_fcode":"PPL",
    "qs_pg:gn_pop":0,
    "qs_pg:name":"Fairview Heights",
    "qs_pg:name_adm0":"United States",
    "qs_pg:name_adm1":"Virginia",
    "qs_pg:photos":50,
    "qs_pg:photos_1k":10,
    "qs_pg:photos_9k":1,
    "qs_pg:photos_9r":2,
    "qs_pg:photos_all":50,
    "qs_pg:photos_sr":2,
    "qs_pg:pop_sr":0,
    "qs_pg:qs_pg_placetype":"neighbourhood",
    "qs_pg:qs_pg_placetype_gp":"Suburb",
    "qs_pg:woe_adm0":23424977,
    "woe:adm0_id":23424977,
    "woe:name_adm0":"United States",
    "woe:name_adm1":"Virginia",
    "woe:placetype":"Suburb",
    "wof:name":"Fairview Heights",
    "wof:placetype":"neighbourhood",
    "wof:population":2823
},
  "geometry": {"coordinates":[-79.14558,37.38792],"type":"Point"}
}