{
  "type": "Feature",
  "properties": {
    "gn:admin1_code":"OH",
    "gn:admin2_code":"115",
    "gn:admin3_code":"78484.0",
    "gn:asciiname":"Morganville",
    "gn:country_code":"US",
    "gn:dem":270,
    "gn:elevation":"269.0",
    "gn:feature_class":"P",
    "gn:feature_code":"PPL",
    "gn:name":"Morganville",
    "gn:population":0,
    "gn:timezone":"America/New_York",
    "iso:country":"US",
    "name:ceb_x_preferred":[
        "Morganville"
    ],
    "name:deu_x_preferred":[
        "Morganville"
    ],
    "name:eng_x_preferred":[
        "Morganville"
    ],
    "name:ita_x_preferred":[
        "Morganville"
    ],
    "name:nld_x_preferred":[
        "Morganville"
    ],
    "name:pol_x_preferred":[
        "Morganville"
    ],
    "name:por_x_preferred":[
        "Morganville"
    ],
    "name:spa_x_preferred":[
        "Morganville"
    ],
    "name:srp_x_preferred":[
        "\u041c\u043e\u0440\u0433\u0430\u043d\u0432\u0438\u043b"
    ],
    "name:und_x_variant":[
        "Morgansville",
        "Morgan",
        "Wolf Creek"
    ],
    "name:vol_x_preferred":[
        "Morganville"
    ],
    "wof:name":"Morganville",
    "wof:placetype":"locality"
},
  "geometry": {"coordinates":[-81.95458000000001,39.63229000000001],"type":"Point"}
}