{
  "type": "Feature",
  "properties": {
    "gn:admin1_code":"PA",
    "gn:admin2_code":"133.0",
    "gn:admin3_code":"35704.0",
    "gn:asciiname":"Anstine",
    "gn:country_code":"US",
    "gn:dem":267,
    "gn:elevation":"262.0",
    "gn:feature_class":"P",
    "gn:feature_code":"PPL",
    "gn:name":"Anstine",
    "gn:population":0,
    "gn:timezone":"America/New_York",
    "iso:country":"US",
    "wof:name":"Anstine",
    "wof:placetype":"locality"
},
  "geometry": {"coordinates":[-76.63497,39.75427],"type":"Point"}
}