{
  "type": "Feature",
  "properties": {
    "gn:admin1_code":"VA",
    "gn:admin2_code":"177",
    "gn:asciiname":"Granite Springs",
    "gn:country_code":"US",
    "gn:dem":132,
    "gn:elevation":"131.0",
    "gn:feature_class":"P",
    "gn:feature_code":"PPL",
    "gn:name":"Granite Springs",
    "gn:population":0,
    "gn:timezone":"America/New_York",
    "iso:country":"US",
    "wof:name":"Granite Springs",
    "wof:placetype":"locality"
},
  "geometry": {"coordinates":[-77.85444,38.18847],"type":"Point"}
}