{
  "type": "Feature",
  "properties": {
    "iso:country":"US",
    "name:ceb_x_preferred":[
        "Briar Creek"
    ],
    "name:eng_x_preferred":[
        "Briar Creek"
    ],
    "name:pol_x_preferred":[
        "Briar Creek"
    ],
    "wof:name":"Briar Creek",
    "wof:placetype":"neighbourhood",
    "wof:population":852
},
  "geometry": {"coordinates":[-93.57802047651808,41.75620013044644],"type":"Point"}
}