{
  "type": "Feature",
  "properties": {
    "gn:admin1_code":"MI",
    "gn:admin2_code":"159.0",
    "gn:admin3_code":"63000.0",
    "gn:asciiname":"Devan Mobile Home Park",
    "gn:country_code":"US",
    "gn:dem":231,
    "gn:elevation":"230.0",
    "gn:feature_class":"P",
    "gn:feature_code":"PPL",
    "gn:name":"Devan Mobile Home Park",
    "gn:population":0,
    "gn:timezone":"America/Detroit",
    "iso:country":"US",
    "wof:name":"Devan Mobile Home Park",
    "wof:placetype":"campus"
},
  "geometry": {"coordinates":[-85.87860999999999,42.20389],"type":"Point"}
}