{
  "type": "Feature",
  "properties": {
    "gn:admin1_code":"WV",
    "gn:admin2_code":"97",
    "gn:asciiname":"Holly Grove",
    "gn:country_code":"US",
    "gn:dem":532,
    "gn:elevation":"527.0",
    "gn:feature_class":"P",
    "gn:feature_code":"PPL",
    "gn:name":"Holly Grove",
    "gn:population":0,
    "gn:timezone":"America/New_York",
    "iso:country":"US",
    "name:eng_x_preferred":[
        "Holly Grove"
    ],
    "name:und_x_variant":[
        "Hollygrove"
    ],
    "wof:name":"Holly Grove",
    "wof:placetype":"locality"
},
  "geometry": {"coordinates":[-80.28953,38.80205],"type":"Point"}
}