{
  "type": "Feature",
  "properties": {
    "gn:admin1_code":"FL",
    "gn:admin2_code":"55.0",
    "gn:asciiname":"Valencia Family Mobile Home Park",
    "gn:country_code":"US",
    "gn:dem":39,
    "gn:elevation":"37.0",
    "gn:feature_class":"P",
    "gn:feature_code":"PPL",
    "gn:name":"Valencia Family Mobile Home Park",
    "gn:population":0,
    "gn:timezone":"America/New_York",
    "iso:country":"US",
    "wof:name":"Valencia Family Mobile Home Park",
    "wof:placetype":"campus"
},
  "geometry": {"coordinates":[-81.42846999999998,27.4803],"type":"Point"}
}