{
  "type": "Feature",
  "properties": {
    "gn:admin1_code":"MD",
    "gn:admin2_code":"3.0",
    "gn:asciiname":"Whitehall Estates",
    "gn:country_code":"US",
    "gn:dem":10,
    "gn:elevation":"3.0",
    "gn:feature_class":"P",
    "gn:feature_code":"PPL",
    "gn:name":"Whitehall Estates",
    "gn:population":0,
    "gn:timezone":"America/New_York",
    "iso:country":"US",
    "wof:name":"Whitehall Estates",
    "wof:placetype":"locality"
},
  "geometry": {"coordinates":[-76.43134999999999,39.01539],"type":"Point"}
}