{
  "type": "Feature",
  "properties": {
    "gn:admin1_code":"TX",
    "gn:admin2_code":"467.0",
    "gn:asciiname":"Sand Flat",
    "gn:country_code":"US",
    "gn:dem":149,
    "gn:elevation":"141.0",
    "gn:feature_class":"P",
    "gn:feature_code":"PPL",
    "gn:name":"Sand Flat",
    "gn:population":0,
    "gn:timezone":"America/Chicago",
    "iso:country":"US",
    "wof:name":"Sand Flat",
    "wof:placetype":"locality"
},
  "geometry": {"coordinates":[-95.65052,32.62736],"type":"Point"}
}