{
  "type": "Feature",
  "properties": {
    "gn:admin1_code":"NM",
    "gn:admin2_code":"19.0",
    "gn:asciiname":"Upper Dilia",
    "gn:country_code":"US",
    "gn:dem":1589,
    "gn:elevation":"1593.0",
    "gn:feature_class":"P",
    "gn:feature_code":"PPL",
    "gn:name":"Upper Dilia",
    "gn:population":0,
    "gn:timezone":"America/Denver",
    "iso:country":"US",
    "wof:name":"Upper Dilia",
    "wof:placetype":"locality"
},
  "geometry": {"coordinates":[-105.08083000000001,35.18477],"type":"Point"}
}