{
  "type": "Feature",
  "properties": {
    "gn:admin1_code":"SC",
    "gn:admin2_code":"11.0",
    "gn:asciiname":"Ashleigh",
    "gn:country_code":"US",
    "gn:dem":87,
    "gn:elevation":"84.0",
    "gn:feature_class":"P",
    "gn:feature_code":"PPL",
    "gn:name":"Ashleigh",
    "gn:population":0,
    "gn:timezone":"America/New_York",
    "iso:country":"US",
    "wof:name":"Ashleigh",
    "wof:placetype":"locality"
},
  "geometry": {"coordinates":[-81.31761,33.30098],"type":"Point"}
}