{
  "type": "Feature",
  "properties": {
    "gn:admin1_code":"MI",
    "gn:admin2_code":"33",
    "gn:admin3_code":"11280.0",
    "gn:asciiname":"Donaldson",
    "gn:country_code":"US",
    "gn:dem":207,
    "gn:elevation":"211.0",
    "gn:feature_class":"P",
    "gn:feature_code":"PPL",
    "gn:name":"Donaldson",
    "gn:population":0,
    "gn:timezone":"America/Detroit",
    "iso:country":"US",
    "name:ces_x_preferred":[
        "Donaldson"
    ],
    "wof:name":"Donaldson",
    "wof:placetype":"locality"
},
  "geometry": {"coordinates":[-84.36360999999999,46.31667],"type":"Point"}
}