{
  "type": "Feature",
  "properties": {
    "gn:admin1_code":"AZ",
    "gn:admin2_code":"5.0",
    "gn:asciiname":"Frazier Wells",
    "gn:country_code":"US",
    "gn:dem":1848,
    "gn:elevation":"1843.0",
    "gn:feature_class":"P",
    "gn:feature_code":"PPL",
    "gn:name":"Frazier Wells",
    "gn:population":0,
    "gn:timezone":"America/Phoenix",
    "iso:country":"US",
    "name:eng_x_preferred":[
        "Frazier Wells"
    ],
    "name:und_x_variant":[
        "Frazier Well",
        "Fraziers Well"
    ],
    "wof:name":"Frazier Wells",
    "wof:placetype":"locality"
},
  "geometry": {"coordinates":[-113.07214999999999,35.78249],"type":"Point"}
}