{
  "type": "Feature",
  "properties": {
    "gn:admin1_code":"MD",
    "gn:admin2_code":"27.0",
    "gn:asciiname":"Aladdin Village Trailer Park",
    "gn:country_code":"US",
    "gn:dem":74,
    "gn:elevation":"73.0",
    "gn:feature_class":"P",
    "gn:feature_code":"PPL",
    "gn:name":"Aladdin Village Trailer Park",
    "gn:population":0,
    "gn:timezone":"America/New_York",
    "iso:country":"US",
    "wof:name":"Aladdin Village Trailer Park",
    "wof:placetype":"campus"
},
  "geometry": {"coordinates":[-76.78331,39.17455],"type":"Point"}
}