{
  "type": "Feature",
  "properties": {
    "gn:gn_country":"US",
    "gn:gn_fcode":"PPL",
    "gn:gn_pop":0,
    "iso:country":"US",
    "name:ast_x_preferred":[
        "Morse"
    ],
    "name:cat_x_preferred":[
        "Morse"
    ],
    "name:ceb_x_preferred":[
        "Morse"
    ],
    "name:ces_x_preferred":[
        "Morse"
    ],
    "name:deu_x_preferred":[
        "Morse"
    ],
    "name:eus_x_preferred":[
        "Morse"
    ],
    "name:fas_x_preferred":[
        "\u0645\u0648\u0631\u0633"
    ],
    "name:fin_x_preferred":[
        "Morse"
    ],
    "name:fra_x_preferred":[
        "Morse"
    ],
    "name:frr_x_preferred":[
        "Morse"
    ],
    "name:fry_x_preferred":[
        "Morse"
    ],
    "name:heb_x_preferred":[
        "\u05de\u05d5\u05e8\u05e1"
    ],
    "name:ita_x_preferred":[
        "Morse"
    ],
    "name:jpn_x_preferred":[
        "\u30e2\u30fc\u30b9"
    ],
    "name:nld_x_preferred":[
        "Morse"
    ],
    "name:nor_x_preferred":[
        "Morse"
    ],
    "name:pol_x_preferred":[
        "Morse"
    ],
    "name:por_x_preferred":[
        "Morse"
    ],
    "name:slv_x_preferred":[
        "Morse"
    ],
    "name:spa_x_preferred":[
        "Morse"
    ],
    "name:swe_x_preferred":[
        "Morse"
    ],
    "name:tur_x_preferred":[
        "Morse"
    ],
    "name:ukr_x_preferred":[
        "\u041c\u043e\u0440\u0437\u0435"
    ],
    "name:vie_x_preferred":[
        "Morse"
    ],
    "name:vol_x_preferred":[
        "Morse"
    ],
    "name:zho_x_preferred":[
        "\u6469\u65af"
    ],
    "qs_pg:aaroncc":"US",
    "qs_pg:gn_country":"US",
    "qs_pg:gn_fcode":"PPL",
    "qs_pg:gn_pop":0,
    "qs_pg:name":"Morse",
    "qs_pg:name_adm0":"United States",
    "qs_pg:name_adm1":"North Carolina",
    "qs_pg:photos":5,
    "qs_pg:photos_1k":1,
    "qs_pg:photos_9k":1,
    "qs_pg:photos_9r":1,
    "qs_pg:photos_all":5,
    "qs_pg:photos_sr":1,
    "qs_pg:pop_sr":0,
    "qs_pg:qs_pg_placetype":"locality",
    "qs_pg:qs_pg_placetype_gp":"Town",
    "qs_pg:woe_adm0":23424977,
    "woe:adm0_id":23424977,
    "woe:name_adm0":"United States",
    "woe:name_adm1":"North Carolina",
    "woe:placetype":"Town",
    "wof:name":"Morse",
    "wof:placetype":"locality"
},
  "geometry": {"coordinates":[-76.16632,36.51849],"type":"Point"}
}