{
  "type": "Feature",
  "properties": {
    "gn:admin1_code":"OH",
    "gn:admin2_code":"35.0",
    "gn:admin3_code":"83622.0",
    "gn:asciiname":"Pebblebrook",
    "gn:country_code":"US",
    "gn:dem":222,
    "gn:elevation":"221.0",
    "gn:feature_class":"P",
    "gn:feature_code":"PPL",
    "gn:name":"Pebblebrook",
    "gn:population":0,
    "gn:timezone":"America/New_York",
    "iso:country":"US",
    "wof:name":"Pebblebrook",
    "wof:placetype":"locality"
},
  "geometry": {"coordinates":[-81.87860000000001,41.45403],"type":"Point"}
}