{
  "type": "Feature",
  "properties": {
    "gn:admin1_code":"MD",
    "gn:admin2_code":"5.0",
    "gn:asciiname":"Rolling Road Farms",
    "gn:country_code":"US",
    "gn:dem":120,
    "gn:elevation":"122.0",
    "gn:feature_class":"P",
    "gn:feature_code":"PPL",
    "gn:name":"Rolling Road Farms",
    "gn:population":0,
    "gn:timezone":"America/New_York",
    "iso:country":"US",
    "wof:name":"Rolling Road Farms",
    "wof:placetype":"locality"
},
  "geometry": {"coordinates":[-76.74942,39.32038],"type":"Point"}
}