{
  "type": "Feature",
  "properties": {
    "gn:elevation":417,
    "iso:country":"US",
    "name:eng_x_preferred":[
        "North Urbana"
    ],
    "name:eng_x_variant":[
        "N Urbana"
    ],
    "qs:gn_adm0_cc":"US",
    "qs:gn_fcode":"PPL",
    "qs:gn_local":5142047,
    "qs:gn_nam_loc":"Urbana, Steuben, New York, US",
    "qs:gn_namadm1":"NY",
    "qs:gn_name":"North Urbana",
    "qs:local_max":332,
    "qs:local_sum":500,
    "qs:localhoods":3,
    "qs:name":"North Urbana",
    "qs:name_adm0":"United States",
    "qs:name_adm1":"New York",
    "qs:name_adm2":"Steuben",
    "qs:name_local":"Urbana",
    "qs:photo_max":1,
    "qs:photo_sum":3,
    "qs:placetype":"Suburb",
    "qs:quad_count":3,
    "qs:woe_adm0":23424977,
    "qs:woe_adm1":2347591,
    "qs:woe_adm2":12589362,
    "qs:woe_lau":0,
    "qs:woe_local":2510432,
    "qs:woe_ver":"7.10.0",
    "wof:lang":[
        "eng"
    ],
    "wof:name":"North Urbana",
    "wof:placetype":"neighbourhood",
    "wof:population":66,
    "zs:blockids":[
        361019615001082,
        361019615001083
    ],
    "zs:housing10":27,
    "zs:pop10":66
},
  "geometry": {"coordinates":[-77.181702,42.420077],"type":"Point"}
}