{
  "type": "Feature",
  "properties": {
    "gn:country":"US",
    "gn:fcode":"PPL",
    "gn:population":0,
    "iso:country":"US",
    "name:azb_x_preferred":[
        "\u067e\u0646\u0648\u0686"
    ],
    "name:eng_x_preferred":[
        "Panoche"
    ],
    "name:fas_x_preferred":[
        "\u067e\u0646\u0648\u0686"
    ],
    "name:fra_x_preferred":[
        "Panoche"
    ],
    "name:nld_x_preferred":[
        "Panoche"
    ],
    "name:spa_x_preferred":[
        "Panoche"
    ],
    "name:tur_x_preferred":[
        "Panoche"
    ],
    "name:vol_x_preferred":[
        "Panoche"
    ],
    "name:zho_x_preferred":[
        "\u5e15\u8afe\u5947"
    ],
    "qs_pg:aaroncc":"US",
    "qs_pg:gn_country":"US",
    "qs_pg:gn_fcode":"PPL",
    "qs_pg:gn_pop":0,
    "qs_pg:name":"Panoche",
    "qs_pg:name_adm0":"United States",
    "qs_pg:name_adm1":"California",
    "qs_pg:photos":116,
    "qs_pg:photos_1k":24,
    "qs_pg:photos_9k":1,
    "qs_pg:photos_9r":3,
    "qs_pg:photos_all":116,
    "qs_pg:photos_sr":3,
    "qs_pg:pop_sr":0,
    "qs_pg:qs_pg_placetype":"locality",
    "qs_pg:qs_pg_placetype_gp":"Town",
    "qs_pg:woe_adm0":23424977,
    "woe:adm0_id":23424977,
    "woe:name_adm0":"United States",
    "woe:name_adm1":"California",
    "woe:placetype":"Town",
    "wof:name":"Panoche",
    "wof:placetype":"locality"
},
  "geometry": {"coordinates":[-120.83351,36.5969],"type":"Point"}
}