{
  "type": "Feature",
  "properties": {
    "gn:admin1_code":"TX",
    "gn:admin2_code":"73.0",
    "gn:asciiname":"Tecula",
    "gn:country_code":"US",
    "gn:dem":130,
    "gn:elevation":"125.0",
    "gn:feature_class":"P",
    "gn:feature_code":"PPL",
    "gn:name":"Tecula",
    "gn:population":0,
    "gn:timezone":"America/Chicago",
    "iso:country":"US",
    "wof:name":"Tecula",
    "wof:placetype":"locality"
},
  "geometry": {"coordinates":[-95.20939,32.01989],"type":"Point"}
}