{
  "type": "Feature",
  "properties": {
    "gn:admin1_code":"TX",
    "gn:admin2_code":"21.0",
    "gn:asciiname":"Upton",
    "gn:country_code":"US",
    "gn:dem":108,
    "gn:elevation":"104.0",
    "gn:feature_class":"P",
    "gn:feature_code":"PPL",
    "gn:name":"Upton",
    "gn:population":0,
    "gn:timezone":"America/Chicago",
    "iso:country":"US",
    "name:ita_x_preferred":[
        "Upton"
    ],
    "wof:name":"Upton",
    "wof:placetype":"locality"
},
  "geometry": {"coordinates":[-97.26416,30.01133],"type":"Point"}
}