{
  "type": "Feature",
  "properties": {
    "gn:admin1_code":"WA",
    "gn:admin2_code":"33.0",
    "gn:asciiname":"Atkinson",
    "gn:country_code":"US",
    "gn:dem":164,
    "gn:elevation":"169.0",
    "gn:feature_class":"P",
    "gn:feature_code":"PPL",
    "gn:name":"Atkinson",
    "gn:population":0,
    "gn:timezone":"America/Los_Angeles",
    "iso:country":"US",
    "name:cat_x_preferred":[
        "Atkinson"
    ],
    "name:ceb_x_preferred":[
        "Atkinson"
    ],
    "name:deu_x_preferred":[
        "Atkinson"
    ],
    "name:fas_x_preferred":[
        "\u0627\u062a\u06a9\u06cc\u0646\u0633\u0646"
    ],
    "name:fin_x_preferred":[
        "Atkinson"
    ],
    "name:fra_x_preferred":[
        "Atkinson"
    ],
    "name:heb_x_preferred":[
        "\u05d0\u05d8\u05e7\u05d9\u05e0\u05e1\u05d5\u05df"
    ],
    "name:ita_x_preferred":[
        "Atkinson"
    ],
    "name:jpn_x_preferred":[
        "\u30a2\u30c8\u30ad\u30f3\u30bd\u30f3"
    ],
    "name:kor_x_preferred":[
        "\uc573\ud0a8\uc2a8"
    ],
    "name:nld_x_preferred":[
        "Atkinson"
    ],
    "name:pol_x_preferred":[
        "Atkinson"
    ],
    "name:por_x_preferred":[
        "Atkinson"
    ],
    "name:rus_x_preferred":[
        "\u0410\u0442\u043a\u0438\u043d\u0441\u043e\u043d"
    ],
    "name:spa_x_preferred":[
        "Atkinson"
    ],
    "name:srp_x_preferred":[
        "\u0410\u0442\u043a\u0438\u043d\u0441\u043e\u043d"
    ],
    "name:swe_x_preferred":[
        "Atkinson"
    ],
    "name:ukr_x_preferred":[
        "\u0410\u0442\u043a\u0456\u043d\u0441\u043e\u043d"
    ],
    "name:vol_x_preferred":[
        "Atkinson"
    ],
    "wof:name":"Atkinson",
    "wof:placetype":"locality"
},
  "geometry": {"coordinates":[-122.01678,47.40871],"type":"Point"}
}