{
  "type": "Feature",
  "properties": {
    "gn:admin1_code":"AR",
    "gn:admin2_code":"145.0",
    "gn:admin3_code":"93789.0",
    "gn:asciiname":"Velvet Ridge",
    "gn:country_code":"US",
    "gn:dem":194,
    "gn:elevation":"196.0",
    "gn:feature_class":"P",
    "gn:feature_code":"PPL",
    "gn:name":"Velvet Ridge",
    "gn:population":0,
    "gn:timezone":"America/Chicago",
    "iso:country":"US",
    "wof:name":"Velvet Ridge",
    "wof:placetype":"locality"
},
  "geometry": {"coordinates":[-91.57625,35.41314000000001],"type":"Point"}
}