{
  "type": "Feature",
  "properties": {
    "gn:admin1_code":"AR",
    "gn:admin2_code":"13.0",
    "gn:asciiname":"Big Hill",
    "gn:country_code":"US",
    "gn:dem":98,
    "gn:elevation":"87.0",
    "gn:feature_class":"P",
    "gn:feature_code":"PPL",
    "gn:name":"Big Hill",
    "gn:population":0,
    "gn:timezone":"America/Chicago",
    "iso:country":"US",
    "name:ces_x_preferred":[
        "Spiral Tunnels"
    ],
    "name:deu_x_preferred":[
        "Spiral Tunnel"
    ],
    "name:nld_x_preferred":[
        "Spiral Tunnels"
    ],
    "name:rus_x_preferred":[
        "\u0411\u043e\u043b\u044c\u0448\u043e\u0439 \u0445\u043e\u043b\u043c"
    ],
    "wof:name":"Big Hill",
    "wof:placetype":"locality"
},
  "geometry": {"coordinates":[-92.41543,33.66566],"type":"Point"}
}