{
  "type": "Feature",
  "properties": {
    "iso:country":"US",
    "name:ara_x_preferred":[
        "\u0639\u0634\u0628 \u0628\u0631\u064a"
    ],
    "name:eng_x_preferred":[
        "Wildflower"
    ],
    "name:eng_x_variant":[
        "wildflower"
    ],
    "name:heb_x_preferred":[
        "\u05e6\u05de\u05d7 \u05d1\u05e8"
    ],
    "name:jpn_x_preferred":[
        "\u30ef\u30a4\u30eb\u30c9\u30d5\u30e9\u30ef\u30fc"
    ],
    "name:kor_x_preferred":[
        "\ub4e4\uaf43"
    ],
    "name:rus_x_preferred":[
        "\u043f\u043e\u043b\u0435\u0432\u043e\u0439 \u0446\u0432\u0435\u0442\u043e\u043a"
    ],
    "name:spa_x_preferred":[
        "Flor silvestre"
    ],
    "name:vie_x_preferred":[
        "Hoa d\u1ea1i"
    ],
    "wd:wordcount":447,
    "wof:name":"Wildflower",
    "wof:placetype":"neighbourhood",
    "wof:population":400,
    "zs:area_m":3352333.520042,
    "zs:blockids":[
        350010038051030,
        350010038051060,
        350010038051034,
        350010038041004,
        350010038051035,
        350010038041002,
        350010038041003,
        350010038051059,
        350010038032020,
        350010038032023,
        350010038051032,
        350010038051031,
        350010038032019,
        350010038032022,
        350010038051061,
        350010038031004
    ],
    "zs:housing10":198,
    "zs:label":"Wildflower",
    "zs:pop10":400
},
  "geometry": {"coordinates":[-106.346907,35.157977],"type":"Point"}
}