{
  "type": "Feature",
  "properties": {
    "iso:country":"US",
    "name:ara_x_preferred":[
        "\u0639\u0634\u0628 \u0628\u0631\u064a"
    ],
    "name:bul_x_preferred":[
        "\u0414\u0438\u0432\u043e \u0446\u0432\u0435\u0442\u0435"
    ],
    "name:deu_x_preferred":[
        "Wildblume"
    ],
    "name:eng_x_preferred":[
        "Wildflower"
    ],
    "name:eng_x_variant":[
        "wildflower"
    ],
    "name:epo_x_preferred":[
        "sova\u011da floro"
    ],
    "name:fas_x_preferred":[
        "\u06af\u0644 \u0648\u062d\u0634\u06cc"
    ],
    "name:fra_x_preferred":[
        "fleurs sauvages"
    ],
    "name:heb_x_preferred":[
        "\u05e6\u05de\u05d7 \u05d1\u05e8"
    ],
    "name:hin_x_preferred":[
        "\u092c\u0928\u092b\u0942\u0932"
    ],
    "name:hun_x_preferred":[
        "vadvir\u00e1g"
    ],
    "name:jpn_x_preferred":[
        "\u30ef\u30a4\u30eb\u30c9\u30d5\u30e9\u30ef\u30fc"
    ],
    "name:jpn_x_variant":[
        "\u91ce\u751f\u306e\u82b1"
    ],
    "name:kor_x_preferred":[
        "\ub4e4\uaf43"
    ],
    "name:lit_x_preferred":[
        "Piev\u0173 g\u0117l\u0117s"
    ],
    "name:nld_x_preferred":[
        "veldbloemen"
    ],
    "name:nob_x_preferred":[
        "markblomster"
    ],
    "name:rus_x_preferred":[
        "\u043f\u043e\u043b\u0435\u0432\u043e\u0439 \u0446\u0432\u0435\u0442\u043e\u043a"
    ],
    "name:spa_x_preferred":[
        "Flor silvestre"
    ],
    "name:tgl_x_preferred":[
        "Wild Flower"
    ],
    "name:tha_x_preferred":[
        "\u0e14\u0e2d\u0e01\u0e44\u0e21\u0e49\u0e1b\u0e48\u0e32"
    ],
    "name:tur_x_preferred":[
        "K\u0131r \u00e7i\u00e7e\u011fi"
    ],
    "name:vie_x_preferred":[
        "Hoa d\u1ea1i"
    ],
    "wd:wordcount":447,
    "wof:name":"Wildflower",
    "wof:placetype":"neighbourhood",
    "wof:population":400,
    "zs:area_m":3352333.520042,
    "zs:blockids":[
        350010038051030,
        350010038051060,
        350010038051034,
        350010038041004,
        350010038051035,
        350010038041002,
        350010038041003,
        350010038051059,
        350010038032020,
        350010038032023,
        350010038051032,
        350010038051031,
        350010038032019,
        350010038032022,
        350010038051061,
        350010038031004
    ],
    "zs:housing10":198,
    "zs:label":"Wildflower",
    "zs:pop10":400
},
  "geometry": {"coordinates":[-106.346907,35.157977],"type":"Point"}
}