{
  "type": "Feature",
  "properties": {
    "gn:admin1_code":"SC",
    "gn:admin2_code":"73.0",
    "gn:asciiname":"Oconee Estates",
    "gn:country_code":"US",
    "gn:dem":285,
    "gn:elevation":"282.0",
    "gn:feature_class":"P",
    "gn:feature_code":"PPL",
    "gn:name":"Oconee Estates",
    "gn:population":0,
    "gn:timezone":"America/New_York",
    "iso:country":"US",
    "wof:name":"Oconee Estates",
    "wof:placetype":"locality"
},
  "geometry": {"coordinates":[-83.00681999999998,34.70426],"type":"Point"}
}