{
  "type": "Feature",
  "properties": {
    "gn:admin1_code":"NH",
    "gn:admin2_code":"9.0",
    "gn:admin3_code":"33860.0",
    "gn:asciiname":"Etna",
    "gn:country_code":"US",
    "gn:dem":235,
    "gn:elevation":"233.0",
    "gn:feature_class":"P",
    "gn:feature_code":"PPL",
    "gn:name":"Etna",
    "gn:population":0,
    "gn:timezone":"America/New_York",
    "iso:country":"US",
    "name:azb_x_preferred":[
        "\u0627\u062a\u0646\u0627"
    ],
    "name:eng_x_preferred":[
        "Etna"
    ],
    "name:fas_x_preferred":[
        "\u0627\u062a\u0646\u0627"
    ],
    "name:und_x_variant":[
        "Mill Village"
    ],
    "name:vol_x_preferred":[
        "Etna"
    ],
    "wof:name":"Etna",
    "wof:placetype":"locality"
},
  "geometry": {"coordinates":[-72.22176,43.69285],"type":"Point"}
}