{
  "type": "Feature",
  "properties": {
    "iso:country":"US",
    "name:eng_x_preferred":[
        "Kaohe 5 Ahupua`a"
    ],
    "wof:name":"Kaohe 5 Ahupua`a",
    "wof:placetype":"neighbourhood",
    "wof:population":223,
    "zs:area_m":34385684.430068,
    "zs:blockids":[
        150010213001058,
        150010213001083
    ],
    "zs:housing10":91,
    "zs:label":"Kaohe 5 Ahupua`a",
    "zs:pop10":223
},
  "geometry": {"coordinates":[-155.84005500000001,19.293353],"type":"Point"}
}