{
  "type": "Feature",
  "properties": {
    "iso:country":"US",
    "name:eng_x_preferred":[
        "Churchdale"
    ],
    "wof:name":"Churchdale",
    "wof:placetype":"neighbourhood",
    "wof:population":51,
    "zs:area_m":20380.52277,
    "zs:blockids":[
        191530008022027
    ],
    "zs:housing10":25,
    "zs:label":"Churchdale",
    "zs:pop10":51
},
  "geometry": {"coordinates":[-93.67854199999999,41.617626],"type":"Point"}
}