{
  "type": "Feature",
  "properties": {
    "gn:admin1_code":"WA",
    "gn:admin2_code":"53.0",
    "gn:asciiname":"Franklin Pierce Mobile Estates",
    "gn:country_code":"US",
    "gn:dem":126,
    "gn:elevation":"129.0",
    "gn:feature_class":"P",
    "gn:feature_code":"PPL",
    "gn:name":"Franklin Pierce Mobile Estates",
    "gn:population":0,
    "gn:timezone":"America/Los_Angeles",
    "iso:country":"US",
    "wof:name":"Franklin Pierce Mobile Estates",
    "wof:placetype":"campus"
},
  "geometry": {"coordinates":[-122.4004,47.15285],"type":"Point"}
}