{
  "type": "Feature",
  "properties": {
    "gn:admin1_code":"KY",
    "gn:admin2_code":"23",
    "gn:asciiname":"Stonewall",
    "gn:country_code":"US",
    "gn:dem":276,
    "gn:elevation":"282.0",
    "gn:feature_class":"P",
    "gn:feature_code":"PPL",
    "gn:name":"Stonewall",
    "gn:population":0,
    "gn:timezone":"America/New_York",
    "iso:country":"US",
    "name:ceb_x_preferred":[
        "Stonewall"
    ],
    "name:cym_x_preferred":[
        "Stonewall"
    ],
    "name:deu_x_preferred":[
        "Stonewall"
    ],
    "name:est_x_preferred":[
        "Stonewall"
    ],
    "name:fin_x_preferred":[
        "Stonewall"
    ],
    "name:fra_x_preferred":[
        "Stonewall"
    ],
    "name:heb_x_preferred":[
        "\u05e1\u05d8\u05d5\u05e0\u05d5\u05d5\u05dc"
    ],
    "name:ita_x_preferred":[
        "Stonewall"
    ],
    "name:jpn_x_preferred":[
        "\u30b9\u30c8\u30fc\u30f3\u30a6\u30a9\u30fc\u30eb"
    ],
    "name:kor_x_preferred":[
        "\uc2a4\ud1a4\uc6d4"
    ],
    "name:nld_x_preferred":[
        "Stonewall"
    ],
    "name:pol_x_preferred":[
        "Stonewall"
    ],
    "name:por_x_preferred":[
        "Stonewall"
    ],
    "name:rus_x_preferred":[
        "\u0421\u0442\u043e\u0443\u043d\u0432\u043e\u043b\u043b"
    ],
    "name:spa_x_preferred":[
        "Stonewall"
    ],
    "name:srp_x_preferred":[
        "\u0421\u0442\u043e\u0443\u043d\u0432\u043e\u043b"
    ],
    "name:swe_x_preferred":[
        "Stonewall"
    ],
    "name:tur_x_preferred":[
        "Stonewall"
    ],
    "name:ukr_x_preferred":[
        "\u0421\u0442\u043e\u0443\u043d\u0432\u043e\u043b\u043b"
    ],
    "name:vol_x_preferred":[
        "Stonewall"
    ],
    "name:zho_x_preferred":[
        "Stonewall"
    ],
    "wof:name":"Stonewall",
    "wof:placetype":"locality"
},
  "geometry": {"coordinates":[-84.01132,38.61924000000001],"type":"Point"}
}