{
  "type": "Feature",
  "properties": {
    "gn:admin1_code":"OK",
    "gn:admin2_code":"35.0",
    "gn:asciiname":"Pyramid Corners",
    "gn:country_code":"US",
    "gn:dem":238,
    "gn:elevation":"238.0",
    "gn:feature_class":"P",
    "gn:feature_code":"PPL",
    "gn:name":"Pyramid Corners",
    "gn:population":0,
    "gn:timezone":"America/Chicago",
    "iso:country":"US",
    "wof:name":"Pyramid Corners",
    "wof:placetype":"locality"
},
  "geometry": {"coordinates":[-95.1433,36.80174],"type":"Point"}
}