{
  "type": "Feature",
  "properties": {
    "gn:admin1_code":"WV",
    "gn:admin2_code":"101",
    "gn:asciiname":"Diana",
    "gn:country_code":"US",
    "gn:dem":379,
    "gn:elevation":"375.0",
    "gn:feature_class":"P",
    "gn:feature_code":"PPL",
    "gn:name":"Diana",
    "gn:population":0,
    "gn:timezone":"America/New_York",
    "iso:country":"US",
    "name:ara_x_preferred":[
        "\u062f\u064a\u0627\u0646\u0627"
    ],
    "name:azb_x_preferred":[
        "\u062f\u06cc\u0627\u0646\u0627"
    ],
    "name:ben_x_preferred":[
        "\u09a6\u09bf\u09df\u09be\u09a8\u09be"
    ],
    "name:deu_x_preferred":[
        "Diana"
    ],
    "name:ell_x_preferred":[
        "\u039d\u03c4\u03b9\u03ac\u03bd\u03b1"
    ],
    "name:eng_x_preferred":[
        "Diana"
    ],
    "name:fas_x_preferred":[
        "\u062f\u06cc\u0627\u0646\u0627"
    ],
    "name:fra_x_preferred":[
        "Diana"
    ],
    "name:heb_x_preferred":[
        "\u05d3\u05d9\u05d0\u05e0\u05d4"
    ],
    "name:hin_x_preferred":[
        "\u0921\u093e\u092f\u0928\u093e"
    ],
    "name:hun_x_preferred":[
        "Diana"
    ],
    "name:ind_x_preferred":[
        "Diana"
    ],
    "name:ita_x_preferred":[
        "Diana"
    ],
    "name:jpn_x_preferred":[
        "\u30c0\u30a4\u30a2\u30ca"
    ],
    "name:kor_x_preferred":[
        "\ub2e4\uc774\uc544\ub098"
    ],
    "name:nld_x_preferred":[
        "Diana"
    ],
    "name:pol_x_preferred":[
        "Diana"
    ],
    "name:por_x_preferred":[
        "Diana"
    ],
    "name:rus_x_preferred":[
        "\u0414\u0438\u0430\u043d\u0430"
    ],
    "name:spa_x_preferred":[
        "Diana"
    ],
    "name:swe_x_preferred":[
        "Diana"
    ],
    "name:tur_x_preferred":[
        "Diana"
    ],
    "name:ukr_x_preferred":[
        "\u0414\u0456\u0430\u043d\u0430"
    ],
    "name:urd_x_preferred":[
        "\u0688\u0627\u0626\u0627\u0646\u0627"
    ],
    "name:vie_x_preferred":[
        "Diana"
    ],
    "name:vol_x_preferred":[
        "Diana"
    ],
    "name:zho_cn_x_preferred":[
        "\u9edb\u5b89\u5a1c"
    ],
    "name:zho_tw_x_preferred":[
        "\u6234\u5b89\u5a1c"
    ],
    "wof:name":"Diana",
    "wof:placetype":"locality"
},
  "geometry": {"coordinates":[-80.45647,38.57372],"type":"Point"}
}