{
  "type": "Feature",
  "properties": {
    "gn:admin1_code":"WV",
    "gn:admin2_code":"101",
    "gn:asciiname":"Diana",
    "gn:country_code":"US",
    "gn:dem":379,
    "gn:elevation":"375.0",
    "gn:feature_class":"P",
    "gn:feature_code":"PPL",
    "gn:name":"Diana",
    "gn:population":0,
    "gn:timezone":"America/New_York",
    "iso:country":"US",
    "name:azb_x_preferred":[
        "\u062f\u06cc\u0627\u0646\u0627"
    ],
    "name:fas_x_preferred":[
        "\u062f\u06cc\u0627\u0646\u0627"
    ],
    "name:vol_x_preferred":[
        "Diana"
    ],
    "wof:name":"Diana",
    "wof:placetype":"locality"
},
  "geometry": {"coordinates":[-80.45647,38.57372],"type":"Point"}
}