{
  "type": "Feature",
  "properties": {
    "gn:admin1_code":"OH",
    "gn:admin2_code":"145",
    "gn:admin3_code":"34020.0",
    "gn:asciiname":"Wheelers Mill",
    "gn:country_code":"US",
    "gn:dem":183,
    "gn:elevation":"172.0",
    "gn:feature_class":"P",
    "gn:feature_code":"PPL",
    "gn:name":"Wheelers Mill",
    "gn:population":0,
    "gn:timezone":"America/New_York",
    "iso:country":"US",
    "name:eng_x_preferred":[
        "Wheelers Mill"
    ],
    "name:und_x_variant":[
        "Wheeler",
        "Wheelers Siding"
    ],
    "wof:name":"Wheelers Mill",
    "wof:placetype":"locality"
},
  "geometry": {"coordinates":[-82.84989,38.82758],"type":"Point"}
}