{
  "type": "Feature",
  "properties": {
    "gn:admin1_code":"GA",
    "gn:admin2_code":"31.0",
    "gn:asciiname":"Hazelwood",
    "gn:country_code":"US",
    "gn:dem":72,
    "gn:elevation":"67.0",
    "gn:feature_class":"P",
    "gn:feature_code":"PPL",
    "gn:name":"Hazelwood",
    "gn:population":0,
    "gn:timezone":"America/New_York",
    "iso:country":"US",
    "name:ceb_x_preferred":[
        "Hazelwood"
    ],
    "name:deu_x_preferred":[
        "Hazelwood"
    ],
    "name:fra_x_preferred":[
        "Hazelwood"
    ],
    "name:nld_x_preferred":[
        "Hazelwood"
    ],
    "name:pol_x_preferred":[
        "Hazelwood"
    ],
    "name:swe_x_preferred":[
        "Hazelwood"
    ],
    "wof:name":"Hazelwood",
    "wof:placetype":"locality"
},
  "geometry": {"coordinates":[-81.819,32.42518],"type":"Point"}
}