{
  "type": "Feature",
  "properties": {
    "iso:country":"US",
    "name:eng_x_preferred":[
        "Light Lane"
    ],
    "wof:name":"Light Lane",
    "wof:placetype":"neighbourhood",
    "wof:population":43,
    "zs:area_m":61801.527012,
    "zs:blockids":[
        120710016021000
    ],
    "zs:housing10":14,
    "zs:label":"Light Lane",
    "zs:pop10":43
},
  "geometry": {"coordinates":[-81.855912,26.544138],"type":"Point"}
}