{
  "type": "Feature",
  "properties": {
    "gn:admin1_code":"SC",
    "gn:admin2_code":"51.0",
    "gn:asciiname":"Cochran Town",
    "gn:country_code":"US",
    "gn:dem":2,
    "gn:elevation":"8.0",
    "gn:feature_class":"P",
    "gn:feature_code":"PPL",
    "gn:name":"Cochran Town",
    "gn:population":0,
    "gn:timezone":"America/New_York",
    "iso:country":"US",
    "wof:name":"Cochran Town",
    "wof:placetype":"locality"
},
  "geometry": {"coordinates":[-79.07059,33.87323],"type":"Point"}
}