{
  "type": "Feature",
  "properties": {
    "gn:admin1_code":"DE",
    "gn:admin2_code":"3.0",
    "gn:asciiname":"Loveville",
    "gn:country_code":"US",
    "gn:dem":100,
    "gn:elevation":"98.0",
    "gn:feature_class":"P",
    "gn:feature_code":"PPL",
    "gn:name":"Loveville",
    "gn:population":0,
    "gn:timezone":"America/New_York",
    "iso:country":"US",
    "name:zho_x_preferred":[
        "\u62c9\u592b\u7dad\u723e"
    ],
    "wof:name":"Loveville",
    "wof:placetype":"locality"
},
  "geometry": {"coordinates":[-75.66438000000002,39.77095],"type":"Point"}
}