{
  "type": "Feature",
  "properties": {
    "gn:admin1_code":"MO",
    "gn:admin2_code":"1.0",
    "gn:admin3_code":"57224.0",
    "gn:asciiname":"Dart",
    "gn:country_code":"US",
    "gn:dem":289,
    "gn:elevation":"284.0",
    "gn:feature_class":"P",
    "gn:feature_code":"PPL",
    "gn:name":"Dart",
    "gn:population":0,
    "gn:timezone":"America/Chicago",
    "iso:country":"US",
    "name:ceb_x_preferred":[
        "Dart"
    ],
    "name:ces_x_preferred":[
        "Dart"
    ],
    "name:chv_x_preferred":[
        "\u0414\u0430\u0440\u0442"
    ],
    "name:deu_x_preferred":[
        "Dart"
    ],
    "name:fra_x_preferred":[
        "Dart"
    ],
    "name:hun_x_preferred":[
        "Dart"
    ],
    "name:ita_x_preferred":[
        "Dart"
    ],
    "name:nld_x_preferred":[
        "Dart"
    ],
    "name:pol_x_preferred":[
        "Dart"
    ],
    "name:rus_x_preferred":[
        "\u0414\u0430\u0440\u0442"
    ],
    "name:srp_x_preferred":[
        "\u0414\u0430\u0440\u0442"
    ],
    "name:swe_x_preferred":[
        "Dart"
    ],
    "wof:name":"Dart",
    "wof:placetype":"locality"
},
  "geometry": {"coordinates":[-92.56741,40.0467],"type":"Point"}
}