{
  "type": "Feature",
  "properties": {
    "gn:admin1_code":"UT",
    "gn:admin2_code":"35.0",
    "gn:asciiname":"North Crest Park Condominium",
    "gn:country_code":"US",
    "gn:dem":1436,
    "gn:elevation":"1429.0",
    "gn:feature_class":"P",
    "gn:feature_code":"PPL",
    "gn:name":"North Crest Park Condominium",
    "gn:population":0,
    "gn:timezone":"America/Denver",
    "iso:country":"US",
    "wof:name":"North Crest Park Condominium",
    "wof:placetype":"locality"
},
  "geometry": {"coordinates":[-111.87688,40.7805],"type":"Point"}
}