{
  "type": "Feature",
  "properties": {
    "gn:admin1_code":"NC",
    "gn:admin2_code":"67",
    "gn:admin3_code":"91696.0",
    "gn:asciiname":"Dilhast",
    "gn:country_code":"US",
    "gn:dem":295,
    "gn:elevation":"293.0",
    "gn:feature_class":"P",
    "gn:feature_code":"PPL",
    "gn:name":"Dilhast",
    "gn:population":0,
    "gn:timezone":"America/New_York",
    "iso:country":"US",
    "wof:name":"Dilhast",
    "wof:placetype":"locality"
},
  "geometry": {"coordinates":[-80.12893000000003,36.15125],"type":"Point"}
}