{
  "type": "Feature",
  "properties": {
    "gn:admin1_code":"KY",
    "gn:admin2_code":"183",
    "gn:asciiname":"Dogwalk",
    "gn:country_code":"US",
    "gn:dem":197,
    "gn:elevation":"196.0",
    "gn:feature_class":"P",
    "gn:feature_code":"PPL",
    "gn:name":"Dogwalk",
    "gn:population":0,
    "gn:timezone":"America/Chicago",
    "iso:country":"US",
    "name:eng_x_preferred":[
        "Dogwalk"
    ],
    "name:und_x_variant":[
        "Antioch"
    ],
    "wof:name":"Dogwalk",
    "wof:placetype":"locality"
},
  "geometry": {"coordinates":[-86.63025999999998,37.40477],"type":"Point"}
}