{
  "type": "Feature",
  "properties": {
    "gn:admin1_code":"FL",
    "gn:admin2_code":"57",
    "gn:asciiname":"Treehouses at Mohr Loop",
    "gn:country_code":"US",
    "gn:dem":13,
    "gn:elevation":"1.0",
    "gn:feature_class":"P",
    "gn:feature_code":"PPL",
    "gn:name":"Treehouses at Mohr Loop",
    "gn:population":0,
    "gn:timezone":"America/New_York",
    "iso:country":"US",
    "wof:name":"Treehouses at Mohr Loop",
    "wof:placetype":"locality"
},
  "geometry": {"coordinates":[-82.58620000000001,28.003],"type":"Point"}
}