{
  "type": "Feature",
  "properties": {
    "gn:admin1_code":"MI",
    "gn:admin2_code":"49.0",
    "gn:admin3_code":"29420.0",
    "gn:asciiname":"Orchard Cove Manufactured Home Community",
    "gn:country_code":"US",
    "gn:dem":242,
    "gn:elevation":"242.0",
    "gn:feature_class":"P",
    "gn:feature_code":"PPL",
    "gn:name":"Orchard Cove Manufactured Home Community",
    "gn:population":0,
    "gn:timezone":"America/Detroit",
    "iso:country":"US",
    "wof:name":"Orchard Cove Manufactured Home Community",
    "wof:placetype":"campus"
},
  "geometry": {"coordinates":[-83.52889,43.16306],"type":"Point"}
}