{
  "type": "Feature",
  "properties": {
    "gn:admin1_code":"MO",
    "gn:admin2_code":"29.0",
    "gn:admin3_code":"190.0",
    "gn:asciiname":"Dodds",
    "gn:country_code":"US",
    "gn:dem":211,
    "gn:elevation":"208.0",
    "gn:feature_class":"P",
    "gn:feature_code":"PPL",
    "gn:name":"Dodds",
    "gn:population":0,
    "gn:timezone":"America/Chicago",
    "iso:country":"US",
    "name:deu_x_preferred":[
        "Dodds"
    ],
    "name:fra_x_preferred":[
        "Dodds"
    ],
    "name:ita_x_preferred":[
        "Dodds"
    ],
    "name:nds_x_preferred":[
        "Dodds"
    ],
    "name:pol_x_preferred":[
        "Dodds"
    ],
    "name:rus_x_preferred":[
        "\u0414\u043e\u0434\u0434\u0441"
    ],
    "wof:name":"Dodds",
    "wof:placetype":"locality"
},
  "geometry": {"coordinates":[-92.98519,38.1542],"type":"Point"}
}