{
  "type": "Feature",
  "properties": {
    "gn:country":"US",
    "gn:fcode":"PPL",
    "gn:population":15802,
    "iso:country":"US",
    "name:azb_x_preferred":[
        "\u0622\u0634\u0644\u0627\u0646\u062f"
    ],
    "name:cat_x_preferred":[
        "Ashland"
    ],
    "name:ceb_x_preferred":[
        "Ashland"
    ],
    "name:che_x_preferred":[
        "\u042d\u0448\u043b\u0435\u043d\u0434"
    ],
    "name:cym_x_preferred":[
        "Ashland"
    ],
    "name:deu_x_preferred":[
        "Ashland"
    ],
    "name:eng_x_preferred":[
        "Ashland"
    ],
    "name:eus_x_preferred":[
        "Ashland"
    ],
    "name:fas_x_preferred":[
        "\u0627\u0634\u0644\u0646\u062f\u060c \u0645\u0627\u0633\u0627\u0686\u0648\u0633\u062a"
    ],
    "name:fas_x_variant":[
        "\u0627\u0634\u0644\u0646\u062f"
    ],
    "name:fra_x_preferred":[
        "Ashland"
    ],
    "name:heb_x_preferred":[
        "\u05d0\u05e9\u05dc\u05e0\u05d3"
    ],
    "name:hun_x_preferred":[
        "Ashland"
    ],
    "name:ita_x_preferred":[
        "Ashland"
    ],
    "name:jpn_x_preferred":[
        "\u30a2\u30c3\u30b7\u30e5\u30e9\u30f3\u30c9"
    ],
    "name:kaz_x_preferred":[
        "\u0410\u0448\u043b\u044d\u043d\u0434"
    ],
    "name:kir_x_preferred":[
        "\u0410\u0448\u043b\u044d\u043d\u0434"
    ],
    "name:kor_x_preferred":[
        "\uc560\uc290\ub79c\ub4dc"
    ],
    "name:nld_x_preferred":[
        "Ashland"
    ],
    "name:pol_x_preferred":[
        "Ashland"
    ],
    "name:por_x_preferred":[
        "Ashland"
    ],
    "name:rus_x_preferred":[
        "\u0410\u0448\u043b\u0435\u043d\u0434"
    ],
    "name:spa_x_preferred":[
        "Ashland"
    ],
    "name:swa_x_preferred":[
        "Ashland"
    ],
    "name:tat_x_preferred":[
        "\u042d\u0448\u043b\u0435\u043d\u0434"
    ],
    "name:tur_x_preferred":[
        "Ashland"
    ],
    "name:ukr_x_preferred":[
        "\u0415\u0448\u043b\u0435\u043d\u0434"
    ],
    "name:und_x_variant":[
        "Unionville"
    ],
    "name:urd_x_preferred":[
        "\u0627\u06cc\u0634\u0644\u0646\u0688\u060c \u0645\u06cc\u0633\u0627\u0686\u0648\u0633\u0679\u0633"
    ],
    "name:urd_x_variant":[
        "\u0627\u06cc\u0634\u0644\u0646\u0688"
    ],
    "name:vol_x_preferred":[
        "Ashland"
    ],
    "qs_pg:aaroncc":"US",
    "qs_pg:gn_country":"US",
    "qs_pg:gn_fcode":"PPL",
    "qs_pg:gn_pop":15802,
    "qs_pg:name":"Ashland",
    "qs_pg:name_adm0":"United States",
    "qs_pg:name_adm1":"Massachusetts",
    "qs_pg:photos":739,
    "qs_pg:photos_1k":150,
    "qs_pg:photos_9k":3,
    "qs_pg:photos_9r":5,
    "qs_pg:photos_all":740,
    "qs_pg:photos_sr":8,
    "qs_pg:pop_sr":6,
    "qs_pg:qs_pg_placetype":"locality",
    "qs_pg:qs_pg_placetype_gp":"Town",
    "qs_pg:woe_adm0":23424977,
    "woe:adm0_id":23424977,
    "woe:name_adm0":"United States",
    "woe:name_adm1":"Massachusetts",
    "woe:placetype":"Town",
    "wof:coterminous":[
        404476321
    ],
    "wof:name":"Ashland",
    "wof:placetype":"locality",
    "wof:population":15802,
    "wof:statistical_gore":1
},
  "geometry": {"coordinates":[-71.46339999999999,42.26121],"type":"Point"}
}