{
  "type": "Feature",
  "properties": {
    "gn:country":"US",
    "gn:fcode":"PPL",
    "gn:population":0,
    "iso:country":"US",
    "name:azb_x_preferred":[
        "\u0646\u06cc\u0648\u0627\u0631\u06a9"
    ],
    "name:eng_x_preferred":[
        "Newark"
    ],
    "name:fas_x_preferred":[
        "\u0646\u06cc\u0648\u0622\u0631\u06a9"
    ],
    "name:fra_x_preferred":[
        "Newark"
    ],
    "qs_pg:aaroncc":"US",
    "qs_pg:gn_country":"US",
    "qs_pg:gn_fcode":"PPL",
    "qs_pg:gn_pop":0,
    "qs_pg:name":"Newark",
    "qs_pg:name_adm0":"United States",
    "qs_pg:name_adm1":"Nebraska",
    "qs_pg:photos":469,
    "qs_pg:photos_1k":95,
    "qs_pg:photos_9k":2,
    "qs_pg:photos_9r":5,
    "qs_pg:photos_all":469,
    "qs_pg:photos_sr":7,
    "qs_pg:pop_sr":0,
    "qs_pg:qs_pg_placetype":"locality",
    "qs_pg:qs_pg_placetype_gp":"Town",
    "qs_pg:woe_adm0":23424977,
    "woe:adm0_id":23424977,
    "woe:name_adm0":"United States",
    "woe:name_adm1":"Nebraska",
    "woe:placetype":"Town",
    "wof:name":"Newark",
    "wof:placetype":"locality"
},
  "geometry": {"coordinates":[-98.96314,40.64112],"type":"Point"}
}