{
  "type": "Feature",
  "properties": {
    "gn:elevation":451,
    "iso:country":"US",
    "name:arz_x_preferred":[
        "\u0645\u0637\u0627\u0631 \u0627\u0648\u0631\u064a\u062c\u0648\u0646 \u0627\u0644\u0627\u0642\u0644\u064a\u0645\u0649 \u0627\u0644\u0634\u0631\u0642\u0649"
    ],
    "name:ceb_x_preferred":[
        "Eastern Oregon Regional Airport"
    ],
    "name:eng_x_preferred":[
        "Eastern Oregon Regional Airport"
    ],
    "name:eng_x_variant":[
        "PDT",
        "KPDT",
        "Pendleton Army Airfield",
        "Pendleton Regional Airport"
    ],
    "name:fas_x_preferred":[
        "\u0641\u0631\u0648\u062f\u06af\u0627\u0647 \u0645\u0646\u0637\u0642\u0647\u200c\u0627\u06cc \u0627\u06cc\u0633\u062a\u0631\u0646 \u0627\u0631\u06cc\u06af\u0646"
    ],
    "name:fra_x_preferred":[
        "a\u00e9rodrome d'Eastern Oregon Rgnl At Pendleton"
    ],
    "name:jpn_x_preferred":[
        "Eastern Oregon\u5730\u57df\u7a7a\u6e2f"
    ],
    "name:ron_x_preferred":[
        "Aeroportul Regional Eastern Oregon"
    ],
    "name:tgk_x_preferred":[
        "\u0424\u0443\u0440\u0443\u0434\u0433\u043e\u04b3\u0438 \u043c\u0430\u043d\u0442\u0430\u049b\u0430\u200c\u0438\u0439 \u043e\u0438\u0441\u0442\u0440\u043d \u043e\u0440\u0438\u0433\u043d"
    ],
    "name:und_x_variant":[
        "Pendleton Municipal Airport"
    ],
    "name:urd_x_preferred":[
        "\u0627\u06cc\u0633\u0679\u0631\u0646 \u0627\u0648\u0631\u06cc\u06af\u0648\u0646 \u0631\u06cc\u062c\u0646\u0644 \u06c1\u0648\u0627\u0626\u06cc \u0627\u0688\u0627"
    ],
    "oa:elevation_ft":"1497",
    "oa:type":"medium_airport",
    "wd:wordcount":872,
    "woe:hierarchy":{
        "country_id":23424977,
        "county_id":12589721,
        "planet_id":1,
        "state_id":2347596
    },
    "wof:name":"Eastern Oregon Regional Airport",
    "wof:placetype":"campus"
},
  "geometry": {"coordinates":[-118.841003,45.695099],"type":"Point"}
}