{
  "type": "Feature",
  "properties": {
    "iso:country":"US",
    "name:eng_x_preferred":[
        "Harbordale"
    ],
    "qs:gn_adm0_cc":"US",
    "qs:gn_local":4155966,
    "qs:gn_nam_loc":"Fort Lauderdale, Broward, Florida, US",
    "qs:gn_namadm1":"FL",
    "qs:local_max":9605,
    "qs:local_sum":52477,
    "qs:localhoods":58,
    "qs:name":"Harbordale",
    "qs:name_adm0":"United States",
    "qs:name_adm1":"Florida",
    "qs:name_adm2":"Broward",
    "qs:name_local":"Fort Lauderdale",
    "qs:photo_max":403,
    "qs:photo_sum":3998,
    "qs:placetype":"Suburb",
    "qs:quad_count":83,
    "qs:woe_adm0":23424977,
    "qs:woe_adm1":2347568,
    "qs:woe_adm2":12587808,
    "qs:woe_lau":0,
    "qs:woe_local":2405797,
    "qs:woe_ver":"7.10.0",
    "wof:lang":[
        "eng"
    ],
    "wof:name":"Harbordale",
    "wof:placetype":"neighbourhood",
    "wof:population":2347,
    "zs:blockids":[
        120110423013007,
        120110423013009,
        120110423013008,
        120110423021027,
        120110423011037,
        120110423021022,
        120110423021023,
        120110423011036,
        120110423021025,
        120110901021005,
        120110901021009,
        120110423011032,
        120110423021004,
        120110423011040,
        120110901021013,
        120110423021021,
        120110423012005,
        120110423011027,
        120110423011026,
        120110423011028,
        120110423011030,
        120110901021007,
        120110423011025,
        120110423011031,
        120110901021015,
        120110901021029,
        120110423011023,
        120110901021004,
        120110423012001,
        120110423012003,
        120110423012004,
        120110423012008,
        120110423021008,
        120110423021001,
        120110423011039,
        120110901021021,
        120110901021012,
        120110423011038,
        120110901021022,
        120110423021000,
        120110423021026,
        120110423012000,
        120110801025000,
        120110423011034,
        120110423021003,
        120110901021030,
        120110901021031,
        120110423012002,
        120110423021024,
        120110423021002,
        120110901021014,
        120110901021011,
        120110423011029,
        120110423011035,
        120110423021005
    ],
    "zs:housing10":1869,
    "zs:pop10":2347
},
  "geometry": {"coordinates":[-80.129687,26.102282],"type":"Point"}
}