{
  "type": "Feature",
  "properties": {
    "iso:country":"US",
    "name:ast_x_preferred":[
        "Finn"
    ],
    "name:bre_x_preferred":[
        "Finn"
    ],
    "name:ceb_x_preferred":[
        "Finn"
    ],
    "name:ces_x_preferred":[
        "Finn"
    ],
    "name:deu_x_preferred":[
        "Finn"
    ],
    "name:fin_x_preferred":[
        "Finn"
    ],
    "name:fra_x_preferred":[
        "Finn"
    ],
    "name:heb_x_preferred":[
        "\u05e4\u05d9\u05df"
    ],
    "name:hun_x_preferred":[
        "Finn"
    ],
    "name:ita_x_preferred":[
        "Finn"
    ],
    "name:lat_x_preferred":[
        "Finnus"
    ],
    "name:nds_x_preferred":[
        "Finn"
    ],
    "name:nld_x_preferred":[
        "Finn"
    ],
    "name:nor_x_preferred":[
        "Finn"
    ],
    "name:pol_x_preferred":[
        "Finn"
    ],
    "name:por_x_preferred":[
        "Finn"
    ],
    "name:rus_x_preferred":[
        "\u0424\u0438\u043d\u043d"
    ],
    "name:spa_x_preferred":[
        "Finn"
    ],
    "name:swe_x_preferred":[
        "Finn"
    ],
    "name:tur_x_preferred":[
        "Finn"
    ],
    "name:ukr_x_preferred":[
        "\u0424\u0456\u043d\u043d"
    ],
    "qs_pg:aaroncc":"US",
    "qs_pg:name":"Finn",
    "qs_pg:name_adm0":"United States",
    "qs_pg:name_adm1":"Oregon",
    "qs_pg:photos":492,
    "qs_pg:photos_1k":100,
    "qs_pg:photos_9k":2,
    "qs_pg:photos_9r":5,
    "qs_pg:photos_all":492,
    "qs_pg:photos_sr":7,
    "qs_pg:pop_sr":0,
    "qs_pg:qs_pg_placetype":"locality",
    "qs_pg:qs_pg_placetype_gp":"Town",
    "qs_pg:woe_adm0":23424977,
    "woe:adm0_id":23424977,
    "woe:name_adm0":"United States",
    "woe:name_adm1":"Oregon",
    "woe:placetype":"Town",
    "wof:name":"Finn",
    "wof:placetype":"locality"
},
  "geometry": {"coordinates":[-123.236287,44.082475],"type":"Point"}
}