{
  "type": "Feature",
  "properties": {
    "gn:admin1_code":"GA",
    "gn:admin2_code":"67",
    "gn:asciiname":"Ridgewood Park",
    "gn:country_code":"US",
    "gn:dem":308,
    "gn:elevation":"295.0",
    "gn:feature_class":"P",
    "gn:feature_code":"PPL",
    "gn:name":"Ridgewood Park",
    "gn:population":0,
    "gn:timezone":"America/New_York",
    "iso:country":"US",
    "name:ceb_x_preferred":[
        "Ridgewood Park"
    ],
    "name:swe_x_preferred":[
        "Ridgewood Park"
    ],
    "wof:name":"Ridgewood Park",
    "wof:placetype":"locality"
},
  "geometry": {"coordinates":[-84.61688000000002,33.95427],"type":"Point"}
}