{
  "type": "Feature",
  "properties": {
    "gn:elevation":101,
    "iso:country":"US",
    "name:arz_x_preferred":[
        "\u0645\u0643\u062c\u0631\u0627\u062b \u0627\u064a\u0631\u067e\u0648\u0631\u062a"
    ],
    "name:ceb_x_preferred":[
        "McGrath Airport"
    ],
    "name:eng_x_preferred":[
        "Mcgrath Airport"
    ],
    "name:eng_x_variant":[
        "MCG",
        "PAMC",
        "McGrath Airport"
    ],
    "name:fas_x_preferred":[
        "\u0641\u0631\u0648\u062f\u06af\u0627\u0647 \u0645\u06a9\u200c\u06af\u0631\u0627\u062b"
    ],
    "name:fas_x_variant":[
        "\u0641\u0631\u0648\u062f\u06af\u0627\u0647 \u0645\u06a9 \u06af\u0631\u0627\u062a"
    ],
    "name:pol_x_preferred":[
        "Port lotniczy McGrath"
    ],
    "name:ron_x_preferred":[
        "Aeroportul McGrath"
    ],
    "name:rus_x_preferred":[
        "\u041c\u0430\u043a\u0433\u0440\u0430\u0442"
    ],
    "name:rus_x_variant":[
        "\u0410\u044d\u0440\u043e\u043f\u043e\u0440\u0442 \u041c\u0430\u043a-\u0413\u0440\u0430\u0442",
        "\u041c\u0430\u043a-\u0413\u0440\u0430\u0442"
    ],
    "name:tgk_x_preferred":[
        "\u0424\u0443\u0440\u0443\u0434\u0433\u043e\u04b3\u0438 \u043c\u0430\u043a\u200c\u0433\u0430\u0440\u043e"
    ],
    "name:zho_x_preferred":[
        "\u8056\u4f50\u6cbb"
    ],
    "oa:elevation_ft":"341",
    "oa:type":"medium_airport",
    "wd:wordcount":448,
    "woe:hierarchy":{
        "country_id":23424977,
        "county_id":12587579,
        "planet_id":1,
        "state_id":2347560
    },
    "wof:name":"Mcgrath Airport",
    "wof:placetype":"campus"
},
  "geometry": {"coordinates":[-155.60600299999999,62.9529],"type":"Point"}
}