{
  "type": "Feature",
  "properties": {
    "gn:admin1_code":"MD",
    "gn:admin2_code":"5.0",
    "gn:asciiname":"Carrollwood Manor",
    "gn:country_code":"US",
    "gn:dem":7,
    "gn:elevation":"8.0",
    "gn:feature_class":"P",
    "gn:feature_code":"PPL",
    "gn:name":"Carrollwood Manor",
    "gn:population":0,
    "gn:timezone":"America/New_York",
    "iso:country":"US",
    "wof:name":"Carrollwood Manor",
    "wof:placetype":"locality"
},
  "geometry": {"coordinates":[-76.38385,39.32983],"type":"Point"}
}