{
  "type": "Feature",
  "properties": {
    "iso:country":"US",
    "name:ceb_x_preferred":[
        "Crane Creek"
    ],
    "name:deu_x_preferred":[
        "Crane Creek"
    ],
    "name:eng_x_preferred":[
        "Crane Creek"
    ],
    "name:eng_x_variant":[
        "Crane Crk",
        "Highlands"
    ],
    "name:fra_x_preferred":[
        "Crane Creek"
    ],
    "name:pol_x_preferred":[
        "Crane Creek"
    ],
    "name:swe_x_preferred":[
        "Crane Creek"
    ],
    "qs:gn_adm0_cc":"US",
    "qs:gn_local":5586437,
    "qs:local_max":3422,
    "qs:local_sum":26185,
    "qs:localhoods":36,
    "qs:name":"Crane Creek",
    "qs:name_adm0":"United States",
    "qs:name_adm1":"Idaho",
    "qs:name_adm2":"Ada",
    "qs:name_local":"Boise",
    "qs:photo_max":88,
    "qs:photo_sum":202,
    "qs:placetype":"Suburb",
    "qs:quad_count":19,
    "qs:woe_adm0":23424977,
    "qs:woe_adm1":2347571,
    "qs:woe_adm2":12588034,
    "qs:woe_lau":0,
    "qs:woe_local":2366355,
    "qs:woe_ver":"7.10.0",
    "wd:wordcount":32,
    "wof:lang":[
        "eng"
    ],
    "wof:name":"Crane Creek",
    "wof:placetype":"neighbourhood",
    "wof:population":3195,
    "zs:blockids":[
        160010002022018,
        160010002021032,
        160010002021033,
        160010002024001,
        160010002021047,
        160010002023008,
        160010002021037,
        160010002023007,
        160010002021042,
        160010002021013,
        160010002021016,
        160010002023011,
        160010002023016,
        160010002021028,
        160010002021030,
        160010002022016,
        160010002021002,
        160010002023017,
        160010002021010,
        160010002024006,
        160010002024002,
        160010002023013,
        160010002021029,
        160010002021031,
        160010002021006,
        160010002023004,
        160010002023006,
        160010002023015,
        160010002021003,
        160010002023003,
        160010002024007,
        160010002024003,
        160010002023014,
        160010002023010,
        160010002021015,
        160010002023009,
        160010002023001,
        160010002023002,
        160010002021005,
        160010002024000,
        160010002021004,
        160010002021009,
        160010002023005,
        160010002021012,
        160010002022017,
        160010002023000,
        160010002023012,
        160010002011002,
        160010002021008
    ],
    "zs:housing10":1332,
    "zs:pop10":3195
},
  "geometry": {"coordinates":[-116.200771,43.651456],"type":"Point"}
}