{
  "type": "Feature",
  "properties": {
    "iso:country":"US",
    "name:ceb_x_preferred":[
        "Cottonwood Creek"
    ],
    "name:deu_x_preferred":[
        "Cottonwood Creek"
    ],
    "name:eng_x_preferred":[
        "Cottonwood Creek"
    ],
    "name:swe_x_preferred":[
        "Cottonwood Creek"
    ],
    "wd:wordcount":33,
    "wof:name":"Cottonwood Creek",
    "wof:placetype":"neighbourhood",
    "wof:population":1031,
    "zs:area_m":2221144.318231,
    "zs:blockids":[
        130570906012042,
        130570907021014,
        130570906012083,
        130570907014037,
        130570906012046,
        130570907014133,
        130570907014132,
        130570907014064,
        130570906012099,
        130570906012041,
        130570907021042,
        130570907021015,
        130570907021040,
        130570907021016,
        130570907014130,
        130570907014039,
        130570907014035,
        130570906012108,
        130570907014038,
        130570906012109,
        130570906012058,
        130570907021001,
        130570907014056,
        130570906012059,
        130570907014036,
        130570907014058,
        130570906012093,
        130570906012096,
        130570906012095,
        130570907014057,
        130570907021000,
        130570907021002,
        130570906012094,
        130570907021048,
        130570907014040,
        130570906012100,
        130570906012057,
        130570907021043,
        130570907021041,
        130570907021003,
        130570906012097,
        130570907014034,
        130570906012113,
        130570906012098
    ],
    "zs:housing10":478,
    "zs:label":"Cottonwood Creek",
    "zs:pop10":1031
},
  "geometry": {"coordinates":[-84.49670999999999,34.202836],"type":"Point"}
}