{
  "type": "Feature",
  "properties": {
    "gn:admin1_code":"MO",
    "gn:admin2_code":"215.0",
    "gn:admin3_code":"11854.0",
    "gn:asciiname":"Grogan",
    "gn:country_code":"US",
    "gn:dem":398,
    "gn:elevation":"397.0",
    "gn:feature_class":"P",
    "gn:feature_code":"PPL",
    "gn:name":"Grogan",
    "gn:population":0,
    "gn:timezone":"America/Chicago",
    "iso:country":"US",
    "wof:name":"Grogan",
    "wof:placetype":"locality"
},
  "geometry": {"coordinates":[-91.88625999999999,37.15477],"type":"Point"}
}