{
  "type": "Feature",
  "properties": {
    "gn:admin1_code":"KY",
    "gn:admin2_code":"39.0",
    "gn:asciiname":"California Hills",
    "gn:country_code":"US",
    "gn:dem":137,
    "gn:elevation":"138.0",
    "gn:feature_class":"P",
    "gn:feature_code":"PPL",
    "gn:name":"California Hills",
    "gn:population":0,
    "gn:timezone":"America/Chicago",
    "iso:country":"US",
    "wof:name":"California Hills",
    "wof:placetype":"locality"
},
  "geometry": {"coordinates":[-88.85343,36.93748],"type":"Point"}
}