{
  "type": "Feature",
  "properties": {
    "iso:country":"US",
    "name:eng_x_preferred":[
        "Downtown Carrollton"
    ],
    "qs:gn_adm0_cc":"US",
    "qs:gn_local":4186416,
    "qs:gn_nam_loc":"Carrollton, Carroll, Georgia, US",
    "qs:gn_namadm1":"GA",
    "qs:local_max":881,
    "qs:local_sum":1182,
    "qs:localhoods":4,
    "qs:name":"Downtown Carrollton",
    "qs:name_adm0":"United States",
    "qs:name_adm1":"Georgia",
    "qs:name_adm2":"Carroll",
    "qs:name_local":"Carrollton",
    "qs:photo_max":116,
    "qs:photo_sum":252,
    "qs:placetype":"Suburb",
    "qs:quad_count":17,
    "qs:woe_adm0":23424977,
    "qs:woe_adm1":2347569,
    "qs:woe_adm2":12587891,
    "qs:woe_lau":0,
    "qs:woe_local":2375544,
    "qs:woe_ver":"7.10.0",
    "wof:lang":[
        "eng"
    ],
    "wof:name":"Downtown Carrollton",
    "wof:placetype":"neighbourhood",
    "wof:population":1768,
    "zs:blockids":[
        130459106003015,
        130459111002002,
        130459111005006,
        130459111002007,
        130459111002008,
        130459110003000,
        130459111005031,
        130459105014005,
        130459111005027,
        130459111005036,
        130459106003030,
        130459105014004,
        130459111005007,
        130459111003009,
        130459111005001,
        130459106003039,
        130459106003020,
        130459106003034,
        130459111005008,
        130459111002015,
        130459105023027,
        130459110001021,
        130459105023008,
        130459106003037,
        130459105012028,
        130459111003001,
        130459105012031,
        130459111005010
    ],
    "zs:housing10":675,
    "zs:pop10":1768
},
  "geometry": {"coordinates":[-85.08642,33.569625],"type":"Point"}
}