{
  "type": "Feature",
  "properties": {
    "gn:admin1_code":"PA",
    "gn:admin2_code":"91",
    "gn:admin3_code":"43312.0",
    "gn:asciiname":"Summer Chase",
    "gn:country_code":"US",
    "gn:dem":98,
    "gn:elevation":"99.0",
    "gn:feature_class":"P",
    "gn:feature_code":"PPL",
    "gn:name":"Summer Chase",
    "gn:population":0,
    "gn:timezone":"America/New_York",
    "iso:country":"US",
    "wof:name":"Summer Chase",
    "wof:placetype":"locality"
},
  "geometry": {"coordinates":[-75.5324,40.2361],"type":"Point"}
}