{
  "type": "Feature",
  "properties": {
    "gn:admin1_code":"FL",
    "gn:admin2_code":"57",
    "gn:asciiname":"Dixie Terrace",
    "gn:country_code":"US",
    "gn:dem":24,
    "gn:elevation":"15.0",
    "gn:feature_class":"P",
    "gn:feature_code":"PPL",
    "gn:name":"Dixie Terrace",
    "gn:population":0,
    "gn:timezone":"America/New_York",
    "iso:country":"US",
    "wof:name":"Dixie Terrace",
    "wof:placetype":"locality"
},
  "geometry": {"coordinates":[-82.4507,28.0129],"type":"Point"}
}