{
  "type": "Feature",
  "properties": {
    "gn:admin1_code":"KS",
    "gn:admin2_code":"173",
    "gn:admin3_code":"36250.0",
    "gn:asciiname":"Chisholm Creek Manor Mobile Home Park",
    "gn:country_code":"US",
    "gn:dem":412,
    "gn:elevation":"409.0",
    "gn:feature_class":"P",
    "gn:feature_code":"PPL",
    "gn:name":"Chisholm Creek Manor Mobile Home Park",
    "gn:population":0,
    "gn:timezone":"America/Chicago",
    "iso:country":"US",
    "wof:name":"Chisholm Creek Manor Mobile Home Park",
    "wof:placetype":"campus"
},
  "geometry": {"coordinates":[-97.33184,37.80196],"type":"Point"}
}