{
  "type": "Feature",
  "properties": {
    "gn:admin1_code":"MD",
    "gn:admin2_code":"13.0",
    "gn:asciiname":"Dinterman",
    "gn:country_code":"US",
    "gn:dem":153,
    "gn:elevation":"152.0",
    "gn:feature_class":"P",
    "gn:feature_code":"PPL",
    "gn:name":"Dinterman",
    "gn:population":0,
    "gn:timezone":"America/New_York",
    "iso:country":"US",
    "wof:name":"Dinterman",
    "wof:placetype":"locality"
},
  "geometry": {"coordinates":[-77.25748,39.63204],"type":"Point"}
}