{
  "type": "Feature",
  "properties": {
    "gn:admin1_code":"WA",
    "gn:admin2_code":"39.0",
    "gn:asciiname":"Blockhouse",
    "gn:country_code":"US",
    "gn:dem":486,
    "gn:elevation":"486.0",
    "gn:feature_class":"P",
    "gn:feature_code":"PPL",
    "gn:name":"Blockhouse",
    "gn:population":0,
    "gn:timezone":"America/Los_Angeles",
    "iso:country":"US",
    "name:afr_x_preferred":[
        "Blokhuis"
    ],
    "name:ara_x_preferred":[
        "\u062d\u0635\u0646 \u0635\u063a\u064a\u0631"
    ],
    "name:ces_x_preferred":[
        "Blockhaus"
    ],
    "name:deu_x_preferred":[
        "Blockhaus"
    ],
    "name:epo_x_preferred":[
        "Blokha\u016dso"
    ],
    "name:fra_x_preferred":[
        "Fortin militaire"
    ],
    "name:fry_x_preferred":[
        "Blokh\u00fbs"
    ],
    "name:heb_x_preferred":[
        "\u05d1\u05dc\u05d5\u05e7\u05d4\u05d0\u05d5\u05e1"
    ],
    "name:ido_x_preferred":[
        "Blokhauso"
    ],
    "name:ind_x_preferred":[
        "Blockhouse"
    ],
    "name:lat_x_preferred":[
        "Burgus"
    ],
    "name:lit_x_preferred":[
        "Blokhausas"
    ],
    "name:msa_x_preferred":[
        "Blok kebal"
    ],
    "name:nld_x_preferred":[
        "Blokhuis"
    ],
    "name:nno_x_preferred":[
        "Blokkhus"
    ],
    "name:pol_x_preferred":[
        "Blokhauz"
    ],
    "name:por_x_preferred":[
        "Blocausse"
    ],
    "name:rus_x_preferred":[
        "\u0411\u043b\u043e\u043a\u0433\u0430\u0443\u0437"
    ],
    "name:spa_x_preferred":[
        "Blocao"
    ],
    "name:srp_x_preferred":[
        "\u0411\u043b\u043e\u043a\u0445\u0430\u0443\u0437"
    ],
    "name:swe_x_preferred":[
        "Blockhus"
    ],
    "name:ukr_x_preferred":[
        "\u0411\u043b\u043e\u043a\u0433\u0430\u0443\u0437"
    ],
    "name:vie_x_preferred":[
        "L\u00f4 c\u1ed1t"
    ],
    "wof:name":"Blockhouse",
    "wof:placetype":"locality"
},
  "geometry": {"coordinates":[-120.93756999999999,45.83957],"type":"Point"}
}