{
  "type": "Feature",
  "properties": {
    "gn:admin1_code":"TX",
    "gn:admin2_code":"177.0",
    "gn:asciiname":"Schoolland",
    "gn:country_code":"US",
    "gn:dem":112,
    "gn:elevation":"111.0",
    "gn:feature_class":"P",
    "gn:feature_code":"PPL",
    "gn:name":"Schoolland",
    "gn:population":0,
    "gn:timezone":"America/Chicago",
    "iso:country":"US",
    "wof:name":"Schoolland",
    "wof:placetype":"locality"
},
  "geometry": {"coordinates":[-97.66444,29.33385],"type":"Point"}
}