{
  "type": "Feature",
  "properties": {
    "gn:admin1_code":"TX",
    "gn:admin2_code":"407.0",
    "gn:asciiname":"Staley",
    "gn:country_code":"US",
    "gn:dem":88,
    "gn:elevation":"80.0",
    "gn:feature_class":"P",
    "gn:feature_code":"PPL",
    "gn:name":"Staley",
    "gn:population":0,
    "gn:timezone":"America/Chicago",
    "iso:country":"US",
    "name:ceb_x_preferred":[
        "Staley"
    ],
    "name:deu_x_preferred":[
        "Staley"
    ],
    "name:ita_x_preferred":[
        "Staley"
    ],
    "name:por_x_preferred":[
        "Staley"
    ],
    "name:rus_x_preferred":[
        "\u0421\u0442\u044d\u0439\u043b\u0438"
    ],
    "name:swe_x_preferred":[
        "Staley"
    ],
    "wof:name":"Staley",
    "wof:placetype":"locality"
},
  "geometry": {"coordinates":[-95.29216,30.8338],"type":"Point"}
}