{
  "type": "Feature",
  "properties": {
    "gn:admin1_code":"TX",
    "gn:admin2_code":"93.0",
    "gn:asciiname":"Amity",
    "gn:country_code":"US",
    "gn:dem":489,
    "gn:elevation":"489.0",
    "gn:feature_class":"P",
    "gn:feature_code":"PPL",
    "gn:name":"Amity",
    "gn:population":0,
    "gn:timezone":"America/Chicago",
    "iso:country":"US",
    "name:cat_x_preferred":[
        "Amity"
    ],
    "name:ceb_x_preferred":[
        "Amity"
    ],
    "name:deu_x_preferred":[
        "Amity"
    ],
    "name:fra_x_preferred":[
        "Amity"
    ],
    "name:ita_x_preferred":[
        "Amity"
    ],
    "name:nld_x_preferred":[
        "Amity"
    ],
    "name:pol_x_preferred":[
        "Amity"
    ],
    "name:por_x_preferred":[
        "Amity"
    ],
    "name:spa_x_preferred":[
        "Amity"
    ],
    "name:srp_x_preferred":[
        "\u0410\u043c\u0438\u0442\u0438"
    ],
    "name:ukr_x_preferred":[
        "\u0415\u0439\u043c\u0456\u0442\u0456"
    ],
    "name:vol_x_preferred":[
        "Amity"
    ],
    "name:zho_x_preferred":[
        "\u963f\u7c73\u8482"
    ],
    "wof:name":"Amity",
    "wof:placetype":"locality"
},
  "geometry": {"coordinates":[-98.88367,32.05931],"type":"Point"}
}