{
  "type": "Feature",
  "properties": {
    "iso:country":"US",
    "name:eng_x_preferred":[
        "Musical Heights"
    ],
    "wof:name":"Musical Heights",
    "wof:placetype":"neighbourhood",
    "wof:population":839,
    "zs:area_m":1614330.007962,
    "zs:blockids":[
        450910616023017,
        450910616023018,
        450910616023016,
        450910616023007,
        450910616023014,
        450910616023015
    ],
    "zs:housing10":395,
    "zs:label":"Musical Heights",
    "zs:pop10":839
},
  "geometry": {"coordinates":[-81.220214,34.989567],"type":"Point"}
}