{
  "type": "Feature",
  "properties": {
    "gn:admin1_code":"MS",
    "gn:admin2_code":"91.0",
    "gn:asciiname":"New Hope",
    "gn:country_code":"US",
    "gn:dem":77,
    "gn:elevation":"73.0",
    "gn:feature_class":"P",
    "gn:feature_code":"PPL",
    "gn:name":"New Hope",
    "gn:population":0,
    "gn:timezone":"America/Chicago",
    "iso:country":"US",
    "name:cat_x_preferred":[
        "New Hope"
    ],
    "name:ceb_x_preferred":[
        "New Hope"
    ],
    "name:ces_x_preferred":[
        "New Hope"
    ],
    "name:deu_x_preferred":[
        "New Hope"
    ],
    "name:fra_x_preferred":[
        "New Hope"
    ],
    "name:ita_x_preferred":[
        "New Hope"
    ],
    "name:jpn_x_preferred":[
        "\u30cb\u30e5\u30fc\u30db\u30fc\u30d7"
    ],
    "name:nld_x_preferred":[
        "New Hope"
    ],
    "name:pol_x_preferred":[
        "New Hope"
    ],
    "name:spa_x_preferred":[
        "New Hope"
    ],
    "name:srp_x_preferred":[
        "\u040a\u0443 \u0425\u043e\u0443\u043f"
    ],
    "name:swe_x_preferred":[
        "New Hope"
    ],
    "name:ukr_x_preferred":[
        "\u041d\u044c\u044e-\u0413\u043e\u0443\u043f"
    ],
    "name:vol_x_preferred":[
        "New Hope"
    ],
    "wof:name":"New Hope",
    "wof:placetype":"locality"
},
  "geometry": {"coordinates":[-89.91342,31.15768],"type":"Point"}
}