{
  "type": "Feature",
  "properties": {
    "gn:admin1_code":"GA",
    "gn:admin2_code":"293",
    "gn:asciiname":"Topeka Junction",
    "gn:country_code":"US",
    "gn:dem":250,
    "gn:elevation":"247.0",
    "gn:feature_class":"P",
    "gn:feature_code":"PPL",
    "gn:name":"Topeka Junction",
    "gn:population":0,
    "gn:timezone":"America/New_York",
    "iso:country":"US",
    "wof:name":"Topeka Junction",
    "wof:placetype":"locality"
},
  "geometry": {"coordinates":[-84.20853000000002,32.97457],"type":"Point"}
}