{
  "type": "Feature",
  "properties": {
    "iso:country":"US",
    "name:eng_x_preferred":[
        "High Country Dream"
    ],
    "qs:gn_local":0,
    "qs:local_max":818,
    "qs:local_sum":2149,
    "qs:localhoods":12,
    "qs:name":"High Country Dream",
    "qs:name_adm0":"United States",
    "qs:name_adm1":"Colorado",
    "qs:name_adm2":"Mesa",
    "qs:name_local":"Grand Junction",
    "qs:photo_max":10,
    "qs:photo_sum":33,
    "qs:placetype":"Suburb",
    "qs:quad_count":8,
    "qs:woe_adm0":23424977,
    "qs:woe_adm1":2347564,
    "qs:woe_adm2":12587766,
    "qs:woe_lau":0,
    "qs:woe_local":2412807,
    "qs:woe_ver":"7.10.0",
    "wof:lang":[
        "eng"
    ],
    "wof:name":"High Country Dream",
    "wof:placetype":"neighbourhood",
    "wof:population":91,
    "zs:blockids":[
        80770019001065
    ],
    "zs:housing10":42,
    "zs:pop10":91
},
  "geometry": {"coordinates":[-108.59760799999999,39.036576],"type":"Point"}
}