{
  "type": "Feature",
  "properties": {
    "iso:country":"US",
    "name:eng_x_preferred":[
        "Village at Antigua"
    ],
    "wof:name":"Village at Antigua",
    "wof:placetype":"neighbourhood",
    "wof:population":2715,
    "zs:area_m":3394791.278833,
    "zs:blockids":[
        121030250113006,
        121030250071001,
        121030250071003,
        121030250072019,
        121030250071009,
        121030250071012,
        121030250113027,
        121030250111039,
        121030250072051,
        121030250072013,
        121030250072015,
        121030251121000,
        121030250113008,
        121030250113022,
        121030250113023,
        121030250113021,
        121030250113016,
        121030250072002,
        121030250072057,
        121030250071010,
        121030250072043,
        121030250071013,
        121030250113024,
        121030250072004,
        121030250071000,
        121030250072006,
        121030250113007,
        121030250071002,
        121030250072007,
        121030250072049,
        121030250072014,
        121030250071004,
        121030250072017,
        121030250113019,
        121030250113012,
        121030250113005,
        121030250113014,
        121030250072000,
        121030250113011,
        121030250072009,
        121030250071014,
        121030250113013,
        121030250071011,
        121030250123023,
        121030250113025,
        121030250113026,
        121030250072005,
        121030251142000,
        121030250113020,
        121030250072001,
        121030250113018,
        121030250072003,
        121030250072052,
        121030250113015,
        121030250072050
    ],
    "zs:housing10":1209,
    "zs:label":"Village at Antigua",
    "zs:pop10":2715
},
  "geometry": {"coordinates":[-82.772594,27.860568],"type":"Point"}
}