{
  "type": "Feature",
  "properties": {
    "gn:admin1_code":"CA",
    "gn:admin2_code":"71.0",
    "gn:asciiname":"North Star Ranch",
    "gn:country_code":"US",
    "gn:dem":1041,
    "gn:elevation":"1040.0",
    "gn:feature_class":"P",
    "gn:feature_code":"PPL",
    "gn:name":"North Star Ranch",
    "gn:population":0,
    "gn:timezone":"America/Los_Angeles",
    "iso:country":"US",
    "wof:name":"North Star Ranch",
    "wof:placetype":"locality"
},
  "geometry": {"coordinates":[-117.35921,34.43417],"type":"Point"}
}