{
  "type": "Feature",
  "properties": {
    "gn:admin1_code":"CA",
    "gn:admin2_code":"111.0",
    "gn:asciiname":"Villa del Arroyo Mobile Home Estates",
    "gn:country_code":"US",
    "gn:dem":188,
    "gn:elevation":"186.0",
    "gn:feature_class":"P",
    "gn:feature_code":"PPL",
    "gn:name":"Villa del Arroyo Mobile Home Estates",
    "gn:population":0,
    "gn:timezone":"America/Los_Angeles",
    "iso:country":"US",
    "wof:name":"Villa del Arroyo Mobile Home Estates",
    "wof:placetype":"campus"
},
  "geometry": {"coordinates":[-118.83454,34.29028],"type":"Point"}
}