{
  "type": "Feature",
  "properties": {
    "gn:admin1_code":"MO",
    "gn:admin2_code":"179.0",
    "gn:admin3_code":"11530.0",
    "gn:asciiname":"Melton",
    "gn:country_code":"US",
    "gn:dem":402,
    "gn:elevation":"402.0",
    "gn:feature_class":"P",
    "gn:feature_code":"PPL",
    "gn:name":"Melton",
    "gn:population":0,
    "gn:timezone":"America/Chicago",
    "iso:country":"US",
    "name:ara_x_preferred":[
        "\u0645\u064a\u0644\u062a\u0648\u0646"
    ],
    "name:bar_x_preferred":[
        "Melton"
    ],
    "name:ben_x_preferred":[
        "\u09ae\u09c7\u09b2\u09cd\u099f\u09a8"
    ],
    "name:ceb_x_preferred":[
        "Melton"
    ],
    "name:ces_x_preferred":[
        "Melton"
    ],
    "name:deu_x_preferred":[
        "Melton"
    ],
    "name:ell_x_preferred":[
        "\u039c\u03ad\u03bb\u03c4\u03bf\u03bd"
    ],
    "name:fra_x_preferred":[
        "Melton"
    ],
    "name:heb_x_preferred":[
        "\u05de\u05dc\u05d8\u05d5\u05df"
    ],
    "name:hin_x_preferred":[
        "\u092e\u0947\u0932\u094d\u091f\u0928"
    ],
    "name:hun_x_preferred":[
        "Melton"
    ],
    "name:ind_x_preferred":[
        "Melton"
    ],
    "name:ita_x_preferred":[
        "Melton"
    ],
    "name:jpn_x_preferred":[
        "\u30e1\u30eb\u30c8\u30f3"
    ],
    "name:kor_x_preferred":[
        "\uba5c\ud134 \ub098\uc0ac"
    ],
    "name:mlg_x_preferred":[
        "Melton"
    ],
    "name:nld_x_preferred":[
        "Melton"
    ],
    "name:pol_x_preferred":[
        "Melton"
    ],
    "name:rus_x_preferred":[
        "\u041c\u0435\u043b\u0442\u043e\u043d"
    ],
    "name:spa_x_preferred":[
        "Melton"
    ],
    "name:swe_x_preferred":[
        "Melton"
    ],
    "name:tur_x_preferred":[
        "Melton"
    ],
    "name:ukr_x_preferred":[
        "\u041c\u0435\u043b\u0442\u043e\u043d"
    ],
    "name:vie_x_preferred":[
        "Melton"
    ],
    "wof:name":"Melton",
    "wof:placetype":"locality"
},
  "geometry": {"coordinates":[-91.18013000000001,37.42838],"type":"Point"}
}