{
  "type": "Feature",
  "properties": {
    "gn:admin1_code":"MO",
    "gn:admin2_code":"73.0",
    "gn:admin3_code":"6814.0",
    "gn:asciiname":"Swiss",
    "gn:country_code":"US",
    "gn:dem":277,
    "gn:elevation":"276.0",
    "gn:feature_class":"P",
    "gn:feature_code":"PPL",
    "gn:name":"Swiss",
    "gn:population":0,
    "gn:timezone":"America/Chicago",
    "iso:country":"US",
    "wof:name":"Swiss",
    "wof:placetype":"locality"
},
  "geometry": {"coordinates":[-91.47127,38.56282],"type":"Point"}
}