{
  "type": "Feature",
  "properties": {
    "gn:admin1_code":"KY",
    "gn:admin2_code":"231",
    "gn:asciiname":"Ramsey Island",
    "gn:country_code":"US",
    "gn:dem":309,
    "gn:elevation":"313.0",
    "gn:feature_class":"P",
    "gn:feature_code":"PPL",
    "gn:name":"Ramsey Island",
    "gn:population":0,
    "gn:timezone":"America/Kentucky/Monticello",
    "iso:country":"US",
    "name:bre_x_preferred":[
        "Ynys Dewi"
    ],
    "name:ceb_x_preferred":[
        "Ramsey Island"
    ],
    "name:cym_x_preferred":[
        "Ynys Dewi"
    ],
    "name:eng_x_preferred":[
        "Ramsey Island"
    ],
    "name:ita_x_preferred":[
        "Isola Ramsey"
    ],
    "name:nno_x_preferred":[
        "Ramsey Island"
    ],
    "name:olo_x_preferred":[
        "Ynys Dewi"
    ],
    "name:pol_x_preferred":[
        "Ramsey"
    ],
    "name:spa_x_preferred":[
        "Isla Ramsey"
    ],
    "name:swe_x_preferred":[
        "Ramsey Island"
    ],
    "name:und_x_variant":[
        "Mount Union",
        "Seedtick",
        "Ramsey Branch"
    ],
    "name:urd_x_preferred":[
        "\u062c\u0632\u06cc\u0631\u06c1 \u0631\u06cc\u0645\u0633\u06cc"
    ],
    "wof:name":"Ramsey Island",
    "wof:placetype":"locality"
},
  "geometry": {"coordinates":[-84.98245,36.81118],"type":"Point"}
}