{
  "type": "Feature",
  "properties": {
    "gn:country":"US",
    "gn:fcode":"PPL",
    "gn:population":0,
    "iso:country":"US",
    "name:azb_x_preferred":[
        "\u0645\u06cc\u062f\u0648\u0627\u06cc"
    ],
    "name:eng_x_preferred":[
        "Midway"
    ],
    "name:fas_x_preferred":[
        "\u0645\u06cc\u062f\u0648\u06cc"
    ],
    "name:fra_x_preferred":[
        "Midway"
    ],
    "name:urd_x_preferred":[
        "\u0645\u0688\u0648\u06d2"
    ],
    "name:zho_x_preferred":[
        "\u7c73\u5fb7\u97cb"
    ],
    "qs_pg:aaroncc":"US",
    "qs_pg:gn_country":"US",
    "qs_pg:gn_fcode":"PPL",
    "qs_pg:gn_pop":0,
    "qs_pg:name":"Midway",
    "qs_pg:name_adm0":"United States",
    "qs_pg:name_adm1":"Delaware",
    "qs_pg:photos":134,
    "qs_pg:photos_1k":27,
    "qs_pg:photos_9k":1,
    "qs_pg:photos_9r":3,
    "qs_pg:photos_all":134,
    "qs_pg:photos_sr":3,
    "qs_pg:pop_sr":0,
    "qs_pg:qs_pg_placetype":"locality",
    "qs_pg:qs_pg_placetype_gp":"Town",
    "qs_pg:woe_adm0":23424977,
    "woe:adm0_id":23424977,
    "woe:name_adm0":"United States",
    "woe:name_adm1":"Delaware",
    "woe:placetype":"Town",
    "wof:name":"Midway",
    "wof:placetype":"locality"
},
  "geometry": {"coordinates":[-75.12935,38.72817],"type":"Point"}
}