{
  "type": "Feature",
  "properties": {
    "gn:gn_country":"US",
    "gn:gn_fcode":"PPL",
    "gn:gn_pop":0,
    "iso:country":"US",
    "name:ceb_x_preferred":[
        "Buckeye"
    ],
    "name:deu_x_preferred":[
        "Buckeye"
    ],
    "name:eng_x_preferred":[
        "Buckeye"
    ],
    "name:fra_x_preferred":[
        "Buckeye"
    ],
    "name:hye_x_preferred":[
        "\u0532\u0561\u056f\u0561\u0575"
    ],
    "name:ita_x_preferred":[
        "Buckeye"
    ],
    "name:nld_x_preferred":[
        "Buckeye"
    ],
    "name:pol_x_preferred":[
        "Buckeye"
    ],
    "name:por_x_preferred":[
        "Buckeye"
    ],
    "name:rus_x_preferred":[
        "\u0411\u0430\u043a\u0430\u0439"
    ],
    "name:srp_x_preferred":[
        "\u0411\u0430\u043a\u0430\u0458"
    ],
    "name:ukr_x_preferred":[
        "\u0411\u0430\u043a\u0430\u0439"
    ],
    "name:unk_x_variant":[
        "Ohio City"
    ],
    "name:urd_x_preferred":[
        "\u0628\u06a9\u0622\u0626\u06cc"
    ],
    "name:vol_x_preferred":[
        "Buckeye"
    ],
    "qs_pg:aaroncc":"US",
    "qs_pg:gn_country":"US",
    "qs_pg:gn_fcode":"PPL",
    "qs_pg:gn_pop":0,
    "qs_pg:name":"Buckeye",
    "qs_pg:name_adm0":"United States",
    "qs_pg:name_adm1":"California",
    "qs_pg:photos":36,
    "qs_pg:photos_1k":7,
    "qs_pg:photos_9k":1,
    "qs_pg:photos_9r":2,
    "qs_pg:photos_all":36,
    "qs_pg:photos_sr":2,
    "qs_pg:pop_sr":0,
    "qs_pg:qs_pg_placetype":"locality",
    "qs_pg:qs_pg_placetype_gp":"Town",
    "qs_pg:woe_adm0":23424977,
    "woe:adm0_id":23424977,
    "woe:name_adm0":"United States",
    "woe:name_adm1":"California",
    "woe:placetype":"Town",
    "wof:name":"Buckeye",
    "wof:placetype":"locality"
},
  "geometry": {"coordinates":[-122.39751,40.64348],"type":"Point"}
}