{
  "type": "Feature",
  "properties": {
    "gn:admin1_code":"SC",
    "gn:admin2_code":"83.0",
    "gn:asciiname":"Calico",
    "gn:country_code":"US",
    "gn:dem":238,
    "gn:elevation":"240.0",
    "gn:feature_class":"P",
    "gn:feature_code":"PPL",
    "gn:name":"Calico",
    "gn:population":0,
    "gn:timezone":"America/New_York",
    "iso:country":"US",
    "name:ces_x_preferred":[
        "Kaliko"
    ],
    "name:deu_x_preferred":[
        "Kaliko"
    ],
    "name:epo_x_preferred":[
        "Kalikoto"
    ],
    "name:eus_x_preferred":[
        "Kaliko"
    ],
    "name:fin_x_preferred":[
        "Kaliko"
    ],
    "name:fra_x_preferred":[
        "Calicot"
    ],
    "name:hin_x_preferred":[
        "\u0915\u0948\u0932\u093f\u0915\u094b"
    ],
    "name:ido_x_preferred":[
        "Kaliko"
    ],
    "name:ita_x_preferred":[
        "Calic\u00f2"
    ],
    "name:jpn_x_preferred":[
        "\u30ad\u30e3\u30e9\u30b3"
    ],
    "name:kor_x_preferred":[
        "\uc625\uc591\ubaa9"
    ],
    "name:mal_x_preferred":[
        "\u0d15\u0d3e\u0d32\u0d3f\u0d15\u0d4d\u0d15\u0d4b"
    ],
    "name:nno_x_preferred":[
        "Kaliko"
    ],
    "name:pol_x_preferred":[
        "Kaliko"
    ],
    "name:por_x_preferred":[
        "Calic\u00f4"
    ],
    "name:rus_x_preferred":[
        "\u0421\u0438\u0442\u0435\u0446"
    ],
    "name:slk_x_preferred":[
        "Kaliko"
    ],
    "name:spa_x_preferred":[
        "Calic\u00f3"
    ],
    "name:swa_x_preferred":[
        "Marekani"
    ],
    "name:swe_x_preferred":[
        "Kalik\u00e5"
    ],
    "name:ukr_x_preferred":[
        "\u0421\u0438\u0442\u0435\u0446\u044c"
    ],
    "wof:name":"Calico",
    "wof:placetype":"locality"
},
  "geometry": {"coordinates":[-81.79455,34.90763],"type":"Point"}
}