{
  "type": "Feature",
  "properties": {
    "gn:admin1_code":"VA",
    "gn:admin2_code":"770",
    "gn:asciiname":"Wilmont Park",
    "gn:country_code":"US",
    "gn:dem":318,
    "gn:elevation":"322.0",
    "gn:feature_class":"P",
    "gn:feature_code":"PPL",
    "gn:name":"Wilmont Park",
    "gn:population":0,
    "gn:timezone":"America/New_York",
    "iso:country":"US",
    "wof:name":"Wilmont Park",
    "wof:placetype":"locality"
},
  "geometry": {"coordinates":[-80.00309,37.28291],"type":"Point"}
}