{
  "type": "Feature",
  "properties": {
    "gn:admin1_code":"FL",
    "gn:admin2_code":"57",
    "gn:asciiname":"Pretty Lake Estates",
    "gn:country_code":"US",
    "gn:dem":21,
    "gn:elevation":"15.0",
    "gn:feature_class":"P",
    "gn:feature_code":"PPL",
    "gn:name":"Pretty Lake Estates",
    "gn:population":0,
    "gn:timezone":"America/New_York",
    "iso:country":"US",
    "wof:name":"Pretty Lake Estates",
    "wof:placetype":"locality"
},
  "geometry": {"coordinates":[-82.5639,28.1056],"type":"Point"}
}