{
  "type": "Feature",
  "properties": {
    "gn:admin1_code":"PA",
    "gn:admin2_code":"45.0",
    "gn:admin3_code":"79000.0",
    "gn:asciiname":"Primos",
    "gn:country_code":"US",
    "gn:dem":59,
    "gn:elevation":"56.0",
    "gn:feature_class":"P",
    "gn:feature_code":"PPL",
    "gn:name":"Primos",
    "gn:population":0,
    "gn:timezone":"America/New_York",
    "iso:country":"US",
    "wof:name":"Primos",
    "wof:placetype":"locality"
},
  "geometry": {"coordinates":[-75.30658000000003,39.92039000000001],"type":"Point"}
}