{
  "type": "Feature",
  "properties": {
    "gn:admin1_code":"NC",
    "gn:admin2_code":"57",
    "gn:admin3_code":"91796.0",
    "gn:asciiname":"Bryans Woods",
    "gn:country_code":"US",
    "gn:dem":217,
    "gn:elevation":"215.0",
    "gn:feature_class":"P",
    "gn:feature_code":"PPL",
    "gn:name":"Bryans Woods",
    "gn:population":0,
    "gn:timezone":"America/New_York",
    "iso:country":"US",
    "wof:name":"Bryans Woods",
    "wof:placetype":"locality"
},
  "geometry": {"coordinates":[-80.22199000000001,35.86569],"type":"Point"}
}