{
  "type": "Feature",
  "properties": {
    "gn:admin1_code":"MS",
    "gn:admin2_code":"053",
    "gn:asciiname":"Refuge",
    "gn:country_code":"US",
    "gn:dem":35,
    "gn:elevation":"35.0",
    "gn:feature_class":"P",
    "gn:feature_code":"PPL",
    "gn:name":"Refuge",
    "gn:population":0,
    "gn:timezone":"America/Chicago",
    "iso:country":"US",
    "name:cat_x_preferred":[
        "Refugi"
    ],
    "name:deu_x_preferred":[
        "Refuge"
    ],
    "name:fra_x_preferred":[
        "Refuge"
    ],
    "name:nld_x_preferred":[
        "Refuge"
    ],
    "wof:name":"Refuge",
    "wof:placetype":"locality"
},
  "geometry": {"coordinates":[-90.33453,33.13707],"type":"Point"}
}