{
  "type": "Feature",
  "properties": {
    "gn:country":"US",
    "gn:fcode":"PPL",
    "gn:population":0,
    "iso:country":"US",
    "name:azb_x_preferred":[
        "\u0642\u0648\u0634\u0646"
    ],
    "name:eng_x_preferred":[
        "Goshen"
    ],
    "name:fas_x_preferred":[
        "\u06af\u0648\u0634\u0646"
    ],
    "name:fra_x_preferred":[
        "Goshen"
    ],
    "name:urd_x_preferred":[
        "\u06af\u0648\u0634\u06cc\u0646"
    ],
    "qs_pg:aaroncc":"US",
    "qs_pg:gn_country":"US",
    "qs_pg:gn_fcode":"PPL",
    "qs_pg:gn_pop":0,
    "qs_pg:name":"Goshen",
    "qs_pg:name_adm0":"United States",
    "qs_pg:name_adm1":"New Jersey",
    "qs_pg:photos":148,
    "qs_pg:photos_1k":30,
    "qs_pg:photos_9k":1,
    "qs_pg:photos_9r":3,
    "qs_pg:photos_all":148,
    "qs_pg:photos_sr":3,
    "qs_pg:pop_sr":0,
    "qs_pg:qs_pg_placetype":"locality",
    "qs_pg:qs_pg_placetype_gp":"Town",
    "qs_pg:woe_adm0":23424977,
    "woe:adm0_id":23424977,
    "woe:name_adm0":"United States",
    "woe:name_adm1":"New Jersey",
    "woe:placetype":"Town",
    "wof:name":"Goshen",
    "wof:placetype":"locality"
},
  "geometry": {"coordinates":[-74.85295000000001,39.1415],"type":"Point"}
}