{
  "type": "Feature",
  "properties": {
    "iso:country":"US",
    "name:eng_x_preferred":[
        "Ardmore at Reedy Creek"
    ],
    "wof:name":"Ardmore at Reedy Creek",
    "wof:placetype":"neighbourhood",
    "wof:population":86,
    "zs:area_m":9681.325946,
    "zs:blockids":[
        371830535203000
    ],
    "zs:housing10":36,
    "zs:label":"Ardmore at Reedy Creek",
    "zs:pop10":86
},
  "geometry": {"coordinates":[-78.770121,35.802278],"type":"Point"}
}