{
  "type": "Feature",
  "properties": {
    "gn:admin1_code":"FL",
    "gn:admin2_code":"57",
    "gn:asciiname":"Country Breeze Estates",
    "gn:country_code":"US",
    "gn:dem":32,
    "gn:elevation":"24.0",
    "gn:feature_class":"P",
    "gn:feature_code":"PPL",
    "gn:name":"Country Breeze Estates",
    "gn:population":0,
    "gn:timezone":"America/New_York",
    "iso:country":"US",
    "wof:name":"Country Breeze Estates",
    "wof:placetype":"locality"
},
  "geometry": {"coordinates":[-82.15170000000001,27.9481],"type":"Point"}
}