{
  "type": "Feature",
  "properties": {
    "gn:admin1_code":"SC",
    "gn:admin2_code":"21.0",
    "gn:asciiname":"Garden Park",
    "gn:country_code":"US",
    "gn:dem":243,
    "gn:elevation":"246.0",
    "gn:feature_class":"P",
    "gn:feature_code":"PPL",
    "gn:name":"Garden Park",
    "gn:population":0,
    "gn:timezone":"America/New_York",
    "iso:country":"US",
    "name:pol_x_preferred":[
        "Garden Park"
    ],
    "wof:name":"Garden Park",
    "wof:placetype":"locality"
},
  "geometry": {"coordinates":[-81.69232,35.12013],"type":"Point"}
}