{
  "type": "Feature",
  "properties": {
    "iso:country":"US",
    "name:ceb_x_preferred":[
        "Wharton"
    ],
    "name:deu_x_preferred":[
        "Wharton"
    ],
    "name:fas_x_preferred":[
        "\u0648\u0627\u0631\u062a\u0648\u0646"
    ],
    "name:fra_x_preferred":[
        "Wharton"
    ],
    "name:ita_x_preferred":[
        "Wharton"
    ],
    "name:nds_x_preferred":[
        "Wharton"
    ],
    "name:nld_x_preferred":[
        "Wharton"
    ],
    "name:pol_x_preferred":[
        "Wharton"
    ],
    "name:por_x_preferred":[
        "Wharton"
    ],
    "name:rus_x_preferred":[
        "\u0423\u043e\u0440\u0442\u043e\u043d"
    ],
    "name:srp_x_preferred":[
        "\u0412\u043e\u0440\u0442\u043e\u043d"
    ],
    "name:swe_x_preferred":[
        "Wharton"
    ],
    "name:vol_x_preferred":[
        "Wharton"
    ],
    "qs_pg:aaroncc":"US",
    "qs_pg:name":"Wharton",
    "qs_pg:name_adm0":"United States",
    "qs_pg:name_adm1":"Pennsylvania",
    "qs_pg:photos":66,
    "qs_pg:photos_1k":13,
    "qs_pg:photos_9k":1,
    "qs_pg:photos_9r":4,
    "qs_pg:photos_all":291,
    "qs_pg:photos_sr":2,
    "qs_pg:pop_sr":0,
    "qs_pg:qs_pg_placetype":"locality",
    "qs_pg:qs_pg_placetype_gp":"Town",
    "qs_pg:woe_adm0":23424977,
    "woe:adm0_id":23424977,
    "woe:name_adm0":"United States",
    "woe:name_adm1":"Pennsylvania",
    "woe:placetype":"Town",
    "wof:name":"Wharton",
    "wof:placetype":"locality"
},
  "geometry": {"coordinates":[-79.683752,39.764576],"type":"Point"}
}