{
  "type": "Feature",
  "properties": {
    "gn:admin1_code":"KY",
    "gn:admin2_code":"109",
    "gn:asciiname":"Royrader",
    "gn:country_code":"US",
    "gn:dem":322,
    "gn:elevation":"315.0",
    "gn:feature_class":"P",
    "gn:feature_code":"PPL",
    "gn:name":"Royrader",
    "gn:population":0,
    "gn:timezone":"America/New_York",
    "iso:country":"US",
    "wof:name":"Royrader",
    "wof:placetype":"locality"
},
  "geometry": {"coordinates":[-83.94298000000001,37.2637],"type":"Point"}
}