{
  "type": "Feature",
  "properties": {
    "gn:admin1_code":"DE",
    "gn:admin2_code":"3.0",
    "gn:asciiname":"Fox Chase Park",
    "gn:country_code":"US",
    "gn:dem":25,
    "gn:elevation":"25.0",
    "gn:feature_class":"P",
    "gn:feature_code":"PPL",
    "gn:name":"Fox Chase Park",
    "gn:population":0,
    "gn:timezone":"America/New_York",
    "iso:country":"US",
    "wof:name":"Fox Chase Park",
    "wof:placetype":"locality"
},
  "geometry": {"coordinates":[-75.68299,39.67511],"type":"Point"}
}