{
  "type": "Feature",
  "properties": {
    "gn:country":"US",
    "gn:fcode":"PPL",
    "gn:population":0,
    "iso:country":"US",
    "name:ceb_x_preferred":[
        "Riverview"
    ],
    "name:deu_x_preferred":[
        "Riverview"
    ],
    "name:fra_x_preferred":[
        "Riverview"
    ],
    "name:ind_x_preferred":[
        "Riverview"
    ],
    "name:ita_x_preferred":[
        "Riverview"
    ],
    "name:mlg_x_preferred":[
        "Riverview"
    ],
    "name:nld_x_preferred":[
        "Riverview"
    ],
    "name:pol_x_preferred":[
        "Riverview"
    ],
    "name:por_x_preferred":[
        "Riverview"
    ],
    "name:ron_x_preferred":[
        "Riverview"
    ],
    "name:rus_x_preferred":[
        "\u0420\u0438\u0432\u0435\u0440\u0432\u044c\u044e"
    ],
    "name:srp_x_preferred":[
        "\u0420\u0438\u0432\u0435\u0440\u0432\u0458\u0443"
    ],
    "name:swe_x_preferred":[
        "Riverview"
    ],
    "name:vol_x_preferred":[
        "Riverview"
    ],
    "qs_pg:aaroncc":"US",
    "qs_pg:gn_country":"US",
    "qs_pg:gn_fcode":"PPL",
    "qs_pg:gn_pop":0,
    "qs_pg:name":"Riverview",
    "qs_pg:name_adm0":"United States",
    "qs_pg:name_adm1":"Louisiana",
    "qs_pg:photos":127,
    "qs_pg:photos_1k":26,
    "qs_pg:photos_9k":1,
    "qs_pg:photos_9r":3,
    "qs_pg:photos_all":127,
    "qs_pg:photos_sr":3,
    "qs_pg:pop_sr":0,
    "qs_pg:qs_pg_placetype":"locality",
    "qs_pg:qs_pg_placetype_gp":"Town",
    "qs_pg:woe_adm0":23424977,
    "woe:adm0_id":23424977,
    "woe:name_adm0":"United States",
    "woe:name_adm1":"Louisiana",
    "woe:placetype":"Town",
    "wof:name":"Riverview",
    "wof:placetype":"locality"
},
  "geometry": {"coordinates":[-90.99594,30.4613],"type":"Point"}
}