{
  "type": "Feature",
  "properties": {
    "iso:country":"US",
    "name:ces_x_preferred":[
        "Wilhelm"
    ],
    "name:deu_x_preferred":[
        "Wilhelm"
    ],
    "name:est_x_preferred":[
        "Wilhelm"
    ],
    "name:fas_x_preferred":[
        "\u0648\u06cc\u0644\u0647\u0644\u0645"
    ],
    "name:fra_x_preferred":[
        "Wilhelm"
    ],
    "name:heb_x_preferred":[
        "\u05d5\u05d9\u05dc\u05d4\u05dc\u05dd"
    ],
    "name:ita_x_preferred":[
        "Wilhelm"
    ],
    "name:jpn_x_preferred":[
        "\u30f4\u30a3\u30eb\u30d8\u30eb\u30e0"
    ],
    "name:kor_x_preferred":[
        "\ube4c\ud5ec\ub984"
    ],
    "name:nld_x_preferred":[
        "Wilhelm"
    ],
    "name:pol_x_preferred":[
        "Wilhelm"
    ],
    "name:rus_x_preferred":[
        "\u0412\u0438\u043b\u044c\u0433\u0435\u043b\u044c\u043c"
    ],
    "name:spa_x_preferred":[
        "Wilhelm"
    ],
    "name:swe_x_preferred":[
        "Wilhelm"
    ],
    "qs_pg:aaroncc":"US",
    "qs_pg:name":"Wilhelm",
    "qs_pg:name_adm0":"United States",
    "qs_pg:name_adm1":"Pennsylvania",
    "qs_pg:photos":1,
    "qs_pg:photos_1k":1,
    "qs_pg:photos_9k":1,
    "qs_pg:photos_9r":1,
    "qs_pg:photos_all":1,
    "qs_pg:photos_sr":1,
    "qs_pg:pop_sr":0,
    "qs_pg:qs_pg_placetype":"locality",
    "qs_pg:qs_pg_placetype_gp":"Town",
    "qs_pg:woe_adm0":23424977,
    "woe:adm0_id":23424977,
    "woe:name_adm0":"United States",
    "woe:name_adm1":"Pennsylvania",
    "woe:placetype":"Town",
    "wof:name":"Wilhelm",
    "wof:placetype":"locality"
},
  "geometry": {"coordinates":[-76.79130000000001,40.220567],"type":"Point"}
}