{
  "type": "Feature",
  "properties": {
    "gn:elevation":82,
    "iso:country":"US",
    "name:eng_x_preferred":[
        "Massabesic"
    ],
    "name:eng_x_variant":[
        "Massabesic Lake"
    ],
    "name:fra_x_preferred":[
        "Massabesic Lake"
    ],
    "qs:gn_adm0_cc":"US",
    "qs:gn_fcode":"PPL",
    "qs:gn_local":5089178,
    "qs:gn_nam_loc":"manchester",
    "qs:gn_namadm1":"NH",
    "qs:gn_name":"Massabesic",
    "qs:local_max":3386,
    "qs:local_sum":6998,
    "qs:localhoods":11,
    "qs:name":"Massabesic",
    "qs:name_adm0":"United States",
    "qs:name_adm1":"New Hampshire",
    "qs:name_adm2":"Hillsborough",
    "qs:name_local":"Manchester",
    "qs:photo_max":33,
    "qs:photo_sum":66,
    "qs:placetype":"Suburb",
    "qs:quad_count":5,
    "qs:woe_adm0":23424977,
    "qs:woe_adm1":2347588,
    "qs:woe_adm2":12589253,
    "qs:woe_lau":0,
    "qs:woe_local":2444674,
    "qs:woe_ver":"7.10.0",
    "wd:wordcount":264,
    "wof:lang":[
        "eng"
    ],
    "wof:name":"Massabesic",
    "wof:placetype":"neighbourhood",
    "wof:population":386,
    "zs:blockids":[
        330110010001010,
        330110009021002,
        330110010001028,
        330110009022007,
        330110010001004,
        330110010001012,
        330110010001000,
        330110010001011,
        330110009021000,
        330110009022005,
        330110010001008,
        330110009022006,
        330110010001002,
        330110009021001,
        330110010001027,
        330110009022004,
        330110010001030,
        330110010001007,
        330110010001013,
        330110010003000,
        330110010003001,
        330110010001005,
        330110010001003,
        330110010001006,
        330110009022021,
        330110010001001,
        330110009022000,
        330110010001009,
        330110009022001,
        330110009022008,
        330110010001029,
        330110009022002
    ],
    "zs:housing10":135,
    "zs:pop10":386
},
  "geometry": {"coordinates":[-71.391284,43.002851],"type":"Point"}
}