{
  "type": "Feature",
  "properties": {
    "iso:country":"US",
    "name:eng_x_preferred":[
        "Port Johnson"
    ],
    "name:eng_x_variant":[
        "Pt Johnson"
    ],
    "qs:gn_adm0_cc":"US",
    "qs:gn_fcode":"PPL",
    "qs:gn_local":5095445,
    "qs:gn_nam_loc":"bayonne",
    "qs:gn_namadm1":"NJ",
    "qs:gn_name":"Port Johnson",
    "qs:local_max":424,
    "qs:local_sum":1195,
    "qs:localhoods":5,
    "qs:name":"Port Johnson",
    "qs:name_adm0":"United States",
    "qs:name_adm1":"New Jersey",
    "qs:name_adm2":"Hudson",
    "qs:name_local":"Bayonne",
    "qs:photo_max":4,
    "qs:photo_sum":4,
    "qs:placetype":"Suburb",
    "qs:quad_count":1,
    "qs:woe_adm0":23424977,
    "qs:woe_adm1":2347589,
    "qs:woe_adm2":12589266,
    "qs:woe_funk":"Parented by a neighborhood",
    "qs:woe_lau":0,
    "qs:woe_local":2360347,
    "qs:woe_ver":"7.10.0",
    "wof:lang":[
        "eng"
    ],
    "wof:name":"Port Johnson",
    "wof:placetype":"neighbourhood",
    "wof:population":1719,
    "zs:blockids":[
        340170108001027,
        340170109001021,
        340170108001023,
        340170108001032,
        340170108001034,
        340170113002004,
        340170108001033,
        340170108001028,
        340170108001026,
        340170113001004,
        340170108001036,
        340170114002008,
        340170114003000,
        340170108001035,
        340170108001031,
        340170108001022,
        340170108001024,
        340170108001021,
        340170114001008,
        340170109001020,
        340170114001007,
        340170113002005,
        340170113002006,
        340170114003013,
        340170113003000,
        340170113001002,
        340170108001025,
        340170114001006,
        340170109001019,
        340170108001030
    ],
    "zs:housing10":700,
    "zs:pop10":1719
},
  "geometry": {"coordinates":[-74.116516,40.653557],"type":"Point"}
}