{
  "type": "Feature",
  "properties": {
    "iso:country":"US",
    "name:eng_x_preferred":[
        "Proximity"
    ],
    "wd:wordcount":90,
    "wof:name":"Proximity",
    "wof:placetype":"neighbourhood",
    "wof:population":492,
    "zs:area_m":1228170.674197,
    "zs:blockids":[
        370810103001011,
        370810103002038,
        370810103002045,
        370810103002047,
        370810103002022,
        370810103002023,
        370810103002030,
        370810103002029,
        370810103001013,
        370810103002024,
        370810103002039,
        370810103002031,
        370810103002033,
        370810103002035,
        370810103002028,
        370810103002032,
        370810103001012,
        370810103002025,
        370810103002026,
        370810103002034,
        370810103002021,
        370810103002027,
        370810103001014,
        370810103002059,
        370810103002046,
        370810103002040
    ],
    "zs:housing10":233,
    "zs:label":"Proximity",
    "zs:pop10":492
},
  "geometry": {"coordinates":[-79.781392,36.092172],"type":"Point"}
}