{
  "type": "Feature",
  "properties": {
    "gn:admin1_code":"MD",
    "gn:admin2_code":"17.0",
    "gn:asciiname":"Lakeside Mews",
    "gn:country_code":"US",
    "gn:dem":64,
    "gn:elevation":"64.0",
    "gn:feature_class":"P",
    "gn:feature_code":"PPL",
    "gn:name":"Lakeside Mews",
    "gn:population":0,
    "gn:timezone":"America/New_York",
    "iso:country":"US",
    "wof:name":"Lakeside Mews",
    "wof:placetype":"locality"
},
  "geometry": {"coordinates":[-76.93025,38.6254],"type":"Point"}
}