{
  "type": "Feature",
  "properties": {
    "iso:country":"US",
    "name:eng_x_preferred":[
        "Powhatan Place"
    ],
    "wof:name":"Powhatan Place",
    "wof:placetype":"neighbourhood",
    "wof:population":308,
    "zs:area_m":139338.849616,
    "zs:blockids":[
        510950803031068,
        510950803031067,
        510950803031031,
        510950802062051,
        510950802062054,
        510950803031066,
        510950803031030
    ],
    "zs:housing10":144,
    "zs:label":"Powhatan Place",
    "zs:pop10":308
},
  "geometry": {"coordinates":[-76.766676,37.270355],"type":"Point"}
}