{
  "type": "Feature",
  "properties": {
    "gn:admin1_code":"IN",
    "gn:admin2_code":"143.0",
    "gn:admin3_code":"38772.0",
    "gn:asciiname":"Blocher",
    "gn:country_code":"US",
    "gn:dem":209,
    "gn:elevation":"209.0",
    "gn:feature_class":"P",
    "gn:feature_code":"PPL",
    "gn:name":"Blocher",
    "gn:population":0,
    "gn:timezone":"America/Indiana/Indianapolis",
    "iso:country":"US",
    "name:eng_x_preferred":[
        "Blocher"
    ],
    "name:und_x_variant":[
        "Holman",
        "Holman Station"
    ],
    "wof:name":"Blocher",
    "wof:placetype":"locality"
},
  "geometry": {"coordinates":[-85.65663000000001,38.71811],"type":"Point"}
}