{
  "type": "Feature",
  "properties": {
    "gn:admin1_code":"MN",
    "gn:admin2_code":"171.0",
    "gn:admin3_code":"11800.0",
    "gn:asciiname":"Clearwater Estates",
    "gn:country_code":"US",
    "gn:dem":286,
    "gn:elevation":"290.0",
    "gn:feature_class":"P",
    "gn:feature_code":"PPL",
    "gn:name":"Clearwater Estates",
    "gn:population":0,
    "gn:timezone":"America/Chicago",
    "iso:country":"US",
    "wof:name":"Clearwater Estates",
    "wof:placetype":"locality"
},
  "geometry": {"coordinates":[-94.04028,45.4125],"type":"Point"}
}