{
  "type": "Feature",
  "properties": {
    "gn:admin1_code":"MS",
    "gn:admin2_code":"29.0",
    "gn:asciiname":"Cowanville",
    "gn:country_code":"US",
    "gn:dem":75,
    "gn:elevation":"71.0",
    "gn:feature_class":"P",
    "gn:feature_code":"PPL",
    "gn:name":"Cowanville",
    "gn:population":0,
    "gn:timezone":"America/Chicago",
    "iso:country":"US",
    "wof:name":"Cowanville",
    "wof:placetype":"locality"
},
  "geometry": {"coordinates":[-90.15980999999999,31.75516],"type":"Point"}
}