{
  "type": "Feature",
  "properties": {
    "gn:admin1_code":"DE",
    "gn:admin2_code":"5.0",
    "gn:asciiname":"Arabian Acres",
    "gn:country_code":"US",
    "gn:dem":7,
    "gn:elevation":"7.0",
    "gn:feature_class":"P",
    "gn:feature_code":"PPL",
    "gn:name":"Arabian Acres",
    "gn:population":0,
    "gn:timezone":"America/New_York",
    "iso:country":"US",
    "wof:name":"Arabian Acres",
    "wof:placetype":"locality"
},
  "geometry": {"coordinates":[-75.22629999999999,38.73567],"type":"Point"}
}