{
  "type": "Feature",
  "properties": {
    "gn:admin1_code":"WV",
    "gn:admin2_code":"77",
    "gn:asciiname":"Herring",
    "gn:country_code":"US",
    "gn:dem":613,
    "gn:elevation":"611.0",
    "gn:feature_class":"P",
    "gn:feature_code":"PPL",
    "gn:name":"Herring",
    "gn:population":0,
    "gn:timezone":"America/New_York",
    "iso:country":"US",
    "name:ces_x_preferred":[
        "Sle\u010f"
    ],
    "name:fas_x_preferred":[
        "\u0634\u0627\u0647\u200c\u0645\u0627\u0647\u06cc"
    ],
    "name:fra_x_preferred":[
        "Hareng frais"
    ],
    "name:gom_x_preferred":[
        "Dawak"
    ],
    "name:hrv_x_preferred":[
        "Haringe"
    ],
    "name:ind_x_preferred":[
        "Haring"
    ],
    "name:jpn_x_preferred":[
        "\u30cb\u30b7\u30f3"
    ],
    "name:msa_x_preferred":[
        "Ikan hering"
    ],
    "name:pol_x_preferred":[
        "\u015aled\u017a"
    ],
    "name:slk_x_preferred":[
        "Sle\u010f"
    ],
    "name:tha_x_preferred":[
        "\u0e1b\u0e25\u0e32\u0e40\u0e2e\u0e23\u0e4c\u0e23\u0e34\u0e07"
    ],
    "name:yid_x_preferred":[
        "\u05d4\u05e2\u05e8\u05d9\u05e0\u05d2"
    ],
    "wof:name":"Herring",
    "wof:placetype":"locality"
},
  "geometry": {"coordinates":[-79.73810999999998,39.54258],"type":"Point"}
}