{
  "type": "Feature",
  "properties": {
    "gn:admin1_code":"IL",
    "gn:admin2_code":"31.0",
    "gn:admin3_code":"53676.0",
    "gn:asciiname":"Michealsen Subdivision",
    "gn:country_code":"US",
    "gn:dem":211,
    "gn:elevation":"206.0",
    "gn:feature_class":"P",
    "gn:feature_code":"PPL",
    "gn:name":"Michealsen Subdivision",
    "gn:population":0,
    "gn:timezone":"America/Chicago",
    "iso:country":"US",
    "wof:name":"Michealsen Subdivision",
    "wof:placetype":"locality"
},
  "geometry": {"coordinates":[-87.85583000000003,42.11944],"type":"Point"}
}