{
  "type": "Feature",
  "properties": {
    "gn:admin1_code":"PA",
    "gn:admin2_code":"15.0",
    "gn:admin3_code":"57176.0",
    "gn:asciiname":"South Hill",
    "gn:country_code":"US",
    "gn:dem":415,
    "gn:elevation":"414.0",
    "gn:feature_class":"P",
    "gn:feature_code":"PPL",
    "gn:name":"South Hill",
    "gn:population":0,
    "gn:timezone":"America/New_York",
    "iso:country":"US",
    "name:ceb_x_preferred":[
        "South Hill"
    ],
    "name:deu_x_preferred":[
        "South Hill"
    ],
    "name:fra_x_preferred":[
        "South Hill"
    ],
    "name:ita_x_preferred":[
        "South Hill"
    ],
    "name:nld_x_preferred":[
        "South Hill"
    ],
    "name:pol_x_preferred":[
        "South Hill"
    ],
    "name:por_x_preferred":[
        "South Hill"
    ],
    "name:srp_x_preferred":[
        "\u0421\u0430\u0443\u0442 \u0425\u0438\u043b"
    ],
    "name:vol_x_preferred":[
        "South Hill"
    ],
    "wof:name":"South Hill",
    "wof:placetype":"locality"
},
  "geometry": {"coordinates":[-76.26354000000001,41.83591],"type":"Point"}
}