{
  "type": "Feature",
  "properties": {
    "gn:admin1_code":"PA",
    "gn:admin2_code":"15.0",
    "gn:admin3_code":"57176.0",
    "gn:asciiname":"South Hill",
    "gn:country_code":"US",
    "gn:dem":415,
    "gn:elevation":"414.0",
    "gn:feature_class":"P",
    "gn:feature_code":"PPL",
    "gn:name":"South Hill",
    "gn:population":0,
    "gn:timezone":"America/New_York",
    "iso:country":"US",
    "name:ara_x_preferred":[
        "\u0633\u0627\u0648\u062b \u0647\u064a\u0644"
    ],
    "name:ben_x_preferred":[
        "\u09b8\u09be\u0989\u09a5 \u09b9\u09bf\u09b2"
    ],
    "name:ceb_x_preferred":[
        "South Hill"
    ],
    "name:deu_x_preferred":[
        "South Hill"
    ],
    "name:ell_x_preferred":[
        "\u03a3\u03ac\u03bf\u03c5\u03b8 \u03a7\u03b9\u03bb"
    ],
    "name:eng_x_preferred":[
        "South Hill"
    ],
    "name:fas_x_preferred":[
        "\u0633\u0627\u0648\u062a \u0647\u06cc\u0644"
    ],
    "name:fra_x_preferred":[
        "South Hill"
    ],
    "name:heb_x_preferred":[
        "\u05d3\u05e8\u05d5\u05dd \u05d4\u05d9\u05dc"
    ],
    "name:hin_x_preferred":[
        "\u0938\u093e\u0909\u0925 \u0939\u093f\u0932"
    ],
    "name:hun_x_preferred":[
        "South Hill"
    ],
    "name:ind_x_preferred":[
        "South Hill"
    ],
    "name:ita_x_preferred":[
        "South Hill"
    ],
    "name:jpn_x_preferred":[
        "\u30b5\u30a6\u30b9\u30fb\u30d2\u30eb"
    ],
    "name:kor_x_preferred":[
        "\uc0ac\uc6b0\uc2a4 \ud790"
    ],
    "name:nld_x_preferred":[
        "South Hill"
    ],
    "name:pol_x_preferred":[
        "Po\u0142udniowe wzg\u00f3rze"
    ],
    "name:pol_x_variant":[
        "South Hill"
    ],
    "name:por_x_preferred":[
        "South Hill"
    ],
    "name:rus_x_preferred":[
        "\u0421\u0430\u0443\u0442-\u0425\u0438\u043b\u043b"
    ],
    "name:spa_x_preferred":[
        "South Hill"
    ],
    "name:srp_x_preferred":[
        "\u0421\u0430\u0443\u0442 \u0425\u0438\u043b"
    ],
    "name:swe_x_preferred":[
        "South Hill"
    ],
    "name:tur_x_preferred":[
        "South Hill"
    ],
    "name:ukr_x_preferred":[
        "\u0421\u0430\u0443\u0441-\u0425\u0456\u043b\u043b"
    ],
    "name:urd_x_preferred":[
        "\u0633\u0627\u0624\u062a\u06be \u06c1\u0644"
    ],
    "name:vie_x_preferred":[
        "South Hill"
    ],
    "name:vol_x_preferred":[
        "South Hill"
    ],
    "name:zho_cn_x_preferred":[
        "\u5357\u5e0c\u5c14"
    ],
    "name:zho_tw_x_preferred":[
        "\u5357\u5e0c\u723e\u5c71"
    ],
    "wof:name":"South Hill",
    "wof:placetype":"locality"
},
  "geometry": {"coordinates":[-76.26354000000001,41.83591],"type":"Point"}
}