{
  "type": "Feature",
  "properties": {
    "gn:admin1_code":"PA",
    "gn:admin2_code":"61.0",
    "gn:admin3_code":"73072.0",
    "gn:asciiname":"Maddensville",
    "gn:country_code":"US",
    "gn:dem":224,
    "gn:elevation":"222.0",
    "gn:feature_class":"P",
    "gn:feature_code":"PPL",
    "gn:name":"Maddensville",
    "gn:population":0,
    "gn:timezone":"America/New_York",
    "iso:country":"US",
    "wof:name":"Maddensville",
    "wof:placetype":"locality"
},
  "geometry": {"coordinates":[-77.95806,40.12675],"type":"Point"}
}