{
  "type": "Feature",
  "properties": {
    "gn:admin1_code":"OH",
    "gn:admin2_code":"155.0",
    "gn:admin3_code":"13470.0",
    "gn:asciiname":"State Road",
    "gn:country_code":"US",
    "gn:dem":288,
    "gn:elevation":"285.0",
    "gn:feature_class":"P",
    "gn:feature_code":"PPL",
    "gn:name":"State Road",
    "gn:population":0,
    "gn:timezone":"America/New_York",
    "iso:country":"US",
    "wof:name":"State Road",
    "wof:placetype":"locality"
},
  "geometry": {"coordinates":[-80.89787,41.30033],"type":"Point"}
}