{
  "type": "Feature",
  "properties": {
    "gn:admin1_code":"AL",
    "gn:admin2_code":"81.0",
    "gn:asciiname":"Union Crossroads",
    "gn:country_code":"US",
    "gn:dem":193,
    "gn:elevation":"185.0",
    "gn:feature_class":"P",
    "gn:feature_code":"PPL",
    "gn:name":"Union Crossroads",
    "gn:population":0,
    "gn:timezone":"America/Chicago",
    "iso:country":"US",
    "wof:name":"Union Crossroads",
    "wof:placetype":"locality"
},
  "geometry": {"coordinates":[-85.41161,32.57097],"type":"Point"}
}