{
  "type": "Feature",
  "properties": {
    "gn:elevation":319,
    "iso:country":"US",
    "name:eng_x_preferred":[
        "Tompkins Corners"
    ],
    "name:eng_x_variant":[
        "Tompkins Cors"
    ],
    "name:und_x_variant":[
        "Catlin"
    ],
    "qs:gn_fcode":"PPL",
    "qs:gn_local":0,
    "qs:gn_namadm1":"NY",
    "qs:gn_name":"Tompkins Corners",
    "qs:local_max":60,
    "qs:local_sum":60,
    "qs:localhoods":1,
    "qs:name":"Tompkins Corners",
    "qs:name_adm0":"United States",
    "qs:name_adm1":"New York",
    "qs:name_adm2":"Chemung",
    "qs:name_local":"Catlin",
    "qs:photo_max":60,
    "qs:photo_sum":60,
    "qs:placetype":"Suburb",
    "qs:quad_count":1,
    "qs:woe_adm0":23424977,
    "qs:woe_adm1":2347591,
    "qs:woe_adm2":12589319,
    "qs:woe_lau":0,
    "qs:woe_local":28744460,
    "qs:woe_ver":"7.10.0",
    "wof:lang":[
        "eng"
    ],
    "wof:name":"Tompkins Corners",
    "wof:placetype":"neighbourhood"
},
  "geometry": {"coordinates":[-76.91391,42.205124],"type":"Point"}
}