{
  "type": "Feature",
  "properties": {
    "gn:admin1_code":"KY",
    "gn:admin2_code":"183",
    "gn:asciiname":"Taffy",
    "gn:country_code":"US",
    "gn:dem":153,
    "gn:elevation":"148.0",
    "gn:feature_class":"P",
    "gn:feature_code":"PPL",
    "gn:name":"Taffy",
    "gn:population":0,
    "gn:timezone":"America/Chicago",
    "iso:country":"US",
    "name:deu_x_preferred":[
        "Taffy"
    ],
    "wof:name":"Taffy",
    "wof:placetype":"locality"
},
  "geometry": {"coordinates":[-86.89166,37.55394],"type":"Point"}
}