{
  "type": "Feature",
  "properties": {
    "gn:admin1_code":"AZ",
    "gn:admin2_code":"13.0",
    "gn:asciiname":"Royal Palm Travel Trailer and Mobile Home Park",
    "gn:country_code":"US",
    "gn:dem":374,
    "gn:elevation":"375.0",
    "gn:feature_class":"P",
    "gn:feature_code":"PPL",
    "gn:name":"Royal Palm Travel Trailer and Mobile Home Park",
    "gn:population":0,
    "gn:timezone":"America/Phoenix",
    "iso:country":"US",
    "wof:name":"Royal Palm Travel Trailer and Mobile Home Park",
    "wof:placetype":"campus"
},
  "geometry": {"coordinates":[-112.10236999999999,33.57004000000001],"type":"Point"}
}