{
  "type": "Feature",
  "properties": {
    "gn:admin1_code":"MO",
    "gn:admin2_code":"33.0",
    "gn:admin3_code":"41672.0",
    "gn:asciiname":"Mandeville",
    "gn:country_code":"US",
    "gn:dem":297,
    "gn:elevation":"295.0",
    "gn:feature_class":"P",
    "gn:feature_code":"PPL",
    "gn:name":"Mandeville",
    "gn:population":0,
    "gn:timezone":"America/Chicago",
    "iso:country":"US",
    "name:cat_x_preferred":[
        "Mandeville"
    ],
    "name:ceb_x_preferred":[
        "Mandeville"
    ],
    "name:ces_x_preferred":[
        "Mandeville"
    ],
    "name:deu_x_preferred":[
        "Mandeville"
    ],
    "name:fra_x_preferred":[
        "Mandeville"
    ],
    "name:ita_x_preferred":[
        "Mandeville"
    ],
    "name:jpn_x_preferred":[
        "\u30de\u30f3\u30c7\u30d3\u30eb"
    ],
    "name:kor_x_preferred":[
        "\ub9e8\ub354\ube4c"
    ],
    "name:nld_x_preferred":[
        "Mandeville"
    ],
    "name:oci_x_preferred":[
        "Mandeville"
    ],
    "name:pol_x_preferred":[
        "Mandeville"
    ],
    "name:por_x_preferred":[
        "Mandeville"
    ],
    "name:spa_x_preferred":[
        "Mandeville"
    ],
    "name:swe_x_preferred":[
        "Mandeville"
    ],
    "wof:name":"Mandeville",
    "wof:placetype":"locality"
},
  "geometry": {"coordinates":[-93.62105,39.49641],"type":"Point"}
}