{
  "type": "Feature",
  "properties": {
    "gn:admin1_code":"TX",
    "gn:admin2_code":"217.0",
    "gn:asciiname":"Winslow",
    "gn:country_code":"US",
    "gn:dem":187,
    "gn:elevation":"183.0",
    "gn:feature_class":"P",
    "gn:feature_code":"PPL",
    "gn:name":"Winslow",
    "gn:population":0,
    "gn:timezone":"America/Chicago",
    "iso:country":"US",
    "name:ara_x_preferred":[
        "\u0648\u064a\u0646\u0633\u0644\u0648"
    ],
    "name:cat_x_preferred":[
        "Winslow"
    ],
    "name:ceb_x_preferred":[
        "Winslow"
    ],
    "name:deu_x_preferred":[
        "Winslow"
    ],
    "name:fra_x_preferred":[
        "Winslow"
    ],
    "name:heb_x_preferred":[
        "\u05d5\u05d9\u05e0\u05e1\u05dc\u05d5"
    ],
    "name:ita_x_preferred":[
        "Winslow"
    ],
    "name:nld_x_preferred":[
        "Winslow"
    ],
    "name:nor_x_preferred":[
        "Winslow"
    ],
    "name:pol_x_preferred":[
        "Winslow"
    ],
    "name:por_x_preferred":[
        "Winslow"
    ],
    "name:rus_x_preferred":[
        "\u0423\u0438\u043d\u0441\u043b\u043e\u0443"
    ],
    "name:slk_x_preferred":[
        "Winslow"
    ],
    "name:spa_x_preferred":[
        "Winslow"
    ],
    "name:srp_x_preferred":[
        "\u0412\u0438\u043d\u0441\u043b\u043e\u0443"
    ],
    "name:swe_x_preferred":[
        "Winslow"
    ],
    "name:ukr_x_preferred":[
        "\u0412\u0456\u043d\u0441\u043b\u043e\u0432"
    ],
    "name:urd_x_preferred":[
        "\u0648\u06cc\u0646\u0633\u0644\u0648"
    ],
    "name:vol_x_preferred":[
        "Winslow"
    ],
    "wof:name":"Winslow",
    "wof:placetype":"locality"
},
  "geometry": {"coordinates":[-97.12417000000001,31.99599000000001],"type":"Point"}
}