{
  "type": "Feature",
  "properties": {
    "gn:admin1_code":"GA",
    "gn:admin2_code":"321",
    "gn:asciiname":"Shingler",
    "gn:country_code":"US",
    "gn:dem":139,
    "gn:elevation":"137.0",
    "gn:feature_class":"P",
    "gn:feature_code":"PPL",
    "gn:name":"Shingler",
    "gn:population":0,
    "gn:timezone":"America/New_York",
    "iso:country":"US",
    "wof:name":"Shingler",
    "wof:placetype":"locality"
},
  "geometry": {"coordinates":[-83.78461999999998,31.57824],"type":"Point"}
}