{
  "type": "Feature",
  "properties": {
    "gn:admin1_code":"VA",
    "gn:admin2_code":"93",
    "gn:asciiname":"Stotts Crossroads",
    "gn:country_code":"US",
    "gn:dem":29,
    "gn:elevation":"24.0",
    "gn:feature_class":"P",
    "gn:feature_code":"PPL",
    "gn:name":"Stotts Crossroads",
    "gn:population":0,
    "gn:timezone":"America/New_York",
    "iso:country":"US",
    "name:eng_x_preferred":[
        "Stotts Crossroads"
    ],
    "name:und_x_variant":[
        "Stott",
        "Stotts Corners"
    ],
    "wof:name":"Stotts Crossroads",
    "wof:placetype":"locality"
},
  "geometry": {"coordinates":[-76.77024,36.92626],"type":"Point"}
}