{
  "type": "Feature",
  "properties": {
    "iso:country":"US",
    "name:eng_x_preferred":[
        "Bon Ton"
    ],
    "qs:gn_adm0_cc":"US",
    "qs:gn_local":5641727,
    "qs:gn_nam_loc":"Bozeman, Gallatin, Montana, US",
    "qs:gn_namadm1":"MT",
    "qs:local_max":1088,
    "qs:local_sum":4184,
    "qs:localhoods":24,
    "qs:name":"Bon Ton",
    "qs:name_adm0":"United States",
    "qs:name_adm1":"Montana",
    "qs:name_adm2":"Gallatin",
    "qs:name_local":"Bozeman",
    "qs:photo_max":143,
    "qs:photo_sum":497,
    "qs:placetype":"Suburb",
    "qs:quad_count":28,
    "qs:woe_adm0":23424977,
    "qs:woe_adm1":2347585,
    "qs:woe_adm2":12589096,
    "qs:woe_lau":0,
    "qs:woe_local":2367749,
    "qs:woe_ver":"7.10.0",
    "wof:lang":[
        "eng"
    ],
    "wof:name":"Bon Ton",
    "wof:placetype":"neighbourhood"
},
  "geometry": {"coordinates":[-111.050146,45.667583],"type":"Point"}
}