{
  "type": "Feature",
  "properties": {
    "gn:admin1_code":"WV",
    "gn:admin2_code":"17",
    "gn:asciiname":"Central Station",
    "gn:country_code":"US",
    "gn:dem":251,
    "gn:elevation":"244.0",
    "gn:feature_class":"P",
    "gn:feature_code":"PPL",
    "gn:name":"Central Station",
    "gn:population":0,
    "gn:timezone":"America/New_York",
    "iso:country":"US",
    "name:eng_x_preferred":[
        "Central Station"
    ],
    "name:und_x_variant":[
        "Midway Station"
    ],
    "wof:name":"Central Station",
    "wof:placetype":"locality"
},
  "geometry": {"coordinates":[-80.82566,39.29397],"type":"Point"}
}