{
  "type": "Feature",
  "properties": {
    "gn:admin1_code":"GA",
    "gn:admin2_code":"217",
    "gn:asciiname":"Salem Cove",
    "gn:country_code":"US",
    "gn:dem":262,
    "gn:elevation":"261.0",
    "gn:feature_class":"P",
    "gn:feature_code":"PPL",
    "gn:name":"Salem Cove",
    "gn:population":0,
    "gn:timezone":"America/New_York",
    "iso:country":"US",
    "wof:name":"Salem Cove",
    "wof:placetype":"locality"
},
  "geometry": {"coordinates":[-83.97158,33.60372],"type":"Point"}
}