{
  "type": "Feature",
  "properties": {
    "gn:admin1_code":"CT",
    "gn:admin2_code":"11.0",
    "gn:admin3_code":"57040.0",
    "gn:asciiname":"Miami Shores",
    "gn:country_code":"US",
    "gn:dem":8,
    "gn:elevation":"4.0",
    "gn:feature_class":"P",
    "gn:feature_code":"PPL",
    "gn:name":"Miami Shores",
    "gn:population":0,
    "gn:timezone":"America/New_York",
    "iso:country":"US",
    "wof:name":"Miami Shores",
    "wof:placetype":"locality"
},
  "geometry": {"coordinates":[-72.27758,41.28454],"type":"Point"}
}