{
  "type": "Feature",
  "properties": {
    "gn:admin1_code":"OH",
    "gn:admin2_code":"75.0",
    "gn:admin3_code":"66712.0",
    "gn:asciiname":"Stillwell",
    "gn:country_code":"US",
    "gn:dem":270,
    "gn:elevation":"273.0",
    "gn:feature_class":"P",
    "gn:feature_code":"PPL",
    "gn:name":"Stillwell",
    "gn:population":0,
    "gn:timezone":"America/New_York",
    "iso:country":"US",
    "name:eng_x_preferred":[
        "Stillwell"
    ],
    "name:und_x_variant":[
        "Stilwell"
    ],
    "wof:name":"Stillwell",
    "wof:placetype":"locality"
},
  "geometry": {"coordinates":[-82.09432,40.46062],"type":"Point"}
}