{
  "type": "Feature",
  "properties": {
    "iso:country":"US",
    "name:eng_x_preferred":[
        "Holston Heights"
    ],
    "wof:name":"Holston Heights",
    "wof:placetype":"neighbourhood",
    "wof:population":104,
    "zs:area_m":1741061.478637,
    "zs:blockids":[
        471630402001002,
        471630402002037,
        471630402002039,
        471630402002079,
        471630402002035,
        471630402002038,
        471630402002042,
        471630402002097,
        471630402002093,
        471630402002081,
        471630402001016,
        471630402002034,
        471630402002096,
        471630402002091,
        471630402002077,
        471630402002036,
        471630402002024,
        471630402001010,
        471630402002098,
        471630402002087,
        471630402002099,
        471630402002100,
        471630402002095,
        471630402002030,
        471630402002076,
        471630402002021,
        471630402001015,
        471630402001017,
        471630402002089,
        471630402002085,
        471630402002045,
        471630402001004,
        471630402002032,
        471630402002031,
        471630402002073,
        471630402002029,
        471630402002075,
        471630402002086,
        471630402002090,
        471630402001003,
        471630402001009,
        471630402002082,
        471630402002041,
        471630402002078,
        471630402002080,
        471630402001011,
        471630402001019,
        471630402002048,
        471630402002088,
        471630402002033,
        471630402002028,
        471630402002083,
        471630402002092,
        471630402002094,
        471630402002074,
        471630402001018,
        471630402001082,
        471630402002026,
        471630402002025,
        471630402002084,
        471630402002040,
        471630402002015
    ],
    "zs:housing10":82,
    "zs:label":"Holston Heights",
    "zs:pop10":104
},
  "geometry": {"coordinates":[-82.559798,36.539654],"type":"Point"}
}