{
  "type": "Feature",
  "properties": {
    "gn:admin1_code":"GA",
    "gn:admin2_code":"5.0",
    "gn:asciiname":"New Lacy",
    "gn:country_code":"US",
    "gn:dem":60,
    "gn:elevation":"55.0",
    "gn:feature_class":"P",
    "gn:feature_code":"PPL",
    "gn:name":"New Lacy",
    "gn:population":0,
    "gn:timezone":"America/New_York",
    "iso:country":"US",
    "wof:name":"New Lacy",
    "wof:placetype":"locality"
},
  "geometry": {"coordinates":[-82.37151999999998,31.53937],"type":"Point"}
}