{
  "type": "Feature",
  "properties": {
    "gn:admin1_code":"ID",
    "gn:admin2_code":"33.0",
    "gn:asciiname":"Jones Crossing",
    "gn:country_code":"US",
    "gn:dem":1500,
    "gn:elevation":"1499.0",
    "gn:feature_class":"P",
    "gn:feature_code":"PPL",
    "gn:name":"Jones Crossing",
    "gn:population":0,
    "gn:timezone":"America/Boise",
    "iso:country":"US",
    "wof:name":"Jones Crossing",
    "wof:placetype":"locality"
},
  "geometry": {"coordinates":[-112.21943,44.08685],"type":"Point"}
}