{
  "type": "Feature",
  "properties": {
    "gn:admin1_code":"TN",
    "gn:admin2_code":"59",
    "gn:asciiname":"Heritage Hills",
    "gn:country_code":"US",
    "gn:dem":459,
    "gn:elevation":"452.0",
    "gn:feature_class":"P",
    "gn:feature_code":"PPL",
    "gn:name":"Heritage Hills",
    "gn:population":0,
    "gn:timezone":"America/New_York",
    "iso:country":"US",
    "name:cat_x_preferred":[
        "Heritage Hills"
    ],
    "name:ceb_x_preferred":[
        "Heritage Hills"
    ],
    "name:deu_x_preferred":[
        "Heritage Hills"
    ],
    "name:nld_x_preferred":[
        "Heritage Hills"
    ],
    "name:vol_x_preferred":[
        "Heritage Hills"
    ],
    "wof:name":"Heritage Hills",
    "wof:placetype":"locality"
},
  "geometry": {"coordinates":[-82.77986999999997,36.16455],"type":"Point"}
}