{
  "type": "Feature",
  "properties": {
    "gn:admin1_code":"WV",
    "gn:admin2_code":"51.0",
    "gn:asciiname":"Mozart",
    "gn:country_code":"US",
    "gn:dem":383,
    "gn:elevation":"384.0",
    "gn:feature_class":"P",
    "gn:feature_code":"PPL",
    "gn:name":"Mozart",
    "gn:population":0,
    "gn:timezone":"America/New_York",
    "iso:country":"US",
    "wof:name":"Mozart",
    "wof:placetype":"locality"
},
  "geometry": {"coordinates":[-80.7148,40.0323],"type":"Point"}
}