{
  "type": "Feature",
  "properties": {
    "gn:admin1_code":"TN",
    "gn:admin2_code":"63.0",
    "gn:asciiname":"Wilderness Shores",
    "gn:country_code":"US",
    "gn:dem":359,
    "gn:elevation":"358.0",
    "gn:feature_class":"P",
    "gn:feature_code":"PPL",
    "gn:name":"Wilderness Shores",
    "gn:population":0,
    "gn:timezone":"America/New_York",
    "iso:country":"US",
    "wof:name":"Wilderness Shores",
    "wof:placetype":"locality"
},
  "geometry": {"coordinates":[-83.45795,36.17537],"type":"Point"}
}