{
  "type": "Feature",
  "properties": {
    "gn:country":"US",
    "gn:fcode":"PPL",
    "gn:population":0,
    "iso:country":"US",
    "name:eng_x_preferred":[
        "Lewis"
    ],
    "name:fas_x_preferred":[
        "\u0644\u0648\u0626\u06cc\u0633"
    ],
    "name:fra_x_preferred":[
        "Lewis"
    ],
    "name:und_x_variant":[
        "Centreville"
    ],
    "name:urd_x_preferred":[
        "\u0644\u0648\u0626\u06cc\u0633"
    ],
    "qs_pg:aaroncc":"US",
    "qs_pg:gn_country":"US",
    "qs_pg:gn_fcode":"PPL",
    "qs_pg:gn_pop":0,
    "qs_pg:name":"Lewis",
    "qs_pg:name_adm0":"United States",
    "qs_pg:name_adm1":"Indiana",
    "qs_pg:photos_9k":1,
    "qs_pg:photos_9r":1,
    "qs_pg:photos_all":6,
    "qs_pg:photos_sr":0,
    "qs_pg:pop_sr":5,
    "qs_pg:qs_pg_placetype":"locality",
    "qs_pg:qs_pg_placetype_gp":"Town",
    "qs_pg:woe_adm0":23424977,
    "woe:adm0_id":23424977,
    "woe:name_adm0":"United States",
    "woe:name_adm1":"Indiana",
    "woe:placetype":"Town",
    "wof:name":"Lewis",
    "wof:placetype":"locality"
},
  "geometry": {"coordinates":[-87.25752,39.26004],"type":"Point"}
}