{
  "type": "Feature",
  "properties": {
    "gn:admin1_code":"LA",
    "gn:admin2_code":"75.0",
    "gn:asciiname":"Saint Rosalie",
    "gn:country_code":"US",
    "gn:dem":1,
    "gn:elevation":"1.0",
    "gn:feature_class":"P",
    "gn:feature_code":"PPL",
    "gn:name":"Saint Rosalie",
    "gn:population":0,
    "gn:timezone":"America/Chicago",
    "iso:country":"US",
    "wof:name":"Saint Rosalie",
    "wof:placetype":"locality"
},
  "geometry": {"coordinates":[-89.96951,29.66382],"type":"Point"}
}