{
  "type": "Feature",
  "properties": {
    "iso:country":"US",
    "name:eng_x_preferred":[
        "Strathmore Gate East"
    ],
    "qs:gn_adm0_cc":"US",
    "qs:gn_local":4167545,
    "qs:gn_nam_loc":"Palm Harbor, Pinellas, Florida, US",
    "qs:gn_namadm1":"FL",
    "qs:local_max":365,
    "qs:local_sum":929,
    "qs:localhoods":5,
    "qs:name":"Strathmore Gate East",
    "qs:name_adm0":"United States",
    "qs:name_adm1":"Florida",
    "qs:name_adm2":"Pinellas",
    "qs:name_local":"Palm Harbor",
    "qs:photo_max":31,
    "qs:photo_sum":106,
    "qs:placetype":"Suburb",
    "qs:quad_count":9,
    "qs:woe_adm0":23424977,
    "qs:woe_adm1":2347568,
    "qs:woe_adm2":12587854,
    "qs:woe_lau":0,
    "qs:woe_local":2467681,
    "qs:woe_ver":"7.10.0",
    "wof:name":"Strathmore Gate East",
    "wof:placetype":"neighbourhood",
    "wof:population":5232,
    "zs:blockids":[
        121030273151001,
        121030273142024,
        121030273151002,
        121030273141002,
        121030273172021,
        121030273172002,
        121030273232009,
        121030273232006,
        121030273232004,
        121030273141001,
        121030273142017,
        121030273141000,
        121030273172004,
        121030273232008,
        121030273232001,
        121030273141008,
        121030273232002,
        121030273142026,
        121030273172003,
        121030273142019,
        121030273142020,
        121030273142016,
        121030273142013,
        121030273141003,
        121030273232000,
        121030273232007,
        121030273141009,
        121030273232010,
        121030273172000,
        121030273172019,
        121030273172018,
        121030273142025,
        121030273172001,
        121030273232003,
        121030273141006,
        121030273172017,
        121030273142021,
        121030273141004,
        121030273232012,
        121030273232011,
        121030273142014,
        121030273151000,
        121030273151005,
        121030273141005,
        121030273142023,
        121030273141007,
        121030273142015,
        121030273151003,
        121030273142022,
        121030273141010,
        121030273142027,
        121030273232005,
        121030273172020
    ],
    "zs:housing10":2836,
    "zs:pop10":5232
},
  "geometry": {"coordinates":[-82.71256700000001,28.064595],"type":"Point"}
}