{
  "type": "Feature",
  "properties": {
    "gn:admin1_code":"VA",
    "gn:admin2_code":"105",
    "gn:asciiname":"Ben Hur",
    "gn:country_code":"US",
    "gn:dem":447,
    "gn:elevation":"440.0",
    "gn:feature_class":"P",
    "gn:feature_code":"PPL",
    "gn:name":"Ben Hur",
    "gn:population":0,
    "gn:timezone":"America/New_York",
    "iso:country":"US",
    "name:eng_x_preferred":[
        "Ben Hur"
    ],
    "name:und_x_variant":[
        "Benhur"
    ],
    "wof:name":"Ben Hur",
    "wof:placetype":"locality"
},
  "geometry": {"coordinates":[-83.08211,36.73287],"type":"Point"}
}