{
  "type": "Feature",
  "properties": {
    "gn:admin1_code":"WV",
    "gn:admin2_code":"075",
    "gn:asciiname":"Wanless",
    "gn:country_code":"US",
    "gn:dem":915,
    "gn:elevation":"918.0",
    "gn:feature_class":"P",
    "gn:feature_code":"PPL",
    "gn:name":"Wanless",
    "gn:population":0,
    "gn:timezone":"America/New_York",
    "iso:country":"US",
    "name:eng_x_preferred":[
        "Wanless"
    ],
    "name:und_x_variant":[
        "Waniess"
    ],
    "wof:name":"Wanless",
    "wof:placetype":"locality"
},
  "geometry": {"coordinates":[-79.90701,38.43734],"type":"Point"}
}