{
  "type": "Feature",
  "properties": {
    "gn:admin1_code":"MO",
    "gn:admin2_code":"71.0",
    "gn:admin3_code":"64496.0",
    "gn:asciiname":"Clover Bottom",
    "gn:country_code":"US",
    "gn:dem":208,
    "gn:elevation":"209.0",
    "gn:feature_class":"P",
    "gn:feature_code":"PPL",
    "gn:name":"Clover Bottom",
    "gn:population":0,
    "gn:timezone":"America/Chicago",
    "iso:country":"US",
    "wof:name":"Clover Bottom",
    "wof:placetype":"locality"
},
  "geometry": {"coordinates":[-91.11959,38.50366],"type":"Point"}
}