{
  "type": "Feature",
  "properties": {
    "iso:country":"US",
    "name:eng_x_preferred":[
        "Carriage Hills"
    ],
    "wof:name":"Carriage Hills",
    "wof:placetype":"neighbourhood",
    "wof:population":1305,
    "zs:area_m":1288964.469645,
    "zs:blockids":[
        370810125112009,
        370810125114003,
        370810125114011,
        370810125112004,
        370810125112006,
        370810125112016,
        370810125114001,
        370810125114006,
        370810125051007,
        370810125101018,
        370810125114005,
        370810125112010,
        370810125112017,
        370810125112003,
        370810125112005,
        370810161012016,
        370810125112012,
        370810125114002,
        370810125112008,
        370810125114004,
        370810125112007,
        370810125114000,
        370810125112011,
        370810125112018
    ],
    "zs:housing10":534,
    "zs:label":"Carriage Hills",
    "zs:pop10":1305
},
  "geometry": {"coordinates":[-79.868679,36.100643],"type":"Point"}
}