{
  "type": "Feature",
  "properties": {
    "iso:country":"US",
    "name:cym_x_preferred":[
        "Baird"
    ],
    "name:deu_x_preferred":[
        "Baird"
    ],
    "name:eng_x_preferred":[
        "Baird"
    ],
    "name:hun_x_preferred":[
        "Baird"
    ],
    "name:nld_x_preferred":[
        "Baird"
    ],
    "qs_pg:aaroncc":"US",
    "qs_pg:name":"Baird",
    "qs_pg:name_adm0":"United States",
    "qs_pg:name_adm1":"Washington",
    "qs_pg:photos":771,
    "qs_pg:photos_1k":156,
    "qs_pg:photos_9k":3,
    "qs_pg:photos_9r":6,
    "qs_pg:photos_all":771,
    "qs_pg:photos_sr":9,
    "qs_pg:pop_sr":0,
    "qs_pg:qs_pg_placetype":"locality",
    "qs_pg:qs_pg_placetype_gp":"Town",
    "qs_pg:woe_adm0":23424977,
    "woe:adm0_id":23424977,
    "woe:name_adm0":"United States",
    "woe:name_adm1":"Washington",
    "woe:placetype":"Town",
    "wof:name":"Baird",
    "wof:placetype":"locality"
},
  "geometry": {"coordinates":[-119.38705400000001,47.593661],"type":"Point"}
}