{
  "type": "Feature",
  "properties": {
    "gn:admin1_code":"DE",
    "gn:admin2_code":"1.0",
    "gn:asciiname":"Bicentennial Village",
    "gn:country_code":"US",
    "gn:dem":18,
    "gn:elevation":"16.0",
    "gn:feature_class":"P",
    "gn:feature_code":"PPL",
    "gn:name":"Bicentennial Village",
    "gn:population":0,
    "gn:timezone":"America/New_York",
    "iso:country":"US",
    "wof:name":"Bicentennial Village",
    "wof:placetype":"locality"
},
  "geometry": {"coordinates":[-75.55381,39.16539],"type":"Point"}
}