{
  "type": "Feature",
  "properties": {
    "gn:admin1_code":"GA",
    "gn:admin2_code":"75",
    "gn:asciiname":"Staunton",
    "gn:country_code":"US",
    "gn:dem":90,
    "gn:elevation":"90.0",
    "gn:feature_class":"P",
    "gn:feature_code":"PPL",
    "gn:name":"Staunton",
    "gn:population":0,
    "gn:timezone":"America/New_York",
    "iso:country":"US",
    "name:cat_x_preferred":[
        "Staunton"
    ],
    "name:ceb_x_preferred":[
        "Staunton"
    ],
    "name:dan_x_preferred":[
        "Staunton"
    ],
    "name:deu_x_preferred":[
        "Staunton"
    ],
    "name:eng_x_preferred":[
        "Staunton"
    ],
    "name:fin_x_preferred":[
        "Staunton"
    ],
    "name:fra_x_preferred":[
        "Staunton"
    ],
    "name:heb_x_preferred":[
        "\u05e1\u05d8\u05d0\u05d5\u05e0\u05d8\u05d5\u05df"
    ],
    "name:hun_x_preferred":[
        "Staunton"
    ],
    "name:ita_x_preferred":[
        "Staunton"
    ],
    "name:nld_x_preferred":[
        "Staunton"
    ],
    "name:pol_x_preferred":[
        "Staunton"
    ],
    "name:por_x_preferred":[
        "Staunton"
    ],
    "name:rus_x_preferred":[
        "\u0421\u0442\u043e\u043d\u0442\u043e\u043d"
    ],
    "name:spa_x_preferred":[
        "Staunton"
    ],
    "name:srp_x_preferred":[
        "\u0421\u0442\u043e\u043d\u0442\u043e\u043d"
    ],
    "name:swe_x_preferred":[
        "Staunton"
    ],
    "name:ukr_x_preferred":[
        "\u0421\u0442\u043e\u043d\u0442\u043e\u043d"
    ],
    "name:und_x_variant":[
        "Mogal"
    ],
    "name:vol_x_preferred":[
        "Staunton"
    ],
    "wof:name":"Staunton",
    "wof:placetype":"locality"
},
  "geometry": {"coordinates":[-83.46683,31.2813],"type":"Point"}
}