{
  "type": "Feature",
  "properties": {
    "gn:admin1_code":"SC",
    "gn:admin2_code":"61.0",
    "gn:asciiname":"South Lynchburg",
    "gn:country_code":"US",
    "gn:dem":45,
    "gn:elevation":"45.0",
    "gn:feature_class":"P",
    "gn:feature_code":"PPL",
    "gn:name":"South Lynchburg",
    "gn:population":0,
    "gn:timezone":"America/New_York",
    "iso:country":"US",
    "name:eng_x_preferred":[
        "South Lynchburg"
    ],
    "name:und_x_variant":[
        "Lynchburg"
    ],
    "wof:name":"South Lynchburg",
    "wof:placetype":"locality"
},
  "geometry": {"coordinates":[-80.0609,34.05238],"type":"Point"}
}