{
  "type": "Feature",
  "properties": {
    "gn:admin1_code":"KS",
    "gn:admin2_code":"55.0",
    "gn:admin3_code":"25350.0",
    "gn:asciiname":"Balls Trailer Park",
    "gn:country_code":"US",
    "gn:dem":872,
    "gn:elevation":"869.0",
    "gn:feature_class":"P",
    "gn:feature_code":"PPL",
    "gn:name":"Balls Trailer Park",
    "gn:population":0,
    "gn:timezone":"America/Chicago",
    "iso:country":"US",
    "wof:name":"Balls Trailer Park",
    "wof:placetype":"campus"
},
  "geometry": {"coordinates":[-100.91888,37.99472],"type":"Point"}
}