{
  "type": "Feature",
  "properties": {
    "gn:admin1_code":"FL",
    "gn:admin2_code":"57",
    "gn:asciiname":"Stevens Manor",
    "gn:country_code":"US",
    "gn:dem":24,
    "gn:elevation":"15.0",
    "gn:feature_class":"P",
    "gn:feature_code":"PPL",
    "gn:name":"Stevens Manor",
    "gn:population":0,
    "gn:timezone":"America/New_York",
    "iso:country":"US",
    "wof:name":"Stevens Manor",
    "wof:placetype":"locality"
},
  "geometry": {"coordinates":[-82.26100000000002,27.9902],"type":"Point"}
}