{
  "type": "Feature",
  "properties": {
    "gn:admin1_code":"MD",
    "gn:admin2_code":"11.0",
    "gn:asciiname":"Everlea",
    "gn:country_code":"US",
    "gn:dem":14,
    "gn:elevation":"14.0",
    "gn:feature_class":"P",
    "gn:feature_code":"PPL",
    "gn:name":"Everlea",
    "gn:population":0,
    "gn:timezone":"America/New_York",
    "iso:country":"US",
    "wof:name":"Everlea",
    "wof:placetype":"locality"
},
  "geometry": {"coordinates":[-75.95383000000002,38.73678],"type":"Point"}
}