{
  "type": "Feature",
  "properties": {
    "gn:admin1_code":"AR",
    "gn:admin2_code":"41.0",
    "gn:admin3_code":"91341.0",
    "gn:asciiname":"Jersey Point",
    "gn:country_code":"US",
    "gn:dem":48,
    "gn:elevation":"43.0",
    "gn:feature_class":"P",
    "gn:feature_code":"PPL",
    "gn:name":"Jersey Point",
    "gn:population":0,
    "gn:timezone":"America/Chicago",
    "iso:country":"US",
    "wof:name":"Jersey Point",
    "wof:placetype":"locality"
},
  "geometry": {"coordinates":[-91.10872000000001,33.67428],"type":"Point"}
}