{
  "type": "Feature",
  "properties": {
    "gn:admin1_code":"PA",
    "gn:admin2_code":"63.0",
    "gn:admin3_code":"4056.0",
    "gn:asciiname":"Keal Run",
    "gn:country_code":"US",
    "gn:dem":499,
    "gn:elevation":"500.0",
    "gn:feature_class":"P",
    "gn:feature_code":"PPL",
    "gn:name":"Keal Run",
    "gn:population":0,
    "gn:timezone":"America/New_York",
    "iso:country":"US",
    "wof:name":"Keal Run",
    "wof:placetype":"locality"
},
  "geometry": {"coordinates":[-78.83225,40.87701],"type":"Point"}
}