{
  "type": "Feature",
  "properties": {
    "gn:admin1_code":"MD",
    "gn:admin2_code":"37.0",
    "gn:asciiname":"Breton Beach",
    "gn:country_code":"US",
    "gn:dem":6,
    "gn:elevation":"2.0",
    "gn:feature_class":"P",
    "gn:feature_code":"PPL",
    "gn:name":"Breton Beach",
    "gn:population":0,
    "gn:timezone":"America/New_York",
    "iso:country":"US",
    "wof:name":"Breton Beach",
    "wof:placetype":"locality"
},
  "geometry": {"coordinates":[-76.68691,38.23735],"type":"Point"}
}