{
  "type": "Feature",
  "properties": {
    "iso:country":"US",
    "name:eng_x_preferred":[
        "Quaker Settlement"
    ],
    "wof:name":"Quaker Settlement",
    "wof:placetype":"neighbourhood",
    "wof:population":109,
    "zs:area_m":16225969.128142,
    "zs:blockids":[
        360530308003049,
        360530308003054,
        360530308003044,
        360530308003046,
        360530308003047,
        360530308002087,
        360530308003048,
        360530308003045,
        360530308003053
    ],
    "zs:housing10":48,
    "zs:label":"Quaker Settlement",
    "zs:pop10":109
},
  "geometry": {"coordinates":[-75.84827199999999,42.768534],"type":"Point"}
}