{
  "type": "Feature",
  "properties": {
    "gn:admin1_code":"CA",
    "gn:admin2_code":"101",
    "gn:asciiname":"Joesphine",
    "gn:country_code":"US",
    "gn:dem":9,
    "gn:elevation":"11.0",
    "gn:feature_class":"P",
    "gn:feature_code":"PPL",
    "gn:name":"Joesphine",
    "gn:population":0,
    "gn:timezone":"America/Los_Angeles",
    "iso:country":"US",
    "wof:name":"Joesphine",
    "wof:placetype":"locality"
},
  "geometry": {"coordinates":[-121.80108,39.09406],"type":"Point"}
}