{
  "type": "Feature",
  "properties": {
    "gn:admin1_code":"MD",
    "gn:admin2_code":"41.0",
    "gn:asciiname":"Kittys Corner",
    "gn:country_code":"US",
    "gn:dem":16,
    "gn:elevation":"18.0",
    "gn:feature_class":"P",
    "gn:feature_code":"PPL",
    "gn:name":"Kittys Corner",
    "gn:population":0,
    "gn:timezone":"America/New_York",
    "iso:country":"US",
    "wof:name":"Kittys Corner",
    "wof:placetype":"locality"
},
  "geometry": {"coordinates":[-75.98383000000003,38.84623],"type":"Point"}
}