{
  "type": "Feature",
  "properties": {
    "gn:country":"US",
    "gn:fcode":"PPL",
    "gn:population":0,
    "iso:country":"US",
    "name:eng_x_preferred":[
        "Tryons Corners"
    ],
    "qs_pg:aaroncc":"US",
    "qs_pg:gn_country":"US",
    "qs_pg:gn_fcode":"PPL",
    "qs_pg:gn_pop":0,
    "qs_pg:name":"Tryons Corners",
    "qs_pg:name_adm0":"United States",
    "qs_pg:name_adm1":"New York",
    "qs_pg:photos":3,
    "qs_pg:photos_1k":1,
    "qs_pg:photos_9k":1,
    "qs_pg:photos_9r":1,
    "qs_pg:photos_all":3,
    "qs_pg:photos_sr":1,
    "qs_pg:pop_sr":0,
    "qs_pg:qs_pg_placetype":"neighbourhood",
    "qs_pg:qs_pg_placetype_gp":"Suburb",
    "qs_pg:woe_adm0":23424977,
    "wof:name":"Tryons Corners",
    "wof:placetype":"neighbourhood",
    "wof:population":40,
    "zs:blockids":[
        360510302011090,
        361219701002077,
        361219701002044,
        361219701002043,
        361219701002038,
        361219701002045
    ],
    "zs:housing10":17,
    "zs:label":"Tryons Corners",
    "zs:pop10":40
},
  "geometry": {"coordinates":[-77.92856,42.839152],"type":"Point"}
}