{
  "type": "Feature",
  "properties": {
    "gn:admin1_code":"VA",
    "gn:admin2_code":"710.0",
    "gn:asciiname":"Cherokee Heights",
    "gn:country_code":"US",
    "gn:dem":12,
    "gn:elevation":"4.0",
    "gn:feature_class":"P",
    "gn:feature_code":"PPL",
    "gn:name":"Cherokee Heights",
    "gn:population":0,
    "gn:timezone":"America/New_York",
    "iso:country":"US",
    "wof:name":"Cherokee Heights",
    "wof:placetype":"locality"
},
  "geometry": {"coordinates":[-76.23971999999998,36.92639000000001],"type":"Point"}
}