{
  "type": "Feature",
  "properties": {
    "gn:admin1_code":"KS",
    "gn:admin2_code":"155.0",
    "gn:admin3_code":"13600.0",
    "gn:asciiname":"Showalter Mobile Home Park",
    "gn:country_code":"US",
    "gn:dem":486,
    "gn:elevation":"479.0",
    "gn:feature_class":"P",
    "gn:feature_code":"PPL",
    "gn:name":"Showalter Mobile Home Park",
    "gn:population":0,
    "gn:timezone":"America/Chicago",
    "iso:country":"US",
    "wof:name":"Showalter Mobile Home Park",
    "wof:placetype":"campus"
},
  "geometry": {"coordinates":[-97.8142,38.08726],"type":"Point"}
}