{
  "type": "Feature",
  "properties": {
    "gn:admin1_code":"MO",
    "gn:admin2_code":"207.0",
    "gn:admin3_code":"21592.0",
    "gn:asciiname":"Marco",
    "gn:country_code":"US",
    "gn:dem":91,
    "gn:elevation":"89.0",
    "gn:feature_class":"P",
    "gn:feature_code":"PPL",
    "gn:name":"Marco",
    "gn:population":0,
    "gn:timezone":"America/Chicago",
    "iso:country":"US",
    "name:bpy_x_preferred":[
        "\u09ae\u09be\u09b0\u09cd\u0995\u09cb"
    ],
    "name:bre_x_preferred":[
        "Marco"
    ],
    "name:ceb_x_preferred":[
        "Marco"
    ],
    "name:deu_x_preferred":[
        "Marco"
    ],
    "name:fas_x_preferred":[
        "\u0645\u0627\u0631\u06a9\u0648"
    ],
    "name:fra_x_preferred":[
        "Marco"
    ],
    "name:glg_x_preferred":[
        "Marco"
    ],
    "name:heb_x_preferred":[
        "\u05de\u05e8\u05e7\u05d5"
    ],
    "name:ita_x_preferred":[
        "Marco"
    ],
    "name:jpn_x_preferred":[
        "\u30de\u30eb\u30b3"
    ],
    "name:kor_x_preferred":[
        "\ub9c8\ub974\ucf54"
    ],
    "name:nld_x_preferred":[
        "Marco"
    ],
    "name:nor_x_preferred":[
        "Marco"
    ],
    "name:por_x_preferred":[
        "Marco"
    ],
    "name:spa_x_preferred":[
        "Marco"
    ],
    "name:swe_x_preferred":[
        "Marco"
    ],
    "name:vie_x_preferred":[
        "Marco"
    ],
    "name:zho_x_preferred":[
        "\u9a6c\u5c14\u79d1"
    ],
    "wof:name":"Marco",
    "wof:placetype":"locality"
},
  "geometry": {"coordinates":[-89.80814000000002,36.74783],"type":"Point"}
}