{
  "type": "Feature",
  "properties": {
    "gn:admin1_code":"VA",
    "gn:admin2_code":"85",
    "gn:asciiname":"Crosses Corner",
    "gn:country_code":"US",
    "gn:dem":58,
    "gn:elevation":"57.0",
    "gn:feature_class":"P",
    "gn:feature_code":"PPL",
    "gn:name":"Crosses Corner",
    "gn:population":0,
    "gn:timezone":"America/New_York",
    "iso:country":"US",
    "wof:name":"Crosses Corner",
    "wof:placetype":"locality"
},
  "geometry": {"coordinates":[-77.36609,37.72681],"type":"Point"}
}