{
  "type": "Feature",
  "properties": {
    "gn:admin1_code":"TX",
    "gn:admin2_code":"27",
    "gn:asciiname":"New Colony",
    "gn:country_code":"US",
    "gn:dem":131,
    "gn:elevation":"131.0",
    "gn:feature_class":"P",
    "gn:feature_code":"PPL",
    "gn:name":"New Colony",
    "gn:population":0,
    "gn:timezone":"America/Chicago",
    "iso:country":"US",
    "wof:name":"New Colony",
    "wof:placetype":"locality"
},
  "geometry": {"coordinates":[-97.16305,30.96213],"type":"Point"}
}