{
  "type": "Feature",
  "properties": {
    "iso:country":"US",
    "name:eng_x_preferred":[
        "Crackersport"
    ],
    "name:und_x_variant":[
        "South Whitehall"
    ],
    "qs:gn_adm0_cc":"US",
    "qs:gn_fcode":"PPL",
    "qs:gn_local":5213129,
    "qs:gn_nam_loc":"South Whitehall, Lehigh, Pennsylvania, US",
    "qs:gn_namadm1":"PA",
    "qs:gn_name":"Crackersport",
    "qs:local_max":288,
    "qs:local_sum":711,
    "qs:localhoods":5,
    "qs:name":"Crackersport",
    "qs:name_adm0":"United States",
    "qs:name_adm1":"Pennsylvania",
    "qs:name_adm2":"Lehigh",
    "qs:name_local":"South Whitehall",
    "qs:photo_max":29,
    "qs:photo_sum":102,
    "qs:placetype":"Suburb",
    "qs:quad_count":15,
    "qs:woe_adm0":23424977,
    "qs:woe_adm1":2347597,
    "qs:woe_adm2":12589766,
    "qs:woe_lau":0,
    "qs:woe_local":28745501,
    "qs:woe_ver":"7.10.0",
    "wof:lang":[
        "eng"
    ],
    "wof:name":"Crackersport",
    "wof:placetype":"neighbourhood",
    "wof:population":1510,
    "zs:blockids":[
        420770060022027,
        420770060023026,
        420770060023024,
        420770061013006,
        420770060023051,
        420770062033001,
        420770060023050,
        420770060023029,
        420770060023023,
        420770062033004,
        420770060023049,
        420770060023047,
        420770060023020,
        420770060023054,
        420770061024032,
        420770060023056,
        420770061013014,
        420770060023032,
        420770060023048,
        420770060023035,
        420770061013000,
        420770060022026,
        420770060023057,
        420770061024031,
        420770061024008,
        420770060023046,
        420770060023010,
        420770060023038,
        420770062033005,
        420770060023052,
        420770061013012,
        420770061024007,
        420770060023031,
        420770062033000,
        420770061013009,
        420770060023033,
        420770060023019,
        420770061013003,
        420770060023018,
        420770060023021,
        420770061013004,
        420770060023034,
        420770062033003,
        420770061013005,
        420770060023027,
        420770062033015,
        420770060022023,
        420770060022017,
        420770060022025,
        420770060023009,
        420770060022024,
        420770060023037,
        420770060023039,
        420770061013015,
        420770061013002,
        420770060023036,
        420770060023025,
        420770060022018,
        420770061013010,
        420770061013008,
        420770060023053,
        420770061013007,
        420770061013001,
        420770060023030,
        420770061024010,
        420770060023042,
        420770061024009
    ],
    "zs:housing10":609,
    "zs:pop10":1510
},
  "geometry": {"coordinates":[-75.55972,40.604892],"type":"Point"}
}