{
  "type": "Feature",
  "properties": {
    "gn:admin1_code":"MS",
    "gn:admin2_code":"41.0",
    "gn:asciiname":"Hillman",
    "gn:country_code":"US",
    "gn:dem":67,
    "gn:elevation":"61.0",
    "gn:feature_class":"P",
    "gn:feature_code":"PPL",
    "gn:name":"Hillman",
    "gn:population":0,
    "gn:timezone":"America/Chicago",
    "iso:country":"US",
    "name:azb_x_preferred":[
        "\u0647\u06cc\u0644\u0645\u0646"
    ],
    "name:deu_x_preferred":[
        "Hillman"
    ],
    "name:fas_x_preferred":[
        "\u0647\u06cc\u0644\u0645\u0646"
    ],
    "name:fin_x_preferred":[
        "Hillman"
    ],
    "name:fra_x_preferred":[
        "Hillman"
    ],
    "name:ita_x_preferred":[
        "Hillman"
    ],
    "name:jpn_x_preferred":[
        "\u30d2\u30eb\u30de\u30f3"
    ],
    "name:nld_x_preferred":[
        "Hillman"
    ],
    "name:nor_x_preferred":[
        "Hillman"
    ],
    "name:pol_x_preferred":[
        "Hillman"
    ],
    "name:por_x_preferred":[
        "Hillman"
    ],
    "name:spa_x_preferred":[
        "Hillman"
    ],
    "name:swe_x_preferred":[
        "Hillman"
    ],
    "name:ukr_x_preferred":[
        "Hillman"
    ],
    "wof:name":"Hillman",
    "wof:placetype":"locality"
},
  "geometry": {"coordinates":[-88.6328,31.13352],"type":"Point"}
}