{
  "type": "Feature",
  "properties": {
    "gn:admin1_code":"GA",
    "gn:admin2_code":"115",
    "gn:asciiname":"River Ridge",
    "gn:country_code":"US",
    "gn:dem":211,
    "gn:elevation":"201.0",
    "gn:feature_class":"P",
    "gn:feature_code":"PPL",
    "gn:name":"River Ridge",
    "gn:population":0,
    "gn:timezone":"America/New_York",
    "iso:country":"US",
    "name:ceb_x_preferred":[
        "River Ridge"
    ],
    "name:deu_x_preferred":[
        "River Ridge"
    ],
    "name:ita_x_preferred":[
        "River Ridge"
    ],
    "name:srp_x_preferred":[
        "\u0420\u0438\u0432\u0435\u0440 \u0420\u0438\u045f"
    ],
    "wof:name":"River Ridge",
    "wof:placetype":"locality"
},
  "geometry": {"coordinates":[-85.21634,34.22982],"type":"Point"}
}