{
  "type": "Feature",
  "properties": {
    "gn:admin1_code":"CA",
    "gn:admin2_code":"45.0",
    "gn:asciiname":"Whitesboro",
    "gn:country_code":"US",
    "gn:dem":43,
    "gn:elevation":"12.0",
    "gn:feature_class":"P",
    "gn:feature_code":"PPL",
    "gn:name":"Whitesboro",
    "gn:population":0,
    "gn:timezone":"America/Los_Angeles",
    "iso:country":"US",
    "name:zho_x_preferred":[
        "\u61f7\u8328\u4f2f\u52d2"
    ],
    "wof:name":"Whitesboro",
    "wof:placetype":"locality"
},
  "geometry": {"coordinates":[-123.76446,39.21462],"type":"Point"}
}