{
  "type": "Feature",
  "properties": {
    "gn:admin1_code":"AZ",
    "gn:admin2_code":"19.0",
    "gn:asciiname":"Siovi Shuatak",
    "gn:country_code":"US",
    "gn:dem":661,
    "gn:elevation":"659.0",
    "gn:feature_class":"P",
    "gn:feature_code":"PPL",
    "gn:name":"Siovi Shuatak",
    "gn:population":0,
    "gn:timezone":"America/Phoenix",
    "iso:country":"US",
    "name:eng_x_preferred":[
        "Siovi Shuatak"
    ],
    "name:und_x_variant":[
        "Sweetwater",
        "Cochivo",
        "Cochibo",
        "Manuels Well",
        "Cochiba Well",
        "Coons Can Well",
        "Con Quien",
        "Cochibo Well"
    ],
    "wof:name":"Siovi Shuatak",
    "wof:placetype":"locality"
},
  "geometry": {"coordinates":[-112.59820000000001,31.9509],"type":"Point"}
}