{
  "type": "Feature",
  "properties": {
    "gn:admin1_code":"AL",
    "gn:admin2_code":"45",
    "gn:asciiname":"Echo",
    "gn:country_code":"US",
    "gn:dem":143,
    "gn:elevation":"138.0",
    "gn:feature_class":"P",
    "gn:feature_code":"PPL",
    "gn:name":"Echo",
    "gn:population":0,
    "gn:timezone":"America/Chicago",
    "iso:country":"US",
    "name:eng_x_preferred":[
        "Echo"
    ],
    "name:fas_x_preferred":[
        "\u0627\u06a9\u0648"
    ],
    "name:und_x_variant":[
        "Marshalls Cross Roads"
    ],
    "name:urd_x_preferred":[
        "\u0627\u06cc\u06a9\u0648"
    ],
    "name:zho_x_preferred":[
        "\u57c3\u79d1"
    ],
    "wof:name":"Echo",
    "wof:placetype":"locality"
},
  "geometry": {"coordinates":[-85.46576999999998,31.47572000000001],"type":"Point"}
}