{
  "type": "Feature",
  "properties": {
    "iso:country":"US",
    "name:eng_x_preferred":[
        "Upper Long Hill"
    ],
    "wof:name":"Upper Long Hill",
    "wof:placetype":"neighbourhood",
    "wof:population":2967,
    "zs:area_m":5892149.085342,
    "zs:blockids":[
        90010902003000,
        90010902001014,
        90010902003017,
        90010902001010,
        90010902003021,
        90010902003018,
        90010907003008,
        90010902003022,
        90010902001009,
        90010902004023,
        90010902003020,
        90010902001007,
        90010902003024,
        90010902001005,
        90010902003004,
        90010902004024,
        90010907003003,
        90010907003005,
        90010907003016,
        90010902004021,
        90010902003023,
        90010902001017,
        90010902001006,
        90010907003004,
        90010907003012,
        90010902003019,
        90010902004020,
        90010902003025,
        90010902001011,
        90010902003014,
        90010902001012,
        90010902001015,
        90010902004022,
        90010902003013,
        90010902004025,
        90010902003016,
        90010902001018,
        90010907003018
    ],
    "zs:housing10":1087,
    "zs:label":"Upper Long Hill",
    "zs:pop10":2967
},
  "geometry": {"coordinates":[-73.21703599999999,41.26862],"type":"Point"}
}