{
  "type": "Feature",
  "properties": {
    "gn:admin1_code":"MD",
    "gn:admin2_code":"17.0",
    "gn:asciiname":"Karen Knolls",
    "gn:country_code":"US",
    "gn:dem":54,
    "gn:elevation":"53.0",
    "gn:feature_class":"P",
    "gn:feature_code":"PPL",
    "gn:name":"Karen Knolls",
    "gn:population":0,
    "gn:timezone":"America/New_York",
    "iso:country":"US",
    "wof:name":"Karen Knolls",
    "wof:placetype":"locality"
},
  "geometry": {"coordinates":[-76.77663000000003,38.5104],"type":"Point"}
}