{
  "type": "Feature",
  "properties": {
    "gn:admin1_code":"MO",
    "gn:admin2_code":"119.0",
    "gn:admin3_code":"45240.0",
    "gn:asciiname":"Coy",
    "gn:country_code":"US",
    "gn:dem":290,
    "gn:elevation":"288.0",
    "gn:feature_class":"P",
    "gn:feature_code":"PPL",
    "gn:name":"Coy",
    "gn:population":0,
    "gn:timezone":"America/Chicago",
    "iso:country":"US",
    "name:ceb_x_preferred":[
        "Coy"
    ],
    "name:deu_x_preferred":[
        "Coy"
    ],
    "name:swe_x_preferred":[
        "Coy"
    ],
    "wof:name":"Coy",
    "wof:placetype":"locality"
},
  "geometry": {"coordinates":[-94.53216,36.66118],"type":"Point"}
}