{
  "type": "Feature",
  "properties": {
    "gn:admin1_code":"IN",
    "gn:admin2_code":"127.0",
    "gn:admin3_code":"61182.0",
    "gn:asciiname":"Porter Crossroads",
    "gn:country_code":"US",
    "gn:dem":234,
    "gn:elevation":"231.0",
    "gn:feature_class":"P",
    "gn:feature_code":"PPL",
    "gn:name":"Porter Crossroads",
    "gn:population":0,
    "gn:timezone":"America/Chicago",
    "iso:country":"US",
    "wof:name":"Porter Crossroads",
    "wof:placetype":"locality"
},
  "geometry": {"coordinates":[-87.1617,41.3992],"type":"Point"}
}