{
  "type": "Feature",
  "properties": {
    "gn:admin1_code":"AL",
    "gn:admin2_code":"127",
    "gn:asciiname":"Lake Shore Subdivision",
    "gn:country_code":"US",
    "gn:dem":171,
    "gn:elevation":"169.0",
    "gn:feature_class":"P",
    "gn:feature_code":"PPL",
    "gn:name":"Lake Shore Subdivision",
    "gn:population":0,
    "gn:timezone":"America/Chicago",
    "iso:country":"US",
    "wof:name":"Lake Shore Subdivision",
    "wof:placetype":"locality"
},
  "geometry": {"coordinates":[-87.19112,33.99538],"type":"Point"}
}