{
  "type": "Feature",
  "properties": {
    "gn:admin1_code":"WI",
    "gn:admin2_code":"9.0",
    "gn:admin3_code":"35950.0",
    "gn:asciiname":"Mill Center",
    "gn:country_code":"US",
    "gn:dem":232,
    "gn:elevation":"232.0",
    "gn:feature_class":"P",
    "gn:feature_code":"PPL",
    "gn:name":"Mill Center",
    "gn:population":0,
    "gn:timezone":"America/Chicago",
    "iso:country":"US",
    "name:eng_x_preferred":[
        "Mill Center"
    ],
    "name:und_x_variant":[
        "Mills Centre"
    ],
    "wof:name":"Mill Center",
    "wof:placetype":"locality"
},
  "geometry": {"coordinates":[-88.16065999999999,44.58805],"type":"Point"}
}