{
  "type": "Feature",
  "properties": {
    "iso:country":"US",
    "name:eng_x_preferred":[
        "Rusty Pines"
    ],
    "wof:name":"Rusty Pines",
    "wof:placetype":"neighbourhood",
    "wof:population":338,
    "zs:area_m":227597.126545,
    "zs:blockids":[
        51190041032001,
        51190041032000
    ],
    "zs:housing10":144,
    "zs:label":"Rusty Pines",
    "zs:pop10":338
},
  "geometry": {"coordinates":[-92.36449,34.678552],"type":"Point"}
}