{
  "type": "Feature",
  "properties": {
    "gn:admin1_code":"TN",
    "gn:admin2_code":"149.0",
    "gn:asciiname":"Cherry Hill Estates",
    "gn:country_code":"US",
    "gn:dem":168,
    "gn:elevation":"167.0",
    "gn:feature_class":"P",
    "gn:feature_code":"PPL",
    "gn:name":"Cherry Hill Estates",
    "gn:population":0,
    "gn:timezone":"America/Chicago",
    "iso:country":"US",
    "wof:name":"Cherry Hill Estates",
    "wof:placetype":"locality"
},
  "geometry": {"coordinates":[-86.46888,35.93201],"type":"Point"}
}