{
  "type": "Feature",
  "properties": {
    "gn:elevation":471,
    "iso:country":"US",
    "name:eng_x_preferred":[
        "Brairwood Acres"
    ],
    "qs:gn_adm0_cc":"US",
    "qs:gn_fcode":"PPLX",
    "qs:gn_local":4634662,
    "qs:gn_nam_loc":"Kingsport, Sullivan, Tennessee, US",
    "qs:gn_namadm1":"TN",
    "qs:gn_name":"Brairwood Acres",
    "qs:local_max":841,
    "qs:local_sum":2331,
    "qs:localhoods":14,
    "qs:name":"Brairwood Acres",
    "qs:name_adm0":"United States",
    "qs:name_adm1":"Tennessee",
    "qs:name_adm2":"Sullivan",
    "qs:name_local":"Kingsport",
    "qs:photo_max":98,
    "qs:photo_sum":110,
    "qs:placetype":"Suburb",
    "qs:quad_count":6,
    "qs:woe_adm0":23424977,
    "qs:woe_adm1":2347601,
    "qs:woe_adm2":12589993,
    "qs:woe_lau":0,
    "qs:woe_local":2432757,
    "qs:woe_ver":"7.10.0",
    "wof:lang":[
        "eng"
    ],
    "wof:name":"Brairwood Acres",
    "wof:placetype":"neighbourhood",
    "wof:population":224,
    "zs:blockids":[
        471630409001014,
        471630409001008
    ],
    "zs:housing10":94,
    "zs:pop10":224
},
  "geometry": {"coordinates":[-82.483728,36.545528],"type":"Point"}
}