{
  "type": "Feature",
  "properties": {
    "gn:elevation":14,
    "iso:country":"US",
    "name:arz_x_preferred":[
        "\u0643\u0648\u062f\u064a\u0627\u0643 \u0627\u064a\u0631\u067e\u0648\u0631\u062a"
    ],
    "name:deu_x_preferred":[
        "Kodiak Airport"
    ],
    "name:eng_x_preferred":[
        "Kodiak Airport"
    ],
    "name:eng_x_variant":[
        "ADQ",
        "PADQ",
        "Kodiak Benny Benson State Airport"
    ],
    "name:fas_x_preferred":[
        "\u0641\u0631\u0648\u062f\u06af\u0627\u0647 \u06a9\u0648\u062f\u06cc\u0627\u06a9"
    ],
    "name:fra_x_preferred":[
        "A\u00e9roport de Kodiak"
    ],
    "name:ind_x_preferred":[
        "Bandar Udara Kodiak"
    ],
    "name:jpn_x_preferred":[
        "\u30b3\u30c7\u30a3\u30a2\u30c3\u30af\u7a7a\u6e2f"
    ],
    "name:nob_x_preferred":[
        "Kodiak lufthavn"
    ],
    "name:pol_x_preferred":[
        "Port lotniczy Kodiak"
    ],
    "name:ron_x_preferred":[
        "Aeroportul Kodiak"
    ],
    "name:rus_x_preferred":[
        "\u041a\u0430\u0434\u044c\u044f\u043a"
    ],
    "name:spa_x_preferred":[
        "Aeropuerto de Kodiak"
    ],
    "name:tgk_x_preferred":[
        "\u0424\u0443\u0440\u0443\u0434\u0433\u043e\u04b3\u0438 \u043a\u0443\u0434\u0438\u043e\u043a"
    ],
    "name:zho_x_preferred":[
        "\u79d1\u8fea\u4e9e\u514b\u6a5f\u5834"
    ],
    "oa:elevation_ft":"78",
    "oa:type":"medium_airport",
    "wd:wordcount":1062,
    "woe:hierarchy":{
        "country_id":23424977,
        "county_id":12587566,
        "planet_id":1,
        "state_id":2347560
    },
    "wof:name":"Kodiak Airport",
    "wof:placetype":"campus"
},
  "geometry": {"coordinates":[-152.49400299999999,57.75],"type":"Point"}
}