{
  "type": "Feature",
  "properties": {
    "iso:country":"US",
    "name:eng_x_preferred":[
        "Bellafont"
    ],
    "wof:name":"Bellafont",
    "wof:placetype":"neighbourhood",
    "zs:area_m":24551.846791,
    "zs:blockids":[
        51430101063045
    ],
    "zs:housing10":0,
    "zs:label":"Bellafont",
    "zs:pop10":0
},
  "geometry": {"coordinates":[-94.13892199999999,36.121021],"type":"Point"}
}