{
  "type": "Feature",
  "properties": {
    "gn:admin1_code":"FL",
    "gn:admin2_code":"1.0",
    "gn:asciiname":"Hasan",
    "gn:country_code":"US",
    "gn:dem":50,
    "gn:elevation":"53.0",
    "gn:feature_class":"P",
    "gn:feature_code":"PPL",
    "gn:name":"Hasan",
    "gn:population":0,
    "gn:timezone":"America/New_York",
    "iso:country":"US",
    "name:zho_x_preferred":[
        "\u54c8\u6851"
    ],
    "wof:name":"Hasan",
    "wof:placetype":"locality"
},
  "geometry": {"coordinates":[-82.43789,29.85885],"type":"Point"}
}