{
  "type": "Feature",
  "properties": {
    "gn:admin1_code":"TX",
    "gn:admin2_code":"69.0",
    "gn:asciiname":"Roy",
    "gn:country_code":"US",
    "gn:dem":1148,
    "gn:elevation":"1145.0",
    "gn:feature_class":"P",
    "gn:feature_code":"PPL",
    "gn:name":"Roy",
    "gn:population":0,
    "gn:timezone":"America/Chicago",
    "iso:country":"US",
    "name:deu_x_preferred":[
        "Roy"
    ],
    "name:fin_x_preferred":[
        "Roy"
    ],
    "name:nno_x_preferred":[
        "Roy"
    ],
    "name:nor_x_preferred":[
        "Roy"
    ],
    "name:swe_x_preferred":[
        "Roy"
    ],
    "wof:name":"Roy",
    "wof:placetype":"locality"
},
  "geometry": {"coordinates":[-102.21380000000001,34.46646],"type":"Point"}
}