{
  "type": "Feature",
  "properties": {
    "gn:admin1_code":"PA",
    "gn:admin2_code":"125.0",
    "gn:admin3_code":"12848.0",
    "gn:asciiname":"Moninger",
    "gn:country_code":"US",
    "gn:dem":300,
    "gn:elevation":"302.0",
    "gn:feature_class":"P",
    "gn:feature_code":"PPL",
    "gn:name":"Moninger",
    "gn:population":0,
    "gn:timezone":"America/New_York",
    "iso:country":"US",
    "wof:name":"Moninger",
    "wof:placetype":"locality"
},
  "geometry": {"coordinates":[-80.21256,40.24174],"type":"Point"}
}