{
  "type": "Feature",
  "properties": {
    "gn:admin1_code":"OH",
    "gn:admin2_code":"19.0",
    "gn:admin3_code":"58576.0",
    "gn:asciiname":"Glens Cottage Area",
    "gn:country_code":"US",
    "gn:dem":326,
    "gn:elevation":"305.0",
    "gn:feature_class":"P",
    "gn:feature_code":"PPL",
    "gn:name":"Glens Cottage Area",
    "gn:population":0,
    "gn:timezone":"America/New_York",
    "iso:country":"US",
    "wof:name":"Glens Cottage Area",
    "wof:placetype":"locality"
},
  "geometry": {"coordinates":[-81.19121,40.48756],"type":"Point"}
}