{
  "type": "Feature",
  "properties": {
    "gn:gn_country":"US",
    "gn:gn_fcode":"PPL",
    "gn:gn_pop":0,
    "iso:country":"US",
    "name:eng_x_preferred":[
        "Huyett"
    ],
    "name:fra_x_preferred":[
        "Huyett"
    ],
    "name:unk_x_variant":[
        "Huyetts Crossroads"
    ],
    "qs_pg:aaroncc":"US",
    "qs_pg:gn_country":"US",
    "qs_pg:gn_fcode":"PPL",
    "qs_pg:gn_pop":0,
    "qs_pg:name":"Huyett",
    "qs_pg:name_adm0":"United States",
    "qs_pg:name_adm1":"Maryland",
    "qs_pg:photos":74,
    "qs_pg:photos_1k":15,
    "qs_pg:photos_9k":1,
    "qs_pg:photos_9r":2,
    "qs_pg:photos_all":74,
    "qs_pg:photos_sr":2,
    "qs_pg:pop_sr":0,
    "qs_pg:qs_pg_placetype":"locality",
    "qs_pg:qs_pg_placetype_gp":"Town",
    "qs_pg:woe_adm0":23424977,
    "woe:adm0_id":23424977,
    "woe:name_adm0":"United States",
    "woe:name_adm1":"Maryland",
    "woe:placetype":"Town",
    "wof:name":"Huyett",
    "wof:placetype":"locality"
},
  "geometry": {"coordinates":[-77.79916,39.65148],"type":"Point"}
}