{
  "type": "Feature",
  "properties": {
    "gn:admin1_code":"WV",
    "gn:admin2_code":"77.0",
    "gn:asciiname":"White Oak Springs",
    "gn:country_code":"US",
    "gn:dem":836,
    "gn:elevation":"832.0",
    "gn:feature_class":"P",
    "gn:feature_code":"PPL",
    "gn:name":"White Oak Springs",
    "gn:population":0,
    "gn:timezone":"America/New_York",
    "iso:country":"US",
    "name:eng_x_preferred":[
        "White Oak Springs"
    ],
    "name:und_x_variant":[
        "Whiteoak Springs"
    ],
    "wof:name":"White Oak Springs",
    "wof:placetype":"locality"
},
  "geometry": {"coordinates":[-79.50060000000001,39.48704],"type":"Point"}
}