{
  "type": "Feature",
  "properties": {
    "gn:admin1_code":"CO",
    "gn:admin2_code":"55.0",
    "gn:asciiname":"Occidental",
    "gn:country_code":"US",
    "gn:dem":2370,
    "gn:elevation":"2352.0",
    "gn:feature_class":"P",
    "gn:feature_code":"PPL",
    "gn:name":"Occidental",
    "gn:population":0,
    "gn:timezone":"America/Denver",
    "iso:country":"US",
    "name:cat_x_preferred":[
        "Occidental"
    ],
    "name:deu_x_preferred":[
        "Occidental"
    ],
    "name:fra_x_preferred":[
        "Occidental"
    ],
    "name:ina_x_preferred":[
        "Occidental"
    ],
    "name:jpn_x_preferred":[
        "\u30aa\u30af\u30b7\u30c7\u30f3\u30bf\u30eb"
    ],
    "name:nld_x_preferred":[
        "Occidental"
    ],
    "name:por_x_preferred":[
        "Occidental"
    ],
    "name:vol_x_preferred":[
        "Occidental"
    ],
    "wof:name":"Occidental",
    "wof:placetype":"locality"
},
  "geometry": {"coordinates":[-105.10693999999999,37.51501],"type":"Point"}
}