{
  "type": "Feature",
  "properties": {
    "gn:admin1_code":"MS",
    "gn:admin2_code":"51.0",
    "gn:asciiname":"Eulogy",
    "gn:country_code":"US",
    "gn:dem":99,
    "gn:elevation":"93.0",
    "gn:feature_class":"P",
    "gn:feature_code":"PPL",
    "gn:name":"Eulogy",
    "gn:population":0,
    "gn:timezone":"America/Chicago",
    "iso:country":"US",
    "wof:name":"Eulogy",
    "wof:placetype":"locality"
},
  "geometry": {"coordinates":[-90.17480999999999,33.03374],"type":"Point"}
}