{
  "type": "Feature",
  "properties": {
    "iso:country":"US",
    "name:ceb_x_preferred":[
        "La Brea"
    ],
    "name:deu_x_preferred":[
        "La Brea"
    ],
    "name:eng_x_preferred":[
        "La Brea"
    ],
    "name:fin_x_preferred":[
        "La Brea"
    ],
    "name:srp_x_preferred":[
        "\u041b\u0430 \u0411\u0440\u0435\u0430"
    ],
    "name:swe_x_preferred":[
        "La Brea"
    ],
    "wd:wordcount":67,
    "wof:name":"La Brea",
    "wof:placetype":"neighbourhood",
    "wof:population":2051,
    "zs:area_m":554209.86553,
    "zs:blockids":[
        60376010022001,
        60376012112000,
        60376010012021,
        60376010022000,
        60376010022002,
        60376010012001,
        60376010012018,
        60376012112001,
        60376010023009,
        60376010012043,
        60376010012034,
        60376010012012,
        60376010012015,
        60376010012038,
        60376010012035,
        60376012112010,
        60376010012027,
        60376010012025,
        60376010012026,
        60376010012030,
        60376010012023,
        60376010023008,
        60376010012040,
        60376010022009,
        60376012121008,
        60376010012028,
        60376010012002,
        60376010012022,
        60376012121007,
        60376010012037,
        60376012121000,
        60376010012010,
        60376010011017,
        60376010012036,
        60376010012042,
        60376010012029,
        60376010012044,
        60376012121014,
        60376012121009,
        60376010012041,
        60376010023007,
        60376010012016,
        60376010012014,
        60376010012020,
        60376010012011,
        60376010012032,
        60376010012039,
        60376010012024,
        60376012111015,
        60376010012031,
        60376010012033,
        60376010012003,
        60376010012017
    ],
    "zs:housing10":960,
    "zs:label":"La Brea",
    "zs:pop10":2051
},
  "geometry": {"coordinates":[-118.351918,33.959596],"type":"Point"}
}