{
  "type": "Feature",
  "properties": {
    "gn:gn_country":"US",
    "gn:gn_fcode":"PPLX",
    "gn:gn_pop":0,
    "iso:country":"US",
    "name:deu_x_preferred":[
        "Wayside"
    ],
    "name:eng_x_preferred":[
        "Wayside"
    ],
    "name:ita_x_preferred":[
        "Wayside"
    ],
    "qs_pg:aaroncc":"US",
    "qs_pg:gn_country":"US",
    "qs_pg:gn_fcode":"PPLX",
    "qs_pg:gn_pop":0,
    "qs_pg:name":"Wayside",
    "qs_pg:name_adm0":"United States",
    "qs_pg:name_adm1":"Alabama",
    "qs_pg:photos":3,
    "qs_pg:photos_1k":1,
    "qs_pg:photos_9k":1,
    "qs_pg:photos_9r":1,
    "qs_pg:photos_all":3,
    "qs_pg:photos_sr":1,
    "qs_pg:pop_sr":0,
    "qs_pg:qs_pg_placetype":"neighbourhood",
    "qs_pg:qs_pg_placetype_gp":"Suburb",
    "qs_pg:woe_adm0":23424977,
    "wd:wordcount":72,
    "wof:name":"Wayside",
    "wof:placetype":"neighbourhood",
    "wof:population":2554,
    "zs:area_m":12432273.297209,
    "zs:blockids":[
        10150014003007,
        10150014002025,
        10150014003001,
        10150014003028,
        10150013002023,
        10150014003002,
        10150014003038,
        10150014003027,
        10150014002007,
        10150014003034,
        10150014003033,
        10150014004013,
        10150013001027,
        10150014002017,
        10150014004005,
        10150014003021,
        10150014003004,
        10150014003022,
        10150014003016,
        10150014002009,
        10150014002016,
        10150014003036,
        10150014003009,
        10150014003018,
        10150014003014,
        10150014002010,
        10150014002005,
        10150014002020,
        10150014004010,
        10150014003019,
        10150014002008,
        10150014003026,
        10150014003035,
        10150014002014,
        10150014003006,
        10150014003013,
        10150014004011,
        10150014003012,
        10150014001004,
        10150014003032,
        10150014003042,
        10150014004016,
        10150014003017,
        10150013002011,
        10150014003008,
        10150014003010,
        10150014003011,
        10150014004012,
        10150014003025,
        10150013001026,
        10150014004008,
        10150014003003,
        10150014002022,
        10150014003037,
        10150014003005,
        10150014004007,
        10150014003020,
        10150014003029,
        10150014002015
    ],
    "zs:housing10":1128,
    "zs:label":"Wayside",
    "zs:pop10":2554
},
  "geometry": {"coordinates":[-85.899816,33.64663],"type":"Point"}
}