{
  "type": "Feature",
  "properties": {
    "gn:admin1_code":"MS",
    "gn:admin2_code":"159.0",
    "gn:asciiname":"Boon",
    "gn:country_code":"US",
    "gn:dem":152,
    "gn:elevation":"152.0",
    "gn:feature_class":"P",
    "gn:feature_code":"PPL",
    "gn:name":"Boon",
    "gn:population":0,
    "gn:timezone":"America/Chicago",
    "iso:country":"US",
    "name:cat_x_preferred":[
        "Boon"
    ],
    "name:ceb_x_preferred":[
        "Boon"
    ],
    "name:deu_x_preferred":[
        "Boon"
    ],
    "name:fra_x_preferred":[
        "Boon"
    ],
    "name:ita_x_preferred":[
        "Boon"
    ],
    "name:nld_x_preferred":[
        "Boon"
    ],
    "name:pol_x_preferred":[
        "Boon"
    ],
    "name:rus_x_preferred":[
        "\u0411\u043e\u043e\u043d"
    ],
    "wof:name":"Boon",
    "wof:placetype":"locality"
},
  "geometry": {"coordinates":[-88.95645,33.10068],"type":"Point"}
}