{
  "type": "Feature",
  "properties": {
    "gn:admin1_code":"LA",
    "gn:admin2_code":"9.0",
    "gn:asciiname":"Dunlap",
    "gn:country_code":"US",
    "gn:dem":21,
    "gn:elevation":"17.0",
    "gn:feature_class":"P",
    "gn:feature_code":"PPL",
    "gn:name":"Dunlap",
    "gn:population":0,
    "gn:timezone":"America/Chicago",
    "iso:country":"US",
    "name:cat_x_preferred":[
        "Dunlap"
    ],
    "name:ceb_x_preferred":[
        "Dunlap"
    ],
    "name:deu_x_preferred":[
        "Dunlap"
    ],
    "name:fra_x_preferred":[
        "Dunlap"
    ],
    "name:ido_x_preferred":[
        "Dunlap"
    ],
    "name:ita_x_preferred":[
        "Dunlap"
    ],
    "name:nld_x_preferred":[
        "Dunlap"
    ],
    "name:pol_x_preferred":[
        "Dunlap"
    ],
    "name:por_x_preferred":[
        "Dunlap"
    ],
    "name:spa_x_preferred":[
        "Dunlap"
    ],
    "name:srp_x_preferred":[
        "\u0414\u0430\u043d\u043b\u0430\u043f"
    ],
    "name:vol_x_preferred":[
        "Dunlap"
    ],
    "wof:name":"Dunlap",
    "wof:placetype":"locality"
},
  "geometry": {"coordinates":[-92.05901,31.20935],"type":"Point"}
}