{
  "type": "Feature",
  "properties": {
    "gn:country":"US",
    "gn:fcode":"PPL",
    "gn:population":0,
    "iso:country":"US",
    "name:deu_x_preferred":[
        "Dodd"
    ],
    "name:fra_x_preferred":[
        "Dodd"
    ],
    "name:ita_x_preferred":[
        "Dodd"
    ],
    "name:jpn_x_preferred":[
        "\u30c9\u30c3\u30c9"
    ],
    "name:rus_x_preferred":[
        "\u0414\u043e\u0434\u0434"
    ],
    "name:swe_x_preferred":[
        "Dodd"
    ],
    "name:ukr_x_preferred":[
        "\u0414\u043e\u0434\u0434"
    ],
    "qs_pg:aaroncc":"US",
    "qs_pg:gn_country":"US",
    "qs_pg:gn_fcode":"PPL",
    "qs_pg:gn_pop":0,
    "qs_pg:name":"Dodd",
    "qs_pg:name_adm0":"United States",
    "qs_pg:name_adm1":"Colorado",
    "qs_pg:photos":20,
    "qs_pg:photos_1k":4,
    "qs_pg:photos_9k":1,
    "qs_pg:photos_9r":1,
    "qs_pg:photos_all":20,
    "qs_pg:photos_sr":1,
    "qs_pg:pop_sr":0,
    "qs_pg:qs_pg_placetype":"locality",
    "qs_pg:qs_pg_placetype_gp":"Town",
    "qs_pg:woe_adm0":23424977,
    "woe:adm0_id":23424977,
    "woe:name_adm0":"United States",
    "woe:name_adm1":"Colorado",
    "woe:placetype":"Town",
    "wof:name":"Dodd",
    "wof:placetype":"locality"
},
  "geometry": {"coordinates":[-103.70744999999999,40.2872],"type":"Point"}
}