{
  "type": "Feature",
  "properties": {
    "gn:admin1_code":"WV",
    "gn:admin2_code":"47",
    "gn:asciiname":"Apple Grove",
    "gn:country_code":"US",
    "gn:dem":329,
    "gn:elevation":"315.0",
    "gn:feature_class":"P",
    "gn:feature_code":"PPL",
    "gn:name":"Apple Grove",
    "gn:population":0,
    "gn:timezone":"America/New_York",
    "iso:country":"US",
    "name:eng_x_preferred":[
        "Apple Grove"
    ],
    "name:fas_x_preferred":[
        "\u0627\u067e\u0644 \u06af\u0631\u0648\u0648"
    ],
    "name:und_x_variant":[
        "Applegrove"
    ],
    "name:vol_x_preferred":[
        "Apple Grove"
    ],
    "wof:name":"Apple Grove",
    "wof:placetype":"locality"
},
  "geometry": {"coordinates":[-81.80484,37.43761],"type":"Point"}
}