{
  "type": "Feature",
  "properties": {
    "gn:country":"US",
    "gn:fcode":"PPL",
    "gn:population":0,
    "iso:country":"US",
    "name:deu_x_preferred":[
        "Leeman"
    ],
    "name:nld_x_preferred":[
        "Leeman"
    ],
    "name:ukr_x_preferred":[
        "\u041b\u0456\u043c\u0435\u043d"
    ],
    "qs_pg:aaroncc":"US",
    "qs_pg:gn_country":"US",
    "qs_pg:gn_fcode":"PPL",
    "qs_pg:gn_pop":0,
    "qs_pg:name":"Leeman",
    "qs_pg:name_adm0":"United States",
    "qs_pg:name_adm1":"Wisconsin",
    "qs_pg:photos":2,
    "qs_pg:photos_1k":1,
    "qs_pg:photos_9k":1,
    "qs_pg:photos_9r":1,
    "qs_pg:photos_all":2,
    "qs_pg:photos_sr":1,
    "qs_pg:pop_sr":0,
    "qs_pg:qs_pg_placetype":"neighbourhood",
    "qs_pg:qs_pg_placetype_gp":"Suburb",
    "qs_pg:woe_adm0":23424977,
    "woe:adm0_id":23424977,
    "woe:name_adm0":"United States",
    "woe:name_adm1":"Wisconsin",
    "woe:placetype":"Suburb",
    "wof:name":"Leeman",
    "wof:placetype":"neighbourhood"
},
  "geometry": {"coordinates":[-88.55649,44.57415],"type":"Point"}
}