{
  "type": "Feature",
  "properties": {
    "gn:admin1_code":"DE",
    "gn:admin2_code":"003",
    "gn:asciiname":"Winterset Farms",
    "gn:country_code":"US",
    "gn:dem":133,
    "gn:elevation":"134.0",
    "gn:feature_class":"P",
    "gn:feature_code":"PPL",
    "gn:name":"Winterset Farms",
    "gn:population":0,
    "gn:timezone":"America/New_York",
    "iso:country":"US",
    "wof:name":"Winterset Farms",
    "wof:placetype":"locality"
},
  "geometry": {"coordinates":[-75.5241,39.8363],"type":"Point"}
}