{
  "type": "Feature",
  "properties": {
    "gn:admin1_code":"MD",
    "gn:admin2_code":"3.0",
    "gn:asciiname":"Fairoaks",
    "gn:country_code":"US",
    "gn:dem":11,
    "gn:elevation":"8.0",
    "gn:feature_class":"P",
    "gn:feature_code":"PPL",
    "gn:name":"Fairoaks",
    "gn:population":0,
    "gn:timezone":"America/New_York",
    "iso:country":"US",
    "wof:name":"Fairoaks",
    "wof:placetype":"locality"
},
  "geometry": {"coordinates":[-76.53357,39.08539],"type":"Point"}
}