{
  "type": "Feature",
  "properties": {
    "gn:admin1_code":"LA",
    "gn:admin2_code":"73.0",
    "gn:asciiname":"Hillside Park",
    "gn:country_code":"US",
    "gn:dem":71,
    "gn:elevation":"58.0",
    "gn:feature_class":"P",
    "gn:feature_code":"PPL",
    "gn:name":"Hillside Park",
    "gn:population":0,
    "gn:timezone":"America/Chicago",
    "iso:country":"US",
    "wof:name":"Hillside Park",
    "wof:placetype":"locality"
},
  "geometry": {"coordinates":[-92.23291999999999,32.53487],"type":"Point"}
}