{
  "type": "Feature",
  "properties": {
    "gn:admin1_code":"WY",
    "gn:admin2_code":"35.0",
    "gn:asciiname":"Bronx",
    "gn:country_code":"US",
    "gn:dem":2270,
    "gn:elevation":"2270.0",
    "gn:feature_class":"P",
    "gn:feature_code":"PPL",
    "gn:name":"Bronx",
    "gn:population":0,
    "gn:timezone":"America/Denver",
    "iso:country":"US",
    "wof:name":"Bronx",
    "wof:placetype":"locality"
},
  "geometry": {"coordinates":[-110.11572,42.99272],"type":"Point"}
}