{
  "type": "Feature",
  "properties": {
    "gn:admin1_code":"MO",
    "gn:admin2_code":"067",
    "gn:admin3_code":"48206.0",
    "gn:asciiname":"Basher",
    "gn:country_code":"US",
    "gn:dem":410,
    "gn:elevation":"409.0",
    "gn:feature_class":"P",
    "gn:feature_code":"PPL",
    "gn:name":"Basher",
    "gn:population":0,
    "gn:timezone":"America/Chicago",
    "iso:country":"US",
    "name:deu_x_preferred":[
        "Basher"
    ],
    "wof:name":"Basher",
    "wof:placetype":"locality"
},
  "geometry": {"coordinates":[-92.60599999999999,36.99672],"type":"Point"}
}