{
  "type": "Feature",
  "properties": {
    "iso:country":"US",
    "name:eng_x_preferred":[
        "Smoky Hollow"
    ],
    "wof:name":"Smoky Hollow",
    "wof:placetype":"neighbourhood",
    "wof:population":1196,
    "zs:area_m":229803.690093,
    "zs:blockids":[
        60376200021015,
        60376201022021,
        60376201022000,
        60376200021010,
        60376200021001,
        60376200021011,
        60376200021023,
        60376201022028,
        60376201022023,
        60376200023006,
        60376200021003,
        60376200021018,
        60376200021017,
        60376200023003,
        60376200021016,
        60376200021002,
        60376200021012,
        60376201022025,
        60376200021009,
        60376201022026,
        60376200021014,
        60376200023004,
        60376201022024,
        60376201022027,
        60376200021004,
        60376200021013
    ],
    "zs:housing10":566,
    "zs:label":"Smoky Hollow",
    "zs:pop10":1196
},
  "geometry": {"coordinates":[-118.410776,33.918778],"type":"Point"}
}