{
  "type": "Feature",
  "properties": {
    "gn:admin1_code":"TX",
    "gn:admin2_code":"187",
    "gn:asciiname":"Dugger",
    "gn:country_code":"US",
    "gn:dem":163,
    "gn:elevation":"161.0",
    "gn:feature_class":"P",
    "gn:feature_code":"PPL",
    "gn:name":"Dugger",
    "gn:population":0,
    "gn:timezone":"America/Chicago",
    "iso:country":"US",
    "wof:name":"Dugger",
    "wof:placetype":"locality"
},
  "geometry": {"coordinates":[-97.95139,29.50245],"type":"Point"}
}