{
  "type": "Feature",
  "properties": {
    "gn:admin1_code":"MO",
    "gn:admin2_code":"171.0",
    "gn:admin3_code":"21952.0",
    "gn:asciiname":"Graysville",
    "gn:country_code":"US",
    "gn:dem":301,
    "gn:elevation":"304.0",
    "gn:feature_class":"P",
    "gn:feature_code":"PPL",
    "gn:name":"Graysville",
    "gn:population":0,
    "gn:timezone":"America/Chicago",
    "iso:country":"US",
    "name:ceb_x_preferred":[
        "Graysville"
    ],
    "name:deu_x_preferred":[
        "Graysville"
    ],
    "name:eng_x_preferred":[
        "Graysville"
    ],
    "name:fra_x_preferred":[
        "Graysville"
    ],
    "name:ido_x_preferred":[
        "Graysville"
    ],
    "name:ita_x_preferred":[
        "Graysville"
    ],
    "name:nld_x_preferred":[
        "Graysville"
    ],
    "name:pol_x_preferred":[
        "Graysville"
    ],
    "name:por_x_preferred":[
        "Graysville"
    ],
    "name:srp_x_preferred":[
        "\u0413\u0440\u0435\u0458\u0441\u0432\u0438\u043b"
    ],
    "name:und_x_variant":[
        "Millersburg"
    ],
    "name:vol_x_preferred":[
        "Graysville"
    ],
    "wof:name":"Graysville",
    "wof:placetype":"locality"
},
  "geometry": {"coordinates":[-92.77909,40.44586],"type":"Point"}
}