{
  "type": "Feature",
  "properties": {
    "gn:admin1_code":"VT",
    "gn:admin2_code":"5.0",
    "gn:admin3_code":"64075.0",
    "gn:asciiname":"Sheffield Square",
    "gn:country_code":"US",
    "gn:dem":502,
    "gn:elevation":"506.0",
    "gn:feature_class":"P",
    "gn:feature_code":"PPL",
    "gn:name":"Sheffield Square",
    "gn:population":0,
    "gn:timezone":"America/New_York",
    "iso:country":"US",
    "wof:name":"Sheffield Square",
    "wof:placetype":"locality"
},
  "geometry": {"coordinates":[-72.15676999999999,44.62255],"type":"Point"}
}