{
  "type": "Feature",
  "properties": {
    "gn:admin1_code":"TN",
    "gn:admin2_code":"141.0",
    "gn:asciiname":"Brotherton",
    "gn:country_code":"US",
    "gn:dem":435,
    "gn:elevation":"435.0",
    "gn:feature_class":"P",
    "gn:feature_code":"PPL",
    "gn:name":"Brotherton",
    "gn:population":0,
    "gn:timezone":"America/Chicago",
    "iso:country":"US",
    "name:ceb_x_preferred":[
        "Brotherton"
    ],
    "name:nld_x_preferred":[
        "Brotherton"
    ],
    "name:pol_x_preferred":[
        "Brotherton"
    ],
    "name:swe_x_preferred":[
        "Brotherton"
    ],
    "wof:name":"Brotherton",
    "wof:placetype":"locality"
},
  "geometry": {"coordinates":[-85.37914000000001,36.18895],"type":"Point"}
}