{
  "type": "Feature",
  "properties": {
    "gn:admin1_code":"MD",
    "gn:admin2_code":"13.0",
    "gn:asciiname":"Centennial Homestead",
    "gn:country_code":"US",
    "gn:dem":161,
    "gn:elevation":"165.0",
    "gn:feature_class":"P",
    "gn:feature_code":"PPL",
    "gn:name":"Centennial Homestead",
    "gn:population":0,
    "gn:timezone":"America/New_York",
    "iso:country":"US",
    "wof:name":"Centennial Homestead",
    "wof:placetype":"locality"
},
  "geometry": {"coordinates":[-76.90498000000002,39.49455],"type":"Point"}
}