{
  "type": "Feature",
  "properties": {
    "gn:country":"US",
    "gn:fcode":"PPL",
    "gn:population":0,
    "iso:country":"US",
    "name:ara_x_preferred":[
        "\u0628\u064a\u063a \u0628\u0646\u062f"
    ],
    "name:ben_x_preferred":[
        "\u09ac\u09bf\u0997 \u09ac\u09c7\u09a8\u09cd\u09a1"
    ],
    "name:cat_x_preferred":[
        "Big Bend"
    ],
    "name:ceb_x_preferred":[
        "Big Bend"
    ],
    "name:deu_x_preferred":[
        "Big-Bend-Nationalpark"
    ],
    "name:deu_x_variant":[
        "Big Bend"
    ],
    "name:ell_x_preferred":[
        "\u039c\u03c0\u03b9\u03b3\u03ba \u039c\u03c0\u03b5\u03bd\u03c4"
    ],
    "name:fas_x_preferred":[
        "\u0628\u06cc\u06af \u0628\u0646\u062f"
    ],
    "name:fra_x_preferred":[
        "Big Bend"
    ],
    "name:heb_x_preferred":[
        "\u05d1\u05d9\u05d2 \u05d1\u05e0\u05d3"
    ],
    "name:hin_x_preferred":[
        "\u092c\u093f\u0917 \u092c\u0947\u0902\u0921 "
    ],
    "name:hun_x_preferred":[
        "Big Bend"
    ],
    "name:ind_x_preferred":[
        "Big Bend"
    ],
    "name:ita_x_preferred":[
        "Big Bend"
    ],
    "name:kor_x_preferred":[
        "\ube45 \ubca4\ub4dc"
    ],
    "name:nld_x_preferred":[
        "Big Bend"
    ],
    "name:pol_x_preferred":[
        "Big Bend"
    ],
    "name:por_x_preferred":[
        "Big Bend"
    ],
    "name:rus_x_preferred":[
        "\u0411\u0438\u0433-\u0411\u0435\u043d\u0434"
    ],
    "name:spa_x_preferred":[
        "Big Bend"
    ],
    "name:srp_x_preferred":[
        "\u0411\u0438\u0433 \u0411\u0435\u043d\u0434"
    ],
    "name:swe_x_preferred":[
        "Big Bend"
    ],
    "name:tur_x_preferred":[
        "Big Bend"
    ],
    "name:ukr_x_preferred":[
        "\u0411\u0456\u0433-\u0411\u0435\u043d\u0434"
    ],
    "name:urd_x_preferred":[
        "\u0628\u06cc\u06af \u0628\u06cc\u0646\u0688"
    ],
    "name:vie_x_preferred":[
        "Sa m\u1ea1c Big Bend"
    ],
    "name:vol_x_preferred":[
        "Big Bend"
    ],
    "name:zho_cn_x_preferred":[
        "\u5927\u672c\u5fb7\u6c99\u6f20"
    ],
    "name:zho_tw_x_preferred":[
        "\u7562\u672c\u5fb7\u6c99\u6f20"
    ],
    "qs_pg:aaroncc":"US",
    "qs_pg:gn_country":"US",
    "qs_pg:gn_fcode":"PPL",
    "qs_pg:gn_pop":0,
    "qs_pg:name":"Big Bend",
    "qs_pg:name_adm0":"United States",
    "qs_pg:name_adm1":"New York",
    "qs_pg:photos":3,
    "qs_pg:photos_1k":1,
    "qs_pg:photos_9k":1,
    "qs_pg:photos_9r":1,
    "qs_pg:photos_all":3,
    "qs_pg:photos_sr":1,
    "qs_pg:pop_sr":0,
    "qs_pg:qs_pg_placetype":"neighbourhood",
    "qs_pg:qs_pg_placetype_gp":"Suburb",
    "qs_pg:woe_adm0":23424977,
    "woe:adm0_id":23424977,
    "woe:name_adm0":"United States",
    "woe:name_adm1":"New York",
    "woe:placetype":"Suburb",
    "wof:name":"Big Bend",
    "wof:placetype":"neighbourhood"
},
  "geometry": {"coordinates":[-76.08965000000001,42.87757],"type":"Point"}
}