{
  "type": "Feature",
  "properties": {
    "gn:country":"US",
    "gn:fcode":"PPL",
    "gn:population":0,
    "iso:country":"US",
    "name:cat_x_preferred":[
        "Big Bend"
    ],
    "name:ceb_x_preferred":[
        "Big Bend"
    ],
    "name:deu_x_preferred":[
        "Big Bend"
    ],
    "name:fra_x_preferred":[
        "Big Bend"
    ],
    "name:heb_x_preferred":[
        "\u05d1\u05d9\u05d2 \u05d1\u05e0\u05d3"
    ],
    "name:ita_x_preferred":[
        "Big Bend"
    ],
    "name:nld_x_preferred":[
        "Big Bend"
    ],
    "name:pol_x_preferred":[
        "Big Bend"
    ],
    "name:por_x_preferred":[
        "Big Bend"
    ],
    "name:rus_x_preferred":[
        "\u0411\u0438\u0433-\u0411\u0435\u043d\u0434"
    ],
    "name:spa_x_preferred":[
        "Big Bend"
    ],
    "name:srp_x_preferred":[
        "\u0411\u0438\u0433 \u0411\u0435\u043d\u0434"
    ],
    "name:swe_x_preferred":[
        "Big Bend"
    ],
    "name:ukr_x_preferred":[
        "\u0411\u0456\u0433-\u0411\u0435\u043d\u0434"
    ],
    "name:vol_x_preferred":[
        "Big Bend"
    ],
    "qs_pg:aaroncc":"US",
    "qs_pg:gn_country":"US",
    "qs_pg:gn_fcode":"PPL",
    "qs_pg:gn_pop":0,
    "qs_pg:name":"Big Bend",
    "qs_pg:name_adm0":"United States",
    "qs_pg:name_adm1":"New York",
    "qs_pg:photos":3,
    "qs_pg:photos_1k":1,
    "qs_pg:photos_9k":1,
    "qs_pg:photos_9r":1,
    "qs_pg:photos_all":3,
    "qs_pg:photos_sr":1,
    "qs_pg:pop_sr":0,
    "qs_pg:qs_pg_placetype":"neighbourhood",
    "qs_pg:qs_pg_placetype_gp":"Suburb",
    "qs_pg:woe_adm0":23424977,
    "woe:adm0_id":23424977,
    "woe:name_adm0":"United States",
    "woe:name_adm1":"New York",
    "woe:placetype":"Suburb",
    "wof:name":"Big Bend",
    "wof:placetype":"neighbourhood"
},
  "geometry": {"coordinates":[-76.08965000000001,42.87757],"type":"Point"}
}