{
  "type": "Feature",
  "properties": {
    "gn:admin1_code":"AZ",
    "gn:admin2_code":"13.0",
    "gn:asciiname":"Twin Acres Family Mobile Park",
    "gn:country_code":"US",
    "gn:dem":475,
    "gn:elevation":"476.0",
    "gn:feature_class":"P",
    "gn:feature_code":"PPL",
    "gn:name":"Twin Acres Family Mobile Park",
    "gn:population":0,
    "gn:timezone":"America/Phoenix",
    "iso:country":"US",
    "wof:name":"Twin Acres Family Mobile Park",
    "wof:placetype":"locality"
},
  "geometry": {"coordinates":[-111.61651999999999,33.41366],"type":"Point"}
}