{
  "type": "Feature",
  "properties": {
    "iso:country":"US",
    "name:ceb_x_preferred":[
        "Lake Ridge"
    ],
    "name:deu_x_preferred":[
        "Lake Ridge"
    ],
    "name:eng_x_preferred":[
        "Lake Ridge"
    ],
    "name:swe_x_preferred":[
        "Lake Ridge"
    ],
    "wd:wordcount":25,
    "wof:name":"Lake Ridge",
    "wof:placetype":"neighbourhood",
    "wof:population":27,
    "zs:area_m":38257.228187,
    "zs:blockids":[
        120570113041011,
        120570113041010
    ],
    "zs:housing10":10,
    "zs:label":"Lake Ridge",
    "zs:pop10":27
},
  "geometry": {"coordinates":[-82.488433,28.054385],"type":"Point"}
}