{
  "type": "Feature",
  "properties": {
    "gn:country":"US",
    "gn:fcode":"PPL",
    "gn:population":0,
    "iso:country":"US",
    "name:ara_x_preferred":[
        "\u0628\u0631\u0627\u063a\u0627\u062f\u0648\u062a\u0634\u064a\u0648\u060c \u0645\u064a\u0632\u0648\u0631\u064a"
    ],
    "name:ara_x_variant":[
        "\u0628\u0631\u0627\u063a\u0627\u062f\u0648\u062a\u0634\u064a\u0648"
    ],
    "name:eng_x_preferred":[
        "Braggadocio"
    ],
    "name:fra_x_preferred":[
        "Braggadocio"
    ],
    "name:und_x_variant":[
        "Braggadocia"
    ],
    "name:vol_x_preferred":[
        "Braggadocio"
    ],
    "qs_pg:aaroncc":"US",
    "qs_pg:gn_country":"US",
    "qs_pg:gn_fcode":"PPL",
    "qs_pg:gn_pop":0,
    "qs_pg:name":"Braggadocio",
    "qs_pg:name_adm0":"United States",
    "qs_pg:name_adm1":"Missouri",
    "qs_pg:photos_9k":1,
    "qs_pg:photos_9r":1,
    "qs_pg:photos_all":23,
    "qs_pg:photos_sr":0,
    "qs_pg:pop_sr":5,
    "qs_pg:qs_pg_placetype":"locality",
    "qs_pg:qs_pg_placetype_gp":"Town",
    "qs_pg:woe_adm0":23424977,
    "woe:adm0_id":23424977,
    "woe:name_adm0":"United States",
    "woe:name_adm1":"Missouri",
    "woe:placetype":"Town",
    "wof:name":"Braggadocio",
    "wof:placetype":"locality"
},
  "geometry": {"coordinates":[-89.82953000000001,36.17535],"type":"Point"}
}