{
  "type": "Feature",
  "properties": {
    "iso:country":"US",
    "name:eng_x_preferred":[
        "Strawberry Heights"
    ],
    "qs:gn_local":0,
    "qs:local_max":205,
    "qs:local_sum":385,
    "qs:localhoods":4,
    "qs:name":"Strawberry Heights",
    "qs:name_adm0":"United States",
    "qs:name_adm1":"California",
    "qs:name_adm2":"El Dorado",
    "qs:name_local":"Kyburz",
    "qs:photo_max":26,
    "qs:photo_sum":73,
    "qs:placetype":"Suburb",
    "qs:quad_count":4,
    "qs:woe_adm0":23424977,
    "qs:woe_adm1":2347563,
    "qs:woe_adm2":12587678,
    "qs:woe_lau":0,
    "qs:woe_local":2434067,
    "qs:woe_ver":"7.10.0",
    "wof:lang":[
        "eng"
    ],
    "wof:name":"Strawberry Heights",
    "wof:placetype":"neighbourhood",
    "wof:population":11,
    "zs:blockids":[
        60170306034096,
        60170319001067,
        60170306034095
    ],
    "zs:housing10":45,
    "zs:pop10":11
},
  "geometry": {"coordinates":[-120.145319,38.796469],"type":"Point"}
}