{
  "type": "Feature",
  "properties": {
    "gn:admin1_code":"IL",
    "gn:admin2_code":"197",
    "gn:admin3_code":"21241.0",
    "gn:asciiname":"Rivermist",
    "gn:country_code":"US",
    "gn:dem":200,
    "gn:elevation":"195.0",
    "gn:feature_class":"P",
    "gn:feature_code":"PPL",
    "gn:name":"Rivermist",
    "gn:population":0,
    "gn:timezone":"America/Chicago",
    "iso:country":"US",
    "wof:name":"Rivermist",
    "wof:placetype":"locality"
},
  "geometry": {"coordinates":[-88.13500000000001,41.71694],"type":"Point"}
}