{
  "type": "Feature",
  "properties": {
    "gn:admin1_code":"AR",
    "gn:admin2_code":"35.0",
    "gn:admin3_code":"93033.0",
    "gn:asciiname":"Millers",
    "gn:country_code":"US",
    "gn:dem":63,
    "gn:elevation":"63.0",
    "gn:feature_class":"P",
    "gn:feature_code":"PPL",
    "gn:name":"Millers",
    "gn:population":0,
    "gn:timezone":"America/Chicago",
    "iso:country":"US",
    "name:deu_x_preferred":[
        "Millers"
    ],
    "name:eng_x_preferred":[
        "Millers"
    ],
    "name:lav_x_preferred":[
        "Millers"
    ],
    "name:und_x_variant":[
        "Scanlan"
    ],
    "wof:name":"Millers",
    "wof:placetype":"locality"
},
  "geometry": {"coordinates":[-90.23009999999999,35.06287],"type":"Point"}
}