{
  "type": "Feature",
  "properties": {
    "gn:admin1_code":"AZ",
    "gn:admin2_code":"13.0",
    "gn:asciiname":"Purple Sage Mobile Home Park",
    "gn:country_code":"US",
    "gn:dem":345,
    "gn:elevation":"347.0",
    "gn:feature_class":"P",
    "gn:feature_code":"PPL",
    "gn:name":"Purple Sage Mobile Home Park",
    "gn:population":0,
    "gn:timezone":"America/Phoenix",
    "iso:country":"US",
    "wof:name":"Purple Sage Mobile Home Park",
    "wof:placetype":"campus"
},
  "geometry": {"coordinates":[-112.19932,33.53921],"type":"Point"}
}