{
  "type": "Feature",
  "properties": {
    "gn:admin1_code":"FL",
    "gn:admin2_code":"57",
    "gn:asciiname":"Lake View",
    "gn:country_code":"US",
    "gn:dem":22,
    "gn:elevation":"15.0",
    "gn:feature_class":"P",
    "gn:feature_code":"PPL",
    "gn:name":"Lake View",
    "gn:population":0,
    "gn:timezone":"America/New_York",
    "iso:country":"US",
    "name:ceb_x_preferred":[
        "Lake View"
    ],
    "name:deu_x_preferred":[
        "Lake View"
    ],
    "name:ita_x_preferred":[
        "Lake View"
    ],
    "name:nld_x_preferred":[
        "Lake View"
    ],
    "name:pol_x_preferred":[
        "Lake View"
    ],
    "name:por_x_preferred":[
        "Lake View"
    ],
    "name:spa_x_preferred":[
        "Lake View"
    ],
    "name:srp_x_preferred":[
        "\u041b\u0435\u0458\u043a \u0412\u0458\u0443"
    ],
    "name:ukr_x_preferred":[
        "\u041b\u0435\u0439\u043a-\u0412'\u044e"
    ],
    "name:vol_x_preferred":[
        "Lake View"
    ],
    "name:zho_x_preferred":[
        "\u62c9\u514b\u592b\u7531"
    ],
    "wof:name":"Lake View",
    "wof:placetype":"locality"
},
  "geometry": {"coordinates":[-82.2711,27.9853],"type":"Point"}
}