{
  "type": "Feature",
  "properties": {
    "gn:admin1_code":"TX",
    "gn:admin2_code":"201.0",
    "gn:asciiname":"Tarrytown",
    "gn:country_code":"US",
    "gn:dem":13,
    "gn:elevation":"11.0",
    "gn:feature_class":"P",
    "gn:feature_code":"PPL",
    "gn:name":"Tarrytown",
    "gn:population":0,
    "gn:timezone":"America/Chicago",
    "iso:country":"US",
    "wof:name":"Tarrytown",
    "wof:placetype":"locality"
},
  "geometry": {"coordinates":[-95.19799999999999,29.6789],"type":"Point"}
}