{
  "type": "Feature",
  "properties": {
    "iso:country":"US",
    "wof:name":"Chambers Lake Basin",
    "wof:placetype":"neighbourhood"
},
  "geometry": {"coordinates":[-122.84971976556308,47.02163789531679],"type":"Point"}
}