{
  "type": "Feature",
  "properties": {
    "gn:admin1_code":"VA",
    "gn:admin2_code":"163",
    "gn:asciiname":"South River",
    "gn:country_code":"US",
    "gn:dem":291,
    "gn:elevation":"300.0",
    "gn:feature_class":"P",
    "gn:feature_code":"PPL",
    "gn:name":"South River",
    "gn:population":0,
    "gn:timezone":"America/New_York",
    "iso:country":"US",
    "name:ceb_x_preferred":[
        "South River"
    ],
    "name:deu_x_preferred":[
        "South River"
    ],
    "name:nld_x_preferred":[
        "South River"
    ],
    "name:pol_x_preferred":[
        "South River"
    ],
    "name:swe_x_preferred":[
        "South River"
    ],
    "wof:name":"South River",
    "wof:placetype":"locality"
},
  "geometry": {"coordinates":[-79.38809000000001,37.77458],"type":"Point"}
}