{
  "type": "Feature",
  "properties": {
    "gn:admin1_code":"TX",
    "gn:admin2_code":"37.0",
    "gn:asciiname":"Old Boston",
    "gn:country_code":"US",
    "gn:dem":111,
    "gn:elevation":"107.0",
    "gn:feature_class":"P",
    "gn:feature_code":"PPL",
    "gn:name":"Old Boston",
    "gn:population":0,
    "gn:timezone":"America/Chicago",
    "iso:country":"US",
    "wof:name":"Old Boston",
    "wof:placetype":"locality"
},
  "geometry": {"coordinates":[-94.41631,33.40401],"type":"Point"}
}