{
  "type": "Feature",
  "properties": {
    "gn:admin1_code":"AL",
    "gn:admin2_code":"121",
    "gn:asciiname":"Mardisville",
    "gn:country_code":"US",
    "gn:dem":161,
    "gn:elevation":"155.0",
    "gn:feature_class":"P",
    "gn:feature_code":"PPL",
    "gn:name":"Mardisville",
    "gn:population":0,
    "gn:timezone":"America/Chicago",
    "iso:country":"US",
    "name:eng_x_preferred":[
        "Mardisville"
    ],
    "name:fas_x_preferred":[
        "\u0645\u0627\u0631\u062f\u06cc\u0632\u0648\u06cc\u0644"
    ],
    "name:und_x_variant":[
        "Jumpers Spring"
    ],
    "name:zho_x_preferred":[
        "\u9a6c\u8fea\u65af\u7ef4\u5c14"
    ],
    "wof:name":"Mardisville",
    "wof:placetype":"locality"
},
  "geometry": {"coordinates":[-86.15914000000002,33.38455],"type":"Point"}
}