{
  "type": "Feature",
  "properties": {
    "iso:country":"US",
    "name:eng_x_preferred":[
        "Hernage"
    ],
    "wof:name":"Hernage",
    "wof:placetype":"neighbourhood",
    "wof:population":68,
    "zs:area_m":45979829.699637,
    "zs:blockids":[
        81070008001102,
        81070008001162,
        81070008001103,
        81070008001093,
        81070008001130,
        81070008001158,
        81070008001161,
        81070008001163,
        81070008001101,
        81070008001160
    ],
    "zs:housing10":43,
    "zs:label":"Hernage",
    "zs:pop10":68
},
  "geometry": {"coordinates":[-106.91860800000001,40.101716],"type":"Point"}
}