{
  "type": "Feature",
  "properties": {
    "gn:admin1_code":"AL",
    "gn:admin2_code":"073",
    "gn:asciiname":"Bel Air",
    "gn:country_code":"US",
    "gn:dem":232,
    "gn:elevation":"218.0",
    "gn:feature_class":"P",
    "gn:feature_code":"PPL",
    "gn:name":"Bel Air",
    "gn:population":0,
    "gn:timezone":"America/Chicago",
    "iso:country":"US",
    "name:ceb_x_preferred":[
        "Bel Air"
    ],
    "name:deu_x_preferred":[
        "Bel Air"
    ],
    "name:fra_x_preferred":[
        "Bel Air"
    ],
    "name:heb_x_preferred":[
        "\u05d1\u05dc \u05d0\u05d9\u05d9\u05e8"
    ],
    "name:hun_x_preferred":[
        "Bel Air"
    ],
    "name:ita_x_preferred":[
        "Bel Air"
    ],
    "name:kor_x_preferred":[
        "\ubca8\uc5d0\uc5b4"
    ],
    "name:nld_x_preferred":[
        "Bel Air"
    ],
    "name:pol_x_preferred":[
        "Bel Air"
    ],
    "name:por_x_preferred":[
        "Bel Air"
    ],
    "name:rus_x_preferred":[
        "Bel Air"
    ],
    "name:srp_x_preferred":[
        "\u0411\u0435\u043b \u0415\u0440"
    ],
    "name:ukr_x_preferred":[
        "\u0411\u0435\u043b\u044c-\u0415\u0440"
    ],
    "name:vol_x_preferred":[
        "Bel Air"
    ],
    "wof:name":"Bel Air",
    "wof:placetype":"locality"
},
  "geometry": {"coordinates":[-86.72138,33.5851],"type":"Point"}
}