{
  "type": "Feature",
  "properties": {
    "gn:admin1_code":"IL",
    "gn:admin2_code":"147.0",
    "gn:admin3_code":"67587.0",
    "gn:asciiname":"Galesville",
    "gn:country_code":"US",
    "gn:dem":219,
    "gn:elevation":"218.0",
    "gn:feature_class":"P",
    "gn:feature_code":"PPL",
    "gn:name":"Galesville",
    "gn:population":0,
    "gn:timezone":"America/Chicago",
    "iso:country":"US",
    "name:eng_x_preferred":[
        "Galesville"
    ],
    "name:und_x_variant":[
        "Calef Station"
    ],
    "wof:name":"Galesville",
    "wof:placetype":"locality"
},
  "geometry": {"coordinates":[-88.55645,40.15531],"type":"Point"}
}