{
  "type": "Feature",
  "properties": {
    "gn:admin1_code":"WI",
    "gn:admin2_code":"29.0",
    "gn:admin3_code":"10700.0",
    "gn:asciiname":"Kolberg",
    "gn:country_code":"US",
    "gn:dem":216,
    "gn:elevation":"215.0",
    "gn:feature_class":"P",
    "gn:feature_code":"PPL",
    "gn:name":"Kolberg",
    "gn:population":0,
    "gn:timezone":"America/Chicago",
    "iso:country":"US",
    "wof:name":"Kolberg",
    "wof:placetype":"locality"
},
  "geometry": {"coordinates":[-87.54898,44.71916],"type":"Point"}
}