{
  "type": "Feature",
  "properties": {
    "gn:admin1_code":"IL",
    "gn:admin2_code":"157.0",
    "gn:asciiname":"Welge",
    "gn:country_code":"US",
    "gn:dem":119,
    "gn:elevation":"123.0",
    "gn:feature_class":"P",
    "gn:feature_code":"PPL",
    "gn:name":"Welge",
    "gn:population":0,
    "gn:timezone":"America/Chicago",
    "iso:country":"US",
    "name:eng_x_preferred":[
        "Welge"
    ],
    "name:und_x_variant":[
        "Wedge"
    ],
    "wof:name":"Welge",
    "wof:placetype":"locality"
},
  "geometry": {"coordinates":[-89.71259999999999,37.95644],"type":"Point"}
}