{
  "type": "Feature",
  "properties": {
    "iso:country":"US",
    "name:ceb_x_preferred":[
        "Cedar Hill"
    ],
    "name:deu_x_preferred":[
        "Cedar Hill"
    ],
    "name:eng_x_preferred":[
        "Cedar Hill"
    ],
    "name:ita_x_preferred":[
        "Cedar Hill"
    ],
    "name:nld_x_preferred":[
        "Cedar Hill"
    ],
    "name:pol_x_preferred":[
        "Cedar Hill"
    ],
    "name:por_x_preferred":[
        "Cedar Hill"
    ],
    "name:rus_x_preferred":[
        "\u0421\u0438\u0434\u0430\u0440-\u0425\u0438\u043b\u043b"
    ],
    "name:srp_x_preferred":[
        "\u0421\u0438\u0434\u0430\u0440 \u0425\u0438\u043b"
    ],
    "name:swe_x_preferred":[
        "Cedar Hill"
    ],
    "name:vol_x_preferred":[
        "Cedar Hill"
    ],
    "wof:name":"Cedar Hill",
    "wof:placetype":"neighbourhood",
    "wof:population":1058,
    "zs:area_m":10182323.962399,
    "zs:blockids":[
        360010143012054,
        360010143011031,
        360010143011007,
        360010144011008,
        360010143012055,
        360010143011006,
        360010143011015,
        360010144011009,
        360010143011005,
        360010143011039,
        360010143011014,
        360010143012059,
        360010144011006,
        360010143011002,
        360010143011012,
        360010143012058,
        360010143012061,
        360010143011035,
        360010143011016,
        360010143011025,
        360010143012051,
        360010143011024,
        360010143011032,
        360010143011009,
        360010143011034,
        360010144011004,
        360010144011080,
        360010143012050,
        360010143011011,
        360010143011013,
        360010143011038,
        360010143011010,
        360010144011010,
        360010144011003,
        360010144011007,
        360010143011004,
        360010143011026,
        360010143011008,
        360010143011037,
        360010144011005,
        360010144011030,
        360010143011033,
        360010143012056,
        360010143012057,
        360010144011011,
        360010143012049
    ],
    "zs:housing10":422,
    "zs:label":"Cedar Hill",
    "zs:pop10":1058
},
  "geometry": {"coordinates":[-73.791428,42.545205],"type":"Point"}
}