{
  "type": "Feature",
  "properties": {
    "gn:admin1_code":"MD",
    "gn:admin2_code":"13.0",
    "gn:asciiname":"Ross Run Estates",
    "gn:country_code":"US",
    "gn:dem":234,
    "gn:elevation":"222.0",
    "gn:feature_class":"P",
    "gn:feature_code":"PPL",
    "gn:name":"Ross Run Estates",
    "gn:population":0,
    "gn:timezone":"America/New_York",
    "iso:country":"US",
    "wof:name":"Ross Run Estates",
    "wof:placetype":"locality"
},
  "geometry": {"coordinates":[-76.92804,39.64316],"type":"Point"}
}