{
  "type": "Feature",
  "properties": {
    "gn:admin1_code":"AZ",
    "gn:admin2_code":"17.0",
    "gn:asciiname":"Rainbow Lake Mobile Home Park",
    "gn:country_code":"US",
    "gn:dem":2058,
    "gn:elevation":"2055.0",
    "gn:feature_class":"P",
    "gn:feature_code":"PPL",
    "gn:name":"Rainbow Lake Mobile Home Park",
    "gn:population":0,
    "gn:timezone":"America/Phoenix",
    "iso:country":"US",
    "wof:name":"Rainbow Lake Mobile Home Park",
    "wof:placetype":"campus"
},
  "geometry": {"coordinates":[-109.99321,34.16027],"type":"Point"}
}