{
  "type": "Feature",
  "properties": {
    "gn:admin1_code":"AK",
    "gn:admin2_code":"290.0",
    "gn:asciiname":"Old McGrath",
    "gn:country_code":"US",
    "gn:dem":101,
    "gn:elevation":"101.0",
    "gn:feature_class":"P",
    "gn:feature_code":"PPL",
    "gn:name":"Old McGrath",
    "gn:population":0,
    "gn:timezone":"America/Anchorage",
    "iso:country":"US",
    "wof:name":"Old McGrath",
    "wof:placetype":"locality"
},
  "geometry": {"coordinates":[-155.57972000000001,62.96639],"type":"Point"}
}