{
  "type": "Feature",
  "properties": {
    "gn:admin1_code":"DE",
    "gn:admin2_code":"5.0",
    "gn:asciiname":"Pinetown",
    "gn:country_code":"US",
    "gn:dem":6,
    "gn:elevation":"6.0",
    "gn:feature_class":"P",
    "gn:feature_code":"PPL",
    "gn:name":"Pinetown",
    "gn:population":0,
    "gn:timezone":"America/New_York",
    "iso:country":"US",
    "name:zho_x_preferred":[
        "\u6d3e\u6069\u6566"
    ],
    "wof:name":"Pinetown",
    "wof:placetype":"locality"
},
  "geometry": {"coordinates":[-75.2238,38.74539],"type":"Point"}
}