{
  "type": "Feature",
  "properties": {
    "gn:country":"US",
    "gn:fcode":"PPL",
    "gn:population":0,
    "iso:country":"US",
    "qs_pg:aaroncc":"US",
    "qs_pg:gn_country":"US",
    "qs_pg:gn_fcode":"PPL",
    "qs_pg:gn_pop":0,
    "qs_pg:name":"Paulina Hills",
    "qs_pg:name_adm0":"United States",
    "qs_pg:name_adm1":"Missouri",
    "qs_pg:photos":413,
    "qs_pg:photos_1k":84,
    "qs_pg:photos_9k":2,
    "qs_pg:photos_9r":5,
    "qs_pg:photos_all":413,
    "qs_pg:photos_sr":6,
    "qs_pg:pop_sr":0,
    "qs_pg:qs_pg_placetype":"locality",
    "qs_pg:qs_pg_placetype_gp":"Town",
    "qs_pg:woe_adm0":23424977,
    "woe:adm0_id":23424977,
    "woe:name_adm0":"United States",
    "woe:name_adm1":"Missouri",
    "woe:placetype":"Town",
    "wof:name":"Paulina Hills",
    "wof:placetype":"locality"
},
  "geometry": {"coordinates":[-90.42845,38.46089],"type":"Point"}
}