{
  "type": "Feature",
  "properties": {
    "gn:admin1_code":"MO",
    "gn:admin2_code":"223.0",
    "gn:admin3_code":"48404.0",
    "gn:asciiname":"Gaylor",
    "gn:country_code":"US",
    "gn:dem":140,
    "gn:elevation":"135.0",
    "gn:feature_class":"P",
    "gn:feature_code":"PPL",
    "gn:name":"Gaylor",
    "gn:population":0,
    "gn:timezone":"America/Chicago",
    "iso:country":"US",
    "name:eng_x_preferred":[
        "Gaylor"
    ],
    "name:fra_x_preferred":[
        "Gaylor"
    ],
    "name:und_x_variant":[
        "Chilton"
    ],
    "wof:name":"Gaylor",
    "wof:placetype":"locality"
},
  "geometry": {"coordinates":[-90.71401,37.09672],"type":"Point"}
}