{
  "type": "Feature",
  "properties": {
    "gn:admin1_code":"LA",
    "gn:admin2_code":"119.0",
    "gn:asciiname":"Invincible",
    "gn:country_code":"US",
    "gn:dem":80,
    "gn:elevation":"71.0",
    "gn:feature_class":"P",
    "gn:feature_code":"PPL",
    "gn:name":"Invincible",
    "gn:population":0,
    "gn:timezone":"America/Chicago",
    "iso:country":"US",
    "name:ces_x_preferred":[
        "Invincible"
    ],
    "name:dan_x_preferred":[
        "Invincible"
    ],
    "name:deu_x_preferred":[
        "Invincible"
    ],
    "name:est_x_preferred":[
        "Invincible"
    ],
    "name:fin_x_preferred":[
        "Invincible"
    ],
    "name:fra_x_preferred":[
        "Invincible"
    ],
    "name:heb_x_preferred":[
        "\u05d1\u05dc\u05ea\u05d9 \u05de\u05e0\u05d5\u05e6\u05d7"
    ],
    "name:hun_x_preferred":[
        "Invincible"
    ],
    "name:hye_x_preferred":[
        "Invincible"
    ],
    "name:ita_x_preferred":[
        "Invincible"
    ],
    "name:jpn_x_preferred":[
        "\u30a4\u30f3\u30f4\u30a3\u30f3\u30b7\u30d6\u30eb"
    ],
    "name:kor_x_preferred":[
        "\uc778\ube48\uc11c\ube14"
    ],
    "name:nld_x_preferred":[
        "Invincible"
    ],
    "name:pol_x_preferred":[
        "Invincible"
    ],
    "name:por_x_preferred":[
        "Invincible"
    ],
    "name:rus_x_preferred":[
        "\u041d\u0435\u043f\u043e\u0431\u0435\u0434\u0438\u043c\u044b\u0439"
    ],
    "name:slv_x_preferred":[
        "Invincible"
    ],
    "name:spa_x_preferred":[
        "Invincible"
    ],
    "name:swe_x_preferred":[
        "Invincible"
    ],
    "name:tur_x_preferred":[
        "Invincible"
    ],
    "name:ukr_x_preferred":[
        "Invincible"
    ],
    "wof:name":"Invincible",
    "wof:placetype":"locality"
},
  "geometry": {"coordinates":[-93.40767,32.78737],"type":"Point"}
}