{
  "type": "Feature",
  "properties": {
    "gn:admin1_code":"TX",
    "gn:admin2_code":"455.0",
    "gn:asciiname":"Nogalus",
    "gn:country_code":"US",
    "gn:dem":119,
    "gn:elevation":"115.0",
    "gn:feature_class":"P",
    "gn:feature_code":"PPL",
    "gn:name":"Nogalus",
    "gn:population":0,
    "gn:timezone":"America/Chicago",
    "iso:country":"US",
    "name:eng_x_preferred":[
        "Nogalus"
    ],
    "name:und_x_variant":[
        "Nogallows",
        "Nogallis"
    ],
    "wof:name":"Nogalus",
    "wof:placetype":"locality"
},
  "geometry": {"coordinates":[-95.08826999999999,31.25546],"type":"Point"}
}