{
  "type": "Feature",
  "properties": {
    "gn:admin1_code":"GA",
    "gn:admin2_code":"57.0",
    "gn:asciiname":"Laffingal",
    "gn:country_code":"US",
    "gn:dem":336,
    "gn:elevation":"334.0",
    "gn:feature_class":"P",
    "gn:feature_code":"PPL",
    "gn:name":"Laffingal",
    "gn:population":0,
    "gn:timezone":"America/New_York",
    "iso:country":"US",
    "name:eng_x_preferred":[
        "Laffingal"
    ],
    "name:und_x_variant":[
        "Laughing Gal",
        "Laffing Gal"
    ],
    "wof:name":"Laffingal",
    "wof:placetype":"locality"
},
  "geometry": {"coordinates":[-84.64854,34.19149],"type":"Point"}
}