{
  "type": "Feature",
  "properties": {
    "gn:admin1_code":"CA",
    "gn:admin2_code":"107.0",
    "gn:asciiname":"Rayo",
    "gn:country_code":"US",
    "gn:dem":117,
    "gn:elevation":"114.0",
    "gn:feature_class":"P",
    "gn:feature_code":"PPL",
    "gn:name":"Rayo",
    "gn:population":0,
    "gn:timezone":"America/Los_Angeles",
    "iso:country":"US",
    "wof:name":"Rayo",
    "wof:placetype":"locality"
},
  "geometry": {"coordinates":[-119.18817,36.44995],"type":"Point"}
}