{
  "type": "Feature",
  "properties": {
    "gn:admin1_code":"MD",
    "gn:admin2_code":"5.0",
    "gn:asciiname":"Valley Mill",
    "gn:country_code":"US",
    "gn:dem":175,
    "gn:elevation":"165.0",
    "gn:feature_class":"P",
    "gn:feature_code":"PPL",
    "gn:name":"Valley Mill",
    "gn:population":0,
    "gn:timezone":"America/New_York",
    "iso:country":"US",
    "wof:name":"Valley Mill",
    "wof:placetype":"locality"
},
  "geometry": {"coordinates":[-76.69247,39.67344],"type":"Point"}
}