{
  "type": "Feature",
  "properties": {
    "iso:country":"US",
    "name:ceb_x_preferred":[
        "Mesta Park"
    ],
    "wof:name":"Mesta Park",
    "wof:placetype":"neighbourhood"
},
  "geometry": {"coordinates":[-97.52567733363055,35.48932981696284],"type":"Point"}
}