{
  "type": "Feature",
  "properties": {
    "gn:country":"US",
    "gn:fcode":"PPL",
    "gn:population":22560,
    "iso:country":"US",
    "name:azb_x_preferred":[
        "\u0648\u0627\u0633\u06a9\u0648"
    ],
    "name:ceb_x_preferred":[
        "Wasco"
    ],
    "name:eng_x_preferred":[
        "Wasco"
    ],
    "name:fas_x_preferred":[
        "\u0648\u0627\u0633\u06a9\u0648"
    ],
    "name:fra_x_preferred":[
        "Wasco"
    ],
    "name:nld_x_preferred":[
        "Wasco"
    ],
    "name:zho_x_preferred":[
        "\u74e6\u65af\u79d1"
    ],
    "qs_pg:aaroncc":"US",
    "qs_pg:gn_country":"US",
    "qs_pg:gn_fcode":"PPL",
    "qs_pg:gn_pop":22560,
    "qs_pg:name":"Wasco",
    "qs_pg:name_adm0":"United States",
    "qs_pg:name_adm1":"Illinois",
    "qs_pg:photos":276,
    "qs_pg:photos_1k":56,
    "qs_pg:photos_9k":1,
    "qs_pg:photos_9r":4,
    "qs_pg:photos_all":276,
    "qs_pg:photos_sr":5,
    "qs_pg:pop_sr":7,
    "qs_pg:qs_pg_placetype":"locality",
    "qs_pg:qs_pg_placetype_gp":"Town",
    "qs_pg:woe_adm0":23424977,
    "woe:adm0_id":23424977,
    "woe:name_adm0":"United States",
    "woe:name_adm1":"Illinois",
    "woe:placetype":"Town",
    "wof:name":"Wasco",
    "wof:placetype":"locality",
    "wof:population":22560
},
  "geometry": {"coordinates":[-88.40452000000001,41.93808],"type":"Point"}
}