{
  "type": "Feature",
  "properties": {
    "gn:country":"US",
    "gn:fcode":"PPL",
    "gn:population":0,
    "iso:country":"US",
    "name:eng_x_preferred":[
        "Oldrag"
    ],
    "name:fra_x_preferred":[
        "Oldrag"
    ],
    "qs_pg:aaroncc":"US",
    "qs_pg:gn_country":"US",
    "qs_pg:gn_fcode":"PPL",
    "qs_pg:gn_pop":0,
    "qs_pg:name":"Oldrag",
    "qs_pg:name_adm0":"United States",
    "qs_pg:name_adm1":"Virginia",
    "qs_pg:photos":3451,
    "qs_pg:photos_1k":699,
    "qs_pg:photos_9k":15,
    "qs_pg:photos_9r":11,
    "qs_pg:photos_all":3451,
    "qs_pg:photos_sr":20,
    "qs_pg:pop_sr":0,
    "qs_pg:qs_pg_placetype":"locality",
    "qs_pg:qs_pg_placetype_gp":"Town",
    "qs_pg:woe_adm0":23424977,
    "woe:adm0_id":23424977,
    "woe:name_adm0":"United States",
    "woe:name_adm1":"Virginia",
    "woe:placetype":"Town",
    "wof:name":"Oldrag",
    "wof:placetype":"locality"
},
  "geometry": {"coordinates":[-78.33306,38.55707],"type":"Point"}
}