{
  "type": "Feature",
  "properties": {
    "gn:admin1_code":"CA",
    "gn:admin2_code":"97",
    "gn:asciiname":"Mills",
    "gn:country_code":"US",
    "gn:dem":60,
    "gn:elevation":"58.0",
    "gn:feature_class":"P",
    "gn:feature_code":"PPL",
    "gn:name":"Mills",
    "gn:population":0,
    "gn:timezone":"America/Los_Angeles",
    "iso:country":"US",
    "name:bel_x_preferred":[
        "\u041c\u0456\u043b\u0441"
    ],
    "name:cat_x_preferred":[
        "Mills"
    ],
    "name:ceb_x_preferred":[
        "Mills"
    ],
    "name:ces_x_preferred":[
        "Mills"
    ],
    "name:deu_x_preferred":[
        "Mills"
    ],
    "name:fin_x_preferred":[
        "Mills"
    ],
    "name:fra_x_preferred":[
        "Mills"
    ],
    "name:heb_x_preferred":[
        "\u05de\u05d9\u05dc\u05e1"
    ],
    "name:ita_x_preferred":[
        "Mills"
    ],
    "name:jpn_x_preferred":[
        "\u30df\u30eb\u30ba"
    ],
    "name:lav_x_preferred":[
        "Mills"
    ],
    "name:nld_x_preferred":[
        "Mills"
    ],
    "name:pol_x_preferred":[
        "Mills"
    ],
    "name:rus_x_preferred":[
        "\u041c\u0438\u043b\u043b\u0441"
    ],
    "name:swe_x_preferred":[
        "Mills"
    ],
    "name:ukr_x_preferred":[
        "\u041c\u0456\u043b\u043b\u0441"
    ],
    "wof:name":"Mills",
    "wof:placetype":"locality"
},
  "geometry": {"coordinates":[-122.84332999999999,38.41325],"type":"Point"}
}