{
  "type": "Feature",
  "properties": {
    "gn:gn_country":"US",
    "gn:gn_fcode":"PPL",
    "gn:gn_pop":0,
    "iso:country":"US",
    "name:eng_x_preferred":[
        "Agness"
    ],
    "name:fas_x_preferred":[
        "\u0627\u06cc\u062c\u0646\u0633\u060c \u0627\u0648\u0631\u06af\u0648\u0646"
    ],
    "name:fra_x_preferred":[
        "Agness"
    ],
    "name:hat_x_preferred":[
        "Agness"
    ],
    "name:urd_x_preferred":[
        "\u0627\u06cc\u062c\u0646\u0633\u060c \u0627\u0648\u0631\u06cc\u06af\u0648\u0646"
    ],
    "name:vol_x_preferred":[
        "Agness"
    ],
    "qs_pg:aaroncc":"US",
    "qs_pg:gn_country":"US",
    "qs_pg:gn_fcode":"PPL",
    "qs_pg:gn_pop":0,
    "qs_pg:name":"Agness",
    "qs_pg:name_adm0":"United States",
    "qs_pg:name_adm1":"Oregon",
    "qs_pg:photos":92,
    "qs_pg:photos_1k":19,
    "qs_pg:photos_9k":1,
    "qs_pg:photos_9r":3,
    "qs_pg:photos_all":92,
    "qs_pg:photos_sr":3,
    "qs_pg:pop_sr":5,
    "qs_pg:qs_pg_placetype":"locality",
    "qs_pg:qs_pg_placetype_gp":"Town",
    "qs_pg:woe_adm0":23424977,
    "woe:adm0_id":23424977,
    "woe:name_adm0":"United States",
    "woe:name_adm1":"Oregon",
    "woe:placetype":"Town",
    "wof:name":"Agness",
    "wof:placetype":"locality"
},
  "geometry": {"coordinates":[-124.06898,42.5565],"type":"Point"}
}