{
  "type": "Feature",
  "properties": {
    "iso:country":"US",
    "name:eng_x_preferred":[
        "Diamond Creek"
    ],
    "wof:name":"Diamond Creek",
    "wof:placetype":"neighbourhood",
    "wof:population":174,
    "zs:area_m":42758.832398,
    "zs:blockids":[
        60610231001007,
        60610231001005
    ],
    "zs:housing10":47,
    "zs:label":"Diamond Creek",
    "zs:pop10":174
},
  "geometry": {"coordinates":[-121.33756,38.807538],"type":"Point"}
}