{
  "type": "Feature",
  "properties": {
    "gn:admin1_code":"TX",
    "gn:admin2_code":"411.0",
    "gn:asciiname":"Bend",
    "gn:country_code":"US",
    "gn:dem":343,
    "gn:elevation":"339.0",
    "gn:feature_class":"P",
    "gn:feature_code":"PPL",
    "gn:name":"Bend",
    "gn:population":0,
    "gn:timezone":"America/Chicago",
    "iso:country":"US",
    "name:ceb_x_preferred":[
        "Bend"
    ],
    "name:ces_x_preferred":[
        "Bend"
    ],
    "name:deu_x_preferred":[
        "Bend"
    ],
    "name:eng_x_preferred":[
        "Bend"
    ],
    "name:hun_x_preferred":[
        "Bend"
    ],
    "name:jpn_x_preferred":[
        "\u30d9\u30f3\u30c9"
    ],
    "name:nld_x_preferred":[
        "Bend"
    ],
    "name:pol_x_preferred":[
        "Bend"
    ],
    "name:por_x_preferred":[
        "Bend"
    ],
    "name:spa_x_preferred":[
        "Bend"
    ],
    "name:srp_x_preferred":[
        "\u0411\u0435\u043d\u0434"
    ],
    "name:swe_x_preferred":[
        "Bend"
    ],
    "name:ukr_x_preferred":[
        "\u0411\u0435\u043d\u0434"
    ],
    "name:und_x_variant":[
        "Eagle",
        "Schleicher's Bend",
        "McAnelly's Bend"
    ],
    "name:vol_x_preferred":[
        "Bend"
    ],
    "wof:name":"Bend",
    "wof:placetype":"locality"
},
  "geometry": {"coordinates":[-98.51281,31.09934],"type":"Point"}
}