{
  "type": "Feature",
  "properties": {
    "gn:admin1_code":"GA",
    "gn:admin2_code":"57.0",
    "gn:asciiname":"Burris Crossroads",
    "gn:country_code":"US",
    "gn:dem":408,
    "gn:elevation":"408.0",
    "gn:feature_class":"P",
    "gn:feature_code":"PPL",
    "gn:name":"Burris Crossroads",
    "gn:population":0,
    "gn:timezone":"America/New_York",
    "iso:country":"US",
    "wof:name":"Burris Crossroads",
    "wof:placetype":"locality"
},
  "geometry": {"coordinates":[-84.48743,34.33009000000001],"type":"Point"}
}