{
  "type": "Feature",
  "properties": {
    "gn:elevation":27,
    "iso:country":"US",
    "name:cat_x_preferred":[
        "pelatge negre"
    ],
    "name:deu_x_preferred":[
        "Rappe"
    ],
    "name:eng_x_preferred":[
        "Black Horse"
    ],
    "name:eng_x_variant":[
        "Black"
    ],
    "name:fin_x_preferred":[
        "Musta"
    ],
    "name:fra_x_preferred":[
        "noir"
    ],
    "name:ita_x_preferred":[
        "Morello"
    ],
    "name:jpn_x_preferred":[
        "\u9752\u6bdb"
    ],
    "name:kor_x_preferred":[
        "\ud751\ub9c8"
    ],
    "name:swe_x_preferred":[
        "Rapp"
    ],
    "name:tat_x_preferred":[
        "\u041a\u0430\u0440\u0430"
    ],
    "name:ukr_x_preferred":[
        "\u0412\u043e\u0440\u043e\u043d\u0430 \u043c\u0430\u0441\u0442\u044c"
    ],
    "name:vie_x_preferred":[
        "Ng\u1ef1a \u0111en"
    ],
    "name:zho_x_preferred":[
        "\u9ed1\u8272"
    ],
    "qs:gn_adm0_cc":"US",
    "qs:gn_fcode":"PPL",
    "qs:gn_local":6946944,
    "qs:gn_nam_loc":"North Brunswick, Middlesex, New Jersey, US",
    "qs:gn_namadm1":"NJ",
    "qs:gn_name":"Black Horse",
    "qs:local_max":198,
    "qs:local_sum":262,
    "qs:localhoods":3,
    "qs:name":"Black Horse",
    "qs:name_adm0":"United States",
    "qs:name_adm1":"New Jersey",
    "qs:name_adm2":"Middlesex",
    "qs:name_local":"North Brunswick",
    "qs:photo_max":14,
    "qs:photo_sum":42,
    "qs:placetype":"Suburb",
    "qs:quad_count":11,
    "qs:woe_adm0":23424977,
    "qs:woe_adm1":2347589,
    "qs:woe_adm2":12589269,
    "qs:woe_lau":0,
    "qs:woe_local":23417714,
    "qs:woe_ver":"7.10.0",
    "wd:wordcount":1343,
    "wof:lang":[
        "eng"
    ],
    "wof:name":"Black Horse",
    "wof:placetype":"neighbourhood"
},
  "geometry": {"coordinates":[-74.515686,40.430322],"type":"Point"}
}