{
  "type": "Feature",
  "properties": {
    "gn:admin1_code":"MT",
    "gn:admin2_code":"109.0",
    "gn:asciiname":"Saint Phillip",
    "gn:country_code":"US",
    "gn:dem":866,
    "gn:elevation":"871.0",
    "gn:feature_class":"P",
    "gn:feature_code":"PPL",
    "gn:name":"Saint Phillip",
    "gn:population":0,
    "gn:timezone":"America/Denver",
    "iso:country":"US",
    "name:eng_x_preferred":[
        "Saint Phillip"
    ],
    "name:und_x_variant":[
        "Saint Philip",
        "Saint Philips",
        "Saint Phillips"
    ],
    "wof:name":"Saint Phillip",
    "wof:placetype":"locality"
},
  "geometry": {"coordinates":[-104.14549,46.83168],"type":"Point"}
}