{
  "type": "Feature",
  "properties": {
    "gn:admin1_code":"CA",
    "gn:admin2_code":"113.0",
    "gn:asciiname":"Willow Point",
    "gn:country_code":"US",
    "gn:dem":1,
    "gn:elevation":"0.0",
    "gn:feature_class":"P",
    "gn:feature_code":"PPL",
    "gn:name":"Willow Point",
    "gn:population":0,
    "gn:timezone":"America/Los_Angeles",
    "iso:country":"US",
    "name:zho_x_preferred":[
        "\u5a01\u6d1b\u9ede"
    ],
    "wof:name":"Willow Point",
    "wof:placetype":"locality"
},
  "geometry": {"coordinates":[-121.55246,38.42546],"type":"Point"}
}