{
  "type": "Feature",
  "properties": {
    "gn:admin1_code":"AR",
    "gn:admin2_code":"99.0",
    "gn:admin3_code":"91449.0",
    "gn:asciiname":"Morris",
    "gn:country_code":"US",
    "gn:dem":87,
    "gn:elevation":"80.0",
    "gn:feature_class":"P",
    "gn:feature_code":"PPL",
    "gn:name":"Morris",
    "gn:population":0,
    "gn:timezone":"America/Chicago",
    "iso:country":"US",
    "name:bel_x_preferred":[
        "\u041c\u043e\u0440\u044b\u0441"
    ],
    "name:cat_x_preferred":[
        "Morris"
    ],
    "name:ceb_x_preferred":[
        "Morris"
    ],
    "name:ces_x_preferred":[
        "Morris"
    ],
    "name:dan_x_preferred":[
        "Morris"
    ],
    "name:deu_x_preferred":[
        "Morris"
    ],
    "name:est_x_preferred":[
        "Morris"
    ],
    "name:fas_x_preferred":[
        "\u0645\u0648\u0631\u06cc\u0633"
    ],
    "name:fin_x_preferred":[
        "Morris"
    ],
    "name:fra_x_preferred":[
        "Morris"
    ],
    "name:glg_x_preferred":[
        "Morris"
    ],
    "name:heb_x_preferred":[
        "\u05de\u05d5\u05e8\u05d9\u05e1"
    ],
    "name:hun_x_preferred":[
        "Morris"
    ],
    "name:ita_x_preferred":[
        "Morris"
    ],
    "name:jpn_x_preferred":[
        "\u30e2\u30fc\u30ea\u30b9"
    ],
    "name:kor_x_preferred":[
        "\ubaa8\ub9ac\uc2a4"
    ],
    "name:lav_x_preferred":[
        "Morris"
    ],
    "name:nld_x_preferred":[
        "Morris"
    ],
    "name:pol_x_preferred":[
        "Morris"
    ],
    "name:por_x_preferred":[
        "Morris"
    ],
    "name:ron_x_preferred":[
        "Morris"
    ],
    "name:rus_x_preferred":[
        "\u041c\u043e\u0440\u0440\u0438\u0441"
    ],
    "name:spa_x_preferred":[
        "Morris"
    ],
    "name:swe_x_preferred":[
        "Morris"
    ],
    "name:tur_x_preferred":[
        "Morris"
    ],
    "name:ukr_x_preferred":[
        "\u041c\u043e\u0440\u0440\u0456\u0441"
    ],
    "name:vep_x_preferred":[
        "Morris"
    ],
    "name:vie_x_preferred":[
        "Morris"
    ],
    "name:vol_x_preferred":[
        "Morris"
    ],
    "name:zho_x_preferred":[
        "\u83ab\u91cc\u65af"
    ],
    "wof:name":"Morris",
    "wof:placetype":"locality"
},
  "geometry": {"coordinates":[-93.24656,33.67011],"type":"Point"}
}