{
  "type": "Feature",
  "properties": {
    "gn:country":"US",
    "gn:fcode":"PPL",
    "gn:population":0,
    "iso:country":"US",
    "name:azb_x_preferred":[
        "\u0631\u062f\u0648\u06cc\u0646\u0642"
    ],
    "name:cym_x_preferred":[
        "Redwing"
    ],
    "name:eng_x_preferred":[
        "Redwing"
    ],
    "name:fas_x_preferred":[
        "\u0631\u062f\u0648\u06cc\u0646\u06af"
    ],
    "name:fra_x_preferred":[
        "Redwing"
    ],
    "name:und_x_variant":[
        "Red Wing"
    ],
    "name:zho_x_preferred":[
        "\u96f7\u5fb7\u6eab"
    ],
    "qs_pg:aaroncc":"US",
    "qs_pg:gn_country":"US",
    "qs_pg:gn_fcode":"PPL",
    "qs_pg:gn_pop":0,
    "qs_pg:name":"Redwing",
    "qs_pg:name_adm0":"United States",
    "qs_pg:name_adm1":"Kansas",
    "qs_pg:photos":80,
    "qs_pg:photos_1k":16,
    "qs_pg:photos_9k":1,
    "qs_pg:photos_9r":3,
    "qs_pg:photos_all":80,
    "qs_pg:photos_sr":3,
    "qs_pg:pop_sr":0,
    "qs_pg:qs_pg_placetype":"locality",
    "qs_pg:qs_pg_placetype_gp":"Town",
    "qs_pg:woe_adm0":23424977,
    "woe:adm0_id":23424977,
    "woe:name_adm0":"United States",
    "woe:name_adm1":"Kansas",
    "woe:placetype":"Town",
    "wof:name":"Redwing",
    "wof:placetype":"locality"
},
  "geometry": {"coordinates":[-98.66452,38.52196],"type":"Point"}
}