{
  "type": "Feature",
  "properties": {
    "gn:admin1_code":"SC",
    "gn:admin2_code":"45.0",
    "gn:asciiname":"Points North",
    "gn:country_code":"US",
    "gn:dem":331,
    "gn:elevation":"327.0",
    "gn:feature_class":"P",
    "gn:feature_code":"PPL",
    "gn:name":"Points North",
    "gn:population":0,
    "gn:timezone":"America/New_York",
    "iso:country":"US",
    "wof:name":"Points North",
    "wof:placetype":"locality"
},
  "geometry": {"coordinates":[-82.41929,34.96484],"type":"Point"}
}