{
  "type": "Feature",
  "properties": {
    "gn:admin1_code":"IL",
    "gn:admin2_code":"119",
    "gn:admin3_code":"22710.0",
    "gn:asciiname":"Glen Carbon Crossing",
    "gn:country_code":"US",
    "gn:dem":172,
    "gn:elevation":"167.0",
    "gn:feature_class":"P",
    "gn:feature_code":"PPL",
    "gn:name":"Glen Carbon Crossing",
    "gn:population":0,
    "gn:timezone":"America/Chicago",
    "iso:country":"US",
    "wof:name":"Glen Carbon Crossing",
    "wof:placetype":"locality"
},
  "geometry": {"coordinates":[-89.95538000000001,38.75227],"type":"Point"}
}