{
  "type": "Feature",
  "properties": {
    "iso:country":"US",
    "name:cat_x_preferred":[
        "Ira"
    ],
    "name:ceb_x_preferred":[
        "Ira"
    ],
    "name:dan_x_preferred":[
        "IRA"
    ],
    "name:deu_x_preferred":[
        "Ira"
    ],
    "name:eng_x_preferred":[
        "Ira"
    ],
    "name:fas_x_preferred":[
        "\u0627\u06cc\u0631\u0627"
    ],
    "name:fra_x_preferred":[
        "Ira"
    ],
    "name:fry_x_preferred":[
        "Ira"
    ],
    "name:hun_x_preferred":[
        "IRA"
    ],
    "name:pol_x_preferred":[
        "Ira"
    ],
    "name:por_x_preferred":[
        "Ira"
    ],
    "name:rus_x_preferred":[
        "\u0418\u0440\u0430"
    ],
    "name:slv_x_preferred":[
        "Ira"
    ],
    "name:spa_x_preferred":[
        "Ira"
    ],
    "name:swe_x_preferred":[
        "Ira"
    ],
    "name:und_x_variant":[
        "Hawkins Station"
    ],
    "name:vol_x_preferred":[
        "Ira"
    ],
    "qs:gn_adm0_cc":"US",
    "qs:gn_fcode":"PPL",
    "qs:gn_local":5145476,
    "qs:gn_nam_loc":"Akron, Summit, Ohio, US",
    "qs:gn_namadm1":"OH",
    "qs:gn_name":"Ira",
    "qs:local_max":4046,
    "qs:local_sum":16451,
    "qs:localhoods":27,
    "qs:name":"Ira",
    "qs:name_adm0":"United States",
    "qs:name_adm1":"Ohio",
    "qs:name_adm2":"Summit",
    "qs:name_local":"Akron",
    "qs:photo_max":538,
    "qs:photo_sum":1827,
    "qs:placetype":"Suburb",
    "qs:quad_count":72,
    "qs:woe_adm0":23424977,
    "qs:woe_adm1":2347594,
    "qs:woe_adm2":12589603,
    "qs:woe_lau":0,
    "qs:woe_local":2352491,
    "qs:woe_ver":"7.10.0",
    "wd:wordcount":341,
    "wof:lang":[
        "eng"
    ],
    "wof:name":"Ira",
    "wof:placetype":"neighbourhood"
},
  "geometry": {"coordinates":[-81.578451,41.188224],"type":"Point"}
}