{
  "type": "Feature",
  "properties": {
    "gn:admin1_code":"MS",
    "gn:admin2_code":"47.0",
    "gn:asciiname":"Grasslawn Mobile Home Park",
    "gn:country_code":"US",
    "gn:dem":13,
    "gn:elevation":"7.0",
    "gn:feature_class":"P",
    "gn:feature_code":"PPL",
    "gn:name":"Grasslawn Mobile Home Park",
    "gn:population":0,
    "gn:timezone":"America/Chicago",
    "iso:country":"US",
    "wof:name":"Grasslawn Mobile Home Park",
    "wof:placetype":"campus"
},
  "geometry": {"coordinates":[-89.06534000000001,30.38379],"type":"Point"}
}