{
  "type": "Feature",
  "properties": {
    "gn:admin1_code":"PA",
    "gn:admin2_code":"129.0",
    "gn:admin3_code":"15912.0",
    "gn:asciiname":"Pleasant Grove",
    "gn:country_code":"US",
    "gn:dem":481,
    "gn:elevation":"479.0",
    "gn:feature_class":"P",
    "gn:feature_code":"PPL",
    "gn:name":"Pleasant Grove",
    "gn:population":0,
    "gn:timezone":"America/New_York",
    "iso:country":"US",
    "name:cat_x_preferred":[
        "Pleasant Grove"
    ],
    "name:ceb_x_preferred":[
        "Pleasant Grove"
    ],
    "name:ces_x_preferred":[
        "Pleasant Grove"
    ],
    "name:deu_x_preferred":[
        "Pleasant Grove"
    ],
    "name:fra_x_preferred":[
        "Pleasant Grove"
    ],
    "name:ita_x_preferred":[
        "Pleasant Grove"
    ],
    "name:nld_x_preferred":[
        "Pleasant Grove"
    ],
    "name:pol_x_preferred":[
        "Pleasant Grove"
    ],
    "name:por_x_preferred":[
        "Pleasant Grove"
    ],
    "name:srp_x_preferred":[
        "\u041f\u043b\u0435\u0437\u0430\u043d\u0442 \u0413\u0440\u043e\u0443\u0432"
    ],
    "name:vol_x_preferred":[
        "Pleasant Grove"
    ],
    "wof:name":"Pleasant Grove",
    "wof:placetype":"locality"
},
  "geometry": {"coordinates":[-79.28586999999997,40.18507],"type":"Point"}
}