{
  "type": "Feature",
  "properties": {
    "gn:admin1_code":"IN",
    "gn:admin2_code":"73.0",
    "gn:admin3_code":"46944.0",
    "gn:asciiname":"North Marion",
    "gn:country_code":"US",
    "gn:dem":213,
    "gn:elevation":"210.0",
    "gn:feature_class":"P",
    "gn:feature_code":"PPL",
    "gn:name":"North Marion",
    "gn:population":0,
    "gn:timezone":"America/Chicago",
    "iso:country":"US",
    "wof:name":"North Marion",
    "wof:placetype":"locality"
},
  "geometry": {"coordinates":[-87.15002,40.97087],"type":"Point"}
}