{
  "type": "Feature",
  "properties": {
    "gn:admin1_code":"KY",
    "gn:admin2_code":"169",
    "gn:asciiname":"Node",
    "gn:country_code":"US",
    "gn:dem":232,
    "gn:elevation":"229.0",
    "gn:feature_class":"P",
    "gn:feature_code":"PPL",
    "gn:name":"Node",
    "gn:population":0,
    "gn:timezone":"America/Chicago",
    "iso:country":"US",
    "wof:name":"Node",
    "wof:placetype":"locality"
},
  "geometry": {"coordinates":[-85.64386,37.12922],"type":"Point"}
}