{
  "type": "Feature",
  "properties": {
    "gn:admin1_code":"OH",
    "gn:admin2_code":"49",
    "gn:admin3_code":"46410.0",
    "gn:asciiname":"Edgewater Park",
    "gn:country_code":"US",
    "gn:dem":227,
    "gn:elevation":"227.0",
    "gn:feature_class":"P",
    "gn:feature_code":"PPL",
    "gn:name":"Edgewater Park",
    "gn:population":0,
    "gn:timezone":"America/New_York",
    "iso:country":"US",
    "name:ceb_x_preferred":[
        "Edgewater Park"
    ],
    "name:deu_x_preferred":[
        "Edgewater Park"
    ],
    "name:swe_x_preferred":[
        "Edgewater Park"
    ],
    "wof:name":"Edgewater Park",
    "wof:placetype":"locality"
},
  "geometry": {"coordinates":[-82.88268000000002,39.90812],"type":"Point"}
}