{
  "type": "Feature",
  "properties": {
    "gn:gn_country":"US",
    "gn:gn_fcode":"PPL",
    "gn:gn_pop":0,
    "iso:country":"US",
    "name:cat_x_preferred":[
        "Pine Ridge"
    ],
    "name:ceb_x_preferred":[
        "Pine Ridge"
    ],
    "name:deu_x_preferred":[
        "Pine Ridge"
    ],
    "name:fin_x_preferred":[
        "Pine Ridge"
    ],
    "name:fra_x_preferred":[
        "Pine Ridge"
    ],
    "name:ind_x_preferred":[
        "Pine Ridge"
    ],
    "name:ita_x_preferred":[
        "Pine Ridge"
    ],
    "name:nld_x_preferred":[
        "Pine Ridge"
    ],
    "name:pol_x_preferred":[
        "Pine Ridge"
    ],
    "name:por_x_preferred":[
        "Pine Ridge"
    ],
    "name:rus_x_preferred":[
        "\u041f\u0430\u0439\u043d-\u0420\u0438\u0434\u0436"
    ],
    "name:srp_x_preferred":[
        "\u041f\u0430\u0458\u043d \u0420\u0438\u045f"
    ],
    "name:swe_x_preferred":[
        "Pine Ridge"
    ],
    "name:tur_x_preferred":[
        "Pine Ridge"
    ],
    "name:vol_x_preferred":[
        "Pine Ridge"
    ],
    "qs_pg:aaroncc":"US",
    "qs_pg:gn_country":"US",
    "qs_pg:gn_fcode":"PPL",
    "qs_pg:gn_pop":0,
    "qs_pg:name":"Pine Ridge",
    "qs_pg:name_adm0":"United States",
    "qs_pg:name_adm1":"Mississippi",
    "qs_pg:photos":11,
    "qs_pg:photos_1k":2,
    "qs_pg:photos_9k":1,
    "qs_pg:photos_9r":1,
    "qs_pg:photos_all":11,
    "qs_pg:photos_sr":1,
    "qs_pg:pop_sr":0,
    "qs_pg:qs_pg_placetype":"locality",
    "qs_pg:qs_pg_placetype_gp":"Town",
    "qs_pg:woe_adm0":23424977,
    "woe:adm0_id":23424977,
    "woe:name_adm0":"United States",
    "woe:name_adm1":"Mississippi",
    "woe:placetype":"Town",
    "wof:name":"Pine Ridge",
    "wof:placetype":"locality"
},
  "geometry": {"coordinates":[-89.44534,31.20323],"type":"Point"}
}