{
  "type": "Feature",
  "properties": {
    "gn:admin1_code":"AL",
    "gn:admin2_code":"101",
    "gn:asciiname":"Gibson",
    "gn:country_code":"US",
    "gn:dem":116,
    "gn:elevation":"102.0",
    "gn:feature_class":"P",
    "gn:feature_code":"PPL",
    "gn:name":"Gibson",
    "gn:population":0,
    "gn:timezone":"America/Chicago",
    "iso:country":"US",
    "name:ara_x_preferred":[
        "\u063a\u064a\u0628\u0633\u0648\u0646"
    ],
    "name:aze_x_preferred":[
        "Gibson"
    ],
    "name:bul_x_preferred":[
        "\u0413\u0438\u0431\u0441\u044a\u043d \u041a\u043e\u0440\u043f\u043e\u0440\u0435\u0439\u0448\u044a\u043d"
    ],
    "name:dan_x_preferred":[
        "Gibson"
    ],
    "name:glg_x_preferred":[
        "Gibson"
    ],
    "name:heb_x_preferred":[
        "\u05d2\u05d9\u05d1\u05e1\u05d5\u05df"
    ],
    "name:jpn_x_preferred":[
        "\u30ae\u30d6\u30bd\u30f3"
    ],
    "name:kat_x_preferred":[
        "Gibson"
    ],
    "name:kor_x_preferred":[
        "\uae41\uc2a8"
    ],
    "name:nor_x_preferred":[
        "Gibson Brands"
    ],
    "name:por_x_preferred":[
        "Gibson"
    ],
    "name:rus_x_preferred":[
        "Gibson"
    ],
    "name:swe_x_preferred":[
        "Gibson Brands"
    ],
    "name:tha_x_preferred":[
        "\u0e01\u0e34\u0e1a\u0e0b\u0e31\u0e19"
    ],
    "name:tur_x_preferred":[
        "Gibson"
    ],
    "name:ukr_x_preferred":[
        "Gibson"
    ],
    "name:zho_x_preferred":[
        "\u5409\u666e\u68ee\u54c1\u724c"
    ],
    "wof:name":"Gibson",
    "wof:placetype":"locality"
},
  "geometry": {"coordinates":[-86.15607,32.09348],"type":"Point"}
}