{
  "type": "Feature",
  "properties": {
    "gn:admin1_code":"PA",
    "gn:admin2_code":"133.0",
    "gn:admin3_code":"19704.0",
    "gn:asciiname":"Davidsburg",
    "gn:country_code":"US",
    "gn:dem":137,
    "gn:elevation":"141.0",
    "gn:feature_class":"P",
    "gn:feature_code":"PPL",
    "gn:name":"Davidsburg",
    "gn:population":0,
    "gn:timezone":"America/New_York",
    "iso:country":"US",
    "wof:name":"Davidsburg",
    "wof:placetype":"locality"
},
  "geometry": {"coordinates":[-76.89442,39.98371],"type":"Point"}
}