{
  "type": "Feature",
  "properties": {
    "gn:admin1_code":"MD",
    "gn:admin2_code":"45.0",
    "gn:asciiname":"Twin River Trailer Park",
    "gn:country_code":"US",
    "gn:dem":3,
    "gn:elevation":"2.0",
    "gn:feature_class":"P",
    "gn:feature_code":"PPL",
    "gn:name":"Twin River Trailer Park",
    "gn:population":0,
    "gn:timezone":"America/New_York",
    "iso:country":"US",
    "wof:name":"Twin River Trailer Park",
    "wof:placetype":"campus"
},
  "geometry": {"coordinates":[-75.87604,38.29068],"type":"Point"}
}