{
  "type": "Feature",
  "properties": {
    "gn:admin1_code":"NY",
    "gn:admin2_code":"67.0",
    "gn:admin3_code":"59036.0",
    "gn:asciiname":"Swift Corner",
    "gn:country_code":"US",
    "gn:dem":499,
    "gn:elevation":"499.0",
    "gn:feature_class":"P",
    "gn:feature_code":"PPL",
    "gn:name":"Swift Corner",
    "gn:population":0,
    "gn:timezone":"America/New_York",
    "iso:country":"US",
    "wof:name":"Swift Corner",
    "wof:placetype":"locality"
},
  "geometry": {"coordinates":[-76.02853,42.86646],"type":"Point"}
}