{
  "type": "Feature",
  "properties": {
    "gn:country":"US",
    "gn:fcode":"PPL",
    "gn:population":0,
    "iso:country":"US",
    "name:ceb_x_preferred":[
        "Hilltop"
    ],
    "name:deu_x_preferred":[
        "Hilltop"
    ],
    "name:eng_x_preferred":[
        "Hilltop"
    ],
    "name:ita_x_preferred":[
        "Hilltop"
    ],
    "name:nld_x_preferred":[
        "Hilltop"
    ],
    "name:pol_x_preferred":[
        "Hilltop"
    ],
    "name:por_x_preferred":[
        "Hilltop"
    ],
    "name:spa_x_preferred":[
        "Hilltop"
    ],
    "name:srp_x_preferred":[
        "\u0425\u0438\u043b\u0442\u043e\u043f"
    ],
    "name:ukr_x_preferred":[
        "\u0413\u0456\u043b\u043b\u0442\u043e\u043f"
    ],
    "name:vol_x_preferred":[
        "Hilltop"
    ],
    "qs_pg:aaroncc":"US",
    "qs_pg:gn_country":"US",
    "qs_pg:gn_fcode":"PPL",
    "qs_pg:gn_pop":0,
    "qs_pg:name":"Hilltop",
    "qs_pg:name_adm0":"United States",
    "qs_pg:name_adm1":"Pennsylvania",
    "qs_pg:photos":5,
    "qs_pg:photos_1k":1,
    "qs_pg:photos_9k":1,
    "qs_pg:photos_9r":1,
    "qs_pg:photos_all":5,
    "qs_pg:photos_sr":1,
    "qs_pg:pop_sr":0,
    "qs_pg:qs_pg_placetype":"neighbourhood",
    "qs_pg:qs_pg_placetype_gp":"Suburb",
    "qs_pg:woe_adm0":23424977,
    "woe:adm0_id":23424977,
    "woe:name_adm0":"United States",
    "woe:name_adm1":"Pennsylvania",
    "woe:placetype":"Suburb",
    "wof:name":"Hilltop",
    "wof:placetype":"neighbourhood",
    "wof:population":280
},
  "geometry": {"coordinates":[-75.37879,40.4926],"type":"Point"}
}