{
  "type": "Feature",
  "properties": {
    "iso:country":"US",
    "name:eng_x_preferred":[
        "East Highland"
    ],
    "wof:name":"East Highland",
    "wof:placetype":"neighbourhood",
    "wof:population":517,
    "zs:area_m":295111.746909,
    "zs:blockids":[
        132150018001010,
        132150018001017,
        132150018001034,
        132150018001039,
        132150112001031,
        132150112001030,
        132150018001040,
        132150018001038,
        132150018001022,
        132150018001035,
        132150018001037,
        132150018001042,
        132150018001023,
        132150018001036
    ],
    "zs:housing10":246,
    "zs:label":"East Highland",
    "zs:pop10":517
},
  "geometry": {"coordinates":[-84.977146,32.477505],"type":"Point"}
}