{
  "type": "Feature",
  "properties": {
    "gn:admin1_code":"IL",
    "gn:admin2_code":"99.0",
    "gn:admin3_code":"22424.0",
    "gn:asciiname":"Ticona",
    "gn:country_code":"US",
    "gn:dem":197,
    "gn:elevation":"197.0",
    "gn:feature_class":"P",
    "gn:feature_code":"PPL",
    "gn:name":"Ticona",
    "gn:population":0,
    "gn:timezone":"America/Chicago",
    "iso:country":"US",
    "name:deu_x_preferred":[
        "Ticona"
    ],
    "wof:name":"Ticona",
    "wof:placetype":"locality"
},
  "geometry": {"coordinates":[-89.05258000000001,41.2242],"type":"Point"}
}