{
  "type": "Feature",
  "properties": {
    "gn:country":"US",
    "gn:fcode":"PPL",
    "gn:population":0,
    "iso:country":"US",
    "name:cat_x_preferred":[
        "Holbrook"
    ],
    "name:ceb_x_preferred":[
        "Holbrook"
    ],
    "name:ces_x_preferred":[
        "Holbrook"
    ],
    "name:deu_x_preferred":[
        "Holbrook"
    ],
    "name:eng_x_preferred":[
        "Holbrook"
    ],
    "name:est_x_preferred":[
        "Holbrook"
    ],
    "name:fas_x_preferred":[
        "\u0647\u0627\u0644\u0628\u0631\u0648\u06a9"
    ],
    "name:fra_x_preferred":[
        "Holbrook"
    ],
    "name:heb_x_preferred":[
        "\u05d4\u05d5\u05dc\u05d1\u05e8\u05d5\u05e7"
    ],
    "name:hun_x_preferred":[
        "Holbrook"
    ],
    "name:ita_x_preferred":[
        "Holbrook"
    ],
    "name:jpn_x_preferred":[
        "\u30db\u30eb\u30d6\u30eb\u30c3\u30af"
    ],
    "name:nld_x_preferred":[
        "Holbrook"
    ],
    "name:pol_x_preferred":[
        "Holbrook"
    ],
    "name:rus_x_preferred":[
        "Holbrook"
    ],
    "name:spa_x_preferred":[
        "Holbrook"
    ],
    "name:swe_x_preferred":[
        "Holbrook"
    ],
    "name:ukr_x_preferred":[
        "\u0413\u043e\u043b\u0431\u0440\u0443\u043a"
    ],
    "name:und_x_variant":[
        "Wards Chapel"
    ],
    "name:vol_x_preferred":[
        "Holbrook"
    ],
    "qs_pg:aaroncc":"US",
    "qs_pg:gn_country":"US",
    "qs_pg:gn_fcode":"PPL",
    "qs_pg:gn_pop":0,
    "qs_pg:name":"Holbrook",
    "qs_pg:name_adm0":"United States",
    "qs_pg:name_adm1":"Maryland",
    "qs_pg:photos":352,
    "qs_pg:photos_1k":71,
    "qs_pg:photos_9k":2,
    "qs_pg:photos_9r":5,
    "qs_pg:photos_all":352,
    "qs_pg:photos_sr":6,
    "qs_pg:pop_sr":0,
    "qs_pg:qs_pg_placetype":"locality",
    "qs_pg:qs_pg_placetype_gp":"Town",
    "qs_pg:woe_adm0":23424977,
    "woe:adm0_id":23424977,
    "woe:name_adm0":"United States",
    "woe:name_adm1":"Maryland",
    "woe:placetype":"Town",
    "wof:name":"Holbrook",
    "wof:placetype":"locality"
},
  "geometry": {"coordinates":[-76.85275,39.39455],"type":"Point"}
}