{
  "type": "Feature",
  "properties": {
    "gn:admin1_code":"LA",
    "gn:admin2_code":"19.0",
    "gn:asciiname":"Oak Hurst Mobile Home Park",
    "gn:country_code":"US",
    "gn:dem":7,
    "gn:elevation":"5.0",
    "gn:feature_class":"P",
    "gn:feature_code":"PPL",
    "gn:name":"Oak Hurst Mobile Home Park",
    "gn:population":0,
    "gn:timezone":"America/Chicago",
    "iso:country":"US",
    "wof:name":"Oak Hurst Mobile Home Park",
    "wof:placetype":"campus"
},
  "geometry": {"coordinates":[-93.11112,30.22973],"type":"Point"}
}