{
  "type": "Feature",
  "properties": {
    "gn:admin1_code":"PA",
    "gn:admin2_code":"117.0",
    "gn:admin3_code":"18760.0",
    "gn:asciiname":"Stokesdale",
    "gn:country_code":"US",
    "gn:dem":364,
    "gn:elevation":"363.0",
    "gn:feature_class":"P",
    "gn:feature_code":"PPL",
    "gn:name":"Stokesdale",
    "gn:population":0,
    "gn:timezone":"America/New_York",
    "iso:country":"US",
    "wof:name":"Stokesdale",
    "wof:placetype":"locality"
},
  "geometry": {"coordinates":[-77.30941999999997,41.77757],"type":"Point"}
}