{
  "type": "Feature",
  "properties": {
    "gn:country":"US",
    "gn:fcode":"PPL",
    "gn:population":0,
    "iso:country":"US",
    "name:ceb_x_preferred":[
        "North Park"
    ],
    "name:swe_x_preferred":[
        "North Park"
    ],
    "qs_pg:aaroncc":"US",
    "qs_pg:gn_country":"US",
    "qs_pg:gn_fcode":"PPL",
    "qs_pg:gn_pop":0,
    "qs_pg:name":"North Park",
    "qs_pg:name_adm0":"United States",
    "qs_pg:name_adm1":"Pennsylvania",
    "qs_pg:photos_9r":0,
    "qs_pg:photos_sr":0,
    "qs_pg:pop_sr":0,
    "qs_pg:qs_pg_placetype":"neighbourhood",
    "qs_pg:qs_pg_placetype_gp":"Suburb",
    "qs_pg:woe_adm0":23424977,
    "woe:adm0_id":23424977,
    "woe:name_adm0":"United States",
    "woe:name_adm1":"Pennsylvania",
    "woe:placetype":"Suburb",
    "wof:name":"North Park",
    "wof:placetype":"neighbourhood"
},
  "geometry": {"coordinates":[-74.81627,40.16678],"type":"Point"}
}