{
  "type": "Feature",
  "properties": {
    "gn:admin1_code":"SC",
    "gn:admin2_code":"91.0",
    "gn:asciiname":"Sturgis Estates",
    "gn:country_code":"US",
    "gn:dem":173,
    "gn:elevation":"172.0",
    "gn:feature_class":"P",
    "gn:feature_code":"PPL",
    "gn:name":"Sturgis Estates",
    "gn:population":0,
    "gn:timezone":"America/New_York",
    "iso:country":"US",
    "wof:name":"Sturgis Estates",
    "wof:placetype":"locality"
},
  "geometry": {"coordinates":[-80.97758,34.93403],"type":"Point"}
}