{
  "type": "Feature",
  "properties": {
    "gn:admin1_code":"FL",
    "gn:admin2_code":"57",
    "gn:asciiname":"Everett",
    "gn:country_code":"US",
    "gn:dem":11,
    "gn:elevation":"3.0",
    "gn:feature_class":"P",
    "gn:feature_code":"PPL",
    "gn:name":"Everett",
    "gn:population":0,
    "gn:timezone":"America/New_York",
    "iso:country":"US",
    "name:bel_x_preferred":[
        "\u042d\u0432\u0435\u0440\u044d\u0442"
    ],
    "name:bul_x_preferred":[
        "\u0415\u0432\u044a\u0440\u0435\u0442"
    ],
    "name:ceb_x_preferred":[
        "Everett"
    ],
    "name:ces_x_preferred":[
        "Everett"
    ],
    "name:deu_x_preferred":[
        "Everett"
    ],
    "name:fas_x_preferred":[
        "\u0627\u0648\u0631\u062a"
    ],
    "name:fin_x_preferred":[
        "Everett"
    ],
    "name:fra_x_preferred":[
        "Everett"
    ],
    "name:heb_x_preferred":[
        "\u05d0\u05d5\u05d5\u05e8\u05d8"
    ],
    "name:ita_x_preferred":[
        "Everett"
    ],
    "name:jpn_x_preferred":[
        "\u30a8\u30f4\u30a1\u30ec\u30c3\u30c8"
    ],
    "name:kor_x_preferred":[
        "\uc5d0\ubc84\ub81b"
    ],
    "name:nld_x_preferred":[
        "Everett"
    ],
    "name:pol_x_preferred":[
        "Everett"
    ],
    "name:por_x_preferred":[
        "Everett"
    ],
    "name:rus_x_preferred":[
        "\u042d\u0432\u0435\u0440\u0435\u0442\u0442"
    ],
    "name:slv_x_preferred":[
        "Everett"
    ],
    "name:spa_x_preferred":[
        "Everett"
    ],
    "name:srp_x_preferred":[
        "\u0415\u0432\u0435\u0440\u0435\u0442"
    ],
    "name:swe_x_preferred":[
        "Everett"
    ],
    "name:ukr_x_preferred":[
        "\u0415\u0432\u0435\u0440\u0435\u0442\u0442"
    ],
    "name:vol_x_preferred":[
        "Everett"
    ],
    "wof:name":"Everett",
    "wof:placetype":"locality"
},
  "geometry": {"coordinates":[-82.39409999999999,27.9439],"type":"Point"}
}