{
  "type": "Feature",
  "properties": {
    "iso:country":"US",
    "name:eng_x_preferred":[
        "Raleigh Hills"
    ],
    "wof:name":"Raleigh Hills",
    "wof:placetype":"neighbourhood",
    "wof:population":340,
    "zs:area_m":650400.259713,
    "zs:blockids":[
        50070208032016,
        50070208033013,
        50070208033010,
        50070208033011,
        50070208033009,
        50070208033012,
        50070208033016,
        50070208032000
    ],
    "zs:housing10":237,
    "zs:label":"Raleigh Hills",
    "zs:pop10":340
},
  "geometry": {"coordinates":[-94.25697599999999,36.479531],"type":"Point"}
}