{
  "type": "Feature",
  "properties": {
    "gn:admin1_code":"AL",
    "gn:admin2_code":"121.0",
    "gn:asciiname":"Reubenville",
    "gn:country_code":"US",
    "gn:dem":147,
    "gn:elevation":"147.0",
    "gn:feature_class":"P",
    "gn:feature_code":"PPL",
    "gn:name":"Reubenville",
    "gn:population":0,
    "gn:timezone":"America/Chicago",
    "iso:country":"US",
    "name:eng_x_preferred":[
        "Reubenville"
    ],
    "name:und_x_variant":[
        "Ruebenville"
    ],
    "wof:name":"Reubenville",
    "wof:placetype":"locality"
},
  "geometry": {"coordinates":[-86.23803000000002,33.36955],"type":"Point"}
}