{
  "type": "Feature",
  "properties": {
    "gn:admin1_code":"SC",
    "gn:admin2_code":"83",
    "gn:asciiname":"Heatherwood Mobile Home Park",
    "gn:country_code":"US",
    "gn:dem":219,
    "gn:elevation":"212.0",
    "gn:feature_class":"P",
    "gn:feature_code":"PPL",
    "gn:name":"Heatherwood Mobile Home Park",
    "gn:population":0,
    "gn:timezone":"America/New_York",
    "iso:country":"US",
    "wof:name":"Heatherwood Mobile Home Park",
    "wof:placetype":"campus"
},
  "geometry": {"coordinates":[-81.95583000000001,34.87583],"type":"Point"}
}