{
  "type": "Feature",
  "properties": {
    "gn:admin1_code":"NJ",
    "gn:admin2_code":"21",
    "gn:admin3_code":"29310.0",
    "gn:asciiname":"Yardville-Groveville",
    "gn:country_code":"US",
    "gn:dem":20,
    "gn:elevation":"17.0",
    "gn:feature_class":"P",
    "gn:feature_code":"PPL",
    "gn:name":"Yardville-Groveville",
    "gn:population":0,
    "gn:timezone":"America/New_York",
    "iso:country":"US",
    "name:azb_x_preferred":[
        "\u06cc\u0627\u0631\u062f\u0648\u06cc\u0644-\u0642\u0631\u0648\u0648\u0648\u06cc\u0644"
    ],
    "name:cat_x_preferred":[
        "Yardville-Groveville"
    ],
    "name:ceb_x_preferred":[
        "Yardville-Groveville"
    ],
    "name:fas_x_preferred":[
        "\u06cc\u0627\u0631\u062f\u0648\u06cc\u0644-\u06af\u0631\u0648\u0648\u0648\u06cc\u0644"
    ],
    "name:kaz_x_preferred":[
        "\u042f\u0440\u0434\u0432\u0438\u043b\u043b-\u0413\u0440\u043e\u0443\u0432\u0438\u0432\u0438\u043b\u043b"
    ],
    "name:kir_x_preferred":[
        "\u042f\u0440\u0434\u0432\u0438\u043b\u043b-\u0413\u0440\u043e\u0443\u0432\u0438\u0432\u0438\u043b\u043b"
    ],
    "name:nld_x_preferred":[
        "Yardville-Groveville"
    ],
    "name:por_x_preferred":[
        "Yardville-Groveville"
    ],
    "name:spa_x_preferred":[
        "Yardville"
    ],
    "name:srp_x_preferred":[
        "\u0408\u0430\u0440\u0434\u0432\u0438\u043b-\u0413\u0440\u043e\u0432\u0438\u0432\u0438\u043b"
    ],
    "name:und_x_variant":[
        "Yardville-Groveville CDP"
    ],
    "name:urd_x_preferred":[
        "\u06cc\u0627\u0631\u0688\u0648\u06cc\u0644-\u06af\u0631\u0648\u0648\u0648\u06cc\u0644"
    ],
    "name:uzb_x_preferred":[
        "Yardville-Groveville"
    ],
    "name:vol_x_preferred":[
        "Yardville-Groveville"
    ],
    "wof:name":"Yardville-Groveville",
    "wof:placetype":"locality"
},
  "geometry": {"coordinates":[-74.66803,40.18079],"type":"Point"}
}