{
  "type": "Feature",
  "properties": {
    "gn:admin1_code":"GA",
    "gn:admin2_code":"217",
    "gn:asciiname":"Stone Creek",
    "gn:country_code":"US",
    "gn:dem":245,
    "gn:elevation":"244.0",
    "gn:feature_class":"P",
    "gn:feature_code":"PPL",
    "gn:name":"Stone Creek",
    "gn:population":0,
    "gn:timezone":"America/New_York",
    "iso:country":"US",
    "name:ceb_x_preferred":[
        "Stone Creek"
    ],
    "name:pol_x_preferred":[
        "Stone Creek"
    ],
    "name:swe_x_preferred":[
        "Stone Creek"
    ],
    "wof:name":"Stone Creek",
    "wof:placetype":"locality"
},
  "geometry": {"coordinates":[-84.01352,33.55928],"type":"Point"}
}