{
  "type": "Feature",
  "properties": {
    "gn:admin1_code":"FL",
    "gn:admin2_code":"83.0",
    "gn:asciiname":"Forest Lakes Park",
    "gn:country_code":"US",
    "gn:dem":29,
    "gn:elevation":"21.0",
    "gn:feature_class":"P",
    "gn:feature_code":"PPL",
    "gn:name":"Forest Lakes Park",
    "gn:population":0,
    "gn:timezone":"America/New_York",
    "iso:country":"US",
    "wof:name":"Forest Lakes Park",
    "wof:placetype":"locality"
},
  "geometry": {"coordinates":[-81.8373,29.07859],"type":"Point"}
}