{
  "type": "Feature",
  "properties": {
    "iso:country":"US",
    "name:eng_x_preferred":[
        "Wedington Place"
    ],
    "wof:name":"Wedington Place",
    "wof:placetype":"neighbourhood",
    "wof:population":516,
    "zs:area_m":611013.210795,
    "zs:blockids":[
        51430106001019,
        51430106002006,
        51430105071016,
        51430105071008,
        51430105061002,
        51430105071017,
        51430106002005,
        51430105061000,
        51430105071009,
        51430105071015,
        51430105071014,
        51430106002007,
        51430105061001,
        51430105071007,
        51430105071011,
        51430106002001
    ],
    "zs:housing10":313,
    "zs:label":"Wedington Place",
    "zs:pop10":516
},
  "geometry": {"coordinates":[-94.20209800000001,36.07917],"type":"Point"}
}