{
  "type": "Feature",
  "properties": {
    "gn:admin1_code":"VA",
    "gn:admin2_code":"700.0",
    "gn:asciiname":"Davis Mobile Home Park",
    "gn:country_code":"US",
    "gn:dem":7,
    "gn:elevation":"6.0",
    "gn:feature_class":"P",
    "gn:feature_code":"PPL",
    "gn:name":"Davis Mobile Home Park",
    "gn:population":0,
    "gn:timezone":"America/New_York",
    "iso:country":"US",
    "wof:name":"Davis Mobile Home Park",
    "wof:placetype":"campus"
},
  "geometry": {"coordinates":[-76.44139,37.01194],"type":"Point"}
}