{
  "type": "Feature",
  "properties": {
    "gn:country":"US",
    "gn:fcode":"PPL",
    "gn:population":539,
    "iso:country":"US",
    "name:ara_x_preferred":[
        "\u063a\u0631\u0627\u0646\u062f \u0625\u064a\u0633\u0644"
    ],
    "name:cat_x_preferred":[
        "Grand Isle"
    ],
    "name:ceb_x_preferred":[
        "Grand Isle"
    ],
    "name:che_x_preferred":[
        "\u0413\u0440\u0430\u043d\u0434-\u0410\u0439\u043b"
    ],
    "name:cym_x_preferred":[
        "Grand Isle"
    ],
    "name:deu_x_preferred":[
        "Grand Isle"
    ],
    "name:eng_x_preferred":[
        "Grand Isle"
    ],
    "name:eus_x_preferred":[
        "Grand Isle"
    ],
    "name:fra_x_preferred":[
        "Grand Isle"
    ],
    "name:hat_x_preferred":[
        "Grand Isle"
    ],
    "name:hun_x_preferred":[
        "Grand Isle"
    ],
    "name:ita_x_preferred":[
        "Grand Isle"
    ],
    "name:jpn_x_preferred":[
        "\u30b0\u30e9\u30f3\u30c9\u30fb\u30a2\u30a4\u30eb"
    ],
    "name:kaz_x_preferred":[
        "\u0413\u0440\u0430\u043d\u0434 \u0410\u0439\u0441\u043b"
    ],
    "name:kir_x_preferred":[
        "\u0413\u0440\u0430\u043d\u0434 \u0410\u0439\u0441\u043b"
    ],
    "name:lld_x_preferred":[
        "Grand Isle"
    ],
    "name:nld_x_preferred":[
        "Grand Isle"
    ],
    "name:pol_x_preferred":[
        "Grand Isle"
    ],
    "name:spa_x_preferred":[
        "Grand Isle"
    ],
    "name:tat_x_preferred":[
        "\u0413\u0440\u0430\u043d\u0434-\u0410\u0439\u043b"
    ],
    "name:tur_x_preferred":[
        "Grand Isle"
    ],
    "name:ukr_x_preferred":[
        "\u0413\u0440\u0430\u043d\u0434-\u0410\u0439\u043b"
    ],
    "name:vol_x_preferred":[
        "Grand Isle"
    ],
    "qs_pg:aaroncc":"US",
    "qs_pg:gn_country":"US",
    "qs_pg:gn_fcode":"PPL",
    "qs_pg:gn_pop":539,
    "qs_pg:name":"Grand Isle",
    "qs_pg:name_adm0":"United States",
    "qs_pg:name_adm1":"Maine",
    "qs_pg:photos":4,
    "qs_pg:photos_1k":1,
    "qs_pg:photos_9k":1,
    "qs_pg:photos_9r":1,
    "qs_pg:photos_all":5,
    "qs_pg:photos_sr":1,
    "qs_pg:pop_sr":2,
    "qs_pg:qs_pg_placetype":"locality",
    "qs_pg:qs_pg_placetype_gp":"Town",
    "qs_pg:woe_adm0":23424977,
    "woe:adm0_id":23424977,
    "woe:name_adm0":"United States",
    "woe:name_adm1":"Maine",
    "woe:placetype":"Town",
    "wof:name":"Grand Isle",
    "wof:placetype":"locality",
    "wof:population":539
},
  "geometry": {"coordinates":[-68.15197999999999,47.30532],"type":"Point"}
}