{
  "type": "Feature",
  "properties": {
    "gn:admin1_code":"LA",
    "gn:admin2_code":"63.0",
    "gn:asciiname":"Watson Estates Mobile Home Park",
    "gn:country_code":"US",
    "gn:dem":24,
    "gn:elevation":"22.0",
    "gn:feature_class":"P",
    "gn:feature_code":"PPL",
    "gn:name":"Watson Estates Mobile Home Park",
    "gn:population":0,
    "gn:timezone":"America/Chicago",
    "iso:country":"US",
    "wof:name":"Watson Estates Mobile Home Park",
    "wof:placetype":"campus"
},
  "geometry": {"coordinates":[-90.91669,30.58489],"type":"Point"}
}