{
  "type": "Feature",
  "properties": {
    "gn:admin1_code":"KS",
    "gn:admin2_code":"155.0",
    "gn:admin3_code":"33625.0",
    "gn:asciiname":"Hutchinson Regency Mobile Home Park",
    "gn:country_code":"US",
    "gn:dem":469,
    "gn:elevation":"461.0",
    "gn:feature_class":"P",
    "gn:feature_code":"PPL",
    "gn:name":"Hutchinson Regency Mobile Home Park",
    "gn:population":0,
    "gn:timezone":"America/Chicago",
    "iso:country":"US",
    "wof:name":"Hutchinson Regency Mobile Home Park",
    "wof:placetype":"campus"
},
  "geometry": {"coordinates":[-97.89614,38.02626],"type":"Point"}
}