{
  "type": "Feature",
  "properties": {
    "iso:country":"US",
    "name:eng_x_preferred":[
        "North Mills"
    ],
    "wof:name":"North Mills",
    "wof:placetype":"neighbourhood",
    "wof:population":108,
    "zs:area_m":1358738.168147,
    "zs:blockids":[
        420850325021073,
        420850326014030,
        420850325021070,
        420850325021075,
        420850326014032,
        420850326014042,
        420850326014045,
        420850326014044,
        420850325021071,
        420850325021072,
        420850326014043
    ],
    "zs:housing10":92,
    "zs:label":"North Mills",
    "zs:pop10":108
},
  "geometry": {"coordinates":[-80.181527,41.27862],"type":"Point"}
}