{
  "type": "Feature",
  "properties": {
    "gn:admin1_code":"VA",
    "gn:admin2_code":"770",
    "gn:asciiname":"Oakland",
    "gn:country_code":"US",
    "gn:dem":302,
    "gn:elevation":"304.0",
    "gn:feature_class":"P",
    "gn:feature_code":"PPL",
    "gn:name":"Oakland",
    "gn:population":0,
    "gn:timezone":"America/New_York",
    "iso:country":"US",
    "wof:name":"Oakland",
    "wof:placetype":"locality"
},
  "geometry": {"coordinates":[-79.93143000000001,37.28903],"type":"Point"}
}