{
  "type": "Feature",
  "properties": {
    "gn:admin1_code":"MD",
    "gn:admin2_code":"3.0",
    "gn:asciiname":"West River Plantation",
    "gn:country_code":"US",
    "gn:dem":5,
    "gn:elevation":"2.0",
    "gn:feature_class":"P",
    "gn:feature_code":"PPL",
    "gn:name":"West River Plantation",
    "gn:population":0,
    "gn:timezone":"America/New_York",
    "iso:country":"US",
    "wof:name":"West River Plantation",
    "wof:placetype":"locality"
},
  "geometry": {"coordinates":[-76.54746,38.82317000000001],"type":"Point"}
}