{
  "type": "Feature",
  "properties": {
    "gn:admin1_code":"NY",
    "gn:admin2_code":"57.0",
    "gn:admin3_code":"47614.0",
    "gn:asciiname":"Highland Mobile Home Estates",
    "gn:country_code":"US",
    "gn:dem":144,
    "gn:elevation":"143.0",
    "gn:feature_class":"P",
    "gn:feature_code":"PPL",
    "gn:name":"Highland Mobile Home Estates",
    "gn:population":0,
    "gn:timezone":"America/New_York",
    "iso:country":"US",
    "wof:name":"Highland Mobile Home Estates",
    "wof:placetype":"campus"
},
  "geometry": {"coordinates":[-74.63343,42.92549],"type":"Point"}
}