{
  "type": "Feature",
  "properties": {
    "gn:admin1_code":"VA",
    "gn:admin2_code":"800",
    "gn:asciiname":"Wilson Pines",
    "gn:country_code":"US",
    "gn:dem":12,
    "gn:elevation":"7.0",
    "gn:feature_class":"P",
    "gn:feature_code":"PPL",
    "gn:name":"Wilson Pines",
    "gn:population":0,
    "gn:timezone":"America/New_York",
    "iso:country":"US",
    "wof:name":"Wilson Pines",
    "wof:placetype":"locality"
},
  "geometry": {"coordinates":[-76.55023,36.73848],"type":"Point"}
}