{
  "type": "Feature",
  "properties": {
    "gn:admin1_code":"CA",
    "gn:admin2_code":"109.0",
    "gn:asciiname":"Yankee Hill",
    "gn:country_code":"US",
    "gn:dem":697,
    "gn:elevation":"681.0",
    "gn:feature_class":"P",
    "gn:feature_code":"PPL",
    "gn:name":"Yankee Hill",
    "gn:population":0,
    "gn:timezone":"America/Los_Angeles",
    "iso:country":"US",
    "name:ceb_x_preferred":[
        "Yankee Hill"
    ],
    "name:deu_x_preferred":[
        "Yankee Hill"
    ],
    "name:ita_x_preferred":[
        "Yankee Hill"
    ],
    "name:srp_x_preferred":[
        "\u0408\u0435\u043d\u043a\u0438 \u0425\u0438\u043b"
    ],
    "name:swe_x_preferred":[
        "Yankee Hill"
    ],
    "wof:name":"Yankee Hill",
    "wof:placetype":"locality"
},
  "geometry": {"coordinates":[-120.37797,38.03965],"type":"Point"}
}