{
  "type": "Feature",
  "properties": {
    "gn:admin1_code":"NC",
    "gn:admin2_code":"133",
    "gn:admin3_code":"92672.0",
    "gn:asciiname":"Ervintown",
    "gn:country_code":"US",
    "gn:dem":20,
    "gn:elevation":"20.0",
    "gn:feature_class":"P",
    "gn:feature_code":"PPL",
    "gn:name":"Ervintown",
    "gn:population":0,
    "gn:timezone":"America/New_York",
    "iso:country":"US",
    "wof:name":"Ervintown",
    "wof:placetype":"locality"
},
  "geometry": {"coordinates":[-77.56191,34.90822],"type":"Point"}
}