{
  "type": "Feature",
  "properties": {
    "gn:admin1_code":"GA",
    "gn:admin2_code":"139",
    "gn:asciiname":"Sugar Hill",
    "gn:country_code":"US",
    "gn:dem":295,
    "gn:elevation":"289.0",
    "gn:feature_class":"P",
    "gn:feature_code":"PPL",
    "gn:name":"Sugar Hill",
    "gn:population":0,
    "gn:timezone":"America/New_York",
    "iso:country":"US",
    "name:ceb_x_preferred":[
        "Sugar Hill"
    ],
    "name:deu_x_preferred":[
        "Sugar Hill"
    ],
    "name:fra_x_preferred":[
        "Sugar Hill"
    ],
    "name:ita_x_preferred":[
        "Sugar Hill"
    ],
    "name:jpn_x_preferred":[
        "\u30b7\u30e5\u30ac\u30fc\u30d2\u30eb"
    ],
    "name:kor_x_preferred":[
        "\uc288\uac70\ud790"
    ],
    "name:pol_x_preferred":[
        "Sugar Hill"
    ],
    "name:por_x_preferred":[
        "Sugar Hill"
    ],
    "name:swe_x_preferred":[
        "Sugar Hill"
    ],
    "name:vol_x_preferred":[
        "Sugar Hill"
    ],
    "wof:name":"Sugar Hill",
    "wof:placetype":"locality"
},
  "geometry": {"coordinates":[-83.73628000000002,34.22649000000001],"type":"Point"}
}