{
  "type": "Feature",
  "properties": {
    "gn:admin1_code":"AR",
    "gn:admin2_code":"119.0",
    "gn:admin3_code":"91731.0",
    "gn:asciiname":"Estes",
    "gn:country_code":"US",
    "gn:dem":74,
    "gn:elevation":"72.0",
    "gn:feature_class":"P",
    "gn:feature_code":"PPL",
    "gn:name":"Estes",
    "gn:population":0,
    "gn:timezone":"America/Chicago",
    "iso:country":"US",
    "name:eng_x_preferred":[
        "Estes"
    ],
    "name:und_x_variant":[
        "Estes Store"
    ],
    "wof:name":"Estes",
    "wof:placetype":"locality"
},
  "geometry": {"coordinates":[-92.11875999999999,34.60843],"type":"Point"}
}