{
  "type": "Feature",
  "properties": {
    "iso:country":"US",
    "name:ceb_x_preferred":[
        "Ridgewood"
    ],
    "name:ces_x_preferred":[
        "Ridgewood"
    ],
    "name:deu_x_preferred":[
        "Ridgewood"
    ],
    "name:eng_x_preferred":[
        "Ridgewood"
    ],
    "name:fra_x_preferred":[
        "Ridgewood"
    ],
    "name:ita_x_preferred":[
        "Ridgewood"
    ],
    "name:nld_x_preferred":[
        "Ridgewood"
    ],
    "name:pol_x_preferred":[
        "Ridgewood"
    ],
    "name:swe_x_preferred":[
        "Ridgewood"
    ],
    "wd:wordcount":157,
    "wof:name":"Ridgewood",
    "wof:placetype":"neighbourhood",
    "wof:population":2395,
    "zs:area_m":1014028.026458,
    "zs:blockids":[
        250138019021003,
        250138019022009,
        250138019022008,
        250138018001018,
        250138012002001,
        250138019021012,
        250138012002006,
        250138012002007,
        250138019021001,
        250138012002005,
        250138019022001,
        250138011021003,
        250138019021002,
        250138018001023,
        250138018004002,
        250138020001000,
        250138019021009,
        250138018004004,
        250138018004012,
        250138019021000,
        250138019021010,
        250138018001017,
        250138018004001,
        250138012002010,
        250138012002004,
        250138019022011,
        250138018001019,
        250138018001022,
        250138019021011,
        250138012002009,
        250138013003019
    ],
    "zs:housing10":1125,
    "zs:label":"Ridgewood",
    "zs:pop10":2395
},
  "geometry": {"coordinates":[-72.579938,42.107824],"type":"Point"}
}