{
  "type": "Feature",
  "properties": {
    "iso:country":"US",
    "name:eng_x_preferred":[
        "Clifton Prado"
    ],
    "wof:name":"Clifton Prado",
    "wof:placetype":"neighbourhood",
    "wof:population":752,
    "zs:area_m":105516.997705,
    "zs:blockids":[
        390351606023002,
        390351606022001,
        390351606022002,
        390351606022004,
        390351606023003,
        390351606022003
    ],
    "zs:housing10":466,
    "zs:label":"Clifton Prado",
    "zs:pop10":752
},
  "geometry": {"coordinates":[-81.772188,41.487287],"type":"Point"}
}