{
  "type": "Feature",
  "properties": {
    "gn:admin1_code":"FL",
    "gn:admin2_code":"131.0",
    "gn:asciiname":"Pleasant Ridge",
    "gn:country_code":"US",
    "gn:dem":69,
    "gn:elevation":"67.0",
    "gn:feature_class":"P",
    "gn:feature_code":"PPL",
    "gn:name":"Pleasant Ridge",
    "gn:population":0,
    "gn:timezone":"America/Chicago",
    "iso:country":"US",
    "name:ceb_x_preferred":[
        "Pleasant Ridge"
    ],
    "name:deu_x_preferred":[
        "Pleasant Ridge"
    ],
    "name:fra_x_preferred":[
        "Pleasant Ridge"
    ],
    "name:ita_x_preferred":[
        "Pleasant Ridge"
    ],
    "name:pol_x_preferred":[
        "Pleasant Ridge"
    ],
    "name:swe_x_preferred":[
        "Pleasant Ridge"
    ],
    "name:vol_x_preferred":[
        "Pleasant Ridge"
    ],
    "wof:name":"Pleasant Ridge",
    "wof:placetype":"locality"
},
  "geometry": {"coordinates":[-86.17411,30.69297000000001],"type":"Point"}
}