{
  "type": "Feature",
  "properties": {
    "iso:country":"US",
    "name:eng_x_preferred":[
        "Alburg Center"
    ],
    "wof:name":"Alburg Center",
    "wof:placetype":"neighbourhood",
    "wof:population":365,
    "zs:area_m":19664228.802785,
    "zs:blockids":[
        500130201001064,
        500130201004039,
        500130201001017,
        500130201004037,
        500130201004006
    ],
    "zs:housing10":183,
    "zs:label":"Alburg Center",
    "zs:pop10":365
},
  "geometry": {"coordinates":[-73.291172,44.947955],"type":"Point"}
}