{
  "type": "Feature",
  "properties": {
    "iso:country":"US",
    "name:eng_x_preferred":[
        "North Creek"
    ],
    "qs:gn_adm0_cc":"US",
    "qs:gn_local":5787829,
    "qs:gn_nam_loc":"Bothell, King, Washington, US",
    "qs:gn_namadm1":"WA",
    "qs:local_max":1024,
    "qs:local_sum":5156,
    "qs:localhoods":13,
    "qs:name":"North Creek",
    "qs:name_adm0":"United States",
    "qs:name_adm1":"Washington",
    "qs:name_adm2":"King",
    "qs:name_local":"Bothell",
    "qs:photo_max":110,
    "qs:photo_sum":336,
    "qs:placetype":"Suburb",
    "qs:quad_count":20,
    "qs:woe_adm0":23424977,
    "qs:woe_adm1":2347606,
    "qs:woe_adm2":12590456,
    "qs:woe_lau":0,
    "qs:woe_local":2367188,
    "qs:woe_ver":"7.10.0",
    "wof:lang":[
        "eng"
    ],
    "wof:name":"North Creek-195th St",
    "wof:placetype":"neighbourhood",
    "wof:population":2996,
    "zs:blockids":[
        530330219053002,
        530330218021009,
        530330218022030,
        530330218022011,
        530330218021022,
        530330218022005,
        530330218022006,
        530330218022024,
        530330218022023,
        530330218021023,
        530330218042040,
        530330218022009,
        530330218022004,
        530330218041027,
        530330218021026,
        530330218042034,
        530330218022015,
        530330218022017,
        530330219053004,
        530330218022021,
        530330219053003,
        530330219061003,
        530330218022007,
        530330218022034,
        530330218041010,
        530330219053001,
        530330219061000,
        530330218022018,
        530330218022031,
        530330218022025,
        530330218022043,
        530330218022054,
        530330218022037,
        530330218021025,
        530330218022044,
        530330218022029,
        530330218021027,
        530330218022012,
        530330218041014,
        530330218041009,
        530330218021007,
        530330218022016,
        530330218022056,
        530330218022027,
        530330218042041,
        530330219051011,
        530330218022020,
        530330219051000,
        530330218022019,
        530330218021024,
        530330218022052,
        530330219061004,
        530330218041000,
        530330219051005,
        530330218022028,
        530330218022013,
        530330218041015,
        530330218022045,
        530330218022026,
        530330218022032,
        530330218022003,
        530330218021008,
        530330218022053,
        530330218021028,
        530330218021021,
        530330218022022,
        530330218042000,
        530330218022014,
        530330218022046,
        530330219051009,
        530330218022008,
        530330218022033,
        530330218042035
    ],
    "zs:housing10":1382,
    "zs:pop10":2996
},
  "geometry": {"coordinates":[-122.182462,47.767229],"type":"Point"}
}