{
  "type": "Feature",
  "properties": {
    "gn:admin1_code":"VT",
    "gn:admin2_code":"3.0",
    "gn:admin3_code":"55000.0",
    "gn:asciiname":"Bromley Village",
    "gn:country_code":"US",
    "gn:dem":676,
    "gn:elevation":"679.0",
    "gn:feature_class":"P",
    "gn:feature_code":"PPL",
    "gn:name":"Bromley Village",
    "gn:population":0,
    "gn:timezone":"America/New_York",
    "iso:country":"US",
    "wof:name":"Bromley Village",
    "wof:placetype":"locality"
},
  "geometry": {"coordinates":[-72.94315999999998,43.21202],"type":"Point"}
}