{
  "type": "Feature",
  "properties": {
    "gn:admin1_code":"SC",
    "gn:admin2_code":"15.0",
    "gn:asciiname":"Oak Corner",
    "gn:country_code":"US",
    "gn:dem":12,
    "gn:elevation":"12.0",
    "gn:feature_class":"P",
    "gn:feature_code":"PPL",
    "gn:name":"Oak Corner",
    "gn:population":0,
    "gn:timezone":"America/New_York",
    "iso:country":"US",
    "wof:name":"Oak Corner",
    "wof:placetype":"locality"
},
  "geometry": {"coordinates":[-79.70813000000003,33.16905999999999],"type":"Point"}
}