{
  "type": "Feature",
  "properties": {
    "gn:admin1_code":"KY",
    "gn:admin2_code":"105.0",
    "gn:asciiname":"Whaynes Corner",
    "gn:country_code":"US",
    "gn:dem":92,
    "gn:elevation":"90.0",
    "gn:feature_class":"P",
    "gn:feature_code":"PPL",
    "gn:name":"Whaynes Corner",
    "gn:population":0,
    "gn:timezone":"America/Chicago",
    "iso:country":"US",
    "wof:name":"Whaynes Corner",
    "wof:placetype":"locality"
},
  "geometry": {"coordinates":[-89.12173,36.64923],"type":"Point"}
}