{
  "type": "Feature",
  "properties": {
    "gn:admin1_code":"NC",
    "gn:admin2_code":"69",
    "gn:admin3_code":"90926.0",
    "gn:asciiname":"Daddysville",
    "gn:country_code":"US",
    "gn:dem":92,
    "gn:elevation":"91.0",
    "gn:feature_class":"P",
    "gn:feature_code":"PPL",
    "gn:name":"Daddysville",
    "gn:population":0,
    "gn:timezone":"America/New_York",
    "iso:country":"US",
    "wof:name":"Daddysville",
    "wof:placetype":"locality"
},
  "geometry": {"coordinates":[-78.22166,35.90765],"type":"Point"}
}