{
  "type": "Feature",
  "properties": {
    "gn:admin1_code":"VA",
    "gn:admin2_code":"141",
    "gn:asciiname":"Gilbert Mill",
    "gn:country_code":"US",
    "gn:dem":362,
    "gn:elevation":"348.0",
    "gn:feature_class":"P",
    "gn:feature_code":"PPL",
    "gn:name":"Gilbert Mill",
    "gn:population":0,
    "gn:timezone":"America/New_York",
    "iso:country":"US",
    "wof:name":"Gilbert Mill",
    "wof:placetype":"locality"
},
  "geometry": {"coordinates":[-80.24476999999997,36.58514],"type":"Point"}
}