{
  "type": "Feature",
  "properties": {
    "gn:admin1_code":"OH",
    "gn:admin2_code":"151.0",
    "gn:admin3_code":"62988.0",
    "gn:asciiname":"Oval City",
    "gn:country_code":"US",
    "gn:dem":341,
    "gn:elevation":"342.0",
    "gn:feature_class":"P",
    "gn:feature_code":"PPL",
    "gn:name":"Oval City",
    "gn:population":0,
    "gn:timezone":"America/New_York",
    "iso:country":"US",
    "wof:name":"Oval City",
    "wof:placetype":"locality"
},
  "geometry": {"coordinates":[-81.32733,40.89589],"type":"Point"}
}