{
  "type": "Feature",
  "properties": {
    "gn:admin1_code":"CO",
    "gn:admin2_code":"93.0",
    "gn:asciiname":"Glenisle",
    "gn:country_code":"US",
    "gn:dem":2462,
    "gn:elevation":"2455.0",
    "gn:feature_class":"P",
    "gn:feature_code":"PPL",
    "gn:name":"Glenisle",
    "gn:population":0,
    "gn:timezone":"America/Denver",
    "iso:country":"US",
    "name:ind_x_preferred":[
        "Glenisle"
    ],
    "wof:name":"Glenisle",
    "wof:placetype":"locality"
},
  "geometry": {"coordinates":[-105.50972,39.40888],"type":"Point"}
}