{
  "type": "Feature",
  "properties": {
    "gn:gn_country":"US",
    "gn:gn_fcode":"PPL",
    "gn:gn_pop":0,
    "iso:country":"US",
    "name:bre_x_preferred":[
        "Brennan"
    ],
    "name:cat_x_preferred":[
        "Brennan"
    ],
    "name:ceb_x_preferred":[
        "Brennan"
    ],
    "name:ces_x_preferred":[
        "Brennan"
    ],
    "name:deu_x_preferred":[
        "Brennan"
    ],
    "name:fin_x_preferred":[
        "Brennan"
    ],
    "name:fra_x_preferred":[
        "Brennan"
    ],
    "name:heb_x_preferred":[
        "\u05d1\u05e8\u05e0\u05df"
    ],
    "name:ita_x_preferred":[
        "Brennan"
    ],
    "name:jpn_x_preferred":[
        "\u30d6\u30ec\u30ca\u30f3"
    ],
    "name:nld_x_preferred":[
        "Brennan"
    ],
    "name:pol_x_preferred":[
        "Brennan"
    ],
    "name:rus_x_preferred":[
        "\u0411\u0440\u0435\u043d\u043d\u0430\u043d"
    ],
    "qs_pg:aaroncc":"US",
    "qs_pg:gn_country":"US",
    "qs_pg:gn_fcode":"PPL",
    "qs_pg:gn_pop":0,
    "qs_pg:name":"Brennan",
    "qs_pg:name_adm0":"United States",
    "qs_pg:name_adm1":"Washington",
    "qs_pg:photos":181,
    "qs_pg:photos_1k":37,
    "qs_pg:photos_9k":1,
    "qs_pg:photos_9r":4,
    "qs_pg:photos_all":181,
    "qs_pg:photos_sr":4,
    "qs_pg:pop_sr":0,
    "qs_pg:qs_pg_placetype":"locality",
    "qs_pg:qs_pg_placetype_gp":"Town",
    "qs_pg:woe_adm0":23424977,
    "woe:adm0_id":23424977,
    "woe:name_adm0":"United States",
    "woe:name_adm1":"Washington",
    "woe:placetype":"Town",
    "wof:name":"Brennan",
    "wof:placetype":"locality"
},
  "geometry": {"coordinates":[-122.56238999999999,48.82233],"type":"Point"}
}