{
  "type": "Feature",
  "properties": {
    "gn:admin1_code":"NC",
    "gn:admin2_code":"149.0",
    "gn:admin3_code":"90772.0",
    "gn:asciiname":"Poplar Grove",
    "gn:country_code":"US",
    "gn:dem":294,
    "gn:elevation":"287.0",
    "gn:feature_class":"P",
    "gn:feature_code":"PPL",
    "gn:name":"Poplar Grove",
    "gn:population":0,
    "gn:timezone":"America/New_York",
    "iso:country":"US",
    "name:ceb_x_preferred":[
        "Poplar Grove"
    ],
    "name:deu_x_preferred":[
        "Poplar Grove"
    ],
    "name:pol_x_preferred":[
        "Poplar Grove"
    ],
    "wof:name":"Poplar Grove",
    "wof:placetype":"locality"
},
  "geometry": {"coordinates":[-82.13178000000001,35.38429],"type":"Point"}
}