{
  "type": "Feature",
  "properties": {
    "gn:admin1_code":"MS",
    "gn:admin2_code":"23.0",
    "gn:asciiname":"Nancy",
    "gn:country_code":"US",
    "gn:dem":86,
    "gn:elevation":"80.0",
    "gn:feature_class":"P",
    "gn:feature_code":"PPL",
    "gn:name":"Nancy",
    "gn:population":0,
    "gn:timezone":"America/Chicago",
    "iso:country":"US",
    "name:ara_x_preferred":[
        "\u0646\u0627\u0646\u0633\u064a"
    ],
    "name:ceb_x_preferred":[
        "Nancy"
    ],
    "name:ces_x_preferred":[
        "Nancy"
    ],
    "name:deu_x_preferred":[
        "Nancy"
    ],
    "name:eus_x_preferred":[
        "Nancy"
    ],
    "name:fas_x_preferred":[
        "\u0646\u0627\u0646\u0633\u06cc"
    ],
    "name:fra_x_preferred":[
        "Nancy"
    ],
    "name:hun_x_preferred":[
        "Nancy"
    ],
    "name:ind_x_preferred":[
        "Nancy"
    ],
    "name:ita_x_preferred":[
        "Nancy"
    ],
    "name:jpn_x_preferred":[
        "\u30ca\u30f3\u30b7\u30fc"
    ],
    "name:nds_x_preferred":[
        "Nancy"
    ],
    "name:rus_x_preferred":[
        "\u041d\u0430\u043d\u0441\u0438"
    ],
    "name:slk_x_preferred":[
        "Nancy"
    ],
    "name:spa_x_preferred":[
        "Nancy"
    ],
    "name:swe_x_preferred":[
        "Nancy"
    ],
    "name:zho_x_preferred":[
        "Nancy"
    ],
    "wof:name":"Nancy",
    "wof:placetype":"locality"
},
  "geometry": {"coordinates":[-88.84255,31.94349],"type":"Point"}
}