{
  "type": "Feature",
  "properties": {
    "gn:admin1_code":"HI",
    "gn:admin2_code":"1.0",
    "gn:asciiname":"Papa Bay Estates",
    "gn:country_code":"US",
    "gn:dem":424,
    "gn:elevation":"433.0",
    "gn:feature_class":"P",
    "gn:feature_code":"PPL",
    "gn:name":"P\u0101p\u0101 Bay Estates",
    "gn:population":0,
    "gn:timezone":"Pacific/Honolulu",
    "iso:country":"US",
    "name:eng_x_preferred":[
        "P\u0101p\u0101 Bay Estates"
    ],
    "wof:name":"Papa Bay Estates",
    "wof:placetype":"locality"
},
  "geometry": {"coordinates":[-155.87741,19.21338],"type":"Point"}
}