{
  "type": "Feature",
  "properties": {
    "gn:admin1_code":"CA",
    "gn:admin2_code":"57.0",
    "gn:asciiname":"Sebastopol",
    "gn:country_code":"US",
    "gn:dem":585,
    "gn:elevation":"583.0",
    "gn:feature_class":"P",
    "gn:feature_code":"PPL",
    "gn:name":"Sebastopol",
    "gn:population":0,
    "gn:timezone":"America/Los_Angeles",
    "iso:country":"US",
    "wof:name":"Sebastopol",
    "wof:placetype":"locality"
},
  "geometry": {"coordinates":[-121.12107,39.36267],"type":"Point"}
}