{
  "type": "Feature",
  "properties": {
    "gn:elevation":17,
    "iso:country":"US",
    "name:arz_x_preferred":[
        "\u0645\u0637\u0627\u0631 \u0633\u0627\u0646\u062f \u0628\u0648\u064a\u0646\u062a"
    ],
    "name:ceb_x_preferred":[
        "Sand Point Airport"
    ],
    "name:eng_x_preferred":[
        "Sand Point Airport"
    ],
    "name:eng_x_variant":[
        "SDP",
        "PASD"
    ],
    "name:fas_x_preferred":[
        "\u0641\u0631\u0648\u062f\u06af\u0627\u0647 \u0633\u0646\u062f \u067e\u0648\u06cc\u0646\u062a"
    ],
    "name:ron_x_preferred":[
        "Aeroportul Sand Point"
    ],
    "name:rus_x_preferred":[
        "\u0421\u0430\u043d\u0434-\u041f\u043e\u0439\u043d\u0442"
    ],
    "name:zho_x_preferred":[
        "\u6c99\u9ede"
    ],
    "oa:elevation_ft":"21",
    "oa:type":"medium_airport",
    "wd:wordcount":415,
    "woe:hierarchy":{
        "country_id":23424977,
        "county_id":12587554,
        "planet_id":1,
        "state_id":2347560
    },
    "wof:name":"Sand Point Airport",
    "wof:placetype":"campus"
},
  "geometry": {"coordinates":[-160.52299500000001,55.314999],"type":"Point"}
}