{
  "type": "Feature",
  "properties": {
    "gn:admin1_code":"AR",
    "gn:admin2_code":"71.0",
    "gn:admin3_code":"91770.0",
    "gn:asciiname":"Edna",
    "gn:country_code":"US",
    "gn:dem":204,
    "gn:elevation":"193.0",
    "gn:feature_class":"P",
    "gn:feature_code":"PPL",
    "gn:name":"Edna",
    "gn:population":0,
    "gn:timezone":"America/Chicago",
    "iso:country":"US",
    "name:ceb_x_preferred":[
        "Edna"
    ],
    "name:deu_x_preferred":[
        "Edna"
    ],
    "name:ita_x_preferred":[
        "Edna"
    ],
    "name:jpn_x_preferred":[
        "\u30a8\u30c9\u30ca"
    ],
    "name:nld_x_preferred":[
        "Edna"
    ],
    "name:pol_x_preferred":[
        "Edna"
    ],
    "name:por_x_preferred":[
        "Edna"
    ],
    "name:rus_x_preferred":[
        "\u042d\u0434\u043d\u0430"
    ],
    "name:srp_x_preferred":[
        "\u0415\u0434\u043d\u0430"
    ],
    "name:swe_x_preferred":[
        "Edna"
    ],
    "name:ukr_x_preferred":[
        "\u0415\u0434\u043d\u0430"
    ],
    "wof:name":"Edna",
    "wof:placetype":"locality"
},
  "geometry": {"coordinates":[-93.63213,35.55481],"type":"Point"}
}