{
  "type": "Feature",
  "properties": {
    "gn:country":"US",
    "gn:fcode":"PPL",
    "gn:population":413,
    "iso:country":"US",
    "name:eng_x_preferred":[
        "Colonia Iglesia Antigua"
    ],
    "name:und_x_variant":[
        "Iglesia Antigua Colonia"
    ],
    "qs_pg:aaroncc":"US",
    "qs_pg:gn_country":"US",
    "qs_pg:gn_fcode":"PPL",
    "qs_pg:gn_pop":413,
    "qs_pg:name":"Colonia Iglesia Antigua",
    "qs_pg:photos_9r":0,
    "qs_pg:photos_sr":0,
    "qs_pg:pop_sr":2,
    "qs_pg:qs_pg_placetype":"locality",
    "wof:name":"Colonia Iglesia Antigua",
    "wof:placetype":"locality",
    "wof:population":413
},
  "geometry": {"coordinates":[-97.83833,26.0773],"type":"Point"}
}