{
  "type": "Feature",
  "properties": {
    "gn:gn_country":"US",
    "gn:gn_fcode":"PPL",
    "gn:gn_pop":0,
    "iso:country":"US",
    "name:cat_x_preferred":[
        "Daniels"
    ],
    "name:ces_x_preferred":[
        "Daniels"
    ],
    "name:deu_x_preferred":[
        "Daniels"
    ],
    "name:fra_x_preferred":[
        "Daniels"
    ],
    "name:heb_x_preferred":[
        "\u05d3\u05e0\u05d9\u05d0\u05dc\u05e1"
    ],
    "name:ita_x_preferred":[
        "Daniels"
    ],
    "name:nld_x_preferred":[
        "Daniels"
    ],
    "name:pol_x_preferred":[
        "Daniels"
    ],
    "name:por_x_preferred":[
        "Daniels"
    ],
    "name:rus_x_preferred":[
        "\u0414\u044d\u043d\u0438\u0435\u043b\u0441"
    ],
    "name:srp_x_preferred":[
        "\u0414\u0430\u043d\u0438\u0458\u0435\u043b\u0441"
    ],
    "name:ukr_x_preferred":[
        "\u0414\u0435\u043d\u0456\u0435\u043b\u0441"
    ],
    "name:zho_x_preferred":[
        "\u4e39\u5c3c\u5c14\u65af"
    ],
    "qs_pg:aaroncc":"US",
    "qs_pg:gn_country":"US",
    "qs_pg:gn_fcode":"PPL",
    "qs_pg:gn_pop":0,
    "qs_pg:name":"Daniels",
    "qs_pg:name_adm0":"United States",
    "qs_pg:name_adm1":"Texas",
    "qs_pg:photos":37,
    "qs_pg:photos_1k":7,
    "qs_pg:photos_9k":1,
    "qs_pg:photos_9r":2,
    "qs_pg:photos_all":37,
    "qs_pg:photos_sr":2,
    "qs_pg:pop_sr":0,
    "qs_pg:qs_pg_placetype":"locality",
    "qs_pg:qs_pg_placetype_gp":"Town",
    "qs_pg:woe_adm0":23424977,
    "woe:adm0_id":23424977,
    "woe:name_adm0":"United States",
    "woe:name_adm1":"Texas",
    "woe:placetype":"Town",
    "wof:name":"Daniels",
    "wof:placetype":"locality"
},
  "geometry": {"coordinates":[-96.20578999999999,30.19883],"type":"Point"}
}