{
  "type": "Feature",
  "properties": {
    "iso:country":"US",
    "name:bul_x_preferred":[
        "\u0425\u0430\u0440\u0434\u0438"
    ],
    "name:cat_x_preferred":[
        "Hardy"
    ],
    "name:ceb_x_preferred":[
        "Hardy"
    ],
    "name:ces_x_preferred":[
        "Hardy"
    ],
    "name:deu_x_preferred":[
        "Hardy"
    ],
    "name:eng_x_preferred":[
        "Hardy"
    ],
    "name:fas_x_preferred":[
        "\u0647\u0627\u0631\u062f\u06cc"
    ],
    "name:fin_x_preferred":[
        "Hardy"
    ],
    "name:fra_x_preferred":[
        "Hardy"
    ],
    "name:heb_x_preferred":[
        "\u05d4\u05d0\u05e8\u05d3\u05d9"
    ],
    "name:ita_x_preferred":[
        "Hardy"
    ],
    "name:jpn_x_preferred":[
        "\u30cf\u30fc\u30c7\u30a3"
    ],
    "name:lav_x_preferred":[
        "H\u0101rdijs"
    ],
    "name:lit_x_preferred":[
        "Hardy"
    ],
    "name:nld_x_preferred":[
        "Hardy"
    ],
    "name:pol_x_preferred":[
        "Hardy"
    ],
    "name:por_x_preferred":[
        "Hardy"
    ],
    "name:rus_x_preferred":[
        "\u0425\u0430\u0440\u0434\u0438"
    ],
    "name:spa_x_preferred":[
        "Hardy"
    ],
    "name:srp_x_preferred":[
        "\u0425\u0430\u0440\u0434\u0438"
    ],
    "name:swe_x_preferred":[
        "Hardy"
    ],
    "name:ukr_x_preferred":[
        "\u0413\u0430\u0440\u0434\u0456"
    ],
    "name:vol_x_preferred":[
        "Hardy"
    ],
    "wof:name":"Hardy",
    "wof:placetype":"neighbourhood",
    "wof:population":85,
    "zs:area_m":236608.551906,
    "zs:blockids":[
        400710012002194,
        400710012004069,
        400710012002263,
        400710012004081,
        400710012004067,
        400710012003116,
        400710012003177,
        400710012002192,
        400710012004042,
        400710012002189,
        400710012002188,
        400710012002261
    ],
    "zs:housing10":34,
    "zs:label":"Hardy",
    "zs:pop10":85
},
  "geometry": {"coordinates":[-97.053575,36.891865],"type":"Point"}
}