{
  "type": "Feature",
  "properties": {
    "iso:country":"US",
    "name:eng_x_preferred":[
        "Victoria Place"
    ],
    "wd:wordcount":275,
    "wof:name":"Victoria Place",
    "wof:placetype":"neighbourhood",
    "wof:population":180,
    "zs:area_m":303879.234118,
    "zs:blockids":[
        120530414011010,
        120530414011015,
        120530414011009,
        120530414011014,
        120530414011008
    ],
    "zs:housing10":71,
    "zs:label":"Victoria Place",
    "zs:pop10":180
},
  "geometry": {"coordinates":[-82.626136,28.456439],"type":"Point"}
}