{
  "type": "Feature",
  "properties": {
    "gn:admin1_code":"GA",
    "gn:admin2_code":"217",
    "gn:asciiname":"Shoal Creek",
    "gn:country_code":"US",
    "gn:dem":243,
    "gn:elevation":"237.0",
    "gn:feature_class":"P",
    "gn:feature_code":"PPL",
    "gn:name":"Shoal Creek",
    "gn:population":0,
    "gn:timezone":"America/New_York",
    "iso:country":"US",
    "name:ceb_x_preferred":[
        "Shoal Creek"
    ],
    "name:deu_x_preferred":[
        "Shoal Creek"
    ],
    "name:pol_x_preferred":[
        "Shoal Creek"
    ],
    "name:swe_x_preferred":[
        "Shoal Creek"
    ],
    "wof:name":"Shoal Creek",
    "wof:placetype":"locality"
},
  "geometry": {"coordinates":[-83.99574,33.5665],"type":"Point"}
}