{
  "type": "Feature",
  "properties": {
    "gn:admin1_code":"AR",
    "gn:admin2_code":"123.0",
    "gn:admin3_code":"90321.0",
    "gn:asciiname":"Bledsoe",
    "gn:country_code":"US",
    "gn:dem":60,
    "gn:elevation":"60.0",
    "gn:feature_class":"P",
    "gn:feature_code":"PPL",
    "gn:name":"Bledsoe",
    "gn:population":0,
    "gn:timezone":"America/Chicago",
    "iso:country":"US",
    "wof:name":"Bledsoe",
    "wof:placetype":"locality"
},
  "geometry": {"coordinates":[-90.52427,34.90537],"type":"Point"}
}