{
  "type": "Feature",
  "properties": {
    "gn:admin1_code":"NM",
    "gn:admin2_code":"49.0",
    "gn:asciiname":"Spiess",
    "gn:country_code":"US",
    "gn:dem":1944,
    "gn:elevation":"1946.0",
    "gn:feature_class":"P",
    "gn:feature_code":"PPL",
    "gn:name":"Spiess",
    "gn:population":0,
    "gn:timezone":"America/Denver",
    "iso:country":"US",
    "name:deu_x_preferred":[
        "Spie\u00df"
    ],
    "wof:name":"Spiess",
    "wof:placetype":"locality"
},
  "geometry": {"coordinates":[-105.90669,35.4592],"type":"Point"}
}