{
  "type": "Feature",
  "properties": {
    "iso:country":"US",
    "name:eng_x_preferred":[
        "Leavell Woods"
    ],
    "qs:gn_adm0_cc":"US",
    "qs:gn_fcode":"PPLX",
    "qs:gn_local":4431410,
    "qs:gn_nam_loc":"Jackson, Hinds, Mississippi, US",
    "qs:gn_namadm1":"MS",
    "qs:gn_name":"Leavell woods",
    "qs:local_max":1538,
    "qs:local_sum":8499,
    "qs:localhoods":30,
    "qs:name":"Leavell Woods",
    "qs:name_adm0":"United States",
    "qs:name_adm1":"Mississippi",
    "qs:name_adm2":"Hinds",
    "qs:name_local":"Jackson",
    "qs:photo_max":15,
    "qs:photo_sum":29,
    "qs:placetype":"Suburb",
    "qs:quad_count":5,
    "qs:woe_adm0":23424977,
    "qs:woe_adm1":2347583,
    "qs:woe_adm2":12588908,
    "qs:woe_lau":0,
    "qs:woe_local":2428184,
    "qs:woe_ver":"7.10.0",
    "wof:name":"Leavell Woods",
    "wof:placetype":"neighbourhood"
},
  "geometry": {"coordinates":[-90.214518,32.253097],"type":"Point"}
}