{
  "type": "Feature",
  "properties": {
    "gn:elevation":176,
    "iso:country":"US",
    "name:eng_x_preferred":[
        "Valdawood"
    ],
    "qs:gn_adm0_cc":"US",
    "qs:gn_fcode":"PPLX",
    "qs:gn_local":4049979,
    "qs:gn_nam_loc":"Birmingham, Jefferson, Alabama, US",
    "qs:gn_namadm1":"AL",
    "qs:gn_name":"Valdawood",
    "qs:local_max":5643,
    "qs:local_sum":38742,
    "qs:localhoods":77,
    "qs:name":"Valdawood",
    "qs:name_adm0":"United States",
    "qs:name_adm1":"Alabama",
    "qs:name_adm2":"Shelby",
    "qs:name_local":"Birmingham",
    "qs:photo_max":13,
    "qs:photo_sum":40,
    "qs:placetype":"Suburb",
    "qs:quad_count":9,
    "qs:woe_adm0":23424977,
    "qs:woe_adm1":2347559,
    "qs:woe_adm2":12587544,
    "qs:woe_lau":0,
    "qs:woe_local":2364559,
    "qs:woe_ver":"7.10.0",
    "wof:lang":[
        "eng"
    ],
    "wof:name":"Valdawood",
    "wof:placetype":"neighbourhood",
    "wof:population":3228,
    "zs:blockids":[
        11170303041032,
        11170303041002,
        11170303043038,
        11170303041016,
        11170303041026,
        11170303041010,
        11170303421055,
        11170303421054,
        11170303421086,
        11170303041022,
        11170303041014,
        11170303421061,
        11170303421045,
        11170303041021,
        11170303041023,
        11170303051007,
        11170303421062,
        11170303421089,
        11170303051002,
        11170303041006,
        11170303153003,
        11170303051003,
        11170303051008,
        11170303043041,
        11170303153000,
        11170303043036,
        11170303053028,
        11170303041009,
        11170303043035,
        11170303053016,
        11170303041020,
        11170303053037,
        11170303041007,
        11170303043033,
        11170303051004,
        11170303041015,
        11170303053027,
        11170303043026,
        11170303053036,
        11170303051006,
        11170303421063,
        11170303142004,
        11170303043037,
        11170303051009,
        11170303421060,
        11170303142007,
        11170303043043,
        11170303421046,
        11170303051000,
        11170303041018,
        11170303041005,
        11170303421058,
        11170303053014,
        11170303053029,
        11170303041012,
        11170303041030,
        11170303053030,
        11170303053015,
        11170303053033,
        11170303043040,
        11170303421057,
        11170303041031,
        11170303142005,
        11170303043032,
        11170303041013,
        11170303142006,
        11170303051005,
        11170303041028,
        11170303043044,
        11170303041027,
        11170303041029,
        11170303421059,
        11170303041025,
        11170303421041,
        11170303142040,
        11170303043034,
        11170303041017,
        11170303043017,
        11170303053032,
        11170303041024,
        11170303051001,
        11170303421056,
        11170303041019,
        11170303041004,
        11170303153002
    ],
    "zs:housing10":1305,
    "zs:pop10":3228
},
  "geometry": {"coordinates":[-86.76968100000001,33.358229],"type":"Point"}
}