{
  "type": "Feature",
  "properties": {
    "gn:admin1_code":"MT",
    "gn:admin2_code":"17.0",
    "gn:asciiname":"Bonfield",
    "gn:country_code":"US",
    "gn:dem":690,
    "gn:elevation":"692.0",
    "gn:feature_class":"P",
    "gn:feature_code":"PPL",
    "gn:name":"Bonfield",
    "gn:population":0,
    "gn:timezone":"America/Denver",
    "iso:country":"US",
    "name:ceb_x_preferred":[
        "Bonfield"
    ],
    "name:deu_x_preferred":[
        "Bonfield"
    ],
    "name:eng_x_preferred":[
        "Bonfield"
    ],
    "name:fra_x_preferred":[
        "Bonfield"
    ],
    "name:ita_x_preferred":[
        "Bonfield"
    ],
    "name:swe_x_preferred":[
        "Bonfield"
    ],
    "name:und_x_variant":[
        "Sheds Bridge"
    ],
    "wof:name":"Bonfield",
    "wof:placetype":"locality"
},
  "geometry": {"coordinates":[-105.57138,46.63278],"type":"Point"}
}