{
  "type": "Feature",
  "properties": {
    "gn:admin1_code":"ME",
    "gn:admin2_code":"11.0",
    "gn:admin3_code":"13470.0",
    "gn:asciiname":"Dixon Corner",
    "gn:country_code":"US",
    "gn:dem":107,
    "gn:elevation":"104.0",
    "gn:feature_class":"P",
    "gn:feature_code":"PPL",
    "gn:name":"Dixon Corner",
    "gn:population":0,
    "gn:timezone":"America/New_York",
    "iso:country":"US",
    "wof:name":"Dixon Corner",
    "wof:placetype":"locality"
},
  "geometry": {"coordinates":[-69.49338,44.71173],"type":"Point"}
}