{
  "type": "Feature",
  "properties": {
    "gn:admin1_code":"IN",
    "gn:admin2_code":"181.0",
    "gn:admin3_code":"77732.0",
    "gn:asciiname":"Gingrich Addition",
    "gn:country_code":"US",
    "gn:dem":202,
    "gn:elevation":"197.0",
    "gn:feature_class":"P",
    "gn:feature_code":"PPL",
    "gn:name":"Gingrich Addition",
    "gn:population":0,
    "gn:timezone":"America/Indiana/Indianapolis",
    "iso:country":"US",
    "wof:name":"Gingrich Addition",
    "wof:placetype":"locality"
},
  "geometry": {"coordinates":[-86.75418000000001,40.67393],"type":"Point"}
}