{
  "type": "Feature",
  "properties": {
    "gn:admin1_code":"NY",
    "gn:admin2_code":"95.0",
    "gn:admin3_code":"46855.0",
    "gn:asciiname":"Huntersland",
    "gn:country_code":"US",
    "gn:dem":364,
    "gn:elevation":"363.0",
    "gn:feature_class":"P",
    "gn:feature_code":"PPL",
    "gn:name":"Huntersland",
    "gn:population":0,
    "gn:timezone":"America/New_York",
    "iso:country":"US",
    "name:eng_x_preferred":[
        "Huntersland"
    ],
    "name:und_x_variant":[
        "Hunters Land",
        "Hunter's Land"
    ],
    "wof:name":"Huntersland",
    "wof:placetype":"locality"
},
  "geometry": {"coordinates":[-74.25958,42.57091],"type":"Point"}
}