{
  "type": "Feature",
  "properties": {
    "gn:admin1_code":"MN",
    "gn:admin2_code":"141.0",
    "gn:admin3_code":"18674.0",
    "gn:asciiname":"Lake Orono Estates",
    "gn:country_code":"US",
    "gn:dem":266,
    "gn:elevation":"269.0",
    "gn:feature_class":"P",
    "gn:feature_code":"PPL",
    "gn:name":"Lake Orono Estates",
    "gn:population":0,
    "gn:timezone":"America/Chicago",
    "iso:country":"US",
    "wof:name":"Lake Orono Estates",
    "wof:placetype":"locality"
},
  "geometry": {"coordinates":[-93.60278,45.30833],"type":"Point"}
}