{
  "type": "Feature",
  "properties": {
    "gn:admin1_code":"CO",
    "gn:admin2_code":"75.0",
    "gn:asciiname":"Twin Mills",
    "gn:country_code":"US",
    "gn:dem":1279,
    "gn:elevation":"1280.0",
    "gn:feature_class":"P",
    "gn:feature_code":"PPL",
    "gn:name":"Twin Mills",
    "gn:population":0,
    "gn:timezone":"America/Denver",
    "iso:country":"US",
    "wof:name":"Twin Mills",
    "wof:placetype":"locality"
},
  "geometry": {"coordinates":[-103.12632000000001,40.5736],"type":"Point"}
}