{
  "type": "Feature",
  "properties": {
    "gn:admin1_code":"PA",
    "gn:admin2_code":"107.0",
    "gn:admin3_code":"20880.0",
    "gn:asciiname":"Rauschs",
    "gn:country_code":"US",
    "gn:dem":167,
    "gn:elevation":"166.0",
    "gn:feature_class":"P",
    "gn:feature_code":"PPL",
    "gn:name":"Rauschs",
    "gn:population":0,
    "gn:timezone":"America/New_York",
    "iso:country":"US",
    "name:eng_x_preferred":[
        "Rauschs"
    ],
    "name:und_x_variant":[
        "Rausch"
    ],
    "wof:name":"Rauschs",
    "wof:placetype":"locality"
},
  "geometry": {"coordinates":[-75.99243,40.66454],"type":"Point"}
}