{
  "type": "Feature",
  "properties": {
    "gn:admin1_code":"VA",
    "gn:admin2_code":"41",
    "gn:asciiname":"Felipos Mobile Court",
    "gn:country_code":"US",
    "gn:dem":41,
    "gn:elevation":"37.0",
    "gn:feature_class":"P",
    "gn:feature_code":"PPL",
    "gn:name":"Felipos Mobile Court",
    "gn:population":0,
    "gn:timezone":"America/New_York",
    "iso:country":"US",
    "wof:name":"Felipos Mobile Court",
    "wof:placetype":"locality"
},
  "geometry": {"coordinates":[-77.42693,37.38682],"type":"Point"}
}