{
  "type": "Feature",
  "properties": {
    "iso:country":"US",
    "name:eng_x_preferred":[
        "The Plantation at Leesburg"
    ],
    "wof:name":"The Plantation at Leesburg",
    "wof:placetype":"neighbourhood",
    "wof:population":9,
    "zs:area_m":2198518.942132,
    "zs:blockids":[
        120690311012034,
        120690311012090,
        120690311012074,
        120690311012080,
        120690311012038,
        120690311012078,
        120690311012035
    ],
    "zs:housing10":6,
    "zs:label":"The Plantation at Leesburg",
    "zs:pop10":9
},
  "geometry": {"coordinates":[-81.890136,28.702869],"type":"Point"}
}