{
  "type": "Feature",
  "properties": {
    "gn:admin1_code":"FL",
    "gn:admin2_code":"73.0",
    "gn:asciiname":"Felkel",
    "gn:country_code":"US",
    "gn:dem":60,
    "gn:elevation":"46.0",
    "gn:feature_class":"P",
    "gn:feature_code":"PPL",
    "gn:name":"Felkel",
    "gn:population":0,
    "gn:timezone":"America/New_York",
    "iso:country":"US",
    "name:vol_x_preferred":[
        "Felkel"
    ],
    "name:zho_x_preferred":[
        "\u8cbb\u723e\u514b\u723e"
    ],
    "wof:name":"Felkel",
    "wof:placetype":"locality"
},
  "geometry": {"coordinates":[-84.11766999999998,30.59714],"type":"Point"}
}