{
  "type": "Feature",
  "properties": {
    "gn:admin1_code":"MO",
    "gn:admin2_code":"217.0",
    "gn:admin3_code":"14644.0",
    "gn:asciiname":"Portia",
    "gn:country_code":"US",
    "gn:dem":256,
    "gn:elevation":"254.0",
    "gn:feature_class":"P",
    "gn:feature_code":"PPL",
    "gn:name":"Portia",
    "gn:population":0,
    "gn:timezone":"America/Chicago",
    "iso:country":"US",
    "name:ces_x_preferred":[
        "Portia"
    ],
    "name:cym_x_preferred":[
        "Portia"
    ],
    "name:deu_x_preferred":[
        "Portia"
    ],
    "name:ita_x_preferred":[
        "Portia"
    ],
    "name:nds_x_preferred":[
        "Portia"
    ],
    "name:nld_x_preferred":[
        "Portia"
    ],
    "name:pol_x_preferred":[
        "Portia"
    ],
    "name:slv_x_preferred":[
        "Portia"
    ],
    "name:vie_x_preferred":[
        "Portia"
    ],
    "wof:name":"Portia",
    "wof:placetype":"locality"
},
  "geometry": {"coordinates":[-94.07494,37.90837],"type":"Point"}
}