{
  "type": "Feature",
  "properties": {
    "gn:admin1_code":"TN",
    "gn:admin2_code":"187",
    "gn:asciiname":"Owl Creek",
    "gn:country_code":"US",
    "gn:dem":172,
    "gn:elevation":"174.0",
    "gn:feature_class":"P",
    "gn:feature_code":"PPL",
    "gn:name":"Owl Creek",
    "gn:population":0,
    "gn:timezone":"America/Chicago",
    "iso:country":"US",
    "name:ceb_x_preferred":[
        "Owl Creek"
    ],
    "name:rus_x_preferred":[
        "\u041e\u0443\u043b-\u041a\u0440\u0438\u043a"
    ],
    "name:swe_x_preferred":[
        "Owl Creek"
    ],
    "name:vol_x_preferred":[
        "Owl Creek"
    ],
    "wof:name":"Owl Creek",
    "wof:placetype":"locality"
},
  "geometry": {"coordinates":[-86.70278,35.99784000000001],"type":"Point"}
}