{
  "type": "Feature",
  "properties": {
    "gn:admin1_code":"NC",
    "gn:admin2_code":"195.0",
    "gn:admin3_code":"91208.0",
    "gn:asciiname":"Pine Tree",
    "gn:country_code":"US",
    "gn:dem":37,
    "gn:elevation":"36.0",
    "gn:feature_class":"P",
    "gn:feature_code":"PPL",
    "gn:name":"Pine Tree",
    "gn:population":0,
    "gn:timezone":"America/New_York",
    "iso:country":"US",
    "wof:name":"Pine Tree",
    "wof:placetype":"locality"
},
  "geometry": {"coordinates":[-77.79526,35.74044],"type":"Point"}
}