{
  "type": "Feature",
  "properties": {
    "gn:admin1_code":"TN",
    "gn:admin2_code":"143",
    "gn:asciiname":"Evensville",
    "gn:country_code":"US",
    "gn:dem":234,
    "gn:elevation":"235.0",
    "gn:feature_class":"P",
    "gn:feature_code":"PPL",
    "gn:name":"Evensville",
    "gn:population":0,
    "gn:timezone":"America/New_York",
    "iso:country":"US",
    "name:eng_x_preferred":[
        "Evensville"
    ],
    "name:und_x_variant":[
        "Evansville",
        "Darwin"
    ],
    "wof:name":"Evensville",
    "wof:placetype":"locality"
},
  "geometry": {"coordinates":[-84.95466999999999,35.56451],"type":"Point"}
}