{
  "type": "Feature",
  "properties": {
    "iso:country":"US",
    "name:eng_x_preferred":[
        "Glyn Terrace"
    ],
    "wof:name":"Glyn Terrace",
    "wof:placetype":"neighbourhood",
    "wof:population":488,
    "zs:area_m":1616074.858842,
    "zs:blockids":[
        450190031111026,
        450190031111094,
        450190031112003,
        450190031111035,
        450190031112008,
        450190031112029
    ],
    "zs:housing10":206,
    "zs:label":"Glyn Terrace",
    "zs:pop10":488
},
  "geometry": {"coordinates":[-80.04428,32.869549],"type":"Point"}
}