{
  "type": "Feature",
  "properties": {
    "gn:admin1_code":"KY",
    "gn:admin2_code":"85",
    "gn:asciiname":"Rock Creek",
    "gn:country_code":"US",
    "gn:dem":201,
    "gn:elevation":"196.0",
    "gn:feature_class":"P",
    "gn:feature_code":"PPL",
    "gn:name":"Rock Creek",
    "gn:population":0,
    "gn:timezone":"America/Chicago",
    "iso:country":"US",
    "name:cat_x_preferred":[
        "Rock Creek"
    ],
    "name:ceb_x_preferred":[
        "Rock Creek"
    ],
    "name:deu_x_preferred":[
        "Rock Creek"
    ],
    "name:ita_x_preferred":[
        "Rock Creek"
    ],
    "name:nld_x_preferred":[
        "Rock Creek"
    ],
    "name:pol_x_preferred":[
        "Rock Creek"
    ],
    "name:por_x_preferred":[
        "Rock Creek"
    ],
    "name:spa_x_preferred":[
        "Rock Creek"
    ],
    "name:srp_x_preferred":[
        "\u0420\u043e\u043a \u041a\u0440\u0438\u043a"
    ],
    "name:swe_x_preferred":[
        "Rock Creek"
    ],
    "name:vol_x_preferred":[
        "Rock Creek"
    ],
    "wof:name":"Rock Creek",
    "wof:placetype":"locality"
},
  "geometry": {"coordinates":[-86.15803000000002,37.432],"type":"Point"}
}