{
  "type": "Feature",
  "properties": {
    "iso:country":"US",
    "name:eng_x_preferred":[
        "East Auburn"
    ],
    "qs:gn_adm0_cc":"US",
    "qs:gn_local":5785965,
    "qs:gn_nam_loc":"Auburn, King, Washington, US",
    "qs:gn_namadm1":"WA",
    "qs:local_max":2391,
    "qs:local_sum":7266,
    "qs:localhoods":14,
    "qs:name":"East Auburn",
    "qs:name_adm0":"United States",
    "qs:name_adm1":"Washington",
    "qs:name_adm2":"King",
    "qs:name_local":"Auburn",
    "qs:photo_max":586,
    "qs:photo_sum":2391,
    "qs:placetype":"Suburb",
    "qs:quad_count":27,
    "qs:woe_adm0":23424977,
    "qs:woe_adm1":2347606,
    "qs:woe_adm2":12590456,
    "qs:woe_lau":0,
    "qs:woe_local":2357286,
    "qs:woe_ver":"7.10.0",
    "wof:lang":[
        "eng"
    ],
    "wof:name":"East Auburn",
    "wof:placetype":"neighbourhood",
    "wof:population":4629,
    "zs:blockids":[
        530330312045003,
        530330312044018,
        530330312045000,
        530330312045004,
        530330312045001,
        530330312044006,
        530330312042002,
        530330312041001,
        530330312041015,
        530330312041017,
        530330312042004,
        530330316012010,
        530330312045007,
        530330312044012,
        530330312041013,
        530330312044005,
        530330312041018,
        530330316012021,
        530330312044014,
        530330312044009,
        530330316012011,
        530330312045002,
        530330312041012,
        530330312041019,
        530330312042000,
        530330312042001,
        530330312044011,
        530330312044017,
        530330312044010,
        530330316012014,
        530330312044008,
        530330316012012,
        530330312041002,
        530330312044007,
        530330316012025,
        530330312041016,
        530330312044013,
        530330316012016,
        530330312041000,
        530330316012017,
        530330312041024,
        530330316012015,
        530330312045005,
        530330316012019,
        530330312041026,
        530330312044004,
        530330312042003,
        530330312044015,
        530330312045006,
        530330312041011,
        530330312044000,
        530330316012024,
        530330316012020,
        530330316012018,
        530330312044016,
        530330312045008
    ],
    "zs:housing10":1754,
    "zs:pop10":4629
},
  "geometry": {"coordinates":[-122.142601,47.32036],"type":"Point"}
}