{
  "type": "Feature",
  "properties": {
    "gn:admin1_code":"MD",
    "gn:admin2_code":"13.0",
    "gn:asciiname":"Bird Hill Estates",
    "gn:country_code":"US",
    "gn:dem":221,
    "gn:elevation":"222.0",
    "gn:feature_class":"P",
    "gn:feature_code":"PPL",
    "gn:name":"Bird Hill Estates",
    "gn:population":0,
    "gn:timezone":"America/New_York",
    "iso:country":"US",
    "wof:name":"Bird Hill Estates",
    "wof:placetype":"locality"
},
  "geometry": {"coordinates":[-76.95941999999999,39.48677],"type":"Point"}
}