{
  "type": "Feature",
  "properties": {
    "iso:country":"US",
    "name:eng_x_preferred":[
        "Hills"
    ],
    "wof:name":"Hills",
    "wof:placetype":"neighbourhood",
    "wof:population":1207,
    "zs:area_m":1288791.277838,
    "zs:blockids":[
        51430111014031,
        51430101044026,
        51430101044011,
        51430111014034,
        51430101044027,
        51430111014023,
        51430111014022,
        51430111014016,
        51430111014032,
        51430111023008,
        51430111023009,
        51430111014033,
        51430111014014,
        51430111014013,
        51430111014015,
        51430111014024
    ],
    "zs:housing10":672,
    "zs:label":"Hills",
    "zs:pop10":1207
},
  "geometry": {"coordinates":[-94.15003299999999,36.051818],"type":"Point"}
}