{
  "type": "Feature",
  "properties": {
    "gn:admin1_code":"PA",
    "gn:admin2_code":"81.0",
    "gn:admin3_code":"56608.0",
    "gn:asciiname":"Fairlawn",
    "gn:country_code":"US",
    "gn:dem":172,
    "gn:elevation":"174.0",
    "gn:feature_class":"P",
    "gn:feature_code":"PPL",
    "gn:name":"Fairlawn",
    "gn:population":0,
    "gn:timezone":"America/New_York",
    "iso:country":"US",
    "name:ceb_x_preferred":[
        "Fairlawn"
    ],
    "name:deu_x_preferred":[
        "Fairlawn"
    ],
    "name:ita_x_preferred":[
        "Fairlawn"
    ],
    "name:nld_x_preferred":[
        "Fairlawn"
    ],
    "name:srp_x_preferred":[
        "\u0424\u0435\u0440\u043b\u043e\u043d"
    ],
    "name:vol_x_preferred":[
        "Fairlawn"
    ],
    "wof:name":"Fairlawn",
    "wof:placetype":"locality"
},
  "geometry": {"coordinates":[-77.06191,41.29285],"type":"Point"}
}