{
  "type": "Feature",
  "properties": {
    "gn:admin1_code":"OH",
    "gn:admin2_code":"121",
    "gn:admin3_code":"25438.0",
    "gn:asciiname":"Fulda",
    "gn:country_code":"US",
    "gn:dem":349,
    "gn:elevation":"353.0",
    "gn:feature_class":"P",
    "gn:feature_code":"PPL",
    "gn:name":"Fulda",
    "gn:population":0,
    "gn:timezone":"America/New_York",
    "iso:country":"US",
    "name:eng_x_preferred":[
        "Fulda"
    ],
    "name:und_x_variant":[
        "Fuldah",
        "Folda",
        "Enoch"
    ],
    "wof:name":"Fulda",
    "wof:placetype":"locality"
},
  "geometry": {"coordinates":[-81.41568000000002,39.72452],"type":"Point"}
}