{
  "type": "Feature",
  "properties": {
    "gn:admin1_code":"MO",
    "gn:admin2_code":"147.0",
    "gn:admin3_code":"35036.0",
    "gn:asciiname":"Orrsburg",
    "gn:country_code":"US",
    "gn:dem":355,
    "gn:elevation":"352.0",
    "gn:feature_class":"P",
    "gn:feature_code":"PPL",
    "gn:name":"Orrsburg",
    "gn:population":0,
    "gn:timezone":"America/Chicago",
    "iso:country":"US",
    "wof:name":"Orrsburg",
    "wof:placetype":"locality"
},
  "geometry": {"coordinates":[-94.72136,40.43082],"type":"Point"}
}