{
  "type": "Feature",
  "properties": {
    "gn:admin1_code":"WA",
    "gn:admin2_code":"53.0",
    "gn:asciiname":"Rancho Villa Mobile Home Park",
    "gn:country_code":"US",
    "gn:dem":81,
    "gn:elevation":"86.0",
    "gn:feature_class":"P",
    "gn:feature_code":"PPL",
    "gn:name":"Rancho Villa Mobile Home Park",
    "gn:population":0,
    "gn:timezone":"America/Los_Angeles",
    "iso:country":"US",
    "wof:name":"Rancho Villa Mobile Home Park",
    "wof:placetype":"campus"
},
  "geometry": {"coordinates":[-122.4961,47.16342],"type":"Point"}
}