{
  "type": "Feature",
  "properties": {
    "iso:country":"US",
    "name:eng_x_preferred":[
        "Sunshine Place"
    ],
    "wof:name":"Sunshine Place",
    "wof:placetype":"neighbourhood",
    "wof:population":1192,
    "zs:area_m":2843298.389708,
    "zs:blockids":[
        120690309131048,
        120690309131036,
        120690309131042,
        120690309142007,
        120690309131040,
        120690309142006,
        120690309121036,
        120690309122000,
        120690309122008,
        120690309122018,
        120690309131045,
        120690309131044,
        120690309131035,
        120690309142004,
        120690309131041,
        120690309122017,
        120690309122025,
        120690309131043,
        120690309131038,
        120690309131032,
        120690309122023,
        120690309122021,
        120690309122032,
        120690309131030,
        120690309131028,
        120690309131027,
        120690309121027,
        120690309131034,
        120690309131046,
        120690309142003,
        120690309142010,
        120690309131062,
        120690309131049,
        120690309131047,
        120690309142001,
        120690309122007,
        120690309131039,
        120690309131029,
        120690309131033,
        120690309142005,
        120690309142008,
        120690309122020
    ],
    "zs:housing10":633,
    "zs:label":"Sunshine Place",
    "zs:pop10":1192
},
  "geometry": {"coordinates":[-81.657479,28.815225],"type":"Point"}
}