{
  "type": "Feature",
  "properties": {
    "gn:country":"US",
    "gn:fcode":"PPL",
    "gn:population":0,
    "iso:country":"US",
    "name:eng_x_preferred":[
        "Bitterwater"
    ],
    "name:fra_x_preferred":[
        "Bitterwater"
    ],
    "name:tur_x_preferred":[
        "Bitterwater"
    ],
    "name:und_x_variant":[
        "Bitter Water"
    ],
    "name:zho_x_preferred":[
        "\u6bd4\u7279\u6c83\u7279"
    ],
    "qs_pg:aaroncc":"US",
    "qs_pg:gn_country":"US",
    "qs_pg:gn_fcode":"PPL",
    "qs_pg:gn_pop":0,
    "qs_pg:name":"Bitterwater",
    "qs_pg:name_adm0":"United States",
    "qs_pg:name_adm1":"California",
    "qs_pg:photos":43,
    "qs_pg:photos_1k":9,
    "qs_pg:photos_9k":1,
    "qs_pg:photos_9r":2,
    "qs_pg:photos_all":43,
    "qs_pg:photos_sr":2,
    "qs_pg:pop_sr":0,
    "qs_pg:qs_pg_placetype":"locality",
    "qs_pg:qs_pg_placetype_gp":"Town",
    "qs_pg:woe_adm0":23424977,
    "woe:adm0_id":23424977,
    "woe:name_adm0":"United States",
    "woe:name_adm1":"California",
    "woe:placetype":"Town",
    "wof:name":"Bitterwater",
    "wof:placetype":"locality"
},
  "geometry": {"coordinates":[-121.00269,36.38024],"type":"Point"}
}