{
  "type": "Feature",
  "properties": {
    "iso:country":"US",
    "name:ara_x_preferred":[
        "\u0643\u0627\u0645\u064a\u0631\u0648\u0646"
    ],
    "name:bel_x_preferred":[
        "\u041a\u044d\u043c\u0435\u0440\u0430\u043d"
    ],
    "name:cat_x_preferred":[
        "Cameron"
    ],
    "name:ceb_x_preferred":[
        "Cameron"
    ],
    "name:ces_x_preferred":[
        "Cameron"
    ],
    "name:dan_x_preferred":[
        "Cameron"
    ],
    "name:deu_x_preferred":[
        "Cameron"
    ],
    "name:ell_x_preferred":[
        "\u039a\u03ac\u03bc\u03b5\u03c1\u03bf\u03bd"
    ],
    "name:eng_x_preferred":[
        "Cameron"
    ],
    "name:fra_x_preferred":[
        "Cameron"
    ],
    "name:heb_x_preferred":[
        "\u05e7\u05de\u05e8\u05d5\u05df"
    ],
    "name:hun_x_preferred":[
        "Cameron"
    ],
    "name:ita_x_preferred":[
        "Cameron"
    ],
    "name:jpn_x_preferred":[
        "\u30ad\u30e3\u30e1\u30ed\u30f3"
    ],
    "name:kor_x_preferred":[
        "\uce90\uba38\ub7f0"
    ],
    "name:lav_x_preferred":[
        "Kemerons"
    ],
    "name:nld_x_preferred":[
        "Cameron"
    ],
    "name:pol_x_preferred":[
        "Cameron"
    ],
    "name:por_x_preferred":[
        "Cameron"
    ],
    "name:ron_x_preferred":[
        "Cameron"
    ],
    "name:rus_x_preferred":[
        "\u041a\u0430\u043c\u0435\u0440\u043e\u043d"
    ],
    "name:spa_x_preferred":[
        "Cameron"
    ],
    "name:srp_x_preferred":[
        "\u041a\u0430\u043c\u0435\u0440\u043e\u043d"
    ],
    "name:swe_x_preferred":[
        "Cameron"
    ],
    "name:tha_x_preferred":[
        "\u0e04\u0e32\u0e40\u0e21\u0e23\u0e2d\u0e19"
    ],
    "name:ukr_x_preferred":[
        "\u041a\u0430\u043c\u0435\u0440\u043e\u043d"
    ],
    "name:urd_x_preferred":[
        "\u06a9\u06cc\u0645\u0631\u0648\u0646"
    ],
    "name:vol_x_preferred":[
        "Cameron"
    ],
    "qs:gn_adm0_cc":"US",
    "qs:gn_fcode":"PPL",
    "qs:gn_local":5206769,
    "qs:gn_nam_loc":"Point, Northumberland, Pennsylvania, US",
    "qs:gn_namadm1":"PA",
    "qs:gn_name":"Cameron",
    "qs:local_max":95,
    "qs:local_sum":95,
    "qs:localhoods":1,
    "qs:name":"Cameron",
    "qs:name_adm0":"United States",
    "qs:name_adm1":"Pennsylvania",
    "qs:name_adm2":"Northumberland",
    "qs:name_local":"Point",
    "qs:photo_max":95,
    "qs:photo_sum":95,
    "qs:placetype":"Suburb",
    "qs:quad_count":1,
    "qs:woe_adm0":23424977,
    "qs:woe_adm1":2347597,
    "qs:woe_adm2":12589776,
    "qs:woe_lau":0,
    "qs:woe_local":28745280,
    "qs:woe_ver":"7.10.0",
    "wof:lang":[
        "eng"
    ],
    "wof:name":"Cameron",
    "wof:placetype":"neighbourhood"
},
  "geometry": {"coordinates":[-76.70517,40.935303],"type":"Point"}
}