{
  "type": "Feature",
  "properties": {
    "gn:admin1_code":"VA",
    "gn:admin2_code":"179.0",
    "gn:asciiname":"Aqua Villa",
    "gn:country_code":"US",
    "gn:dem":18,
    "gn:elevation":"20.0",
    "gn:feature_class":"P",
    "gn:feature_code":"PPL",
    "gn:name":"Aqua Villa",
    "gn:population":0,
    "gn:timezone":"America/New_York",
    "iso:country":"US",
    "wof:name":"Aqua Villa",
    "wof:placetype":"locality"
},
  "geometry": {"coordinates":[-77.3717,38.4313],"type":"Point"}
}