{
  "type": "Feature",
  "properties": {
    "gn:admin1_code":"DE",
    "gn:admin2_code":"1.0",
    "gn:asciiname":"Bay View Heights",
    "gn:country_code":"US",
    "gn:dem":1,
    "gn:elevation":"1.0",
    "gn:feature_class":"P",
    "gn:feature_code":"PPL",
    "gn:name":"Bay View Heights",
    "gn:population":0,
    "gn:timezone":"America/New_York",
    "iso:country":"US",
    "wof:name":"Bay View Heights",
    "wof:placetype":"locality"
},
  "geometry": {"coordinates":[-75.40158000000002,39.05483],"type":"Point"}
}