{
  "type": "Feature",
  "properties": {
    "iso:country":"US",
    "name:eng_x_preferred":[
        "Carol Oaks"
    ],
    "wof:name":"Carol Oaks",
    "wof:placetype":"neighbourhood",
    "wof:population":2509,
    "zs:area_m":951504.508283,
    "zs:blockids":[
        484391065121005,
        484391065144037,
        484391065121013,
        484391065122005,
        484391065121003,
        484391065122013,
        484391065121012,
        484391065121014,
        484391065121004,
        484391065123000,
        484391065122010,
        484391065123002,
        484391065122006,
        484391065123009,
        484391065121017,
        484391065123012,
        484391065122009,
        484391065122003,
        484391065121006,
        484391065123011,
        484391065122012,
        484391065121015,
        484391065121011,
        484391065123004,
        484391065122011,
        484391065122004
    ],
    "zs:housing10":1236,
    "zs:label":"Carol Oaks",
    "zs:pop10":2509
},
  "geometry": {"coordinates":[-97.19125099999999,32.755148],"type":"Point"}
}