{
  "type": "Feature",
  "properties": {
    "iso:country":"US",
    "name:ceb_x_preferred":[
        "Grace"
    ],
    "name:deu_x_preferred":[
        "Grace"
    ],
    "name:eng_x_preferred":[
        "Grace"
    ],
    "name:est_x_preferred":[
        "Grace"
    ],
    "name:fin_x_preferred":[
        "Grace"
    ],
    "name:fra_x_preferred":[
        "Grace"
    ],
    "name:ita_x_preferred":[
        "Grace"
    ],
    "name:jpn_x_preferred":[
        "\u30b0\u30ec\u30fc\u30b9"
    ],
    "name:kor_x_preferred":[
        "\uadf8\ub808\uc774\uc2a4"
    ],
    "name:nld_x_preferred":[
        "Grace"
    ],
    "name:pol_x_preferred":[
        "Grace"
    ],
    "name:por_x_preferred":[
        "Grace"
    ],
    "name:rus_x_preferred":[
        "\u0413\u0440\u0435\u0439\u0441"
    ],
    "name:spa_x_preferred":[
        "Grace"
    ],
    "name:swe_x_preferred":[
        "Grace"
    ],
    "name:ukr_x_preferred":[
        "\u0413\u0440\u0435\u0439\u0441"
    ],
    "name:vie_x_preferred":[
        "Grace"
    ],
    "name:vol_x_preferred":[
        "Grace"
    ],
    "name:zho_x_preferred":[
        "Grace"
    ],
    "wd:wordcount":609,
    "wof:name":"Grace",
    "wof:placetype":"neighbourhood",
    "wof:population":270,
    "zs:area_m":2803354.777702,
    "zs:blockids":[
        261635667002016,
        261635667002014,
        261635667002013,
        261635667002017,
        261635667002019,
        261635858001000,
        261635858001002,
        261635667002015,
        261635858002001
    ],
    "zs:housing10":128,
    "zs:label":"Grace",
    "zs:pop10":270
},
  "geometry": {"coordinates":[-83.405974,42.270495],"type":"Point"}
}