{
  "type": "Feature",
  "properties": {
    "gn:admin1_code":"TN",
    "gn:admin2_code":"163",
    "gn:asciiname":"Harrtown",
    "gn:country_code":"US",
    "gn:dem":511,
    "gn:elevation":"508.0",
    "gn:feature_class":"P",
    "gn:feature_code":"PPL",
    "gn:name":"Harrtown",
    "gn:population":0,
    "gn:timezone":"America/New_York",
    "iso:country":"US",
    "wof:name":"Harrtown",
    "wof:placetype":"locality"
},
  "geometry": {"coordinates":[-82.38598,36.56066],"type":"Point"}
}