{
  "type": "Feature",
  "properties": {
    "gn:admin1_code":"GA",
    "gn:admin2_code":"27.0",
    "gn:asciiname":"Nankin",
    "gn:country_code":"US",
    "gn:dem":63,
    "gn:elevation":"60.0",
    "gn:feature_class":"P",
    "gn:feature_code":"PPL",
    "gn:name":"Nankin",
    "gn:population":0,
    "gn:timezone":"America/New_York",
    "iso:country":"US",
    "wof:name":"Nankin",
    "wof:placetype":"locality"
},
  "geometry": {"coordinates":[-83.46793000000002,30.66604],"type":"Point"}
}