{
  "type": "Feature",
  "properties": {
    "gn:admin1_code":"PA",
    "gn:admin2_code":"121.0",
    "gn:admin3_code":"16944.0",
    "gn:asciiname":"Hill City",
    "gn:country_code":"US",
    "gn:dem":432,
    "gn:elevation":"431.0",
    "gn:feature_class":"P",
    "gn:feature_code":"PPL",
    "gn:name":"Hill City",
    "gn:population":0,
    "gn:timezone":"America/New_York",
    "iso:country":"US",
    "name:ceb_x_preferred":[
        "Hill City"
    ],
    "name:deu_x_preferred":[
        "Hill City"
    ],
    "name:ita_x_preferred":[
        "Hill City"
    ],
    "name:nld_x_preferred":[
        "Hill City"
    ],
    "name:pol_x_preferred":[
        "Hill City"
    ],
    "name:por_x_preferred":[
        "Hill City"
    ],
    "name:spa_x_preferred":[
        "Hill City"
    ],
    "name:srp_x_preferred":[
        "\u0425\u0438\u043b \u0421\u0438\u0442\u0438"
    ],
    "name:swe_x_preferred":[
        "Hill City"
    ],
    "name:ukr_x_preferred":[
        "\u0413\u0456\u043b\u043b-\u0421\u0456\u0442\u0456"
    ],
    "name:vol_x_preferred":[
        "Hill City"
    ],
    "name:zho_x_preferred":[
        "\u5e0c\u5c14\u57ce"
    ],
    "wof:name":"Hill City",
    "wof:placetype":"locality"
},
  "geometry": {"coordinates":[-79.64505,41.35367],"type":"Point"}
}