{
  "type": "Feature",
  "properties": {
    "gn:admin1_code":"OH",
    "gn:admin2_code":"81.0",
    "gn:admin3_code":"82698.0",
    "gn:asciiname":"Salt Run",
    "gn:country_code":"US",
    "gn:dem":220,
    "gn:elevation":"218.0",
    "gn:feature_class":"P",
    "gn:feature_code":"PPL",
    "gn:name":"Salt Run",
    "gn:population":0,
    "gn:timezone":"America/New_York",
    "iso:country":"US",
    "wof:name":"Salt Run",
    "wof:placetype":"locality"
},
  "geometry": {"coordinates":[-80.66313000000002,40.24924],"type":"Point"}
}