{
  "type": "Feature",
  "properties": {
    "gn:admin1_code":"GA",
    "gn:admin2_code":"113.0",
    "gn:asciiname":"Briarwood Park",
    "gn:country_code":"US",
    "gn:dem":271,
    "gn:elevation":"263.0",
    "gn:feature_class":"P",
    "gn:feature_code":"PPL",
    "gn:name":"Briarwood Park",
    "gn:population":0,
    "gn:timezone":"America/New_York",
    "iso:country":"US",
    "wof:name":"Briarwood Park",
    "wof:placetype":"locality"
},
  "geometry": {"coordinates":[-84.41965,33.43817],"type":"Point"}
}