{
  "type": "Feature",
  "properties": {
    "gn:admin1_code":"CA",
    "gn:admin2_code":"109.0",
    "gn:asciiname":"Scenic Heights",
    "gn:country_code":"US",
    "gn:dem":1006,
    "gn:elevation":"1016.0",
    "gn:feature_class":"P",
    "gn:feature_code":"PPL",
    "gn:name":"Scenic Heights",
    "gn:population":0,
    "gn:timezone":"America/Los_Angeles",
    "iso:country":"US",
    "wof:name":"Scenic Heights",
    "wof:placetype":"locality"
},
  "geometry": {"coordinates":[-120.25658,38.01659],"type":"Point"}
}