{
  "type": "Feature",
  "properties": {
    "gn:admin1_code":"MS",
    "gn:admin2_code":"49.0",
    "gn:asciiname":"Bear Creek",
    "gn:country_code":"US",
    "gn:dem":96,
    "gn:elevation":"91.0",
    "gn:feature_class":"P",
    "gn:feature_code":"PPL",
    "gn:name":"Bear Creek",
    "gn:population":0,
    "gn:timezone":"America/Chicago",
    "iso:country":"US",
    "name:cat_x_preferred":[
        "Bear Creek"
    ],
    "name:deu_x_preferred":[
        "Bear Creek"
    ],
    "name:eng_x_preferred":[
        "Bear Creek"
    ],
    "name:fra_x_preferred":[
        "Bear Creek"
    ],
    "name:ido_x_preferred":[
        "Bear Creek"
    ],
    "name:ita_x_preferred":[
        "Bear Creek"
    ],
    "name:nld_x_preferred":[
        "Bear Creek"
    ],
    "name:pol_x_preferred":[
        "Bear Creek"
    ],
    "name:por_x_preferred":[
        "Bear Creek"
    ],
    "name:rus_x_preferred":[
        "\u0411\u044d\u0440-\u041a\u0440\u0438\u043a"
    ],
    "name:spa_x_preferred":[
        "Bear Creek"
    ],
    "name:srp_x_preferred":[
        "\u0411\u0435\u0440 \u041a\u0440\u0438\u043a"
    ],
    "name:swe_x_preferred":[
        "Bear Creek"
    ],
    "name:ukr_x_preferred":[
        "\u0411\u0435\u0440-\u041a\u0440\u0456\u043a"
    ],
    "name:und_x_variant":[
        "Bear Creek Church Community"
    ],
    "name:urd_x_preferred":[
        "\u0628\u0626\u06cc\u0631 \u06a9\u0631\u06cc\u06a9"
    ],
    "name:vol_x_preferred":[
        "Bear Creek"
    ],
    "wof:name":"Bear Creek",
    "wof:placetype":"locality"
},
  "geometry": {"coordinates":[-90.51954000000001,32.06377],"type":"Point"}
}