{
  "type": "Feature",
  "properties": {
    "gn:admin1_code":"NY",
    "gn:admin2_code":"103.0",
    "gn:admin3_code":"69463.0",
    "gn:asciiname":"Cedar Beach",
    "gn:country_code":"US",
    "gn:dem":6,
    "gn:elevation":"3.0",
    "gn:feature_class":"P",
    "gn:feature_code":"PPL",
    "gn:name":"Cedar Beach",
    "gn:population":0,
    "gn:timezone":"America/New_York",
    "iso:country":"US",
    "name:ceb_x_preferred":[
        "Cedar Beach"
    ],
    "name:deu_x_preferred":[
        "Cedar Beach"
    ],
    "name:swe_x_preferred":[
        "Cedar Beach"
    ],
    "wof:name":"Cedar Beach",
    "wof:placetype":"locality"
},
  "geometry": {"coordinates":[-72.39806,41.0325],"type":"Point"}
}