{
  "type": "Feature",
  "properties": {
    "gn:country":"US",
    "gn:fcode":"PPL",
    "gn:population":0,
    "iso:country":"US",
    "name:azb_x_preferred":[
        "\u0627\u0648\u0633\u06a9"
    ],
    "name:cym_x_preferred":[
        "Usk"
    ],
    "name:eng_x_preferred":[
        "Usk"
    ],
    "name:fas_x_preferred":[
        "\u0627\u0648\u0633\u06a9 \u0648\u0627\u0634\u06cc\u0646\u06af\u062a\u0646"
    ],
    "name:fra_x_preferred":[
        "Usk"
    ],
    "name:hun_x_preferred":[
        "Usk"
    ],
    "name:por_x_preferred":[
        "Usk"
    ],
    "qs_pg:aaroncc":"US",
    "qs_pg:gn_country":"US",
    "qs_pg:gn_fcode":"PPL",
    "qs_pg:gn_pop":0,
    "qs_pg:name":"Usk",
    "qs_pg:name_adm0":"United States",
    "qs_pg:name_adm1":"Washington",
    "qs_pg:photos":71,
    "qs_pg:photos_1k":14,
    "qs_pg:photos_9k":1,
    "qs_pg:photos_9r":2,
    "qs_pg:photos_all":71,
    "qs_pg:photos_sr":2,
    "qs_pg:pop_sr":5,
    "qs_pg:qs_pg_placetype":"locality",
    "qs_pg:qs_pg_placetype_gp":"Town",
    "qs_pg:woe_adm0":23424977,
    "woe:adm0_id":23424977,
    "woe:name_adm0":"United States",
    "woe:name_adm1":"Washington",
    "woe:placetype":"Town",
    "wof:name":"Usk",
    "wof:placetype":"locality"
},
  "geometry": {"coordinates":[-117.27966000000001,48.31379],"type":"Point"}
}