{
  "type": "Feature",
  "properties": {
    "gn:admin1_code":"GA",
    "gn:admin2_code":"127.0",
    "gn:asciiname":"Benedict",
    "gn:country_code":"US",
    "gn:dem":17,
    "gn:elevation":"5.0",
    "gn:feature_class":"P",
    "gn:feature_code":"PPL",
    "gn:name":"Benedict",
    "gn:population":0,
    "gn:timezone":"America/New_York",
    "iso:country":"US",
    "name:ceb_x_preferred":[
        "Benedict"
    ],
    "name:deu_x_preferred":[
        "Benedict"
    ],
    "name:ell_x_preferred":[
        "\u0392\u03b5\u03bd\u03ad\u03b4\u03b9\u03ba\u03c4\u03bf\u03c2"
    ],
    "name:fas_x_preferred":[
        "\u0628\u0646\u062f\u06cc\u06a9\u062a"
    ],
    "name:fra_x_preferred":[
        "Benedict"
    ],
    "name:glg_x_preferred":[
        "Benedict"
    ],
    "name:heb_x_preferred":[
        "\u05d1\u05e0\u05d3\u05d9\u05e7\u05d8"
    ],
    "name:ita_x_preferred":[
        "Benedetto#Persone"
    ],
    "name:jpn_x_preferred":[
        "\u30d9\u30cd\u30c7\u30a3\u30af\u30c8"
    ],
    "name:kor_x_preferred":[
        "\ubca0\ub124\ub515\ud2b8"
    ],
    "name:nld_x_preferred":[
        "Benedict"
    ],
    "name:nor_x_preferred":[
        "Benedikt#Se ogs\u00e5"
    ],
    "name:pol_x_preferred":[
        "Benedict"
    ],
    "name:por_x_preferred":[
        "Benedict"
    ],
    "name:ron_x_preferred":[
        "Benedict"
    ],
    "name:slk_x_preferred":[
        "Benedikt#Nositelia mena"
    ],
    "name:swe_x_preferred":[
        "Benedict"
    ],
    "name:ukr_x_preferred":[
        "\u0411\u0435\u043d\u0435\u0434\u0438\u043a\u0442"
    ],
    "name:vol_x_preferred":[
        "Benedict"
    ],
    "wof:name":"Benedict",
    "wof:placetype":"locality"
},
  "geometry": {"coordinates":[-81.50149,31.21606],"type":"Point"}
}