{
  "type": "Feature",
  "properties": {
    "gn:admin1_code":"NC",
    "gn:admin2_code":"31",
    "gn:admin3_code":"92272.0",
    "gn:asciiname":"Thornes Farm Trailer Park",
    "gn:country_code":"US",
    "gn:dem":7,
    "gn:elevation":"1.0",
    "gn:feature_class":"P",
    "gn:feature_code":"PPL",
    "gn:name":"Thornes Farm Trailer Park",
    "gn:population":0,
    "gn:timezone":"America/New_York",
    "iso:country":"US",
    "wof:name":"Thornes Farm Trailer Park",
    "wof:placetype":"campus"
},
  "geometry": {"coordinates":[-76.89157,34.79107],"type":"Point"}
}