{
  "type": "Feature",
  "properties": {
    "gn:admin1_code":"TX",
    "gn:admin2_code":"457.0",
    "gn:asciiname":"Oldham",
    "gn:country_code":"US",
    "gn:dem":66,
    "gn:elevation":"62.0",
    "gn:feature_class":"P",
    "gn:feature_code":"PPL",
    "gn:name":"Oldham",
    "gn:population":0,
    "gn:timezone":"America/Chicago",
    "iso:country":"US",
    "name:ara_x_preferred":[
        "\u0623\u0648\u0644\u062f\u0645"
    ],
    "name:azb_x_preferred":[
        "\u0627\u0648\u0644\u062f\u0647\u0627\u0645"
    ],
    "name:bul_x_preferred":[
        "\u041e\u043b\u0434\u044a\u043c"
    ],
    "name:ceb_x_preferred":[
        "Oldham"
    ],
    "name:ces_x_preferred":[
        "Oldham"
    ],
    "name:cym_x_preferred":[
        "Oldham"
    ],
    "name:dan_x_preferred":[
        "Oldham"
    ],
    "name:deu_x_preferred":[
        "Oldham"
    ],
    "name:ell_x_preferred":[
        "\u038c\u03bb\u03bd\u03c4\u03b1\u03bc"
    ],
    "name:epo_x_preferred":[
        "Oldham"
    ],
    "name:fas_x_preferred":[
        "\u0627\u0648\u0644\u062f\u0647\u0627\u0645"
    ],
    "name:fin_x_preferred":[
        "Oldham"
    ],
    "name:fra_x_preferred":[
        "Oldham"
    ],
    "name:gle_x_preferred":[
        "Oldham"
    ],
    "name:glg_x_preferred":[
        "Oldham"
    ],
    "name:heb_x_preferred":[
        "\u05d0\u05d5\u05dc\u05d3\u05d4\u05dd"
    ],
    "name:heb_x_variant":[
        "\u05d0\u05d5\u05dc\u05d3\u05d4\u05d0\u05dd"
    ],
    "name:hin_x_preferred":[
        "\u0913\u0932\u094d\u0921\u092e"
    ],
    "name:hun_x_preferred":[
        "Oldham"
    ],
    "name:hye_x_preferred":[
        "\u0555\u056c\u0564\u0565\u0574"
    ],
    "name:ind_x_preferred":[
        "Oldham"
    ],
    "name:isl_x_preferred":[
        "Oldham"
    ],
    "name:ita_x_preferred":[
        "Oldham"
    ],
    "name:jpn_x_preferred":[
        "\u30aa\u30fc\u30eb\u30c0\u30e0"
    ],
    "name:lav_x_preferred":[
        "Oldema"
    ],
    "name:lit_x_preferred":[
        "Oldamas"
    ],
    "name:nld_x_preferred":[
        "Oldham"
    ],
    "name:nno_x_preferred":[
        "Oldham"
    ],
    "name:nor_x_preferred":[
        "Oldham"
    ],
    "name:pol_x_preferred":[
        "Oldham"
    ],
    "name:por_x_preferred":[
        "Oldham"
    ],
    "name:ron_x_preferred":[
        "Oldham"
    ],
    "name:rus_x_preferred":[
        "\u041e\u043b\u0434\u0435\u043c"
    ],
    "name:sco_x_preferred":[
        "Oldham"
    ],
    "name:spa_x_preferred":[
        "Oldham"
    ],
    "name:srp_x_preferred":[
        "\u041e\u043b\u0434\u0430\u043c"
    ],
    "name:swa_x_preferred":[
        "Oldham"
    ],
    "name:swe_x_preferred":[
        "Oldham"
    ],
    "name:szl_x_preferred":[
        "Oldham"
    ],
    "name:tat_x_preferred":[
        "\u041e\u043b\u0434\u0435\u043c"
    ],
    "name:tha_x_preferred":[
        "\u0e42\u0e2d\u0e25\u0e14\u0e31\u0e21"
    ],
    "name:tur_x_preferred":[
        "Oldham"
    ],
    "name:ukr_x_preferred":[
        "\u041e\u043b\u0434\u0435\u043c"
    ],
    "name:vie_x_preferred":[
        "Oldham"
    ],
    "name:war_x_preferred":[
        "Oldham"
    ],
    "name:zho_x_preferred":[
        "\u5967\u723e\u5fb7\u59c6"
    ],
    "wof:name":"Oldham",
    "wof:placetype":"locality"
},
  "geometry": {"coordinates":[-94.23408000000001,30.74131],"type":"Point"}
}