{
  "type": "Feature",
  "properties": {
    "gn:admin1_code":"IN",
    "gn:admin2_code":"107.0",
    "gn:admin3_code":"77480.0",
    "gn:asciiname":"Garfield",
    "gn:country_code":"US",
    "gn:dem":244,
    "gn:elevation":"243.0",
    "gn:feature_class":"P",
    "gn:feature_code":"PPL",
    "gn:name":"Garfield",
    "gn:population":0,
    "gn:timezone":"America/Indiana/Indianapolis",
    "iso:country":"US",
    "name:azb_x_preferred":[
        "\u0642\u0627\u0631\u0641\u06cc\u0644\u062f"
    ],
    "name:fas_x_preferred":[
        "\u06af\u0627\u0631\u0641\u06cc\u0644\u062f"
    ],
    "name:urd_x_preferred":[
        "\u06af\u0627\u0631\u0641\u06cc\u0644\u0688"
    ],
    "wof:name":"Garfield",
    "wof:placetype":"locality"
},
  "geometry": {"coordinates":[-86.82389999999999,40.0831],"type":"Point"}
}