{
  "type": "Feature",
  "properties": {
    "gn:admin1_code":"AL",
    "gn:admin2_code":"25",
    "gn:asciiname":"Campbell",
    "gn:country_code":"US",
    "gn:dem":38,
    "gn:elevation":"29.0",
    "gn:feature_class":"P",
    "gn:feature_code":"PPL",
    "gn:name":"Campbell",
    "gn:population":0,
    "gn:timezone":"America/Chicago",
    "iso:country":"US",
    "name:azb_x_preferred":[
        "\u06a9\u0645\u067e\u0628\u0644"
    ],
    "name:deu_x_preferred":[
        "Campbell"
    ],
    "name:eng_x_preferred":[
        "Campbell"
    ],
    "name:fas_x_preferred":[
        "\u06a9\u0645\u067e\u0628\u0644"
    ],
    "name:hat_x_preferred":[
        "Campbell"
    ],
    "name:ind_x_preferred":[
        "Campbell"
    ],
    "name:ita_x_preferred":[
        "Campbell"
    ],
    "name:und_x_variant":[
        "Millersville"
    ],
    "name:urd_x_preferred":[
        "\u06a9\u06cc\u0645\u0628\u0644"
    ],
    "name:vol_x_preferred":[
        "Campbell"
    ],
    "name:zho_x_preferred":[
        "\u574e\u8c9d\u723e"
    ],
    "wof:name":"Campbell",
    "wof:placetype":"locality"
},
  "geometry": {"coordinates":[-87.98111999999998,31.92349],"type":"Point"}
}