{
  "type": "Feature",
  "properties": {
    "iso:country":"US",
    "name:eng_x_preferred":[
        "Crossfields"
    ],
    "wof:name":"Crossfields",
    "wof:placetype":"neighbourhood",
    "wof:population":2077,
    "zs:area_m":6527284.329005,
    "zs:blockids":[
        180571110011058,
        180571110011041,
        180571110011052,
        180571110011031,
        180571110011026,
        180571110011033,
        180571110011043,
        180571110011030,
        180571110011022,
        180571110011042,
        180571110012015,
        180571110011045,
        180571110011032,
        180571110011025,
        180571110011040,
        180571110011044,
        180571110011057,
        180571110011051,
        180571110011047,
        180571110011023,
        180571110012017,
        180571110011046,
        180571110011027
    ],
    "zs:housing10":632,
    "zs:label":"Crossfields",
    "zs:pop10":2077
},
  "geometry": {"coordinates":[-86.213396,39.959885],"type":"Point"}
}