{
  "type": "Feature",
  "properties": {
    "gn:admin1_code":"MD",
    "gn:admin2_code":"15.0",
    "gn:asciiname":"Mount Zoar",
    "gn:country_code":"US",
    "gn:dem":115,
    "gn:elevation":"110.0",
    "gn:feature_class":"P",
    "gn:feature_code":"PPL",
    "gn:name":"Mount Zoar",
    "gn:population":0,
    "gn:timezone":"America/New_York",
    "iso:country":"US",
    "name:ceb_x_preferred":[
        "Mount Zoar"
    ],
    "name:eng_x_preferred":[
        "Mount Zoar"
    ],
    "name:und_x_variant":[
        "Mount Zion",
        "Mount Zora"
    ],
    "wof:name":"Mount Zoar",
    "wof:placetype":"locality"
},
  "geometry": {"coordinates":[-76.18079,39.6815],"type":"Point"}
}