{
  "type": "Feature",
  "properties": {
    "gn:admin1_code":"WA",
    "gn:admin2_code":"33.0",
    "gn:asciiname":"Houghton",
    "gn:country_code":"US",
    "gn:dem":12,
    "gn:elevation":"13.0",
    "gn:feature_class":"P",
    "gn:feature_code":"PPL",
    "gn:name":"Houghton",
    "gn:population":0,
    "gn:timezone":"America/Los_Angeles",
    "iso:country":"US",
    "name:epo_x_preferred":[
        "Houghton"
    ],
    "name:spa_x_preferred":[
        "Houghton"
    ],
    "wof:name":"Houghton",
    "wof:placetype":"locality"
},
  "geometry": {"coordinates":[-122.20596,47.66093],"type":"Point"}
}