{
  "type": "Feature",
  "properties": {
    "iso:country":"US",
    "name:cat_x_preferred":[
        "Rolling Hills"
    ],
    "name:ceb_x_preferred":[
        "Rolling Hills"
    ],
    "name:deu_x_preferred":[
        "Rolling Hills"
    ],
    "name:eng_x_preferred":[
        "Rolling Hills"
    ],
    "name:fra_x_preferred":[
        "Rolling Hills"
    ],
    "name:hbs_x_preferred":[
        "Roling Hils"
    ],
    "name:ita_x_preferred":[
        "Rolling Hills"
    ],
    "name:nld_x_preferred":[
        "Rolling Hills"
    ],
    "name:pol_x_preferred":[
        "Rolling Hills"
    ],
    "name:por_x_preferred":[
        "Rolling Hills"
    ],
    "name:rus_x_preferred":[
        "\u0420\u043e\u043b\u043b\u0438\u043d\u0433-\u0425\u0438\u043b\u0441"
    ],
    "name:srp_x_preferred":[
        "\u0420\u043e\u043b\u0438\u043d\u0433 \u0425\u0438\u043b\u0441"
    ],
    "name:swe_x_preferred":[
        "Rolling Hills"
    ],
    "name:unk_x_variant":[
        "Rolling Hills"
    ],
    "name:vol_x_preferred":[
        "Rolling Hills"
    ],
    "qs:gn_adm0_cc":"US",
    "qs:gn_fcode":"PPL",
    "qs:gn_local":5364329,
    "qs:gn_nam_loc":"Laguna Niguel, Orange, California, US",
    "qs:gn_namadm1":"CA",
    "qs:gn_name":"Rolling Hills",
    "qs:local_max":1512,
    "qs:local_sum":5293,
    "qs:localhoods":21,
    "qs:name":"Rolling Hills",
    "qs:name_adm0":"United States",
    "qs:name_adm1":"California",
    "qs:name_adm2":"Orange",
    "qs:name_local":"Laguna Niguel",
    "qs:photo_max":15,
    "qs:photo_sum":40,
    "qs:placetype":"Suburb",
    "qs:quad_count":3,
    "qs:woe_adm0":23424977,
    "qs:woe_adm1":2347563,
    "qs:woe_adm2":12587699,
    "qs:woe_lau":0,
    "qs:woe_local":2434651,
    "qs:woe_ver":"7.10.0",
    "wd:wordcount":78,
    "wof:lang":[
        "eng"
    ],
    "wof:name":"Rolling Hills",
    "wof:placetype":"neighbourhood",
    "wof:population":902,
    "zs:blockids":[
        60590423152040,
        60590423152008,
        60590423152034,
        60590423155014,
        60590423152042,
        60590423152038,
        60590423152010,
        60590423152046,
        60590423154017,
        60590423155024,
        60590423152039,
        60590423154000,
        60590423152032,
        60590423152030,
        60590423152047,
        60590423152035,
        60590423154003,
        60590423152033,
        60590423152044,
        60590423152049,
        60590423152048,
        60590423152041,
        60590423152031,
        60590423152036,
        60590423155012,
        60590423152043
    ],
    "zs:housing10":367,
    "zs:pop10":902
},
  "geometry": {"coordinates":[-117.686508,33.542309],"type":"Point"}
}