{
  "type": "Feature",
  "properties": {
    "gn:admin1_code":"TX",
    "gn:admin2_code":"67.0",
    "gn:asciiname":"Roach",
    "gn:country_code":"US",
    "gn:dem":113,
    "gn:elevation":"106.0",
    "gn:feature_class":"P",
    "gn:feature_code":"PPL",
    "gn:name":"Roach",
    "gn:population":0,
    "gn:timezone":"America/Chicago",
    "iso:country":"US",
    "name:ces_x_preferred":[
        "Roach"
    ],
    "name:deu_x_preferred":[
        "Roach"
    ],
    "name:fra_x_preferred":[
        "Roach"
    ],
    "name:ita_x_preferred":[
        "Roach"
    ],
    "name:jpn_x_preferred":[
        "\u30ed\u30fc\u30c1"
    ],
    "name:nld_x_preferred":[
        "Roach"
    ],
    "name:rus_x_preferred":[
        "\u0420\u043e\u0443\u0447"
    ],
    "name:ukr_x_preferred":[
        "\u0420\u043e\u0443\u0447"
    ],
    "wof:name":"Roach",
    "wof:placetype":"locality"
},
  "geometry": {"coordinates":[-94.27186,33.06958],"type":"Point"}
}