{
  "type": "Feature",
  "properties": {
    "gn:admin1_code":"MI",
    "gn:admin2_code":"103",
    "gn:admin3_code":"15660.0",
    "gn:asciiname":"Pine Acres Trailer Court",
    "gn:country_code":"US",
    "gn:dem":190,
    "gn:elevation":"187.0",
    "gn:feature_class":"P",
    "gn:feature_code":"PPL",
    "gn:name":"Pine Acres Trailer Court",
    "gn:population":0,
    "gn:timezone":"America/Detroit",
    "iso:country":"US",
    "wof:name":"Pine Acres Trailer Court",
    "wof:placetype":"locality"
},
  "geometry": {"coordinates":[-87.33333,46.49361],"type":"Point"}
}