{
  "type": "Feature",
  "properties": {
    "gn:admin1_code":"LA",
    "gn:admin2_code":"75.0",
    "gn:asciiname":"Reussite",
    "gn:country_code":"US",
    "gn:dem":3,
    "gn:elevation":"2.0",
    "gn:feature_class":"P",
    "gn:feature_code":"PPL",
    "gn:name":"Reussite",
    "gn:population":0,
    "gn:timezone":"America/Chicago",
    "iso:country":"US",
    "name:eng_x_preferred":[
        "Reussite"
    ],
    "name:und_x_variant":[
        "La Roussit"
    ],
    "wof:name":"Reussite",
    "wof:placetype":"locality"
},
  "geometry": {"coordinates":[-89.98618,29.70104000000001],"type":"Point"}
}