{
  "type": "Feature",
  "properties": {
    "iso:country":"US",
    "name:eng_x_preferred":[
        "Braesview Terrace"
    ],
    "wof:name":"Braesview Terrace",
    "wof:placetype":"neighbourhood",
    "wof:population":3421,
    "zs:area_m":1787514.123395,
    "zs:blockids":[
        482014226001026,
        482014226001015,
        482014217003012,
        482014217003001,
        482014217002013,
        482014217003020,
        482014217004008,
        482014217003017,
        482014226003000,
        482014218004013,
        482014218004006,
        482014218004003,
        482014217003009,
        482014217003004,
        482014218004019,
        482014217003019,
        482014217004002,
        482014217002012,
        482014217001013,
        482014217004004,
        482014217004005,
        482014217002014,
        482014218004010,
        482014218004007,
        482014217002011,
        482014217002010,
        482014217003006,
        482014226001019,
        482014226001020,
        482014226001022,
        482014217003015,
        482014217003003,
        482014217003016,
        482014217003014,
        482014218004012,
        482014217003000,
        482014226001027,
        482014217003010,
        482014217002007,
        482014218004011,
        482014217004010,
        482014217003018,
        482014217004001,
        482014217004006,
        482014217003011,
        482014217003008,
        482014217003007,
        482014217003002,
        482014217002009,
        482014217004007,
        482014226001021,
        482014226001023,
        482014218003001,
        482014218004024,
        482014218004017,
        482014218004018,
        482014217003005,
        482014218004016,
        482014217004003,
        482014217004009,
        482014217002008,
        482014218004002,
        482014217004000
    ],
    "zs:housing10":1441,
    "zs:label":"Braesview Terrace",
    "zs:pop10":3421
},
  "geometry": {"coordinates":[-95.487656,29.686269],"type":"Point"}
}