{
  "type": "Feature",
  "properties": {
    "gn:admin1_code":"VA",
    "gn:admin2_code":"159",
    "gn:asciiname":"Totuskey",
    "gn:country_code":"US",
    "gn:dem":48,
    "gn:elevation":"46.0",
    "gn:feature_class":"P",
    "gn:feature_code":"PPL",
    "gn:name":"Totuskey",
    "gn:population":0,
    "gn:timezone":"America/New_York",
    "iso:country":"US",
    "wof:name":"Totuskey",
    "wof:placetype":"locality"
},
  "geometry": {"coordinates":[-76.61718,37.94402],"type":"Point"}
}