{
  "type": "Feature",
  "properties": {
    "iso:country":"US",
    "name:eng_x_preferred":[
        "Garden Ridge"
    ],
    "qs:gn_adm0_cc":"US",
    "qs:gn_local":4724129,
    "qs:gn_nam_loc":"Round Rock, Williamson, Texas, US",
    "qs:gn_namadm1":"TX",
    "qs:local_max":2122,
    "qs:local_sum":10214,
    "qs:localhoods":33,
    "qs:name":"Garden Ridge",
    "qs:name_adm0":"United States",
    "qs:name_adm1":"Texas",
    "qs:name_adm2":"Williamson",
    "qs:name_local":"Round Rock",
    "qs:photo_max":141,
    "qs:photo_sum":246,
    "qs:placetype":"Suburb",
    "qs:quad_count":12,
    "qs:woe_adm0":23424977,
    "qs:woe_adm1":2347602,
    "qs:woe_adm2":12590252,
    "qs:woe_lau":0,
    "qs:woe_local":2485177,
    "qs:woe_ver":"7.10.0",
    "wof:lang":[
        "eng"
    ],
    "wof:name":"Garden Ridge",
    "wof:placetype":"neighbourhood",
    "wof:population":977,
    "zs:blockids":[
        484530018514006,
        484530018514001,
        484530018514005,
        484530018514003,
        484530018514002,
        484530018514000,
        484530018514011,
        484530018572020,
        484530018514004,
        484530018572019,
        484530018572018,
        484530018514007
    ],
    "zs:housing10":516,
    "zs:pop10":977
},
  "geometry": {"coordinates":[-97.67508100000001,30.482052],"type":"Point"}
}