{
  "type": "Feature",
  "properties": {
    "gn:admin1_code":"DE",
    "gn:admin2_code":"5.0",
    "gn:asciiname":"Susan Beach Corner",
    "gn:country_code":"US",
    "gn:dem":18,
    "gn:elevation":"13.0",
    "gn:feature_class":"P",
    "gn:feature_code":"PPL",
    "gn:name":"Susan Beach Corner",
    "gn:population":0,
    "gn:timezone":"America/New_York",
    "iso:country":"US",
    "wof:name":"Susan Beach Corner",
    "wof:placetype":"locality"
},
  "geometry": {"coordinates":[-75.65243000000002,38.46817],"type":"Point"}
}