{
  "type": "Feature",
  "properties": {
    "gn:admin1_code":"LA",
    "gn:admin2_code":"69.0",
    "gn:asciiname":"Wood",
    "gn:country_code":"US",
    "gn:dem":50,
    "gn:elevation":"46.0",
    "gn:feature_class":"P",
    "gn:feature_code":"PPL",
    "gn:name":"Wood",
    "gn:population":0,
    "gn:timezone":"America/Chicago",
    "iso:country":"US",
    "name:fas_x_preferred":[
        "\u0648\u0648\u062f"
    ],
    "wof:name":"Wood",
    "wof:placetype":"locality"
},
  "geometry": {"coordinates":[-93.16182999999999,31.90016],"type":"Point"}
}