{
  "type": "Feature",
  "properties": {
    "gn:admin1_code":"MO",
    "gn:admin2_code":"71.0",
    "gn:admin3_code":"7192.0",
    "gn:asciiname":"Peters Ford",
    "gn:country_code":"US",
    "gn:dem":191,
    "gn:elevation":"188.0",
    "gn:feature_class":"P",
    "gn:feature_code":"PPL",
    "gn:name":"Peters Ford",
    "gn:population":0,
    "gn:timezone":"America/Chicago",
    "iso:country":"US",
    "wof:name":"Peters Ford",
    "wof:placetype":"locality"
},
  "geometry": {"coordinates":[-91.20765,38.37449],"type":"Point"}
}