{
  "type": "Feature",
  "properties": {
    "gn:admin1_code":"PA",
    "gn:admin2_code":"41.0",
    "gn:admin3_code":"50472.0",
    "gn:asciiname":"White Rock Acres",
    "gn:country_code":"US",
    "gn:dem":253,
    "gn:elevation":"253.0",
    "gn:feature_class":"P",
    "gn:feature_code":"PPL",
    "gn:name":"White Rock Acres",
    "gn:population":0,
    "gn:timezone":"America/New_York",
    "iso:country":"US",
    "wof:name":"White Rock Acres",
    "wof:placetype":"locality"
},
  "geometry": {"coordinates":[-77.0822,40.12898],"type":"Point"}
}