{
  "type": "Feature",
  "properties": {
    "gn:admin1_code":"UT",
    "gn:admin2_code":"47.0",
    "gn:asciiname":"Bennett",
    "gn:country_code":"US",
    "gn:dem":1661,
    "gn:elevation":"1660.0",
    "gn:feature_class":"P",
    "gn:feature_code":"PPL",
    "gn:name":"Bennett",
    "gn:population":0,
    "gn:timezone":"America/Denver",
    "iso:country":"US",
    "name:cat_x_preferred":[
        "Bennett"
    ],
    "name:ceb_x_preferred":[
        "Bennett"
    ],
    "name:ces_x_preferred":[
        "Bennett"
    ],
    "name:deu_x_preferred":[
        "Bennett"
    ],
    "name:eng_x_preferred":[
        "Bennett"
    ],
    "name:fin_x_preferred":[
        "Bennett"
    ],
    "name:fra_x_preferred":[
        "Bennett"
    ],
    "name:glg_x_preferred":[
        "Bennett"
    ],
    "name:ita_x_preferred":[
        "Bennett"
    ],
    "name:jpn_x_preferred":[
        "\u30d9\u30cd\u30c3\u30c8"
    ],
    "name:nld_x_preferred":[
        "Bennett"
    ],
    "name:pol_x_preferred":[
        "Bennett"
    ],
    "name:por_x_preferred":[
        "Bennett"
    ],
    "name:slv_x_preferred":[
        "Bennett"
    ],
    "name:spa_x_preferred":[
        "Bennett"
    ],
    "name:swe_x_preferred":[
        "Bennett"
    ],
    "name:ukr_x_preferred":[
        "\u0411\u0435\u043d\u043d\u0435\u0442\u0442"
    ],
    "name:und_x_variant":[
        "Cuneal"
    ],
    "name:vol_x_preferred":[
        "Bennett"
    ],
    "wof:name":"Bennett",
    "wof:placetype":"locality"
},
  "geometry": {"coordinates":[-109.93543,40.37385],"type":"Point"}
}