{
  "type": "Feature",
  "properties": {
    "gn:country":"US",
    "gn:fcode":"PPL",
    "gn:population":0,
    "iso:country":"US",
    "name:eng_x_preferred":[
        "Morgans Corners"
    ],
    "name:und_x_variant":[
        "Morgans Corner"
    ],
    "qs_pg:aaroncc":"US",
    "qs_pg:gn_country":"US",
    "qs_pg:gn_fcode":"PPL",
    "qs_pg:gn_pop":0,
    "qs_pg:name":"Morgans Corners",
    "qs_pg:name_adm0":"United States",
    "qs_pg:name_adm1":"North Carolina",
    "qs_pg:photos":76,
    "qs_pg:photos_1k":15,
    "qs_pg:photos_9k":1,
    "qs_pg:photos_9r":3,
    "qs_pg:photos_all":76,
    "qs_pg:photos_sr":3,
    "qs_pg:pop_sr":0,
    "qs_pg:qs_pg_placetype":"locality",
    "qs_pg:qs_pg_placetype_gp":"Town",
    "qs_pg:woe_adm0":23424977,
    "woe:adm0_id":23424977,
    "woe:name_adm0":"United States",
    "woe:name_adm1":"North Carolina",
    "woe:placetype":"Town",
    "wof:name":"Morgans Corners",
    "wof:placetype":"locality"
},
  "geometry": {"coordinates":[-76.34911,36.41738],"type":"Point"}
}