{
  "type": "Feature",
  "properties": {
    "gn:admin1_code":"NV",
    "gn:admin2_code":"7",
    "gn:asciiname":"Scraper Springs",
    "gn:country_code":"US",
    "gn:dem":1807,
    "gn:elevation":"1804.0",
    "gn:feature_class":"P",
    "gn:feature_code":"PPL",
    "gn:name":"Scraper Springs",
    "gn:population":0,
    "gn:timezone":"America/Los_Angeles",
    "iso:country":"US",
    "wof:name":"Scraper Springs",
    "wof:placetype":"locality"
},
  "geometry": {"coordinates":[-116.68122,41.33768],"type":"Point"}
}