{
  "type": "Feature",
  "properties": {
    "gn:country":"US",
    "gn:fcode":"PPL",
    "gn:population":0,
    "iso:country":"US",
    "name:deu_x_preferred":[
        "Springtown"
    ],
    "name:ita_x_preferred":[
        "Springtown"
    ],
    "name:nld_x_preferred":[
        "Springtown"
    ],
    "name:pol_x_preferred":[
        "Springtown"
    ],
    "name:por_x_preferred":[
        "Springtown"
    ],
    "name:srp_x_preferred":[
        "\u0421\u043f\u0440\u0438\u043d\u0433\u0442\u0430\u0443\u043d"
    ],
    "name:swe_x_preferred":[
        "Springtown"
    ],
    "qs_pg:aaroncc":"US",
    "qs_pg:gn_country":"US",
    "qs_pg:gn_fcode":"PPL",
    "qs_pg:gn_pop":0,
    "qs_pg:name":"Springtown",
    "qs_pg:name_adm0":"United States",
    "qs_pg:name_adm1":"Pennsylvania",
    "qs_pg:photos":9,
    "qs_pg:photos_1k":2,
    "qs_pg:photos_9k":1,
    "qs_pg:photos_9r":1,
    "qs_pg:photos_all":9,
    "qs_pg:photos_sr":1,
    "qs_pg:pop_sr":0,
    "qs_pg:qs_pg_placetype":"neighbourhood",
    "qs_pg:qs_pg_placetype_gp":"Suburb",
    "qs_pg:woe_adm0":23424977,
    "woe:adm0_id":23424977,
    "woe:name_adm0":"United States",
    "woe:name_adm1":"Pennsylvania",
    "woe:placetype":"Suburb",
    "wof:name":"Springtown",
    "wof:placetype":"neighbourhood"
},
  "geometry": {"coordinates":[-77.81972,40.08064],"type":"Point"}
}