{
  "type": "Feature",
  "properties": {
    "gn:admin1_code":"GA",
    "gn:admin2_code":"119",
    "gn:asciiname":"Sandy Cross",
    "gn:country_code":"US",
    "gn:dem":255,
    "gn:elevation":"255.0",
    "gn:feature_class":"P",
    "gn:feature_code":"PPL",
    "gn:name":"Sandy Cross",
    "gn:population":0,
    "gn:timezone":"America/New_York",
    "iso:country":"US",
    "name:deu_x_preferred":[
        "Sandy Cross"
    ],
    "wof:name":"Sandy Cross",
    "wof:placetype":"locality"
},
  "geometry": {"coordinates":[-83.22599,34.28733],"type":"Point"}
}