{
  "type": "Feature",
  "properties": {
    "gn:elevation":704,
    "iso:country":"US",
    "name:eng_x_preferred":[
        "Glen Savage"
    ],
    "qs:gn_fcode":"PPL",
    "qs:gn_local":0,
    "qs:gn_namadm1":"PA",
    "qs:gn_name":"Glen Savage",
    "qs:local_max":6,
    "qs:local_sum":6,
    "qs:localhoods":1,
    "qs:name":"Glen Savage",
    "qs:name_adm0":"United States",
    "qs:name_adm1":"Pennsylvania",
    "qs:name_adm2":"Somerset",
    "qs:name_local":"Allegheny",
    "qs:photo_max":5,
    "qs:photo_sum":6,
    "qs:placetype":"Suburb",
    "qs:quad_count":2,
    "qs:woe_adm0":23424977,
    "qs:woe_adm1":2347597,
    "qs:woe_adm2":12589783,
    "qs:woe_lau":0,
    "qs:woe_local":28744832,
    "qs:woe_ver":"7.10.0",
    "wof:lang":[
        "eng"
    ],
    "wof:name":"Glen Savage",
    "wof:placetype":"neighbourhood",
    "wof:population":76,
    "zs:blockids":[
        421110213003079,
        421110213003060,
        421110213003080
    ],
    "zs:housing10":51,
    "zs:pop10":76
},
  "geometry": {"coordinates":[-78.78387499999999,39.93361],"type":"Point"}
}