{
  "type": "Feature",
  "properties": {
    "gn:admin1_code":"LA",
    "gn:admin2_code":"115.0",
    "gn:asciiname":"Walnut Hill",
    "gn:country_code":"US",
    "gn:dem":95,
    "gn:elevation":"82.0",
    "gn:feature_class":"P",
    "gn:feature_code":"PPL",
    "gn:name":"Walnut Hill",
    "gn:population":0,
    "gn:timezone":"America/Chicago",
    "iso:country":"US",
    "name:ceb_x_preferred":[
        "Walnut Hill"
    ],
    "name:deu_x_preferred":[
        "Walnut Hill"
    ],
    "name:eng_x_preferred":[
        "Walnut Hill"
    ],
    "name:ita_x_preferred":[
        "Walnut Hill"
    ],
    "name:nld_x_preferred":[
        "Walnut Hill"
    ],
    "name:pol_x_preferred":[
        "Walnut Hill"
    ],
    "name:por_x_preferred":[
        "Walnut Hill"
    ],
    "name:srp_x_preferred":[
        "\u0412\u043e\u043b\u043d\u0430\u0442 \u0425\u0438\u043b"
    ],
    "name:und_x_variant":[
        "Walnuthill"
    ],
    "name:vol_x_preferred":[
        "Walnut Hill"
    ],
    "wof:name":"Walnut Hill",
    "wof:placetype":"locality"
},
  "geometry": {"coordinates":[-93.09183,31.19685],"type":"Point"}
}