{
  "type": "Feature",
  "properties": {
    "gn:admin1_code":"PA",
    "gn:admin2_code":"97.0",
    "gn:admin3_code":"66752.0",
    "gn:asciiname":"Klines Grove",
    "gn:country_code":"US",
    "gn:dem":196,
    "gn:elevation":"203.0",
    "gn:feature_class":"P",
    "gn:feature_code":"PPL",
    "gn:name":"Klines Grove",
    "gn:population":0,
    "gn:timezone":"America/New_York",
    "iso:country":"US",
    "name:eng_x_preferred":[
        "Klines Grove"
    ],
    "name:und_x_variant":[
        "Klinegrove",
        "Kline Grove"
    ],
    "wof:name":"Klines Grove",
    "wof:placetype":"locality"
},
  "geometry": {"coordinates":[-76.68913000000001,40.90536],"type":"Point"}
}