{
  "type": "Feature",
  "properties": {
    "gn:admin1_code":"WV",
    "gn:admin2_code":"63.0",
    "gn:asciiname":"Wikel",
    "gn:country_code":"US",
    "gn:dem":661,
    "gn:elevation":"664.0",
    "gn:feature_class":"P",
    "gn:feature_code":"PPL",
    "gn:name":"Wikel",
    "gn:population":0,
    "gn:timezone":"America/New_York",
    "iso:country":"US",
    "wof:name":"Wikel",
    "wof:placetype":"locality"
},
  "geometry": {"coordinates":[-80.64757,37.51207],"type":"Point"}
}