{
  "type": "Feature",
  "properties": {
    "gn:gn_country":"US",
    "gn:gn_fcode":"PPL",
    "gn:gn_pop":0,
    "iso:country":"US",
    "name:deu_x_preferred":[
        "Hinkle"
    ],
    "name:fra_x_preferred":[
        "Hinkle"
    ],
    "qs_pg:aaroncc":"US",
    "qs_pg:gn_country":"US",
    "qs_pg:gn_fcode":"PPL",
    "qs_pg:gn_pop":0,
    "qs_pg:name":"Hinkle",
    "qs_pg:name_adm0":"United States",
    "qs_pg:name_adm1":"Louisiana",
    "qs_pg:photos":10,
    "qs_pg:photos_1k":2,
    "qs_pg:photos_9k":1,
    "qs_pg:photos_9r":1,
    "qs_pg:photos_all":10,
    "qs_pg:photos_sr":1,
    "qs_pg:pop_sr":0,
    "qs_pg:qs_pg_placetype":"neighbourhood",
    "qs_pg:qs_pg_placetype_gp":"Suburb",
    "qs_pg:woe_adm0":23424977,
    "woe:adm0_id":23424977,
    "woe:name_adm0":"United States",
    "woe:name_adm1":"Louisiana",
    "woe:placetype":"Suburb",
    "wof:name":"Hinkle",
    "wof:placetype":"neighbourhood"
},
  "geometry": {"coordinates":[-93.71823000000001,32.5321],"type":"Point"}
}