{
  "type": "Feature",
  "properties": {
    "gn:admin1_code":"SC",
    "gn:admin2_code":"57.0",
    "gn:asciiname":"Jones Crossroads",
    "gn:country_code":"US",
    "gn:dem":180,
    "gn:elevation":"181.0",
    "gn:feature_class":"P",
    "gn:feature_code":"PPL",
    "gn:name":"Jones Crossroads",
    "gn:population":0,
    "gn:timezone":"America/New_York",
    "iso:country":"US",
    "name:eng_x_preferred":[
        "Jones Crossroads"
    ],
    "name:und_x_variant":[
        "Jones Cross Roads"
    ],
    "wof:name":"Jones Crossroads",
    "wof:placetype":"locality"
},
  "geometry": {"coordinates":[-80.76618000000001,34.65098],"type":"Point"}
}