{
  "type": "Feature",
  "properties": {
    "gn:admin1_code":"IN",
    "gn:admin2_code":"1.0",
    "gn:admin3_code":"32206.0",
    "gn:asciiname":"Perryville",
    "gn:country_code":"US",
    "gn:dem":259,
    "gn:elevation":"260.0",
    "gn:feature_class":"P",
    "gn:feature_code":"PPL",
    "gn:name":"Perryville",
    "gn:population":0,
    "gn:timezone":"America/Indiana/Indianapolis",
    "iso:country":"US",
    "name:ara_x_preferred":[
        "\u0628\u064a\u0631\u064a\u0641\u064a\u0644"
    ],
    "name:ben_x_preferred":[
        "\u09aa\u09c7\u09b0\u09bf\u09ad\u09bf\u09b2\u09c7"
    ],
    "name:cat_x_preferred":[
        "Perryville"
    ],
    "name:ceb_x_preferred":[
        "Perryville"
    ],
    "name:deu_x_preferred":[
        "Perryville"
    ],
    "name:ell_x_preferred":[
        "\u03a0\u03ad\u03c1\u03b9\u03b2\u03b9\u03bb"
    ],
    "name:fra_x_preferred":[
        "Perryville"
    ],
    "name:heb_x_preferred":[
        "\u05e4\u05e8\u05d9\u05d5\u05d5\u05d9\u05dc"
    ],
    "name:hin_x_preferred":[
        "\u092a\u0947\u0930\u0940\u0935\u093f\u0932"
    ],
    "name:hun_x_preferred":[
        "Perryville"
    ],
    "name:ind_x_preferred":[
        "Perryville"
    ],
    "name:ita_x_preferred":[
        "Perryville"
    ],
    "name:jpn_x_preferred":[
        "\u30da\u30ea\u30fc\u30d3\u30eb"
    ],
    "name:kor_x_preferred":[
        "\ud398\ub9ac\ube4c"
    ],
    "name:nld_x_preferred":[
        "Perryville"
    ],
    "name:pol_x_preferred":[
        "Perryville"
    ],
    "name:por_x_preferred":[
        "Perryville"
    ],
    "name:rus_x_preferred":[
        "\u041f\u0435\u0440\u0440\u0438\u0432\u0438\u043b\u043b"
    ],
    "name:spa_x_preferred":[
        "Perryville"
    ],
    "name:srp_x_preferred":[
        "\u041f\u0435\u0440\u0438\u0432\u0438\u043b"
    ],
    "name:swe_x_preferred":[
        "Perryville"
    ],
    "name:tur_x_preferred":[
        "Perryville"
    ],
    "name:urd_x_preferred":[
        "\u067e\u06cc\u0631\u06cc \u0648\u0644"
    ],
    "name:vie_x_preferred":[
        "Perryville"
    ],
    "name:vol_x_preferred":[
        "Perryville"
    ],
    "wof:name":"Perryville",
    "wof:placetype":"locality"
},
  "geometry": {"coordinates":[-85.04052,40.59116],"type":"Point"}
}