{
  "type": "Feature",
  "properties": {
    "gn:admin1_code":"IN",
    "gn:admin2_code":"1.0",
    "gn:admin3_code":"32206.0",
    "gn:asciiname":"Perryville",
    "gn:country_code":"US",
    "gn:dem":259,
    "gn:elevation":"260.0",
    "gn:feature_class":"P",
    "gn:feature_code":"PPL",
    "gn:name":"Perryville",
    "gn:population":0,
    "gn:timezone":"America/Indiana/Indianapolis",
    "iso:country":"US",
    "name:cat_x_preferred":[
        "Perryville"
    ],
    "name:ceb_x_preferred":[
        "Perryville"
    ],
    "name:deu_x_preferred":[
        "Perryville"
    ],
    "name:fra_x_preferred":[
        "Perryville"
    ],
    "name:ita_x_preferred":[
        "Perryville"
    ],
    "name:nld_x_preferred":[
        "Perryville"
    ],
    "name:pol_x_preferred":[
        "Perryville"
    ],
    "name:por_x_preferred":[
        "Perryville"
    ],
    "name:rus_x_preferred":[
        "\u041f\u0435\u0440\u0440\u0438\u0432\u0438\u043b\u043b"
    ],
    "name:spa_x_preferred":[
        "Perryville"
    ],
    "name:srp_x_preferred":[
        "\u041f\u0435\u0440\u0438\u0432\u0438\u043b"
    ],
    "name:swe_x_preferred":[
        "Perryville"
    ],
    "name:vol_x_preferred":[
        "Perryville"
    ],
    "wof:name":"Perryville",
    "wof:placetype":"locality"
},
  "geometry": {"coordinates":[-85.04052,40.59116],"type":"Point"}
}