{
  "type": "Feature",
  "properties": {
    "gn:country":"US",
    "gn:fcode":"PPL",
    "gn:population":0,
    "iso:country":"US",
    "name:ara_x_preferred":[
        "\u064a\u0648\u0646\u064a\u0648\u0646 \u0633\u064a\u062a\u064a"
    ],
    "name:ceb_x_preferred":[
        "Union City"
    ],
    "name:deu_x_preferred":[
        "Union City"
    ],
    "name:fin_x_preferred":[
        "Union City"
    ],
    "name:fra_x_preferred":[
        "Union City"
    ],
    "name:ita_x_preferred":[
        "Union City"
    ],
    "name:jpn_x_preferred":[
        "\u30e6\u30cb\u30aa\u30f3\u30b7\u30c6\u30a3"
    ],
    "name:kor_x_preferred":[
        "\uc720\ub2c8\uc5b8\uc2dc\ud2f0"
    ],
    "name:nld_x_preferred":[
        "Union City"
    ],
    "name:pol_x_preferred":[
        "Union City"
    ],
    "name:por_x_preferred":[
        "Union City"
    ],
    "name:rus_x_preferred":[
        "\u042e\u043d\u0438\u043e\u043d-\u0421\u0438\u0442\u0438"
    ],
    "name:sco_x_preferred":[
        "Union City"
    ],
    "name:spa_x_preferred":[
        "Union City"
    ],
    "name:srp_x_preferred":[
        "\u0408\u0443\u043d\u0438\u043e\u043d \u0421\u0438\u0442\u0438"
    ],
    "name:swa_x_preferred":[
        "Union City"
    ],
    "name:swe_x_preferred":[
        "Union City"
    ],
    "name:urd_x_preferred":[
        "\u06cc\u0648\u0646\u06cc\u0646 \u0633\u0679\u06cc"
    ],
    "name:vol_x_preferred":[
        "Union City"
    ],
    "name:zho_x_preferred":[
        "\u806f\u5408\u5e02"
    ],
    "qs_pg:aaroncc":"US",
    "qs_pg:gn_country":"US",
    "qs_pg:gn_fcode":"PPL",
    "qs_pg:gn_pop":0,
    "qs_pg:name":"Union City",
    "qs_pg:name_adm0":"United States",
    "qs_pg:name_adm1":"Kentucky",
    "qs_pg:photos":603,
    "qs_pg:photos_1k":122,
    "qs_pg:photos_9k":3,
    "qs_pg:photos_9r":5,
    "qs_pg:photos_all":603,
    "qs_pg:photos_sr":8,
    "qs_pg:pop_sr":0,
    "qs_pg:qs_pg_placetype":"locality",
    "qs_pg:qs_pg_placetype_gp":"Town",
    "qs_pg:woe_adm0":23424977,
    "woe:adm0_id":23424977,
    "woe:name_adm0":"United States",
    "woe:name_adm1":"Kentucky",
    "woe:placetype":"Town",
    "wof:name":"Union City",
    "wof:placetype":"locality"
},
  "geometry": {"coordinates":[-86.07192000000001,37.13699],"type":"Point"}
}