{
  "type": "Feature",
  "properties": {
    "iso:country":"US",
    "name:bar_x_preferred":[
        "Hillside"
    ],
    "name:ceb_x_preferred":[
        "Hillside"
    ],
    "name:cym_x_preferred":[
        "Hillside"
    ],
    "name:deu_x_preferred":[
        "Hillside"
    ],
    "name:eng_x_preferred":[
        "Hillside"
    ],
    "name:ita_x_preferred":[
        "Hillside"
    ],
    "name:mlg_x_preferred":[
        "Hillside"
    ],
    "name:nld_x_preferred":[
        "Hillside"
    ],
    "name:pol_x_preferred":[
        "Hillside"
    ],
    "name:por_x_preferred":[
        "Hillside"
    ],
    "name:srp_x_preferred":[
        "\u0425\u0438\u043b\u0441\u0430\u0458\u0434"
    ],
    "name:swe_x_preferred":[
        "Hillside"
    ],
    "name:ukr_x_preferred":[
        "\u0413\u0456\u043b\u043b\u0441\u0430\u0439\u0434"
    ],
    "name:vol_x_preferred":[
        "Hillside"
    ],
    "wd:wordcount":191,
    "wof:name":"Hillside",
    "wof:placetype":"neighbourhood",
    "wof:population":23,
    "zs:area_m":5337662.155738,
    "zs:blockids":[
        230050160005070,
        230050160005073,
        230050160005071,
        230050160005066
    ],
    "zs:housing10":40,
    "zs:label":"Hillside",
    "zs:pop10":23
},
  "geometry": {"coordinates":[-70.701481,43.964891],"type":"Point"}
}