{
  "type": "Feature",
  "properties": {
    "gn:admin1_code":"CA",
    "gn:admin2_code":"57.0",
    "gn:asciiname":"Sahl Court",
    "gn:country_code":"US",
    "gn:dem":801,
    "gn:elevation":"798.0",
    "gn:feature_class":"P",
    "gn:feature_code":"PPL",
    "gn:name":"Sahl Court",
    "gn:population":0,
    "gn:timezone":"America/Los_Angeles",
    "iso:country":"US",
    "wof:name":"Sahl Court",
    "wof:placetype":"locality"
},
  "geometry": {"coordinates":[-121.06856000000001,39.23406],"type":"Point"}
}