{
  "type": "Feature",
  "properties": {
    "gn:admin1_code":"SC",
    "gn:admin2_code":"71.0",
    "gn:asciiname":"Beth Eden",
    "gn:country_code":"US",
    "gn:dem":171,
    "gn:elevation":"166.0",
    "gn:feature_class":"P",
    "gn:feature_code":"PPL",
    "gn:name":"Beth Eden",
    "gn:population":0,
    "gn:timezone":"America/New_York",
    "iso:country":"US",
    "wof:name":"Beth Eden",
    "wof:placetype":"locality"
},
  "geometry": {"coordinates":[-81.62260999999999,34.35319],"type":"Point"}
}