{
  "type": "Feature",
  "properties": {
    "gn:admin1_code":"MD",
    "gn:admin2_code":"9.0",
    "gn:asciiname":"Wallville",
    "gn:country_code":"US",
    "gn:dem":33,
    "gn:elevation":"30.0",
    "gn:feature_class":"P",
    "gn:feature_code":"PPL",
    "gn:name":"Wallville",
    "gn:population":0,
    "gn:timezone":"America/New_York",
    "iso:country":"US",
    "wof:name":"Wallville",
    "wof:placetype":"locality"
},
  "geometry": {"coordinates":[-76.50523000000003,38.4154],"type":"Point"}
}