{
  "type": "Feature",
  "properties": {
    "gn:country":"US",
    "gn:fcode":"PPL",
    "gn:population":0,
    "iso:country":"US",
    "name:azb_x_preferred":[
        "\u0622\u0644\u067e\u0644\u0627\u0648\u0633"
    ],
    "name:ceb_x_preferred":[
        "Alplaus"
    ],
    "name:eng_x_preferred":[
        "Alplaus"
    ],
    "name:fas_x_preferred":[
        "\u0627\u0644\u067e\u0644\u0627\u0626\u0648\u0633\u060c \u0646\u06cc\u0648 \u06cc\u0648\u0631\u06a9"
    ],
    "name:fas_x_variant":[
        "\u0627\u0644\u067e\u0644\u0627\u0626\u0648\u0633"
    ],
    "name:nld_x_preferred":[
        "Alplaus"
    ],
    "name:spa_x_preferred":[
        "Alplaus"
    ],
    "name:tur_x_preferred":[
        "Alplaus"
    ],
    "name:und_x_variant":[
        "Aalplaats"
    ],
    "name:vol_x_preferred":[
        "Alplaus"
    ],
    "qs_pg:aaroncc":"US",
    "qs_pg:gn_country":"US",
    "qs_pg:gn_fcode":"PPL",
    "qs_pg:gn_pop":0,
    "qs_pg:name":"Alplaus",
    "qs_pg:name_adm0":"United States",
    "qs_pg:name_adm1":"New York",
    "qs_pg:photos":216,
    "qs_pg:photos_1k":44,
    "qs_pg:photos_9k":1,
    "qs_pg:photos_9r":4,
    "qs_pg:photos_all":216,
    "qs_pg:photos_sr":4,
    "qs_pg:pop_sr":0,
    "qs_pg:qs_pg_placetype":"locality",
    "qs_pg:qs_pg_placetype_gp":"Town",
    "qs_pg:woe_adm0":23424977,
    "woe:adm0_id":23424977,
    "woe:name_adm0":"United States",
    "woe:name_adm1":"New York",
    "woe:placetype":"Town",
    "wof:name":"Alplaus",
    "wof:placetype":"locality"
},
  "geometry": {"coordinates":[-73.89901,42.85535],"type":"Point"}
}