{
  "type": "Feature",
  "properties": {
    "gn:admin1_code":"VA",
    "gn:admin2_code":"143",
    "gn:asciiname":"Sandy River",
    "gn:country_code":"US",
    "gn:dem":274,
    "gn:elevation":"276.0",
    "gn:feature_class":"P",
    "gn:feature_code":"PPL",
    "gn:name":"Sandy River",
    "gn:population":0,
    "gn:timezone":"America/New_York",
    "iso:country":"US",
    "wof:name":"Sandy River",
    "wof:placetype":"locality"
},
  "geometry": {"coordinates":[-79.65142,36.72319],"type":"Point"}
}