{
  "type": "Feature",
  "properties": {
    "gn:admin1_code":"HI",
    "gn:admin2_code":"3.0",
    "gn:asciiname":"'Aiea Heights",
    "gn:country_code":"US",
    "gn:dem":138,
    "gn:elevation":"126.0",
    "gn:feature_class":"P",
    "gn:feature_code":"PPL",
    "gn:name":"\u2018Aiea Heights",
    "gn:population":0,
    "gn:timezone":"Pacific/Honolulu",
    "iso:country":"US",
    "name:haw_x_preferred":[
        "\u2018Aiea Heights"
    ],
    "name:und_x_variant":[
        "Aiea Heights"
    ],
    "wof:name":"'Aiea Heights",
    "wof:placetype":"locality"
},
  "geometry": {"coordinates":[-157.92053000000001,21.39083],"type":"Point"}
}