{
  "type": "Feature",
  "properties": {
    "iso:country":"US",
    "qs_pg:aaroncc":"US",
    "qs_pg:name":"Coast Fork",
    "qs_pg:name_adm0":"United States",
    "qs_pg:name_adm1":"Oregon",
    "qs_pg:photos":15,
    "qs_pg:photos_1k":3,
    "qs_pg:photos_9k":1,
    "qs_pg:photos_9r":1,
    "qs_pg:photos_all":15,
    "qs_pg:photos_sr":1,
    "qs_pg:pop_sr":0,
    "qs_pg:qs_pg_placetype":"locality",
    "qs_pg:qs_pg_placetype_gp":"Town",
    "qs_pg:woe_adm0":23424977,
    "woe:adm0_id":23424977,
    "woe:name_adm0":"United States",
    "woe:name_adm1":"Oregon",
    "woe:placetype":"Town",
    "wof:name":"Coast Fork",
    "wof:placetype":"locality"
},
  "geometry": {"coordinates":[-123.023,43.86338],"type":"Point"}
}