{
  "type": "Feature",
  "properties": {
    "gn:elevation":305,
    "iso:country":"US",
    "name:eng_x_preferred":[
        "Notchland"
    ],
    "qs:gn_fcode":"PPL",
    "qs:gn_local":0,
    "qs:gn_namadm1":"NH",
    "qs:gn_name":"Notchland",
    "qs:local_max":708,
    "qs:local_sum":797,
    "qs:localhoods":3,
    "qs:name":"Notchland",
    "qs:name_adm0":"United States",
    "qs:name_adm1":"New Hampshire",
    "qs:name_adm2":"Carroll",
    "qs:name_local":"Hart's Location",
    "qs:photo_max":8,
    "qs:photo_sum":24,
    "qs:placetype":"Suburb",
    "qs:quad_count":9,
    "qs:woe_adm0":23424977,
    "qs:woe_adm1":2347588,
    "qs:woe_adm2":12589249,
    "qs:woe_lau":0,
    "qs:woe_local":23417693,
    "qs:woe_ver":"7.10.0",
    "wof:lang":[
        "eng"
    ],
    "wof:name":"Notchland",
    "wof:placetype":"neighbourhood",
    "zs:blockids":[
        330079510002294
    ],
    "zs:housing10":0,
    "zs:pop10":0
},
  "geometry": {"coordinates":[-71.344757,44.115689],"type":"Point"}
}