{
  "type": "Feature",
  "properties": {
    "iso:country":"US",
    "name:eng_x_preferred":[
        "Downtown Burlingame"
    ],
    "qs:gn_adm0_cc":"US",
    "qs:gn_local":5331920,
    "qs:gn_nam_loc":"Burlingame, San Mateo, California, US",
    "qs:gn_namadm1":"CA",
    "qs:local_max":2703,
    "qs:local_sum":7771,
    "qs:localhoods":13,
    "qs:name":"Downtown Burlingame",
    "qs:name_adm0":"United States",
    "qs:name_adm1":"California",
    "qs:name_adm2":"San Mateo",
    "qs:name_local":"Burlingame",
    "qs:photo_max":631,
    "qs:photo_sum":2703,
    "qs:placetype":"Suburb",
    "qs:quad_count":33,
    "qs:woe_adm0":23424977,
    "qs:woe_adm1":2347563,
    "qs:woe_adm2":12587710,
    "qs:woe_lau":0,
    "qs:woe_local":2372044,
    "qs:woe_ver":"7.10.0",
    "wof:name":"Downtown Burlingame",
    "wof:placetype":"neighbourhood",
    "wof:population":6403,
    "zs:blockids":[
        60816059001007,
        60816055001009,
        60816055002018,
        60816055003006,
        60816055003005,
        60816055003002,
        60816055003015,
        60816058001012,
        60816059001013,
        60816056002007,
        60816055002006,
        60816055003008,
        60816054003006,
        60816055001011,
        60816055001002,
        60816055001008,
        60816055003007,
        60816055003009,
        60816055003010,
        60816055002002,
        60816058001003,
        60816055003014,
        60816055002009,
        60816055002015,
        60816055002012,
        60816055002020,
        60816058001008,
        60816055002005,
        60816055002007,
        60816055003013,
        60816055003017,
        60816058001005,
        60816055001003,
        60816055001000,
        60816054003008,
        60816053001012,
        60816055003023,
        60816059001005,
        60816056002006,
        60816055002019,
        60816055002000,
        60816055003016,
        60816055003018,
        60816054004012,
        60816055001001,
        60816055002017,
        60816055002011,
        60816055002010,
        60816055003022,
        60816055001007,
        60816055003012,
        60816055003011,
        60816055003020,
        60816055002001,
        60816055003003,
        60816054004011,
        60816055001004,
        60816055001005,
        60816056002008,
        60816056002017,
        60816055001006,
        60816055002004,
        60816058001007,
        60816058001000,
        60816059001004,
        60816058001002,
        60816053001017,
        60816055001010,
        60816055002016,
        60816055002008,
        60816055003004,
        60816059001006,
        60816058001006,
        60816058001001,
        60816053001016,
        60816055001013,
        60816055002013,
        60816055002014,
        60816055003021,
        60816055002003,
        60816054003007,
        60816058001004
    ],
    "zs:housing10":3588,
    "zs:pop10":6403
},
  "geometry": {"coordinates":[-122.345995,37.578923],"type":"Point"}
}