{
  "type": "Feature",
  "properties": {
    "gn:admin1_code":"TN",
    "gn:admin2_code":"115.0",
    "gn:asciiname":"Sulphur Springs",
    "gn:country_code":"US",
    "gn:dem":204,
    "gn:elevation":"202.0",
    "gn:feature_class":"P",
    "gn:feature_code":"PPL",
    "gn:name":"Sulphur Springs",
    "gn:population":0,
    "gn:timezone":"America/Chicago",
    "iso:country":"US",
    "name:cat_x_preferred":[
        "Sulphur Springs"
    ],
    "name:ceb_x_preferred":[
        "Sulphur Springs"
    ],
    "name:deu_x_preferred":[
        "Sulphur Springs"
    ],
    "name:ita_x_preferred":[
        "Sulphur Springs"
    ],
    "name:nld_x_preferred":[
        "Sulphur Springs"
    ],
    "name:pol_x_preferred":[
        "Sulphur Springs"
    ],
    "name:por_x_preferred":[
        "Sulphur Springs"
    ],
    "name:rus_x_preferred":[
        "\u0421\u0430\u043b\u0444\u0435\u0440-\u0421\u043f\u0440\u0438\u043d\u0433\u0441"
    ],
    "name:spa_x_preferred":[
        "Sulphur Springs"
    ],
    "name:srp_x_preferred":[
        "\u0421\u0430\u043b\u0444\u0443\u0440 \u0421\u043f\u0440\u0438\u043d\u0433\u0441"
    ],
    "name:vol_x_preferred":[
        "Sulphur Springs"
    ],
    "wof:name":"Sulphur Springs",
    "wof:placetype":"locality"
},
  "geometry": {"coordinates":[-85.49635000000001,35.1648],"type":"Point"}
}