{
  "type": "Feature",
  "properties": {
    "gn:admin1_code":"OK",
    "gn:admin2_code":"113.0",
    "gn:asciiname":"Pershing",
    "gn:country_code":"US",
    "gn:dem":283,
    "gn:elevation":"280.0",
    "gn:feature_class":"P",
    "gn:feature_code":"PPL",
    "gn:name":"Pershing",
    "gn:population":0,
    "gn:timezone":"America/Chicago",
    "iso:country":"US",
    "name:bul_x_preferred":[
        "\u041f\u044a\u0440\u0448\u0438\u043d\u0433"
    ],
    "name:dan_x_preferred":[
        "Pershing"
    ],
    "name:deu_x_preferred":[
        "Pershing"
    ],
    "name:fra_x_preferred":[
        "Pershing"
    ],
    "name:heb_x_preferred":[
        "\u05e4\u05e8\u05e9\u05d9\u05e0\u05d2"
    ],
    "name:jpn_x_preferred":[
        "\u30d1\u30fc\u30b7\u30f3\u30b0"
    ],
    "name:nld_x_preferred":[
        "Pershing"
    ],
    "name:pol_x_preferred":[
        "Pershing"
    ],
    "name:por_x_preferred":[
        "Pershing"
    ],
    "name:rus_x_preferred":[
        "\u041f\u0435\u0440\u0448\u0438\u043d\u0433"
    ],
    "name:spa_x_preferred":[
        "Pershing"
    ],
    "name:swe_x_preferred":[
        "Pershing"
    ],
    "name:ukr_x_preferred":[
        "\u041f\u0435\u0440\u0448\u0438\u043d\u0433"
    ],
    "wof:name":"Pershing",
    "wof:placetype":"locality"
},
  "geometry": {"coordinates":[-96.27528,36.5934],"type":"Point"}
}