{
  "type": "Feature",
  "properties": {
    "iso:country":"US",
    "name:eng_x_preferred":[
        "Sunset View"
    ],
    "wof:name":"Sunset View",
    "wof:placetype":"neighbourhood",
    "zs:area_m":96859.829093,
    "zs:blockids":[
        50070214091084
    ],
    "zs:housing10":0,
    "zs:label":"Sunset View",
    "zs:pop10":0
},
  "geometry": {"coordinates":[-94.004397,36.338203],"type":"Point"}
}