{
  "type": "Feature",
  "properties": {
    "gn:admin1_code":"MI",
    "gn:admin2_code":"103.0",
    "gn:admin3_code":"71460.0",
    "gn:asciiname":"Cascade",
    "gn:country_code":"US",
    "gn:dem":369,
    "gn:elevation":"374.0",
    "gn:feature_class":"P",
    "gn:feature_code":"PPL",
    "gn:name":"Cascade",
    "gn:population":0,
    "gn:timezone":"America/Detroit",
    "iso:country":"US",
    "name:ceb_x_preferred":[
        "Cascade"
    ],
    "name:deu_x_preferred":[
        "Cascade"
    ],
    "name:fin_x_preferred":[
        "Cascade"
    ],
    "name:fra_x_preferred":[
        "Cascade"
    ],
    "name:hun_x_preferred":[
        "Cascade"
    ],
    "name:hun_x_variant":[
        "Kaszk\u00e1d"
    ],
    "name:ita_x_preferred":[
        "Cascade"
    ],
    "name:nld_x_preferred":[
        "Cascade"
    ],
    "name:pol_x_preferred":[
        "Cascade"
    ],
    "name:por_x_preferred":[
        "Cascade"
    ],
    "name:spa_x_preferred":[
        "Cascade"
    ],
    "name:swe_x_preferred":[
        "Cascade"
    ],
    "name:ukr_x_preferred":[
        "\u041a\u0430\u0441\u043a\u0435\u0439\u0434"
    ],
    "name:vol_x_preferred":[
        "Cascade"
    ],
    "wof:name":"Cascade",
    "wof:placetype":"locality"
},
  "geometry": {"coordinates":[-87.48542,46.44688],"type":"Point"}
}