{
  "type": "Feature",
  "properties": {
    "gn:country":"US",
    "gn:fcode":"PPL",
    "gn:population":14101,
    "iso:country":"US",
    "name:ara_x_preferred":[
        "\u0646\u0648\u0631\u062b \u0631\u064a\u062f\u064a\u0646\u063a"
    ],
    "name:cat_x_preferred":[
        "North Reading"
    ],
    "name:ceb_x_preferred":[
        "North Reading"
    ],
    "name:deu_x_preferred":[
        "North Reading"
    ],
    "name:eng_x_preferred":[
        "North Reading"
    ],
    "name:eus_x_preferred":[
        "North Reading"
    ],
    "name:fas_x_preferred":[
        "\u0631\u06cc\u062f\u06cc\u0646\u06af \u0634\u0645\u0627\u0644\u06cc\u060c \u0645\u0627\u0633\u0627\u0686\u0648\u0633\u062a"
    ],
    "name:fas_x_variant":[
        "\u0631\u06cc\u062f\u06cc\u0646\u06af \u0634\u0645\u0627\u0644\u06cc"
    ],
    "name:fra_x_preferred":[
        "North Reading"
    ],
    "name:hat_x_preferred":[
        "North Reading"
    ],
    "name:hun_x_preferred":[
        "North Reading"
    ],
    "name:ita_x_preferred":[
        "North Reading"
    ],
    "name:jpn_x_preferred":[
        "\u30ce\u30fc\u30b9\u30fb\u30ec\u30c7\u30a3\u30f3\u30b0"
    ],
    "name:kaz_x_preferred":[
        "\u041d\u043e\u0440\u0441 \u0420\u0438\u0434\u0438\u043d\u0433"
    ],
    "name:kir_x_preferred":[
        "\u041d\u043e\u0440\u0441 \u0420\u0438\u0434\u0438\u043d\u0433"
    ],
    "name:nld_x_preferred":[
        "North Reading"
    ],
    "name:pol_x_preferred":[
        "North Reading"
    ],
    "name:por_x_preferred":[
        "North Reading"
    ],
    "name:spa_x_preferred":[
        "North Reading"
    ],
    "name:swa_x_preferred":[
        "North Reading"
    ],
    "name:tur_x_preferred":[
        "North Reading"
    ],
    "name:und_x_variant":[
        "North Parish Village"
    ],
    "name:urd_x_preferred":[
        "\u0634\u0645\u0627\u0644\u06cc \u0631\u06cc\u0688\u0646\u06af\u060c \u0645\u06cc\u0633\u0627\u0686\u0648\u0633\u0679\u0633"
    ],
    "name:urd_x_variant":[
        "\u0634\u0645\u0627\u0644\u06cc \u0631\u06cc\u0688\u0646\u06af"
    ],
    "name:vol_x_preferred":[
        "North Reading"
    ],
    "qs_pg:aaroncc":"US",
    "qs_pg:gn_country":"US",
    "qs_pg:gn_fcode":"PPL",
    "qs_pg:gn_pop":14101,
    "qs_pg:name":"North Reading",
    "qs_pg:name_adm0":"United States",
    "qs_pg:name_adm1":"Massachusetts",
    "qs_pg:photos":5000,
    "qs_pg:photos_1k":1000,
    "qs_pg:photos_9k":22,
    "qs_pg:photos_9r":14,
    "qs_pg:photos_all":5000,
    "qs_pg:photos_sr":24,
    "qs_pg:pop_sr":6,
    "qs_pg:qs_pg_placetype":"locality",
    "qs_pg:qs_pg_placetype_gp":"Town",
    "qs_pg:woe_adm0":23424977,
    "woe:adm0_id":23424977,
    "woe:name_adm0":"United States",
    "woe:name_adm1":"Massachusetts",
    "woe:placetype":"Town",
    "wof:name":"North Reading",
    "wof:placetype":"locality",
    "wof:population":14101
},
  "geometry": {"coordinates":[-71.07867,42.57509],"type":"Point"}
}