{
  "type": "Feature",
  "properties": {
    "iso:country":"US",
    "name:ita_x_preferred":[
        "Fort Wainwright"
    ],
    "name:kor_x_preferred":[
        "\ud3ec\ud2b8 \uc6e8\uc778\ub77c\uc774\ud2b8"
    ],
    "name:ukr_x_preferred":[
        "\u0424\u043e\u0440\u0442 \u0412\u0435\u0439\u043d\u0440\u0430\u0439\u0442"
    ],
    "qs_pg:aaroncc":"US",
    "qs_pg:name":"Fort Wainwright",
    "qs_pg:name_adm0":"United States",
    "qs_pg:name_adm1":"Alaska",
    "qs_pg:photos":347,
    "qs_pg:photos_1k":70,
    "qs_pg:photos_9k":2,
    "qs_pg:photos_9r":5,
    "qs_pg:photos_all":347,
    "qs_pg:photos_sr":5,
    "qs_pg:pop_sr":0,
    "qs_pg:qs_pg_placetype":"locality",
    "qs_pg:qs_pg_placetype_gp":"Town",
    "qs_pg:woe_adm0":23424977,
    "woe:adm0_id":23424977,
    "woe:name_adm0":"United States",
    "woe:name_adm1":"Alaska",
    "woe:placetype":"Town",
    "wof:name":"Fort Wainwright",
    "wof:placetype":"locality"
},
  "geometry": {"coordinates":[-147.62114500000001,64.83344700000001],"type":"Point"}
}