{
  "type": "Feature",
  "properties": {
    "gn:admin1_code":"TN",
    "gn:admin2_code":"31",
    "gn:asciiname":"Farrar Hill",
    "gn:country_code":"US",
    "gn:dem":358,
    "gn:elevation":"342.0",
    "gn:feature_class":"P",
    "gn:feature_code":"PPL",
    "gn:name":"Farrar Hill",
    "gn:population":0,
    "gn:timezone":"America/Chicago",
    "iso:country":"US",
    "wof:name":"Farrar Hill",
    "wof:placetype":"locality"
},
  "geometry": {"coordinates":[-86.16221,35.57813],"type":"Point"}
}