{
  "type": "Feature",
  "properties": {
    "gn:admin1_code":"AR",
    "gn:admin2_code":"123.0",
    "gn:admin3_code":"92340.0",
    "gn:asciiname":"Rosine",
    "gn:country_code":"US",
    "gn:dem":74,
    "gn:elevation":"73.0",
    "gn:feature_class":"P",
    "gn:feature_code":"PPL",
    "gn:name":"Rosine",
    "gn:population":0,
    "gn:timezone":"America/Chicago",
    "iso:country":"US",
    "name:bre_x_preferred":[
        "Rosine"
    ],
    "name:deu_x_preferred":[
        "Rosine"
    ],
    "name:fra_x_preferred":[
        "Rosine"
    ],
    "wof:name":"Rosine",
    "wof:placetype":"locality"
},
  "geometry": {"coordinates":[-90.80428000000001,35.03759],"type":"Point"}
}