{
  "type": "Feature",
  "properties": {
    "iso:country":"US",
    "name:ceb_x_preferred":[
        "Dellwood"
    ],
    "name:deu_x_preferred":[
        "Dellwood"
    ],
    "name:fra_x_preferred":[
        "Dellwood"
    ],
    "name:ido_x_preferred":[
        "Dellwood"
    ],
    "name:ita_x_preferred":[
        "Dellwood"
    ],
    "name:nld_x_preferred":[
        "Dellwood"
    ],
    "name:pol_x_preferred":[
        "Dellwood"
    ],
    "name:srp_x_preferred":[
        "\u0414\u0435\u043b\u0432\u0443\u0434"
    ],
    "name:vol_x_preferred":[
        "Dellwood"
    ],
    "qs_pg:aaroncc":"US",
    "qs_pg:name":"Dellwood",
    "qs_pg:name_adm0":"United States",
    "qs_pg:name_adm1":"New York",
    "qs_pg:photos":5,
    "qs_pg:photos_1k":1,
    "qs_pg:photos_9k":1,
    "qs_pg:photos_9r":1,
    "qs_pg:photos_all":5,
    "qs_pg:photos_sr":1,
    "qs_pg:pop_sr":0,
    "qs_pg:qs_pg_placetype":"neighbourhood",
    "qs_pg:qs_pg_placetype_gp":"Suburb",
    "qs_pg:woe_adm0":23424977,
    "woe:adm0_id":23424977,
    "woe:name_adm0":"United States",
    "woe:name_adm1":"New York",
    "woe:placetype":"Suburb",
    "wof:name":"Dellwood",
    "wof:placetype":"neighbourhood"
},
  "geometry": {"coordinates":[-78.661669,42.917612],"type":"Point"}
}