{
  "type": "Feature",
  "properties": {
    "gn:admin1_code":"MA",
    "gn:admin2_code":"17.0",
    "gn:admin3_code":"45560.0",
    "gn:asciiname":"Oak Hill Park",
    "gn:country_code":"US",
    "gn:dem":37,
    "gn:elevation":"35.0",
    "gn:feature_class":"P",
    "gn:feature_code":"PPL",
    "gn:name":"Oak Hill Park",
    "gn:population":0,
    "gn:timezone":"America/New_York",
    "iso:country":"US",
    "wof:name":"Oak Hill Park",
    "wof:placetype":"locality"
},
  "geometry": {"coordinates":[-71.18561,42.29454000000001],"type":"Point"}
}