{
  "type": "Feature",
  "properties": {
    "gn:admin1_code":"FL",
    "gn:admin2_code":"57",
    "gn:asciiname":"Lumsden Pointe",
    "gn:country_code":"US",
    "gn:dem":31,
    "gn:elevation":"25.0",
    "gn:feature_class":"P",
    "gn:feature_code":"PPL",
    "gn:name":"Lumsden Pointe",
    "gn:population":0,
    "gn:timezone":"America/New_York",
    "iso:country":"US",
    "wof:name":"Lumsden Pointe",
    "wof:placetype":"locality"
},
  "geometry": {"coordinates":[-82.2572,27.9196],"type":"Point"}
}