{
  "type": "Feature",
  "properties": {
    "gn:admin1_code":"LA",
    "gn:admin2_code":"81.0",
    "gn:asciiname":"Crichton",
    "gn:country_code":"US",
    "gn:dem":47,
    "gn:elevation":"43.0",
    "gn:feature_class":"P",
    "gn:feature_code":"PPL",
    "gn:name":"Crichton",
    "gn:population":0,
    "gn:timezone":"America/Chicago",
    "iso:country":"US",
    "name:eng_x_preferred":[
        "Crichton"
    ],
    "name:und_x_variant":[
        "Crichton Station"
    ],
    "wof:name":"Crichton",
    "wof:placetype":"locality"
},
  "geometry": {"coordinates":[-93.43351,32.1246],"type":"Point"}
}