{
  "type": "Feature",
  "properties": {
    "gn:admin1_code":"PA",
    "gn:admin2_code":"69.0",
    "gn:admin3_code":"16664.0",
    "gn:asciiname":"Yostville",
    "gn:country_code":"US",
    "gn:dem":519,
    "gn:elevation":"518.0",
    "gn:feature_class":"P",
    "gn:feature_code":"PPL",
    "gn:name":"Yostville",
    "gn:population":0,
    "gn:timezone":"America/New_York",
    "iso:country":"US",
    "wof:name":"Yostville",
    "wof:placetype":"locality"
},
  "geometry": {"coordinates":[-75.55463,41.29675],"type":"Point"}
}