{
  "type": "Feature",
  "properties": {
    "gn:elevation":81,
    "iso:country":"US",
    "name:eng_x_preferred":[
        "Carlmont"
    ],
    "qs:gn_adm0_cc":"US",
    "qs:gn_fcode":"PPL",
    "qs:gn_local":5327455,
    "qs:gn_nam_loc":"Belmont, San Mateo, California, US",
    "qs:gn_namadm1":"CA",
    "qs:gn_name":"Claremont",
    "qs:local_max":1390,
    "qs:local_sum":3674,
    "qs:localhoods":9,
    "qs:name":"Carlmont",
    "qs:name_adm0":"United States",
    "qs:name_adm1":"California",
    "qs:name_adm2":"San Mateo",
    "qs:name_local":"Belmont",
    "qs:photo_max":19,
    "qs:photo_sum":65,
    "qs:placetype":"Suburb",
    "qs:quad_count":6,
    "qs:woe_adm0":23424977,
    "qs:woe_adm1":2347563,
    "qs:woe_adm2":12587710,
    "qs:woe_lau":0,
    "qs:woe_local":2362268,
    "qs:woe_ver":"7.10.0",
    "wof:name":"Carlmont",
    "wof:placetype":"neighbourhood",
    "wof:population":2561,
    "zs:blockids":[
        60816095001017,
        60816089002002,
        60816090002010,
        60816090002011,
        60816090002012,
        60816090002013,
        60816089002004,
        60816089003013,
        60816089002001,
        60816087005015,
        60816089002000,
        60816096011000,
        60816096011003,
        60816096011001,
        60816089002003,
        60816089002007,
        60816090002016,
        60816089002005,
        60816095001016,
        60816096011002,
        60816090002017,
        60816090002015
    ],
    "zs:housing10":1221,
    "zs:pop10":2561
},
  "geometry": {"coordinates":[-122.295895,37.510346],"type":"Point"}
}