{
  "type": "Feature",
  "properties": {
    "gn:admin1_code":"VA",
    "gn:admin2_code":"179",
    "gn:asciiname":"Brooke",
    "gn:country_code":"US",
    "gn:dem":23,
    "gn:elevation":"21.0",
    "gn:feature_class":"P",
    "gn:feature_code":"PPL",
    "gn:name":"Brooke",
    "gn:population":0,
    "gn:timezone":"America/New_York",
    "iso:country":"US",
    "name:eng_x_preferred":[
        "Brooke"
    ],
    "name:sco_x_preferred":[
        "Brooke"
    ],
    "name:und_x_variant":[
        "Brookes Station",
        "Brookes",
        "Brooke's Station"
    ],
    "wof:name":"Brooke",
    "wof:placetype":"locality"
},
  "geometry": {"coordinates":[-77.3797,38.38763],"type":"Point"}
}