{
  "type": "Feature",
  "properties": {
    "gn:admin1_code":"OK",
    "gn:admin2_code":"93",
    "gn:asciiname":"Cedar Springs",
    "gn:country_code":"US",
    "gn:dem":528,
    "gn:elevation":"521.0",
    "gn:feature_class":"P",
    "gn:feature_code":"PPL",
    "gn:name":"Cedar Springs",
    "gn:population":0,
    "gn:timezone":"America/Chicago",
    "iso:country":"US",
    "name:ceb_x_preferred":[
        "Cedar Springs"
    ],
    "name:deu_x_preferred":[
        "Cedar Springs"
    ],
    "name:ita_x_preferred":[
        "Cedar Springs"
    ],
    "name:srp_x_preferred":[
        "\u0421\u0438\u0434\u0430\u0440 \u0421\u043f\u0440\u0438\u043d\u0433\u0441"
    ],
    "wof:name":"Cedar Springs",
    "wof:placetype":"locality"
},
  "geometry": {"coordinates":[-98.58342,36.21754],"type":"Point"}
}