{
  "type": "Feature",
  "properties": {
    "gn:admin1_code":"LA",
    "gn:admin2_code":"107.0",
    "gn:asciiname":"Tensas Bluff Landing",
    "gn:country_code":"US",
    "gn:dem":24,
    "gn:elevation":"14.0",
    "gn:feature_class":"P",
    "gn:feature_code":"PPL",
    "gn:name":"Tensas Bluff Landing",
    "gn:population":0,
    "gn:timezone":"America/Chicago",
    "iso:country":"US",
    "wof:name":"Tensas Bluff Landing",
    "wof:placetype":"locality"
},
  "geometry": {"coordinates":[-91.40428,32.16487],"type":"Point"}
}