{
  "type": "Feature",
  "properties": {
    "gn:admin1_code":"GA",
    "gn:admin2_code":"59.0",
    "gn:asciiname":"Homewood Hills",
    "gn:country_code":"US",
    "gn:dem":235,
    "gn:elevation":"229.0",
    "gn:feature_class":"P",
    "gn:feature_code":"PPL",
    "gn:name":"Homewood Hills",
    "gn:population":0,
    "gn:timezone":"America/New_York",
    "iso:country":"US",
    "wof:name":"Homewood Hills",
    "wof:placetype":"locality"
},
  "geometry": {"coordinates":[-83.42959999999999,33.97734000000001],"type":"Point"}
}