{
  "type": "Feature",
  "properties": {
    "iso:country":"US",
    "name:deu_x_preferred":[
        "Rosston"
    ],
    "name:eng_x_preferred":[
        "Rosston"
    ],
    "name:hbs_x_preferred":[
        "Roston"
    ],
    "name:ita_x_preferred":[
        "Rosston"
    ],
    "name:nld_x_preferred":[
        "Rosston"
    ],
    "name:pol_x_preferred":[
        "Rosston"
    ],
    "name:srp_x_preferred":[
        "\u0420\u043e\u0441\u0442\u043e\u043d"
    ],
    "name:swe_x_preferred":[
        "Rosston"
    ],
    "name:ukr_x_preferred":[
        "\u0420\u043e\u0441\u0441\u0442\u043e\u043d"
    ],
    "wd:wordcount":18,
    "wof:name":"Rosston",
    "wof:placetype":"neighbourhood",
    "wof:population":1070,
    "zs:area_m":18941005.444192,
    "zs:blockids":[
        420059508004018,
        420059509001005,
        420059509002036,
        420059508004014,
        420059508002010,
        420059508004002,
        420059509001037,
        420059509001017,
        420059509002023,
        420059509002057,
        420059508004001,
        420059509001013,
        420059509002054,
        420059508002014,
        420059508004015,
        420059509001011,
        420059509001003,
        420059509001007,
        420059509001028,
        420059509001030,
        420059509001027,
        420059509002034,
        420059509001002,
        420059509002035,
        420059509001001,
        420059509001009,
        420059509002050,
        420059509001008,
        420059508002013,
        420059509002017,
        420059508002017,
        420059509001036,
        420059509001006,
        420059509001010,
        420059508004017,
        420059509001029,
        420059508004016,
        420059509002051,
        420059509001000,
        420059508002012,
        420059508004000
    ],
    "zs:housing10":594,
    "zs:label":"Rosston",
    "zs:pop10":1070
},
  "geometry": {"coordinates":[-79.49478499999999,40.75953],"type":"Point"}
}