{
  "type": "Feature",
  "properties": {
    "iso:country":"US",
    "name:azb_x_preferred":[
        "\u0627\u0633\u062a\u0631\u0644\u06cc\u0646\u0642 \u067e\u0627\u0631\u06a9"
    ],
    "name:deu_x_preferred":[
        "Sterling Park"
    ],
    "name:eng_x_preferred":[
        "Sterling Park"
    ],
    "name:fas_x_preferred":[
        "\u0627\u0633\u062a\u0631\u0644\u06cc\u0646\u06af \u067e\u0627\u0631\u06a9"
    ],
    "name:nld_x_preferred":[
        "Sterling Park"
    ],
    "name:por_x_preferred":[
        "Sterling Park"
    ],
    "name:vol_x_preferred":[
        "Sterling Park"
    ],
    "qs_pg:aaroncc":"US",
    "qs_pg:name":"Sterling Park",
    "qs_pg:name_adm0":"United States",
    "qs_pg:name_adm1":"Virginia",
    "qs_pg:photos":196,
    "qs_pg:photos_1k":40,
    "qs_pg:photos_9k":1,
    "qs_pg:photos_9r":4,
    "qs_pg:photos_all":196,
    "qs_pg:photos_sr":4,
    "qs_pg:pop_sr":0,
    "qs_pg:qs_pg_placetype":"neighbourhood",
    "qs_pg:qs_pg_placetype_gp":"Suburb",
    "qs_pg:woe_adm0":23424977,
    "woe:adm0_id":23424977,
    "woe:name_adm0":"United States",
    "woe:name_adm1":"Virginia",
    "woe:placetype":"Suburb",
    "wof:name":"Sterling Park",
    "wof:placetype":"neighbourhood",
    "wof:population":2215
},
  "geometry": {"coordinates":[-77.41240550000001,39.018684],"type":"Point"}
}