{
  "type": "Feature",
  "properties": {
    "iso:country":"US",
    "name:ceb_x_preferred":[
        "White Pine"
    ],
    "name:deu_x_preferred":[
        "White Pine"
    ],
    "name:eng_x_preferred":[
        "White Pine"
    ],
    "name:fra_x_preferred":[
        "Pin blanc"
    ],
    "name:ita_x_preferred":[
        "White Pine"
    ],
    "name:pol_x_preferred":[
        "White Pine"
    ],
    "name:rus_x_preferred":[
        "\u0423\u0430\u0439\u0442-\u041f\u0430\u0439\u043d"
    ],
    "name:srp_x_preferred":[
        "\u0412\u0430\u0458\u0442 \u041f\u0430\u0458\u043d"
    ],
    "name:ukr_x_preferred":[
        "\u0412\u0430\u0439\u0442-\u041f\u0430\u0439\u043d"
    ],
    "wof:name":"White Pine",
    "wof:placetype":"neighbourhood",
    "wof:population":89,
    "zs:area_m":29836.879882,
    "zs:blockids":[
        120570001012007,
        120570001012008
    ],
    "zs:housing10":37,
    "zs:label":"White Pine",
    "zs:pop10":89
},
  "geometry": {"coordinates":[-82.408331,28.046333],"type":"Point"}
}