{
  "type": "Feature",
  "properties": {
    "gn:admin1_code":"IL",
    "gn:admin2_code":"31.0",
    "gn:admin3_code":"53676.0",
    "gn:asciiname":"Brockdale Manor",
    "gn:country_code":"US",
    "gn:dem":215,
    "gn:elevation":"208.0",
    "gn:feature_class":"P",
    "gn:feature_code":"PPL",
    "gn:name":"Brockdale Manor",
    "gn:population":0,
    "gn:timezone":"America/Chicago",
    "iso:country":"US",
    "wof:name":"Brockdale Manor",
    "wof:placetype":"locality"
},
  "geometry": {"coordinates":[-87.86,42.10306],"type":"Point"}
}