{
  "type": "Feature",
  "properties": {
    "gn:admin1_code":"MT",
    "gn:admin2_code":"63.0",
    "gn:asciiname":"Bonner Junction",
    "gn:country_code":"US",
    "gn:dem":1004,
    "gn:elevation":"997.0",
    "gn:feature_class":"P",
    "gn:feature_code":"PPL",
    "gn:name":"Bonner Junction",
    "gn:population":0,
    "gn:timezone":"America/Denver",
    "iso:country":"US",
    "wof:name":"Bonner Junction",
    "wof:placetype":"locality"
},
  "geometry": {"coordinates":[-113.88177,46.85993],"type":"Point"}
}