{
  "type": "Feature",
  "properties": {
    "gn:admin1_code":"CA",
    "gn:admin2_code":"97.0",
    "gn:asciiname":"Venado",
    "gn:country_code":"US",
    "gn:dem":357,
    "gn:elevation":"336.0",
    "gn:feature_class":"P",
    "gn:feature_code":"PPL",
    "gn:name":"Venado",
    "gn:population":0,
    "gn:timezone":"America/Los_Angeles",
    "iso:country":"US",
    "name:fas_x_preferred":[
        "\u0648\u0646\u062f\u0648"
    ],
    "name:zho_x_preferred":[
        "\u97cb\u7d0d\u591a"
    ],
    "wof:name":"Venado",
    "wof:placetype":"locality"
},
  "geometry": {"coordinates":[-123.00806,38.60547],"type":"Point"}
}