{
  "type": "Feature",
  "properties": {
    "iso:country":"US",
    "name:eng_x_preferred":[
        "Maxine Jennings"
    ],
    "wof:name":"Maxine Jennings",
    "wof:placetype":"neighbourhood",
    "wof:population":116,
    "zs:area_m":1067367.974002,
    "zs:blockids":[
        370810144061022
    ],
    "zs:housing10":53,
    "zs:label":"Maxine Jennings",
    "zs:pop10":116
},
  "geometry": {"coordinates":[-79.968925,35.970825],"type":"Point"}
}