{
  "type": "Feature",
  "properties": {
    "gn:admin1_code":"TN",
    "gn:admin2_code":"11",
    "gn:asciiname":"Dockery",
    "gn:country_code":"US",
    "gn:dem":285,
    "gn:elevation":"287.0",
    "gn:feature_class":"P",
    "gn:feature_code":"PPL",
    "gn:name":"Dockery",
    "gn:population":0,
    "gn:timezone":"America/New_York",
    "iso:country":"US",
    "name:deu_x_preferred":[
        "Dockery"
    ],
    "name:fra_x_preferred":[
        "Dockery"
    ],
    "wof:name":"Dockery",
    "wof:placetype":"locality"
},
  "geometry": {"coordinates":[-84.88994,35.1173],"type":"Point"}
}