{
  "type": "Feature",
  "properties": {
    "iso:country":"US",
    "name:eng_x_preferred":[
        "Harbor Drive"
    ],
    "name:eng_x_variant":[
        "Harbor",
        "Harbor Dr"
    ],
    "name:spa_x_preferred":[
        "Harbor Drive"
    ],
    "qs:gn_adm0_cc":"US",
    "qs:gn_local":4155966,
    "qs:gn_nam_loc":"Fort Lauderdale, Broward, Florida, US",
    "qs:gn_namadm1":"FL",
    "qs:local_max":9605,
    "qs:local_sum":52477,
    "qs:localhoods":58,
    "qs:name":"Harbor Drive",
    "qs:name_adm0":"United States",
    "qs:name_adm1":"Florida",
    "qs:name_adm2":"Broward",
    "qs:name_local":"Fort Lauderdale",
    "qs:photo_max":774,
    "qs:photo_sum":3604,
    "qs:placetype":"Suburb",
    "qs:quad_count":108,
    "qs:woe_adm0":23424977,
    "qs:woe_adm1":2347568,
    "qs:woe_adm2":12587808,
    "qs:woe_lau":0,
    "qs:woe_local":2405797,
    "qs:woe_ver":"7.10.0",
    "wd:wordcount":1089,
    "wof:name":"Harbor Drive",
    "wof:placetype":"neighbourhood",
    "wof:population":1542,
    "zs:blockids":[
        120110422001029,
        120110422001000,
        120110422001001,
        120110422001008,
        120110422001049,
        120110422001005,
        120110422001002,
        120110422001003,
        120110422001011,
        120110422001042,
        120110421001021,
        120110421002038,
        120110422001010,
        120110422001007,
        120110422001012,
        120110422001028,
        120110422001006,
        120110422001004,
        120110422001040,
        120110422001039,
        120110421002037,
        120110422001041,
        120110422001009,
        120110421002039,
        120110422001054
    ],
    "zs:housing10":1846,
    "zs:pop10":1542
},
  "geometry": {"coordinates":[-80.107919,26.109458],"type":"Point"}
}