{
  "type": "Feature",
  "properties": {
    "iso:country":"US",
    "name:eng_x_preferred":[
        "Echo South Shores"
    ],
    "wof:name":"Echo South Shores",
    "wof:placetype":"neighbourhood",
    "zs:area_m":1019729.423067,
    "zs:blockids":[
        60170320002038
    ],
    "zs:housing10":0,
    "zs:label":"Echo South Shores",
    "zs:pop10":0
},
  "geometry": {"coordinates":[-120.05823599999999,38.83987],"type":"Point"}
}