{
  "type": "Feature",
  "properties": {
    "gn:admin1_code":"VA",
    "gn:admin2_code":"59",
    "gn:asciiname":"Mosby Woods",
    "gn:country_code":"US",
    "gn:dem":116,
    "gn:elevation":"110.0",
    "gn:feature_class":"P",
    "gn:feature_code":"PPL",
    "gn:name":"Mosby Woods",
    "gn:population":0,
    "gn:timezone":"America/New_York",
    "iso:country":"US",
    "wof:name":"Mosby Woods",
    "wof:placetype":"locality"
},
  "geometry": {"coordinates":[-77.29693,38.8665],"type":"Point"}
}