{
  "type": "Feature",
  "properties": {
    "gn:admin1_code":"FL",
    "gn:admin2_code":"9.0",
    "gn:asciiname":"Cocoa Palms Mobile Home Park",
    "gn:country_code":"US",
    "gn:dem":6,
    "gn:elevation":"3.0",
    "gn:feature_class":"P",
    "gn:feature_code":"PPL",
    "gn:name":"Cocoa Palms Mobile Home Park",
    "gn:population":0,
    "gn:timezone":"America/New_York",
    "iso:country":"US",
    "wof:name":"Cocoa Palms Mobile Home Park",
    "wof:placetype":"campus"
},
  "geometry": {"coordinates":[-80.6074,28.3794],"type":"Point"}
}