{
  "type": "Feature",
  "properties": {
    "iso:country":"US",
    "name:ceb_x_preferred":[
        "Harwood"
    ],
    "name:deu_x_preferred":[
        "Harwood"
    ],
    "name:fra_x_preferred":[
        "Harwood"
    ],
    "name:ita_x_preferred":[
        "Harwood"
    ],
    "name:jpn_x_preferred":[
        "\u30cf\u30fc\u30a6\u30c3\u30c9"
    ],
    "name:nds_x_preferred":[
        "Harwood"
    ],
    "name:nld_x_preferred":[
        "Harwood"
    ],
    "name:pol_x_preferred":[
        "Harwood"
    ],
    "name:por_x_preferred":[
        "Harwood"
    ],
    "name:rus_x_preferred":[
        "\u0425\u0430\u0440\u0432\u0443\u0434"
    ],
    "name:srp_x_preferred":[
        "\u0425\u0435\u0440\u0432\u0443\u0434"
    ],
    "name:swe_x_preferred":[
        "Harwood"
    ],
    "name:ukr_x_preferred":[
        "\u0413\u0430\u0440\u0432\u0443\u0434"
    ],
    "name:vol_x_preferred":[
        "Harwood"
    ],
    "wof:name":"Harwood",
    "wof:placetype":"neighbourhood"
},
  "geometry": {"coordinates":[-76.62088631596248,37.22463345016536],"type":"Point"}
}