{
  "type": "Feature",
  "properties": {
    "gn:admin1_code":"VA",
    "gn:admin2_code":"75",
    "gn:asciiname":"Oak Grove Estates",
    "gn:country_code":"US",
    "gn:dem":66,
    "gn:elevation":"71.0",
    "gn:feature_class":"P",
    "gn:feature_code":"PPL",
    "gn:name":"Oak Grove Estates",
    "gn:population":0,
    "gn:timezone":"America/New_York",
    "iso:country":"US",
    "wof:name":"Oak Grove Estates",
    "wof:placetype":"locality"
},
  "geometry": {"coordinates":[-77.6836,37.66709],"type":"Point"}
}