{
  "type": "Feature",
  "properties": {
    "gn:admin1_code":"VT",
    "gn:admin2_code":"5.0",
    "gn:admin3_code":"83500.0",
    "gn:asciiname":"Ramsey Corner",
    "gn:country_code":"US",
    "gn:dem":464,
    "gn:elevation":"466.0",
    "gn:feature_class":"P",
    "gn:feature_code":"PPL",
    "gn:name":"Ramsey Corner",
    "gn:population":0,
    "gn:timezone":"America/New_York",
    "iso:country":"US",
    "name:eng_x_preferred":[
        "Ramsey Corner"
    ],
    "name:und_x_variant":[
        "Ramsay Corner",
        "Ramsey Corners"
    ],
    "wof:name":"Ramsey Corner",
    "wof:placetype":"locality"
},
  "geometry": {"coordinates":[-72.11065000000001,44.57061],"type":"Point"}
}