{
  "type": "Feature",
  "properties": {
    "iso:country":"US",
    "wof:name":"Carolando",
    "wof:placetype":"neighbourhood"
},
  "geometry": {"coordinates":[-80.64869291946293,35.36083731035205],"type":"Point"}
}