{
  "type": "Feature",
  "properties": {
    "gn:admin1_code":"TN",
    "gn:admin2_code":"149.0",
    "gn:asciiname":"Weakley Hills",
    "gn:country_code":"US",
    "gn:dem":164,
    "gn:elevation":"161.0",
    "gn:feature_class":"P",
    "gn:feature_code":"PPL",
    "gn:name":"Weakley Hills",
    "gn:population":0,
    "gn:timezone":"America/Chicago",
    "iso:country":"US",
    "name:eng_x_preferred":[
        "Weakley Hills"
    ],
    "name:und_x_variant":[
        "Weakley Hills Estates"
    ],
    "wof:name":"Weakley Hills",
    "wof:placetype":"locality"
},
  "geometry": {"coordinates":[-86.49027,36.02562],"type":"Point"}
}