{
  "type": "Feature",
  "properties": {
    "gn:country":"US",
    "gn:elevation":110,
    "gn:fcode":"PPLX",
    "gn:population":0,
    "iso:country":"US",
    "name:cym_x_preferred":[
        "Pineview"
    ],
    "name:eng_x_preferred":[
        "Pineview Hills"
    ],
    "name:eng_x_variant":[
        "Pineview Hls",
        "Pineview"
    ],
    "name:fra_x_preferred":[
        "Pineview"
    ],
    "name:spa_x_preferred":[
        "Pineview"
    ],
    "qs:gn_adm0_cc":"US",
    "qs:gn_fcode":"PPLX",
    "qs:gn_local":4459467,
    "qs:gn_nam_loc":"Cary, Wake, North Carolina, US",
    "qs:gn_namadm1":"NC",
    "qs:gn_name":"Pineview Hills",
    "qs:local_max":1353,
    "qs:local_sum":11778,
    "qs:localhoods":52,
    "qs:name":"Pineview Hills",
    "qs:name_adm0":"United States",
    "qs:name_adm1":"North Carolina",
    "qs:name_adm2":"Wake",
    "qs:name_local":"Cary",
    "qs:photo_max":162,
    "qs:photo_sum":841,
    "qs:placetype":"Suburb",
    "qs:quad_count":46,
    "qs:woe_adm0":23424977,
    "qs:woe_adm1":2347592,
    "qs:woe_adm2":12589465,
    "qs:woe_lau":0,
    "qs:woe_local":2375810,
    "qs:woe_ver":"7.10.0",
    "qs_pg:aaroncc":"US",
    "qs_pg:gn_country":"US",
    "qs_pg:gn_fcode":"PPLX",
    "qs_pg:gn_pop":0,
    "qs_pg:name":"Pineview Hills",
    "qs_pg:name_adm0":"United States",
    "qs_pg:name_adm1":"North Carolina",
    "qs_pg:photos":305,
    "qs_pg:photos_1k":62,
    "qs_pg:photos_9k":1,
    "qs_pg:photos_9r":5,
    "qs_pg:photos_all":305,
    "qs_pg:photos_sr":5,
    "qs_pg:pop_sr":0,
    "qs_pg:qs_pg_placetype":"neighbourhood",
    "qs_pg:qs_pg_placetype_gp":"Suburb",
    "qs_pg:woe_adm0":23424977,
    "wd:wordcount":123,
    "wof:lang":[
        "eng"
    ],
    "wof:name":"Pineview Hills",
    "wof:placetype":"neighbourhood",
    "wof:population":465,
    "zs:blockids":[
        371830523011001,
        371830523011002
    ],
    "zs:housing10":293,
    "zs:pop10":465
},
  "geometry": {"coordinates":[-78.69091400000001,35.765496],"type":"Point"}
}