{
  "type": "Feature",
  "properties": {
    "gn:admin1_code":"OH",
    "gn:admin2_code":"111",
    "gn:admin3_code":"81480.0",
    "gn:asciiname":"Rinard Mills",
    "gn:country_code":"US",
    "gn:dem":207,
    "gn:elevation":"209.0",
    "gn:feature_class":"P",
    "gn:feature_code":"PPL",
    "gn:name":"Rinard Mills",
    "gn:population":0,
    "gn:timezone":"America/New_York",
    "iso:country":"US",
    "name:eng_x_preferred":[
        "Rinard Mills"
    ],
    "name:und_x_variant":[
        "Rinards Mill",
        "Rinards Mills",
        "Rinard Mill"
    ],
    "name:vol_x_preferred":[
        "Rinard Mills"
    ],
    "wof:name":"Rinard Mills",
    "wof:placetype":"locality"
},
  "geometry": {"coordinates":[-81.15510999999999,39.5848],"type":"Point"}
}