{
  "type": "Feature",
  "properties": {
    "gn:admin1_code":"SC",
    "gn:admin2_code":"83.0",
    "gn:asciiname":"Meadow Spring",
    "gn:country_code":"US",
    "gn:dem":261,
    "gn:elevation":"260.0",
    "gn:feature_class":"P",
    "gn:feature_code":"PPL",
    "gn:name":"Meadow Spring",
    "gn:population":0,
    "gn:timezone":"America/New_York",
    "iso:country":"US",
    "wof:name":"Meadow Spring",
    "wof:placetype":"locality"
},
  "geometry": {"coordinates":[-81.91677,35.01373],"type":"Point"}
}