{
  "type": "Feature",
  "properties": {
    "iso:country":"US",
    "name:cat_x_preferred":[
        "Fairmount"
    ],
    "name:ceb_x_preferred":[
        "Fairmount"
    ],
    "name:deu_x_preferred":[
        "Fairmount"
    ],
    "name:eng_x_preferred":[
        "Fairmount"
    ],
    "name:est_x_preferred":[
        "Fairmount"
    ],
    "name:ita_x_preferred":[
        "Fairmount"
    ],
    "name:nld_x_preferred":[
        "Fairmount"
    ],
    "name:pol_x_preferred":[
        "Fairmount"
    ],
    "name:por_x_preferred":[
        "Fairmount"
    ],
    "name:spa_x_preferred":[
        "Fairmount"
    ],
    "name:srp_x_preferred":[
        "\u0424\u0435\u0440\u043c\u0430\u0443\u043d\u0442"
    ],
    "name:ukr_x_preferred":[
        "\u0424\u0435\u0439\u0440\u043c\u0430\u0443\u043d\u0442"
    ],
    "name:urd_x_preferred":[
        "\u0641\u06cc\u0626\u0631\u0645\u0627\u0624\u0646\u0679"
    ],
    "name:vol_x_preferred":[
        "Fairmount"
    ],
    "wof:name":"Fairmount",
    "wof:placetype":"neighbourhood",
    "wof:population":272,
    "zs:area_m":7646577.181972,
    "zs:blockids":[
        420710146022028,
        420710146022063,
        420710146022027,
        420710146022002,
        420710146022026,
        420710146022022
    ],
    "zs:housing10":79,
    "zs:label":"Fairmount",
    "zs:pop10":272
},
  "geometry": {"coordinates":[-76.131068,39.823577],"type":"Point"}
}