{
  "type": "Feature",
  "properties": {
    "iso:country":"US",
    "name:ara_x_preferred":[
        "\u0647\u0627\u064a\u0644\u0627\u0646\u062f \u0628\u0627\u0631\u0643"
    ],
    "name:cat_x_preferred":[
        "Highland Park"
    ],
    "name:ceb_x_preferred":[
        "Highland Park"
    ],
    "name:deu_x_preferred":[
        "Highland Park"
    ],
    "name:fra_x_preferred":[
        "Highland Park"
    ],
    "name:hrv_x_preferred":[
        "Highland Park"
    ],
    "name:ita_x_preferred":[
        "Highland Park"
    ],
    "name:jpn_x_preferred":[
        "\u30cf\u30a4\u30e9\u30f3\u30c9\u30fb\u30d1\u30fc\u30af"
    ],
    "name:kor_x_preferred":[
        "\ud558\uc77c\ub79c\ub4dc\ud30c\ud06c"
    ],
    "name:nds_x_preferred":[
        "Highland Park"
    ],
    "name:nld_x_preferred":[
        "Highland Park"
    ],
    "name:nor_x_preferred":[
        "Highland Park"
    ],
    "name:pol_x_preferred":[
        "Highland Park"
    ],
    "name:por_x_preferred":[
        "Highland Park"
    ],
    "name:spa_x_preferred":[
        "Highland Park"
    ],
    "name:srp_x_preferred":[
        "\u0425\u0430\u0458\u043b\u0430\u043d\u0434 \u041f\u0430\u0440\u043a"
    ],
    "name:swa_x_preferred":[
        "Highland Park"
    ],
    "name:ukr_x_preferred":[
        "\u0413\u0430\u0439\u043b\u0435\u043d\u0434-\u041f\u0430\u0440\u043a"
    ],
    "name:vol_x_preferred":[
        "Highland Park"
    ],
    "qs_pg:aaroncc":"US",
    "qs_pg:name":"Highland Park",
    "qs_pg:name_adm0":"United States",
    "qs_pg:name_adm1":"Virginia",
    "qs_pg:photos":1,
    "qs_pg:photos_1k":1,
    "qs_pg:photos_9k":1,
    "qs_pg:photos_9r":1,
    "qs_pg:photos_all":1,
    "qs_pg:photos_sr":1,
    "qs_pg:pop_sr":0,
    "qs_pg:qs_pg_placetype":"neighbourhood",
    "qs_pg:qs_pg_placetype_gp":"Suburb",
    "qs_pg:woe_adm0":23424977,
    "woe:adm0_id":23424977,
    "woe:name_adm0":"United States",
    "woe:name_adm1":"Virginia",
    "woe:placetype":"Suburb",
    "wof:name":"Highland Park",
    "wof:placetype":"neighbourhood"
},
  "geometry": {"coordinates":[-77.45261499999999,37.544347],"type":"Point"}
}