{
  "type": "Feature",
  "properties": {
    "gn:admin1_code":"MN",
    "gn:admin2_code":"111.0",
    "gn:admin3_code":"20906.0",
    "gn:asciiname":"Lakeview Estates",
    "gn:country_code":"US",
    "gn:dem":386,
    "gn:elevation":"390.0",
    "gn:feature_class":"P",
    "gn:feature_code":"PPL",
    "gn:name":"Lakeview Estates",
    "gn:population":0,
    "gn:timezone":"America/Chicago",
    "iso:country":"US",
    "wof:name":"Lakeview Estates",
    "wof:placetype":"locality"
},
  "geometry": {"coordinates":[-96.04806000000001,46.29944],"type":"Point"}
}