{
  "type": "Feature",
  "properties": {
    "iso:country":"US",
    "name:cat_x_preferred":[
        "Rolling Hills"
    ],
    "name:ceb_x_preferred":[
        "Rolling Hills"
    ],
    "name:deu_x_preferred":[
        "Rolling Hills"
    ],
    "name:eng_x_preferred":[
        "Rolling Hills"
    ],
    "name:fra_x_preferred":[
        "Rolling Hills"
    ],
    "name:ita_x_preferred":[
        "Rolling Hills"
    ],
    "name:nld_x_preferred":[
        "Rolling Hills"
    ],
    "name:pol_x_preferred":[
        "Rolling Hills"
    ],
    "name:por_x_preferred":[
        "Rolling Hills"
    ],
    "name:rus_x_preferred":[
        "\u0420\u043e\u043b\u043b\u0438\u043d\u0433-\u0425\u0438\u043b\u0441"
    ],
    "name:srp_x_preferred":[
        "\u0420\u043e\u043b\u0438\u043d\u0433 \u0425\u0438\u043b\u0441"
    ],
    "name:swe_x_preferred":[
        "Rolling Hills"
    ],
    "name:vol_x_preferred":[
        "Rolling Hills"
    ],
    "wd:wordcount":78,
    "wof:name":"Rolling Hills",
    "wof:placetype":"neighbourhood",
    "wof:population":1090,
    "zs:area_m":849158.891458,
    "zs:blockids":[
        201730093021009,
        201730093024008,
        201730093021013,
        201730093024009,
        201730093021008,
        201730093021007
    ],
    "zs:housing10":686,
    "zs:label":"Rolling Hills",
    "zs:pop10":1090
},
  "geometry": {"coordinates":[-97.438849,37.689825],"type":"Point"}
}