{
  "type": "Feature",
  "properties": {
    "gn:admin1_code":"CO",
    "gn:admin2_code":"59",
    "gn:asciiname":"Wandcrest Park",
    "gn:country_code":"US",
    "gn:dem":2530,
    "gn:elevation":"2519.0",
    "gn:feature_class":"P",
    "gn:feature_code":"PPL",
    "gn:name":"Wandcrest Park",
    "gn:population":0,
    "gn:timezone":"America/Denver",
    "iso:country":"US",
    "wof:name":"Wandcrest Park",
    "wof:placetype":"locality"
},
  "geometry": {"coordinates":[-105.39388999999998,39.43554],"type":"Point"}
}