{
  "type": "Feature",
  "properties": {
    "gn:country":"US",
    "gn:fcode":"PPL",
    "gn:population":0,
    "iso:country":"US",
    "name:ara_x_preferred":[
        "\u062c\u0648\u0631\u062c\u062a\u0627\u0648\u0646"
    ],
    "name:cat_x_preferred":[
        "Georgetown"
    ],
    "name:deu_x_preferred":[
        "Georgetown"
    ],
    "name:eng_x_preferred":[
        "Georgetown"
    ],
    "name:eus_x_preferred":[
        "Georgetown"
    ],
    "name:fra_x_preferred":[
        "Georgetown"
    ],
    "name:hat_x_preferred":[
        "Georgetown"
    ],
    "name:hun_x_preferred":[
        "Georgetown"
    ],
    "name:ita_x_preferred":[
        "Georgetown"
    ],
    "name:jpn_x_preferred":[
        "\u30b8\u30e7\u30fc\u30b8\u30bf\u30a6\u30f3"
    ],
    "name:kaz_x_preferred":[
        "\u0414\u0436\u043e\u0440\u0434\u0436\u0442\u0430\u0443\u043d"
    ],
    "name:kir_x_preferred":[
        "\u0414\u0436\u043e\u0440\u0434\u0436\u0442\u0430\u0443\u043d"
    ],
    "name:nld_x_preferred":[
        "Georgetown"
    ],
    "name:pol_x_preferred":[
        "Georgetown"
    ],
    "name:spa_x_preferred":[
        "Georgetown"
    ],
    "name:und_x_variant":[
        "Georgetown Village"
    ],
    "name:urd_x_preferred":[
        "\u062c\u0627\u0631\u062c \u0679\u0627\u0624\u0646\u060c \u0645\u06cc\u0646\u06d2"
    ],
    "name:urd_x_variant":[
        "\u062c\u0627\u0631\u062c \u0679\u0627\u0624\u0646"
    ],
    "name:vol_x_preferred":[
        "Georgetown"
    ],
    "name:zho_x_preferred":[
        "\u55ac\u6cbb\u6566"
    ],
    "qs_pg:aaroncc":"US",
    "qs_pg:gn_country":"US",
    "qs_pg:gn_fcode":"PPL",
    "qs_pg:gn_pop":0,
    "qs_pg:name":"Georgetown",
    "qs_pg:name_adm0":"United States",
    "qs_pg:name_adm1":"Maine",
    "qs_pg:photos":1285,
    "qs_pg:photos_1k":260,
    "qs_pg:photos_9k":7,
    "qs_pg:photos_9r":8,
    "qs_pg:photos_all":1672,
    "qs_pg:photos_sr":12,
    "qs_pg:pop_sr":0,
    "qs_pg:qs_pg_placetype":"locality",
    "qs_pg:qs_pg_placetype_gp":"Town",
    "qs_pg:woe_adm0":23424977,
    "woe:adm0_id":23424977,
    "woe:name_adm0":"United States",
    "woe:name_adm1":"Maine",
    "woe:placetype":"Town",
    "wof:name":"Georgetown",
    "wof:placetype":"locality"
},
  "geometry": {"coordinates":[-69.74670999999999,43.80453],"type":"Point"}
}