{
  "type": "Feature",
  "properties": {
    "gn:admin1_code":"KS",
    "gn:admin2_code":"141.0",
    "gn:admin3_code":"55350.0",
    "gn:asciiname":"Forney",
    "gn:country_code":"US",
    "gn:dem":467,
    "gn:elevation":"464.0",
    "gn:feature_class":"P",
    "gn:feature_code":"PPL",
    "gn:name":"Forney",
    "gn:population":0,
    "gn:timezone":"America/Chicago",
    "iso:country":"US",
    "name:deu_x_preferred":[
        "Forney"
    ],
    "wof:name":"Forney",
    "wof:placetype":"locality"
},
  "geometry": {"coordinates":[-98.62007,39.41557],"type":"Point"}
}