{
  "type": "Feature",
  "properties": {
    "iso:country":"US",
    "name:azb_x_preferred":[
        "\u0648\u0632\u067e\u0631"
    ],
    "name:deu_x_preferred":[
        "Vesper"
    ],
    "name:eng_x_preferred":[
        "Vesper"
    ],
    "name:hun_x_preferred":[
        "Vesper"
    ],
    "name:nld_x_preferred":[
        "Vesper"
    ],
    "qs_pg:aaroncc":"US",
    "qs_pg:name":"Vesper",
    "qs_pg:name_adm0":"United States",
    "qs_pg:name_adm1":"Oregon",
    "qs_pg:photos":46,
    "qs_pg:photos_1k":9,
    "qs_pg:photos_9k":1,
    "qs_pg:photos_9r":2,
    "qs_pg:photos_all":46,
    "qs_pg:photos_sr":2,
    "qs_pg:pop_sr":0,
    "qs_pg:qs_pg_placetype":"locality",
    "qs_pg:qs_pg_placetype_gp":"Town",
    "qs_pg:woe_adm0":23424977,
    "woe:adm0_id":23424977,
    "woe:name_adm0":"United States",
    "woe:name_adm1":"Oregon",
    "woe:placetype":"Town",
    "wof:name":"Vesper",
    "wof:placetype":"locality"
},
  "geometry": {"coordinates":[-123.375349,45.993458],"type":"Point"}
}