{
  "type": "Feature",
  "properties": {
    "gn:country":"US",
    "gn:fcode":"PPL",
    "gn:population":0,
    "iso:country":"US",
    "name:deu_x_preferred":[
        "South Pass City"
    ],
    "name:eng_x_preferred":[
        "South Pass City"
    ],
    "name:fas_x_preferred":[
        "\u0633\u0627\u0648\u062a \u067e\u0633 \u0633\u06cc\u062a\u06cc"
    ],
    "name:nld_x_preferred":[
        "South Pass City"
    ],
    "name:rus_x_preferred":[
        "\u0421\u0430\u0443\u0442-\u041f\u0430\u0441\u0441-\u0421\u0438\u0442\u0438"
    ],
    "name:swe_x_preferred":[
        "South Pass City"
    ],
    "name:vol_x_preferred":[
        "South Pass City"
    ],
    "name:zho_x_preferred":[
        "\u5357\u5c71\u53e3\u57ce"
    ],
    "qs_pg:aaroncc":"US",
    "qs_pg:gn_country":"US",
    "qs_pg:gn_fcode":"PPL",
    "qs_pg:gn_pop":0,
    "qs_pg:name":"South Pass City",
    "qs_pg:name_adm0":"United States",
    "qs_pg:name_adm1":"Wyoming",
    "qs_pg:photos":282,
    "qs_pg:photos_1k":57,
    "qs_pg:photos_9k":1,
    "qs_pg:photos_9r":4,
    "qs_pg:photos_all":282,
    "qs_pg:photos_sr":5,
    "qs_pg:pop_sr":5,
    "qs_pg:qs_pg_placetype":"locality",
    "qs_pg:qs_pg_placetype_gp":"Town",
    "qs_pg:woe_adm0":23424977,
    "woe:adm0_id":23424977,
    "woe:name_adm0":"United States",
    "woe:name_adm1":"Wyoming",
    "woe:placetype":"Town",
    "wof:name":"South Pass City",
    "wof:placetype":"locality"
},
  "geometry": {"coordinates":[-108.79984,42.46829],"type":"Point"}
}