{
  "type": "Feature",
  "properties": {
    "gn:admin1_code":"FL",
    "gn:admin2_code":"57",
    "gn:asciiname":"Nix",
    "gn:country_code":"US",
    "gn:dem":11,
    "gn:elevation":"1.0",
    "gn:feature_class":"P",
    "gn:feature_code":"PPL",
    "gn:name":"Nix",
    "gn:population":0,
    "gn:timezone":"America/New_York",
    "iso:country":"US",
    "name:ast_x_preferred":[
        "Nix"
    ],
    "name:ces_x_preferred":[
        "Nix"
    ],
    "name:deu_x_preferred":[
        "Nix"
    ],
    "name:eus_x_preferred":[
        "Nix"
    ],
    "name:fra_x_preferred":[
        "Nix"
    ],
    "name:glg_x_preferred":[
        "Nix"
    ],
    "name:hye_x_preferred":[
        "\u0546\u056b\u0584\u057d"
    ],
    "name:jpn_x_preferred":[
        "\u30cb\u30c3\u30af\u30b9"
    ],
    "name:nds_x_preferred":[
        "Nix"
    ],
    "name:nld_x_preferred":[
        "Nix"
    ],
    "name:pol_x_preferred":[
        "Nix"
    ],
    "name:rus_x_preferred":[
        "\u041d\u0438\u043a\u0441"
    ],
    "name:spa_x_preferred":[
        "Nix"
    ],
    "wof:name":"Nix",
    "wof:placetype":"locality"
},
  "geometry": {"coordinates":[-82.4889,27.8957],"type":"Point"}
}