{
  "type": "Feature",
  "properties": {
    "gn:admin1_code":"GA",
    "gn:admin2_code":"151.0",
    "gn:asciiname":"Highland Village",
    "gn:country_code":"US",
    "gn:dem":229,
    "gn:elevation":"223.0",
    "gn:feature_class":"P",
    "gn:feature_code":"PPL",
    "gn:name":"Highland Village",
    "gn:population":0,
    "gn:timezone":"America/New_York",
    "iso:country":"US",
    "name:fra_x_preferred":[
        "Highland Village"
    ],
    "name:pol_x_preferred":[
        "Highland Village"
    ],
    "wof:name":"Highland Village",
    "wof:placetype":"locality"
},
  "geometry": {"coordinates":[-84.19131,33.52872],"type":"Point"}
}