{
  "type": "Feature",
  "properties": {
    "gn:admin1_code":"GA",
    "gn:admin2_code":"245.0",
    "gn:asciiname":"Forest Estates",
    "gn:country_code":"US",
    "gn:dem":100,
    "gn:elevation":"92.0",
    "gn:feature_class":"P",
    "gn:feature_code":"PPL",
    "gn:name":"Forest Estates",
    "gn:population":0,
    "gn:timezone":"America/New_York",
    "iso:country":"US",
    "wof:name":"Forest Estates",
    "wof:placetype":"locality"
},
  "geometry": {"coordinates":[-82.07205999999999,33.4793],"type":"Point"}
}