{
  "type": "Feature",
  "properties": {
    "gn:admin1_code":"ME",
    "gn:admin2_code":"27.0",
    "gn:admin3_code":"52845.0",
    "gn:asciiname":"Herricks Corner",
    "gn:country_code":"US",
    "gn:dem":124,
    "gn:elevation":"113.0",
    "gn:feature_class":"P",
    "gn:feature_code":"PPL",
    "gn:name":"Herricks Corner",
    "gn:population":0,
    "gn:timezone":"America/New_York",
    "iso:country":"US",
    "wof:name":"Herricks Corner",
    "wof:placetype":"locality"
},
  "geometry": {"coordinates":[-69.01281,44.35535],"type":"Point"}
}