{
  "type": "Feature",
  "properties": {
    "gn:admin1_code":"UT",
    "gn:admin2_code":"35.0",
    "gn:asciiname":"Merton Park",
    "gn:country_code":"US",
    "gn:dem":1312,
    "gn:elevation":"1308.0",
    "gn:feature_class":"P",
    "gn:feature_code":"PPL",
    "gn:name":"Merton Park",
    "gn:population":0,
    "gn:timezone":"America/Denver",
    "iso:country":"US",
    "name:jpn_x_preferred":[
        "\u30de\u30fc\u30c8\u30f3\u30fb\u30d1\u30fc\u30af"
    ],
    "name:nld_x_preferred":[
        "Merton Park"
    ],
    "name:nor_x_preferred":[
        "Merton Park"
    ],
    "name:pol_x_preferred":[
        "Merton Park"
    ],
    "wof:name":"Merton Park",
    "wof:placetype":"locality"
},
  "geometry": {"coordinates":[-112.10021999999999,40.70717],"type":"Point"}
}