{
  "type": "Feature",
  "properties": {
    "gn:admin1_code":"AR",
    "gn:admin2_code":"21.0",
    "gn:admin3_code":"90232.0",
    "gn:asciiname":"Hickoria",
    "gn:country_code":"US",
    "gn:dem":89,
    "gn:elevation":"87.0",
    "gn:feature_class":"P",
    "gn:feature_code":"PPL",
    "gn:name":"Hickoria",
    "gn:population":0,
    "gn:timezone":"America/Chicago",
    "iso:country":"US",
    "wof:name":"Hickoria",
    "wof:placetype":"locality"
},
  "geometry": {"coordinates":[-90.44344,36.39117],"type":"Point"}
}