{
  "type": "Feature",
  "properties": {
    "gn:admin1_code":"MS",
    "gn:admin2_code":"115",
    "gn:asciiname":"Troy",
    "gn:country_code":"US",
    "gn:dem":154,
    "gn:elevation":"154.0",
    "gn:feature_class":"P",
    "gn:feature_code":"PPL",
    "gn:name":"Troy",
    "gn:population":0,
    "gn:timezone":"America/Chicago",
    "iso:country":"US",
    "wof:name":"Troy",
    "wof:placetype":"locality"
},
  "geometry": {"coordinates":[-88.88506,34.119],"type":"Point"}
}