{
  "type": "Feature",
  "properties": {
    "gn:admin1_code":"WV",
    "gn:admin2_code":"53",
    "gn:asciiname":"Fivemile",
    "gn:country_code":"US",
    "gn:dem":196,
    "gn:elevation":"191.0",
    "gn:feature_class":"P",
    "gn:feature_code":"PPL",
    "gn:name":"Fivemile",
    "gn:population":0,
    "gn:timezone":"America/New_York",
    "iso:country":"US",
    "name:eng_x_preferred":[
        "Fivemile"
    ],
    "name:und_x_variant":[
        "Five Mile"
    ],
    "wof:name":"Fivemile",
    "wof:placetype":"locality"
},
  "geometry": {"coordinates":[-82.08153,38.75092],"type":"Point"}
}