{
  "type": "Feature",
  "properties": {
    "gn:admin1_code":"PA",
    "gn:admin2_code":"39.0",
    "gn:admin3_code":"7032.0",
    "gn:asciiname":"Rootville",
    "gn:country_code":"US",
    "gn:dem":409,
    "gn:elevation":"408.0",
    "gn:feature_class":"P",
    "gn:feature_code":"PPL",
    "gn:name":"Rootville",
    "gn:population":0,
    "gn:timezone":"America/New_York",
    "iso:country":"US",
    "wof:name":"Rootville",
    "wof:placetype":"locality"
},
  "geometry": {"coordinates":[-79.87089,41.77478],"type":"Point"}
}