{
  "type": "Feature",
  "properties": {
    "gn:elevation":24,
    "iso:country":"US",
    "name:eng_x_preferred":[
        "Taylors Mills"
    ],
    "name:eng_x_variant":[
        "Taylors Mls"
    ],
    "name:fra_x_preferred":[
        "Taylors Mills"
    ],
    "name:nld_x_preferred":[
        "Taylors Mills"
    ],
    "wd:wordcount":53,
    "wof:lang":[
        "eng"
    ],
    "wof:name":"Taylors Mills",
    "wof:placetype":"neighbourhood",
    "wof:population":6042,
    "zs:blockids":[
        340258103001000,
        340258100041003,
        340258100041013,
        340258100043003,
        340258102002014,
        340258100032002,
        340258100013024,
        340258100013022,
        340258103001001,
        340258100013023,
        340258100041009,
        340258102001020,
        340258100043002,
        340258100032006,
        340258100041011,
        340258102001023,
        340258102002015,
        340258100013026,
        340258100013028,
        340258103001024,
        340258103001017,
        340258103001028,
        340258103001022,
        340258103001030,
        340258100041012,
        340258103001027,
        340258100041001,
        340258103001016,
        340258102001009,
        340258103001037,
        340258100041006,
        340258102001018,
        340258100043014,
        340258102001012,
        340258100013029,
        340258100041008,
        340258103001006,
        340258103001026,
        340258103001025,
        340258102002018,
        340258100032003,
        340258100013021,
        340258100013027,
        340258103001033,
        340258102001017,
        340258102001013,
        340258103001002,
        340258100043001,
        340258103001032,
        340258100032001,
        340258100013025,
        340258102001016,
        340258103001018,
        340258103001020,
        340258103001029,
        340258103001023,
        340258103001035,
        340258103001031,
        340258100041014,
        340258100041007,
        340258100043006,
        340258102002025,
        340258102001019,
        340258103001005,
        340258103001036,
        340258102001015,
        340258100013019,
        340258100013020,
        340258103001019,
        340258100013018,
        340258100043005,
        340258100032004,
        340258102002026,
        340258100043004,
        340258100032005,
        340258103001004,
        340258103001003,
        340258103001021,
        340258102001022,
        340258102001021,
        340258100041010,
        340258100041005,
        340258100041004,
        340258102001014,
        340258103001034
    ],
    "zs:housing10":1990,
    "zs:pop10":6042
},
  "geometry": {"coordinates":[-74.358529,40.296106],"type":"Point"}
}