{
  "type": "Feature",
  "properties": {
    "gn:admin1_code":"PA",
    "gn:admin2_code":"55.0",
    "gn:admin3_code":"80992.0",
    "gn:asciiname":"Sylvan",
    "gn:country_code":"US",
    "gn:dem":154,
    "gn:elevation":"152.0",
    "gn:feature_class":"P",
    "gn:feature_code":"PPL",
    "gn:name":"Sylvan",
    "gn:population":0,
    "gn:timezone":"America/New_York",
    "iso:country":"US",
    "wof:name":"Sylvan",
    "wof:placetype":"locality"
},
  "geometry": {"coordinates":[-78.02167,39.75343],"type":"Point"}
}