{
  "type": "Feature",
  "properties": {
    "gn:admin1_code":"FL",
    "gn:admin2_code":"31.0",
    "gn:asciiname":"Study Estates Mobile Home Park",
    "gn:country_code":"US",
    "gn:dem":11,
    "gn:elevation":"7.0",
    "gn:feature_class":"P",
    "gn:feature_code":"PPL",
    "gn:name":"Study Estates Mobile Home Park",
    "gn:population":0,
    "gn:timezone":"America/New_York",
    "iso:country":"US",
    "wof:name":"Study Estates Mobile Home Park",
    "wof:placetype":"campus"
},
  "geometry": {"coordinates":[-81.75287,30.39983],"type":"Point"}
}