{
  "type": "Feature",
  "properties": {
    "gn:admin1_code":"VA",
    "gn:admin2_code":"63",
    "gn:asciiname":"Carthage",
    "gn:country_code":"US",
    "gn:dem":729,
    "gn:elevation":"733.0",
    "gn:feature_class":"P",
    "gn:feature_code":"PPL",
    "gn:name":"Carthage",
    "gn:population":0,
    "gn:timezone":"America/New_York",
    "iso:country":"US",
    "wof:name":"Carthage",
    "wof:placetype":"locality"
},
  "geometry": {"coordinates":[-80.49589,36.96763],"type":"Point"}
}