{
  "type": "Feature",
  "properties": {
    "gn:admin1_code":"VA",
    "gn:admin2_code":"49",
    "gn:asciiname":"Sunny Side",
    "gn:country_code":"US",
    "gn:dem":113,
    "gn:elevation":"113.0",
    "gn:feature_class":"P",
    "gn:feature_code":"PPL",
    "gn:name":"Sunny Side",
    "gn:population":0,
    "gn:timezone":"America/New_York",
    "iso:country":"US",
    "name:eng_x_preferred":[
        "Sunny Side"
    ],
    "name:und_x_variant":[
        "Sunnyside"
    ],
    "wof:name":"Sunny Side",
    "wof:placetype":"locality"
},
  "geometry": {"coordinates":[-78.15916,37.47932],"type":"Point"}
}