{
  "type": "Feature",
  "properties": {
    "gn:admin1_code":"OH",
    "gn:admin2_code":"81.0",
    "gn:admin3_code":"37534.0",
    "gn:asciiname":"Markle",
    "gn:country_code":"US",
    "gn:dem":223,
    "gn:elevation":"226.0",
    "gn:feature_class":"P",
    "gn:feature_code":"PPL",
    "gn:name":"Markle",
    "gn:population":0,
    "gn:timezone":"America/New_York",
    "iso:country":"US",
    "name:deu_x_preferred":[
        "Markle"
    ],
    "name:fra_x_preferred":[
        "Markle"
    ],
    "name:ita_x_preferred":[
        "Markle"
    ],
    "name:spa_x_preferred":[
        "Markle"
    ],
    "wof:name":"Markle",
    "wof:placetype":"locality"
},
  "geometry": {"coordinates":[-80.6173,40.45007],"type":"Point"}
}