{
  "type": "Feature",
  "properties": {
    "gn:country":"US",
    "gn:fcode":"PPL",
    "gn:population":0,
    "iso:country":"US",
    "name:eng_x_preferred":[
        "Roxburg"
    ],
    "name:und_x_variant":[
        "Roxburgh"
    ],
    "qs_pg:aaroncc":"US",
    "qs_pg:gn_country":"US",
    "qs_pg:gn_fcode":"PPL",
    "qs_pg:gn_pop":0,
    "qs_pg:name":"Roxburg",
    "qs_pg:name_adm0":"United States",
    "qs_pg:name_adm1":"New Jersey",
    "qs_pg:photos":2,
    "qs_pg:photos_1k":1,
    "qs_pg:photos_9k":1,
    "qs_pg:photos_9r":1,
    "qs_pg:photos_all":2,
    "qs_pg:photos_sr":1,
    "qs_pg:pop_sr":0,
    "qs_pg:qs_pg_placetype":"neighbourhood",
    "qs_pg:qs_pg_placetype_gp":"Suburb",
    "qs_pg:woe_adm0":23424977,
    "wof:name":"Roxburg",
    "wof:placetype":"neighbourhood",
    "wof:population":16,
    "zs:area_m":376530.421376,
    "zs:blockids":[
        340410316013064
    ],
    "zs:housing10":5,
    "zs:label":"Roxburg",
    "zs:pop10":16
},
  "geometry": {"coordinates":[-75.094362,40.786945],"type":"Point"}
}