{
  "type": "Feature",
  "properties": {
    "iso:country":"US",
    "name:deu_x_preferred":[
        "Redstone"
    ],
    "name:eng_x_preferred":[
        "Redstone"
    ],
    "name:fra_x_preferred":[
        "Redstone"
    ],
    "name:jpn_x_preferred":[
        "\u30ec\u30c3\u30c9\u30b9\u30c8\u30fc\u30f3"
    ],
    "name:kor_x_preferred":[
        "\ub808\ub4dc\uc2a4\ud1a4"
    ],
    "name:pol_x_preferred":[
        "Redstone"
    ],
    "name:swe_x_preferred":[
        "Redstone"
    ],
    "name:vol_x_preferred":[
        "Redstone"
    ],
    "wd:wordcount":346,
    "wof:name":"Redstone",
    "wof:placetype":"neighbourhood",
    "wof:population":114,
    "zs:area_m":326485.690717,
    "zs:blockids":[
        471630429003000,
        471630429002010,
        471630429002008,
        471630429002006,
        471630429002007
    ],
    "zs:housing10":58,
    "zs:label":"Redstone",
    "zs:pop10":114
},
  "geometry": {"coordinates":[-82.135221,36.592874],"type":"Point"}
}