{
  "type": "Feature",
  "properties": {
    "gn:admin1_code":"KY",
    "gn:admin2_code":"103",
    "gn:asciiname":"Sligo",
    "gn:country_code":"US",
    "gn:dem":269,
    "gn:elevation":"268.0",
    "gn:feature_class":"P",
    "gn:feature_code":"PPL",
    "gn:name":"Sligo",
    "gn:population":0,
    "gn:timezone":"America/New_York",
    "iso:country":"US",
    "name:ara_x_preferred":[
        "\u0633\u0644\u0627\u064a\u063a\u0648"
    ],
    "name:ben_x_preferred":[
        "\u09b8\u09bf\u09b2\u0997\u09cb"
    ],
    "name:bre_x_preferred":[
        "Sligeach"
    ],
    "name:bul_x_preferred":[
        "\u0421\u043b\u0430\u0439\u0433\u043e"
    ],
    "name:cat_x_preferred":[
        "Sligo"
    ],
    "name:ceb_x_preferred":[
        "Sligo"
    ],
    "name:ces_x_preferred":[
        "Sligo"
    ],
    "name:cym_x_preferred":[
        "Sligeach"
    ],
    "name:dan_x_preferred":[
        "Sligo"
    ],
    "name:deu_x_preferred":[
        "Sligo"
    ],
    "name:epo_x_preferred":[
        "Sligo"
    ],
    "name:est_x_preferred":[
        "Sligo"
    ],
    "name:eus_x_preferred":[
        "Sligo"
    ],
    "name:fas_x_preferred":[
        "\u0627\u0633\u0644\u0627\u06cc\u06af\u0648"
    ],
    "name:fin_x_preferred":[
        "Sligo"
    ],
    "name:fra_x_preferred":[
        "Sligo"
    ],
    "name:gla_x_preferred":[
        "Sligeach"
    ],
    "name:gle_x_preferred":[
        "Sligeach"
    ],
    "name:glg_x_preferred":[
        "Sligo"
    ],
    "name:glv_x_preferred":[
        "Shliggagh"
    ],
    "name:heb_x_preferred":[
        "\u05e1\u05dc\u05d9\u05d9\u05d2\u05d5"
    ],
    "name:hin_x_preferred":[
        "\u0938\u094d\u0932\u093f\u0917\u094b"
    ],
    "name:hun_x_preferred":[
        "Sligo"
    ],
    "name:ido_x_preferred":[
        "Sligo"
    ],
    "name:ind_x_preferred":[
        "Sligo"
    ],
    "name:ita_x_preferred":[
        "Sligo"
    ],
    "name:jpn_x_preferred":[
        "\u30b9\u30e9\u30a4\u30b4"
    ],
    "name:kat_x_preferred":[
        "\u10e1\u10da\u10d0\u10d8\u10d2\u10dd"
    ],
    "name:kor_x_preferred":[
        "\uc2ac\ub77c\uc774\uace0"
    ],
    "name:lit_x_preferred":[
        "Slaigo"
    ],
    "name:mlt_x_preferred":[
        "Sligo"
    ],
    "name:nld_x_preferred":[
        "Sligo"
    ],
    "name:nno_x_preferred":[
        "Sligo"
    ],
    "name:nor_x_preferred":[
        "Sligo"
    ],
    "name:oss_x_preferred":[
        "\u0421\u043b\u0430\u0439\u0433\u043e"
    ],
    "name:pms_x_preferred":[
        "Sligo"
    ],
    "name:pol_x_preferred":[
        "Sligo"
    ],
    "name:por_x_preferred":[
        "Sligo"
    ],
    "name:rus_x_preferred":[
        "\u0421\u043b\u0430\u0439\u0433\u043e"
    ],
    "name:slk_x_preferred":[
        "Sligo"
    ],
    "name:slv_x_preferred":[
        "Sligo"
    ],
    "name:spa_x_preferred":[
        "Sligo"
    ],
    "name:srd_x_preferred":[
        "Sligo"
    ],
    "name:srp_x_preferred":[
        "\u0421\u043b\u0430\u0458\u0433\u043e"
    ],
    "name:swa_x_preferred":[
        "Sligo"
    ],
    "name:swe_x_preferred":[
        "Sligo"
    ],
    "name:tur_x_preferred":[
        "Sligo"
    ],
    "name:ukr_x_preferred":[
        "\u0421\u043b\u0430\u0439\u0433\u043e"
    ],
    "name:urd_x_preferred":[
        "\u0633\u0644\u06cc\u06af\u0648"
    ],
    "name:vie_x_preferred":[
        "Sligo"
    ],
    "name:wuu_x_preferred":[
        "\u65af\u83b1\u6208"
    ],
    "name:zho_x_preferred":[
        "\u65af\u83b1\u6208"
    ],
    "wof:name":"Sligo",
    "wof:placetype":"locality"
},
  "geometry": {"coordinates":[-85.31328999999999,38.48895],"type":"Point"}
}