{
  "type": "Feature",
  "properties": {
    "gn:elevation":102,
    "iso:country":"US",
    "name:eng_x_preferred":[
        "Landisville"
    ],
    "name:und_x_variant":[
        "Ely"
    ],
    "qs:gn_adm0_cc":"US",
    "qs:gn_fcode":"PPL",
    "qs:gn_local":5206646,
    "qs:gn_nam_loc":"Plumstead, Bucks, Pennsylvania, US",
    "qs:gn_namadm1":"PA",
    "qs:gn_name":"Landisville",
    "qs:local_max":244,
    "qs:local_sum":321,
    "qs:localhoods":3,
    "qs:name":"Landisville",
    "qs:name_adm0":"United States",
    "qs:name_adm1":"Pennsylvania",
    "qs:name_adm2":"Bucks",
    "qs:name_local":"Plumstead",
    "qs:photo_max":28,
    "qs:photo_sum":60,
    "qs:placetype":"Suburb",
    "qs:quad_count":7,
    "qs:woe_adm0":23424977,
    "qs:woe_adm1":2347597,
    "qs:woe_adm2":12589736,
    "qs:woe_lau":0,
    "qs:woe_local":28745209,
    "qs:woe_ver":"7.10.0",
    "wof:lang":[
        "eng"
    ],
    "wof:name":"Landisville",
    "wof:placetype":"neighbourhood",
    "wof:population":6690,
    "zs:blockids":[
        420171045061027,
        420171045053017,
        420171045053009,
        420171045051008,
        420171045053016,
        420171042031002,
        420171045061010,
        420171045051014,
        420171042031006,
        420171045053004,
        420171045061007,
        420171042011064,
        420171042031001,
        420171045051000,
        420171045053007,
        420171045061009,
        420171045061011,
        420171045051011,
        420171045051007,
        420171045051001,
        420171045053005,
        420171045053008,
        420171045051003,
        420171045051017,
        420171045052000,
        420171045053011,
        420171045031001,
        420171045052001,
        420171045051004,
        420171045052003,
        420171045051013,
        420171045053010,
        420171045053002,
        420171045052004,
        420171045031014,
        420171045051009,
        420171045053012,
        420171045053015,
        420171045061026,
        420171045051012,
        420171045053001,
        420171045053000,
        420171045053013,
        420171045052007,
        420171045061008,
        420171045051006,
        420171045051010,
        420171045061029,
        420171045061000,
        420171045061001,
        420171045053006,
        420171045051002,
        420171045051005,
        420171045053014,
        420171045052002,
        420171045051016,
        420171045051015,
        420171045053003
    ],
    "zs:housing10":2117,
    "zs:pop10":6690
},
  "geometry": {"coordinates":[-75.104553,40.353033],"type":"Point"}
}