{
  "type": "Feature",
  "properties": {
    "gn:admin1_code":"MO",
    "gn:admin2_code":"67.0",
    "gn:admin3_code":"69626.0",
    "gn:asciiname":"Smallett",
    "gn:country_code":"US",
    "gn:dem":326,
    "gn:elevation":"320.0",
    "gn:feature_class":"P",
    "gn:feature_code":"PPL",
    "gn:name":"Smallett",
    "gn:population":0,
    "gn:timezone":"America/Chicago",
    "iso:country":"US",
    "name:fas_x_preferred":[
        "\u0627\u0633\u0645\u0627\u0644\u062a"
    ],
    "name:vol_x_preferred":[
        "Smallett"
    ],
    "wof:name":"Smallett",
    "wof:placetype":"locality"
},
  "geometry": {"coordinates":[-92.71406,36.84867],"type":"Point"}
}