{
  "type": "Feature",
  "properties": {
    "iso:country":"US",
    "name:deu_x_preferred":[
        "Stettler"
    ],
    "name:eng_x_preferred":[
        "Stettler"
    ],
    "name:rus_x_preferred":[
        "\u0428\u0442\u0435\u0442\u0442\u043b\u0435\u0440"
    ],
    "wd:wordcount":51,
    "wof:name":"Stettler",
    "wof:placetype":"neighbourhood",
    "wof:population":29,
    "zs:area_m":12576.454167,
    "zs:blockids":[
        490572001002006
    ],
    "zs:housing10":11,
    "zs:label":"Stettler",
    "zs:pop10":29
},
  "geometry": {"coordinates":[-111.945815,41.2605],"type":"Point"}
}