{
  "type": "Feature",
  "properties": {
    "iso:country":"US",
    "name:deu_x_preferred":[
        "Stettler"
    ],
    "name:eng_x_preferred":[
        "Stettler"
    ],
    "name:rus_x_preferred":[
        "\u0421\u0442\u0435\u0442\u043b\u0435\u0440"
    ],
    "name:rus_x_variant":[
        "\u0428\u0442\u0435\u0442\u0442\u043b\u0435\u0440"
    ],
    "name:tur_x_preferred":[
        "Stettler"
    ],
    "name:urd_x_preferred":[
        "\u0633\u0679\u06cc\u0679\u0644\u0631"
    ],
    "name:vie_x_preferred":[
        "Stettler"
    ],
    "name:zho_cn_x_preferred":[
        "\u65af\u6cf0\u7279\u52d2"
    ],
    "name:zho_tw_x_preferred":[
        "\u65af\u6234\u5fb7\u52d2"
    ],
    "wd:wordcount":51,
    "wof:name":"Stettler",
    "wof:placetype":"neighbourhood",
    "wof:population":29,
    "zs:area_m":12576.454167,
    "zs:blockids":[
        490572001002006
    ],
    "zs:housing10":11,
    "zs:label":"Stettler",
    "zs:pop10":29
},
  "geometry": {"coordinates":[-111.945815,41.2605],"type":"Point"}
}