{
  "type": "Feature",
  "properties": {
    "gn:admin1_code":"MD",
    "gn:admin2_code":"21.0",
    "gn:asciiname":"Glade Creek",
    "gn:country_code":"US",
    "gn:dem":102,
    "gn:elevation":"109.0",
    "gn:feature_class":"P",
    "gn:feature_code":"PPL",
    "gn:name":"Glade Creek",
    "gn:population":0,
    "gn:timezone":"America/New_York",
    "iso:country":"US",
    "name:ceb_x_preferred":[
        "Glade Creek"
    ],
    "name:swe_x_preferred":[
        "Glade Creek"
    ],
    "wof:name":"Glade Creek",
    "wof:placetype":"locality"
},
  "geometry": {"coordinates":[-77.34331999999998,39.51955],"type":"Point"}
}