{
  "type": "Feature",
  "properties": {
    "gn:admin1_code":"ME",
    "gn:admin2_code":"31.0",
    "gn:admin3_code":"70030.0",
    "gn:asciiname":"Boyd Corner",
    "gn:country_code":"US",
    "gn:dem":55,
    "gn:elevation":"52.0",
    "gn:feature_class":"P",
    "gn:feature_code":"PPL",
    "gn:name":"Boyd Corner",
    "gn:population":0,
    "gn:timezone":"America/New_York",
    "iso:country":"US",
    "wof:name":"Boyd Corner",
    "wof:placetype":"locality"
},
  "geometry": {"coordinates":[-70.71366999999999,43.29647],"type":"Point"}
}