{
  "type": "Feature",
  "properties": {
    "gn:admin1_code":"WV",
    "gn:admin2_code":"77",
    "gn:asciiname":"Hiram",
    "gn:country_code":"US",
    "gn:dem":389,
    "gn:elevation":"390.0",
    "gn:feature_class":"P",
    "gn:feature_code":"PPL",
    "gn:name":"Hiram",
    "gn:population":0,
    "gn:timezone":"America/New_York",
    "iso:country":"US",
    "wof:name":"Hiram",
    "wof:placetype":"locality"
},
  "geometry": {"coordinates":[-79.9323,39.29315],"type":"Point"}
}