{
  "type": "Feature",
  "properties": {
    "gn:country":"US",
    "gn:elevation":260,
    "gn:fcode":"PPL",
    "gn:population":0,
    "iso:country":"US",
    "name:cat_x_preferred":[
        "New Boston"
    ],
    "name:ceb_x_preferred":[
        "New Boston"
    ],
    "name:deu_x_preferred":[
        "New Boston"
    ],
    "name:eng_x_preferred":[
        "New Boston"
    ],
    "name:fra_x_preferred":[
        "New Boston"
    ],
    "name:hbs_x_preferred":[
        "Nju Boston"
    ],
    "name:ita_x_preferred":[
        "New Boston"
    ],
    "name:kor_x_preferred":[
        "\ub274\ubcf4\uc2a4\ud134"
    ],
    "name:nld_x_preferred":[
        "New Boston"
    ],
    "name:pol_x_preferred":[
        "New Boston"
    ],
    "name:srp_x_preferred":[
        "\u040a\u0443 \u0411\u043e\u0441\u0442\u043e\u043d"
    ],
    "name:swe_x_preferred":[
        "New Boston"
    ],
    "name:vol_x_preferred":[
        "New Boston"
    ],
    "qs_pg:aaroncc":"US",
    "qs_pg:gn_country":"US",
    "qs_pg:gn_fcode":"PPL",
    "qs_pg:gn_pop":0,
    "qs_pg:name":"New Boston",
    "qs_pg:name_adm0":"United States",
    "qs_pg:name_adm1":"Massachusetts",
    "qs_pg:photos":4,
    "qs_pg:photos_1k":1,
    "qs_pg:photos_9k":1,
    "qs_pg:photos_9r":1,
    "qs_pg:photos_all":4,
    "qs_pg:photos_sr":1,
    "qs_pg:pop_sr":0,
    "qs_pg:qs_pg_placetype":"neighbourhood",
    "qs_pg:qs_pg_placetype_gp":"Suburb",
    "qs_pg:woe_adm0":23424977,
    "woe:adm0_id":23424977,
    "woe:name_adm0":"United States",
    "woe:name_adm1":"Massachusetts",
    "woe:placetype":"Suburb",
    "wof:name":"New Boston",
    "wof:placetype":"neighbourhood",
    "wof:population":181
},
  "geometry": {"coordinates":[-73.07594,42.0937],"type":"Point"}
}