{
  "type": "Feature",
  "properties": {
    "gn:admin1_code":"IN",
    "gn:admin2_code":"5.0",
    "gn:admin3_code":"81656.0",
    "gn:asciiname":"Bethel Village",
    "gn:country_code":"US",
    "gn:dem":188,
    "gn:elevation":"186.0",
    "gn:feature_class":"P",
    "gn:feature_code":"PPL",
    "gn:name":"Bethel Village",
    "gn:population":0,
    "gn:timezone":"America/Indiana/Indianapolis",
    "iso:country":"US",
    "wof:name":"Bethel Village",
    "wof:placetype":"locality"
},
  "geometry": {"coordinates":[-85.92471,39.152],"type":"Point"}
}