{
  "type": "Feature",
  "properties": {
    "gn:admin1_code":"KY",
    "gn:admin2_code":"169",
    "gn:asciiname":"Echo",
    "gn:country_code":"US",
    "gn:dem":271,
    "gn:elevation":"271.0",
    "gn:feature_class":"P",
    "gn:feature_code":"PPL",
    "gn:name":"Echo",
    "gn:population":0,
    "gn:timezone":"America/Chicago",
    "iso:country":"US",
    "name:azb_x_preferred":[
        "\u0627\u06a9\u0648"
    ],
    "name:fas_x_preferred":[
        "\u0627\u06a9\u0648"
    ],
    "name:urd_x_preferred":[
        "\u0627\u06cc\u06a9\u0648"
    ],
    "wof:name":"Echo",
    "wof:placetype":"locality"
},
  "geometry": {"coordinates":[-85.74746999999998,37.02783],"type":"Point"}
}