{
  "type": "Feature",
  "properties": {
    "gn:admin1_code":"TX",
    "gn:admin2_code":"481.0",
    "gn:asciiname":"Bonus",
    "gn:country_code":"US",
    "gn:dem":48,
    "gn:elevation":"45.0",
    "gn:feature_class":"P",
    "gn:feature_code":"PPL",
    "gn:name":"Bonus",
    "gn:population":0,
    "gn:timezone":"America/Chicago",
    "iso:country":"US",
    "name:fas_x_preferred":[
        "\u0628\u0648\u0646\u0648\u0633"
    ],
    "wof:name":"Bonus",
    "wof:placetype":"locality"
},
  "geometry": {"coordinates":[-96.2808,29.45163],"type":"Point"}
}