{
  "type": "Feature",
  "properties": {
    "iso:country":"US",
    "name:eng_x_preferred":[
        "Franklin-Eastern"
    ],
    "wof:name":"Franklin-Eastern",
    "wof:placetype":"neighbourhood"
},
  "geometry": {"coordinates":[-85.64870529330891,42.94809330947982],"type":"Point"}
}