{
  "type": "Feature",
  "properties": {
    "gn:admin1_code":"PA",
    "gn:admin2_code":"97.0",
    "gn:admin3_code":"20976.0",
    "gn:asciiname":"Potts Grove",
    "gn:country_code":"US",
    "gn:dem":154,
    "gn:elevation":"149.0",
    "gn:feature_class":"P",
    "gn:feature_code":"PPL",
    "gn:name":"Potts Grove",
    "gn:population":0,
    "gn:timezone":"America/New_York",
    "iso:country":"US",
    "name:eng_x_preferred":[
        "Potts Grove"
    ],
    "name:und_x_variant":[
        "Pottsgrove"
    ],
    "wof:name":"Potts Grove",
    "wof:placetype":"locality"
},
  "geometry": {"coordinates":[-76.78913,40.9937],"type":"Point"}
}