{
  "type": "Feature",
  "properties": {
    "gn:country":"US",
    "gn:fcode":"PPL",
    "gn:population":0,
    "iso:country":"US",
    "name:eng_x_preferred":[
        "Ekastown"
    ],
    "qs_pg:aaroncc":"US",
    "qs_pg:gn_country":"US",
    "qs_pg:gn_fcode":"PPL",
    "qs_pg:gn_pop":0,
    "qs_pg:name":"Ekastown",
    "qs_pg:name_adm0":"United States",
    "qs_pg:name_adm1":"Pennsylvania",
    "qs_pg:photos":26,
    "qs_pg:photos_1k":5,
    "qs_pg:photos_9k":1,
    "qs_pg:photos_9r":2,
    "qs_pg:photos_all":26,
    "qs_pg:photos_sr":2,
    "qs_pg:pop_sr":0,
    "qs_pg:qs_pg_placetype":"neighbourhood",
    "qs_pg:qs_pg_placetype_gp":"Suburb",
    "qs_pg:woe_adm0":23424977,
    "wof:name":"Ekastown",
    "wof:placetype":"neighbourhood",
    "wof:population":3164,
    "zs:area_m":58984291.610355,
    "zs:blockids":[
        420199115022030,
        420199115022031,
        420199115023026,
        420199115023029,
        420199115022029,
        420199115022032,
        420199115023040,
        420199115022036,
        420199127003006,
        420199127003020,
        420199115022013,
        420199115022042,
        420199115022044,
        420199115023036,
        420199115023038,
        420199115012027,
        420199127003005,
        420199115022027,
        420199115022037,
        420199127003008,
        420199127003012,
        420199127003010,
        420199127003017,
        420199127005009,
        420199115022047,
        420199115023034,
        420199115022021,
        420199115022024,
        420199115022043,
        420199127002012,
        420199127003009,
        420199127002015,
        420199115022039,
        420199115022001,
        420199115023035,
        420199115023041,
        420199115022000,
        420199115022017,
        420199127002005,
        420199115022035,
        420199115022045,
        420199115023043,
        420199115022012,
        420199115022004,
        420199115022005,
        420199115022023,
        420199115022033,
        420199127003021,
        420199115022006,
        420199115022028,
        420199115022011,
        420199115022002,
        420199115022022,
        420199115022025,
        420199115023037,
        420199115022034,
        420199127002013,
        420199115022018,
        420199127002016,
        420199127003007,
        420199127003016,
        420199115023042,
        420199115023032,
        420199115022038,
        420199115022015,
        420199115022046,
        420199115022019,
        420199115023014,
        420199115023015,
        420199127002014,
        420199115023030,
        420199115023027,
        420199115023016,
        420199115022014,
        420199115022016,
        420199115022026,
        420199115023039,
        420199114003016,
        420199127003018,
        420199127003013,
        420199127003011,
        420199127005010,
        420199127003022,
        420199127005011,
        420199115022040,
        420199115022041
    ],
    "zs:housing10":1294,
    "zs:label":"Ekastown",
    "zs:pop10":3164
},
  "geometry": {"coordinates":[-79.802708,40.703708],"type":"Point"}
}