{
  "type": "Feature",
  "properties": {
    "iso:country":"US",
    "name:eng_x_preferred":[
        "Lone Pasture"
    ],
    "wof:name":"Lone Pasture",
    "wof:placetype":"neighbourhood",
    "wof:population":13,
    "zs:area_m":1236682.745334,
    "zs:blockids":[
        80010085261019,
        80010085261020,
        80010085261017,
        80010085261037,
        80010085261018
    ],
    "zs:housing10":7,
    "zs:label":"Lone Pasture",
    "zs:pop10":13
},
  "geometry": {"coordinates":[-104.9829,39.949911],"type":"Point"}
}