{
  "type": "Feature",
  "properties": {
    "gn:admin1_code":"NC",
    "gn:admin2_code":"129",
    "gn:admin3_code":"91404.0",
    "gn:asciiname":"D and H Estates Mobile Home Park",
    "gn:country_code":"US",
    "gn:dem":12,
    "gn:elevation":"14.0",
    "gn:feature_class":"P",
    "gn:feature_code":"PPL",
    "gn:name":"D and H Estates Mobile Home Park",
    "gn:population":0,
    "gn:timezone":"America/New_York",
    "iso:country":"US",
    "wof:name":"D and H Estates Mobile Home Park",
    "wof:placetype":"campus"
},
  "geometry": {"coordinates":[-77.8105,34.2876],"type":"Point"}
}