{
  "type": "Feature",
  "properties": {
    "gn:admin1_code":"LA",
    "gn:admin2_code":"73.0",
    "gn:asciiname":"Huntington Park",
    "gn:country_code":"US",
    "gn:dem":24,
    "gn:elevation":"20.0",
    "gn:feature_class":"P",
    "gn:feature_code":"PPL",
    "gn:name":"Huntington Park",
    "gn:population":0,
    "gn:timezone":"America/Chicago",
    "iso:country":"US",
    "name:ceb_x_preferred":[
        "Huntington Park"
    ],
    "name:fra_x_preferred":[
        "Huntington Park"
    ],
    "name:ita_x_preferred":[
        "Huntington Park"
    ],
    "name:pol_x_preferred":[
        "Huntington Park"
    ],
    "name:rus_x_preferred":[
        "\u0425\u0430\u043d\u0442\u0438\u043d\u0433\u0442\u043e\u043d-\u041f\u0430\u0440\u043a"
    ],
    "wof:name":"Huntington Park",
    "wof:placetype":"locality"
},
  "geometry": {"coordinates":[-92.05708,32.49042],"type":"Point"}
}