{
  "type": "Feature",
  "properties": {
    "gn:admin1_code":"WV",
    "gn:admin2_code":"83",
    "gn:asciiname":"Cheat Junction",
    "gn:country_code":"US",
    "gn:dem":868,
    "gn:elevation":"858.0",
    "gn:feature_class":"P",
    "gn:feature_code":"PPL",
    "gn:name":"Cheat Junction",
    "gn:population":0,
    "gn:timezone":"America/New_York",
    "iso:country":"US",
    "wof:name":"Cheat Junction",
    "wof:placetype":"locality"
},
  "geometry": {"coordinates":[-79.75451,38.79483],"type":"Point"}
}