{
  "type": "Feature",
  "properties": {
    "gn:admin1_code":"GA",
    "gn:admin2_code":"115.0",
    "gn:asciiname":"Forrest Heights",
    "gn:country_code":"US",
    "gn:dem":226,
    "gn:elevation":"225.0",
    "gn:feature_class":"P",
    "gn:feature_code":"PPL",
    "gn:name":"Forrest Heights",
    "gn:population":0,
    "gn:timezone":"America/New_York",
    "iso:country":"US",
    "wof:name":"Forrest Heights",
    "wof:placetype":"locality"
},
  "geometry": {"coordinates":[-85.16773000000001,34.20093],"type":"Point"}
}