{
  "type": "Feature",
  "properties": {
    "gn:admin1_code":"WV",
    "gn:admin2_code":"61.0",
    "gn:asciiname":"Opekiska",
    "gn:country_code":"US",
    "gn:dem":264,
    "gn:elevation":"269.0",
    "gn:feature_class":"P",
    "gn:feature_code":"PPL",
    "gn:name":"Opekiska",
    "gn:population":0,
    "gn:timezone":"America/New_York",
    "iso:country":"US",
    "wof:name":"Opekiska",
    "wof:placetype":"locality"
},
  "geometry": {"coordinates":[-80.05563000000002,39.55731],"type":"Point"}
}