{
  "type": "Feature",
  "properties": {
    "gn:gn_country":"US",
    "gn:gn_fcode":"PPL",
    "gn:gn_pop":0,
    "iso:country":"US",
    "name:cat_x_preferred":[
        "Bingham"
    ],
    "name:ceb_x_preferred":[
        "Bingham"
    ],
    "name:deu_x_preferred":[
        "Bingham"
    ],
    "name:fas_x_preferred":[
        "\u0628\u06cc\u0646\u06af\u0647\u0627\u0645"
    ],
    "name:fra_x_preferred":[
        "Bingham"
    ],
    "name:heb_x_preferred":[
        "\u05d1\u05d9\u05e0\u05d2\u05d4\u05d0\u05dd"
    ],
    "name:ind_x_preferred":[
        "Bingham"
    ],
    "name:ita_x_preferred":[
        "Bingham"
    ],
    "name:jpn_x_preferred":[
        "\u30d3\u30f3\u30ac\u30e0"
    ],
    "name:nld_x_preferred":[
        "Bingham"
    ],
    "name:pol_x_preferred":[
        "Bingham"
    ],
    "name:srp_x_preferred":[
        "\u0411\u0438\u043d\u0433\u0430\u043c"
    ],
    "name:ukr_x_preferred":[
        "\u0411\u0456\u043d\u0433\u0430\u043c"
    ],
    "name:urd_x_preferred":[
        "\u0628\u0646\u06af\u06c1\u0645"
    ],
    "name:vol_x_preferred":[
        "Bingham"
    ],
    "name:zho_x_preferred":[
        "\u5bbe\u5384\u59c6"
    ],
    "qs_pg:aaroncc":"US",
    "qs_pg:gn_country":"US",
    "qs_pg:gn_fcode":"PPL",
    "qs_pg:gn_pop":0,
    "qs_pg:name":"Bingham",
    "qs_pg:name_adm0":"United States",
    "qs_pg:name_adm1":"New Mexico",
    "qs_pg:photos":45,
    "qs_pg:photos_1k":9,
    "qs_pg:photos_9k":1,
    "qs_pg:photos_9r":2,
    "qs_pg:photos_all":45,
    "qs_pg:photos_sr":2,
    "qs_pg:pop_sr":5,
    "qs_pg:qs_pg_placetype":"locality",
    "qs_pg:qs_pg_placetype_gp":"Town",
    "qs_pg:woe_adm0":23424977,
    "woe:adm0_id":23424977,
    "woe:name_adm0":"United States",
    "woe:name_adm1":"New Mexico",
    "woe:placetype":"Town",
    "wof:name":"Bingham",
    "wof:placetype":"locality"
},
  "geometry": {"coordinates":[-106.37251000000001,33.88896],"type":"Point"}
}