{
  "type": "Feature",
  "properties": {
    "gn:admin1_code":"CA",
    "gn:admin2_code":"83.0",
    "gn:asciiname":"Rex",
    "gn:country_code":"US",
    "gn:dem":88,
    "gn:elevation":"86.0",
    "gn:feature_class":"P",
    "gn:feature_code":"PPL",
    "gn:name":"Rex",
    "gn:population":0,
    "gn:timezone":"America/Los_Angeles",
    "iso:country":"US",
    "name:bul_x_preferred":[
        "\u0420\u0435\u043a\u0441"
    ],
    "name:cat_x_preferred":[
        "Rex"
    ],
    "name:ceb_x_preferred":[
        "Rex"
    ],
    "name:ces_x_preferred":[
        "Rex"
    ],
    "name:dan_x_preferred":[
        "Rex"
    ],
    "name:deu_x_preferred":[
        "Rex"
    ],
    "name:fas_x_preferred":[
        "\u0631\u06a9\u0633"
    ],
    "name:fin_x_preferred":[
        "Rex"
    ],
    "name:fra_x_preferred":[
        "Rex"
    ],
    "name:hun_x_preferred":[
        "Rex"
    ],
    "name:jpn_x_preferred":[
        "\u30ec\u30c3\u30af\u30b9"
    ],
    "name:lat_x_preferred":[
        "Rex"
    ],
    "name:nld_x_preferred":[
        "Rex"
    ],
    "name:nor_x_preferred":[
        "Rex"
    ],
    "name:pol_x_preferred":[
        "Rex"
    ],
    "name:por_x_preferred":[
        "Rex"
    ],
    "name:rus_x_preferred":[
        "\u0420\u0435\u043a\u0441"
    ],
    "name:slk_x_preferred":[
        "Rex"
    ],
    "name:slv_x_preferred":[
        "Rex"
    ],
    "name:spa_x_preferred":[
        "Rex"
    ],
    "name:srp_x_preferred":[
        "Rex"
    ],
    "name:swe_x_preferred":[
        "Rex"
    ],
    "name:ukr_x_preferred":[
        "\u0420\u0435\u043a\u0441"
    ],
    "wof:name":"Rex",
    "wof:placetype":"locality"
},
  "geometry": {"coordinates":[-120.37711000000002,34.94526],"type":"Point"}
}