{
  "type": "Feature",
  "properties": {
    "gn:admin1_code":"LA",
    "gn:admin2_code":"23.0",
    "gn:asciiname":"Grand Lake",
    "gn:country_code":"US",
    "gn:dem":13,
    "gn:elevation":"3.0",
    "gn:feature_class":"P",
    "gn:feature_code":"PPL",
    "gn:name":"Grand Lake",
    "gn:population":0,
    "gn:timezone":"America/Chicago",
    "iso:country":"US",
    "name:eng_x_preferred":[
        "Grand Lake"
    ],
    "name:und_x_variant":[
        "Grandlake"
    ],
    "wof:name":"Grand Lake",
    "wof:placetype":"locality"
},
  "geometry": {"coordinates":[-93.27209999999999,30.03077],"type":"Point"}
}