{
  "type": "Feature",
  "properties": {
    "gn:admin1_code":"LA",
    "gn:admin2_code":"23.0",
    "gn:asciiname":"Grand Lake",
    "gn:country_code":"US",
    "gn:dem":13,
    "gn:elevation":"3.0",
    "gn:feature_class":"P",
    "gn:feature_code":"PPL",
    "gn:name":"Grand Lake",
    "gn:population":0,
    "gn:timezone":"America/Chicago",
    "iso:country":"US",
    "name:ara_x_preferred":[
        "\u063a\u0631\u0627\u0646\u062f \u0644\u064a\u0643"
    ],
    "name:ben_x_preferred":[
        "\u0997\u09cd\u09b0\u09cd\u09af\u09be\u09a8\u09cd\u09a1 \u09b2\u09c7\u0995"
    ],
    "name:deu_x_preferred":[
        "Grand Lake"
    ],
    "name:ell_x_preferred":[
        "\u039b\u03af\u03bc\u03bd\u03b7 \u0393\u03ba\u03c1\u03b1\u03bd\u03c4"
    ],
    "name:eng_x_preferred":[
        "Grand Lake"
    ],
    "name:fas_x_preferred":[
        "\u062f\u0631\u06cc\u0627\u0686\u0647 \u06af\u0631\u0646\u062f"
    ],
    "name:fra_x_preferred":[
        "Grand Lake"
    ],
    "name:heb_x_preferred":[
        "\u05d2\u05e8\u05e0\u05d3 \u05dc\u05d9\u05d9\u05e7"
    ],
    "name:hin_x_preferred":[
        "\u0917\u094d\u0930\u0948\u0902\u0921 \u091d\u0940\u0932"
    ],
    "name:hun_x_preferred":[
        "Grand Lake"
    ],
    "name:ind_x_preferred":[
        "Danau Grand"
    ],
    "name:ita_x_preferred":[
        "Grand Lake"
    ],
    "name:kor_x_preferred":[
        "\uadf8\ub79c\ub4dc \ub808\uc774\ud06c"
    ],
    "name:nld_x_preferred":[
        "Grand Lake"
    ],
    "name:pol_x_preferred":[
        "Grand Lake"
    ],
    "name:spa_x_preferred":[
        "Lago Grand"
    ],
    "name:swe_x_preferred":[
        "Grand Lake"
    ],
    "name:tur_x_preferred":[
        "Grand Lake"
    ],
    "name:ukr_x_preferred":[
        "\u0413\u0440\u0430\u043d\u0434-\u041b\u0435\u0439\u043a"
    ],
    "name:und_x_variant":[
        "Grandlake"
    ],
    "name:urd_x_preferred":[
        "\u06af\u0631\u06cc\u0646\u0688 \u0644\u06cc\u06a9"
    ],
    "name:vie_x_preferred":[
        "H\u1ed3 Grand"
    ],
    "wof:name":"Grand Lake",
    "wof:placetype":"locality"
},
  "geometry": {"coordinates":[-93.27209999999999,30.03077],"type":"Point"}
}