{
  "type": "Feature",
  "properties": {
    "gn:admin1_code":"IL",
    "gn:admin2_code":"29",
    "gn:admin3_code":"36555.0",
    "gn:asciiname":"Dorans",
    "gn:country_code":"US",
    "gn:dem":208,
    "gn:elevation":"209.0",
    "gn:feature_class":"P",
    "gn:feature_code":"PPL",
    "gn:name":"Dorans",
    "gn:population":0,
    "gn:timezone":"America/Chicago",
    "iso:country":"US",
    "wof:name":"Dorans",
    "wof:placetype":"locality"
},
  "geometry": {"coordinates":[-88.34449000000002,39.55114],"type":"Point"}
}