{
  "type": "Feature",
  "properties": {
    "gn:admin1_code":"IA",
    "gn:admin2_code":"111.0",
    "gn:admin3_code":"91869.0",
    "gn:asciiname":"Primrose",
    "gn:country_code":"US",
    "gn:dem":220,
    "gn:elevation":"216.0",
    "gn:feature_class":"P",
    "gn:feature_code":"PPL",
    "gn:name":"Primrose",
    "gn:population":0,
    "gn:timezone":"America/Chicago",
    "iso:country":"US",
    "name:cat_x_preferred":[
        "Primrose"
    ],
    "name:ceb_x_preferred":[
        "Primrose"
    ],
    "name:deu_x_preferred":[
        "Primrose"
    ],
    "name:fra_x_preferred":[
        "Primrose"
    ],
    "name:ita_x_preferred":[
        "Primrose"
    ],
    "name:jpn_x_preferred":[
        "\u30d7\u30ea\u30e0\u30ed\u30fc\u30ba"
    ],
    "name:nld_x_preferred":[
        "Primrose"
    ],
    "name:pol_x_preferred":[
        "Primrose"
    ],
    "name:por_x_preferred":[
        "Primrose"
    ],
    "name:rus_x_preferred":[
        "\u041f\u0440\u0438\u043c\u0440\u043e\u0443\u0437"
    ],
    "name:srp_x_preferred":[
        "\u041f\u0440\u0438\u043c\u0440\u043e\u0443\u0437"
    ],
    "name:swe_x_preferred":[
        "Primrose"
    ],
    "name:vol_x_preferred":[
        "Primrose"
    ],
    "wof:name":"Primrose",
    "wof:placetype":"locality"
},
  "geometry": {"coordinates":[-91.63822,40.67559],"type":"Point"}
}