{
  "type": "Feature",
  "properties": {
    "gn:admin1_code":"OR",
    "gn:admin2_code":"7.0",
    "gn:asciiname":"Oklahoma Hill",
    "gn:country_code":"US",
    "gn:dem":20,
    "gn:elevation":"15.0",
    "gn:feature_class":"P",
    "gn:feature_code":"PPL",
    "gn:name":"Oklahoma Hill",
    "gn:population":0,
    "gn:timezone":"America/Los_Angeles",
    "iso:country":"US",
    "wof:name":"Oklahoma Hill",
    "wof:placetype":"locality"
},
  "geometry": {"coordinates":[-123.40595999999999,46.14317],"type":"Point"}
}