{
  "type": "Feature",
  "properties": {
    "gn:country":"US",
    "gn:fcode":"PPL",
    "gn:population":0,
    "iso:country":"US",
    "name:azb_x_preferred":[
        "\u067e\u06cc\u06a9\u0631\u0644"
    ],
    "name:eng_x_preferred":[
        "Pickerel"
    ],
    "name:fas_x_preferred":[
        "\u067e\u06cc\u06a9\u06cc\u0631\u06cc\u0644"
    ],
    "name:fra_x_preferred":[
        "Pickerel"
    ],
    "qs_pg:aaroncc":"US",
    "qs_pg:gn_country":"US",
    "qs_pg:gn_fcode":"PPL",
    "qs_pg:gn_pop":0,
    "qs_pg:name":"Pickerel",
    "qs_pg:name_adm0":"United States",
    "qs_pg:name_adm1":"Wisconsin",
    "qs_pg:photos":63,
    "qs_pg:photos_1k":13,
    "qs_pg:photos_9k":1,
    "qs_pg:photos_9r":2,
    "qs_pg:photos_all":63,
    "qs_pg:photos_sr":2,
    "qs_pg:pop_sr":0,
    "qs_pg:qs_pg_placetype":"locality",
    "qs_pg:qs_pg_placetype_gp":"Town",
    "qs_pg:woe_adm0":23424977,
    "woe:adm0_id":23424977,
    "woe:name_adm0":"United States",
    "woe:name_adm1":"Wisconsin",
    "woe:placetype":"Town",
    "wof:name":"Pickerel",
    "wof:placetype":"locality"
},
  "geometry": {"coordinates":[-88.91094,45.35941],"type":"Point"}
}