{
  "type": "Feature",
  "properties": {
    "gn:admin1_code":"KY",
    "gn:admin2_code":"163",
    "gn:asciiname":"Grahamton",
    "gn:country_code":"US",
    "gn:dem":159,
    "gn:elevation":"160.0",
    "gn:feature_class":"P",
    "gn:feature_code":"PPL",
    "gn:name":"Grahamton",
    "gn:population":0,
    "gn:timezone":"America/New_York",
    "iso:country":"US",
    "wof:name":"Grahamton",
    "wof:placetype":"locality"
},
  "geometry": {"coordinates":[-86.02552,37.90285],"type":"Point"}
}