{
  "type": "Feature",
  "properties": {
    "gn:admin1_code":"AR",
    "gn:admin2_code":"27.0",
    "gn:admin3_code":"92355.0",
    "gn:asciiname":"Rocky Mound",
    "gn:country_code":"US",
    "gn:dem":97,
    "gn:elevation":"89.0",
    "gn:feature_class":"P",
    "gn:feature_code":"PPL",
    "gn:name":"Rocky Mound",
    "gn:population":0,
    "gn:timezone":"America/Chicago",
    "iso:country":"US",
    "wof:name":"Rocky Mound",
    "wof:placetype":"locality"
},
  "geometry": {"coordinates":[-93.36489,33.14097],"type":"Point"}
}