{
  "type": "Feature",
  "properties": {
    "gn:admin1_code":"VA",
    "gn:admin2_code":"15",
    "gn:asciiname":"Trimbles Mill",
    "gn:country_code":"US",
    "gn:dem":489,
    "gn:elevation":"487.0",
    "gn:feature_class":"P",
    "gn:feature_code":"PPL",
    "gn:name":"Trimbles Mill",
    "gn:population":0,
    "gn:timezone":"America/New_York",
    "iso:country":"US",
    "wof:name":"Trimbles Mill",
    "wof:placetype":"locality"
},
  "geometry": {"coordinates":[-79.21864000000002,38.13541],"type":"Point"}
}