{
  "type": "Feature",
  "properties": {
    "gn:admin1_code":"IA",
    "gn:admin2_code":"25.0",
    "gn:admin3_code":"94179.0",
    "gn:asciiname":"Wightman",
    "gn:country_code":"US",
    "gn:dem":351,
    "gn:elevation":"357.0",
    "gn:feature_class":"P",
    "gn:feature_code":"PPL",
    "gn:name":"Wightman",
    "gn:population":0,
    "gn:timezone":"America/Chicago",
    "iso:country":"US",
    "wof:name":"Wightman",
    "wof:placetype":"locality"
},
  "geometry": {"coordinates":[-94.6097,42.23248],"type":"Point"}
}