{
  "type": "Feature",
  "properties": {
    "gn:admin1_code":"MO",
    "gn:admin2_code":"91.0",
    "gn:admin3_code":"50960.0",
    "gn:asciiname":"Lanton",
    "gn:country_code":"US",
    "gn:dem":272,
    "gn:elevation":"270.0",
    "gn:feature_class":"P",
    "gn:feature_code":"PPL",
    "gn:name":"Lanton",
    "gn:population":0,
    "gn:timezone":"America/Chicago",
    "iso:country":"US",
    "name:vol_x_preferred":[
        "Lanton"
    ],
    "wof:name":"Lanton",
    "wof:placetype":"locality"
},
  "geometry": {"coordinates":[-91.80154,36.51729],"type":"Point"}
}