{
  "type": "Feature",
  "properties": {
    "gn:admin1_code":"OK",
    "gn:admin2_code":"69.0",
    "gn:asciiname":"Reagan",
    "gn:country_code":"US",
    "gn:dem":284,
    "gn:elevation":"278.0",
    "gn:feature_class":"P",
    "gn:feature_code":"PPL",
    "gn:name":"Reagan",
    "gn:population":0,
    "gn:timezone":"America/Chicago",
    "iso:country":"US",
    "wof:name":"Reagan",
    "wof:placetype":"locality"
},
  "geometry": {"coordinates":[-96.72167,34.34898],"type":"Point"}
}