{
  "type": "Feature",
  "properties": {
    "gn:admin1_code":"CO",
    "gn:admin2_code":"21.0",
    "gn:asciiname":"Espinosa",
    "gn:country_code":"US",
    "gn:dem":2364,
    "gn:elevation":"2361.0",
    "gn:feature_class":"P",
    "gn:feature_code":"PPL",
    "gn:name":"Espinosa",
    "gn:population":0,
    "gn:timezone":"America/Denver",
    "iso:country":"US",
    "wof:name":"Espinosa",
    "wof:placetype":"locality"
},
  "geometry": {"coordinates":[-105.94613,37.13057],"type":"Point"}
}