{
  "type": "Feature",
  "properties": {
    "gn:admin1_code":"WV",
    "gn:admin2_code":"47",
    "gn:asciiname":"Capels",
    "gn:country_code":"US",
    "gn:dem":390,
    "gn:elevation":"399.0",
    "gn:feature_class":"P",
    "gn:feature_code":"PPL",
    "gn:name":"Capels",
    "gn:population":0,
    "gn:timezone":"America/New_York",
    "iso:country":"US",
    "name:azb_x_preferred":[
        "\u06a9\u06cc\u067e\u0644\u0632"
    ],
    "name:eng_x_preferred":[
        "Capels"
    ],
    "name:fas_x_preferred":[
        "\u06a9\u06cc\u067e\u0644\u0632"
    ],
    "name:und_x_variant":[
        "Farm",
        "Ritter"
    ],
    "name:vol_x_preferred":[
        "Capels"
    ],
    "wof:name":"Capels",
    "wof:placetype":"locality"
},
  "geometry": {"coordinates":[-81.6015,37.45456],"type":"Point"}
}