{
  "type": "Feature",
  "properties": {
    "iso:country":"US",
    "name:eng_x_preferred":[
        "Smith Ranch"
    ],
    "wof:name":"Smith Ranch",
    "wof:placetype":"neighbourhood",
    "wof:population":193,
    "zs:area_m":7858067.311408,
    "zs:blockids":[
        60411050001035,
        60411060013050,
        60411060013025,
        60411060013044,
        60411060013022,
        60411060013040,
        60411060013023,
        60411060013013,
        60411060013008,
        60411060013020,
        60411060013045,
        60411060013006,
        60411060022009,
        60411060013016,
        60411060013024,
        60411060013003,
        60411060013017,
        60411060013018,
        60411060013000,
        60411060013014,
        60411060013004,
        60411060013010,
        60411050001032,
        60411060013015,
        60411060013007,
        60411060013009,
        60411050001034,
        60411060013043,
        60411050001033,
        60411060022000,
        60411060013021,
        60411060013042,
        60411060013046,
        60411060013005,
        60411060013019
    ],
    "zs:housing10":88,
    "zs:label":"Smith Ranch",
    "zs:pop10":193
},
  "geometry": {"coordinates":[-122.50496,38.027972],"type":"Point"}
}