{
  "type": "Feature",
  "properties": {
    "gn:admin1_code":"VA",
    "gn:admin2_code":"199",
    "gn:asciiname":"Grafton Mobile Home Park",
    "gn:country_code":"US",
    "gn:dem":19,
    "gn:elevation":"16.0",
    "gn:feature_class":"P",
    "gn:feature_code":"PPL",
    "gn:name":"Grafton Mobile Home Park",
    "gn:population":0,
    "gn:timezone":"America/New_York",
    "iso:country":"US",
    "wof:name":"Grafton Mobile Home Park",
    "wof:placetype":"campus"
},
  "geometry": {"coordinates":[-76.46514000000001,37.14734],"type":"Point"}
}