{
  "type": "Feature",
  "properties": {
    "gn:admin1_code":"PA",
    "gn:admin2_code":"43.0",
    "gn:admin3_code":"45056.0",
    "gn:asciiname":"Locust Lane Acres",
    "gn:country_code":"US",
    "gn:dem":164,
    "gn:elevation":"160.0",
    "gn:feature_class":"P",
    "gn:feature_code":"PPL",
    "gn:name":"Locust Lane Acres",
    "gn:population":0,
    "gn:timezone":"America/New_York",
    "iso:country":"US",
    "wof:name":"Locust Lane Acres",
    "wof:placetype":"locality"
},
  "geometry": {"coordinates":[-76.79469,40.29342000000001],"type":"Point"}
}