{
  "type": "Feature",
  "properties": {
    "iso:country":"US",
    "name:eng_x_preferred":[
        "Steamboat Villa"
    ],
    "qs:gn_adm0_cc":"US",
    "qs:gn_local":5582371,
    "qs:gn_nam_loc":"Steamboat Springs, Routt, Colorado, US",
    "qs:gn_namadm1":"CO",
    "qs:local_max":650,
    "qs:local_sum":1378,
    "qs:localhoods":9,
    "qs:name":"Steamboat Villa",
    "qs:name_adm0":"United States",
    "qs:name_adm1":"Colorado",
    "qs:name_adm2":"Routt",
    "qs:name_local":"Steamboat Springs",
    "qs:photo_max":17,
    "qs:photo_sum":43,
    "qs:placetype":"Suburb",
    "qs:quad_count":4,
    "qs:woe_adm0":23424977,
    "qs:woe_adm1":2347564,
    "qs:woe_adm2":12587781,
    "qs:woe_lau":0,
    "qs:woe_local":2499383,
    "qs:woe_ver":"7.10.0",
    "wof:lang":[
        "eng"
    ],
    "wof:name":"Steamboat Villa",
    "wof:placetype":"neighbourhood",
    "wof:population":270,
    "zs:blockids":[
        81070005004022,
        81070006001037,
        81070006001029,
        81070006001042,
        81070006001034,
        81070006001033,
        81070006001032,
        81070006001038,
        81070006001041,
        81070006001027,
        81070006001035,
        81070006001036
    ],
    "zs:housing10":133,
    "zs:pop10":270
},
  "geometry": {"coordinates":[-106.828022,40.47302],"type":"Point"}
}