{
  "type": "Feature",
  "properties": {
    "iso:country":"US",
    "name:eng_x_preferred":[
        "Beville Heights"
    ],
    "wof:name":"Beville Heights",
    "wof:placetype":"neighbourhood",
    "wof:population":211,
    "zs:area_m":457413.003544,
    "zs:blockids":[
        120010016041023,
        120010016041022,
        120010017022026,
        120010016031018
    ],
    "zs:housing10":116,
    "zs:label":"Beville Heights",
    "zs:pop10":211
},
  "geometry": {"coordinates":[-82.39366699999999,29.658304],"type":"Point"}
}