{
  "type": "Feature",
  "properties": {
    "gn:admin1_code":"NC",
    "gn:admin2_code":"195",
    "gn:admin3_code":"93084.0",
    "gn:asciiname":"Kirbys Crossing",
    "gn:country_code":"US",
    "gn:dem":66,
    "gn:elevation":"64.0",
    "gn:feature_class":"P",
    "gn:feature_code":"PPL",
    "gn:name":"Kirbys Crossing",
    "gn:population":0,
    "gn:timezone":"America/New_York",
    "iso:country":"US",
    "name:eng_x_preferred":[
        "Kirbys Crossing"
    ],
    "name:und_x_variant":[
        "Boyette",
        "Silversboro",
        "Silverboro",
        "Boyett"
    ],
    "wof:name":"Kirbys Crossing",
    "wof:placetype":"locality"
},
  "geometry": {"coordinates":[-78.09026999999998,35.61349000000001],"type":"Point"}
}