{
  "type": "Feature",
  "properties": {
    "gn:admin1_code":"NE",
    "gn:admin2_code":"55.0",
    "gn:admin3_code":"92237.0",
    "gn:asciiname":"Maplewood Estates",
    "gn:country_code":"US",
    "gn:dem":339,
    "gn:elevation":"338.0",
    "gn:feature_class":"P",
    "gn:feature_code":"PPL",
    "gn:name":"Maplewood Estates",
    "gn:population":0,
    "gn:timezone":"America/Chicago",
    "iso:country":"US",
    "wof:name":"Maplewood Estates",
    "wof:placetype":"locality"
},
  "geometry": {"coordinates":[-96.11279999999999,41.295],"type":"Point"}
}