{
  "type": "Feature",
  "properties": {
    "gn:admin1_code":"TX",
    "gn:admin2_code":"215",
    "gn:asciiname":"El Sol Colonia",
    "gn:country_code":"US",
    "gn:dem":31,
    "gn:elevation":"28.0",
    "gn:feature_class":"P",
    "gn:feature_code":"PPL",
    "gn:name":"El Sol Colonia",
    "gn:population":0,
    "gn:timezone":"America/Chicago",
    "iso:country":"US",
    "wof:name":"El Sol Colonia",
    "wof:placetype":"locality"
},
  "geometry": {"coordinates":[-98.19723,26.13146],"type":"Point"}
}