{
  "type": "Feature",
  "properties": {
    "iso:country":"US",
    "name:eng_x_preferred":[
        "Thunderbird North"
    ],
    "wof:name":"Thunderbird North",
    "wof:placetype":"neighbourhood",
    "wof:population":296,
    "zs:area_m":113256.420316,
    "zs:blockids":[
        481576710022004,
        481576710022003,
        481576710022001
    ],
    "zs:housing10":112,
    "zs:label":"Thunderbird North",
    "zs:pop10":296
},
  "geometry": {"coordinates":[-95.52806099999999,29.573193],"type":"Point"}
}