{
  "type": "Feature",
  "properties": {
    "gn:admin1_code":"MN",
    "gn:admin2_code":"79.0",
    "gn:admin3_code":"15760.0",
    "gn:asciiname":"Union Hill",
    "gn:country_code":"US",
    "gn:dem":300,
    "gn:elevation":"303.0",
    "gn:feature_class":"P",
    "gn:feature_code":"PPL",
    "gn:name":"Union Hill",
    "gn:population":0,
    "gn:timezone":"America/Chicago",
    "iso:country":"US",
    "name:fas_x_preferred":[
        "\u06cc\u0648\u0646\u06cc\u0648\u0646 \u0647\u06cc\u0644"
    ],
    "name:vol_x_preferred":[
        "Union Hill"
    ],
    "wof:name":"Union Hill",
    "wof:placetype":"locality"
},
  "geometry": {"coordinates":[-93.66718,44.54357],"type":"Point"}
}