{
  "type": "Feature",
  "properties": {
    "gn:admin1_code":"NY",
    "gn:admin2_code":"105.0",
    "gn:admin3_code":"26528.0",
    "gn:asciiname":"Forestburg",
    "gn:country_code":"US",
    "gn:dem":379,
    "gn:elevation":"372.0",
    "gn:feature_class":"P",
    "gn:feature_code":"PPL",
    "gn:name":"Forestburg",
    "gn:population":0,
    "gn:timezone":"America/New_York",
    "iso:country":"US",
    "name:deu_x_preferred":[
        "Forestburg"
    ],
    "name:eng_x_preferred":[
        "Forestburg"
    ],
    "name:ita_x_preferred":[
        "Forestburg"
    ],
    "name:und_x_variant":[
        "Forestburgh"
    ],
    "wof:name":"Forestburg",
    "wof:placetype":"locality"
},
  "geometry": {"coordinates":[-74.75126999999998,41.55009],"type":"Point"}
}