{
  "type": "Feature",
  "properties": {
    "iso:country":"US",
    "name:bel_x_preferred":[
        "\u0406\u0442\u0430\u043d"
    ],
    "name:cat_x_preferred":[
        "Eaton"
    ],
    "name:ceb_x_preferred":[
        "Eaton"
    ],
    "name:deu_x_preferred":[
        "Eaton"
    ],
    "name:eng_x_preferred":[
        "Eaton"
    ],
    "name:fra_x_preferred":[
        "Eaton"
    ],
    "name:heb_x_preferred":[
        "\u05d0\u05d9\u05d8\u05d5\u05df"
    ],
    "name:ita_x_preferred":[
        "Eaton"
    ],
    "name:lav_x_preferred":[
        "\u012atons"
    ],
    "name:mlg_x_preferred":[
        "Eaton"
    ],
    "name:nds_x_preferred":[
        "Eaton"
    ],
    "name:nld_x_preferred":[
        "Eaton"
    ],
    "name:pol_x_preferred":[
        "Eaton"
    ],
    "name:por_x_preferred":[
        "Eaton"
    ],
    "name:ron_x_preferred":[
        "Eaton"
    ],
    "name:rus_x_preferred":[
        "Eaton"
    ],
    "name:spa_x_preferred":[
        "Eaton"
    ],
    "name:srp_x_preferred":[
        "\u0418\u0442\u043e\u043d"
    ],
    "name:swe_x_preferred":[
        "Eaton"
    ],
    "name:ukr_x_preferred":[
        "\u0406\u0442\u043e\u043d"
    ],
    "name:vol_x_preferred":[
        "Eaton"
    ],
    "wof:name":"Eaton",
    "wof:placetype":"neighbourhood",
    "wof:population":225,
    "zs:area_m":3817732.692001,
    "zs:blockids":[
        80770015023016
    ],
    "zs:housing10":87,
    "zs:label":"Eaton",
    "zs:pop10":225
},
  "geometry": {"coordinates":[-108.618387,39.172355],"type":"Point"}
}