{
  "type": "Feature",
  "properties": {
    "iso:country":"US",
    "name:eng_x_preferred":[
        "Downtown Vermilion"
    ],
    "wof:name":"Downtown Vermilion",
    "wof:placetype":"neighbourhood",
    "wof:population":349,
    "zs:area_m":1128926.160464,
    "zs:blockids":[
        390430401002008,
        390430401001008,
        390430401002010,
        390430401001009,
        390430401001007,
        390430401001014,
        390430401001000,
        390430401001004,
        390430401001035,
        390430401001016,
        390430401001032,
        390430401002016,
        390430401001011,
        390430401001029,
        390430401002009,
        390430401002040,
        390430401001028,
        390430401001017,
        390430401001015,
        390430401001010,
        390430401001002,
        390430401001005,
        390430401001001,
        390430401001031,
        390430401001012,
        390430401001018,
        390430401001060,
        390430401001070,
        390430401001033,
        390430401001013,
        390430401001030,
        390430401001006
    ],
    "zs:housing10":401,
    "zs:label":"Downtown Vermilion",
    "zs:pop10":349
},
  "geometry": {"coordinates":[-82.357035,41.42605],"type":"Point"}
}