{
  "type": "Feature",
  "properties": {
    "gn:admin1_code":"HI",
    "gn:admin2_code":"1.0",
    "gn:asciiname":"Kukui Village",
    "gn:country_code":"US",
    "gn:dem":134,
    "gn:elevation":"131.0",
    "gn:feature_class":"P",
    "gn:feature_code":"PPL",
    "gn:name":"Kukui Village",
    "gn:population":0,
    "gn:timezone":"Pacific/Honolulu",
    "iso:country":"US",
    "wof:name":"Kukui Village",
    "wof:placetype":"locality"
},
  "geometry": {"coordinates":[-155.27778999999995,20.01324],"type":"Point"}
}