{
  "type": "Feature",
  "properties": {
    "gn:admin1_code":"GA",
    "gn:admin2_code":"67.0",
    "gn:asciiname":"Oak Creek Estates",
    "gn:country_code":"US",
    "gn:dem":301,
    "gn:elevation":"293.0",
    "gn:feature_class":"P",
    "gn:feature_code":"PPL",
    "gn:name":"Oak Creek Estates",
    "gn:population":0,
    "gn:timezone":"America/New_York",
    "iso:country":"US",
    "wof:name":"Oak Creek Estates",
    "wof:placetype":"locality"
},
  "geometry": {"coordinates":[-84.51549,34.03120999999999],"type":"Point"}
}