{
  "type": "Feature",
  "properties": {
    "gn:admin1_code":"ME",
    "gn:admin2_code":"5.0",
    "gn:admin3_code":"73670.0",
    "gn:asciiname":"Dow Corner",
    "gn:country_code":"US",
    "gn:dem":103,
    "gn:elevation":"100.0",
    "gn:feature_class":"P",
    "gn:feature_code":"PPL",
    "gn:name":"Dow Corner",
    "gn:population":0,
    "gn:timezone":"America/New_York",
    "iso:country":"US",
    "wof:name":"Dow Corner",
    "wof:placetype":"locality"
},
  "geometry": {"coordinates":[-70.59033000000002,43.72008],"type":"Point"}
}