{
  "type": "Feature",
  "properties": {
    "gn:admin1_code":"UT",
    "gn:admin2_code":"35.0",
    "gn:asciiname":"Garden Towers Condominium",
    "gn:country_code":"US",
    "gn:dem":1356,
    "gn:elevation":"1346.0",
    "gn:feature_class":"P",
    "gn:feature_code":"PPL",
    "gn:name":"Garden Towers Condominium",
    "gn:population":0,
    "gn:timezone":"America/Denver",
    "iso:country":"US",
    "wof:name":"Garden Towers Condominium",
    "wof:placetype":"locality"
},
  "geometry": {"coordinates":[-111.88521,40.77078],"type":"Point"}
}