{
  "type": "Feature",
  "properties": {
    "gn:elevation":281,
    "iso:country":"US",
    "name:eng_x_preferred":[
        "Mission Farms"
    ],
    "qs:gn_fcode":"PPL",
    "qs:gn_local":0,
    "qs:gn_namadm1":"MN",
    "qs:gn_name":"Mission Farms",
    "qs:local_max":693,
    "qs:local_sum":732,
    "qs:localhoods":2,
    "qs:name":"Mission Farms",
    "qs:name_adm0":"United States",
    "qs:name_adm1":"Minnesota",
    "qs:name_adm2":"Hennepin",
    "qs:name_local":"Plymouth",
    "qs:photo_max":345,
    "qs:photo_sum":693,
    "qs:placetype":"Suburb",
    "qs:quad_count":40,
    "qs:woe_adm0":23424977,
    "qs:woe_adm1":2347582,
    "qs:woe_adm2":12588823,
    "qs:woe_lau":0,
    "qs:woe_local":2474411,
    "qs:woe_ver":"7.10.0",
    "wof:lang":[
        "eng"
    ],
    "wof:name":"Mission Farms",
    "wof:placetype":"neighbourhood"
},
  "geometry": {"coordinates":[-93.433182,45.018492],"type":"Point"}
}