{
  "type": "Feature",
  "properties": {
    "gn:admin1_code":"KY",
    "gn:admin2_code":"235",
    "gn:asciiname":"Redbird",
    "gn:country_code":"US",
    "gn:dem":282,
    "gn:elevation":"279.0",
    "gn:feature_class":"P",
    "gn:feature_code":"PPL",
    "gn:name":"Redbird",
    "gn:population":0,
    "gn:timezone":"America/New_York",
    "iso:country":"US",
    "wof:name":"Redbird",
    "wof:placetype":"locality"
},
  "geometry": {"coordinates":[-84.21994000000002,36.76203],"type":"Point"}
}