{
  "type": "Feature",
  "properties": {
    "gn:admin1_code":"VA",
    "gn:admin2_code":"117",
    "gn:asciiname":"Dunns Corner",
    "gn:country_code":"US",
    "gn:dem":143,
    "gn:elevation":"146.0",
    "gn:feature_class":"P",
    "gn:feature_code":"PPL",
    "gn:name":"Dunns Corner",
    "gn:population":0,
    "gn:timezone":"America/New_York",
    "iso:country":"US",
    "wof:name":"Dunns Corner",
    "wof:placetype":"locality"
},
  "geometry": {"coordinates":[-78.27415999999999,36.74625],"type":"Point"}
}