{
  "type": "Feature",
  "properties": {
    "gn:admin1_code":"MI",
    "gn:admin2_code":"71.0",
    "gn:admin3_code":"19150.0",
    "gn:asciiname":"Balsam",
    "gn:country_code":"US",
    "gn:dem":459,
    "gn:elevation":"463.0",
    "gn:feature_class":"P",
    "gn:feature_code":"PPL",
    "gn:name":"Balsam",
    "gn:population":0,
    "gn:timezone":"America/Menominee",
    "iso:country":"US",
    "wof:name":"Balsam",
    "wof:placetype":"locality"
},
  "geometry": {"coordinates":[-88.38096999999998,46.20773],"type":"Point"}
}