{
  "type": "Feature",
  "properties": {
    "iso:country":"US",
    "name:eng_x_preferred":[
        "East Fogelsville"
    ],
    "name:eng_x_variant":[
        "E Fogelsville"
    ],
    "qs:gn_adm0_cc":"US",
    "qs:gn_fcode":"PPL",
    "qs:gn_local":5216861,
    "qs:gn_nam_loc":"Upper Macungie, Lehigh, Pennsylvania, US",
    "qs:gn_namadm1":"PA",
    "qs:gn_name":"East Fogelsville",
    "qs:local_max":238,
    "qs:local_sum":465,
    "qs:localhoods":6,
    "qs:name":"East Fogelsville",
    "qs:name_adm0":"United States",
    "qs:name_adm1":"Pennsylvania",
    "qs:name_adm2":"Lehigh",
    "qs:name_local":"Upper Macungie",
    "qs:photo_max":55,
    "qs:photo_sum":158,
    "qs:placetype":"Suburb",
    "qs:quad_count":15,
    "qs:woe_adm0":23424977,
    "qs:woe_adm1":2347597,
    "qs:woe_adm2":12589766,
    "qs:woe_lau":0,
    "qs:woe_local":28745493,
    "qs:woe_ver":"7.10.0",
    "wof:lang":[
        "eng"
    ],
    "wof:name":"East Fogelsville",
    "wof:placetype":"neighbourhood",
    "wof:population":763,
    "zs:blockids":[
        420770062022011,
        420770062021002,
        420770062042030,
        420770062023000,
        420770062021006,
        420770062022019,
        420770062024014,
        420770062042010,
        420770062042008,
        420770062023005,
        420770062023001,
        420770062041069,
        420770062021000,
        420770062022031,
        420770062022025,
        420770062022021,
        420770062022013,
        420770062022024,
        420770062022027,
        420770062042002,
        420770062042011,
        420770062042000,
        420770062021007,
        420770062022012,
        420770062042004,
        420770062041043,
        420770062042028,
        420770062042016,
        420770062022016,
        420770062042027,
        420770062022022,
        420770062022029,
        420770062022026,
        420770062022014,
        420770062041068,
        420770062024018,
        420770062021008,
        420770062022030,
        420770062041046,
        420770062023003,
        420770062042017,
        420770062042003,
        420770062042009,
        420770062042023,
        420770062042001,
        420770062022018,
        420770062021001,
        420770062022028,
        420770062022023,
        420770062042018,
        420770062042014,
        420770062041045,
        420770062022017,
        420770062042005,
        420770062023002,
        420770062022020,
        420770062042022,
        420770062042029,
        420770062042013,
        420770062042015,
        420770062021019,
        420770062042019,
        420770062041070,
        420770062022015,
        420770062022032,
        420770062021020
    ],
    "zs:housing10":291,
    "zs:pop10":763
},
  "geometry": {"coordinates":[-75.624612,40.579867],"type":"Point"}
}