{
  "type": "Feature",
  "properties": {
    "gn:admin1_code":"DE",
    "gn:admin2_code":"5.0",
    "gn:asciiname":"Fenwick Estates",
    "gn:country_code":"US",
    "gn:dem":4,
    "gn:elevation":"3.0",
    "gn:feature_class":"P",
    "gn:feature_code":"PPL",
    "gn:name":"Fenwick Estates",
    "gn:population":0,
    "gn:timezone":"America/New_York",
    "iso:country":"US",
    "name:eng_x_preferred":[
        "Fenwick Estates"
    ],
    "name:und_x_variant":[
        "Fenwick Development"
    ],
    "wof:name":"Fenwick Estates",
    "wof:placetype":"locality"
},
  "geometry": {"coordinates":[-75.05046,38.45233],"type":"Point"}
}