{
  "type": "Feature",
  "properties": {
    "gn:admin1_code":"OK",
    "gn:admin2_code":"143",
    "gn:asciiname":"Lake",
    "gn:country_code":"US",
    "gn:dem":199,
    "gn:elevation":"197.0",
    "gn:feature_class":"P",
    "gn:feature_code":"PPL",
    "gn:name":"Lake",
    "gn:population":0,
    "gn:timezone":"America/Chicago",
    "iso:country":"US",
    "name:azb_x_preferred":[
        "\u0644\u06cc\u06a9"
    ],
    "name:fas_x_preferred":[
        "\u0644\u06cc\u06a9"
    ],
    "name:urd_x_preferred":[
        "\u0644\u06cc\u06a9"
    ],
    "name:vol_x_preferred":[
        "Lake"
    ],
    "wof:name":"Lake",
    "wof:placetype":"locality"
},
  "geometry": {"coordinates":[-96.08195000000001,36.14009],"type":"Point"}
}