{
  "type": "Feature",
  "properties": {
    "iso:country":"US",
    "name:ara_x_preferred":[
        "\u063a\u0631\u064a\u0646 \u0623\u064a\u0643\u0631\u0632"
    ],
    "name:ast_x_preferred":[
        "Green Acres"
    ],
    "name:deu_x_preferred":[
        "Green Acres"
    ],
    "name:eng_x_preferred":[
        "Green Acres"
    ],
    "name:fra_x_preferred":[
        "Les Arpents verts"
    ],
    "name:gle_x_preferred":[
        "Green Acres"
    ],
    "name:glg_x_preferred":[
        "Granxeiro \u00faltimo modelo"
    ],
    "name:hye_x_preferred":[
        "\u053f\u0561\u0576\u0561\u0579 \u0561\u056f\u0580\u0565\u0580"
    ],
    "name:jpn_x_preferred":[
        "\u8fb2\u5712\u5929\u56fd"
    ],
    "name:nld_x_preferred":[
        "Green Acres"
    ],
    "name:rus_x_preferred":[
        "\u0417\u0435\u043b\u0451\u043d\u044b\u0435 \u043f\u0440\u043e\u0441\u0442\u043e\u0440\u044b"
    ],
    "name:spa_x_preferred":[
        "Green Acres"
    ],
    "name:ukr_x_preferred":[
        "\u0417\u0435\u043b\u0435\u043d\u0456 \u0433\u0435\u043a\u0442\u0430\u0440\u0438"
    ],
    "name:zho_x_preferred":[
        "\u7da0\u8272\u7530\u91ce"
    ],
    "wd:wordcount":3281,
    "wof:name":"Green Acres",
    "wof:placetype":"neighbourhood",
    "wof:population":155,
    "zs:area_m":1778875.771894,
    "zs:blockids":[
        40270009081033,
        40270009081049,
        40270009081055,
        40270009081048
    ],
    "zs:housing10":50,
    "zs:label":"Green Acres",
    "zs:pop10":155
},
  "geometry": {"coordinates":[-114.647115,32.643347],"type":"Point"}
}