{
  "type": "Feature",
  "properties": {
    "gn:country":"US",
    "gn:fcode":"PPL",
    "gn:population":9686,
    "iso:country":"US",
    "name:cat_x_preferred":[
        "Southborough"
    ],
    "name:ceb_x_preferred":[
        "Southborough"
    ],
    "name:che_x_preferred":[
        "\u0421\u0430\u0443\u0442\u0431\u043e\u0440\u043e"
    ],
    "name:cym_x_preferred":[
        "Southborough"
    ],
    "name:deu_x_preferred":[
        "Southborough"
    ],
    "name:eng_x_preferred":[
        "Southborough"
    ],
    "name:eus_x_preferred":[
        "Southborough"
    ],
    "name:fas_x_preferred":[
        "\u0633\u0627\u062a\u0628\u0631\u0648\u060c \u0645\u0627\u0633\u0627\u0686\u0648\u0633\u062a"
    ],
    "name:fas_x_variant":[
        "\u0633\u0627\u062a\u0628\u0631\u0648"
    ],
    "name:fra_x_preferred":[
        "Southborough"
    ],
    "name:hat_x_preferred":[
        "Southborough"
    ],
    "name:hun_x_preferred":[
        "Southborough"
    ],
    "name:ita_x_preferred":[
        "Southborough"
    ],
    "name:jpn_x_preferred":[
        "\u30b5\u30a6\u30b9\u30dc\u30ed"
    ],
    "name:kaz_x_preferred":[
        "\u0421\u043e\u0443\u0441\u0431\u043e\u0440\u043e\u0443"
    ],
    "name:kir_x_preferred":[
        "\u0421\u043e\u0443\u0441\u0431\u043e\u0440\u043e\u0443"
    ],
    "name:nld_x_preferred":[
        "Southborough"
    ],
    "name:pol_x_preferred":[
        "Southborough"
    ],
    "name:por_x_preferred":[
        "Southborough"
    ],
    "name:rus_x_preferred":[
        "\u0421\u0430\u0443\u0442\u0431\u043e\u0440\u043e"
    ],
    "name:spa_x_preferred":[
        "Southborough"
    ],
    "name:swe_x_preferred":[
        "Southborough"
    ],
    "name:tat_x_preferred":[
        "\u0421\u0430\u0443\u0442\u0431\u043e\u0440\u043e"
    ],
    "name:tur_x_preferred":[
        "Southborough"
    ],
    "name:ukr_x_preferred":[
        "\u0421\u0430\u0443\u0442\u0431\u043e\u0440\u043e"
    ],
    "name:und_x_variant":[
        "Southboro"
    ],
    "name:vol_x_preferred":[
        "Southborough"
    ],
    "name:zho_x_preferred":[
        "\u7ecd\u65af\u4f2f\u52d2"
    ],
    "qs_pg:aaroncc":"US",
    "qs_pg:gn_country":"US",
    "qs_pg:gn_fcode":"PPL",
    "qs_pg:gn_pop":9686,
    "qs_pg:name":"Southborough",
    "qs_pg:name_adm0":"United States",
    "qs_pg:name_adm1":"Massachusetts",
    "qs_pg:photos":1261,
    "qs_pg:photos_1k":256,
    "qs_pg:photos_9k":7,
    "qs_pg:photos_9r":8,
    "qs_pg:photos_all":1554,
    "qs_pg:photos_sr":12,
    "qs_pg:pop_sr":5,
    "qs_pg:qs_pg_placetype":"locality",
    "qs_pg:qs_pg_placetype_gp":"Town",
    "qs_pg:woe_adm0":23424977,
    "woe:adm0_id":23424977,
    "woe:name_adm0":"United States",
    "woe:name_adm1":"Massachusetts",
    "woe:placetype":"Town",
    "wof:name":"Southborough",
    "wof:placetype":"locality",
    "wof:population":9686
},
  "geometry": {"coordinates":[-71.52451000000001,42.30565],"type":"Point"}
}