{
  "type": "Feature",
  "properties": {
    "iso:country":"US",
    "name:eng_x_preferred":[
        "Forest Ridge"
    ],
    "name:eng_x_variant":[
        "Forest Rdg"
    ],
    "qs:gn_adm0_cc":"US",
    "qs:gn_local":4156404,
    "qs:local_max":6360,
    "qs:local_sum":28658,
    "qs:localhoods":41,
    "qs:name":"Forest Ridge",
    "qs:name_adm0":"United States",
    "qs:name_adm1":"Florida",
    "qs:name_adm2":"Alachua",
    "qs:name_local":"Gainesville",
    "qs:photo_max":142,
    "qs:photo_sum":250,
    "qs:placetype":"Suburb",
    "qs:quad_count":13,
    "qs:woe_adm0":23424977,
    "qs:woe_adm1":2347568,
    "qs:woe_adm2":12587803,
    "qs:woe_lau":0,
    "qs:woe_local":2408354,
    "qs:woe_ver":"7.10.0",
    "wof:lang":[
        "eng"
    ],
    "wof:name":"Forest Ridge",
    "wof:placetype":"neighbourhood",
    "wof:population":1843,
    "zs:blockids":[
        120010012032006,
        120010011003009,
        120010010001034,
        120010010001016,
        120010010001003,
        120010011003011,
        120010011003015,
        120010011003018,
        120010011003031,
        120010011003026,
        120010010001033,
        120010011003012,
        120010011003027,
        120010011003017,
        120010010005001,
        120010011003030,
        120010011003035,
        120010011003013,
        120010011003016,
        120010010001017,
        120010012032005,
        120010011003002,
        120010011003008,
        120010011003007,
        120010010001007,
        120010011003001,
        120010011003020,
        120010010001009,
        120010010001008,
        120010011003014,
        120010011003019,
        120010011003033,
        120010011003024,
        120010010001004,
        120010010001018,
        120010011003025,
        120010011003010,
        120010011003022,
        120010010001015,
        120010011003032,
        120010011003006,
        120010011003004,
        120010010001010,
        120010011004022,
        120010011003000,
        120010011003021,
        120010011003029,
        120010011003023,
        120010010001006,
        120010011004017,
        120010011004025
    ],
    "zs:housing10":903,
    "zs:pop10":1843
},
  "geometry": {"coordinates":[-82.34608299999999,29.671555],"type":"Point"}
}