{
  "type": "Feature",
  "properties": {
    "gn:admin1_code":"LA",
    "gn:admin2_code":"7.0",
    "gn:asciiname":"Bellewood",
    "gn:country_code":"US",
    "gn:dem":6,
    "gn:elevation":"2.0",
    "gn:feature_class":"P",
    "gn:feature_code":"PPL",
    "gn:name":"Bellewood",
    "gn:population":0,
    "gn:timezone":"America/Chicago",
    "iso:country":"US",
    "name:eng_x_preferred":[
        "Bellewood"
    ],
    "name:und_x_variant":[
        "Belle Wood"
    ],
    "wof:name":"Bellewood",
    "wof:placetype":"locality"
},
  "geometry": {"coordinates":[-91.06816000000001,29.90687],"type":"Point"}
}