{
  "type": "Feature",
  "properties": {
    "iso:country":"US",
    "name:eng_x_preferred":[
        "Golf View"
    ],
    "wd:wordcount":273,
    "wof:name":"Golf View",
    "wof:placetype":"neighbourhood",
    "zs:area_m":6102.788337,
    "zs:blockids":[
        240217505063018,
        240217505063041
    ],
    "zs:housing10":0,
    "zs:label":"Golf View",
    "zs:pop10":0
},
  "geometry": {"coordinates":[-77.46393,39.420186],"type":"Point"}
}