{
  "type": "Feature",
  "properties": {
    "gn:admin1_code":"VA",
    "gn:admin2_code":"550.0",
    "gn:asciiname":"Jolliff Woods",
    "gn:country_code":"US",
    "gn:dem":4,
    "gn:elevation":"6.0",
    "gn:feature_class":"P",
    "gn:feature_code":"PPL",
    "gn:name":"Jolliff Woods",
    "gn:population":0,
    "gn:timezone":"America/New_York",
    "iso:country":"US",
    "wof:name":"Jolliff Woods",
    "wof:placetype":"locality"
},
  "geometry": {"coordinates":[-76.44055999999998,36.80361],"type":"Point"}
}