{
  "type": "Feature",
  "properties": {
    "gn:admin1_code":"OR",
    "gn:admin2_code":"39",
    "gn:asciiname":"Alpha",
    "gn:country_code":"US",
    "gn:dem":128,
    "gn:elevation":"127.0",
    "gn:feature_class":"P",
    "gn:feature_code":"PPL",
    "gn:name":"Alpha",
    "gn:population":0,
    "gn:timezone":"America/Los_Angeles",
    "iso:country":"US",
    "wof:name":"Alpha",
    "wof:placetype":"locality"
},
  "geometry": {"coordinates":[-123.70066,44.16429],"type":"Point"}
}