{
  "type": "Feature",
  "properties": {
    "gn:admin1_code":"MS",
    "gn:admin2_code":"147.0",
    "gn:asciiname":"Kirklin",
    "gn:country_code":"US",
    "gn:dem":101,
    "gn:elevation":"98.0",
    "gn:feature_class":"P",
    "gn:feature_code":"PPL",
    "gn:name":"Kirklin",
    "gn:population":0,
    "gn:timezone":"America/Chicago",
    "iso:country":"US",
    "wof:name":"Kirklin",
    "wof:placetype":"locality"
},
  "geometry": {"coordinates":[-90.11592,31.04796],"type":"Point"}
}