{
  "type": "Feature",
  "properties": {
    "gn:admin1_code":"NC",
    "gn:admin2_code":"55",
    "gn:admin3_code":"90964.0",
    "gn:asciiname":"Beach Land Landing",
    "gn:country_code":"US",
    "gn:dem":12,
    "gn:elevation":"0.0",
    "gn:feature_class":"P",
    "gn:feature_code":"PPL",
    "gn:name":"Beach Land Landing",
    "gn:population":0,
    "gn:timezone":"America/New_York",
    "iso:country":"US",
    "wof:name":"Beach Land Landing",
    "wof:placetype":"locality"
},
  "geometry": {"coordinates":[-75.90852,35.79266],"type":"Point"}
}