{
  "type": "Feature",
  "properties": {
    "gn:admin1_code":"WA",
    "gn:admin2_code":"73.0",
    "gn:asciiname":"Diablo",
    "gn:country_code":"US",
    "gn:dem":277,
    "gn:elevation":"273.0",
    "gn:feature_class":"P",
    "gn:feature_code":"PPL",
    "gn:name":"Diablo",
    "gn:population":0,
    "gn:timezone":"America/Los_Angeles",
    "iso:country":"US",
    "name:fas_x_preferred":[
        "\u062f\u06cc\u0627\u0628\u0644\u0648"
    ],
    "name:fra_x_preferred":[
        "Diablo"
    ],
    "wof:name":"Diablo",
    "wof:placetype":"locality"
},
  "geometry": {"coordinates":[-121.14122999999999,48.71346],"type":"Point"}
}