{
  "type": "Feature",
  "properties": {
    "gn:admin1_code":"MT",
    "gn:admin2_code":"79.0",
    "gn:asciiname":"Crow Rock",
    "gn:country_code":"US",
    "gn:dem":828,
    "gn:elevation":"831.0",
    "gn:feature_class":"P",
    "gn:feature_code":"PPL",
    "gn:name":"Crow Rock",
    "gn:population":0,
    "gn:timezone":"America/Denver",
    "iso:country":"US",
    "name:ceb_x_preferred":[
        "Crow Rock"
    ],
    "name:nno_x_preferred":[
        "Crow Rock"
    ],
    "name:swe_x_preferred":[
        "Crow Rock"
    ],
    "wof:name":"Crow Rock",
    "wof:placetype":"locality"
},
  "geometry": {"coordinates":[-106.07086,46.91139],"type":"Point"}
}