{
  "type": "Feature",
  "properties": {
    "gn:admin1_code":"TX",
    "gn:admin2_code":"85.0",
    "gn:asciiname":"Bloomdale",
    "gn:country_code":"US",
    "gn:dem":213,
    "gn:elevation":"206.0",
    "gn:feature_class":"P",
    "gn:feature_code":"PPL",
    "gn:name":"Bloomdale",
    "gn:population":0,
    "gn:timezone":"America/Chicago",
    "iso:country":"US",
    "wof:name":"Bloomdale",
    "wof:placetype":"locality"
},
  "geometry": {"coordinates":[-96.67944,33.24734],"type":"Point"}
}