{
  "type": "Feature",
  "properties": {
    "gn:admin1_code":"NJ",
    "gn:admin2_code":"37.0",
    "gn:admin3_code":"69690.0",
    "gn:asciiname":"Mahola",
    "gn:country_code":"US",
    "gn:dem":354,
    "gn:elevation":"344.0",
    "gn:feature_class":"P",
    "gn:feature_code":"PPL",
    "gn:name":"Mahola",
    "gn:population":0,
    "gn:timezone":"America/New_York",
    "iso:country":"US",
    "wof:name":"Mahola",
    "wof:placetype":"locality"
},
  "geometry": {"coordinates":[-74.59238000000001,41.03565],"type":"Point"}
}