{
  "type": "Feature",
  "properties": {
    "gn:admin1_code":"TN",
    "gn:admin2_code":"121.0",
    "gn:asciiname":"Akeman Crossroad",
    "gn:country_code":"US",
    "gn:dem":236,
    "gn:elevation":"236.0",
    "gn:feature_class":"P",
    "gn:feature_code":"PPL",
    "gn:name":"Akeman Crossroad",
    "gn:population":0,
    "gn:timezone":"America/New_York",
    "iso:country":"US",
    "wof:name":"Akeman Crossroad",
    "wof:placetype":"locality"
},
  "geometry": {"coordinates":[-84.75133000000002,35.62674000000001],"type":"Point"}
}