{
  "type": "Feature",
  "properties": {
    "gn:admin1_code":"NH",
    "gn:admin2_code":"15.0",
    "gn:admin3_code":"33060.0",
    "gn:asciiname":"Hampton Beach State Recreational Vehicle Park",
    "gn:country_code":"US",
    "gn:dem":1,
    "gn:elevation":"0.0",
    "gn:feature_class":"P",
    "gn:feature_code":"PPL",
    "gn:name":"Hampton Beach State Recreational Vehicle Park",
    "gn:population":0,
    "gn:timezone":"America/New_York",
    "iso:country":"US",
    "wof:name":"Hampton Beach State Recreational Vehicle Park",
    "wof:placetype":"locality"
},
  "geometry": {"coordinates":[-70.81421999999998,42.89704],"type":"Point"}
}