{
  "type": "Feature",
  "properties": {
    "gn:admin1_code":"TN",
    "gn:admin2_code":"1",
    "gn:asciiname":"Fork Mountain",
    "gn:country_code":"US",
    "gn:dem":478,
    "gn:elevation":"473.0",
    "gn:feature_class":"P",
    "gn:feature_code":"PPL",
    "gn:name":"Fork Mountain",
    "gn:population":0,
    "gn:timezone":"America/New_York",
    "iso:country":"US",
    "wof:name":"Fork Mountain",
    "wof:placetype":"locality"
},
  "geometry": {"coordinates":[-84.41993000000002,36.12674000000001],"type":"Point"}
}