{
  "type": "Feature",
  "properties": {
    "gn:admin1_code":"OH",
    "gn:admin2_code":"155",
    "gn:admin3_code":"8056.0",
    "gn:asciiname":"Arhaven Estates",
    "gn:country_code":"US",
    "gn:dem":279,
    "gn:elevation":"275.0",
    "gn:feature_class":"P",
    "gn:feature_code":"PPL",
    "gn:name":"Arhaven Estates",
    "gn:population":0,
    "gn:timezone":"America/New_York",
    "iso:country":"US",
    "wof:name":"Arhaven Estates",
    "wof:placetype":"locality"
},
  "geometry": {"coordinates":[-80.93416999999999,41.21611],"type":"Point"}
}