{
  "type": "Feature",
  "properties": {
    "gn:admin1_code":"AL",
    "gn:admin2_code":"83",
    "gn:asciiname":"Murphree Place",
    "gn:country_code":"US",
    "gn:dem":189,
    "gn:elevation":"187.0",
    "gn:feature_class":"P",
    "gn:feature_code":"PPL",
    "gn:name":"Murphree Place",
    "gn:population":0,
    "gn:timezone":"America/Chicago",
    "iso:country":"US",
    "wof:name":"Murphree Place",
    "wof:placetype":"locality"
},
  "geometry": {"coordinates":[-86.95695000000001,34.6987],"type":"Point"}
}