{
  "type": "Feature",
  "properties": {
    "gn:admin1_code":"MD",
    "gn:admin2_code":"5.0",
    "gn:asciiname":"Town and Country North",
    "gn:country_code":"US",
    "gn:dem":154,
    "gn:elevation":"155.0",
    "gn:feature_class":"P",
    "gn:feature_code":"PPL",
    "gn:name":"Town and Country North",
    "gn:population":0,
    "gn:timezone":"America/New_York",
    "iso:country":"US",
    "wof:name":"Town and Country North",
    "wof:placetype":"locality"
},
  "geometry": {"coordinates":[-76.61886,39.46955],"type":"Point"}
}