{
  "type": "Feature",
  "properties": {
    "gn:admin1_code":"KS",
    "gn:admin2_code":"41.0",
    "gn:admin3_code":"125.0",
    "gn:asciiname":"Cottonwood Mobile Home Park",
    "gn:country_code":"US",
    "gn:dem":354,
    "gn:elevation":"351.0",
    "gn:feature_class":"P",
    "gn:feature_code":"PPL",
    "gn:name":"Cottonwood Mobile Home Park",
    "gn:population":0,
    "gn:timezone":"America/Chicago",
    "iso:country":"US",
    "wof:name":"Cottonwood Mobile Home Park",
    "wof:placetype":"campus"
},
  "geometry": {"coordinates":[-97.2256,38.91405],"type":"Point"}
}