{
  "type": "Feature",
  "properties": {
    "gn:admin1_code":"ID",
    "gn:admin2_code":"7.0",
    "gn:asciiname":"Harer",
    "gn:country_code":"US",
    "gn:dem":1830,
    "gn:elevation":"1830.0",
    "gn:feature_class":"P",
    "gn:feature_code":"PPL",
    "gn:name":"Harer",
    "gn:population":0,
    "gn:timezone":"America/Boise",
    "iso:country":"US",
    "wof:name":"Harer",
    "wof:placetype":"locality"
},
  "geometry": {"coordinates":[-111.17158999999999,42.18938],"type":"Point"}
}