{
  "type": "Feature",
  "properties": {
    "gn:admin1_code":"WV",
    "gn:admin2_code":"97.0",
    "gn:asciiname":"Queens",
    "gn:country_code":"US",
    "gn:dem":597,
    "gn:elevation":"593.0",
    "gn:feature_class":"P",
    "gn:feature_code":"PPL",
    "gn:name":"Queens",
    "gn:population":0,
    "gn:timezone":"America/New_York",
    "iso:country":"US",
    "name:eng_x_preferred":[
        "Queens"
    ],
    "name:und_x_variant":[
        "Queens Mills",
        "Queen",
        "Queens Mill"
    ],
    "wof:name":"Queens",
    "wof:placetype":"locality"
},
  "geometry": {"coordinates":[-80.13674,38.85705],"type":"Point"}
}