{
  "type": "Feature",
  "properties": {
    "gn:country":"US",
    "gn:fcode":"PPL",
    "gn:population":0,
    "iso:country":"US",
    "name:bre_x_preferred":[
        "Cl\u00e9ment"
    ],
    "name:ces_x_preferred":[
        "Clement"
    ],
    "name:deu_x_preferred":[
        "Clement"
    ],
    "name:fas_x_preferred":[
        "\u06a9\u0644\u0645\u0646\u062a"
    ],
    "name:fin_x_preferred":[
        "Clement"
    ],
    "name:fra_x_preferred":[
        "Cl\u00e9ment"
    ],
    "name:hrv_x_preferred":[
        "Clement"
    ],
    "name:hye_x_preferred":[
        "\u053f\u056c\u0565\u0574\u0561\u0576"
    ],
    "name:ita_x_preferred":[
        "Clement"
    ],
    "name:jpn_x_preferred":[
        "\u30af\u30ec\u30de\u30f3"
    ],
    "name:ltz_x_preferred":[
        "Clement"
    ],
    "name:nld_x_preferred":[
        "Clement"
    ],
    "name:pol_x_preferred":[
        "Clement"
    ],
    "name:por_x_preferred":[
        "Clement"
    ],
    "name:rus_x_preferred":[
        "\u041a\u043b\u0435\u043c\u0430\u043d"
    ],
    "name:swe_x_preferred":[
        "Clement"
    ],
    "name:ukr_x_preferred":[
        "\u041a\u043b\u0435\u043c\u0430\u043d"
    ],
    "name:zho_x_preferred":[
        "\u514b\u83b1\u95e8\u7279"
    ],
    "qs_pg:aaroncc":"US",
    "qs_pg:gn_country":"US",
    "qs_pg:gn_fcode":"PPL",
    "qs_pg:gn_pop":0,
    "qs_pg:name":"Clement",
    "qs_pg:name_adm0":"United States",
    "qs_pg:name_adm1":"Ohio",
    "qs_pg:photos":19,
    "qs_pg:photos_1k":4,
    "qs_pg:photos_9k":1,
    "qs_pg:photos_9r":1,
    "qs_pg:photos_all":19,
    "qs_pg:photos_sr":1,
    "qs_pg:pop_sr":0,
    "qs_pg:qs_pg_placetype":"locality",
    "qs_pg:qs_pg_placetype_gp":"Town",
    "qs_pg:woe_adm0":23424977,
    "woe:adm0_id":23424977,
    "woe:name_adm0":"United States",
    "woe:name_adm1":"Ohio",
    "woe:placetype":"Town",
    "wof:name":"Clement",
    "wof:placetype":"locality"
},
  "geometry": {"coordinates":[-84.10549,39.74034],"type":"Point"}
}