{
  "type": "Feature",
  "properties": {
    "gn:admin1_code":"LA",
    "gn:admin2_code":"9.0",
    "gn:asciiname":"Bodoc",
    "gn:country_code":"US",
    "gn:dem":19,
    "gn:elevation":"12.0",
    "gn:feature_class":"P",
    "gn:feature_code":"PPL",
    "gn:name":"Bodoc",
    "gn:population":0,
    "gn:timezone":"America/Chicago",
    "iso:country":"US",
    "wof:name":"Bodoc",
    "wof:placetype":"locality"
},
  "geometry": {"coordinates":[-91.99066999999999,30.91908],"type":"Point"}
}