{
  "type": "Feature",
  "properties": {
    "gn:admin1_code":"KS",
    "gn:admin2_code":"173.0",
    "gn:admin3_code":"73275.0",
    "gn:asciiname":"McKinley Mobile Home Park",
    "gn:country_code":"US",
    "gn:dem":425,
    "gn:elevation":"418.0",
    "gn:feature_class":"P",
    "gn:feature_code":"PPL",
    "gn:name":"McKinley Mobile Home Park",
    "gn:population":0,
    "gn:timezone":"America/Chicago",
    "iso:country":"US",
    "wof:name":"McKinley Mobile Home Park",
    "wof:placetype":"campus"
},
  "geometry": {"coordinates":[-97.42354,37.91156],"type":"Point"}
}