{
  "type": "Feature",
  "properties": {
    "iso:country":"US",
    "name:eng_x_preferred":[
        "Cal-Gisler"
    ],
    "qs:gn_adm0_cc":"US",
    "qs:gn_local":5380184,
    "qs:gn_nam_loc":"Oxnard, Ventura, California, US",
    "qs:gn_namadm1":"CA",
    "qs:local_max":1503,
    "qs:local_sum":8135,
    "qs:localhoods":30,
    "qs:name":"Cal-Gisler",
    "qs:name_adm0":"United States",
    "qs:name_adm1":"California",
    "qs:name_adm2":"Ventura",
    "qs:name_local":"Oxnard",
    "qs:photo_max":900,
    "qs:photo_sum":1092,
    "qs:placetype":"Suburb",
    "qs:quad_count":14,
    "qs:woe_adm0":23424977,
    "qs:woe_adm1":2347563,
    "qs:woe_adm2":12587725,
    "qs:woe_lau":0,
    "qs:woe_local":2467212,
    "qs:woe_ver":"7.10.0",
    "wof:lang":[
        "eng"
    ],
    "wof:name":"Cal-Gisler",
    "wof:placetype":"neighbourhood",
    "zs:blockids":[
        61110091003019,
        61110091003018
    ],
    "zs:housing10":0,
    "zs:pop10":0
},
  "geometry": {"coordinates":[-119.16493199999999,34.183002],"type":"Point"}
}