{
  "type": "Feature",
  "properties": {
    "gn:elevation":63,
    "iso:country":"US",
    "name:eng_x_preferred":[
        "Mealing Heights"
    ],
    "name:eng_x_variant":[
        "Mealing Hts"
    ],
    "qs:gn_adm0_cc":"US",
    "qs:gn_fcode":"PPLX",
    "qs:gn_local":4180531,
    "qs:gn_nam_loc":"Augusta, Richmond, Georgia, US",
    "qs:gn_namadm1":"SC",
    "qs:gn_name":"Mealing Heights",
    "qs:local_max":3765,
    "qs:local_sum":16447,
    "qs:localhoods":24,
    "qs:name":"Mealing Heights",
    "qs:name_adm0":"United States",
    "qs:name_adm1":"South Carolina",
    "qs:name_adm2":"Aiken",
    "qs:name_local":"Augusta",
    "qs:photo_max":54,
    "qs:photo_sum":115,
    "qs:placetype":"Suburb",
    "qs:quad_count":5,
    "qs:woe_adm0":23424977,
    "qs:woe_adm1":2347599,
    "qs:woe_adm2":12589801,
    "qs:woe_lau":0,
    "qs:woe_local":2357383,
    "qs:woe_ver":"7.10.0",
    "wof:lang":[
        "eng"
    ],
    "wof:name":"Mealing Heights",
    "wof:placetype":"neighbourhood",
    "wof:population":23,
    "zs:blockids":[
        450030208022014,
        450030208022013,
        450030208022012,
        450030208022023,
        450030208022021
    ],
    "zs:housing10":20,
    "zs:pop10":23
},
  "geometry": {"coordinates":[-81.972835,33.487687],"type":"Point"}
}