{
  "type": "Feature",
  "properties": {
    "iso:country":"US",
    "name:eng_x_preferred":[
        "North Hollow"
    ],
    "wof:name":"North Hollow",
    "wof:placetype":"neighbourhood",
    "zs:area_m":2404278.287363,
    "zs:blockids":[
        90033301001058,
        90033301001093
    ],
    "zs:housing10":0,
    "zs:label":"North Hollow",
    "zs:pop10":0
},
  "geometry": {"coordinates":[-72.947446,42.015923],"type":"Point"}
}