{
  "type": "Feature",
  "properties": {
    "gn:admin1_code":"TX",
    "gn:admin2_code":"119.0",
    "gn:asciiname":"Charleston",
    "gn:country_code":"US",
    "gn:dem":139,
    "gn:elevation":"134.0",
    "gn:feature_class":"P",
    "gn:feature_code":"PPL",
    "gn:name":"Charleston",
    "gn:population":0,
    "gn:timezone":"America/Chicago",
    "iso:country":"US",
    "name:afr_x_preferred":[
        "Charleston"
    ],
    "name:ara_x_preferred":[
        "\u062a\u0634\u0627\u0631\u0644\u0633\u062a\u0648\u0646"
    ],
    "name:ast_x_preferred":[
        "Charleston"
    ],
    "name:bel_x_preferred":[
        "\u0427\u0430\u0440\u043b\u0441\u0442\u0430\u043d"
    ],
    "name:bre_x_preferred":[
        "Charleston"
    ],
    "name:bul_x_preferred":[
        "\u0427\u0430\u0440\u043b\u0441\u0442\u044a\u043d"
    ],
    "name:cat_x_preferred":[
        "Charleston"
    ],
    "name:ceb_x_preferred":[
        "Charleston"
    ],
    "name:ces_x_preferred":[
        "Charleston"
    ],
    "name:dan_x_preferred":[
        "Charleston"
    ],
    "name:deu_x_preferred":[
        "Charleston"
    ],
    "name:ell_x_preferred":[
        "\u03a4\u03c3\u03ac\u03c1\u03bb\u03b5\u03c3\u03c4\u03bf\u03bd"
    ],
    "name:epo_x_preferred":[
        "Charleston"
    ],
    "name:est_x_preferred":[
        "Charleston"
    ],
    "name:eus_x_preferred":[
        "Charleston"
    ],
    "name:fas_x_preferred":[
        "\u0686\u0627\u0631\u0644\u0633\u062a\u0648\u0646"
    ],
    "name:fin_x_preferred":[
        "Charleston"
    ],
    "name:fra_x_preferred":[
        "Charleston"
    ],
    "name:heb_x_preferred":[
        "\u05e6'\u05d0\u05e8\u05dc\u05e1\u05d8\u05d5\u05df"
    ],
    "name:hun_x_preferred":[
        "Charleston"
    ],
    "name:ita_x_preferred":[
        "Charleston"
    ],
    "name:jpn_x_preferred":[
        "\u30c1\u30e3\u30fc\u30eb\u30b9\u30c8\u30f3"
    ],
    "name:kor_x_preferred":[
        "\ucc30\uc2a4\ud134"
    ],
    "name:nld_x_preferred":[
        "Charleston"
    ],
    "name:nno_x_preferred":[
        "Charleston"
    ],
    "name:nor_x_preferred":[
        "Charleston"
    ],
    "name:pol_x_preferred":[
        "Charleston"
    ],
    "name:por_x_preferred":[
        "Charleston"
    ],
    "name:ron_x_preferred":[
        "Charleston"
    ],
    "name:rus_x_preferred":[
        "\u0427\u0430\u0440\u043b\u0441\u0442\u043e\u043d"
    ],
    "name:sco_x_preferred":[
        "Charleston"
    ],
    "name:slk_x_preferred":[
        "Charleston"
    ],
    "name:spa_x_preferred":[
        "Charleston"
    ],
    "name:srp_x_preferred":[
        "\u0427\u0430\u0440\u043b\u0441\u0442\u043e\u043d"
    ],
    "name:swa_x_preferred":[
        "Charleston"
    ],
    "name:swe_x_preferred":[
        "Charleston"
    ],
    "name:tur_x_preferred":[
        "Charleston"
    ],
    "name:ukr_x_preferred":[
        "\u0427\u0430\u0440\u043b\u0441\u0442\u043e\u043d"
    ],
    "name:urd_x_preferred":[
        "\u0686\u0627\u0631\u0644\u0633\u0679\u0646"
    ],
    "name:vol_x_preferred":[
        "Charleston"
    ],
    "name:zho_x_preferred":[
        "\u67e5\u5c14\u65af\u987f"
    ],
    "wof:name":"Charleston",
    "wof:placetype":"locality"
},
  "geometry": {"coordinates":[-95.53384,33.3865],"type":"Point"}
}