{
  "type": "Feature",
  "properties": {
    "gn:elevation":86,
    "gn:population":2541,
    "iso:country":"US",
    "name:ara_x_preferred":[
        "\u0645\u064a\u062f\u0648 \u063a\u0644\u0627\u062f"
    ],
    "name:azb_x_preferred":[
        "\u0645\u06cc\u062f\u0648 \u0642\u0644\u06cc\u062f"
    ],
    "name:cat_x_preferred":[
        "Meadow Glade"
    ],
    "name:ceb_x_preferred":[
        "Meadow Glade"
    ],
    "name:che_x_preferred":[
        "\u041c\u0435\u0434\u043e\u0443-\u0413\u043b\u0435\u0439\u0434"
    ],
    "name:deu_x_preferred":[
        "Meadow Glade"
    ],
    "name:eng_x_preferred":[
        "Meadow Glade"
    ],
    "name:eus_x_preferred":[
        "Meadow Glade"
    ],
    "name:fas_x_preferred":[
        "\u0645\u06cc\u062f\u0648 \u06af\u0644\u06cc\u062f"
    ],
    "name:fra_x_preferred":[
        "Meadow Glade"
    ],
    "name:gle_x_preferred":[
        "Meadow Glade"
    ],
    "name:hun_x_preferred":[
        "Meadow Glade"
    ],
    "name:ita_x_preferred":[
        "Meadow Glade"
    ],
    "name:lld_x_preferred":[
        "Meadow Glade"
    ],
    "name:nan_x_preferred":[
        "Meadow Glade"
    ],
    "name:nld_x_preferred":[
        "Meadow Glade"
    ],
    "name:pol_x_preferred":[
        "Meadow Glade"
    ],
    "name:por_x_preferred":[
        "Meadow Glade"
    ],
    "name:spa_x_preferred":[
        "Meadow Glade"
    ],
    "name:srp_x_preferred":[
        "\u041c\u0435\u0434\u043e\u0443 \u0413\u043b\u0435\u0458\u0434"
    ],
    "name:tat_x_preferred":[
        "\u041c\u0435\u0434\u043e\u0443-\u0413\u043b\u0435\u0439\u0434"
    ],
    "name:ukr_x_preferred":[
        "\u041c\u0435\u0434\u043e\u0443-\u0413\u043b\u0435\u0439\u0434"
    ],
    "name:uzb_x_preferred":[
        "Meadow Glade"
    ],
    "name:vol_x_preferred":[
        "Meadow Glade"
    ],
    "name:zho_x_preferred":[
        "\u6885\u591a\u683c\u840a\u5fb7"
    ],
    "qs:gn_adm0_cc":"US",
    "qs:gn_fcode":"PPL",
    "qs:gn_local":5786485,
    "qs:gn_nam_loc":"Battle Ground, Clark, Washington, US",
    "qs:gn_namadm1":"WA",
    "qs:gn_name":"Meadow Glade",
    "qs:local_max":200,
    "qs:local_sum":311,
    "qs:localhoods":5,
    "qs:name":"Meadow Glade",
    "qs:name_adm0":"United States",
    "qs:name_adm1":"Washington",
    "qs:name_adm2":"Clark",
    "qs:name_local":"Battle Ground",
    "qs:photo_max":1,
    "qs:photo_sum":1,
    "qs:placetype":"Suburb",
    "qs:quad_count":1,
    "qs:woe_adm0":23424977,
    "qs:woe_adm1":2347606,
    "qs:woe_adm2":12590445,
    "qs:woe_lau":0,
    "qs:woe_local":2360057,
    "qs:woe_ver":"7.10.0",
    "wof:lang":[
        "eng"
    ],
    "wof:name":"Meadow Glade",
    "wof:placetype":"neighbourhood",
    "wof:population":2541
},
  "geometry": {"coordinates":[-122.56073000000001,45.754108],"type":"Point"}
}