{
  "type": "Feature",
  "properties": {
    "gn:admin1_code":"NY",
    "gn:admin2_code":"65.0",
    "gn:admin3_code":"63418.0",
    "gn:asciiname":"Coonrod",
    "gn:country_code":"US",
    "gn:dem":131,
    "gn:elevation":"133.0",
    "gn:feature_class":"P",
    "gn:feature_code":"PPL",
    "gn:name":"Coonrod",
    "gn:population":0,
    "gn:timezone":"America/New_York",
    "iso:country":"US",
    "wof:name":"Coonrod",
    "wof:placetype":"locality"
},
  "geometry": {"coordinates":[-75.52323,43.2484],"type":"Point"}
}