{
  "type": "Feature",
  "properties": {
    "gn:elevation":137,
    "iso:country":"US",
    "name:eng_x_preferred":[
        "Pill Hill"
    ],
    "name:eng_x_variant":[
        "Pill Hl"
    ],
    "qs:gn_adm0_cc":"US",
    "qs:gn_fcode":"PPL",
    "qs:gn_local":5095626,
    "qs:gn_nam_loc":"Bernardsville, Somerset, New Jersey, US",
    "qs:gn_namadm1":"NJ",
    "qs:gn_name":"Pill Hill",
    "qs:local_max":209,
    "qs:local_sum":218,
    "qs:localhoods":2,
    "qs:name":"Pill Hill",
    "qs:name_adm0":"United States",
    "qs:name_adm1":"New Jersey",
    "qs:name_adm2":"Somerset",
    "qs:name_local":"Bernardsville",
    "qs:photo_max":7,
    "qs:photo_sum":9,
    "qs:placetype":"Suburb",
    "qs:quad_count":2,
    "qs:woe_adm0":23424977,
    "qs:woe_adm1":2347589,
    "qs:woe_adm2":12589275,
    "qs:woe_lau":0,
    "qs:woe_local":2363070,
    "qs:woe_ver":"7.10.0",
    "wof:lang":[
        "eng"
    ],
    "wof:name":"Pill Hill",
    "wof:placetype":"neighbourhood",
    "wof:population":361,
    "zs:blockids":[
        340350527004011,
        340350527004013,
        340350527004010,
        340350527004032,
        340350527004012,
        340350527004009
    ],
    "zs:housing10":126,
    "zs:pop10":361
},
  "geometry": {"coordinates":[-74.57794199999999,40.712797],"type":"Point"}
}