{
  "type": "Feature",
  "properties": {
    "gn:admin1_code":"NY",
    "gn:admin2_code":"27.0",
    "gn:admin3_code":"58695.0",
    "gn:asciiname":"Cedar Hollow Mobile Home Park",
    "gn:country_code":"US",
    "gn:dem":69,
    "gn:elevation":"70.0",
    "gn:feature_class":"P",
    "gn:feature_code":"PPL",
    "gn:name":"Cedar Hollow Mobile Home Park",
    "gn:population":0,
    "gn:timezone":"America/New_York",
    "iso:country":"US",
    "wof:name":"Cedar Hollow Mobile Home Park",
    "wof:placetype":"campus"
},
  "geometry": {"coordinates":[-73.80422,41.77378],"type":"Point"}
}