{
  "type": "Feature",
  "properties": {
    "iso:country":"US",
    "name:eng_x_preferred":[
        "Hamburg"
    ],
    "name:fas_x_preferred":[
        "\u0647\u0627\u0645\u0628\u0648\u0631\u06af"
    ],
    "name:fra_x_preferred":[
        "Hamburg"
    ],
    "name:urd_x_preferred":[
        "\u06c1\u06cc\u0645\u0628\u0631\u06af"
    ],
    "name:zho_x_preferred":[
        "\u6f22\u5821"
    ],
    "qs:gn_adm0_cc":"US",
    "qs:gn_fcode":"PPL",
    "qs:gn_local":4264598,
    "qs:gn_nam_loc":"Sellersburg, Clark, Indiana, US",
    "qs:gn_namadm1":"IN",
    "qs:gn_name":"Hamburg",
    "qs:local_max":98,
    "qs:local_sum":98,
    "qs:localhoods":1,
    "qs:name":"Hamburg",
    "qs:name_adm0":"United States",
    "qs:name_adm1":"Indiana",
    "qs:name_adm2":"Clark",
    "qs:name_local":"Sellersburg",
    "qs:photo_max":43,
    "qs:photo_sum":98,
    "qs:placetype":"Suburb",
    "qs:quad_count":19,
    "qs:woe_adm0":23424977,
    "qs:woe_adm1":2347573,
    "qs:woe_adm2":12588189,
    "qs:woe_lau":0,
    "qs:woe_local":2490688,
    "qs:woe_ver":"7.10.0",
    "wof:lang":[
        "eng"
    ],
    "wof:name":"Hamburg",
    "wof:placetype":"neighbourhood",
    "wof:population":1801,
    "zs:blockids":[
        180430710051002,
        180430710053003,
        180430710053002,
        180430710051008,
        180430710051001,
        180430710051000,
        180430710053004,
        180430710053000,
        180430710051003
    ],
    "zs:housing10":627,
    "zs:pop10":1801
},
  "geometry": {"coordinates":[-85.764196,38.379971],"type":"Point"}
}