{
  "type": "Feature",
  "properties": {
    "gn:admin1_code":"NC",
    "gn:admin2_code":"115.0",
    "gn:asciiname":"Terry Fork",
    "gn:country_code":"US",
    "gn:dem":772,
    "gn:elevation":"762.0",
    "gn:feature_class":"P",
    "gn:feature_code":"PPL",
    "gn:name":"Terry Fork",
    "gn:population":0,
    "gn:timezone":"America/New_York",
    "iso:country":"US",
    "name:eng_x_preferred":[
        "Terry Fork"
    ],
    "name:und_x_variant":[
        "Just"
    ],
    "wof:name":"Terry Fork",
    "wof:placetype":"locality"
},
  "geometry": {"coordinates":[-82.44069,35.8215],"type":"Point"}
}