{
  "type": "Feature",
  "properties": {
    "gn:admin1_code":"FL",
    "gn:admin2_code":"57",
    "gn:asciiname":"Winding Creek",
    "gn:country_code":"US",
    "gn:dem":15,
    "gn:elevation":"4.0",
    "gn:feature_class":"P",
    "gn:feature_code":"PPL",
    "gn:name":"Winding Creek",
    "gn:population":0,
    "gn:timezone":"America/New_York",
    "iso:country":"US",
    "wof:name":"Winding Creek",
    "wof:placetype":"locality"
},
  "geometry": {"coordinates":[-82.45299999999997,27.6687],"type":"Point"}
}