{
  "type": "Feature",
  "properties": {
    "gn:admin1_code":"AL",
    "gn:admin2_code":"87",
    "gn:asciiname":"Milstead",
    "gn:country_code":"US",
    "gn:dem":65,
    "gn:elevation":"63.0",
    "gn:feature_class":"P",
    "gn:feature_code":"PPL",
    "gn:name":"Milstead",
    "gn:population":0,
    "gn:timezone":"America/Chicago",
    "iso:country":"US",
    "name:ceb_x_preferred":[
        "Milstead"
    ],
    "name:cym_x_preferred":[
        "Milstead"
    ],
    "name:eng_x_preferred":[
        "Milstead"
    ],
    "name:fas_x_preferred":[
        "\u0645\u06cc\u0644\u0633\u062a\u062f"
    ],
    "name:ita_x_preferred":[
        "Milstead"
    ],
    "name:nld_x_preferred":[
        "Milstead"
    ],
    "name:pol_x_preferred":[
        "Milstead"
    ],
    "name:spa_x_preferred":[
        "Milstead"
    ],
    "name:swe_x_preferred":[
        "Milstead"
    ],
    "name:und_x_variant":[
        "Cowles Station",
        "Cowles"
    ],
    "wof:name":"Milstead",
    "wof:placetype":"locality"
},
  "geometry": {"coordinates":[-85.89746,32.44264],"type":"Point"}
}