{
  "type": "Feature",
  "properties": {
    "gn:admin1_code":"PA",
    "gn:admin2_code":"1.0",
    "gn:admin3_code":"51640.0",
    "gn:asciiname":"Germantown",
    "gn:country_code":"US",
    "gn:dem":179,
    "gn:elevation":"177.0",
    "gn:feature_class":"P",
    "gn:feature_code":"PPL",
    "gn:name":"Germantown",
    "gn:population":0,
    "gn:timezone":"America/New_York",
    "iso:country":"US",
    "name:cat_x_preferred":[
        "Germantown"
    ],
    "name:ceb_x_preferred":[
        "Germantown"
    ],
    "name:deu_x_preferred":[
        "Germantown"
    ],
    "name:fra_x_preferred":[
        "Germantown"
    ],
    "name:ita_x_preferred":[
        "Germantown"
    ],
    "name:kor_x_preferred":[
        "\uc800\uba3c\ud0c0\uc6b4"
    ],
    "name:nld_x_preferred":[
        "Germantown"
    ],
    "name:nor_x_preferred":[
        "Germantown"
    ],
    "name:pol_x_preferred":[
        "Germantown"
    ],
    "name:por_x_preferred":[
        "Germantown"
    ],
    "name:slk_x_preferred":[
        "Germantown"
    ],
    "name:spa_x_preferred":[
        "Germantown"
    ],
    "name:srp_x_preferred":[
        "\u040f\u0435\u0440\u043c\u0430\u043d\u0442\u0430\u0443\u043d"
    ],
    "name:swe_x_preferred":[
        "Germantown"
    ],
    "name:ukr_x_preferred":[
        "\u0414\u0436\u0435\u0440\u043c\u0430\u043d\u0442\u0430\u0443\u043d"
    ],
    "name:vol_x_preferred":[
        "Germantown"
    ],
    "wof:name":"Germantown",
    "wof:placetype":"locality"
},
  "geometry": {"coordinates":[-77.14804000000002,39.76927],"type":"Point"}
}