{
  "type": "Feature",
  "properties": {
    "gn:admin1_code":"TX",
    "gn:admin2_code":"453",
    "gn:asciiname":"Elroy",
    "gn:country_code":"US",
    "gn:dem":185,
    "gn:elevation":"181.0",
    "gn:feature_class":"P",
    "gn:feature_code":"PPL",
    "gn:name":"Elroy",
    "gn:population":0,
    "gn:timezone":"America/Chicago",
    "iso:country":"US",
    "name:azb_x_preferred":[
        "\u0627\u0644\u0648\u0631\u06cc"
    ],
    "name:fas_x_preferred":[
        "\u0627\u0644\u0648\u0631\u06cc"
    ],
    "wof:name":"Elroy",
    "wof:placetype":"locality"
},
  "geometry": {"coordinates":[-97.63527999999999,30.12077],"type":"Point"}
}