{
  "type": "Feature",
  "properties": {
    "iso:country":"US",
    "name:eng_x_preferred":[
        "Northwood Forest"
    ],
    "name:eng_x_variant":[
        "Northwood Frst",
        "Northwoods"
    ],
    "name:zho_x_preferred":[
        "\u8bfa\u65af\u4f0d\u5179"
    ],
    "qs:gn_adm0_cc":"US",
    "qs:gn_fcode":"PPL",
    "qs:gn_local":4369596,
    "qs:gn_nam_loc":"Silver Spring, Montgomery, Maryland, US",
    "qs:gn_namadm1":"MD",
    "qs:gn_name":"Northwood Forest",
    "qs:local_max":5273,
    "qs:local_sum":19137,
    "qs:localhoods":40,
    "qs:name":"Northwood Forest",
    "qs:name_adm0":"United States",
    "qs:name_adm1":"Maryland",
    "qs:name_adm2":"Montgomery",
    "qs:name_local":"Silver Spring",
    "qs:photo_max":60,
    "qs:photo_sum":69,
    "qs:placetype":"Suburb",
    "qs:quad_count":2,
    "qs:woe_adm0":23424977,
    "qs:woe_adm1":2347579,
    "qs:woe_adm2":12588691,
    "qs:woe_lau":0,
    "qs:woe_local":2493761,
    "qs:woe_ver":"7.10.0",
    "wd:wordcount":641,
    "wof:lang":[
        "eng"
    ],
    "wof:name":"Northwood Forest",
    "wof:placetype":"neighbourhood",
    "wof:population":5866,
    "zs:blockids":[
        240317032084002,
        240317031001010,
        240317032083002,
        240317032083007,
        240317032084015,
        240317032084010,
        240317032084004,
        240317032084013,
        240317032101011,
        240317032102010,
        240317032102006,
        240317032081015,
        240317032082002,
        240317032084005,
        240317032084014,
        240317032102001,
        240317032101002,
        240317032102002,
        240317032083004,
        240317032083008,
        240317031001000,
        240317032102007,
        240317032083005,
        240317031001003,
        240317031001002,
        240317032101013,
        240317032102012,
        240317032102011,
        240317031004000,
        240317032082000,
        240317032082001,
        240317032084006,
        240317031001014,
        240317032084003,
        240317032084016,
        240317032083003,
        240317032101021,
        240317032102013,
        240317032102003,
        240317032102005,
        240317032101014,
        240317032084009,
        240317032084011,
        240317032102000,
        240317032101012,
        240317032101004,
        240317032102009,
        240317032081003,
        240317032084012,
        240317032083001,
        240317031001009,
        240317031001008,
        240317032101003,
        240317032102004,
        240317032082010,
        240317032082011,
        240317032084007,
        240317032101005,
        240317032101015,
        240317032101020
    ],
    "zs:housing10":1931,
    "zs:pop10":5866
},
  "geometry": {"coordinates":[-77.015894,39.039174],"type":"Point"}
}