{
  "type": "Feature",
  "properties": {
    "gn:admin1_code":"AL",
    "gn:admin2_code":"61.0",
    "gn:asciiname":"Scranton",
    "gn:country_code":"US",
    "gn:dem":86,
    "gn:elevation":"82.0",
    "gn:feature_class":"P",
    "gn:feature_code":"PPL",
    "gn:name":"Scranton",
    "gn:population":0,
    "gn:timezone":"America/Chicago",
    "iso:country":"US",
    "wof:name":"Scranton",
    "wof:placetype":"locality"
},
  "geometry": {"coordinates":[-85.84188,31.19295],"type":"Point"}
}