{
  "type": "Feature",
  "properties": {
    "gn:admin1_code":"PA",
    "gn:admin2_code":"91.0",
    "gn:admin3_code":"44976.0",
    "gn:asciiname":"West Spring Mills",
    "gn:country_code":"US",
    "gn:dem":99,
    "gn:elevation":"92.0",
    "gn:feature_class":"P",
    "gn:feature_code":"PPL",
    "gn:name":"West Spring Mills",
    "gn:population":0,
    "gn:timezone":"America/New_York",
    "iso:country":"US",
    "wof:name":"West Spring Mills",
    "wof:placetype":"locality"
},
  "geometry": {"coordinates":[-75.28463000000001,40.06844],"type":"Point"}
}