{
  "type": "Feature",
  "properties": {
    "gn:admin1_code":"VA",
    "gn:admin2_code":"169",
    "gn:asciiname":"Bush Mill",
    "gn:country_code":"US",
    "gn:dem":560,
    "gn:elevation":"546.0",
    "gn:feature_class":"P",
    "gn:feature_code":"PPL",
    "gn:name":"Bush Mill",
    "gn:population":0,
    "gn:timezone":"America/New_York",
    "iso:country":"US",
    "name:eng_x_preferred":[
        "Bush Mill"
    ],
    "name:und_x_variant":[
        "Bonds Mill"
    ],
    "wof:name":"Bush Mill",
    "wof:placetype":"locality"
},
  "geometry": {"coordinates":[-82.43543000000003,36.75566],"type":"Point"}
}