{
  "type": "Feature",
  "properties": {
    "gn:admin1_code":"IL",
    "gn:admin2_code":"191",
    "gn:admin3_code":"34501.0",
    "gn:asciiname":"Keenesville",
    "gn:country_code":"US",
    "gn:dem":139,
    "gn:elevation":"141.0",
    "gn:feature_class":"P",
    "gn:feature_code":"PPL",
    "gn:name":"Keenesville",
    "gn:population":0,
    "gn:timezone":"America/Chicago",
    "iso:country":"US",
    "name:eng_x_preferred":[
        "Keenesville"
    ],
    "name:und_x_variant":[
        "Keenville"
    ],
    "wof:name":"Keenesville",
    "wof:placetype":"locality"
},
  "geometry": {"coordinates":[-88.64811,38.40227],"type":"Point"}
}