{
  "type": "Feature",
  "properties": {
    "gn:admin1_code":"MS",
    "gn:admin2_code":"29.0",
    "gn:asciiname":"Conn",
    "gn:country_code":"US",
    "gn:dem":95,
    "gn:elevation":"89.0",
    "gn:feature_class":"P",
    "gn:feature_code":"PPL",
    "gn:name":"Conn",
    "gn:population":0,
    "gn:timezone":"America/Chicago",
    "iso:country":"US",
    "wof:name":"Conn",
    "wof:placetype":"locality"
},
  "geometry": {"coordinates":[-90.7101,31.89794],"type":"Point"}
}