{
  "type": "Feature",
  "properties": {
    "gn:country":"US",
    "gn:fcode":"PPL",
    "gn:population":0,
    "iso:country":"US",
    "name:azb_x_preferred":[
        "\u0642\u0644\u0646\u200c\u062f\u06cc\u0644"
    ],
    "name:eng_x_preferred":[
        "Glendale"
    ],
    "name:fas_x_preferred":[
        "\u06af\u0644\u0646\u200c\u062f\u06cc\u0644"
    ],
    "name:fra_x_preferred":[
        "Glendale"
    ],
    "name:hat_x_preferred":[
        "Glendale"
    ],
    "name:ita_x_preferred":[
        "Glendale"
    ],
    "name:nld_x_preferred":[
        "Glendale"
    ],
    "name:por_x_preferred":[
        "Glendale"
    ],
    "name:spa_x_preferred":[
        "Glendale"
    ],
    "qs_pg:aaroncc":"US",
    "qs_pg:gn_country":"US",
    "qs_pg:gn_fcode":"PPL",
    "qs_pg:gn_pop":0,
    "qs_pg:name":"Glendale",
    "qs_pg:name_adm0":"United States",
    "qs_pg:name_adm1":"Nevada",
    "qs_pg:photos":78,
    "qs_pg:photos_1k":16,
    "qs_pg:photos_9k":1,
    "qs_pg:photos_9r":3,
    "qs_pg:photos_all":78,
    "qs_pg:photos_sr":3,
    "qs_pg:pop_sr":5,
    "qs_pg:qs_pg_placetype":"locality",
    "qs_pg:qs_pg_placetype_gp":"Town",
    "qs_pg:woe_adm0":23424977,
    "woe:adm0_id":23424977,
    "woe:name_adm0":"United States",
    "woe:name_adm1":"Nevada",
    "woe:placetype":"Town",
    "wof:name":"Glendale",
    "wof:placetype":"locality"
},
  "geometry": {"coordinates":[-114.56914999999999,36.66525],"type":"Point"}
}