{
  "type": "Feature",
  "properties": {
    "gn:admin1_code":"PA",
    "gn:admin2_code":"45",
    "gn:admin3_code":"22584.0",
    "gn:asciiname":"Springton Woods",
    "gn:country_code":"US",
    "gn:dem":132,
    "gn:elevation":"127.0",
    "gn:feature_class":"P",
    "gn:feature_code":"PPL",
    "gn:name":"Springton Woods",
    "gn:population":0,
    "gn:timezone":"America/New_York",
    "iso:country":"US",
    "wof:name":"Springton Woods",
    "wof:placetype":"locality"
},
  "geometry": {"coordinates":[-75.4359,39.965],"type":"Point"}
}