{
  "type": "Feature",
  "properties": {
    "gn:admin1_code":"WI",
    "gn:admin2_code":"95.0",
    "gn:admin3_code":"15125.0",
    "gn:asciiname":"Richardson",
    "gn:country_code":"US",
    "gn:dem":358,
    "gn:elevation":"366.0",
    "gn:feature_class":"P",
    "gn:feature_code":"PPL",
    "gn:name":"Richardson",
    "gn:population":0,
    "gn:timezone":"America/Chicago",
    "iso:country":"US",
    "name:fas_x_preferred":[
        "\u0631\u06cc\u0686\u0627\u0631\u062f\u0633\u0648\u0646"
    ],
    "name:urd_x_preferred":[
        "\u0631\u0686\u0631\u0688\u0633\u0646"
    ],
    "wof:name":"Richardson",
    "wof:placetype":"locality"
},
  "geometry": {"coordinates":[-92.19991,45.31913],"type":"Point"}
}