{
  "type": "Feature",
  "properties": {
    "gn:admin1_code":"AL",
    "gn:admin2_code":"111",
    "gn:asciiname":"Omaha",
    "gn:country_code":"US",
    "gn:dem":397,
    "gn:elevation":"398.0",
    "gn:feature_class":"P",
    "gn:feature_code":"PPL",
    "gn:name":"Omaha",
    "gn:population":0,
    "gn:timezone":"America/Chicago",
    "iso:country":"US",
    "wof:name":"Omaha",
    "wof:placetype":"locality"
},
  "geometry": {"coordinates":[-85.31023,33.30262],"type":"Point"}
}