{
  "type": "Feature",
  "properties": {
    "gn:admin1_code":"AR",
    "gn:admin2_code":"21.0",
    "gn:admin3_code":"93971.0",
    "gn:asciiname":"Heubner",
    "gn:country_code":"US",
    "gn:dem":76,
    "gn:elevation":"79.0",
    "gn:feature_class":"P",
    "gn:feature_code":"PPL",
    "gn:name":"Heubner",
    "gn:population":0,
    "gn:timezone":"America/Chicago",
    "iso:country":"US",
    "wof:name":"Heubner",
    "wof:placetype":"locality"
},
  "geometry": {"coordinates":[-90.31205,36.21701],"type":"Point"}
}