{
  "type": "Feature",
  "properties": {
    "gn:admin1_code":"AL",
    "gn:admin2_code":"83",
    "gn:asciiname":"Lentzville",
    "gn:country_code":"US",
    "gn:dem":220,
    "gn:elevation":"219.0",
    "gn:feature_class":"P",
    "gn:feature_code":"PPL",
    "gn:name":"Lentzville",
    "gn:population":0,
    "gn:timezone":"America/Chicago",
    "iso:country":"US",
    "wof:name":"Lentzville",
    "wof:placetype":"locality"
},
  "geometry": {"coordinates":[-87.14085,34.84425],"type":"Point"}
}