{
  "type": "Feature",
  "properties": {
    "gn:admin1_code":"KY",
    "gn:admin2_code":"57",
    "gn:asciiname":"Judio",
    "gn:country_code":"US",
    "gn:dem":165,
    "gn:elevation":"166.0",
    "gn:feature_class":"P",
    "gn:feature_code":"PPL",
    "gn:name":"Judio",
    "gn:population":0,
    "gn:timezone":"America/Chicago",
    "iso:country":"US",
    "wof:name":"Judio",
    "wof:placetype":"locality"
},
  "geometry": {"coordinates":[-85.4808,36.69589000000001],"type":"Point"}
}