{
  "type": "Feature",
  "properties": {
    "gn:admin1_code":"NY",
    "gn:admin2_code":"29.0",
    "gn:admin3_code":"17200.0",
    "gn:asciiname":"Collins Center",
    "gn:country_code":"US",
    "gn:dem":340,
    "gn:elevation":"336.0",
    "gn:feature_class":"P",
    "gn:feature_code":"PPL",
    "gn:name":"Collins Center",
    "gn:population":0,
    "gn:timezone":"America/New_York",
    "iso:country":"US",
    "name:eng_x_preferred":[
        "Collins Center"
    ],
    "name:und_x_variant":[
        "Collins Centre"
    ],
    "wof:name":"Collins Center",
    "wof:placetype":"locality"
},
  "geometry": {"coordinates":[-78.85141999999998,42.49367],"type":"Point"}
}