{
  "type": "Feature",
  "properties": {
    "gn:country":"US",
    "gn:fcode":"PPL",
    "gn:population":0,
    "iso:country":"US",
    "name:afr_x_preferred":[
        "Mana"
    ],
    "name:ara_x_preferred":[
        "\u0645\u0627\u0646\u0627"
    ],
    "name:ben_x_preferred":[
        "\u09ae\u09be\u09a8\u09be"
    ],
    "name:cat_x_preferred":[
        "Mana"
    ],
    "name:ces_x_preferred":[
        "Mana"
    ],
    "name:dan_x_preferred":[
        "Mana"
    ],
    "name:deu_x_preferred":[
        "Mana"
    ],
    "name:ell_x_preferred":[
        "\u039c\u03ac\u03bd\u03b1"
    ],
    "name:eng_x_preferred":[
        "M\u0101n\u0101"
    ],
    "name:fas_x_preferred":[
        "\u0645\u0627\u0646\u0627"
    ],
    "name:fin_x_preferred":[
        "Mana"
    ],
    "name:fra_x_preferred":[
        "Mana"
    ],
    "name:heb_x_preferred":[
        "\u05de\u05e0\u05e4\u05d5\u05d5\u05d4"
    ],
    "name:hin_x_preferred":[
        "\u092e\u093e\u0928\u093e"
    ],
    "name:hun_x_preferred":[
        "Mana"
    ],
    "name:ind_x_preferred":[
        "Mana"
    ],
    "name:ita_x_preferred":[
        "Mana"
    ],
    "name:kor_x_preferred":[
        "\ub9c8\ub098"
    ],
    "name:lat_x_preferred":[
        "Mana"
    ],
    "name:lit_x_preferred":[
        "Magin\u0117 energija"
    ],
    "name:mkd_x_preferred":[
        "\u041c\u0430\u043d\u0430"
    ],
    "name:nld_x_preferred":[
        "Mana"
    ],
    "name:pol_x_preferred":[
        "Mana"
    ],
    "name:por_x_preferred":[
        "Mana"
    ],
    "name:rus_x_preferred":[
        "\u041c\u0430\u043d\u0430"
    ],
    "name:slk_x_preferred":[
        "Mana"
    ],
    "name:spa_x_preferred":[
        "Mana"
    ],
    "name:swe_x_preferred":[
        "Mana"
    ],
    "name:tur_x_preferred":[
        "Mana"
    ],
    "name:ukr_x_preferred":[
        "\u041c\u0430\u043d\u0430"
    ],
    "name:urd_x_preferred":[
        "\u0645\u0627\u0646\u0627"
    ],
    "name:vie_x_preferred":[
        "S\u00f4ng Mana"
    ],
    "qs_pg:aaroncc":"US",
    "qs_pg:gn_country":"US",
    "qs_pg:gn_fcode":"PPL",
    "qs_pg:gn_pop":0,
    "qs_pg:name":"Mana",
    "qs_pg:name_adm0":"United States",
    "qs_pg:name_adm1":"Hawaii",
    "qs_pg:photos":78,
    "qs_pg:photos_1k":16,
    "qs_pg:photos_9k":1,
    "qs_pg:photos_9r":3,
    "qs_pg:photos_all":78,
    "qs_pg:photos_sr":3,
    "qs_pg:pop_sr":0,
    "qs_pg:qs_pg_placetype":"locality",
    "qs_pg:qs_pg_placetype_gp":"Town",
    "qs_pg:woe_adm0":23424977,
    "woe:adm0_id":23424977,
    "woe:name_adm0":"United States",
    "woe:name_adm1":"Hawaii",
    "woe:placetype":"Town",
    "wof:name":"Mana",
    "wof:placetype":"locality"
},
  "geometry": {"coordinates":[-155.56028000000001,20.00056],"type":"Point"}
}