{
  "type": "Feature",
  "properties": {
    "gn:admin1_code":"VA",
    "gn:admin2_code":"650.0",
    "gn:asciiname":"Langley Mobile Home Park",
    "gn:country_code":"US",
    "gn:dem":4,
    "gn:elevation":"3.0",
    "gn:feature_class":"P",
    "gn:feature_code":"PPL",
    "gn:name":"Langley Mobile Home Park",
    "gn:population":0,
    "gn:timezone":"America/New_York",
    "iso:country":"US",
    "wof:name":"Langley Mobile Home Park",
    "wof:placetype":"campus"
},
  "geometry": {"coordinates":[-76.38417,37.08472],"type":"Point"}
}