{
  "type": "Feature",
  "properties": {
    "iso:country":"US",
    "name:eng_x_preferred":[
        "Wooden Shoe"
    ],
    "wof:name":"Wooden Shoe",
    "wof:placetype":"neighbourhood",
    "wof:population":605,
    "zs:area_m":494804.523115,
    "zs:blockids":[
        80010093231009,
        80010085063002,
        80010602001010,
        80010093231014,
        80010085063004,
        80010085063005,
        80010085063003,
        80010093231006,
        80010093231012,
        80010093231005,
        80010093231010,
        80010093231000,
        80010093231007,
        80010093231017,
        80010093231016
    ],
    "zs:housing10":195,
    "zs:label":"Wooden Shoe",
    "zs:pop10":605
},
  "geometry": {"coordinates":[-104.99293900000001,39.909263],"type":"Point"}
}