{
  "type": "Feature",
  "properties": {
    "gn:admin1_code":"FL",
    "gn:admin2_code":"117.0",
    "gn:asciiname":"Roseland Park",
    "gn:country_code":"US",
    "gn:dem":10,
    "gn:elevation":"8.0",
    "gn:feature_class":"P",
    "gn:feature_code":"PPL",
    "gn:name":"Roseland Park",
    "gn:population":0,
    "gn:timezone":"America/New_York",
    "iso:country":"US",
    "wof:name":"Roseland Park",
    "wof:placetype":"locality"
},
  "geometry": {"coordinates":[-81.24645,28.79638],"type":"Point"}
}