{
  "type": "Feature",
  "properties": {
    "iso:country":"US",
    "name:eng_x_preferred":[
        "Pinkney City"
    ],
    "wof:name":"Pinkney City",
    "wof:placetype":"neighbourhood",
    "wof:population":757,
    "zs:area_m":19307145.543295,
    "zs:blockids":[
        10730121032096,
        10730116003035,
        10730121032054,
        10730116001075,
        10730116003033,
        10730116001046,
        10730116003066,
        10730116003048,
        10730121032004,
        10730116001038,
        10730116003045,
        10730116001049,
        10730116003057,
        10730116003042,
        10730116003100,
        10730121032003,
        10730116003000,
        10730116001048,
        10730116003002,
        10730116003051,
        10730116001077,
        10730116001084,
        10730116003032,
        10730116003029,
        10730121032097,
        10730116003020,
        10730116003031,
        10730121032006,
        10730116003063,
        10730121032055,
        10730116003067,
        10730121032053,
        10730121032056,
        10730116003005,
        10730116003022,
        10730116003086,
        10730116001076,
        10730116001079,
        10730116003040,
        10730121032005,
        10730116003024,
        10730116003089,
        10730116003003,
        10730121032002,
        10730116003068,
        10730116003061,
        10730116003065,
        10730116003056,
        10730116003064,
        10730116001000,
        10730116001036,
        10730116003037,
        10730116003044,
        10730116001074,
        10730116001073,
        10730116003036,
        10730116003004,
        10730121032008,
        10730116003023,
        10730121032007,
        10730116003034,
        10730116001040,
        10730116001039,
        10730116003101,
        10730116003084,
        10730116001001,
        10730121032009,
        10730121032001,
        10730116003006,
        10730116003027,
        10730116003047,
        10730116003038,
        10730116003060,
        10730116003001,
        10730121033045,
        10730116001078,
        10730116001037,
        10730116001072,
        10730116003041,
        10730116003088,
        10730121032000,
        10730121032017,
        10730116003046,
        10730116003062,
        10730116003085,
        10730116003087,
        10730116003026
    ],
    "zs:housing10":333,
    "zs:label":"Pinkney City",
    "zs:pop10":757
},
  "geometry": {"coordinates":[-86.913872,33.64838],"type":"Point"}
}