{
  "type": "Feature",
  "properties": {
    "gn:country":"US",
    "gn:fcode":"PPL",
    "gn:population":0,
    "iso:country":"US",
    "name:azb_x_preferred":[
        "\u0627\u06cc\u0631\u0648\u0646\u0634\u06cc\u0631"
    ],
    "name:eng_x_preferred":[
        "Ironshire"
    ],
    "name:fas_x_preferred":[
        "\u0622\u06cc\u0631\u0648\u0646\u0634\u0627\u06cc\u0631"
    ],
    "name:fra_x_preferred":[
        "Ironshire"
    ],
    "name:und_x_variant":[
        "Derricksons"
    ],
    "qs_pg:aaroncc":"US",
    "qs_pg:gn_country":"US",
    "qs_pg:gn_fcode":"PPL",
    "qs_pg:gn_pop":0,
    "qs_pg:name":"Ironshire",
    "qs_pg:name_adm0":"United States",
    "qs_pg:name_adm1":"Maryland",
    "qs_pg:photos":9,
    "qs_pg:photos_1k":2,
    "qs_pg:photos_9k":1,
    "qs_pg:photos_9r":1,
    "qs_pg:photos_all":9,
    "qs_pg:photos_sr":1,
    "qs_pg:pop_sr":0,
    "qs_pg:qs_pg_placetype":"locality",
    "qs_pg:qs_pg_placetype_gp":"Town",
    "qs_pg:woe_adm0":23424977,
    "woe:adm0_id":23424977,
    "woe:name_adm0":"United States",
    "woe:name_adm1":"Maryland",
    "woe:placetype":"Town",
    "wof:name":"Ironshire",
    "wof:placetype":"locality"
},
  "geometry": {"coordinates":[-75.23102,38.284],"type":"Point"}
}