{
  "type": "Feature",
  "properties": {
    "gn:admin1_code":"ND",
    "gn:admin2_code":"97.0",
    "gn:admin3_code":"22820.0",
    "gn:asciiname":"Taft",
    "gn:country_code":"US",
    "gn:dem":276,
    "gn:elevation":"276.0",
    "gn:feature_class":"P",
    "gn:feature_code":"PPL",
    "gn:name":"Taft",
    "gn:population":0,
    "gn:timezone":"America/Chicago",
    "iso:country":"US",
    "name:bel_x_preferred":[
        "\u0422\u0430\u0444\u0442"
    ],
    "name:ceb_x_preferred":[
        "Taft"
    ],
    "name:ces_x_preferred":[
        "Taft"
    ],
    "name:deu_x_preferred":[
        "Taft"
    ],
    "name:fas_x_preferred":[
        "\u062a\u0641\u062a"
    ],
    "name:fra_x_preferred":[
        "Taft"
    ],
    "name:heb_x_preferred":[
        "\u05d8\u05d0\u05e4\u05d8"
    ],
    "name:ita_x_preferred":[
        "Taft"
    ],
    "name:jpn_x_preferred":[
        "\u30bf\u30d5\u30c8"
    ],
    "name:kor_x_preferred":[
        "\ud0dc\ud504\ud2b8"
    ],
    "name:nld_x_preferred":[
        "Taft"
    ],
    "name:pol_x_preferred":[
        "Taft"
    ],
    "name:por_x_preferred":[
        "Taft"
    ],
    "name:rus_x_preferred":[
        "\u0422\u0430\u0444\u0442"
    ],
    "name:spa_x_preferred":[
        "Taft"
    ],
    "name:srp_x_preferred":[
        "\u0422\u0430\u0444\u0442"
    ],
    "name:swe_x_preferred":[
        "Taft"
    ],
    "name:tgl_x_preferred":[
        "Taft"
    ],
    "name:ukr_x_preferred":[
        "\u0422\u0430\u0444\u0442"
    ],
    "name:vol_x_preferred":[
        "Taft"
    ],
    "wof:name":"Taft",
    "wof:placetype":"locality"
},
  "geometry": {"coordinates":[-97.07008999999999,47.45637],"type":"Point"}
}