{
  "type": "Feature",
  "properties": {
    "gn:admin1_code":"IL",
    "gn:admin2_code":"83.0",
    "gn:admin3_code":"63745.0",
    "gn:asciiname":"Spankey",
    "gn:country_code":"US",
    "gn:dem":131,
    "gn:elevation":"133.0",
    "gn:feature_class":"P",
    "gn:feature_code":"PPL",
    "gn:name":"Spankey",
    "gn:population":0,
    "gn:timezone":"America/Chicago",
    "iso:country":"US",
    "name:eng_x_preferred":[
        "Spankey"
    ],
    "name:und_x_variant":[
        "Clendenin"
    ],
    "wof:name":"Spankey",
    "wof:placetype":"locality"
},
  "geometry": {"coordinates":[-90.55068,39.18894],"type":"Point"}
}