{
  "type": "Feature",
  "properties": {
    "gn:admin1_code":"MN",
    "gn:admin2_code":"147.0",
    "gn:admin3_code":"6598.0",
    "gn:asciiname":"Union",
    "gn:country_code":"US",
    "gn:dem":377,
    "gn:elevation":"380.0",
    "gn:feature_class":"P",
    "gn:feature_code":"PPL",
    "gn:name":"Union",
    "gn:population":0,
    "gn:timezone":"America/Chicago",
    "iso:country":"US",
    "name:ara_x_preferred":[
        "\u0627\u062a\u062d\u0627\u062f"
    ],
    "name:bre_x_preferred":[
        "Union"
    ],
    "name:bul_x_preferred":[
        "\u042e\u043d\u0438\u044a\u043d"
    ],
    "name:cat_x_preferred":[
        "Union"
    ],
    "name:ceb_x_preferred":[
        "Union"
    ],
    "name:ces_x_preferred":[
        "Union"
    ],
    "name:deu_x_preferred":[
        "Union"
    ],
    "name:est_x_preferred":[
        "Union"
    ],
    "name:fas_x_preferred":[
        "\u0627\u062a\u062d\u0627\u062f"
    ],
    "name:fin_x_preferred":[
        "Union"
    ],
    "name:fra_x_preferred":[
        "Union"
    ],
    "name:heb_x_preferred":[
        "\u05d0\u05d9\u05d7\u05d5\u05d3"
    ],
    "name:hun_x_preferred":[
        "Union"
    ],
    "name:ind_x_preferred":[
        "Union"
    ],
    "name:ita_x_preferred":[
        "Union"
    ],
    "name:jpn_x_preferred":[
        "\u30e6\u30cb\u30aa\u30f3"
    ],
    "name:kaz_x_preferred":[
        "\u0411\u0456\u0440\u043b\u0435\u0441\u0442\u0456\u043a"
    ],
    "name:kor_x_preferred":[
        "\uc720\ub2c8\uc5b8"
    ],
    "name:lav_x_preferred":[
        "Savien\u012bba"
    ],
    "name:nld_x_preferred":[
        "Union"
    ],
    "name:nno_x_preferred":[
        "Union"
    ],
    "name:nor_x_preferred":[
        "Union"
    ],
    "name:pol_x_preferred":[
        "Union"
    ],
    "name:por_x_preferred":[
        "Union"
    ],
    "name:rus_x_preferred":[
        "Union"
    ],
    "name:sco_x_preferred":[
        "Union"
    ],
    "name:slk_x_preferred":[
        "Union"
    ],
    "name:srp_x_preferred":[
        "\u0423\u043d\u0438\u0458\u0430"
    ],
    "name:swe_x_preferred":[
        "Union"
    ],
    "name:tur_x_preferred":[
        "Union"
    ],
    "name:ukr_x_preferred":[
        "Union"
    ],
    "name:urd_x_preferred":[
        "\u06cc\u0648\u0646\u06cc\u0646"
    ],
    "name:vol_x_preferred":[
        "Union"
    ],
    "wof:name":"Union",
    "wof:placetype":"locality"
},
  "geometry": {"coordinates":[-93.12548,43.89191],"type":"Point"}
}