{
  "type": "Feature",
  "properties": {
    "gn:country":"US",
    "gn:fcode":"PPL",
    "gn:population":0,
    "iso:country":"US",
    "name:ceb_x_preferred":[
        "Kato"
    ],
    "name:deu_x_preferred":[
        "Kat\u014d"
    ],
    "name:epo_x_preferred":[
        "Kato"
    ],
    "name:fas_x_preferred":[
        "\u06a9\u0627\u062a\u0648"
    ],
    "name:fin_x_preferred":[
        "Kato"
    ],
    "name:fra_x_preferred":[
        "Kato"
    ],
    "name:fry_x_preferred":[
        "Kato"
    ],
    "name:ita_x_preferred":[
        "Kato"
    ],
    "name:nld_x_preferred":[
        "Kato"
    ],
    "name:pol_x_preferred":[
        "Kato"
    ],
    "name:por_x_preferred":[
        "Kato"
    ],
    "name:ron_x_preferred":[
        "Kato"
    ],
    "name:rus_x_preferred":[
        "\u041a\u0430\u0442\u043e"
    ],
    "name:spa_x_preferred":[
        "Kato"
    ],
    "name:swe_x_preferred":[
        "Kato"
    ],
    "name:ukr_x_preferred":[
        "\u041a\u0430\u0442\u043e"
    ],
    "qs_pg:aaroncc":"US",
    "qs_pg:gn_country":"US",
    "qs_pg:gn_fcode":"PPL",
    "qs_pg:gn_pop":0,
    "qs_pg:name":"Kato",
    "qs_pg:name_adm0":"United States",
    "qs_pg:name_adm1":"Pennsylvania",
    "qs_pg:photos_9r":0,
    "qs_pg:photos_sr":0,
    "qs_pg:pop_sr":0,
    "qs_pg:qs_pg_placetype":"neighbourhood",
    "qs_pg:qs_pg_placetype_gp":"Suburb",
    "qs_pg:woe_adm0":23424977,
    "woe:adm0_id":23424977,
    "woe:name_adm0":"United States",
    "woe:name_adm1":"Pennsylvania",
    "woe:placetype":"Suburb",
    "wof:name":"Kato",
    "wof:placetype":"neighbourhood"
},
  "geometry": {"coordinates":[-77.86611000000001,41.08478],"type":"Point"}
}