{
  "type": "Feature",
  "properties": {
    "gn:admin1_code":"VA",
    "gn:admin2_code":"29",
    "gn:asciiname":"Slate Hill",
    "gn:country_code":"US",
    "gn:dem":116,
    "gn:elevation":"116.0",
    "gn:feature_class":"P",
    "gn:feature_code":"PPL",
    "gn:name":"Slate Hill",
    "gn:population":0,
    "gn:timezone":"America/New_York",
    "iso:country":"US",
    "wof:name":"Slate Hill",
    "wof:placetype":"locality"
},
  "geometry": {"coordinates":[-78.38695,37.63209000000001],"type":"Point"}
}