{
  "type": "Feature",
  "properties": {
    "gn:admin1_code":"IA",
    "gn:admin2_code":"175.0",
    "gn:admin3_code":"92280.0",
    "gn:asciiname":"Talmage",
    "gn:country_code":"US",
    "gn:dem":331,
    "gn:elevation":"328.0",
    "gn:feature_class":"P",
    "gn:feature_code":"PPL",
    "gn:name":"Talmage",
    "gn:population":0,
    "gn:timezone":"America/Chicago",
    "iso:country":"US",
    "name:ceb_x_preferred":[
        "Talmage"
    ],
    "name:deu_x_preferred":[
        "Talmage"
    ],
    "name:fra_x_preferred":[
        "Talmage"
    ],
    "name:ita_x_preferred":[
        "Talmage"
    ],
    "name:nds_x_preferred":[
        "Talmage"
    ],
    "name:nld_x_preferred":[
        "Talmage"
    ],
    "name:pol_x_preferred":[
        "Talmage"
    ],
    "name:por_x_preferred":[
        "Talmage"
    ],
    "name:srp_x_preferred":[
        "\u0422\u0430\u043b\u043c\u0438\u045f"
    ],
    "name:vol_x_preferred":[
        "Talmage"
    ],
    "wof:name":"Talmage",
    "wof:placetype":"locality"
},
  "geometry": {"coordinates":[-94.11190000000001,41.02694],"type":"Point"}
}