{
  "type": "Feature",
  "properties": {
    "gn:admin1_code":"MI",
    "gn:admin2_code":"75.0",
    "gn:admin3_code":"8760.0",
    "gn:asciiname":"Coffman Trailer Court",
    "gn:country_code":"US",
    "gn:dem":304,
    "gn:elevation":"305.0",
    "gn:feature_class":"P",
    "gn:feature_code":"PPL",
    "gn:name":"Coffman Trailer Court",
    "gn:population":0,
    "gn:timezone":"America/Detroit",
    "iso:country":"US",
    "wof:name":"Coffman Trailer Court",
    "wof:placetype":"locality"
},
  "geometry": {"coordinates":[-84.46611,42.25417],"type":"Point"}
}