{
  "type": "Feature",
  "properties": {
    "gn:admin1_code":"OH",
    "gn:admin2_code":"153.0",
    "gn:asciiname":"Kings Ridge",
    "gn:country_code":"US",
    "gn:dem":341,
    "gn:elevation":"333.0",
    "gn:feature_class":"P",
    "gn:feature_code":"PPL",
    "gn:name":"Kings Ridge",
    "gn:population":0,
    "gn:timezone":"America/New_York",
    "iso:country":"US",
    "wof:name":"Kings Ridge",
    "wof:placetype":"locality"
},
  "geometry": {"coordinates":[-81.5082,40.95604],"type":"Point"}
}