{
  "type": "Feature",
  "properties": {
    "gn:admin1_code":"NY",
    "gn:admin2_code":"19.0",
    "gn:admin3_code":"6761.0",
    "gn:asciiname":"West Kilns",
    "gn:country_code":"US",
    "gn:dem":511,
    "gn:elevation":"518.0",
    "gn:feature_class":"P",
    "gn:feature_code":"PPL",
    "gn:name":"West Kilns",
    "gn:population":0,
    "gn:timezone":"America/New_York",
    "iso:country":"US",
    "wof:name":"West Kilns",
    "wof:placetype":"locality"
},
  "geometry": {"coordinates":[-73.90098,44.43866],"type":"Point"}
}