{
  "type": "Feature",
  "properties": {
    "gn:admin1_code":"SC",
    "gn:admin2_code":"63.0",
    "gn:asciiname":"Gardendale",
    "gn:country_code":"US",
    "gn:dem":59,
    "gn:elevation":"57.0",
    "gn:feature_class":"P",
    "gn:feature_code":"PPL",
    "gn:name":"Gardendale",
    "gn:population":0,
    "gn:timezone":"America/New_York",
    "iso:country":"US",
    "name:ceb_x_preferred":[
        "Gardendale"
    ],
    "name:deu_x_preferred":[
        "Gardendale"
    ],
    "name:fra_x_preferred":[
        "Gardendale"
    ],
    "name:ita_x_preferred":[
        "Gardendale"
    ],
    "name:nld_x_preferred":[
        "Gardendale"
    ],
    "name:por_x_preferred":[
        "Gardendale"
    ],
    "name:srp_x_preferred":[
        "\u0413\u0430\u0440\u0434\u0435\u043d\u0434\u0435\u0458\u043b"
    ],
    "name:vol_x_preferred":[
        "Gardendale"
    ],
    "wof:name":"Gardendale",
    "wof:placetype":"locality"
},
  "geometry": {"coordinates":[-81.13898,34.03765],"type":"Point"}
}