{
  "type": "Feature",
  "properties": {
    "gn:admin1_code":"IL",
    "gn:admin2_code":"167",
    "gn:admin3_code":"37140.0",
    "gn:asciiname":"Haynes",
    "gn:country_code":"US",
    "gn:dem":181,
    "gn:elevation":"185.0",
    "gn:feature_class":"P",
    "gn:feature_code":"PPL",
    "gn:name":"Haynes",
    "gn:population":0,
    "gn:timezone":"America/Chicago",
    "iso:country":"US",
    "name:cat_x_preferred":[
        "Haynes"
    ],
    "name:ceb_x_preferred":[
        "Haynes"
    ],
    "name:ces_x_preferred":[
        "Haynes"
    ],
    "name:deu_x_preferred":[
        "Haynes"
    ],
    "name:fra_x_preferred":[
        "Haynes"
    ],
    "name:heb_x_preferred":[
        "\u05d4\u05d9\u05d9\u05e0\u05e1"
    ],
    "name:ita_x_preferred":[
        "Haynes"
    ],
    "name:nds_x_preferred":[
        "Haynes"
    ],
    "name:nld_x_preferred":[
        "Haynes"
    ],
    "name:pol_x_preferred":[
        "Haynes"
    ],
    "name:srp_x_preferred":[
        "\u0425\u0435\u0458\u043d\u0441"
    ],
    "name:swe_x_preferred":[
        "Haynes"
    ],
    "wof:name":"Haynes",
    "wof:placetype":"locality"
},
  "geometry": {"coordinates":[-89.29648,39.84949],"type":"Point"}
}