{
  "type": "Feature",
  "properties": {
    "gn:gn_country":"US",
    "gn:gn_fcode":"PPL",
    "gn:gn_pop":0,
    "iso:country":"US",
    "name:eng_x_preferred":[
        "Waldo Junction"
    ],
    "name:fra_x_preferred":[
        "Waldo Junction"
    ],
    "name:unk_x_variant":[
        "Cabbage Patch"
    ],
    "qs_pg:aaroncc":"US",
    "qs_pg:gn_country":"US",
    "qs_pg:gn_fcode":"PPL",
    "qs_pg:gn_pop":0,
    "qs_pg:name":"Waldo Junction",
    "qs_pg:name_adm0":"United States",
    "qs_pg:name_adm1":"California",
    "qs_pg:photos":302,
    "qs_pg:photos_1k":61,
    "qs_pg:photos_9k":1,
    "qs_pg:photos_9r":5,
    "qs_pg:photos_all":302,
    "qs_pg:photos_sr":5,
    "qs_pg:pop_sr":0,
    "qs_pg:qs_pg_placetype":"locality",
    "qs_pg:qs_pg_placetype_gp":"Town",
    "qs_pg:woe_adm0":23424977,
    "woe:adm0_id":23424977,
    "woe:name_adm0":"United States",
    "woe:name_adm1":"California",
    "woe:placetype":"Town",
    "wof:name":"Waldo Junction",
    "wof:placetype":"locality"
},
  "geometry": {"coordinates":[-121.30911999999999,39.11101],"type":"Point"}
}