{
  "type": "Feature",
  "properties": {
    "gn:admin1_code":"KY",
    "gn:admin2_code":"41",
    "gn:asciiname":"Locust",
    "gn:country_code":"US",
    "gn:dem":145,
    "gn:elevation":"142.0",
    "gn:feature_class":"P",
    "gn:feature_code":"PPL",
    "gn:name":"Locust",
    "gn:population":0,
    "gn:timezone":"America/New_York",
    "iso:country":"US",
    "name:eng_x_preferred":[
        "Locust"
    ],
    "name:und_x_variant":[
        "Locust School"
    ],
    "wof:name":"Locust",
    "wof:placetype":"locality"
},
  "geometry": {"coordinates":[-85.26079,38.70312],"type":"Point"}
}