{
  "type": "Feature",
  "properties": {
    "iso:country":"US",
    "name:eng_x_preferred":[
        "Ancient Oaks"
    ],
    "wof:name":"Ancient Oaks",
    "wof:placetype":"neighbourhood",
    "wof:population":301,
    "zs:area_m":1124462.524449,
    "zs:blockids":[
        120810019082008,
        120810019082007,
        120810019111088,
        120810019082009,
        120810019082011,
        120810019082010
    ],
    "zs:housing10":129,
    "zs:label":"Ancient Oaks",
    "zs:pop10":301
},
  "geometry": {"coordinates":[-82.47454999999999,27.559503],"type":"Point"}
}