{
  "type": "Feature",
  "properties": {
    "gn:elevation":1347,
    "iso:country":"US",
    "name:cat_x_preferred":[
        "Edgewood"
    ],
    "name:ceb_x_preferred":[
        "Edgewood"
    ],
    "name:deu_x_preferred":[
        "Edgewood"
    ],
    "name:eng_x_preferred":[
        "Edgewood"
    ],
    "name:fas_x_preferred":[
        "\u0627\u062c\u0648\u0648\u062f"
    ],
    "name:fra_x_preferred":[
        "Edgewood"
    ],
    "name:ita_x_preferred":[
        "Edgewood"
    ],
    "name:kor_x_preferred":[
        "\uc5d0\uc9c0\uc6b0\ub4dc"
    ],
    "name:nld_x_preferred":[
        "Edgewood"
    ],
    "name:pol_x_preferred":[
        "Edgewood"
    ],
    "name:por_x_preferred":[
        "Edgewood"
    ],
    "name:spa_x_preferred":[
        "Edgewood"
    ],
    "name:srp_x_preferred":[
        "\u0415\u045f\u0432\u0443\u0434"
    ],
    "name:swe_x_preferred":[
        "Edgewood"
    ],
    "name:ukr_x_preferred":[
        "\u0415\u0434\u0436\u0432\u0443\u0434"
    ],
    "name:unk_x_variant":[
        "Edgewood"
    ],
    "name:urd_x_preferred":[
        "\u0627\u06cc\u062c\u0648\u0648\u0688"
    ],
    "name:vol_x_preferred":[
        "Edgewood"
    ],
    "qs:gn_adm0_cc":"US",
    "qs:gn_fcode":"PPLX",
    "qs:gn_local":5780557,
    "qs:gn_nam_loc":"Riverton, Salt Lake, Utah, US",
    "qs:gn_namadm1":"UT",
    "qs:gn_name":"Edgewood",
    "qs:local_max":4286,
    "qs:local_sum":4742,
    "qs:localhoods":7,
    "qs:name":"Edgewood",
    "qs:name_adm0":"United States",
    "qs:name_adm1":"Utah",
    "qs:name_adm2":"Salt Lake",
    "qs:name_local":"Riverton",
    "qs:photo_max":4,
    "qs:photo_sum":11,
    "qs:placetype":"Suburb",
    "qs:quad_count":5,
    "qs:woe_adm0":23424977,
    "qs:woe_adm1":2347603,
    "qs:woe_adm2":12590278,
    "qs:woe_lau":0,
    "qs:woe_local":2482335,
    "qs:woe_ver":"7.10.0",
    "wd:wordcount":376,
    "wof:lang":[
        "eng"
    ],
    "wof:name":"Edgewood",
    "wof:placetype":"neighbourhood",
    "wof:population":2466,
    "zs:blockids":[
        490351146001013,
        490351146002015,
        490351146003006,
        490351146001011,
        490351146001021,
        490351146003008,
        490351146003009,
        490351146001014,
        490351146001000,
        490351146002024,
        490351146001008,
        490351146003021,
        490351146003010,
        490351146003018,
        490351146002012,
        490351146001002,
        490351146002014,
        490351146003007,
        490351146001012,
        490351128173014,
        490351146001005,
        490351146001004,
        490351146002016,
        490351128173013,
        490351146001007,
        490351146001006,
        490351128171055,
        490351128171054,
        490351146002013,
        490351146003016
    ],
    "zs:housing10":785,
    "zs:pop10":2466
},
  "geometry": {"coordinates":[-111.917474,40.5231],"type":"Point"}
}