{
  "type": "Feature",
  "properties": {
    "iso:country":"US",
    "name:ceb_x_preferred":[
        "Fruitvale"
    ],
    "name:deu_x_preferred":[
        "Fruitvale"
    ],
    "name:eng_x_preferred":[
        "Fruitvale"
    ],
    "name:est_x_preferred":[
        "Fruitvale"
    ],
    "name:fra_x_preferred":[
        "Fruitvale"
    ],
    "name:hun_x_preferred":[
        "Fruitvale"
    ],
    "name:ita_x_preferred":[
        "Fruitvale"
    ],
    "name:kor_x_preferred":[
        "\ud504\ub8e8\ud2b8\ubca0\uc77c"
    ],
    "name:nds_x_preferred":[
        "Fruitvale"
    ],
    "name:nld_x_preferred":[
        "Fruitvale"
    ],
    "name:pol_x_preferred":[
        "Fruitvale"
    ],
    "name:por_x_preferred":[
        "Fruitvale"
    ],
    "name:srp_x_preferred":[
        "\u0424\u0440\u0443\u0442\u0432\u0435\u0458\u043b"
    ],
    "name:swe_x_preferred":[
        "Fruitvale"
    ],
    "name:ukr_x_preferred":[
        "\u0424\u0440\u0443\u0442\u0432\u0435\u0439\u043b"
    ],
    "name:und_x_variant":[
        "Brays"
    ],
    "wd:wordcount":56,
    "wof:name":"Fruitvale",
    "wof:placetype":"neighbourhood",
    "wof:population":2619,
    "zs:area_m":4231966.715515,
    "zs:blockids":[
        60855073015010,
        60855073015019,
        60855073015017,
        60855073015008,
        60855073013013,
        60855073015023,
        60855073016007,
        60855073016021,
        60855073015022,
        60855073016010,
        60855073015018,
        60855073015021,
        60855073016005,
        60855073016016,
        60855073021037,
        60855073022009,
        60855073016004,
        60855073016000,
        60855073015014,
        60855073022007,
        60855073015027,
        60855073015029,
        60855073013011,
        60855073016014,
        60855073016015,
        60855073013009,
        60855073015024,
        60855073016009,
        60855073013012,
        60855073022008,
        60855073022010,
        60855073016012,
        60855073016019,
        60855073013010,
        60855073015028,
        60855073016006,
        60855073015020,
        60855073015025,
        60855073016017,
        60855073013008,
        60855073015026,
        60855073015034,
        60855073015011,
        60855073022004,
        60855073015009,
        60855073016001,
        60855073016013,
        60855073015007,
        60855073016023,
        60855073016011,
        60855073016022,
        60855073016008,
        60855073016018
    ],
    "zs:housing10":1162,
    "zs:label":"Fruitvale",
    "zs:pop10":2619
},
  "geometry": {"coordinates":[-122.003901,37.253585],"type":"Point"}
}