{
  "type": "Feature",
  "properties": {
    "gn:country":"US",
    "gn:fcode":"PPL",
    "gn:population":0,
    "iso:country":"US",
    "name:ara_x_preferred":[
        "\u0645\u0648\u0646\u062a \u0647\u0648\u0628"
    ],
    "name:arz_x_preferred":[
        "\u0645\u0648\u0646\u062a \u0647\u0648\u0628"
    ],
    "name:che_x_preferred":[
        "\u041c\u0430\u0443\u043d\u0442-\u0413\u043e\u0443\u043f"
    ],
    "name:deu_x_preferred":[
        "Mount Hope"
    ],
    "name:eng_x_preferred":[
        "Mount Hope"
    ],
    "name:eus_x_preferred":[
        "Mount Hope"
    ],
    "name:fra_x_preferred":[
        "Mount Hope"
    ],
    "name:hat_x_preferred":[
        "Mount Hope"
    ],
    "name:hun_x_preferred":[
        "Mount Hope"
    ],
    "name:pol_x_preferred":[
        "Mount Hope"
    ],
    "name:spa_x_preferred":[
        "Mount Hope"
    ],
    "name:tat_x_preferred":[
        "\u041c\u0430\u0443\u043d\u0442-\u0413\u043e\u0443\u043f"
    ],
    "name:tur_x_preferred":[
        "Mount Hope"
    ],
    "name:ukr_x_preferred":[
        "\u041c\u0430\u0443\u043d\u0442-\u0413\u043e\u0443\u043f"
    ],
    "name:uzb_x_preferred":[
        "Mount Hope"
    ],
    "qs_pg:aaroncc":"US",
    "qs_pg:gn_country":"US",
    "qs_pg:gn_fcode":"PPL",
    "qs_pg:gn_pop":0,
    "qs_pg:name":"Mount Hope",
    "qs_pg:name_adm0":"United States",
    "qs_pg:name_adm1":"New York",
    "qs_pg:photos":125,
    "qs_pg:photos_1k":25,
    "qs_pg:photos_9k":1,
    "qs_pg:photos_9r":5,
    "qs_pg:photos_all":312,
    "qs_pg:photos_sr":3,
    "qs_pg:pop_sr":0,
    "qs_pg:qs_pg_placetype":"locality",
    "qs_pg:qs_pg_placetype_gp":"Town",
    "qs_pg:woe_adm0":23424977,
    "woe:adm0_id":23424977,
    "woe:name_adm0":"United States",
    "woe:name_adm1":"New York",
    "woe:placetype":"Town",
    "wof:name":"Mount Hope",
    "wof:placetype":"locality",
    "wof:statistical_gore":1
},
  "geometry": {"coordinates":[-74.52182999999999,41.44454],"type":"Point"}
}