{
  "type": "Feature",
  "properties": {
    "gn:admin1_code":"VA",
    "gn:admin2_code":"167",
    "gn:asciiname":"Daw",
    "gn:country_code":"US",
    "gn:dem":581,
    "gn:elevation":"575.0",
    "gn:feature_class":"P",
    "gn:feature_code":"PPL",
    "gn:name":"Daw",
    "gn:population":0,
    "gn:timezone":"America/New_York",
    "iso:country":"US",
    "name:eng_x_preferred":[
        "Daw"
    ],
    "name:fra_x_preferred":[
        "Daw"
    ],
    "name:und_x_variant":[
        "Sugar Daw"
    ],
    "wof:name":"Daw",
    "wof:placetype":"locality"
},
  "geometry": {"coordinates":[-81.85706,37.05261],"type":"Point"}
}