{
  "type": "Feature",
  "properties": {
    "gn:admin1_code":"TN",
    "gn:admin2_code":"181.0",
    "gn:asciiname":"Stout",
    "gn:country_code":"US",
    "gn:dem":160,
    "gn:elevation":"162.0",
    "gn:feature_class":"P",
    "gn:feature_code":"PPL",
    "gn:name":"Stout",
    "gn:population":0,
    "gn:timezone":"America/Chicago",
    "iso:country":"US",
    "name:bul_x_preferred":[
        "\u0421\u0442\u0430\u0443\u0442"
    ],
    "name:cat_x_preferred":[
        "Stout"
    ],
    "name:ces_x_preferred":[
        "Stout"
    ],
    "name:cym_x_preferred":[
        "Cwrw du"
    ],
    "name:dan_x_preferred":[
        "Stout"
    ],
    "name:deu_x_preferred":[
        "Stout"
    ],
    "name:eus_x_preferred":[
        "Stout"
    ],
    "name:fin_x_preferred":[
        "Stout"
    ],
    "name:fra_x_preferred":[
        "Stout"
    ],
    "name:gle_x_preferred":[
        "Leann dubh"
    ],
    "name:glv_x_preferred":[
        "Lhune doo"
    ],
    "name:ind_x_preferred":[
        "Stout"
    ],
    "name:isl_x_preferred":[
        "Stout"
    ],
    "name:ita_x_preferred":[
        "Stout"
    ],
    "name:jpn_x_preferred":[
        "\u30b9\u30bf\u30a6\u30c8"
    ],
    "name:kat_x_preferred":[
        "\u10e1\u10e2\u10d0\u10e3\u10e2\u10d8"
    ],
    "name:kor_x_preferred":[
        "\uc2a4\ud0c0\uc6b0\ud2b8"
    ],
    "name:lit_x_preferred":[
        "Stautas"
    ],
    "name:mkd_x_preferred":[
        "\u0422\u0435\u043c\u043d\u043e \u043f\u0438\u0432\u043e"
    ],
    "name:nld_x_preferred":[
        "Stout"
    ],
    "name:nno_x_preferred":[
        "Stout"
    ],
    "name:nor_x_preferred":[
        "Stout"
    ],
    "name:pol_x_preferred":[
        "Stout"
    ],
    "name:por_x_preferred":[
        "Oatmeal stout"
    ],
    "name:rus_x_preferred":[
        "\u0421\u0442\u0430\u0443\u0442"
    ],
    "name:spa_x_preferred":[
        "Stout"
    ],
    "name:swe_x_preferred":[
        "Stout"
    ],
    "name:tha_x_preferred":[
        "\u0e2a\u0e40\u0e15\u0e32\u0e15\u0e4c"
    ],
    "name:tur_x_preferred":[
        "Stout"
    ],
    "name:ukr_x_preferred":[
        "\u0421\u0442\u0430\u0443\u0442"
    ],
    "name:zho_x_preferred":[
        "\u53f8\u9676\u7279\u5564\u9152"
    ],
    "wof:name":"Stout",
    "wof:placetype":"locality"
},
  "geometry": {"coordinates":[-87.98503000000002,35.01592],"type":"Point"}
}