{
  "type": "Feature",
  "properties": {
    "gn:admin1_code":"KY",
    "gn:admin2_code":"9",
    "gn:asciiname":"Haywood",
    "gn:country_code":"US",
    "gn:dem":234,
    "gn:elevation":"232.0",
    "gn:feature_class":"P",
    "gn:feature_code":"PPL",
    "gn:name":"Haywood",
    "gn:population":0,
    "gn:timezone":"America/Chicago",
    "iso:country":"US",
    "name:azb_x_preferred":[
        "\u0647\u06cc\u0648\u0648\u062f"
    ],
    "name:fas_x_preferred":[
        "\u0647\u06cc\u0648\u0648\u062f"
    ],
    "name:urd_x_preferred":[
        "\u06c1\u06cc\u0648\u0648\u0688"
    ],
    "wof:name":"Haywood",
    "wof:placetype":"locality"
},
  "geometry": {"coordinates":[-85.97441999999999,36.94616],"type":"Point"}
}