{
  "type": "Feature",
  "properties": {
    "gn:admin1_code":"WV",
    "gn:admin2_code":"41.0",
    "gn:asciiname":"Westfield",
    "gn:country_code":"US",
    "gn:dem":321,
    "gn:elevation":"322.0",
    "gn:feature_class":"P",
    "gn:feature_code":"PPL",
    "gn:name":"Westfield",
    "gn:population":0,
    "gn:timezone":"America/New_York",
    "iso:country":"US",
    "name:cat_x_preferred":[
        "Westfield"
    ],
    "name:ceb_x_preferred":[
        "Westfield"
    ],
    "name:deu_x_preferred":[
        "Westfield"
    ],
    "name:fra_x_preferred":[
        "Westfield"
    ],
    "name:ita_x_preferred":[
        "Westfield"
    ],
    "name:jpn_x_preferred":[
        "\u30a6\u30a7\u30b9\u30c8\u30d5\u30a3\u30fc\u30eb\u30c9"
    ],
    "name:kor_x_preferred":[
        "\uc6e8\uc2a4\ud2b8\ud544\ub4dc"
    ],
    "name:nld_x_preferred":[
        "Westfield"
    ],
    "name:pol_x_preferred":[
        "Westfield"
    ],
    "name:por_x_preferred":[
        "Westfield"
    ],
    "name:ron_x_preferred":[
        "Westfield"
    ],
    "name:rus_x_preferred":[
        "\u0423\u044d\u0441\u0442\u0444\u0438\u043b\u0434"
    ],
    "name:sco_x_preferred":[
        "Westfield"
    ],
    "name:spa_x_preferred":[
        "Westfield"
    ],
    "name:srp_x_preferred":[
        "\u0412\u0435\u0441\u0442\u0444\u0438\u043b\u0434"
    ],
    "name:swe_x_preferred":[
        "Westfield"
    ],
    "name:urd_x_preferred":[
        "\u0648\u06cc\u0633\u0679 \u0641\u06cc\u0644\u0688"
    ],
    "name:vol_x_preferred":[
        "Westfield"
    ],
    "wof:name":"Westfield",
    "wof:placetype":"locality"
},
  "geometry": {"coordinates":[-80.45537,39.10565],"type":"Point"}
}