{
  "type": "Feature",
  "properties": {
    "gn:admin1_code":"WA",
    "gn:admin2_code":"7.0",
    "gn:asciiname":"Foothills Senior Mobile Home Park",
    "gn:country_code":"US",
    "gn:dem":241,
    "gn:elevation":"242.0",
    "gn:feature_class":"P",
    "gn:feature_code":"PPL",
    "gn:name":"Foothills Senior Mobile Home Park",
    "gn:population":0,
    "gn:timezone":"America/Los_Angeles",
    "iso:country":"US",
    "wof:name":"Foothills Senior Mobile Home Park",
    "wof:placetype":"campus"
},
  "geometry": {"coordinates":[-120.34452,47.43791],"type":"Point"}
}