{
  "type": "Feature",
  "properties": {
    "iso:country":"US",
    "name:eng_x_preferred":[
        "Holiday Heights"
    ],
    "wof:name":"Holiday Heights",
    "wof:placetype":"neighbourhood",
    "wof:population":1896,
    "zs:area_m":10239301.186226,
    "zs:blockids":[
        340297312041056,
        340297312041024,
        340297312041058,
        340297312041014,
        340297312041022,
        340297312041004,
        340297312041010,
        340297312041007,
        340297312041062,
        340297312041016,
        340297312041002,
        340297312041001,
        340297312041013,
        340297312041006,
        340297312041003,
        340297312041012,
        340297312041059,
        340297312042003,
        340297312041008,
        340297312041060,
        340297312041061,
        340297312041017,
        340297312041015,
        340297312042029,
        340297312041000,
        340297312041030,
        340297312041057,
        340297312041023
    ],
    "zs:housing10":1287,
    "zs:label":"Holiday Heights",
    "zs:pop10":1896
},
  "geometry": {"coordinates":[-74.253246,39.936302],"type":"Point"}
}