{
  "type": "Feature",
  "properties": {
    "gn:admin1_code":"FL",
    "gn:admin2_code":"87.0",
    "gn:asciiname":"Tropic Palms Mobile Home Park",
    "gn:country_code":"US",
    "gn:dem":1,
    "gn:elevation":"0.0",
    "gn:feature_class":"P",
    "gn:feature_code":"PPL",
    "gn:name":"Tropic Palms Mobile Home Park",
    "gn:population":0,
    "gn:timezone":"America/New_York",
    "iso:country":"US",
    "wof:name":"Tropic Palms Mobile Home Park",
    "wof:placetype":"campus"
},
  "geometry": {"coordinates":[-81.73520000000001,24.57324],"type":"Point"}
}