{
  "type": "Feature",
  "properties": {
    "gn:admin1_code":"WI",
    "gn:admin2_code":"101",
    "gn:admin3_code":"54875.0",
    "gn:asciiname":"Jensen's Mobile Home Village",
    "gn:country_code":"US",
    "gn:dem":224,
    "gn:elevation":"225.0",
    "gn:feature_class":"P",
    "gn:feature_code":"PPL",
    "gn:name":"Jensen's Mobile Home Village",
    "gn:population":0,
    "gn:timezone":"America/Chicago",
    "iso:country":"US",
    "wof:name":"Jensen's Mobile Home Village",
    "wof:placetype":"campus"
},
  "geometry": {"coordinates":[-87.925,42.71861],"type":"Point"}
}