{
  "type": "Feature",
  "properties": {
    "gn:admin1_code":"MI",
    "gn:admin2_code":"79.0",
    "gn:admin3_code":"16340.0",
    "gn:asciiname":"Torch River",
    "gn:country_code":"US",
    "gn:dem":178,
    "gn:elevation":"180.0",
    "gn:feature_class":"P",
    "gn:feature_code":"PPL",
    "gn:name":"Torch River",
    "gn:population":0,
    "gn:timezone":"America/Detroit",
    "iso:country":"US",
    "wof:name":"Torch River",
    "wof:placetype":"locality"
},
  "geometry": {"coordinates":[-85.32395,44.85111],"type":"Point"}
}