{
  "type": "Feature",
  "properties": {
    "gn:admin1_code":"NC",
    "gn:admin2_code":"121",
    "gn:admin3_code":"93012.0",
    "gn:asciiname":"Bandana",
    "gn:country_code":"US",
    "gn:dem":797,
    "gn:elevation":"795.0",
    "gn:feature_class":"P",
    "gn:feature_code":"PPL",
    "gn:name":"Bandana",
    "gn:population":0,
    "gn:timezone":"America/New_York",
    "iso:country":"US",
    "wof:name":"Bandana",
    "wof:placetype":"locality"
},
  "geometry": {"coordinates":[-82.17596,35.97317],"type":"Point"}
}