{
  "type": "Feature",
  "properties": {
    "gn:admin1_code":"FL",
    "gn:admin2_code":"86.0",
    "gn:asciiname":"Tenmile Corner",
    "gn:country_code":"US",
    "gn:dem":4,
    "gn:elevation":"1.0",
    "gn:feature_class":"P",
    "gn:feature_code":"PPL",
    "gn:name":"Tenmile Corner",
    "gn:population":0,
    "gn:timezone":"America/New_York",
    "iso:country":"US",
    "wof:name":"Tenmile Corner",
    "wof:placetype":"locality"
},
  "geometry": {"coordinates":[-80.85729000000001,25.61594],"type":"Point"}
}