{
  "type": "Feature",
  "properties": {
    "iso:country":"US",
    "name:eng_x_preferred":[
        "Royal Oaks"
    ],
    "wof:name":"Royal Oaks",
    "wof:placetype":"neighbourhood",
    "zs:area_m":230926.58214,
    "zs:blockids":[
        371830535202014
    ],
    "zs:housing10":0,
    "zs:label":"Royal Oaks",
    "zs:pop10":0
},
  "geometry": {"coordinates":[-78.780789,35.805474],"type":"Point"}
}