{
  "type": "Feature",
  "properties": {
    "gn:admin1_code":"MD",
    "gn:admin2_code":"29.0",
    "gn:asciiname":"Hanesville",
    "gn:country_code":"US",
    "gn:dem":23,
    "gn:elevation":"22.0",
    "gn:feature_class":"P",
    "gn:feature_code":"PPL",
    "gn:name":"Hanesville",
    "gn:population":0,
    "gn:timezone":"America/New_York",
    "iso:country":"US",
    "wof:name":"Hanesville",
    "wof:placetype":"locality"
},
  "geometry": {"coordinates":[-76.13551,39.27594000000001],"type":"Point"}
}