{
  "type": "Feature",
  "properties": {
    "gn:admin1_code":"SD",
    "gn:admin2_code":"65.0",
    "gn:admin3_code":"70390.0",
    "gn:asciiname":"Oahe",
    "gn:country_code":"US",
    "gn:dem":486,
    "gn:elevation":"491.0",
    "gn:feature_class":"P",
    "gn:feature_code":"PPL",
    "gn:name":"Oahe",
    "gn:population":0,
    "gn:timezone":"America/Chicago",
    "iso:country":"US",
    "wof:name":"Oahe",
    "wof:placetype":"locality"
},
  "geometry": {"coordinates":[-100.53097,44.45776],"type":"Point"}
}