{
  "type": "Feature",
  "properties": {
    "gn:admin1_code":"MI",
    "gn:admin2_code":"77.0",
    "gn:admin3_code":"71880.0",
    "gn:asciiname":"Sugarloaf Mobile Home Park",
    "gn:country_code":"US",
    "gn:dem":271,
    "gn:elevation":"269.0",
    "gn:feature_class":"P",
    "gn:feature_code":"PPL",
    "gn:name":"Sugarloaf Mobile Home Park",
    "gn:population":0,
    "gn:timezone":"America/Detroit",
    "iso:country":"US",
    "wof:name":"Sugarloaf Mobile Home Park",
    "wof:placetype":"campus"
},
  "geometry": {"coordinates":[-85.62917,42.15083],"type":"Point"}
}