{
  "type": "Feature",
  "properties": {
    "iso:country":"US",
    "name:eng_x_preferred":[
        "Clement Oaks"
    ],
    "wof:name":"Clement Oaks",
    "wof:placetype":"neighbourhood",
    "wof:population":233,
    "zs:area_m":6607026.673248,
    "zs:blockids":[
        371830542111035,
        371830542111019,
        371830542111031
    ],
    "zs:housing10":89,
    "zs:label":"Clement Oaks",
    "zs:pop10":233
},
  "geometry": {"coordinates":[-78.44197200000001,35.946357],"type":"Point"}
}