{
  "type": "Feature",
  "properties": {
    "gn:admin1_code":"MD",
    "gn:admin2_code":"25.0",
    "gn:asciiname":"Highfield Park",
    "gn:country_code":"US",
    "gn:dem":146,
    "gn:elevation":"147.0",
    "gn:feature_class":"P",
    "gn:feature_code":"PPL",
    "gn:name":"Highfield Park",
    "gn:population":0,
    "gn:timezone":"America/New_York",
    "iso:country":"US",
    "wof:name":"Highfield Park",
    "wof:placetype":"locality"
},
  "geometry": {"coordinates":[-76.43857,39.57483],"type":"Point"}
}