{
  "type": "Feature",
  "properties": {
    "gn:admin1_code":"NC",
    "gn:admin2_code":"129",
    "gn:admin3_code":"92008.0",
    "gn:asciiname":"Rosemans Mobile Home Park",
    "gn:country_code":"US",
    "gn:dem":8,
    "gn:elevation":"7.0",
    "gn:feature_class":"P",
    "gn:feature_code":"PPL",
    "gn:name":"Rosemans Mobile Home Park",
    "gn:population":0,
    "gn:timezone":"America/New_York",
    "iso:country":"US",
    "wof:name":"Rosemans Mobile Home Park",
    "wof:placetype":"campus"
},
  "geometry": {"coordinates":[-77.8746,34.1484],"type":"Point"}
}