{
  "type": "Feature",
  "properties": {
    "gn:country":"US",
    "gn:fcode":"PPL",
    "gn:population":0,
    "iso:country":"US",
    "name:bul_x_preferred":[
        "\u041e\u0442\u043a\u0443\u043f"
    ],
    "name:ces_x_preferred":[
        "V\u00fdkupn\u00e9"
    ],
    "name:dan_x_preferred":[
        "L\u00f8sepenge"
    ],
    "name:deu_x_preferred":[
        "L\u00f6segeld"
    ],
    "name:eng_x_preferred":[
        "Ransom"
    ],
    "name:epo_x_preferred":[
        "Ela\u0109eta mono"
    ],
    "name:fra_x_preferred":[
        "Ran\u00e7on"
    ],
    "name:ido_x_preferred":[
        "Ransono"
    ],
    "name:ind_x_preferred":[
        "Tebusan"
    ],
    "name:jpn_x_preferred":[
        "\u8eab\u4ee3\u91d1"
    ],
    "name:nld_x_preferred":[
        "Losgeld"
    ],
    "name:rus_x_preferred":[
        "\u0412\u044b\u043a\u0443\u043f"
    ],
    "name:swe_x_preferred":[
        "L\u00f6sensumma"
    ],
    "name:tam_x_preferred":[
        "\u0bae\u0bc0\u0b9f\u0bcd\u0baa\u0bc1\u0baa\u0bcd \u0baa\u0ba3\u0bae\u0bcd"
    ],
    "name:ukr_x_preferred":[
        "\u0412\u0438\u043a\u0443\u043f"
    ],
    "name:und_x_variant":[
        "Ranson"
    ],
    "qs_pg:aaroncc":"US",
    "qs_pg:gn_country":"US",
    "qs_pg:gn_fcode":"PPL",
    "qs_pg:gn_pop":0,
    "qs_pg:name":"Ransom",
    "qs_pg:name_adm0":"United States",
    "qs_pg:name_adm1":"Pennsylvania",
    "qs_pg:photos_9k":1,
    "qs_pg:photos_9r":1,
    "qs_pg:photos_all":9,
    "qs_pg:photos_sr":0,
    "qs_pg:pop_sr":0,
    "qs_pg:qs_pg_placetype":"locality",
    "qs_pg:qs_pg_placetype_gp":"Town",
    "qs_pg:woe_adm0":23424977,
    "woe:adm0_id":23424977,
    "woe:name_adm0":"United States",
    "woe:name_adm1":"Pennsylvania",
    "woe:placetype":"Town",
    "wof:name":"Ransom",
    "wof:placetype":"locality"
},
  "geometry": {"coordinates":[-75.82186,41.39425],"type":"Point"}
}