{
  "type": "Feature",
  "properties": {
    "gn:admin1_code":"IN",
    "gn:admin2_code":"061",
    "gn:admin3_code":"80684.0",
    "gn:asciiname":"Valley City",
    "gn:country_code":"US",
    "gn:dem":177,
    "gn:elevation":"175.0",
    "gn:feature_class":"P",
    "gn:feature_code":"PPL",
    "gn:name":"Valley City",
    "gn:population":0,
    "gn:timezone":"America/Kentucky/Louisville",
    "iso:country":"US",
    "name:fas_x_preferred":[
        "\u0648\u0644\u06cc \u0633\u06cc\u062a\u06cc"
    ],
    "name:urd_x_preferred":[
        "\u0648\u06cc\u0644\u06cc \u0633\u0679\u06cc"
    ],
    "wof:name":"Valley City",
    "wof:placetype":"locality"
},
  "geometry": {"coordinates":[-86.22275,38.09396],"type":"Point"}
}