{
  "type": "Feature",
  "properties": {
    "iso:country":"US",
    "name:eng_x_preferred":[
        "Dark Lake"
    ],
    "name:fra_x_preferred":[
        "Dark Lake"
    ],
    "name:swe_x_preferred":[
        "Dark Lake"
    ],
    "qs:gn_adm0_cc":"US",
    "qs:gn_local":5384133,
    "qs:gn_nam_loc":"Pollock Pines, El Dorado, California, US",
    "qs:gn_namadm1":"CA",
    "qs:local_max":114,
    "qs:local_sum":193,
    "qs:localhoods":4,
    "qs:name":"Dark Lake",
    "qs:name_adm0":"United States",
    "qs:name_adm1":"California",
    "qs:name_adm2":"El Dorado",
    "qs:name_local":"Pollock Pines",
    "qs:photo_max":1,
    "qs:photo_sum":1,
    "qs:placetype":"Suburb",
    "qs:quad_count":1,
    "qs:woe_adm0":23424977,
    "qs:woe_adm1":2347563,
    "qs:woe_adm2":12587678,
    "qs:woe_lau":0,
    "qs:woe_local":2474809,
    "qs:woe_ver":"7.10.0",
    "wd:wordcount":21,
    "wof:lang":[
        "eng"
    ],
    "wof:name":"Dark Lake",
    "wof:placetype":"neighbourhood",
    "zs:blockids":[
        60170306034048,
        60170306034130,
        60170306034135,
        60170306034042,
        60170306034062,
        60170306034051,
        60170306034061,
        60170306034064,
        60170306034551,
        60170306034133,
        60170306034058,
        60170306034132,
        60170306034044,
        60170306034050,
        60170306034533,
        60170306034128,
        60170306034134,
        60170306034052,
        60170306034011,
        60170306034033,
        60170306034019,
        60170306034129,
        60170306034039,
        60170306034053,
        60170306034550,
        60170306034035,
        60170306034055,
        60170306034125,
        60170306034049,
        60170306034065,
        60170306034126,
        60170306034054,
        60170306034127,
        60170306034066,
        60170306034025
    ],
    "zs:housing10":14,
    "zs:pop10":0
},
  "geometry": {"coordinates":[-120.226135,38.867512],"type":"Point"}
}