{
  "type": "Feature",
  "properties": {
    "iso:country":"US",
    "name:eng_x_preferred":[
        "Camp Pioneer"
    ],
    "wd:wordcount":24,
    "wof:name":"Camp Pioneer",
    "wof:placetype":"neighbourhood",
    "wof:population":104,
    "zs:area_m":324647.345846,
    "zs:blockids":[
        360290155042002,
        360290155042001
    ],
    "zs:housing10":87,
    "zs:label":"Camp Pioneer",
    "zs:pop10":104
},
  "geometry": {"coordinates":[-79.092299,42.62795],"type":"Point"}
}