{
  "type": "Feature",
  "properties": {
    "gn:admin1_code":"MN",
    "gn:admin2_code":"69.0",
    "gn:admin3_code":"58162.0",
    "gn:asciiname":"Noyes",
    "gn:country_code":"US",
    "gn:dem":240,
    "gn:elevation":"240.0",
    "gn:feature_class":"P",
    "gn:feature_code":"PPL",
    "gn:name":"Noyes",
    "gn:population":0,
    "gn:timezone":"America/Chicago",
    "iso:country":"US",
    "wof:name":"Noyes",
    "wof:placetype":"locality"
},
  "geometry": {"coordinates":[-97.20451,48.99749],"type":"Point"}
}