{
  "type": "Feature",
  "properties": {
    "iso:country":"US",
    "name:ara_x_preferred":[
        "\u0625\u0645\u0631\u0633\u0648\u0646"
    ],
    "name:cat_x_preferred":[
        "Emerson"
    ],
    "name:ceb_x_preferred":[
        "Emerson"
    ],
    "name:ces_x_preferred":[
        "Emerson"
    ],
    "name:deu_x_preferred":[
        "Emerson"
    ],
    "name:eng_x_preferred":[
        "Emerson"
    ],
    "name:fin_x_preferred":[
        "Emerson"
    ],
    "name:fra_x_preferred":[
        "Emerson"
    ],
    "name:heb_x_preferred":[
        "\u05d0\u05de\u05e8\u05e1\u05d5\u05df"
    ],
    "name:hun_x_preferred":[
        "Emerson"
    ],
    "name:ita_x_preferred":[
        "Emerson"
    ],
    "name:jpn_x_preferred":[
        "\u30a8\u30de\u30fc\u30bd\u30f3"
    ],
    "name:kor_x_preferred":[
        "\uc5d0\uba38\uc2a8"
    ],
    "name:nld_x_preferred":[
        "Emerson"
    ],
    "name:nor_x_preferred":[
        "Emerson"
    ],
    "name:pol_x_preferred":[
        "Emerson"
    ],
    "name:ron_x_preferred":[
        "Emerson"
    ],
    "name:rus_x_preferred":[
        "\u042d\u043c\u0435\u0440\u0441\u043e\u043d"
    ],
    "name:slk_x_preferred":[
        "Emerson"
    ],
    "name:spa_x_preferred":[
        "Emerson"
    ],
    "name:srp_x_preferred":[
        "\u0415\u043c\u0435\u0440\u0441\u043e\u043d"
    ],
    "name:swa_x_preferred":[
        "Emerson"
    ],
    "name:swe_x_preferred":[
        "Emerson"
    ],
    "name:tur_x_preferred":[
        "Emerson"
    ],
    "name:ukr_x_preferred":[
        "\u0415\u043c\u0435\u0440\u0441\u043e\u043d"
    ],
    "name:vol_x_preferred":[
        "Emerson"
    ],
    "wof:name":"Emerson",
    "wof:placetype":"neighbourhood",
    "wof:population":446,
    "zs:area_m":49172618.312774,
    "zs:blockids":[
        300310005012037,
        300310005042046,
        300310005011020,
        300310005024010,
        300310005011085,
        300310005042079,
        300310005011088,
        300310005011032,
        300310005011054,
        300310005012051,
        300310005012044,
        300310005012053,
        300310005011081,
        300310005012056,
        300310005042075,
        300310005042054,
        300310005012046,
        300310005024008,
        300310005011010,
        300310005042073,
        300310005011089,
        300310005042051,
        300310005024000,
        300310005012057,
        300310005042074,
        300310005012059,
        300310005042055,
        300310005011080,
        300310005042056,
        300310005011086,
        300310005011052,
        300310005012050,
        300310005024013,
        300310005012097,
        300310005011031,
        300310005012048,
        300310005042058,
        300310005042066,
        300310005042053,
        300310005024014,
        300310005012041,
        300310005024009,
        300310005012042,
        300310005042077,
        300310005011087,
        300310005011082,
        300310005024007,
        300310005024012,
        300310005024006,
        300310005042057,
        300310005024011,
        300310005011051,
        300310005024030
    ],
    "zs:housing10":212,
    "zs:label":"Emerson",
    "zs:pop10":446
},
  "geometry": {"coordinates":[-110.901518,45.625719],"type":"Point"}
}