{
  "type": "Feature",
  "properties": {
    "gn:admin1_code":"MO",
    "gn:admin2_code":"23.0",
    "gn:admin3_code":"22492.0",
    "gn:asciiname":"Halloran",
    "gn:country_code":"US",
    "gn:dem":144,
    "gn:elevation":"139.0",
    "gn:feature_class":"P",
    "gn:feature_code":"PPL",
    "gn:name":"Halloran",
    "gn:population":0,
    "gn:timezone":"America/Chicago",
    "iso:country":"US",
    "name:deu_x_preferred":[
        "Halloran"
    ],
    "wof:name":"Halloran",
    "wof:placetype":"locality"
},
  "geometry": {"coordinates":[-90.61817000000001,36.83339],"type":"Point"}
}