{
  "type": "Feature",
  "properties": {
    "iso:country":"US",
    "name:deu_x_preferred":[
        "Venier"
    ],
    "name:eng_x_preferred":[
        "Venier"
    ],
    "name:fra_x_preferred":[
        "Venier"
    ],
    "name:ita_x_preferred":[
        "Venier"
    ],
    "name:rus_x_preferred":[
        "\u0412\u0435\u043d\u044c\u0435\u0440"
    ],
    "wd:wordcount":109,
    "wof:name":"Venier",
    "wof:placetype":"neighbourhood",
    "wof:population":328,
    "zs:area_m":169180.081095,
    "zs:blockids":[
        490351112023003,
        490351112023009,
        490351112023002,
        490351112023011,
        490351112023010,
        490351112023004
    ],
    "zs:housing10":114,
    "zs:label":"Venier",
    "zs:pop10":328
},
  "geometry": {"coordinates":[-111.840081,40.622713],"type":"Point"}
}