{
  "type": "Feature",
  "properties": {
    "gn:admin1_code":"SC",
    "gn:admin2_code":"41.0",
    "gn:asciiname":"Prospect Crossroads",
    "gn:country_code":"US",
    "gn:dem":11,
    "gn:elevation":"12.0",
    "gn:feature_class":"P",
    "gn:feature_code":"PPL",
    "gn:name":"Prospect Crossroads",
    "gn:population":0,
    "gn:timezone":"America/New_York",
    "iso:country":"US",
    "name:eng_x_preferred":[
        "Prospect Crossroads"
    ],
    "name:und_x_variant":[
        "Prospect Cross Roads"
    ],
    "wof:name":"Prospect Crossroads",
    "wof:placetype":"locality"
},
  "geometry": {"coordinates":[-79.55478000000002,33.83128],"type":"Point"}
}