{
  "type": "Feature",
  "properties": {
    "gn:admin1_code":"VA",
    "gn:admin2_code":"161",
    "gn:asciiname":"Riverside Estates",
    "gn:country_code":"US",
    "gn:dem":318,
    "gn:elevation":"317.0",
    "gn:feature_class":"P",
    "gn:feature_code":"PPL",
    "gn:name":"Riverside Estates",
    "gn:population":0,
    "gn:timezone":"America/New_York",
    "iso:country":"US",
    "wof:name":"Riverside Estates",
    "wof:placetype":"locality"
},
  "geometry": {"coordinates":[-80.10254,37.27847],"type":"Point"}
}