{
  "type": "Feature",
  "properties": {
    "gn:country":"US",
    "gn:fcode":"PPL",
    "gn:population":6177,
    "iso:country":"US",
    "name:azb_x_preferred":[
        "\u0642\u0648\u062f\u0627\u0631\u062f"
    ],
    "name:cat_x_preferred":[
        "Goddard"
    ],
    "name:ceb_x_preferred":[
        "Goddard"
    ],
    "name:eng_x_preferred":[
        "Goddard"
    ],
    "name:fas_x_preferred":[
        "\u06af\u0648\u062f\u0627\u0631\u062f"
    ],
    "name:fra_x_preferred":[
        "Goddard"
    ],
    "name:gle_x_preferred":[
        "Goddard"
    ],
    "name:kaz_x_preferred":[
        "\u0413\u043e\u0434\u0434\u0430\u0440\u0434"
    ],
    "name:kir_x_preferred":[
        "\u0413\u043e\u0434\u0434\u0430\u0440\u0434"
    ],
    "name:nan_x_preferred":[
        "Goddard"
    ],
    "name:nld_x_preferred":[
        "Goddard"
    ],
    "name:por_x_preferred":[
        "Goddard"
    ],
    "name:spa_x_preferred":[
        "Goddard"
    ],
    "name:srp_x_preferred":[
        "\u0413\u043e\u0434\u0430\u0440\u0434"
    ],
    "name:uzb_x_preferred":[
        "Goddard"
    ],
    "name:vol_x_preferred":[
        "Goddard"
    ],
    "name:zho_x_preferred":[
        "\u68ee\u9ebb\u5be6\u90e1"
    ],
    "qs_pg:aaroncc":"US",
    "qs_pg:gn_country":"US",
    "qs_pg:gn_fcode":"PPL",
    "qs_pg:gn_pop":6177,
    "qs_pg:name":"Goddard",
    "qs_pg:name_adm0":"United States",
    "qs_pg:name_adm1":"Maryland",
    "qs_pg:photos":614,
    "qs_pg:photos_1k":124,
    "qs_pg:photos_9k":3,
    "qs_pg:photos_9r":5,
    "qs_pg:photos_all":614,
    "qs_pg:photos_sr":8,
    "qs_pg:pop_sr":5,
    "qs_pg:qs_pg_placetype":"locality",
    "qs_pg:qs_pg_placetype_gp":"Town",
    "qs_pg:woe_adm0":23424977,
    "woe:adm0_id":23424977,
    "woe:name_adm0":"United States",
    "woe:name_adm1":"Maryland",
    "woe:placetype":"Town",
    "wof:name":"Goddard",
    "wof:placetype":"locality",
    "wof:population":6177
},
  "geometry": {"coordinates":[-76.85330999999999,38.98955],"type":"Point"}
}