{
  "type": "Feature",
  "properties": {
    "gn:admin1_code":"AK",
    "gn:admin2_code":"240.0",
    "gn:asciiname":"Kathakne",
    "gn:country_code":"US",
    "gn:dem":515,
    "gn:elevation":"517.0",
    "gn:feature_class":"P",
    "gn:feature_code":"PPL",
    "gn:name":"Kathakne",
    "gn:population":0,
    "gn:timezone":"America/Anchorage",
    "iso:country":"US",
    "name:fas_x_preferred":[
        "\u06a9\u0627\u062a\u06a9\u0646 \u0622\u0644\u0627\u0633\u06a9\u0627"
    ],
    "name:zho_x_preferred":[
        "\u5361\u5854\u514b\u6d85"
    ],
    "wof:name":"Kathakne",
    "wof:placetype":"locality"
},
  "geometry": {"coordinates":[-141.83333000000005,62.96944000000001],"type":"Point"}
}