{
  "type": "Feature",
  "properties": {
    "gn:country":"US",
    "gn:fcode":"PPL",
    "gn:population":0,
    "iso:country":"US",
    "name:ara_x_preferred":[
        "\u0625\u0644\u0643\u0644\u0627\u0646\u062f\u060c \u0645\u064a\u0632\u0648\u0631\u064a"
    ],
    "name:ara_x_variant":[
        "\u0625\u0644\u0643\u0644\u0627\u0646\u062f"
    ],
    "name:eng_x_preferred":[
        "Elkland"
    ],
    "name:fra_x_preferred":[
        "Elkland"
    ],
    "name:vol_x_preferred":[
        "Elkland"
    ],
    "qs_pg:aaroncc":"US",
    "qs_pg:gn_country":"US",
    "qs_pg:gn_fcode":"PPL",
    "qs_pg:gn_pop":0,
    "qs_pg:name":"Elkland",
    "qs_pg:name_adm0":"United States",
    "qs_pg:name_adm1":"Missouri",
    "qs_pg:photos":10,
    "qs_pg:photos_1k":2,
    "qs_pg:photos_9k":1,
    "qs_pg:photos_9r":1,
    "qs_pg:photos_all":10,
    "qs_pg:photos_sr":1,
    "qs_pg:pop_sr":5,
    "qs_pg:qs_pg_placetype":"locality",
    "qs_pg:qs_pg_placetype_gp":"Town",
    "qs_pg:woe_adm0":23424977,
    "woe:adm0_id":23424977,
    "woe:name_adm0":"United States",
    "woe:name_adm1":"Missouri",
    "woe:placetype":"Town",
    "wof:name":"Elkland",
    "wof:placetype":"locality"
},
  "geometry": {"coordinates":[-93.03102,37.4431],"type":"Point"}
}