{
  "type": "Feature",
  "properties": {
    "gn:admin1_code":"AL",
    "gn:admin2_code":"71.0",
    "gn:asciiname":"Rock City",
    "gn:country_code":"US",
    "gn:dem":355,
    "gn:elevation":"357.0",
    "gn:feature_class":"P",
    "gn:feature_code":"PPL",
    "gn:name":"Rock City",
    "gn:population":0,
    "gn:timezone":"America/Chicago",
    "iso:country":"US",
    "name:ceb_x_preferred":[
        "Rock City"
    ],
    "name:deu_x_preferred":[
        "Rock City"
    ],
    "name:ita_x_preferred":[
        "Rock City"
    ],
    "wof:name":"Rock City",
    "wof:placetype":"locality"
},
  "geometry": {"coordinates":[-85.95025,34.53259],"type":"Point"}
}