{
  "type": "Feature",
  "properties": {
    "gn:admin1_code":"OK",
    "gn:admin2_code":"79.0",
    "gn:asciiname":"Stony Point",
    "gn:country_code":"US",
    "gn:dem":148,
    "gn:elevation":"143.0",
    "gn:feature_class":"P",
    "gn:feature_code":"PPL",
    "gn:name":"Stony Point",
    "gn:population":0,
    "gn:timezone":"America/Chicago",
    "iso:country":"US",
    "name:ceb_x_preferred":[
        "Stony Point"
    ],
    "name:deu_x_preferred":[
        "Stoney Point"
    ],
    "name:fas_x_preferred":[
        "\u0627\u0633\u062a\u0648\u0648\u0646\u06cc \u067e\u0648\u06cc\u0646\u062a"
    ],
    "name:fra_x_preferred":[
        "Stony Point"
    ],
    "name:ita_x_preferred":[
        "Stony Point"
    ],
    "name:nld_x_preferred":[
        "Stony Point"
    ],
    "name:pol_x_preferred":[
        "Stony Point"
    ],
    "name:por_x_preferred":[
        "Stony Point"
    ],
    "name:srp_x_preferred":[
        "\u0421\u0442\u043e\u043d\u0438 \u041f\u043e\u0458\u043d\u0442"
    ],
    "name:swe_x_preferred":[
        "Stony Point"
    ],
    "name:vol_x_preferred":[
        "Stony Point"
    ],
    "wof:name":"Stony Point",
    "wof:placetype":"locality"
},
  "geometry": {"coordinates":[-94.66856,35.25287],"type":"Point"}
}