{
  "type": "Feature",
  "properties": {
    "gn:admin1_code":"WA",
    "gn:admin2_code":"63.0",
    "gn:asciiname":"Stringtown",
    "gn:country_code":"US",
    "gn:dem":859,
    "gn:elevation":"862.0",
    "gn:feature_class":"P",
    "gn:feature_code":"PPL",
    "gn:name":"Stringtown",
    "gn:population":0,
    "gn:timezone":"America/Los_Angeles",
    "iso:country":"US",
    "name:deu_x_preferred":[
        "Stringtown"
    ],
    "name:vol_x_preferred":[
        "Stringtown"
    ],
    "wof:name":"Stringtown",
    "wof:placetype":"locality"
},
  "geometry": {"coordinates":[-117.06268,47.31795],"type":"Point"}
}