{
  "type": "Feature",
  "properties": {
    "gn:admin1_code":"AL",
    "gn:admin2_code":"1",
    "gn:asciiname":"Fremont",
    "gn:country_code":"US",
    "gn:dem":59,
    "gn:elevation":"58.0",
    "gn:feature_class":"P",
    "gn:feature_code":"PPL",
    "gn:name":"Fremont",
    "gn:population":0,
    "gn:timezone":"America/Chicago",
    "iso:country":"US",
    "name:cat_x_preferred":[
        "Fremont"
    ],
    "name:ceb_x_preferred":[
        "Fremont"
    ],
    "name:deu_x_preferred":[
        "Fremont"
    ],
    "name:eng_x_preferred":[
        "Fremont"
    ],
    "name:epo_x_preferred":[
        "Fremont"
    ],
    "name:fin_x_preferred":[
        "Fremont"
    ],
    "name:fra_x_preferred":[
        "Fremont"
    ],
    "name:heb_x_preferred":[
        "\u05e4\u05e8\u05d9\u05de\u05d5\u05e0\u05d8"
    ],
    "name:hun_x_preferred":[
        "Fremont"
    ],
    "name:ita_x_preferred":[
        "Fremont"
    ],
    "name:jpn_x_preferred":[
        "\u30d5\u30ea\u30fc\u30e2\u30f3\u30c8"
    ],
    "name:kor_x_preferred":[
        "\ud504\ub9ac\ubaac\ud2b8"
    ],
    "name:mar_x_preferred":[
        "\u092b\u094d\u0930\u0947\u092e\u093e\u0901\u091f"
    ],
    "name:nds_x_preferred":[
        "Fremont"
    ],
    "name:nld_x_preferred":[
        "Fremont"
    ],
    "name:pol_x_preferred":[
        "Fremont"
    ],
    "name:por_x_preferred":[
        "Fremont"
    ],
    "name:ron_x_preferred":[
        "Fremont"
    ],
    "name:rus_x_preferred":[
        "\u0424\u0440\u0438\u043c\u043e\u043d\u0442"
    ],
    "name:spa_x_preferred":[
        "Fremont"
    ],
    "name:srp_x_preferred":[
        "\u0424\u0440\u0438\u043c\u043e\u043d\u0442"
    ],
    "name:swe_x_preferred":[
        "Fremont"
    ],
    "name:ukr_x_preferred":[
        "\u0424\u0440\u0456\u043c\u043e\u043d\u0442"
    ],
    "name:und_x_variant":[
        "Dunklin",
        "Clay"
    ],
    "name:urd_x_preferred":[
        "\u0641\u0631\u06cc\u0645\u0648\u0646\u0679"
    ],
    "name:vol_x_preferred":[
        "Fremont"
    ],
    "name:zho_x_preferred":[
        "\u4f5b\u745e\u8499"
    ],
    "wof:name":"Fremont",
    "wof:placetype":"locality"
},
  "geometry": {"coordinates":[-86.89471,32.54541],"type":"Point"}
}