{
  "type": "Feature",
  "properties": {
    "gn:country":"US",
    "gn:fcode":"PPL",
    "gn:population":0,
    "iso:country":"US",
    "name:azb_x_preferred":[
        "\u06a9\u0627\u0644\u06cc\u0641\u0648\u0631\u0646\u06cc\u0627 \u0648\u0644\u06cc"
    ],
    "name:eng_x_preferred":[
        "California Valley"
    ],
    "name:fas_x_preferred":[
        "\u06a9\u0627\u0644\u06cc\u0641\u0631\u0646\u06cc\u0627 \u0648\u0644\u06cc"
    ],
    "name:fra_x_preferred":[
        "California Valley"
    ],
    "name:hye_x_preferred":[
        "\u053f\u0561\u056c\u056b\u0586\u0578\u057c\u0576\u056b\u0561\u0575\u056b \u0570\u0578\u057e\u056b\u057f"
    ],
    "name:nld_x_preferred":[
        "California Valley"
    ],
    "name:spa_x_preferred":[
        "California Valley"
    ],
    "name:tur_x_preferred":[
        "California Valley"
    ],
    "name:vol_x_preferred":[
        "California Valley"
    ],
    "name:zho_x_preferred":[
        "\u52a0\u5dde\u8c37"
    ],
    "qs_pg:aaroncc":"US",
    "qs_pg:gn_country":"US",
    "qs_pg:gn_fcode":"PPL",
    "qs_pg:gn_pop":0,
    "qs_pg:name":"California Valley",
    "qs_pg:name_adm0":"United States",
    "qs_pg:name_adm1":"California",
    "qs_pg:photos":69,
    "qs_pg:photos_1k":14,
    "qs_pg:photos_9k":1,
    "qs_pg:photos_9r":2,
    "qs_pg:photos_all":69,
    "qs_pg:photos_sr":2,
    "qs_pg:pop_sr":0,
    "qs_pg:qs_pg_placetype":"locality",
    "qs_pg:qs_pg_placetype_gp":"Town",
    "qs_pg:woe_adm0":23424977,
    "woe:adm0_id":23424977,
    "woe:name_adm0":"United States",
    "woe:name_adm1":"California",
    "woe:placetype":"Town",
    "wof:name":"California Valley",
    "wof:placetype":"locality"
},
  "geometry": {"coordinates":[-120.0068,35.31997],"type":"Point"}
}