{
  "type": "Feature",
  "properties": {
    "iso:country":"US",
    "name:eng_x_preferred":[
        "Bens Creek"
    ],
    "name:eng_x_variant":[
        "Bens Crk"
    ],
    "qs:gn_adm0_cc":"US",
    "qs:gn_fcode":"PPL",
    "qs:gn_local":5185145,
    "qs:gn_nam_loc":"Conemaugh, Somerset, Pennsylvania, US",
    "qs:gn_namadm1":"PA",
    "qs:gn_name":"Bens Creek",
    "qs:local_max":27,
    "qs:local_sum":28,
    "qs:localhoods":2,
    "qs:name":"Bens Creek",
    "qs:name_adm0":"United States",
    "qs:name_adm1":"Pennsylvania",
    "qs:name_adm2":"Somerset",
    "qs:name_local":"Conemaugh",
    "qs:photo_max":16,
    "qs:photo_sum":27,
    "qs:placetype":"Suburb",
    "qs:quad_count":3,
    "qs:woe_adm0":23424977,
    "qs:woe_adm1":2347597,
    "qs:woe_adm2":12589783,
    "qs:woe_lau":0,
    "qs:woe_local":28744599,
    "qs:woe_ver":"7.10.0",
    "wof:lang":[
        "eng"
    ],
    "wof:name":"Bens Creek",
    "wof:placetype":"neighbourhood"
},
  "geometry": {"coordinates":[-78.95050000000001,40.279293],"type":"Point"}
}