{
  "type": "Feature",
  "properties": {
    "gn:admin1_code":"WA",
    "gn:admin2_code":"49.0",
    "gn:asciiname":"Bedford",
    "gn:country_code":"US",
    "gn:dem":164,
    "gn:elevation":"159.0",
    "gn:feature_class":"P",
    "gn:feature_code":"PPL",
    "gn:name":"Bedford",
    "gn:population":0,
    "gn:timezone":"America/Los_Angeles",
    "iso:country":"US",
    "name:ara_x_preferred":[
        "\u0628\u064a\u062f\u0641\u0648\u0631\u062f"
    ],
    "name:ast_x_preferred":[
        "Bedford"
    ],
    "name:azb_x_preferred":[
        "\u0628\u062f\u0641\u0648\u0631\u062f"
    ],
    "name:ben_x_preferred":[
        "\u09ac\u09c7\u09a1\u09ab\u09cb\u09b0\u09cd\u09a1"
    ],
    "name:cat_x_preferred":[
        "Bedford"
    ],
    "name:ceb_x_preferred":[
        "Bedford"
    ],
    "name:cym_x_preferred":[
        "Bedford"
    ],
    "name:dan_x_preferred":[
        "Bedford"
    ],
    "name:deu_x_preferred":[
        "Bedford"
    ],
    "name:ell_x_preferred":[
        "\u039c\u03c0\u03ad\u03bd\u03c4\u03c6\u03bf\u03c1\u03bd\u03c4"
    ],
    "name:epo_x_preferred":[
        "Bedford"
    ],
    "name:fas_x_preferred":[
        "\u0628\u062f\u0641\u0648\u0631\u062f"
    ],
    "name:fin_x_preferred":[
        "Bedford"
    ],
    "name:fra_x_preferred":[
        "Bedford"
    ],
    "name:fry_x_preferred":[
        "Bedford"
    ],
    "name:gle_x_preferred":[
        "Bedford"
    ],
    "name:heb_x_preferred":[
        "\u05d1\u05d3\u05e4\u05d5\u05e8\u05d3"
    ],
    "name:hin_x_preferred":[
        "\u092c\u0947\u0921\u092b\u094b\u0930\u094d\u0921"
    ],
    "name:hun_x_preferred":[
        "Bedford"
    ],
    "name:ind_x_preferred":[
        "Bedford"
    ],
    "name:isl_x_preferred":[
        "Bedford"
    ],
    "name:ita_x_preferred":[
        "Bedford"
    ],
    "name:jpn_x_preferred":[
        "\u30d9\u30c3\u30c9\u30d5\u30a9\u30fc\u30c9"
    ],
    "name:kor_x_preferred":[
        "\ubca0\ub4dc\ud37c\ub4dc"
    ],
    "name:lat_x_preferred":[
        "Bedfordia"
    ],
    "name:lit_x_preferred":[
        "Bedfordas"
    ],
    "name:lmo_x_preferred":[
        "Bedford"
    ],
    "name:mlg_x_preferred":[
        "Bedford"
    ],
    "name:nld_x_preferred":[
        "Bedford"
    ],
    "name:nno_x_preferred":[
        "Bedford"
    ],
    "name:nor_x_preferred":[
        "Bedford"
    ],
    "name:pol_x_preferred":[
        "Bedford"
    ],
    "name:por_x_preferred":[
        "Bedford"
    ],
    "name:ron_x_preferred":[
        "Bedford"
    ],
    "name:rus_x_preferred":[
        "\u0411\u0435\u0434\u0444\u043e\u0440\u0434"
    ],
    "name:sco_x_preferred":[
        "Bedford"
    ],
    "name:slv_x_preferred":[
        "Bedford"
    ],
    "name:spa_x_preferred":[
        "Bedford"
    ],
    "name:srp_x_preferred":[
        "\u0411\u0435\u0434\u0444\u043e\u0440\u0434"
    ],
    "name:swe_x_preferred":[
        "Bedford"
    ],
    "name:tat_x_preferred":[
        "\u0411\u0435\u0434\u0444\u043e\u0440\u0434"
    ],
    "name:tur_x_preferred":[
        "Bedford"
    ],
    "name:ukr_x_preferred":[
        "\u0411\u0435\u0434\u0444\u043e\u0440\u0434"
    ],
    "name:urd_x_preferred":[
        "\u0628\u06cc\u0688\u0641\u0648\u0631\u0688"
    ],
    "name:vec_x_preferred":[
        "Bedford"
    ],
    "name:vie_x_preferred":[
        "Bedford"
    ],
    "name:vol_x_preferred":[
        "Bedford"
    ],
    "name:war_x_preferred":[
        "Bedford"
    ],
    "name:yid_x_preferred":[
        "\u05d1\u05e2\u05d3\u05e4\u05d0\u05e8\u05d3"
    ],
    "name:zho_x_preferred":[
        "\u8c9d\u5fb7\u798f\u5fb7"
    ],
    "wof:name":"Bedford",
    "wof:placetype":"locality"
},
  "geometry": {"coordinates":[-123.46793,46.66121],"type":"Point"}
}