{
  "type": "Feature",
  "properties": {
    "gn:admin1_code":"AZ",
    "gn:admin2_code":"5.0",
    "gn:asciiname":"Durfee Crossing",
    "gn:country_code":"US",
    "gn:dem":1894,
    "gn:elevation":"1883.0",
    "gn:feature_class":"P",
    "gn:feature_code":"PPL",
    "gn:name":"Durfee Crossing",
    "gn:population":0,
    "gn:timezone":"America/Phoenix",
    "iso:country":"US",
    "wof:name":"Durfee Crossing",
    "wof:placetype":"locality"
},
  "geometry": {"coordinates":[-110.80485,34.57392],"type":"Point"}
}