{
  "type": "Feature",
  "properties": {
    "iso:country":"US",
    "name:ceb_x_preferred":[
        "Fox Creek"
    ],
    "name:deu_x_preferred":[
        "Fox Creek"
    ],
    "name:eng_x_preferred":[
        "Fox Creek"
    ],
    "name:fra_x_preferred":[
        "Fox Creek"
    ],
    "name:swe_x_preferred":[
        "Fox Creek"
    ],
    "wd:wordcount":66,
    "wof:name":"Fox Creek",
    "wof:placetype":"neighbourhood",
    "wof:population":1813,
    "zs:area_m":520411.566262,
    "zs:blockids":[
        60770034031019,
        60770034033004,
        60770034032001,
        60770034033002,
        60770034043002,
        60770034032000,
        60770034033001,
        60770034031008,
        60770034043001,
        60770034033000,
        60770034033003,
        60770034031020
    ],
    "zs:housing10":483,
    "zs:label":"Fox Creek",
    "zs:pop10":1813
},
  "geometry": {"coordinates":[-121.29766100000001,38.033062],"type":"Point"}
}