{
  "type": "Feature",
  "properties": {
    "iso:country":"US",
    "name:eng_x_preferred":[
        "North Brewer"
    ],
    "name:eng_x_variant":[
        "N Brewer"
    ],
    "qs:gn_adm0_cc":"US",
    "qs:gn_fcode":"PPL",
    "qs:gn_local":4959233,
    "qs:gn_nam_loc":"Brewer, Penobscot, Maine, US",
    "qs:gn_namadm1":"ME",
    "qs:gn_name":"North Brewer",
    "qs:local_max":22,
    "qs:local_sum":22,
    "qs:localhoods":1,
    "qs:name":"North Brewer",
    "qs:name_adm0":"United States",
    "qs:name_adm1":"Maine",
    "qs:name_adm2":"Penobscot",
    "qs:name_local":"Brewer",
    "qs:photo_max":13,
    "qs:photo_sum":22,
    "qs:placetype":"Suburb",
    "qs:quad_count":8,
    "qs:woe_adm0":23424977,
    "qs:woe_adm1":2347578,
    "qs:woe_adm2":12588669,
    "qs:woe_lau":0,
    "qs:woe_local":2368636,
    "qs:woe_ver":"7.10.0",
    "wof:lang":[
        "eng"
    ],
    "wof:name":"North Brewer",
    "wof:placetype":"neighbourhood",
    "wof:population":4009,
    "zs:blockids":[
        230190043002009,
        230190043002007,
        230190050002018,
        230190050001018,
        230190050001007,
        230190043001001,
        230190043001002,
        230190050001017,
        230190043002013,
        230190003001023,
        230190050001003,
        230190043002035,
        230190043002022,
        230190050002003,
        230190043002034,
        230190050001019,
        230190050001012,
        230190090003010,
        230190050001009,
        230190043002012,
        230190043002000,
        230190050001005,
        230190043002033,
        230190090005003,
        230190050001010,
        230190090005002,
        230190043002032,
        230190090005001,
        230190043002011,
        230190090002000,
        230190050001013,
        230190043002004,
        230190090005006,
        230190050002017,
        230190090005004,
        230190050001008,
        230190090002008,
        230190050001015,
        230190050002013,
        230190043002005,
        230190050001001,
        230190003001024,
        230190043002001,
        230190043002023,
        230190050002016,
        230190090003014,
        230190050001006,
        230190061001030,
        230190090002009,
        230190003001022,
        230190043002002,
        230190043002010,
        230190050001011,
        230190090005000,
        230190090003015,
        230190090002007,
        230190043002006,
        230190050002015,
        230190043002021,
        230190043002008,
        230190043002020,
        230190043001000,
        230190043002003,
        230190090004003,
        230190050001020,
        230190043002019,
        230190050001014,
        230190050001004,
        230190050001002,
        230190050001000,
        230190050001016,
        230190090005005
    ],
    "zs:housing10":1816,
    "zs:pop10":4009
},
  "geometry": {"coordinates":[-68.72123000000001,44.822584],"type":"Point"}
}