{
  "type": "Feature",
  "properties": {
    "gn:admin1_code":"GA",
    "gn:admin2_code":"245.0",
    "gn:asciiname":"Bridgeport",
    "gn:country_code":"US",
    "gn:dem":134,
    "gn:elevation":"127.0",
    "gn:feature_class":"P",
    "gn:feature_code":"PPL",
    "gn:name":"Bridgeport",
    "gn:population":0,
    "gn:timezone":"America/New_York",
    "iso:country":"US",
    "wof:name":"Bridgeport",
    "wof:placetype":"locality"
},
  "geometry": {"coordinates":[-82.10429000000001,33.46153],"type":"Point"}
}