{
  "type": "Feature",
  "properties": {
    "gn:admin1_code":"GA",
    "gn:admin2_code":"25.0",
    "gn:asciiname":"Browntown",
    "gn:country_code":"US",
    "gn:dem":26,
    "gn:elevation":"22.0",
    "gn:feature_class":"P",
    "gn:feature_code":"PPL",
    "gn:name":"Browntown",
    "gn:population":0,
    "gn:timezone":"America/New_York",
    "iso:country":"US",
    "name:ceb_x_preferred":[
        "Browntown"
    ],
    "name:deu_x_preferred":[
        "Browntown"
    ],
    "name:srp_x_preferred":[
        "\u0411\u0440\u0430\u0443\u043d\u0442\u0430\u0443\u043d"
    ],
    "wof:name":"Browntown",
    "wof:placetype":"locality"
},
  "geometry": {"coordinates":[-81.78178,31.33745],"type":"Point"}
}