{
  "type": "Feature",
  "properties": {
    "iso:country":"US",
    "name:eng_x_preferred":[
        "Franklin Forest"
    ],
    "wd:wordcount":138,
    "wof:name":"Franklin Forest",
    "wof:placetype":"neighbourhood",
    "wof:population":558,
    "zs:area_m":515470.295605,
    "zs:blockids":[
        510594709002000,
        510594709001015,
        510594709001014,
        510594709001013,
        510594709001019
    ],
    "zs:housing10":200,
    "zs:label":"Franklin Forest",
    "zs:pop10":558
},
  "geometry": {"coordinates":[-77.161568,38.910568],"type":"Point"}
}