{
  "type": "Feature",
  "properties": {
    "gn:admin1_code":"GA",
    "gn:admin2_code":"61.0",
    "gn:asciiname":"Harrisons Mill",
    "gn:country_code":"US",
    "gn:dem":90,
    "gn:elevation":"83.0",
    "gn:feature_class":"P",
    "gn:feature_code":"PPL",
    "gn:name":"Harrisons Mill",
    "gn:population":0,
    "gn:timezone":"America/New_York",
    "iso:country":"US",
    "name:eng_x_preferred":[
        "Harrisons Mill"
    ],
    "name:und_x_variant":[
        "Harrison Mill"
    ],
    "wof:name":"Harrisons Mill",
    "wof:placetype":"locality"
},
  "geometry": {"coordinates":[-84.88576,31.54823],"type":"Point"}
}