{
  "type": "Feature",
  "properties": {
    "gn:admin1_code":"TN",
    "gn:admin2_code":"145",
    "gn:asciiname":"Eblen Estates",
    "gn:country_code":"US",
    "gn:dem":233,
    "gn:elevation":"231.0",
    "gn:feature_class":"P",
    "gn:feature_code":"PPL",
    "gn:name":"Eblen Estates",
    "gn:population":0,
    "gn:timezone":"America/New_York",
    "iso:country":"US",
    "wof:name":"Eblen Estates",
    "wof:placetype":"locality"
},
  "geometry": {"coordinates":[-84.4866,35.8523],"type":"Point"}
}