{
  "type": "Feature",
  "properties": {
    "gn:admin1_code":"NY",
    "gn:admin2_code":"65",
    "gn:admin3_code":"77123.0",
    "gn:asciiname":"Vernon Downs Mobile Home Park",
    "gn:country_code":"US",
    "gn:dem":203,
    "gn:elevation":"204.0",
    "gn:feature_class":"P",
    "gn:feature_code":"PPL",
    "gn:name":"Vernon Downs Mobile Home Park",
    "gn:population":0,
    "gn:timezone":"America/New_York",
    "iso:country":"US",
    "wof:name":"Vernon Downs Mobile Home Park",
    "wof:placetype":"campus"
},
  "geometry": {"coordinates":[-75.53583,43.06917],"type":"Point"}
}