{
  "type": "Feature",
  "properties": {
    "gn:admin1_code":"MD",
    "gn:admin2_code":"1.0",
    "gn:asciiname":"Amcelle Acres",
    "gn:country_code":"US",
    "gn:dem":267,
    "gn:elevation":"266.0",
    "gn:feature_class":"P",
    "gn:feature_code":"PPL",
    "gn:name":"Amcelle Acres",
    "gn:population":0,
    "gn:timezone":"America/New_York",
    "iso:country":"US",
    "wof:name":"Amcelle Acres",
    "wof:placetype":"locality"
},
  "geometry": {"coordinates":[-78.84919000000002,39.58898],"type":"Point"}
}