{
  "type": "Feature",
  "properties": {
    "iso:country":"US",
    "name:cat_x_preferred":[
        "Grandview"
    ],
    "name:ceb_x_preferred":[
        "Grandview"
    ],
    "name:deu_x_preferred":[
        "Grandview"
    ],
    "name:eng_x_preferred":[
        "Grandview"
    ],
    "name:fin_x_preferred":[
        "Grandview"
    ],
    "name:fra_x_preferred":[
        "Grandview"
    ],
    "name:ita_x_preferred":[
        "Grandview"
    ],
    "name:kor_x_preferred":[
        "\uadf8\ub79c\ub4dc\ubdf0"
    ],
    "name:nld_x_preferred":[
        "Grandview"
    ],
    "name:pol_x_preferred":[
        "Grandview"
    ],
    "name:srp_x_preferred":[
        "\u0413\u0440\u0430\u043d\u0434\u0432\u0458\u0443"
    ],
    "name:swe_x_preferred":[
        "Grandview"
    ],
    "name:ukr_x_preferred":[
        "\u0413\u0440\u0430\u043d\u0434\u0432'\u044e"
    ],
    "name:vol_x_preferred":[
        "Grandview"
    ],
    "name:zho_x_preferred":[
        "\u683c\u5170\u5fb7\u7ef4\u5c24"
    ],
    "wof:name":"Grandview",
    "wof:placetype":"neighbourhood",
    "wof:population":3296,
    "zs:blockids":[
        202090448051033,
        202090449001009,
        202090449001007,
        202090448051031,
        202090448051036,
        202090448051021,
        202090448051016,
        202090448051037,
        202090448051035,
        202090448051020,
        202090448051024,
        202090448051023,
        202090448051022,
        202090448051032,
        202090448061056,
        202090448051018,
        202090448051029,
        202090448061062,
        202090448061067,
        202090449001008,
        202090448061065,
        202090448051034,
        202090448051025,
        202090448051017,
        202090448051030,
        202090448051040,
        202090448051028,
        202090448061063,
        202090448051019,
        202090448051039,
        202090448051027,
        202090448051038,
        202090449001006,
        202090448061064,
        202090448051026,
        201030712021039,
        201030712022007,
        201030714002048,
        201030714002069,
        201030712022003,
        201030714002003,
        201030714002052,
        201030712022000,
        201030712022004,
        201030714002045,
        201030714002047,
        201030714002059,
        201030714002000,
        201030714002051,
        201030714002063,
        201030714002046,
        201030712021021,
        201030714002044,
        201030714002075,
        201030714002080,
        201030712022006,
        201030712022002,
        201030714002039,
        201030712021038,
        201030714002043,
        201030714002004,
        201030714002040,
        201030714002078,
        201030714002082,
        201030712022048,
        201030714002041,
        201030712022034,
        201030714002001,
        201030714002081,
        201030712021066,
        201030712022005,
        201030714002050,
        201030712022035,
        201030714002067,
        201030714002065,
        201030712022037,
        201030714002079,
        201030714002058,
        201030712022036,
        201030714002068,
        201030712022001,
        201030714002064,
        201030714002042,
        201030712022008,
        201030714002053,
        201030714002054
    ],
    "zs:housing10":1260,
    "zs:label":"Grandview",
    "zs:pop10":3296
},
  "geometry": {"coordinates":[-94.929081,39.041657],"type":"Point"}
}