{
  "type": "Feature",
  "properties": {
    "gn:admin1_code":"GA",
    "gn:admin2_code":"37.0",
    "gn:asciiname":"Dickey",
    "gn:country_code":"US",
    "gn:dem":95,
    "gn:elevation":"86.0",
    "gn:feature_class":"P",
    "gn:feature_code":"PPL",
    "gn:name":"Dickey",
    "gn:population":0,
    "gn:timezone":"America/New_York",
    "iso:country":"US",
    "name:eng_x_preferred":[
        "Dickey"
    ],
    "name:und_x_variant":[
        "Whitney"
    ],
    "wof:name":"Dickey",
    "wof:placetype":"locality"
},
  "geometry": {"coordinates":[-84.6602,31.55712],"type":"Point"}
}