{
  "type": "Feature",
  "properties": {
    "iso:country":"US",
    "name:eng_x_preferred":[
        "Kings Acres"
    ],
    "wof:name":"Kings Acres",
    "wof:placetype":"neighbourhood",
    "wof:population":234,
    "zs:area_m":32536576.899033,
    "zs:blockids":[
        11250125011168,
        11250125011133,
        11250125011167,
        11250125011129,
        11250125011171,
        11250125022010,
        11250125011135,
        11250125022009,
        11250125011141,
        11250125011134,
        11250125011172,
        11250117032087,
        11250125011178,
        11250125011140,
        11250125022012,
        11250125011169,
        11250125022008,
        11250125011122,
        11250125022030,
        11250125022092,
        11250125011123,
        11250125011132,
        11250125011166,
        11250125011124,
        11250125022095,
        11250125022093,
        11250125011170
    ],
    "zs:housing10":97,
    "zs:label":"Kings Acres",
    "zs:pop10":234
},
  "geometry": {"coordinates":[-87.623081,33.134526],"type":"Point"}
}