{
  "type": "Feature",
  "properties": {
    "gn:admin1_code":"DE",
    "gn:admin2_code":"1.0",
    "gn:asciiname":"D and K Mobile Home Park",
    "gn:country_code":"US",
    "gn:dem":15,
    "gn:elevation":"15.0",
    "gn:feature_class":"P",
    "gn:feature_code":"PPL",
    "gn:name":"D and K Mobile Home Park",
    "gn:population":0,
    "gn:timezone":"America/New_York",
    "iso:country":"US",
    "wof:name":"D and K Mobile Home Park",
    "wof:placetype":"campus"
},
  "geometry": {"coordinates":[-75.52659,38.97095],"type":"Point"}
}