{
  "type": "Feature",
  "properties": {
    "gn:admin1_code":"TN",
    "gn:admin2_code":"77",
    "gn:asciiname":"Mount Gilead",
    "gn:country_code":"US",
    "gn:dem":172,
    "gn:elevation":"171.0",
    "gn:feature_class":"P",
    "gn:feature_code":"PPL",
    "gn:name":"Mount Gilead",
    "gn:population":0,
    "gn:timezone":"America/Chicago",
    "iso:country":"US",
    "wof:name":"Mount Gilead",
    "wof:placetype":"locality"
},
  "geometry": {"coordinates":[-88.53976999999998,35.7659],"type":"Point"}
}