{
  "type": "Feature",
  "properties": {
    "gn:admin1_code":"MI",
    "gn:admin2_code":"161.0",
    "gn:admin3_code":"71160.0",
    "gn:asciiname":"River Ridge Mobile Home Community",
    "gn:country_code":"US",
    "gn:dem":251,
    "gn:elevation":"253.0",
    "gn:feature_class":"P",
    "gn:feature_code":"PPL",
    "gn:name":"River Ridge Mobile Home Community",
    "gn:population":0,
    "gn:timezone":"America/Detroit",
    "iso:country":"US",
    "wof:name":"River Ridge Mobile Home Community",
    "wof:placetype":"campus"
},
  "geometry": {"coordinates":[-83.80278,42.15694000000001],"type":"Point"}
}