{
  "type": "Feature",
  "properties": {
    "gn:country":"US",
    "gn:fcode":"PPL",
    "gn:population":0,
    "iso:country":"US",
    "name:ceb_x_preferred":[
        "Stuart"
    ],
    "name:ces_x_preferred":[
        "Stuart"
    ],
    "name:deu_x_preferred":[
        "Stuart"
    ],
    "name:fin_x_preferred":[
        "Stuart"
    ],
    "name:fra_x_preferred":[
        "Stuart"
    ],
    "name:hrv_x_preferred":[
        "Stuart"
    ],
    "name:hun_x_preferred":[
        "Stuart"
    ],
    "name:ita_x_preferred":[
        "Stuart"
    ],
    "name:jpn_x_preferred":[
        "\u30b9\u30c6\u30e5\u30a2\u30fc\u30c8"
    ],
    "name:kor_x_preferred":[
        "\uc2a4\ud29c\uc5b4\ud2b8"
    ],
    "name:nld_x_preferred":[
        "Stuart"
    ],
    "name:nor_x_preferred":[
        "Stuart"
    ],
    "name:pol_x_preferred":[
        "Stuart"
    ],
    "name:por_x_preferred":[
        "Stuart"
    ],
    "name:spa_x_preferred":[
        "Stuart"
    ],
    "name:srp_x_preferred":[
        "\u0421\u0442\u0458\u0443\u0430\u0440\u0442"
    ],
    "name:swe_x_preferred":[
        "Stuart"
    ],
    "name:vol_x_preferred":[
        "Stuart"
    ],
    "name:zho_x_preferred":[
        "\u65af\u56fe\u4e9a\u7279"
    ],
    "qs_pg:aaroncc":"US",
    "qs_pg:gn_country":"US",
    "qs_pg:gn_fcode":"PPL",
    "qs_pg:gn_pop":0,
    "qs_pg:name":"Stuart",
    "qs_pg:name_adm0":"United States",
    "qs_pg:name_adm1":"California",
    "qs_pg:photos":103,
    "qs_pg:photos_1k":21,
    "qs_pg:photos_9k":1,
    "qs_pg:photos_9r":3,
    "qs_pg:photos_all":103,
    "qs_pg:photos_sr":3,
    "qs_pg:pop_sr":0,
    "qs_pg:qs_pg_placetype":"locality",
    "qs_pg:qs_pg_placetype_gp":"Town",
    "qs_pg:woe_adm0":23424977,
    "woe:adm0_id":23424977,
    "woe:name_adm0":"United States",
    "woe:name_adm1":"California",
    "woe:placetype":"Town",
    "wof:name":"Stuart",
    "wof:placetype":"locality"
},
  "geometry": {"coordinates":[-117.42086999999999,33.25115],"type":"Point"}
}