{
  "type": "Feature",
  "properties": {
    "gn:country":"US",
    "gn:fcode":"PPL",
    "gn:population":0,
    "iso:country":"US",
    "qs_pg:aaroncc":"US",
    "qs_pg:gn_country":"US",
    "qs_pg:gn_fcode":"PPL",
    "qs_pg:gn_pop":0,
    "qs_pg:name":"Plantation Heights",
    "qs_pg:name_adm0":"United States",
    "qs_pg:name_adm1":"Virginia",
    "qs_pg:photos":18,
    "qs_pg:photos_1k":4,
    "qs_pg:photos_9k":1,
    "qs_pg:photos_9r":1,
    "qs_pg:photos_all":18,
    "qs_pg:photos_sr":1,
    "qs_pg:pop_sr":0,
    "qs_pg:qs_pg_placetype":"locality",
    "qs_pg:qs_pg_placetype_gp":"Town",
    "qs_pg:woe_adm0":23424977,
    "woe:adm0_id":23424977,
    "woe:name_adm0":"United States",
    "woe:name_adm1":"Virginia",
    "woe:placetype":"Town",
    "wof:name":"Plantation Heights",
    "wof:placetype":"locality"
},
  "geometry": {"coordinates":[-76.71107000000001,37.29209],"type":"Point"}
}