{
  "type": "Feature",
  "properties": {
    "gn:elevation":20,
    "iso:country":"US",
    "name:eng_x_preferred":[
        "North Duxbury"
    ],
    "name:eng_x_variant":[
        "N Duxbury"
    ],
    "name:und_x_variant":[
        "North Duxbury Station"
    ],
    "qs:gn_adm0_cc":"US",
    "qs:gn_fcode":"PPL",
    "qs:gn_local":4935211,
    "qs:gn_nam_loc":"Duxbury, Plymouth, Massachusetts, US",
    "qs:gn_namadm1":"MA",
    "qs:gn_name":"North Duxbury",
    "qs:local_max":604,
    "qs:local_sum":840,
    "qs:localhoods":3,
    "qs:name":"North Duxbury",
    "qs:name_adm0":"United States",
    "qs:name_adm1":"Massachusetts",
    "qs:name_adm2":"Plymouth",
    "qs:name_local":"Duxbury",
    "qs:photo_max":15,
    "qs:photo_sum":25,
    "qs:placetype":"Suburb",
    "qs:quad_count":6,
    "qs:woe_adm0":23424977,
    "qs:woe_adm1":2347580,
    "qs:woe_adm2":12588711,
    "qs:woe_lau":0,
    "qs:woe_local":2394878,
    "qs:woe_ver":"7.10.0",
    "wof:lang":[
        "eng"
    ],
    "wof:name":"North Duxbury",
    "wof:placetype":"neighbourhood",
    "wof:population":2259,
    "zs:blockids":[
        250235071041023,
        250235071041027,
        250235071041041,
        250235062031030,
        250235062031023,
        250235062021000,
        250235071041012,
        250235062021006,
        250235071042002,
        250235071041032,
        250235062021007,
        250235062021009,
        250235071041011,
        250235062021012,
        250235062031020,
        250235062031025,
        250235062021013,
        250235061014033,
        250235062021028,
        250235071042006,
        250235071041034,
        250235062021005,
        250235071041028,
        250235071041024,
        250235062021026,
        250235062021030,
        250235062021011,
        250235062021031,
        250235071042000,
        250235062021029,
        250235071041025,
        250235071041026,
        250235062021003,
        250235062031022,
        250235062021008,
        250235062021002,
        250235062021010,
        250235071013023,
        250235071042003,
        250235071041033,
        250235062031021,
        250235062021004,
        250235071041010,
        250235062021001,
        250235062021014
    ],
    "zs:housing10":902,
    "zs:pop10":2259
},
  "geometry": {"coordinates":[-70.712512,42.08689],"type":"Point"}
}