{
  "type": "Feature",
  "properties": {
    "gn:admin1_code":"MI",
    "gn:admin2_code":"93.0",
    "gn:admin3_code":"81240.0",
    "gn:asciiname":"Williamsville",
    "gn:country_code":"US",
    "gn:dem":281,
    "gn:elevation":"280.0",
    "gn:feature_class":"P",
    "gn:feature_code":"PPL",
    "gn:name":"Williamsville",
    "gn:population":0,
    "gn:timezone":"America/Detroit",
    "iso:country":"US",
    "name:cat_x_preferred":[
        "Williamsville"
    ],
    "name:ceb_x_preferred":[
        "Williamsville"
    ],
    "name:deu_x_preferred":[
        "Williamsville"
    ],
    "name:fra_x_preferred":[
        "Williamsville"
    ],
    "name:ido_x_preferred":[
        "Williamsville"
    ],
    "name:ita_x_preferred":[
        "Williamsville"
    ],
    "name:nld_x_preferred":[
        "Williamsville"
    ],
    "name:pol_x_preferred":[
        "Williamsville"
    ],
    "name:rus_x_preferred":[
        "\u0423\u0438\u043b\u044c\u044f\u043c\u0441\u0432\u0438\u043b\u043b"
    ],
    "name:srp_x_preferred":[
        "\u0412\u0438\u043b\u0438\u0458\u0430\u043c\u0441\u0432\u0438\u043b"
    ],
    "name:vol_x_preferred":[
        "Williamsville"
    ],
    "wof:name":"Williamsville",
    "wof:placetype":"locality"
},
  "geometry": {"coordinates":[-84.09662,42.43892],"type":"Point"}
}