{
  "type": "Feature",
  "properties": {
    "gn:admin1_code":"KS",
    "gn:admin2_code":"97",
    "gn:admin3_code":"37185.0",
    "gn:asciiname":"Wellsford",
    "gn:country_code":"US",
    "gn:dem":653,
    "gn:elevation":"645.0",
    "gn:feature_class":"P",
    "gn:feature_code":"PPL",
    "gn:name":"Wellsford",
    "gn:population":0,
    "gn:timezone":"America/Chicago",
    "iso:country":"US",
    "name:eng_x_preferred":[
        "Wellsford"
    ],
    "name:und_x_variant":[
        "Dowell",
        "McDowell"
    ],
    "wof:name":"Wellsford",
    "wof:placetype":"locality"
},
  "geometry": {"coordinates":[-99.02871,37.61669000000001],"type":"Point"}
}