{
  "type": "Feature",
  "properties": {
    "gn:admin1_code":"VA",
    "gn:admin2_code":"131",
    "gn:asciiname":"Hideaway Cove",
    "gn:country_code":"US",
    "gn:dem":12,
    "gn:elevation":"5.0",
    "gn:feature_class":"P",
    "gn:feature_code":"PPL",
    "gn:name":"Hideaway Cove",
    "gn:population":0,
    "gn:timezone":"America/New_York",
    "iso:country":"US",
    "wof:name":"Hideaway Cove",
    "wof:placetype":"locality"
},
  "geometry": {"coordinates":[-75.94270999999998,37.48458],"type":"Point"}
}