{
  "type": "Feature",
  "properties": {
    "gn:admin1_code":"TX",
    "gn:admin2_code":"29",
    "gn:asciiname":"Garza Crossing",
    "gn:country_code":"US",
    "gn:dem":169,
    "gn:elevation":"162.0",
    "gn:feature_class":"P",
    "gn:feature_code":"PPL",
    "gn:name":"Garza Crossing",
    "gn:population":0,
    "gn:timezone":"America/Chicago",
    "iso:country":"US",
    "wof:name":"Garza Crossing",
    "wof:placetype":"locality"
},
  "geometry": {"coordinates":[-98.61391,29.28329],"type":"Point"}
}