{
  "type": "Feature",
  "properties": {
    "gn:country":"US",
    "gn:fcode":"PPL",
    "gn:population":0,
    "iso:country":"US",
    "name:azb_x_preferred":[
        "\u067e\u062a\u06cc\u0642\u0631\u06cc\u0648"
    ],
    "name:eng_x_preferred":[
        "Pettigrew"
    ],
    "name:fas_x_preferred":[
        "\u067e\u062a\u06cc\u06af\u0631\u0648"
    ],
    "name:fra_x_preferred":[
        "Pettigrew"
    ],
    "name:zho_x_preferred":[
        "\u4f69\u8482\u683c\u9b6f"
    ],
    "qs_pg:aaroncc":"US",
    "qs_pg:gn_country":"US",
    "qs_pg:gn_fcode":"PPL",
    "qs_pg:gn_pop":0,
    "qs_pg:name":"Pettigrew",
    "qs_pg:name_adm0":"United States",
    "qs_pg:name_adm1":"Arkansas",
    "qs_pg:photos":7,
    "qs_pg:photos_1k":1,
    "qs_pg:photos_9k":1,
    "qs_pg:photos_9r":1,
    "qs_pg:photos_all":7,
    "qs_pg:photos_sr":1,
    "qs_pg:pop_sr":5,
    "qs_pg:qs_pg_placetype":"locality",
    "qs_pg:qs_pg_placetype_gp":"Town",
    "qs_pg:woe_adm0":23424977,
    "woe:adm0_id":23424977,
    "woe:name_adm0":"United States",
    "woe:name_adm1":"Arkansas",
    "woe:placetype":"Town",
    "wof:name":"Pettigrew",
    "wof:placetype":"locality"
},
  "geometry": {"coordinates":[-93.64852,35.81786],"type":"Point"}
}