{
  "type": "Feature",
  "properties": {
    "gn:admin1_code":"NC",
    "gn:admin2_code":"153",
    "gn:admin3_code":"93116.0",
    "gn:asciiname":"Capels Mill",
    "gn:country_code":"US",
    "gn:dem":111,
    "gn:elevation":"107.0",
    "gn:feature_class":"P",
    "gn:feature_code":"PPL",
    "gn:name":"Capels Mill",
    "gn:population":0,
    "gn:timezone":"America/New_York",
    "iso:country":"US",
    "wof:name":"Capels Mill",
    "wof:placetype":"locality"
},
  "geometry": {"coordinates":[-79.79616,35.15598],"type":"Point"}
}