{
  "type": "Feature",
  "properties": {
    "gn:admin1_code":"MD",
    "gn:admin2_code":"21.0",
    "gn:asciiname":"Briercrest Heights",
    "gn:country_code":"US",
    "gn:dem":173,
    "gn:elevation":"175.0",
    "gn:feature_class":"P",
    "gn:feature_code":"PPL",
    "gn:name":"Briercrest Heights",
    "gn:population":0,
    "gn:timezone":"America/New_York",
    "iso:country":"US",
    "wof:name":"Briercrest Heights",
    "wof:placetype":"locality"
},
  "geometry": {"coordinates":[-77.53499000000002,39.36816],"type":"Point"}
}