{
  "type": "Feature",
  "properties": {
    "gn:admin1_code":"IN",
    "gn:admin2_code":"63.0",
    "gn:admin3_code":"13078.0",
    "gn:asciiname":"Reno",
    "gn:country_code":"US",
    "gn:dem":280,
    "gn:elevation":"278.0",
    "gn:feature_class":"P",
    "gn:feature_code":"PPL",
    "gn:name":"Reno",
    "gn:population":0,
    "gn:timezone":"America/Indiana/Indianapolis",
    "iso:country":"US",
    "wof:name":"Reno",
    "wof:placetype":"locality"
},
  "geometry": {"coordinates":[-86.67028000000001,39.71032],"type":"Point"}
}