{
  "type": "Feature",
  "properties": {
    "gn:country":"US",
    "gn:fcode":"PPL",
    "gn:population":0,
    "iso:country":"US",
    "name:cym_x_preferred":[
        "Institute"
    ],
    "name:eng_x_preferred":[
        "Institute"
    ],
    "name:fas_x_preferred":[
        "\u0627\u06cc\u0646\u0633\u062a\u06cc\u062a\u06cc\u0648\u062a"
    ],
    "name:fra_x_preferred":[
        "Institute"
    ],
    "name:lld_x_preferred":[
        "Institute"
    ],
    "name:vol_x_preferred":[
        "Institute"
    ],
    "qs_pg:aaroncc":"US",
    "qs_pg:gn_country":"US",
    "qs_pg:gn_fcode":"PPL",
    "qs_pg:gn_pop":0,
    "qs_pg:name":"Institute",
    "qs_pg:name_adm0":"United States",
    "qs_pg:name_adm1":"West Virginia",
    "qs_pg:photos":353,
    "qs_pg:photos_1k":72,
    "qs_pg:photos_9k":2,
    "qs_pg:photos_9r":5,
    "qs_pg:photos_all":353,
    "qs_pg:photos_sr":6,
    "qs_pg:pop_sr":0,
    "qs_pg:qs_pg_placetype":"locality",
    "qs_pg:qs_pg_placetype_gp":"Town",
    "qs_pg:woe_adm0":23424977,
    "woe:adm0_id":23424977,
    "woe:name_adm0":"United States",
    "woe:name_adm1":"West Virginia",
    "woe:placetype":"Town",
    "wof:name":"Institute",
    "wof:placetype":"locality"
},
  "geometry": {"coordinates":[-81.76541,38.38371],"type":"Point"}
}