{
  "type": "Feature",
  "properties": {
    "gn:admin1_code":"CT",
    "gn:admin2_code":"11.0",
    "gn:admin3_code":"66210.0",
    "gn:asciiname":"Milestone Corner",
    "gn:country_code":"US",
    "gn:dem":173,
    "gn:elevation":"171.0",
    "gn:feature_class":"P",
    "gn:feature_code":"PPL",
    "gn:name":"Milestone Corner",
    "gn:population":0,
    "gn:timezone":"America/New_York",
    "iso:country":"US",
    "wof:name":"Milestone Corner",
    "wof:placetype":"locality"
},
  "geometry": {"coordinates":[-72.2748,41.5151],"type":"Point"}
}