{
  "type": "Feature",
  "properties": {
    "iso:country":"US",
    "name:eng_x_preferred":[
        "Blair Mill Village"
    ],
    "wof:name":"Blair Mill Village",
    "wof:placetype":"neighbourhood",
    "wof:population":837,
    "zs:area_m":255689.494019,
    "zs:blockids":[
        420912003012018,
        420912005021007
    ],
    "zs:housing10":638,
    "zs:label":"Blair Mill Village",
    "zs:pop10":837
},
  "geometry": {"coordinates":[-75.119652,40.181921],"type":"Point"}
}