{
  "type": "Feature",
  "properties": {
    "iso:country":"US",
    "name:eng_x_preferred":[
        "Dimple Dell Ranchettes"
    ],
    "wof:name":"Dimple Dell Ranchettes",
    "wof:placetype":"neighbourhood",
    "wof:population":937,
    "zs:area_m":808930.902859,
    "zs:blockids":[
        490351128142020,
        490351128141006,
        490351128142015,
        490351128142021,
        490351128142016,
        490351128142017,
        490351128142019,
        490351128142022,
        490351128142023,
        490351128142018
    ],
    "zs:housing10":287,
    "zs:label":"Dimple Dell Ranchettes",
    "zs:pop10":937
},
  "geometry": {"coordinates":[-111.824277,40.554527],"type":"Point"}
}