{
  "type": "Feature",
  "properties": {
    "gn:admin1_code":"KY",
    "gn:admin2_code":"127",
    "gn:asciiname":"Georges Creek",
    "gn:country_code":"US",
    "gn:dem":174,
    "gn:elevation":"177.0",
    "gn:feature_class":"P",
    "gn:feature_code":"PPL",
    "gn:name":"Georges Creek",
    "gn:population":0,
    "gn:timezone":"America/New_York",
    "iso:country":"US",
    "name:ceb_x_preferred":[
        "Georges Creek"
    ],
    "name:deu_x_preferred":[
        "Georges Creek"
    ],
    "name:swe_x_preferred":[
        "Georges Creek"
    ],
    "wof:name":"Georges Creek",
    "wof:placetype":"locality"
},
  "geometry": {"coordinates":[-82.65655,37.97787],"type":"Point"}
}