{
  "type": "Feature",
  "properties": {
    "gn:admin1_code":"UT",
    "gn:admin2_code":"11.0",
    "gn:asciiname":"Lupine Village",
    "gn:country_code":"US",
    "gn:dem":1312,
    "gn:elevation":"1308.0",
    "gn:feature_class":"P",
    "gn:feature_code":"PPL",
    "gn:name":"Lupine Village",
    "gn:population":0,
    "gn:timezone":"America/Denver",
    "iso:country":"US",
    "wof:name":"Lupine Village",
    "wof:placetype":"locality"
},
  "geometry": {"coordinates":[-111.90494,41.00217],"type":"Point"}
}