{
  "type": "Feature",
  "properties": {
    "gn:admin1_code":"MO",
    "gn:admin2_code":"183.0",
    "gn:admin3_code":"78448.0",
    "gn:asciiname":"Crystal Creek",
    "gn:country_code":"US",
    "gn:dem":176,
    "gn:elevation":"176.0",
    "gn:feature_class":"P",
    "gn:feature_code":"PPL",
    "gn:name":"Crystal Creek",
    "gn:population":0,
    "gn:timezone":"America/Chicago",
    "iso:country":"US",
    "name:ara_x_preferred":[
        "\u0643\u0631\u064a\u0633\u062a\u0627\u0644"
    ],
    "wof:name":"Crystal Creek",
    "wof:placetype":"locality"
},
  "geometry": {"coordinates":[-90.87163,38.82845],"type":"Point"}
}