{
  "type": "Feature",
  "properties": {
    "gn:admin1_code":"KS",
    "gn:admin2_code":"161.0",
    "gn:admin3_code":"44275.0",
    "gn:asciiname":"Fairmont",
    "gn:country_code":"US",
    "gn:dem":313,
    "gn:elevation":"308.0",
    "gn:feature_class":"P",
    "gn:feature_code":"PPL",
    "gn:name":"Fairmont",
    "gn:population":0,
    "gn:timezone":"America/Chicago",
    "iso:country":"US",
    "name:cat_x_preferred":[
        "Fairmont"
    ],
    "name:ceb_x_preferred":[
        "Fairmont"
    ],
    "name:deu_x_preferred":[
        "Fairmont"
    ],
    "name:fas_x_preferred":[
        "\u0641\u06cc\u0631\u0645\u0648\u0646\u062a"
    ],
    "name:fra_x_preferred":[
        "Fairmont"
    ],
    "name:ido_x_preferred":[
        "Fairmont"
    ],
    "name:ita_x_preferred":[
        "Fairmont"
    ],
    "name:jpn_x_preferred":[
        "\u30d5\u30a7\u30a2\u30e2\u30f3\u30c8"
    ],
    "name:nld_x_preferred":[
        "Fairmont"
    ],
    "name:pol_x_preferred":[
        "Fairmont"
    ],
    "name:por_x_preferred":[
        "Fairmont"
    ],
    "name:rus_x_preferred":[
        "\u0424\u044d\u0440\u043c\u043e\u043d\u0442"
    ],
    "name:srp_x_preferred":[
        "\u0424\u0435\u0440\u043c\u043e\u043d\u0442"
    ],
    "name:swe_x_preferred":[
        "Fairmont"
    ],
    "name:ukr_x_preferred":[
        "\u0424\u0435\u0439\u0440\u043c\u043e\u043d\u0442"
    ],
    "name:vol_x_preferred":[
        "Fairmont"
    ],
    "wof:name":"Fairmont",
    "wof:placetype":"locality"
},
  "geometry": {"coordinates":[-96.54889,39.17694],"type":"Point"}
}