{
  "type": "Feature",
  "properties": {
    "gn:admin1_code":"OH",
    "gn:admin2_code":"49.0",
    "gn:admin3_code":"18000.0",
    "gn:asciiname":"Heritage Farms",
    "gn:country_code":"US",
    "gn:dem":283,
    "gn:elevation":"286.0",
    "gn:feature_class":"P",
    "gn:feature_code":"PPL",
    "gn:name":"Heritage Farms",
    "gn:population":0,
    "gn:timezone":"America/New_York",
    "iso:country":"US",
    "wof:name":"Heritage Farms",
    "wof:placetype":"locality"
},
  "geometry": {"coordinates":[-83.16807,40.00966],"type":"Point"}
}