{
  "type": "Feature",
  "properties": {
    "gn:admin1_code":"IN",
    "gn:admin2_code":"121.0",
    "gn:admin3_code":"62622.0",
    "gn:asciiname":"Minshall",
    "gn:country_code":"US",
    "gn:dem":170,
    "gn:elevation":"167.0",
    "gn:feature_class":"P",
    "gn:feature_code":"PPL",
    "gn:name":"Minshall",
    "gn:population":0,
    "gn:timezone":"America/Indiana/Indianapolis",
    "iso:country":"US",
    "name:eng_x_preferred":[
        "Minshall"
    ],
    "name:und_x_variant":[
        "Minchel",
        "Odd"
    ],
    "wof:name":"Minshall",
    "wof:placetype":"locality"
},
  "geometry": {"coordinates":[-87.22168000000001,39.67171],"type":"Point"}
}