{
  "type": "Feature",
  "properties": {
    "gn:admin1_code":"KY",
    "gn:admin2_code":"47",
    "gn:asciiname":"Bluff Spring",
    "gn:country_code":"US",
    "gn:dem":176,
    "gn:elevation":"176.0",
    "gn:feature_class":"P",
    "gn:feature_code":"PPL",
    "gn:name":"Bluff Spring",
    "gn:population":0,
    "gn:timezone":"America/Chicago",
    "iso:country":"US",
    "wof:name":"Bluff Spring",
    "wof:placetype":"locality"
},
  "geometry": {"coordinates":[-87.31471999999999,37.00504],"type":"Point"}
}