{
  "type": "Feature",
  "properties": {
    "iso:country":"US",
    "name:eng_x_preferred":[
        "La Mirada Landmark"
    ],
    "name:eng_x_variant":[
        "Lamirada Landmark"
    ],
    "qs:gn_adm0_cc":"US",
    "qs:gn_local":5364007,
    "qs:gn_nam_loc":"La Mirada, Los Angeles, California, US",
    "qs:gn_namadm1":"CA",
    "qs:local_max":448,
    "qs:local_sum":1383,
    "qs:localhoods":4,
    "qs:name":"La Mirada Landmark",
    "qs:name_adm0":"United States",
    "qs:name_adm1":"California",
    "qs:name_adm2":"Los Angeles",
    "qs:name_local":"La Mirada",
    "qs:photo_max":240,
    "qs:photo_sum":448,
    "qs:placetype":"Suburb",
    "qs:quad_count":20,
    "qs:woe_adm0":23424977,
    "qs:woe_adm1":2347563,
    "qs:woe_adm2":12587688,
    "qs:woe_lau":0,
    "qs:woe_local":2434280,
    "qs:woe_ver":"7.10.0",
    "wof:lang":[
        "eng"
    ],
    "wof:name":"La Mirada Landmark",
    "wof:placetype":"neighbourhood",
    "wof:population":5764,
    "zs:blockids":[
        60375038011009,
        60375038021006,
        60375038011007,
        60375037033009,
        60375038011004,
        60375036022030,
        60375038011000,
        60375038011017,
        60375038023002,
        60375038021002,
        60375038021004,
        60375038022003,
        60375038011014,
        60375038013002,
        60375036022034,
        60375038011013,
        60375036022028,
        60375038011015,
        60375038012007,
        60375038012006,
        60375038023003,
        60375038021001,
        60375038021011,
        60375038011011,
        60375038011001,
        60375038021007,
        60375036022035,
        60375038011020,
        60375038011016,
        60375036022031,
        60375038012004,
        60375038012005,
        60375038023000,
        60375038011005,
        60375038011010,
        60375036022016,
        60375036022032,
        60375038011002,
        60375038011022,
        60375038011018,
        60375038011019,
        60375038021008,
        60375037033006,
        60375038021003,
        60375038013000,
        60375038013003,
        60375038012010,
        60375037033022,
        60375036022014,
        60375038012001,
        60375038012011,
        60375038023005,
        60375037033011,
        60375038014001,
        60375038012003,
        60375036022025,
        60375037033008,
        60375038012009,
        60375038012000,
        60375038021000,
        60375038021005,
        60375038012002,
        60375038013001,
        60375038011006,
        60375037033018,
        60375038011012,
        60375037033007,
        60375036022015,
        60375038012008,
        60375036022027,
        60375038023001,
        60375038022000,
        60375037033021,
        60375037033010,
        60375038013005,
        60375038013004,
        60375038011008,
        60375038011003,
        60375038011021
    ],
    "zs:housing10":2019,
    "zs:pop10":5764
},
  "geometry": {"coordinates":[-118.003338,33.904908],"type":"Point"}
}