{
  "type": "Feature",
  "properties": {
    "gn:admin1_code":"VA",
    "gn:admin2_code":"63",
    "gn:asciiname":"Poff",
    "gn:country_code":"US",
    "gn:dem":755,
    "gn:elevation":"755.0",
    "gn:feature_class":"P",
    "gn:feature_code":"PPL",
    "gn:name":"Poff",
    "gn:population":0,
    "gn:timezone":"America/New_York",
    "iso:country":"US",
    "wof:name":"Poff",
    "wof:placetype":"locality"
},
  "geometry": {"coordinates":[-80.31310000000001,36.93791],"type":"Point"}
}