{
  "type": "Feature",
  "properties": {
    "gn:admin1_code":"LA",
    "gn:admin2_code":"15.0",
    "gn:asciiname":"Fillmore",
    "gn:country_code":"US",
    "gn:dem":88,
    "gn:elevation":"85.0",
    "gn:feature_class":"P",
    "gn:feature_code":"PPL",
    "gn:name":"Fillmore",
    "gn:population":0,
    "gn:timezone":"America/Chicago",
    "iso:country":"US",
    "wof:name":"Fillmore",
    "wof:placetype":"locality"
},
  "geometry": {"coordinates":[-93.51517,32.56293],"type":"Point"}
}