{
  "type": "Feature",
  "properties": {
    "gn:admin1_code":"WY",
    "gn:admin2_code":"17.0",
    "gn:asciiname":"Red Lane",
    "gn:country_code":"US",
    "gn:dem":1316,
    "gn:elevation":"1315.0",
    "gn:feature_class":"P",
    "gn:feature_code":"PPL",
    "gn:name":"Red Lane",
    "gn:population":0,
    "gn:timezone":"America/Denver",
    "iso:country":"US",
    "name:fra_x_preferred":[
        "Red Lane"
    ],
    "wof:name":"Red Lane",
    "wof:placetype":"locality"
},
  "geometry": {"coordinates":[-108.20593,43.67857],"type":"Point"}
}