{
  "type": "Feature",
  "properties": {
    "gn:admin1_code":"SC",
    "gn:admin2_code":"23.0",
    "gn:asciiname":"Caldwell Crossroad",
    "gn:country_code":"US",
    "gn:dem":142,
    "gn:elevation":"138.0",
    "gn:feature_class":"P",
    "gn:feature_code":"PPL",
    "gn:name":"Caldwell Crossroad",
    "gn:population":0,
    "gn:timezone":"America/New_York",
    "iso:country":"US",
    "name:eng_x_preferred":[
        "Caldwell Crossroad"
    ],
    "name:und_x_variant":[
        "Dewitt",
        "Caldwells Crossroads"
    ],
    "wof:name":"Caldwell Crossroad",
    "wof:placetype":"locality"
},
  "geometry": {"coordinates":[-80.97203,34.57375],"type":"Point"}
}