{
  "type": "Feature",
  "properties": {
    "gn:admin1_code":"KS",
    "gn:admin2_code":"103.0",
    "gn:admin3_code":"17450.0",
    "gn:asciiname":"Maltby",
    "gn:country_code":"US",
    "gn:dem":236,
    "gn:elevation":"230.0",
    "gn:feature_class":"P",
    "gn:feature_code":"PPL",
    "gn:name":"Maltby",
    "gn:population":0,
    "gn:timezone":"America/Chicago",
    "iso:country":"US",
    "name:ceb_x_preferred":[
        "Maltby"
    ],
    "name:deu_x_preferred":[
        "Maltby"
    ],
    "name:ita_x_preferred":[
        "Maltby"
    ],
    "name:nld_x_preferred":[
        "Maltby"
    ],
    "name:pol_x_preferred":[
        "Maltby"
    ],
    "name:por_x_preferred":[
        "Maltby"
    ],
    "name:swe_x_preferred":[
        "Maltby"
    ],
    "name:vol_x_preferred":[
        "Maltby"
    ],
    "wof:name":"Maltby",
    "wof:placetype":"locality"
},
  "geometry": {"coordinates":[-94.83635,39.21945],"type":"Point"}
}