{
  "type": "Feature",
  "properties": {
    "gn:country":"US",
    "gn:fcode":"PPL",
    "gn:population":0,
    "iso:country":"US",
    "name:eng_x_preferred":[
        "Borland"
    ],
    "name:fas_x_preferred":[
        "\u0628\u0648\u0631\u0644\u0646\u062f"
    ],
    "name:fra_x_preferred":[
        "Borland"
    ],
    "name:spa_x_preferred":[
        "Borland"
    ],
    "qs_pg:aaroncc":"US",
    "qs_pg:gn_country":"US",
    "qs_pg:gn_fcode":"PPL",
    "qs_pg:gn_pop":0,
    "qs_pg:name":"Borland",
    "qs_pg:name_adm0":"United States",
    "qs_pg:name_adm1":"West Virginia",
    "qs_pg:photos":13,
    "qs_pg:photos_1k":3,
    "qs_pg:photos_9k":1,
    "qs_pg:photos_9r":1,
    "qs_pg:photos_all":13,
    "qs_pg:photos_sr":1,
    "qs_pg:pop_sr":0,
    "qs_pg:qs_pg_placetype":"locality",
    "qs_pg:qs_pg_placetype_gp":"Town",
    "qs_pg:woe_adm0":23424977,
    "woe:adm0_id":23424977,
    "woe:name_adm0":"United States",
    "woe:name_adm1":"West Virginia",
    "woe:placetype":"Town",
    "wof:name":"Borland",
    "wof:placetype":"locality"
},
  "geometry": {"coordinates":[-81.28261999999999,39.29785],"type":"Point"}
}