{
  "type": "Feature",
  "properties": {
    "gn:admin1_code":"AZ",
    "gn:admin2_code":"13.0",
    "gn:asciiname":"Patrick Park",
    "gn:country_code":"US",
    "gn:dem":340,
    "gn:elevation":"343.0",
    "gn:feature_class":"P",
    "gn:feature_code":"PPL",
    "gn:name":"Patrick Park",
    "gn:population":0,
    "gn:timezone":"America/Phoenix",
    "iso:country":"US",
    "name:ara_x_preferred":[
        "\u0628\u0627\u062a\u0631\u064a\u0643 \u0628\u0627\u0631\u0643"
    ],
    "name:fin_x_preferred":[
        "Patrick Park"
    ],
    "name:por_x_preferred":[
        "Patrick Park"
    ],
    "name:swe_x_preferred":[
        "Patrick Park"
    ],
    "wof:name":"Patrick Park",
    "wof:placetype":"locality"
},
  "geometry": {"coordinates":[-112.02070000000001,33.39366],"type":"Point"}
}