{
  "type": "Feature",
  "properties": {
    "gn:admin1_code":"CA",
    "gn:admin2_code":"33.0",
    "gn:asciiname":"Whispering Pines",
    "gn:country_code":"US",
    "gn:dem":828,
    "gn:elevation":"805.0",
    "gn:feature_class":"P",
    "gn:feature_code":"PPL",
    "gn:name":"Whispering Pines",
    "gn:population":0,
    "gn:timezone":"America/Los_Angeles",
    "iso:country":"US",
    "name:zho_x_preferred":[
        "\u97cb\u65af\u5e15\u6797\u6d3e\u56e0\u65af"
    ],
    "wof:name":"Whispering Pines",
    "wof:placetype":"locality"
},
  "geometry": {"coordinates":[-122.71249,38.81351],"type":"Point"}
}