{
  "type": "Feature",
  "properties": {
    "gn:admin1_code":"FL",
    "gn:admin2_code":"57",
    "gn:asciiname":"Indian Hills",
    "gn:country_code":"US",
    "gn:dem":19,
    "gn:elevation":"14.0",
    "gn:feature_class":"P",
    "gn:feature_code":"PPL",
    "gn:name":"Indian Hills",
    "gn:population":0,
    "gn:timezone":"America/New_York",
    "iso:country":"US",
    "name:ceb_x_preferred":[
        "Indian Hills"
    ],
    "name:deu_x_preferred":[
        "Indian Hills"
    ],
    "name:ita_x_preferred":[
        "Indian Hills"
    ],
    "name:nld_x_preferred":[
        "Indian Hills"
    ],
    "name:pol_x_preferred":[
        "Indian Hills"
    ],
    "name:por_x_preferred":[
        "Indian Hills"
    ],
    "name:spa_x_preferred":[
        "Indian Hills"
    ],
    "name:srp_x_preferred":[
        "\u0418\u043d\u0434\u0438\u0458\u0430\u043d \u0425\u0438\u043b\u0441"
    ],
    "name:vol_x_preferred":[
        "Indian Hills"
    ],
    "wof:name":"Indian Hills",
    "wof:placetype":"locality"
},
  "geometry": {"coordinates":[-82.2754,27.866],"type":"Point"}
}