{
  "type": "Feature",
  "properties": {
    "gn:admin1_code":"NC",
    "gn:admin2_code":"153.0",
    "gn:admin3_code":"92736.0",
    "gn:asciiname":"Yates Hill",
    "gn:country_code":"US",
    "gn:dem":79,
    "gn:elevation":"76.0",
    "gn:feature_class":"P",
    "gn:feature_code":"PPL",
    "gn:name":"Yates Hill",
    "gn:population":0,
    "gn:timezone":"America/New_York",
    "iso:country":"US",
    "wof:name":"Yates Hill",
    "wof:placetype":"locality"
},
  "geometry": {"coordinates":[-79.79756,34.93488],"type":"Point"}
}