{
  "type": "Feature",
  "properties": {
    "gn:admin1_code":"NC",
    "gn:admin2_code":"83.0",
    "gn:admin3_code":"92432.0",
    "gn:asciiname":"Norfleet",
    "gn:country_code":"US",
    "gn:dem":14,
    "gn:elevation":"10.0",
    "gn:feature_class":"P",
    "gn:feature_code":"PPL",
    "gn:name":"Norfleet",
    "gn:population":0,
    "gn:timezone":"America/New_York",
    "iso:country":"US",
    "wof:name":"Norfleet",
    "wof:placetype":"locality"
},
  "geometry": {"coordinates":[-77.29858,36.1421],"type":"Point"}
}