{
  "type": "Feature",
  "properties": {
    "gn:elevation":1,
    "iso:country":"US",
    "name:cat_x_preferred":[
        "Velasco"
    ],
    "name:eng_x_preferred":[
        "Velasco"
    ],
    "name:glg_x_preferred":[
        "Velasco"
    ],
    "name:hun_x_preferred":[
        "Velasco"
    ],
    "name:ita_x_preferred":[
        "Velasco"
    ],
    "name:jpn_x_preferred":[
        "\u30f4\u30a7\u30e9\u30b9\u30b3"
    ],
    "name:nld_x_preferred":[
        "Velasco"
    ],
    "name:slk_x_preferred":[
        "Velasco"
    ],
    "name:spa_x_preferred":[
        "Velasco"
    ],
    "name:zho_x_preferred":[
        "\u97cb\u62c9\u65af\u79d1"
    ],
    "qs:gn_adm0_cc":"US",
    "qs:gn_fcode":"PPL",
    "qs:gn_local":4692355,
    "qs:gn_nam_loc":"Freeport, Brazoria, Texas, US",
    "qs:gn_namadm1":"TX",
    "qs:gn_name":"Velasco",
    "qs:local_max":671,
    "qs:local_sum":671,
    "qs:localhoods":1,
    "qs:name":"Velasco",
    "qs:name_adm0":"United States",
    "qs:name_adm1":"Texas",
    "qs:name_adm2":"Brazoria",
    "qs:name_local":"Freeport",
    "qs:photo_max":204,
    "qs:photo_sum":671,
    "qs:placetype":"Suburb",
    "qs:quad_count":26,
    "qs:woe_adm0":23424977,
    "qs:woe_adm1":2347602,
    "qs:woe_adm2":12590026,
    "qs:woe_lau":0,
    "qs:woe_local":2407347,
    "qs:woe_ver":"7.10.0",
    "wd:wordcount":1206,
    "wof:name":"Velasco",
    "wof:placetype":"neighbourhood"
},
  "geometry": {"coordinates":[-95.361447,28.952791],"type":"Point"}
}