{
  "type": "Feature",
  "properties": {
    "gn:admin1_code":"AZ",
    "gn:admin2_code":"13.0",
    "gn:asciiname":"Vistancia",
    "gn:country_code":"US",
    "gn:dem":428,
    "gn:elevation":"432.0",
    "gn:feature_class":"P",
    "gn:feature_code":"PPL",
    "gn:name":"Vistancia",
    "gn:population":0,
    "gn:timezone":"America/Phoenix",
    "iso:country":"US",
    "wof:name":"Vistancia",
    "wof:placetype":"locality"
},
  "geometry": {"coordinates":[-112.32808,33.75282],"type":"Point"}
}