{
  "type": "Feature",
  "properties": {
    "gn:admin1_code":"TX",
    "gn:admin2_code":"61.0",
    "gn:asciiname":"Ranchito",
    "gn:country_code":"US",
    "gn:dem":16,
    "gn:elevation":"14.0",
    "gn:feature_class":"P",
    "gn:feature_code":"PPL",
    "gn:name":"Ranchito",
    "gn:population":0,
    "gn:timezone":"America/Chicago",
    "iso:country":"US",
    "name:eng_x_preferred":[
        "Ranchito"
    ],
    "name:und_x_variant":[
        "Encantada",
        "Ranchita"
    ],
    "wof:name":"Ranchito",
    "wof:placetype":"locality"
},
  "geometry": {"coordinates":[-97.63027,26.02563],"type":"Point"}
}