{
  "type": "Feature",
  "properties": {
    "gn:elevation":318,
    "iso:country":"US",
    "name:eng_x_preferred":[
        "Palentown"
    ],
    "name:nld_x_preferred":[
        "Palentown"
    ],
    "name:vol_x_preferred":[
        "Palentown"
    ],
    "qs:gn_adm0_cc":"US",
    "qs:gn_fcode":"PPL",
    "qs:gn_local":5134099,
    "qs:gn_nam_loc":"Rochester, Ulster, New York, US",
    "qs:gn_namadm1":"NY",
    "qs:gn_name":"Palentown",
    "qs:local_max":168,
    "qs:local_sum":369,
    "qs:localhoods":3,
    "qs:name":"Palentown",
    "qs:name_adm0":"United States",
    "qs:name_adm1":"New York",
    "qs:name_adm2":"Ulster",
    "qs:name_local":"Rochester",
    "qs:photo_max":24,
    "qs:photo_sum":35,
    "qs:placetype":"Suburb",
    "qs:quad_count":3,
    "qs:woe_adm0":23424977,
    "qs:woe_adm1":2347591,
    "qs:woe_adm2":12589367,
    "qs:woe_lau":0,
    "qs:woe_local":28745009,
    "qs:woe_ver":"7.10.0",
    "wd:wordcount":242,
    "wof:lang":[
        "eng"
    ],
    "wof:name":"Palentown",
    "wof:placetype":"neighbourhood",
    "wof:population":196,
    "zs:blockids":[
        361119510003060,
        361119510003047,
        361119550003000
    ],
    "zs:housing10":120,
    "zs:pop10":196
},
  "geometry": {"coordinates":[-74.302499,41.889018],"type":"Point"}
}