{
  "type": "Feature",
  "properties": {
    "gn:admin1_code":"NC",
    "gn:admin2_code":"173.0",
    "gn:admin3_code":"91144.0",
    "gn:asciiname":"Proctor",
    "gn:country_code":"US",
    "gn:dem":545,
    "gn:elevation":"522.0",
    "gn:feature_class":"P",
    "gn:feature_code":"PPL",
    "gn:name":"Proctor",
    "gn:population":0,
    "gn:timezone":"America/New_York",
    "iso:country":"US",
    "wof:name":"Proctor",
    "wof:placetype":"locality"
},
  "geometry": {"coordinates":[-83.72628,35.47342000000001],"type":"Point"}
}