{
  "type": "Feature",
  "properties": {
    "gn:admin1_code":"SD",
    "gn:admin2_code":"31.0",
    "gn:admin3_code":"17745.0",
    "gn:asciiname":"Snake Creek",
    "gn:country_code":"US",
    "gn:dem":497,
    "gn:elevation":"500.0",
    "gn:feature_class":"P",
    "gn:feature_code":"PPL",
    "gn:name":"Snake Creek",
    "gn:population":0,
    "gn:timezone":"America/Denver",
    "iso:country":"US",
    "name:ceb_x_preferred":[
        "Snake Creek"
    ],
    "name:deu_x_preferred":[
        "Snake Creek"
    ],
    "name:swe_x_preferred":[
        "Snake Creek"
    ],
    "wof:name":"Snake Creek",
    "wof:placetype":"locality"
},
  "geometry": {"coordinates":[-100.58597,45.58472],"type":"Point"}
}