{
  "type": "Feature",
  "properties": {
    "gn:admin1_code":"MD",
    "gn:admin2_code":"31.0",
    "gn:asciiname":"Middlebrook Mobile Home Park",
    "gn:country_code":"US",
    "gn:dem":127,
    "gn:elevation":"118.0",
    "gn:feature_class":"P",
    "gn:feature_code":"PPL",
    "gn:name":"Middlebrook Mobile Home Park",
    "gn:population":0,
    "gn:timezone":"America/New_York",
    "iso:country":"US",
    "wof:name":"Middlebrook Mobile Home Park",
    "wof:placetype":"campus"
},
  "geometry": {"coordinates":[-77.23415,39.17872],"type":"Point"}
}