{
  "type": "Feature",
  "properties": {
    "gn:admin1_code":"OH",
    "gn:admin2_code":"101.0",
    "gn:admin3_code":"77742.0",
    "gn:asciiname":"Martel",
    "gn:country_code":"US",
    "gn:dem":316,
    "gn:elevation":"317.0",
    "gn:feature_class":"P",
    "gn:feature_code":"PPL",
    "gn:name":"Martel",
    "gn:population":0,
    "gn:timezone":"America/New_York",
    "iso:country":"US",
    "name:deu_x_preferred":[
        "Martel"
    ],
    "name:eng_x_preferred":[
        "Martel"
    ],
    "name:und_x_variant":[
        "Baker",
        "Tully City",
        "Three Locusts"
    ],
    "name:vol_x_preferred":[
        "Martel"
    ],
    "wof:name":"Martel",
    "wof:placetype":"locality"
},
  "geometry": {"coordinates":[-82.91018000000003,40.66895],"type":"Point"}
}