{
  "type": "Feature",
  "properties": {
    "gn:admin1_code":"NY",
    "gn:admin2_code":"89.0",
    "gn:admin3_code":"71410.0",
    "gn:asciiname":"Beechertown",
    "gn:country_code":"US",
    "gn:dem":168,
    "gn:elevation":"167.0",
    "gn:feature_class":"P",
    "gn:feature_code":"PPL",
    "gn:name":"Beechertown",
    "gn:population":0,
    "gn:timezone":"America/New_York",
    "iso:country":"US",
    "wof:name":"Beechertown",
    "wof:placetype":"locality"
},
  "geometry": {"coordinates":[-74.78853000000002,44.702],"type":"Point"}
}