{
  "type": "Feature",
  "properties": {
    "gn:admin1_code":"TN",
    "gn:admin2_code":"47",
    "gn:asciiname":"New Bethel",
    "gn:country_code":"US",
    "gn:dem":130,
    "gn:elevation":"124.0",
    "gn:feature_class":"P",
    "gn:feature_code":"PPL",
    "gn:name":"New Bethel",
    "gn:population":0,
    "gn:timezone":"America/Chicago",
    "iso:country":"US",
    "wof:name":"New Bethel",
    "wof:placetype":"locality"
},
  "geometry": {"coordinates":[-89.53452,35.09453],"type":"Point"}
}