{
  "type": "Feature",
  "properties": {
    "gn:admin1_code":"AZ",
    "gn:admin2_code":"7.0",
    "gn:asciiname":"Christmas",
    "gn:country_code":"US",
    "gn:dem":809,
    "gn:elevation":"815.0",
    "gn:feature_class":"P",
    "gn:feature_code":"PPL",
    "gn:name":"Christmas",
    "gn:population":0,
    "gn:timezone":"America/Phoenix",
    "iso:country":"US",
    "wof:name":"Christmas",
    "wof:placetype":"locality"
},
  "geometry": {"coordinates":[-110.74261,33.06229],"type":"Point"}
}