{
  "type": "Feature",
  "properties": {
    "gn:admin1_code":"MI",
    "gn:admin2_code":"121.0",
    "gn:admin3_code":"13840.0",
    "gn:asciiname":"Canada Corners",
    "gn:country_code":"US",
    "gn:dem":234,
    "gn:elevation":"234.0",
    "gn:feature_class":"P",
    "gn:feature_code":"PPL",
    "gn:name":"Canada Corners",
    "gn:population":0,
    "gn:timezone":"America/Detroit",
    "iso:country":"US",
    "wof:name":"Canada Corners",
    "wof:placetype":"locality"
},
  "geometry": {"coordinates":[-85.84921,43.2353],"type":"Point"}
}