{
  "type": "Feature",
  "properties": {
    "iso:country":"US",
    "name:ceb_x_preferred":[
        "The Hill"
    ],
    "name:deu_x_preferred":[
        "The Hill"
    ],
    "name:eng_x_preferred":[
        "The Hill"
    ],
    "name:ita_x_preferred":[
        "The Hill"
    ],
    "name:spa_x_preferred":[
        "The Hill"
    ],
    "name:swe_x_preferred":[
        "The Hill"
    ],
    "wof:name":"The Hill",
    "wof:placetype":"neighbourhood",
    "wof:population":343,
    "zs:area_m":263782.216412,
    "zs:blockids":[
        220330038025017,
        220330038025018,
        220330038025016,
        220330038051005,
        220330038041026
    ],
    "zs:housing10":175,
    "zs:label":"The Hill",
    "zs:pop10":343
},
  "geometry": {"coordinates":[-91.080933,30.415644],"type":"Point"}
}