{
  "type": "Feature",
  "properties": {
    "iso:country":"US",
    "name:eng_x_preferred":[
        "Centennial"
    ],
    "wd:wordcount":309,
    "wof:name":"Centennial",
    "wof:placetype":"neighbourhood",
    "wof:population":816,
    "zs:area_m":512341.347299,
    "zs:blockids":[
        180571103006105,
        180571103006097,
        180571103006096,
        180571103006107,
        180571103006094,
        180571103006095,
        180571103006145,
        180571103006098,
        180571103006111,
        180571103006106
    ],
    "zs:housing10":258,
    "zs:label":"Centennial",
    "zs:pop10":816
},
  "geometry": {"coordinates":[-86.168077,40.008277],"type":"Point"}
}