{
  "type": "Feature",
  "properties": {
    "gn:admin1_code":"TX",
    "gn:admin2_code":"115.0",
    "gn:asciiname":"Hindman",
    "gn:country_code":"US",
    "gn:dem":911,
    "gn:elevation":"913.0",
    "gn:feature_class":"P",
    "gn:feature_code":"PPL",
    "gn:name":"Hindman",
    "gn:population":0,
    "gn:timezone":"America/Chicago",
    "iso:country":"US",
    "wof:name":"Hindman",
    "wof:placetype":"locality"
},
  "geometry": {"coordinates":[-101.87821,32.88621],"type":"Point"}
}