{
  "type": "Feature",
  "properties": {
    "gn:admin1_code":"VA",
    "gn:admin2_code":"97",
    "gn:asciiname":"Powcan",
    "gn:country_code":"US",
    "gn:dem":51,
    "gn:elevation":"47.0",
    "gn:feature_class":"P",
    "gn:feature_code":"PPL",
    "gn:name":"Powcan",
    "gn:population":0,
    "gn:timezone":"America/New_York",
    "iso:country":"US",
    "name:eng_x_preferred":[
        "Powcan"
    ],
    "name:und_x_variant":[
        "Powan"
    ],
    "wof:name":"Powcan",
    "wof:placetype":"locality"
},
  "geometry": {"coordinates":[-76.94275,37.78236],"type":"Point"}
}