{
  "type": "Feature",
  "properties": {
    "gn:admin1_code":"FL",
    "gn:admin2_code":"57",
    "gn:asciiname":"Peeples Acres",
    "gn:country_code":"US",
    "gn:dem":27,
    "gn:elevation":"22.0",
    "gn:feature_class":"P",
    "gn:feature_code":"PPL",
    "gn:name":"Peeples Acres",
    "gn:population":0,
    "gn:timezone":"America/New_York",
    "iso:country":"US",
    "wof:name":"Peeples Acres",
    "wof:placetype":"locality"
},
  "geometry": {"coordinates":[-82.1816,27.9483],"type":"Point"}
}