{
  "type": "Feature",
  "properties": {
    "gn:admin1_code":"WV",
    "gn:admin2_code":"7",
    "gn:asciiname":"Dingy",
    "gn:country_code":"US",
    "gn:dem":286,
    "gn:elevation":"283.0",
    "gn:feature_class":"P",
    "gn:feature_code":"PPL",
    "gn:name":"Dingy",
    "gn:population":0,
    "gn:timezone":"America/New_York",
    "iso:country":"US",
    "wof:name":"Dingy",
    "wof:placetype":"locality"
},
  "geometry": {"coordinates":[-80.94677,38.65176],"type":"Point"}
}