{
  "type": "Feature",
  "properties": {
    "gn:admin1_code":"NC",
    "gn:admin2_code":"83.0",
    "gn:admin3_code":"91876.0",
    "gn:asciiname":"Roper Springs",
    "gn:country_code":"US",
    "gn:dem":108,
    "gn:elevation":"102.0",
    "gn:feature_class":"P",
    "gn:feature_code":"PPL",
    "gn:name":"Roper Springs",
    "gn:population":0,
    "gn:timezone":"America/New_York",
    "iso:country":"US",
    "name:eng_x_preferred":[
        "Roper Springs"
    ],
    "name:und_x_variant":[
        "Roper Spring"
    ],
    "wof:name":"Roper Springs",
    "wof:placetype":"locality"
},
  "geometry": {"coordinates":[-77.87304,36.42682],"type":"Point"}
}