{
  "type": "Feature",
  "properties": {
    "iso:country":"US",
    "name:eng_x_preferred":[
        "Bland Villa"
    ],
    "qs:gn_local":0,
    "qs:local_max":30,
    "qs:local_sum":30,
    "qs:localhoods":1,
    "qs:name":"Bland Villa",
    "qs:name_adm0":"United States",
    "qs:name_adm1":"Georgia",
    "qs:name_adm2":"Crisp",
    "qs:name_local":"Cordele",
    "qs:photo_max":14,
    "qs:photo_sum":30,
    "qs:placetype":"Suburb",
    "qs:quad_count":10,
    "qs:woe_adm0":23424977,
    "qs:woe_adm1":2347569,
    "qs:woe_adm2":12587909,
    "qs:woe_lau":0,
    "qs:woe_local":2384951,
    "qs:woe_ver":"7.10.0",
    "wof:lang":[
        "eng"
    ],
    "wof:name":"Bland Villa",
    "wof:placetype":"neighbourhood",
    "wof:population":301,
    "zs:blockids":[
        130810103001015,
        130810104002011,
        130810102014027,
        130810101001075,
        130810104003036,
        130810103001038,
        130810103001042,
        130810104002005,
        130810104002007,
        130810104005006,
        130810104002031,
        130810103001063,
        130810103001092,
        130810104002009
    ],
    "zs:housing10":133,
    "zs:pop10":301
},
  "geometry": {"coordinates":[-83.760498,31.960552],"type":"Point"}
}