{
  "type": "Feature",
  "properties": {
    "gn:admin1_code":"NC",
    "gn:admin2_code":"5",
    "gn:admin3_code":"91232.0",
    "gn:asciiname":"Edmonds",
    "gn:country_code":"US",
    "gn:dem":836,
    "gn:elevation":"840.0",
    "gn:feature_class":"P",
    "gn:feature_code":"PPL",
    "gn:name":"Edmonds",
    "gn:population":0,
    "gn:timezone":"America/New_York",
    "iso:country":"US",
    "name:ces_x_preferred":[
        "Edmonds"
    ],
    "name:deu_x_preferred":[
        "Edmonds"
    ],
    "name:fra_x_preferred":[
        "Edmonds"
    ],
    "name:nld_x_preferred":[
        "Edmonds"
    ],
    "name:rus_x_preferred":[
        "\u042d\u0434\u043c\u043e\u043d\u0434\u0441"
    ],
    "wof:name":"Edmonds",
    "wof:placetype":"locality"
},
  "geometry": {"coordinates":[-80.94341,36.56069],"type":"Point"}
}