{
  "type": "Feature",
  "properties": {
    "gn:admin1_code":"PA",
    "gn:admin2_code":"129.0",
    "gn:admin3_code":"72256.0",
    "gn:asciiname":"Mill Grove",
    "gn:country_code":"US",
    "gn:dem":274,
    "gn:elevation":"270.0",
    "gn:feature_class":"P",
    "gn:feature_code":"PPL",
    "gn:name":"Mill Grove",
    "gn:population":0,
    "gn:timezone":"America/New_York",
    "iso:country":"US",
    "wof:name":"Mill Grove",
    "wof:placetype":"locality"
},
  "geometry": {"coordinates":[-79.73976999999999,40.21257],"type":"Point"}
}