{
  "type": "Feature",
  "properties": {
    "gn:admin1_code":"OH",
    "gn:admin2_code":"81.0",
    "gn:admin3_code":"82698.0",
    "gn:asciiname":"Weems",
    "gn:country_code":"US",
    "gn:dem":300,
    "gn:elevation":"290.0",
    "gn:feature_class":"P",
    "gn:feature_code":"PPL",
    "gn:name":"Weems",
    "gn:population":0,
    "gn:timezone":"America/New_York",
    "iso:country":"US",
    "name:eng_x_preferred":[
        "Weems"
    ],
    "name:und_x_variant":[
        "Smithfield Station"
    ],
    "name:vol_x_preferred":[
        "Weems"
    ],
    "wof:name":"Weems",
    "wof:placetype":"locality"
},
  "geometry": {"coordinates":[-80.75425,40.28618],"type":"Point"}
}