{
  "type": "Feature",
  "properties": {
    "gn:admin1_code":"IL",
    "gn:admin2_code":"53.0",
    "gn:admin3_code":"58122.0",
    "gn:asciiname":"Perdueville",
    "gn:country_code":"US",
    "gn:dem":232,
    "gn:elevation":"234.0",
    "gn:feature_class":"P",
    "gn:feature_code":"PPL",
    "gn:name":"Perdueville",
    "gn:population":0,
    "gn:timezone":"America/Chicago",
    "iso:country":"US",
    "name:eng_x_preferred":[
        "Perdueville"
    ],
    "name:und_x_variant":[
        "Henderson Station"
    ],
    "wof:name":"Perdueville",
    "wof:placetype":"locality"
},
  "geometry": {"coordinates":[-88.17921,40.46559],"type":"Point"}
}