{
  "type": "Feature",
  "properties": {
    "gn:admin1_code":"VA",
    "gn:admin2_code":"53",
    "gn:asciiname":"Stony Springs",
    "gn:country_code":"US",
    "gn:dem":55,
    "gn:elevation":"57.0",
    "gn:feature_class":"P",
    "gn:feature_code":"PPL",
    "gn:name":"Stony Springs",
    "gn:population":0,
    "gn:timezone":"America/New_York",
    "iso:country":"US",
    "wof:name":"Stony Springs",
    "wof:placetype":"locality"
},
  "geometry": {"coordinates":[-77.56359999999999,37.05459000000001],"type":"Point"}
}