{
  "type": "Feature",
  "properties": {
    "iso:country":"US",
    "name:ceb_x_preferred":[
        "Point Breeze"
    ],
    "name:deu_x_preferred":[
        "Point Breeze"
    ],
    "name:eng_x_preferred":[
        "Point Breeze"
    ],
    "qs:gn_fcode":"PPLX",
    "qs:gn_local":0,
    "qs:gn_namadm1":"PA",
    "qs:gn_name":"Point Breeze",
    "qs:local_max":129,
    "qs:local_sum":205,
    "qs:localhoods":4,
    "qs:name":"Point Breeze",
    "qs:name_adm0":"United States",
    "qs:name_adm1":"New Jersey",
    "qs:name_adm2":"Hunterdon",
    "qs:name_local":"Kingwood",
    "qs:photo_max":45,
    "qs:photo_sum":129,
    "qs:placetype":"Suburb",
    "qs:quad_count":7,
    "qs:woe_adm0":23424977,
    "qs:woe_adm1":2347589,
    "qs:woe_adm2":12589267,
    "qs:woe_lau":0,
    "qs:woe_local":2432888,
    "qs:woe_ver":"7.10.0",
    "wd:wordcount":29,
    "wof:lang":[
        "eng"
    ],
    "wof:name":"Point Breeze",
    "wof:placetype":"neighbourhood",
    "wof:population":214,
    "zs:blockids":[
        340190107022034,
        340190116001001,
        340190107022035,
        340190107022032,
        340190115003058,
        340190116001002,
        340190107022033,
        340190115003037,
        340190115003033,
        340190116001004,
        340190116001005,
        340190107022036,
        340190115003038,
        340190113013012,
        340190116001007,
        340190116001003,
        340190115003039
    ],
    "zs:housing10":101,
    "zs:pop10":214
},
  "geometry": {"coordinates":[-74.947845,40.507462],"type":"Point"}
}