{
  "type": "Feature",
  "properties": {
    "gn:country":"US",
    "gn:fcode":"PPL",
    "gn:population":0,
    "iso:country":"US",
    "name:ceb_x_preferred":[
        "Belleview"
    ],
    "name:deu_x_preferred":[
        "Belleview"
    ],
    "name:pol_x_preferred":[
        "Belleview"
    ],
    "name:rus_x_preferred":[
        "\u0411\u0435\u043b\u044c\u0432\u044e"
    ],
    "name:srp_x_preferred":[
        "\u0411\u0435\u043b\u0432\u0458\u0443"
    ],
    "name:ukr_x_preferred":[
        "\u0411\u0435\u043b\u044c\u0432'\u044e"
    ],
    "qs_pg:aaroncc":"US",
    "qs_pg:gn_country":"US",
    "qs_pg:gn_fcode":"PPL",
    "qs_pg:gn_pop":0,
    "qs_pg:name":"Belleview",
    "qs_pg:name_adm0":"United States",
    "qs_pg:name_adm1":"Virginia",
    "qs_pg:photos":1251,
    "qs_pg:photos_1k":253,
    "qs_pg:photos_9k":6,
    "qs_pg:photos_9r":7,
    "qs_pg:photos_all":1251,
    "qs_pg:photos_sr":12,
    "qs_pg:pop_sr":0,
    "qs_pg:qs_pg_placetype":"locality",
    "qs_pg:qs_pg_placetype_gp":"Town",
    "qs_pg:woe_adm0":23424977,
    "woe:adm0_id":23424977,
    "woe:name_adm0":"United States",
    "woe:name_adm1":"Virginia",
    "woe:placetype":"Town",
    "wof:name":"Belleview",
    "wof:placetype":"locality"
},
  "geometry": {"coordinates":[-77.23998,38.96094],"type":"Point"}
}