{
  "type": "Feature",
  "properties": {
    "iso:country":"US",
    "name:eng_x_preferred":[
        "Shamburg"
    ],
    "wof:name":"Shamburg",
    "wof:placetype":"neighbourhood",
    "zs:area_m":2893682.09863,
    "zs:blockids":[
        420311605003004,
        420311605003136,
        420311604001104
    ],
    "zs:housing10":1,
    "zs:label":"Shamburg",
    "zs:pop10":0
},
  "geometry": {"coordinates":[-79.442742,41.181639],"type":"Point"}
}