{
  "type": "Feature",
  "properties": {
    "gn:admin1_code":"LA",
    "gn:admin2_code":"33.0",
    "gn:asciiname":"Lafitte Hill",
    "gn:country_code":"US",
    "gn:dem":14,
    "gn:elevation":"7.0",
    "gn:feature_class":"P",
    "gn:feature_code":"PPL",
    "gn:name":"Lafitte Hill",
    "gn:population":0,
    "gn:timezone":"America/Chicago",
    "iso:country":"US",
    "wof:name":"Lafitte Hill",
    "wof:placetype":"locality"
},
  "geometry": {"coordinates":[-91.06037999999999,30.34519],"type":"Point"}
}