{
  "type": "Feature",
  "properties": {
    "gn:admin1_code":"OH",
    "gn:admin2_code":"157.0",
    "gn:admin3_code":"15574.0",
    "gn:asciiname":"Lock Seventeen",
    "gn:country_code":"US",
    "gn:dem":252,
    "gn:elevation":"252.0",
    "gn:feature_class":"P",
    "gn:feature_code":"PPL",
    "gn:name":"Lock Seventeen",
    "gn:population":0,
    "gn:timezone":"America/New_York",
    "iso:country":"US",
    "name:eng_x_preferred":[
        "Lock Seventeen"
    ],
    "name:und_x_variant":[
        "Lock Number Seventeen",
        "Seventeen"
    ],
    "wof:name":"Lock Seventeen",
    "wof:placetype":"locality"
},
  "geometry": {"coordinates":[-81.45567,40.35618],"type":"Point"}
}