{
  "type": "Feature",
  "properties": {
    "gn:admin1_code":"IA",
    "gn:admin2_code":"13.0",
    "gn:admin3_code":"91128.0",
    "gn:asciiname":"Big Rock",
    "gn:country_code":"US",
    "gn:dem":290,
    "gn:elevation":"287.0",
    "gn:feature_class":"P",
    "gn:feature_code":"PPL",
    "gn:name":"Big Rock",
    "gn:population":0,
    "gn:timezone":"America/Chicago",
    "iso:country":"US",
    "name:ceb_x_preferred":[
        "Big Rock"
    ],
    "name:deu_x_preferred":[
        "Big Rock"
    ],
    "name:pol_x_preferred":[
        "Big Rock"
    ],
    "name:swe_x_preferred":[
        "Big Rock"
    ],
    "name:urd_x_preferred":[
        "\u0628\u06af \u0631\u0627\u06a9"
    ],
    "name:vol_x_preferred":[
        "Big Rock"
    ],
    "wof:name":"Big Rock",
    "wof:placetype":"locality"
},
  "geometry": {"coordinates":[-92.29796,42.55165],"type":"Point"}
}