{
  "type": "Feature",
  "properties": {
    "gn:admin1_code":"NC",
    "gn:admin2_code":"153",
    "gn:admin3_code":"91988.0",
    "gn:asciiname":"Ghio Scholl Station",
    "gn:country_code":"US",
    "gn:dem":96,
    "gn:elevation":"94.0",
    "gn:feature_class":"P",
    "gn:feature_code":"PPL",
    "gn:name":"Ghio Scholl Station",
    "gn:population":0,
    "gn:timezone":"America/New_York",
    "iso:country":"US",
    "wof:name":"Ghio Scholl Station",
    "wof:placetype":"locality"
},
  "geometry": {"coordinates":[-79.65089,34.81682],"type":"Point"}
}