{
  "type": "Feature",
  "properties": {
    "gn:admin1_code":"WV",
    "gn:admin2_code":"61",
    "gn:asciiname":"Hilderbrand",
    "gn:country_code":"US",
    "gn:dem":274,
    "gn:elevation":"268.0",
    "gn:feature_class":"P",
    "gn:feature_code":"PPL",
    "gn:name":"Hilderbrand",
    "gn:population":0,
    "gn:timezone":"America/New_York",
    "iso:country":"US",
    "name:eng_x_preferred":[
        "Hilderbrand"
    ],
    "name:und_x_variant":[
        "Hildebrand",
        "Delmar"
    ],
    "wof:name":"Hilderbrand",
    "wof:placetype":"locality"
},
  "geometry": {"coordinates":[-79.99757,39.59064],"type":"Point"}
}