{
  "type": "Feature",
  "properties": {
    "gn:admin1_code":"NC",
    "gn:admin2_code":"89",
    "gn:admin3_code":"91456.0",
    "gn:asciiname":"Country Club Estates",
    "gn:country_code":"US",
    "gn:dem":711,
    "gn:elevation":"706.0",
    "gn:feature_class":"P",
    "gn:feature_code":"PPL",
    "gn:name":"Country Club Estates",
    "gn:population":0,
    "gn:timezone":"America/New_York",
    "iso:country":"US",
    "wof:name":"Country Club Estates",
    "wof:placetype":"locality"
},
  "geometry": {"coordinates":[-82.48012,35.30789],"type":"Point"}
}