{
  "type": "Feature",
  "properties": {
    "gn:admin1_code":"VA",
    "gn:admin2_code":"179.0",
    "gn:asciiname":"Sunnyside",
    "gn:country_code":"US",
    "gn:dem":21,
    "gn:elevation":"15.0",
    "gn:feature_class":"P",
    "gn:feature_code":"PPL",
    "gn:name":"Sunnyside",
    "gn:population":0,
    "gn:timezone":"America/New_York",
    "iso:country":"US",
    "name:bar_x_preferred":[
        "Sunnyside"
    ],
    "name:ceb_x_preferred":[
        "Sunnyside"
    ],
    "name:deu_x_preferred":[
        "Sunnyside"
    ],
    "name:fra_x_preferred":[
        "Sunnyside"
    ],
    "name:ita_x_preferred":[
        "Sunnyside"
    ],
    "name:kor_x_preferred":[
        "\uc11c\ub2c8\uc0ac\uc774\ub4dc"
    ],
    "name:nld_x_preferred":[
        "Sunnyside"
    ],
    "name:pol_x_preferred":[
        "Sunnyside"
    ],
    "name:por_x_preferred":[
        "Sunnyside"
    ],
    "name:rus_x_preferred":[
        "\u0421\u0430\u043d\u043d\u0438\u0441\u0430\u0439\u0434"
    ],
    "name:spa_x_preferred":[
        "Sunnyside"
    ],
    "name:srp_x_preferred":[
        "\u0421\u0430\u043d\u0438\u0441\u0430\u0458\u0434"
    ],
    "name:swe_x_preferred":[
        "Sunnyside"
    ],
    "name:und_x_variant":[
        "Vasquez"
    ],
    "name:vol_x_preferred":[
        "Sunnyside"
    ],
    "wof:name":"Sunnyside",
    "wof:placetype":"locality"
},
  "geometry": {"coordinates":[-77.387,38.4826],"type":"Point"}
}