{
  "type": "Feature",
  "properties": {
    "iso:country":"US",
    "name:eng_x_preferred":[
        "Rockhold Acres"
    ],
    "wof:name":"Rockhold Acres",
    "wof:placetype":"neighbourhood",
    "wof:population":2501,
    "zs:area_m":62080208.071971,
    "zs:blockids":[
        191530107023072,
        191530108041065,
        191530108042064,
        191530108042077,
        191530107021023,
        191530108042071,
        191530108042069,
        191530108041012,
        191530107023074,
        191530108041022,
        191530108041082,
        191530108041018,
        191530108041033,
        191530107023075,
        191530108041035,
        191530108041015,
        191530107023077,
        191530107021005,
        191530108022001,
        191530107021020,
        191530108041086,
        191530108041087,
        191530108042078,
        191530108041050,
        191530108041031,
        191530107023071,
        191530108041072,
        191530107061050,
        191530108041074,
        191530107021071,
        191530108042056,
        191530108042059,
        191530108041067,
        191530107021028,
        191530108042062,
        191530108041027,
        191530108041081,
        191530107061048,
        191530107061047,
        191530108041026,
        191530108041079,
        191530108042058,
        191530108041077,
        191530107021026,
        191530108041071,
        191530107021019,
        191530107021008,
        191530108042055,
        191530108041021,
        191530108041032,
        191530107061041,
        191530107021007,
        191530107021006,
        191530108042068,
        191530108042076,
        191530108041083,
        191530108042053,
        191530108041080,
        191530108041029,
        191530108041019,
        191530108041006,
        191530107061049,
        191530108022000,
        191530108041005,
        191530107023076,
        191530108042061,
        191530108042057,
        191530107021021,
        191530107021022,
        191530108041030,
        191530108041014,
        191530108041020,
        191530108041002,
        191530108041007,
        191530108041024,
        191530108041073,
        191530108042060,
        191530108042063,
        191530108041068,
        191530108041070,
        191530108042054,
        191530108041085,
        191530107021027,
        191530107021025,
        191530107021024,
        191530108041025,
        191530108041069,
        191530108042000,
        191530108041028,
        191530108042001,
        191530108041017,
        191530108041004,
        191530108041023,
        191530108041001,
        191530108041037,
        191530108041036,
        191530108041013,
        191530108041066,
        191530108041003,
        191530108041000,
        191530108041084,
        191530108041078,
        191530108042070,
        191530108041064
    ],
    "zs:housing10":902,
    "zs:label":"Rockhold Acres",
    "zs:pop10":2501
},
  "geometry": {"coordinates":[-93.448927,41.570435],"type":"Point"}
}