{
  "type": "Feature",
  "properties": {
    "gn:admin1_code":"AL",
    "gn:admin2_code":"43",
    "gn:asciiname":"Mount View",
    "gn:country_code":"US",
    "gn:dem":285,
    "gn:elevation":"282.0",
    "gn:feature_class":"P",
    "gn:feature_code":"PPL",
    "gn:name":"Mount View",
    "gn:population":0,
    "gn:timezone":"America/Chicago",
    "iso:country":"US",
    "name:ceb_x_preferred":[
        "Mount View"
    ],
    "name:swe_x_preferred":[
        "Mount View"
    ],
    "wof:name":"Mount View",
    "wof:placetype":"locality"
},
  "geometry": {"coordinates":[-86.78471999999999,34.25482],"type":"Point"}
}