{
  "type": "Feature",
  "properties": {
    "iso:country":"US",
    "name:eng_x_preferred":[
        "Coolspring"
    ],
    "name:und_x_variant":[
        "Coal Spring Furnace"
    ],
    "wof:name":"Coolspring",
    "wof:placetype":"neighbourhood",
    "wof:population":150,
    "zs:area_m":645242.696786,
    "zs:blockids":[
        420512618002019,
        420512618002017,
        420512618002030,
        420512618002029,
        420512618002018,
        420512618002066,
        420512618002028,
        420512618002007,
        420512618002016,
        420512618002032,
        420512618002031
    ],
    "zs:housing10":70,
    "zs:label":"Coolspring",
    "zs:pop10":150
},
  "geometry": {"coordinates":[-79.695047,39.906197],"type":"Point"}
}