{
  "type": "Feature",
  "properties": {
    "gn:admin1_code":"TX",
    "gn:admin2_code":"313.0",
    "gn:asciiname":"Bundy Crossing",
    "gn:country_code":"US",
    "gn:dem":83,
    "gn:elevation":"70.0",
    "gn:feature_class":"P",
    "gn:feature_code":"PPL",
    "gn:name":"Bundy Crossing",
    "gn:population":0,
    "gn:timezone":"America/Chicago",
    "iso:country":"US",
    "wof:name":"Bundy Crossing",
    "wof:placetype":"locality"
},
  "geometry": {"coordinates":[-96.20440000000001,30.92436],"type":"Point"}
}