{
  "type": "Feature",
  "properties": {
    "gn:admin1_code":"TN",
    "gn:admin2_code":"163",
    "gn:asciiname":"Crest View",
    "gn:country_code":"US",
    "gn:dem":489,
    "gn:elevation":"495.0",
    "gn:feature_class":"P",
    "gn:feature_code":"PPL",
    "gn:name":"Crest View",
    "gn:population":0,
    "gn:timezone":"America/New_York",
    "iso:country":"US",
    "wof:name":"Crest View",
    "wof:placetype":"locality"
},
  "geometry": {"coordinates":[-82.19847,36.51955],"type":"Point"}
}