{
  "type": "Feature",
  "properties": {
    "gn:admin1_code":"GA",
    "gn:admin2_code":"89.0",
    "gn:asciiname":"Blue Creek Forest",
    "gn:country_code":"US",
    "gn:dem":284,
    "gn:elevation":"280.0",
    "gn:feature_class":"P",
    "gn:feature_code":"PPL",
    "gn:name":"Blue Creek Forest",
    "gn:population":0,
    "gn:timezone":"America/New_York",
    "iso:country":"US",
    "wof:name":"Blue Creek Forest",
    "wof:placetype":"locality"
},
  "geometry": {"coordinates":[-84.29992,33.67233],"type":"Point"}
}