{
  "type": "Feature",
  "properties": {
    "gn:admin1_code":"OH",
    "gn:admin2_code":"53",
    "gn:admin3_code":"13946.0",
    "gn:asciiname":"Kyger",
    "gn:country_code":"US",
    "gn:dem":183,
    "gn:elevation":"183.0",
    "gn:feature_class":"P",
    "gn:feature_code":"PPL",
    "gn:name":"Kyger",
    "gn:population":0,
    "gn:timezone":"America/New_York",
    "iso:country":"US",
    "name:eng_x_preferred":[
        "Kyger"
    ],
    "name:und_x_variant":[
        "Kygerville"
    ],
    "wof:name":"Kyger",
    "wof:placetype":"locality"
},
  "geometry": {"coordinates":[-82.15486999999997,38.98147],"type":"Point"}
}