{
  "type": "Feature",
  "properties": {
    "gn:admin1_code":"MD",
    "gn:admin2_code":"13.0",
    "gn:asciiname":"Keyview",
    "gn:country_code":"US",
    "gn:dem":193,
    "gn:elevation":"192.0",
    "gn:feature_class":"P",
    "gn:feature_code":"PPL",
    "gn:name":"Keyview",
    "gn:population":0,
    "gn:timezone":"America/New_York",
    "iso:country":"US",
    "wof:name":"Keyview",
    "wof:placetype":"locality"
},
  "geometry": {"coordinates":[-77.14359,39.59871],"type":"Point"}
}