{
  "type": "Feature",
  "properties": {
    "iso:country":"US",
    "name:eng_x_preferred":[
        "Cragmere Woods"
    ],
    "wof:name":"Cragmere Woods",
    "wof:placetype":"neighbourhood",
    "zs:area_m":1171548.207725,
    "zs:blockids":[
        100030105024001,
        100030105024027
    ],
    "zs:housing10":0,
    "zs:label":"Cragmere Woods",
    "zs:pop10":0
},
  "geometry": {"coordinates":[-75.483098,39.76348],"type":"Point"}
}