{
  "type": "Feature",
  "properties": {
    "gn:admin1_code":"FL",
    "gn:admin2_code":"105.0",
    "gn:asciiname":"Twelve Oaks Mobile Home Park",
    "gn:country_code":"US",
    "gn:dem":54,
    "gn:elevation":"49.0",
    "gn:feature_class":"P",
    "gn:feature_code":"PPL",
    "gn:name":"Twelve Oaks Mobile Home Park",
    "gn:population":0,
    "gn:timezone":"America/New_York",
    "iso:country":"US",
    "wof:name":"Twelve Oaks Mobile Home Park",
    "wof:placetype":"campus"
},
  "geometry": {"coordinates":[-81.95634,28.08516],"type":"Point"}
}