{
  "type": "Feature",
  "properties": {
    "iso:country":"US",
    "name:eng_x_preferred":[
        "Edmund Terrace"
    ],
    "qs_pg:aaroncc":"US",
    "qs_pg:name":"Edmund Terrace",
    "qs_pg:name_adm0":"United States",
    "qs_pg:name_adm1":"New Jersey",
    "qs_pg:photos":480,
    "qs_pg:photos_1k":97,
    "qs_pg:photos_9k":2,
    "qs_pg:photos_9r":5,
    "qs_pg:photos_all":480,
    "qs_pg:photos_sr":7,
    "qs_pg:pop_sr":0,
    "qs_pg:qs_pg_placetype":"neighbourhood",
    "qs_pg:qs_pg_placetype_gp":"Suburb",
    "qs_pg:woe_adm0":23424977,
    "woe:adm0_id":23424977,
    "woe:name_adm0":"United States",
    "woe:name_adm1":"New Jersey",
    "woe:placetype":"Suburb",
    "wof:name":"Edmund Terrace",
    "wof:placetype":"neighbourhood",
    "wof:population":1953
},
  "geometry": {"coordinates":[-74.2608025,40.71437],"type":"Point"}
}