{
  "type": "Feature",
  "properties": {
    "gn:admin1_code":"GA",
    "gn:admin2_code":"113",
    "gn:asciiname":"Whitfield Farms",
    "gn:country_code":"US",
    "gn:dem":271,
    "gn:elevation":"265.0",
    "gn:feature_class":"P",
    "gn:feature_code":"PPL",
    "gn:name":"Whitfield Farms",
    "gn:population":0,
    "gn:timezone":"America/New_York",
    "iso:country":"US",
    "wof:name":"Whitfield Farms",
    "wof:placetype":"locality"
},
  "geometry": {"coordinates":[-84.55604,33.40678],"type":"Point"}
}