{
  "type": "Feature",
  "properties": {
    "iso:country":"US",
    "name:deu_x_preferred":[
        "Vermilion Dam"
    ],
    "name:eng_x_preferred":[
        "Vermilion Dam"
    ],
    "name:fas_x_preferred":[
        "\u0648\u0631\u0645\u06cc\u0644\u06cc\u0648\u0646 \u062f\u0645\u060c \u0645\u06cc\u0646\u0647\u200c\u0633\u0648\u062a\u0627"
    ],
    "name:fas_x_variant":[
        "\u0648\u0631\u0645\u06cc\u0644\u06cc\u0648\u0646 \u062f\u0645"
    ],
    "name:fra_x_preferred":[
        "Vermilion Dam"
    ],
    "name:vol_x_preferred":[
        "Vermilion Dam"
    ],
    "qs_pg:aaroncc":"US",
    "qs_pg:name":"Vermilion Dam",
    "qs_pg:name_adm0":"United States",
    "qs_pg:name_adm1":"Minnesota",
    "qs_pg:photos":20,
    "qs_pg:photos_1k":4,
    "qs_pg:photos_9k":1,
    "qs_pg:photos_9r":1,
    "qs_pg:photos_all":20,
    "qs_pg:photos_sr":1,
    "qs_pg:pop_sr":0,
    "qs_pg:qs_pg_placetype":"locality",
    "qs_pg:qs_pg_placetype_gp":"Town",
    "qs_pg:woe_adm0":23424977,
    "woe:adm0_id":23424977,
    "woe:name_adm0":"United States",
    "woe:name_adm1":"Minnesota",
    "woe:placetype":"Town",
    "wof:name":"Vermilion Dam",
    "wof:placetype":"locality"
},
  "geometry": {"coordinates":[-92.4772605,47.959812],"type":"Point"}
}