{
  "type": "Feature",
  "properties": {
    "gn:country":"US",
    "gn:fcode":"PPL",
    "gn:population":0,
    "iso:country":"US",
    "name:bre_x_preferred":[
        "Avon"
    ],
    "name:bul_x_preferred":[
        "\u0415\u0439\u0432\u044a\u043d"
    ],
    "name:cat_x_preferred":[
        "Avon"
    ],
    "name:ceb_x_preferred":[
        "Avon"
    ],
    "name:deu_x_preferred":[
        "Avon"
    ],
    "name:fin_x_preferred":[
        "Avon"
    ],
    "name:fra_x_preferred":[
        "Avon"
    ],
    "name:heb_x_preferred":[
        "\u05d0\u05d9\u05d9\u05d1\u05d5\u05df"
    ],
    "name:hif_x_preferred":[
        "Avon"
    ],
    "name:hun_x_preferred":[
        "Avon"
    ],
    "name:ita_x_preferred":[
        "Avon"
    ],
    "name:jpn_x_preferred":[
        "\u30a8\u30a4\u30f4\u30a9\u30f3"
    ],
    "name:kor_x_preferred":[
        "\uc5d0\uc774\ubc88"
    ],
    "name:lmo_x_preferred":[
        "Avon"
    ],
    "name:nds_x_preferred":[
        "Avon"
    ],
    "name:nld_x_preferred":[
        "Avon"
    ],
    "name:nno_x_preferred":[
        "Avon"
    ],
    "name:nor_x_preferred":[
        "Avon"
    ],
    "name:pms_x_preferred":[
        "Avon"
    ],
    "name:pol_x_preferred":[
        "Avon"
    ],
    "name:por_x_preferred":[
        "Avon"
    ],
    "name:ron_x_preferred":[
        "Avon"
    ],
    "name:rus_x_preferred":[
        "\u042d\u0439\u0432\u043e\u043d"
    ],
    "name:slk_x_preferred":[
        "Avon"
    ],
    "name:spa_x_preferred":[
        "Avon"
    ],
    "name:srp_x_preferred":[
        "\u0415\u0458\u0432\u043e\u043d"
    ],
    "name:swa_x_preferred":[
        "Avon"
    ],
    "name:swe_x_preferred":[
        "Avon"
    ],
    "name:ukr_x_preferred":[
        "\u0410\u0432\u043e\u043d"
    ],
    "name:vol_x_preferred":[
        "Avon"
    ],
    "qs_pg:aaroncc":"US",
    "qs_pg:gn_country":"US",
    "qs_pg:gn_fcode":"PPL",
    "qs_pg:gn_pop":0,
    "qs_pg:name":"Avon",
    "qs_pg:name_adm0":"United States",
    "qs_pg:name_adm1":"Missouri",
    "qs_pg:photos":2,
    "qs_pg:photos_1k":1,
    "qs_pg:photos_9k":1,
    "qs_pg:photos_9r":1,
    "qs_pg:photos_all":2,
    "qs_pg:photos_sr":1,
    "qs_pg:pop_sr":0,
    "qs_pg:qs_pg_placetype":"locality",
    "qs_pg:qs_pg_placetype_gp":"Town",
    "qs_pg:woe_adm0":23424977,
    "woe:adm0_id":23424977,
    "woe:name_adm0":"United States",
    "woe:name_adm1":"Missouri",
    "woe:placetype":"Town",
    "wof:name":"Avon",
    "wof:placetype":"locality"
},
  "geometry": {"coordinates":[-94.31578,38.83029],"type":"Point"}
}