{
  "type": "Feature",
  "properties": {
    "iso:country":"US",
    "name:eng_x_preferred":[
        "Sharon Heights"
    ],
    "qs:gn_adm0_cc":"US",
    "qs:gn_local":5372223,
    "qs:gn_nam_loc":"Menlo Park, San Mateo, California, US",
    "qs:gn_namadm1":"CA",
    "qs:local_max":3410,
    "qs:local_sum":15033,
    "qs:localhoods":11,
    "qs:name":"Sharon Heights",
    "qs:name_adm0":"United States",
    "qs:name_adm1":"California",
    "qs:name_adm2":"San Mateo",
    "qs:name_local":"Menlo Park",
    "qs:photo_max":263,
    "qs:photo_sum":715,
    "qs:placetype":"Suburb",
    "qs:quad_count":26,
    "qs:woe_adm0":23424977,
    "qs:woe_adm1":2347563,
    "qs:woe_adm2":12587710,
    "qs:woe_lau":0,
    "qs:woe_local":2449435,
    "qs:woe_ver":"7.10.0",
    "wof:name":"Sharon Heights",
    "wof:placetype":"neighbourhood",
    "wof:population":1678,
    "zs:blockids":[
        60816130002008,
        60816130002060,
        60816130002013,
        60816130002017,
        60816132001014,
        60816130002023,
        60816130002025,
        60816130002027,
        60816130002024,
        60816130002012,
        60816130002053,
        60816129002010,
        60816130001017,
        60816130002029,
        60816130002033,
        60816130002037,
        60816130002035,
        60816130002055,
        60816130002057,
        60816130001001,
        60816130002059,
        60816130001015,
        60816133002023,
        60816130002032,
        60816130002031,
        60816130002034,
        60816130002015,
        60816130001022,
        60816132001012,
        60816114003018,
        60816130002018,
        60816132001013,
        60816130002021,
        60816130002020,
        60816130001011,
        60816130002030,
        60816130002009,
        60816114003015,
        60816130001010,
        60816114003014,
        60816114003017,
        60816130001007,
        60816130001013,
        60816130002028,
        60816114003016,
        60816130001008,
        60816130001005,
        60816130001018,
        60816130002026,
        60816132001016,
        60816130002007,
        60816130002016,
        60816130002022,
        60816130001004,
        60816130001003,
        60816130001012,
        60816130002014,
        60816114003010,
        60816130002036,
        60816130002056,
        60816130002054,
        60816130001002,
        60816130002019,
        60816130001006,
        60816129002006,
        60816132001015,
        60816130002047,
        60816130002058
    ],
    "zs:housing10":766,
    "zs:pop10":1678
},
  "geometry": {"coordinates":[-122.207982,37.427111],"type":"Point"}
}