{
  "type": "Feature",
  "properties": {
    "gn:admin1_code":"FL",
    "gn:admin2_code":"105.0",
    "gn:asciiname":"Spring Lake Mobile Home Park",
    "gn:country_code":"US",
    "gn:dem":41,
    "gn:elevation":"32.0",
    "gn:feature_class":"P",
    "gn:feature_code":"PPL",
    "gn:name":"Spring Lake Mobile Home Park",
    "gn:population":0,
    "gn:timezone":"America/New_York",
    "iso:country":"US",
    "wof:name":"Spring Lake Mobile Home Park",
    "wof:placetype":"campus"
},
  "geometry": {"coordinates":[-81.59501999999998,28.17375],"type":"Point"}
}