{
  "type": "Feature",
  "properties": {
    "gn:admin1_code":"GA",
    "gn:admin2_code":"73",
    "gn:asciiname":"Village at Watervale",
    "gn:country_code":"US",
    "gn:dem":87,
    "gn:elevation":"83.0",
    "gn:feature_class":"P",
    "gn:feature_code":"PPL",
    "gn:name":"Village at Watervale",
    "gn:population":0,
    "gn:timezone":"America/New_York",
    "iso:country":"US",
    "wof:name":"Village at Watervale",
    "wof:placetype":"locality"
},
  "geometry": {"coordinates":[-82.06178,33.53847],"type":"Point"}
}