{
  "type": "Feature",
  "properties": {
    "gn:admin1_code":"WI",
    "gn:admin2_code":"101",
    "gn:admin3_code":"89575.0",
    "gn:asciiname":"Harvest View Estates",
    "gn:country_code":"US",
    "gn:dem":234,
    "gn:elevation":"233.0",
    "gn:feature_class":"P",
    "gn:feature_code":"PPL",
    "gn:name":"Harvest View Estates",
    "gn:population":0,
    "gn:timezone":"America/Chicago",
    "iso:country":"US",
    "wof:name":"Harvest View Estates",
    "wof:placetype":"locality"
},
  "geometry": {"coordinates":[-87.99444,42.68694],"type":"Point"}
}