{
  "type": "Feature",
  "properties": {
    "iso:country":"US",
    "name:deu_x_preferred":[
        "Griswold"
    ],
    "name:eng_x_preferred":[
        "Griswold"
    ],
    "name:fra_x_preferred":[
        "Griswold"
    ],
    "name:ita_x_preferred":[
        "Griswold"
    ],
    "name:pol_x_preferred":[
        "Griswold"
    ],
    "name:rus_x_preferred":[
        "\u0413\u0440\u0438\u0437\u0443\u043e\u043b\u0434"
    ],
    "name:ukr_x_preferred":[
        "\u0413\u0440\u0438\u0441\u0432\u0443\u0434"
    ],
    "name:vol_x_preferred":[
        "Griswold"
    ],
    "wd:wordcount":161,
    "wof:name":"Griswold",
    "wof:placetype":"neighbourhood",
    "wof:population":35,
    "zs:area_m":4702277.575271,
    "zs:blockids":[
        360130361002050,
        360130361002029
    ],
    "zs:housing10":21,
    "zs:label":"Griswold",
    "zs:pop10":35
},
  "geometry": {"coordinates":[-79.225121,42.391649],"type":"Point"}
}