{
  "type": "Feature",
  "properties": {
    "gn:admin1_code":"SC",
    "gn:admin2_code":"83.0",
    "gn:asciiname":"Lake Forest",
    "gn:country_code":"US",
    "gn:dem":234,
    "gn:elevation":"228.0",
    "gn:feature_class":"P",
    "gn:feature_code":"PPL",
    "gn:name":"Lake Forest",
    "gn:population":0,
    "gn:timezone":"America/New_York",
    "iso:country":"US",
    "name:ceb_x_preferred":[
        "Lake Forest"
    ],
    "name:deu_x_preferred":[
        "Lake Forest"
    ],
    "name:fas_x_preferred":[
        "\u0644\u06cc\u06a9 \u0641\u0627\u0631\u0633\u062a"
    ],
    "name:fra_x_preferred":[
        "Lake Forest"
    ],
    "name:ita_x_preferred":[
        "Lake Forest"
    ],
    "name:jpn_x_preferred":[
        "\u30ec\u30a4\u30af\u30d5\u30a9\u30ec\u30b9\u30c8"
    ],
    "name:kor_x_preferred":[
        "\ub808\uc774\ud06c\ud3ec\ub9ac\uc2a4\ud2b8"
    ],
    "name:nld_x_preferred":[
        "Lake Forest"
    ],
    "name:pol_x_preferred":[
        "Lake Forest"
    ],
    "name:por_x_preferred":[
        "Lake Forest"
    ],
    "name:spa_x_preferred":[
        "Lake Forest"
    ],
    "name:srp_x_preferred":[
        "\u041b\u0435\u0458\u043a \u0424\u043e\u0440\u0438\u0441\u0442"
    ],
    "name:swe_x_preferred":[
        "Lake Forest"
    ],
    "name:ukr_x_preferred":[
        "\u041b\u0435\u0439\u043a-\u0424\u043e\u0440\u0435\u0441\u0442"
    ],
    "name:urd_x_preferred":[
        "\u0644\u06cc\u06a9 \u0641\u0627\u0631\u0633\u0679"
    ],
    "name:vol_x_preferred":[
        "Lake Forest"
    ],
    "wof:name":"Lake Forest",
    "wof:placetype":"locality"
},
  "geometry": {"coordinates":[-81.86094,34.96762],"type":"Point"}
}