{
  "type": "Feature",
  "properties": {
    "iso:country":"US",
    "name:eng_x_preferred":[
        "Dittmerville"
    ],
    "wof:name":"Dittmerville",
    "wof:placetype":"neighbourhood",
    "wof:population":147,
    "zs:area_m":144372.328983,
    "zs:blockids":[
        130510044001018,
        130510028003039,
        130510028003034,
        130510034001002,
        130510044001001
    ],
    "zs:housing10":61,
    "zs:label":"Dittmerville",
    "zs:pop10":147
},
  "geometry": {"coordinates":[-81.110747,32.042969],"type":"Point"}
}