{
  "type": "Feature",
  "properties": {
    "gn:admin1_code":"GA",
    "gn:admin2_code":"7.0",
    "gn:asciiname":"Jones Spur",
    "gn:country_code":"US",
    "gn:dem":73,
    "gn:elevation":"68.0",
    "gn:feature_class":"P",
    "gn:feature_code":"PPL",
    "gn:name":"Jones Spur",
    "gn:population":0,
    "gn:timezone":"America/New_York",
    "iso:country":"US",
    "wof:name":"Jones Spur",
    "wof:placetype":"locality"
},
  "geometry": {"coordinates":[-84.63491999999999,31.42684],"type":"Point"}
}