{
  "type": "Feature",
  "properties": {
    "gn:admin1_code":"FL",
    "gn:admin2_code":"9.0",
    "gn:asciiname":"River Palms Mobile Home Park",
    "gn:country_code":"US",
    "gn:dem":4,
    "gn:elevation":"0.0",
    "gn:feature_class":"P",
    "gn:feature_code":"PPL",
    "gn:name":"River Palms Mobile Home Park",
    "gn:population":0,
    "gn:timezone":"America/New_York",
    "iso:country":"US",
    "wof:name":"River Palms Mobile Home Park",
    "wof:placetype":"campus"
},
  "geometry": {"coordinates":[-80.66204,28.35221],"type":"Point"}
}