{
  "type": "Feature",
  "properties": {
    "gn:admin1_code":"MN",
    "gn:admin2_code":"71.0",
    "gn:admin3_code":"53134.0",
    "gn:asciiname":"Falls Junction",
    "gn:country_code":"US",
    "gn:dem":342,
    "gn:elevation":"344.0",
    "gn:feature_class":"P",
    "gn:feature_code":"PPL",
    "gn:name":"Falls Junction",
    "gn:population":0,
    "gn:timezone":"America/Chicago",
    "iso:country":"US",
    "wof:name":"Falls Junction",
    "wof:placetype":"locality"
},
  "geometry": {"coordinates":[-93.34292000000001,48.60271],"type":"Point"}
}