{
  "type": "Feature",
  "properties": {
    "iso:country":"US",
    "name:eng_x_preferred":[
        "Ruby's Yumesa"
    ],
    "wof:name":"Ruby's Yumesa",
    "wof:placetype":"neighbourhood",
    "wof:population":719,
    "zs:area_m":859930.387191,
    "zs:blockids":[
        40270001002028,
        40270001002017,
        40270001002027,
        40270001002020,
        40270001001059,
        40270001002029,
        40270001001074,
        40270001002007,
        40270001002019,
        40270001002005,
        40270001002004,
        40270001001057,
        40270001002016,
        40270001002008,
        40270001002022,
        40270001002018,
        40270001001073
    ],
    "zs:housing10":202,
    "zs:label":"Ruby's Yumesa",
    "zs:pop10":719
},
  "geometry": {"coordinates":[-114.61753299999999,32.71265],"type":"Point"}
}