{
  "type": "Feature",
  "properties": {
    "gn:country":"US",
    "gn:fcode":"PPL",
    "gn:population":0,
    "iso:country":"US",
    "name:eng_x_preferred":[
        "Medora"
    ],
    "name:fra_x_preferred":[
        "Medora"
    ],
    "name:und_x_variant":[
        "Leslie"
    ],
    "qs_pg:aaroncc":"US",
    "qs_pg:gn_country":"US",
    "qs_pg:gn_fcode":"PPL",
    "qs_pg:gn_pop":0,
    "qs_pg:name":"Medora",
    "qs_pg:name_adm0":"United States",
    "qs_pg:name_adm1":"Kansas",
    "qs_pg:photos":42,
    "qs_pg:photos_1k":9,
    "qs_pg:photos_9k":1,
    "qs_pg:photos_9r":2,
    "qs_pg:photos_all":42,
    "qs_pg:photos_sr":2,
    "qs_pg:pop_sr":5,
    "qs_pg:qs_pg_placetype":"locality",
    "qs_pg:qs_pg_placetype_gp":"Town",
    "qs_pg:woe_adm0":23424977,
    "woe:adm0_id":23424977,
    "woe:name_adm0":"United States",
    "woe:name_adm1":"Kansas",
    "woe:placetype":"Town",
    "wof:name":"Medora",
    "wof:placetype":"locality"
},
  "geometry": {"coordinates":[-97.84560999999999,38.1489],"type":"Point"}
}