{
  "type": "Feature",
  "properties": {
    "gn:admin1_code":"KY",
    "gn:admin2_code":"5.0",
    "gn:asciiname":"Stringtown",
    "gn:country_code":"US",
    "gn:dem":262,
    "gn:elevation":"262.0",
    "gn:feature_class":"P",
    "gn:feature_code":"PPL",
    "gn:name":"Stringtown",
    "gn:population":0,
    "gn:timezone":"America/New_York",
    "iso:country":"US",
    "name:deu_x_preferred":[
        "Stringtown"
    ],
    "name:vol_x_preferred":[
        "Stringtown"
    ],
    "wof:name":"Stringtown",
    "wof:placetype":"locality"
},
  "geometry": {"coordinates":[-84.88078,38.00813],"type":"Point"}
}