{
  "type": "Feature",
  "properties": {
    "gn:admin1_code":"GA",
    "gn:admin2_code":"193.0",
    "gn:asciiname":"Four Points",
    "gn:country_code":"US",
    "gn:dem":122,
    "gn:elevation":"119.0",
    "gn:feature_class":"P",
    "gn:feature_code":"PPL",
    "gn:name":"Four Points",
    "gn:population":0,
    "gn:timezone":"America/New_York",
    "iso:country":"US",
    "wof:name":"Four Points",
    "wof:placetype":"locality"
},
  "geometry": {"coordinates":[-83.99185,32.31793],"type":"Point"}
}