{
  "type": "Feature",
  "properties": {
    "gn:admin1_code":"VA",
    "gn:admin2_code":"33",
    "gn:asciiname":"Broadus Corner",
    "gn:country_code":"US",
    "gn:dem":60,
    "gn:elevation":"56.0",
    "gn:feature_class":"P",
    "gn:feature_code":"PPL",
    "gn:name":"Broadus Corner",
    "gn:population":0,
    "gn:timezone":"America/New_York",
    "iso:country":"US",
    "wof:name":"Broadus Corner",
    "wof:placetype":"locality"
},
  "geometry": {"coordinates":[-77.18080999999999,37.9793],"type":"Point"}
}