{
  "type": "Feature",
  "properties": {
    "iso:country":"US",
    "name:deu_x_preferred":[
        "Claridge"
    ],
    "name:eng_x_preferred":[
        "Claridge"
    ],
    "wof:name":"Claridge",
    "wof:placetype":"neighbourhood",
    "wof:population":394,
    "zs:area_m":526781.406164,
    "zs:blockids":[
        371830537121004,
        371830537112023,
        371830537121012,
        371830537121014,
        371830537121013,
        371830537121015,
        371830537112022,
        371830537121018,
        371830537111034,
        371830537112026,
        371830537121017,
        371830537121011,
        371830537111036,
        371830537112010,
        371830537112008,
        371830537112009,
        371830537112021,
        371830537121016,
        371830537111037,
        371830537112027,
        371830537111035,
        371830537121010
    ],
    "zs:housing10":150,
    "zs:label":"Claridge",
    "zs:pop10":394
},
  "geometry": {"coordinates":[-78.69820300000001,35.88937],"type":"Point"}
}