{
  "type": "Feature",
  "properties": {
    "iso:country":"US",
    "name:eng_x_preferred":[
        "Gateway East"
    ],
    "wof:name":"Gateway East",
    "wof:placetype":"neighbourhood",
    "wof:population":6411,
    "zs:area_m":1590535.728188,
    "zs:blockids":[
        120111002022000,
        120111001032003,
        120111001032001,
        120111001012012,
        120111001013001,
        120111002021019,
        120111001014005,
        120111001011006,
        120111001014007,
        120111001014004,
        120111001013002,
        120111002022011,
        120111001013003,
        120111001014002,
        120111001014006,
        120111001032004,
        120111001014003,
        120111001032002,
        120111001011005,
        120111002021020,
        120111001032000,
        120110901012006,
        120111001032005,
        120111002022001,
        120111002022010,
        120111002021013,
        120111001012014
    ],
    "zs:housing10":5444,
    "zs:label":"Gateway East",
    "zs:pop10":6411
},
  "geometry": {"coordinates":[-80.129446,25.989903],"type":"Point"}
}