{
  "type": "Feature",
  "properties": {
    "iso:country":"US",
    "name:cat_x_preferred":[
        "Estancia"
    ],
    "name:deu_x_preferred":[
        "Estancia"
    ],
    "name:eng_x_preferred":[
        "Estancia"
    ],
    "name:fra_x_preferred":[
        "Estancia"
    ],
    "name:kor_x_preferred":[
        "\uc5d0\uc2a4\ud0c4\uc2dc\uc544"
    ],
    "name:pol_x_preferred":[
        "Estancja"
    ],
    "name:por_x_preferred":[
        "Est\u00e2ncia"
    ],
    "name:spa_x_preferred":[
        "Estancia"
    ],
    "name:swe_x_preferred":[
        "Estancia"
    ],
    "wof:name":"Estancia",
    "wof:placetype":"neighbourhood",
    "wof:population":728,
    "zs:area_m":1229691.679656,
    "zs:blockids":[
        61110058012022,
        61110058022017,
        61110058012023,
        61110058012020,
        61110058022012,
        61110058012019
    ],
    "zs:housing10":228,
    "zs:label":"Estancia",
    "zs:pop10":728
},
  "geometry": {"coordinates":[-118.978086,34.1615],"type":"Point"}
}