{
  "type": "Feature",
  "properties": {
    "gn:country":"US",
    "gn:fcode":"PPL",
    "gn:population":0,
    "iso:country":"US",
    "name:azb_x_preferred":[
        "\u0631\u0627\u06a9 \u0627\u0633\u067e\u0631\u06cc\u0646\u0642"
    ],
    "name:eng_x_preferred":[
        "Rock Spring"
    ],
    "name:fas_x_preferred":[
        "\u0631\u0627\u06a9 \u0627\u0633\u067e\u0631\u06cc\u0646\u06af"
    ],
    "name:fra_x_preferred":[
        "Rock Spring"
    ],
    "name:hat_x_preferred":[
        "Rock Spring"
    ],
    "name:lld_x_preferred":[
        "Rock Spring"
    ],
    "name:und_x_variant":[
        "Rock Springs"
    ],
    "name:vol_x_preferred":[
        "Rock Spring"
    ],
    "name:zho_x_preferred":[
        "\u7f85\u514b\u65af\u666e\u6797"
    ],
    "qs_pg:aaroncc":"US",
    "qs_pg:gn_country":"US",
    "qs_pg:gn_fcode":"PPL",
    "qs_pg:gn_pop":0,
    "qs_pg:name":"Rock Spring",
    "qs_pg:name_adm0":"United States",
    "qs_pg:name_adm1":"Georgia",
    "qs_pg:photos_9k":6,
    "qs_pg:photos_9r":7,
    "qs_pg:photos_all":1407,
    "qs_pg:photos_sr":0,
    "qs_pg:pop_sr":5,
    "qs_pg:qs_pg_placetype":"locality",
    "qs_pg:qs_pg_placetype_gp":"Town",
    "qs_pg:woe_adm0":23424977,
    "woe:adm0_id":23424977,
    "woe:name_adm0":"United States",
    "woe:name_adm1":"Georgia",
    "woe:placetype":"Town",
    "wof:name":"Rock Spring",
    "wof:placetype":"locality"
},
  "geometry": {"coordinates":[-85.24272999999999,34.82424],"type":"Point"}
}