{
  "type": "Feature",
  "properties": {
    "gn:admin1_code":"TX",
    "gn:admin2_code":"85.0",
    "gn:asciiname":"Buckner",
    "gn:country_code":"US",
    "gn:dem":200,
    "gn:elevation":"201.0",
    "gn:feature_class":"P",
    "gn:feature_code":"PPL",
    "gn:name":"Buckner",
    "gn:population":0,
    "gn:timezone":"America/Chicago",
    "iso:country":"US",
    "name:fas_x_preferred":[
        "\u0628\u0627\u06a9\u0646\u0631"
    ],
    "name:urd_x_preferred":[
        "\u0628\u06a9\u0646\u0631"
    ],
    "wof:name":"Buckner",
    "wof:placetype":"locality"
},
  "geometry": {"coordinates":[-96.6636,33.21762],"type":"Point"}
}