{
  "type": "Feature",
  "properties": {
    "gn:admin1_code":"OH",
    "gn:admin2_code":"141",
    "gn:admin3_code":"38808.0",
    "gn:asciiname":"Rittenours",
    "gn:country_code":"US",
    "gn:dem":186,
    "gn:elevation":"183.0",
    "gn:feature_class":"P",
    "gn:feature_code":"PPL",
    "gn:name":"Rittenours",
    "gn:population":0,
    "gn:timezone":"America/New_York",
    "iso:country":"US",
    "wof:name":"Rittenours",
    "wof:placetype":"locality"
},
  "geometry": {"coordinates":[-82.84267,39.21646],"type":"Point"}
}