{
  "type": "Feature",
  "properties": {
    "gn:admin1_code":"GA",
    "gn:admin2_code":"59.0",
    "gn:asciiname":"Brookstone",
    "gn:country_code":"US",
    "gn:dem":224,
    "gn:elevation":"210.0",
    "gn:feature_class":"P",
    "gn:feature_code":"PPL",
    "gn:name":"Brookstone",
    "gn:population":0,
    "gn:timezone":"America/New_York",
    "iso:country":"US",
    "name:spa_x_preferred":[
        "Brookstone"
    ],
    "wof:name":"Brookstone",
    "wof:placetype":"locality"
},
  "geometry": {"coordinates":[-83.33459999999999,33.90262],"type":"Point"}
}