{
  "type": "Feature",
  "properties": {
    "iso:country":"US",
    "name:deu_x_preferred":[
        "Westlawn"
    ],
    "name:eng_x_preferred":[
        "Westlawn Place"
    ],
    "name:unk_x_variant":[
        "Westlawn Place"
    ],
    "qs:gn_adm0_cc":"US",
    "qs:gn_local":4846960,
    "qs:gn_nam_loc":"Ankeny, Polk, Iowa, US",
    "qs:gn_namadm1":"IA",
    "qs:local_max":1026,
    "qs:local_sum":2084,
    "qs:localhoods":10,
    "qs:name":"Westlawn Place",
    "qs:name_adm0":"United States",
    "qs:name_adm1":"Iowa",
    "qs:name_adm2":"Polk",
    "qs:name_local":"Ankeny",
    "qs:photo_max":5,
    "qs:photo_sum":7,
    "qs:placetype":"Suburb",
    "qs:quad_count":3,
    "qs:woe_adm0":23424977,
    "qs:woe_adm1":2347574,
    "qs:woe_adm2":12588348,
    "qs:woe_lau":0,
    "qs:woe_local":2354828,
    "qs:woe_ver":"7.10.0",
    "wof:lang":[
        "eng"
    ],
    "wof:name":"Westlawn",
    "wof:placetype":"neighbourhood",
    "wof:population":1809,
    "zs:blockids":[
        191530102073011,
        191530102082024,
        191530102052020,
        191530102053018,
        191530102052023,
        191530102082018,
        191530102053009,
        191530102053012,
        191530102052022,
        191530102082022,
        191530102052026,
        191530102082027,
        191530102053005,
        191530102053004,
        191530102052027,
        191530102082015,
        191530102052021,
        191530102053008,
        191530102052024,
        191530102052031,
        191530102053013,
        191530102053014,
        191530102053002,
        191530102053010,
        191530102053043,
        191530102073012,
        191530102053001,
        191530102053006,
        191530102073013,
        191530102052028,
        191530102053011,
        191530102053007,
        191530102053000,
        191530102082026,
        191530102052032,
        191530102053003,
        191530102053015
    ],
    "zs:housing10":760,
    "zs:pop10":1809
},
  "geometry": {"coordinates":[-93.61964999999999,41.72777],"type":"Point"}
}