{
  "type": "Feature",
  "properties": {
    "gn:gn_country":"US",
    "gn:gn_fcode":"PPL",
    "gn:gn_pop":0,
    "iso:country":"US",
    "name:eng_x_preferred":[
        "Cartwright"
    ],
    "name:fra_x_preferred":[
        "Cartwright"
    ],
    "qs_pg:aaroncc":"US",
    "qs_pg:gn_country":"US",
    "qs_pg:gn_fcode":"PPL",
    "qs_pg:gn_pop":0,
    "qs_pg:name":"Cartwright",
    "qs_pg:name_adm0":"United States",
    "qs_pg:name_adm1":"Texas",
    "qs_pg:photos":52,
    "qs_pg:photos_1k":11,
    "qs_pg:photos_9k":1,
    "qs_pg:photos_9r":2,
    "qs_pg:photos_all":52,
    "qs_pg:photos_sr":2,
    "qs_pg:pop_sr":0,
    "qs_pg:qs_pg_placetype":"locality",
    "qs_pg:qs_pg_placetype_gp":"Town",
    "qs_pg:woe_adm0":23424977,
    "woe:adm0_id":23424977,
    "woe:name_adm0":"United States",
    "woe:name_adm1":"Texas",
    "woe:placetype":"Town",
    "wof:name":"Cartwright",
    "wof:placetype":"locality"
},
  "geometry": {"coordinates":[-96.27164999999999,32.6593],"type":"Point"}
}