{
  "type": "Feature",
  "properties": {
    "gn:country":"US",
    "gn:fcode":"PPL",
    "gn:population":0,
    "iso:country":"US",
    "name:ara_x_preferred":[
        "\u0643\u0627\u0631\u062a\u0631\u0627\u064a\u062a"
    ],
    "name:ben_x_preferred":[
        "\u0995\u09be\u09b0\u09cd\u099f\u09b0\u09bf\u099f"
    ],
    "name:ell_x_preferred":[
        "\u039a\u03ac\u03c1\u03c4\u03c1\u03b1\u03b9\u03c4"
    ],
    "name:eng_x_preferred":[
        "Cartwright"
    ],
    "name:fas_x_preferred":[
        "\u06a9\u0627\u0631\u062a\u0631\u0627\u06cc\u062a"
    ],
    "name:fra_x_preferred":[
        "Cartwright"
    ],
    "name:heb_x_preferred":[
        "\u05e7\u05e8\u05d8\u05e8\u05d9\u05d9\u05d8"
    ],
    "name:hin_x_preferred":[
        "\u0915\u093e\u0930\u094d\u091f\u0930\u093e\u0907\u091f"
    ],
    "name:hun_x_preferred":[
        "Cartwright"
    ],
    "name:ind_x_preferred":[
        "Cartwright"
    ],
    "name:kor_x_preferred":[
        "\uce74\ud2b8\ub77c\uc774\ud2b8"
    ],
    "name:pol_x_preferred":[
        "Cartwright"
    ],
    "name:rus_x_preferred":[
        "\u041a\u0430\u0440\u0442\u0440\u0430\u0439\u0442"
    ],
    "name:spa_x_preferred":[
        "Cartwright"
    ],
    "name:swe_x_preferred":[
        "Cartwright"
    ],
    "name:tur_x_preferred":[
        "Cartwright"
    ],
    "name:urd_x_preferred":[
        "\u06a9\u0627\u0631\u0679\u0631\u0627\u0626\u0679"
    ],
    "name:vie_x_preferred":[
        "Cartwright"
    ],
    "name:zho_cn_x_preferred":[
        "\u5361\u7279\u8d56\u7279"
    ],
    "name:zho_tw_x_preferred":[
        "\u5361\u7279\u8cf4\u7279"
    ],
    "qs_pg:aaroncc":"US",
    "qs_pg:gn_country":"US",
    "qs_pg:gn_fcode":"PPL",
    "qs_pg:gn_pop":0,
    "qs_pg:name":"Cartwright",
    "qs_pg:name_adm0":"United States",
    "qs_pg:name_adm1":"Texas",
    "qs_pg:photos":52,
    "qs_pg:photos_1k":11,
    "qs_pg:photos_9k":1,
    "qs_pg:photos_9r":2,
    "qs_pg:photos_all":52,
    "qs_pg:photos_sr":2,
    "qs_pg:pop_sr":0,
    "qs_pg:qs_pg_placetype":"locality",
    "qs_pg:qs_pg_placetype_gp":"Town",
    "qs_pg:woe_adm0":23424977,
    "woe:adm0_id":23424977,
    "woe:name_adm0":"United States",
    "woe:name_adm1":"Texas",
    "woe:placetype":"Town",
    "wof:name":"Cartwright",
    "wof:placetype":"locality"
},
  "geometry": {"coordinates":[-96.27164999999999,32.6593],"type":"Point"}
}