{
  "type": "Feature",
  "properties": {
    "gn:admin1_code":"MI",
    "gn:admin2_code":"37.0",
    "gn:admin3_code":"82320.0",
    "gn:asciiname":"Westchester Heights",
    "gn:country_code":"US",
    "gn:dem":248,
    "gn:elevation":"247.0",
    "gn:feature_class":"P",
    "gn:feature_code":"PPL",
    "gn:name":"Westchester Heights",
    "gn:population":0,
    "gn:timezone":"America/Detroit",
    "iso:country":"US",
    "wof:name":"Westchester Heights",
    "wof:placetype":"locality"
},
  "geometry": {"coordinates":[-84.38109,42.9192],"type":"Point"}
}