{
  "type": "Feature",
  "properties": {
    "gn:admin1_code":"OH",
    "gn:admin2_code":"111.0",
    "gn:admin3_code":"31808.0",
    "gn:asciiname":"Benwood",
    "gn:country_code":"US",
    "gn:dem":257,
    "gn:elevation":"250.0",
    "gn:feature_class":"P",
    "gn:feature_code":"PPL",
    "gn:name":"Benwood",
    "gn:population":0,
    "gn:timezone":"America/New_York",
    "iso:country":"US",
    "name:deu_x_preferred":[
        "Benwood"
    ],
    "name:fra_x_preferred":[
        "Benwood"
    ],
    "name:spa_x_preferred":[
        "Benwood"
    ],
    "wof:name":"Benwood",
    "wof:placetype":"locality"
},
  "geometry": {"coordinates":[-81.00038000000001,39.68591],"type":"Point"}
}