{
  "type": "Feature",
  "properties": {
    "gn:gn_country":"US",
    "gn:gn_fcode":"PPL",
    "gn:gn_pop":0,
    "iso:country":"US",
    "name:deu_x_preferred":[
        "Gleason"
    ],
    "name:fra_x_preferred":[
        "Gleason"
    ],
    "name:ita_x_preferred":[
        "Gleason"
    ],
    "name:jpn_x_preferred":[
        "\u30b0\u30ea\u30fc\u30bd\u30f3"
    ],
    "name:nds_x_preferred":[
        "Gleason"
    ],
    "name:nld_x_preferred":[
        "Gleason"
    ],
    "name:por_x_preferred":[
        "Gleason"
    ],
    "name:ukr_x_preferred":[
        "\u0413\u043b\u0456\u0441\u043e\u043d"
    ],
    "qs_pg:aaroncc":"US",
    "qs_pg:gn_country":"US",
    "qs_pg:gn_fcode":"PPL",
    "qs_pg:gn_pop":0,
    "qs_pg:name":"Gleason",
    "qs_pg:name_adm0":"United States",
    "qs_pg:name_adm1":"Arkansas",
    "qs_pg:photos":342,
    "qs_pg:photos_1k":69,
    "qs_pg:photos_9k":2,
    "qs_pg:photos_9r":5,
    "qs_pg:photos_all":342,
    "qs_pg:photos_sr":5,
    "qs_pg:pop_sr":0,
    "qs_pg:qs_pg_placetype":"locality",
    "qs_pg:qs_pg_placetype_gp":"Town",
    "qs_pg:woe_adm0":23424977,
    "woe:adm0_id":23424977,
    "woe:name_adm0":"United States",
    "woe:name_adm1":"Arkansas",
    "woe:placetype":"Town",
    "wof:name":"Gleason",
    "wof:placetype":"locality"
},
  "geometry": {"coordinates":[-92.51599,35.11092],"type":"Point"}
}