{
  "type": "Feature",
  "properties": {
    "gn:admin1_code":"NM",
    "gn:admin2_code":"9",
    "gn:asciiname":"Claud",
    "gn:country_code":"US",
    "gn:dem":1353,
    "gn:elevation":"1354.0",
    "gn:feature_class":"P",
    "gn:feature_code":"PPL",
    "gn:name":"Claud",
    "gn:population":0,
    "gn:timezone":"America/Denver",
    "iso:country":"US",
    "wof:name":"Claud",
    "wof:placetype":"locality"
},
  "geometry": {"coordinates":[-103.17912,34.59424],"type":"Point"}
}