{
  "type": "Feature",
  "properties": {
    "gn:admin1_code":"VA",
    "gn:admin2_code":"75",
    "gn:asciiname":"Cedar Point",
    "gn:country_code":"US",
    "gn:dem":51,
    "gn:elevation":"47.0",
    "gn:feature_class":"P",
    "gn:feature_code":"PPL",
    "gn:name":"Cedar Point",
    "gn:population":0,
    "gn:timezone":"America/New_York",
    "iso:country":"US",
    "wof:name":"Cedar Point",
    "wof:placetype":"locality"
},
  "geometry": {"coordinates":[-77.90944,37.69181],"type":"Point"}
}