{
  "type": "Feature",
  "properties": {
    "gn:admin1_code":"FL",
    "gn:admin2_code":"105.0",
    "gn:asciiname":"Grove Shores Mobile Colony",
    "gn:country_code":"US",
    "gn:dem":46,
    "gn:elevation":"43.0",
    "gn:feature_class":"P",
    "gn:feature_code":"PPL",
    "gn:name":"Grove Shores Mobile Colony",
    "gn:population":0,
    "gn:timezone":"America/New_York",
    "iso:country":"US",
    "wof:name":"Grove Shores Mobile Colony",
    "wof:placetype":"locality"
},
  "geometry": {"coordinates":[-81.6591,27.9912],"type":"Point"}
}