{
  "type": "Feature",
  "properties": {
    "gn:admin1_code":"SC",
    "gn:admin2_code":"43.0",
    "gn:asciiname":"Willie Towne",
    "gn:country_code":"US",
    "gn:dem":14,
    "gn:elevation":"12.0",
    "gn:feature_class":"P",
    "gn:feature_code":"PPL",
    "gn:name":"Willie Towne",
    "gn:population":0,
    "gn:timezone":"America/New_York",
    "iso:country":"US",
    "wof:name":"Willie Towne",
    "wof:placetype":"locality"
},
  "geometry": {"coordinates":[-79.43311,33.54045],"type":"Point"}
}