{
  "type": "Feature",
  "properties": {
    "gn:admin1_code":"LA",
    "gn:admin2_code":"57.0",
    "gn:asciiname":"Chegby",
    "gn:country_code":"US",
    "gn:dem":6,
    "gn:elevation":"1.0",
    "gn:feature_class":"P",
    "gn:feature_code":"PPL",
    "gn:name":"Chegby",
    "gn:population":0,
    "gn:timezone":"America/Chicago",
    "iso:country":"US",
    "wof:name":"Chegby",
    "wof:placetype":"locality"
},
  "geometry": {"coordinates":[-90.80732,29.87854],"type":"Point"}
}