{
  "type": "Feature",
  "properties": {
    "gn:admin1_code":"WA",
    "gn:admin2_code":"31.0",
    "gn:asciiname":"Shine-Gri-La",
    "gn:country_code":"US",
    "gn:dem":7,
    "gn:elevation":"3.0",
    "gn:feature_class":"P",
    "gn:feature_code":"PPL",
    "gn:name":"Shine-Gri-La",
    "gn:population":0,
    "gn:timezone":"America/Los_Angeles",
    "iso:country":"US",
    "wof:name":"Shine-Gri-La",
    "wof:placetype":"locality"
},
  "geometry": {"coordinates":[-122.68904999999999,47.86954],"type":"Point"}
}