{
  "type": "Feature",
  "properties": {
    "gn:country":"US",
    "gn:fcode":"PPL",
    "gn:population":0,
    "iso:country":"US",
    "name:ara_x_preferred":[
        "\u0647\u0627\u0631\u062a\u0641\u0648\u0631\u062f"
    ],
    "name:eng_x_preferred":[
        "Hartford"
    ],
    "name:jpn_x_preferred":[
        "\u30cf\u30fc\u30c8\u30d5\u30a9\u30fc\u30c9"
    ],
    "name:rus_x_preferred":[
        "\u0425\u0430\u0440\u0442\u0444\u043e\u0440\u0434"
    ],
    "name:ukr_x_preferred":[
        "\u0425\u0430\u0440\u0442\u0444\u043e\u0440\u0434"
    ],
    "name:und_x_variant":[
        "Centerville"
    ],
    "name:urd_x_preferred":[
        "\u06c1\u0627\u0631\u0679\u0641\u0648\u0631\u0688\u060c \u0648\u0631\u0645\u0648\u0646\u0679"
    ],
    "qs_pg:aaroncc":"US",
    "qs_pg:gn_country":"US",
    "qs_pg:gn_fcode":"PPL",
    "qs_pg:gn_pop":0,
    "qs_pg:name":"Hartford",
    "qs_pg:name_adm0":"United States",
    "qs_pg:name_adm1":"Vermont",
    "qs_pg:photos":369,
    "qs_pg:photos_1k":75,
    "qs_pg:photos_9k":6,
    "qs_pg:photos_9r":7,
    "qs_pg:photos_all":1458,
    "qs_pg:photos_sr":6,
    "qs_pg:pop_sr":0,
    "qs_pg:qs_pg_placetype":"locality",
    "qs_pg:qs_pg_placetype_gp":"Town",
    "qs_pg:woe_adm0":23424977,
    "woe:adm0_id":23424977,
    "woe:name_adm0":"United States",
    "woe:name_adm1":"Vermont",
    "woe:placetype":"Town",
    "wof:name":"Hartford",
    "wof:placetype":"locality",
    "wof:population":9779
},
  "geometry": {"coordinates":[-72.33842,43.66063],"type":"Point"}
}