{
  "type": "Feature",
  "properties": {
    "gn:admin1_code":"TN",
    "gn:admin2_code":"49",
    "gn:asciiname":"Jonesville",
    "gn:country_code":"US",
    "gn:dem":521,
    "gn:elevation":"520.0",
    "gn:feature_class":"P",
    "gn:feature_code":"PPL",
    "gn:name":"Jonesville",
    "gn:population":0,
    "gn:timezone":"America/Chicago",
    "iso:country":"US",
    "name:ceb_x_preferred":[
        "Jonesville"
    ],
    "name:cym_x_preferred":[
        "Jonesville"
    ],
    "name:deu_x_preferred":[
        "Jonesville"
    ],
    "name:fra_x_preferred":[
        "Jonesville"
    ],
    "name:ita_x_preferred":[
        "Jonesville"
    ],
    "name:nld_x_preferred":[
        "Jonesville"
    ],
    "name:pol_x_preferred":[
        "Jonesville"
    ],
    "name:por_x_preferred":[
        "Jonesville"
    ],
    "name:rus_x_preferred":[
        "\u0414\u0436\u043e\u043d\u0441\u0432\u0438\u043b\u043b"
    ],
    "name:spa_x_preferred":[
        "Jonesville"
    ],
    "name:srp_x_preferred":[
        "\u040f\u043e\u0443\u043d\u0441\u0432\u0438\u043b"
    ],
    "name:swe_x_preferred":[
        "Jonesville"
    ],
    "name:vol_x_preferred":[
        "Jonesville"
    ],
    "wof:name":"Jonesville",
    "wof:placetype":"locality"
},
  "geometry": {"coordinates":[-84.93718,36.1834],"type":"Point"}
}