{
  "type": "Feature",
  "properties": {
    "gn:admin1_code":"FL",
    "gn:admin2_code":"57",
    "gn:asciiname":"Horseshoe Estates",
    "gn:country_code":"US",
    "gn:dem":19,
    "gn:elevation":"11.0",
    "gn:feature_class":"P",
    "gn:feature_code":"PPL",
    "gn:name":"Horseshoe Estates",
    "gn:population":0,
    "gn:timezone":"America/New_York",
    "iso:country":"US",
    "wof:name":"Horseshoe Estates",
    "wof:placetype":"locality"
},
  "geometry": {"coordinates":[-82.60209999999999,28.0946],"type":"Point"}
}