{
  "type": "Feature",
  "properties": {
    "gn:admin1_code":"WI",
    "gn:admin2_code":"25.0",
    "gn:admin3_code":"48000.0",
    "gn:asciiname":"Elmside",
    "gn:country_code":"US",
    "gn:dem":273,
    "gn:elevation":"271.0",
    "gn:feature_class":"P",
    "gn:feature_code":"PPL",
    "gn:name":"Elmside",
    "gn:population":0,
    "gn:timezone":"America/Chicago",
    "iso:country":"US",
    "wof:name":"Elmside",
    "wof:placetype":"locality"
},
  "geometry": {"coordinates":[-89.34401,43.09222000000001],"type":"Point"}
}