{
  "type": "Feature",
  "properties": {
    "gn:elevation":17,
    "iso:country":"US",
    "name:eng_x_preferred":[
        "Linfield Oaks"
    ],
    "qs:gn_adm0_cc":"US",
    "qs:gn_fcode":"PPL",
    "qs:gn_local":5372223,
    "qs:gn_nam_loc":"Menlo Park, San Mateo, California, US",
    "qs:gn_namadm1":"CA",
    "qs:gn_name":"Linfield Oaks",
    "qs:local_max":3410,
    "qs:local_sum":15033,
    "qs:localhoods":11,
    "qs:name":"Linfield Oaks",
    "qs:name_adm0":"United States",
    "qs:name_adm1":"California",
    "qs:name_adm2":"San Mateo",
    "qs:name_local":"Menlo Park",
    "qs:photo_max":239,
    "qs:photo_sum":1010,
    "qs:placetype":"Suburb",
    "qs:quad_count":23,
    "qs:woe_adm0":23424977,
    "qs:woe_adm1":2347563,
    "qs:woe_adm2":12587710,
    "qs:woe_lau":0,
    "qs:woe_local":2449435,
    "qs:woe_ver":"7.10.0",
    "wof:lang":[
        "eng"
    ],
    "wof:name":"Linfield Oaks",
    "wof:placetype":"neighbourhood",
    "wof:population":1353,
    "zs:blockids":[
        60816125003002,
        60816125003011,
        60816125003018,
        60816125003019,
        60816125003012,
        60816125003003,
        60816125003013,
        60816125003007,
        60816125003015,
        60816125003010,
        60816125003009,
        60816125003004,
        60816125003001,
        60816125003006,
        60816125003016,
        60816125003014,
        60816125003000,
        60816125003017
    ],
    "zs:housing10":676,
    "zs:pop10":1353
},
  "geometry": {"coordinates":[-122.170849,37.453817],"type":"Point"}
}