{
  "type": "Feature",
  "properties": {
    "gn:country":"US",
    "gn:fcode":"PPL",
    "gn:population":0,
    "iso:country":"US",
    "name:azb_x_preferred":[
        "\u06a9\u0627\u06cc"
    ],
    "name:cym_x_preferred":[
        "Coy"
    ],
    "name:deu_x_preferred":[
        "Coy"
    ],
    "name:eng_x_preferred":[
        "Coy"
    ],
    "name:fas_x_preferred":[
        "\u06a9\u0627\u06cc"
    ],
    "name:fra_x_preferred":[
        "Coy"
    ],
    "name:jpn_x_preferred":[
        "\u30b3\u30a4"
    ],
    "name:zho_x_preferred":[
        "\u79d1\u4f0a"
    ],
    "qs_pg:aaroncc":"US",
    "qs_pg:gn_country":"US",
    "qs_pg:gn_fcode":"PPL",
    "qs_pg:gn_pop":0,
    "qs_pg:name":"Coy",
    "qs_pg:name_adm0":"United States",
    "qs_pg:name_adm1":"Alabama",
    "qs_pg:photos_9r":0,
    "qs_pg:photos_sr":0,
    "qs_pg:pop_sr":0,
    "qs_pg:qs_pg_placetype":"locality",
    "qs_pg:qs_pg_placetype_gp":"Town",
    "qs_pg:woe_adm0":23424977,
    "woe:adm0_id":23424977,
    "woe:name_adm0":"United States",
    "woe:name_adm1":"Alabama",
    "woe:placetype":"Town",
    "wof:name":"Coy",
    "wof:placetype":"locality"
},
  "geometry": {"coordinates":[-87.46277000000001,31.89487],"type":"Point"}
}