{
  "type": "Feature",
  "properties": {
    "gn:admin1_code":"MS",
    "gn:admin2_code":"13.0",
    "gn:asciiname":"Sabougla",
    "gn:country_code":"US",
    "gn:dem":102,
    "gn:elevation":"102.0",
    "gn:feature_class":"P",
    "gn:feature_code":"PPL",
    "gn:name":"Sabougla",
    "gn:population":0,
    "gn:timezone":"America/Chicago",
    "iso:country":"US",
    "wof:name":"Sabougla",
    "wof:placetype":"locality"
},
  "geometry": {"coordinates":[-89.46424,33.77595],"type":"Point"}
}