{
  "type": "Feature",
  "properties": {
    "gn:admin1_code":"IL",
    "gn:admin2_code":"75.0",
    "gn:admin3_code":"44979.0",
    "gn:asciiname":"Alonzo",
    "gn:country_code":"US",
    "gn:dem":206,
    "gn:elevation":"204.0",
    "gn:feature_class":"P",
    "gn:feature_code":"PPL",
    "gn:name":"Alonzo",
    "gn:population":0,
    "gn:timezone":"America/Chicago",
    "iso:country":"US",
    "wof:name":"Alonzo",
    "wof:placetype":"locality"
},
  "geometry": {"coordinates":[-87.73114,40.5667],"type":"Point"}
}