{
  "type": "Feature",
  "properties": {
    "gn:admin1_code":"PA",
    "gn:admin2_code":"131.0",
    "gn:admin3_code":"42616.0",
    "gn:asciiname":"Avery",
    "gn:country_code":"US",
    "gn:dem":335,
    "gn:elevation":"318.0",
    "gn:feature_class":"P",
    "gn:feature_code":"PPL",
    "gn:name":"Avery",
    "gn:population":0,
    "gn:timezone":"America/New_York",
    "iso:country":"US",
    "name:cat_x_preferred":[
        "Avery"
    ],
    "name:ceb_x_preferred":[
        "Avery"
    ],
    "name:ces_x_preferred":[
        "Avery"
    ],
    "name:deu_x_preferred":[
        "Avery"
    ],
    "name:fin_x_preferred":[
        "Avery"
    ],
    "name:fra_x_preferred":[
        "Avery"
    ],
    "name:ita_x_preferred":[
        "Avery"
    ],
    "name:jpn_x_preferred":[
        "\u30a8\u30a4\u30f4\u30ea\u30fc"
    ],
    "name:kor_x_preferred":[
        "\uc5d0\uc774\ubc84\ub9ac"
    ],
    "name:nld_x_preferred":[
        "Avery"
    ],
    "name:pol_x_preferred":[
        "Avery"
    ],
    "name:por_x_preferred":[
        "Avery"
    ],
    "name:rus_x_preferred":[
        "\u042d\u0432\u0435\u0440\u0438"
    ],
    "name:spa_x_preferred":[
        "Avery"
    ],
    "name:srp_x_preferred":[
        "\u0415\u0458\u0432\u0435\u0440\u0438"
    ],
    "name:swe_x_preferred":[
        "D\u00f6ds\u00e4tare#Avery"
    ],
    "name:ukr_x_preferred":[
        "\u0415\u0439\u0432\u0435\u0440\u0456"
    ],
    "name:vol_x_preferred":[
        "Avery"
    ],
    "wof:name":"Avery",
    "wof:placetype":"locality"
},
  "geometry": {"coordinates":[-75.93103000000001,41.63869],"type":"Point"}
}