{
  "type": "Feature",
  "properties": {
    "iso:country":"US",
    "name:eng_x_preferred":[
        "South Shoreview"
    ],
    "name:unk_x_variant":[
        "South Shoreview"
    ],
    "qs:gn_adm0_cc":"US",
    "qs:gn_local":5392423,
    "qs:gn_nam_loc":"San Mateo, San Mateo, California, US",
    "qs:gn_namadm1":"CA",
    "qs:local_max":12077,
    "qs:local_sum":31677,
    "qs:localhoods":37,
    "qs:name":"South Shoreview",
    "qs:name_adm0":"United States",
    "qs:name_adm1":"California",
    "qs:name_adm2":"San Mateo",
    "qs:name_local":"San Mateo",
    "qs:photo_max":106,
    "qs:photo_sum":279,
    "qs:placetype":"Suburb",
    "qs:quad_count":17,
    "qs:woe_adm0":23424977,
    "qs:woe_adm1":2347563,
    "qs:woe_adm2":12587710,
    "qs:woe_lau":0,
    "qs:woe_local":2488142,
    "qs:woe_ver":"7.10.0",
    "wof:lang":[
        "eng"
    ],
    "wof:name":"South Shoreview",
    "wof:placetype":"neighbourhood",
    "wof:population":2199,
    "zs:blockids":[
        60816077013001,
        60816077013000,
        60816077022000,
        60816077013010,
        60816077013003,
        60816077013006,
        60816077013008,
        60816077013007,
        60816077013011,
        60816077022002,
        60816077013002,
        60816077013004,
        60816077021000,
        60816077013005,
        60816077022001,
        60816077022003,
        60816077013012,
        60816077013009
    ],
    "zs:housing10":645,
    "zs:pop10":2199
},
  "geometry": {"coordinates":[-122.298805,37.572038],"type":"Point"}
}