{
  "type": "Feature",
  "properties": {
    "iso:country":"US",
    "name:eng_x_preferred":[
        "Ho\u2018olehua Ahupua`a"
    ],
    "qs:gn_adm0_cc":"US",
    "qs:gn_local":5856351,
    "qs:gn_nam_loc":"tenney village",
    "qs:gn_namadm1":"HI",
    "qs:local_max":152,
    "qs:local_sum":168,
    "qs:localhoods":2,
    "qs:name":"Ho\u2018olehua Ahupua`a",
    "qs:name_adm0":"United States",
    "qs:name_adm1":"Hawaii",
    "qs:name_adm2":"Maui",
    "qs:name_local":"Hoolehua",
    "qs:photo_max":14,
    "qs:photo_sum":16,
    "qs:placetype":"Suburb",
    "qs:quad_count":3,
    "qs:woe_adm0":23424977,
    "qs:woe_adm1":2347570,
    "qs:woe_adm2":12588033,
    "qs:woe_lau":0,
    "qs:woe_local":2424067,
    "qs:woe_ver":"7.10.0",
    "qs_pg:name":"Ho\u2018olehua Ahupua`a",
    "qs_pg:name_adm0":"United States",
    "qs_pg:name_adm1":"Hawaii",
    "qs_pg:photos":17,
    "qs_pg:photos_1k":3,
    "qs_pg:photos_9k":1,
    "qs_pg:photos_9r":1,
    "qs_pg:photos_all":17,
    "qs_pg:photos_sr":1,
    "qs_pg:pop_sr":0,
    "qs_pg:qs_pg_placetype":"neighbourhood",
    "qs_pg:qs_pg_placetype_gp":"Suburb",
    "qs_pg:woe_adm0":23424977,
    "woe:adm0_id":23424977,
    "woe:name_adm0":"United States",
    "woe:name_adm1":"Hawaii",
    "woe:placetype":"Suburb",
    "wof:lang":[
        "eng"
    ],
    "wof:name":"Ho\u2018olehua Ahupua`a",
    "wof:placetype":"neighbourhood",
    "wof:population":11,
    "zs:blockids":[
        150090318011123,
        150090318011217,
        150090318011076,
        150090318011220
    ],
    "zs:housing10":7,
    "zs:pop10":11
},
  "geometry": {"coordinates":[-157.0942,21.139589],"type":"Point"}
}