{
  "type": "Feature",
  "properties": {
    "gn:gn_country":"US",
    "gn:gn_fcode":"PPL",
    "gn:gn_pop":0,
    "iso:country":"US",
    "name:ceb_x_preferred":[
        "Rock Run"
    ],
    "qs_pg:aaroncc":"US",
    "qs_pg:gn_country":"US",
    "qs_pg:gn_fcode":"PPL",
    "qs_pg:gn_pop":0,
    "qs_pg:name":"Rock Run",
    "qs_pg:name_adm0":"United States",
    "qs_pg:name_adm1":"Maryland",
    "qs_pg:photos":727,
    "qs_pg:photos_1k":147,
    "qs_pg:photos_9k":3,
    "qs_pg:photos_9r":5,
    "qs_pg:photos_all":727,
    "qs_pg:photos_sr":8,
    "qs_pg:pop_sr":0,
    "qs_pg:qs_pg_placetype":"locality",
    "qs_pg:qs_pg_placetype_gp":"Town",
    "qs_pg:woe_adm0":23424977,
    "woe:adm0_id":23424977,
    "woe:name_adm0":"United States",
    "woe:name_adm1":"Maryland",
    "woe:placetype":"Town",
    "wof:name":"Rock Run",
    "wof:placetype":"locality"
},
  "geometry": {"coordinates":[-76.14301,39.60817],"type":"Point"}
}