{
  "type": "Feature",
  "properties": {
    "iso:country":"US",
    "name:eng_x_preferred":[
        "Quoddy"
    ],
    "qs:gn_adm0_cc":"US",
    "qs:gn_local":4963486,
    "qs:gn_nam_loc":"eastport",
    "qs:gn_namadm1":"ME",
    "qs:local_max":8,
    "qs:local_sum":8,
    "qs:localhoods":1,
    "qs:name":"Quoddy",
    "qs:name_adm0":"United States",
    "qs:name_adm1":"Maine",
    "qs:name_adm2":"Washington",
    "qs:name_local":"Eastport",
    "qs:photo_max":3,
    "qs:photo_sum":8,
    "qs:placetype":"Suburb",
    "qs:quad_count":4,
    "qs:woe_adm0":23424977,
    "qs:woe_adm1":2347578,
    "qs:woe_adm2":12588674,
    "qs:woe_lau":0,
    "qs:woe_local":2396558,
    "qs:woe_ver":"7.10.0",
    "wd:wordcount":29,
    "wof:lang":[
        "eng"
    ],
    "wof:name":"Quoddy",
    "wof:placetype":"neighbourhood",
    "wof:population":232,
    "zs:blockids":[
        230299557001119,
        230299557001032,
        230299557001030,
        230299557001123,
        230299557001018,
        230299557001021,
        230299557001120,
        230299557001020,
        230299557001027,
        230299557001125,
        230299557001116,
        230299557001024,
        230299557001040,
        230299557001017,
        230299557001031,
        230299557001019,
        230299557001117,
        230299557001118,
        230299557001035,
        230299557001004,
        230299557001025,
        230299557001034,
        230299557001124,
        230299557001039,
        230299557001028,
        230299557001115,
        230299557001036,
        230299557001008,
        230299557001113,
        230299557001114,
        230299557001026,
        230299557001029,
        230299557001022,
        230299557001037
    ],
    "zs:housing10":175,
    "zs:pop10":232
},
  "geometry": {"coordinates":[-67.02278099999999,44.92592],"type":"Point"}
}