{
  "type": "Feature",
  "properties": {
    "gn:admin1_code":"PA",
    "gn:admin2_code":"71.0",
    "gn:admin3_code":"81168.0",
    "gn:asciiname":"Lexington",
    "gn:country_code":"US",
    "gn:dem":175,
    "gn:elevation":"178.0",
    "gn:feature_class":"P",
    "gn:feature_code":"PPL",
    "gn:name":"Lexington",
    "gn:population":0,
    "gn:timezone":"America/New_York",
    "iso:country":"US",
    "name:afr_x_preferred":[
        "Lexington"
    ],
    "name:bre_x_preferred":[
        "Lexington"
    ],
    "name:bul_x_preferred":[
        "\u041b\u0435\u043a\u0441\u0438\u043d\u0433\u0442\u044a\u043d"
    ],
    "name:cat_x_preferred":[
        "Lexington"
    ],
    "name:ceb_x_preferred":[
        "Lexington"
    ],
    "name:ces_x_preferred":[
        "Lexington"
    ],
    "name:dan_x_preferred":[
        "Lexington"
    ],
    "name:deu_x_preferred":[
        "Lexington"
    ],
    "name:epo_x_preferred":[
        "Lexington"
    ],
    "name:fas_x_preferred":[
        "\u0644\u06a9\u0633\u06cc\u0646\u06af\u062a\u0648\u0646"
    ],
    "name:fin_x_preferred":[
        "Lexington"
    ],
    "name:fra_x_preferred":[
        "Lexington"
    ],
    "name:heb_x_preferred":[
        "\u05dc\u05e7\u05e1\u05d9\u05e0\u05d2\u05d8\u05d5\u05df"
    ],
    "name:hun_x_preferred":[
        "Lexington"
    ],
    "name:ido_x_preferred":[
        "Lexington"
    ],
    "name:ita_x_preferred":[
        "Lexington"
    ],
    "name:jpn_x_preferred":[
        "\u30ec\u30ad\u30b7\u30f3\u30c8\u30f3"
    ],
    "name:kor_x_preferred":[
        "\ub809\uc2f1\ud134"
    ],
    "name:nld_x_preferred":[
        "Lexington"
    ],
    "name:nor_x_preferred":[
        "Lexington"
    ],
    "name:pol_x_preferred":[
        "Lexington"
    ],
    "name:por_x_preferred":[
        "Lexington"
    ],
    "name:rus_x_preferred":[
        "\u041b\u0435\u043a\u0441\u0438\u043d\u0433\u0442\u043e\u043d"
    ],
    "name:scn_x_preferred":[
        "Lexington"
    ],
    "name:slk_x_preferred":[
        "Lexington"
    ],
    "name:spa_x_preferred":[
        "Lexington"
    ],
    "name:srp_x_preferred":[
        "\u041b\u0435\u043a\u0441\u0438\u043d\u0433\u0442\u043e\u043d"
    ],
    "name:swa_x_preferred":[
        "Lexington"
    ],
    "name:swe_x_preferred":[
        "Lexington"
    ],
    "name:ukr_x_preferred":[
        "\u041b\u0435\u043a\u0441\u0456\u043d\u0433\u0442\u043e\u043d"
    ],
    "name:urd_x_preferred":[
        "\u0644\u06cc\u06a9\u0633\u0646\u06af\u0679\u0646"
    ],
    "name:vol_x_preferred":[
        "Lexington"
    ],
    "name:war_x_preferred":[
        "Lexington"
    ],
    "name:zho_x_preferred":[
        "\u5217\u514b\u661f\u6566"
    ],
    "wof:name":"Lexington",
    "wof:placetype":"locality"
},
  "geometry": {"coordinates":[-76.29968000000002,40.18843],"type":"Point"}
}