{
  "type": "Feature",
  "properties": {
    "gn:admin1_code":"VT",
    "gn:admin2_code":"21.0",
    "gn:admin3_code":"44125.0",
    "gn:asciiname":"Brewers Corner",
    "gn:country_code":"US",
    "gn:dem":555,
    "gn:elevation":"544.0",
    "gn:feature_class":"P",
    "gn:feature_code":"PPL",
    "gn:name":"Brewers Corner",
    "gn:population":0,
    "gn:timezone":"America/New_York",
    "iso:country":"US",
    "wof:name":"Brewers Corner",
    "wof:placetype":"locality"
},
  "geometry": {"coordinates":[-72.87676999999999,43.61923],"type":"Point"}
}