{
  "type": "Feature",
  "properties": {
    "gn:admin1_code":"OH",
    "gn:admin2_code":"63.0",
    "gn:admin3_code":"64066.0",
    "gn:asciiname":"Murphys",
    "gn:country_code":"US",
    "gn:dem":244,
    "gn:elevation":"245.0",
    "gn:feature_class":"P",
    "gn:feature_code":"PPL",
    "gn:name":"Murphys",
    "gn:population":0,
    "gn:timezone":"America/New_York",
    "iso:country":"US",
    "name:deu_x_preferred":[
        "Murphys"
    ],
    "name:eng_x_preferred":[
        "Murphys"
    ],
    "name:und_x_variant":[
        "Murphys Siding",
        "Murphy's Siding",
        "Murphy"
    ],
    "wof:name":"Murphys",
    "wof:placetype":"locality"
},
  "geometry": {"coordinates":[-83.72688000000002,41.08339],"type":"Point"}
}