{
  "type": "Feature",
  "properties": {
    "iso:country":"US",
    "name:eng_x_preferred":[
        "Hewitt Farm"
    ],
    "name:unk_x_variant":[
        "Hewitt Farm"
    ],
    "qs:gn_adm0_cc":"US",
    "qs:gn_fcode":"PPLX",
    "qs:gn_local":4776222,
    "qs:gn_nam_loc":"Norfolk, Norfolk, Virginia, US",
    "qs:gn_namadm1":"VA",
    "qs:gn_name":"Hewitt Farm",
    "qs:local_max":6835,
    "qs:local_sum":36858,
    "qs:localhoods":52,
    "qs:name":"Hewitt Farm",
    "qs:name_adm0":"United States",
    "qs:name_adm1":"Virginia",
    "qs:name_adm2":"Norfolk City",
    "qs:name_local":"Norfolk",
    "qs:photo_max":197,
    "qs:photo_sum":219,
    "qs:placetype":"Suburb",
    "qs:quad_count":7,
    "qs:woe_adm0":23424977,
    "qs:woe_adm1":2347605,
    "qs:woe_adm2":12590391,
    "qs:woe_lau":0,
    "qs:woe_local":2460389,
    "qs:woe_ver":"7.10.0",
    "wof:lang":[
        "eng"
    ],
    "wof:name":"Hewitt Farm",
    "wof:placetype":"neighbourhood",
    "wof:population":2376,
    "zs:blockids":[
        517100066032014,
        517100066032012,
        517100066021003,
        517100066051014,
        517100066022001,
        517100066022015,
        517100066021009,
        517100066022029,
        517100066032011,
        517100066032028,
        517100066021002,
        517100066021011,
        517100066031008,
        517100066022006,
        517100066032030,
        517100066051016,
        517100066021006,
        517100066021007,
        517100066022016,
        517100066032029,
        517100066051012,
        517100066032008,
        517100066022025,
        517100066032003,
        517100066022002,
        517100066022003,
        517100066022031,
        517100066022014,
        517100066022028,
        517100066032007,
        517100066032002,
        517100066031019,
        517100066032031,
        517100066051015,
        517100066021012,
        517100066021010,
        517100066022027,
        517100066051011,
        517100066032006,
        517100066022012,
        517100066021008,
        517100066022030,
        517100066022032,
        517100066032015,
        517100066032010,
        517100066032013,
        517100066032032,
        517100066051017,
        517100066022013,
        517100066022017,
        517100066032009,
        517100066022000,
        517100066063000,
        517100066022033,
        517100066032016,
        517100066032005,
        517100066032017,
        517100066032018,
        517100066022005,
        517100066051010,
        517100066022026
    ],
    "zs:housing10":940,
    "zs:pop10":2376
},
  "geometry": {"coordinates":[-76.22620999999999,36.926698],"type":"Point"}
}