{
  "type": "Feature",
  "properties": {
    "gn:admin1_code":"IL",
    "gn:admin2_code":"35.0",
    "gn:admin3_code":"31537.0",
    "gn:asciiname":"Timothy",
    "gn:country_code":"US",
    "gn:dem":184,
    "gn:elevation":"182.0",
    "gn:feature_class":"P",
    "gn:feature_code":"PPL",
    "gn:name":"Timothy",
    "gn:population":0,
    "gn:timezone":"America/Chicago",
    "iso:country":"US",
    "wof:name":"Timothy",
    "wof:placetype":"locality"
},
  "geometry": {"coordinates":[-88.12948,39.30309000000001],"type":"Point"}
}