{
  "type": "Feature",
  "properties": {
    "gn:admin1_code":"VA",
    "gn:admin2_code":"115",
    "gn:asciiname":"Redart",
    "gn:country_code":"US",
    "gn:dem":16,
    "gn:elevation":"1.0",
    "gn:feature_class":"P",
    "gn:feature_code":"PPL",
    "gn:name":"Redart",
    "gn:population":0,
    "gn:timezone":"America/New_York",
    "iso:country":"US",
    "wof:name":"Redart",
    "wof:placetype":"locality"
},
  "geometry": {"coordinates":[-76.30161,37.47013],"type":"Point"}
}