{
  "type": "Feature",
  "properties": {
    "iso:country":"US",
    "name:eng_x_preferred":[
        "Coconut Creek"
    ],
    "wof:name":"Coconut Creek",
    "wof:placetype":"neighbourhood",
    "wof:population":2552,
    "zs:area_m":2577153.305269,
    "zs:blockids":[
        120710019122011,
        120710019122008,
        120710019122012,
        120710019122016,
        120710019122004,
        120710019121005,
        120710019141014,
        120710019141004,
        120710019142002,
        120710019141013,
        120710019121020,
        120710019121009,
        120710019142023,
        120710019141006,
        120710019141001,
        120710019141008,
        120710019141009,
        120710019141002,
        120710019121006,
        120710019142032,
        120710019141003,
        120710019121010,
        120710019121013,
        120710019122003,
        120710019122009,
        120710019142019,
        120710019142024,
        120710019142020,
        120710019141012,
        120710019121015,
        120710019121014,
        120710019122010,
        120710019121011,
        120710019143030,
        120710019122007,
        120710019141011,
        120710019122005,
        120710019142029,
        120710019122006,
        120710019141015,
        120710019141007,
        120710019121019,
        120710019121008,
        120710019141005,
        120710019142026,
        120710019142021,
        120710019122017,
        120710019142018,
        120710019141010,
        120710019142031,
        120710019142030,
        120710019121012,
        120710019141000,
        120710019142025,
        120710019142061,
        120710019142022
    ],
    "zs:housing10":1872,
    "zs:label":"Coconut Creek",
    "zs:pop10":2552
},
  "geometry": {"coordinates":[-81.962175,26.508425],"type":"Point"}
}