{
  "type": "Feature",
  "properties": {
    "iso:country":"US",
    "name:eng_x_preferred":[
        "Arch Beach Heights"
    ],
    "wof:name":"Arch Beach Heights",
    "wof:placetype":"neighbourhood",
    "wof:population":1137,
    "zs:area_m":1978244.585324,
    "zs:blockids":[
        60590626204004,
        60590626204012,
        60590626324003,
        60590626324002,
        60590626204005,
        60590626204001,
        60590626204018,
        60590626204003,
        60590626324000,
        60590626204007,
        60590626204008,
        60590626204015,
        60590626204014,
        60590626204011,
        60590626204006,
        60590626204002,
        60590626204010,
        60590626204016,
        60590626204017,
        60590626324001,
        60590626204009,
        60590626201007,
        60590626204013
    ],
    "zs:housing10":533,
    "zs:label":"Arch Beach Heights",
    "zs:pop10":1137
},
  "geometry": {"coordinates":[-117.747702,33.531087],"type":"Point"}
}