{
  "type": "Feature",
  "properties": {
    "iso:country":"US",
    "wof:name":"Linkhorn Park",
    "wof:placetype":"neighbourhood"
},
  "geometry": {"coordinates":[-75.9894439282438,36.86689536909039],"type":"Point"}
}