{
  "type": "Feature",
  "properties": {
    "gn:admin1_code":"VA",
    "gn:admin2_code":"65",
    "gn:asciiname":"Stage Junction",
    "gn:country_code":"US",
    "gn:dem":123,
    "gn:elevation":"123.0",
    "gn:feature_class":"P",
    "gn:feature_code":"PPL",
    "gn:name":"Stage Junction",
    "gn:population":0,
    "gn:timezone":"America/New_York",
    "iso:country":"US",
    "wof:name":"Stage Junction",
    "wof:placetype":"locality"
},
  "geometry": {"coordinates":[-78.15333000000003,37.79098],"type":"Point"}
}