{
  "type": "Feature",
  "properties": {
    "gn:admin1_code":"GA",
    "gn:admin2_code":"285.0",
    "gn:asciiname":"Brays Lakeview",
    "gn:country_code":"US",
    "gn:dem":214,
    "gn:elevation":"211.0",
    "gn:feature_class":"P",
    "gn:feature_code":"PPL",
    "gn:name":"Brays Lakeview",
    "gn:population":0,
    "gn:timezone":"America/New_York",
    "iso:country":"US",
    "name:eng_x_preferred":[
        "Brays Lakeview"
    ],
    "name:und_x_variant":[
        "Bray's Lakeview"
    ],
    "wof:name":"Brays Lakeview",
    "wof:placetype":"locality"
},
  "geometry": {"coordinates":[-84.97133000000002,33.14762],"type":"Point"}
}