{
  "type": "Feature",
  "properties": {
    "gn:admin1_code":"VA",
    "gn:admin2_code":"31",
    "gn:asciiname":"Sherwill",
    "gn:country_code":"US",
    "gn:dem":251,
    "gn:elevation":"251.0",
    "gn:feature_class":"P",
    "gn:feature_code":"PPL",
    "gn:name":"Sherwill",
    "gn:population":0,
    "gn:timezone":"America/New_York",
    "iso:country":"US",
    "name:eng_x_preferred":[
        "Sherwill"
    ],
    "name:und_x_variant":[
        "Wyatt Shop"
    ],
    "wof:name":"Sherwill",
    "wof:placetype":"locality"
},
  "geometry": {"coordinates":[-78.95974,37.28237],"type":"Point"}
}