{
  "type": "Feature",
  "properties": {
    "gn:admin1_code":"MD",
    "gn:admin2_code":"9.0",
    "gn:asciiname":"Mary E White Estate",
    "gn:country_code":"US",
    "gn:dem":26,
    "gn:elevation":"28.0",
    "gn:feature_class":"P",
    "gn:feature_code":"PPL",
    "gn:name":"Mary E White Estate",
    "gn:population":0,
    "gn:timezone":"America/New_York",
    "iso:country":"US",
    "wof:name":"Mary E White Estate",
    "wof:placetype":"locality"
},
  "geometry": {"coordinates":[-76.65663000000001,38.7565],"type":"Point"}
}