{
  "type": "Feature",
  "properties": {
    "gn:admin1_code":"AL",
    "gn:admin2_code":"33.0",
    "gn:asciiname":"Wilson Lake Shores",
    "gn:country_code":"US",
    "gn:dem":180,
    "gn:elevation":"172.0",
    "gn:feature_class":"P",
    "gn:feature_code":"PPL",
    "gn:name":"Wilson Lake Shores",
    "gn:population":0,
    "gn:timezone":"America/Chicago",
    "iso:country":"US",
    "wof:name":"Wilson Lake Shores",
    "wof:placetype":"locality"
},
  "geometry": {"coordinates":[-87.57892,34.80314],"type":"Point"}
}