{
  "type": "Feature",
  "properties": {
    "gn:admin1_code":"KY",
    "gn:admin2_code":"189",
    "gn:asciiname":"Sebastian",
    "gn:country_code":"US",
    "gn:dem":245,
    "gn:elevation":"237.0",
    "gn:feature_class":"P",
    "gn:feature_code":"PPL",
    "gn:name":"Sebastian",
    "gn:population":0,
    "gn:timezone":"America/New_York",
    "iso:country":"US",
    "name:ara_x_preferred":[
        "\u0633\u064a\u0628\u0627\u0633\u062a\u064a\u0627\u0646"
    ],
    "name:ceb_x_preferred":[
        "Sebastian"
    ],
    "name:dan_x_preferred":[
        "Sebastian"
    ],
    "name:deu_x_preferred":[
        "Sebastian"
    ],
    "name:fas_x_preferred":[
        "\u0633\u0628\u0627\u0633\u062a\u06cc\u0646"
    ],
    "name:fra_x_preferred":[
        "Sebastian"
    ],
    "name:glg_x_preferred":[
        "Sebasti\u00e1n"
    ],
    "name:heb_x_preferred":[
        "\u05e1\u05d1\u05e1\u05d8\u05d9\u05d0\u05df"
    ],
    "name:ita_x_preferred":[
        "Sebastian"
    ],
    "name:jpn_x_preferred":[
        "\u30bb\u30d0\u30b9\u30c1\u30e3\u30f3"
    ],
    "name:kor_x_preferred":[
        "\uc138\ubc14\uc2a4\ud2f0\uc575"
    ],
    "name:nld_x_preferred":[
        "Sebastian"
    ],
    "name:pol_x_preferred":[
        "Sebastian"
    ],
    "name:por_x_preferred":[
        "Sebastian"
    ],
    "name:slv_x_preferred":[
        "Sebastian"
    ],
    "name:spa_x_preferred":[
        "Sebastian"
    ],
    "name:srp_x_preferred":[
        "\u0421\u0435\u0431\u0430\u0448\u0447\u0430\u043d"
    ],
    "name:tur_x_preferred":[
        "Sebastian"
    ],
    "name:vol_x_preferred":[
        "Sebastian"
    ],
    "wof:name":"Sebastian",
    "wof:placetype":"locality"
},
  "geometry": {"coordinates":[-83.62019000000002,37.36092],"type":"Point"}
}