{
  "type": "Feature",
  "properties": {
    "iso:country":"US",
    "wof:name":"Turnwater Hill",
    "wof:placetype":"neighbourhood"
},
  "geometry": {"coordinates":[-122.92021540650181,47.01761987095599],"type":"Point"}
}