{
  "type": "Feature",
  "properties": {
    "gn:admin1_code":"NY",
    "gn:admin2_code":"119.0",
    "gn:admin3_code":"84077.0",
    "gn:asciiname":"Lake Mohegan",
    "gn:country_code":"US",
    "gn:dem":161,
    "gn:elevation":"159.0",
    "gn:feature_class":"P",
    "gn:feature_code":"PPL",
    "gn:name":"Lake Mohegan",
    "gn:population":6010,
    "gn:timezone":"America/New_York",
    "iso:country":"US",
    "wof:name":"Lake Mohegan",
    "wof:placetype":"locality",
    "wof:population":6010
},
  "geometry": {"coordinates":[-73.84625,41.31787],"type":"Point"}
}