{
  "type": "Feature",
  "properties": {
    "iso:country":"US",
    "name:eng_x_preferred":[
        "Hummingbird Ridge"
    ],
    "wof:name":"Hummingbird Ridge",
    "wof:placetype":"neighbourhood",
    "wof:population":2597,
    "zs:area_m":23894173.25135,
    "zs:blockids":[
        370250405001069,
        370250405002000,
        370250417011036,
        370250405001067,
        370250405001058,
        370250405001055,
        370250416021009,
        370250405001020,
        370250405001071,
        370250417011029,
        370250416021005,
        370250405001085,
        370250405001075,
        370250405001050,
        370250405001024,
        370250417021017,
        370250405001018,
        370250416021003,
        370250405001072,
        370250417011032,
        370250405001051,
        370250405001022,
        370250405001065,
        370250405001073,
        370250405001057,
        370250405001078,
        370250416021010,
        370250405001054,
        370250416021007,
        370250405001053,
        370250405001021,
        370250405001056,
        370250405001074,
        370250405001052,
        370250405001077,
        370250405001066,
        370250416021008,
        370250405001025,
        370250416021006,
        370250405001070,
        370250405001068,
        370250405001049,
        370250405001059,
        370250417011031,
        370250405001076,
        370250405001023
    ],
    "zs:housing10":1051,
    "zs:label":"Hummingbird Ridge",
    "zs:pop10":2597
},
  "geometry": {"coordinates":[-80.49857900000001,35.385415],"type":"Point"}
}