{
  "type": "Feature",
  "properties": {
    "gn:admin1_code":"MS",
    "gn:admin2_code":"163.0",
    "gn:asciiname":"Kearney",
    "gn:country_code":"US",
    "gn:dem":30,
    "gn:elevation":"30.0",
    "gn:feature_class":"P",
    "gn:feature_code":"PPL",
    "gn:name":"Kearney",
    "gn:population":0,
    "gn:timezone":"America/Chicago",
    "iso:country":"US",
    "name:ceb_x_preferred":[
        "Kearney"
    ],
    "name:deu_x_preferred":[
        "Kearney"
    ],
    "name:fin_x_preferred":[
        "Kearney"
    ],
    "name:fra_x_preferred":[
        "Kearney"
    ],
    "name:ita_x_preferred":[
        "Kearney"
    ],
    "name:jpn_x_preferred":[
        "\u30ab\u30fc\u30cb\u30fc"
    ],
    "name:nld_x_preferred":[
        "Kearney"
    ],
    "name:pol_x_preferred":[
        "Kearney"
    ],
    "name:por_x_preferred":[
        "Kearney"
    ],
    "name:rus_x_preferred":[
        "\u041a\u0438\u0440\u043d\u0438"
    ],
    "name:swe_x_preferred":[
        "Kearney"
    ],
    "name:vol_x_preferred":[
        "Kearney"
    ],
    "wof:name":"Kearney",
    "wof:placetype":"locality"
},
  "geometry": {"coordinates":[-90.72899,32.75319],"type":"Point"}
}