{
  "type": "Feature",
  "properties": {
    "gn:admin1_code":"MS",
    "gn:admin2_code":"139.0",
    "gn:asciiname":"Chalybeate",
    "gn:country_code":"US",
    "gn:dem":159,
    "gn:elevation":"155.0",
    "gn:feature_class":"P",
    "gn:feature_code":"PPL",
    "gn:name":"Chalybeate",
    "gn:population":0,
    "gn:timezone":"America/Chicago",
    "iso:country":"US",
    "name:eng_x_preferred":[
        "Chalybeate"
    ],
    "name:und_x_variant":[
        "Chalybeate Springs"
    ],
    "name:vol_x_preferred":[
        "Chalybeate"
    ],
    "wof:name":"Chalybeate",
    "wof:placetype":"locality"
},
  "geometry": {"coordinates":[-88.86811,34.93037],"type":"Point"}
}