{
  "type": "Feature",
  "properties": {
    "gn:admin1_code":"TX",
    "gn:admin2_code":"221",
    "gn:asciiname":"Brushy",
    "gn:country_code":"US",
    "gn:dem":298,
    "gn:elevation":"295.0",
    "gn:feature_class":"P",
    "gn:feature_code":"PPL",
    "gn:name":"Brushy",
    "gn:population":0,
    "gn:timezone":"America/Chicago",
    "iso:country":"US",
    "wof:name":"Brushy",
    "wof:placetype":"locality"
},
  "geometry": {"coordinates":[-97.82698000000001,32.38653],"type":"Point"}
}