{
  "type": "Feature",
  "properties": {
    "gn:country":"US",
    "gn:fcode":"PPL",
    "gn:population":4877,
    "iso:country":"US",
    "name:ara_x_preferred":[
        "\u0647\u0627\u062f\u0644\u064a"
    ],
    "name:cat_x_preferred":[
        "Hadley"
    ],
    "name:ceb_x_preferred":[
        "Hadley"
    ],
    "name:deu_x_preferred":[
        "Hadley"
    ],
    "name:eng_x_preferred":[
        "Hadley"
    ],
    "name:eus_x_preferred":[
        "Hadley"
    ],
    "name:fas_x_preferred":[
        "\u0647\u062f\u0644\u06cc\u060c \u0645\u0627\u0633\u0627\u0686\u0648\u0633\u062a"
    ],
    "name:fas_x_variant":[
        "\u0647\u062f\u0644\u06cc"
    ],
    "name:fra_x_preferred":[
        "Hadley"
    ],
    "name:hat_x_preferred":[
        "Hadley"
    ],
    "name:hun_x_preferred":[
        "Hadley"
    ],
    "name:ita_x_preferred":[
        "Hadley"
    ],
    "name:jpn_x_preferred":[
        "\u30cf\u30fc\u30c9\u30ea\u30fc"
    ],
    "name:kaz_x_preferred":[
        "\u0425\u0430\u0434\u043b\u044d\u0439"
    ],
    "name:kir_x_preferred":[
        "\u0425\u0430\u0434\u043b\u044d\u0439"
    ],
    "name:nld_x_preferred":[
        "Hadley"
    ],
    "name:pol_x_preferred":[
        "Hadley"
    ],
    "name:spa_x_preferred":[
        "Hadley"
    ],
    "name:und_x_variant":[
        "Nalwottoge"
    ],
    "name:urd_x_preferred":[
        "\u06c1\u06cc\u0688\u0644\u06cc\u060c \u0645\u06cc\u0633\u0627\u0686\u0648\u0633\u0679\u0633"
    ],
    "name:urd_x_variant":[
        "\u06c1\u06cc\u0688\u0644\u06cc"
    ],
    "name:vol_x_preferred":[
        "Hadley"
    ],
    "name:zho_x_preferred":[
        "\u54c8\u5fb7\u5229"
    ],
    "qs_pg:aaroncc":"US",
    "qs_pg:gn_country":"US",
    "qs_pg:gn_fcode":"PPL",
    "qs_pg:gn_pop":4877,
    "qs_pg:name":"Hadley",
    "qs_pg:name_adm0":"United States",
    "qs_pg:name_adm1":"Massachusetts",
    "qs_pg:photos":1307,
    "qs_pg:photos_1k":265,
    "qs_pg:photos_9k":17,
    "qs_pg:photos_9r":12,
    "qs_pg:photos_all":3742,
    "qs_pg:photos_sr":12,
    "qs_pg:pop_sr":4,
    "qs_pg:qs_pg_placetype":"locality",
    "qs_pg:qs_pg_placetype_gp":"Town",
    "qs_pg:woe_adm0":23424977,
    "woe:adm0_id":23424977,
    "woe:name_adm0":"United States",
    "woe:name_adm1":"Massachusetts",
    "woe:placetype":"Town",
    "wof:name":"Hadley",
    "wof:placetype":"locality",
    "wof:population":4877
},
  "geometry": {"coordinates":[-72.58842,42.34176],"type":"Point"}
}