{
  "type": "Feature",
  "properties": {
    "iso:country":"US",
    "name:eng_x_preferred":[
        "Rosemont North"
    ],
    "wof:name":"Rosemont North",
    "wof:placetype":"neighbourhood",
    "wof:population":8548,
    "zs:area_m":6021946.69251,
    "zs:blockids":[
        120950151031046,
        120950123061000,
        120950151062023,
        120950124011070,
        120950124011063,
        120950124011064,
        120950124031063,
        120950124011017,
        120950124011029,
        120950124011026,
        120950124011012,
        120950124011059,
        120950124031064,
        120950124011032,
        120950124011019,
        120950151063002,
        120950151062022,
        120950124011003,
        120950124011006,
        120950123061004,
        120950151062016,
        120950124031044,
        120950124011050,
        120950124011013,
        120950124011062,
        120950124011008,
        120950124011057,
        120950151062024,
        120950151062020,
        120950151062014,
        120950151031022,
        120950151031032,
        120950151031021,
        120950151062015,
        120950124031060,
        120950151062026,
        120950124011025,
        120950124011030,
        120950124031057,
        120950151063000,
        120950124011018,
        120950124011020,
        120950151031019,
        120950151031045,
        120950124011022,
        120950123061008,
        120950151062018,
        120950151031023,
        120950151063001,
        120950124011039,
        120950124011066,
        120950124011069,
        120950124011014,
        120950151031017,
        120950124011016,
        120950151031031,
        120950151063003,
        120950151062021,
        120950124011011,
        120950124011005,
        120950151062025,
        120950124031061,
        120950124011015,
        120950124011060,
        120950124011021,
        120950124011009,
        120950124011065,
        120950124011004,
        120950151031051,
        120950124011051,
        120950124031051,
        120950124031052,
        120950124031066,
        120950151063010,
        120950124011000,
        120950124031046,
        120950124011045,
        120950151063009,
        120950151031033,
        120950151062017,
        120950124011010,
        120950123061006,
        120950124031053,
        120950124011034,
        120950124011031,
        120950124011023,
        120950124031047,
        120950124011002,
        120950151031020,
        120950124011067,
        120950151063004,
        120950151062019,
        120950124011068,
        120950151063008,
        120950151063005,
        120950124011058,
        120950124011061,
        120950124031065
    ],
    "zs:housing10":3266,
    "zs:label":"Rosemont North",
    "zs:pop10":8548
},
  "geometry": {"coordinates":[-81.44198,28.614052],"type":"Point"}
}