{
  "type": "Feature",
  "properties": {
    "gn:admin1_code":"NE",
    "gn:admin2_code":"101.0",
    "gn:asciiname":"Broganville",
    "gn:country_code":"US",
    "gn:dem":939,
    "gn:elevation":"939.0",
    "gn:feature_class":"P",
    "gn:feature_code":"PPL",
    "gn:name":"Broganville",
    "gn:population":0,
    "gn:timezone":"America/Denver",
    "iso:country":"US",
    "wof:name":"Broganville",
    "wof:placetype":"locality"
},
  "geometry": {"coordinates":[-101.51656,41.20721],"type":"Point"}
}