{
  "type": "Feature",
  "properties": {
    "gn:admin1_code":"SC",
    "gn:admin2_code":"83.0",
    "gn:asciiname":"Anglewood",
    "gn:country_code":"US",
    "gn:dem":254,
    "gn:elevation":"246.0",
    "gn:feature_class":"P",
    "gn:feature_code":"PPL",
    "gn:name":"Anglewood",
    "gn:population":0,
    "gn:timezone":"America/New_York",
    "iso:country":"US",
    "wof:name":"Anglewood",
    "wof:placetype":"locality"
},
  "geometry": {"coordinates":[-81.99370999999999,34.91873],"type":"Point"}
}