{
  "type": "Feature",
  "properties": {
    "gn:admin1_code":"FL",
    "gn:admin2_code":"57.0",
    "gn:asciiname":"Sweats",
    "gn:country_code":"US",
    "gn:dem":46,
    "gn:elevation":"40.0",
    "gn:feature_class":"P",
    "gn:feature_code":"PPL",
    "gn:name":"Sweats",
    "gn:population":0,
    "gn:timezone":"America/New_York",
    "iso:country":"US",
    "wof:name":"Sweats",
    "wof:placetype":"locality"
},
  "geometry": {"coordinates":[-82.1219,28.0237],"type":"Point"}
}