{
  "type": "Feature",
  "properties": {
    "gn:admin1_code":"MD",
    "gn:admin2_code":"5.0",
    "gn:asciiname":"Chapelgate",
    "gn:country_code":"US",
    "gn:dem":179,
    "gn:elevation":"177.0",
    "gn:feature_class":"P",
    "gn:feature_code":"PPL",
    "gn:name":"Chapelgate",
    "gn:population":0,
    "gn:timezone":"America/New_York",
    "iso:country":"US",
    "wof:name":"Chapelgate",
    "wof:placetype":"locality"
},
  "geometry": {"coordinates":[-76.66247,39.45261],"type":"Point"}
}