{
  "type": "Feature",
  "properties": {
    "iso:country":"US",
    "name:eng_x_preferred":[
        "Kaunolu Ahupua`a"
    ],
    "qs:gn_adm0_cc":"US",
    "qs:gn_local":5850059,
    "qs:gn_nam_loc":"kaalawai",
    "qs:gn_namadm1":"HI",
    "qs:local_max":1683,
    "qs:local_sum":2830,
    "qs:localhoods":7,
    "qs:name":"Kaunolu Ahupua`a",
    "qs:name_adm0":"United States",
    "qs:name_adm1":"Hawaii",
    "qs:name_adm2":"Maui",
    "qs:name_local":"Lanai City",
    "qs:photo_max":3,
    "qs:photo_sum":6,
    "qs:placetype":"Suburb",
    "qs:quad_count":4,
    "qs:woe_adm0":23424977,
    "qs:woe_adm1":2347570,
    "qs:woe_adm2":12588033,
    "qs:woe_lau":0,
    "qs:woe_local":2436045,
    "qs:woe_ver":"7.10.0",
    "wof:name":"Kaunolu Ahupua`a",
    "wof:placetype":"neighbourhood",
    "wof:population":1122,
    "zs:blockids":[
        150090316011140,
        150090316011134,
        150090316011133,
        150090316011131,
        150090316011145,
        150090316012052,
        150090316012029,
        150090316012045,
        150090316012000,
        150090316011130,
        150090316012026,
        150090316012022,
        150090316012020,
        150090316011125,
        150090316011124,
        150090316011137,
        150090316011143,
        150090316012001,
        150090316012002,
        150090316012040,
        150090316012049,
        150090316012025,
        150090316012005,
        150090316011127,
        150090316011128,
        150090316011115,
        150090316012037,
        150090316012035,
        150090316012054,
        150090316012023,
        150090316012019,
        150090316012021,
        150090316012032,
        150090316012031,
        150090316011129,
        150090316011144,
        150090316012041,
        150090316012051,
        150090316012053,
        150090316011253,
        150090316012034,
        150090316011119,
        150090316012027,
        150090316012024,
        150090316012030,
        150090316012004,
        150090316011188,
        150090316012033,
        150090316012036,
        150090316012039,
        150090316012048,
        150090316012046,
        150090316011123,
        150090316011122,
        150090316012042,
        150090316012047,
        150090316012050,
        150090316012003,
        150090316011132,
        150090316011142,
        150090316011146,
        150090316011126,
        150090316012038,
        150090316012044,
        150090316012043,
        150090316012028,
        150090316012055
    ],
    "zs:housing10":494,
    "zs:pop10":1122
},
  "geometry": {"coordinates":[-156.922302,20.798913],"type":"Point"}
}