{
  "type": "Feature",
  "properties": {
    "gn:admin1_code":"AL",
    "gn:admin2_code":"63",
    "gn:asciiname":"New Mount Hebron",
    "gn:country_code":"US",
    "gn:dem":42,
    "gn:elevation":"40.0",
    "gn:feature_class":"P",
    "gn:feature_code":"PPL",
    "gn:name":"New Mount Hebron",
    "gn:population":0,
    "gn:timezone":"America/Chicago",
    "iso:country":"US",
    "wof:name":"New Mount Hebron",
    "wof:placetype":"locality"
},
  "geometry": {"coordinates":[-88.10113,32.85707],"type":"Point"}
}