{
  "type": "Feature",
  "properties": {
    "gn:admin1_code":"NE",
    "gn:admin2_code":"111.0",
    "gn:asciiname":"Village Square",
    "gn:country_code":"US",
    "gn:dem":865,
    "gn:elevation":"859.0",
    "gn:feature_class":"P",
    "gn:feature_code":"PPL",
    "gn:name":"Village Square",
    "gn:population":0,
    "gn:timezone":"America/Chicago",
    "iso:country":"US",
    "wof:name":"Village Square",
    "wof:placetype":"locality"
},
  "geometry": {"coordinates":[-100.80237,41.13972],"type":"Point"}
}