{
  "type": "Feature",
  "properties": {
    "gn:admin1_code":"OH",
    "gn:admin2_code":"79.0",
    "gn:admin3_code":"37856.0",
    "gn:asciiname":"Brocks Corner",
    "gn:country_code":"US",
    "gn:dem":191,
    "gn:elevation":"193.0",
    "gn:feature_class":"P",
    "gn:feature_code":"PPL",
    "gn:name":"Brocks Corner",
    "gn:population":0,
    "gn:timezone":"America/New_York",
    "iso:country":"US",
    "name:eng_x_preferred":[
        "Brocks Corner"
    ],
    "name:und_x_variant":[
        "Springer",
        "Brox Corner",
        "Springers"
    ],
    "wof:name":"Brocks Corner",
    "wof:placetype":"locality"
},
  "geometry": {"coordinates":[-82.76045000000001,39.19062],"type":"Point"}
}