{
  "type": "Feature",
  "properties": {
    "iso:country":"US",
    "name:eng_x_preferred":[
        "Lionspaw"
    ],
    "qs:gn_adm0_cc":"US",
    "qs:gn_local":4161438,
    "qs:gn_nam_loc":"Lakeland, Polk, Florida, US",
    "qs:gn_namadm1":"FL",
    "qs:local_max":3081,
    "qs:local_sum":7667,
    "qs:localhoods":24,
    "qs:name":"Lionspaw",
    "qs:name_adm0":"United States",
    "qs:name_adm1":"Florida",
    "qs:name_adm2":"Polk",
    "qs:name_local":"Lakeland",
    "qs:photo_max":75,
    "qs:photo_sum":151,
    "qs:placetype":"Suburb",
    "qs:quad_count":6,
    "qs:woe_adm0":23424977,
    "qs:woe_adm1":2347568,
    "qs:woe_adm2":12587855,
    "qs:woe_lau":0,
    "qs:woe_local":2435325,
    "qs:woe_ver":"7.10.0",
    "wof:lang":[
        "eng"
    ],
    "wof:name":"Lionspaw",
    "wof:placetype":"neighbourhood",
    "zs:blockids":[
        121050105023002
    ],
    "zs:housing10":0,
    "zs:pop10":0
},
  "geometry": {"coordinates":[-81.945949,28.017959],"type":"Point"}
}