{
  "type": "Feature",
  "properties": {
    "gn:country":"US",
    "gn:fcode":"PPL",
    "gn:population":0,
    "iso:country":"US",
    "name:ara_x_preferred":[
        "\u0647\u0646\u062a\u0646\u063a\u062a\u0648\u0646"
    ],
    "name:cat_x_preferred":[
        "Huntington"
    ],
    "name:deu_x_preferred":[
        "Huntington"
    ],
    "name:eng_x_preferred":[
        "Huntington"
    ],
    "name:eus_x_preferred":[
        "Huntington"
    ],
    "name:fra_x_preferred":[
        "Huntington"
    ],
    "name:hat_x_preferred":[
        "Huntington"
    ],
    "name:ita_x_preferred":[
        "Huntington"
    ],
    "name:pol_x_preferred":[
        "Huntington"
    ],
    "name:spa_x_preferred":[
        "Huntington"
    ],
    "name:swe_x_preferred":[
        "Huntington"
    ],
    "name:und_x_variant":[
        "Huntingdon"
    ],
    "name:uzb_x_preferred":[
        "Huntington"
    ],
    "name:vol_x_preferred":[
        "Huntington"
    ],
    "qs_pg:aaroncc":"US",
    "qs_pg:gn_country":"US",
    "qs_pg:gn_fcode":"PPL",
    "qs_pg:gn_pop":0,
    "qs_pg:name":"Huntington",
    "qs_pg:name_adm0":"United States",
    "qs_pg:name_adm1":"Vermont",
    "qs_pg:photos":362,
    "qs_pg:photos_1k":73,
    "qs_pg:photos_9k":2,
    "qs_pg:photos_9r":5,
    "qs_pg:photos_all":375,
    "qs_pg:photos_sr":6,
    "qs_pg:pop_sr":0,
    "qs_pg:qs_pg_placetype":"locality",
    "qs_pg:qs_pg_placetype_gp":"Town",
    "qs_pg:woe_adm0":23424977,
    "woe:adm0_id":23424977,
    "woe:name_adm0":"United States",
    "woe:name_adm1":"Vermont",
    "woe:placetype":"Town",
    "wof:name":"Huntington",
    "wof:placetype":"locality"
},
  "geometry": {"coordinates":[-72.98734,44.32533],"type":"Point"}
}