{
  "type": "Feature",
  "properties": {
    "gn:country":"US",
    "gn:fcode":"PPL",
    "gn:population":0,
    "iso:country":"US",
    "name:ara_x_preferred":[
        "\u0628\u0627\u0644\u0628\u0648\u0627"
    ],
    "name:ben_x_preferred":[
        "\u09ac\u09be\u09b2\u09ac\u09cb\u09df\u09be"
    ],
    "name:bul_x_preferred":[
        "\u0411\u0430\u043b\u0431\u043e\u0430"
    ],
    "name:cat_x_preferred":[
        "Balboa"
    ],
    "name:ceb_x_preferred":[
        "Balboa"
    ],
    "name:ces_x_preferred":[
        "Balboa"
    ],
    "name:deu_x_preferred":[
        "Balboa"
    ],
    "name:ell_x_preferred":[
        "\u039c\u03c0\u03b1\u03bb\u03bc\u03c0\u03cc\u03b1"
    ],
    "name:epo_x_preferred":[
        "Balboo"
    ],
    "name:fas_x_preferred":[
        "\u0628\u0627\u0644\u0628\u0648\u0622"
    ],
    "name:fin_x_preferred":[
        "Balboa"
    ],
    "name:fra_x_preferred":[
        "Balboa"
    ],
    "name:glg_x_preferred":[
        "Balboa"
    ],
    "name:heb_x_preferred":[
        "\u05d1\u05dc\u05d1\u05d5\u05d0\u05d4"
    ],
    "name:hin_x_preferred":[
        "\u092c\u093e\u0932\u092c\u094b\u0906"
    ],
    "name:hun_x_preferred":[
        "Balboa"
    ],
    "name:ind_x_preferred":[
        "Balboa"
    ],
    "name:ita_x_preferred":[
        "Balboa"
    ],
    "name:jpn_x_preferred":[
        "\u30d0\u30eb\u30dc\u30a2"
    ],
    "name:kor_x_preferred":[
        "\ubc1c\ubcf4\uc544"
    ],
    "name:lav_x_preferred":[
        "Balboa"
    ],
    "name:lit_x_preferred":[
        "Balboa"
    ],
    "name:nld_x_preferred":[
        "Balboa"
    ],
    "name:nor_x_preferred":[
        "Balboa"
    ],
    "name:pol_x_preferred":[
        "Balboa"
    ],
    "name:por_x_preferred":[
        "Balboa"
    ],
    "name:rus_x_preferred":[
        "\u0411\u0430\u043b\u044c\u0431\u043e\u0430"
    ],
    "name:sco_x_preferred":[
        "Balboa"
    ],
    "name:slv_x_preferred":[
        "Balboa"
    ],
    "name:spa_x_preferred":[
        "Balboa"
    ],
    "name:swe_x_preferred":[
        "Balboa"
    ],
    "name:tur_x_preferred":[
        "Balboa"
    ],
    "name:ukr_x_preferred":[
        "\u0411\u0430\u043b\u044c\u0431\u043e\u0430"
    ],
    "name:vie_x_preferred":[
        "Balboa"
    ],
    "qs_pg:aaroncc":"US",
    "qs_pg:gn_country":"US",
    "qs_pg:gn_fcode":"PPL",
    "qs_pg:gn_pop":0,
    "qs_pg:name":"Balboa",
    "qs_pg:name_adm0":"United States",
    "qs_pg:name_adm1":"California",
    "qs_pg:photos":3935,
    "qs_pg:photos_1k":797,
    "qs_pg:photos_9k":17,
    "qs_pg:photos_9r":12,
    "qs_pg:photos_all":3935,
    "qs_pg:photos_sr":22,
    "qs_pg:pop_sr":0,
    "qs_pg:qs_pg_placetype":"locality",
    "qs_pg:qs_pg_placetype_gp":"Town",
    "qs_pg:woe_adm0":23424977,
    "woe:adm0_id":23424977,
    "woe:name_adm0":"United States",
    "woe:name_adm1":"California",
    "woe:placetype":"Town",
    "wof:name":"Balboa",
    "wof:placetype":"locality"
},
  "geometry": {"coordinates":[-117.90089,33.58697],"type":"Point"}
}