{
  "type": "Feature",
  "properties": {
    "gn:admin1_code":"ME",
    "gn:admin2_code":"3.0",
    "gn:admin3_code":"78570.0",
    "gn:asciiname":"Kennedy Terrace",
    "gn:country_code":"US",
    "gn:dem":143,
    "gn:elevation":"143.0",
    "gn:feature_class":"P",
    "gn:feature_code":"PPL",
    "gn:name":"Kennedy Terrace",
    "gn:population":0,
    "gn:timezone":"America/New_York",
    "iso:country":"US",
    "wof:name":"Kennedy Terrace",
    "wof:placetype":"locality"
},
  "geometry": {"coordinates":[-67.96058000000001,47.18782],"type":"Point"}
}