{
  "type": "Feature",
  "properties": {
    "gn:admin1_code":"GA",
    "gn:admin2_code":"73.0",
    "gn:asciiname":"Howell",
    "gn:country_code":"US",
    "gn:dem":125,
    "gn:elevation":"122.0",
    "gn:feature_class":"P",
    "gn:feature_code":"PPL",
    "gn:name":"Howell",
    "gn:population":0,
    "gn:timezone":"America/New_York",
    "iso:country":"US",
    "name:cat_x_preferred":[
        "Howell"
    ],
    "name:ceb_x_preferred":[
        "Howell"
    ],
    "name:ces_x_preferred":[
        "Howell"
    ],
    "name:deu_x_preferred":[
        "Howell"
    ],
    "name:eng_x_preferred":[
        "Howell"
    ],
    "name:fra_x_preferred":[
        "Howell"
    ],
    "name:heb_x_preferred":[
        "\u05d4\u05d0\u05d5\u05d5\u05dc"
    ],
    "name:ita_x_preferred":[
        "Howell"
    ],
    "name:jpn_x_preferred":[
        "\u30cf\u30a6\u30a8\u30eb"
    ],
    "name:nds_x_preferred":[
        "Howell"
    ],
    "name:nld_x_preferred":[
        "Howell"
    ],
    "name:pol_x_preferred":[
        "Howell"
    ],
    "name:por_x_preferred":[
        "Howell"
    ],
    "name:rus_x_preferred":[
        "\u0425\u0430\u0443\u044d\u043b\u043b"
    ],
    "name:srp_x_preferred":[
        "\u0425\u0430\u0443\u0435\u043b"
    ],
    "name:swe_x_preferred":[
        "Howell"
    ],
    "name:ukr_x_preferred":[
        "\u0413\u043e\u0432\u0435\u043b\u043b"
    ],
    "name:und_x_variant":[
        "Howells"
    ],
    "name:vol_x_preferred":[
        "Howell"
    ],
    "wof:name":"Howell",
    "wof:placetype":"locality"
},
  "geometry": {"coordinates":[-82.31789999999999,33.55652],"type":"Point"}
}