{
  "type": "Feature",
  "properties": {
    "gn:admin1_code":"SC",
    "gn:admin2_code":"87.0",
    "gn:asciiname":"Cross Keys",
    "gn:country_code":"US",
    "gn:dem":196,
    "gn:elevation":"192.0",
    "gn:feature_class":"P",
    "gn:feature_code":"PPL",
    "gn:name":"Cross Keys",
    "gn:population":0,
    "gn:timezone":"America/New_York",
    "iso:country":"US",
    "name:eng_x_preferred":[
        "Cross Keys"
    ],
    "name:und_x_variant":[
        "Crosskeys"
    ],
    "wof:name":"Cross Keys",
    "wof:placetype":"locality"
},
  "geometry": {"coordinates":[-81.77677,34.63208],"type":"Point"}
}