{
  "type": "Feature",
  "properties": {
    "gn:admin1_code":"ID",
    "gn:admin2_code":"31.0",
    "gn:asciiname":"Basin",
    "gn:country_code":"US",
    "gn:dem":1525,
    "gn:elevation":"1523.0",
    "gn:feature_class":"P",
    "gn:feature_code":"PPL",
    "gn:name":"Basin",
    "gn:population":0,
    "gn:timezone":"America/Boise",
    "iso:country":"US",
    "name:ara_x_preferred":[
        "\u062d\u0648\u0636"
    ],
    "name:cat_x_preferred":[
        "Basin"
    ],
    "name:ceb_x_preferred":[
        "Basin"
    ],
    "name:deu_x_preferred":[
        "Basin"
    ],
    "name:eng_x_preferred":[
        "Basin"
    ],
    "name:fra_x_preferred":[
        "Basin"
    ],
    "name:ind_x_preferred":[
        "Basin"
    ],
    "name:ita_x_preferred":[
        "Basin"
    ],
    "name:nld_x_preferred":[
        "Basin"
    ],
    "name:pol_x_preferred":[
        "Basin"
    ],
    "name:por_x_preferred":[
        "Basin"
    ],
    "name:rus_x_preferred":[
        "\u0411\u0430\u0441\u0438\u043d"
    ],
    "name:spa_x_preferred":[
        "Basin"
    ],
    "name:srp_x_preferred":[
        "\u0411\u0430\u0441\u0435\u043d"
    ],
    "name:ukr_x_preferred":[
        "\u0411\u0430\u0441\u0456\u043d"
    ],
    "name:und_x_variant":[
        "Spring Basin"
    ],
    "name:vol_x_preferred":[
        "Basin"
    ],
    "wof:name":"Basin",
    "wof:placetype":"locality"
},
  "geometry": {"coordinates":[-113.78446,42.24547000000001],"type":"Point"}
}