{
  "type": "Feature",
  "properties": {
    "iso:country":"US",
    "name:aze_x_preferred":[
        "Qreyslend"
    ],
    "name:cat_x_preferred":[
        "Graceland"
    ],
    "name:ces_x_preferred":[
        "Graceland"
    ],
    "name:dan_x_preferred":[
        "Graceland"
    ],
    "name:deu_x_preferred":[
        "Graceland"
    ],
    "name:eng_x_preferred":[
        "Graceland"
    ],
    "name:est_x_preferred":[
        "Graceland"
    ],
    "name:eus_x_preferred":[
        "Graceland"
    ],
    "name:fin_x_preferred":[
        "Graceland"
    ],
    "name:fra_x_preferred":[
        "Graceland"
    ],
    "name:glg_x_preferred":[
        "Graceland"
    ],
    "name:ind_x_preferred":[
        "Graceland"
    ],
    "name:ita_x_preferred":[
        "Graceland"
    ],
    "name:jpn_x_preferred":[
        "\u30b0\u30ec\u30a4\u30b9\u30e9\u30f3\u30c9"
    ],
    "name:kor_x_preferred":[
        "\uadf8\ub808\uc774\uc2a4\ub79c\ub4dc"
    ],
    "name:lat_x_preferred":[
        "Graceland"
    ],
    "name:lav_x_preferred":[
        "Greislenda"
    ],
    "name:nld_x_preferred":[
        "Graceland"
    ],
    "name:nor_x_preferred":[
        "Graceland"
    ],
    "name:pol_x_preferred":[
        "Graceland"
    ],
    "name:por_x_preferred":[
        "Graceland"
    ],
    "name:ron_x_preferred":[
        "Graceland"
    ],
    "name:rus_x_preferred":[
        "\u0413\u0440\u0435\u0439\u0441\u043b\u0435\u043d\u0434"
    ],
    "name:scn_x_preferred":[
        "Graceland"
    ],
    "name:slk_x_preferred":[
        "Graceland"
    ],
    "name:spa_x_preferred":[
        "Graceland"
    ],
    "name:swe_x_preferred":[
        "Graceland"
    ],
    "name:tur_x_preferred":[
        "Graceland"
    ],
    "name:ukr_x_preferred":[
        "\u0413\u0440\u0435\u0439\u0441\u043b\u0435\u043d\u0434"
    ],
    "wd:wordcount":5314,
    "wof:name":"Graceland",
    "wof:placetype":"neighbourhood",
    "zs:area_m":70871.758675,
    "zs:blockids":[
        550790011001007
    ],
    "zs:housing10":0,
    "zs:label":"Graceland",
    "zs:pop10":0
},
  "geometry": {"coordinates":[-87.98051700000001,43.132558],"type":"Point"}
}