{
  "type": "Feature",
  "properties": {
    "gn:admin1_code":"MI",
    "gn:admin2_code":"155.0",
    "gn:admin3_code":"82040.0",
    "gn:asciiname":"Lakeview Estates Mobile Home Park",
    "gn:country_code":"US",
    "gn:dem":233,
    "gn:elevation":"234.0",
    "gn:feature_class":"P",
    "gn:feature_code":"PPL",
    "gn:name":"Lakeview Estates Mobile Home Park",
    "gn:population":0,
    "gn:timezone":"America/Detroit",
    "iso:country":"US",
    "wof:name":"Lakeview Estates Mobile Home Park",
    "wof:placetype":"campus"
},
  "geometry": {"coordinates":[-84.00055999999999,42.93167],"type":"Point"}
}