{
  "type": "Feature",
  "properties": {
    "gn:admin1_code":"GA",
    "gn:admin2_code":"135.0",
    "gn:asciiname":"Level Creek",
    "gn:country_code":"US",
    "gn:dem":312,
    "gn:elevation":"315.0",
    "gn:feature_class":"P",
    "gn:feature_code":"PPL",
    "gn:name":"Level Creek",
    "gn:population":0,
    "gn:timezone":"America/New_York",
    "iso:country":"US",
    "wof:name":"Level Creek",
    "wof:placetype":"locality"
},
  "geometry": {"coordinates":[-84.07297,34.08427],"type":"Point"}
}