{
  "type": "Feature",
  "properties": {
    "gn:admin1_code":"WI",
    "gn:admin2_code":"123.0",
    "gn:admin3_code":"27400.0",
    "gn:asciiname":"Fargo",
    "gn:country_code":"US",
    "gn:dem":391,
    "gn:elevation":"392.0",
    "gn:feature_class":"P",
    "gn:feature_code":"PPL",
    "gn:name":"Fargo",
    "gn:population":0,
    "gn:timezone":"America/Chicago",
    "iso:country":"US",
    "wof:name":"Fargo",
    "wof:placetype":"locality"
},
  "geometry": {"coordinates":[-90.95735000000001,43.45581],"type":"Point"}
}