{
  "type": "Feature",
  "properties": {
    "gn:admin1_code":"MI",
    "gn:admin2_code":"21",
    "gn:admin3_code":"57780.0",
    "gn:asciiname":"Franklin Woods Mobile Home Park",
    "gn:country_code":"US",
    "gn:dem":228,
    "gn:elevation":"225.0",
    "gn:feature_class":"P",
    "gn:feature_code":"PPL",
    "gn:name":"Franklin Woods Mobile Home Park",
    "gn:population":0,
    "gn:timezone":"America/Detroit",
    "iso:country":"US",
    "name:und_x_variant":[
        "Windward Village",
        "Franklin Woods Mobile Home Park"
    ],
    "wof:name":"Franklin Woods Mobile Home Park",
    "wof:placetype":"campus"
},
  "geometry": {"coordinates":[-86.24583,41.79444],"type":"Point"}
}