{
  "type": "Feature",
  "properties": {
    "gn:admin1_code":"FL",
    "gn:admin2_code":"77.0",
    "gn:asciiname":"Jensen Place",
    "gn:country_code":"US",
    "gn:dem":34,
    "gn:elevation":"25.0",
    "gn:feature_class":"P",
    "gn:feature_code":"PPL",
    "gn:name":"Jensen Place",
    "gn:population":0,
    "gn:timezone":"America/New_York",
    "iso:country":"US",
    "wof:name":"Jensen Place",
    "wof:placetype":"locality"
},
  "geometry": {"coordinates":[-84.92685999999998,30.2302],"type":"Point"}
}