{
  "type": "Feature",
  "properties": {
    "gn:admin1_code":"LA",
    "gn:admin2_code":"59.0",
    "gn:asciiname":"Cane",
    "gn:country_code":"US",
    "gn:dem":46,
    "gn:elevation":"42.0",
    "gn:feature_class":"P",
    "gn:feature_code":"PPL",
    "gn:name":"Cane",
    "gn:population":0,
    "gn:timezone":"America/Chicago",
    "iso:country":"US",
    "name:cat_x_preferred":[
        "Cane"
    ],
    "name:ceb_x_preferred":[
        "Cane"
    ],
    "name:deu_x_preferred":[
        "Cane"
    ],
    "name:fra_x_preferred":[
        "Cane"
    ],
    "name:ita_x_preferred":[
        "Cane"
    ],
    "name:jpn_x_preferred":[
        "\u30b1\u30fc\u30f3"
    ],
    "name:nld_x_preferred":[
        "Cane"
    ],
    "name:srp_x_preferred":[
        "Cane"
    ],
    "name:swe_x_preferred":[
        "Cane"
    ],
    "wof:name":"Cane",
    "wof:placetype":"locality"
},
  "geometry": {"coordinates":[-92.01958,31.64406],"type":"Point"}
}