{
  "type": "Feature",
  "properties": {
    "gn:admin1_code":"DE",
    "gn:admin2_code":"3.0",
    "gn:asciiname":"Weber Tract",
    "gn:country_code":"US",
    "gn:dem":115,
    "gn:elevation":"108.0",
    "gn:feature_class":"P",
    "gn:feature_code":"PPL",
    "gn:name":"Weber Tract",
    "gn:population":0,
    "gn:timezone":"America/New_York",
    "iso:country":"US",
    "wof:name":"Weber Tract",
    "wof:placetype":"locality"
},
  "geometry": {"coordinates":[-75.50575000000001,39.82706],"type":"Point"}
}