{
  "type": "Feature",
  "properties": {
    "iso:country":"US",
    "name:eng_x_preferred":[
        "White Oak"
    ],
    "wof:name":"White Oak",
    "wof:placetype":"neighbourhood",
    "wof:population":342,
    "zs:area_m":413258.898231,
    "zs:blockids":[
        470650107001004,
        470650107002016,
        470650107001003,
        470650107002020,
        470650108002017,
        470650107002019
    ],
    "zs:housing10":169,
    "zs:label":"White Oak",
    "zs:pop10":342
},
  "geometry": {"coordinates":[-85.3062,35.096848],"type":"Point"}
}