{
  "type": "Feature",
  "properties": {
    "gn:admin1_code":"MD",
    "gn:admin2_code":"3.0",
    "gn:asciiname":"Marwood",
    "gn:country_code":"US",
    "gn:dem":17,
    "gn:elevation":"17.0",
    "gn:feature_class":"P",
    "gn:feature_code":"PPL",
    "gn:name":"Marwood",
    "gn:population":0,
    "gn:timezone":"America/New_York",
    "iso:country":"US",
    "name:ceb_x_preferred":[
        "Marwood"
    ],
    "name:deu_x_preferred":[
        "Marwood"
    ],
    "name:nld_x_preferred":[
        "Marwood"
    ],
    "name:pol_x_preferred":[
        "Marwood"
    ],
    "name:swe_x_preferred":[
        "Marwood"
    ],
    "wof:name":"Marwood",
    "wof:placetype":"locality"
},
  "geometry": {"coordinates":[-76.59052,39.1465],"type":"Point"}
}