{
  "type": "Feature",
  "properties": {
    "gn:admin1_code":"TN",
    "gn:admin2_code":"29.0",
    "gn:asciiname":"Tom Town",
    "gn:country_code":"US",
    "gn:dem":535,
    "gn:elevation":"522.0",
    "gn:feature_class":"P",
    "gn:feature_code":"PPL",
    "gn:name":"Tom Town",
    "gn:population":0,
    "gn:timezone":"America/New_York",
    "iso:country":"US",
    "wof:name":"Tom Town",
    "wof:placetype":"locality"
},
  "geometry": {"coordinates":[-83.01654000000001,35.84538],"type":"Point"}
}