{
  "type": "Feature",
  "properties": {
    "gn:admin1_code":"LA",
    "gn:admin2_code":"79.0",
    "gn:asciiname":"Campbell",
    "gn:country_code":"US",
    "gn:dem":57,
    "gn:elevation":"48.0",
    "gn:feature_class":"P",
    "gn:feature_code":"PPL",
    "gn:name":"Campbell",
    "gn:population":0,
    "gn:timezone":"America/Chicago",
    "iso:country":"US",
    "name:bul_x_preferred":[
        "\u041a\u0435\u043c\u0431\u044a\u043b"
    ],
    "name:cat_x_preferred":[
        "Campbell"
    ],
    "name:ceb_x_preferred":[
        "Campbell"
    ],
    "name:ces_x_preferred":[
        "Campbell"
    ],
    "name:deu_x_preferred":[
        "Campbell"
    ],
    "name:ell_x_preferred":[
        "\u039a\u03ac\u03bc\u03c0\u03b5\u03bb"
    ],
    "name:fas_x_preferred":[
        "\u06a9\u0645\u067e\u0644"
    ],
    "name:fin_x_preferred":[
        "Campbell"
    ],
    "name:fra_x_preferred":[
        "Campbell"
    ],
    "name:heb_x_preferred":[
        "\u05e7\u05de\u05e4\u05d1\u05dc"
    ],
    "name:ind_x_preferred":[
        "Campbell"
    ],
    "name:ita_x_preferred":[
        "Campbell"
    ],
    "name:jpn_x_preferred":[
        "\u30ad\u30e3\u30f3\u30d9\u30eb"
    ],
    "name:nld_x_preferred":[
        "Campbell"
    ],
    "name:nor_x_preferred":[
        "Campbell"
    ],
    "name:pol_x_preferred":[
        "Campbell"
    ],
    "name:por_x_preferred":[
        "Campbell"
    ],
    "name:spa_x_preferred":[
        "Campbell"
    ],
    "name:srp_x_preferred":[
        "\u041a\u0435\u043c\u0431\u0435\u043b"
    ],
    "name:swa_x_preferred":[
        "Campbell"
    ],
    "name:swe_x_preferred":[
        "Campbell"
    ],
    "name:tur_x_preferred":[
        "Campbell"
    ],
    "name:ukr_x_preferred":[
        "\u041a\u0435\u043c\u043f\u0431\u0435\u043b\u043b"
    ],
    "name:urd_x_preferred":[
        "\u06a9\u06cc\u0645\u0628\u0644"
    ],
    "name:vol_x_preferred":[
        "Campbell"
    ],
    "name:zho_x_preferred":[
        "\u574e\u8c9d\u723e"
    ],
    "wof:name":"Campbell",
    "wof:placetype":"locality"
},
  "geometry": {"coordinates":[-92.7946,31.40184],"type":"Point"}
}