{
  "type": "Feature",
  "properties": {
    "gn:admin1_code":"SC",
    "gn:admin2_code":"41.0",
    "gn:asciiname":"Glencove",
    "gn:country_code":"US",
    "gn:dem":36,
    "gn:elevation":"41.0",
    "gn:feature_class":"P",
    "gn:feature_code":"PPL",
    "gn:name":"Glencove",
    "gn:population":0,
    "gn:timezone":"America/New_York",
    "iso:country":"US",
    "wof:name":"Glencove",
    "wof:placetype":"locality"
},
  "geometry": {"coordinates":[-79.70811999999999,34.19988],"type":"Point"}
}