{
  "type": "Feature",
  "properties": {
    "gn:admin1_code":"GA",
    "gn:admin2_code":"317.0",
    "gn:asciiname":"Aonia",
    "gn:country_code":"US",
    "gn:dem":152,
    "gn:elevation":"155.0",
    "gn:feature_class":"P",
    "gn:feature_code":"PPL",
    "gn:name":"Aonia",
    "gn:population":0,
    "gn:timezone":"America/New_York",
    "iso:country":"US",
    "name:bre_x_preferred":[
        "Aonia"
    ],
    "name:ita_x_preferred":[
        "Aonia"
    ],
    "name:spa_x_preferred":[
        "Aonia"
    ],
    "name:zho_x_preferred":[
        "\u963f\u4fc4\u5c3c\u4e9a"
    ],
    "wof:name":"Aonia",
    "wof:placetype":"locality"
},
  "geometry": {"coordinates":[-82.62319000000002,33.67541],"type":"Point"}
}