{
  "type": "Feature",
  "properties": {
    "gn:admin1_code":"NC",
    "gn:admin2_code":"53.0",
    "gn:admin3_code":"90816.0",
    "gn:asciiname":"Snowden",
    "gn:country_code":"US",
    "gn:dem":5,
    "gn:elevation":"2.0",
    "gn:feature_class":"P",
    "gn:feature_code":"PPL",
    "gn:name":"Snowden",
    "gn:population":0,
    "gn:timezone":"America/New_York",
    "iso:country":"US",
    "name:ceb_x_preferred":[
        "Snowden"
    ],
    "name:ces_x_preferred":[
        "Snowden"
    ],
    "name:deu_x_preferred":[
        "Snowden"
    ],
    "name:fas_x_preferred":[
        "\u0627\u0633\u0646\u0648\u062f\u0646"
    ],
    "name:fra_x_preferred":[
        "Snowden"
    ],
    "name:ita_x_preferred":[
        "Snowden"
    ],
    "name:jpn_x_preferred":[
        "\u30b9\u30ce\u30fc\u30c7\u30f3"
    ],
    "name:kor_x_preferred":[
        "\uc2a4\ub178\ub4e0"
    ],
    "name:nds_x_preferred":[
        "Snowden"
    ],
    "name:nld_x_preferred":[
        "Snowden"
    ],
    "name:pol_x_preferred":[
        "Snowden"
    ],
    "name:spa_x_preferred":[
        "Snowden"
    ],
    "name:ukr_x_preferred":[
        "\u0421\u043d\u043e\u0443\u0434\u0435\u043d"
    ],
    "name:zho_x_preferred":[
        "\u65af\u8afe\u767b"
    ],
    "wof:name":"Snowden",
    "wof:placetype":"locality"
},
  "geometry": {"coordinates":[-76.10854,36.45682],"type":"Point"}
}