{
  "type": "Feature",
  "properties": {
    "gn:admin1_code":"SC",
    "gn:admin2_code":"47.0",
    "gn:asciiname":"Highland Forest",
    "gn:country_code":"US",
    "gn:dem":189,
    "gn:elevation":"187.0",
    "gn:feature_class":"P",
    "gn:feature_code":"PPL",
    "gn:name":"Highland Forest",
    "gn:population":0,
    "gn:timezone":"America/New_York",
    "iso:country":"US",
    "wof:name":"Highland Forest",
    "wof:placetype":"locality"
},
  "geometry": {"coordinates":[-82.13318000000002,34.14818],"type":"Point"}
}