{
  "type": "Feature",
  "properties": {
    "gn:admin1_code":"MN",
    "gn:admin2_code":"135",
    "gn:admin3_code":"3160.0",
    "gn:asciiname":"Oak View Mobile Home Park",
    "gn:country_code":"US",
    "gn:dem":328,
    "gn:elevation":"329.0",
    "gn:feature_class":"P",
    "gn:feature_code":"PPL",
    "gn:name":"Oak View Mobile Home Park",
    "gn:population":0,
    "gn:timezone":"America/Chicago",
    "iso:country":"US",
    "wof:name":"Oak View Mobile Home Park",
    "wof:placetype":"campus"
},
  "geometry": {"coordinates":[-96.01416999999999,48.7825],"type":"Point"}
}