{
  "type": "Feature",
  "properties": {
    "gn:gn_country":"US",
    "gn:gn_fcode":"PPL",
    "gn:gn_pop":0,
    "iso:country":"US",
    "name:pol_x_preferred":[
        "Westcliffe"
    ],
    "qs_pg:aaroncc":"US",
    "qs_pg:gn_country":"US",
    "qs_pg:gn_fcode":"PPL",
    "qs_pg:gn_pop":0,
    "qs_pg:name":"Westcliffe",
    "qs_pg:name_adm0":"United States",
    "qs_pg:name_adm1":"South Carolina",
    "qs_pg:photos":13,
    "qs_pg:photos_1k":3,
    "qs_pg:photos_9k":1,
    "qs_pg:photos_9r":1,
    "qs_pg:photos_all":13,
    "qs_pg:photos_sr":1,
    "qs_pg:pop_sr":0,
    "qs_pg:qs_pg_placetype":"locality",
    "qs_pg:qs_pg_placetype_gp":"Town",
    "qs_pg:woe_adm0":23424977,
    "woe:adm0_id":23424977,
    "woe:name_adm0":"United States",
    "woe:name_adm1":"South Carolina",
    "woe:placetype":"Town",
    "wof:name":"Westcliffe",
    "wof:placetype":"locality"
},
  "geometry": {"coordinates":[-82.46845999999999,34.8654],"type":"Point"}
}