{
  "type": "Feature",
  "properties": {
    "iso:country":"US",
    "name:eng_x_preferred":[
        "Casa Linda"
    ],
    "qs:gn_adm0_cc":"US",
    "qs:gn_local":5490263,
    "qs:gn_nam_loc":"Santa Fe, Santa Fe, New Mexico, US",
    "qs:gn_namadm1":"NM",
    "qs:local_max":8972,
    "qs:local_sum":19509,
    "qs:localhoods":43,
    "qs:name":"Casa Linda",
    "qs:name_adm0":"United States",
    "qs:name_adm1":"New Mexico",
    "qs:name_adm2":"Santa Fe",
    "qs:name_local":"Santa Fe",
    "qs:photo_max":20,
    "qs:photo_sum":39,
    "qs:placetype":"Suburb",
    "qs:quad_count":6,
    "qs:woe_adm0":23424977,
    "qs:woe_adm1":2347590,
    "qs:woe_adm2":12589305,
    "qs:woe_lau":0,
    "qs:woe_local":2488867,
    "qs:woe_ver":"7.10.0",
    "wof:lang":[
        "eng"
    ],
    "wof:name":"Casa Linda",
    "wof:placetype":"neighbourhood",
    "wof:population":703,
    "zs:blockids":[
        350490010022009,
        350490007001056,
        350490010022012,
        350490010022006,
        350490010022003,
        350490009001012,
        350490010022008,
        350490010022010,
        350490010022020,
        350490010022007,
        350490010022005,
        350490010022004,
        350490010022011,
        350490010022015,
        350490010022017,
        350490009001007,
        350490010022013,
        350490010022014
    ],
    "zs:housing10":402,
    "zs:pop10":703
},
  "geometry": {"coordinates":[-105.964844,35.668951],"type":"Point"}
}