{
  "type": "Feature",
  "properties": {
    "gn:admin1_code":"IA",
    "gn:admin2_code":"163.0",
    "gn:admin3_code":"93849.0",
    "gn:asciiname":"Mount Joy Mobile Home Park",
    "gn:country_code":"US",
    "gn:dem":221,
    "gn:elevation":"220.0",
    "gn:feature_class":"P",
    "gn:feature_code":"PPL",
    "gn:name":"Mount Joy Mobile Home Park",
    "gn:population":0,
    "gn:timezone":"America/Chicago",
    "iso:country":"US",
    "wof:name":"Mount Joy Mobile Home Park",
    "wof:placetype":"campus"
},
  "geometry": {"coordinates":[-90.56125,41.61753],"type":"Point"}
}