{
  "type": "Feature",
  "properties": {
    "gn:admin1_code":"FL",
    "gn:admin2_code":"31.0",
    "gn:asciiname":"Mandeville",
    "gn:country_code":"US",
    "gn:dem":30,
    "gn:elevation":"26.0",
    "gn:feature_class":"P",
    "gn:feature_code":"PPL",
    "gn:name":"Mandeville",
    "gn:population":0,
    "gn:timezone":"America/New_York",
    "iso:country":"US",
    "name:ben_x_preferred":[
        "\u09ae\u09cd\u09af\u09be\u09a8\u09cd\u09a1\u09c7\u09ad\u09bf\u09b2\u09be"
    ],
    "name:cat_x_preferred":[
        "Mandeville"
    ],
    "name:ceb_x_preferred":[
        "Mandeville"
    ],
    "name:ces_x_preferred":[
        "Mandeville"
    ],
    "name:deu_x_preferred":[
        "Mandeville"
    ],
    "name:fas_x_preferred":[
        "\u0645\u0627\u0646\u062f\u0648\u06cc\u0644"
    ],
    "name:fra_x_preferred":[
        "Mandeville"
    ],
    "name:hin_x_preferred":[
        "\u092e\u0948\u0902\u0921\u0935\u093f\u0932"
    ],
    "name:hun_x_preferred":[
        "Mandeville"
    ],
    "name:ind_x_preferred":[
        "Mandeville"
    ],
    "name:ita_x_preferred":[
        "Mandeville"
    ],
    "name:jpn_x_preferred":[
        "\u30de\u30f3\u30c7\u30d3\u30eb"
    ],
    "name:kor_x_preferred":[
        "\ub9e8\ub354\ube4c"
    ],
    "name:nld_x_preferred":[
        "Mandeville"
    ],
    "name:oci_x_preferred":[
        "Mandeville"
    ],
    "name:pol_x_preferred":[
        "Mandeville"
    ],
    "name:por_x_preferred":[
        "Mandeville"
    ],
    "name:spa_x_preferred":[
        "Mandeville"
    ],
    "name:swe_x_preferred":[
        "Mandeville"
    ],
    "name:tur_x_preferred":[
        "Mandeville"
    ],
    "name:urd_x_preferred":[
        "\u0645\u0627\u0646\u0688\u06cc\u0648\u06cc\u0644\u06d2"
    ],
    "name:vie_x_preferred":[
        "Mandeville"
    ],
    "wof:name":"Mandeville",
    "wof:placetype":"locality"
},
  "geometry": {"coordinates":[-81.89399,30.32941],"type":"Point"}
}