{
  "type": "Feature",
  "properties": {
    "gn:admin1_code":"FL",
    "gn:admin2_code":"105.0",
    "gn:asciiname":"Neilson",
    "gn:country_code":"US",
    "gn:dem":34,
    "gn:elevation":"30.0",
    "gn:feature_class":"P",
    "gn:feature_code":"PPL",
    "gn:name":"Neilson",
    "gn:population":0,
    "gn:timezone":"America/New_York",
    "iso:country":"US",
    "name:deu_x_preferred":[
        "Neilson"
    ],
    "name:fin_x_preferred":[
        "Neilson"
    ],
    "name:fra_x_preferred":[
        "Neilson"
    ],
    "name:ita_x_preferred":[
        "Neilson"
    ],
    "name:pol_x_preferred":[
        "Neilson"
    ],
    "wof:name":"Neilson",
    "wof:placetype":"locality"
},
  "geometry": {"coordinates":[-81.50091,27.67836],"type":"Point"}
}