{
  "type": "Feature",
  "properties": {
    "gn:admin1_code":"AL",
    "gn:admin2_code":"33",
    "gn:asciiname":"East Sheffield",
    "gn:country_code":"US",
    "gn:dem":179,
    "gn:elevation":"175.0",
    "gn:feature_class":"P",
    "gn:feature_code":"PPL",
    "gn:name":"East Sheffield",
    "gn:population":0,
    "gn:timezone":"America/Chicago",
    "iso:country":"US",
    "wof:name":"East Sheffield",
    "wof:placetype":"locality"
},
  "geometry": {"coordinates":[-87.67780999999999,34.77092],"type":"Point"}
}