{
  "type": "Feature",
  "properties": {
    "gn:admin1_code":"GA",
    "gn:admin2_code":"45.0",
    "gn:asciiname":"Castlegate East",
    "gn:country_code":"US",
    "gn:dem":337,
    "gn:elevation":"336.0",
    "gn:feature_class":"P",
    "gn:feature_code":"PPL",
    "gn:name":"Castlegate East",
    "gn:population":0,
    "gn:timezone":"America/New_York",
    "iso:country":"US",
    "wof:name":"Castlegate East",
    "wof:placetype":"locality"
},
  "geometry": {"coordinates":[-85.03411,33.60983],"type":"Point"}
}