{
  "type": "Feature",
  "properties": {
    "gn:admin1_code":"CA",
    "gn:admin2_code":"73.0",
    "gn:asciiname":"San Ysidro",
    "gn:country_code":"US",
    "gn:dem":1226,
    "gn:elevation":"1221.0",
    "gn:feature_class":"P",
    "gn:feature_code":"PPL",
    "gn:name":"San Ysidro",
    "gn:population":0,
    "gn:timezone":"America/Los_Angeles",
    "iso:country":"US",
    "wof:name":"San Ysidro",
    "wof:placetype":"locality"
},
  "geometry": {"coordinates":[-116.56641,33.25532],"type":"Point"}
}