{
  "type": "Feature",
  "properties": {
    "gn:admin1_code":"MD",
    "gn:admin2_code":"21.0",
    "gn:asciiname":"Windsor Estates",
    "gn:country_code":"US",
    "gn:dem":120,
    "gn:elevation":"130.0",
    "gn:feature_class":"P",
    "gn:feature_code":"PPL",
    "gn:name":"Windsor Estates",
    "gn:population":0,
    "gn:timezone":"America/New_York",
    "iso:country":"US",
    "wof:name":"Windsor Estates",
    "wof:placetype":"locality"
},
  "geometry": {"coordinates":[-77.47275999999999,39.35121],"type":"Point"}
}