{
  "type": "Feature",
  "properties": {
    "gn:admin1_code":"KS",
    "gn:admin2_code":"89.0",
    "gn:admin3_code":"75650.0",
    "gn:asciiname":"Montrose",
    "gn:country_code":"US",
    "gn:dem":507,
    "gn:elevation":"501.0",
    "gn:feature_class":"P",
    "gn:feature_code":"PPL",
    "gn:name":"Montrose",
    "gn:population":0,
    "gn:timezone":"America/Chicago",
    "iso:country":"US",
    "name:ben_x_preferred":[
        "\u09ae\u09a8\u09cd\u099f\u09cd\u09b0\u09cb\u09b8"
    ],
    "name:ell_x_preferred":[
        "\u039c\u03bf\u03bd\u03c4\u03c1\u03cc\u03bf\u03c5\u03b6"
    ],
    "name:eng_x_preferred":[
        "Montrose"
    ],
    "name:fas_x_preferred":[
        "\u0645\u0648\u0646\u062a\u0631\u0648\u0632"
    ],
    "name:hin_x_preferred":[
        "\u092e\u094b\u0902\u091f\u094d\u0930\u094b\u0938"
    ],
    "name:ind_x_preferred":[
        "Montrose"
    ],
    "name:kor_x_preferred":[
        "\ubaac\ud2b8\ub85c\uc988"
    ],
    "name:und_x_variant":[
        "Delta"
    ],
    "name:zho_x_preferred":[
        "\u8499\u7279\u7f85\u65af"
    ],
    "wof:name":"Montrose",
    "wof:placetype":"locality"
},
  "geometry": {"coordinates":[-98.08783,39.78446],"type":"Point"}
}