{
  "type": "Feature",
  "properties": {
    "gn:admin1_code":"MD",
    "gn:admin2_code":"3.0",
    "gn:asciiname":"Longmeadow",
    "gn:country_code":"US",
    "gn:dem":9,
    "gn:elevation":"9.0",
    "gn:feature_class":"P",
    "gn:feature_code":"PPL",
    "gn:name":"Longmeadow",
    "gn:population":0,
    "gn:timezone":"America/New_York",
    "iso:country":"US",
    "wof:name":"Longmeadow",
    "wof:placetype":"locality"
},
  "geometry": {"coordinates":[-76.53301999999999,39.069],"type":"Point"}
}