{
  "type": "Feature",
  "properties": {
    "gn:elevation":167,
    "iso:country":"US",
    "name:ara_x_preferred":[
        "\u0633\u0627\u0648\u062b\u0647\u0627\u0641\u0646"
    ],
    "name:azb_x_preferred":[
        "\u0633\u0648\u062a\u0627\u0648\u0646"
    ],
    "name:ben_x_preferred":[
        "\u09b8\u09be\u0989\u09a5\u09be\u09ad\u09c7\u09a8"
    ],
    "name:ell_x_preferred":[
        "\u03a3\u03b1\u03bf\u03c5\u03b8\u03c7\u03ad\u03b9\u03b2\u03b5\u03bd"
    ],
    "name:eng_x_preferred":[
        "Southaven"
    ],
    "name:fra_x_preferred":[
        "Southaven"
    ],
    "name:hin_x_preferred":[
        "\u0938\u093e\u0909\u0925\u0947\u0935\u0947\u0928"
    ],
    "name:hun_x_preferred":[
        "Southaven"
    ],
    "name:ind_x_preferred":[
        "Southaven"
    ],
    "name:kor_x_preferred":[
        "\uc0ac\uc6b0\uc2a4\ud5e4\uc774\ube10"
    ],
    "name:rus_x_preferred":[
        "\u0421\u0430\u0443\u0442\u0445\u0435\u0439\u0432\u0435\u043d"
    ],
    "qs:gn_adm0_cc":"US",
    "qs:gn_fcode":"PPLX",
    "qs:gn_local":4613868,
    "qs:gn_namadm1":"TN",
    "qs:gn_name":"Southaven",
    "qs:local_max":772,
    "qs:local_sum":4120,
    "qs:localhoods":28,
    "qs:name":"Southaven",
    "qs:name_adm0":"United States",
    "qs:name_adm1":"Tennessee",
    "qs:name_adm2":"Montgomery",
    "qs:name_local":"Clarksville",
    "qs:photo_max":2,
    "qs:photo_sum":7,
    "qs:placetype":"Suburb",
    "qs:quad_count":6,
    "qs:woe_adm0":23424977,
    "qs:woe_adm1":2347601,
    "qs:woe_adm2":12589974,
    "qs:woe_lau":0,
    "qs:woe_local":2380893,
    "qs:woe_ver":"7.10.0",
    "wd:wordcount":43,
    "wof:lang":[
        "eng"
    ],
    "wof:name":"Southaven",
    "wof:placetype":"neighbourhood",
    "wof:population":1553,
    "zs:blockids":[
        471251010012012,
        471251010012062,
        471251010012019,
        471251010012007,
        471251011011019,
        471251010012060,
        471251010012059,
        471251010012005,
        471251010012003,
        471251010012010,
        471251011011000,
        471251011011018,
        471251010012016,
        471251010012018,
        471251010012011,
        471251010012058,
        471251010012015,
        471251010012004,
        471251010012009,
        471251010012006,
        471251010012063
    ],
    "zs:housing10":702,
    "zs:pop10":1553
},
  "geometry": {"coordinates":[-87.40291000000001,36.570479],"type":"Point"}
}