{
  "type": "Feature",
  "properties": {
    "gn:admin1_code":"MD",
    "gn:admin2_code":"21.0",
    "gn:asciiname":"Robin Meadows",
    "gn:country_code":"US",
    "gn:dem":85,
    "gn:elevation":"86.0",
    "gn:feature_class":"P",
    "gn:feature_code":"PPL",
    "gn:name":"Robin Meadows",
    "gn:population":0,
    "gn:timezone":"America/New_York",
    "iso:country":"US",
    "wof:name":"Robin Meadows",
    "wof:placetype":"locality"
},
  "geometry": {"coordinates":[-77.43026,39.3701],"type":"Point"}
}