{
  "type": "Feature",
  "properties": {
    "gn:admin1_code":"PA",
    "gn:admin2_code":"15.0",
    "gn:admin3_code":"72096.0",
    "gn:asciiname":"Dunning",
    "gn:country_code":"US",
    "gn:dem":381,
    "gn:elevation":"377.0",
    "gn:feature_class":"P",
    "gn:feature_code":"PPL",
    "gn:name":"Dunning",
    "gn:population":0,
    "gn:timezone":"America/New_York",
    "iso:country":"US",
    "name:ceb_x_preferred":[
        "Dunning"
    ],
    "name:cym_x_preferred":[
        "Dunning"
    ],
    "name:eus_x_preferred":[
        "Dunning"
    ],
    "name:gle_x_preferred":[
        "D\u00fan\u00e1n"
    ],
    "name:nld_x_preferred":[
        "Dunning"
    ],
    "name:spa_x_preferred":[
        "Dunning"
    ],
    "name:swe_x_preferred":[
        "Dunning"
    ],
    "wof:name":"Dunning",
    "wof:placetype":"locality"
},
  "geometry": {"coordinates":[-76.79857,41.93341],"type":"Point"}
}