{
  "type": "Feature",
  "properties": {
    "gn:admin1_code":"OK",
    "gn:admin2_code":"13",
    "gn:asciiname":"Kiersey",
    "gn:country_code":"US",
    "gn:dem":231,
    "gn:elevation":"228.0",
    "gn:feature_class":"P",
    "gn:feature_code":"PPL",
    "gn:name":"Kiersey",
    "gn:population":0,
    "gn:timezone":"America/Chicago",
    "iso:country":"US",
    "wof:name":"Kiersey",
    "wof:placetype":"locality"
},
  "geometry": {"coordinates":[-96.46554999999999,34.00565],"type":"Point"}
}