{
  "type": "Feature",
  "properties": {
    "iso:country":"US",
    "name:eng_x_preferred":[
        "South Liberty"
    ],
    "wof:name":"South Liberty",
    "wof:placetype":"neighbourhood",
    "wof:population":88,
    "zs:area_m":5014176.484832,
    "zs:blockids":[
        230270450005036,
        230270450005086,
        230270450005045
    ],
    "zs:housing10":99,
    "zs:label":"South Liberty",
    "zs:pop10":88
},
  "geometry": {"coordinates":[-69.343878,44.364695],"type":"Point"}
}