{
  "type": "Feature",
  "properties": {
    "gn:admin1_code":"NJ",
    "gn:admin2_code":"25.0",
    "gn:admin3_code":"33300.0",
    "gn:asciiname":"Winston Park",
    "gn:country_code":"US",
    "gn:dem":36,
    "gn:elevation":"28.0",
    "gn:feature_class":"P",
    "gn:feature_code":"PPL",
    "gn:name":"Winston Park",
    "gn:population":0,
    "gn:timezone":"America/New_York",
    "iso:country":"US",
    "wof:name":"Winston Park",
    "wof:placetype":"locality"
},
  "geometry": {"coordinates":[-74.23931,40.15761],"type":"Point"}
}