{
  "type": "Feature",
  "properties": {
    "gn:admin1_code":"LA",
    "gn:admin2_code":"101.0",
    "gn:asciiname":"Julien",
    "gn:country_code":"US",
    "gn:dem":5,
    "gn:elevation":"3.0",
    "gn:feature_class":"P",
    "gn:feature_code":"PPL",
    "gn:name":"Julien",
    "gn:population":0,
    "gn:timezone":"America/Chicago",
    "iso:country":"US",
    "name:fra_x_preferred":[
        "Julien"
    ],
    "name:rus_x_preferred":[
        "\u0414\u0436\u0443\u043b\u044c\u0435\u043d"
    ],
    "name:ukr_x_preferred":[
        "\u0414\u0436\u0443\u043b\u0456\u0435\u043d"
    ],
    "wof:name":"Julien",
    "wof:placetype":"locality"
},
  "geometry": {"coordinates":[-91.63234,29.85743],"type":"Point"}
}