{
  "type": "Feature",
  "properties": {
    "gn:admin1_code":"MN",
    "gn:admin2_code":"135",
    "gn:admin3_code":"55546.0",
    "gn:asciiname":"Mobile Court East",
    "gn:country_code":"US",
    "gn:dem":317,
    "gn:elevation":"320.0",
    "gn:feature_class":"P",
    "gn:feature_code":"PPL",
    "gn:name":"Mobile Court East",
    "gn:population":0,
    "gn:timezone":"America/Chicago",
    "iso:country":"US",
    "wof:name":"Mobile Court East",
    "wof:placetype":"locality"
},
  "geometry": {"coordinates":[-95.74833,48.84861],"type":"Point"}
}