{
  "type": "Feature",
  "properties": {
    "gn:admin1_code":"LA",
    "gn:admin2_code":"29.0",
    "gn:asciiname":"Wildsville",
    "gn:country_code":"US",
    "gn:dem":22,
    "gn:elevation":"17.0",
    "gn:feature_class":"P",
    "gn:feature_code":"PPL",
    "gn:name":"Wildsville",
    "gn:population":0,
    "gn:timezone":"America/Chicago",
    "iso:country":"US",
    "wof:name":"Wildsville",
    "wof:placetype":"locality"
},
  "geometry": {"coordinates":[-91.78402,31.61573],"type":"Point"}
}