{
  "type": "Feature",
  "properties": {
    "gn:admin1_code":"AL",
    "gn:admin2_code":"97.0",
    "gn:asciiname":"Pine Haven Mobile Home Park",
    "gn:country_code":"US",
    "gn:dem":70,
    "gn:elevation":"66.0",
    "gn:feature_class":"P",
    "gn:feature_code":"PPL",
    "gn:name":"Pine Haven Mobile Home Park",
    "gn:population":0,
    "gn:timezone":"America/Chicago",
    "iso:country":"US",
    "wof:name":"Pine Haven Mobile Home Park",
    "wof:placetype":"campus"
},
  "geometry": {"coordinates":[-88.23905000000001,30.80202],"type":"Point"}
}