{
  "type": "Feature",
  "properties": {
    "gn:admin1_code":"IN",
    "gn:admin2_code":"89.0",
    "gn:admin3_code":"54414.0",
    "gn:asciiname":"Robertsdale",
    "gn:country_code":"US",
    "gn:dem":179,
    "gn:elevation":"178.0",
    "gn:feature_class":"P",
    "gn:feature_code":"PPL",
    "gn:name":"Robertsdale",
    "gn:population":0,
    "gn:timezone":"America/Chicago",
    "iso:country":"US",
    "name:deu_x_preferred":[
        "Robertsdale"
    ],
    "wof:name":"Robertsdale",
    "wof:placetype":"locality"
},
  "geometry": {"coordinates":[-87.5081,41.68309],"type":"Point"}
}