{
  "type": "Feature",
  "properties": {
    "gn:country":"US",
    "gn:fcode":"PPL",
    "gn:population":2496,
    "iso:country":"US",
    "name:ceb_x_preferred":[
        "Sand Hill"
    ],
    "name:deu_x_preferred":[
        "Sand Hill"
    ],
    "name:eng_x_preferred":[
        "Sand Hill"
    ],
    "name:nds_x_preferred":[
        "Sand Hill"
    ],
    "name:pol_x_preferred":[
        "Sand Hill"
    ],
    "name:srp_x_preferred":[
        "\u0421\u0430\u043d\u0434 \u0425\u0438\u043b"
    ],
    "name:swe_x_preferred":[
        "Sand Hill"
    ],
    "qs_pg:aaroncc":"US",
    "qs_pg:gn_country":"US",
    "qs_pg:gn_fcode":"PPL",
    "qs_pg:gn_pop":2496,
    "qs_pg:name":"Sand Hill",
    "qs_pg:name_adm0":"United States",
    "qs_pg:name_adm1":"Pennsylvania",
    "qs_pg:photos":1,
    "qs_pg:photos_1k":1,
    "qs_pg:photos_9k":1,
    "qs_pg:photos_9r":1,
    "qs_pg:photos_all":1,
    "qs_pg:photos_sr":1,
    "qs_pg:pop_sr":4,
    "qs_pg:qs_pg_placetype":"neighbourhood",
    "qs_pg:qs_pg_placetype_gp":"Suburb",
    "qs_pg:woe_adm0":23424977,
    "wof:name":"Sand Hill",
    "wof:placetype":"neighbourhood",
    "wof:population":177,
    "zs:area_m":1858323.665854,
    "zs:blockids":[
        420750027011008
    ],
    "zs:housing10":75,
    "zs:label":"Sand Hill",
    "zs:pop10":177
},
  "geometry": {"coordinates":[-76.42115800000001,40.372977],"type":"Point"}
}