{
  "type": "Feature",
  "properties": {
    "gn:admin1_code":"VA",
    "gn:admin2_code":"47",
    "gn:asciiname":"Countryside Estates",
    "gn:country_code":"US",
    "gn:dem":133,
    "gn:elevation":"128.0",
    "gn:feature_class":"P",
    "gn:feature_code":"PPL",
    "gn:name":"Countryside Estates",
    "gn:population":0,
    "gn:timezone":"America/New_York",
    "iso:country":"US",
    "wof:name":"Countryside Estates",
    "wof:placetype":"locality"
},
  "geometry": {"coordinates":[-77.92,38.63234],"type":"Point"}
}