{
  "type": "Feature",
  "properties": {
    "gn:admin1_code":"AR",
    "gn:admin2_code":"143.0",
    "gn:admin3_code":"93486.0",
    "gn:asciiname":"Suttle",
    "gn:country_code":"US",
    "gn:dem":435,
    "gn:elevation":"432.0",
    "gn:feature_class":"P",
    "gn:feature_code":"PPL",
    "gn:name":"Suttle",
    "gn:population":0,
    "gn:timezone":"America/Chicago",
    "iso:country":"US",
    "name:fas_x_preferred":[
        "\u0633\u0627\u062a\u0644"
    ],
    "name:zho_x_preferred":[
        "\u85a9\u7279\u723e"
    ],
    "wof:name":"Suttle",
    "wof:placetype":"locality"
},
  "geometry": {"coordinates":[-94.39827,35.97619],"type":"Point"}
}