{
  "type": "Feature",
  "properties": {
    "gn:country":"US",
    "gn:fcode":"PPL",
    "gn:population":0,
    "iso:country":"US",
    "name:cat_x_preferred":[
        "Bonner"
    ],
    "name:ces_x_preferred":[
        "Bonner"
    ],
    "name:deu_x_preferred":[
        "Bonner"
    ],
    "name:fin_x_preferred":[
        "Bonner"
    ],
    "name:fra_x_preferred":[
        "Bonner"
    ],
    "name:ita_x_preferred":[
        "Bonner"
    ],
    "name:por_x_preferred":[
        "Bonner"
    ],
    "name:rus_x_preferred":[
        "\u0411\u043e\u043d\u043d\u0435\u0440"
    ],
    "name:ukr_x_preferred":[
        "\u0411\u043e\u043d\u043d\u0435\u0440"
    ],
    "qs_pg:aaroncc":"US",
    "qs_pg:gn_country":"US",
    "qs_pg:gn_fcode":"PPL",
    "qs_pg:gn_pop":0,
    "qs_pg:name":"Bonner",
    "qs_pg:name_adm0":"United States",
    "qs_pg:name_adm1":"Mississippi",
    "qs_pg:photos":9,
    "qs_pg:photos_1k":2,
    "qs_pg:photos_9k":1,
    "qs_pg:photos_9r":1,
    "qs_pg:photos_all":9,
    "qs_pg:photos_sr":1,
    "qs_pg:pop_sr":0,
    "qs_pg:qs_pg_placetype":"locality",
    "qs_pg:qs_pg_placetype_gp":"Town",
    "qs_pg:woe_adm0":23424977,
    "woe:adm0_id":23424977,
    "woe:name_adm0":"United States",
    "woe:name_adm1":"Mississippi",
    "woe:placetype":"Town",
    "wof:name":"Bonner",
    "wof:placetype":"locality"
},
  "geometry": {"coordinates":[-89.04894,31.81377],"type":"Point"}
}