{
  "type": "Feature",
  "properties": {
    "gn:elevation":44,
    "iso:country":"US",
    "name:eng_x_preferred":[
        "Marlboro County Airport"
    ],
    "name:eng_x_variant":[
        "BBP",
        "BTN",
        "KBBP",
        "H.E. Avent Field",
        "Marlboro County Jetport",
        "Marlboro County Jetport - HE Avent Field"
    ],
    "name:fas_x_preferred":[
        "\u0641\u0631\u0648\u062f\u06af\u0627\u0647 \u0634\u0647\u0631\u0633\u062a\u0627\u0646 \u0645\u0627\u0631\u0644\u0628\u0631\u0648"
    ],
    "name:urd_x_preferred":[
        "\u0645\u0627\u0631\u0644\u0628\u0648\u0631\u0648 \u06a9\u0627\u0624\u0646\u0679\u06cc \u062c\u06cc\u0679 \u067e\u0648\u0631\u0679"
    ],
    "name:zho_x_preferred":[
        "\u99ac\u723e\u4f2f\u52d2\u7e23\u5674\u5c04\u6a5f\u6a5f\u5834"
    ],
    "oa:elevation_ft":"147",
    "oa:type":"small_airport",
    "woe:hierarchy":{
        "country_id":23424977,
        "county_id":12589833,
        "planet_id":1,
        "state_id":2347599
    },
    "wof:name":"Marlboro County Airport",
    "wof:placetype":"campus"
},
  "geometry": {"coordinates":[-79.734398,34.6217],"type":"Point"}
}