{
  "type": "Feature",
  "properties": {
    "iso:country":"US",
    "name:eng_x_preferred":[
        "Rich Acres"
    ],
    "wof:name":"Rich Acres",
    "wof:placetype":"neighbourhood",
    "wof:population":54,
    "zs:area_m":835754.430355,
    "zs:blockids":[
        490572105052009,
        490572105052027
    ],
    "zs:housing10":20,
    "zs:label":"Rich Acres",
    "zs:pop10":54
},
  "geometry": {"coordinates":[-112.028558,41.230397],"type":"Point"}
}