{
  "type": "Feature",
  "properties": {
    "gn:admin1_code":"NM",
    "gn:admin2_code":"37.0",
    "gn:asciiname":"Rain Place",
    "gn:country_code":"US",
    "gn:dem":1215,
    "gn:elevation":"1214.0",
    "gn:feature_class":"P",
    "gn:feature_code":"PPL",
    "gn:name":"Rain Place",
    "gn:population":0,
    "gn:timezone":"America/Denver",
    "iso:country":"US",
    "name:eng_x_preferred":[
        "Rain Place"
    ],
    "name:und_x_variant":[
        "Coyote",
        "Llano del Coyote"
    ],
    "wof:name":"Rain Place",
    "wof:placetype":"locality"
},
  "geometry": {"coordinates":[-103.06634,35.28033],"type":"Point"}
}