{
  "type": "Feature",
  "properties": {
    "gn:admin1_code":"FL",
    "gn:admin2_code":"127.0",
    "gn:asciiname":"Granada Mobile Home Park",
    "gn:country_code":"US",
    "gn:dem":7,
    "gn:elevation":"3.0",
    "gn:feature_class":"P",
    "gn:feature_code":"PPL",
    "gn:name":"Granada Mobile Home Park",
    "gn:population":0,
    "gn:timezone":"America/New_York",
    "iso:country":"US",
    "wof:name":"Granada Mobile Home Park",
    "wof:placetype":"campus"
},
  "geometry": {"coordinates":[-81.06189999999999,29.2848],"type":"Point"}
}