{
  "type": "Feature",
  "properties": {
    "gn:admin1_code":"TN",
    "gn:admin2_code":"23.0",
    "gn:asciiname":"Cabo",
    "gn:country_code":"US",
    "gn:dem":200,
    "gn:elevation":"198.0",
    "gn:feature_class":"P",
    "gn:feature_code":"PPL",
    "gn:name":"Cabo",
    "gn:population":0,
    "gn:timezone":"America/Chicago",
    "iso:country":"US",
    "name:bul_x_preferred":[
        "\u041a\u0430\u0431\u043e"
    ],
    "name:ceb_x_preferred":[
        "Cabo"
    ],
    "name:deu_x_preferred":[
        "Cabo"
    ],
    "name:epo_x_preferred":[
        "Kabo"
    ],
    "name:fra_x_preferred":[
        "Cabo"
    ],
    "name:glg_x_preferred":[
        "Cabo"
    ],
    "name:heb_x_preferred":[
        "\u05e7\u05d0\u05d1\u05d5"
    ],
    "name:ind_x_preferred":[
        "Cabo"
    ],
    "name:ita_x_preferred":[
        "Cabo"
    ],
    "name:mlg_x_preferred":[
        "Cabo"
    ],
    "name:por_x_preferred":[
        "Cabo"
    ],
    "name:rus_x_preferred":[
        "\u041a\u0430\u0431\u043e"
    ],
    "name:spa_x_preferred":[
        "Cabo"
    ],
    "name:swe_x_preferred":[
        "Cabo"
    ],
    "name:ukr_x_preferred":[
        "\u041a\u0430\u0431\u043e"
    ],
    "wof:name":"Cabo",
    "wof:placetype":"locality"
},
  "geometry": {"coordinates":[-88.47421,35.43063],"type":"Point"}
}