{
  "type": "Feature",
  "properties": {
    "gn:gn_country":"US",
    "gn:gn_fcode":"PPL",
    "gn:gn_pop":0,
    "iso:country":"US",
    "name:deu_x_preferred":[
        "Daggett"
    ],
    "name:eng_x_preferred":[
        "Daggett"
    ],
    "name:fra_x_preferred":[
        "Daggett"
    ],
    "name:ita_x_preferred":[
        "Daggett"
    ],
    "name:nds_x_preferred":[
        "Daggett"
    ],
    "name:nld_x_preferred":[
        "Daggett"
    ],
    "name:pol_x_preferred":[
        "Daggett"
    ],
    "name:por_x_preferred":[
        "Daggett"
    ],
    "name:rus_x_preferred":[
        "\u0414\u0430\u0433\u0433\u0435\u0442\u0442"
    ],
    "name:srp_x_preferred":[
        "\u0414\u0430\u0433\u0435\u0442"
    ],
    "name:unk_x_variant":[
        "Calico"
    ],
    "name:vol_x_preferred":[
        "Daggett"
    ],
    "qs_pg:aaroncc":"US",
    "qs_pg:gn_country":"US",
    "qs_pg:gn_fcode":"PPL",
    "qs_pg:gn_pop":0,
    "qs_pg:name":"Daggett",
    "qs_pg:name_adm0":"United States",
    "qs_pg:name_adm1":"California",
    "qs_pg:photos":519,
    "qs_pg:photos_1k":105,
    "qs_pg:photos_9k":2,
    "qs_pg:photos_9r":5,
    "qs_pg:photos_all":519,
    "qs_pg:photos_sr":7,
    "qs_pg:pop_sr":5,
    "qs_pg:qs_pg_placetype":"locality",
    "qs_pg:qs_pg_placetype_gp":"Town",
    "qs_pg:woe_adm0":23424977,
    "woe:adm0_id":23424977,
    "woe:name_adm0":"United States",
    "woe:name_adm1":"California",
    "woe:placetype":"Town",
    "wof:name":"Daggett",
    "wof:placetype":"locality"
},
  "geometry": {"coordinates":[-116.88809000000001,34.86332],"type":"Point"}
}