{
  "type": "Feature",
  "properties": {
    "gn:admin1_code":"CA",
    "gn:admin2_code":"115",
    "gn:asciiname":"Horstville",
    "gn:country_code":"US",
    "gn:dem":34,
    "gn:elevation":"34.0",
    "gn:feature_class":"P",
    "gn:feature_code":"PPL",
    "gn:name":"Horstville",
    "gn:population":0,
    "gn:timezone":"America/Los_Angeles",
    "iso:country":"US",
    "name:zho_x_preferred":[
        "\u970d\u65af\u7279\u7dad\u723e"
    ],
    "wof:name":"Horstville",
    "wof:placetype":"locality"
},
  "geometry": {"coordinates":[-121.39162,39.02795],"type":"Point"}
}