{
  "type": "Feature",
  "properties": {
    "gn:admin1_code":"MD",
    "gn:admin2_code":"3.0",
    "gn:asciiname":"Old Mill Bottom Estates",
    "gn:country_code":"US",
    "gn:dem":29,
    "gn:elevation":"25.0",
    "gn:feature_class":"P",
    "gn:feature_code":"PPL",
    "gn:name":"Old Mill Bottom Estates",
    "gn:population":0,
    "gn:timezone":"America/New_York",
    "iso:country":"US",
    "wof:name":"Old Mill Bottom Estates",
    "wof:placetype":"locality"
},
  "geometry": {"coordinates":[-76.46356999999998,39.02344],"type":"Point"}
}