{
  "type": "Feature",
  "properties": {
    "gn:admin1_code":"GA",
    "gn:admin2_code":"279.0",
    "gn:asciiname":"Cedar Crossing",
    "gn:country_code":"US",
    "gn:dem":69,
    "gn:elevation":"67.0",
    "gn:feature_class":"P",
    "gn:feature_code":"PPL",
    "gn:name":"Cedar Crossing",
    "gn:population":0,
    "gn:timezone":"America/New_York",
    "iso:country":"US",
    "wof:name":"Cedar Crossing",
    "wof:placetype":"locality"
},
  "geometry": {"coordinates":[-82.40791,32.02575],"type":"Point"}
}