{
  "type": "Feature",
  "properties": {
    "gn:admin1_code":"MI",
    "gn:admin2_code":"115.0",
    "gn:admin3_code":"6740.0",
    "gn:asciiname":"Liberty Corners",
    "gn:country_code":"US",
    "gn:dem":192,
    "gn:elevation":"190.0",
    "gn:feature_class":"P",
    "gn:feature_code":"PPL",
    "gn:name":"Liberty Corners",
    "gn:population":0,
    "gn:timezone":"America/Detroit",
    "iso:country":"US",
    "wof:name":"Liberty Corners",
    "wof:placetype":"locality"
},
  "geometry": {"coordinates":[-83.58716,41.74977],"type":"Point"}
}