{
  "type": "Feature",
  "properties": {
    "iso:country":"US",
    "name:eng_x_preferred":[
        "Brentwood-Cavalier"
    ],
    "wof:name":"Brentwood-Cavalier",
    "wof:placetype":"neighbourhood",
    "wof:population":121,
    "zs:area_m":70917.714536,
    "zs:blockids":[
        40133196002016
    ],
    "zs:housing10":55,
    "zs:label":"Brentwood-Cavalier",
    "zs:pop10":121
},
  "geometry": {"coordinates":[-111.93273499999999,33.393926],"type":"Point"}
}