{
  "type": "Feature",
  "properties": {
    "gn:country":"US",
    "gn:fcode":"PPL",
    "gn:population":0,
    "iso:country":"US",
    "name:cat_x_preferred":[
        "Hooverville"
    ],
    "name:deu_x_preferred":[
        "Hooverville"
    ],
    "name:eng_x_preferred":[
        "Hooverville"
    ],
    "name:epo_x_preferred":[
        "Hooverville"
    ],
    "name:fra_x_preferred":[
        "Hooverville"
    ],
    "name:heb_x_preferred":[
        "\u05e2\u05e8\u05d9 \u05d4\u05d5\u05d1\u05e8"
    ],
    "name:ita_x_preferred":[
        "Hooverville"
    ],
    "name:jpn_x_preferred":[
        "\u30d5\u30fc\u30d0\u30fc\u30d3\u30eb"
    ],
    "name:kor_x_preferred":[
        "\ud6c4\ubc84\ube4c"
    ],
    "name:nld_x_preferred":[
        "Hooverville"
    ],
    "name:nob_x_preferred":[
        "Hooverville"
    ],
    "name:por_x_preferred":[
        "Hooverville"
    ],
    "name:rus_x_preferred":[
        "\u0413\u0443\u0432\u0435\u0440\u0432\u0438\u043b\u043b\u044c"
    ],
    "name:spa_x_preferred":[
        "Hooverville"
    ],
    "name:srp_x_preferred":[
        "\u0425\u0443\u0432\u0435\u0440\u0432\u0438\u043b"
    ],
    "name:swe_x_preferred":[
        "Hooverville"
    ],
    "name:zho_x_preferred":[
        "\u80e1\u4f5b\u6751"
    ],
    "qs_pg:aaroncc":"US",
    "qs_pg:gn_country":"US",
    "qs_pg:gn_fcode":"PPL",
    "qs_pg:gn_pop":0,
    "qs_pg:name":"Hooverville",
    "qs_pg:name_adm0":"United States",
    "qs_pg:name_adm1":"Pennsylvania",
    "qs_pg:photos":2,
    "qs_pg:photos_1k":1,
    "qs_pg:photos_9k":1,
    "qs_pg:photos_9r":1,
    "qs_pg:photos_all":2,
    "qs_pg:photos_sr":1,
    "qs_pg:pop_sr":0,
    "qs_pg:qs_pg_placetype":"neighbourhood",
    "qs_pg:qs_pg_placetype_gp":"Suburb",
    "qs_pg:woe_adm0":23424977,
    "wd:wordcount":1433,
    "wof:name":"Hooverville",
    "wof:placetype":"neighbourhood",
    "wof:population":175,
    "zs:area_m":229602.770415,
    "zs:blockids":[
        421298083003086,
        421298083003085,
        421298083003083,
        421298083003066,
        421298083003067,
        421298083003087,
        421298083003079,
        421298083003084,
        421298083003064
    ],
    "zs:housing10":70,
    "zs:label":"Hooverville",
    "zs:pop10":175
},
  "geometry": {"coordinates":[-79.02746,40.412984],"type":"Point"}
}