{
  "type": "Feature",
  "properties": {
    "iso:country":"US",
    "name:eng_x_preferred":[
        "Sierra Vista South"
    ],
    "wof:name":"Sierra Vista South",
    "wof:placetype":"neighbourhood",
    "wof:population":503,
    "zs:area_m":7008255.962888,
    "zs:blockids":[
        350010038041026,
        350010038041023,
        350010038041016,
        350010038041048,
        350010038041029,
        350010038041025,
        350010038041019,
        350010038041017,
        350010038041076,
        350010038041022
    ],
    "zs:housing10":241,
    "zs:label":"Sierra Vista South",
    "zs:pop10":503
},
  "geometry": {"coordinates":[-106.352215,35.12862],"type":"Point"}
}