{
  "type": "Feature",
  "properties": {
    "gn:admin1_code":"GA",
    "gn:admin2_code":"77",
    "gn:asciiname":"Willow Creek Subdivision",
    "gn:country_code":"US",
    "gn:dem":286,
    "gn:elevation":"270.0",
    "gn:feature_class":"P",
    "gn:feature_code":"PPL",
    "gn:name":"Willow Creek Subdivision",
    "gn:population":0,
    "gn:timezone":"America/New_York",
    "iso:country":"US",
    "wof:name":"Willow Creek Subdivision",
    "wof:placetype":"locality"
},
  "geometry": {"coordinates":[-84.80159999999999,33.439],"type":"Point"}
}