{
  "type": "Feature",
  "properties": {
    "gn:admin1_code":"RI",
    "gn:admin2_code":"5.0",
    "gn:admin3_code":"36820.0",
    "gn:asciiname":"Clarks Village",
    "gn:country_code":"US",
    "gn:dem":-12,
    "gn:elevation":"10.0",
    "gn:feature_class":"P",
    "gn:feature_code":"PPL",
    "gn:name":"Clarks Village",
    "gn:population":0,
    "gn:timezone":"America/New_York",
    "iso:country":"US",
    "wof:name":"Clarks Village",
    "wof:placetype":"locality"
},
  "geometry": {"coordinates":[-71.39061,41.4626],"type":"Point"}
}