{
  "type": "Feature",
  "properties": {
    "gn:admin1_code":"SC",
    "gn:admin2_code":"51.0",
    "gn:asciiname":"Singleton Crossroads",
    "gn:country_code":"US",
    "gn:dem":13,
    "gn:elevation":"18.0",
    "gn:feature_class":"P",
    "gn:feature_code":"PPL",
    "gn:name":"Singleton Crossroads",
    "gn:population":0,
    "gn:timezone":"America/New_York",
    "iso:country":"US",
    "wof:name":"Singleton Crossroads",
    "wof:placetype":"locality"
},
  "geometry": {"coordinates":[-79.19532,33.83572],"type":"Point"}
}