{
  "type": "Feature",
  "properties": {
    "gn:admin1_code":"VA",
    "gn:admin2_code":"770",
    "gn:asciiname":"Liberty Land",
    "gn:country_code":"US",
    "gn:dem":307,
    "gn:elevation":"311.0",
    "gn:feature_class":"P",
    "gn:feature_code":"PPL",
    "gn:name":"Liberty Land",
    "gn:population":0,
    "gn:timezone":"America/New_York",
    "iso:country":"US",
    "wof:name":"Liberty Land",
    "wof:placetype":"locality"
},
  "geometry": {"coordinates":[-79.93698000000001,37.29791],"type":"Point"}
}