{
  "type": "Feature",
  "properties": {
    "gn:admin1_code":"ND",
    "gn:admin2_code":"25.0",
    "gn:admin3_code":"74105.0",
    "gn:asciiname":"Hirschville",
    "gn:country_code":"US",
    "gn:dem":646,
    "gn:elevation":"648.0",
    "gn:feature_class":"P",
    "gn:feature_code":"PPL",
    "gn:name":"Hirschville",
    "gn:population":0,
    "gn:timezone":"America/Denver",
    "iso:country":"US",
    "name:azb_x_preferred":[
        "\u0647\u06cc\u0631\u0634\u0648\u06cc\u0644"
    ],
    "name:fas_x_preferred":[
        "\u0647\u06cc\u0631\u0634\u0648\u06cc\u0644"
    ],
    "wof:name":"Hirschville",
    "wof:placetype":"locality"
},
  "geometry": {"coordinates":[-102.5638,47.06806],"type":"Point"}
}