{
  "type": "Feature",
  "properties": {
    "gn:admin1_code":"PA",
    "gn:admin2_code":"121.0",
    "gn:admin3_code":"16944.0",
    "gn:asciiname":"Tippery",
    "gn:country_code":"US",
    "gn:dem":453,
    "gn:elevation":"449.0",
    "gn:feature_class":"P",
    "gn:feature_code":"PPL",
    "gn:name":"Tippery",
    "gn:population":0,
    "gn:timezone":"America/New_York",
    "iso:country":"US",
    "name:eng_x_preferred":[
        "Tippery"
    ],
    "name:und_x_variant":[
        "Tenmile Bottom"
    ],
    "wof:name":"Tippery",
    "wof:placetype":"locality"
},
  "geometry": {"coordinates":[-79.63727,41.37756],"type":"Point"}
}