{
  "type": "Feature",
  "properties": {
    "gn:admin1_code":"OR",
    "gn:admin2_code":"53",
    "gn:asciiname":"Buell",
    "gn:country_code":"US",
    "gn:dem":125,
    "gn:elevation":"121.0",
    "gn:feature_class":"P",
    "gn:feature_code":"PPL",
    "gn:name":"Buell",
    "gn:population":0,
    "gn:timezone":"America/Los_Angeles",
    "iso:country":"US",
    "name:deu_x_preferred":[
        "Buell"
    ],
    "name:epo_x_preferred":[
        "Buell"
    ],
    "name:fra_x_preferred":[
        "Buell"
    ],
    "name:heb_x_preferred":[
        "\u05d1\u05d5\u05d0\u05dc"
    ],
    "name:ita_x_preferred":[
        "Buell"
    ],
    "name:nld_x_preferred":[
        "Buell"
    ],
    "name:rus_x_preferred":[
        "\u0411\u044c\u044e\u044d\u043b\u043b"
    ],
    "wof:name":"Buell",
    "wof:placetype":"locality"
},
  "geometry": {"coordinates":[-123.41844,45.01623],"type":"Point"}
}