{
  "type": "Feature",
  "properties": {
    "gn:admin1_code":"GA",
    "gn:admin2_code":"77.0",
    "gn:asciiname":"Madras",
    "gn:country_code":"US",
    "gn:dem":305,
    "gn:elevation":"299.0",
    "gn:feature_class":"P",
    "gn:feature_code":"PPL",
    "gn:name":"Madras",
    "gn:population":0,
    "gn:timezone":"America/New_York",
    "iso:country":"US",
    "name:eng_x_preferred":[
        "Madras"
    ],
    "name:und_x_variant":[
        "Powell Station",
        "Powellville",
        "Powellton",
        "Madres",
        "Powells Station",
        "Powelville",
        "Powellton Station"
    ],
    "wof:name":"Madras",
    "wof:placetype":"locality"
},
  "geometry": {"coordinates":[-84.74216,33.44011],"type":"Point"}
}