{
  "type": "Feature",
  "properties": {
    "gn:admin1_code":"IL",
    "gn:admin2_code":"197",
    "gn:admin3_code":"35827.0",
    "gn:asciiname":"Erin Hills",
    "gn:country_code":"US",
    "gn:dem":203,
    "gn:elevation":"202.0",
    "gn:feature_class":"P",
    "gn:feature_code":"PPL",
    "gn:name":"Erin Hills",
    "gn:population":0,
    "gn:timezone":"America/Chicago",
    "iso:country":"US",
    "name:nld_x_preferred":[
        "Erin Hills Golf Course"
    ],
    "wof:name":"Erin Hills",
    "wof:placetype":"locality"
},
  "geometry": {"coordinates":[-87.96250000000001,41.63806],"type":"Point"}
}