{
  "type": "Feature",
  "properties": {
    "gn:admin1_code":"OH",
    "gn:admin2_code":"167",
    "gn:admin3_code":"37268.0",
    "gn:asciiname":"Leith",
    "gn:country_code":"US",
    "gn:dem":191,
    "gn:elevation":"188.0",
    "gn:feature_class":"P",
    "gn:feature_code":"PPL",
    "gn:name":"Leith",
    "gn:population":0,
    "gn:timezone":"America/New_York",
    "iso:country":"US",
    "name:cat_x_preferred":[
        "Leith"
    ],
    "name:dan_x_preferred":[
        "Leith"
    ],
    "name:deu_x_preferred":[
        "Leith"
    ],
    "name:eus_x_preferred":[
        "Leith"
    ],
    "name:fin_x_preferred":[
        "Leith"
    ],
    "name:fra_x_preferred":[
        "Leith"
    ],
    "name:gla_x_preferred":[
        "L\u00ecte"
    ],
    "name:ita_x_preferred":[
        "Leith"
    ],
    "name:kaz_x_preferred":[
        "\u041b\u0438\u0442"
    ],
    "name:kor_x_preferred":[
        "\ub9ac\uc2a4"
    ],
    "name:nor_x_preferred":[
        "Leith"
    ],
    "name:pol_x_preferred":[
        "Leith"
    ],
    "name:ron_x_preferred":[
        "Leith"
    ],
    "name:rus_x_preferred":[
        "\u041b\u0438\u0442"
    ],
    "name:sco_x_preferred":[
        "Leith"
    ],
    "name:spa_x_preferred":[
        "Leith"
    ],
    "name:swe_x_preferred":[
        "Leith"
    ],
    "name:tha_x_preferred":[
        "\u0e25\u0e35\u0e18"
    ],
    "name:zho_x_preferred":[
        "\u5229\u65af"
    ],
    "wof:name":"Leith",
    "wof:placetype":"locality"
},
  "geometry": {"coordinates":[-81.15039,39.45535],"type":"Point"}
}