{
  "type": "Feature",
  "properties": {
    "gn:admin1_code":"SC",
    "gn:admin2_code":"27.0",
    "gn:asciiname":"Cypress Fork Crossroads",
    "gn:country_code":"US",
    "gn:dem":30,
    "gn:elevation":"29.0",
    "gn:feature_class":"P",
    "gn:feature_code":"PPL",
    "gn:name":"Cypress Fork Crossroads",
    "gn:population":0,
    "gn:timezone":"America/New_York",
    "iso:country":"US",
    "name:eng_x_preferred":[
        "Cypress Fork Crossroads"
    ],
    "name:und_x_variant":[
        "Cypress Fork Cross Roads"
    ],
    "wof:name":"Cypress Fork Crossroads",
    "wof:placetype":"locality"
},
  "geometry": {"coordinates":[-80.07451999999998,33.74711],"type":"Point"}
}