{
  "type": "Feature",
  "properties": {
    "gn:elevation":1,
    "iso:country":"US",
    "name:ceb_x_preferred":[
        "Ridgewood Park"
    ],
    "name:eng_x_preferred":[
        "Ridgewood Lakes"
    ],
    "name:eng_x_variant":[
        "Ridgewood Park"
    ],
    "name:nld_x_preferred":[
        "Ridgewood Park"
    ],
    "name:unk_x_variant":[
        "Ridgewood Lakes"
    ],
    "qs:gn_adm0_cc":"US",
    "qs:gn_fcode":"PPL",
    "qs:gn_local":4152805,
    "qs:gn_nam_loc":"Davenport, Polk, Florida, US",
    "qs:gn_namadm1":"FL",
    "qs:gn_name":"Ridgewood Park",
    "qs:local_max":201,
    "qs:local_sum":616,
    "qs:localhoods":10,
    "qs:name":"Ridgewood Lakes",
    "qs:name_adm0":"United States",
    "qs:name_adm1":"Florida",
    "qs:name_adm2":"Polk",
    "qs:name_local":"Davenport",
    "qs:photo_max":1,
    "qs:photo_sum":1,
    "qs:placetype":"Suburb",
    "qs:quad_count":1,
    "qs:woe_adm0":23424977,
    "qs:woe_adm1":2347568,
    "qs:woe_adm2":12587855,
    "qs:woe_lau":0,
    "qs:woe_local":2389560,
    "qs:woe_ver":"7.10.0",
    "wof:lang":[
        "eng"
    ],
    "wof:name":"Ridgewood Lakes",
    "wof:placetype":"neighbourhood"
},
  "geometry": {"coordinates":[-81.620178,28.176138],"type":"Point"}
}