{
  "type": "Feature",
  "properties": {
    "gn:admin1_code":"SC",
    "gn:admin2_code":"7.0",
    "gn:asciiname":"West Anderson",
    "gn:country_code":"US",
    "gn:dem":245,
    "gn:elevation":"240.0",
    "gn:feature_class":"P",
    "gn:feature_code":"PPL",
    "gn:name":"West Anderson",
    "gn:population":0,
    "gn:timezone":"America/New_York",
    "iso:country":"US",
    "wof:name":"West Anderson",
    "wof:placetype":"locality"
},
  "geometry": {"coordinates":[-82.68819000000001,34.50205],"type":"Point"}
}