{
  "type": "Feature",
  "properties": {
    "iso:country":"US",
    "name:ara_x_preferred":[
        "\u0628\u0631\u064a\u0627\u0646 \u0648\u0648\u062f\u0632"
    ],
    "name:arz_x_preferred":[
        "\u0628\u0631\u064a\u0627\u0646 \u0648\u0648\u062f\u0632"
    ],
    "name:ast_x_preferred":[
        "Bryan Woods"
    ],
    "name:cat_x_preferred":[
        "Bryan Woods"
    ],
    "name:dan_x_preferred":[
        "Bryan Woods"
    ],
    "name:deu_x_preferred":[
        "Bryan Woods"
    ],
    "name:eng_x_preferred":[
        "Bryan Woods"
    ],
    "name:fas_x_preferred":[
        "\u0628\u0631\u0627\u06cc\u0627\u0646 \u0648\u0648\u062f\u0632"
    ],
    "name:fin_x_preferred":[
        "Bryan Woods"
    ],
    "name:fra_x_preferred":[
        "Bryan Woods"
    ],
    "name:gle_x_preferred":[
        "Bryan Woods"
    ],
    "name:heb_x_preferred":[
        "\u05d1\u05e8\u05d9\u05d0\u05df \u05d5\u05d5\u05d3\u05e1"
    ],
    "name:hun_x_preferred":[
        "Bryan Woods"
    ],
    "name:ita_x_preferred":[
        "Bryan Woods"
    ],
    "name:jpn_x_preferred":[
        "\u30d6\u30e9\u30a4\u30a2\u30f3\u30fb\u30a6\u30c3\u30ba"
    ],
    "name:nld_x_preferred":[
        "Bryan Woods"
    ],
    "name:nno_x_preferred":[
        "Bryan Woods"
    ],
    "name:nob_x_preferred":[
        "Bryan Woods"
    ],
    "name:pap_x_preferred":[
        "Bryan Woods"
    ],
    "name:por_x_preferred":[
        "Bryan Woods"
    ],
    "name:rus_x_preferred":[
        "\u0411\u0440\u0430\u0439\u0430\u043d \u0412\u0443\u0434\u0441"
    ],
    "name:slv_x_preferred":[
        "Bryan Woods"
    ],
    "name:spa_x_preferred":[
        "Bryan Woods"
    ],
    "name:sqi_x_preferred":[
        "Bryan Woods"
    ],
    "name:swe_x_preferred":[
        "Bryan Woods"
    ],
    "name:zho_x_preferred":[
        "\u5e03\u83b1\u6069\u00b7\u4f0d\u5179"
    ],
    "wd:wordcount":126,
    "wof:name":"Bryan Woods",
    "wof:placetype":"neighbourhood",
    "wof:population":1140,
    "zs:area_m":793671.793015,
    "zs:blockids":[
        371830524063014,
        371830524063013,
        371830524063019,
        371830535171018,
        371830535161001,
        371830524063003,
        371830524063008,
        371830524063007,
        371830535171020,
        371830524063015,
        371830535161000
    ],
    "zs:housing10":621,
    "zs:label":"Bryan Woods",
    "zs:pop10":1140
},
  "geometry": {"coordinates":[-78.739389,35.779194],"type":"Point"}
}