{
  "type": "Feature",
  "properties": {
    "gn:admin1_code":"MI",
    "gn:admin2_code":"105.0",
    "gn:admin3_code":"73060.0",
    "gn:asciiname":"Batcheller",
    "gn:country_code":"US",
    "gn:dem":225,
    "gn:elevation":"219.0",
    "gn:feature_class":"P",
    "gn:feature_code":"PPL",
    "gn:name":"Batcheller",
    "gn:population":0,
    "gn:timezone":"America/Detroit",
    "iso:country":"US",
    "name:eng_x_preferred":[
        "Batcheller"
    ],
    "name:und_x_variant":[
        "Batchelor",
        "Bachelor"
    ],
    "wof:name":"Batcheller",
    "wof:placetype":"locality"
},
  "geometry": {"coordinates":[-86.13091,44.00417],"type":"Point"}
}