{
  "type": "Feature",
  "properties": {
    "iso:country":"US",
    "name:eng_x_preferred":[
        "Talbot Hill"
    ],
    "qs:gn_adm0_cc":"US",
    "qs:gn_local":5808189,
    "qs:gn_nam_loc":"Renton, King, Washington, US",
    "qs:gn_namadm1":"WA",
    "qs:local_max":3249,
    "qs:local_sum":5819,
    "qs:localhoods":13,
    "qs:name":"Talbot Hill",
    "qs:name_adm0":"United States",
    "qs:name_adm1":"Washington",
    "qs:name_adm2":"King",
    "qs:name_local":"Renton",
    "qs:photo_max":4,
    "qs:photo_sum":6,
    "qs:placetype":"Suburb",
    "qs:quad_count":3,
    "qs:woe_adm0":23424977,
    "qs:woe_adm1":2347606,
    "qs:woe_adm2":12590456,
    "qs:woe_lau":0,
    "qs:woe_local":2480240,
    "qs:woe_ver":"7.10.0",
    "wof:lang":[
        "eng"
    ],
    "wof:name":"Talbot Hill",
    "wof:placetype":"neighbourhood",
    "wof:population":1103,
    "zs:blockids":[
        530330258061020,
        530330262001188,
        530330293035006,
        530330258061007,
        530330262001180,
        530330262001179,
        530330262001184,
        530330262001183,
        530330258061016,
        530330258062000,
        530330258061015,
        530330258061004,
        530330262001182,
        530330262001181,
        530330292061001,
        530330262001177,
        530330258061014,
        530330262001176,
        530330258061012,
        530330258061017,
        530330293035012,
        530330258052014,
        530330258061005,
        530330292061000,
        530330292061002,
        530330258062002,
        530330258061008
    ],
    "zs:housing10":379,
    "zs:pop10":1103
},
  "geometry": {"coordinates":[-122.211113,47.464462],"type":"Point"}
}