{
  "type": "Feature",
  "properties": {
    "gn:admin1_code":"KS",
    "gn:admin2_code":"183",
    "gn:admin3_code":"5200.0",
    "gn:asciiname":"Thornburg",
    "gn:country_code":"US",
    "gn:dem":638,
    "gn:elevation":"635.0",
    "gn:feature_class":"P",
    "gn:feature_code":"PPL",
    "gn:name":"Thornburg",
    "gn:population":0,
    "gn:timezone":"America/Chicago",
    "iso:country":"US",
    "wof:name":"Thornburg",
    "wof:placetype":"locality"
},
  "geometry": {"coordinates":[-98.78619,39.94446],"type":"Point"}
}