{
  "type": "Feature",
  "properties": {
    "iso:country":"US",
    "name:ara_x_preferred":[
        "\u062d\u0644\u0642\u0629"
    ],
    "name:bos_x_preferred":[
        "Prsten"
    ],
    "name:ces_x_preferred":[
        "Ring"
    ],
    "name:chv_x_preferred":[
        "\u0423\u043d\u043a\u0103"
    ],
    "name:dan_x_preferred":[
        "Ring"
    ],
    "name:deu_x_preferred":[
        "Ring"
    ],
    "name:eng_x_preferred":[
        "Ring"
    ],
    "name:est_x_preferred":[
        "Ring"
    ],
    "name:fas_x_preferred":[
        "\u062d\u0644\u0642\u0647"
    ],
    "name:fra_x_preferred":[
        "Ring"
    ],
    "name:hbs_x_preferred":[
        "Prsten"
    ],
    "name:heb_x_preferred":[
        "\u05d8\u05d1\u05e2\u05ea"
    ],
    "name:hrv_x_preferred":[
        "Prsten"
    ],
    "name:hun_x_preferred":[
        "Ring"
    ],
    "name:ind_x_preferred":[
        "Ring"
    ],
    "name:ita_x_preferred":[
        "Ring"
    ],
    "name:jpn_x_preferred":[
        "\u30ea\u30f3\u30b0"
    ],
    "name:kor_x_preferred":[
        "\ub9c1"
    ],
    "name:lit_x_preferred":[
        "\u017diedas"
    ],
    "name:nds_x_preferred":[
        "Ring"
    ],
    "name:nld_x_preferred":[
        "Ring"
    ],
    "name:nno_x_preferred":[
        "Ring"
    ],
    "name:nor_x_preferred":[
        "Ring"
    ],
    "name:pol_x_preferred":[
        "Ring"
    ],
    "name:por_x_preferred":[
        "Ring"
    ],
    "name:rus_x_preferred":[
        "Ring"
    ],
    "name:spa_x_preferred":[
        "Ring"
    ],
    "name:srp_x_preferred":[
        "\u041f\u0440\u0441\u0442\u0435\u043d"
    ],
    "name:swe_x_preferred":[
        "Ring"
    ],
    "name:tgl_x_preferred":[
        "Ring"
    ],
    "name:tha_x_preferred":[
        "\u0e23\u0e34\u0e07"
    ],
    "name:ukr_x_preferred":[
        "\u041a\u0456\u043b\u044c\u0446\u0435"
    ],
    "name:ukr_x_variant":[
        "Ring"
    ],
    "name:zho_x_preferred":[
        "Ring"
    ],
    "name:zho_yue_x_preferred":[
        "Ring"
    ],
    "wd:wordcount":350,
    "wof:name":"Ring",
    "wof:placetype":"neighbourhood",
    "wof:population":37,
    "zs:area_m":3943060.836121,
    "zs:blockids":[
        551390020004115
    ],
    "zs:housing10":18,
    "zs:label":"Ring",
    "zs:pop10":37
},
  "geometry": {"coordinates":[-88.712165,43.909258],"type":"Point"}
}