{
  "type": "Feature",
  "properties": {
    "iso:country":"US",
    "name:ceb_x_preferred":[
        "Swan Creek"
    ],
    "name:deu_x_preferred":[
        "Swan Creek"
    ],
    "name:pol_x_preferred":[
        "Swan Creek"
    ],
    "name:swe_x_preferred":[
        "Swan Creek"
    ],
    "qs_pg:aaroncc":"US",
    "qs_pg:name":"Swan Creek",
    "qs_pg:name_adm0":"United States",
    "qs_pg:name_adm1":"Utah",
    "qs_pg:photos":6,
    "qs_pg:photos_1k":1,
    "qs_pg:photos_9k":1,
    "qs_pg:photos_9r":1,
    "qs_pg:photos_all":6,
    "qs_pg:photos_sr":1,
    "qs_pg:pop_sr":0,
    "qs_pg:qs_pg_placetype":"locality",
    "qs_pg:qs_pg_placetype_gp":"Town",
    "qs_pg:woe_adm0":23424977,
    "woe:adm0_id":23424977,
    "woe:name_adm0":"United States",
    "woe:name_adm1":"Utah",
    "woe:placetype":"Town",
    "wof:name":"Swan Creek",
    "wof:placetype":"locality"
},
  "geometry": {"coordinates":[-111.41117250000001,41.9770305],"type":"Point"}
}