{
  "type": "Feature",
  "properties": {
    "gn:admin1_code":"TN",
    "gn:admin2_code":"51.0",
    "gn:asciiname":"Shady Grove",
    "gn:country_code":"US",
    "gn:dem":299,
    "gn:elevation":"300.0",
    "gn:feature_class":"P",
    "gn:feature_code":"PPL",
    "gn:name":"Shady Grove",
    "gn:population":0,
    "gn:timezone":"America/Chicago",
    "iso:country":"US",
    "name:cat_x_preferred":[
        "Shady Grove"
    ],
    "name:ceb_x_preferred":[
        "Shady Grove"
    ],
    "name:deu_x_preferred":[
        "Shady Grove"
    ],
    "name:ita_x_preferred":[
        "Shady Grove"
    ],
    "name:nld_x_preferred":[
        "Shady Grove"
    ],
    "name:pol_x_preferred":[
        "Shady Grove"
    ],
    "name:srp_x_preferred":[
        "\u0428\u0435\u0458\u0434\u0438 \u0413\u0440\u043e\u0443\u0432"
    ],
    "name:vol_x_preferred":[
        "Shady Grove"
    ],
    "wof:name":"Shady Grove",
    "wof:placetype":"locality"
},
  "geometry": {"coordinates":[-85.98943,35.30397],"type":"Point"}
}