{
  "type": "Feature",
  "properties": {
    "gn:admin1_code":"NC",
    "gn:admin2_code":"109",
    "gn:admin3_code":"92300.0",
    "gn:asciiname":"Hulls Crossroads",
    "gn:country_code":"US",
    "gn:dem":336,
    "gn:elevation":"334.0",
    "gn:feature_class":"P",
    "gn:feature_code":"PPL",
    "gn:name":"Hulls Crossroads",
    "gn:population":0,
    "gn:timezone":"America/New_York",
    "iso:country":"US",
    "name:eng_x_preferred":[
        "Hulls Crossroads"
    ],
    "name:und_x_variant":[
        "Hull Crossroads",
        "Hull X Roads"
    ],
    "wof:name":"Hulls Crossroads",
    "wof:placetype":"locality"
},
  "geometry": {"coordinates":[-81.45730999999998,35.50874],"type":"Point"}
}