{
  "type": "Feature",
  "properties": {
    "iso:country":"US",
    "name:cat_x_preferred":[
        "Norwood"
    ],
    "name:ceb_x_preferred":[
        "Norwood"
    ],
    "name:ces_x_preferred":[
        "Norwood"
    ],
    "name:deu_x_preferred":[
        "Norwood"
    ],
    "name:eng_x_preferred":[
        "Norwood"
    ],
    "name:fas_x_preferred":[
        "\u0646\u0648\u0631\u0648\u0648\u062f"
    ],
    "name:fra_x_preferred":[
        "Norwood"
    ],
    "name:ita_x_preferred":[
        "Norwood"
    ],
    "name:nld_x_preferred":[
        "Norwood"
    ],
    "name:pol_x_preferred":[
        "Norwood"
    ],
    "name:por_x_preferred":[
        "Norwood"
    ],
    "name:rus_x_preferred":[
        "\u041d\u043e\u0440\u0432\u0443\u0434"
    ],
    "name:srp_x_preferred":[
        "\u041d\u043e\u0440\u0432\u0443\u0434"
    ],
    "name:swa_x_preferred":[
        "Norwood"
    ],
    "name:swe_x_preferred":[
        "Norwood"
    ],
    "wof:name":"Norwood",
    "wof:placetype":"neighbourhood",
    "wof:population":903,
    "zs:area_m":2573362.570292,
    "zs:blockids":[
        51430110022020,
        51430105045026,
        51430105043095,
        51430105043084,
        51430105043092,
        51430110022013,
        51430110022022,
        51430105043091,
        51430110022018,
        51430110022019,
        51430105045028,
        51430105043085,
        51430105043094,
        51430105045024,
        51430110022012,
        51430105045025,
        51430105045022,
        51430105045035,
        51430105045023,
        51430105045021,
        51430110022014,
        51430110022045,
        51430105045020,
        51430105045036,
        51430105045037,
        51430110022021,
        51430110022023,
        51430105043093
    ],
    "zs:housing10":399,
    "zs:label":"Norwood",
    "zs:pop10":903
},
  "geometry": {"coordinates":[-94.412798,35.949063],"type":"Point"}
}