{
  "type": "Feature",
  "properties": {
    "gn:admin1_code":"FL",
    "gn:admin2_code":"57",
    "gn:asciiname":"Hill Top Heights",
    "gn:country_code":"US",
    "gn:dem":25,
    "gn:elevation":"14.0",
    "gn:feature_class":"P",
    "gn:feature_code":"PPL",
    "gn:name":"Hill Top Heights",
    "gn:population":0,
    "gn:timezone":"America/New_York",
    "iso:country":"US",
    "wof:name":"Hill Top Heights",
    "wof:placetype":"locality"
},
  "geometry": {"coordinates":[-82.42749999999999,28.0129],"type":"Point"}
}