{
  "type": "Feature",
  "properties": {
    "gn:country":"US",
    "gn:fcode":"PPL",
    "gn:population":0,
    "iso:country":"US",
    "name:ast_x_preferred":[
        "Brogue"
    ],
    "name:deu_x_preferred":[
        "Brogue"
    ],
    "name:eng_x_preferred":[
        "Brogue"
    ],
    "name:eus_x_preferred":[
        "Brogue"
    ],
    "name:spa_x_preferred":[
        "Brogue"
    ],
    "name:und_x_variant":[
        "Union"
    ],
    "qs_pg:aaroncc":"US",
    "qs_pg:gn_country":"US",
    "qs_pg:gn_fcode":"PPL",
    "qs_pg:gn_pop":0,
    "qs_pg:name":"Brogue",
    "qs_pg:name_adm0":"United States",
    "qs_pg:name_adm1":"Pennsylvania",
    "qs_pg:photos":12,
    "qs_pg:photos_1k":2,
    "qs_pg:photos_9k":1,
    "qs_pg:photos_9r":1,
    "qs_pg:photos_all":12,
    "qs_pg:photos_sr":1,
    "qs_pg:pop_sr":0,
    "qs_pg:qs_pg_placetype":"locality",
    "qs_pg:qs_pg_placetype_gp":"Town",
    "qs_pg:woe_adm0":23424977,
    "woe:adm0_id":23424977,
    "woe:name_adm0":"United States",
    "woe:name_adm1":"Pennsylvania",
    "woe:placetype":"Town",
    "wof:name":"Brogue",
    "wof:placetype":"locality"
},
  "geometry": {"coordinates":[-76.48302,39.87177],"type":"Point"}
}