{
  "type": "Feature",
  "properties": {
    "gn:admin1_code":"TX",
    "gn:admin2_code":"213.0",
    "gn:asciiname":"Sumer Hill",
    "gn:country_code":"US",
    "gn:dem":151,
    "gn:elevation":"148.0",
    "gn:feature_class":"P",
    "gn:feature_code":"PPL",
    "gn:name":"Sumer Hill",
    "gn:population":0,
    "gn:timezone":"America/Chicago",
    "iso:country":"US",
    "wof:name":"Sumer Hill",
    "wof:placetype":"locality"
},
  "geometry": {"coordinates":[-95.82080000000001,32.33681],"type":"Point"}
}