{
  "type": "Feature",
  "properties": {
    "gn:admin1_code":"OH",
    "gn:admin2_code":"41.0",
    "gn:admin3_code":"29694.0",
    "gn:asciiname":"Lake of the Woods",
    "gn:country_code":"US",
    "gn:dem":279,
    "gn:elevation":"279.0",
    "gn:feature_class":"P",
    "gn:feature_code":"PPL",
    "gn:name":"Lake of the Woods",
    "gn:population":0,
    "gn:timezone":"America/New_York",
    "iso:country":"US",
    "name:ara_x_preferred":[
        "\u0628\u062d\u064a\u0631\u0629 \u0627\u0644\u063a\u0627\u0628\u0627\u062a"
    ],
    "name:aze_x_preferred":[
        "Me\u015f\u0259li g\u00f6l"
    ],
    "name:bul_x_preferred":[
        "\u0413\u043e\u0440\u0441\u043a\u043e \u0435\u0437\u0435\u0440\u043e"
    ],
    "name:ces_x_preferred":[
        "Lesn\u00ed jezero"
    ],
    "name:deu_x_preferred":[
        "Lake of the Woods"
    ],
    "name:est_x_preferred":[
        "Lake of the Woods"
    ],
    "name:eus_x_preferred":[
        "Oihanetako aintzira"
    ],
    "name:fin_x_preferred":[
        "Lake of the Woods"
    ],
    "name:fra_x_preferred":[
        "Lac des Bois"
    ],
    "name:ita_x_preferred":[
        "Lago dei Boschi"
    ],
    "name:kat_x_preferred":[
        "\u10e2\u10e7\u10d8\u10e1 \u10e2\u10d1\u10d0"
    ],
    "name:lav_x_preferred":[
        "Vudsu ezers"
    ],
    "name:lit_x_preferred":[
        "Mi\u0161k\u0173 e\u017eeras"
    ],
    "name:mkd_x_preferred":[
        "\u0428\u0443\u043c\u0441\u043a\u043e \u0415\u0437\u0435\u0440\u043e"
    ],
    "name:nld_x_preferred":[
        "Lake of the Woods"
    ],
    "name:por_x_preferred":[
        "Lago dos Bosques"
    ],
    "name:srp_x_preferred":[
        "\u0428\u0443\u043c\u0441\u043a\u043e \u0458\u0435\u0437\u0435\u0440\u043e"
    ],
    "name:swe_x_preferred":[
        "Lake of the Woods"
    ],
    "name:ukr_x_preferred":[
        "\u041b\u0456\u0441\u043e\u0432\u0435 \u043e\u0437\u0435\u0440\u043e"
    ],
    "name:xmf_x_preferred":[
        "\u10e2\u10e7\u10d0\u10e8 \u10e2\u10dd\u10d1\u10d0"
    ],
    "wof:name":"Lake of the Woods",
    "wof:placetype":"locality"
},
  "geometry": {"coordinates":[-82.86929000000001,40.15139],"type":"Point"}
}