{
  "type": "Feature",
  "properties": {
    "gn:admin1_code":"OH",
    "gn:admin2_code":"125.0",
    "gn:admin3_code":"37954.0",
    "gn:asciiname":"Molasses Gap",
    "gn:country_code":"US",
    "gn:dem":216,
    "gn:elevation":"218.0",
    "gn:feature_class":"P",
    "gn:feature_code":"PPL",
    "gn:name":"Molasses Gap",
    "gn:population":0,
    "gn:timezone":"America/New_York",
    "iso:country":"US",
    "wof:name":"Molasses Gap",
    "wof:placetype":"locality"
},
  "geometry": {"coordinates":[-84.47689,41.15033],"type":"Point"}
}