{
  "type": "Feature",
  "properties": {
    "gn:admin1_code":"TN",
    "gn:admin2_code":"71.0",
    "gn:asciiname":"Cerro Gordo",
    "gn:country_code":"US",
    "gn:dem":124,
    "gn:elevation":"124.0",
    "gn:feature_class":"P",
    "gn:feature_code":"PPL",
    "gn:name":"Cerro Gordo",
    "gn:population":0,
    "gn:timezone":"America/Chicago",
    "iso:country":"US",
    "name:eng_x_preferred":[
        "Cerro Gordo"
    ],
    "name:und_x_variant":[
        "Cerrogordo"
    ],
    "wof:name":"Cerro Gordo",
    "wof:placetype":"locality"
},
  "geometry": {"coordinates":[-88.18059000000002,35.30369],"type":"Point"}
}