{
  "type": "Feature",
  "properties": {
    "iso:country":"US",
    "name:ara_x_preferred":[
        "\u063a\u0627\u0628\u0629 \u0634\u064a\u0631\u0648\u0648\u062f"
    ],
    "name:aze_x_preferred":[
        "\u015eervud me\u015f\u0259si"
    ],
    "name:ben_x_preferred":[
        "\u09b6\u09c7\u09b0\u0989\u09a1 \u09ac\u09a8"
    ],
    "name:ceb_x_preferred":[
        "Sherwood Forest"
    ],
    "name:ces_x_preferred":[
        "Sherwoodsk\u00fd les"
    ],
    "name:cym_x_preferred":[
        "Fforest Sherwood"
    ],
    "name:dan_x_preferred":[
        "Sherwoodskoven"
    ],
    "name:deu_x_preferred":[
        "Sherwood Forest"
    ],
    "name:eng_x_preferred":[
        "Sherwood Forest"
    ],
    "name:epo_x_preferred":[
        "Arbaro Sherwood"
    ],
    "name:eus_x_preferred":[
        "Sherwood basoa"
    ],
    "name:fas_x_preferred":[
        "\u062c\u0646\u06af\u0644 \u0634\u0631\u0648\u0648\u062f"
    ],
    "name:fin_x_preferred":[
        "Sherwood"
    ],
    "name:heb_x_preferred":[
        "\u05d9\u05e2\u05e8 \u05e9\u05e8\u05d5\u05d5\u05d3"
    ],
    "name:hye_x_preferred":[
        "\u0547\u0565\u0580\u057e\u0578\u0582\u0564\u0575\u0561\u0576 \u0561\u0576\u057f\u0561\u057c"
    ],
    "name:isl_x_preferred":[
        "Sk\u00edrissk\u00f3gur"
    ],
    "name:jpn_x_preferred":[
        "\u30b7\u30e3\u30fc\u30a6\u30c3\u30c9\u306e\u68ee"
    ],
    "name:kor_x_preferred":[
        "\uc154\uc6b0\ub4dc\uc232"
    ],
    "name:lat_x_preferred":[
        "Limpidia Sylva"
    ],
    "name:nld_x_preferred":[
        "Sherwood Forest"
    ],
    "name:nob_x_preferred":[
        "Sherwoodskogen"
    ],
    "name:pol_x_preferred":[
        "Sherwood"
    ],
    "name:por_x_preferred":[
        "Sherwood"
    ],
    "name:ron_x_preferred":[
        "P\u0103durea Sherwood"
    ],
    "name:rus_x_preferred":[
        "\u0428\u0435\u0440\u0432\u0443\u0434\u0441\u043a\u0438\u0439 \u043b\u0435\u0441"
    ],
    "name:sqi_x_preferred":[
        "Pylli Sherud"
    ],
    "name:swe_x_preferred":[
        "Sherwoodskogen"
    ],
    "name:tur_x_preferred":[
        "Sherwood Orman\u0131"
    ],
    "name:ukr_x_preferred":[
        "\u0428\u0435\u0440\u0432\u0443\u0434\u0441\u044c\u043a\u0438\u0439 \u043b\u0456\u0441"
    ],
    "name:zho_x_preferred":[
        "\u96ea\u4f0d\u5fb7\u68ee\u6797"
    ],
    "wd:wordcount":1131,
    "wof:name":"Sherwood Forest",
    "wof:placetype":"neighbourhood",
    "wof:population":433,
    "zs:area_m":1060430.463113,
    "zs:blockids":[
        130570910013030,
        130570910013036,
        130570910013028,
        130570910013042,
        130570910013029,
        130570910013033
    ],
    "zs:housing10":168,
    "zs:label":"Sherwood Forest",
    "zs:pop10":433
},
  "geometry": {"coordinates":[-84.528881,34.108159],"type":"Point"}
}