{
  "type": "Feature",
  "properties": {
    "gn:admin1_code":"VA",
    "gn:admin2_code":"7",
    "gn:asciiname":"Gills",
    "gn:country_code":"US",
    "gn:dem":161,
    "gn:elevation":"159.0",
    "gn:feature_class":"P",
    "gn:feature_code":"PPL",
    "gn:name":"Gills",
    "gn:population":0,
    "gn:timezone":"America/New_York",
    "iso:country":"US",
    "name:eng_x_preferred":[
        "Gills"
    ],
    "name:und_x_variant":[
        "New London"
    ],
    "wof:name":"Gills",
    "wof:placetype":"locality"
},
  "geometry": {"coordinates":[-78.19861,37.29349000000001],"type":"Point"}
}