{
  "type": "Feature",
  "properties": {
    "gn:country":"US",
    "gn:fcode":"PPL",
    "gn:population":0,
    "iso:country":"US",
    "name:cat_x_preferred":[
        "Bourne"
    ],
    "name:ceb_x_preferred":[
        "Bourne"
    ],
    "name:deu_x_preferred":[
        "Bourne"
    ],
    "name:est_x_preferred":[
        "Bourne"
    ],
    "name:fas_x_preferred":[
        "\u0628\u0648\u0631\u0646"
    ],
    "name:fin_x_preferred":[
        "Bourne"
    ],
    "name:fra_x_preferred":[
        "Bourne"
    ],
    "name:ita_x_preferred":[
        "Bourne"
    ],
    "name:lit_x_preferred":[
        "Bornas"
    ],
    "name:nld_x_preferred":[
        "Bourne"
    ],
    "name:nor_x_preferred":[
        "Bourne"
    ],
    "name:pol_x_preferred":[
        "Bourne"
    ],
    "name:por_x_preferred":[
        "Bourne"
    ],
    "name:spa_x_preferred":[
        "Bourne"
    ],
    "name:swe_x_preferred":[
        "Bourne"
    ],
    "name:vol_x_preferred":[
        "Bourne"
    ],
    "qs_pg:aaroncc":"US",
    "qs_pg:gn_country":"US",
    "qs_pg:gn_fcode":"PPL",
    "qs_pg:gn_pop":0,
    "qs_pg:name":"Bourne",
    "qs_pg:name_adm0":"United States",
    "qs_pg:name_adm1":"Kentucky",
    "qs_pg:photos":87,
    "qs_pg:photos_1k":18,
    "qs_pg:photos_9k":1,
    "qs_pg:photos_9r":3,
    "qs_pg:photos_all":87,
    "qs_pg:photos_sr":3,
    "qs_pg:pop_sr":5,
    "qs_pg:qs_pg_placetype":"locality",
    "qs_pg:qs_pg_placetype_gp":"Town",
    "qs_pg:woe_adm0":23424977,
    "woe:adm0_id":23424977,
    "woe:name_adm0":"United States",
    "woe:name_adm1":"Kentucky",
    "woe:placetype":"Town",
    "wof:name":"Bourne",
    "wof:placetype":"locality"
},
  "geometry": {"coordinates":[-84.613,37.7098],"type":"Point"}
}