{
  "type": "Feature",
  "properties": {
    "iso:country":"US",
    "qs_pg:aaroncc":"US",
    "qs_pg:name":"East Cairo",
    "qs_pg:name_adm0":"United States",
    "qs_pg:name_adm1":"Kentucky",
    "qs_pg:photos":199,
    "qs_pg:photos_1k":40,
    "qs_pg:photos_9k":1,
    "qs_pg:photos_9r":4,
    "qs_pg:photos_all":199,
    "qs_pg:photos_sr":4,
    "qs_pg:pop_sr":0,
    "qs_pg:qs_pg_placetype":"locality",
    "qs_pg:qs_pg_placetype_gp":"Town",
    "qs_pg:woe_adm0":23424977,
    "woe:adm0_id":23424977,
    "woe:name_adm0":"United States",
    "woe:name_adm1":"Kentucky",
    "woe:placetype":"Town",
    "wof:name":"East Cairo",
    "wof:placetype":"locality"
},
  "geometry": {"coordinates":[-89.140834,36.987059],"type":"Point"}
}