{
  "type": "Feature",
  "properties": {
    "gn:admin1_code":"MI",
    "gn:admin2_code":"149.0",
    "gn:admin3_code":"59400.0",
    "gn:asciiname":"Wasepi",
    "gn:country_code":"US",
    "gn:dem":257,
    "gn:elevation":"257.0",
    "gn:feature_class":"P",
    "gn:feature_code":"PPL",
    "gn:name":"Wasepi",
    "gn:population":0,
    "gn:timezone":"America/Detroit",
    "iso:country":"US",
    "wof:name":"Wasepi",
    "wof:placetype":"locality"
},
  "geometry": {"coordinates":[-85.46165000000001,41.94088],"type":"Point"}
}