{
  "type": "Feature",
  "properties": {
    "iso:country":"US",
    "name:eng_x_preferred":[
        "Southwest Arcadia"
    ],
    "qs:gn_adm0_cc":"US",
    "qs:gn_fcode":"PPL",
    "qs:gn_local":5324477,
    "qs:gn_nam_loc":"Arcadia, Los Angeles, California, US",
    "qs:gn_namadm1":"CA",
    "qs:gn_name":"West Arcadia",
    "qs:local_max":14158,
    "qs:local_sum":18055,
    "qs:localhoods":9,
    "qs:name":"Southwest Arcadia",
    "qs:name_adm0":"United States",
    "qs:name_adm1":"California",
    "qs:name_adm2":"Los Angeles",
    "qs:name_local":"Arcadia",
    "qs:photo_max":25,
    "qs:photo_sum":36,
    "qs:placetype":"Suburb",
    "qs:quad_count":7,
    "qs:woe_adm0":23424977,
    "qs:woe_adm1":2347563,
    "qs:woe_adm2":12587688,
    "qs:woe_lau":0,
    "qs:woe_local":2355540,
    "qs:woe_ver":"7.10.0",
    "wof:lang":[
        "eng"
    ],
    "wof:name":"Southwest Arcadia",
    "wof:placetype":"neighbourhood",
    "wof:population":5811,
    "zs:blockids":[
        60374317002001,
        60374316002003,
        60374316003000,
        60374320004011,
        60374317005007,
        60374317001003,
        60374317002002,
        60374317004001,
        60374317004003,
        60374317003008,
        60374317003004,
        60374319001007,
        60374317002008,
        60374320004009,
        60374320004010,
        60374317002007,
        60374317002005,
        60374316002011,
        60374319001002,
        60374317003001,
        60374317002003,
        60374317002004,
        60374317004002,
        60374316003001,
        60374317003007,
        60374317003006,
        60374317002006,
        60374316002007,
        60374317003003,
        60374317003000,
        60374316002005,
        60374317003009,
        60374316002006,
        60374317003002,
        60374317001005,
        60374317001004,
        60374317001001,
        60374317003005,
        60374316002010,
        60374316002004,
        60374316002002,
        60374316002000,
        60374320003000,
        60374317002000,
        60374317001002,
        60374319001008,
        60374316002001,
        60374319001006
    ],
    "zs:housing10":1914,
    "zs:pop10":5811
},
  "geometry": {"coordinates":[-118.03291900000001,34.118147],"type":"Point"}
}