{
  "type": "Feature",
  "properties": {
    "gn:admin1_code":"AR",
    "gn:admin2_code":"57.0",
    "gn:admin3_code":"91077.0",
    "gn:asciiname":"Shover Springs",
    "gn:country_code":"US",
    "gn:dem":118,
    "gn:elevation":"110.0",
    "gn:feature_class":"P",
    "gn:feature_code":"PPL",
    "gn:name":"Shover Springs",
    "gn:population":0,
    "gn:timezone":"America/Chicago",
    "iso:country":"US",
    "name:eng_x_preferred":[
        "Shover Springs"
    ],
    "name:und_x_variant":[
        "Shovers Spring",
        "Shovers Springs"
    ],
    "wof:name":"Shover Springs",
    "wof:placetype":"locality"
},
  "geometry": {"coordinates":[-93.53045,33.6229],"type":"Point"}
}