{
  "type": "Feature",
  "properties": {
    "gn:admin1_code":"IN",
    "gn:admin2_code":"121.0",
    "gn:admin3_code":"23764.0",
    "gn:asciiname":"Lyford",
    "gn:country_code":"US",
    "gn:dem":170,
    "gn:elevation":"165.0",
    "gn:feature_class":"P",
    "gn:feature_code":"PPL",
    "gn:name":"Lyford",
    "gn:population":0,
    "gn:timezone":"America/Indiana/Indianapolis",
    "iso:country":"US",
    "name:eng_x_preferred":[
        "Lyford"
    ],
    "name:und_x_variant":[
        "Clinton Locks",
        "Williamson"
    ],
    "wof:name":"Lyford",
    "wof:placetype":"locality"
},
  "geometry": {"coordinates":[-87.37085,39.65004],"type":"Point"}
}