{
  "type": "Feature",
  "properties": {
    "gn:admin1_code":"IN",
    "gn:admin2_code":"37.0",
    "gn:admin3_code":"30456.0",
    "gn:asciiname":"Ellsworth",
    "gn:country_code":"US",
    "gn:dem":165,
    "gn:elevation":"163.0",
    "gn:feature_class":"P",
    "gn:feature_code":"PPL",
    "gn:name":"Ellsworth",
    "gn:population":0,
    "gn:timezone":"America/Indiana/Vincennes",
    "iso:country":"US",
    "name:fas_x_preferred":[
        "\u0627\u0644\u0633\u0648\u0631\u062b"
    ],
    "name:urd_x_preferred":[
        "\u0627\u06cc\u0644\u0633\u0648\u0631\u062a\u06be"
    ],
    "wof:name":"Ellsworth",
    "wof:placetype":"locality"
},
  "geometry": {"coordinates":[-86.71833000000002,38.42783],"type":"Point"}
}