{
  "type": "Feature",
  "properties": {
    "gn:admin1_code":"PA",
    "gn:admin2_code":"89.0",
    "gn:admin3_code":"61928.0",
    "gn:asciiname":"Pleasant View Lake",
    "gn:country_code":"US",
    "gn:dem":223,
    "gn:elevation":"220.0",
    "gn:feature_class":"P",
    "gn:feature_code":"PPL",
    "gn:name":"Pleasant View Lake",
    "gn:population":0,
    "gn:timezone":"America/New_York",
    "iso:country":"US",
    "wof:name":"Pleasant View Lake",
    "wof:placetype":"locality"
},
  "geometry": {"coordinates":[-75.45990999999999,40.91759],"type":"Point"}
}