{
  "type": "Feature",
  "properties": {
    "gn:admin1_code":"VA",
    "gn:admin2_code":"119",
    "gn:asciiname":"Cooks Corner",
    "gn:country_code":"US",
    "gn:dem":29,
    "gn:elevation":"28.0",
    "gn:feature_class":"P",
    "gn:feature_code":"PPL",
    "gn:name":"Cooks Corner",
    "gn:population":0,
    "gn:timezone":"America/New_York",
    "iso:country":"US",
    "wof:name":"Cooks Corner",
    "wof:placetype":"locality"
},
  "geometry": {"coordinates":[-76.56605999999999,37.60153],"type":"Point"}
}