{
  "type": "Feature",
  "properties": {
    "gn:admin1_code":"VA",
    "gn:admin2_code":"141.0",
    "gn:asciiname":"Ararat",
    "gn:country_code":"US",
    "gn:dem":447,
    "gn:elevation":"441.0",
    "gn:feature_class":"P",
    "gn:feature_code":"PPL",
    "gn:name":"Ararat",
    "gn:population":0,
    "gn:timezone":"America/New_York",
    "iso:country":"US",
    "name:ben_x_preferred":[
        "\u0986\u09b0\u09be\u09b0\u09be\u09a4"
    ],
    "name:ell_x_preferred":[
        "\u0391\u03c1\u03b1\u03c1\u03ac\u03c4"
    ],
    "name:fas_x_preferred":[
        "\u0622\u0631\u0627\u0631\u0627\u062a"
    ],
    "name:heb_x_preferred":[
        "\u05d0\u05e8\u05e8\u05d8"
    ],
    "name:hin_x_preferred":[
        "\u0905\u0930\u093e\u0930\u093e\u0924"
    ],
    "name:hun_x_preferred":[
        "Ararat"
    ],
    "name:ind_x_preferred":[
        "Ararat"
    ],
    "name:kor_x_preferred":[
        "\uc544\ub77c\ub78f"
    ],
    "name:tur_x_preferred":[
        "Ararat"
    ],
    "wof:name":"Ararat",
    "wof:placetype":"locality"
},
  "geometry": {"coordinates":[-80.51062,36.59902],"type":"Point"}
}