{
  "type": "Feature",
  "properties": {
    "gn:admin1_code":"VA",
    "gn:admin2_code":"141.0",
    "gn:asciiname":"Ararat",
    "gn:country_code":"US",
    "gn:dem":447,
    "gn:elevation":"441.0",
    "gn:feature_class":"P",
    "gn:feature_code":"PPL",
    "gn:name":"Ararat",
    "gn:population":0,
    "gn:timezone":"America/New_York",
    "iso:country":"US",
    "name:fas_x_preferred":[
        "\u0622\u0631\u0627\u0631\u0627\u062a"
    ],
    "wof:name":"Ararat",
    "wof:placetype":"locality"
},
  "geometry": {"coordinates":[-80.51061999999997,36.59902],"type":"Point"}
}