{
  "type": "Feature",
  "properties": {
    "gn:admin1_code":"IL",
    "gn:admin2_code":"125.0",
    "gn:admin3_code":"4169.0",
    "gn:asciiname":"Matanzas",
    "gn:country_code":"US",
    "gn:dem":145,
    "gn:elevation":"141.0",
    "gn:feature_class":"P",
    "gn:feature_code":"PPL",
    "gn:name":"Matanzas",
    "gn:population":0,
    "gn:timezone":"America/Chicago",
    "iso:country":"US",
    "name:ara_x_preferred":[
        "\u0645\u0627\u062a\u0627\u0646\u0632\u0627\u0633"
    ],
    "name:ast_x_preferred":[
        "Matanzas"
    ],
    "name:bel_x_preferred":[
        "\u041c\u0430\u0442\u0430\u043d\u0441\u0430\u0441"
    ],
    "name:bre_x_preferred":[
        "Matanzas"
    ],
    "name:cat_x_preferred":[
        "Matanzas"
    ],
    "name:ceb_x_preferred":[
        "Matanzas"
    ],
    "name:ces_x_preferred":[
        "Matanzas"
    ],
    "name:dan_x_preferred":[
        "Matanzas"
    ],
    "name:deu_x_preferred":[
        "Matanzas"
    ],
    "name:epo_x_preferred":[
        "Matanzas"
    ],
    "name:eus_x_preferred":[
        "Matanzas"
    ],
    "name:fas_x_preferred":[
        "\u0645\u0627\u062a\u0627\u0646\u0632\u0627\u0633"
    ],
    "name:fin_x_preferred":[
        "Matanzas"
    ],
    "name:fra_x_preferred":[
        "Matanzas"
    ],
    "name:fry_x_preferred":[
        "Matanzas"
    ],
    "name:hat_x_preferred":[
        "Matanzas"
    ],
    "name:hun_x_preferred":[
        "Matanzas"
    ],
    "name:ita_x_preferred":[
        "Matanzas"
    ],
    "name:jpn_x_preferred":[
        "\u30de\u30bf\u30f3\u30b5\u30b9"
    ],
    "name:kat_x_preferred":[
        "\u10db\u10d0\u10e2\u10d0\u10dc\u10e1\u10d0\u10e1\u10d8"
    ],
    "name:kor_x_preferred":[
        "\ub9c8\ud0c4\uc0ac\uc2a4"
    ],
    "name:lit_x_preferred":[
        "Matansasas"
    ],
    "name:myv_x_preferred":[
        "\u041c\u0430\u0442\u0430\u043d\u0441\u0430\u0441"
    ],
    "name:nld_x_preferred":[
        "Matanzas"
    ],
    "name:nor_x_preferred":[
        "Matanzas"
    ],
    "name:pol_x_preferred":[
        "Matanzas"
    ],
    "name:por_x_preferred":[
        "Matanzas"
    ],
    "name:ron_x_preferred":[
        "Matanzas"
    ],
    "name:rus_x_preferred":[
        "\u041c\u0430\u0442\u0430\u043d\u0441\u0430\u0441"
    ],
    "name:sco_x_preferred":[
        "Matanzas"
    ],
    "name:spa_x_preferred":[
        "Matanzas"
    ],
    "name:srp_x_preferred":[
        "\u041c\u0430\u0442\u0430\u043d\u0437\u0430\u0441"
    ],
    "name:szl_x_preferred":[
        "Matanzas"
    ],
    "name:tur_x_preferred":[
        "Matanzas"
    ],
    "name:ukr_x_preferred":[
        "\u041c\u0430\u0442\u0430\u043d\u0441\u0430\u0441"
    ],
    "name:urd_x_preferred":[
        "\u0645\u0627\u062a\u0627\u0646\u0633\u0627\u0633"
    ],
    "name:uzb_x_preferred":[
        "Matansas"
    ],
    "name:vie_x_preferred":[
        "Matanzas"
    ],
    "name:vol_x_preferred":[
        "Matanzas"
    ],
    "name:war_x_preferred":[
        "Matanzas"
    ],
    "name:zho_x_preferred":[
        "\u99ac\u5766\u85a9\u65af"
    ],
    "wof:name":"Matanzas",
    "wof:placetype":"locality"
},
  "geometry": {"coordinates":[-90.09956,40.23116],"type":"Point"}
}