{
  "type": "Feature",
  "properties": {
    "gn:admin1_code":"OK",
    "gn:admin2_code":"81",
    "gn:asciiname":"Emsey",
    "gn:country_code":"US",
    "gn:dem":310,
    "gn:elevation":"306.0",
    "gn:feature_class":"P",
    "gn:feature_code":"PPL",
    "gn:name":"Emsey",
    "gn:population":0,
    "gn:timezone":"America/Chicago",
    "iso:country":"US",
    "wof:name":"Emsey",
    "wof:placetype":"locality"
},
  "geometry": {"coordinates":[-97.02446999999999,35.76756],"type":"Point"}
}