{
  "type": "Feature",
  "properties": {
    "gn:admin1_code":"AL",
    "gn:admin2_code":"45",
    "gn:asciiname":"Kelly",
    "gn:country_code":"US",
    "gn:dem":58,
    "gn:elevation":"50.0",
    "gn:feature_class":"P",
    "gn:feature_code":"PPL",
    "gn:name":"Kelly",
    "gn:population":0,
    "gn:timezone":"America/Chicago",
    "iso:country":"US",
    "name:eng_x_preferred":[
        "Kelly"
    ],
    "name:fas_x_preferred":[
        "\u062f\u0627\u06af\u0644\u0627\u0633 \u06a9\u0644\u06cc"
    ],
    "name:und_x_variant":[
        "Douglas",
        "Douglas Kelly Station"
    ],
    "name:zho_x_preferred":[
        "\u51f1\u5229"
    ],
    "wof:name":"Kelly",
    "wof:placetype":"locality"
},
  "geometry": {"coordinates":[-85.65521,31.32378],"type":"Point"}
}