{
  "type": "Feature",
  "properties": {
    "gn:admin1_code":"UT",
    "gn:admin2_code":"35.0",
    "gn:asciiname":"Whitaker Estates",
    "gn:country_code":"US",
    "gn:dem":1330,
    "gn:elevation":"1325.0",
    "gn:feature_class":"P",
    "gn:feature_code":"PPL",
    "gn:name":"Whitaker Estates",
    "gn:population":0,
    "gn:timezone":"America/Denver",
    "iso:country":"US",
    "wof:name":"Whitaker Estates",
    "wof:placetype":"locality"
},
  "geometry": {"coordinates":[-111.95049,40.65995],"type":"Point"}
}