{
  "type": "Feature",
  "properties": {
    "iso:country":"US",
    "name:deu_x_preferred":[
        "Stonebridge"
    ],
    "name:eng_x_preferred":[
        "Stonebridge"
    ],
    "name:hin_x_preferred":[
        "\u0938\u094d\u091f\u094b\u0928\u092c\u094d\u0930\u093f\u091c"
    ],
    "name:pol_x_preferred":[
        "Stonebridge"
    ],
    "wd:wordcount":305,
    "wof:name":"Stonebridge",
    "wof:placetype":"neighbourhood",
    "wof:population":921,
    "zs:area_m":2811127.407186,
    "zs:blockids":[
        371830538072015,
        371830538072012,
        371830538072009,
        371830538072008,
        371830538072013,
        371830538072021,
        371830538072007,
        371830538072014,
        371830538072017,
        371830538072010,
        371830538072016
    ],
    "zs:housing10":346,
    "zs:label":"Stonebridge",
    "zs:pop10":921
},
  "geometry": {"coordinates":[-78.675715,35.920448],"type":"Point"}
}