{
  "type": "Feature",
  "properties": {
    "iso:country":"US",
    "name:deu_x_preferred":[
        "Crown Royal"
    ],
    "name:eng_x_preferred":[
        "Crown Royal"
    ],
    "name:fas_x_preferred":[
        "\u06a9\u0631\u0627\u0648\u0646 \u0631\u0648\u06cc\u0627\u0644"
    ],
    "name:fra_x_preferred":[
        "Crown Royal"
    ],
    "name:ita_x_preferred":[
        "Crown Royal"
    ],
    "name:jpn_x_preferred":[
        "\u30af\u30e9\u30a6\u30f3\u30fb\u30ed\u30fc\u30e4\u30eb"
    ],
    "name:nld_x_preferred":[
        "Crown Royal"
    ],
    "name:por_x_preferred":[
        "Crown Royal"
    ],
    "name:spa_x_preferred":[
        "Crown Royal"
    ],
    "name:spa_x_variant":[
        "Crown  Royal"
    ],
    "name:zho_x_preferred":[
        "Crown Royal"
    ],
    "qs:gn_local":0,
    "qs:local_max":2284,
    "qs:local_sum":12322,
    "qs:localhoods":20,
    "qs:name":"Crown Royal",
    "qs:name_adm0":"United States",
    "qs:name_adm1":"California",
    "qs:name_adm2":"Orange",
    "qs:name_local":"Laguna Beach",
    "qs:photo_max":12,
    "qs:photo_sum":34,
    "qs:placetype":"Suburb",
    "qs:quad_count":6,
    "qs:woe_adm0":23424977,
    "qs:woe_adm1":2347563,
    "qs:woe_adm2":12587699,
    "qs:woe_lau":0,
    "qs:woe_local":2434641,
    "qs:woe_ver":"7.10.0",
    "wd:wordcount":1139,
    "wof:lang":[
        "eng"
    ],
    "wof:name":"Crown Royal",
    "wof:placetype":"neighbourhood",
    "zs:blockids":[
        60590423251010,
        60590626324032,
        60590626324033,
        60590626324011
    ],
    "zs:housing10":0,
    "zs:pop10":0
},
  "geometry": {"coordinates":[-117.746887,33.51252],"type":"Point"}
}