{
  "type": "Feature",
  "properties": {
    "gn:admin1_code":"SC",
    "gn:admin2_code":"65.0",
    "gn:asciiname":"Little River Subdivision",
    "gn:country_code":"US",
    "gn:dem":117,
    "gn:elevation":"111.0",
    "gn:feature_class":"P",
    "gn:feature_code":"PPL",
    "gn:name":"Little River Subdivision",
    "gn:population":0,
    "gn:timezone":"America/New_York",
    "iso:country":"US",
    "wof:name":"Little River Subdivision",
    "wof:placetype":"locality"
},
  "geometry": {"coordinates":[-82.36707,33.85013],"type":"Point"}
}