{
  "type": "Feature",
  "properties": {
    "gn:admin1_code":"MN",
    "gn:admin2_code":"21.0",
    "gn:admin3_code":"46825.0",
    "gn:asciiname":"Ryan Village",
    "gn:country_code":"US",
    "gn:dem":408,
    "gn:elevation":"402.0",
    "gn:feature_class":"P",
    "gn:feature_code":"PPL",
    "gn:name":"Ryan Village",
    "gn:population":0,
    "gn:timezone":"America/Chicago",
    "iso:country":"US",
    "wof:name":"Ryan Village",
    "wof:placetype":"locality"
},
  "geometry": {"coordinates":[-94.28913,47.35884],"type":"Point"}
}