{
  "type": "Feature",
  "properties": {
    "gn:admin1_code":"IA",
    "gn:admin2_code":"105.0",
    "gn:admin3_code":"94611.0",
    "gn:asciiname":"Langworthy",
    "gn:country_code":"US",
    "gn:dem":265,
    "gn:elevation":"262.0",
    "gn:feature_class":"P",
    "gn:feature_code":"PPL",
    "gn:name":"Langworthy",
    "gn:population":0,
    "gn:timezone":"America/Chicago",
    "iso:country":"US",
    "name:fas_x_preferred":[
        "\u0644\u0646\u06af\u0648\u0631\u062a\u06cc"
    ],
    "name:urd_x_preferred":[
        "\u0644\u0627\u0646\u06af\u0648\u0648\u0631\u0679\u06c1\u06cc"
    ],
    "wof:name":"Langworthy",
    "wof:placetype":"locality"
},
  "geometry": {"coordinates":[-91.22404,42.19111],"type":"Point"}
}