{
  "type": "Feature",
  "properties": {
    "gn:admin1_code":"IL",
    "gn:admin2_code":"167",
    "gn:admin3_code":"52181.0",
    "gn:asciiname":"Bates",
    "gn:country_code":"US",
    "gn:dem":195,
    "gn:elevation":"195.0",
    "gn:feature_class":"P",
    "gn:feature_code":"PPL",
    "gn:name":"Bates",
    "gn:population":0,
    "gn:timezone":"America/Chicago",
    "iso:country":"US",
    "name:fas_x_preferred":[
        "\u0628\u06cc\u062a\u0633"
    ],
    "wof:name":"Bates",
    "wof:placetype":"locality"
},
  "geometry": {"coordinates":[-89.84954999999999,39.72422],"type":"Point"}
}