{
  "type": "Feature",
  "properties": {
    "gn:admin1_code":"WA",
    "gn:admin2_code":"75.0",
    "gn:asciiname":"Juno",
    "gn:country_code":"US",
    "gn:dem":598,
    "gn:elevation":"602.0",
    "gn:feature_class":"P",
    "gn:feature_code":"PPL",
    "gn:name":"Juno",
    "gn:population":0,
    "gn:timezone":"America/Los_Angeles",
    "iso:country":"US",
    "name:als_x_preferred":[
        "Juno"
    ],
    "name:ara_x_preferred":[
        "\u062c\u0648\u0646\u0648"
    ],
    "name:bel_x_preferred":[
        "\u042e\u043d\u043e\u043d\u0430"
    ],
    "name:bre_x_preferred":[
        "Juno"
    ],
    "name:cat_x_preferred":[
        "Juno"
    ],
    "name:ceb_x_preferred":[
        "Juno"
    ],
    "name:ces_x_preferred":[
        "Juno"
    ],
    "name:cym_x_preferred":[
        "Juno"
    ],
    "name:dan_x_preferred":[
        "Juno"
    ],
    "name:deu_x_preferred":[
        "Juno"
    ],
    "name:eng_x_preferred":[
        "Juno"
    ],
    "name:epo_x_preferred":[
        "Juno"
    ],
    "name:est_x_preferred":[
        "Juno"
    ],
    "name:eus_x_preferred":[
        "Juno"
    ],
    "name:fas_x_preferred":[
        "\u062c\u0648\u0646\u0648"
    ],
    "name:fin_x_preferred":[
        "Juno"
    ],
    "name:fra_x_preferred":[
        "Juno"
    ],
    "name:hrv_x_preferred":[
        "Juno"
    ],
    "name:hun_x_preferred":[
        "Juno"
    ],
    "name:ita_x_preferred":[
        "Juno"
    ],
    "name:jpn_x_preferred":[
        "\u30b8\u30e5\u30ce"
    ],
    "name:lav_x_preferred":[
        "Juno"
    ],
    "name:lmo_x_preferred":[
        "Juno"
    ],
    "name:ltz_x_preferred":[
        "Juno"
    ],
    "name:mar_x_preferred":[
        "\u091c\u0941\u0928\u094b"
    ],
    "name:nds_x_preferred":[
        "Juno"
    ],
    "name:nld_x_preferred":[
        "Juno"
    ],
    "name:nor_x_preferred":[
        "Juno"
    ],
    "name:pol_x_preferred":[
        "Juno"
    ],
    "name:por_x_preferred":[
        "Juno"
    ],
    "name:ron_x_preferred":[
        "Juno"
    ],
    "name:rus_x_preferred":[
        "\u042e\u043d\u043e\u043d\u0430"
    ],
    "name:slk_x_preferred":[
        "Juno"
    ],
    "name:slv_x_preferred":[
        "Juno"
    ],
    "name:spa_x_preferred":[
        "Juno"
    ],
    "name:swe_x_preferred":[
        "Juno"
    ],
    "name:tur_x_preferred":[
        "Juno"
    ],
    "name:ukr_x_preferred":[
        "\u042e\u043d\u043e\u043d\u0430"
    ],
    "name:und_x_variant":[
        "Juno Station"
    ],
    "wof:name":"Juno",
    "wof:placetype":"locality"
},
  "geometry": {"coordinates":[-117.57492000000001,47.11489],"type":"Point"}
}