{
  "type": "Feature",
  "properties": {
    "iso:country":"US",
    "name:eng_x_preferred":[
        "Beechcroft"
    ],
    "wof:name":"Beechcroft",
    "wof:placetype":"neighbourhood",
    "zs:area_m":48476.877174,
    "zs:blockids":[
        370810126071000
    ],
    "zs:housing10":0,
    "zs:label":"Beechcroft",
    "zs:pop10":0
},
  "geometry": {"coordinates":[-79.879801,36.052205],"type":"Point"}
}