{
  "type": "Feature",
  "properties": {
    "iso:country":"US",
    "name:eng_x_preferred":[
        "Palm Lake Club"
    ],
    "wof:name":"Palm Lake Club",
    "wof:placetype":"neighbourhood",
    "wof:population":227,
    "zs:area_m":627016.29907,
    "zs:blockids":[
        120610508052051,
        120610508052062,
        120610508053016,
        120610508053017,
        120610508052003,
        120610508052047,
        120610508052046,
        120610508052061,
        120610508052050,
        120610508052048,
        120610508051013,
        120610508053023,
        120610508051005,
        120610508052052,
        120610508052021,
        120610508051010,
        120610508051007,
        120610508052022,
        120610508053018,
        120610508051012,
        120610508052049,
        120610508052053,
        120610508052005,
        120610508051006,
        120610508052020
    ],
    "zs:housing10":159,
    "zs:label":"Palm Lake Club",
    "zs:pop10":227
},
  "geometry": {"coordinates":[-80.450838,27.77247],"type":"Point"}
}