{
  "type": "Feature",
  "properties": {
    "iso:country":"US",
    "name:eng_x_preferred":[
        "Meadowlark Hill"
    ],
    "wof:name":"Meadowlark Hill",
    "wof:placetype":"neighbourhood",
    "wof:population":457,
    "zs:area_m":139380.218823,
    "zs:blockids":[
        191030104004044,
        191030104004108,
        191030104004036,
        191030104004042,
        191030104004040,
        191030104004037,
        191030104004107,
        191030104004038,
        191030104004045
    ],
    "zs:housing10":195,
    "zs:label":"Meadowlark Hill",
    "zs:pop10":457
},
  "geometry": {"coordinates":[-91.553471,41.627948],"type":"Point"}
}