{
  "type": "Feature",
  "properties": {
    "iso:country":"US",
    "name:eng_x_preferred":[
        "Rolling Wood Heights"
    ],
    "qs:gn_adm0_cc":"US",
    "qs:gn_local":5397664,
    "qs:gn_nam_loc":"South Lake Tahoe, El Dorado, California, US",
    "qs:gn_namadm1":"CA",
    "qs:local_max":3801,
    "qs:local_sum":15128,
    "qs:localhoods":37,
    "qs:name":"Rolling Wood Heights",
    "qs:name_adm0":"United States",
    "qs:name_adm1":"California",
    "qs:name_adm2":"El Dorado",
    "qs:name_local":"South Lake Tahoe",
    "qs:photo_max":63,
    "qs:photo_sum":181,
    "qs:placetype":"Suburb",
    "qs:quad_count":22,
    "qs:woe_adm0":23424977,
    "qs:woe_adm1":2347563,
    "qs:woe_adm2":12587678,
    "qs:woe_lau":0,
    "qs:woe_local":2496420,
    "qs:woe_ver":"7.10.0",
    "wof:lang":[
        "eng"
    ],
    "wof:name":"Rolling Wood Heights",
    "wof:placetype":"neighbourhood",
    "wof:population":1248,
    "zs:blockids":[
        60170305043001,
        60170304025009,
        60170305043017,
        60170305053048,
        60170305043007,
        60170305052031,
        60170305043019,
        60170305043027,
        60170305041015,
        60170305043030,
        60170305043016,
        60170305043013,
        60170305053049,
        60170305043024,
        60170305043026,
        60170305043028,
        60170305043018,
        60170305043014,
        60170305052006,
        60170304025010,
        60170305052028,
        60170304022021,
        60170305043002,
        60170305043029,
        60170305043031,
        60170305043035,
        60170305043012,
        60170305041029,
        60170304022028,
        60170305041030,
        60170305043021,
        60170305043032,
        60170305043022,
        60170305043009,
        60170305052027,
        60170305043025,
        60170305041020,
        60170305043033,
        60170305043015,
        60170304022031,
        60170305052026,
        60170305052005,
        60170305043006,
        60170304022029,
        60170305043003,
        60170305052025,
        60170305052002,
        60170305043020,
        60170305043023,
        60170305043034,
        60170305043008,
        60170305043010,
        60170305053005,
        60170305052024
    ],
    "zs:housing10":947,
    "zs:pop10":1248
},
  "geometry": {"coordinates":[-119.994561,38.887035],"type":"Point"}
}