{
  "type": "Feature",
  "properties": {
    "gn:elevation":5,
    "iso:country":"US",
    "name:eng_x_preferred":[
        "Germantown"
    ],
    "name:nld_x_preferred":[
        "Germantown"
    ],
    "name:und_x_variant":[
        "German Town"
    ],
    "qs:gn_adm0_cc":"US",
    "qs:gn_fcode":"PPL",
    "qs:gn_local":4948247,
    "qs:gn_nam_loc":"Quincy, Norfolk, Massachusetts, US",
    "qs:gn_namadm1":"MA",
    "qs:gn_name":"Germantown",
    "qs:local_max":2957,
    "qs:local_sum":12862,
    "qs:localhoods":16,
    "qs:name":"Germantown",
    "qs:name_adm0":"United States",
    "qs:name_adm1":"Massachusetts",
    "qs:name_adm2":"Norfolk",
    "qs:name_local":"Quincy",
    "qs:photo_max":808,
    "qs:photo_sum":1016,
    "qs:placetype":"Suburb",
    "qs:quad_count":25,
    "qs:woe_adm0":23424977,
    "qs:woe_adm1":2347580,
    "qs:woe_adm2":12588710,
    "qs:woe_lau":0,
    "qs:woe_local":2477869,
    "qs:woe_ver":"7.10.0",
    "wd:wordcount":386,
    "wof:lang":[
        "eng"
    ],
    "wof:name":"Germantown",
    "wof:placetype":"neighbourhood",
    "wof:population":3962,
    "zs:blockids":[
        250214228002006,
        250214228001003,
        250214178021031,
        250214178022008,
        250214178021021,
        250214178021029,
        250214178022012,
        250214178022014,
        250214178022009,
        250214178021017,
        250214178022022,
        250214178021015,
        250214178021019,
        250214179015000,
        250214178013024,
        250214178021016,
        250214178021012,
        250214178021018,
        250214178021014,
        250214228004000,
        250214178022020,
        250214179011002,
        250214178021004,
        250214178021010,
        250214178022010,
        250214178022004,
        250214178021013,
        250214228003000,
        250214178015036,
        250214179011013,
        250214178021001,
        250214178021028,
        250214178021032,
        250214178022017,
        250214178022005,
        250214178021026,
        250214178021011,
        250214178021006,
        250214179011003,
        250214178013025,
        250214178022011,
        250214178021027,
        250214178021009,
        250214178021030,
        250214178022003,
        250214228004010,
        250214178022001,
        250214178022000,
        250214178021023,
        250214178022013,
        250214178021025,
        250214178021008,
        250214178021020,
        250214178022018,
        250214178022021,
        250214178022019,
        250214178021024,
        250214178021007,
        250214178015034,
        250214178013026,
        250214178022015,
        250214178021022,
        250214178022016,
        250214179011001,
        250214178022002,
        250214179011000
    ],
    "zs:housing10":1786,
    "zs:pop10":3962
},
  "geometry": {"coordinates":[-70.968436,42.245275],"type":"Point"}
}