{
  "type": "Feature",
  "properties": {
    "gn:admin1_code":"OK",
    "gn:admin2_code":"19.0",
    "gn:asciiname":"Woodford",
    "gn:country_code":"US",
    "gn:dem":285,
    "gn:elevation":"284.0",
    "gn:feature_class":"P",
    "gn:feature_code":"PPL",
    "gn:name":"Woodford",
    "gn:population":0,
    "gn:timezone":"America/Chicago",
    "iso:country":"US",
    "wof:name":"Woodford",
    "wof:placetype":"locality"
},
  "geometry": {"coordinates":[-97.28446,34.3387],"type":"Point"}
}