{
  "type": "Feature",
  "properties": {
    "gn:admin1_code":"ID",
    "gn:admin2_code":"79.0",
    "gn:asciiname":"Herrick",
    "gn:country_code":"US",
    "gn:dem":685,
    "gn:elevation":"686.0",
    "gn:feature_class":"P",
    "gn:feature_code":"PPL",
    "gn:name":"Herrick",
    "gn:population":0,
    "gn:timezone":"America/Los_Angeles",
    "iso:country":"US",
    "name:ceb_x_preferred":[
        "Herrick"
    ],
    "name:deu_x_preferred":[
        "Herrick"
    ],
    "name:fra_x_preferred":[
        "Herrick"
    ],
    "name:ita_x_preferred":[
        "Herrick"
    ],
    "name:jpn_x_preferred":[
        "\u30d8\u30ea\u30c3\u30af"
    ],
    "name:nld_x_preferred":[
        "Herrick"
    ],
    "name:pol_x_preferred":[
        "Herrick"
    ],
    "name:por_x_preferred":[
        "Herrick"
    ],
    "name:rus_x_preferred":[
        "\u0425\u0435\u0440\u0440\u0438\u043a"
    ],
    "name:srp_x_preferred":[
        "\u0425\u0435\u0440\u0438\u043a"
    ],
    "name:swe_x_preferred":[
        "Herrick"
    ],
    "name:ukr_x_preferred":[
        "\u0413\u0435\u0440\u0440\u0456\u043a"
    ],
    "name:vol_x_preferred":[
        "Herrick"
    ],
    "wof:name":"Herrick",
    "wof:placetype":"locality"
},
  "geometry": {"coordinates":[-116.10655,47.2727],"type":"Point"}
}