{
  "type": "Feature",
  "properties": {
    "gn:admin1_code":"MD",
    "gn:admin2_code":"17.0",
    "gn:asciiname":"Melody Acres",
    "gn:country_code":"US",
    "gn:dem":41,
    "gn:elevation":"41.0",
    "gn:feature_class":"P",
    "gn:feature_code":"PPL",
    "gn:name":"Melody Acres",
    "gn:population":0,
    "gn:timezone":"America/New_York",
    "iso:country":"US",
    "wof:name":"Melody Acres",
    "wof:placetype":"locality"
},
  "geometry": {"coordinates":[-77.09137,38.48346],"type":"Point"}
}