{
  "type": "Feature",
  "properties": {
    "iso:country":"US",
    "name:eng_x_preferred":[
        "Picketville"
    ],
    "wof:name":"Picketville",
    "wof:placetype":"neighbourhood",
    "wof:population":56,
    "zs:area_m":1488409.155825,
    "zs:blockids":[
        120310106003000,
        120310106003008,
        120310105004009,
        120310106003006
    ],
    "zs:housing10":32,
    "zs:label":"Picketville",
    "zs:pop10":56
},
  "geometry": {"coordinates":[-81.75632400000001,30.408856],"type":"Point"}
}