{
  "type": "Feature",
  "properties": {
    "gn:elevation":20,
    "iso:country":"US",
    "name:eng_x_preferred":[
        "Rooty Plain"
    ],
    "name:eng_x_variant":[
        "Rooty Pln"
    ],
    "qs:gn_fcode":"PPL",
    "qs:gn_local":0,
    "qs:gn_namadm1":"MA",
    "qs:gn_name":"Rooty Plain",
    "qs:local_max":60,
    "qs:local_sum":136,
    "qs:localhoods":5,
    "qs:name":"Rooty Plain",
    "qs:name_adm0":"United States",
    "qs:name_adm1":"Massachusetts",
    "qs:name_adm2":"Essex",
    "qs:name_local":"Rowley",
    "qs:photo_max":44,
    "qs:photo_sum":60,
    "qs:placetype":"Suburb",
    "qs:quad_count":7,
    "qs:woe_adm0":23424977,
    "qs:woe_adm1":2347580,
    "qs:woe_adm2":12588704,
    "qs:woe_lau":0,
    "qs:woe_local":2485332,
    "qs:woe_ver":"7.10.0",
    "wof:lang":[
        "eng"
    ],
    "wof:name":"Rooty Plain",
    "wof:placetype":"neighbourhood"
},
  "geometry": {"coordinates":[-70.953186,42.705448],"type":"Point"}
}