{
  "type": "Feature",
  "properties": {
    "gn:admin1_code":"IL",
    "gn:admin2_code":"143.0",
    "gn:admin3_code":"65715.0",
    "gn:asciiname":"Olin",
    "gn:country_code":"US",
    "gn:dem":157,
    "gn:elevation":"158.0",
    "gn:feature_class":"P",
    "gn:feature_code":"PPL",
    "gn:name":"Olin",
    "gn:population":0,
    "gn:timezone":"America/Chicago",
    "iso:country":"US",
    "name:ceb_x_preferred":[
        "Olin"
    ],
    "name:deu_x_preferred":[
        "Olin"
    ],
    "name:fra_x_preferred":[
        "Olin"
    ],
    "name:ita_x_preferred":[
        "Olin"
    ],
    "name:jpn_x_preferred":[
        "\u30aa\u30ea\u30f3"
    ],
    "name:pol_x_preferred":[
        "Olin"
    ],
    "name:rus_x_preferred":[
        "\u041e\u043b\u0438\u043d"
    ],
    "wof:name":"Olin",
    "wof:placetype":"locality"
},
  "geometry": {"coordinates":[-89.76844,40.75281],"type":"Point"}
}