{
  "type": "Feature",
  "properties": {
    "gn:country":"US",
    "gn:fcode":"PPL",
    "gn:population":0,
    "iso:country":"US",
    "name:bre_x_preferred":[
        "Ramona"
    ],
    "name:fra_x_preferred":[
        "Ramona"
    ],
    "name:ita_x_preferred":[
        "Ramona"
    ],
    "name:nld_x_preferred":[
        "Ramona"
    ],
    "name:pan_x_preferred":[
        "\u0a30\u0a3e\u0a2e\u0a4b\u0a28\u0a3e"
    ],
    "name:pnb_x_preferred":[
        "\u0631\u0645\u0648\u0646\u0627"
    ],
    "name:spa_x_preferred":[
        "Ramona"
    ],
    "name:swe_x_preferred":[
        "Ramona"
    ],
    "qs_pg:aaroncc":"US",
    "qs_pg:gn_country":"US",
    "qs_pg:gn_fcode":"PPL",
    "qs_pg:gn_pop":0,
    "qs_pg:name":"Ramona",
    "qs_pg:name_adm0":"United States",
    "qs_pg:name_adm1":"Michigan",
    "qs_pg:photos":13,
    "qs_pg:photos_1k":3,
    "qs_pg:photos_9k":1,
    "qs_pg:photos_9r":1,
    "qs_pg:photos_all":13,
    "qs_pg:photos_sr":1,
    "qs_pg:pop_sr":0,
    "qs_pg:qs_pg_placetype":"locality",
    "qs_pg:qs_pg_placetype_gp":"Town",
    "qs_pg:woe_adm0":23424977,
    "woe:adm0_id":23424977,
    "woe:name_adm0":"United States",
    "woe:name_adm1":"Michigan",
    "woe:placetype":"Town",
    "wof:name":"Ramona",
    "wof:placetype":"locality"
},
  "geometry": {"coordinates":[-85.80200000000001,43.60418],"type":"Point"}
}