{
  "type": "Feature",
  "properties": {
    "gn:country":"US",
    "gn:fcode":"PPL",
    "gn:population":0,
    "iso:country":"US",
    "name:ceb_x_preferred":[
        "Capitan"
    ],
    "name:deu_x_preferred":[
        "Capitan"
    ],
    "name:fas_x_preferred":[
        "\u06a9\u0627\u067e\u06cc\u062a\u0627\u0646"
    ],
    "name:fra_x_preferred":[
        "Capitan"
    ],
    "name:nld_x_preferred":[
        "Capitan"
    ],
    "name:spa_x_preferred":[
        "Capit\u00e1n"
    ],
    "name:swe_x_preferred":[
        "Capitan"
    ],
    "qs_pg:aaroncc":"US",
    "qs_pg:gn_country":"US",
    "qs_pg:gn_fcode":"PPL",
    "qs_pg:gn_pop":0,
    "qs_pg:name":"Capitan",
    "qs_pg:name_adm0":"United States",
    "qs_pg:name_adm1":"California",
    "qs_pg:photos":2622,
    "qs_pg:photos_1k":531,
    "qs_pg:photos_9k":12,
    "qs_pg:photos_9r":10,
    "qs_pg:photos_all":2622,
    "qs_pg:photos_sr":18,
    "qs_pg:pop_sr":0,
    "qs_pg:qs_pg_placetype":"locality",
    "qs_pg:qs_pg_placetype_gp":"Town",
    "qs_pg:woe_adm0":23424977,
    "woe:adm0_id":23424977,
    "woe:name_adm0":"United States",
    "woe:name_adm1":"California",
    "woe:placetype":"Town",
    "wof:name":"Capitan",
    "wof:placetype":"locality"
},
  "geometry": {"coordinates":[-120.0432,34.46332],"type":"Point"}
}