{
  "type": "Feature",
  "properties": {
    "gn:admin1_code":"GA",
    "gn:admin2_code":"67.0",
    "gn:asciiname":"Laurel Hills",
    "gn:country_code":"US",
    "gn:dem":292,
    "gn:elevation":"285.0",
    "gn:feature_class":"P",
    "gn:feature_code":"PPL",
    "gn:name":"Laurel Hills",
    "gn:population":0,
    "gn:timezone":"America/New_York",
    "iso:country":"US",
    "wof:name":"Laurel Hills",
    "wof:placetype":"locality"
},
  "geometry": {"coordinates":[-84.67355000000001,34.04454],"type":"Point"}
}