{
  "type": "Feature",
  "properties": {
    "gn:admin1_code":"SC",
    "gn:admin2_code":"13.0",
    "gn:asciiname":"Bon Aire",
    "gn:country_code":"US",
    "gn:dem":16,
    "gn:elevation":"5.0",
    "gn:feature_class":"P",
    "gn:feature_code":"PPL",
    "gn:name":"Bon Aire",
    "gn:population":0,
    "gn:timezone":"America/New_York",
    "iso:country":"US",
    "wof:name":"Bon Aire",
    "wof:placetype":"locality"
},
  "geometry": {"coordinates":[-80.74316,32.39464],"type":"Point"}
}