{
  "type": "Feature",
  "properties": {
    "gn:admin1_code":"TN",
    "gn:admin2_code":"95",
    "gn:asciiname":"Edgewater Beach",
    "gn:country_code":"US",
    "gn:dem":91,
    "gn:elevation":"88.0",
    "gn:feature_class":"P",
    "gn:feature_code":"PPL",
    "gn:name":"Edgewater Beach",
    "gn:population":0,
    "gn:timezone":"America/Chicago",
    "iso:country":"US",
    "name:deu_x_preferred":[
        "Edgewater Beach"
    ],
    "wof:name":"Edgewater Beach",
    "wof:placetype":"locality"
},
  "geometry": {"coordinates":[-89.43201999999999,36.35645],"type":"Point"}
}