{
  "type": "Feature",
  "properties": {
    "gn:admin1_code":"GA",
    "gn:admin2_code":"295.0",
    "gn:asciiname":"Martindale",
    "gn:country_code":"US",
    "gn:dem":243,
    "gn:elevation":"235.0",
    "gn:feature_class":"P",
    "gn:feature_code":"PPL",
    "gn:name":"Martindale",
    "gn:population":0,
    "gn:timezone":"America/New_York",
    "iso:country":"US",
    "name:ceb_x_preferred":[
        "Martindale"
    ],
    "name:deu_x_preferred":[
        "Martindale"
    ],
    "name:fra_x_preferred":[
        "Martindale"
    ],
    "name:ita_x_preferred":[
        "Martindale"
    ],
    "name:nld_x_preferred":[
        "Martindale"
    ],
    "wof:name":"Martindale",
    "wof:placetype":"locality"
},
  "geometry": {"coordinates":[-85.30218000000001,34.62286],"type":"Point"}
}