{
  "type": "Feature",
  "properties": {
    "gn:admin1_code":"FL",
    "gn:admin2_code":"81.0",
    "gn:asciiname":"Keentown",
    "gn:country_code":"US",
    "gn:dem":40,
    "gn:elevation":"35.0",
    "gn:feature_class":"P",
    "gn:feature_code":"PPL",
    "gn:name":"Keentown",
    "gn:population":0,
    "gn:timezone":"America/New_York",
    "iso:country":"US",
    "wof:name":"Keentown",
    "wof:placetype":"locality"
},
  "geometry": {"coordinates":[-82.13759,27.57143],"type":"Point"}
}