{
  "type": "Feature",
  "properties": {
    "gn:admin1_code":"WI",
    "gn:admin2_code":"3.0",
    "gn:admin3_code":"54400.0",
    "gn:asciiname":"Cayuga",
    "gn:country_code":"US",
    "gn:dem":444,
    "gn:elevation":"443.0",
    "gn:feature_class":"P",
    "gn:feature_code":"PPL",
    "gn:name":"Cayuga",
    "gn:population":0,
    "gn:timezone":"America/Chicago",
    "iso:country":"US",
    "wof:name":"Cayuga",
    "wof:placetype":"locality"
},
  "geometry": {"coordinates":[-90.6824,46.2444],"type":"Point"}
}