{
  "type": "Feature",
  "properties": {
    "gn:admin1_code":"MD",
    "gn:admin2_code":"31.0",
    "gn:asciiname":"Highlands of Olney",
    "gn:country_code":"US",
    "gn:dem":166,
    "gn:elevation":"166.0",
    "gn:feature_class":"P",
    "gn:feature_code":"PPL",
    "gn:name":"Highlands of Olney",
    "gn:population":0,
    "gn:timezone":"America/New_York",
    "iso:country":"US",
    "wof:name":"Highlands of Olney",
    "wof:placetype":"locality"
},
  "geometry": {"coordinates":[-77.06498000000001,39.14677],"type":"Point"}
}