{
  "type": "Feature",
  "properties": {
    "gn:admin1_code":"TX",
    "gn:admin2_code":"409.0",
    "gn:asciiname":"West Sinton",
    "gn:country_code":"US",
    "gn:dem":36,
    "gn:elevation":"32.0",
    "gn:feature_class":"P",
    "gn:feature_code":"PPL",
    "gn:name":"West Sinton",
    "gn:population":0,
    "gn:timezone":"America/Chicago",
    "iso:country":"US",
    "wof:name":"West Sinton",
    "wof:placetype":"locality"
},
  "geometry": {"coordinates":[-97.67305,28.02918],"type":"Point"}
}