{
  "type": "Feature",
  "properties": {
    "gn:admin1_code":"DE",
    "gn:admin2_code":"1.0",
    "gn:asciiname":"Choptank Mills",
    "gn:country_code":"US",
    "gn:dem":19,
    "gn:elevation":"14.0",
    "gn:feature_class":"P",
    "gn:feature_code":"PPL",
    "gn:name":"Choptank Mills",
    "gn:population":0,
    "gn:timezone":"America/New_York",
    "iso:country":"US",
    "wof:name":"Choptank Mills",
    "wof:placetype":"locality"
},
  "geometry": {"coordinates":[-75.73521,39.06706],"type":"Point"}
}