{
  "type": "Feature",
  "properties": {
    "gn:admin1_code":"AR",
    "gn:admin2_code":"141.0",
    "gn:admin3_code":"92190.0",
    "gn:asciiname":"Stumptoe",
    "gn:country_code":"US",
    "gn:dem":327,
    "gn:elevation":"325.0",
    "gn:feature_class":"P",
    "gn:feature_code":"PPL",
    "gn:name":"Stumptoe",
    "gn:population":0,
    "gn:timezone":"America/Chicago",
    "iso:country":"US",
    "name:fas_x_preferred":[
        "\u0627\u0633\u062a\u0627\u0645\u067e\u062a\u0648"
    ],
    "name:zho_x_preferred":[
        "\u65af\u5766\u666e\u6258"
    ],
    "wof:name":"Stumptoe",
    "wof:placetype":"locality"
},
  "geometry": {"coordinates":[-92.82989000000001,35.46591],"type":"Point"}
}