{
  "type": "Feature",
  "properties": {
    "iso:country":"US",
    "name:eng_x_preferred":[
        "Rowe Corner"
    ],
    "name:eng_x_variant":[
        "Rowe Cor"
    ],
    "name:und_x_variant":[
        "Rowes Corner"
    ],
    "qs:gn_fcode":"PPL",
    "qs:gn_local":0,
    "qs:gn_namadm1":"ME",
    "qs:gn_name":"Rowe Corner",
    "qs:local_max":1268,
    "qs:local_sum":1463,
    "qs:localhoods":7,
    "qs:name":"Rowe Corner",
    "qs:name_adm0":"United States",
    "qs:name_adm1":"Maine",
    "qs:name_adm2":"Androscoggin",
    "qs:name_local":"Auburn",
    "qs:photo_max":1,
    "qs:photo_sum":4,
    "qs:placetype":"Suburb",
    "qs:quad_count":4,
    "qs:woe_adm0":23424977,
    "qs:woe_adm1":2347578,
    "qs:woe_adm2":12588660,
    "qs:woe_lau":0,
    "qs:woe_local":2357263,
    "qs:woe_ver":"7.10.0",
    "wof:lang":[
        "eng"
    ],
    "wof:name":"Rowe Corner",
    "wof:placetype":"neighbourhood",
    "wof:population":54,
    "zs:blockids":[
        230010106002010
    ],
    "zs:housing10":25,
    "zs:pop10":54
},
  "geometry": {"coordinates":[-70.224609,44.057985],"type":"Point"}
}