{
  "type": "Feature",
  "properties": {
    "iso:country":"US",
    "name:eng_x_preferred":[
        "Biscayne Highlands"
    ],
    "wof:name":"Biscayne Highlands",
    "wof:placetype":"neighbourhood",
    "wof:population":975,
    "zs:area_m":1440397.779342,
    "zs:blockids":[
        10730053021007,
        10730053021025,
        10730053021010,
        10730053021015,
        10730053021006,
        10730053021024,
        10730053021013,
        10730053021012,
        10730059032032,
        10730053021005,
        10730053022000,
        10730053021017,
        10730053021009,
        10730053021011,
        10730053021008,
        10730053021028,
        10730059032027,
        10730053021004,
        10730053021023,
        10730053021018,
        10730059032028,
        10730053021003,
        10730053021029,
        10730053021014,
        10730059032031
    ],
    "zs:housing10":464,
    "zs:label":"Biscayne Highlands",
    "zs:pop10":975
},
  "geometry": {"coordinates":[-86.690782,33.581914],"type":"Point"}
}