{
  "type": "Feature",
  "properties": {
    "gn:gn_country":"US",
    "gn:gn_fcode":"PPL",
    "gn:gn_pop":0,
    "iso:country":"US",
    "name:eng_x_preferred":[
        "Savoy"
    ],
    "name:fra_x_preferred":[
        "Savoy"
    ],
    "name:unk_x_variant":[
        "Ladds Mill"
    ],
    "qs_pg:aaroncc":"US",
    "qs_pg:gn_country":"US",
    "qs_pg:gn_fcode":"PPL",
    "qs_pg:gn_pop":0,
    "qs_pg:name":"Savoy",
    "qs_pg:name_adm0":"United States",
    "qs_pg:name_adm1":"Arkansas",
    "qs_pg:photos":256,
    "qs_pg:photos_1k":52,
    "qs_pg:photos_9k":1,
    "qs_pg:photos_9r":4,
    "qs_pg:photos_all":256,
    "qs_pg:photos_sr":5,
    "qs_pg:pop_sr":0,
    "qs_pg:qs_pg_placetype":"locality",
    "qs_pg:qs_pg_placetype_gp":"Town",
    "qs_pg:woe_adm0":23424977,
    "woe:adm0_id":23424977,
    "woe:name_adm0":"United States",
    "woe:name_adm1":"Arkansas",
    "woe:placetype":"Town",
    "wof:name":"Savoy",
    "wof:placetype":"locality"
},
  "geometry": {"coordinates":[-94.33271000000001,36.10564],"type":"Point"}
}