{
  "type": "Feature",
  "properties": {
    "gn:admin1_code":"UT",
    "gn:admin2_code":"35.0",
    "gn:asciiname":"Third and M Townhouse Condominium",
    "gn:country_code":"US",
    "gn:dem":1385,
    "gn:elevation":"1375.0",
    "gn:feature_class":"P",
    "gn:feature_code":"PPL",
    "gn:name":"Third and M Townhouse Condominium",
    "gn:population":0,
    "gn:timezone":"America/Denver",
    "iso:country":"US",
    "wof:name":"Third and M Townhouse Condominium",
    "wof:placetype":"locality"
},
  "geometry": {"coordinates":[-111.86521,40.773],"type":"Point"}
}