{
  "type": "Feature",
  "properties": {
    "gn:admin1_code":"IL",
    "gn:admin2_code":"99.0",
    "gn:admin3_code":"49204.0",
    "gn:asciiname":"Stavanger",
    "gn:country_code":"US",
    "gn:dem":206,
    "gn:elevation":"206.0",
    "gn:feature_class":"P",
    "gn:feature_code":"PPL",
    "gn:name":"Stavanger",
    "gn:population":0,
    "gn:timezone":"America/Chicago",
    "iso:country":"US",
    "wof:name":"Stavanger",
    "wof:placetype":"locality"
},
  "geometry": {"coordinates":[-88.61395999999998,41.39864],"type":"Point"}
}