{
  "type": "Feature",
  "properties": {
    "iso:country":"US",
    "name:eng_x_preferred":[
        "Grove Lakes"
    ],
    "wof:name":"Grove Lakes",
    "wof:placetype":"neighbourhood",
    "wof:population":240,
    "zs:area_m":368576.250005,
    "zs:blockids":[
        120710502032031,
        120710502032032,
        120710502032030,
        120710502032033
    ],
    "zs:housing10":95,
    "zs:label":"Grove Lakes",
    "zs:pop10":240
},
  "geometry": {"coordinates":[-81.804365,26.438588],"type":"Point"}
}