{
  "type": "Feature",
  "properties": {
    "gn:admin1_code":"MN",
    "gn:admin2_code":"137.0",
    "gn:admin3_code":"3880.0",
    "gn:asciiname":"Skibo",
    "gn:country_code":"US",
    "gn:dem":485,
    "gn:elevation":"483.0",
    "gn:feature_class":"P",
    "gn:feature_code":"PPL",
    "gn:name":"Skibo",
    "gn:population":0,
    "gn:timezone":"America/Chicago",
    "iso:country":"US",
    "name:fas_x_preferred":[
        "\u0627\u0633\u06a9\u06cc\u0628\u0648"
    ],
    "name:vol_x_preferred":[
        "Skibo"
    ],
    "wof:name":"Skibo",
    "wof:placetype":"locality"
},
  "geometry": {"coordinates":[-91.99433999999999,47.48548],"type":"Point"}
}