{
  "type": "Feature",
  "properties": {
    "gn:admin1_code":"DE",
    "gn:admin2_code":"5.0",
    "gn:asciiname":"Hollyville Acres",
    "gn:country_code":"US",
    "gn:dem":22,
    "gn:elevation":"10.0",
    "gn:feature_class":"P",
    "gn:feature_code":"PPL",
    "gn:name":"Hollyville Acres",
    "gn:population":0,
    "gn:timezone":"America/New_York",
    "iso:country":"US",
    "wof:name":"Hollyville Acres",
    "wof:placetype":"locality"
},
  "geometry": {"coordinates":[-75.22991,38.68845],"type":"Point"}
}