{
  "type": "Feature",
  "properties": {
    "gn:admin1_code":"NC",
    "gn:admin2_code":"185.0",
    "gn:admin3_code":"92688.0",
    "gn:asciiname":"Vaughan",
    "gn:country_code":"US",
    "gn:dem":108,
    "gn:elevation":"105.0",
    "gn:feature_class":"P",
    "gn:feature_code":"PPL",
    "gn:name":"Vaughan",
    "gn:population":0,
    "gn:timezone":"America/New_York",
    "iso:country":"US",
    "name:eng_x_preferred":[
        "Vaughan"
    ],
    "name:und_x_variant":[
        "Vaughn",
        "Browns Siding",
        "Browns Turnout"
    ],
    "wof:name":"Vaughan",
    "wof:placetype":"locality"
},
  "geometry": {"coordinates":[-78.00360000000001,36.42654],"type":"Point"}
}