{
  "type": "Feature",
  "properties": {
    "gn:admin1_code":"VA",
    "gn:admin2_code":"75",
    "gn:asciiname":"Three Square",
    "gn:country_code":"US",
    "gn:dem":94,
    "gn:elevation":"94.0",
    "gn:feature_class":"P",
    "gn:feature_code":"PPL",
    "gn:name":"Three Square",
    "gn:population":0,
    "gn:timezone":"America/New_York",
    "iso:country":"US",
    "wof:name":"Three Square",
    "wof:placetype":"locality"
},
  "geometry": {"coordinates":[-77.99472,37.66515],"type":"Point"}
}