{
  "type": "Feature",
  "properties": {
    "gn:admin1_code":"OH",
    "gn:admin2_code":"19.0",
    "gn:admin3_code":"78260.0",
    "gn:asciiname":"Toots Crossroads",
    "gn:country_code":"US",
    "gn:dem":378,
    "gn:elevation":"377.0",
    "gn:feature_class":"P",
    "gn:feature_code":"PPL",
    "gn:name":"Toots Crossroads",
    "gn:population":0,
    "gn:timezone":"America/New_York",
    "iso:country":"US",
    "wof:name":"Toots Crossroads",
    "wof:placetype":"locality"
},
  "geometry": {"coordinates":[-81.06815,40.53895],"type":"Point"}
}