{
  "type": "Feature",
  "properties": {
    "gn:admin1_code":"NM",
    "gn:admin2_code":"13.0",
    "gn:asciiname":"Malpais",
    "gn:country_code":"US",
    "gn:dem":1254,
    "gn:elevation":"1257.0",
    "gn:feature_class":"P",
    "gn:feature_code":"PPL",
    "gn:name":"Malpais",
    "gn:population":0,
    "gn:timezone":"America/Denver",
    "iso:country":"US",
    "name:ceb_x_preferred":[
        "Malpais"
    ],
    "name:srp_x_preferred":[
        "\u041c\u0430\u043b\u043f\u0430\u0438\u0441"
    ],
    "name:swe_x_preferred":[
        "Malpais"
    ],
    "wof:name":"Malpais",
    "wof:placetype":"locality"
},
  "geometry": {"coordinates":[-107.25306999999999,31.79844000000001],"type":"Point"}
}