{
  "type": "Feature",
  "properties": {
    "iso:country":"US",
    "name:eng_x_preferred":[
        "Woodmont East"
    ],
    "wof:name":"Woodmont East",
    "wof:placetype":"neighbourhood",
    "wof:population":4305,
    "zs:area_m":2163251.312961,
    "zs:blockids":[
        530330300035002,
        530330300035003,
        530330298011003,
        530330300035008,
        530330300033005,
        530330300035016,
        530330300035012,
        530330290033009,
        530330290033006,
        530330300035010,
        530330300035011,
        530330290033012,
        530330300033010,
        530330290042011,
        530330300033000,
        530330290033011,
        530330300033003,
        530330290033010,
        530330300035009,
        530330300035000,
        530330300035004,
        530330300033001,
        530330300035001,
        530330290033005,
        530330300035006,
        530330300035007,
        530330300033006,
        530330290042008,
        530330300033004,
        530330300033002,
        530330298011005
    ],
    "zs:housing10":1700,
    "zs:label":"Woodmont East",
    "zs:pop10":4305
},
  "geometry": {"coordinates":[-122.302465,47.36511],"type":"Point"}
}