{
  "type": "Feature",
  "properties": {
    "gn:admin1_code":"KY",
    "gn:admin2_code":"43",
    "gn:asciiname":"Beetle",
    "gn:country_code":"US",
    "gn:dem":203,
    "gn:elevation":"198.0",
    "gn:feature_class":"P",
    "gn:feature_code":"PPL",
    "gn:name":"Beetle",
    "gn:population":0,
    "gn:timezone":"America/New_York",
    "iso:country":"US",
    "name:fas_x_preferred":[
        "\u0628\u06cc\u062a\u0644"
    ],
    "wof:name":"Beetle",
    "wof:placetype":"locality"
},
  "geometry": {"coordinates":[-82.94628,38.19564],"type":"Point"}
}