{
  "type": "Feature",
  "properties": {
    "gn:admin1_code":"AR",
    "gn:admin2_code":"3.0",
    "gn:admin3_code":"92541.0",
    "gn:asciiname":"Lloyd",
    "gn:country_code":"US",
    "gn:dem":41,
    "gn:elevation":"40.0",
    "gn:feature_class":"P",
    "gn:feature_code":"PPL",
    "gn:name":"Lloyd",
    "gn:population":0,
    "gn:timezone":"America/Chicago",
    "iso:country":"US",
    "name:fas_x_preferred":[
        "\u0644\u0648\u06cc\u062f"
    ],
    "name:zho_x_preferred":[
        "\u52de\u57c3\u5fb7"
    ],
    "wof:name":"Lloyd",
    "wof:placetype":"locality"
},
  "geometry": {"coordinates":[-91.51401,33.29956],"type":"Point"}
}