{
  "type": "Feature",
  "properties": {
    "iso:country":"US",
    "name:eng_x_preferred":[
        "Willow Knolls"
    ],
    "name:eng_x_variant":[
        "Willow Knls"
    ],
    "qs:gn_adm0_cc":"US",
    "qs:gn_local":4905687,
    "qs:gn_nam_loc":"Peoria, Peoria, Illinois, US",
    "qs:gn_namadm1":"IL",
    "qs:local_max":4309,
    "qs:local_sum":14898,
    "qs:localhoods":39,
    "qs:name":"Willow Knolls",
    "qs:name_adm0":"United States",
    "qs:name_adm1":"Illinois",
    "qs:name_adm2":"Peoria",
    "qs:name_local":"Peoria",
    "qs:photo_max":122,
    "qs:photo_sum":212,
    "qs:placetype":"Suburb",
    "qs:quad_count":7,
    "qs:woe_adm0":23424977,
    "qs:woe_adm1":2347572,
    "qs:woe_adm2":12588149,
    "qs:woe_lau":0,
    "qs:woe_local":2470456,
    "qs:woe_ver":"7.10.0",
    "wof:lang":[
        "eng"
    ],
    "wof:name":"Willow Knolls",
    "wof:placetype":"neighbourhood",
    "wof:population":880,
    "zs:blockids":[
        171430032002024,
        171430031022016,
        171430031022019,
        171430031022006,
        171430031022017,
        171430031022020,
        171430031023004,
        171430032001006,
        171430031022008,
        171430031023005,
        171430031022018,
        171430031022009,
        171430031023003,
        171430031022007,
        171430031023002,
        171430031023001
    ],
    "zs:housing10":355,
    "zs:pop10":880
},
  "geometry": {"coordinates":[-89.615174,40.76507],"type":"Point"}
}