{
  "type": "Feature",
  "properties": {
    "gn:admin1_code":"KS",
    "gn:admin2_code":"73",
    "gn:admin3_code":"35000.0",
    "gn:asciiname":"Thrall",
    "gn:country_code":"US",
    "gn:dem":423,
    "gn:elevation":"418.0",
    "gn:feature_class":"P",
    "gn:feature_code":"PPL",
    "gn:name":"Thrall",
    "gn:population":0,
    "gn:timezone":"America/Chicago",
    "iso:country":"US",
    "wof:name":"Thrall",
    "wof:placetype":"locality"
},
  "geometry": {"coordinates":[-96.32111999999999,38.01002],"type":"Point"}
}