{
  "type": "Feature",
  "properties": {
    "gn:admin1_code":"DE",
    "gn:admin2_code":"5.0",
    "gn:asciiname":"Fenwick Estates",
    "gn:country_code":"US",
    "gn:dem":10,
    "gn:elevation":"10.0",
    "gn:feature_class":"P",
    "gn:feature_code":"PPL",
    "gn:name":"Fenwick Estates",
    "gn:population":0,
    "gn:timezone":"America/New_York",
    "iso:country":"US",
    "wof:name":"Fenwick Estates",
    "wof:placetype":"locality"
},
  "geometry": {"coordinates":[-75.18545999999998,38.46261],"type":"Point"}
}