{
  "type": "Feature",
  "properties": {
    "iso:country":"US",
    "name:eng_x_preferred":[
        "Hillsborough Park"
    ],
    "name:ita_x_preferred":[
        "Hillsborough Park"
    ],
    "name:nld_x_preferred":[
        "Hillsborough Park"
    ],
    "qs:gn_adm0_cc":"US",
    "qs:gn_local":5331920,
    "qs:gn_nam_loc":"Burlingame, San Mateo, California, US",
    "qs:gn_namadm1":"CA",
    "qs:local_max":2703,
    "qs:local_sum":7771,
    "qs:localhoods":13,
    "qs:name":"Hillsborough Park",
    "qs:name_adm0":"United States",
    "qs:name_adm1":"California",
    "qs:name_adm2":"San Mateo",
    "qs:name_local":"Burlingame",
    "qs:photo_max":1,
    "qs:photo_sum":1,
    "qs:placetype":"Suburb",
    "qs:quad_count":1,
    "qs:woe_adm0":23424977,
    "qs:woe_adm1":2347563,
    "qs:woe_adm2":12587710,
    "qs:woe_lau":0,
    "qs:woe_local":2372044,
    "qs:woe_ver":"7.10.0",
    "wd:wordcount":192,
    "wof:name":"Hillsborough Park",
    "wof:placetype":"neighbourhood"
},
  "geometry": {"coordinates":[-122.357483,37.555466],"type":"Point"}
}