{
  "type": "Feature",
  "properties": {
    "gn:admin1_code":"MO",
    "gn:admin2_code":"133.0",
    "gn:admin3_code":"64406.0",
    "gn:asciiname":"Whiting",
    "gn:country_code":"US",
    "gn:dem":94,
    "gn:elevation":"93.0",
    "gn:feature_class":"P",
    "gn:feature_code":"PPL",
    "gn:name":"Whiting",
    "gn:population":0,
    "gn:timezone":"America/Chicago",
    "iso:country":"US",
    "name:cat_x_preferred":[
        "Whiting"
    ],
    "name:ceb_x_preferred":[
        "Whiting"
    ],
    "name:ces_x_preferred":[
        "Whiting"
    ],
    "name:deu_x_preferred":[
        "Whiting"
    ],
    "name:fra_x_preferred":[
        "Whiting"
    ],
    "name:ita_x_preferred":[
        "Whiting"
    ],
    "name:jpn_x_preferred":[
        "\u30db\u30ef\u30a4\u30c6\u30a3\u30f3\u30b0"
    ],
    "name:nds_x_preferred":[
        "Whiting"
    ],
    "name:nld_x_preferred":[
        "Whiting"
    ],
    "name:pol_x_preferred":[
        "Whiting"
    ],
    "name:rus_x_preferred":[
        "\u0423\u0430\u0439\u0442\u0438\u043d\u0433"
    ],
    "name:srp_x_preferred":[
        "\u0412\u0430\u0458\u0442\u0438\u043d\u0433"
    ],
    "name:swe_x_preferred":[
        "Whiting"
    ],
    "name:vol_x_preferred":[
        "Whiting"
    ],
    "wof:name":"Whiting",
    "wof:placetype":"locality"
},
  "geometry": {"coordinates":[-89.37396,36.78894],"type":"Point"}
}