{
  "type": "Feature",
  "properties": {
    "gn:admin1_code":"WA",
    "gn:admin2_code":"77.0",
    "gn:asciiname":"Birchfield",
    "gn:country_code":"US",
    "gn:dem":303,
    "gn:elevation":"302.0",
    "gn:feature_class":"P",
    "gn:feature_code":"PPL",
    "gn:name":"Birchfield",
    "gn:population":0,
    "gn:timezone":"America/Los_Angeles",
    "iso:country":"US",
    "wof:name":"Birchfield",
    "wof:placetype":"locality"
},
  "geometry": {"coordinates":[-120.43451,46.57707],"type":"Point"}
}