{
  "type": "Feature",
  "properties": {
    "gn:admin1_code":"MO",
    "gn:admin2_code":"51.0",
    "gn:admin3_code":"49844.0",
    "gn:asciiname":"Millbrook",
    "gn:country_code":"US",
    "gn:dem":191,
    "gn:elevation":"192.0",
    "gn:feature_class":"P",
    "gn:feature_code":"PPL",
    "gn:name":"Millbrook",
    "gn:population":0,
    "gn:timezone":"America/Chicago",
    "iso:country":"US",
    "name:ceb_x_preferred":[
        "Millbrook"
    ],
    "name:deu_x_preferred":[
        "Millbrook"
    ],
    "name:fra_x_preferred":[
        "Millbrook"
    ],
    "name:ita_x_preferred":[
        "Millbrook"
    ],
    "name:kor_x_preferred":[
        "\ubc00\ube0c\ub8e9"
    ],
    "name:nld_x_preferred":[
        "Millbrook"
    ],
    "name:pol_x_preferred":[
        "Millbrook"
    ],
    "name:por_x_preferred":[
        "Millbrook"
    ],
    "name:spa_x_preferred":[
        "Millbrook"
    ],
    "name:srp_x_preferred":[
        "\u041c\u0438\u043b\u0431\u0440\u0443\u043a"
    ],
    "name:swe_x_preferred":[
        "Millbrook"
    ],
    "name:ukr_x_preferred":[
        "\u041c\u0456\u043b\u043b\u0431\u0440\u0443\u043a"
    ],
    "name:vol_x_preferred":[
        "Millbrook"
    ],
    "wof:name":"Millbrook",
    "wof:placetype":"locality"
},
  "geometry": {"coordinates":[-92.35657,38.4992],"type":"Point"}
}