{
  "type": "Feature",
  "properties": {
    "gn:admin1_code":"FL",
    "gn:admin2_code":"97.0",
    "gn:asciiname":"Shady Oaks Park Mobile Home Park",
    "gn:country_code":"US",
    "gn:dem":30,
    "gn:elevation":"24.0",
    "gn:feature_class":"P",
    "gn:feature_code":"PPL",
    "gn:name":"Shady Oaks Park Mobile Home Park",
    "gn:population":0,
    "gn:timezone":"America/New_York",
    "iso:country":"US",
    "wof:name":"Shady Oaks Park Mobile Home Park",
    "wof:placetype":"campus"
},
  "geometry": {"coordinates":[-81.46395,28.31469],"type":"Point"}
}