{
  "type": "Feature",
  "properties": {
    "iso:country":"US",
    "name:ceb_x_preferred":[
        "Ridgecrest"
    ],
    "name:deu_x_preferred":[
        "Ridgecrest"
    ],
    "name:eng_x_preferred":[
        "Ridgecrest"
    ],
    "name:ita_x_preferred":[
        "Ridgecrest"
    ],
    "name:kor_x_preferred":[
        "\ub9ac\uc9c0\ud06c\ub808\uc2a4\ud2b8"
    ],
    "name:nld_x_preferred":[
        "Ridgecrest"
    ],
    "name:pol_x_preferred":[
        "Ridgecrest"
    ],
    "name:por_x_preferred":[
        "Ridgecrest"
    ],
    "name:spa_x_preferred":[
        "Ridgecrest"
    ],
    "name:srp_x_preferred":[
        "\u0420\u0438\u045f\u043a\u0440\u0435\u0441\u0442"
    ],
    "name:swe_x_preferred":[
        "Ridgecrest"
    ],
    "name:vol_x_preferred":[
        "Ridgecrest"
    ],
    "wd:wordcount":25,
    "wof:name":"Ridgecrest",
    "wof:placetype":"neighbourhood",
    "wof:population":54,
    "zs:area_m":69901.258306,
    "zs:blockids":[
        371830515021004
    ],
    "zs:housing10":24,
    "zs:label":"Ridgecrest",
    "zs:pop10":54
},
  "geometry": {"coordinates":[-78.692537,35.811201],"type":"Point"}
}