{
  "type": "Feature",
  "properties": {
    "gn:admin1_code":"PA",
    "gn:admin2_code":"115.0",
    "gn:admin3_code":"2792.0",
    "gn:asciiname":"Burnwood",
    "gn:country_code":"US",
    "gn:dem":587,
    "gn:elevation":"584.0",
    "gn:feature_class":"P",
    "gn:feature_code":"PPL",
    "gn:name":"Burnwood",
    "gn:population":0,
    "gn:timezone":"America/New_York",
    "iso:country":"US",
    "wof:name":"Burnwood",
    "wof:placetype":"locality"
},
  "geometry": {"coordinates":[-75.50685,41.78619000000001],"type":"Point"}
}