{
  "type": "Feature",
  "properties": {
    "gn:country":"US",
    "gn:fcode":"PPL",
    "gn:population":0,
    "iso:country":"US",
    "name:bel_x_preferred":[
        "\u041d\u044c\u044e\u043f\u0430\u0440\u0442"
    ],
    "name:bre_x_preferred":[
        "Newport"
    ],
    "name:bul_x_preferred":[
        "\u041d\u044e\u043f\u043e\u0440\u0442"
    ],
    "name:cat_x_preferred":[
        "Newport"
    ],
    "name:ceb_x_preferred":[
        "Newport"
    ],
    "name:ces_x_preferred":[
        "Newport"
    ],
    "name:cym_x_preferred":[
        "Newport"
    ],
    "name:dan_x_preferred":[
        "Newport"
    ],
    "name:deu_x_preferred":[
        "Newport"
    ],
    "name:eng_x_preferred":[
        "Newport"
    ],
    "name:epo_x_preferred":[
        "Newport"
    ],
    "name:fas_x_preferred":[
        "\u0646\u06cc\u0648\u067e\u0648\u0631\u062a"
    ],
    "name:fin_x_preferred":[
        "Newport"
    ],
    "name:fra_x_preferred":[
        "Newport"
    ],
    "name:heb_x_preferred":[
        "\u05e0\u05d9\u05d5\u05e4\u05d5\u05e8\u05d8"
    ],
    "name:hun_x_preferred":[
        "Newport"
    ],
    "name:isl_x_preferred":[
        "Newport"
    ],
    "name:ita_x_preferred":[
        "Newport"
    ],
    "name:jpn_x_preferred":[
        "\u30cb\u30e5\u30fc\u30dd\u30fc\u30c8"
    ],
    "name:kor_x_preferred":[
        "\ub274\ud3ec\ud2b8"
    ],
    "name:mlg_x_preferred":[
        "Newport"
    ],
    "name:nds_x_preferred":[
        "Newport"
    ],
    "name:nld_x_preferred":[
        "Newport"
    ],
    "name:nor_x_preferred":[
        "Newport"
    ],
    "name:pol_x_preferred":[
        "Newport"
    ],
    "name:por_x_preferred":[
        "Newport"
    ],
    "name:ron_x_preferred":[
        "Newport"
    ],
    "name:rus_x_preferred":[
        "\u041d\u044c\u044e\u043f\u043e\u0440\u0442"
    ],
    "name:sco_x_preferred":[
        "Newport"
    ],
    "name:slk_x_preferred":[
        "Newport"
    ],
    "name:spa_x_preferred":[
        "Newport"
    ],
    "name:srp_x_preferred":[
        "\u040a\u0443\u043f\u043e\u0440\u0442"
    ],
    "name:swe_x_preferred":[
        "Newport"
    ],
    "name:tur_x_preferred":[
        "Newport"
    ],
    "name:ukr_x_preferred":[
        "\u041d\u044c\u044e\u043f\u043e\u0440\u0442"
    ],
    "name:und_x_variant":[
        "Nantuxet"
    ],
    "name:urd_x_preferred":[
        "\u0646\u06cc\u0648\u067e\u0648\u0631\u0679"
    ],
    "name:vol_x_preferred":[
        "Newport"
    ],
    "name:war_x_preferred":[
        "Newport"
    ],
    "name:zho_x_preferred":[
        "\u7d10\u6ce2\u7279"
    ],
    "qs_pg:aaroncc":"US",
    "qs_pg:gn_country":"US",
    "qs_pg:gn_fcode":"PPL",
    "qs_pg:gn_pop":0,
    "qs_pg:name":"Newport",
    "qs_pg:name_adm0":"United States",
    "qs_pg:name_adm1":"New Jersey",
    "qs_pg:photos":28,
    "qs_pg:photos_1k":6,
    "qs_pg:photos_9k":1,
    "qs_pg:photos_9r":2,
    "qs_pg:photos_all":28,
    "qs_pg:photos_sr":2,
    "qs_pg:pop_sr":5,
    "qs_pg:qs_pg_placetype":"locality",
    "qs_pg:qs_pg_placetype_gp":"Town",
    "qs_pg:woe_adm0":23424977,
    "woe:adm0_id":23424977,
    "woe:name_adm0":"United States",
    "woe:name_adm1":"New Jersey",
    "woe:placetype":"Town",
    "wof:name":"Newport",
    "wof:placetype":"locality"
},
  "geometry": {"coordinates":[-75.17657,39.29678],"type":"Point"}
}