{
  "type": "Feature",
  "properties": {
    "gn:country":"US",
    "gn:fcode":"PPL",
    "gn:population":0,
    "iso:country":"US",
    "name:ara_x_preferred":[
        "\u0645\u0627\u0644\u062a\u0627"
    ],
    "name:arz_x_preferred":[
        "\u0645\u0627\u0644\u062a\u0627"
    ],
    "name:ben_x_preferred":[
        "\u09ae\u09be\u09b2\u09cd\u099f\u09be"
    ],
    "name:che_x_preferred":[
        "\u041c\u0430\u043b\u044c\u0442\u0430"
    ],
    "name:deu_x_preferred":[
        "Malta"
    ],
    "name:ell_x_preferred":[
        "\u039c\u03ac\u03bb\u03c4\u03b1"
    ],
    "name:eng_x_preferred":[
        "Malta"
    ],
    "name:eus_x_preferred":[
        "Malta"
    ],
    "name:fra_x_preferred":[
        "Malta"
    ],
    "name:hat_x_preferred":[
        "Malta"
    ],
    "name:hin_x_preferred":[
        "\u092e\u093e\u0932\u094d\u091f\u093e"
    ],
    "name:hun_x_preferred":[
        "Malta"
    ],
    "name:ita_x_preferred":[
        "Malta"
    ],
    "name:pol_x_preferred":[
        "Malta"
    ],
    "name:spa_x_preferred":[
        "Malta"
    ],
    "name:swe_x_preferred":[
        "Malta"
    ],
    "name:tat_x_preferred":[
        "\u041c\u0430\u043b\u044c\u0442\u0430"
    ],
    "name:tur_x_preferred":[
        "Malta"
    ],
    "name:ukr_x_preferred":[
        "\u041c\u0430\u043b\u044c\u0442\u0430"
    ],
    "name:urd_x_preferred":[
        "\u0645\u0627\u0644\u0679\u0627"
    ],
    "name:uzb_x_preferred":[
        "Malta"
    ],
    "name:zho_x_preferred":[
        "\u9a6c\u8033\u4ed6"
    ],
    "qs_pg:aaroncc":"US",
    "qs_pg:gn_country":"US",
    "qs_pg:gn_fcode":"PPL",
    "qs_pg:gn_pop":0,
    "qs_pg:name":"Malta",
    "qs_pg:name_adm0":"United States",
    "qs_pg:name_adm1":"New York",
    "qs_pg:photos":250,
    "qs_pg:photos_1k":51,
    "qs_pg:photos_9k":1,
    "qs_pg:photos_9r":4,
    "qs_pg:photos_all":282,
    "qs_pg:photos_sr":4,
    "qs_pg:pop_sr":0,
    "qs_pg:qs_pg_placetype":"locality",
    "qs_pg:qs_pg_placetype_gp":"Town",
    "qs_pg:woe_adm0":23424977,
    "woe:adm0_id":23424977,
    "woe:name_adm0":"United States",
    "woe:name_adm1":"New York",
    "woe:placetype":"Town",
    "wof:name":"Malta",
    "wof:placetype":"locality",
    "wof:statistical_gore":1
},
  "geometry": {"coordinates":[-73.79262,42.97119],"type":"Point"}
}