{
  "type": "Feature",
  "properties": {
    "gn:admin1_code":"KY",
    "gn:admin2_code":"119",
    "gn:asciiname":"Handshoe",
    "gn:country_code":"US",
    "gn:dem":326,
    "gn:elevation":"302.0",
    "gn:feature_class":"P",
    "gn:feature_code":"PPL",
    "gn:name":"Handshoe",
    "gn:population":0,
    "gn:timezone":"America/New_York",
    "iso:country":"US",
    "wof:name":"Handshoe",
    "wof:placetype":"locality"
},
  "geometry": {"coordinates":[-82.90655,37.4701],"type":"Point"}
}