{
  "type": "Feature",
  "properties": {
    "gn:admin1_code":"TX",
    "gn:admin2_code":"297",
    "gn:asciiname":"Dinero",
    "gn:country_code":"US",
    "gn:dem":35,
    "gn:elevation":"34.0",
    "gn:feature_class":"P",
    "gn:feature_code":"PPL",
    "gn:name":"Dinero",
    "gn:population":0,
    "gn:timezone":"America/Chicago",
    "iso:country":"US",
    "name:eng_x_preferred":[
        "Dinero"
    ],
    "name:und_x_variant":[
        "Barlow's Ferry",
        "Barlows Ferry"
    ],
    "wof:name":"Dinero",
    "wof:placetype":"locality"
},
  "geometry": {"coordinates":[-97.96167,28.22639],"type":"Point"}
}