{
  "type": "Feature",
  "properties": {
    "iso:country":"US",
    "name:bar_x_preferred":[
        "Hillcrest"
    ],
    "name:cat_x_preferred":[
        "Hillcrest"
    ],
    "name:ceb_x_preferred":[
        "Hillcrest"
    ],
    "name:deu_x_preferred":[
        "Hillcrest"
    ],
    "name:eng_x_preferred":[
        "Hillcrest"
    ],
    "name:ita_x_preferred":[
        "Hillcrest"
    ],
    "name:nld_x_preferred":[
        "Hillcrest"
    ],
    "name:pol_x_preferred":[
        "Hillcrest"
    ],
    "name:por_x_preferred":[
        "Hillcrest"
    ],
    "name:srp_x_preferred":[
        "\u0425\u0438\u043b\u043a\u0440\u0435\u0441\u0442"
    ],
    "name:ukr_x_preferred":[
        "\u0413\u0456\u043b\u043b\u043a\u0440\u0435\u0441\u0442"
    ],
    "name:vol_x_preferred":[
        "Hillcrest"
    ],
    "wof:name":"Hillcrest",
    "wof:placetype":"neighbourhood",
    "wof:population":1211,
    "zs:area_m":1254207.918513,
    "zs:blockids":[
        130950006001034,
        130950006002012,
        130950006002067,
        130950006002034,
        130950006002057,
        130950006002051,
        130950006002055,
        130950006002011,
        130950006002059,
        130950006001036,
        130950006002046,
        130950006002040,
        130950006002052,
        130950006002025,
        130950006002053,
        130950006002018,
        130950006002026,
        130950006002035,
        130950006002058,
        130950006002007,
        130950006001037,
        130950006002031,
        130950006002043,
        130950006002073,
        130950006002013,
        130950006002023,
        130950006002030,
        130950006002039,
        130950006002074,
        130950006002054,
        130950006002024,
        130950006002032,
        130950006002027,
        130950006002036,
        130950006002069,
        130950006002066,
        130950006002019,
        130950006002020,
        130950006002045,
        130950006002048,
        130950006001031,
        130950006002047,
        130950006002072,
        130950006001032,
        130950006002064,
        130950006001033,
        130950006002041,
        130950006002063,
        130950006002062,
        130950006002044,
        130950006002033,
        130950006002022,
        130950006002068
    ],
    "zs:housing10":621,
    "zs:label":"Hillcrest",
    "zs:pop10":1211
},
  "geometry": {"coordinates":[-84.184116,31.597412],"type":"Point"}
}