{
  "type": "Feature",
  "properties": {
    "gn:admin1_code":"ND",
    "gn:admin2_code":"63.0",
    "gn:admin3_code":"68820.0",
    "gn:asciiname":"Mapes",
    "gn:country_code":"US",
    "gn:dem":462,
    "gn:elevation":"465.0",
    "gn:feature_class":"P",
    "gn:feature_code":"PPL",
    "gn:name":"Mapes",
    "gn:population":0,
    "gn:timezone":"America/Chicago",
    "iso:country":"US",
    "name:deu_x_preferred":[
        "Mapes"
    ],
    "wof:name":"Mapes",
    "wof:placetype":"locality"
},
  "geometry": {"coordinates":[-98.22732000000001,48.03111],"type":"Point"}
}