{
  "type": "Feature",
  "properties": {
    "gn:admin1_code":"TX",
    "gn:admin2_code":"481",
    "gn:asciiname":"Lane City",
    "gn:country_code":"US",
    "gn:dem":28,
    "gn:elevation":"26.0",
    "gn:feature_class":"P",
    "gn:feature_code":"PPL",
    "gn:name":"Lane City",
    "gn:population":0,
    "gn:timezone":"America/Chicago",
    "iso:country":"US",
    "name:fas_x_preferred":[
        "\u0644\u06cc\u0646 \u0633\u06cc\u062a\u06cc"
    ],
    "wof:name":"Lane City",
    "wof:placetype":"locality"
},
  "geometry": {"coordinates":[-96.02634999999999,29.21608],"type":"Point"}
}