{
  "type": "Feature",
  "properties": {
    "gn:admin1_code":"PA",
    "gn:admin2_code":"39.0",
    "gn:admin3_code":"4720.0",
    "gn:asciiname":"Palmer",
    "gn:country_code":"US",
    "gn:dem":348,
    "gn:elevation":"345.0",
    "gn:feature_class":"P",
    "gn:feature_code":"PPL",
    "gn:name":"Palmer",
    "gn:population":0,
    "gn:timezone":"America/New_York",
    "iso:country":"US",
    "name:ben_x_preferred":[
        "\u09aa\u09be\u09b2\u09ae\u09c7\u09b0"
    ],
    "name:cat_x_preferred":[
        "Palmer"
    ],
    "name:ceb_x_preferred":[
        "Palmer"
    ],
    "name:ces_x_preferred":[
        "Palmer"
    ],
    "name:deu_x_preferred":[
        "Palmer"
    ],
    "name:ell_x_preferred":[
        "\u03a0\u03ac\u03bb\u03bc\u03b5\u03c1"
    ],
    "name:fas_x_preferred":[
        "\u067e\u0627\u0644\u0645\u0631"
    ],
    "name:fin_x_preferred":[
        "Palmer"
    ],
    "name:fra_x_preferred":[
        "Palmer"
    ],
    "name:heb_x_preferred":[
        "\u05e4\u05d0\u05dc\u05de\u05e8"
    ],
    "name:hin_x_preferred":[
        "\u092a\u093e\u092e\u0930"
    ],
    "name:ind_x_preferred":[
        "Palmer"
    ],
    "name:ita_x_preferred":[
        "Palmer"
    ],
    "name:jpn_x_preferred":[
        "\u30d1\u30fc\u30de\u30fc"
    ],
    "name:kor_x_preferred":[
        "\ud314\uba38"
    ],
    "name:lav_x_preferred":[
        "Palmer"
    ],
    "name:nld_x_preferred":[
        "Palmer"
    ],
    "name:pol_x_preferred":[
        "Palmer"
    ],
    "name:por_x_preferred":[
        "Palmer"
    ],
    "name:rus_x_preferred":[
        "\u041f\u0430\u043b\u043c\u0435\u0440"
    ],
    "name:slv_x_preferred":[
        "Palmer"
    ],
    "name:spa_x_preferred":[
        "Palmer"
    ],
    "name:srp_x_preferred":[
        "\u041f\u0430\u043b\u043c\u0435\u0440"
    ],
    "name:swe_x_preferred":[
        "Palmer"
    ],
    "name:tur_x_preferred":[
        "Palmer"
    ],
    "name:ukr_x_preferred":[
        "\u041f\u0430\u043b\u043c\u0435\u0440"
    ],
    "name:urd_x_preferred":[
        "\u067e\u0627\u0645\u0631"
    ],
    "name:vie_x_preferred":[
        "Palmer"
    ],
    "wof:name":"Palmer",
    "wof:placetype":"locality"
},
  "geometry": {"coordinates":[-80.42923,41.76089],"type":"Point"}
}