{
  "type": "Feature",
  "properties": {
    "gn:elevation":9,
    "iso:country":"US",
    "name:eng_x_preferred":[
        "Golden Spur"
    ],
    "qs:gn_fcode":"PPL",
    "qs:gn_local":0,
    "qs:gn_namadm1":"CT",
    "qs:gn_name":"Golden Spur",
    "qs:local_max":305,
    "qs:local_sum":842,
    "qs:localhoods":4,
    "qs:name":"Golden Spur",
    "qs:name_adm0":"United States",
    "qs:name_adm1":"Connecticut",
    "qs:name_adm2":"New London",
    "qs:name_local":"East Lyme",
    "qs:photo_max":35,
    "qs:photo_sum":84,
    "qs:placetype":"Suburb",
    "qs:quad_count":7,
    "qs:woe_adm0":23424977,
    "qs:woe_adm1":2347565,
    "qs:woe_adm2":12587796,
    "qs:woe_lau":0,
    "qs:woe_local":23417276,
    "qs:woe_ver":"7.10.0",
    "wof:lang":[
        "eng"
    ],
    "wof:name":"Golden Spur",
    "wof:placetype":"neighbourhood",
    "wof:population":1592,
    "zs:blockids":[
        90118707011003,
        90116933001004,
        90118707011029,
        90116937001030,
        90118707011011,
        90118707011007,
        90116933001006,
        90118707011012,
        90116937001088,
        90116937001089,
        90118707011004,
        90118707011008,
        90118707011009,
        90118707011015,
        90116937001034,
        90116937001022,
        90116933001009,
        90116937001031,
        90118707011014,
        90116933002022,
        90116937001028,
        90116933001010,
        90116933002007,
        90116937001044,
        90116937001029,
        90116937001090,
        90118707011000,
        90116937001027,
        90116937001084,
        90116937001032,
        90116933001011,
        90118707011010,
        90116933002009,
        90118707011017,
        90118707011013,
        90116937001023,
        90117161022021,
        90117161022030,
        90117161022022,
        90116933001005,
        90116937001033,
        90116933002001,
        90118707011002,
        90116937001035,
        90116937001085,
        90117161022031,
        90118707011005,
        90116937001045,
        90116937001047,
        90116933002008,
        90118707011001,
        90116933001007,
        90118707011006,
        90117161022024,
        90118707011016,
        90117161022029
    ],
    "zs:housing10":744,
    "zs:pop10":1592
},
  "geometry": {"coordinates":[-72.188857,41.365582],"type":"Point"}
}