{
  "type": "Feature",
  "properties": {
    "iso:country":"US",
    "name:eng_x_preferred":[
        "Victoria Farm"
    ],
    "wof:name":"Victoria Farm",
    "wof:placetype":"neighbourhood",
    "wof:population":2195,
    "zs:area_m":2791228.012047,
    "zs:blockids":[
        220330035053010,
        220330007011011,
        220330035053007,
        220330035053001,
        220330035053003,
        220330035053011,
        220330035053000,
        220330035053008,
        220330035051009,
        220330035054007,
        220330007011001,
        220330035053004,
        220330035053002,
        220330007011014,
        220330035053009,
        220330035054008,
        220330007011006,
        220330007011007
    ],
    "zs:housing10":911,
    "zs:label":"Victoria Farm",
    "zs:pop10":2195
},
  "geometry": {"coordinates":[-91.114893,30.490736],"type":"Point"}
}