{
  "type": "Feature",
  "properties": {
    "iso:country":"US",
    "qs_pg:aaroncc":"US",
    "qs_pg:name":"Buels Gore",
    "qs_pg:name_adm0":"United States",
    "qs_pg:name_adm1":"Vermont",
    "qs_pg:photos":348,
    "qs_pg:photos_1k":71,
    "qs_pg:photos_9k":2,
    "qs_pg:photos_9r":5,
    "qs_pg:photos_all":348,
    "qs_pg:photos_sr":5,
    "qs_pg:pop_sr":0,
    "qs_pg:qs_pg_placetype":"locality",
    "qs_pg:qs_pg_placetype_gp":"Town",
    "qs_pg:woe_adm0":23424977,
    "woe:adm0_id":23424977,
    "woe:name_adm0":"United States",
    "woe:name_adm1":"Vermont",
    "woe:placetype":"Town",
    "wof:name":"Buels Gore",
    "wof:placetype":"locality"
},
  "geometry": {"coordinates":[-72.930958,44.204166],"type":"Point"}
}