{
  "type": "Feature",
  "properties": {
    "gn:admin1_code":"VA",
    "gn:admin2_code":"157",
    "gn:asciiname":"Rose Hill",
    "gn:country_code":"US",
    "gn:dem":176,
    "gn:elevation":"178.0",
    "gn:feature_class":"P",
    "gn:feature_code":"PPL",
    "gn:name":"Rose Hill",
    "gn:population":0,
    "gn:timezone":"America/New_York",
    "iso:country":"US",
    "wof:name":"Rose Hill",
    "wof:placetype":"locality"
},
  "geometry": {"coordinates":[-78.12528,38.71651],"type":"Point"}
}