{
  "type": "Feature",
  "properties": {
    "gn:admin1_code":"MS",
    "gn:admin2_code":"67",
    "gn:asciiname":"Walters",
    "gn:country_code":"US",
    "gn:dem":68,
    "gn:elevation":"64.0",
    "gn:feature_class":"P",
    "gn:feature_code":"PPL",
    "gn:name":"Walters",
    "gn:population":0,
    "gn:timezone":"America/Chicago",
    "iso:country":"US",
    "name:bel_x_preferred":[
        "\u0423\u043e\u043b\u0442\u044d\u0440\u0441"
    ],
    "name:deu_x_preferred":[
        "Walters"
    ],
    "name:fin_x_preferred":[
        "Walters"
    ],
    "name:fra_x_preferred":[
        "Walters"
    ],
    "name:heb_x_preferred":[
        "\u05d5\u05dc\u05d8\u05e8\u05e1"
    ],
    "name:ita_x_preferred":[
        "Walters"
    ],
    "name:jpn_x_preferred":[
        "\u30a6\u30a9\u30eb\u30bf\u30fc\u30ba"
    ],
    "name:nld_x_preferred":[
        "Walters"
    ],
    "name:pol_x_preferred":[
        "Walters"
    ],
    "name:por_x_preferred":[
        "Walters"
    ],
    "name:rus_x_preferred":[
        "\u0423\u043e\u043b\u0442\u0435\u0440\u0441"
    ],
    "name:srp_x_preferred":[
        "\u0412\u043e\u0442\u0435\u0440\u0441"
    ],
    "name:swe_x_preferred":[
        "Walters"
    ],
    "name:ukr_x_preferred":[
        "\u0412\u043e\u043b\u0442\u0435\u0440\u0441"
    ],
    "name:vol_x_preferred":[
        "Walters"
    ],
    "wof:name":"Walters",
    "wof:placetype":"locality"
},
  "geometry": {"coordinates":[-89.17811,31.6435],"type":"Point"}
}