{
  "type": "Feature",
  "properties": {
    "gn:admin1_code":"VA",
    "gn:admin2_code":"770",
    "gn:asciiname":"Taryn Hills",
    "gn:country_code":"US",
    "gn:dem":321,
    "gn:elevation":"325.0",
    "gn:feature_class":"P",
    "gn:feature_code":"PPL",
    "gn:name":"Taryn Hills",
    "gn:population":0,
    "gn:timezone":"America/New_York",
    "iso:country":"US",
    "wof:name":"Taryn Hills",
    "wof:placetype":"locality"
},
  "geometry": {"coordinates":[-80.00559,37.24791],"type":"Point"}
}