{
  "type": "Feature",
  "properties": {
    "gn:admin1_code":"MS",
    "gn:admin2_code":"35.0",
    "gn:asciiname":"Eatonville",
    "gn:country_code":"US",
    "gn:dem":90,
    "gn:elevation":"93.0",
    "gn:feature_class":"P",
    "gn:feature_code":"PPL",
    "gn:name":"Eatonville",
    "gn:population":0,
    "gn:timezone":"America/Chicago",
    "iso:country":"US",
    "name:ceb_x_preferred":[
        "Eatonville"
    ],
    "name:deu_x_preferred":[
        "Eatonville"
    ],
    "name:eng_x_preferred":[
        "Eatonville"
    ],
    "name:ita_x_preferred":[
        "Eatonville"
    ],
    "name:nld_x_preferred":[
        "Eatonville"
    ],
    "name:pol_x_preferred":[
        "Eatonville"
    ],
    "name:por_x_preferred":[
        "Eatonville"
    ],
    "name:rus_x_preferred":[
        "\u0418\u0442\u043e\u043d\u0432\u0438\u043b\u043b"
    ],
    "name:spa_x_preferred":[
        "Eatonville"
    ],
    "name:srp_x_preferred":[
        "\u0418\u0442\u043e\u043d\u0432\u0438\u043b"
    ],
    "name:ukr_x_preferred":[
        "\u0406\u0442\u043e\u043d\u0432\u0456\u043b\u043b"
    ],
    "name:und_x_variant":[
        "Eastonville"
    ],
    "name:vol_x_preferred":[
        "Eatonville"
    ],
    "wof:name":"Eatonville",
    "wof:placetype":"locality"
},
  "geometry": {"coordinates":[-89.32923000000002,31.41406],"type":"Point"}
}