{
  "type": "Feature",
  "properties": {
    "gn:admin1_code":"AR",
    "gn:admin2_code":"71.0",
    "gn:admin3_code":"91770.0",
    "gn:asciiname":"Harmony",
    "gn:country_code":"US",
    "gn:dem":202,
    "gn:elevation":"191.0",
    "gn:feature_class":"P",
    "gn:feature_code":"PPL",
    "gn:name":"Harmony",
    "gn:population":0,
    "gn:timezone":"America/Chicago",
    "iso:country":"US",
    "name:fas_x_preferred":[
        "\u0647\u0627\u0631\u0645\u0648\u0646\u06cc"
    ],
    "name:zho_x_preferred":[
        "\u54c8\u83ab\u5c3c"
    ],
    "wof:name":"Harmony",
    "wof:placetype":"locality"
},
  "geometry": {"coordinates":[-93.55574,35.54814000000001],"type":"Point"}
}