{
  "type": "Feature",
  "properties": {
    "gn:admin1_code":"VA",
    "gn:admin2_code":"121",
    "gn:asciiname":"Glade Road Heights",
    "gn:country_code":"US",
    "gn:dem":612,
    "gn:elevation":"622.0",
    "gn:feature_class":"P",
    "gn:feature_code":"PPL",
    "gn:name":"Glade Road Heights",
    "gn:population":0,
    "gn:timezone":"America/New_York",
    "iso:country":"US",
    "wof:name":"Glade Road Heights",
    "wof:placetype":"locality"
},
  "geometry": {"coordinates":[-80.45644,37.23541],"type":"Point"}
}