{
  "type": "Feature",
  "properties": {
    "gn:admin1_code":"IA",
    "gn:admin2_code":"55.0",
    "gn:admin3_code":"90006.0",
    "gn:asciiname":"Robinson",
    "gn:country_code":"US",
    "gn:dem":286,
    "gn:elevation":"284.0",
    "gn:feature_class":"P",
    "gn:feature_code":"PPL",
    "gn:name":"Robinson",
    "gn:population":0,
    "gn:timezone":"America/Chicago",
    "iso:country":"US",
    "wof:name":"Robinson",
    "wof:placetype":"locality"
},
  "geometry": {"coordinates":[-91.57877000000001,42.34193],"type":"Point"}
}