{
  "type": "Feature",
  "properties": {
    "iso:country":"US",
    "name:eng_x_preferred":[
        "Wyckoffs Mills"
    ],
    "wof:name":"Wyckoffs Mills",
    "wof:placetype":"neighbourhood",
    "wof:population":1057,
    "zs:blockids":[
        340230082023072,
        340230082023061,
        340230082023073,
        340230082023060,
        340230087001085,
        340230087001090,
        340230082023078,
        340230082023079,
        340230082023076,
        340230082023054,
        340230082023068,
        340230082023069,
        340230082023080,
        340230087001087,
        340230082023055,
        340230082023075,
        340230082023077,
        340210044053002
    ],
    "zs:housing10":589,
    "zs:label":"Wyckoffs Mills",
    "zs:pop10":1057
},
  "geometry": {"coordinates":[-74.481083,40.28243],"type":"Point"}
}