{
  "type": "Feature",
  "properties": {
    "gn:admin1_code":"WV",
    "gn:admin2_code":"33",
    "gn:asciiname":"Lake Ridge",
    "gn:country_code":"US",
    "gn:dem":360,
    "gn:elevation":"354.0",
    "gn:feature_class":"P",
    "gn:feature_code":"PPL",
    "gn:name":"Lake Ridge",
    "gn:population":0,
    "gn:timezone":"America/New_York",
    "iso:country":"US",
    "name:ceb_x_preferred":[
        "Lake Ridge"
    ],
    "name:deu_x_preferred":[
        "Lake Ridge"
    ],
    "name:swe_x_preferred":[
        "Lake Ridge"
    ],
    "wof:name":"Lake Ridge",
    "wof:placetype":"locality"
},
  "geometry": {"coordinates":[-80.21425000000001,39.27981],"type":"Point"}
}