{
  "type": "Feature",
  "properties": {
    "gn:admin1_code":"PA",
    "gn:admin2_code":"11",
    "gn:admin3_code":"24384.0",
    "gn:asciiname":"Sunset Manor",
    "gn:country_code":"US",
    "gn:dem":77,
    "gn:elevation":"77.0",
    "gn:feature_class":"P",
    "gn:feature_code":"PPL",
    "gn:name":"Sunset Manor",
    "gn:population":0,
    "gn:timezone":"America/New_York",
    "iso:country":"US",
    "wof:name":"Sunset Manor",
    "wof:placetype":"locality"
},
  "geometry": {"coordinates":[-75.82500999999998,40.28469000000001],"type":"Point"}
}