{
  "type": "Feature",
  "properties": {
    "gn:admin1_code":"SD",
    "gn:admin2_code":"23.0",
    "gn:admin3_code":"30380.0",
    "gn:asciiname":"Lake View Colony",
    "gn:country_code":"US",
    "gn:dem":469,
    "gn:elevation":"469.0",
    "gn:feature_class":"P",
    "gn:feature_code":"PPL",
    "gn:name":"Lake View Colony",
    "gn:population":0,
    "gn:timezone":"America/Chicago",
    "iso:country":"US",
    "wof:name":"Lake View Colony",
    "wof:placetype":"locality"
},
  "geometry": {"coordinates":[-98.46428,43.21975],"type":"Point"}
}