{
  "type": "Feature",
  "properties": {
    "gn:admin1_code":"WV",
    "gn:admin2_code":"47",
    "gn:asciiname":"Hemphill",
    "gn:country_code":"US",
    "gn:dem":401,
    "gn:elevation":"390.0",
    "gn:feature_class":"P",
    "gn:feature_code":"PPL",
    "gn:name":"Hemphill",
    "gn:population":0,
    "gn:timezone":"America/New_York",
    "iso:country":"US",
    "name:fas_x_preferred":[
        "\u0647\u0645\u0641\u06cc\u0644"
    ],
    "name:vol_x_preferred":[
        "Hemphill"
    ],
    "wof:name":"Hemphill",
    "wof:placetype":"locality"
},
  "geometry": {"coordinates":[-81.59538000000001,37.44484],"type":"Point"}
}