{
  "type": "Feature",
  "properties": {
    "gn:admin1_code":"KY",
    "gn:admin2_code":"125",
    "gn:asciiname":"Mershons",
    "gn:country_code":"US",
    "gn:dem":332,
    "gn:elevation":"331.0",
    "gn:feature_class":"P",
    "gn:feature_code":"PPL",
    "gn:name":"Mershons",
    "gn:population":0,
    "gn:timezone":"America/New_York",
    "iso:country":"US",
    "wof:name":"Mershons",
    "wof:placetype":"locality"
},
  "geometry": {"coordinates":[-84.12576999999997,37.28314],"type":"Point"}
}