{
  "type": "Feature",
  "properties": {
    "gn:admin1_code":"OH",
    "gn:admin2_code":"017",
    "gn:admin3_code":"83150.0",
    "gn:asciiname":"Emery Acres",
    "gn:country_code":"US",
    "gn:dem":266,
    "gn:elevation":"264.0",
    "gn:feature_class":"P",
    "gn:feature_code":"PPL",
    "gn:name":"Emery Acres",
    "gn:population":0,
    "gn:timezone":"America/New_York",
    "iso:country":"US",
    "wof:name":"Emery Acres",
    "wof:placetype":"locality"
},
  "geometry": {"coordinates":[-84.36221999999999,39.335],"type":"Point"}
}