{
  "type": "Feature",
  "properties": {
    "gn:admin1_code":"NC",
    "gn:admin2_code":"67.0",
    "gn:admin3_code":"94068.0",
    "gn:asciiname":"Reynolda Park",
    "gn:country_code":"US",
    "gn:dem":280,
    "gn:elevation":"279.0",
    "gn:feature_class":"P",
    "gn:feature_code":"PPL",
    "gn:name":"Reynolda Park",
    "gn:population":0,
    "gn:timezone":"America/New_York",
    "iso:country":"US",
    "wof:name":"Reynolda Park",
    "wof:placetype":"locality"
},
  "geometry": {"coordinates":[-80.28671999999997,36.12014],"type":"Point"}
}