{
  "type": "Feature",
  "properties": {
    "iso:country":"US",
    "name:eng_x_preferred":[
        "Arnada"
    ],
    "qs:gn_adm0_cc":"US",
    "qs:gn_local":5814616,
    "qs:gn_nam_loc":"Vancouver, Clark, Washington, US",
    "qs:gn_namadm1":"WA",
    "qs:local_max":2037,
    "qs:local_sum":14855,
    "qs:localhoods":74,
    "qs:name":"Arnada",
    "qs:name_adm0":"United States",
    "qs:name_adm1":"Washington",
    "qs:name_adm2":"Clark",
    "qs:name_local":"Vancouver",
    "qs:photo_max":80,
    "qs:photo_sum":522,
    "qs:placetype":"Suburb",
    "qs:quad_count":22,
    "qs:woe_adm0":23424977,
    "qs:woe_adm1":2347606,
    "qs:woe_adm2":12590445,
    "qs:woe_lau":0,
    "qs:woe_local":2511258,
    "qs:woe_ver":"7.10.0",
    "wof:lang":[
        "eng"
    ],
    "wof:name":"Arnada",
    "wof:placetype":"neighbourhood",
    "wof:population":674,
    "zs:blockids":[
        530110425002009,
        530110425001011,
        530110425001022,
        530110425002018,
        530110425002002,
        530110425002023,
        530110425001021,
        530110425001010,
        530110425001029,
        530110425002007,
        530110425002008,
        530110425001014,
        530110425001024,
        530110425002005,
        530110425002011,
        530110425002021,
        530110425001025,
        530110425001026,
        530110425002058,
        530110425001027,
        530110425001020,
        530110425002015,
        530110425002004,
        530110425002020,
        530110425002000,
        530110425001028,
        530110425001019,
        530110425002001,
        530110425002022,
        530110425002019,
        530110425002006,
        530110425001018,
        530110425001012,
        530110425001023,
        530110425002016,
        530110425002003,
        530110425002010,
        530110425002012,
        530110425002037,
        530110425001002,
        530110425001013
    ],
    "zs:housing10":348,
    "zs:pop10":674
},
  "geometry": {"coordinates":[-122.666957,45.636832],"type":"Point"}
}