{
  "type": "Feature",
  "properties": {
    "iso:country":"US",
    "name:ceb_x_preferred":[
        "Cedar Crest"
    ],
    "name:deu_x_preferred":[
        "Cedar Crest"
    ],
    "name:eng_x_preferred":[
        "Cedar Crest"
    ],
    "name:hrv_x_preferred":[
        "Cedar Crest"
    ],
    "name:ita_x_preferred":[
        "Cedar Crest"
    ],
    "name:nld_x_preferred":[
        "Cedar Crest"
    ],
    "name:spa_x_preferred":[
        "Cedar Crest"
    ],
    "name:srp_x_preferred":[
        "\u0421\u0438\u0434\u0435\u0440 \u041a\u0440\u0435\u0441\u0442"
    ],
    "name:ukr_x_preferred":[
        "\u0421\u0456\u0434\u0430\u0440-\u041a\u0440\u0435\u0441\u0442"
    ],
    "name:vol_x_preferred":[
        "Cedar Crest"
    ],
    "wof:name":"Cedar Crest",
    "wof:placetype":"neighbourhood",
    "wof:population":2,
    "zs:area_m":51495.176868,
    "zs:blockids":[
        120390205004094,
        120390205001046,
        120390205001045,
        120390205004085
    ],
    "zs:housing10":2,
    "zs:label":"Cedar Crest",
    "zs:pop10":2
},
  "geometry": {"coordinates":[-84.57696300000001,30.58918],"type":"Point"}
}