{
  "type": "Feature",
  "properties": {
    "gn:admin1_code":"NC",
    "gn:admin2_code":"37.0",
    "gn:admin3_code":"92012.0",
    "gn:asciiname":"Mount Vernon Springs",
    "gn:country_code":"US",
    "gn:dem":162,
    "gn:elevation":"158.0",
    "gn:feature_class":"P",
    "gn:feature_code":"PPL",
    "gn:name":"Mount Vernon Springs",
    "gn:population":0,
    "gn:timezone":"America/New_York",
    "iso:country":"US",
    "wof:name":"Mount Vernon Springs",
    "wof:placetype":"locality"
},
  "geometry": {"coordinates":[-79.42529999999999,35.66792],"type":"Point"}
}