{
  "type": "Feature",
  "properties": {
    "gn:elevation":4,
    "gn:gn_country":"US",
    "gn:gn_fcode":"PPL",
    "gn:gn_pop":0,
    "iso:country":"US",
    "name:eng_x_preferred":[
        "Robinhood Forest"
    ],
    "name:eng_x_variant":[
        "Robinhood Frst"
    ],
    "name:unk_x_variant":[
        "Robinhood Forest"
    ],
    "qs:gn_adm0_cc":"US",
    "qs:gn_fcode":"PPL",
    "qs:gn_local":4791259,
    "qs:gn_nam_loc":"Virginia Beach, Virginia Beach, Virginia, US",
    "qs:gn_namadm1":"VA",
    "qs:gn_name":"Robinhood Forest",
    "qs:local_max":5828,
    "qs:local_sum":35994,
    "qs:localhoods":70,
    "qs:name":"Robinhood Forest",
    "qs:name_adm0":"United States",
    "qs:name_adm1":"Virginia",
    "qs:name_adm2":"Virginia Beach City",
    "qs:name_local":"Virginia Beach",
    "qs:photo_max":5,
    "qs:photo_sum":6,
    "qs:placetype":"Suburb",
    "qs:quad_count":2,
    "qs:woe_adm0":23424977,
    "qs:woe_adm1":2347605,
    "qs:woe_adm2":12590430,
    "qs:woe_lau":0,
    "qs:woe_local":2512636,
    "qs:woe_ver":"7.10.0",
    "qs_pg:aaroncc":"US",
    "qs_pg:gn_country":"US",
    "qs_pg:gn_fcode":"PPL",
    "qs_pg:gn_pop":0,
    "qs_pg:name":"Robinhood Forest",
    "qs_pg:name_adm0":"United States",
    "qs_pg:name_adm1":"Virginia",
    "qs_pg:photos":6,
    "qs_pg:photos_1k":1,
    "qs_pg:photos_9k":1,
    "qs_pg:photos_9r":1,
    "qs_pg:photos_all":6,
    "qs_pg:photos_sr":1,
    "qs_pg:pop_sr":0,
    "qs_pg:qs_pg_placetype":"neighbourhood",
    "qs_pg:qs_pg_placetype_gp":"Suburb",
    "qs_pg:woe_adm0":23424977,
    "wof:lang":[
        "eng"
    ],
    "wof:name":"Robinhood Forest",
    "wof:placetype":"neighbourhood",
    "wof:population":1097,
    "zs:blockids":[
        518100444013003,
        518100444012019,
        518100444011009,
        518100444011007,
        518100444011003,
        518100422022005,
        518100444012022,
        518100422022006,
        518100430021056,
        518100444012017,
        518100444011000,
        518100444012029,
        518100444011018,
        518100444013004,
        518100444011015,
        518100444011006,
        518100444012023,
        518100444011011,
        518100444013007,
        518100444011010,
        518100444011017,
        518100444011005,
        518100444011014,
        518100444011016,
        518100444011001,
        518100444012016,
        518100430021055,
        518100444012020,
        518100444011019,
        518100444011012,
        518100444012021,
        518100422022000,
        518100444011004,
        518100444011002,
        518100444011008,
        518100444013008,
        518100444011013,
        518100444012018
    ],
    "zs:housing10":441,
    "zs:pop10":1097
},
  "geometry": {"coordinates":[-76.064204,36.861846],"type":"Point"}
}