{
  "type": "Feature",
  "properties": {
    "gn:admin1_code":"CA",
    "gn:admin2_code":"55",
    "gn:asciiname":"Knoxville",
    "gn:country_code":"US",
    "gn:dem":413,
    "gn:elevation":"403.0",
    "gn:feature_class":"P",
    "gn:feature_code":"PPL",
    "gn:name":"Knoxville",
    "gn:population":0,
    "gn:timezone":"America/Los_Angeles",
    "iso:country":"US",
    "name:zho_x_preferred":[
        "\u8afe\u514b\u65af\u7dad\u723e"
    ],
    "wof:name":"Knoxville",
    "wof:placetype":"locality"
},
  "geometry": {"coordinates":[-122.34053,38.82768],"type":"Point"}
}