{
  "type": "Feature",
  "properties": {
    "gn:admin1_code":"NC",
    "gn:admin2_code":"175",
    "gn:admin3_code":"90564.0",
    "gn:asciiname":"Cherryfield",
    "gn:country_code":"US",
    "gn:dem":680,
    "gn:elevation":"681.0",
    "gn:feature_class":"P",
    "gn:feature_code":"PPL",
    "gn:name":"Cherryfield",
    "gn:population":0,
    "gn:timezone":"America/New_York",
    "iso:country":"US",
    "wof:name":"Cherryfield",
    "wof:placetype":"locality"
},
  "geometry": {"coordinates":[-82.80457,35.17372],"type":"Point"}
}