{
  "type": "Feature",
  "properties": {
    "gn:admin1_code":"CA",
    "gn:admin2_code":"93.0",
    "gn:asciiname":"Shadow Mountain Mobile Home Park",
    "gn:country_code":"US",
    "gn:dem":1013,
    "gn:elevation":"1008.0",
    "gn:feature_class":"P",
    "gn:feature_code":"PPL",
    "gn:name":"Shadow Mountain Mobile Home Park",
    "gn:population":0,
    "gn:timezone":"America/Los_Angeles",
    "iso:country":"US",
    "wof:name":"Shadow Mountain Mobile Home Park",
    "wof:placetype":"campus"
},
  "geometry": {"coordinates":[-122.29918000000001,41.27543],"type":"Point"}
}