{
  "type": "Feature",
  "properties": {
    "gn:admin1_code":"IL",
    "gn:admin2_code":"31.0",
    "gn:admin3_code":"53676.0",
    "gn:asciiname":"Dunsten Green",
    "gn:country_code":"US",
    "gn:dem":202,
    "gn:elevation":"201.0",
    "gn:feature_class":"P",
    "gn:feature_code":"PPL",
    "gn:name":"Dunsten Green",
    "gn:population":0,
    "gn:timezone":"America/Chicago",
    "iso:country":"US",
    "wof:name":"Dunsten Green",
    "wof:placetype":"locality"
},
  "geometry": {"coordinates":[-87.84694,42.14194000000001],"type":"Point"}
}