{
  "type": "Feature",
  "properties": {
    "iso:country":"US",
    "name:deu_x_preferred":[
        "Think Big"
    ],
    "name:eng_x_preferred":[
        "Think Big"
    ],
    "name:fra_x_preferred":[
        "Think Big"
    ],
    "name:jpn_x_preferred":[
        "\u30b7\u30f3\u30af\u30fb\u30d3\u30c3\u30b0"
    ],
    "wd:wordcount":1129,
    "wof:name":"Think Big",
    "wof:placetype":"neighbourhood",
    "wof:population":337,
    "zs:area_m":63292141.41186,
    "zs:blockids":[
        300310005011007,
        300310005011000
    ],
    "zs:housing10":188,
    "zs:label":"Think Big",
    "zs:pop10":337
},
  "geometry": {"coordinates":[-110.850076,45.739268],"type":"Point"}
}