{
  "type": "Feature",
  "properties": {
    "gn:admin1_code":"AL",
    "gn:admin2_code":"49.0",
    "gn:asciiname":"Plainview",
    "gn:country_code":"US",
    "gn:dem":384,
    "gn:elevation":"384.0",
    "gn:feature_class":"P",
    "gn:feature_code":"PPL",
    "gn:name":"Plainview",
    "gn:population":0,
    "gn:timezone":"America/Chicago",
    "iso:country":"US",
    "name:ceb_x_preferred":[
        "Plainview"
    ],
    "name:deu_x_preferred":[
        "Plainview"
    ],
    "name:fra_x_preferred":[
        "Plainview"
    ],
    "name:ita_x_preferred":[
        "Plainview"
    ],
    "name:nld_x_preferred":[
        "Plainview"
    ],
    "name:pol_x_preferred":[
        "Plainview"
    ],
    "name:por_x_preferred":[
        "Plainview"
    ],
    "name:rus_x_preferred":[
        "\u041f\u043b\u0435\u0439\u043d\u0432\u044c\u044e"
    ],
    "name:srp_x_preferred":[
        "\u041f\u043b\u0435\u0458\u043d\u0432\u0458\u0443"
    ],
    "name:swe_x_preferred":[
        "Plainview"
    ],
    "name:vol_x_preferred":[
        "Plainview"
    ],
    "wof:name":"Plainview",
    "wof:placetype":"locality"
},
  "geometry": {"coordinates":[-85.82053000000001,34.48314],"type":"Point"}
}