{
  "type": "Feature",
  "properties": {
    "gn:admin1_code":"PA",
    "gn:admin2_code":"133.0",
    "gn:admin3_code":"72992.0",
    "gn:asciiname":"Clear View",
    "gn:country_code":"US",
    "gn:dem":160,
    "gn:elevation":"165.0",
    "gn:feature_class":"P",
    "gn:feature_code":"PPL",
    "gn:name":"Clear View",
    "gn:population":0,
    "gn:timezone":"America/New_York",
    "iso:country":"US",
    "wof:name":"Clear View",
    "wof:placetype":"locality"
},
  "geometry": {"coordinates":[-76.69329999999999,40.00649],"type":"Point"}
}