{
  "type": "Feature",
  "properties": {
    "gn:admin1_code":"VA",
    "gn:admin2_code":"31",
    "gn:asciiname":"Westward Park",
    "gn:country_code":"US",
    "gn:dem":258,
    "gn:elevation":"253.0",
    "gn:feature_class":"P",
    "gn:feature_code":"PPL",
    "gn:name":"Westward Park",
    "gn:population":0,
    "gn:timezone":"America/New_York",
    "iso:country":"US",
    "wof:name":"Westward Park",
    "wof:placetype":"locality"
},
  "geometry": {"coordinates":[-79.25197,37.34792],"type":"Point"}
}