{
  "type": "Feature",
  "properties": {
    "iso:country":"US",
    "name:eng_x_preferred":[
        "Jobee Acres"
    ],
    "wof:name":"Jobee Acres",
    "wof:placetype":"neighbourhood",
    "wof:population":17,
    "zs:area_m":3629173.645144,
    "zs:blockids":[
        460139520005314,
        460139518001000,
        460139520005313,
        460139520005312
    ],
    "zs:housing10":10,
    "zs:label":"Jobee Acres",
    "zs:pop10":17
},
  "geometry": {"coordinates":[-98.385069,45.466151],"type":"Point"}
}