{
  "type": "Feature",
  "properties": {
    "gn:admin1_code":"AR",
    "gn:admin2_code":"65.0",
    "gn:admin3_code":"92916.0",
    "gn:asciiname":"Bone Town",
    "gn:country_code":"US",
    "gn:dem":220,
    "gn:elevation":"219.0",
    "gn:feature_class":"P",
    "gn:feature_code":"PPL",
    "gn:name":"Bone Town",
    "gn:population":0,
    "gn:timezone":"America/Chicago",
    "iso:country":"US",
    "wof:name":"Bone Town",
    "wof:placetype":"locality"
},
  "geometry": {"coordinates":[-91.77652999999999,36.04479],"type":"Point"}
}