{
  "type": "Feature",
  "properties": {
    "gn:admin1_code":"FL",
    "gn:admin2_code":"61",
    "gn:asciiname":"North Beach  (historical)",
    "gn:country_code":"US",
    "gn:dem":-9999,
    "gn:elevation":"0.0",
    "gn:feature_class":"P",
    "gn:feature_code":"PPL",
    "gn:name":"North Beach  (historical)",
    "gn:population":0,
    "gn:timezone":"America/New_York",
    "iso:country":"US",
    "name:und_x_variant":[
        "North Beach (historical)"
    ],
    "wof:name":"North Beach (historical)",
    "wof:placetype":"locality"
},
  "geometry": {"coordinates":[-80.40315,27.79654],"type":"Point"}
}