{
  "type": "Feature",
  "properties": {
    "gn:admin1_code":"TX",
    "gn:admin2_code":"293",
    "gn:asciiname":"Davis Prairie",
    "gn:country_code":"US",
    "gn:dem":153,
    "gn:elevation":"147.0",
    "gn:feature_class":"P",
    "gn:feature_code":"PPL",
    "gn:name":"Davis Prairie",
    "gn:population":0,
    "gn:timezone":"America/Chicago",
    "iso:country":"US",
    "wof:name":"Davis Prairie",
    "wof:placetype":"locality"
},
  "geometry": {"coordinates":[-96.52553,31.42045],"type":"Point"}
}