{
  "type": "Feature",
  "properties": {
    "gn:admin1_code":"AR",
    "gn:admin2_code":"75.0",
    "gn:admin3_code":"92385.0",
    "gn:asciiname":"Strangers Home",
    "gn:country_code":"US",
    "gn:dem":78,
    "gn:elevation":"79.0",
    "gn:feature_class":"P",
    "gn:feature_code":"PPL",
    "gn:name":"Strangers Home",
    "gn:population":0,
    "gn:timezone":"America/Chicago",
    "iso:country":"US",
    "wof:name":"Strangers Home",
    "wof:placetype":"locality"
},
  "geometry": {"coordinates":[-91.12846,35.92035],"type":"Point"}
}