{
  "type": "Feature",
  "properties": {
    "gn:admin1_code":"AL",
    "gn:admin2_code":"73",
    "gn:asciiname":"Lake Highlands",
    "gn:country_code":"US",
    "gn:dem":214,
    "gn:elevation":"213.0",
    "gn:feature_class":"P",
    "gn:feature_code":"PPL",
    "gn:name":"Lake Highlands",
    "gn:population":0,
    "gn:timezone":"America/Chicago",
    "iso:country":"US",
    "name:urd_x_preferred":[
        "\u0644\u06cc\u06a9 \u06c1\u0627\u0626\u06cc \u0644\u06cc\u0646\u0688\u0632"
    ],
    "wof:name":"Lake Highlands",
    "wof:placetype":"locality"
},
  "geometry": {"coordinates":[-86.73081999999999,33.57288],"type":"Point"}
}