{
  "type": "Feature",
  "properties": {
    "gn:admin1_code":"IA",
    "gn:admin2_code":"97.0",
    "gn:admin3_code":"92958.0",
    "gn:asciiname":"Millrock",
    "gn:country_code":"US",
    "gn:dem":240,
    "gn:elevation":"239.0",
    "gn:feature_class":"P",
    "gn:feature_code":"PPL",
    "gn:name":"Millrock",
    "gn:population":0,
    "gn:timezone":"America/Chicago",
    "iso:country":"US",
    "wof:name":"Millrock",
    "wof:placetype":"locality"
},
  "geometry": {"coordinates":[-90.83931,42.05502],"type":"Point"}
}