{
  "type": "Feature",
  "properties": {
    "iso:country":"US",
    "name:arz_x_preferred":[
        "\u0645\u0637\u0627\u0631 \u0645\u0642\u0627\u0637\u0639\u0647 \u062c\u0627\u0631\u0641\u064a\u0644\u062f \u0627\u0644\u0627\u0642\u0644\u064a\u0645\u0649"
    ],
    "name:ceb_x_preferred":[
        "Garfield County Regional Airport"
    ],
    "name:eng_x_preferred":[
        "Garfield County Regional Airport"
    ],
    "name:eng_x_variant":[
        "RIL",
        "KRIL"
    ],
    "name:fas_x_preferred":[
        "\u0641\u0631\u0648\u062f\u06af\u0627\u0647 \u0645\u062d\u0644\u06cc \u0634\u0647\u0631\u0633\u062a\u0627\u0646 \u06af\u0627\u0631\u0641\u06cc\u0644\u062f"
    ],
    "name:jpn_x_preferred":[
        "Garfield County\u5730\u57df\u7a7a\u6e2f"
    ],
    "name:nav_x_preferred":[
        "Bee\u02bceld\u01eb\u01ebst\u00e1n\u00edidi chid\u00ed naat\u02bca\u02bc\u00ed \u0144dinib\u012f\u012fh\u00edgi"
    ],
    "name:ron_x_preferred":[
        "Aeroportul Regional Garfield County"
    ],
    "name:tgk_x_preferred":[
        "\u0424\u0443\u0440\u0443\u0434\u0433\u043e\u04b3\u0438 \u041c\u0430\u04b3\u0430\u043b\u04e3 \u0448\u0430\u04b3\u0440\u0438\u0441\u0442\u043e\u043d \u0433\u043e\u0440\u0444\u0438\u043b\u0434"
    ],
    "name:urd_x_preferred":[
        "\u06af\u0627\u0631\u0641\u06cc\u0644\u0688 \u06a9\u0627\u0624\u0646\u0679\u06cc \u0631\u06cc\u062c\u0646\u0644 \u06c1\u0648\u0627\u0626\u06cc \u0627\u0688\u0627"
    ],
    "oa:elevation_ft":"5548",
    "oa:type":"medium_airport",
    "wd:wordcount":289,
    "woe:hierarchy":{
        "country_id":23424977,
        "county_id":12587750,
        "planet_id":1,
        "state_id":2347564
    },
    "wof:name":"Garfield County Regional Airport",
    "wof:placetype":"campus"
},
  "geometry": {"coordinates":[-107.727,39.5264],"type":"Point"}
}