{
  "type": "Feature",
  "properties": {
    "gn:admin1_code":"CA",
    "gn:admin2_code":"103.0",
    "gn:asciiname":"Favinger Place",
    "gn:country_code":"US",
    "gn:dem":182,
    "gn:elevation":"179.0",
    "gn:feature_class":"P",
    "gn:feature_code":"PPL",
    "gn:name":"Favinger Place",
    "gn:population":0,
    "gn:timezone":"America/Los_Angeles",
    "iso:country":"US",
    "wof:name":"Favinger Place",
    "wof:placetype":"locality"
},
  "geometry": {"coordinates":[-121.97749,40.0446],"type":"Point"}
}