{
  "type": "Feature",
  "properties": {
    "gn:admin1_code":"ID",
    "gn:admin2_code":"43.0",
    "gn:asciiname":"Pyke",
    "gn:country_code":"US",
    "gn:dem":1506,
    "gn:elevation":"1507.0",
    "gn:feature_class":"P",
    "gn:feature_code":"PPL",
    "gn:name":"Pyke",
    "gn:population":0,
    "gn:timezone":"America/Boise",
    "iso:country":"US",
    "wof:name":"Pyke",
    "wof:placetype":"locality"
},
  "geometry": {"coordinates":[-111.72413,43.95936],"type":"Point"}
}