{
  "type": "Feature",
  "properties": {
    "gn:admin1_code":"MS",
    "gn:admin2_code":"147.0",
    "gn:asciiname":"Kioto",
    "gn:country_code":"US",
    "gn:dem":114,
    "gn:elevation":"107.0",
    "gn:feature_class":"P",
    "gn:feature_code":"PPL",
    "gn:name":"Kioto",
    "gn:population":0,
    "gn:timezone":"America/Chicago",
    "iso:country":"US",
    "wof:name":"Kioto",
    "wof:placetype":"locality"
},
  "geometry": {"coordinates":[-90.24565,31.16407],"type":"Point"}
}