{
  "type": "Feature",
  "properties": {
    "gn:admin1_code":"NC",
    "gn:admin2_code":"171",
    "gn:admin3_code":"93128.0",
    "gn:asciiname":"Beulah",
    "gn:country_code":"US",
    "gn:dem":351,
    "gn:elevation":"348.0",
    "gn:feature_class":"P",
    "gn:feature_code":"PPL",
    "gn:name":"Beulah",
    "gn:population":0,
    "gn:timezone":"America/New_York",
    "iso:country":"US",
    "name:bre_x_preferred":[
        "Beulah"
    ],
    "name:ceb_x_preferred":[
        "Beulah"
    ],
    "name:cor_x_preferred":[
        "Beulah"
    ],
    "name:cym_x_preferred":[
        "Beulah"
    ],
    "name:deu_x_preferred":[
        "Beulah"
    ],
    "name:eng_x_preferred":[
        "Beulah"
    ],
    "name:fra_x_preferred":[
        "Beulah"
    ],
    "name:gla_x_preferred":[
        "Beulah"
    ],
    "name:ita_x_preferred":[
        "Beulah"
    ],
    "name:nld_x_preferred":[
        "Beulah"
    ],
    "name:nor_x_preferred":[
        "Beulah"
    ],
    "name:pol_x_preferred":[
        "Beulah"
    ],
    "name:por_x_preferred":[
        "Beulah"
    ],
    "name:spa_x_preferred":[
        "Beulah"
    ],
    "name:srp_x_preferred":[
        "\u0411\u0458\u0443\u043b\u0430"
    ],
    "name:swe_x_preferred":[
        "Beulah"
    ],
    "name:ukr_x_preferred":[
        "\u0411\u044e\u043b\u0430\u0433"
    ],
    "name:und_x_variant":[
        "Bottom"
    ],
    "name:vol_x_preferred":[
        "Beulah"
    ],
    "wof:name":"Beulah",
    "wof:placetype":"locality"
},
  "geometry": {"coordinates":[-80.77396,36.47485],"type":"Point"}
}