{
  "type": "Feature",
  "properties": {
    "gn:admin1_code":"NC",
    "gn:admin2_code":"91",
    "gn:admin3_code":"90016.0",
    "gn:asciiname":"Brantleys Grove",
    "gn:country_code":"US",
    "gn:dem":19,
    "gn:elevation":"13.0",
    "gn:feature_class":"P",
    "gn:feature_code":"PPL",
    "gn:name":"Brantleys Grove",
    "gn:population":0,
    "gn:timezone":"America/New_York",
    "iso:country":"US",
    "wof:name":"Brantleys Grove",
    "wof:placetype":"locality"
},
  "geometry": {"coordinates":[-76.94884999999999,36.32127],"type":"Point"}
}