{
  "type": "Feature",
  "properties": {
    "gn:admin1_code":"KY",
    "gn:admin2_code":"71",
    "gn:asciiname":"Hunter",
    "gn:country_code":"US",
    "gn:dem":242,
    "gn:elevation":"205.0",
    "gn:feature_class":"P",
    "gn:feature_code":"PPL",
    "gn:name":"Hunter",
    "gn:population":0,
    "gn:timezone":"America/New_York",
    "iso:country":"US",
    "name:eng_x_preferred":[
        "Hunter"
    ],
    "name:und_x_variant":[
        "Salisbury"
    ],
    "wof:name":"Hunter",
    "wof:placetype":"locality"
},
  "geometry": {"coordinates":[-82.75627,37.50621],"type":"Point"}
}