{
  "type": "Feature",
  "properties": {
    "gn:admin1_code":"IL",
    "gn:admin2_code":"57.0",
    "gn:admin3_code":"42574.0",
    "gn:asciiname":"Checkrow",
    "gn:country_code":"US",
    "gn:dem":189,
    "gn:elevation":"189.0",
    "gn:feature_class":"P",
    "gn:feature_code":"PPL",
    "gn:name":"Checkrow",
    "gn:population":0,
    "gn:timezone":"America/Chicago",
    "iso:country":"US",
    "name:eng_x_preferred":[
        "Checkrow"
    ],
    "name:und_x_variant":[
        "Check Row"
    ],
    "wof:name":"Checkrow",
    "wof:placetype":"locality"
},
  "geometry": {"coordinates":[-90.37818,40.55421],"type":"Point"}
}