{
  "type": "Feature",
  "properties": {
    "gn:admin1_code":"NC",
    "gn:admin2_code":"73.0",
    "gn:admin3_code":"91560.0",
    "gn:asciiname":"Wardville",
    "gn:country_code":"US",
    "gn:dem":13,
    "gn:elevation":"10.0",
    "gn:feature_class":"P",
    "gn:feature_code":"PPL",
    "gn:name":"Wardville",
    "gn:population":0,
    "gn:timezone":"America/New_York",
    "iso:country":"US",
    "name:eng_x_preferred":[
        "Wardville"
    ],
    "name:und_x_variant":[
        "Bosley"
    ],
    "wof:name":"Wardville",
    "wof:placetype":"locality"
},
  "geometry": {"coordinates":[-76.58495000000001,36.40682],"type":"Point"}
}