{
  "type": "Feature",
  "properties": {
    "gn:admin1_code":"NC",
    "gn:admin2_code":"27",
    "gn:admin3_code":"91780.0",
    "gn:asciiname":"Cloverdale",
    "gn:country_code":"US",
    "gn:dem":341,
    "gn:elevation":"337.0",
    "gn:feature_class":"P",
    "gn:feature_code":"PPL",
    "gn:name":"Cloverdale",
    "gn:population":0,
    "gn:timezone":"America/New_York",
    "iso:country":"US",
    "name:ceb_x_preferred":[
        "Cloverdale"
    ],
    "name:deu_x_preferred":[
        "Cloverdale"
    ],
    "name:fra_x_preferred":[
        "Cloverdale"
    ],
    "name:ita_x_preferred":[
        "Cloverdale"
    ],
    "name:nld_x_preferred":[
        "Cloverdale"
    ],
    "name:pol_x_preferred":[
        "Cloverdale"
    ],
    "name:por_x_preferred":[
        "Cloverdale"
    ],
    "name:rus_x_preferred":[
        "\u041a\u043b\u043e\u0432\u0435\u0440\u0434\u0435\u0439\u043b"
    ],
    "name:spa_x_preferred":[
        "Cloverdale"
    ],
    "name:srp_x_preferred":[
        "\u041a\u043b\u043e\u0432\u0435\u0440\u0434\u0435\u0458\u043b"
    ],
    "name:swe_x_preferred":[
        "Cloverdale"
    ],
    "name:ukr_x_preferred":[
        "\u041a\u043b\u043e\u0443\u0432\u0435\u0440\u0434\u0435\u0439\u043b"
    ],
    "name:vol_x_preferred":[
        "Cloverdale"
    ],
    "wof:name":"Cloverdale",
    "wof:placetype":"locality"
},
  "geometry": {"coordinates":[-81.5801,35.86652],"type":"Point"}
}