{
  "type": "Feature",
  "properties": {
    "gn:admin1_code":"NC",
    "gn:admin2_code":"163",
    "gn:admin3_code":"91844.0",
    "gn:asciiname":"Highsmiths",
    "gn:country_code":"US",
    "gn:dem":47,
    "gn:elevation":"45.0",
    "gn:feature_class":"P",
    "gn:feature_code":"PPL",
    "gn:name":"Highsmiths",
    "gn:population":0,
    "gn:timezone":"America/New_York",
    "iso:country":"US",
    "name:eng_x_preferred":[
        "Highsmiths"
    ],
    "name:und_x_variant":[
        "Highsmith"
    ],
    "wof:name":"Highsmiths",
    "wof:placetype":"locality"
},
  "geometry": {"coordinates":[-78.49666999999999,34.9185],"type":"Point"}
}