{
  "type": "Feature",
  "properties": {
    "gn:admin1_code":"OH",
    "gn:admin2_code":"155.0",
    "gn:admin3_code":"9190.0",
    "gn:asciiname":"Yankee Hills",
    "gn:country_code":"US",
    "gn:dem":321,
    "gn:elevation":"312.0",
    "gn:feature_class":"P",
    "gn:feature_code":"PPL",
    "gn:name":"Yankee Hills",
    "gn:population":0,
    "gn:timezone":"America/New_York",
    "iso:country":"US",
    "wof:name":"Yankee Hills",
    "wof:placetype":"locality"
},
  "geometry": {"coordinates":[-80.54924,41.23422],"type":"Point"}
}