{
  "type": "Feature",
  "properties": {
    "gn:admin1_code":"WA",
    "gn:admin2_code":"61.0",
    "gn:asciiname":"Brookside Mobile Home Park",
    "gn:country_code":"US",
    "gn:dem":16,
    "gn:elevation":"14.0",
    "gn:feature_class":"P",
    "gn:feature_code":"PPL",
    "gn:name":"Brookside Mobile Home Park",
    "gn:population":0,
    "gn:timezone":"America/Los_Angeles",
    "iso:country":"US",
    "wof:name":"Brookside Mobile Home Park",
    "wof:placetype":"campus"
},
  "geometry": {"coordinates":[-122.17332,48.0849],"type":"Point"}
}