{
  "type": "Feature",
  "properties": {
    "gn:admin1_code":"AR",
    "gn:admin2_code":"117.0",
    "gn:admin3_code":"94023.0",
    "gn:asciiname":"Gospoda",
    "gn:country_code":"US",
    "gn:dem":63,
    "gn:elevation":"62.0",
    "gn:feature_class":"P",
    "gn:feature_code":"PPL",
    "gn:name":"Gospoda",
    "gn:population":0,
    "gn:timezone":"America/Chicago",
    "iso:country":"US",
    "wof:name":"Gospoda",
    "wof:placetype":"locality"
},
  "geometry": {"coordinates":[-91.49513,34.8887],"type":"Point"}
}