{
  "type": "Feature",
  "properties": {
    "gn:admin1_code":"FL",
    "gn:admin2_code":"57",
    "gn:asciiname":"North Side Homes",
    "gn:country_code":"US",
    "gn:dem":18,
    "gn:elevation":"9.0",
    "gn:feature_class":"P",
    "gn:feature_code":"PPL",
    "gn:name":"North Side Homes",
    "gn:population":0,
    "gn:timezone":"America/New_York",
    "iso:country":"US",
    "wof:name":"North Side Homes",
    "wof:placetype":"locality"
},
  "geometry": {"coordinates":[-82.4533,28.0373],"type":"Point"}
}