{
  "type": "Feature",
  "properties": {
    "gn:admin1_code":"FL",
    "gn:admin2_code":"105.0",
    "gn:asciiname":"Scenic View Mobile Home Park",
    "gn:country_code":"US",
    "gn:dem":59,
    "gn:elevation":"52.0",
    "gn:feature_class":"P",
    "gn:feature_code":"PPL",
    "gn:name":"Scenic View Mobile Home Park",
    "gn:population":0,
    "gn:timezone":"America/New_York",
    "iso:country":"US",
    "wof:name":"Scenic View Mobile Home Park",
    "wof:placetype":"campus"
},
  "geometry": {"coordinates":[-81.98915,28.12215],"type":"Point"}
}