{
  "type": "Feature",
  "properties": {
    "gn:admin1_code":"NM",
    "gn:admin2_code":"39",
    "gn:asciiname":"Alire",
    "gn:country_code":"US",
    "gn:dem":2174,
    "gn:elevation":"2174.0",
    "gn:feature_class":"P",
    "gn:feature_code":"PPL",
    "gn:name":"Alire",
    "gn:population":0,
    "gn:timezone":"America/Denver",
    "iso:country":"US",
    "wof:name":"Alire",
    "wof:placetype":"locality"
},
  "geometry": {"coordinates":[-106.58087,36.47641],"type":"Point"}
}