{
  "type": "Feature",
  "properties": {
    "gn:admin1_code":"AL",
    "gn:admin2_code":"97.0",
    "gn:asciiname":"Pleasant Mobile Home Park",
    "gn:country_code":"US",
    "gn:dem":67,
    "gn:elevation":"63.0",
    "gn:feature_class":"P",
    "gn:feature_code":"PPL",
    "gn:name":"Pleasant Mobile Home Park",
    "gn:population":0,
    "gn:timezone":"America/Chicago",
    "iso:country":"US",
    "wof:name":"Pleasant Mobile Home Park",
    "wof:placetype":"campus"
},
  "geometry": {"coordinates":[-88.21741999999998,30.6786],"type":"Point"}
}