{
  "type": "Feature",
  "properties": {
    "gn:admin1_code":"MD",
    "gn:admin2_code":"35.0",
    "gn:asciiname":"East Prospect Plantation",
    "gn:country_code":"US",
    "gn:dem":5,
    "gn:elevation":"4.0",
    "gn:feature_class":"P",
    "gn:feature_code":"PPL",
    "gn:name":"East Prospect Plantation",
    "gn:population":0,
    "gn:timezone":"America/New_York",
    "iso:country":"US",
    "name:eng_x_preferred":[
        "East Prospect Plantation"
    ],
    "name:und_x_variant":[
        "Prospect Plantation"
    ],
    "wof:name":"East Prospect Plantation",
    "wof:placetype":"locality"
},
  "geometry": {"coordinates":[-76.18411999999999,38.92234000000001],"type":"Point"}
}