{
  "type": "Feature",
  "properties": {
    "gn:country":"US",
    "gn:fcode":"PPLX",
    "gn:population":0,
    "iso:country":"US",
    "name:eng_x_preferred":[
        "Whipporrwill Hills"
    ],
    "qs_pg:aaroncc":"US",
    "qs_pg:gn_country":"US",
    "qs_pg:gn_fcode":"PPLX",
    "qs_pg:gn_pop":0,
    "qs_pg:name":"Whipporrwill Hills",
    "qs_pg:name_adm0":"United States",
    "qs_pg:name_adm1":"North Carolina",
    "qs_pg:photos":4,
    "qs_pg:photos_1k":1,
    "qs_pg:photos_9k":1,
    "qs_pg:photos_9r":1,
    "qs_pg:photos_all":4,
    "qs_pg:photos_sr":1,
    "qs_pg:pop_sr":0,
    "qs_pg:qs_pg_placetype":"neighbourhood",
    "qs_pg:qs_pg_placetype_gp":"Suburb",
    "qs_pg:woe_adm0":23424977,
    "wof:name":"Whipporrwill Hills",
    "wof:placetype":"neighbourhood",
    "wof:population":965,
    "zs:area_m":11161719.191797,
    "zs:blockids":[
        371570411002011,
        371570411003015,
        371570411003006,
        371570411002013,
        371570411002001,
        371570411003002,
        371570411003004,
        371570411002012,
        371570411003003,
        371570411003014,
        371570411003001
    ],
    "zs:housing10":434,
    "zs:label":"Whipporrwill Hills",
    "zs:pop10":965
},
  "geometry": {"coordinates":[-79.75251,36.457656],"type":"Point"}
}