{
  "type": "Feature",
  "properties": {
    "iso:country":"US",
    "name:eng_x_preferred":[
        "Broadalbin Junction"
    ],
    "wof:name":"Broadalbin Junction",
    "wof:placetype":"neighbourhood",
    "wof:population":1081,
    "zs:area_m":7357519.055516,
    "zs:blockids":[
        360359702001027,
        360359703001001,
        360359702001056,
        360359702001041,
        360359703001005,
        360359703001000,
        360359702001043,
        360359702001048,
        360359703001004,
        360359703002044,
        360359703001011,
        360359702001037,
        360359702001046,
        360359702001044,
        360359703001007,
        360359703001016,
        360359702001058,
        360359702001036,
        360359702001062,
        360359702001024,
        360359703001008,
        360359702001025,
        360359703001002,
        360359703002028,
        360359703001019,
        360359702001023,
        360359702001057,
        360359703001014,
        360359703002029,
        360359703001009,
        360359703002027,
        360359702001047,
        360359702001061,
        360359702001049,
        360359703002004,
        360359703002006,
        360359702001060,
        360359702001042,
        360359703001012,
        360359702001039,
        360359703001010,
        360359703001006,
        360359702001026,
        360359703001003,
        360359703001013,
        360359702001040,
        360359703001018,
        360359702001038,
        360359702001035,
        360359703002005
    ],
    "zs:housing10":578,
    "zs:label":"Broadalbin Junction",
    "zs:pop10":1081
},
  "geometry": {"coordinates":[-74.27009,43.095642],"type":"Point"}
}