{
  "type": "Feature",
  "properties": {
    "gn:admin1_code":"AR",
    "gn:admin2_code":"83.0",
    "gn:admin3_code":"90807.0",
    "gn:asciiname":"Wilkins",
    "gn:country_code":"US",
    "gn:dem":135,
    "gn:elevation":"131.0",
    "gn:feature_class":"P",
    "gn:feature_code":"PPL",
    "gn:name":"Wilkins",
    "gn:population":0,
    "gn:timezone":"America/Chicago",
    "iso:country":"US",
    "name:ceb_x_preferred":[
        "Wilkins"
    ],
    "name:ces_x_preferred":[
        "Wilkins"
    ],
    "name:deu_x_preferred":[
        "Wilkins"
    ],
    "name:fra_x_preferred":[
        "Wilkins"
    ],
    "name:heb_x_preferred":[
        "\u05d5\u05d9\u05dc\u05e7\u05d9\u05e0\u05e1"
    ],
    "name:ita_x_preferred":[
        "Wilkins"
    ],
    "name:jpn_x_preferred":[
        "\u30a6\u30a3\u30eb\u30ad\u30f3\u30b9"
    ],
    "name:lav_x_preferred":[
        "Wilkins"
    ],
    "name:nds_x_preferred":[
        "Wilkins"
    ],
    "name:nld_x_preferred":[
        "Wilkins"
    ],
    "name:por_x_preferred":[
        "Wilkins"
    ],
    "name:rus_x_preferred":[
        "\u0423\u0438\u043b\u043a\u0438\u043d\u0441"
    ],
    "name:slv_x_preferred":[
        "Wilkins"
    ],
    "name:swe_x_preferred":[
        "Wilkins"
    ],
    "name:ukr_x_preferred":[
        "\u0412\u0456\u043b\u043a\u0456\u043d\u0441"
    ],
    "wof:name":"Wilkins",
    "wof:placetype":"locality"
},
  "geometry": {"coordinates":[-93.61408,35.33064],"type":"Point"}
}