{
  "type": "Feature",
  "properties": {
    "gn:country":"US",
    "gn:fcode":"PPL",
    "gn:population":0,
    "iso:country":"US",
    "name:azb_x_preferred":[
        "\u0633\u062f\u0627\u0631 \u0646\u0648\u0644\u0632"
    ],
    "name:eng_x_preferred":[
        "Cedar Knolls"
    ],
    "name:fas_x_preferred":[
        "\u0633\u062f\u0627\u0631 \u0646\u0648\u0644\u0632"
    ],
    "name:fra_x_preferred":[
        "Cedar Knolls"
    ],
    "name:lld_x_preferred":[
        "Cedar Knolls"
    ],
    "name:por_x_preferred":[
        "Cedar Knolls"
    ],
    "name:tur_x_preferred":[
        "Cedar Knolls"
    ],
    "name:und_x_variant":[
        "Cedar Knolles"
    ],
    "name:vol_x_preferred":[
        "Cedar Knolls"
    ],
    "qs_pg:aaroncc":"US",
    "qs_pg:gn_country":"US",
    "qs_pg:gn_fcode":"PPL",
    "qs_pg:gn_pop":0,
    "qs_pg:name":"Cedar Knolls",
    "qs_pg:name_adm0":"United States",
    "qs_pg:name_adm1":"New Jersey",
    "qs_pg:photos":334,
    "qs_pg:photos_1k":68,
    "qs_pg:photos_9k":1,
    "qs_pg:photos_9r":5,
    "qs_pg:photos_all":334,
    "qs_pg:photos_sr":5,
    "qs_pg:pop_sr":7,
    "qs_pg:qs_pg_placetype":"locality",
    "qs_pg:qs_pg_placetype_gp":"Town",
    "qs_pg:woe_adm0":23424977,
    "woe:adm0_id":23424977,
    "woe:name_adm0":"United States",
    "woe:name_adm1":"New Jersey",
    "woe:placetype":"Town",
    "wof:name":"Cedar Knolls",
    "wof:placetype":"locality"
},
  "geometry": {"coordinates":[-74.44875999999999,40.82204],"type":"Point"}
}