{
  "type": "Feature",
  "properties": {
    "gn:country":"US",
    "gn:elevation":96,
    "gn:fcode":"PPL",
    "gn:population":0,
    "iso:country":"US",
    "name:eng_x_preferred":[
        "Cannon Knolls"
    ],
    "qs:gn_adm0_cc":"US",
    "qs:gn_fcode":"PPL",
    "qs:gn_local":4760059,
    "qs:gn_nam_loc":"Fredericksburg, Fredericksburg, City of Fredericksburg, Virginia, US",
    "qs:gn_namadm1":"VA",
    "qs:gn_name":"Cannon Knolls",
    "qs:local_max":1387,
    "qs:local_sum":4212,
    "qs:localhoods":16,
    "qs:name":"Cannon Knolls",
    "qs:name_adm0":"United States",
    "qs:name_adm1":"Virginia",
    "qs:name_adm2":"Stafford",
    "qs:name_local":"Fredericksburg",
    "qs:photo_max":14,
    "qs:photo_sum":29,
    "qs:placetype":"Suburb",
    "qs:quad_count":7,
    "qs:woe_adm0":23424977,
    "qs:woe_adm1":2347605,
    "qs:woe_adm2":12590424,
    "qs:woe_lau":0,
    "qs:woe_local":2407171,
    "qs:woe_ver":"7.10.0",
    "qs_pg:aaroncc":"US",
    "qs_pg:gn_country":"US",
    "qs_pg:gn_fcode":"PPL",
    "qs_pg:gn_pop":0,
    "qs_pg:name":"Cannon Knolls",
    "qs_pg:name_adm0":"United States",
    "qs_pg:name_adm1":"Virginia",
    "qs_pg:photos":27,
    "qs_pg:photos_1k":5,
    "qs_pg:photos_9k":1,
    "qs_pg:photos_9r":2,
    "qs_pg:photos_all":27,
    "qs_pg:photos_sr":2,
    "qs_pg:pop_sr":0,
    "qs_pg:qs_pg_placetype":"neighbourhood",
    "qs_pg:qs_pg_placetype_gp":"Suburb",
    "qs_pg:woe_adm0":23424977,
    "wof:lang":[
        "eng"
    ],
    "wof:name":"Cannon Knolls",
    "wof:placetype":"neighbourhood",
    "wof:population":1994,
    "zs:blockids":[
        511790103012018,
        511790102041013,
        511790102041020,
        511790103012017,
        511790102041019,
        511790102041021,
        511790103051000,
        511790103012001,
        511790103012014,
        511790103012016,
        511790102041016,
        511790103012000,
        511790103012015,
        511790103051002
    ],
    "zs:housing10":630,
    "zs:pop10":1994
},
  "geometry": {"coordinates":[-77.56338100000001,38.435563],"type":"Point"}
}