{
  "type": "Feature",
  "properties": {
    "gn:admin1_code":"AK",
    "gn:admin2_code":"122.0",
    "gn:asciiname":"Klutchevya",
    "gn:country_code":"US",
    "gn:dem":248,
    "gn:elevation":"256.0",
    "gn:feature_class":"P",
    "gn:feature_code":"PPL",
    "gn:name":"Klutchevya",
    "gn:population":0,
    "gn:timezone":"America/Anchorage",
    "iso:country":"US",
    "wof:name":"Klutchevya",
    "wof:placetype":"locality"
},
  "geometry": {"coordinates":[-151.61111,59.81111],"type":"Point"}
}