{
  "type": "Feature",
  "properties": {
    "gn:admin1_code":"TX",
    "gn:admin2_code":"215.0",
    "gn:asciiname":"Racquet Club Colonia",
    "gn:country_code":"US",
    "gn:dem":31,
    "gn:elevation":"30.0",
    "gn:feature_class":"P",
    "gn:feature_code":"PPL",
    "gn:name":"Racquet Club Colonia",
    "gn:population":0,
    "gn:timezone":"America/Chicago",
    "iso:country":"US",
    "name:eng_x_preferred":[
        "Racquet Club Colonia"
    ],
    "name:und_x_variant":[
        "Racquet Club Subdivision Colonia"
    ],
    "wof:name":"Racquet Club Colonia",
    "wof:placetype":"locality"
},
  "geometry": {"coordinates":[-98.21639999999999,26.30424],"type":"Point"}
}