{
  "type": "Feature",
  "properties": {
    "gn:admin1_code":"LA",
    "gn:admin2_code":"101.0",
    "gn:asciiname":"North Bend",
    "gn:country_code":"US",
    "gn:dem":5,
    "gn:elevation":"2.0",
    "gn:feature_class":"P",
    "gn:feature_code":"PPL",
    "gn:name":"North Bend",
    "gn:population":0,
    "gn:timezone":"America/Chicago",
    "iso:country":"US",
    "name:cat_x_preferred":[
        "North Bend"
    ],
    "name:ceb_x_preferred":[
        "North Bend"
    ],
    "name:deu_x_preferred":[
        "North Bend"
    ],
    "name:fin_x_preferred":[
        "North Bend"
    ],
    "name:fra_x_preferred":[
        "North Bend"
    ],
    "name:hun_x_preferred":[
        "North Bend"
    ],
    "name:ita_x_preferred":[
        "North Bend"
    ],
    "name:nld_x_preferred":[
        "North Bend"
    ],
    "name:pol_x_preferred":[
        "North Bend"
    ],
    "name:por_x_preferred":[
        "North Bend"
    ],
    "name:rus_x_preferred":[
        "\u041d\u043e\u0440\u0442-\u0411\u0435\u043d\u0434"
    ],
    "name:spa_x_preferred":[
        "North Bend"
    ],
    "name:srp_x_preferred":[
        "\u041d\u043e\u0440\u0442 \u0411\u0435\u043d\u0434"
    ],
    "name:swe_x_preferred":[
        "North Bend"
    ],
    "name:vol_x_preferred":[
        "North Bend"
    ],
    "wof:name":"North Bend",
    "wof:placetype":"locality"
},
  "geometry": {"coordinates":[-91.46983,29.68271],"type":"Point"}
}