{
  "type": "Feature",
  "properties": {
    "gn:country":"US",
    "gn:fcode":"PPL",
    "gn:population":0,
    "iso:country":"US",
    "name:eng_x_preferred":[
        "Junction Overlook"
    ],
    "name:fas_x_preferred":[
        "\u062c\u0627\u0646\u06a9\u0634\u0646 \u0627\u0648\u0631\u0644\u0648\u06a9"
    ],
    "name:por_x_preferred":[
        "Junction Overlook"
    ],
    "name:zho_x_preferred":[
        "\u4ea4\u754c\u8655\u4fef\u77b0"
    ],
    "qs_pg:aaroncc":"US",
    "qs_pg:gn_country":"US",
    "qs_pg:gn_fcode":"PPL",
    "qs_pg:gn_pop":0,
    "qs_pg:name":"Junction Overlook",
    "qs_pg:name_adm0":"United States",
    "qs_pg:name_adm1":"Arizona",
    "qs_pg:photos":2116,
    "qs_pg:photos_1k":429,
    "qs_pg:photos_9k":9,
    "qs_pg:photos_9r":9,
    "qs_pg:photos_all":2116,
    "qs_pg:photos_sr":16,
    "qs_pg:pop_sr":0,
    "qs_pg:qs_pg_placetype":"locality",
    "qs_pg:qs_pg_placetype_gp":"Town",
    "qs_pg:woe_adm0":23424977,
    "woe:adm0_id":23424977,
    "woe:name_adm0":"United States",
    "woe:name_adm1":"Arizona",
    "woe:placetype":"Town",
    "wof:name":"Junction Overlook",
    "wof:placetype":"locality"
},
  "geometry": {"coordinates":[-109.49288,36.13723],"type":"Point"}
}