{
  "type": "Feature",
  "properties": {
    "gn:admin1_code":"FL",
    "gn:admin2_code":"127.0",
    "gn:asciiname":"Riverside Mobile Home Park",
    "gn:country_code":"US",
    "gn:dem":3,
    "gn:elevation":"1.0",
    "gn:feature_class":"P",
    "gn:feature_code":"PPL",
    "gn:name":"Riverside Mobile Home Park",
    "gn:population":0,
    "gn:timezone":"America/New_York",
    "iso:country":"US",
    "wof:name":"Riverside Mobile Home Park",
    "wof:placetype":"campus"
},
  "geometry": {"coordinates":[-80.97709999999999,29.12471],"type":"Point"}
}