{
  "type": "Feature",
  "properties": {
    "gn:admin1_code":"PA",
    "gn:admin2_code":"53.0",
    "gn:admin3_code":"38016.0",
    "gn:asciiname":"Parrish",
    "gn:country_code":"US",
    "gn:dem":435,
    "gn:elevation":"426.0",
    "gn:feature_class":"P",
    "gn:feature_code":"PPL",
    "gn:name":"Parrish",
    "gn:population":0,
    "gn:timezone":"America/New_York",
    "iso:country":"US",
    "name:ces_x_preferred":[
        "Parrish"
    ],
    "name:deu_x_preferred":[
        "Parrish"
    ],
    "name:fra_x_preferred":[
        "Parrish"
    ],
    "name:ita_x_preferred":[
        "Parrish"
    ],
    "name:jpn_x_preferred":[
        "\u30d1\u30ea\u30c3\u30b7\u30e5"
    ],
    "name:pol_x_preferred":[
        "Parrish"
    ],
    "name:ron_x_preferred":[
        "Parrish"
    ],
    "name:rus_x_preferred":[
        "\u041f\u044d\u0440\u0440\u0438\u0448"
    ],
    "name:srp_x_preferred":[
        "\u041f\u0430\u0440\u0438\u0448"
    ],
    "wof:name":"Parrish",
    "wof:placetype":"locality"
},
  "geometry": {"coordinates":[-78.9967,41.49145],"type":"Point"}
}