{
  "type": "Feature",
  "properties": {
    "gn:admin1_code":"AZ",
    "gn:admin2_code":"19.0",
    "gn:asciiname":"Far Horizons Trailer Village",
    "gn:country_code":"US",
    "gn:dem":778,
    "gn:elevation":"785.0",
    "gn:feature_class":"P",
    "gn:feature_code":"PPL",
    "gn:name":"Far Horizons Trailer Village",
    "gn:population":0,
    "gn:timezone":"America/Phoenix",
    "iso:country":"US",
    "wof:name":"Far Horizons Trailer Village",
    "wof:placetype":"locality"
},
  "geometry": {"coordinates":[-110.82662999999999,32.22636],"type":"Point"}
}