{
  "type": "Feature",
  "properties": {
    "gn:admin1_code":"MT",
    "gn:admin2_code":"31.0",
    "gn:asciiname":"Camona",
    "gn:country_code":"US",
    "gn:dem":1383,
    "gn:elevation":"1385.0",
    "gn:feature_class":"P",
    "gn:feature_code":"PPL",
    "gn:name":"Camona",
    "gn:population":0,
    "gn:timezone":"America/Denver",
    "iso:country":"US",
    "wof:name":"Camona",
    "wof:placetype":"locality"
},
  "geometry": {"coordinates":[-111.08134,45.76576],"type":"Point"}
}