{
  "type": "Feature",
  "properties": {
    "iso:country":"US",
    "name:eng_x_preferred":[
        "Downtown Norwalk"
    ],
    "qs:gn_local":0,
    "qs:local_max":566,
    "qs:local_sum":566,
    "qs:localhoods":1,
    "qs:name":"Downtown Norwalk",
    "qs:name_adm0":"United States",
    "qs:name_adm1":"Ohio",
    "qs:name_adm2":"Huron",
    "qs:name_local":"Norwalk",
    "qs:photo_max":357,
    "qs:photo_sum":566,
    "qs:placetype":"Suburb",
    "qs:quad_count":23,
    "qs:woe_adm0":23424977,
    "qs:woe_adm1":2347594,
    "qs:woe_adm2":12589565,
    "qs:woe_lau":0,
    "qs:woe_local":2462246,
    "qs:woe_ver":"7.10.0",
    "wd:wordcount":1350,
    "wof:lang":[
        "eng"
    ],
    "wof:name":"Downtown Norwalk",
    "wof:placetype":"neighbourhood",
    "wof:population":2255,
    "zs:blockids":[
        390779156004012,
        390779155004022,
        390779158003011,
        390779158004048,
        390779156003004,
        390779158003010,
        390779157004016,
        390779158004031,
        390779155004015,
        390779156001027,
        390779158003013,
        390779157004000,
        390779158004041,
        390779158004039,
        390779156001051,
        390779158004029,
        390779156004010,
        390779156002000,
        390779155004026,
        390779158004043,
        390779155003000,
        390779158004047,
        390779157003002,
        390779156003003,
        390779158004038,
        390779157004022,
        390779155001039,
        390779155004000,
        390779156003011,
        390779158003014,
        390779158004040,
        390779158004049,
        390779156003002,
        390779158004027,
        390779157004002,
        390779156001008,
        390779156001010,
        390779158003008,
        390779156004008
    ],
    "zs:housing10":904,
    "zs:pop10":2255
},
  "geometry": {"coordinates":[-82.611581,41.233042],"type":"Point"}
}