{
  "type": "Feature",
  "properties": {
    "gn:elevation":5,
    "gn:gn_country":"US",
    "gn:gn_fcode":"PPL",
    "gn:gn_pop":0,
    "iso:country":"US",
    "name:eng_x_preferred":[
        "Lake Terrace"
    ],
    "name:eng_x_variant":[
        "Lk Ter",
        "Lake Ter",
        "Lk Terrace"
    ],
    "name:unk_x_variant":[
        "Lake Terrace"
    ],
    "qs:gn_adm0_cc":"US",
    "qs:gn_fcode":"PPL",
    "qs:gn_local":4776222,
    "qs:gn_nam_loc":"Norfolk, Norfolk, Virginia, US",
    "qs:gn_namadm1":"VA",
    "qs:gn_name":"Lake Terrace",
    "qs:local_max":6835,
    "qs:local_sum":36858,
    "qs:localhoods":52,
    "qs:name":"Lake Terrace",
    "qs:name_adm0":"United States",
    "qs:name_adm1":"Virginia",
    "qs:name_adm2":"Norfolk City",
    "qs:name_local":"Norfolk",
    "qs:photo_max":17,
    "qs:photo_sum":44,
    "qs:placetype":"Suburb",
    "qs:quad_count":9,
    "qs:woe_adm0":23424977,
    "qs:woe_adm1":2347605,
    "qs:woe_adm2":12590391,
    "qs:woe_funk":"Parented by a neighborhood",
    "qs:woe_lau":0,
    "qs:woe_local":2460389,
    "qs:woe_ver":"7.10.0",
    "qs_pg:aaroncc":"US",
    "qs_pg:gn_country":"US",
    "qs_pg:gn_fcode":"PPL",
    "qs_pg:gn_pop":0,
    "qs_pg:name":"Lake Terrace",
    "qs_pg:name_adm0":"United States",
    "qs_pg:name_adm1":"Virginia",
    "qs_pg:photos":27,
    "qs_pg:photos_1k":5,
    "qs_pg:photos_9k":1,
    "qs_pg:photos_9r":2,
    "qs_pg:photos_all":27,
    "qs_pg:photos_sr":2,
    "qs_pg:pop_sr":0,
    "qs_pg:qs_pg_placetype":"neighbourhood",
    "qs_pg:qs_pg_placetype_gp":"Suburb",
    "qs_pg:woe_adm0":23424977,
    "wd:wordcount":37,
    "wof:lang":[
        "eng"
    ],
    "wof:name":"Lake Terrace",
    "wof:placetype":"neighbourhood",
    "wof:population":1075,
    "zs:blockids":[
        517100069013011,
        517100068001025,
        517100068002003,
        517100069013007,
        517100069013025,
        517100069013030,
        517100069013028,
        517100068001027,
        517100068001018,
        517100068001019,
        517100069013032,
        517100068001021,
        517100069013026,
        517100069013031,
        517100069013029,
        517100068002011,
        517100068001022,
        517100069013008,
        517100068001026,
        517100068002010,
        517100068002030,
        517100069013033,
        517100069013039,
        517100068002005,
        517100069013027,
        517100068001023,
        517100069013038,
        517100069013034,
        517100068002018,
        517100068001024
    ],
    "zs:housing10":449,
    "zs:pop10":1075
},
  "geometry": {"coordinates":[-76.19699799999999,36.862129],"type":"Point"}
}