{
  "type": "Feature",
  "properties": {
    "iso:country":"US",
    "name:eng_x_preferred":[
        "Cascades of Sarasota"
    ],
    "qs:gn_adm0_cc":"US",
    "qs:gn_local":4172131,
    "qs:gn_nam_loc":"Sarasota, Sarasota, Florida, US",
    "qs:gn_namadm1":"FL",
    "qs:local_max":2589,
    "qs:local_sum":4521,
    "qs:localhoods":5,
    "qs:name":"Cascades of Sarasota",
    "qs:name_adm0":"United States",
    "qs:name_adm1":"Florida",
    "qs:name_adm2":"Manatee",
    "qs:name_local":"Sarasota",
    "qs:photo_max":32,
    "qs:photo_sum":36,
    "qs:placetype":"Suburb",
    "qs:quad_count":4,
    "qs:woe_adm0":23424977,
    "qs:woe_adm1":2347568,
    "qs:woe_adm2":12587843,
    "qs:woe_lau":0,
    "qs:woe_local":2489025,
    "qs:woe_ver":"7.10.0",
    "wof:lang":[
        "eng"
    ],
    "wof:name":"Cascades of Sarasota",
    "wof:placetype":"neighbourhood",
    "wof:population":2954,
    "zs:blockids":[
        120810008053023,
        120810008052043,
        120810008081000,
        120810008052045,
        120810008053025,
        120810008084013,
        120810008084014,
        120810008072041,
        120810008072044,
        120810008072056,
        120810008081009,
        120810008081001,
        120810008072061,
        120810008072053,
        120810008081004,
        120810008072050,
        120810008052035,
        120810008072040,
        120810008082027,
        120810008072059,
        120810008072057,
        120810008072042,
        120810008072037,
        120810008081018,
        120810008072043,
        120810008072054,
        120810008072051,
        120810008053024,
        120810008081002,
        120810008052036,
        120810008052040,
        120810008072045,
        120810008084016,
        120810008072058,
        120810008084009,
        120810008084010,
        120810008072055,
        120810008072062,
        120810008072052,
        120810008072060,
        120810008072039,
        120810008081008,
        120810008081003,
        120810008052044,
        120810008084012,
        120810008052041,
        120810008053028
    ],
    "zs:housing10":1419,
    "zs:pop10":2954
},
  "geometry": {"coordinates":[-82.50915500000001,27.421757],"type":"Point"}
}