{
  "type": "Feature",
  "properties": {
    "gn:admin1_code":"GA",
    "gn:admin2_code":"125.0",
    "gn:asciiname":"Five Points",
    "gn:country_code":"US",
    "gn:dem":153,
    "gn:elevation":"157.0",
    "gn:feature_class":"P",
    "gn:feature_code":"PPL",
    "gn:name":"Five Points",
    "gn:population":0,
    "gn:timezone":"America/New_York",
    "iso:country":"US",
    "name:cat_x_preferred":[
        "Five Points"
    ],
    "name:ceb_x_preferred":[
        "Five Points"
    ],
    "name:deu_x_preferred":[
        "Five Points"
    ],
    "name:eng_x_preferred":[
        "Five Points"
    ],
    "name:fra_x_preferred":[
        "Five Points"
    ],
    "name:ita_x_preferred":[
        "Five Points"
    ],
    "name:kor_x_preferred":[
        "\ud30c\uc774\ube0c\ud3ec\uc778\uce20"
    ],
    "name:nld_x_preferred":[
        "Five Points"
    ],
    "name:pol_x_preferred":[
        "Five Points"
    ],
    "name:por_x_preferred":[
        "Five Points"
    ],
    "name:spa_x_preferred":[
        "Five Points"
    ],
    "name:srp_x_preferred":[
        "\u0424\u0430\u0458\u0432 \u041f\u043e\u0458\u043d\u0442\u0441"
    ],
    "name:ukr_x_preferred":[
        "\u0424\u0430\u0439\u0432-\u041f\u043e\u0439\u043d\u0442\u0441"
    ],
    "name:und_x_variant":[
        "Dye"
    ],
    "name:vol_x_preferred":[
        "Five Points"
    ],
    "wof:name":"Five Points",
    "wof:placetype":"locality"
},
  "geometry": {"coordinates":[-82.66124000000001,33.28764],"type":"Point"}
}