{
  "type": "Feature",
  "properties": {
    "iso:country":"US",
    "name:cat_x_preferred":[
        "Coronado"
    ],
    "name:ceb_x_preferred":[
        "Coronado"
    ],
    "name:deu_x_preferred":[
        "Coronado"
    ],
    "name:fra_x_preferred":[
        "Coronado"
    ],
    "name:hye_x_preferred":[
        "\u053f\u0578\u0580\u0578\u0576\u0561\u0564\u0578"
    ],
    "name:ita_x_preferred":[
        "Coronado"
    ],
    "name:jpn_x_preferred":[
        "\u30b3\u30ed\u30ca\u30c9"
    ],
    "name:nld_x_preferred":[
        "Coronado"
    ],
    "name:pol_x_preferred":[
        "Coronado"
    ],
    "name:por_x_preferred":[
        "Coronado"
    ],
    "name:rus_x_preferred":[
        "\u041a\u043e\u0440\u043e\u043d\u0430\u0434\u043e"
    ],
    "name:spa_x_preferred":[
        "Coronado"
    ],
    "name:srp_x_preferred":[
        "\u041a\u043e\u0440\u043e\u043d\u0430\u0434\u043e"
    ],
    "name:swe_x_preferred":[
        "Coronado"
    ],
    "qs_pg:aaroncc":"US",
    "qs_pg:name":"Coronado",
    "qs_pg:name_adm0":"United States",
    "qs_pg:name_adm1":"Arizona",
    "qs_pg:photos":550,
    "qs_pg:photos_1k":111,
    "qs_pg:photos_9k":2,
    "qs_pg:photos_9r":5,
    "qs_pg:photos_all":550,
    "qs_pg:photos_sr":7,
    "qs_pg:pop_sr":0,
    "qs_pg:qs_pg_placetype":"locality",
    "qs_pg:qs_pg_placetype_gp":"Town",
    "qs_pg:woe_adm0":23424977,
    "woe:adm0_id":23424977,
    "woe:name_adm0":"United States",
    "woe:name_adm1":"Arizona",
    "woe:placetype":"Town",
    "wof:name":"Coronado",
    "wof:placetype":"locality"
},
  "geometry": {"coordinates":[-110.882949,32.215224],"type":"Point"}
}