{
  "type": "Feature",
  "properties": {
    "gn:admin1_code":"AR",
    "gn:admin2_code":"67.0",
    "gn:admin3_code":"91467.0",
    "gn:asciiname":"Coffeeville",
    "gn:country_code":"US",
    "gn:dem":73,
    "gn:elevation":"75.0",
    "gn:feature_class":"P",
    "gn:feature_code":"PPL",
    "gn:name":"Coffeeville",
    "gn:population":0,
    "gn:timezone":"America/Chicago",
    "iso:country":"US",
    "name:eng_x_preferred":[
        "Coffeeville"
    ],
    "name:und_x_variant":[
        "Coffey Ville",
        "Coffeyville Community",
        "Coffeyville"
    ],
    "name:zho_x_preferred":[
        "\u79d1\u83f2\u7dad\u723e"
    ],
    "wof:name":"Coffeeville",
    "wof:placetype":"locality"
},
  "geometry": {"coordinates":[-91.40040999999999,35.49119],"type":"Point"}
}