{
  "type": "Feature",
  "properties": {
    "gn:admin1_code":"FL",
    "gn:admin2_code":"11",
    "gn:asciiname":"Rolling Oaks",
    "gn:country_code":"US",
    "gn:dem":6,
    "gn:elevation":"1.0",
    "gn:feature_class":"P",
    "gn:feature_code":"PPL",
    "gn:name":"Rolling Oaks",
    "gn:population":0,
    "gn:timezone":"America/New_York",
    "iso:country":"US",
    "name:azb_x_preferred":[
        "\u0631\u0648\u0644\u06cc\u0646\u0642 \u0627\u0648\u06a9\u0633"
    ],
    "name:ceb_x_preferred":[
        "Rolling Oaks"
    ],
    "name:eus_x_preferred":[
        "Rolling Oaks"
    ],
    "name:fas_x_preferred":[
        "\u0631\u0648\u0644\u06cc\u0646\u06af \u0627\u0648\u06a9\u0633"
    ],
    "name:new_x_preferred":[
        "\u0930\u094b\u0932\u093f\u0902\u0917 \u0913\u0915\u094d\u0938"
    ],
    "name:nld_x_preferred":[
        "Rolling Oaks"
    ],
    "name:por_x_preferred":[
        "Rolling Oaks"
    ],
    "name:uzb_x_preferred":[
        "Rolling Oaks"
    ],
    "wof:name":"Rolling Oaks",
    "wof:placetype":"locality"
},
  "geometry": {"coordinates":[-80.38571999999998,26.04802],"type":"Point"}
}