{
  "type": "Feature",
  "properties": {
    "gn:country":"US",
    "gn:fcode":"PPL",
    "gn:population":0,
    "iso:country":"US",
    "name:azb_x_preferred":[
        "\u067e\u0648\u0646\u0633 \u062f \u0644\u0626\u0648\u0646"
    ],
    "name:eng_x_preferred":[
        "Ponce de Leon"
    ],
    "name:fas_x_preferred":[
        "\u067e\u0648\u0646\u0633 \u062f\u06cc \u0644\u06cc\u0648\u0646"
    ],
    "name:fra_x_preferred":[
        "Ponce de Leon"
    ],
    "name:vol_x_preferred":[
        "Ponce de Leon"
    ],
    "qs_pg:aaroncc":"US",
    "qs_pg:gn_country":"US",
    "qs_pg:gn_fcode":"PPL",
    "qs_pg:gn_pop":0,
    "qs_pg:name":"Ponce de Leon",
    "qs_pg:name_adm0":"United States",
    "qs_pg:name_adm1":"Missouri",
    "qs_pg:photos_9k":1,
    "qs_pg:photos_9r":1,
    "qs_pg:photos_all":1,
    "qs_pg:photos_sr":0,
    "qs_pg:pop_sr":0,
    "qs_pg:qs_pg_placetype":"locality",
    "qs_pg:qs_pg_placetype_gp":"Town",
    "qs_pg:woe_adm0":23424977,
    "woe:adm0_id":23424977,
    "woe:name_adm0":"United States",
    "woe:name_adm1":"Missouri",
    "woe:placetype":"Town",
    "wof:name":"Ponce de Leon",
    "wof:placetype":"locality"
},
  "geometry": {"coordinates":[-93.35158,36.87589],"type":"Point"}
}