{
  "type": "Feature",
  "properties": {
    "gn:country":"US",
    "gn:fcode":"PPL",
    "gn:population":0,
    "iso:country":"US",
    "name:eng_x_preferred":[
        "Sangamon"
    ],
    "name:fra_x_preferred":[
        "Sangamon"
    ],
    "name:jpn_x_preferred":[
        "\u30b5\u30f3\u30ac\u30e2\u30f3"
    ],
    "name:und_x_variant":[
        "Sangamon Station"
    ],
    "name:zho_x_preferred":[
        "\u6851\u52a0\u8499"
    ],
    "qs_pg:aaroncc":"US",
    "qs_pg:gn_country":"US",
    "qs_pg:gn_fcode":"PPL",
    "qs_pg:gn_pop":0,
    "qs_pg:name":"Sangamon",
    "qs_pg:name_adm0":"United States",
    "qs_pg:name_adm1":"Illinois",
    "qs_pg:photos":72,
    "qs_pg:photos_1k":15,
    "qs_pg:photos_9k":1,
    "qs_pg:photos_9r":2,
    "qs_pg:photos_all":72,
    "qs_pg:photos_sr":2,
    "qs_pg:pop_sr":0,
    "qs_pg:qs_pg_placetype":"locality",
    "qs_pg:qs_pg_placetype_gp":"Town",
    "qs_pg:woe_adm0":23424977,
    "woe:adm0_id":23424977,
    "woe:name_adm0":"United States",
    "woe:name_adm1":"Illinois",
    "woe:placetype":"Town",
    "wof:name":"Sangamon",
    "wof:placetype":"locality"
},
  "geometry": {"coordinates":[-88.85590999999999,39.8667],"type":"Point"}
}