{
  "type": "Feature",
  "properties": {
    "iso:country":"US",
    "name:afr_x_preferred":[
        "Steen"
    ],
    "name:arg_x_preferred":[
        "Piedra"
    ],
    "name:ast_x_preferred":[
        "Piedra"
    ],
    "name:aym_x_preferred":[
        "Qala"
    ],
    "name:bos_x_preferred":[
        "Kamen"
    ],
    "name:bre_x_preferred":[
        "Maen"
    ],
    "name:cat_x_preferred":[
        "Pedra"
    ],
    "name:dan_x_preferred":[
        "Sten"
    ],
    "name:deu_x_preferred":[
        "Stein"
    ],
    "name:eng_x_preferred":[
        "Stone"
    ],
    "name:epo_x_preferred":[
        "\u015ctono"
    ],
    "name:est_x_preferred":[
        "Kivi"
    ],
    "name:eus_x_preferred":[
        "Harri"
    ],
    "name:fin_x_preferred":[
        "Luonnonkivi"
    ],
    "name:fra_x_preferred":[
        "Pierre naturelle"
    ],
    "name:frr_x_preferred":[
        "Stian"
    ],
    "name:glg_x_preferred":[
        "Pedra"
    ],
    "name:grn_x_preferred":[
        "Ita"
    ],
    "name:hin_x_preferred":[
        "\u092a\u0924\u094d\u0925\u0930"
    ],
    "name:hye_x_preferred":[
        "\u0554\u0561\u0580"
    ],
    "name:ita_x_preferred":[
        "Pietra"
    ],
    "name:kaz_x_preferred":[
        "\u0422\u0430\u0441"
    ],
    "name:lat_x_preferred":[
        "Lapis"
    ],
    "name:lav_x_preferred":[
        "Akmens"
    ],
    "name:lim_x_preferred":[
        "Stein"
    ],
    "name:mal_x_preferred":[
        "\u0d15\u0d32\u0d4d\u0d32\u0d4d"
    ],
    "name:mkd_x_preferred":[
        "\u041a\u0430\u043c\u0435\u043d"
    ],
    "name:nah_x_preferred":[
        "Tetl"
    ],
    "name:nap_x_preferred":[
        "Preta"
    ],
    "name:nld_x_preferred":[
        "Steen"
    ],
    "name:nno_x_preferred":[
        "Stein"
    ],
    "name:pfl_x_preferred":[
        "Stein"
    ],
    "name:pih_x_preferred":[
        "Stoen"
    ],
    "name:pol_x_preferred":[
        "Kamie\u0144"
    ],
    "name:que_x_preferred":[
        "Rumi"
    ],
    "name:ron_x_preferred":[
        "Piatr\u0103"
    ],
    "name:rus_x_preferred":[
        "\u041a\u0430\u043c\u0435\u043d\u044c"
    ],
    "name:scn_x_preferred":[
        "Petra"
    ],
    "name:slk_x_preferred":[
        "Kame\u0148"
    ],
    "name:slv_x_preferred":[
        "Kamen"
    ],
    "name:spa_x_preferred":[
        "Piedra"
    ],
    "name:srp_x_preferred":[
        "\u041a\u0430\u043c\u0435\u043d"
    ],
    "name:swa_x_preferred":[
        "Jiwe"
    ],
    "name:swe_x_preferred":[
        "Sten"
    ],
    "name:tgk_x_preferred":[
        "\u0421\u0430\u043d\u0433"
    ],
    "name:ukr_x_preferred":[
        "\u041a\u0430\u043c\u0456\u043d\u044c"
    ],
    "wof:name":"Stone",
    "wof:placetype":"neighbourhood",
    "zs:area_m":56086.673241,
    "zs:blockids":[
        202090448032090,
        202090448032083,
        202090448032092,
        202090448032091
    ],
    "zs:housing10":0,
    "zs:label":"Stone",
    "zs:pop10":0
},
  "geometry": {"coordinates":[-94.901734,39.11615],"type":"Point"}
}