{
  "type": "Feature",
  "properties": {
    "gn:admin1_code":"KY",
    "gn:admin2_code":"121",
    "gn:asciiname":"Walker",
    "gn:country_code":"US",
    "gn:dem":312,
    "gn:elevation":"306.0",
    "gn:feature_class":"P",
    "gn:feature_code":"PPL",
    "gn:name":"Walker",
    "gn:population":0,
    "gn:timezone":"America/New_York",
    "iso:country":"US",
    "wof:name":"Walker",
    "wof:placetype":"locality"
},
  "geometry": {"coordinates":[-83.71491999999998,36.88314],"type":"Point"}
}