{
  "type": "Feature",
  "properties": {
    "gn:admin1_code":"OH",
    "gn:admin2_code":"65.0",
    "gn:admin3_code":"68784.0",
    "gn:asciiname":"Holden",
    "gn:country_code":"US",
    "gn:dem":316,
    "gn:elevation":"316.0",
    "gn:feature_class":"P",
    "gn:feature_code":"PPL",
    "gn:name":"Holden",
    "gn:population":0,
    "gn:timezone":"America/New_York",
    "iso:country":"US",
    "name:afr_x_preferred":[
        "Holden"
    ],
    "name:ara_x_preferred":[
        "\u0647\u0648\u0644\u062f\u0646"
    ],
    "name:ast_x_preferred":[
        "Holden"
    ],
    "name:azb_x_preferred":[
        "\u0647\u0648\u0644\u062f\u0646"
    ],
    "name:bel_x_preferred":[
        "Holden"
    ],
    "name:cat_x_preferred":[
        "Holden"
    ],
    "name:ces_x_preferred":[
        "Holden"
    ],
    "name:ckb_x_preferred":[
        "\u06be\u06c6\u06b5\u062f\u0646"
    ],
    "name:dan_x_preferred":[
        "Holden"
    ],
    "name:deu_x_preferred":[
        "Holden"
    ],
    "name:eng_x_preferred":[
        "Holden"
    ],
    "name:est_x_preferred":[
        "Holden"
    ],
    "name:fas_x_preferred":[
        "\u0647\u0648\u0644\u062f\u0646"
    ],
    "name:fin_x_preferred":[
        "Holden"
    ],
    "name:fra_x_preferred":[
        "Holden"
    ],
    "name:hun_x_preferred":[
        "Holden"
    ],
    "name:ind_x_preferred":[
        "Holden"
    ],
    "name:ita_x_preferred":[
        "Holden"
    ],
    "name:jpn_x_preferred":[
        "\u30db\u30fc\u30eb\u30c7\u30f3"
    ],
    "name:kat_x_preferred":[
        "Holden"
    ],
    "name:lit_x_preferred":[
        "Holden"
    ],
    "name:nld_x_preferred":[
        "Holden"
    ],
    "name:nor_x_preferred":[
        "Holden"
    ],
    "name:pnb_x_preferred":[
        "\u06c1\u0648\u0644\u0688\u0646"
    ],
    "name:pol_x_preferred":[
        "Holden"
    ],
    "name:por_x_preferred":[
        "Holden"
    ],
    "name:ron_x_preferred":[
        "Holden"
    ],
    "name:rus_x_preferred":[
        "Holden"
    ],
    "name:sah_x_preferred":[
        "Holden"
    ],
    "name:sco_x_preferred":[
        "Holden"
    ],
    "name:slk_x_preferred":[
        "Holden"
    ],
    "name:spa_x_preferred":[
        "Holden"
    ],
    "name:srp_x_preferred":[
        "\u0425\u043e\u043b\u0434\u0435\u043d"
    ],
    "name:swe_x_preferred":[
        "Holden"
    ],
    "name:tha_x_preferred":[
        "\u0e42\u0e2e\u0e25\u0e40\u0e14\u0e19"
    ],
    "name:tur_x_preferred":[
        "Holden"
    ],
    "name:ukr_x_preferred":[
        "Holden"
    ],
    "name:und_x_variant":[
        "Fletchers Chapel"
    ],
    "name:wuu_x_preferred":[
        "\u970d\u987f\u6c7d\u8f66"
    ],
    "name:zho_x_preferred":[
        "\u970d\u987f\u6c7d\u8f66"
    ],
    "wof:name":"Holden",
    "wof:placetype":"locality"
},
  "geometry": {"coordinates":[-83.88021999999999,40.60255],"type":"Point"}
}