{
  "type": "Feature",
  "properties": {
    "iso:country":"US",
    "name:nld_x_preferred":[
        "Hermit's Rest"
    ],
    "qs_pg:aaroncc":"US",
    "qs_pg:name":"Hermits Rest",
    "qs_pg:name_adm0":"United States",
    "qs_pg:name_adm1":"Arizona",
    "qs_pg:photos":4636,
    "qs_pg:photos_1k":939,
    "qs_pg:photos_9k":21,
    "qs_pg:photos_9r":13,
    "qs_pg:photos_all":4636,
    "qs_pg:photos_sr":23,
    "qs_pg:pop_sr":0,
    "qs_pg:qs_pg_placetype":"locality",
    "qs_pg:qs_pg_placetype_gp":"Town",
    "qs_pg:woe_adm0":23424977,
    "woe:adm0_id":23424977,
    "woe:name_adm0":"United States",
    "woe:name_adm1":"Arizona",
    "woe:placetype":"Town",
    "wof:name":"Hermits Rest",
    "wof:placetype":"locality"
},
  "geometry": {"coordinates":[-112.210055,36.0635],"type":"Point"}
}