{
  "type": "Feature",
  "properties": {
    "gn:country":"US",
    "gn:fcode":"PPL",
    "gn:population":0,
    "iso:country":"US",
    "name:ben_x_preferred":[
        "\u09b9\u09c7\u099c"
    ],
    "name:ceb_x_preferred":[
        "Hays"
    ],
    "name:deu_x_preferred":[
        "Hays"
    ],
    "name:ell_x_preferred":[
        "\u03a7\u03ad\u03b9\u03c2"
    ],
    "name:fra_x_preferred":[
        "Hays"
    ],
    "name:hin_x_preferred":[
        "\u0939\u0947\u091c\u093c"
    ],
    "name:ind_x_preferred":[
        "Hays"
    ],
    "name:ita_x_preferred":[
        "Hays"
    ],
    "name:kor_x_preferred":[
        "\ud5e4\uc774\uc2a4"
    ],
    "name:nld_x_preferred":[
        "Hays"
    ],
    "name:pol_x_preferred":[
        "Hays"
    ],
    "name:por_x_preferred":[
        "Hays"
    ],
    "name:rus_x_preferred":[
        "\u0425\u0435\u0439\u0441"
    ],
    "name:spa_x_preferred":[
        "Hays"
    ],
    "name:srp_x_preferred":[
        "\u0425\u0435\u0458\u0437"
    ],
    "name:swe_x_preferred":[
        "Hays"
    ],
    "name:ukr_x_preferred":[
        "\u0413\u0435\u0439\u0441"
    ],
    "name:vol_x_preferred":[
        "Hays"
    ],
    "qs_pg:aaroncc":"US",
    "qs_pg:gn_country":"US",
    "qs_pg:gn_fcode":"PPL",
    "qs_pg:gn_pop":0,
    "qs_pg:name":"Hays",
    "qs_pg:name_adm0":"United States",
    "qs_pg:name_adm1":"Colorado",
    "qs_pg:photos":12,
    "qs_pg:photos_1k":2,
    "qs_pg:photos_9k":1,
    "qs_pg:photos_9r":1,
    "qs_pg:photos_all":12,
    "qs_pg:photos_sr":1,
    "qs_pg:pop_sr":0,
    "qs_pg:qs_pg_placetype":"locality",
    "qs_pg:qs_pg_placetype_gp":"Town",
    "qs_pg:woe_adm0":23424977,
    "woe:adm0_id":23424977,
    "woe:name_adm0":"United States",
    "woe:name_adm1":"Colorado",
    "woe:placetype":"Town",
    "wof:name":"Hays",
    "wof:placetype":"locality"
},
  "geometry": {"coordinates":[-103.61911000000001,38.07306],"type":"Point"}
}