{
  "type": "Feature",
  "properties": {
    "gn:admin1_code":"FL",
    "gn:admin2_code":"57",
    "gn:asciiname":"Manhattan Park",
    "gn:country_code":"US",
    "gn:dem":22,
    "gn:elevation":"11.0",
    "gn:feature_class":"P",
    "gn:feature_code":"PPL",
    "gn:name":"Manhattan Park",
    "gn:population":0,
    "gn:timezone":"America/New_York",
    "iso:country":"US",
    "wof:name":"Manhattan Park",
    "wof:placetype":"locality"
},
  "geometry": {"coordinates":[-82.568,28.0678],"type":"Point"}
}