{
  "type": "Feature",
  "properties": {
    "iso:country":"US",
    "name:eng_x_preferred":[
        "Pleasant Place"
    ],
    "wof:name":"Pleasant Place",
    "wof:placetype":"neighbourhood",
    "wof:population":1294,
    "zs:area_m":647718.573845,
    "zs:blockids":[
        191030011001017,
        191030011001012,
        191030012002005,
        191030001001059,
        191030001002009,
        191030001002010,
        191030001002003,
        191030001002007,
        191030011001029,
        191030001001019,
        191030001001056,
        191030011001010,
        191030001001055,
        191030001001028,
        191030011001001,
        191030011001016,
        191030001001038,
        191030011001013,
        191030001001031,
        191030001001057,
        191030011001027,
        191030001001030,
        191030001001054,
        191030011001014,
        191030001001032,
        191030011001002,
        191030011001011,
        191030011001028,
        191030011002000,
        191030012002004,
        191030011001000,
        191030011001015,
        191030001001053,
        191030001001058
    ],
    "zs:housing10":661,
    "zs:label":"Pleasant Place",
    "zs:pop10":1294
},
  "geometry": {"coordinates":[-91.52513399999999,41.66798],"type":"Point"}
}