{
  "type": "Feature",
  "properties": {
    "gn:admin1_code":"ME",
    "gn:admin2_code":"27.0",
    "gn:admin3_code":"76610.0",
    "gn:asciiname":"Walker Corner",
    "gn:country_code":"US",
    "gn:dem":188,
    "gn:elevation":"190.0",
    "gn:feature_class":"P",
    "gn:feature_code":"PPL",
    "gn:name":"Walker Corner",
    "gn:population":0,
    "gn:timezone":"America/New_York",
    "iso:country":"US",
    "wof:name":"Walker Corner",
    "wof:placetype":"locality"
},
  "geometry": {"coordinates":[-69.21893,44.56618],"type":"Point"}
}