{
  "type": "Feature",
  "properties": {
    "gn:admin1_code":"MO",
    "gn:admin2_code":"87.0",
    "gn:admin3_code":"52706.0",
    "gn:asciiname":"Nichols Grove",
    "gn:country_code":"US",
    "gn:dem":306,
    "gn:elevation":"305.0",
    "gn:feature_class":"P",
    "gn:feature_code":"PPL",
    "gn:name":"Nichols Grove",
    "gn:population":0,
    "gn:timezone":"America/Chicago",
    "iso:country":"US",
    "wof:name":"Nichols Grove",
    "wof:placetype":"locality"
},
  "geometry": {"coordinates":[-95.08497,40.01944],"type":"Point"}
}