{
  "type": "Feature",
  "properties": {
    "gn:admin1_code":"TX",
    "gn:admin2_code":"215.0",
    "gn:asciiname":"Sotira Estates Colonia",
    "gn:country_code":"US",
    "gn:dem":43,
    "gn:elevation":"39.0",
    "gn:feature_class":"P",
    "gn:feature_code":"PPL",
    "gn:name":"Sotira Estates Colonia",
    "gn:population":0,
    "gn:timezone":"America/Chicago",
    "iso:country":"US",
    "wof:name":"Sotira Estates Colonia",
    "wof:placetype":"locality"
},
  "geometry": {"coordinates":[-98.38224,26.21535],"type":"Point"}
}