{
  "type": "Feature",
  "properties": {
    "gn:admin1_code":"TN",
    "gn:admin2_code":"9.0",
    "gn:asciiname":"Tara Estates",
    "gn:country_code":"US",
    "gn:dem":300,
    "gn:elevation":"298.0",
    "gn:feature_class":"P",
    "gn:feature_code":"PPL",
    "gn:name":"Tara Estates",
    "gn:population":0,
    "gn:timezone":"America/New_York",
    "iso:country":"US",
    "wof:name":"Tara Estates",
    "wof:placetype":"locality"
},
  "geometry": {"coordinates":[-83.91018000000003,35.77285999999999],"type":"Point"}
}