{
  "type": "Feature",
  "properties": {
    "iso:country":"US",
    "name:ceb_x_preferred":[
        "Edgemont"
    ],
    "name:deu_x_preferred":[
        "Edgemont"
    ],
    "name:eng_x_preferred":[
        "Edgemont"
    ],
    "name:pol_x_preferred":[
        "Edgemont"
    ],
    "name:spa_x_preferred":[
        "Edgemont"
    ],
    "name:srp_x_preferred":[
        "\u0415\u045f\u043c\u043e\u043d\u0442"
    ],
    "name:ukr_x_preferred":[
        "\u0415\u0434\u0436\u043c\u043e\u043d\u0442"
    ],
    "wof:name":"Edgemont",
    "wof:placetype":"neighbourhood",
    "wof:population":262,
    "zs:area_m":172066.919189,
    "zs:blockids":[
        361190114004007,
        361190114004020
    ],
    "zs:housing10":96,
    "zs:label":"Edgemont",
    "zs:pop10":262
},
  "geometry": {"coordinates":[-73.847815,41.07138],"type":"Point"}
}