{
  "type": "Feature",
  "properties": {
    "gn:admin1_code":"TX",
    "gn:admin2_code":"201.0",
    "gn:asciiname":"Mill Ridge North",
    "gn:country_code":"US",
    "gn:dem":45,
    "gn:elevation":"41.0",
    "gn:feature_class":"P",
    "gn:feature_code":"PPL",
    "gn:name":"Mill Ridge North",
    "gn:population":0,
    "gn:timezone":"America/Chicago",
    "iso:country":"US",
    "wof:name":"Mill Ridge North",
    "wof:placetype":"locality"
},
  "geometry": {"coordinates":[-95.59059999999999,29.9548],"type":"Point"}
}